{
  "type": "Feature",
  "properties": {
    "addr:full":"Calle de Palacio Valdes, 13 Gijon Asturias 33206",
    "addr:housenumber":"13",
    "addr:postcode":"33206",
    "addr:street":"Calle De Palacio Valdes",
    "iso:country":"ES",
    "sg:address":"Calle de Palacio Valdes, 13",
    "sg:city":"Gijon",
    "sg:orig_category":"Relojer\u00cda (al Por Menor, Reparaci\u00d3n)",
    "sg:phone":"+34 985 34 46 05",
    "sg:postcode":"33206",
    "sg:province":"Asturias",
    "wof:name":"A.gonzalez Losada S.l.",
    "wof:placetype":"venue"
},
  "geometry": {"coordinates":[-5.6660952568,43.5390701294],"type":"Point"}
}