{
  "type": "Feature",
  "properties": {
    "addr:full":"Avda Ramon Y Cajal, 29 Roda Albacete 02630",
    "addr:housenumber":"29",
    "addr:postcode":"02630",
    "addr:street":"Avda Ramon Y Cajal",
    "iso:country":"ES",
    "sg:address":"Avda Ramon Y Cajal, 29",
    "sg:city":"Roda",
    "sg:orig_category":"Florister\u00cdas",
    "sg:phone":"+34 967 44 12 97",
    "sg:postcode":"02630",
    "sg:province":"Albacete",
    "wof:name":"Perez Perez Julian",
    "wof:placetype":"venue"
},
  "geometry": {"coordinates":[-2.1580529213,39.2046661377],"type":"Point"}
}