{
  "type": "Feature",
  "properties": {
    "iso:country":"ES",
    "sg:address":"Ctra Madrid-lisboa, S/n",
    "sg:city":"Navalmoral Mata",
    "sg:orig_category":"Veh\u00cdculos De Ocasi\u00d3n",
    "sg:phone":"+34 927 53 29 64",
    "sg:postcode":"10300",
    "sg:province":"C\u00e1ceres",
    "wof:name":"Vazquez Orellana Miguel",
    "wof:placetype":"venue"
},
  "geometry": {"coordinates":[-5.5606641769,39.8903923035],"type":"Point"}
}