{
  "type": "Feature",
  "properties": {
    "addr:full":"Carrer de Murcia, 41 Barcelona Barcelona 08027",
    "addr:housenumber":"41",
    "addr:postcode":"08027",
    "addr:street":"Carrer De Murcia",
    "iso:country":"ES",
    "sg:address":"Carrer de Murcia, 41",
    "sg:city":"Barcelona",
    "sg:orig_category":"Molduras, Junquillos, Listones Y Molduras Perforadas",
    "sg:phone":"+34 933 40 59 50",
    "sg:postcode":"08027",
    "sg:province":"Barcelona",
    "wof:name":"Porredon Martin-portugues Jose Maria",
    "wof:placetype":"venue"
},
  "geometry": {"coordinates":[2.1898839474,41.4162445068],"type":"Point"}
}