{
  "type": "Feature",
  "properties": {
    "iso:country":"ES",
    "sg:address":"Carr Rossello, 35",
    "sg:city":"Girona",
    "sg:orig_category":"Arquitectos",
    "sg:phone":"+34 972 24 23 29",
    "sg:postcode":"17005",
    "sg:province":"Girona",
    "wof:name":"Puig Montserrat Nuria",
    "wof:placetype":"venue"
},
  "geometry": {"coordinates":[2.8095030785,41.9699287415],"type":"Point"}
}