{
  "type": "Feature",
  "properties": {
    "iso:country":"ES",
    "sg:address":"Bo. Fingoi, 109",
    "sg:city":"Lugo",
    "sg:orig_category":"Servicios De Higiene Y Peluquer\u00cda Para Perros Y Gatos",
    "sg:phone":"+34 982 24 02 80",
    "sg:postcode":"27002",
    "sg:province":"Lugo",
    "wof:name":"Suministros Caninos S.l.",
    "wof:placetype":"venue"
},
  "geometry": {"coordinates":[-7.5560441017,42.9972419739],"type":"Point"}
}