{
  "type": "Feature",
  "properties": {
    "addr:full":"Avda Valladolid, 82 S. Esteban Gormaz Soria 42330",
    "addr:housenumber":"82",
    "addr:postcode":"42330",
    "addr:street":"Avda Valladolid;S. Esteban Gormaz",
    "iso:country":"ES",
    "sg:address":"Avda Valladolid, 82",
    "sg:city":"S. Esteban Gormaz",
    "sg:orig_category":"Bancos",
    "sg:phone":"+34 975 35 02 84",
    "sg:postcode":"42330",
    "sg:province":"Soria",
    "sg:website":"www.gruposantander.es",
    "wof:name":"Bt Espa\u00d1a Compa\u00d1ia De Servicios Globales De Telecomunicaciones S.a.u.",
    "wof:placetype":"venue"
},
  "geometry": {"coordinates":[-3.2019989491,41.5728874207],"type":"Point"}
}