{
  "type": "Feature",
  "properties": {
    "addr:full":"Carr Major, 8 Preses Girona 17178",
    "addr:housenumber":"8",
    "addr:postcode":"17178",
    "addr:street":"Carr Major",
    "iso:country":"ES",
    "sg:address":"Carr Major, 8",
    "sg:city":"Preses",
    "sg:orig_category":"Pintores",
    "sg:phone":"+34 972 69 32 08",
    "sg:postcode":"17178",
    "sg:province":"Girona",
    "wof:name":"Duran Martinez Miguel",
    "wof:placetype":"venue"
},
  "geometry": {"coordinates":[2.4392340183,42.1472587585],"type":"Point"}
}