{
  "type": "Feature",
  "properties": {
    "addr:full":"Carrer de L'emancipacio, 21 Barcelona Barcelona 08022",
    "addr:housenumber":"21",
    "addr:postcode":"08022",
    "addr:street":"Carrer De L'Emancipacio",
    "iso:country":"ES",
    "sg:address":"Carrer de L'emancipacio, 21",
    "sg:city":"Barcelona",
    "sg:orig_category":"Inmobiliaria (agencias)",
    "sg:phone":"+34 934 18 68 15",
    "sg:postcode":"08022",
    "sg:province":"Barcelona",
    "wof:name":"L.g.r. S.l.",
    "wof:placetype":"venue"
},
  "geometry": {"coordinates":[2.13154459,41.4029045105],"type":"Point"}
}