{
  "type": "Feature",
  "properties": {
    "iso:country":"ES",
    "sg:address":"Calle de Cister, 11",
    "sg:city":"Malaga",
    "sg:orig_category":"Oficinas De Cambio",
    "sg:phone":"+34 952 60 37 42",
    "sg:postcode":"29015",
    "sg:province":"M\u00e1laga",
    "wof:name":"Castelo Luque Ana",
    "wof:placetype":"venue"
},
  "geometry": {"coordinates":[-4.4180588722,36.7206001282],"type":"Point"}
}