{
  "type": "Feature",
  "properties": {
    "addr:full":"Cm\u00d1o Roda (da), 13 Xinzo De Limia Ourense 32630",
    "addr:postcode":"32630",
    "iso:country":"ES",
    "sg:address":"Cm\u00d1o Roda (da), 13",
    "sg:city":"Xinzo De Limia",
    "sg:orig_category":"Agentes, Concesionarios Y Sucursales De Veh\u00cdculos",
    "sg:phone":"+34 988 46 21 77",
    "sg:postcode":"32630",
    "sg:province":"Ourense",
    "wof:name":"Antelauto Sl",
    "wof:placetype":"venue"
},
  "geometry": {"coordinates":[-7.7277808189,42.0675811768],"type":"Point"}
}