{
  "type": "Feature",
  "properties": {
    "iso:country":"ES",
    "sg:address":"Calle de Pocillo, 4",
    "sg:city":"Lantejuela",
    "sg:orig_category":"Empresas De Vigilancia, Guardia Y Protecci\u00d3n",
    "sg:phone":"+34 954 82 70 02",
    "sg:postcode":"41630",
    "sg:province":"Sevilla",
    "wof:name":"Segurseba S.l.",
    "wof:placetype":"venue"
},
  "geometry": {"coordinates":[-5.2233982086,37.3525848389],"type":"Point"}
}