{
  "type": "Feature",
  "properties": {
    "iso:country":"ES",
    "sg:address":"Calle de Pintor Mauro Ortiz De Urbina, 16",
    "sg:city":"Vitoria-gasteiz",
    "sg:orig_category":"Centros P\u00dablicos De Formaci\u00d3n Profesional Y T\u00c9cnica",
    "sg:phone":"+34 945 22 28 66",
    "sg:postcode":"01008",
    "sg:province":"\u00c1lava",
    "wof:name":"Colegio Oficial De Aparejadores Y Arquitectos Tecnicos De Alava",
    "wof:placetype":"venue"
},
  "geometry": {"coordinates":[-2.688256979,42.8503303528],"type":"Point"}
}