{
  "type": "Feature",
  "properties": {
    "iso:country":"ES",
    "sg:address":"Manuel De Falla, 2",
    "sg:city":"Iru\u00f1a",
    "sg:orig_category":"Publicidad (soportes Y Gesti\u00d3n)",
    "sg:phone":"+34 948 24 35 28",
    "sg:postcode":"31005",
    "sg:province":"Navarra",
    "wof:name":"Tapiz Legarda Jose Francisco",
    "wof:placetype":"venue"
},
  "geometry": {"coordinates":[-1.6438419819,42.8060493469],"type":"Point"}
}