{
  "type": "Feature",
  "properties": {
    "iso:country":"ES",
    "sg:address":"Avda Region Murciana, 194",
    "sg:city":"Carril De La Enera",
    "sg:orig_category":"Ropa Para Se\u00d1oras Y Caballeros (al Por Menor)",
    "sg:phone":"+34 968 83 75 00",
    "sg:postcode":"30011",
    "sg:province":"Murcia",
    "wof:name":"Stock Eurotextil S.l.",
    "wof:placetype":"venue"
},
  "geometry": {"coordinates":[-1.0986809731,37.9820213318],"type":"Point"}
}