{
  "type": "Feature",
  "properties": {
    "iso:country":"ES",
    "sg:address":"Avda Juan Xxiii, 4",
    "sg:city":"Huesca",
    "sg:orig_category":"Cer\u00c1micas: Material Y Suministros",
    "sg:phone":"+34 974 21 26 47",
    "sg:postcode":"22003",
    "sg:province":"Huesca",
    "wof:name":"Saneamientos Piedrafita S. L.",
    "wof:placetype":"venue"
},
  "geometry": {"coordinates":[-0.4083139896,42.1365661621],"type":"Point"}
}