{
  "type": "Feature",
  "properties": {
    "iso:country":"ES",
    "sg:address":"Calle de Obispo Peralta, 16",
    "sg:city":"Zaragoza",
    "sg:orig_category":"Promotores Constructores",
    "sg:phone":"+34 976 75 37 85",
    "sg:postcode":"50012",
    "sg:province":"Zaragoza",
    "wof:name":"Galvez Rubio Cesareo",
    "wof:placetype":"venue"
},
  "geometry": {"coordinates":[-0.9298670292,41.6391181946],"type":"Point"}
}