{
  "type": "Feature",
  "properties": {
    "addr:full":"Port Esportiu, S/n Hospitalet De L'infant Tarragona 43890",
    "addr:housenumber":"s / n",
    "addr:postcode":"43890",
    "iso:country":"ES",
    "sg:address":"Port Esportiu, S/n",
    "sg:city":"Hospitalet De L'infant",
    "sg:orig_category":"Molduras, Junquillos, Listones Y Molduras Perforadas",
    "sg:phone":"+34 977 82 02 90",
    "sg:postcode":"43890",
    "sg:province":"Tarragona",
    "wof:name":"Escodar Tarazaga Angela",
    "wof:placetype":"venue"
},
  "geometry": {"coordinates":[1.2455840111,41.1117019653],"type":"Point"}
}