{
  "type": "Feature",
  "properties": {
    "addr:full":"Carrer de Ramon Farguell, 25 Manresa Barcelona 08243",
    "addr:housenumber":"25",
    "addr:postcode":"08243",
    "addr:street":"Carrer De Ramon Farguell",
    "iso:country":"ES",
    "sg:address":"Carrer de Ramon Farguell, 25",
    "sg:city":"Manresa",
    "sg:orig_category":"Construcci\u00d3n Mec\u00c1nica",
    "sg:phone":"+34 938 73 97 64",
    "sg:postcode":"08243",
    "sg:province":"Barcelona",
    "wof:name":"Mecaniques Segab S.l.",
    "wof:placetype":"venue"
},
  "geometry": {"coordinates":[1.8437759876,41.7123908997],"type":"Point"}
}