{
  "type": "Feature",
  "properties": {
    "addr:full":"Carrer de Treball, 97 Barcelona Barcelona 08019",
    "addr:housenumber":"97",
    "addr:postcode":"08019",
    "addr:street":"Carrer De Treball",
    "iso:country":"ES",
    "sg:address":"Carrer de Treball, 97",
    "sg:city":"Barcelona",
    "sg:orig_category":"Materiales De Aislamiento T\u00c9rmico Y Ac\u00dastico",
    "sg:phone":"+34 933 07 92 99",
    "sg:postcode":"08019",
    "sg:province":"Barcelona",
    "wof:name":"Almacen De Fibras Aislamientos Y Placas S.a.",
    "wof:placetype":"venue"
},
  "geometry": {"coordinates":[2.2080888748,41.4112472534],"type":"Point"}
}