{
  "type": "Feature",
  "properties": {
    "iso:country":"ES",
    "sg:address":"Plaz Casta\u00d1ares De Rioja, 5",
    "sg:city":"Haro",
    "sg:orig_category":"Panader\u00cdas, Panader\u00cdas",
    "sg:phone":"+34 941 30 55 47",
    "sg:postcode":"26200",
    "sg:province":"La Rioja",
    "wof:name":"Panificadora San Felices S.a.",
    "wof:placetype":"venue"
},
  "geometry": {"coordinates":[-2.8523449898,42.573677063],"type":"Point"}
}