{
  "type": "Feature",
  "properties": {
    "iso:country":"ES",
    "sg:address":"Calle de Graus, 35",
    "sg:city":"Barbastro",
    "sg:orig_category":"Promotores Constructores",
    "sg:phone":"+34 974 31 61 02",
    "sg:postcode":"22300",
    "sg:province":"Huesca",
    "wof:name":"Broligen S L",
    "wof:placetype":"venue"
},
  "geometry": {"coordinates":[0.136559993,42.0426902771],"type":"Point"}
}