{
  "type": "Feature",
  "properties": {
    "iso:country":"ES",
    "sg:address":"C/ Major (m.), 1",
    "sg:city":"Manacor",
    "sg:orig_category":"M\u00c9dicos: An\u00c1lisis Cl\u00cdnicos",
    "sg:phone":"+34 971 55 25 40",
    "sg:postcode":"07500",
    "sg:province":"Islas Baleares",
    "wof:name":"Centre D'analisis Biologiques S.a.",
    "wof:placetype":"venue"
},
  "geometry": {"coordinates":[3.2091319561,39.569732666],"type":"Point"}
}