{
  "type": "Feature",
  "properties": {
    "iso:country":"ES",
    "sg:address":"Ctra Cordoba-malaga, Km. 0042,7",
    "sg:city":"Montilla",
    "sg:orig_category":"Alquiler De Material Y De Programas Audiovisuales",
    "sg:phone":"+34 957 65 11 54",
    "sg:postcode":"14550",
    "sg:province":"C\u00f3rdoba",
    "wof:name":"Vidosa Sonido E Iluminacion S.l.",
    "wof:placetype":"venue"
},
  "geometry": {"coordinates":[-4.6605410576,37.5884437561],"type":"Point"}
}