{
  "type": "Feature",
  "properties": {
    "addr:full":"Calle de Parque Vosa, 27 Mostoles Madrid 28933",
    "addr:housenumber":"27",
    "addr:postcode":"28933",
    "addr:street":"Calle De Parque Vosa",
    "iso:country":"ES",
    "sg:address":"Calle de Parque Vosa, 27",
    "sg:city":"Mostoles",
    "sg:orig_category":"Reposter\u00cdas",
    "sg:phone":"+34 916 13 39 85",
    "sg:postcode":"28933",
    "sg:province":"Madrid",
    "wof:name":"Cabello Lopez Angel",
    "wof:placetype":"venue"
},
  "geometry": {"coordinates":[-3.8636949062,40.3289680481],"type":"Point"}
}