{
  "type": "Feature",
  "properties": {
    "iso:country":"ES",
    "sg:address":"Calle de Rondon, 7",
    "sg:city":"Moralzarzal",
    "sg:orig_category":"Postigos, Persianas Y Celos\u00cdas",
    "sg:phone":"+34 918 57 75 82",
    "sg:postcode":"28411",
    "sg:province":"Madrid",
    "wof:name":"Gonzalez Crespo Ricardo",
    "wof:placetype":"venue"
},
  "geometry": {"coordinates":[-3.9711949825,40.67918396],"type":"Point"}
}