{
  "type": "Feature",
  "properties": {
    "iso:country":"ES",
    "sg:address":"Avda San Vicente Paul, 28",
    "sg:city":"Uncastillo",
    "sg:orig_category":"Controles De Edificaci\u00d3n (construcci\u00d3n, Seguridad)",
    "sg:phone":"+34 976 67 94 28",
    "sg:postcode":"50678",
    "sg:province":"Zaragoza",
    "wof:name":"Jarauta Fernandez Jose Alberto",
    "wof:placetype":"venue"
},
  "geometry": {"coordinates":[-1.1365920305,42.3583946228],"type":"Point"}
}