{
  "type": "Feature",
  "properties": {
    "iso:country":"ES",
    "sg:address":"Rua Chano Pi\u00d1eiro, 3",
    "sg:city":"Vigo",
    "sg:orig_category":"Radiocomunicaciones, Telefon\u00cda M\u00d3vil, Radiomensajer\u00cda: Servicios, Comercializaci\u00d3n",
    "sg:phone":"+34 986 24 79 55",
    "sg:postcode":"36208",
    "sg:province":"Pontevedra",
    "wof:name":"Telga Comunicaciones S.l.",
    "wof:placetype":"venue"
},
  "geometry": {"coordinates":[-8.7362165451,42.2262268066],"type":"Point"}
}