{
  "type": "Feature",
  "properties": {
    "iso:country":"ES",
    "sg:address":"Carrer de Pitarra, 74",
    "sg:city":"S. Feliu Guixols",
    "sg:orig_category":"Empresarios",
    "sg:phone":"+34 972 32 32 57",
    "sg:postcode":"17220",
    "sg:province":"Girona",
    "wof:name":"Alcalde Alonso Manuel",
    "wof:placetype":"venue"
},
  "geometry": {"coordinates":[3.026632309,41.7882003784],"type":"Point"}
}