{
  "type": "Feature",
  "properties": {
    "iso:country":"ES",
    "sg:address":"Afueras, S/n",
    "sg:city":"Aldeanueva Camino",
    "sg:orig_category":"Asilos De Ancianos. Centros Privados",
    "sg:phone":"+34 927 48 40 11",
    "sg:postcode":"10740",
    "sg:province":"C\u00e1ceres",
    "wof:name":"Residencia Fundacion Masides",
    "wof:placetype":"venue"
},
  "geometry": {"coordinates":[-5.9294190407,40.25989151],"type":"Point"}
}