{
  "type": "Feature",
  "properties": {
    "iso:country":"ES",
    "sg:address":"Avda Severino Fernandez, 60",
    "sg:city":"Tafalla",
    "sg:orig_category":"Cristaler\u00cdas",
    "sg:phone":"+34 948 70 28 09",
    "sg:postcode":"31300",
    "sg:province":"Navarra",
    "wof:name":"Parra Pecharroman Juan Manuel",
    "wof:placetype":"venue"
},
  "geometry": {"coordinates":[-1.6724649668,42.5319900513],"type":"Point"}
}