{
  "type": "Feature",
  "properties": {
    "iso:country":"ES",
    "sg:address":"Calle de Comandante Zorita, 38",
    "sg:city":"Madrid",
    "sg:orig_category":"Muebles Y Accesorios Para Cocinas Y Cuartos De Ba\u00d1o (al Por Menor)",
    "sg:phone":"+34 915 54 83 97",
    "sg:postcode":"28020",
    "sg:province":"Madrid",
    "wof:name":"Art. D. Cook El Dise\u00f1o En La Cocina S.l.",
    "wof:placetype":"venue"
},
  "geometry": {"coordinates":[-3.6982195377,40.4508743286],"type":"Point"}
}