{
  "type": "Feature",
  "properties": {
    "iso:country":"ES",
    "sg:address":"Carrer de Jesus, 11",
    "sg:city":"Reus",
    "sg:orig_category":"Cester\u00cda (fabricaci\u00d3n)",
    "sg:phone":"+34 977 34 43 27",
    "sg:postcode":"43201",
    "sg:province":"Tarragona",
    "wof:name":"Cistelleria Carbonell S.c.p.",
    "wof:placetype":"venue"
},
  "geometry": {"coordinates":[1.1081689596,41.1546859741],"type":"Point"}
}