{
  "type": "Feature",
  "properties": {
    "addr:full":"Av Valles, 340 Terrassa Barcelona 08227",
    "addr:housenumber":"340",
    "addr:postcode":"08227",
    "addr:street":"Av Valles",
    "iso:country":"ES",
    "sg:address":"Av Valles, 340",
    "sg:city":"Terrassa",
    "sg:orig_category":"Reciclaje, Desguace De Veh\u00cdculos",
    "sg:phone":"+34 937 86 42 64",
    "sg:postcode":"08227",
    "sg:province":"Barcelona",
    "wof:name":"Vilaltella Serret Pedro",
    "wof:placetype":"venue"
},
  "geometry": {"coordinates":[2.0339729786,41.5597763062],"type":"Point"}
}