{
  "type": "Feature",
  "properties": {
    "addr:full":"Calle de Castillo, 9 Arjona Ja\u00e9n 23760",
    "addr:housenumber":"9",
    "addr:postcode":"23760",
    "addr:street":"Calle De Castillo;Jae\u0301N",
    "iso:country":"ES",
    "sg:address":"Calle de Castillo, 9",
    "sg:city":"Arjona",
    "sg:orig_category":"Lavado, Limpieza De Veh\u00cdculos",
    "sg:phone":"+34 953 51 86 61",
    "sg:postcode":"23760",
    "sg:province":"Ja\u00e9n",
    "wof:name":"Calderat Cisneos Francisco",
    "wof:placetype":"venue"
},
  "geometry": {"coordinates":[-4.0557551384,37.9369316101],"type":"Point"}
}