{
  "type": "Feature",
  "properties": {
    "addr:full":"Av. Esparta, 29 Entremontes Madrid 28230",
    "addr:housenumber":"29",
    "addr:postcode":"28230",
    "addr:street":"Av. Esparta",
    "iso:country":"ES",
    "sg:address":"Av. Esparta, 29",
    "sg:city":"Entremontes",
    "sg:orig_category":"Inmobiliaria (agencias)",
    "sg:phone":"+34 916 31 77 10",
    "sg:postcode":"28230",
    "sg:province":"Madrid",
    "wof:name":"Alonso Martin Juan Carlos",
    "wof:placetype":"venue"
},
  "geometry": {"coordinates":[-3.9074354172,40.517780304],"type":"Point"}
}