{
  "type": "Feature",
  "properties": {
    "iso:country":"ES",
    "sg:address":"Avda Alfonso Xiii, 117",
    "sg:city":"Madrid",
    "sg:orig_category":"Distribuci\u00d3n De Petr\u00d3leo Y Derivados",
    "sg:phone":"+34 913 50 19 46",
    "sg:postcode":"28016",
    "sg:province":"Madrid",
    "wof:name":"Gonzalez David Maria Del Mar",
    "wof:placetype":"venue"
},
  "geometry": {"coordinates":[-3.6688320637,40.4593734741],"type":"Point"}
}