{
  "type": "Feature",
  "properties": {
    "iso:country":"ES",
    "sg:address":"Calle de Tejerias, 10",
    "sg:city":"Tudela",
    "sg:orig_category":"Desinfecci\u00d3n, Desinsectaci\u00d3n, Desratizaci\u00d3n",
    "sg:phone":"+34 948 82 55 88",
    "sg:postcode":"31500",
    "sg:province":"Navarra",
    "wof:name":"Desinfecciones Tripled S.l.",
    "wof:placetype":"venue"
},
  "geometry": {"coordinates":[-1.6117819548,42.0676612854],"type":"Point"}
}