{
  "type": "Feature",
  "properties": {
    "addr:full":"Gijun, 13 La Carrera Asturias 33187",
    "addr:housenumber":"13",
    "addr:postcode":"33187",
    "addr:street":"Gijun",
    "iso:country":"ES",
    "sg:address":"Gijun, 13",
    "sg:city":"La Carrera",
    "sg:orig_category":"Carnicer\u00cdas, Carnicer\u00cdas",
    "sg:phone":"+34 985 74 00 22",
    "sg:postcode":"33187",
    "sg:province":"Asturias",
    "wof:name":"Fernandez Rios Maria",
    "wof:placetype":"venue"
},
  "geometry": {"coordinates":[-5.7102842331,43.3833198547],"type":"Point"}
}