{
  "type": "Feature",
  "properties": {
    "iso:country":"ES",
    "sg:address":"Autovia Logro\u00f1o, Km. 0005,7",
    "sg:city":"Zaragoza",
    "sg:orig_category":"Alquiler De Camiones Y Veh\u00cdculos Industriales",
    "sg:phone":"+34 976 78 30 89",
    "sg:postcode":"50011",
    "sg:province":"Zaragoza",
    "wof:name":"Alquivisa",
    "wof:placetype":"venue"
},
  "geometry": {"coordinates":[-0.9607232213,41.6783638],"type":"Point"}
}