{
  "type": "Feature",
  "properties": {
    "addr:full":"Calle de Entre Los Rios, S/n Castrocalbon Le\u00f3n 24760",
    "addr:postcode":"24760",
    "addr:street":"Calle De Entre Los Rios S / N Castrocalbon Leo\u0301N",
    "iso:country":"ES",
    "sg:address":"Calle de Entre Los Rios, S/n",
    "sg:city":"Castrocalbon",
    "sg:orig_category":"Centros De Educaci\u00d3n Especial",
    "sg:phone":"+34 987 67 10 37",
    "sg:postcode":"24760",
    "sg:province":"Le\u00f3n",
    "wof:name":"Colegio Rural Agrupado Eria-jamuz",
    "wof:placetype":"venue"
},
  "geometry": {"coordinates":[-5.9804291725,42.1928787231],"type":"Point"}
}