{
  "type": "Feature",
  "properties": {
    "iso:country":"ES",
    "sg:address":"Vilar, S/n",
    "sg:city":"Vilar",
    "sg:orig_category":"Carnicer\u00cdas, Carnicer\u00cdas",
    "sg:phone":"+34 982 30 00 49",
    "sg:postcode":"27364",
    "sg:province":"Lugo",
    "wof:name":"Rivera Diaz Manuel",
    "wof:placetype":"venue"
},
  "geometry": {"coordinates":[-7.2342190742,42.9877204895],"type":"Point"}
}