{
  "type": "Feature",
  "properties": {
    "iso:country":"ES",
    "sg:address":"Trva Maragateria, 9",
    "sg:city":"Astorga",
    "sg:orig_category":"Fabrica De Charcuter\u00cda",
    "sg:phone":"+34 987 61 93 29",
    "sg:postcode":"24700",
    "sg:province":"Le\u00f3n",
    "wof:name":"Embutidos Y Jamones El Maragato S.l.",
    "wof:placetype":"venue"
},
  "geometry": {"coordinates":[-6.0654940605,42.4577407837],"type":"Point"}
}