{
  "type": "Feature",
  "properties": {
    "iso:country":"ES",
    "sg:address":"Barr San Inazio, 9",
    "sg:city":"San Inazio",
    "sg:orig_category":"Serrer\u00cdas De Madera",
    "sg:phone":"+34 946 31 30 65",
    "sg:postcode":"48330",
    "sg:province":"Vizcaya",
    "wof:name":"Maderas Echevarria S.l.",
    "wof:placetype":"venue"
},
  "geometry": {"coordinates":[-2.7691090107,43.2078361511],"type":"Point"}
}