{
  "type": "Feature",
  "properties": {
    "addr:full":"Avda Espa\u00d1a, 2 Olmedo Valladolid 47410",
    "addr:housenumber":"2",
    "addr:postcode":"47410",
    "addr:street":"Avda Espan\u0303A",
    "iso:country":"ES",
    "sg:address":"Avda Espa\u00d1a, 2",
    "sg:city":"Olmedo",
    "sg:orig_category":"Ense\u00d1anza: Profesiones Art\u00cdsticas",
    "sg:phone":"+34 983 60 01 13",
    "sg:postcode":"47410",
    "sg:province":"Valladolid",
    "wof:name":"Baruque De San Jose Purificacion",
    "wof:placetype":"venue"
},
  "geometry": {"coordinates":[-4.6851091385,41.2856674194],"type":"Point"}
}