{
  "type": "Feature",
  "properties": {
    "addr:full":"Carrer de Barcelona (de), 37 Salou Tarragona 43840",
    "addr:housenumber":"37",
    "addr:postcode":"43840",
    "addr:street":"Carrer De Barcelona De",
    "iso:country":"ES",
    "sg:address":"Carrer de Barcelona (de), 37",
    "sg:city":"Salou",
    "sg:orig_category":"Peluquer\u00cdas, Peluquer\u00cda Mixta",
    "sg:phone":"+34 977 35 12 74",
    "sg:postcode":"43840",
    "sg:province":"Tarragona",
    "wof:name":"Colmenero Moreno Jose Joaquin",
    "wof:placetype":"venue"
},
  "geometry": {"coordinates":[1.131180048,41.0789718628],"type":"Point"}
}