{
  "type": "Feature",
  "properties": {
    "addr:full":"Carrer de Torres Amat, 39 Sallent Barcelona 08650",
    "addr:housenumber":"39",
    "addr:postcode":"08650",
    "addr:street":"Carrer De Torres Amat",
    "iso:country":"ES",
    "sg:address":"Carrer de Torres Amat, 39",
    "sg:city":"Sallent",
    "sg:orig_category":"Bibliotecas, Mediatecas",
    "sg:phone":"+34 938 20 63 01",
    "sg:postcode":"08650",
    "sg:province":"Barcelona",
    "wof:name":"Ajuntament De Sallent",
    "wof:placetype":"venue"
},
  "geometry": {"coordinates":[1.8948421478,41.8239746094],"type":"Point"}
}