{
  "type": "Feature",
  "properties": {
    "addr:full":"Bo. Abajo, S/n Villasante Burgos 09569",
    "addr:housenumber":"s",
    "addr:postcode":"09569",
    "addr:street":"Abajo;/ N Villasante",
    "iso:country":"ES",
    "sg:address":"Bo. Abajo, S/n",
    "sg:city":"Villasante",
    "sg:orig_category":"Ense\u00d1anza, Formaci\u00d3n Profesional: Aprendizaje",
    "sg:phone":"+34 947 14 00 94",
    "sg:postcode":"09569",
    "sg:province":"Burgos",
    "wof:name":"Ayuntamiento De Merindad De Montija",
    "wof:placetype":"venue"
},
  "geometry": {"coordinates":[-3.4740591049,43.0654754639],"type":"Point"}
}