{
  "type": "Feature",
  "properties": {
    "iso:country":"ES",
    "sg:address":"Pl Constitucion(sta Lucia), 38",
    "sg:city":"Cartagena",
    "sg:orig_category":"Iglesia Cat\u00d3lica",
    "sg:phone":"+34 968 50 28 17",
    "sg:postcode":"30202",
    "sg:province":"Murcia",
    "wof:name":"Parroquia De Santiago Apostol",
    "wof:placetype":"venue"
},
  "geometry": {"coordinates":[-0.972145021,37.5986213684],"type":"Point"}
}