{
  "type": "Feature",
  "properties": {
    "iso:country":"ES",
    "sg:address":"Calle de Castillo Del Ingles, 11",
    "sg:city":"Torremolinos",
    "sg:orig_category":"Oficinas Y Gesti\u00d3n De Inmuebles",
    "sg:phone":"+34 952 37 06 00",
    "sg:postcode":"29620",
    "sg:province":"M\u00e1laga",
    "wof:name":"Representaciones Tecnicas Inmobiliarias S.l",
    "wof:placetype":"venue"
},
  "geometry": {"coordinates":[-4.4997830391,36.6175956726],"type":"Point"}
}