{
  "type": "Feature",
  "properties": {
    "iso:country":"ES",
    "sg:address":"Avda Gijon, Km. 0195,0",
    "sg:city":"Valladolid",
    "sg:orig_category":"Empresas De Carpinter\u00cda De Madera",
    "sg:phone":"+34 983 37 56 66",
    "sg:postcode":"47009",
    "sg:province":"Valladolid",
    "wof:name":"Arranz Hernandez Manuel",
    "wof:placetype":"venue"
},
  "geometry": {"coordinates":[-4.7497925758,41.6608428955],"type":"Point"}
}