{
  "type": "Feature",
  "properties": {
    "iso:country":"ES",
    "sg:address":"Calle de Sor Valentina Miron, 11",
    "sg:city":"Plasencia",
    "sg:orig_category":"Muebles, Minoristas",
    "sg:phone":"+34 927 42 19 94",
    "sg:postcode":"10600",
    "sg:province":"C\u00e1ceres",
    "wof:name":"Martil Martil Esperanza",
    "wof:placetype":"venue"
},
  "geometry": {"coordinates":[-6.0914888382,40.0320587158],"type":"Point"}
}