{
  "type": "Feature",
  "properties": {
    "iso:country":"ES",
    "sg:address":"Avda Gran Canaria (de), S/n",
    "sg:city":"Playa Del Ingles",
    "sg:orig_category":"Confecci\u00d3n (fabricaci\u00d3n, Al Por Mayor)",
    "sg:phone":"+34 928 77 30 44",
    "sg:postcode":"35100",
    "sg:province":"Las Palmas",
    "wof:name":"Macario Tejera Carmelo",
    "wof:placetype":"venue"
},
  "geometry": {"coordinates":[-15.5810842514,27.7560195923],"type":"Point"}
}