{
  "type": "Feature",
  "properties": {
    "addr:full":"Calle de Carretera, 34 Rabita Granada 18760",
    "addr:housenumber":"34",
    "addr:postcode":"18760",
    "addr:street":"Calle De Carretera",
    "iso:country":"ES",
    "sg:address":"Calle de Carretera, 34",
    "sg:city":"Rabita",
    "sg:orig_category":"Productores Recolectores, Venta Directa De Vinos",
    "sg:phone":"+34 958 82 90 19",
    "sg:postcode":"18760",
    "sg:province":"Granada",
    "wof:name":"Tarifa Fernandez Josefa",
    "wof:placetype":"venue"
},
  "geometry": {"coordinates":[-3.1702539921,36.7486724854],"type":"Point"}
}