{
  "type": "Feature",
  "properties": {
    "iso:country":"ES",
    "sg:address":"Calle de Riocabado, 7",
    "sg:city":"Madrid",
    "sg:orig_category":"Comercio De Piezas De Recambio Y De Accesorios De Veh\u00cdculos, Veh\u00cdculos Industriales",
    "sg:phone":"+34 914 63 00 01",
    "sg:postcode":"28047",
    "sg:province":"Madrid",
    "wof:name":"Recambios Puma 3 S.l",
    "wof:placetype":"venue"
},
  "geometry": {"coordinates":[-3.7381219864,40.4029388428],"type":"Point"}
}