{
  "type": "Feature",
  "properties": {
    "iso:country":"ES",
    "sg:address":"Calle de Jesus Del Perdon, 30",
    "sg:city":"Manzanares",
    "sg:orig_category":"Procuradores",
    "sg:phone":"+34 926 61 08 02",
    "sg:postcode":"13200",
    "sg:province":"Ciudad Real",
    "wof:name":"Garcia De Dionisio Montemayor Maria Del Pilar",
    "wof:placetype":"venue"
},
  "geometry": {"coordinates":[-3.3754909039,39.0006561279],"type":"Point"}
}