{
  "type": "Feature",
  "properties": {
    "addr:full":"Calle de Ferraz, 73 Madrid Madrid 28008",
    "addr:housenumber":"73",
    "addr:postcode":"madrid;28008",
    "addr:street":"Calle De Ferraz",
    "iso:country":"ES",
    "sg:address":"Calle de Ferraz, 73",
    "sg:city":"Madrid",
    "sg:orig_category":"Farmacias",
    "sg:phone":"+34 915 44 69 57",
    "sg:postcode":"28008",
    "sg:province":"Madrid",
    "wof:name":"Leon Izard Maria Pilar",
    "wof:placetype":"venue"
},
  "geometry": {"coordinates":[-3.7227859497,40.4317588806],"type":"Point"}
}