{
  "type": "Feature",
  "properties": {
    "addr:full":"Calle de General San Martin, 18 Valencia Valencia 46004",
    "addr:housenumber":"18",
    "addr:postcode":"46004",
    "addr:street":"Calle De General San Martin",
    "iso:country":"ES",
    "sg:address":"Calle de General San Martin, 18",
    "sg:city":"Valencia",
    "sg:classifiers":[
        {
            "category":"Personal",
            "subcategory":"Barber",
            "type":"Services"
        }
    ],
    "sg:phone":"+34 963 42 39 17",
    "sg:postcode":"46004",
    "sg:province":"Valencia",
    "sg:tags":[
        "caballeros",
        "de",
        "peluqueros"
    ],
    "wof:name":"Querol Stil S.l.",
    "wof:placetype":"venue"
},
  "geometry": {"coordinates":[-0.3747659922,39.46509552],"type":"Point"}
}