{
  "type": "Feature",
  "properties": {
    "iso:country":"ES",
    "sg:address":"Torras I Bages, 3",
    "sg:city":"S. Hilari Sacalm",
    "sg:orig_category":"Comercio, Reparaci\u00d3n De Motocicletas, Bicicletas Y Piezas Sueltas",
    "sg:phone":"+34 972 87 22 12",
    "sg:postcode":"17403",
    "sg:province":"Girona",
    "wof:name":"Villegas Jurado Jose",
    "wof:placetype":"venue"
},
  "geometry": {"coordinates":[2.5108449459,41.8810768127],"type":"Point"}
}