{
  "type": "Feature",
  "properties": {
    "addr:full":"Carr Finestres, 22 Planes D'hostoles Girona 17172",
    "addr:housenumber":"22",
    "addr:postcode":"17172",
    "addr:street":"Carr Finestres;D'Hostoles",
    "iso:country":"ES",
    "sg:address":"Carr Finestres, 22",
    "sg:city":"Planes D'hostoles",
    "sg:orig_category":"Transportes Por V\u00cdas Navegables",
    "sg:phone":"+34 972 44 80 98",
    "sg:postcode":"17172",
    "sg:province":"Girona",
    "wof:name":"Garcia O\u00f1a Jose",
    "wof:placetype":"venue"
},
  "geometry": {"coordinates":[2.5476725101,42.0525436401],"type":"Point"}
}