{
  "type": "Feature",
  "properties": {
    "addr:full":"Calle de Darrillo Magdalena, 7 Granada Granada 18002",
    "addr:housenumber":"7",
    "addr:postcode":"18002",
    "addr:street":"Calle De Darrillo Magdalena",
    "iso:country":"ES",
    "sg:address":"Calle de Darrillo Magdalena, 7",
    "sg:city":"Granada",
    "sg:orig_category":"Ropa Para Ni\u00d1os (al Por Menor)",
    "sg:phone":"+34 958 26 72 57",
    "sg:postcode":"18002",
    "sg:province":"Granada",
    "wof:name":"Jimenez Soto Jose Manuel",
    "wof:placetype":"venue"
},
  "geometry": {"coordinates":[-3.6014530659,37.1737785339],"type":"Point"}
}