{
  "type": "Feature",
  "properties": {
    "iso:country":"ES",
    "sg:address":"Ctra Canyet, 6",
    "sg:city":"Badalona",
    "sg:orig_category":"Organizaci\u00d3n De Actos, Seminarios Y Congresos",
    "sg:phone":"+34 933 95 57 61",
    "sg:postcode":"08915",
    "sg:province":"Barcelona",
    "wof:name":"Restaurante Devesa S.a.",
    "wof:placetype":"venue"
},
  "geometry": {"coordinates":[2.2383298874,41.4651145935],"type":"Point"}
}