{
  "type": "Feature",
  "properties": {
    "addr:full":"Avda Doctor Gomez Ferrer, 67 Alfafar Valencia 46910",
    "addr:housenumber":"67",
    "addr:postcode":"46910",
    "addr:street":"Avda Doctor Gomez Ferrer",
    "iso:country":"ES",
    "sg:address":"Avda Doctor Gomez Ferrer, 67",
    "sg:city":"Alfafar",
    "sg:orig_category":"Muebles, Minoristas",
    "sg:phone":"+34 963 75 39 58",
    "sg:postcode":"46910",
    "sg:province":"Valencia",
    "wof:name":"Hipermuebles La Rivera S.l.",
    "wof:placetype":"venue"
},
  "geometry": {"coordinates":[-0.3936389983,39.4264602661],"type":"Point"}
}