{
  "type": "Feature",
  "properties": {
    "addr:full":"Calle de Serrano, 61 Madrid Madrid 28006",
    "addr:housenumber":"61",
    "addr:postcode":"madrid;28006",
    "addr:street":"Calle De Serrano",
    "iso:country":"ES",
    "sg:address":"Calle de Serrano, 61",
    "sg:city":"Madrid",
    "sg:orig_category":"Agencias De Viajes",
    "sg:phone":"+34 915 78 16 26",
    "sg:postcode":"28006",
    "sg:province":"Madrid",
    "sg:website":"www.halconviajes.com",
    "wof:name":"Viajes Halcon S.a.",
    "wof:placetype":"venue"
},
  "geometry": {"coordinates":[-3.6869249344,40.4321975708],"type":"Point"}
}