{
  "type": "Feature",
  "properties": {
    "addr:full":"Avda Musica Espa\u00d1ola (de La), 121 Cuenca Cuenca 16004",
    "addr:housenumber":"121",
    "addr:postcode":"16004",
    "addr:street":"Avda Musica",
    "iso:country":"ES",
    "sg:address":"Avda Musica Espa\u00d1ola (de La), 121",
    "sg:city":"Cuenca",
    "sg:orig_category":"Abogados",
    "sg:phone":"+34 969 17 21 86",
    "sg:postcode":"16004",
    "sg:province":"Cuenca",
    "wof:name":"Martinez Vindel Adrian",
    "wof:placetype":"venue"
},
  "geometry": {"coordinates":[-2.1226110458,40.0580101013],"type":"Point"}
}