{
  "type": "Feature",
  "properties": {
    "iso:country":"ES",
    "sg:address":"Calle de Medico Pascual Perez, 13",
    "sg:city":"Alacant",
    "sg:orig_category":"Servicios Gsm",
    "sg:phone":"+34 965 14 68 97",
    "sg:postcode":"03001",
    "sg:province":"Alicante",
    "wof:name":"Basetel 2000 S.l.",
    "wof:placetype":"venue"
},
  "geometry": {"coordinates":[-0.4866400063,38.3465423584],"type":"Point"}
}