{
  "type": "Feature",
  "properties": {
    "iso:country":"ES",
    "sg:address":"Calle de Quevedo, S/n",
    "sg:city":"Andujar",
    "sg:orig_category":"Fabricaci\u00d3n De Ropa De Deportes",
    "sg:phone":"+34 953 50 18 11",
    "sg:postcode":"23740",
    "sg:province":"Ja\u00e9n",
    "wof:name":"Izquierdo San Blas Francisca",
    "wof:placetype":"venue"
},
  "geometry": {"coordinates":[-4.0504641533,38.03956604],"type":"Point"}
}