{
  "type": "Feature",
  "properties": {
    "iso:country":"ES",
    "sg:address":"Calle de Merindades (las), S/n",
    "sg:city":"Castejon",
    "sg:classifiers":[
        {
            "category":"Home & Garden",
            "subcategory":"Building Materials",
            "type":"Retail Goods"
        }
    ],
    "sg:phone":"+34 948 77 02 64",
    "sg:postcode":"31590",
    "sg:province":"Navarra",
    "sg:tags":[
        "limpieza",
        "de",
        "industrial"
    ],
    "sg:website":"www.ekin-sa.com",
    "wof:name":"Equipamientos Industriales S.a.",
    "wof:placetype":"venue"
},
  "geometry": {"coordinates":[-1.6907789707,42.1715087891],"type":"Point"}
}