{
  "type": "Feature",
  "properties": {
    "iso:country":"ES",
    "sg:address":"Calle de San Francisco, 2",
    "sg:city":"Vitoria-gasteiz",
    "sg:orig_category":"Farmacias",
    "sg:phone":"+34 945 25 98 43",
    "sg:postcode":"01001",
    "sg:province":"\u00c1lava",
    "wof:name":"Puente Valdivielso Gonzalo",
    "wof:placetype":"venue"
},
  "geometry": {"coordinates":[-2.6695849895,42.8471221924],"type":"Point"}
}