{
  "type": "Feature",
  "properties": {
    "addr:full":"Calle de Recoletos, 11 Madrid Madrid 28001",
    "addr:housenumber":"11",
    "addr:postcode":"madrid;28001",
    "addr:street":"Calle De Recoletos",
    "iso:country":"ES",
    "sg:address":"Calle de Recoletos, 11",
    "sg:city":"Madrid",
    "sg:orig_category":"Ense\u00d1anza: Idiomas",
    "sg:phone":"+34 914 35 22 62",
    "sg:postcode":"28001",
    "sg:province":"Madrid",
    "wof:name":"Madrid Sal Y Ven Con Nosotros S.l",
    "wof:placetype":"venue"
},
  "geometry": {"coordinates":[-3.6901159286,40.4220275879],"type":"Point"}
}