{
  "type": "Feature",
  "properties": {
    "iso:country":"ES",
    "sg:address":"Calle de Antonio Alcaide Sanchez, 3",
    "sg:city":"Torremolinos",
    "sg:orig_category":"Promotores Constructores",
    "sg:phone":"+34 952 05 85 39",
    "sg:postcode":"29620",
    "sg:province":"M\u00e1laga",
    "wof:name":"Real Montealto Sl",
    "wof:placetype":"venue"
},
  "geometry": {"coordinates":[-4.515226841,36.612663269],"type":"Point"}
}