{
  "type": "Feature",
  "properties": {
    "addr:full":"Ctra. Montblanc, S/n Reus Tarragona 43206",
    "addr:housenumber":"s / n",
    "addr:postcode":"43206",
    "addr:street":"Ctra. Montblanc",
    "iso:country":"ES",
    "sg:address":"Ctra. Montblanc, S/n",
    "sg:city":"Reus",
    "sg:orig_category":"Escotaduras, Torneados",
    "sg:phone":"+34 977 34 09 14",
    "sg:postcode":"43206",
    "sg:province":"Tarragona",
    "wof:name":"Mecanizados Emilio",
    "wof:placetype":"venue"
},
  "geometry": {"coordinates":[1.1219400167,41.1646156311],"type":"Point"}
}