{
  "type": "Feature",
  "properties": {
    "iso:country":"ES",
    "sg:address":"Avda De Les Corts Valencianes, 7",
    "sg:city":"Alcora",
    "sg:orig_category":"Empresas De Portes Y Mensajer\u00cda",
    "sg:phone":"+34 964 38 65 89",
    "sg:postcode":"12110",
    "sg:province":"Castell\u00f3n",
    "wof:name":"Zafra Anguita Manuel",
    "wof:placetype":"venue"
},
  "geometry": {"coordinates":[-0.2140807956,40.0722465515],"type":"Point"}
}