{
  "type": "Feature",
  "properties": {
    "addr:full":"Calle de Antonio Machado, 24 Madrid Madrid 28035",
    "addr:housenumber":"24",
    "addr:postcode":"madrid;28035",
    "addr:street":"Calle De Antonio Machado",
    "iso:country":"ES",
    "sg:address":"Calle de Antonio Machado, 24",
    "sg:city":"Madrid",
    "sg:orig_category":"Iglesia Cat\u00d3lica",
    "sg:phone":"+34 913 73 30 32",
    "sg:postcode":"28035",
    "sg:province":"Madrid",
    "wof:name":"Parroquia De La Cena Del Se\u00f1or",
    "wof:placetype":"venue"
},
  "geometry": {"coordinates":[-3.7195329666,40.4677238464],"type":"Point"}
}