{
  "type": "Feature",
  "properties": {
    "addr:full":"Mouretan, 14 Mouretan Pontevedra 36710",
    "addr:housenumber":"14",
    "addr:postcode":"36710",
    "addr:street":"Mouretan",
    "iso:country":"ES",
    "sg:address":"Mouretan, 14",
    "sg:city":"Mouretan",
    "sg:orig_category":"Cr\u00cda De Animales",
    "sg:phone":"+34 986 63 98 36",
    "sg:postcode":"36710",
    "sg:province":"Pontevedra",
    "wof:name":"Lorenzo Lopez Nemesio",
    "wof:placetype":"venue"
},
  "geometry": {"coordinates":[-8.6480531693,42.4336204529],"type":"Point"}
}