{
  "type": "Feature",
  "properties": {
    "iso:country":"ES",
    "sg:address":"Calle de Santo Domingo, 11",
    "sg:city":"Alcorcon",
    "sg:orig_category":"Centros M\u00c9dicos Y Sociales, Dispensarios",
    "sg:phone":"+34 916 43 33 83",
    "sg:postcode":"28921",
    "sg:province":"Madrid",
    "wof:name":"Medicina Laboral Informatica S.l.",
    "wof:placetype":"venue"
},
  "geometry": {"coordinates":[-3.8241760731,40.3445053101],"type":"Point"}
}