{
  "type": "Feature",
  "properties": {
    "iso:country":"ES",
    "sg:address":"Calle de Hortaleza, 7",
    "sg:city":"Madrid",
    "sg:orig_category":"Bisuter\u00cda, Joyer\u00cda, Relojer\u00cda (al Por Menor)",
    "sg:phone":"+34 915 22 70 02",
    "sg:postcode":"28004",
    "sg:province":"Madrid",
    "wof:name":"Martin Garcia Lorenzo",
    "wof:placetype":"venue"
},
  "geometry": {"coordinates":[-3.700865984,40.4206008911],"type":"Point"}
}