{
  "type": "Feature",
  "properties": {
    "iso:country":"ES",
    "sg:address":"Pase Espolon (el), S/n",
    "sg:city":"Soria",
    "sg:orig_category":"Restaurantes",
    "sg:phone":"+34 975 22 60 34",
    "sg:postcode":"42001",
    "sg:province":"Soria",
    "wof:name":"La Alameda De Cervantes S.l.",
    "wof:placetype":"venue"
},
  "geometry": {"coordinates":[-2.4691669941,41.7646598816],"type":"Point"}
}