{
  "type": "Feature",
  "properties": {
    "iso:country":"ES",
    "sg:address":"Ctra Sierra (de La), 84",
    "sg:city":"Granada",
    "sg:orig_category":"Caf\u00c9s, Bares, Cervecer\u00cdas",
    "sg:phone":"+34 958 22 71 21",
    "sg:postcode":"18008",
    "sg:province":"Granada",
    "wof:name":"Cafe Bar Robledo C.b.",
    "wof:placetype":"venue"
},
  "geometry": {"coordinates":[-3.5798230171,37.1648216248],"type":"Point"}
}