{
  "type": "Feature",
  "properties": {
    "iso:country":"ES",
    "sg:address":"Carrer de Crom, 35",
    "sg:city":"Hospitalet Llobregat",
    "sg:orig_category":"Camiser\u00cda Y Ropa Interior Masculina (al Por Menor)",
    "sg:phone":"+34 933 35 61 75",
    "sg:postcode":"08907",
    "sg:province":"Barcelona",
    "wof:name":"Marti Izquierdo Jordi",
    "wof:placetype":"venue"
},
  "geometry": {"coordinates":[2.1036729813,41.3523292542],"type":"Point"}
}