{
  "type": "Feature",
  "properties": {
    "addr:full":"Calle de Alcalde Garret Y Souto, 38 Malaga M\u00e1laga 29006",
    "addr:housenumber":"38",
    "addr:postcode":"29006",
    "addr:street":"Calle De Alcalde Garret Y Souto;Ma\u0301Laga",
    "iso:country":"ES",
    "sg:address":"Calle de Alcalde Garret Y Souto, 38",
    "sg:city":"Malaga",
    "sg:orig_category":"Empresarios",
    "sg:phone":"+34 952 31 02 18",
    "sg:postcode":"29006",
    "sg:province":"M\u00e1laga",
    "wof:name":"Reformas Y Rehabilitaciones Laris S.l.",
    "wof:placetype":"venue"
},
  "geometry": {"coordinates":[-4.4755282402,36.7084503174],"type":"Point"}
}