{
  "type": "Feature",
  "properties": {
    "iso:country":"ES",
    "sg:address":"Avda Paz De (la), 43",
    "sg:city":"Logro\u00f1o",
    "sg:orig_category":"\u00d3ptica: Instrumentos (fabricaci\u00d3n)",
    "sg:phone":"+34 941 25 92 51",
    "sg:postcode":"26004",
    "sg:province":"La Rioja",
    "wof:name":"Romanos Segura Enrique",
    "wof:placetype":"venue"
},
  "geometry": {"coordinates":[-2.4356799126,42.4648475647],"type":"Point"}
}