{
  "type": "Feature",
  "properties": {
    "addr:full":"Ptge Mar, 3 Barri Antic Barcelona 08390",
    "addr:housenumber":"3",
    "addr:postcode":"08390",
    "addr:street":"Ptge Mar",
    "iso:country":"ES",
    "sg:address":"Ptge Mar, 3",
    "sg:city":"Barri Antic",
    "sg:orig_category":"Ense\u00d1anza: Imagen Y Sonido",
    "sg:phone":"+34 934 69 16 97",
    "sg:postcode":"08390",
    "sg:province":"Barcelona",
    "wof:name":"Sensemaya S.l",
    "wof:placetype":"venue"
},
  "geometry": {"coordinates":[2.2786700726,41.4704208374],"type":"Point"}
}