{
  "type": "Feature",
  "properties": {
    "addr:full":"Avda Europa, 17 Pozuelo De Alarcon Madrid 28224",
    "addr:housenumber":"17",
    "addr:postcode":"28224",
    "addr:street":"Avda Europa",
    "iso:country":"ES",
    "sg:address":"Avda Europa, 17",
    "sg:city":"Pozuelo De Alarcon",
    "sg:orig_category":"Agencias De Viajes",
    "sg:phone":"+34 913 52 03 43",
    "sg:postcode":"28224",
    "sg:province":"Madrid",
    "sg:website":"www.marsans.es",
    "wof:name":"Viajes Marsans S.a.",
    "wof:placetype":"venue"
},
  "geometry": {"coordinates":[-3.7889230251,40.4404525757],"type":"Point"}
}