{
  "type": "Feature",
  "properties": {
    "addr:full":"Carrer de Amadeu, 39 Calella Barcelona 08370",
    "addr:housenumber":"39",
    "addr:postcode":"08370",
    "addr:street":"Carrer De Amadeu",
    "iso:country":"ES",
    "sg:address":"Carrer de Amadeu, 39",
    "sg:city":"Calella",
    "sg:orig_category":"Agencias De Viajes",
    "sg:phone":"+34 937 69 56 64",
    "sg:postcode":"08370",
    "sg:province":"Barcelona",
    "wof:name":"Viajes Union 2 S. L.",
    "wof:placetype":"venue"
},
  "geometry": {"coordinates":[2.6646099091,41.6154975891],"type":"Point"}
}