{
  "type": "Feature",
  "properties": {
    "addr:full":"Pase Santa Maria De La Cabeza, 68 Madrid Madrid 28045",
    "addr:housenumber":"68",
    "addr:postcode":"madrid;28045",
    "addr:street":"Cabeza",
    "iso:country":"ES",
    "sg:address":"Pase Santa Maria De La Cabeza, 68",
    "sg:city":"Madrid",
    "sg:orig_category":"Ropa De Hogar (al Por Menor)",
    "sg:phone":"+34 914 74 51 01",
    "sg:postcode":"28045",
    "sg:province":"Madrid",
    "wof:name":"Enrique Alonso Hidalgo Y Otros C.b.",
    "wof:placetype":"venue"
},
  "geometry": {"coordinates":[-3.7003090382,40.4000511169],"type":"Point"}
}