{
  "type": "Feature",
  "properties": {
    "iso:country":"ES",
    "sg:address":"Avda Sinforiano Madro\u00d1ero, 17",
    "sg:city":"Badajoz",
    "sg:orig_category":"Farmacias",
    "sg:phone":"+34 924 22 28 59",
    "sg:postcode":"06011",
    "sg:province":"Badajoz",
    "wof:name":"Martinez De Medinilla Martinez Mediero Carlos",
    "wof:placetype":"venue"
},
  "geometry": {"coordinates":[-6.9877910614,38.8697547913],"type":"Point"}
}