{
  "type": "Feature",
  "properties": {
    "addr:full":"Rua Cuba (de), 7 Carballi\u00f1o Ourense 32500",
    "addr:postcode":"32500",
    "addr:street":"Rua Cuba De 7 Carballin\u0303O",
    "iso:country":"ES",
    "sg:address":"Rua Cuba (de), 7",
    "sg:city":"Carballi\u00f1o",
    "sg:orig_category":"Electricidad, Electr\u00d3nica: Material Y Suministros (al Por Mayor)",
    "sg:phone":"+34 988 27 37 59",
    "sg:postcode":"32500",
    "sg:province":"Ourense",
    "wof:name":"Robotizacion Industrial De Galicia S.l.",
    "wof:placetype":"venue"
},
  "geometry": {"coordinates":[-8.0796642303,42.432559967],"type":"Point"}
}