{
  "type": "Feature",
  "properties": {
    "addr:full":"Fano, S/n Fano Asturias 33391",
    "addr:housenumber":"s / n",
    "addr:postcode":"33391",
    "addr:street":"Fano",
    "iso:country":"ES",
    "sg:address":"Fano, S/n",
    "sg:city":"Fano",
    "sg:orig_category":"Restaurantes",
    "sg:phone":"+34 985 13 64 56",
    "sg:postcode":"33391",
    "sg:province":"Asturias",
    "wof:name":"Restaurante La Tabla Gijon S.l.",
    "wof:placetype":"venue"
},
  "geometry": {"coordinates":[-5.6502809525,43.4943695068],"type":"Point"}
}