{
  "type": "Feature",
  "properties": {
    "iso:country":"ES",
    "sg:address":"Av Antoni Gaudi, 17",
    "sg:city":"Viladecans",
    "sg:orig_category":"Aparatos De Iluminaci\u00d3n (al Por Menor)",
    "sg:phone":"+34 936 37 78 01",
    "sg:postcode":"08840",
    "sg:province":"Barcelona",
    "wof:name":"Navarro-rubio Tot Service S.l",
    "wof:placetype":"venue"
},
  "geometry": {"coordinates":[2.0043261051,41.319732666],"type":"Point"}
}