{
  "type": "Feature",
  "properties": {
    "iso:country":"ES",
    "sg:address":"Calle de Brujula, 6",
    "sg:city":"Torrejon Ardoz",
    "sg:orig_category":"Fabricaci\u00d3n De Moldes Y Modelos",
    "sg:phone":"+34 916 75 51 95",
    "sg:postcode":"28850",
    "sg:province":"Madrid",
    "wof:name":"Casas Garcia Miguel",
    "wof:placetype":"venue"
},
  "geometry": {"coordinates":[-3.4598479271,40.4493484497],"type":"Point"}
}