{
  "type": "Feature",
  "properties": {
    "iso:country":"ES",
    "sg:address":"Calle de Sevilla, 2",
    "sg:city":"Montijo",
    "sg:orig_category":"Tapicer\u00cdas",
    "sg:phone":"+34 924 45 07 82",
    "sg:postcode":"06480",
    "sg:province":"Badajoz",
    "wof:name":"Sanz Sanchez Gregorio",
    "wof:placetype":"venue"
},
  "geometry": {"coordinates":[-6.6180148125,38.90366745],"type":"Point"}
}