{
  "type": "Feature",
  "properties": {
    "addr:full":"Calle de Puentes, 1 Navalcan Toledo 45610",
    "addr:housenumber":"1",
    "addr:postcode":"45610",
    "addr:street":"Calle De Puentes",
    "iso:country":"ES",
    "sg:address":"Calle de Puentes, 1",
    "sg:city":"Navalcan",
    "sg:orig_category":"Sociedades, Compa\u00d1\u00cdas Aseguradoras",
    "sg:phone":"+34 925 84 45 54",
    "sg:postcode":"45610",
    "sg:province":"Toledo",
    "wof:name":"Lopez Sanchez Navalcan S.l.",
    "wof:placetype":"venue"
},
  "geometry": {"coordinates":[-5.0909872055,40.0682945251],"type":"Point"}
}