{
  "type": "Feature",
  "properties": {
    "addr:full":"Av Onze De Setembre, 85 Sant Joan De Palamos Girona 17230",
    "addr:housenumber":"85",
    "addr:postcode":"17230",
    "addr:street":"Av Onze De Setembre",
    "iso:country":"ES",
    "sg:address":"Av Onze De Setembre, 85",
    "sg:city":"Sant Joan De Palamos",
    "sg:orig_category":"Ropa Para Se\u00d1oras (al Por Menor)",
    "sg:phone":"+34 972 31 71 91",
    "sg:postcode":"17230",
    "sg:province":"Girona",
    "wof:name":"Balasch Fabra Luisa",
    "wof:placetype":"venue"
},
  "geometry": {"coordinates":[3.1282804012,41.8478736877],"type":"Point"}
}