{
  "type": "Feature",
  "properties": {
    "addr:full":"Calle de Fuerteventura, 3 Fraile Santa Cruz De Tenerife 38640",
    "addr:housenumber":"3",
    "addr:postcode":"38640",
    "addr:street":"Calle De Fuerteventura",
    "iso:country":"ES",
    "sg:address":"Calle de Fuerteventura, 3",
    "sg:city":"Fraile",
    "sg:orig_category":"Administradores De Bienes Y Delegados De Comunidades De Propietarios",
    "sg:phone":"+34 922 78 39 52",
    "sg:postcode":"38640",
    "sg:province":"Santa Cruz De Tenerife",
    "wof:name":"Comunidad De Propietarios Aloe I",
    "wof:placetype":"venue"
},
  "geometry": {"coordinates":[-16.682012558,28.0987625122],"type":"Point"}
}