{
  "type": "Feature",
  "properties": {
    "iso:country":"ES",
    "sg:address":"Rua Celso Emilio Ferreiro, 32",
    "sg:city":"Pontes Garcia Rodriguez",
    "sg:orig_category":"Molduras, Junquillos, Listones Y Molduras Perforadas",
    "sg:phone":"+34 981 45 20 36",
    "sg:postcode":"15320",
    "sg:province":"A Coru\u00f1a",
    "wof:name":"Tojeiro Lopez Elena",
    "wof:placetype":"venue"
},
  "geometry": {"coordinates":[-7.8433189392,43.451210022],"type":"Point"}
}