{
  "type": "Feature",
  "properties": {
    "iso:country":"ES",
    "sg:address":"Calle de Diego Betancor Suarez, S/n",
    "sg:city":"Palmas De Gran Canaria",
    "sg:orig_category":"Pescader\u00cdas (al Por Menor)",
    "sg:phone":"+34 928 41 20 75",
    "sg:postcode":"35012",
    "sg:province":"Las Palmas",
    "wof:name":"Rodriguez Garcia Juana Rosa",
    "wof:placetype":"venue"
},
  "geometry": {"coordinates":[-15.4449567795,28.1116523743],"type":"Point"}
}