{
  "type": "Feature",
  "properties": {
    "addr:full":"Rua Nosa Sra. Da Sainza, 19 Ourense Ourense 32005",
    "addr:housenumber":"19",
    "addr:postcode":"32005",
    "addr:street":"Rua Nosa Sra. Da Sainza",
    "iso:country":"ES",
    "sg:address":"Rua Nosa Sra. Da Sainza, 19",
    "sg:city":"Ourense",
    "sg:orig_category":"Art\u00cdculos Funerarios (al Por Menor)",
    "sg:phone":"+34 988 23 83 37",
    "sg:postcode":"32005",
    "sg:province":"Ourense",
    "wof:name":"Funeraria Santa Eulalia S.l",
    "wof:placetype":"venue"
},
  "geometry": {"coordinates":[-7.8622188568,42.3270111084],"type":"Point"}
}