{
  "type": "Feature",
  "properties": {
    "iso:country":"ES",
    "sg:address":"Send Los Canonigos, 3",
    "sg:city":"Vitoria-gasteiz",
    "sg:orig_category":"Molduras, Junquillos, Listones Y Molduras Perforadas",
    "sg:phone":"+34 945 25 06 74",
    "sg:postcode":"01002",
    "sg:province":"\u00c1lava",
    "wof:name":"Casado Serrano Vicente",
    "wof:placetype":"venue"
},
  "geometry": {"coordinates":[-2.6676280499,42.8535919189],"type":"Point"}
}