{
  "type": "Feature",
  "properties": {
    "iso:country":"ES",
    "sg:address":"Calle de Santa Rita, S/n",
    "sg:city":"Arriondas",
    "sg:orig_category":"Mec\u00c1nico Del Autom\u00d3vil",
    "sg:phone":"+34 985 84 00 00",
    "sg:postcode":"33540",
    "sg:province":"Asturias",
    "wof:name":"Pombal Soto Joaquin Amalio",
    "wof:placetype":"venue"
},
  "geometry": {"coordinates":[-5.1812591553,43.3778991699],"type":"Point"}
}