{
  "type": "Feature",
  "properties": {
    "addr:full":"Part. B. Alta, S/n Las Bayas Alicante 03292",
    "addr:housenumber":"s / n",
    "addr:postcode":"03292",
    "iso:country":"ES",
    "sg:address":"Part. B. Alta, S/n",
    "sg:city":"Las Bayas",
    "sg:orig_category":"Producci\u00d3n De Abonos Y De Fertilizantes",
    "sg:phone":"+34 966 63 73 96",
    "sg:postcode":"03292",
    "sg:province":"Alicante",
    "wof:name":"Cooperativa Del Campo De Las Bayas Coop.v.",
    "wof:placetype":"venue"
},
  "geometry": {"coordinates":[-0.6437839866,38.2202682495],"type":"Point"}
}