{
  "type": "Feature",
  "properties": {
    "addr:full":"Calle de Rosa, 6 Palazuelo Badajoz 06717",
    "addr:housenumber":"6",
    "addr:postcode":"06717",
    "addr:street":"Calle De Rosa",
    "iso:country":"ES",
    "sg:address":"Calle de Rosa, 6",
    "sg:city":"Palazuelo",
    "sg:orig_category":"Bancos",
    "sg:phone":"+34 924 85 70 59",
    "sg:postcode":"06717",
    "sg:province":"Badajoz",
    "wof:name":"Banco Espa\u00f1ol De Credito S.a.",
    "wof:placetype":"venue"
},
  "geometry": {"coordinates":[-5.7395768166,39.1106834412],"type":"Point"}
}