{
  "type": "Feature",
  "properties": {
    "addr:full":"Calle de Botello, 2 Matanza De Acentejo Santa Cruz De Tenerife 38370",
    "addr:housenumber":"2",
    "addr:postcode":"38370",
    "addr:street":"Calle De Botello",
    "iso:country":"ES",
    "sg:address":"Calle de Botello, 2",
    "sg:city":"Matanza De Acentejo",
    "sg:orig_category":"\u00c1rboles Frutales",
    "sg:phone":"+34 922 57 76 36",
    "sg:postcode":"38370",
    "sg:province":"Santa Cruz De Tenerife",
    "wof:name":"Chavez San Diego S.l.",
    "wof:placetype":"venue"
},
  "geometry": {"coordinates":[-16.4562664032,28.4524841309],"type":"Point"}
}