{
  "type": "Feature",
  "properties": {
    "iso:country":"ES",
    "sg:address":"Carrer de Riu Ter, 16",
    "sg:city":"Gava",
    "sg:orig_category":"Empresas De Carpinter\u00cda De Madera",
    "sg:phone":"+34 936 62 43 50",
    "sg:postcode":"08850",
    "sg:province":"Barcelona",
    "wof:name":"Marin Marin Antonio",
    "wof:placetype":"venue"
},
  "geometry": {"coordinates":[1.9891890287,41.3127288818],"type":"Point"}
}