{
  "type": "Feature",
  "properties": {
    "addr:full":"Calle de Fray Luis De Leon, 8 Madrid Madrid 28012",
    "addr:housenumber":"8",
    "addr:postcode":"madrid;28012",
    "addr:street":"Calle De Fray Luis De Leon",
    "iso:country":"ES",
    "sg:address":"Calle de Fray Luis De Leon, 8",
    "sg:city":"Madrid",
    "sg:orig_category":"Inform\u00c1tica, Ofim\u00c1tica (estudios, Asesor\u00cda, Ingenier\u00cda, Formaci\u00d3n)",
    "sg:phone":"+34 914 68 55 28",
    "sg:postcode":"28012",
    "sg:province":"Madrid",
    "sg:website":"www.softworld.es",
    "wof:name":"Softworld S.l.",
    "wof:placetype":"venue"
},
  "geometry": {"coordinates":[-3.6987001896,40.4047317505],"type":"Point"}
}