{
  "type": "Feature",
  "properties": {
    "addr:full":"Avda Mahia, 21 Bertamirans La Coru\u00f1a 15220",
    "addr:housenumber":"21",
    "addr:postcode":"15220",
    "addr:street":"Avda Mahia;La Corun\u0303A",
    "iso:country":"ES",
    "sg:address":"Avda Mahia, 21",
    "sg:city":"Bertamirans",
    "sg:orig_category":"Caf\u00c9s, Bares, Cervecer\u00cdas",
    "sg:phone":"+34 981 89 12 11",
    "sg:postcode":"15220",
    "sg:province":"La Coru\u00f1a",
    "wof:name":"Hosteleria Antena S.l.",
    "wof:placetype":"venue"
},
  "geometry": {"coordinates":[-8.657781601,42.8576889038],"type":"Point"}
}