{
  "type": "Feature",
  "properties": {
    "addr:full":"Calle de Duero, 10 Aranda Duero Burgos 09400",
    "addr:housenumber":"10",
    "addr:postcode":"09400",
    "addr:street":"Calle De Duero",
    "iso:country":"ES",
    "sg:address":"Calle de Duero, 10",
    "sg:city":"Aranda Duero",
    "sg:orig_category":"Asilos De Ancianos. Centros Privados",
    "sg:phone":"+34 947 50 85 00",
    "sg:postcode":"09400",
    "sg:province":"Burgos",
    "wof:name":"Club De Jubilados Y Pensionistas Poligono Residencial",
    "wof:placetype":"venue"
},
  "geometry": {"coordinates":[-3.6934285164,41.6587409973],"type":"Point"}
}