{
  "type": "Feature",
  "properties": {
    "addr:full":"Calle de San Roque, 27 Tomares Sevilla 41940",
    "addr:housenumber":"27",
    "addr:postcode":"41940",
    "addr:street":"Calle De San Roque",
    "iso:country":"ES",
    "sg:address":"Calle de San Roque, 27",
    "sg:city":"Tomares",
    "sg:orig_category":"Fabricaci\u00d3n, Venta De Cuadros, Accesorios Para Enmarcar",
    "sg:phone":"+34 954 15 47 30",
    "sg:postcode":"41940",
    "sg:province":"Sevilla",
    "wof:name":"Garrido Gonzalez Rosario",
    "wof:placetype":"venue"
},
  "geometry": {"coordinates":[-6.0286049843,37.3762741089],"type":"Point"}
}