{
  "type": "Feature",
  "properties": {
    "addr:full":"Calle de Constitucion (de La), 101 Alcobendas Madrid 28100",
    "addr:housenumber":"101",
    "addr:postcode":"28100",
    "addr:street":"Calle De Constitucion De La",
    "iso:country":"ES",
    "sg:address":"Calle de Constitucion (de La), 101",
    "sg:city":"Alcobendas",
    "sg:orig_category":"Ropa Para Se\u00d1oras (al Por Menor)",
    "sg:phone":"+34 916 52 74 68",
    "sg:postcode":"28100",
    "sg:province":"Madrid",
    "wof:name":"Pati\u00f1o Villacorta Maria De Los Reyes Adoracion",
    "wof:placetype":"venue"
},
  "geometry": {"coordinates":[-3.6426670551,40.5454902649],"type":"Point"}
}