{
  "type": "Feature",
  "properties": {
    "addr:full":"Carr Prat De La Riba, 5 Almacelles Lleida 25100",
    "addr:housenumber":"5",
    "addr:postcode":"25100",
    "addr:street":"Carr Prat De La Riba",
    "iso:country":"ES",
    "sg:address":"Carr Prat De La Riba, 5",
    "sg:city":"Almacelles",
    "sg:orig_category":"Zapatos (al Por Menor)",
    "sg:phone":"+34 973 74 05 01",
    "sg:postcode":"25100",
    "sg:province":"Lleida",
    "wof:name":"Roca Domingo Asuncion",
    "wof:placetype":"venue"
},
  "geometry": {"coordinates":[0.4386540055,41.7311172485],"type":"Point"}
}