{
  "type": "Feature",
  "properties": {
    "iso:country":"ES",
    "sg:address":"Carr Cid, El, 3",
    "sg:city":"Eliana",
    "sg:orig_category":"Arquitectos",
    "sg:phone":"+34 961 65 57 66",
    "sg:postcode":"46183",
    "sg:province":"Valencia",
    "wof:name":"I\u00f1urria Montero Victor",
    "wof:placetype":"venue"
},
  "geometry": {"coordinates":[-0.528208971,39.5667457581],"type":"Point"}
}