{
  "type": "Feature",
  "properties": {
    "iso:country":"ES",
    "sg:address":"Carrer de Soledat, 7",
    "sg:city":"Vic",
    "sg:orig_category":"Cerrajer\u00cda, Ferrallista",
    "sg:phone":"+34 938 89 52 83",
    "sg:postcode":"08500",
    "sg:province":"Barcelona",
    "wof:name":"Nuevo Garcia Lucio",
    "wof:placetype":"venue"
},
  "geometry": {"coordinates":[2.2558529377,41.9271621704],"type":"Point"}
}