{
  "type": "Feature",
  "properties": {
    "addr:full":"Ctra Albaida, 36 Agullent Valencia 46890",
    "addr:housenumber":"36",
    "addr:postcode":"46890",
    "addr:street":"Ctra Albaida",
    "iso:country":"ES",
    "sg:address":"Ctra Albaida, 36",
    "sg:city":"Agullent",
    "sg:orig_category":"Fabricaci\u00d3n De Su\u00c9ters Y Chalecos De Punto",
    "sg:phone":"+34 962 90 70 49",
    "sg:postcode":"46890",
    "sg:province":"Valencia",
    "wof:name":"Sanchis Pla Salvador",
    "wof:placetype":"venue"
},
  "geometry": {"coordinates":[-0.545050025,38.8259735107],"type":"Point"}
}