{
  "type": "Feature",
  "properties": {
    "iso:country":"ES",
    "sg:address":"Avda Vino (del), 78",
    "sg:city":"Valdepe\u00f1as",
    "sg:orig_category":"Muebles Y Accesorios Para Cocinas Y Cuartos De Ba\u00d1o (al Por Menor)",
    "sg:phone":"+34 926 32 54 78",
    "sg:postcode":"13300",
    "sg:province":"Ciudad Real",
    "wof:name":"Cocinas Valdepe\u00f1as S.l.",
    "wof:placetype":"venue"
},
  "geometry": {"coordinates":[-3.3884789944,38.7696609497],"type":"Point"}
}