{
  "type": "Feature",
  "properties": {
    "iso:country":"ES",
    "sg:address":"Carrer de Plana, 20",
    "sg:city":"Barcelona",
    "sg:orig_category":"Artes Gr\u00c1ficas, Artes Pl\u00c1sticas (curso)",
    "sg:phone":"+34 933 57 36 30",
    "sg:postcode":"08032",
    "sg:province":"Barcelona",
    "wof:name":"Mozo Diaz Agustin",
    "wof:placetype":"venue"
},
  "geometry": {"coordinates":[2.1579809189,41.4305419922],"type":"Point"}
}