{
  "type": "Feature",
  "properties": {
    "iso:country":"ES",
    "sg:address":"Calle de San Jose, 2",
    "sg:city":"Linea De La Concepcion",
    "sg:orig_category":"Ense\u00d1anza: Comercio, Gesti\u00d3n, Inform\u00c1tica",
    "sg:phone":"+34 956 17 48 66",
    "sg:postcode":"11300",
    "sg:province":"C\u00e1diz",
    "sg:website":"www.iapweb.com",
    "wof:name":"Instituto De Actividades Profesionales S.l.",
    "wof:placetype":"venue"
},
  "geometry": {"coordinates":[-5.347424984,36.1615753174],"type":"Point"}
}