{
  "type": "Feature",
  "properties": {
    "addr:full":"Rua Sol, 45 Ferrol A Coru\u00f1a 15402",
    "addr:housenumber":"45",
    "addr:postcode":"15402",
    "addr:street":"Rua Sol;A Corun\u0303A",
    "iso:country":"ES",
    "sg:address":"Rua Sol, 45",
    "sg:city":"Ferrol",
    "sg:orig_category":"Supermercados Y Hipermercados",
    "sg:phone":"+34 981 35 31 44",
    "sg:postcode":"15402",
    "sg:province":"A Coru\u00f1a",
    "wof:name":"Vego Supermercados S.a.",
    "wof:placetype":"venue"
},
  "geometry": {"coordinates":[-8.2326526642,43.4853744507],"type":"Point"}
}