{
  "type": "Feature",
  "properties": {
    "iso:country":"ES",
    "sg:address":"Carrer de Sant Joan De Malta, 53",
    "sg:city":"Barcelona",
    "sg:orig_category":"Alimentaci\u00d3n General (al Por Menor)",
    "sg:phone":"+34 933 08 83 50",
    "sg:postcode":"08018",
    "sg:province":"Barcelona",
    "wof:name":"Llobet Macian Isabel",
    "wof:placetype":"venue"
},
  "geometry": {"coordinates":[2.1928780079,41.4087409973],"type":"Point"}
}