{
  "type": "Feature",
  "properties": {
    "addr:full":"Ctra Sierra (de La), 47 Granada Granada 18008",
    "addr:housenumber":"47",
    "addr:postcode":"18008",
    "addr:street":"Ctra Sierra De La",
    "iso:country":"ES",
    "sg:address":"Ctra Sierra (de La), 47",
    "sg:city":"Granada",
    "sg:orig_category":"Centros Empresariales",
    "sg:phone":"+34 958 22 47 96",
    "sg:postcode":"18008",
    "sg:province":"Granada",
    "wof:name":"Benages Garcia Josefina",
    "wof:placetype":"venue"
},
  "geometry": {"coordinates":[-3.5840039253,37.1663017273],"type":"Point"}
}