{
  "type": "Feature",
  "properties": {
    "addr:full":"Trva Encomienda, 1 Madrid Madrid 28012",
    "addr:housenumber":"1",
    "addr:postcode":"28012",
    "addr:street":"Trva Encomienda",
    "iso:country":"ES",
    "sg:address":"Trva Encomienda, 1",
    "sg:city":"Madrid",
    "sg:orig_category":"Bisuter\u00cda, Joyer\u00cda, Relojer\u00cda (al Por Menor)",
    "sg:phone":"+34 915 30 74 35",
    "sg:postcode":"28012",
    "sg:province":"Madrid",
    "wof:name":"Scasso  Gustavo Diego",
    "wof:placetype":"venue"
},
  "geometry": {"coordinates":[-3.7054269314,40.4111862183],"type":"Point"}
}