{
  "type": "Feature",
  "properties": {
    "iso:country":"ES",
    "sg:address":"Calle de San Bernardino, 14",
    "sg:city":"Madrid",
    "sg:orig_category":"Inmobiliaria (agencias)",
    "sg:phone":"+34 915 42 43 38",
    "sg:postcode":"28015",
    "sg:province":"Madrid",
    "wof:name":"Almagro 19 S.a.",
    "wof:placetype":"venue"
},
  "geometry": {"coordinates":[-3.7109062672,40.4254112244],"type":"Point"}
}