{
  "type": "Feature",
  "properties": {
    "iso:country":"ES",
    "sg:address":"Rambla Arbolitos, S/n",
    "sg:city":"Fabara",
    "sg:orig_category":"Cooperativas Agr\u00cdcolas",
    "sg:phone":"+34 976 63 52 42",
    "sg:postcode":"50793",
    "sg:province":"Zaragoza",
    "wof:name":"Cooperativa Del Campo San Isidro",
    "wof:placetype":"venue"
},
  "geometry": {"coordinates":[0.1700250059,41.1741981506],"type":"Point"}
}