{
  "type": "Feature",
  "properties": {
    "iso:country":"ES",
    "sg:address":"Carrer de Oliveres, 5",
    "sg:city":"Balsareny",
    "sg:orig_category":"Construcciones Met\u00c1licas",
    "sg:phone":"+34 938 20 03 30",
    "sg:postcode":"08660",
    "sg:province":"Barcelona",
    "wof:name":"Estructuras Naterma S.l.",
    "wof:placetype":"venue"
},
  "geometry": {"coordinates":[1.8747199774,41.8599090576],"type":"Point"}
}