{
  "type": "Feature",
  "properties": {
    "addr:full":"Calle de Gabriel Aresti, 17 Lamiako Vizcaya 48940",
    "addr:housenumber":"17",
    "addr:postcode":"48940",
    "addr:street":"Calle De Gabriel Aresti",
    "iso:country":"ES",
    "sg:address":"Calle de Gabriel Aresti, 17",
    "sg:city":"Lamiako",
    "sg:orig_category":"Transporte En General",
    "sg:phone":"+34 944 80 20 91",
    "sg:postcode":"48940",
    "sg:province":"Vizcaya",
    "wof:name":"Bell House S.l.",
    "wof:placetype":"venue"
},
  "geometry": {"coordinates":[-2.9860789776,43.3275489807],"type":"Point"}
}