{
  "type": "Feature",
  "properties": {
    "iso:country":"ES",
    "sg:address":"Calle de Sotera De La Mier, 8",
    "sg:city":"Sestao",
    "sg:orig_category":"Empresas De Carpinter\u00cda",
    "sg:phone":"+34 944 95 32 99",
    "sg:postcode":"48910",
    "sg:province":"Vizcaya",
    "wof:name":"Metalisteria Alpa S.l.",
    "wof:placetype":"venue"
},
  "geometry": {"coordinates":[-3.0070209503,43.3124008179],"type":"Point"}
}