{
  "type": "Feature",
  "properties": {
    "addr:full":"Calle de Ecuador, 7 Guadalajara Guadalajara 19005",
    "addr:housenumber":"7",
    "addr:postcode":"19005",
    "addr:street":"Calle De Ecuador",
    "iso:country":"ES",
    "sg:address":"Calle de Ecuador, 7",
    "sg:city":"Guadalajara",
    "sg:orig_category":"Animales (al Por Menor)",
    "sg:phone":"+34 949 21 51 40",
    "sg:postcode":"19005",
    "sg:province":"Guadalajara",
    "wof:name":"Marquez Garcia Javier",
    "wof:placetype":"venue"
},
  "geometry": {"coordinates":[-3.1528894901,40.6322097778],"type":"Point"}
}