{
  "type": "Feature",
  "properties": {
    "addr:full":"Ctra Berga, 37 Navas Barcelona 08670",
    "addr:housenumber":"37",
    "addr:postcode":"08670",
    "addr:street":"Ctra Berga",
    "iso:country":"ES",
    "sg:address":"Ctra Berga, 37",
    "sg:city":"Navas",
    "sg:orig_category":"Electrodom\u00c9sticos (al Por Menor)",
    "sg:phone":"+34 938 39 08 21",
    "sg:postcode":"08670",
    "sg:province":"Barcelona",
    "wof:name":"Majoral Roca Ramon",
    "wof:placetype":"venue"
},
  "geometry": {"coordinates":[1.8781139851,41.8988571167],"type":"Point"}
}