{
  "type": "Feature",
  "properties": {
    "addr:full":"Calle de Serrano, 61 Madrid Madrid 28006",
    "addr:housenumber":"61",
    "addr:postcode":"madrid;28006",
    "addr:street":"Calle De Serrano",
    "iso:country":"ES",
    "sg:address":"Calle de Serrano, 61",
    "sg:city":"Madrid",
    "sg:orig_category":"Perfumer\u00cda (al Por Menor)",
    "sg:phone":"+34 915 77 31 98",
    "sg:postcode":"28006",
    "sg:province":"Madrid",
    "sg:website":"www.juteco.es",
    "wof:name":"Ablange S.a.",
    "wof:placetype":"venue"
},
  "geometry": {"coordinates":[-3.686804,40.432194],"type":"Point"}
}