{
  "type": "Feature",
  "properties": {
    "addr:full":"Carrer de Malats, 19 Barcelona Barcelona 08030",
    "addr:housenumber":"19",
    "addr:postcode":"08030",
    "addr:street":"Carrer De Malats",
    "iso:country":"ES",
    "sg:address":"Carrer de Malats, 19",
    "sg:city":"Barcelona",
    "sg:orig_category":"Peluquer\u00cdas, Peluquer\u00cda Mixta",
    "sg:phone":"+34 933 11 91 63",
    "sg:postcode":"08030",
    "sg:province":"Barcelona",
    "wof:name":"Garcia Novales Lorenzo",
    "wof:placetype":"venue"
},
  "geometry": {"coordinates":[2.1893439293,41.4359436035],"type":"Point"}
}