{
  "type": "Feature",
  "properties": {
    "iso:country":"ES",
    "sg:address":"Calle de San Fermin, 34",
    "sg:city":"Torrent",
    "sg:orig_category":"Ropa Para Beb\u00c9s Y Ni\u00d1os (confecci\u00d3n, Al Por Mayor)",
    "sg:phone":"+34 961 58 05 98",
    "sg:postcode":"46900",
    "sg:province":"Valencia",
    "wof:name":"Gadea Marti Adelina",
    "wof:placetype":"venue"
},
  "geometry": {"coordinates":[-0.4726350009,39.4345169067],"type":"Point"}
}