{
  "type": "Feature",
  "properties": {
    "iso:country":"ES",
    "sg:address":"Calle de Obispo Antonio Tavira, 1",
    "sg:city":"Cabo Blanco",
    "sg:orig_category":"Pescader\u00cdas (al Por Menor)",
    "sg:phone":"+34 922 72 10 43",
    "sg:postcode":"38626",
    "sg:province":"Santa Cruz De Tenerife",
    "wof:name":"Garcia Martin Enrique",
    "wof:placetype":"venue"
},
  "geometry": {"coordinates":[-16.671749115,28.0739097595],"type":"Point"}
}