{
  "type": "Feature",
  "properties": {
    "iso:country":"ES",
    "sg:address":"Avda Austria, 15",
    "sg:city":"San Eugenio Alto",
    "sg:orig_category":"Bazares, Art\u00cdculos De Limpieza Y De Cocina (al Por Menor)",
    "sg:phone":"+34 922 71 69 67",
    "sg:postcode":"38660",
    "sg:province":"Santa Cruz De Tenerife",
    "wof:name":"Spanish Style S.l.",
    "wof:placetype":"venue"
},
  "geometry": {"coordinates":[-16.7356548309,28.0891857147],"type":"Point"}
}