{
  "type": "Feature",
  "properties": {
    "iso:country":"ES",
    "sg:address":"Pg Sant Antoni, 6",
    "sg:city":"Mora D'ebre",
    "sg:orig_category":"Peluquer\u00cdas, Peluquer\u00cda Mixta",
    "sg:phone":"+34 977 40 29 41",
    "sg:postcode":"43740",
    "sg:province":"Tarragona",
    "wof:name":"Poyo Martinez Miriam",
    "wof:placetype":"venue"
},
  "geometry": {"coordinates":[1.2600929737,41.118598938],"type":"Point"}
}