{
  "type": "Feature",
  "properties": {
    "iso:country":"ES",
    "sg:address":"Calle de Poeta Salvador Rueda, 1",
    "sg:city":"Fuengirola",
    "sg:orig_category":"Peluquer\u00cdas, Peluquer\u00cda Mixta",
    "sg:phone":"+34 952 46 42 71",
    "sg:postcode":"29640",
    "sg:province":"M\u00e1laga",
    "wof:name":"Navarro Benitez Maria Jesus",
    "wof:placetype":"venue"
},
  "geometry": {"coordinates":[-4.6155438423,36.5503540039],"type":"Point"}
}