{
  "type": "Feature",
  "properties": {
    "addr:full":"Av Francesc Macia, 113 Vilanova I La Geltru Barcelona 08800",
    "addr:housenumber":"113",
    "addr:postcode":"08800",
    "addr:street":"Av Francesc Macia",
    "iso:country":"ES",
    "sg:address":"Av Francesc Macia, 113",
    "sg:city":"Vilanova I La Geltru",
    "sg:orig_category":"Inmobiliaria (agencias)",
    "sg:phone":"+34 938 15 94 81",
    "sg:postcode":"08800",
    "sg:province":"Barcelona",
    "sg:website":"www.remax.es",
    "wof:name":"Tello Y Valero S.l.",
    "wof:placetype":"venue"
},
  "geometry": {"coordinates":[1.7182240486,41.2215919495],"type":"Point"}
}