{
  "type": "Feature",
  "properties": {
    "addr:full":"Ptda Caparrella, 9 Butsenit Lleida 25192",
    "addr:housenumber":"9",
    "addr:postcode":"25192",
    "addr:street":"Ptda Caparrella",
    "iso:country":"ES",
    "sg:address":"Ptda Caparrella, 9",
    "sg:city":"Butsenit",
    "sg:orig_category":"Cr\u00cda De Animales",
    "sg:phone":"+34 973 26 80 39",
    "sg:postcode":"25192",
    "sg:province":"Lleida",
    "wof:name":"Agropecuaria Caparrella S.a.",
    "wof:placetype":"venue"
},
  "geometry": {"coordinates":[0.993789,41.797916],"type":"Point"}
}