{
  "type": "Feature",
  "properties": {
    "iso:country":"ES",
    "sg:address":"Carrer de Valencia, 503",
    "sg:city":"Barcelona",
    "sg:orig_category":"Distribuci\u00d3n De Petr\u00d3leo Y Derivados",
    "sg:phone":"+34 932 32 67 60",
    "sg:postcode":"08013",
    "sg:province":"Barcelona",
    "wof:name":"Servicio Estacion Barcelona S. A.",
    "wof:placetype":"venue"
},
  "geometry": {"coordinates":[2.1797139645,41.4051971436],"type":"Point"}
}