{
  "type": "Feature",
  "properties": {
    "iso:country":"ES",
    "sg:address":"Calle de Valle De Pinares Llanos, 80",
    "sg:city":"Madrid",
    "sg:orig_category":"Doctores En Medicina",
    "sg:phone":"+34 917 39 83 10",
    "sg:postcode":"28035",
    "sg:province":"Madrid",
    "wof:name":"Pastor Valero Julia",
    "wof:placetype":"venue"
},
  "geometry": {"coordinates":[-3.7269260883,40.4857063293],"type":"Point"}
}