{
  "type": "Feature",
  "properties": {
    "iso:country":"ES",
    "sg:address":"Avda Trece De Octubre, S/n",
    "sg:city":"Alcazares",
    "sg:orig_category":"Material Y Herramientas Agr\u00cdcolas",
    "sg:phone":"+34 968 57 55 02",
    "sg:postcode":"30710",
    "sg:province":"Murcia",
    "wof:name":"Marin Garcia Felix",
    "wof:placetype":"venue"
},
  "geometry": {"coordinates":[-0.8516889811,37.7383766174],"type":"Point"}
}