{
  "type": "Feature",
  "properties": {
    "iso:country":"ES",
    "sg:address":"C/ Pou Florit, 74",
    "sg:city":"Porreres",
    "sg:orig_category":"Mec\u00c1nico Del Autom\u00d3vil",
    "sg:phone":"+34 971 64 75 53",
    "sg:postcode":"07260",
    "sg:province":"Islas Baleares",
    "wof:name":"Cabezuelo Martinez Valeriano",
    "wof:placetype":"venue"
},
  "geometry": {"coordinates":[3.0248980522,39.5146751404],"type":"Point"}
}