{
  "type": "Feature",
  "properties": {
    "addr:full":"Pla\u00c7 Espanya, 35 Inca Islas Baleares 07300",
    "addr:housenumber":"35",
    "addr:postcode":"07300",
    "iso:country":"ES",
    "sg:address":"Pla\u00c7 Espanya, 35",
    "sg:city":"Inca",
    "sg:classifiers":[
        {
            "category":"Arts & Performance",
            "subcategory":"Art Gallery",
            "type":"Entertainment"
        }
    ],
    "sg:phone":"+34 971 50 00 86",
    "sg:postcode":"07300",
    "sg:province":"Islas Baleares",
    "sg:tags":[
        "arte",
        "de",
        "galer\u00cdas"
    ],
    "wof:name":"Cajanert Galeria D'art S.l",
    "wof:placetype":"venue"
},
  "geometry": {"coordinates":[2.9208989143,39.7179527283],"type":"Point"}
}