{
  "type": "Feature",
  "properties": {
    "iso:country":"ES",
    "sg:address":"Avda Mozarabes (de Los), 3",
    "sg:city":"Cordoba",
    "sg:orig_category":"Muebles Y Accesorios Para Cocinas Y Cuartos De Ba\u00d1o (al Por Menor)",
    "sg:phone":"+34 957 23 16 49",
    "sg:postcode":"14011",
    "sg:province":"C\u00f3rdoba",
    "wof:name":"Romero Gomez Maria Del Pilar",
    "wof:placetype":"venue"
},
  "geometry": {"coordinates":[-4.7863850594,37.887096405],"type":"Point"}
}