{
  "type": "Feature",
  "properties": {
    "addr:full":"Calle de Getaria, 12 Donostia-san Sebastian Guip\u00f9zcoa 20005",
    "addr:housenumber":"12",
    "addr:postcode":"20005",
    "addr:street":"Calle De Getaria",
    "iso:country":"ES",
    "sg:address":"Calle de Getaria, 12",
    "sg:city":"Donostia-san Sebastian",
    "sg:orig_category":"Bancos",
    "sg:phone":"+34 943 44 06 62",
    "sg:postcode":"20005",
    "sg:province":"Guip\u00f9zcoa",
    "wof:name":"R Cable Y Telecomunicaciones Galicia S.a.",
    "wof:placetype":"venue"
},
  "geometry": {"coordinates":[-1.9808419943,43.3181762695],"type":"Point"}
}