{
  "type": "Feature",
  "properties": {
    "addr:full":"Urb Lomas De Las Joyas, 3 Estepona M\u00e1laga 29680",
    "addr:housenumber":"3",
    "addr:postcode":"29680",
    "addr:street":"Urb Lomas De Las Joyas",
    "iso:country":"ES",
    "sg:address":"Urb Lomas De Las Joyas, 3",
    "sg:city":"Estepona",
    "sg:orig_category":"Trabajos De Topograf\u00cda",
    "sg:phone":"+34 952 80 74 14",
    "sg:postcode":"29680",
    "sg:province":"M\u00e1laga",
    "wof:name":"Top Costa Del Sol S.l.",
    "wof:placetype":"venue"
},
  "geometry": {"coordinates":[-5.0784478188,36.4641304016],"type":"Point"}
}