{
  "type": "Feature",
  "properties": {
    "addr:full":"Calle de Chinchilla, 10 Belmonte Cuenca 16640",
    "addr:housenumber":"10",
    "addr:postcode":"16640",
    "addr:street":"Calle De Chinchilla",
    "iso:country":"ES",
    "sg:address":"Calle de Chinchilla, 10",
    "sg:city":"Belmonte",
    "sg:orig_category":"Empresas De Carpinter\u00cda De Madera",
    "sg:phone":"+34 967 17 03 34",
    "sg:postcode":"16640",
    "sg:province":"Cuenca",
    "wof:name":"Alcazar Sanchez Julian",
    "wof:placetype":"venue"
},
  "geometry": {"coordinates":[-2.7019693851,39.5571365356],"type":"Point"}
}