{
  "type": "Feature",
  "properties": {
    "addr:full":"Plaz Segundo Pastor, 2 Cuenca Cuenca 16004",
    "addr:housenumber":"2",
    "addr:postcode":"16004",
    "addr:street":"Plaz Segundo Pastor",
    "iso:country":"ES",
    "sg:address":"Plaz Segundo Pastor, 2",
    "sg:city":"Cuenca",
    "sg:orig_category":"Perfumer\u00cda (al Por Menor)",
    "sg:phone":"+34 969 23 27 68",
    "sg:postcode":"16004",
    "sg:province":"Cuenca",
    "wof:name":"Droguerias Y Perfumerias Pepe S.l.",
    "wof:placetype":"venue"
},
  "geometry": {"coordinates":[-2.1318309307,40.061290741],"type":"Point"}
}