{
  "type": "Feature",
  "properties": {
    "iso:country":"ES",
    "sg:address":"Avda Don Cristobal Cantero, 3",
    "sg:city":"Ubeda",
    "sg:orig_category":"Muebles, Minoristas",
    "sg:phone":"+34 953 79 06 08",
    "sg:postcode":"23400",
    "sg:province":"Ja\u00e9n",
    "wof:name":"Peralta Gonzalez Maria Jesus",
    "wof:placetype":"venue"
},
  "geometry": {"coordinates":[-3.3716080189,38.0190086365],"type":"Point"}
}