{
  "type": "Feature",
  "properties": {
    "addr:full":"Carr Betera, 35 Burjassot Valencia 46100",
    "addr:housenumber":"35",
    "addr:postcode":"46100",
    "addr:street":"Carr Betera",
    "iso:country":"ES",
    "sg:address":"Carr Betera, 35",
    "sg:city":"Burjassot",
    "sg:orig_category":"Administradores De Bienes Y Delegados De Comunidades De Propietarios",
    "sg:phone":"+34 963 63 62 10",
    "sg:postcode":"46100",
    "sg:province":"Valencia",
    "wof:name":"Cdad Prop Cl Betera 35 Burjassot",
    "wof:placetype":"venue"
},
  "geometry": {"coordinates":[-0.4133619964,39.5168037415],"type":"Point"}
}