{
  "type": "Feature",
  "properties": {
    "addr:full":"Pl. Neda, 1 Algeciras C\u00e1diz 11201",
    "addr:housenumber":"1;ca\u0301diz",
    "addr:postcode":"11201",
    "addr:street":"Neda",
    "iso:country":"ES",
    "sg:address":"Pl. Neda, 1",
    "sg:city":"Algeciras",
    "sg:orig_category":"M\u00c9dicos: Estomatolog\u00cda",
    "sg:phone":"+34 956 66 76 16",
    "sg:postcode":"11201",
    "sg:province":"C\u00e1diz",
    "wof:name":"Jaraba Vazquez Maria Emilia",
    "wof:placetype":"venue"
},
  "geometry": {"coordinates":[-5.4397826195,36.135761261],"type":"Point"}
}