{
  "type": "Feature",
  "properties": {
    "addr:full":"Calle de Fuente, 2 Vallelado Segovia 40213",
    "addr:housenumber":"2",
    "addr:postcode":"40213",
    "addr:street":"Calle De Fuente;Segovia",
    "iso:country":"ES",
    "sg:address":"Calle de Fuente, 2",
    "sg:city":"Vallelado",
    "sg:orig_category":"Bancos",
    "sg:phone":"+34 921 15 03 28",
    "sg:postcode":"40213",
    "sg:province":"Segovia",
    "wof:name":"Gomez Llorente Francisco Javier",
    "wof:placetype":"venue"
},
  "geometry": {"coordinates":[-4.4265475273,41.4053344727],"type":"Point"}
}