{
  "type": "Feature",
  "properties": {
    "iso:country":"ES",
    "sg:address":"Ctra Navas-pbla Infantes, Km. 0005,0",
    "sg:city":"Navas De La Concepcion",
    "sg:orig_category":"Charcuter\u00cdas (al Por Mayor)",
    "sg:phone":"+34 955 95 40 51",
    "sg:postcode":"41460",
    "sg:province":"Sevilla",
    "wof:name":"Agricola Moreno Velez S.l",
    "wof:placetype":"venue"
},
  "geometry": {"coordinates":[-5.4672961235,37.9469680786],"type":"Point"}
}