{
  "type": "Feature",
  "properties": {
    "addr:full":"Mercado Municipal, S/n Carballo A Coru\u00f1a 15100",
    "addr:housenumber":"s / n",
    "addr:postcode":"15100",
    "addr:street":"Corun\u0303A",
    "iso:country":"ES",
    "sg:address":"Mercado Municipal, S/n",
    "sg:city":"Carballo",
    "sg:orig_category":"Fabricaci\u00d3n De Quesos",
    "sg:phone":"+34 981 75 65 57",
    "sg:postcode":"15100",
    "sg:province":"A Coru\u00f1a",
    "wof:name":"Vazquez Souto Consuelo",
    "wof:placetype":"venue"
},
  "geometry": {"coordinates":[-8.6913089752,43.2121582031],"type":"Point"}
}