{
  "type": "Feature",
  "properties": {
    "addr:full":"Poli Las Capellanias, 2 Caceres C\u00e1ceres 10005",
    "addr:housenumber":"2",
    "addr:postcode":"10005",
    "addr:street":"Capellanias;Ca\u0301Ceres",
    "iso:country":"ES",
    "sg:address":"Poli Las Capellanias, 2",
    "sg:city":"Caceres",
    "sg:orig_category":"Cerrajer\u00cda, Ferrallista",
    "sg:phone":"+34 927 23 45 04",
    "sg:postcode":"10005",
    "sg:province":"C\u00e1ceres",
    "wof:name":"Luce\u00f1o Barrantes Pedro Jose",
    "wof:placetype":"venue"
},
  "geometry": {"coordinates":[-6.5341739655,39.4675254822],"type":"Point"}
}