{
  "type": "Feature",
  "properties": {
    "addr:full":"Avda Boliches De Los, 57 Fuengirola M\u00e1laga 29640",
    "addr:postcode":"29640",
    "addr:street":"Avda Boliches De Los;Ma\u0301Laga",
    "iso:country":"ES",
    "sg:address":"Avda Boliches De Los, 57",
    "sg:city":"Fuengirola",
    "sg:orig_category":"Servicios De Telecomunicaciones",
    "sg:phone":"+34 952 58 13 09",
    "sg:postcode":"29640",
    "sg:province":"M\u00e1laga",
    "wof:name":"Engatel Comunicaciones S.l.",
    "wof:placetype":"venue"
},
  "geometry": {"coordinates":[-4.6149492264,36.5528640747],"type":"Point"}
}