{
  "type": "Feature",
  "properties": {
    "addr:full":"Avda Juan Carlos I, 63 Ibi Alicante 03440",
    "addr:housenumber":"63",
    "addr:postcode":"03440",
    "addr:street":"Avda Juan Carlos I",
    "iso:country":"ES",
    "sg:address":"Avda Juan Carlos I, 63",
    "sg:city":"Ibi",
    "sg:orig_category":"Grafistas",
    "sg:phone":"+34 965 55 35 51",
    "sg:postcode":"03440",
    "sg:province":"Alicante",
    "sg:website":"www.escaparatedigital.com",
    "wof:name":"Area Oberta S.l.",
    "wof:placetype":"venue"
},
  "geometry": {"coordinates":[-0.5788909793,38.6205329895],"type":"Point"}
}