{
  "type": "Feature",
  "properties": {
    "iso:country":"ES",
    "sg:address":"Calle de Nuestra Se\u00d1ora De La Luz, 10",
    "sg:city":"Madrid",
    "sg:orig_category":"Loter\u00cda Y T\u00d3mbola",
    "sg:phone":"+34 914 65 90 51",
    "sg:postcode":"28025",
    "sg:province":"Madrid",
    "wof:name":"Garcia Bonacho Maria Del Carmen",
    "wof:placetype":"venue"
},
  "geometry": {"coordinates":[-3.7427179813,40.3830680847],"type":"Point"}
}