{
  "type": "Feature",
  "properties": {
    "addr:full":"Carrer de Xucla, 6 Barcelona Barcelona 08001",
    "addr:housenumber":"6",
    "addr:postcode":"08001",
    "addr:street":"Carrer De Xucla",
    "iso:country":"ES",
    "sg:address":"Carrer de Xucla, 6",
    "sg:city":"Barcelona",
    "sg:orig_category":"Fabricaci\u00d3n, Distribuci\u00d3n De Discos, V\u00cddeodiscos Y Musicassettes",
    "sg:phone":"+34 934 12 60 22",
    "sg:postcode":"08001",
    "sg:province":"Barcelona",
    "wof:name":"Ruana De La Haba Montserrat",
    "wof:placetype":"venue"
},
  "geometry": {"coordinates":[2.1707060337,41.3832206726],"type":"Point"}
}