{
  "type": "Feature",
  "properties": {
    "addr:full":"Calle de Sebastian Elcano, 30 Madrid Madrid 28012",
    "addr:housenumber":"30",
    "addr:postcode":"madrid;28012",
    "addr:street":"Calle De Sebastian Elcano",
    "iso:country":"ES",
    "sg:address":"Calle de Sebastian Elcano, 30",
    "sg:city":"Madrid",
    "sg:orig_category":"Inmobiliaria (agencias)",
    "sg:phone":"+34 915 06 05 82",
    "sg:postcode":"28012",
    "sg:province":"Madrid",
    "wof:name":"Eralan S.a.",
    "wof:placetype":"venue"
},
  "geometry": {"coordinates":[-3.6976919174,40.4048843384],"type":"Point"}
}