{
  "type": "Feature",
  "properties": {
    "iso:country":"ES",
    "sg:address":"Calle de Bazigorta, 13",
    "sg:city":"San Vicente De Barakaldo",
    "sg:orig_category":"Ferreter\u00cda (diversos)",
    "sg:phone":"+34 944 82 03 91",
    "sg:postcode":"48903",
    "sg:province":"Vizcaya",
    "wof:name":"Barreiro Munin Jose",
    "wof:placetype":"venue"
},
  "geometry": {"coordinates":[-2.9775500298,43.2900352478],"type":"Point"}
}