{
  "type": "Feature",
  "properties": {
    "addr:full":"Plaz San Juan, 2 Teruel Teruel 44001",
    "addr:housenumber":"2",
    "addr:postcode":"44001",
    "addr:street":"Plaz San Juan",
    "iso:country":"ES",
    "sg:address":"Plaz San Juan, 2",
    "sg:city":"Teruel",
    "sg:orig_category":"Asociaciones, Organismos Culturales Y Socioeducativos",
    "sg:phone":"+34 978 60 11 82",
    "sg:postcode":"44001",
    "sg:province":"Teruel",
    "wof:name":"Circulo De Recreo Turolense",
    "wof:placetype":"venue"
},
  "geometry": {"coordinates":[-1.1063289642,40.3410377502],"type":"Point"}
}