{
  "type": "Feature",
  "properties": {
    "addr:full":"Via Sant Oleguer, 55 Romanica Barcelona 08210",
    "addr:housenumber":"55",
    "addr:postcode":"08210",
    "addr:street":"Via Sant Oleguer",
    "iso:country":"ES",
    "sg:address":"Via Sant Oleguer, 55",
    "sg:city":"Romanica",
    "sg:orig_category":"Molduras, Junquillos, Listones Y Molduras Perforadas",
    "sg:phone":"+34 937 29 14 66",
    "sg:postcode":"08210",
    "sg:province":"Barcelona",
    "wof:name":"Zu\u00f1iga Polaino Ramon",
    "wof:placetype":"venue"
},
  "geometry": {"coordinates":[2.1252968311,41.5258102417],"type":"Point"}
}