{
  "type": "Feature",
  "properties": {
    "iso:country":"ES",
    "sg:address":"Avda Lugo De, 8",
    "sg:city":"Aviles",
    "sg:orig_category":"Chapister\u00cda",
    "sg:phone":"+34 985 52 71 87",
    "sg:postcode":"33401",
    "sg:province":"Asturias",
    "wof:name":"Gutierrez Sedano Julio",
    "wof:placetype":"venue"
},
  "geometry": {"coordinates":[-5.9258360863,43.5649642944],"type":"Point"}
}