{
  "type": "Feature",
  "properties": {
    "addr:full":"Calle de Jesusa Lara, 29 Estacion Madrid 28250",
    "addr:housenumber":"29",
    "addr:postcode":"28250",
    "addr:street":"Calle De Jesusa Lara",
    "iso:country":"ES",
    "sg:address":"Calle de Jesusa Lara, 29",
    "sg:city":"Estacion",
    "sg:classifiers":[
        {
            "category":"Professional",
            "subcategory":"Research",
            "type":"Services"
        }
    ],
    "sg:phone":"+34 918 59 48 86",
    "sg:postcode":"28250",
    "sg:province":"Madrid",
    "sg:tags":[
        "mercado",
        "de",
        "estudios"
    ],
    "sg:website":"www.canadean.es",
    "wof:name":"Canadean Ltd.sucursal En Espa\u00f1a",
    "wof:placetype":"venue"
},
  "geometry": {"coordinates":[-3.9535450935,40.5787162781],"type":"Point"}
}