{
  "type": "Feature",
  "properties": {
    "iso:country":"ES",
    "sg:address":"Calle de Andalucia, 48",
    "sg:city":"Arroyo De La Miel-benalmadena Costa",
    "sg:orig_category":"Psic\u00d3logos",
    "sg:phone":"+34 952 57 80 96",
    "sg:postcode":"29631",
    "sg:province":"M\u00e1laga",
    "wof:name":"Llama Violeta S.c.",
    "wof:placetype":"venue"
},
  "geometry": {"coordinates":[-4.5318899155,36.5983848572],"type":"Point"}
}