{
  "type": "Feature",
  "properties": {
    "iso:country":"ES",
    "sg:address":"Plaz Espa\u00d1a, 5",
    "sg:city":"Catral",
    "sg:orig_category":"Florister\u00cdas",
    "sg:phone":"+34 966 78 72 58",
    "sg:postcode":"03158",
    "sg:province":"Alicante",
    "wof:name":"Pons Gimenez Jose Ramon",
    "wof:placetype":"venue"
},
  "geometry": {"coordinates":[-0.8041089773,38.1594619751],"type":"Point"}
}