{
  "type": "Feature",
  "properties": {
    "addr:full":"Plaz Cedro Del, S/n Donostia-san Sebastian Guip\u00f9zcoa 20016",
    "addr:housenumber":"/ n",
    "addr:postcode":"20016",
    "addr:street":"S",
    "iso:country":"ES",
    "sg:address":"Plaz Cedro Del, S/n",
    "sg:city":"Donostia-san Sebastian",
    "sg:orig_category":"Electricidad: Instaladores",
    "sg:phone":"+34 943 39 39 86",
    "sg:postcode":"20016",
    "sg:province":"Guip\u00f9zcoa",
    "wof:name":"Larrechau Marchain Francisco Javier",
    "wof:placetype":"venue"
},
  "geometry": {"coordinates":[-1.942620039,43.3229598999],"type":"Point"}
}