{
  "type": "Feature",
  "properties": {
    "iso:country":"ES",
    "sg:address":"Calle de Cobos, 6",
    "sg:city":"Cadiz",
    "sg:orig_category":"Papeler\u00cdas, Librer\u00cdas",
    "sg:phone":"+34 956 28 98 13",
    "sg:postcode":"11005",
    "sg:province":"C\u00e1diz",
    "wof:name":"Vera Barrios Luis",
    "wof:placetype":"venue"
},
  "geometry": {"coordinates":[-6.2942042351,36.530292511],"type":"Point"}
}