{
  "type": "Feature",
  "properties": {
    "addr:full":"Calle de Asturias, 15 Granada Granada 18007",
    "addr:housenumber":"15",
    "addr:postcode":"18007",
    "addr:street":"Calle De Asturias",
    "iso:country":"ES",
    "sg:address":"Calle de Asturias, 15",
    "sg:city":"Granada",
    "sg:orig_category":"Cerrajer\u00cda, Ferrallista",
    "sg:phone":"+34 958 81 25 62",
    "sg:postcode":"18007",
    "sg:province":"Granada",
    "wof:name":"Fernandez Martinez Manuel",
    "wof:placetype":"venue"
},
  "geometry": {"coordinates":[-3.5984294415,37.1556663513],"type":"Point"}
}