{
  "type": "Feature",
  "properties": {
    "addr:full":"Rua Diego Pazos, 24 Sarria Lugo 27600",
    "addr:housenumber":"24",
    "addr:postcode":"27600",
    "addr:street":"Rua Diego Pazos",
    "iso:country":"ES",
    "sg:address":"Rua Diego Pazos, 24",
    "sg:city":"Sarria",
    "sg:orig_category":"Droguer\u00cdas (al Por Menor)",
    "sg:phone":"+34 982 53 10 89",
    "sg:postcode":"27600",
    "sg:province":"Lugo",
    "wof:name":"Diaz Lopez Jesus",
    "wof:placetype":"venue"
},
  "geometry": {"coordinates":[-7.4082069397,42.7822647095],"type":"Point"}
}