{
  "type": "Feature",
  "properties": {
    "addr:full":"Calle de Madre Soledad Torres Acosta, 6 Jaen Ja\u00e9n 23001",
    "addr:housenumber":"6;jae\u0301n",
    "addr:postcode":"23001",
    "addr:street":"Calle De Madre Soledad Torres Acosta",
    "iso:country":"ES",
    "sg:address":"Calle de Madre Soledad Torres Acosta, 6",
    "sg:city":"Jaen",
    "sg:orig_category":"Ropa Para Ni\u00d1os (al Por Menor)",
    "sg:phone":"+34 953 26 67 15",
    "sg:postcode":"23001",
    "sg:province":"Ja\u00e9n",
    "wof:name":"Stradivarius Espa\u00f1a S.a.",
    "wof:placetype":"venue"
},
  "geometry": {"coordinates":[-3.7886269093,37.7692184448],"type":"Point"}
}