{
  "type": "Feature",
  "properties": {
    "iso:country":"ES",
    "sg:address":"Plaz Espa\u00d1a, 3",
    "sg:city":"Jodar",
    "sg:orig_category":"Aceites Y Grasas Alimentarias (fabricaci\u00d3n, Al Por Mayor)",
    "sg:phone":"+34 953 78 50 53",
    "sg:postcode":"23500",
    "sg:province":"Ja\u00e9n",
    "wof:name":"Carrasco Alados Manuela",
    "wof:placetype":"venue"
},
  "geometry": {"coordinates":[-3.3521280289,37.8442077637],"type":"Point"}
}