{
  "type": "Feature",
  "properties": {
    "iso:country":"ES",
    "sg:address":"Calle de Delgado, 185",
    "sg:city":"Galdar",
    "sg:orig_category":"Fabrica, Negocio De Vidrieras, Productos Vidriados Y Espejos",
    "sg:phone":"+34 928 55 25 14",
    "sg:postcode":"35460",
    "sg:province":"Las Palmas",
    "wof:name":"Cristaleria Diaz Molina S.l.",
    "wof:placetype":"venue"
},
  "geometry": {"coordinates":[-15.641119957,28.1455802917],"type":"Point"}
}