{
  "type": "Feature",
  "properties": {
    "addr:full":"Rua Huertas (de Las), 48 Monforte De Lemos Lugo 27400",
    "addr:housenumber":"48",
    "addr:postcode":"27400",
    "addr:street":"Rua Huertas De Las",
    "iso:country":"ES",
    "sg:address":"Rua Huertas (de Las), 48",
    "sg:city":"Monforte De Lemos",
    "sg:orig_category":"Arquitectos",
    "sg:phone":"+34 982 40 38 98",
    "sg:postcode":"27400",
    "sg:province":"Lugo",
    "wof:name":"Lopez Quiroga Ignacio De Loyola",
    "wof:placetype":"venue"
},
  "geometry": {"coordinates":[-7.5142941475,42.5226707458],"type":"Point"}
}