{
  "type": "Feature",
  "properties": {
    "iso:country":"ES",
    "sg:address":"Avda Villafranca, 18",
    "sg:city":"Bembibre",
    "sg:orig_category":"Peluqueros: De Se\u00d1oras",
    "sg:phone":"+34 987 51 06 24",
    "sg:postcode":"24300",
    "sg:province":"Le\u00f3n",
    "wof:name":"Conesa Ramos Jose",
    "wof:placetype":"venue"
},
  "geometry": {"coordinates":[-6.4174609184,42.6158065796],"type":"Point"}
}