{
  "type": "Feature",
  "properties": {
    "iso:country":"ES",
    "sg:address":"Calle de Muralla La, 13",
    "sg:city":"Gijon",
    "sg:orig_category":"Institutos De Belleza",
    "sg:phone":"+34 985 35 94 48",
    "sg:postcode":"33202",
    "sg:province":"Asturias",
    "wof:name":"Centro Estetica Integrada S.l.",
    "wof:placetype":"venue"
},
  "geometry": {"coordinates":[-5.6584191322,43.5401611328],"type":"Point"}
}