{
  "type": "Feature",
  "properties": {
    "iso:country":"ES",
    "sg:address":"Avda Deportista Miriam Blasco, 9",
    "sg:city":"Alacant",
    "sg:orig_category":"Asociaciones Humanitarias, De Cooperaci\u00d3n, De Acci\u00d3n Social",
    "sg:phone":"+34 965 26 79 99",
    "sg:postcode":"03016",
    "sg:province":"Alicante",
    "wof:name":"Asociacion Familiares Y Amigos Enfermos Alzheimer De Alicante",
    "wof:placetype":"venue"
},
  "geometry": {"coordinates":[-0.4345285892,38.3671455383],"type":"Point"}
}