{
  "type": "Feature",
  "properties": {
    "iso:country":"ES",
    "sg:address":"Carr Ca N'illes, 19",
    "sg:city":"Blanes",
    "sg:orig_category":"Agencias De Viajes",
    "sg:phone":"+34 972 33 71 21",
    "sg:postcode":"17300",
    "sg:province":"Girona",
    "sg:website":"www.viajeswanda.com",
    "wof:name":"Viajes Wanda S.l.",
    "wof:placetype":"venue"
},
  "geometry": {"coordinates":[2.7938420773,41.6870117188],"type":"Point"}
}