{
  "type": "Feature",
  "properties": {
    "addr:full":"Avda Reyes Catolicos, 1 Melilla Melilla 52002",
    "addr:housenumber":"1",
    "addr:postcode":"52002",
    "addr:street":"Avda Reyes Catolicos",
    "iso:country":"ES",
    "sg:address":"Avda Reyes Catolicos, 1",
    "sg:city":"Melilla",
    "sg:orig_category":"Lencer\u00cda Femenina, Corseter\u00cda, Trajes De Ba\u00d1o (al Por Menor)",
    "sg:phone":"+34 952 67 78 48",
    "sg:postcode":"52002",
    "sg:province":"Melilla",
    "wof:name":"Martin Pueyo Maria Del Pilar",
    "wof:placetype":"venue"
},
  "geometry": {"coordinates":[-2.9423589706,35.2947158813],"type":"Point"}
}