{
  "type": "Feature",
  "properties": {
    "addr:full":"Praz Maior, 6 Xinzo De Limia Ourense 32630",
    "addr:housenumber":"6",
    "addr:postcode":"32630",
    "addr:street":"Praz Maior",
    "iso:country":"ES",
    "sg:address":"Praz Maior, 6",
    "sg:city":"Xinzo De Limia",
    "sg:orig_category":"Caf\u00c9s, Bares, Cervecer\u00cdas",
    "sg:phone":"+34 988 46 00 58",
    "sg:postcode":"32630",
    "sg:province":"Ourense",
    "wof:name":"Galtelcom",
    "wof:placetype":"venue"
},
  "geometry": {"coordinates":[-7.7261462212,42.0628967285],"type":"Point"}
}