{
  "type": "Feature",
  "properties": {
    "addr:full":"Avda Castilla, 3 Cangas Onis Asturias 33550",
    "addr:housenumber":"3",
    "addr:postcode":"33550",
    "addr:street":"Avda Castilla;Onis Asturias",
    "iso:country":"ES",
    "sg:address":"Avda Castilla, 3",
    "sg:city":"Cangas Onis",
    "sg:orig_category":"Carnicer\u00cdas, Carnicer\u00cdas",
    "sg:phone":"+34 985 84 87 41",
    "sg:postcode":"33550",
    "sg:province":"Asturias",
    "wof:name":"Niembro Moran Jose Luis",
    "wof:placetype":"venue"
},
  "geometry": {"coordinates":[-5.1305217743,43.3498268127],"type":"Point"}
}