{
  "type": "Feature",
  "properties": {
    "iso:country":"ES",
    "sg:address":"Calle de Ocho De Marzo, 1",
    "sg:city":"Sevilla",
    "sg:orig_category":"Molduras, Junquillos, Listones Y Molduras Perforadas",
    "sg:phone":"+34 954 63 49 36",
    "sg:postcode":"41006",
    "sg:province":"Sevilla",
    "wof:name":"Casanova Lopez Maria Angeles",
    "wof:placetype":"venue"
},
  "geometry": {"coordinates":[-5.9536290169,37.3680915833],"type":"Point"}
}