{
  "type": "Feature",
  "properties": {
    "iso:country":"ES",
    "sg:address":"Avda Fuenlabrada (de), 88",
    "sg:city":"Humanes De Madrid",
    "sg:orig_category":"Artesan\u00cda",
    "sg:phone":"+34 916 04 85 12",
    "sg:postcode":"28970",
    "sg:province":"Madrid",
    "wof:name":"China Arte S.a.",
    "wof:placetype":"venue"
},
  "geometry": {"coordinates":[-3.8133730888,40.2665786743],"type":"Point"}
}