{
  "type": "Feature",
  "properties": {
    "iso:country":"ES",
    "sg:address":"Plaz Encuentro, 4",
    "sg:city":"Madrid",
    "sg:orig_category":"Ense\u00d1anza Secundaria: Colegios Y Escuelas Privadas",
    "sg:phone":"+34 914 39 35 70",
    "sg:postcode":"28030",
    "sg:province":"Madrid",
    "wof:name":"Ies Carlos Maria Rodriguez De Valcarcel",
    "wof:placetype":"venue"
},
  "geometry": {"coordinates":[-3.6517748833,40.4055099487],"type":"Point"}
}