{
  "type": "Feature",
  "properties": {
    "addr:full":"Avda Zaragoza, 50 Utebo Zaragoza 50180",
    "addr:housenumber":"50",
    "addr:postcode":"50180",
    "addr:street":"Avda Zaragoza",
    "iso:country":"ES",
    "sg:address":"Avda Zaragoza, 50",
    "sg:city":"Utebo",
    "sg:orig_category":"Inform\u00c1tica, Ofim\u00c1tica (estudios, Asesor\u00cda, Ingenier\u00cda, Formaci\u00d3n)",
    "sg:phone":"+34 976 77 18 02",
    "sg:postcode":"50180",
    "sg:province":"Zaragoza",
    "wof:name":"Esquirolea Gimenez Raul",
    "wof:placetype":"venue"
},
  "geometry": {"coordinates":[-0.9984400272,41.7065620422],"type":"Point"}
}