{
  "type": "Feature",
  "properties": {
    "iso:country":"ES",
    "sg:address":"Carr Corregidor Escofet, 34",
    "sg:city":"Lleida",
    "sg:orig_category":"Alquiler De V\u00cddeo",
    "sg:phone":"+34 973 24 62 05",
    "sg:postcode":"25005",
    "sg:province":"Lleida",
    "wof:name":"Valls Homobono Pedro",
    "wof:placetype":"venue"
},
  "geometry": {"coordinates":[0.6364129782,41.6244812012],"type":"Point"}
}