{
  "type": "Feature",
  "properties": {
    "iso:country":"ES",
    "sg:address":"Calle de Perpetuo Socorro (del), 32",
    "sg:city":"San Sebastian De Los Reyes",
    "sg:orig_category":"Molduras, Junquillos, Listones Y Molduras Perforadas",
    "sg:phone":"+34 916 53 11 21",
    "sg:postcode":"28700",
    "sg:province":"Madrid",
    "wof:name":"Hernando Gonzalo Araceli",
    "wof:placetype":"venue"
},
  "geometry": {"coordinates":[-3.6305789948,40.5457115173],"type":"Point"}
}