{
  "type": "Feature",
  "properties": {
    "addr:full":"Rbla Rambla Nova, 117 Tarragona Tarragona 43001",
    "addr:housenumber":"117",
    "addr:postcode":"43001",
    "addr:street":"Rambla Nova",
    "iso:country":"ES",
    "sg:address":"Rbla Rambla Nova, 117",
    "sg:city":"Tarragona",
    "sg:orig_category":"Arquitectos",
    "sg:phone":"+34 977 21 74 32",
    "sg:postcode":"43001",
    "sg:province":"Tarragona",
    "wof:name":"Lucena Gomez Antonia Maria",
    "wof:placetype":"venue"
},
  "geometry": {"coordinates":[1.2541049719,41.1169281006],"type":"Point"}
}