{
  "type": "Feature",
  "properties": {
    "addr:full":"Avda Industria (de La), 54 Tres Cantos Madrid 28760",
    "addr:housenumber":"54",
    "addr:postcode":"28760",
    "addr:street":"Avda Industria De La",
    "iso:country":"ES",
    "sg:address":"Avda Industria (de La), 54",
    "sg:city":"Tres Cantos",
    "sg:orig_category":"Electricidad, Electr\u00d3nica: Suministros (al Por Menor)",
    "sg:phone":"+34 918 03 21 43",
    "sg:postcode":"28760",
    "sg:province":"Madrid",
    "sg:website":"www.sistena.com",
    "wof:name":"Sistena S. A.",
    "wof:placetype":"venue"
},
  "geometry": {"coordinates":[-3.7022180557,40.6145591736],"type":"Point"}
}