{
  "type": "Feature",
  "properties": {
    "iso:country":"ES",
    "sg:address":"Calle de Ledesma, 12",
    "sg:city":"Bilbao",
    "sg:orig_category":"Pod\u00d3logos: Pedicuros",
    "sg:phone":"+34 944 05 00 50",
    "sg:postcode":"48001",
    "sg:province":"Vizcaya",
    "wof:name":"Jaime Moral Malagon",
    "wof:placetype":"venue"
},
  "geometry": {"coordinates":[-2.9282889366,43.2622680664],"type":"Point"}
}