{
  "type": "Feature",
  "properties": {
    "iso:country":"ES",
    "sg:address":"San Felix, S/n",
    "sg:city":"San Fiz",
    "sg:orig_category":"Charcuter\u00cdas (al Por Mayor)",
    "sg:phone":"+34 982 16 74 87",
    "sg:postcode":"27627",
    "sg:province":"Lugo",
    "wof:name":"Carniceria Y Embutidos Oribio S. L.",
    "wof:placetype":"venue"
},
  "geometry": {"coordinates":[-7.2979550362,42.7666702271],"type":"Point"}
}