{
  "type": "Feature",
  "properties": {
    "iso:country":"ES",
    "sg:address":"Calle de Salvador Giner, 1",
    "sg:city":"Valencia",
    "sg:orig_category":"Estancos",
    "sg:phone":"+34 963 91 88 43",
    "sg:postcode":"46003",
    "sg:province":"Valencia",
    "wof:name":"Hellin Garcia Fernando",
    "wof:placetype":"venue"
},
  "geometry": {"coordinates":[-0.3801130056,39.4799537659],"type":"Point"}
}