{
  "type": "Feature",
  "properties": {
    "addr:full":"Calle de Santa Cruz, 13 Camas Sevilla 41900",
    "addr:housenumber":"13",
    "addr:postcode":"41900",
    "addr:street":"Calle De Santa Cruz",
    "iso:country":"ES",
    "sg:address":"Calle de Santa Cruz, 13",
    "sg:city":"Camas",
    "sg:orig_category":"Porcelanas, Azulejos (fabricaci\u00d3n, Al Por Mayor)",
    "sg:phone":"+34 955 98 00 29",
    "sg:postcode":"41900",
    "sg:province":"Sevilla",
    "wof:name":"Azulejos Hispalis S.l.",
    "wof:placetype":"venue"
},
  "geometry": {"coordinates":[-6.0367031097,37.418006897],"type":"Point"}
}