{
  "type": "Feature",
  "properties": {
    "iso:country":"ES",
    "sg:address":"Calle de Zazuar, 8",
    "sg:city":"Madrid",
    "sg:orig_category":"Psic\u00d3logos",
    "sg:phone":"+34 913 31 44 44",
    "sg:postcode":"28031",
    "sg:province":"Madrid",
    "wof:name":"Nieto Ramos Juan Carlos",
    "wof:placetype":"venue"
},
  "geometry": {"coordinates":[-3.6084558964,40.3812332153],"type":"Point"}
}