{
  "type": "Feature",
  "properties": {
    "iso:country":"ES",
    "sg:address":"Calle de Lagasca, 69",
    "sg:city":"Madrid",
    "sg:orig_category":"Centros Empresariales",
    "sg:phone":"+34 914 31 22 71",
    "sg:postcode":"28001",
    "sg:province":"Madrid",
    "wof:name":"Zapatos Del Milenio S.l.",
    "wof:placetype":"venue"
},
  "geometry": {"coordinates":[-3.6849319935,40.4293556213],"type":"Point"}
}