{
  "type": "Feature",
  "properties": {
    "addr:full":"Cmno Ballesta (de La), S/n Retamar Almer\u00eda 04130",
    "addr:postcode":"04130",
    "addr:street":"Cmno Ballesta De La S / N Retamar",
    "iso:country":"ES",
    "sg:address":"Cmno Ballesta (de La), S/n",
    "sg:city":"Retamar",
    "sg:orig_category":"Molduras, Junquillos, Listones Y Molduras Perforadas",
    "sg:phone":"+34 950 20 90 14",
    "sg:postcode":"04130",
    "sg:province":"Almer\u00eda",
    "wof:name":"Salda\u00f1a Ubeda Antonio",
    "wof:placetype":"venue"
},
  "geometry": {"coordinates":[-2.3529150486,36.8523406982],"type":"Point"}
}