{
  "type": "Feature",
  "properties": {
    "addr:full":"Calle de Resina, 22 Madrid Madrid 28021",
    "addr:housenumber":"22",
    "addr:postcode":"madrid;28021",
    "addr:street":"Calle De Resina",
    "iso:country":"ES",
    "sg:address":"Calle de Resina, 22",
    "sg:city":"Madrid",
    "sg:orig_category":"Inform\u00c1tica: Mantenimiento Y Reparaci\u00d3n De Ordenadores",
    "sg:phone":"+34 917 98 01 28",
    "sg:postcode":"28021",
    "sg:province":"Madrid",
    "sg:website":"rmsistemas@telecontrol.es",
    "wof:name":"Redy Mantenimiento De Sistemas S.l.",
    "wof:placetype":"venue"
},
  "geometry": {"coordinates":[-3.7018558979,40.3360176086],"type":"Point"}
}