{
  "type": "Feature",
  "properties": {
    "addr:full":"Ctra. N. 340, 3 Huercal-overa Almer\u00eda 04600",
    "addr:housenumber":"340 3",
    "addr:postcode":"04600",
    "addr:street":"Ctra. N.;Huercal-Overa Almeri\u0301A",
    "iso:country":"ES",
    "sg:address":"Ctra. N. 340, 3",
    "sg:city":"Huercal-overa",
    "sg:orig_category":"Cajas Para Embalar",
    "sg:phone":"+34 950 47 17 26",
    "sg:postcode":"04600",
    "sg:province":"Almer\u00eda",
    "wof:name":"Cajamar",
    "wof:placetype":"venue"
},
  "geometry": {"coordinates":[-1.9444589615,37.392288208],"type":"Point"}
}