{
  "type": "Feature",
  "properties": {
    "iso:country":"ES",
    "sg:address":"Ctra. N. 340, 3",
    "sg:city":"Huercal-overa",
    "sg:orig_category":"Cajas Para Embalar",
    "sg:phone":"+34 950 47 17 26",
    "sg:postcode":"04600",
    "sg:province":"Almer\u00eda",
    "wof:name":"Cajamar",
    "wof:placetype":"venue"
},
  "geometry": {"coordinates":[-1.9444589615,37.392288208],"type":"Point"}
}