{
  "type": "Feature",
  "properties": {
    "iso:country":"ES",
    "sg:address":"Calle de General Vara De Rey, 46",
    "sg:city":"Logro\u00f1o",
    "sg:orig_category":"M\u00c9dicos: Estomatolog\u00cda",
    "sg:phone":"+34 941 25 89 46",
    "sg:postcode":"26002",
    "sg:province":"La Rioja",
    "wof:name":"Galarreta Miguel Miguel Manuel",
    "wof:placetype":"venue"
},
  "geometry": {"coordinates":[-2.4461593628,42.4599494934],"type":"Point"}
}