{
  "type": "Feature",
  "properties": {
    "iso:country":"ES",
    "sg:address":"Carrer de Soler I Rovirosa, 5",
    "sg:city":"Barcelona",
    "sg:orig_category":"Costureras",
    "sg:phone":"+34 932 46 69 52",
    "sg:postcode":"08018",
    "sg:province":"Barcelona",
    "wof:name":"Gonzalez Martinez Juan Francisco",
    "wof:placetype":"venue"
},
  "geometry": {"coordinates":[2.1896209717,41.4100875854],"type":"Point"}
}