{
  "type": "Feature",
  "properties": {
    "iso:country":"ES",
    "sg:address":"Plaz Espa\u00d1a, S/n",
    "sg:city":"Campillos",
    "sg:orig_category":"Art\u00cdculos De Regalo (al Por Menor)",
    "sg:phone":"+34 952 72 51 87",
    "sg:postcode":"29320",
    "sg:province":"M\u00e1laga",
    "wof:name":"Sanchez Ortega Cristobal",
    "wof:placetype":"venue"
},
  "geometry": {"coordinates":[-4.8618388176,37.0470275879],"type":"Point"}
}