{
  "type": "Feature",
  "properties": {
    "iso:country":"ES",
    "sg:address":"Carrer de Sant Cristofol, 23",
    "sg:city":"Manresa",
    "sg:orig_category":"Agentes, Concesionarios Y Sucursales De Veh\u00cdculos",
    "sg:phone":"+34 938 78 42 10",
    "sg:postcode":"08243",
    "sg:province":"Barcelona",
    "sg:website":"www.chrysler-red.com",
    "wof:name":"Olrait S.a.",
    "wof:placetype":"venue"
},
  "geometry": {"coordinates":[1.8361510038,41.7297859192],"type":"Point"}
}