{
  "type": "Feature",
  "properties": {
    "iso:country":"ES",
    "sg:address":"Calle de Senador Castillo Olivares, 34",
    "sg:city":"Palmas De Gran Canaria",
    "sg:orig_category":"Peluquer\u00cdas, Peluquer\u00cda Mixta",
    "sg:phone":"+34 928 36 55 72",
    "sg:postcode":"35003",
    "sg:province":"Las Palmas",
    "sg:website":"www.pepelopezpeluqueros.com",
    "wof:name":"Grupo Pepe Lopez Peluqueros S.l.",
    "wof:placetype":"venue"
},
  "geometry": {"coordinates":[-15.4219064713,28.110868454],"type":"Point"}
}