{
  "type": "Feature",
  "properties": {
    "addr:full":"Carrer de Sant Isidre, 2 Viladecans Barcelona 08840",
    "addr:housenumber":"2",
    "addr:postcode":"08840",
    "addr:street":"Carrer De Sant Isidre",
    "iso:country":"ES",
    "sg:address":"Carrer de Sant Isidre, 2",
    "sg:city":"Viladecans",
    "sg:orig_category":"Institutos De Belleza",
    "sg:phone":"+34 936 59 06 47",
    "sg:postcode":"08840",
    "sg:province":"Barcelona",
    "wof:name":"Serrano Ros Inma",
    "wof:placetype":"venue"
},
  "geometry": {"coordinates":[2.0179700851,41.3166809082],"type":"Point"}
}