{
  "type": "Feature",
  "properties": {
    "addr:full":"Agricultura(pol. Bankunion Ii), 12 Gijon Asturias 33211",
    "addr:housenumber":"12",
    "addr:postcode":"33211",
    "iso:country":"ES",
    "sg:address":"Agricultura(pol. Bankunion Ii), 12",
    "sg:city":"Gijon",
    "sg:orig_category":"Agencias Y Agentes Comerciales, Representantes",
    "sg:phone":"+34 985 16 77 37",
    "sg:postcode":"33211",
    "sg:province":"Asturias",
    "wof:name":"Saul Margolles Sanchez Y Varios C.b.",
    "wof:placetype":"venue"
},
  "geometry": {"coordinates":[-5.7144961357,43.5288276672],"type":"Point"}
}