{
  "type": "Feature",
  "properties": {
    "addr:full":"Calle de Jordi De Sant Jordi, 6 Valencia Valencia 46022",
    "addr:housenumber":"6",
    "addr:postcode":"46022",
    "addr:street":"Calle De Jordi De Sant Jordi",
    "iso:country":"ES",
    "sg:address":"Calle de Jordi De Sant Jordi, 6",
    "sg:city":"Valencia",
    "sg:orig_category":"Marroquiner\u00cda (confecci\u00d3n)",
    "sg:phone":"+34 963 56 47 90",
    "sg:postcode":"46022",
    "sg:province":"Valencia",
    "wof:name":"Lopez Sanchez Antonio",
    "wof:placetype":"venue"
},
  "geometry": {"coordinates":[-0.3531298041,39.4981231689],"type":"Point"}
}