{
  "type": "Feature",
  "properties": {
    "iso:country":"ES",
    "sg:address":"Carrer de Pompeu Fabra, 28",
    "sg:city":"S. Quirze Valles",
    "sg:orig_category":"Reposter\u00cdas",
    "sg:phone":"+34 937 21 07 05",
    "sg:postcode":"08192",
    "sg:province":"Barcelona",
    "wof:name":"Fleca I Espigues S.l.",
    "wof:placetype":"venue"
},
  "geometry": {"coordinates":[2.0800950527,41.5328216553],"type":"Point"}
}