{
  "type": "Feature",
  "properties": {
    "addr:full":"Carrer de Mercat, 2 S. Just Desvern Barcelona 08960",
    "addr:housenumber":"2",
    "addr:postcode":"08960",
    "addr:street":"Carrer De Mercat",
    "iso:country":"ES",
    "sg:address":"Carrer de Mercat, 2",
    "sg:city":"S. Just Desvern",
    "sg:orig_category":"Agencias Y Agentes Comerciales, Representantes",
    "sg:phone":"+34 934 73 28 62",
    "sg:postcode":"08960",
    "sg:province":"Barcelona",
    "wof:name":"Suarez Alonso Miguel Aurelio",
    "wof:placetype":"venue"
},
  "geometry": {"coordinates":[2.0777299404,41.3841514587],"type":"Point"}
}