{
  "type": "Feature",
  "properties": {
    "addr:full":"Fondon, 9 Fondon Ourense 32930",
    "addr:housenumber":"9",
    "addr:postcode":"32930",
    "addr:street":"Fondon",
    "iso:country":"ES",
    "sg:address":"Fondon, 9",
    "sg:city":"Fondon",
    "sg:orig_category":"Cerrajer\u00cda, Ferrallista",
    "sg:phone":"+34 988 26 13 50",
    "sg:postcode":"32930",
    "sg:province":"Ourense",
    "wof:name":"Vazquez Silva Jose Antonio",
    "wof:placetype":"venue"
},
  "geometry": {"coordinates":[-7.9522171021,42.3144187927],"type":"Point"}
}