{
  "type": "Feature",
  "properties": {
    "addr:full":"Calle de Doctor Talavera, 7 Salamanca Salamanca 37006",
    "addr:housenumber":"7",
    "addr:postcode":"37006",
    "addr:street":"Calle De Doctor Talavera",
    "iso:country":"ES",
    "sg:address":"Calle de Doctor Talavera, 7",
    "sg:city":"Salamanca",
    "sg:orig_category":"Electricidad: Instaladores",
    "sg:phone":"+34 923 22 08 65",
    "sg:postcode":"37006",
    "sg:province":"Salamanca",
    "wof:name":"Santos Hernaandez Bernabe",
    "wof:placetype":"venue"
},
  "geometry": {"coordinates":[-5.6743922234,40.9767951965],"type":"Point"}
}