{
  "type": "Feature",
  "properties": {
    "addr:full":"Vista Bella, 11 Aizoain Navarra 31195",
    "addr:housenumber":"11",
    "addr:postcode":"31195",
    "addr:street":"Vista Bella",
    "iso:country":"ES",
    "sg:address":"Vista Bella, 11",
    "sg:city":"Aizoain",
    "sg:orig_category":"Empresas De Carpinter\u00cda Met\u00c1lica",
    "sg:phone":"+34 948 30 37 99",
    "sg:postcode":"31195",
    "sg:province":"Navarra",
    "wof:name":"Montajes Y Automatizacion De Puertas S.a.l.",
    "wof:placetype":"venue"
},
  "geometry": {"coordinates":[-1.6867979765,42.8470611572],"type":"Point"}
}