{
  "type": "Feature",
  "properties": {
    "addr:full":"Calle de Francos, 4 Olmedo Valladolid 47410",
    "addr:housenumber":"4",
    "addr:postcode":"47410",
    "addr:street":"Calle De Francos",
    "iso:country":"ES",
    "sg:address":"Calle de Francos, 4",
    "sg:city":"Olmedo",
    "sg:orig_category":"Alimentaci\u00d3n General (al Por Menor)",
    "sg:phone":"+34 983 60 00 62",
    "sg:postcode":"47410",
    "sg:province":"Valladolid",
    "wof:name":"Carretero Lopez Tomas",
    "wof:placetype":"venue"
},
  "geometry": {"coordinates":[-4.6877989769,41.288192749],"type":"Point"}
}