{
  "type": "Feature",
  "properties": {
    "addr:full":"Carr Cardenal Benlloc, 8 Balaguer Lleida 25600",
    "addr:housenumber":"8",
    "addr:postcode":"25600",
    "addr:street":"Carr Cardenal Benlloc",
    "iso:country":"ES",
    "sg:address":"Carr Cardenal Benlloc, 8",
    "sg:city":"Balaguer",
    "sg:orig_category":"Mercer\u00cda, Lencer\u00cda (al Por Menor)",
    "sg:phone":"+34 973 44 51 79",
    "sg:postcode":"25600",
    "sg:province":"Lleida",
    "wof:name":"Camarasa Montardit Josefa",
    "wof:placetype":"venue"
},
  "geometry": {"coordinates":[0.8088529706,41.7919387817],"type":"Point"}
}