{
  "type": "Feature",
  "properties": {
    "iso:country":"ES",
    "sg:address":"Calle de Medina Y Galnares, 62",
    "sg:city":"Sevilla",
    "sg:orig_category":"Electricidad: Equipos Industriales, Componentes (fabricaci\u00d3n)",
    "sg:phone":"+34 954 37 72 91",
    "sg:postcode":"41015",
    "sg:province":"Sevilla",
    "wof:name":"Telvent Outsourcing, S.a.",
    "wof:placetype":"venue"
},
  "geometry": {"coordinates":[-5.981710434,37.4267196655],"type":"Point"}
}