{
  "type": "Feature",
  "properties": {
    "addr:full":"Calle de Virgen De Guadalupe, 2 Salamanca Salamanca 37008",
    "addr:housenumber":"2",
    "addr:postcode":"37008",
    "addr:street":"Calle De Virgen De Guadalupe",
    "iso:country":"ES",
    "sg:address":"Calle de Virgen De Guadalupe, 2",
    "sg:city":"Salamanca",
    "sg:orig_category":"M\u00c9dicos: Estomatolog\u00cda",
    "sg:phone":"+34 923 26 08 08",
    "sg:postcode":"37008",
    "sg:province":"Salamanca",
    "wof:name":"Touris Carrera Gaston",
    "wof:placetype":"venue"
},
  "geometry": {"coordinates":[-5.664457798,40.9502792358],"type":"Point"}
}