{
  "type": "Feature",
  "properties": {
    "addr:full":"Carrer de Arquitecte Vives, 3 Valls Tarragona 43800",
    "addr:housenumber":"3",
    "addr:postcode":"43800",
    "addr:street":"Carrer De Arquitecte Vives",
    "iso:country":"ES",
    "sg:address":"Carrer de Arquitecte Vives, 3",
    "sg:city":"Valls",
    "sg:orig_category":"Frutas, Legumbres Frescas Y Tempranas (al Por Menor)",
    "sg:phone":"+34 977 61 36 81",
    "sg:postcode":"43800",
    "sg:province":"Tarragona",
    "wof:name":"Navarro Sanchez Maria Teresa",
    "wof:placetype":"venue"
},
  "geometry": {"coordinates":[1.258867979,41.2955703735],"type":"Point"}
}