{
  "type": "Feature",
  "properties": {
    "iso:country":"ES",
    "sg:address":"Pl Catalunya, 2",
    "sg:city":"Caldes Montbui",
    "sg:orig_category":"Estancos",
    "sg:phone":"+34 938 65 03 94",
    "sg:postcode":"08140",
    "sg:province":"Barcelona",
    "wof:name":"Navarro Escardivol Jose",
    "wof:placetype":"venue"
},
  "geometry": {"coordinates":[2.1642169952,41.6304626465],"type":"Point"}
}