{
  "type": "Feature",
  "properties": {
    "addr:full":"Calle de Martin Fernandez Villaran, 2 Portugalete Vizcaya 48920",
    "addr:housenumber":"2",
    "addr:postcode":"48920",
    "addr:street":"Calle De Martin;Villaran",
    "iso:country":"ES",
    "sg:address":"Calle de Martin Fernandez Villaran, 2",
    "sg:city":"Portugalete",
    "sg:orig_category":"Empresas De Carpinter\u00cda De Madera",
    "sg:phone":"+34 944 61 12 65",
    "sg:postcode":"48920",
    "sg:province":"Vizcaya",
    "wof:name":"Carrasco Martinez Jose Luis",
    "wof:placetype":"venue"
},
  "geometry": {"coordinates":[-3.0194170475,43.3219604492],"type":"Point"}
}