{
  "type": "Feature",
  "properties": {
    "addr:full":"Carrer de Cristofor Colom, 4 Tarragona Tarragona 43001",
    "addr:housenumber":"4",
    "addr:postcode":"43001",
    "addr:street":"Carrer De Cristofor Colom",
    "iso:country":"ES",
    "sg:address":"Carrer de Cristofor Colom, 4",
    "sg:city":"Tarragona",
    "sg:orig_category":"Asesor\u00cda Sobre Comunicaci\u00d3n De Empresas",
    "sg:phone":"+34 977 24 59 48",
    "sg:postcode":"43001",
    "sg:province":"Tarragona",
    "wof:name":"Asde Assessors 2002 S.l.",
    "wof:placetype":"venue"
},
  "geometry": {"coordinates":[1.2490698099,41.1169815063],"type":"Point"}
}