{
  "type": "Feature",
  "properties": {
    "addr:full":"Avda Pirineos (de Los), 15 Huesca Huesca 22004",
    "addr:housenumber":"15",
    "addr:postcode":"22004",
    "addr:street":"Avda Pirineos De Los",
    "iso:country":"ES",
    "sg:address":"Avda Pirineos (de Los), 15",
    "sg:city":"Huesca",
    "sg:orig_category":"Producci\u00d3n, Comercio De Cereales",
    "sg:phone":"+34 974 24 15 68",
    "sg:postcode":"22004",
    "sg:province":"Huesca",
    "wof:name":"Asin Arbues Jesus",
    "wof:placetype":"venue"
},
  "geometry": {"coordinates":[-0.4176844954,42.1430511475],"type":"Point"}
}