{
  "type": "Feature",
  "properties": {
    "iso:country":"ES",
    "sg:address":"Jose Artetxe Kalea, 10",
    "sg:city":"Azpeitia",
    "sg:orig_category":"Confecci\u00d3n De Trajes Para Se\u00d1oras",
    "sg:phone":"+34 943 81 17 69",
    "sg:postcode":"20730",
    "sg:province":"Guip\u00f9zcoa",
    "wof:name":"Abarisqueta Olaizola Bernarda",
    "wof:placetype":"venue"
},
  "geometry": {"coordinates":[-2.267137,43.181896],"type":"Point"}
}