{
  "type": "Feature",
  "properties": {
    "addr:full":"Calle de Jose Alemany Vich, 6 Palma Islas Baleares 07010",
    "addr:housenumber":"6",
    "addr:postcode":"07010",
    "addr:street":"Calle De Jose Alemany Vich",
    "iso:country":"ES",
    "sg:address":"Calle de Jose Alemany Vich, 6",
    "sg:city":"Palma",
    "sg:orig_category":"Perreras, Pensiones Para Perros, Gatos Y Otros Animales",
    "sg:phone":"+34 971 29 79 14",
    "sg:postcode":"07010",
    "sg:province":"Islas Baleares",
    "wof:name":"Centro Canino Internacional",
    "wof:placetype":"venue"
},
  "geometry": {"coordinates":[2.6448509693,39.5817108154],"type":"Point"}
}