{
  "type": "Feature",
  "properties": {
    "iso:country":"ES",
    "sg:address":"Ctr De Navalpino, 94",
    "sg:city":"Piedrabuena",
    "sg:classifiers":[
        {
            "category":"Taxi",
            "type":"Transportation"
        }
    ],
    "sg:phone":"+34 926 76 02 84",
    "sg:postcode":"13100",
    "sg:province":"Ciudad Real",
    "wof:name":"Guillen Toledo Leopoldo",
    "wof:placetype":"venue"
},
  "geometry": {"coordinates":[-4.1716189384,39.0333557129],"type":"Point"}
}