{
  "type": "Feature",
  "properties": {
    "iso:country":"ES",
    "sg:address":"Calle de Ana Teresa, 24",
    "sg:city":"Madrid",
    "sg:orig_category":"M\u00c9dicos: Oftalmolog\u00cda",
    "sg:phone":"+34 913 57 18 61",
    "sg:postcode":"28023",
    "sg:province":"Madrid",
    "sg:website":"www.incivi.com",
    "wof:name":"Clinica Oftalmologica De Madrid S.l.",
    "wof:placetype":"venue"
},
  "geometry": {"coordinates":[-3.7849872112,40.4622306824],"type":"Point"}
}