{
  "type": "Feature",
  "properties": {
    "addr:full":"Pla\u00c7 Hostals, 24 Santa Maria Del Cami Islas Baleares 07320",
    "addr:housenumber":"24",
    "addr:postcode":"07320",
    "addr:street":"Plac\u0327 Hostals;Islas",
    "iso:country":"ES",
    "sg:address":"Pla\u00c7 Hostals, 24",
    "sg:city":"Santa Maria Del Cami",
    "sg:orig_category":"M\u00c9dicos: Estomatolog\u00cda",
    "sg:phone":"+34 971 14 03 13",
    "sg:postcode":"07320",
    "sg:province":"Islas Baleares",
    "wof:name":"Piccotto Cerban Guillermo",
    "wof:placetype":"venue"
},
  "geometry": {"coordinates":[2.7729899883,39.6510467529],"type":"Point"}
}