{
  "type": "Feature",
  "properties": {
    "addr:full":"Avenida De La Vera, 43 Villanueva Vera C\u00e1ceres 10470",
    "addr:housenumber":"43",
    "addr:postcode":"10470",
    "addr:street":"Avenida De La Vera;Ca\u0301Ceres",
    "iso:country":"ES",
    "sg:address":"Avenida De La Vera, 43",
    "sg:city":"Villanueva Vera",
    "sg:orig_category":"Empresas De Desmonte",
    "sg:phone":"+34 927 56 70 33",
    "sg:postcode":"10470",
    "sg:province":"C\u00e1ceres",
    "wof:name":"Timon Sanchez Manuel",
    "wof:placetype":"venue"
},
  "geometry": {"coordinates":[-5.4627428055,40.1311225891],"type":"Point"}
}