{
  "type": "Feature",
  "properties": {
    "iso:country":"ES",
    "sg:address":"Calle de Quinteras, S/n",
    "sg:city":"San Cristobal De La Laguna",
    "sg:orig_category":"Contables",
    "sg:phone":"+34 922 63 26 05",
    "sg:postcode":"38201",
    "sg:province":"Santa Cruz De Tenerife",
    "wof:name":"Fragoso Moreno Jorge Domingo",
    "wof:placetype":"venue"
},
  "geometry": {"coordinates":[-16.3131217957,28.4861125946],"type":"Point"}
}