{
  "type": "Feature",
  "properties": {
    "iso:country":"ES",
    "sg:address":"Carrer de Sant Miquel, 41",
    "sg:city":"Masnou",
    "sg:orig_category":"\u00d3ptica: Instrumentos (fabricaci\u00d3n)",
    "sg:phone":"+34 935 40 15 96",
    "sg:postcode":"08320",
    "sg:province":"Barcelona",
    "wof:name":"Optica Cavex S.l.",
    "wof:placetype":"venue"
},
  "geometry": {"coordinates":[2.3167350292,41.4807739258],"type":"Point"}
}