{
  "type": "Feature",
  "properties": {
    "iso:country":"ES",
    "sg:address":"Afueras, S/n",
    "sg:city":"Son Moro",
    "sg:orig_category":"Agencias De Viajes",
    "sg:phone":"+34 971 58 78 80",
    "sg:postcode":"07560",
    "sg:province":"Islas Baleares",
    "wof:name":"Viajes Aliaga S.l.",
    "wof:placetype":"venue"
},
  "geometry": {"coordinates":[3.3764801025,39.5764541626],"type":"Point"}
}