{
  "type": "Feature",
  "properties": {
    "iso:country":"ES",
    "sg:address":"Carrer de Franc M Herreros, 9",
    "sg:city":"Palma",
    "sg:orig_category":"Impuestos, Tesoro P\u00dablico",
    "sg:phone":"+34 971 77 11 87",
    "sg:postcode":"07005",
    "sg:province":"Islas Baleares",
    "wof:name":"Gabinete Tecnico Pericial Gual S.l.",
    "wof:placetype":"venue"
},
  "geometry": {"coordinates":[2.6619739532,39.573890686],"type":"Point"}
}