{
  "type": "Feature",
  "properties": {
    "iso:country":"ES",
    "sg:address":"Avda Campones, 58",
    "sg:city":"Gijon",
    "sg:orig_category":"Bebidas",
    "sg:phone":"+34 985 32 50 94",
    "sg:postcode":"33211",
    "sg:province":"Asturias",
    "wof:name":"Comercial Distribuidora De Bebidas S. A.",
    "wof:placetype":"venue"
},
  "geometry": {"coordinates":[-5.6932229996,43.532283783],"type":"Point"}
}