{
  "type": "Feature",
  "properties": {
    "addr:full":"Calle de San Juan, 25 Escucha Teruel 44770",
    "addr:housenumber":"25",
    "addr:postcode":"44770",
    "addr:street":"Calle De San Juan",
    "iso:country":"ES",
    "sg:address":"Calle de San Juan, 25",
    "sg:city":"Escucha",
    "sg:orig_category":"Autob\u00das (explotaci\u00d3n Y Servicios De)",
    "sg:phone":"+34 978 75 79 29",
    "sg:postcode":"44770",
    "sg:province":"Teruel",
    "wof:name":"Calvo Ramos Manuel",
    "wof:placetype":"venue"
},
  "geometry": {"coordinates":[-0.8095160127,40.7949905396],"type":"Point"}
}