{
  "type": "Feature",
  "properties": {
    "addr:full":"Carr Lluis Carreres, 42 Muro Islas Baleares 07440",
    "addr:housenumber":"42",
    "addr:postcode":"07440",
    "addr:street":"Carr Lluis Carreres",
    "iso:country":"ES",
    "sg:address":"Carr Lluis Carreres, 42",
    "sg:city":"Muro",
    "sg:orig_category":"Panader\u00cdas, Panader\u00cdas",
    "sg:phone":"+34 971 53 73 28",
    "sg:postcode":"07440",
    "sg:province":"Islas Baleares",
    "wof:name":"Hermanos Barcelo Riutort S.a.",
    "wof:placetype":"venue"
},
  "geometry": {"coordinates":[3.0544149876,39.7392997742],"type":"Point"}
}