{
  "type": "Feature",
  "properties": {
    "iso:country":"ES",
    "sg:address":"Carrer de Barcelona, Km. 0007,8",
    "sg:city":"Cardedeu",
    "sg:orig_category":"Muebles, Minoristas",
    "sg:phone":"+34 938 46 21 05",
    "sg:postcode":"08440",
    "sg:province":"Barcelona",
    "wof:name":"Mobles Panorama S.a.",
    "wof:placetype":"venue"
},
  "geometry": {"coordinates":[2.3605720997,41.6408805847],"type":"Point"}
}