{
  "type": "Feature",
  "properties": {
    "iso:country":"ES",
    "sg:address":"Cmno Sargaitz, 7",
    "sg:city":"Uharte-arakil",
    "sg:orig_category":"Fabrica De Cer\u00c1micas",
    "sg:phone":"+34 948 56 71 11",
    "sg:postcode":"31840",
    "sg:province":"Navarra",
    "wof:name":"Prefabricados De Hormigon Lurgain S. A.",
    "wof:placetype":"venue"
},
  "geometry": {"coordinates":[-1.9775890112,42.9212760925],"type":"Point"}
}