{
  "type": "Feature",
  "properties": {
    "iso:country":"ES",
    "sg:address":"Calle de Paredillas, 2",
    "sg:city":"Zubia",
    "sg:orig_category":"Alimentaci\u00d3n Animal (fabricaci\u00d3n, Al Por Mayor)",
    "sg:phone":"+34 958 59 03 93",
    "sg:postcode":"18140",
    "sg:province":"Granada",
    "wof:name":"Molina Navarro Iunaitz",
    "wof:placetype":"venue"
},
  "geometry": {"coordinates":[-3.5835158825,37.118560791],"type":"Point"}
}