{
  "type": "Feature",
  "properties": {
    "addr:full":"Calle de Marques De Pidal, 9 Oviedo Asturias 33004",
    "addr:housenumber":"9",
    "addr:postcode":"33004",
    "addr:street":"Calle De Marques De Pidal",
    "iso:country":"ES",
    "sg:address":"Calle de Marques De Pidal, 9",
    "sg:city":"Oviedo",
    "sg:orig_category":"Ropa Para Se\u00d1oras (al Por Menor)",
    "sg:phone":"+34 985 23 61 61",
    "sg:postcode":"33004",
    "sg:province":"Asturias",
    "wof:name":"Asturias Shopping S.l.",
    "wof:placetype":"venue"
},
  "geometry": {"coordinates":[-5.8528056145,43.3637161255],"type":"Point"}
}