{
  "type": "Feature",
  "properties": {
    "iso:country":"ES",
    "sg:address":"Valencia(palanc.), 9",
    "sg:city":"Cuenca",
    "sg:orig_category":"Fabricaci\u00d3n De Ropa De Deportes",
    "sg:phone":"+34 969 22 09 48",
    "sg:postcode":"16004",
    "sg:province":"Cuenca",
    "sg:website":"www.mohorte.com",
    "wof:name":"Confecciones Mohorte S.a.",
    "wof:placetype":"venue"
},
  "geometry": {"coordinates":[-2.1237630844,40.0522689819],"type":"Point"}
}