{
  "type": "Feature",
  "properties": {
    "addr:full":"Calle de Rafael Alberti, 4 Mengibar Ja\u00e9n 23620",
    "addr:housenumber":"4",
    "addr:postcode":"23620",
    "addr:street":"Calle De Rafael Alberti;Jae\u0301N",
    "iso:country":"ES",
    "sg:address":"Calle de Rafael Alberti, 4",
    "sg:city":"Mengibar",
    "sg:orig_category":"Promotores Constructores",
    "sg:phone":"+34 953 37 14 90",
    "sg:postcode":"23620",
    "sg:province":"Ja\u00e9n",
    "wof:name":"Decomenjibar S.l.l",
    "wof:placetype":"venue"
},
  "geometry": {"coordinates":[-3.8022289276,37.9703788757],"type":"Point"}
}