{
  "type": "Feature",
  "properties": {
    "iso:country":"ES",
    "sg:address":"Avda Puente De Carlos Iii, 10",
    "sg:city":"Reinosa",
    "sg:orig_category":"Mercer\u00cda, Lencer\u00cda (al Por Menor)",
    "sg:phone":"+34 942 75 18 42",
    "sg:postcode":"39200",
    "sg:province":"Cantabria",
    "wof:name":"Alonso Gonzalez Isidro",
    "wof:placetype":"venue"
},
  "geometry": {"coordinates":[-4.1384277344,42.9993476868],"type":"Point"}
}