{
  "type": "Feature",
  "properties": {
    "iso:country":"ES",
    "sg:address":"Carrer de Corsega, 45",
    "sg:city":"Barcelona",
    "sg:orig_category":"Peluqueros: De Se\u00d1oras",
    "sg:phone":"+34 934 10 97 17",
    "sg:postcode":"08029",
    "sg:province":"Barcelona",
    "wof:name":"Nu\u00f1ez Martin Maria Dolores",
    "wof:placetype":"venue"
},
  "geometry": {"coordinates":[2.1428120136,41.3842430115],"type":"Point"}
}