{
  "type": "Feature",
  "properties": {
    "iso:country":"ES",
    "sg:address":"Carr Joan Baptista Osca, 5",
    "sg:city":"Alcudia",
    "sg:orig_category":"Laboratorios Farmac\u00c9uticos",
    "sg:phone":"+34 962 54 15 15",
    "sg:postcode":"46250",
    "sg:province":"Valencia",
    "wof:name":"Contel Ballesteros Maria Belen",
    "wof:placetype":"venue"
},
  "geometry": {"coordinates":[-0.5070289969,39.1940689087],"type":"Point"}
}