{
  "type": "Feature",
  "properties": {
    "addr:full":"S. Gines, 10 Llano Beal Murcia 30381",
    "addr:housenumber":"10",
    "addr:postcode":"30381",
    "addr:street":"Gines",
    "iso:country":"ES",
    "sg:address":"S. Gines, 10",
    "sg:city":"Llano Beal",
    "sg:orig_category":"Tintorer\u00cdas, Limpieza En Seco",
    "sg:phone":"+34 968 54 60 18",
    "sg:postcode":"30381",
    "sg:province":"Murcia",
    "wof:name":"Lavanderia Isamari S.l.",
    "wof:placetype":"venue"
},
  "geometry": {"coordinates":[-0.8286089897,37.6291046143],"type":"Point"}
}