{
  "type": "Feature",
  "properties": {
    "iso:country":"ES",
    "sg:address":"Calle de Nuestra Se\u00d1ora Del Pilar, 12",
    "sg:city":"Leganes",
    "sg:orig_category":"Mec\u00c1nico Del Autom\u00d3vil",
    "sg:phone":"+34 916 94 15 08",
    "sg:postcode":"28911",
    "sg:province":"Madrid",
    "wof:name":"Sanchez Lopez Agustin",
    "wof:placetype":"venue"
},
  "geometry": {"coordinates":[-3.7692530155,40.3261184692],"type":"Point"}
}