{
  "type": "Feature",
  "properties": {
    "iso:country":"ES",
    "sg:address":"Poli Industrial Autopista Sur, 19",
    "sg:city":"Castellon De La Plana",
    "sg:orig_category":"Asociaciones Y Clubs Deportivos",
    "sg:phone":"+34 964 34 29 86",
    "sg:postcode":"12006",
    "sg:province":"Castell\u00f3n",
    "wof:name":"Sprinter Megacentro Del Deporte S.l.",
    "wof:placetype":"venue"
},
  "geometry": {"coordinates":[-0.1404139996,40.0213813782],"type":"Point"}
}