{
  "type": "Feature",
  "properties": {
    "addr:full":"Avda Cabo Diego Perez Rodriguez, S/n Barbate C\u00e1diz 11160",
    "addr:housenumber":"/ n",
    "addr:postcode":"11160",
    "addr:street":"Avda Cabo Diego Perez Rodriguez S",
    "iso:country":"ES",
    "sg:address":"Avda Cabo Diego Perez Rodriguez, S/n",
    "sg:city":"Barbate",
    "sg:orig_category":"Electricidad (montaje, Ensamblaje De Componentes)",
    "sg:phone":"+34 956 43 13 28",
    "sg:postcode":"11160",
    "sg:province":"C\u00e1diz",
    "wof:name":"Sanchez Ruiz Manuel",
    "wof:placetype":"venue"
},
  "geometry": {"coordinates":[-5.9146690369,36.1866531372],"type":"Point"}
}