{
  "type": "Feature",
  "properties": {
    "addr:full":"C/ Eivissa-sant Antoni, S/n S. Antoni Portmany Islas Baleares 07820",
    "addr:housenumber":"s",
    "addr:postcode":"07820",
    "addr:street":"C / Eivissa-Sant Antoni;/ N S. Antoni Portmany",
    "iso:country":"ES",
    "sg:address":"C/ Eivissa-sant Antoni, S/n",
    "sg:city":"S. Antoni Portmany",
    "sg:orig_category":"Supermercados Y Hipermercados",
    "sg:phone":"+34 971 34 65 04",
    "sg:postcode":"07820",
    "sg:province":"Islas Baleares",
    "wof:name":"Tur Prats Antonio",
    "wof:placetype":"venue"
},
  "geometry": {"coordinates":[1.3320599794,38.975151062],"type":"Point"}
}