{
  "type": "Feature",
  "properties": {
    "iso:country":"ES",
    "sg:address":"Plazaola Kalea, 4",
    "sg:city":"Legazpi",
    "sg:orig_category":"Vinos Y Licores (venta Al Por Menor)",
    "sg:phone":"+34 943 73 00 95",
    "sg:postcode":"20230",
    "sg:province":"Guip\u00f9zcoa",
    "wof:name":"Zubeldia Artano Domingo",
    "wof:placetype":"venue"
},
  "geometry": {"coordinates":[-2.3309476376,43.0508270264],"type":"Point"}
}