{
  "type": "Feature",
  "properties": {
    "addr:full":"Calle de Alheli, 22 Humanes De Madrid Madrid 28970",
    "addr:housenumber":"22",
    "addr:postcode":"28970",
    "addr:street":"Calle De Alheli",
    "iso:country":"ES",
    "sg:address":"Calle de Alheli, 22",
    "sg:city":"Humanes De Madrid",
    "sg:orig_category":"Fabricaci\u00d3n De Pernos, Tornillos Y Clavos",
    "sg:phone":"+34 916 06 15 11",
    "sg:postcode":"28970",
    "sg:province":"Madrid",
    "wof:name":"Varilla Roscada S. A.",
    "wof:placetype":"venue"
},
  "geometry": {"coordinates":[-3.834444046,40.2683868408],"type":"Point"}
}