{
  "type": "Feature",
  "properties": {
    "iso:country":"ES",
    "sg:address":"Carrer de Major, 37",
    "sg:city":"Sitges",
    "sg:orig_category":"Art\u00cdculos De Regalo (al Por Menor)",
    "sg:phone":"+34 938 94 43 02",
    "sg:postcode":"08870",
    "sg:province":"Barcelona",
    "sg:website":"www.naturaselection.com",
    "wof:name":"Trastara S.l.",
    "wof:placetype":"venue"
},
  "geometry": {"coordinates":[1.8099529743,41.2363510132],"type":"Point"}
}