{
  "type": "Feature",
  "properties": {
    "addr:full":"Carrer de Jovellanos, 13 Reus Tarragona 43201",
    "addr:housenumber":"13",
    "addr:postcode":"43201",
    "addr:street":"Carrer De Jovellanos",
    "iso:country":"ES",
    "sg:address":"Carrer de Jovellanos, 13",
    "sg:city":"Reus",
    "sg:classifiers":[
        {
            "category":"Arts & Performance",
            "subcategory":"Art Gallery",
            "type":"Entertainment"
        }
    ],
    "sg:phone":"+34 977 32 25 10",
    "sg:postcode":"43201",
    "sg:province":"Tarragona",
    "sg:tags":[
        "arte",
        "de",
        "galer\u00cdas"
    ],
    "wof:name":"Ferrer Lopez Enric",
    "wof:placetype":"venue"
},
  "geometry": {"coordinates":[1.1032899618,41.1535263062],"type":"Point"}
}