{
  "type": "Feature",
  "properties": {
    "addr:full":"G.v. Corts Catalanes, 318 Barcelona Barcelona 08004",
    "addr:housenumber":"318",
    "addr:postcode":"08004",
    "addr:street":"Catalanes",
    "iso:country":"ES",
    "sg:address":"G.v. Corts Catalanes, 318",
    "sg:city":"Barcelona",
    "sg:orig_category":"Servidores Y Editores De Bases De Datos",
    "sg:phone":"+34 933 25 71 55",
    "sg:postcode":"08004",
    "sg:province":"Barcelona",
    "wof:name":"Dmcsolutions",
    "wof:placetype":"venue"
},
  "geometry": {"coordinates":[2.1469600201,41.373008728],"type":"Point"}
}