{
  "type": "Feature",
  "properties": {
    "addr:full":"Calle de Duque, 6 Talavera Real Badajoz 06140",
    "addr:housenumber":"6",
    "addr:postcode":"06140",
    "addr:street":"Calle De Duque",
    "iso:country":"ES",
    "sg:address":"Calle de Duque, 6",
    "sg:city":"Talavera Real",
    "sg:orig_category":"Electrodom\u00c9sticos (al Por Menor)",
    "sg:phone":"+34 924 44 12 91",
    "sg:postcode":"06140",
    "sg:province":"Badajoz",
    "wof:name":"Caballero Tobalo Pedro",
    "wof:placetype":"venue"
},
  "geometry": {"coordinates":[-6.7725548744,38.8786468506],"type":"Point"}
}