{
  "type": "Feature",
  "properties": {
    "iso:country":"ES",
    "sg:address":"Barr Erreka, 1",
    "sg:city":"Portuondo-basaran",
    "sg:orig_category":"Barbacoas Y Accesorios",
    "sg:phone":"+34 946 17 72 19",
    "sg:postcode":"48360",
    "sg:province":"Vizcaya",
    "wof:name":"Erreka Erretegia S. L.",
    "wof:placetype":"venue"
},
  "geometry": {"coordinates":[-2.7003688812,43.4094314575],"type":"Point"}
}