{
  "type": "Feature",
  "properties": {
    "iso:country":"ES",
    "sg:address":"Calle de Hornos Caleros (de Los), 62",
    "sg:city":"Avila",
    "sg:orig_category":"Venta, Montaje De Neum\u00c1ticos",
    "sg:phone":"+34 920 22 84 82",
    "sg:postcode":"05003",
    "sg:province":"\u00c1vila",
    "wof:name":"Otero Mu\u00f1oz Pedro",
    "wof:placetype":"venue"
},
  "geometry": {"coordinates":[-4.6741662025,40.6494636536],"type":"Point"}
}