{
  "type": "Feature",
  "properties": {
    "addr:full":"Calle de De Sancti Spiritus, 6 Benavente Zamora 49600",
    "addr:housenumber":"6",
    "addr:postcode":"49600",
    "addr:street":"Calle De De Sancti Spiritus",
    "iso:country":"ES",
    "sg:address":"Calle de De Sancti Spiritus, 6",
    "sg:city":"Benavente",
    "sg:orig_category":"Agencias De Viajes",
    "sg:phone":"+34 980 63 50 35",
    "sg:postcode":"49600",
    "sg:province":"Zamora",
    "wof:name":"Vazquez Viajes S.l.",
    "wof:placetype":"venue"
},
  "geometry": {"coordinates":[-5.6816778183,42.0017852783],"type":"Point"}
}