{
  "type": "Feature",
  "properties": {
    "addr:full":"Calle de Parrales (los), 5 Albolote Granada 18220",
    "addr:housenumber":"5",
    "addr:postcode":"18220",
    "addr:street":"Calle De Parrales Los",
    "iso:country":"ES",
    "sg:address":"Calle de Parrales (los), 5",
    "sg:city":"Albolote",
    "sg:orig_category":"Agencias Y Agentes Comerciales, Representantes",
    "sg:phone":"+34 958 49 06 18",
    "sg:postcode":"18220",
    "sg:province":"Granada",
    "wof:name":"Diaz Gomez Maria Eugenia",
    "wof:placetype":"venue"
},
  "geometry": {"coordinates":[-3.6725940704,37.2442512512],"type":"Point"}
}