{
  "type": "Feature",
  "properties": {
    "iso:country":"ES",
    "sg:address":"Calle de Hospital, 4",
    "sg:city":"Conil De La Frontera",
    "sg:orig_category":"Iglesia Cat\u00d3lica",
    "sg:phone":"+34 956 44 00 78",
    "sg:postcode":"11140",
    "sg:province":"C\u00e1diz",
    "wof:name":"Parroquia De Santa Catalina Casa Parroquial",
    "wof:placetype":"venue"
},
  "geometry": {"coordinates":[-6.0893092155,36.2748985291],"type":"Point"}
}