{
  "type": "Feature",
  "properties": {
    "addr:full":"Rua Serra Do Burgo, 11 Ourense Ourense 32005",
    "addr:housenumber":"11",
    "addr:postcode":"32005",
    "addr:street":"Rua Serra Do Burgo",
    "iso:country":"ES",
    "sg:address":"Rua Serra Do Burgo, 11",
    "sg:city":"Ourense",
    "sg:orig_category":"M\u00c9dicos: Neurocirug\u00cda",
    "sg:phone":"+34 988 22 45 70",
    "sg:postcode":"32005",
    "sg:province":"Ourense",
    "wof:name":"Hernansanz Esteban Jose",
    "wof:placetype":"venue"
},
  "geometry": {"coordinates":[-7.8582978249,42.3286705017],"type":"Point"}
}