{
  "type": "Feature",
  "properties": {
    "iso:country":"ES",
    "sg:address":"Calle de Burgos, 70",
    "sg:city":"Sedano",
    "sg:orig_category":"Farmacias",
    "sg:phone":"+34 947 15 00 77",
    "sg:postcode":"09142",
    "sg:province":"Burgos",
    "wof:name":"Martinez Iriarte Ignacio",
    "wof:placetype":"venue"
},
  "geometry": {"coordinates":[-3.7490451336,42.7137451172],"type":"Point"}
}