{
  "type": "Feature",
  "properties": {
    "addr:full":"Carrer de Feliu I Codina, 12 Barcelona Barcelona 08031",
    "addr:housenumber":"12",
    "addr:postcode":"08031",
    "addr:street":"Carrer De Feliu;Codina",
    "iso:country":"ES",
    "sg:address":"Carrer de Feliu I Codina, 12",
    "sg:city":"Barcelona",
    "sg:orig_category":"Cajas De Ahorro",
    "sg:phone":"+34 933 57 42 66",
    "sg:postcode":"08031",
    "sg:province":"Barcelona",
    "sg:website":"www.lacaixa.es",
    "wof:name":"Caixa D'estalvis I Pensions De Barcelona",
    "wof:placetype":"venue"
},
  "geometry": {"coordinates":[2.1605548859,41.4324035645],"type":"Point"}
}