{
  "type": "Feature",
  "properties": {
    "addr:full":"Calle de Calvario, 30 Marbella M\u00e1laga 29600",
    "addr:housenumber":"30",
    "addr:postcode":"29600",
    "addr:street":"Calle De Calvario;Ma\u0301Laga",
    "iso:country":"ES",
    "sg:address":"Calle de Calvario, 30",
    "sg:city":"Marbella",
    "sg:orig_category":"Centros De Educaci\u00d3n Especial",
    "sg:phone":"+34 952 77 52 53",
    "sg:postcode":"29600",
    "sg:province":"M\u00e1laga",
    "wof:name":"Junta De Andalucia",
    "wof:placetype":"venue"
},
  "geometry": {"coordinates":[-4.891283989,36.515171051],"type":"Point"}
}