{
  "type": "Feature",
  "properties": {
    "addr:full":"Pase Morella, 92 Castellon Castell\u00f3n 12004",
    "addr:housenumber":"92",
    "addr:postcode":"12004",
    "addr:street":"Morella",
    "iso:country":"ES",
    "sg:address":"Pase Morella, 92",
    "sg:city":"Castellon",
    "sg:orig_category":"Electricidad Veh\u00cdculo",
    "sg:phone":"+34 964 20 77 11",
    "sg:postcode":"12004",
    "sg:province":"Castell\u00f3n",
    "wof:name":"Electricidad Ferreres Soler S.l.",
    "wof:placetype":"venue"
},
  "geometry": {"coordinates":[-0.0257600006,40.0253791809],"type":"Point"}
}