{
  "type": "Feature",
  "properties": {
    "iso:country":"ES",
    "sg:address":"Crta Azucarera-intelhorce (pi Gudalhorc), 12",
    "sg:city":"Malaga",
    "sg:orig_category":"Postigos, Persianas Y Celos\u00cdas",
    "sg:phone":"+34 952 23 98 77",
    "sg:postcode":"29004",
    "sg:province":"M\u00e1laga",
    "wof:name":"Industrial Gradhermetic S.a.e.",
    "wof:placetype":"venue"
},
  "geometry": {"coordinates":[-4.4768671989,36.6877098083],"type":"Point"}
}