{
  "type": "Feature",
  "properties": {
    "iso:country":"ES",
    "sg:address":"Calle de Corregidor Francisco De Lujan, 3",
    "sg:city":"Malaga",
    "sg:orig_category":"Farmacias",
    "sg:phone":"+34 952 33 35 61",
    "sg:postcode":"29006",
    "sg:province":"M\u00e1laga",
    "wof:name":"Isabel Y Pilar Alfonso Rosas C.b.",
    "wof:placetype":"venue"
},
  "geometry": {"coordinates":[-4.4494314194,36.7114257812],"type":"Point"}
}