{
  "type": "Feature",
  "properties": {
    "addr:full":"Pase San Francisco De Sales, 25 Madrid Madrid 28003",
    "addr:housenumber":"25",
    "addr:postcode":"madrid;28003",
    "addr:street":"Francisco De Sales",
    "iso:country":"ES",
    "sg:address":"Pase San Francisco De Sales, 25",
    "sg:city":"Madrid",
    "sg:orig_category":"Pizzer\u00cdas",
    "sg:phone":"+34 915 50 01 75",
    "sg:postcode":"28003",
    "sg:province":"Madrid",
    "wof:name":"Pizza Jardin Noroeste S.l.",
    "wof:placetype":"venue"
},
  "geometry": {"coordinates":[-3.7143359184,40.4414978027],"type":"Point"}
}