{
  "type": "Feature",
  "properties": {
    "iso:country":"ES",
    "sg:address":"Calle de Gongora, 47",
    "sg:city":"Priego Cordoba",
    "sg:orig_category":"Electricidad: Instaladores",
    "sg:phone":"+34 957 70 03 63",
    "sg:postcode":"14800",
    "sg:province":"C\u00f3rdoba",
    "wof:name":"Manuel Carrillo Montajes Electricos S.l.",
    "wof:placetype":"venue"
},
  "geometry": {"coordinates":[-4.2057890892,37.4413452148],"type":"Point"}
}