{
  "type": "Feature",
  "properties": {
    "iso:country":"ES",
    "sg:address":"Autopista De San Pablo, 1",
    "sg:city":"Sevilla",
    "sg:orig_category":"Deportes Diversos",
    "sg:phone":"+34 954 68 74 35",
    "sg:postcode":"41007",
    "sg:province":"Sevilla",
    "wof:name":"Hacienda De La Plata S.a",
    "wof:placetype":"venue"
},
  "geometry": {"coordinates":[-5.9971051216,37.3905334473],"type":"Point"}
}