{
  "type": "Feature",
  "properties": {
    "addr:full":"Calle de Asturias, 30 Valverde Camino Huelva 21600",
    "addr:housenumber":"30",
    "addr:postcode":"21600",
    "addr:street":"Calle De Asturias;Camino Huelva",
    "iso:country":"ES",
    "sg:address":"Calle de Asturias, 30",
    "sg:city":"Valverde Camino",
    "sg:orig_category":"Metalurgia",
    "sg:phone":"+34 959 55 04 14",
    "sg:postcode":"21600",
    "sg:province":"Huelva",
    "wof:name":"Macias Borrero Jose De Jesus",
    "wof:placetype":"venue"
},
  "geometry": {"coordinates":[-6.7612996101,37.5775794983],"type":"Point"}
}