{
  "type": "Feature",
  "properties": {
    "addr:full":"Calle de Pirita, 115 Valladolid Valladolid 47012",
    "addr:housenumber":"115",
    "addr:postcode":"47012",
    "addr:street":"Calle De Pirita",
    "iso:country":"ES",
    "sg:address":"Calle de Pirita, 115",
    "sg:city":"Valladolid",
    "sg:orig_category":"Fabricaci\u00d3n, Instalaci\u00d3n Y Reparaci\u00d3n De Bombas",
    "sg:phone":"+34 983 39 66 00",
    "sg:postcode":"47012",
    "sg:province":"Valladolid",
    "wof:name":"Sevillano Rodriguez Teodoro",
    "wof:placetype":"venue"
},
  "geometry": {"coordinates":[-4.7016692162,41.6178894043],"type":"Point"}
}