{
  "type": "Feature",
  "properties": {
    "iso:country":"ES",
    "sg:address":"Calle de Leonardo Rucabado, 43",
    "sg:city":"Castro Urdiales",
    "sg:orig_category":"Transportes Internacionales",
    "sg:phone":"+34 942 86 32 53",
    "sg:postcode":"39700",
    "sg:province":"Cantabria",
    "wof:name":"Transportes Casrrez Sal",
    "wof:placetype":"venue"
},
  "geometry": {"coordinates":[-3.2163660526,43.3707046509],"type":"Point"}
}