{
  "type": "Feature",
  "properties": {
    "iso:country":"ES",
    "sg:address":"Camino Viejo Simancas, Km. 0003,2",
    "sg:city":"Valladolid",
    "sg:orig_category":"Arboricultura Y Producci\u00d3n De Frutas",
    "sg:phone":"+34 983 22 21 20",
    "sg:postcode":"47008",
    "sg:province":"Valladolid",
    "wof:name":"Viveros Rabadan Ayuso S.a.t.",
    "wof:placetype":"venue"
},
  "geometry": {"coordinates":[-4.7442202568,41.6281814575],"type":"Point"}
}