{
  "type": "Feature",
  "properties": {
    "iso:country":"ES",
    "sg:address":"Calle de Fika, 64",
    "sg:city":"Bilbao",
    "sg:orig_category":"Importaci\u00d3n",
    "sg:phone":"+34 944 32 92 52",
    "sg:postcode":"48004",
    "sg:province":"Vizcaya",
    "wof:name":"Irizar Import & Export, S.l.",
    "wof:placetype":"venue"
},
  "geometry": {"coordinates":[-2.9163250923,43.2516403198],"type":"Point"}
}