{
  "type": "Feature",
  "properties": {
    "addr:full":"A Ramallosa, S/n Luci La Coru\u00f1a 15883",
    "addr:housenumber":"/ n",
    "addr:postcode":"15883",
    "addr:street":"Ramallosa S;Luci La Corun\u0303A",
    "iso:country":"ES",
    "sg:address":"A Ramallosa, S/n",
    "sg:city":"Luci",
    "sg:orig_category":"Peluquer\u00cdas, Peluquer\u00cda Mixta",
    "sg:phone":"+34 981 80 95 19",
    "sg:postcode":"15883",
    "sg:province":"La Coru\u00f1a",
    "wof:name":"Martinez Cao Digna",
    "wof:placetype":"venue"
},
  "geometry": {"coordinates":[-8.5444011688,42.8382263184],"type":"Point"}
}