{
  "type": "Feature",
  "properties": {
    "addr:full":"Calle de Jesus Nazareno, 1 Jamilena Ja\u00e9n 23658",
    "addr:housenumber":"1",
    "addr:postcode":"23658",
    "addr:street":"Calle De Jesus Nazareno",
    "iso:country":"ES",
    "sg:address":"Calle de Jesus Nazareno, 1",
    "sg:city":"Jamilena",
    "sg:orig_category":"Estancos",
    "sg:phone":"+34 953 56 62 03",
    "sg:postcode":"23658",
    "sg:province":"Ja\u00e9n",
    "wof:name":"Garrido Perez Maria Dolores",
    "wof:placetype":"venue"
},
  "geometry": {"coordinates":[-3.9122331142,37.7475204468],"type":"Point"}
}