{
  "type": "Feature",
  "properties": {
    "iso:country":"ES",
    "sg:address":"C/ Berga, 22",
    "sg:city":"Arenal",
    "sg:orig_category":"Quincaller\u00cda (al Por Menor)",
    "sg:phone":"+34 971 44 17 66",
    "sg:postcode":"07600",
    "sg:province":"Islas Baleares",
    "wof:name":"Garcia Biza\u00f1ez Carolina",
    "wof:placetype":"venue"
},
  "geometry": {"coordinates":[2.752327919,39.5086097717],"type":"Point"}
}