{
  "type": "Feature",
  "properties": {
    "addr:full":"Calle de Concordia, 21 Villasequilla Toledo 45740",
    "addr:housenumber":"21",
    "addr:postcode":"45740",
    "addr:street":"Calle De Concordia",
    "iso:country":"ES",
    "sg:address":"Calle de Concordia, 21",
    "sg:city":"Villasequilla",
    "sg:orig_category":"Transportes Por V\u00cdas Navegables",
    "sg:phone":"+34 925 31 00 73",
    "sg:postcode":"45740",
    "sg:province":"Toledo",
    "wof:name":"Berzosa Berzosa Antonio",
    "wof:placetype":"venue"
},
  "geometry": {"coordinates":[-3.730604887,39.874961853],"type":"Point"}
}