{
  "type": "Feature",
  "properties": {
    "iso:country":"ES",
    "sg:address":"Calle de San Juan, 46",
    "sg:city":"Santiago Ribera",
    "sg:orig_category":"Mercer\u00cda, Lencer\u00cda (al Por Menor)",
    "sg:phone":"+34 968 57 36 35",
    "sg:postcode":"30720",
    "sg:province":"Murcia",
    "wof:name":"Garcia Perez Angel",
    "wof:placetype":"venue"
},
  "geometry": {"coordinates":[-0.8066949844,37.8011856079],"type":"Point"}
}