{
  "type": "Feature",
  "properties": {
    "addr:full":"Calle de Marquesa De Zenete, 29 Ayora Valencia 46620",
    "addr:housenumber":"29",
    "addr:postcode":"46620",
    "addr:street":"Calle De Marquesa De Zenete",
    "iso:country":"ES",
    "sg:address":"Calle de Marquesa De Zenete, 29",
    "sg:city":"Ayora",
    "sg:orig_category":"Telefon\u00cda: Instaladores Varios",
    "sg:phone":"+34 962 19 16 70",
    "sg:postcode":"46620",
    "sg:province":"Valencia",
    "sg:website":"www.gesintel.com.es",
    "wof:name":"Gesintel Ayora S.l.",
    "wof:placetype":"venue"
},
  "geometry": {"coordinates":[-1.055734992,39.0607032776],"type":"Point"}
}