{
  "type": "Feature",
  "properties": {
    "addr:full":"Calle de Villarias, 10 Bilbao Vizcaya 48001",
    "addr:housenumber":"10",
    "addr:postcode":"48001",
    "addr:street":"Calle De Villarias",
    "iso:country":"ES",
    "sg:address":"Calle de Villarias, 10",
    "sg:city":"Bilbao",
    "sg:classifiers":[
        {
            "category":"Cinema",
            "subcategory":"Movie Theater",
            "type":"Entertainment"
        }
    ],
    "sg:phone":"+34 944 23 10 01",
    "sg:postcode":"48001",
    "sg:province":"Vizcaya",
    "sg:tags":[
        "salas",
        "de",
        "cine"
    ],
    "wof:name":"Cinematografia Coliseo S. L.",
    "wof:placetype":"venue"
},
  "geometry": {"coordinates":[-2.9254999161,43.2619857788],"type":"Point"}
}