{
  "type": "Feature",
  "properties": {
    "addr:full":"Plaz Sagrado Corazon De Jesus, 1 Madrid Madrid 28002",
    "addr:housenumber":"1",
    "addr:postcode":"28002",
    "addr:street":"Jesus",
    "iso:country":"ES",
    "sg:address":"Plaz Sagrado Corazon De Jesus, 1",
    "sg:city":"Madrid",
    "sg:orig_category":"Arquitectos",
    "sg:phone":"+34 915 63 26 30",
    "sg:postcode":"28002",
    "sg:province":"Madrid",
    "sg:website":"www.adamlubroch.com",
    "wof:name":"Apple Tree Studio S.l.",
    "wof:placetype":"venue"
},
  "geometry": {"coordinates":[-3.6771996021,40.4449729919],"type":"Point"}
}