{
  "type": "Feature",
  "properties": {
    "iso:country":"ES",
    "sg:address":"Calle de Playa Samil, 11",
    "sg:city":"Estacion",
    "sg:orig_category":"Electricidad, Electr\u00d3nica: Suministros (al Por Menor)",
    "sg:phone":"+34 918 50 35 18",
    "sg:postcode":"28400",
    "sg:province":"Madrid",
    "wof:name":"Satema S.l.",
    "wof:placetype":"venue"
},
  "geometry": {"coordinates":[-4.0113840103,40.618598938],"type":"Point"}
}