{
  "type": "Feature",
  "properties": {
    "iso:country":"ES",
    "sg:address":"Calle de Sevilla, 26",
    "sg:city":"Arahal",
    "sg:orig_category":"Carnicer\u00cdas, Carnicer\u00cdas",
    "sg:phone":"+34 955 84 19 62",
    "sg:postcode":"41600",
    "sg:province":"Sevilla",
    "wof:name":"Carniceria El Chino S.l.",
    "wof:placetype":"venue"
},
  "geometry": {"coordinates":[-5.5464820862,37.2642097473],"type":"Point"}
}