{
  "type": "Feature",
  "properties": {
    "addr:full":"Carrer de Prat De La Riba, 100 Mataro Barcelona 08301",
    "addr:housenumber":"100",
    "addr:postcode":"08301",
    "addr:street":"Carrer De Prat De La Riba",
    "iso:country":"ES",
    "sg:address":"Carrer de Prat De La Riba, 100",
    "sg:city":"Mataro",
    "sg:orig_category":"Fabricaci\u00d3n De Su\u00c9ters Y Chalecos De Punto",
    "sg:phone":"+34 937 90 12 46",
    "sg:postcode":"08301",
    "sg:province":"Barcelona",
    "wof:name":"Ventura Punt S.l.",
    "wof:placetype":"venue"
},
  "geometry": {"coordinates":[2.4523389339,41.5446243286],"type":"Point"}
}