{
  "type": "Feature",
  "properties": {
    "iso:country":"ES",
    "sg:address":"Calle de Covadonga, 7",
    "sg:city":"Candas",
    "sg:orig_category":"Negocio De Materiales De Construcci\u00d3n",
    "sg:phone":"+34 985 87 05 19",
    "sg:postcode":"33430",
    "sg:province":"Asturias",
    "wof:name":"Ferreteria El Campo S.l.",
    "wof:placetype":"venue"
},
  "geometry": {"coordinates":[-5.7676272392,43.5867919922],"type":"Point"}
}