{
  "type": "Feature",
  "properties": {
    "addr:full":"Ctra. Manzanares, Km. 0030,0 Boalo Madrid 28413",
    "addr:postcode":"28413",
    "addr:street":"Ctra. Manzanares Km. 0030,0",
    "iso:country":"ES",
    "sg:address":"Ctra. Manzanares, Km. 0030,0",
    "sg:city":"Boalo",
    "sg:orig_category":"Alimentaci\u00d3n General (al Por Mayor)",
    "sg:phone":"+34 918 55 90 04",
    "sg:postcode":"28413",
    "sg:province":"Madrid",
    "wof:name":"Piensos Benito De Lema S.l.",
    "wof:placetype":"venue"
},
  "geometry": {"coordinates":[-3.9205970764,40.7194519043],"type":"Point"}
}