{
  "type": "Feature",
  "properties": {
    "addr:full":"Ctra Puebla, Km. 0000,5 Alosno Huelva 21520",
    "addr:postcode":"21520",
    "addr:street":"Ctra Puebla Km. 0000,5",
    "iso:country":"ES",
    "sg:address":"Ctra Puebla, Km. 0000,5",
    "sg:city":"Alosno",
    "sg:orig_category":"Producci\u00d3n, Comercio De Cereales",
    "sg:phone":"+34 959 39 61 85",
    "sg:postcode":"21520",
    "sg:province":"Huelva",
    "wof:name":"Isaias Guerra E Hijos S.l.",
    "wof:placetype":"venue"
},
  "geometry": {"coordinates":[-7.1202340126,37.5489349365],"type":"Point"}
}