{
  "type": "Feature",
  "properties": {
    "addr:full":"Calle de Azahar, 1 Huelva Huelva 21005",
    "addr:housenumber":"1",
    "addr:postcode":"21005",
    "addr:street":"Calle De Azahar",
    "iso:country":"ES",
    "sg:address":"Calle de Azahar, 1",
    "sg:city":"Huelva",
    "sg:orig_category":"Alimentaci\u00d3n General (al Por Menor)",
    "sg:phone":"+34 959 15 33 74",
    "sg:postcode":"21005",
    "sg:province":"Huelva",
    "wof:name":"Toscano Monis Cristobalina",
    "wof:placetype":"venue"
},
  "geometry": {"coordinates":[-6.9341144562,37.2748222351],"type":"Point"}
}