{
  "type": "Feature",
  "properties": {
    "iso:country":"ES",
    "sg:address":"Calle de Calahorra, 22",
    "sg:city":"Madrid",
    "sg:orig_category":"Limpieza Con Chorro De Arena Y Con Granalla, Pulido",
    "sg:phone":"+34 917 76 22 23",
    "sg:postcode":"28032",
    "sg:province":"Madrid",
    "wof:name":"Sanz Rodriguez Pablo",
    "wof:placetype":"venue"
},
  "geometry": {"coordinates":[-3.6107668877,40.4089660645],"type":"Point"}
}