{
  "type": "Feature",
  "properties": {
    "addr:full":"Carrer de Balmes, 308 Barcelona Barcelona 08006",
    "addr:housenumber":"308",
    "addr:postcode":"08006",
    "addr:street":"Carrer De Balmes",
    "iso:country":"ES",
    "sg:address":"Carrer de Balmes, 308",
    "sg:city":"Barcelona",
    "sg:orig_category":"Deportes Y Ocio: Art\u00cdculos Y Ropas (al Por Menor Y Accesorios)",
    "sg:phone":"+34 932 09 05 39",
    "sg:postcode":"08006",
    "sg:province":"Barcelona",
    "wof:name":"La General Surfera S.l",
    "wof:placetype":"venue"
},
  "geometry": {"coordinates":[2.1454899311,41.4025306702],"type":"Point"}
}