{
  "type": "Feature",
  "properties": {
    "iso:country":"ES",
    "sg:address":"Calle de Campoamor, 101",
    "sg:city":"Torrevieja",
    "sg:orig_category":"Reposter\u00cdas",
    "sg:phone":"+34 965 71 02 70",
    "sg:postcode":"03180",
    "sg:province":"Alicante",
    "wof:name":"Martinez Rodriguez Manuel",
    "wof:placetype":"venue"
},
  "geometry": {"coordinates":[-0.6848559976,37.9786949158],"type":"Point"}
}