{
  "type": "Feature",
  "properties": {
    "iso:country":"ES",
    "sg:address":"Calle de Viriato, 8",
    "sg:city":"Mazarron",
    "sg:orig_category":"Ense\u00d1anza Variada",
    "sg:phone":"+34 968 33 30 31",
    "sg:postcode":"30870",
    "sg:province":"Murcia",
    "wof:name":"A. P. Cemiferma S.l.",
    "wof:placetype":"venue"
},
  "geometry": {"coordinates":[-1.2566591501,37.5687713623],"type":"Point"}
}