{
  "type": "Feature",
  "properties": {
    "iso:country":"ES",
    "sg:address":"Avda Alcalde Jose Ramirez Bethencourt, 8",
    "sg:city":"Palmas De Gran Canaria",
    "sg:orig_category":"Peluqueros: De Se\u00d1oras",
    "sg:phone":"+34 928 37 26 46",
    "sg:postcode":"35003",
    "sg:province":"Las Palmas",
    "wof:name":"Suarez Correa Antonio Mario",
    "wof:placetype":"venue"
},
  "geometry": {"coordinates":[-15.4164590836,28.1095600128],"type":"Point"}
}