{
  "type": "Feature",
  "properties": {
    "addr:full":"Calle de Nueva, 12 Aljaraque Huelva 21110",
    "addr:housenumber":"12",
    "addr:postcode":"21110",
    "addr:street":"Calle De Nueva",
    "iso:country":"ES",
    "sg:address":"Calle de Nueva, 12",
    "sg:city":"Aljaraque",
    "sg:orig_category":"Caf\u00c9s, Bares, Cervecer\u00cdas",
    "sg:phone":"+34 959 35 50 09",
    "sg:postcode":"21110",
    "sg:province":"Huelva",
    "wof:name":"Seronuba S.a.",
    "wof:placetype":"venue"
},
  "geometry": {"coordinates":[-7.0230569839,37.2714347839],"type":"Point"}
}