{
  "type": "Feature",
  "properties": {
    "iso:country":"ES",
    "sg:address":"Calle de Estepona, 13",
    "sg:city":"Dos Hermanas",
    "sg:orig_category":"Forjas Y Altos Hornos",
    "sg:phone":"+34 954 72 35 12",
    "sg:postcode":"41700",
    "sg:province":"Sevilla",
    "wof:name":"Garcia Cotan Antonio",
    "wof:placetype":"venue"
},
  "geometry": {"coordinates":[-5.9153981209,37.2752914429],"type":"Point"}
}