{
  "type": "Feature",
  "properties": {
    "iso:country":"ES",
    "sg:address":"Rua Sanchez Barcaiztegui, 28",
    "sg:city":"Ferrol",
    "sg:orig_category":"Alquiler De Casas Y Habitaciones Amuebladas",
    "sg:phone":"+34 981 35 17 87",
    "sg:postcode":"15401",
    "sg:province":"A Coru\u00f1a",
    "wof:name":"Xunta De Galicia",
    "wof:placetype":"venue"
},
  "geometry": {"coordinates":[-8.2373151779,43.4839439392],"type":"Point"}
}