{
  "type": "Feature",
  "properties": {
    "iso:country":"ES",
    "sg:address":"Pla\u00c7 Morella, S/n",
    "sg:city":"Silla",
    "sg:orig_category":"Formaci\u00d3n Continuada (variada)",
    "sg:phone":"+34 961 20 26 17",
    "sg:postcode":"46460",
    "sg:province":"Valencia",
    "wof:name":"Centro Ocupacional Tola Cooperativa Valenciana",
    "wof:placetype":"venue"
},
  "geometry": {"coordinates":[-0.4131639898,39.3583755493],"type":"Point"}
}