{
  "type": "Feature",
  "properties": {
    "iso:country":"ES",
    "sg:address":"Pase Rey Don Juan Carlos I, 8",
    "sg:city":"Oliva",
    "sg:orig_category":"Agencias De Viajes",
    "sg:phone":"+34 962 85 30 73",
    "sg:postcode":"46780",
    "sg:province":"Valencia",
    "wof:name":"Agencia De Viajes Oliva S. L.",
    "wof:placetype":"venue"
},
  "geometry": {"coordinates":[-0.1163180992,38.9203987122],"type":"Point"}
}