{
  "type": "Feature",
  "properties": {
    "addr:full":"Luga Loureiro, 1 San Pedro De Visma La Coru\u00f1a 15011",
    "addr:housenumber":"1",
    "addr:postcode":"15011",
    "addr:street":"Loureiro;Corun\u0303A",
    "iso:country":"ES",
    "sg:address":"Luga Loureiro, 1",
    "sg:city":"San Pedro De Visma",
    "sg:orig_category":"Comercio De Hierro",
    "sg:phone":"+34 981 26 91 00",
    "sg:postcode":"15011",
    "sg:province":"La Coru\u00f1a",
    "wof:name":"Francisco Mata S.a.",
    "wof:placetype":"venue"
},
  "geometry": {"coordinates":[-8.4317598343,43.3684883118],"type":"Point"}
}