{
  "type": "Feature",
  "properties": {
    "iso:country":"ES",
    "sg:address":"Calle de Maestro Ramis, 23",
    "sg:city":"Novelda",
    "sg:orig_category":"Cl\u00cdnicas M\u00c9dicas",
    "sg:phone":"+34 965 60 53 39",
    "sg:postcode":"03660",
    "sg:province":"Alicante",
    "wof:name":"Mira Iniesta Maria Remedios",
    "wof:placetype":"venue"
},
  "geometry": {"coordinates":[-0.7665219903,38.3828697205],"type":"Point"}
}