{
  "type": "Feature",
  "properties": {
    "iso:country":"ES",
    "sg:address":"Barr Basadi Auzategia, 12",
    "sg:city":"Zumaia",
    "sg:classifiers":[
        {
            "category":"Autos & Motor Vehicles",
            "subcategory":"Automobile Sales",
            "type":"Retail Goods"
        }
    ],
    "sg:phone":"+34 943 01 61 26",
    "sg:postcode":"20750",
    "sg:province":"Guip\u00f9zcoa",
    "wof:name":"Autoescuela Zumaia",
    "wof:placetype":"venue"
},
  "geometry": {"coordinates":[-2.2593860626,43.2993354797],"type":"Point"}
}