{
  "type": "Feature",
  "properties": {
    "iso:country":"ES",
    "sg:address":"Avda Principe De Asturias, 2",
    "sg:city":"Badajoz",
    "sg:orig_category":"Ingenier\u00cda, Centros De Estudios (diversos)",
    "sg:phone":"+34 924 24 76 59",
    "sg:postcode":"06011",
    "sg:province":"Badajoz",
    "wof:name":"Lopez Rodriguez Fernando",
    "wof:placetype":"venue"
},
  "geometry": {"coordinates":[-6.9916830063,38.8642234802],"type":"Point"}
}