{
  "type": "Feature",
  "properties": {
    "addr:full":"Calle de Clavel, 4 Estrella Las Palmas 35212",
    "addr:housenumber":"4",
    "addr:postcode":"35212",
    "addr:street":"Calle De Clavel",
    "iso:country":"ES",
    "sg:address":"Calle de Clavel, 4",
    "sg:city":"Estrella",
    "sg:classifiers":[
        {
            "category":"Retail",
            "subcategory":"Event Space",
            "type":"Services"
        }
    ],
    "sg:phone":"+34 928 13 05 46",
    "sg:postcode":"35212",
    "sg:province":"Las Palmas",
    "sg:tags":[
        "planchas",
        "surf",
        "alquiler",
        "de",
        "vela",
        "kayak",
        "barcos",
        "canoes",
        "y"
    ],
    "wof:name":"Gecrimar Canarias S.l.",
    "wof:placetype":"venue"
},
  "geometry": {"coordinates":[-15.3837585449,28.0151538849],"type":"Point"}
}