{
  "type": "Feature",
  "properties": {
    "addr:full":"Calle de Padre Francisco Palau Y Quer, 7 Granada Granada 18006",
    "addr:housenumber":"7",
    "addr:postcode":"18006",
    "addr:street":"Calle De Padre Francisco Palau Y Quer",
    "iso:country":"ES",
    "sg:address":"Calle de Padre Francisco Palau Y Quer, 7",
    "sg:city":"Granada",
    "sg:orig_category":"Internados & Ense\u00d1anza Privada",
    "sg:phone":"+34 958 81 26 11",
    "sg:postcode":"18006",
    "sg:province":"Granada",
    "wof:name":"Colegio El Carmelo",
    "wof:placetype":"venue"
},
  "geometry": {"coordinates":[-3.6051990986,37.1540985107],"type":"Point"}
}