{
  "type": "Feature",
  "properties": {
    "iso:country":"ES",
    "sg:address":"Plaz Profesor Eloy Terron, S/n",
    "sg:city":"Fabero",
    "sg:orig_category":"Ense\u00d1anza, Formaci\u00d3n Profesional: Aprendizaje",
    "sg:phone":"+34 987 55 06 38",
    "sg:postcode":"24420",
    "sg:province":"Le\u00f3n",
    "wof:name":"Ayuntamiento De Fabero",
    "wof:placetype":"venue"
},
  "geometry": {"coordinates":[-6.6280488968,42.7658042908],"type":"Point"}
}