{
  "type": "Feature",
  "properties": {
    "iso:country":"ES",
    "sg:address":"Ctra Daroca, 11",
    "sg:city":"Medrano",
    "sg:orig_category":"Agencias Y Agentes Comerciales, Representantes",
    "sg:phone":"+34 941 44 49 22",
    "sg:postcode":"26374",
    "sg:province":"La Rioja",
    "wof:name":"Berges Villar Maria Victoria",
    "wof:placetype":"venue"
},
  "geometry": {"coordinates":[-2.555232048,42.3815116882],"type":"Point"}
}