{
  "type": "Feature",
  "properties": {
    "iso:country":"ES",
    "sg:address":"Calle de Duque De La Victoria, 17",
    "sg:city":"Valladolid",
    "sg:orig_category":"Ropa Para Se\u00d1oras (al Por Menor)",
    "sg:phone":"+34 983 30 46 88",
    "sg:postcode":"47001",
    "sg:province":"Valladolid",
    "wof:name":"Senin 04 S.l.",
    "wof:placetype":"venue"
},
  "geometry": {"coordinates":[-4.7262539864,41.6502304077],"type":"Point"}
}