{
  "type": "Feature",
  "properties": {
    "addr:full":"Luga Lances (los), S/n Tarifa C\u00e1diz 11380",
    "addr:postcode":"11380",
    "addr:street":"Los S / N;Ca\u0301Diz",
    "iso:country":"ES",
    "sg:address":"Luga Lances (los), S/n",
    "sg:city":"Tarifa",
    "sg:orig_category":"Pescader\u00cdas (al Por Menor)",
    "sg:phone":"+34 956 68 43 27",
    "sg:postcode":"11380",
    "sg:province":"C\u00e1diz",
    "wof:name":"Almadrabas De Espa\u00f1a S. A.",
    "wof:placetype":"venue"
},
  "geometry": {"coordinates":[-5.6668305397,36.1076469421],"type":"Point"}
}