{
  "type": "Feature",
  "properties": {
    "iso:country":"ES",
    "sg:address":"Calle de Santiago Ruiz De La Torre, 1",
    "sg:city":"Arnedo",
    "sg:orig_category":"Estilistas Y Estudios De Estilo De Corte Y Confecci\u00d3n",
    "sg:phone":"+34 941 38 06 56",
    "sg:postcode":"26580",
    "sg:province":"La Rioja",
    "wof:name":"Vilchez Navarro Maria Josefa",
    "wof:placetype":"venue"
},
  "geometry": {"coordinates":[-2.0990660191,42.2272338867],"type":"Point"}
}