{
  "type": "Feature",
  "properties": {
    "addr:full":"Pol. Sta. Rita-casta\u00f1era, S/n Cuadrove\u00f1a Asturias 33540",
    "addr:postcode":"33540",
    "addr:street":"Pol.;Rita-Castan\u0303Era S / N Cuadroven\u0303A Asturias",
    "iso:country":"ES",
    "sg:address":"Pol. Sta. Rita-casta\u00f1era, S/n",
    "sg:city":"Cuadrove\u00f1a",
    "sg:orig_category":"Panader\u00cdas, Panader\u00cdas",
    "sg:phone":"+34 985 84 02 68",
    "sg:postcode":"33540",
    "sg:province":"Asturias",
    "wof:name":"Panaderia Santa Rita Sociedad Cooperativa Limitada",
    "wof:placetype":"venue"
},
  "geometry": {"coordinates":[-5.1852741241,43.3902168274],"type":"Point"}
}