{
  "type": "Feature",
  "properties": {
    "addr:full":"Rua Juan Xxiii, 3 Ourense Ourense 32003",
    "addr:housenumber":"3",
    "addr:postcode":"32003",
    "addr:street":"Rua Juan Xxiii",
    "iso:country":"ES",
    "sg:address":"Rua Juan Xxiii, 3",
    "sg:city":"Ourense",
    "sg:orig_category":"\u00d3ptica: Instrumentos (fabricaci\u00d3n)",
    "sg:phone":"+34 988 21 08 42",
    "sg:postcode":"32003",
    "sg:province":"Ourense",
    "sg:website":"www.federopticos.com",
    "wof:name":"Fernandez Rodriguez Jose Luis",
    "wof:placetype":"venue"
},
  "geometry": {"coordinates":[-7.8662590981,42.3402366638],"type":"Point"}
}