{
  "type": "Feature",
  "properties": {
    "iso:country":"ES",
    "sg:address":"Calle de Comercio, 3",
    "sg:city":"Binefar",
    "sg:orig_category":"M\u00c9dicos: Ginecolog\u00cda M\u00c9dica, Obstetricia",
    "sg:phone":"+34 974 42 80 53",
    "sg:postcode":"22500",
    "sg:province":"Huesca",
    "wof:name":"Montejano Fernandez Mercedes",
    "wof:placetype":"venue"
},
  "geometry": {"coordinates":[0.2931756079,41.8517913818],"type":"Point"}
}