{
  "type": "Feature",
  "properties": {
    "addr:full":"Calle de San Pedro Y San Felices, 25 Burgos Burgos 09001",
    "addr:housenumber":"25",
    "addr:postcode":"09001",
    "addr:street":"Calle De San;Felices",
    "iso:country":"ES",
    "sg:address":"Calle de San Pedro Y San Felices, 25",
    "sg:city":"Burgos",
    "sg:orig_category":"Pescader\u00cdas (al Por Menor)",
    "sg:phone":"+34 947 27 10 44",
    "sg:postcode":"09001",
    "sg:province":"Burgos",
    "wof:name":"Garcia Obregon Maria Angeles",
    "wof:placetype":"venue"
},
  "geometry": {"coordinates":[-3.7048830986,42.3327445984],"type":"Point"}
}