{
  "type": "Feature",
  "properties": {
    "addr:full":"Calle de Portubidea, 13 Armintza Vizcaya 48620",
    "addr:housenumber":"13",
    "addr:postcode":"48620",
    "addr:street":"Calle De Portubidea",
    "iso:country":"ES",
    "sg:address":"Calle de Portubidea, 13",
    "sg:city":"Armintza",
    "sg:orig_category":"Inform\u00c1tica (estudios, Servicios, Asesor\u00cda, Formaci\u00d3n)",
    "sg:phone":"+34 946 87 93 12",
    "sg:postcode":"48620",
    "sg:province":"Vizcaya",
    "wof:name":"Sociedad Informatica Del Gobierno Vasco-ejie",
    "wof:placetype":"venue"
},
  "geometry": {"coordinates":[-2.8973970413,43.4324188232],"type":"Point"}
}