{
  "type": "Feature",
  "properties": {
    "iso:country":"ES",
    "sg:address":"Avda Menendez Pelayo, 43",
    "sg:city":"Madrid",
    "sg:orig_category":"Peluqueros: De Se\u00d1oras",
    "sg:phone":"+34 915 73 80 51",
    "sg:postcode":"28009",
    "sg:province":"Madrid",
    "wof:name":"Cabrero Vecino Patricio",
    "wof:placetype":"venue"
},
  "geometry": {"coordinates":[-3.6782538891,40.4173774719],"type":"Point"}
}