{
  "type": "Feature",
  "properties": {
    "addr:full":"Calle de O\u00d1on, 3 Mieres Asturias 33600",
    "addr:housenumber":"3",
    "addr:postcode":"33600",
    "addr:street":"Calle De On\u0303On",
    "iso:country":"ES",
    "sg:address":"Calle de O\u00d1on, 3",
    "sg:city":"Mieres",
    "sg:orig_category":"Plomeros",
    "sg:phone":"+34 985 46 40 34",
    "sg:postcode":"33600",
    "sg:province":"Asturias",
    "wof:name":"Garcia Sama Alvaro",
    "wof:placetype":"venue"
},
  "geometry": {"coordinates":[-5.772233963,43.2525100708],"type":"Point"}
}