{
  "type": "Feature",
  "properties": {
    "iso:country":"ES",
    "sg:address":"Calle de Cruz Del Ovejero, 12",
    "sg:city":"Tamaraceite",
    "sg:orig_category":"Cajas De Ahorro",
    "sg:phone":"+34 928 67 40 56",
    "sg:postcode":"35018",
    "sg:province":"Las Palmas",
    "wof:name":"Caja Insular De Ahorros De Canarias",
    "wof:placetype":"venue"
},
  "geometry": {"coordinates":[-15.4784650803,28.0919818878],"type":"Point"}
}