{
  "type": "Feature",
  "properties": {
    "addr:full":"Calle de Gabriel Usera, 10 Madrid Madrid 28026",
    "addr:housenumber":"10",
    "addr:postcode":"madrid;28026",
    "addr:street":"Calle De Gabriel Usera",
    "iso:country":"ES",
    "sg:address":"Calle de Gabriel Usera, 10",
    "sg:city":"Madrid",
    "sg:orig_category":"Plomeros",
    "sg:phone":"+34 914 76 00 83",
    "sg:postcode":"28026",
    "sg:province":"Madrid",
    "wof:name":"Chantal Martin Luis",
    "wof:placetype":"venue"
},
  "geometry": {"coordinates":[-3.7090480328,40.3862991333],"type":"Point"}
}