{
  "type": "Feature",
  "properties": {
    "addr:full":"Ptda Llobatera (la), 114 Llobatera Valencia 46190",
    "addr:housenumber":"114",
    "addr:postcode":"46190",
    "addr:street":"Ptda Llobatera La",
    "iso:country":"ES",
    "sg:address":"Ptda Llobatera (la), 114",
    "sg:city":"Llobatera",
    "sg:orig_category":"Transportes Por V\u00cdas Navegables",
    "sg:phone":"+34 962 13 31 50",
    "sg:postcode":"46190",
    "sg:province":"Valencia",
    "wof:name":"Perez Contreras Francisco",
    "wof:placetype":"venue"
},
  "geometry": {"coordinates":[-0.5698940158,39.5458450317],"type":"Point"}
}