{
  "type": "Feature",
  "properties": {
    "iso:country":"ES",
    "sg:address":"Calle de Fernando El Catolico, 6",
    "sg:city":"Madrid",
    "sg:orig_category":"Librer\u00cdas",
    "sg:phone":"+34 914 46 63 38",
    "sg:postcode":"28015",
    "sg:province":"Madrid",
    "wof:name":"Duque Mu\u00f1oz Fuencisla",
    "wof:placetype":"venue"
},
  "geometry": {"coordinates":[-3.7066140175,40.4339752197],"type":"Point"}
}