{
  "type": "Feature",
  "properties": {
    "addr:full":"Calle de Valverde, 15 Cadiz C\u00e1diz 11004",
    "addr:housenumber":"15",
    "addr:postcode":"11004",
    "addr:street":"Calle De Valverde",
    "iso:country":"ES",
    "sg:address":"Calle de Valverde, 15",
    "sg:city":"Cadiz",
    "sg:orig_category":"Asesor\u00cda De Formaci\u00d3n Y Gesti\u00d3n De Personal",
    "sg:phone":"+34 956 22 30 72",
    "sg:postcode":"11004",
    "sg:province":"C\u00e1diz",
    "wof:name":"Rojas Garcia Jose Luis",
    "wof:placetype":"venue"
},
  "geometry": {"coordinates":[-6.2966442108,36.5327377319],"type":"Point"}
}