{
  "type": "Feature",
  "properties": {
    "iso:country":"ES",
    "sg:address":"Carrer de Buenos Aires, 28",
    "sg:city":"Barcelona",
    "sg:orig_category":"Psic\u00d3logos",
    "sg:phone":"+34 934 30 61 89",
    "sg:postcode":"08036",
    "sg:province":"Barcelona",
    "wof:name":"Deredinger Gaynor Maria Elisa",
    "wof:placetype":"venue"
},
  "geometry": {"coordinates":[2.1464450359,41.391784668],"type":"Point"}
}