{
  "type": "Feature",
  "properties": {
    "addr:full":"Calle de Cardenal Cisneros, 31 Coria C\u00e1ceres 10800",
    "addr:housenumber":"31",
    "addr:postcode":"10800",
    "addr:street":"Calle De Cardenal Cisneros;Ca\u0301Ceres",
    "iso:country":"ES",
    "sg:address":"Calle de Cardenal Cisneros, 31",
    "sg:city":"Coria",
    "sg:orig_category":"Asesor\u00cda Sobre Comunicaci\u00d3n De Empresas",
    "sg:phone":"+34 927 50 02 09",
    "sg:postcode":"10800",
    "sg:province":"C\u00e1ceres",
    "wof:name":"Centro Fiscal Contable Coria S.l.",
    "wof:placetype":"venue"
},
  "geometry": {"coordinates":[-6.5403738022,39.9894943237],"type":"Point"}
}