{
  "type": "Feature",
  "properties": {
    "addr:full":"Calle de Leganes, 5 Getafe Madrid 28901",
    "addr:housenumber":"5",
    "addr:postcode":"28901",
    "addr:street":"Calle De Leganes",
    "iso:country":"ES",
    "sg:address":"Calle de Leganes, 5",
    "sg:city":"Getafe",
    "sg:orig_category":"Peluquer\u00cdas, Peluquer\u00cda Mixta",
    "sg:phone":"+34 916 95 84 50",
    "sg:postcode":"28901",
    "sg:province":"Madrid",
    "wof:name":"Peluqueria Loram S.l.",
    "wof:placetype":"venue"
},
  "geometry": {"coordinates":[-3.7345924377,40.3074493408],"type":"Point"}
}