{
  "type": "Feature",
  "properties": {
    "addr:full":"Calle de Izaro, S/n Andra Mari Vizcaya 48991",
    "addr:housenumber":"s / n",
    "addr:postcode":"48991",
    "addr:street":"Calle De Izaro",
    "iso:country":"ES",
    "sg:address":"Calle de Izaro, S/n",
    "sg:city":"Andra Mari",
    "sg:orig_category":"Centros De Educaci\u00d3n Especial",
    "sg:phone":"+34 944 30 74 26",
    "sg:postcode":"48991",
    "sg:province":"Vizcaya",
    "wof:name":"Ayuntamiento De Getxo",
    "wof:placetype":"venue"
},
  "geometry": {"coordinates":[-3.0027630329,43.3574790955],"type":"Point"}
}