{
  "type": "Feature",
  "properties": {
    "addr:full":"Calle de Cadenas, 4 Fuente El Saz De Jarama Madrid 28140",
    "addr:housenumber":"4",
    "addr:postcode":"28140",
    "addr:street":"Calle De Cadenas",
    "iso:country":"ES",
    "sg:address":"Calle de Cadenas, 4",
    "sg:city":"Fuente El Saz De Jarama",
    "sg:orig_category":"Formaci\u00d3n A Distancia, Por Correspondencia",
    "sg:phone":"+34 916 20 15 53",
    "sg:postcode":"28140",
    "sg:province":"Madrid",
    "wof:name":"Largo Guerreiro Milagros",
    "wof:placetype":"venue"
},
  "geometry": {"coordinates":[-3.5306766033,40.6316299438],"type":"Point"}
}