{
  "type": "Feature",
  "properties": {
    "iso:country":"ES",
    "sg:address":"Calle de Sanchez Llevot, 12",
    "sg:city":"Alba Tormes",
    "sg:orig_category":"Promotores Constructores",
    "sg:phone":"+34 923 30 09 27",
    "sg:postcode":"37800",
    "sg:province":"Salamanca",
    "wof:name":"Construcciones Justo Gomez Sanchez",
    "wof:placetype":"venue"
},
  "geometry": {"coordinates":[-5.5136489868,40.8270606995],"type":"Point"}
}