{
  "type": "Feature",
  "properties": {
    "addr:full":"Calle de San Lorenzo, 6 Donostia-san Sebastian Guip\u00f9zcoa 20003",
    "addr:housenumber":"6",
    "addr:postcode":"20003",
    "addr:street":"Calle De San Lorenzo",
    "iso:country":"ES",
    "sg:address":"Calle de San Lorenzo, 6",
    "sg:city":"Donostia-san Sebastian",
    "sg:orig_category":"Asociaciones, Organismos Culturales Y Socioeducativos",
    "sg:phone":"+34 943 43 18 81",
    "sg:postcode":"20003",
    "sg:province":"Guip\u00f9zcoa",
    "sg:website":"www.blason.es.vg",
    "wof:name":"Urreizti Aguirre Pilar",
    "wof:placetype":"venue"
},
  "geometry": {"coordinates":[-1.9834760427,43.3232383728],"type":"Point"}
}