{
  "type": "Feature",
  "properties": {
    "addr:full":"Calle de Ramirez De Prado, 8 Madrid Madrid 28045",
    "addr:housenumber":"8",
    "addr:postcode":"madrid;28045",
    "addr:street":"Calle De Ramirez De Prado",
    "iso:country":"ES",
    "sg:address":"Calle de Ramirez De Prado, 8",
    "sg:city":"Madrid",
    "sg:orig_category":"Centros Empresariales",
    "sg:phone":"+34 915 28 55 07",
    "sg:postcode":"28045",
    "sg:province":"Madrid",
    "sg:website":"www.aetcm.es",
    "wof:name":"Asociacion Espa\u00f1ola De Tecnico De Cerveza Y Malta",
    "wof:placetype":"venue"
},
  "geometry": {"coordinates":[-3.686671257,40.3992424011],"type":"Point"}
}