{
  "type": "Feature",
  "properties": {
    "addr:full":"Carrer de Ferran De Querol (de), 11 Torredembarra Tarragona 43830",
    "addr:housenumber":"11",
    "addr:postcode":"43830",
    "addr:street":"Carrer De Ferran De Querol De",
    "iso:country":"ES",
    "sg:address":"Carrer de Ferran De Querol (de), 11",
    "sg:city":"Torredembarra",
    "sg:orig_category":"Molduras, Junquillos, Listones Y Molduras Perforadas",
    "sg:phone":"+34 977 13 00 95",
    "sg:postcode":"43830",
    "sg:province":"Tarragona",
    "wof:name":"Moyano Perez C.b.",
    "wof:placetype":"venue"
},
  "geometry": {"coordinates":[1.4022419453,41.1425590515],"type":"Point"}
}