{
  "type": "Feature",
  "properties": {
    "addr:full":"Carrer de Verge Del Roser, 3 Ondara Alicante 03760",
    "addr:housenumber":"3",
    "addr:postcode":"03760",
    "addr:street":"Carrer De Verge Del Roser",
    "iso:country":"ES",
    "sg:address":"Carrer de Verge Del Roser, 3",
    "sg:city":"Ondara",
    "sg:orig_category":"Caf\u00c9s, Bares, Cervecer\u00cdas",
    "sg:phone":"+34 965 76 75 35",
    "sg:postcode":"03760",
    "sg:province":"Alicante",
    "wof:name":"B-mariblas S.l.",
    "wof:placetype":"venue"
},
  "geometry": {"coordinates":[0.0172049999,38.8265914917],"type":"Point"}
}