{
  "type": "Feature",
  "properties": {
    "iso:country":"ES",
    "sg:address":"Calle de Tintoreros, 24",
    "sg:city":"Trujillo",
    "sg:orig_category":"Pod\u00d3logos: Pedicuros",
    "sg:phone":"+34 927 32 17 66",
    "sg:postcode":"10200",
    "sg:province":"C\u00e1ceres",
    "wof:name":"Oliva Fabian Sonia",
    "wof:placetype":"venue"
},
  "geometry": {"coordinates":[-5.8790478706,39.4582519531],"type":"Point"}
}