{
  "type": "Feature",
  "properties": {
    "addr:full":"Av Catalunya, 46 Valls Tarragona 43800",
    "addr:housenumber":"46",
    "addr:postcode":"43800",
    "addr:street":"Av Catalunya",
    "iso:country":"ES",
    "sg:address":"Av Catalunya, 46",
    "sg:city":"Valls",
    "sg:orig_category":"Agencias Y Agentes Comerciales, Representantes",
    "sg:phone":"+34 977 60 01 38",
    "sg:postcode":"43800",
    "sg:province":"Tarragona",
    "wof:name":"Sanchez Sarto Josep",
    "wof:placetype":"venue"
},
  "geometry": {"coordinates":[1.2496119738,41.291179657],"type":"Point"}
}