{
  "type": "Feature",
  "properties": {
    "iso:country":"ES",
    "sg:address":"Calle de Calderetas, 16",
    "sg:city":"S. Bartolome",
    "sg:orig_category":"Florister\u00cdas",
    "sg:phone":"+34 928 52 03 89",
    "sg:postcode":"35550",
    "sg:province":"Las Palmas",
    "wof:name":"Rocio Santana Jose",
    "wof:placetype":"venue"
},
  "geometry": {"coordinates":[-13.6125545502,29.0021286011],"type":"Point"}
}