{
  "type": "Feature",
  "properties": {
    "iso:country":"ES",
    "sg:address":"Av Pais Valencia, 25",
    "sg:city":"Elche",
    "sg:orig_category":"Peluqueros: De Se\u00d1oras",
    "sg:phone":"+34 965 44 31 52",
    "sg:postcode":"03201",
    "sg:province":"Alicante",
    "wof:name":"Agullo Olmos Bibiana Antonia",
    "wof:placetype":"venue"
},
  "geometry": {"coordinates":[-0.7005025148,38.2678108215],"type":"Point"}
}