{
  "type": "Feature",
  "properties": {
    "iso:country":"ES",
    "sg:address":"Calle de Arriba (de), 34",
    "sg:city":"Pedro Bernardo",
    "sg:orig_category":"Bancos",
    "sg:phone":"+34 920 38 71 99",
    "sg:postcode":"05470",
    "sg:province":"\u00c1vila",
    "wof:name":"Auna Telecomunicaciones S.a.u.",
    "wof:placetype":"venue"
},
  "geometry": {"coordinates":[-4.9126267433,40.2436485291],"type":"Point"}
}