{
  "type": "Feature",
  "properties": {
    "iso:country":"ES",
    "sg:address":"Avda Do Parque, 54",
    "sg:city":"Silleda",
    "sg:orig_category":"Electricidad: Instaladores",
    "sg:phone":"+34 986 58 10 02",
    "sg:postcode":"36540",
    "sg:province":"Pontevedra",
    "wof:name":"Reparaciones Vtf S.l.",
    "wof:placetype":"venue"
},
  "geometry": {"coordinates":[-8.2473487854,42.6961212158],"type":"Point"}
}