{
  "type": "Feature",
  "properties": {
    "iso:country":"ES",
    "sg:address":"Carrer de Bartomeu Rossello, 9",
    "sg:city":"Palma",
    "sg:orig_category":"Centros Empresariales",
    "sg:phone":"+34 971 28 13 26",
    "sg:postcode":"07014",
    "sg:province":"Islas Baleares",
    "wof:name":"Bright M. Production Sl",
    "wof:placetype":"venue"
},
  "geometry": {"coordinates":[2.6317210197,39.5726623535],"type":"Point"}
}