{
  "type": "Feature",
  "properties": {
    "iso:country":"ES",
    "sg:address":"Carr Arxiver Mossen Masdeu, 8",
    "sg:city":"Sant Joan De Les Abadesses",
    "sg:orig_category":"Molduras, Junquillos, Listones Y Molduras Perforadas",
    "sg:phone":"+34 972 72 10 99",
    "sg:postcode":"17860",
    "sg:province":"Girona",
    "wof:name":"Huertas Lopez Jose",
    "wof:placetype":"venue"
},
  "geometry": {"coordinates":[2.2868890762,42.2336006165],"type":"Point"}
}