{
  "type": "Feature",
  "properties": {
    "addr:full":"Calle de Huertos Familiares, 1 S. Isidro Alicante 03349",
    "addr:housenumber":"1",
    "addr:postcode":"03349",
    "addr:street":"Calle De Huertos Familiares;S. Isidro Alicante",
    "iso:country":"ES",
    "sg:address":"Calle de Huertos Familiares, 1",
    "sg:city":"S. Isidro",
    "sg:classifiers":[
        {
            "category":"Manufacturing",
            "subcategory":"Building Materials",
            "type":"Manufacturing & Wholesale Goods"
        }
    ],
    "sg:phone":"+34 965 48 65 10",
    "sg:postcode":"03349",
    "sg:province":"Alicante",
    "sg:tags":[
        "de",
        "industrial",
        "alquiler"
    ],
    "wof:name":"Josefer S.l.",
    "wof:placetype":"venue"
},
  "geometry": {"coordinates":[-0.836006999,38.1773338318],"type":"Point"}
}