{
  "type": "Feature",
  "properties": {
    "iso:country":"ES",
    "sg:address":"Santa Icia, 42",
    "sg:city":"Moras",
    "sg:orig_category":"Teatros Y Salas De Espect\u00c1culos",
    "sg:phone":"+34 981 64 50 80",
    "sg:postcode":"15690",
    "sg:province":"La Coru\u00f1a",
    "wof:name":"Ancora Produccions S.l.",
    "wof:placetype":"venue"
},
  "geometry": {"coordinates":[-8.468788147,43.288974762],"type":"Point"}
}