{
  "type": "Feature",
  "properties": {
    "iso:country":"ES",
    "sg:address":"Calle de Berrocal, 3",
    "sg:city":"Madrid",
    "sg:orig_category":"Guarder\u00cdas",
    "sg:phone":"+34 917 23 50 70",
    "sg:postcode":"28021",
    "sg:province":"Madrid",
    "wof:name":"Amaula Ense\u00f1anza S.l.",
    "wof:placetype":"venue"
},
  "geometry": {"coordinates":[-3.6770737171,40.3470039368],"type":"Point"}
}