{
  "type": "Feature",
  "properties": {
    "iso:country":"ES",
    "sg:address":"Camino Ancho, 5",
    "sg:city":"Villadangos Paramo",
    "sg:orig_category":"Panader\u00cdas, Pasteler\u00cdas, Boller\u00cda Industriale (fabricaci\u00d3n, Al Por Mayor)",
    "sg:phone":"+34 987 39 01 13",
    "sg:postcode":"24392",
    "sg:province":"Le\u00f3n",
    "wof:name":"Garcia Burgo Jose Marcos",
    "wof:placetype":"venue"
},
  "geometry": {"coordinates":[-5.7671308517,42.5188827515],"type":"Point"}
}