{
  "type": "Feature",
  "properties": {
    "iso:country":"ES",
    "sg:address":"Calle de Astilleros, General, 74",
    "sg:city":"Melilla",
    "sg:orig_category":"Ense\u00d1anza Secundaria: Colegios Y Escuelas Privadas",
    "sg:phone":"+34 952 69 64 40",
    "sg:postcode":"52006",
    "sg:province":"Melilla",
    "wof:name":"Apa Del Instituto De Formacion Profesional De Meli",
    "wof:placetype":"venue"
},
  "geometry": {"coordinates":[-2.9365296364,35.2734718323],"type":"Point"}
}