{
  "type": "Feature",
  "properties": {
    "addr:full":"Avda Granada, 8 Santa Pola Alicante 03130",
    "addr:housenumber":"8",
    "addr:postcode":"03130",
    "addr:street":"Avda Granada",
    "iso:country":"ES",
    "sg:address":"Avda Granada, 8",
    "sg:city":"Santa Pola",
    "sg:orig_category":"Restaurantes",
    "sg:phone":"+34 966 69 34 95",
    "sg:postcode":"03130",
    "sg:province":"Alicante",
    "wof:name":"Guillen Exposito Juan",
    "wof:placetype":"venue"
},
  "geometry": {"coordinates":[-0.5628769994,38.1913528442],"type":"Point"}
}