{
  "type": "Feature",
  "properties": {
    "iso:country":"ES",
    "sg:address":"Carr Constitucio, 25",
    "sg:city":"Benetusser",
    "sg:orig_category":"Telas Y Sedas (al Por Menor)",
    "sg:phone":"+34 963 75 05 77",
    "sg:postcode":"46910",
    "sg:province":"Valencia",
    "wof:name":"Mas Asencio Francisco",
    "wof:placetype":"venue"
},
  "geometry": {"coordinates":[-0.3939769864,39.4224777222],"type":"Point"}
}