{
  "type": "Feature",
  "properties": {
    "iso:country":"ES",
    "sg:address":"Calle de Historiador Juan Torres Fontes, 21",
    "sg:city":"Infante Juan Manuel",
    "sg:orig_category":"Abogados",
    "sg:phone":"+34 968 26 01 94",
    "sg:postcode":"30011",
    "sg:province":"Murcia",
    "wof:name":"Ruiz Alarcon Antonio",
    "wof:placetype":"venue"
},
  "geometry": {"coordinates":[-1.1200890541,37.9750785828],"type":"Point"}
}