{
  "type": "Feature",
  "properties": {
    "addr:full":"Avda Blas Infante (de), 29 Lucena C\u00f3rdoba 14900",
    "addr:housenumber":"29",
    "addr:postcode":"14900",
    "addr:street":"Avda Blas Infante De",
    "iso:country":"ES",
    "sg:address":"Avda Blas Infante (de), 29",
    "sg:city":"Lucena",
    "sg:orig_category":"Maquinaria Para Industrias Diversas",
    "sg:phone":"+34 957 51 66 40",
    "sg:postcode":"14900",
    "sg:province":"C\u00f3rdoba",
    "wof:name":"Requerey Luna Francisco Jose",
    "wof:placetype":"venue"
},
  "geometry": {"coordinates":[-4.4740638733,37.4099960327],"type":"Point"}
}