{
  "type": "Feature",
  "properties": {
    "iso:country":"ES",
    "sg:address":"Avda Barrie De La Maza, 7",
    "sg:city":"Sada",
    "sg:orig_category":"Confecci\u00d3n De Trajes Para Se\u00d1oras",
    "sg:phone":"+34 981 62 44 92",
    "sg:postcode":"15160",
    "sg:province":"La Coru\u00f1a",
    "wof:name":"Gayoso Pita Jose Miguel",
    "wof:placetype":"venue"
},
  "geometry": {"coordinates":[-8.2543830872,43.3509178162],"type":"Point"}
}