{
  "type": "Feature",
  "properties": {
    "iso:country":"ES",
    "sg:address":"Calle de California, 11",
    "sg:city":"Palmas De Gran Canaria",
    "sg:orig_category":"Maquinaria Para Industrias Diversas",
    "sg:phone":"+34 928 22 62 22",
    "sg:postcode":"35010",
    "sg:province":"Las Palmas",
    "wof:name":"Antonio Martin Deniz S.l.",
    "wof:placetype":"venue"
},
  "geometry": {"coordinates":[-15.4431533813,28.131937027],"type":"Point"}
}