{
  "type": "Feature",
  "properties": {
    "addr:full":"Martin Deunaren Kalea, 3 Azkoitia Guip\u00f9zcoa 20720",
    "addr:housenumber":"3",
    "addr:postcode":"20720",
    "addr:street":"Deunaren Kalea;Guipu\u0300Zcoa",
    "iso:country":"ES",
    "sg:address":"Martin Deunaren Kalea, 3",
    "sg:city":"Azkoitia",
    "sg:orig_category":"Papel Pintado (al Por Menor)",
    "sg:phone":"+34 943 85 30 94",
    "sg:postcode":"20720",
    "sg:province":"Guip\u00f9zcoa",
    "wof:name":"Gabilondo Badiola Manuel",
    "wof:placetype":"venue"
},
  "geometry": {"coordinates":[-2.3134310246,43.1763687134],"type":"Point"}
}