{
  "type": "Feature",
  "properties": {
    "iso:country":"ES",
    "sg:address":"Calle de Ancha, 18",
    "sg:city":"Jerez De La Frontera",
    "sg:orig_category":"Instalaci\u00d3n, Reparaci\u00d3n De Ascensores Y Montacargas",
    "sg:phone":"+34 956 18 05 15",
    "sg:postcode":"11404",
    "sg:province":"C\u00e1diz",
    "wof:name":"Comercial Instaladora De Ascensores Del Sur S.l.l.",
    "wof:placetype":"venue"
},
  "geometry": {"coordinates":[-6.1426901817,36.6880264282],"type":"Point"}
}