{
  "type": "Feature",
  "properties": {
    "iso:country":"ES",
    "sg:address":"Calle de Rodas, 8",
    "sg:city":"Madrid",
    "sg:orig_category":"Confecci\u00d3n De Trajes Para Se\u00d1oras",
    "sg:phone":"+34 914 68 19 38",
    "sg:postcode":"28005",
    "sg:province":"Madrid",
    "wof:name":"Broughton Espinoza Eduardo Gustavo",
    "wof:placetype":"venue"
},
  "geometry": {"coordinates":[-3.7056798935,40.4086265564],"type":"Point"}
}