{
  "type": "Feature",
  "properties": {
    "addr:full":"Calle de Huertas, 1 Coru\u00d1a La Coru\u00f1a 15003",
    "addr:housenumber":"1",
    "addr:postcode":"15003",
    "addr:street":"Calle De Huertas;La Corun\u0303A",
    "iso:country":"ES",
    "sg:address":"Calle de Huertas, 1",
    "sg:city":"Coru\u00d1a",
    "sg:orig_category":"Edici\u00d3n De Diarios, Revistas, Boletines",
    "sg:phone":"+34 981 21 83 10",
    "sg:postcode":"15003",
    "sg:province":"La Coru\u00f1a",
    "wof:name":"Factoria De Informacion S.a.",
    "wof:placetype":"venue"
},
  "geometry": {"coordinates":[-8.4052629471,43.3682022095],"type":"Point"}
}