{
  "type": "Feature",
  "properties": {
    "addr:full":"Calle de Balmes, 18 Palencia Palencia 34004",
    "addr:housenumber":"18",
    "addr:postcode":"34004",
    "addr:street":"Calle De Balmes",
    "iso:country":"ES",
    "sg:address":"Calle de Balmes, 18",
    "sg:city":"Palencia",
    "sg:orig_category":"Negocio De Materiales De Construcci\u00d3n",
    "sg:phone":"+34 979 72 69 12",
    "sg:postcode":"34004",
    "sg:province":"Palencia",
    "wof:name":"Urbon Ceramicas S.l.",
    "wof:placetype":"venue"
},
  "geometry": {"coordinates":[-4.524503231,42.0047569275],"type":"Point"}
}