{
  "type": "Feature",
  "properties": {
    "addr:full":"Avda Coru\u00d1a (da), 208 Lugo Lugo 27003",
    "addr:housenumber":"208",
    "addr:postcode":"27003",
    "addr:street":"Avda Corun\u0303A Da",
    "iso:country":"ES",
    "sg:address":"Avda Coru\u00d1a (da), 208",
    "sg:city":"Lugo",
    "sg:orig_category":"Perfumer\u00cda, Art\u00cdculos De Ba\u00d1o (fabricaci\u00d3n, Al Por Mayor)",
    "sg:phone":"+34 982 25 13 23",
    "sg:postcode":"27003",
    "sg:province":"Lugo",
    "wof:name":"Fernandez Garcia Javier",
    "wof:placetype":"venue"
},
  "geometry": {"coordinates":[-7.5635199547,43.0212936401],"type":"Point"}
}