{
  "type": "Feature",
  "properties": {
    "iso:country":"ES",
    "sg:address":"Rua Benito Corbal, 25",
    "sg:city":"Pontevedra",
    "sg:orig_category":"Ropa Para Ni\u00d1os (al Por Menor)",
    "sg:phone":"+34 986 84 61 66",
    "sg:postcode":"36001",
    "sg:province":"Pontevedra",
    "wof:name":"Stradivarius Espa\u00d1a S.a",
    "wof:placetype":"venue"
},
  "geometry": {"coordinates":[-8.6411056519,42.4304542542],"type":"Point"}
}