{
  "type": "Feature",
  "properties": {
    "iso:country":"ES",
    "sg:address":"La Cellera, 14",
    "sg:city":"Fla\u00e7a",
    "sg:orig_category":"Asociaciones Humanitarias, De Cooperaci\u00d3n, De Acci\u00d3n Social",
    "sg:phone":"+34 972 48 83 78",
    "sg:postcode":"17463",
    "sg:province":"Girona",
    "wof:name":"Fundacio Lethe",
    "wof:placetype":"venue"
},
  "geometry": {"coordinates":[2.9531850815,42.0498008728],"type":"Point"}
}