{
  "type": "Feature",
  "properties": {
    "addr:full":"Calle de General Casta\u00d1os, 15 Madrid Madrid 28004",
    "addr:housenumber":"15",
    "addr:postcode":"madrid;28004",
    "addr:street":"Calle De General Castan\u0303Os",
    "iso:country":"ES",
    "sg:address":"Calle de General Casta\u00d1os, 15",
    "sg:city":"Madrid",
    "sg:orig_category":"Inmobiliaria (agencias)",
    "sg:phone":"+34 913 08 06 74",
    "sg:postcode":"28004",
    "sg:province":"Madrid",
    "wof:name":"Gestion Inmobiliaria Casta\u00f1os S.l",
    "wof:placetype":"venue"
},
  "geometry": {"coordinates":[-3.6935815811,40.4263534546],"type":"Point"}
}