{
  "type": "Feature",
  "properties": {
    "addr:full":"Calle de Antonio Jimenez Ruiz, 27 Malaga M\u00e1laga 29009",
    "addr:housenumber":"27",
    "addr:postcode":"29009",
    "addr:street":"Calle De Antonio Jimenez Ruiz;Ma\u0301Laga",
    "iso:country":"ES",
    "sg:address":"Calle de Antonio Jimenez Ruiz, 27",
    "sg:city":"Malaga",
    "sg:orig_category":"Asociaciones, Organismos Culturales Y Socioeducativos",
    "sg:phone":"+34 952 28 00 43",
    "sg:postcode":"29009",
    "sg:province":"M\u00e1laga",
    "wof:name":"Pe\u00f1a El Sombrero",
    "wof:placetype":"venue"
},
  "geometry": {"coordinates":[-4.4350752831,36.7220420837],"type":"Point"}
}