{
  "type": "Feature",
  "properties": {
    "iso:country":"ES",
    "sg:address":"Calle de Leon Y Castillo, 157",
    "sg:city":"Palmas De Gran Canaria",
    "sg:orig_category":"Arquitectos",
    "sg:phone":"+34 928 29 07 24",
    "sg:postcode":"35004",
    "sg:province":"Las Palmas",
    "wof:name":"Acosta Padron German",
    "wof:placetype":"venue"
},
  "geometry": {"coordinates":[-15.4228744507,28.1169471741],"type":"Point"}
}