{
  "type": "Feature",
  "properties": {
    "addr:full":"Calle de Cortes De Aragon, 62 Zaragoza Zaragoza 50005",
    "addr:housenumber":"62",
    "addr:postcode":"50005",
    "addr:street":"Calle De Cortes De Aragon",
    "iso:country":"ES",
    "sg:address":"Calle de Cortes De Aragon, 62",
    "sg:city":"Zaragoza",
    "sg:orig_category":"Art\u00cdculos De Regalo (al Por Menor)",
    "sg:phone":"+34 976 40 12 42",
    "sg:postcode":"50005",
    "sg:province":"Zaragoza",
    "wof:name":"Agharta S.l.",
    "wof:placetype":"venue"
},
  "geometry": {"coordinates":[-0.8942241073,41.6433792114],"type":"Point"}
}