{
  "type": "Feature",
  "properties": {
    "addr:full":"Calle de Candilejas, S/n Madrid Madrid 28018",
    "addr:housenumber":"s / n",
    "addr:postcode":"28018",
    "addr:street":"Calle De Candilejas",
    "iso:country":"ES",
    "sg:address":"Calle de Candilejas, S/n",
    "sg:city":"Madrid",
    "sg:orig_category":"Juegos Y Juguetes (al Por Menor)",
    "sg:phone":"+34 917 86 33 61",
    "sg:postcode":"28018",
    "sg:province":"Madrid",
    "sg:website":"www.imaginarium.es",
    "wof:name":"Toyspark S.l.",
    "wof:placetype":"venue"
},
  "geometry": {"coordinates":[-3.6608390808,40.3862380981],"type":"Point"}
}