{
  "type": "Feature",
  "properties": {
    "addr:full":"Avda Marca Hispanica, 106 Segur Calafell Tarragona 43882",
    "addr:housenumber":"106",
    "addr:postcode":"43882",
    "addr:street":"Avda Marca Hispanica",
    "iso:country":"ES",
    "sg:address":"Avda Marca Hispanica, 106",
    "sg:city":"Segur Calafell",
    "sg:orig_category":"Promotores Constructores",
    "sg:phone":"+34 977 16 27 21",
    "sg:postcode":"43882",
    "sg:province":"Tarragona",
    "wof:name":"Boni 50 Empresa Constructora S.l.",
    "wof:placetype":"venue"
},
  "geometry": {"coordinates":[1.6160999537,41.2140312195],"type":"Point"}
}