{
  "type": "Feature",
  "properties": {
    "iso:country":"ES",
    "sg:address":"Mere, S/n",
    "sg:city":"Mere",
    "sg:orig_category":"Centros Empresariales",
    "sg:phone":"+34 985 92 57 90",
    "sg:postcode":"33508",
    "sg:province":"Asturias",
    "wof:name":"Cealtra S.a.",
    "wof:placetype":"venue"
},
  "geometry": {"coordinates":[-4.9141168594,43.375705719],"type":"Point"}
}