{
  "type": "Feature",
  "properties": {
    "iso:country":"ES",
    "sg:address":"Pase Don Carmelo, 28",
    "sg:city":"Avila",
    "sg:orig_category":"Asesor\u00cda Sobre Comunicaci\u00d3n De Empresas",
    "sg:phone":"+34 920 22 39 68",
    "sg:postcode":"05001",
    "sg:province":"\u00c1vila",
    "wof:name":"Intro Avila Sl",
    "wof:placetype":"venue"
},
  "geometry": {"coordinates":[-4.6398692131,40.638092041],"type":"Point"}
}