{
  "type": "Feature",
  "properties": {
    "addr:full":"Alde Santa Baia, S/n Santa Baia Ourense 32825",
    "addr:housenumber":"s / n",
    "addr:postcode":"32825",
    "iso:country":"ES",
    "sg:address":"Alde Santa Baia, S/n",
    "sg:city":"Santa Baia",
    "sg:orig_category":"Art\u00cdculos Funerarios (al Por Menor)",
    "sg:phone":"+34 988 49 10 66",
    "sg:postcode":"32825",
    "sg:province":"Ourense",
    "wof:name":"Bugallo Pereiro Jesus",
    "wof:placetype":"venue"
},
  "geometry": {"coordinates":[-7.9481129646,42.2045173645],"type":"Point"}
}