{
  "type": "Feature",
  "properties": {
    "iso:country":"ES",
    "sg:address":"Calle de Antonio De Leyva, 29",
    "sg:city":"Madrid",
    "sg:orig_category":"Electricidad (montaje, Ensamblaje De Componentes)",
    "sg:phone":"+34 915 69 66 12",
    "sg:postcode":"28019",
    "sg:province":"Madrid",
    "wof:name":"Dylan Auto S.l.",
    "wof:placetype":"venue"
},
  "geometry": {"coordinates":[-3.7154073715,40.3936271667],"type":"Point"}
}