{
  "type": "Feature",
  "properties": {
    "iso:country":"ES",
    "sg:address":"Calle de Mayor, 14",
    "sg:city":"Biescas",
    "sg:orig_category":"Molduras, Junquillos, Listones Y Molduras Perforadas",
    "sg:phone":"+34 974 48 50 30",
    "sg:postcode":"22630",
    "sg:province":"Huesca",
    "wof:name":"Hernando Biel Bego\u00f1a",
    "wof:placetype":"venue"
},
  "geometry": {"coordinates":[-0.3186469972,42.6288566589],"type":"Point"}
}