{
  "type": "Feature",
  "properties": {
    "addr:full":"Ctra. Valmadrid, S/n Cartuja Baja Zaragoza 50720",
    "addr:housenumber":"s / n",
    "addr:postcode":"50720",
    "addr:street":"Ctra. Valmadrid;Baja",
    "iso:country":"ES",
    "sg:address":"Ctra. Valmadrid, S/n",
    "sg:city":"Cartuja Baja",
    "sg:orig_category":"Producci\u00d3n, Venta De Productos De Agricultura Biol\u00d3gica",
    "sg:phone":"+34 976 13 18 42",
    "sg:postcode":"50720",
    "sg:province":"Zaragoza",
    "wof:name":"Seral Seral Jose",
    "wof:placetype":"venue"
},
  "geometry": {"coordinates":[-0.8279389739,41.6048736572],"type":"Point"}
}