{
  "type": "Feature",
  "properties": {
    "addr:full":"Avda Giorgeta, 41 Valencia Valencia 46007",
    "addr:housenumber":"41",
    "addr:postcode":"46007",
    "addr:street":"Avda Giorgeta",
    "iso:country":"ES",
    "sg:address":"Avda Giorgeta, 41",
    "sg:city":"Valencia",
    "sg:orig_category":"Comercio De Piezas De Recambio Y De Accesorios De Veh\u00cdculos, Veh\u00cdculos Industriales",
    "sg:phone":"+34 963 41 00 02",
    "sg:postcode":"46007",
    "sg:province":"Valencia",
    "wof:name":"Vasauto S.a.",
    "wof:placetype":"venue"
},
  "geometry": {"coordinates":[-0.3841750026,39.4590148926],"type":"Point"}
}