{
  "type": "Feature",
  "properties": {
    "iso:country":"ES",
    "sg:address":"Calle de Castilla-leon, 14",
    "sg:city":"Barakaldo",
    "sg:orig_category":"Carnicer\u00cdas, Carnicer\u00cdas",
    "sg:phone":"+34 944 38 69 73",
    "sg:postcode":"48901",
    "sg:province":"Vizcaya",
    "wof:name":"Carnicas Pam S.l",
    "wof:placetype":"venue"
},
  "geometry": {"coordinates":[-2.9857161045,43.2953262329],"type":"Point"}
}