{
  "type": "Feature",
  "properties": {
    "iso:country":"ES",
    "sg:address":"Calle de Torrenueva, 33",
    "sg:city":"Ubeda",
    "sg:orig_category":"Tapicer\u00cdas",
    "sg:phone":"+34 953 75 26 04",
    "sg:postcode":"23400",
    "sg:province":"Ja\u00e9n",
    "wof:name":"Cano Martinez Simon",
    "wof:placetype":"venue"
},
  "geometry": {"coordinates":[-3.3712339401,38.0179290771],"type":"Point"}
}