{
  "type": "Feature",
  "properties": {
    "iso:country":"ES",
    "sg:address":"Calle de Fraternidad, S/n",
    "sg:city":"Oviedo",
    "sg:orig_category":"Promotores Constructores",
    "sg:phone":"+34 985 27 65 03",
    "sg:postcode":"33013",
    "sg:province":"Asturias",
    "wof:name":"Promociones Y Construcciones Asturcasa Asturias S.l.",
    "wof:placetype":"venue"
},
  "geometry": {"coordinates":[-5.8665590286,43.3641395569],"type":"Point"}
}