{
  "type": "Feature",
  "properties": {
    "addr:full":"Calle de Francisco De Quevedo, 32 Elda Alicante 03600",
    "addr:housenumber":"32",
    "addr:postcode":"03600",
    "addr:street":"Calle De Francisco De Quevedo",
    "iso:country":"ES",
    "sg:address":"Calle de Francisco De Quevedo, 32",
    "sg:city":"Elda",
    "sg:orig_category":"Zapater\u00cdas",
    "sg:phone":"+34 965 38 11 32",
    "sg:postcode":"03600",
    "sg:province":"Alicante",
    "wof:name":"Rios Pla Pedro",
    "wof:placetype":"venue"
},
  "geometry": {"coordinates":[-0.7846950293,38.476398468],"type":"Point"}
}