{
  "type": "Feature",
  "properties": {
    "addr:full":"Calle de Perez Comend., 21 Malpartida Caceres C\u00e1ceres 10910",
    "addr:housenumber":"21",
    "addr:postcode":"10910",
    "addr:street":"Calle De Perez Comend.;Ca\u0301Ceres",
    "iso:country":"ES",
    "sg:address":"Calle de Perez Comend., 21",
    "sg:city":"Malpartida Caceres",
    "sg:orig_category":"Pod\u00d3logos: Pedicuros",
    "sg:phone":"+34 927 27 55 98",
    "sg:postcode":"10910",
    "sg:province":"C\u00e1ceres",
    "wof:name":"Gomez Leo Isabel Maria",
    "wof:placetype":"venue"
},
  "geometry": {"coordinates":[-6.5076742172,39.4432449341],"type":"Point"}
}