{
  "type": "Feature",
  "properties": {
    "iso:country":"ES",
    "sg:address":"La Plaza, S/n",
    "sg:city":"Checa",
    "sg:orig_category":"Empresarios",
    "sg:phone":"+34 949 83 61 41",
    "sg:postcode":"19310",
    "sg:province":"Guadalajara",
    "wof:name":"Samper Lopez Antonio",
    "wof:placetype":"venue"
},
  "geometry": {"coordinates":[-1.7915079594,40.5847702026],"type":"Point"}
}