{
  "type": "Feature",
  "properties": {
    "iso:country":"ES",
    "sg:address":"Calle de San Blas, 9",
    "sg:city":"Moraleja",
    "sg:orig_category":"Empresarios",
    "sg:phone":"+34 927 51 54 31",
    "sg:postcode":"10840",
    "sg:province":"C\u00e1ceres",
    "wof:name":"Gonzalez Garcia Florentino",
    "wof:placetype":"venue"
},
  "geometry": {"coordinates":[-6.659072876,40.0648155212],"type":"Point"}
}