{
  "type": "Feature",
  "properties": {
    "iso:country":"ES",
    "sg:address":"Comi\u00f1os, S/n",
    "sg:city":"Covas",
    "sg:orig_category":"Fabricaci\u00d3n De Harinas, S\u00c9molas, Productos De Elaboraci\u00d3n Del Grano",
    "sg:phone":"+34 982 56 34 32",
    "sg:postcode":"27861",
    "sg:province":"Lugo",
    "wof:name":"Hermanos Rego Sierra S.l.",
    "wof:placetype":"venue"
},
  "geometry": {"coordinates":[-7.6583218575,43.691734314],"type":"Point"}
}