{
  "type": "Feature",
  "properties": {
    "addr:full":"Carrer de Anselm Clave, 11 Sant Pere De Torello Barcelona 08572",
    "addr:housenumber":"11",
    "addr:postcode":"08572",
    "addr:street":"Carrer De Anselm Clave",
    "iso:country":"ES",
    "sg:address":"Carrer de Anselm Clave, 11",
    "sg:city":"Sant Pere De Torello",
    "sg:orig_category":"Cepiller\u00cdas",
    "sg:phone":"+34 938 58 41 98",
    "sg:postcode":"08572",
    "sg:province":"Barcelona",
    "wof:name":"Miarons Devesa Jaime",
    "wof:placetype":"venue"
},
  "geometry": {"coordinates":[2.2954549789,42.0752716064],"type":"Point"}
}