{
  "type": "Feature",
  "properties": {
    "iso:country":"ES",
    "sg:address":"Ctra. San Roman, Km. 0009,0",
    "sg:city":"S. Roman Montes",
    "sg:orig_category":"Alimentaci\u00d3n General (al Por Mayor)",
    "sg:phone":"+34 925 88 71 34",
    "sg:postcode":"45646",
    "sg:province":"Toledo",
    "wof:name":"Puntada 3 S.l.",
    "wof:placetype":"venue"
},
  "geometry": {"coordinates":[-4.7319440842,40.0716743469],"type":"Point"}
}