{
  "type": "Feature",
  "properties": {
    "addr:full":"Calle de Leon, 26 Arganda Madrid 28500",
    "addr:housenumber":"26",
    "addr:postcode":"28500",
    "addr:street":"Calle De Leon",
    "iso:country":"ES",
    "sg:address":"Calle de Leon, 26",
    "sg:city":"Arganda",
    "sg:orig_category":"Delegados, Agentes De Tr\u00c1nsito, Auxiliares De Transporte Internacional",
    "sg:phone":"+34 918 75 70 72",
    "sg:postcode":"28500",
    "sg:province":"Madrid",
    "wof:name":"Bamentrans Logistica S.l.",
    "wof:placetype":"venue"
},
  "geometry": {"coordinates":[-3.4568650723,40.3072509766],"type":"Point"}
}