{
  "type": "Feature",
  "properties": {
    "addr:full":"Avda Grandes Playas, S/n Corralejo Playa Las Palmas 35660",
    "addr:housenumber":"s / n",
    "addr:postcode":"35660",
    "addr:street":"Avda Grandes Playas;Playa Las Palmas",
    "iso:country":"ES",
    "sg:address":"Avda Grandes Playas, S/n",
    "sg:city":"Corralejo Playa",
    "sg:orig_category":"Alquiler De Veh\u00cdculos: Turismos Y Utilitarios",
    "sg:phone":"+34 928 86 65 59",
    "sg:postcode":"35660",
    "sg:province":"Las Palmas",
    "sg:website":"www.cicar.com",
    "wof:name":"Canary Islands Car S.l.",
    "wof:placetype":"venue"
},
  "geometry": {"coordinates":[-13.8690338135,28.7329559326],"type":"Point"}
}