{
  "type": "Feature",
  "properties": {
    "addr:full":"Calle de Canfranc (casetas), 1 Casetas Zaragoza 50620",
    "addr:housenumber":"1",
    "addr:postcode":"50620",
    "addr:street":"Calle De Canfranc Casetas",
    "iso:country":"ES",
    "sg:address":"Calle de Canfranc (casetas), 1",
    "sg:city":"Casetas",
    "sg:orig_category":"Cr\u00cda De Animales",
    "sg:phone":"+34 976 77 10 81",
    "sg:postcode":"50620",
    "sg:province":"Zaragoza",
    "wof:name":"Gual Borruel Jose",
    "wof:placetype":"venue"
},
  "geometry": {"coordinates":[-1.0322844982,41.7186965942],"type":"Point"}
}