{
  "type": "Feature",
  "properties": {
    "addr:full":"Avda Sinforiano Madro\u00d1ero, 15 Badajoz Badajoz 06011",
    "addr:housenumber":"15",
    "addr:postcode":"06011",
    "addr:street":"Avda Sinforiano Madron\u0303Ero",
    "iso:country":"ES",
    "sg:address":"Avda Sinforiano Madro\u00d1ero, 15",
    "sg:city":"Badajoz",
    "sg:orig_category":"Calzados Ortop\u00c9dicos",
    "sg:phone":"+34 924 26 13 71",
    "sg:postcode":"06011",
    "sg:province":"Badajoz",
    "wof:name":"Lopez Araguete Miguel",
    "wof:placetype":"venue"
},
  "geometry": {"coordinates":[-6.9877457619,38.8686103821],"type":"Point"}
}