{
  "type": "Feature",
  "properties": {
    "addr:full":"Calle de San Jose, S/n Cangas Pontevedra 36940",
    "addr:housenumber":"s / n",
    "addr:postcode":"36940",
    "addr:street":"Calle De San Jose",
    "iso:country":"ES",
    "sg:address":"Calle de San Jose, S/n",
    "sg:city":"Cangas",
    "sg:orig_category":"Centros P\u00dablicos De Formaci\u00d3n Profesional Y T\u00c9cnica",
    "sg:phone":"+34 986 30 72 54",
    "sg:postcode":"36940",
    "sg:province":"Pontevedra",
    "wof:name":"Colegio Provincial De Procuradores",
    "wof:placetype":"venue"
},
  "geometry": {"coordinates":[-8.8184690475,42.2742500305],"type":"Point"}
}