{
  "type": "Feature",
  "properties": {
    "addr:full":"Calle de Fomento, 1 Cangas Pontevedra 36940",
    "addr:housenumber":"1",
    "addr:postcode":"36940",
    "addr:street":"Calle De Fomento",
    "iso:country":"ES",
    "sg:address":"Calle de Fomento, 1",
    "sg:city":"Cangas",
    "sg:orig_category":"Ense\u00d1anza: Profesiones Art\u00cdsticas",
    "sg:phone":"+34 986 30 53 11",
    "sg:postcode":"36940",
    "sg:province":"Pontevedra",
    "wof:name":"Escola De Expresion Abra S.l.",
    "wof:placetype":"venue"
},
  "geometry": {"coordinates":[-8.7860126495,42.2599220276],"type":"Point"}
}