{
  "type": "Feature",
  "properties": {
    "iso:country":"ES",
    "sg:address":"Calle de Republica Nicaragua, 2",
    "sg:city":"Badajoz",
    "sg:orig_category":"Peluqueros: De Se\u00d1oras",
    "sg:phone":"+34 924 22 12 03",
    "sg:postcode":"06011",
    "sg:province":"Badajoz",
    "wof:name":"Santos Sotoca Pilar",
    "wof:placetype":"venue"
},
  "geometry": {"coordinates":[-6.9855642319,38.8743171692],"type":"Point"}
}