{
  "type": "Feature",
  "properties": {
    "iso:country":"ES",
    "sg:address":"Ctra Matadepera, 104",
    "sg:city":"Terrassa",
    "sg:orig_category":"Hilaturas, Hilos Y Actividades Relacionadas",
    "sg:phone":"+34 937 35 71 59",
    "sg:postcode":"08226",
    "sg:province":"Barcelona",
    "wof:name":"Ambros Materials Per La Construccio S.c.",
    "wof:placetype":"venue"
},
  "geometry": {"coordinates":[2.0182614326,41.5816268921],"type":"Point"}
}