{
  "type": "Feature",
  "properties": {
    "iso:country":"ES",
    "sg:address":"Poli Nava (la), S/n",
    "sg:city":"Tafalla",
    "sg:orig_category":"Imprenta",
    "sg:phone":"+34 948 74 10 12",
    "sg:postcode":"31300",
    "sg:province":"Navarra",
    "wof:name":"Imprenta Ainzua S.l.",
    "wof:placetype":"venue"
},
  "geometry": {"coordinates":[-1.674399972,42.5275344849],"type":"Point"}
}