{
  "type": "Feature",
  "properties": {
    "iso:country":"ES",
    "sg:address":"Calle de Valderrey, 10",
    "sg:city":"Madrid",
    "sg:orig_category":"Promotores Constructores",
    "sg:phone":"+34 913 16 44 47",
    "sg:postcode":"28035",
    "sg:province":"Madrid",
    "wof:name":"Proenbe S.l.",
    "wof:placetype":"venue"
},
  "geometry": {"coordinates":[-3.7211620808,40.4677391052],"type":"Point"}
}