{
  "type": "Feature",
  "properties": {
    "addr:full":"Calle de La Rioja, 3 Madrid Madrid 28042",
    "addr:housenumber":"3",
    "addr:postcode":"28042",
    "addr:street":"Calle De La Rioja",
    "iso:country":"ES",
    "sg:address":"Calle de La Rioja, 3",
    "sg:city":"Madrid",
    "sg:orig_category":"Inform\u00c1tica (estudios, Servicios, Asesor\u00cda, Formaci\u00d3n)",
    "sg:phone":"+34 902 19 78 75",
    "sg:postcode":"28042",
    "sg:province":"Madrid",
    "sg:website":"www.mira-me.net",
    "wof:name":"Mirame Internet Resources And Media Engenieering S.l.",
    "wof:placetype":"venue"
},
  "geometry": {"coordinates":[-3.592394352,40.4547576904],"type":"Point"}
}