{
  "type": "Feature",
  "properties": {
    "iso:country":"ES",
    "sg:address":"Pol Ind Plasencia, 37",
    "sg:city":"Plasencia",
    "sg:orig_category":"Mec\u00c1nico Del Autom\u00d3vil",
    "sg:phone":"+34 927 42 38 78",
    "sg:postcode":"10600",
    "sg:province":"C\u00e1ceres",
    "wof:name":"Salgados C.b.",
    "wof:placetype":"venue"
},
  "geometry": {"coordinates":[-6.0898518562,40.0299453735],"type":"Point"}
}