{
  "type": "Feature",
  "properties": {
    "addr:full":"Plaz Santa Teresa, 14 Avila \u00c1vila 05001",
    "addr:housenumber":"14",
    "addr:postcode":"05001",
    "addr:street":"Santa Teresa;A\u0301Vila",
    "iso:country":"ES",
    "sg:address":"Plaz Santa Teresa, 14",
    "sg:city":"Avila",
    "sg:orig_category":"Arquitectos",
    "sg:phone":"+34 920 25 73 79",
    "sg:postcode":"05001",
    "sg:province":"\u00c1vila",
    "wof:name":"Barroso Gonzalez Sonsoles",
    "wof:placetype":"venue"
},
  "geometry": {"coordinates":[-4.6962537766,40.6540794373],"type":"Point"}
}