{
  "type": "Feature",
  "properties": {
    "addr:full":"Calle de General Tamayo, 6 Almeria Almer\u00eda 04004",
    "addr:housenumber":"6",
    "addr:postcode":"04004",
    "addr:street":"Calle De General Tamayo",
    "iso:country":"ES",
    "sg:address":"Calle de General Tamayo, 6",
    "sg:city":"Almeria",
    "sg:orig_category":"Lencer\u00cda Femenina, Corseter\u00cda, Trajes De Ba\u00d1o (al Por Menor)",
    "sg:phone":"+34 950 23 76 95",
    "sg:postcode":"04004",
    "sg:province":"Almer\u00eda",
    "wof:name":"Deseda C.b.",
    "wof:placetype":"venue"
},
  "geometry": {"coordinates":[-2.4623439312,36.8371429443],"type":"Point"}
}