{
  "type": "Feature",
  "properties": {
    "iso:country":"ES",
    "sg:address":"Pla\u00c7 Milagrosa, 1",
    "sg:city":"Mareny De Barraquetes",
    "sg:orig_category":"Cooperativas Agr\u00cdcolas",
    "sg:phone":"+34 961 76 21 06",
    "sg:postcode":"46419",
    "sg:province":"Valencia",
    "wof:name":"Sociedad De Labradores Y Jornaleros Mareny Agricola",
    "wof:placetype":"venue"
},
  "geometry": {"coordinates":[-0.2640939951,39.2566146851],"type":"Point"}
}