{
  "type": "Feature",
  "properties": {
    "iso:country":"ES",
    "sg:address":"Calle de Jamilena, 10",
    "sg:city":"Jaen",
    "sg:orig_category":"Mec\u00c1nico Del Autom\u00d3vil",
    "sg:phone":"+34 953 28 42 20",
    "sg:postcode":"23009",
    "sg:province":"Ja\u00e9n",
    "wof:name":"Lopez Ortega Manuel",
    "wof:placetype":"venue"
},
  "geometry": {"coordinates":[-3.780258894,37.8023147583],"type":"Point"}
}