{
  "type": "Feature",
  "properties": {
    "iso:country":"ES",
    "sg:address":"Ptda Rafalcaid, 55",
    "sg:city":"Grao Gandia",
    "sg:orig_category":"Molduras, Junquillos, Listones Y Molduras Perforadas",
    "sg:phone":"+34 962 84 27 33",
    "sg:postcode":"46730",
    "sg:province":"Valencia",
    "wof:name":"Monzo Borras Jose Manuel",
    "wof:placetype":"venue"
},
  "geometry": {"coordinates":[-0.1664949954,38.9994888306],"type":"Point"}
}