{
  "type": "Feature",
  "properties": {
    "iso:country":"ES",
    "sg:address":"Calle de Gerardo Mates, 11",
    "sg:city":"Caudete",
    "sg:orig_category":"Arquitectos",
    "sg:phone":"+34 965 82 80 19",
    "sg:postcode":"02660",
    "sg:province":"Albacete",
    "wof:name":"Marco Albero-arquitectura S.l.",
    "wof:placetype":"venue"
},
  "geometry": {"coordinates":[-0.9878460169,38.7029418945],"type":"Point"}
}