{
  "type": "Feature",
  "properties": {
    "iso:country":"ES",
    "sg:address":"Madrid-valencia, 56",
    "sg:city":"Valverde Jucar",
    "sg:orig_category":"Fabricaci\u00d3n De Cervezas",
    "sg:phone":"+34 969 20 10 54",
    "sg:postcode":"16100",
    "sg:province":"Cuenca",
    "wof:name":"Logispal S.l.",
    "wof:placetype":"venue"
},
  "geometry": {"coordinates":[-2.2207920551,39.7152748108],"type":"Point"}
}