{
  "type": "Feature",
  "properties": {
    "iso:country":"ES",
    "sg:address":"Calle de Calvo Sotelo, 8",
    "sg:city":"Mira",
    "sg:orig_category":"Iglesia Cat\u00d3lica",
    "sg:phone":"+34 969 34 00 88",
    "sg:postcode":"16393",
    "sg:province":"Cuenca",
    "wof:name":"Parroquia Nuestra Se\u00f1ora De La Asuncion",
    "wof:placetype":"venue"
},
  "geometry": {"coordinates":[-1.4398132563,39.719619751],"type":"Point"}
}