{
  "type": "Feature",
  "properties": {
    "iso:country":"ES",
    "sg:address":"Calle de Real, 2",
    "sg:city":"Otura",
    "sg:orig_category":"Estancos",
    "sg:phone":"+34 958 55 51 52",
    "sg:postcode":"18630",
    "sg:province":"Granada",
    "wof:name":"Jimenez Llorente Eusebio",
    "wof:placetype":"venue"
},
  "geometry": {"coordinates":[-3.6345291138,37.0934295654],"type":"Point"}
}