{
  "type": "Feature",
  "properties": {
    "iso:country":"ES",
    "sg:address":"Calle de Juan Ramon Jimenez, 2",
    "sg:city":"Cadiz",
    "sg:orig_category":"Abogados",
    "sg:phone":"+34 956 25 28 10",
    "sg:postcode":"11008",
    "sg:province":"C\u00e1diz",
    "wof:name":"Jare\u00f1o Rodriguez-sanchez Jose Manuel",
    "wof:placetype":"venue"
},
  "geometry": {"coordinates":[-6.2864332199,36.5223083496],"type":"Point"}
}