{
  "type": "Feature",
  "properties": {
    "iso:country":"ES",
    "sg:address":"Cra. Lleida, S/n",
    "sg:city":"Alinya",
    "sg:classifiers":[
        {
            "category":"Taxi",
            "type":"Transportation"
        }
    ],
    "sg:phone":"+34 973 37 00 88",
    "sg:postcode":"25794",
    "sg:province":"Lleida",
    "wof:name":"Costa Gilirribo Federico",
    "wof:placetype":"venue"
},
  "geometry": {"coordinates":[1.3279800415,42.2114143372],"type":"Point"}
}