{
  "type": "Feature",
  "properties": {
    "addr:full":"Calle de Colon, 11 Agudo Ciudad Real 13410",
    "addr:housenumber":"11",
    "addr:postcode":"13410",
    "addr:street":"Calle De Colon",
    "iso:country":"ES",
    "sg:address":"Calle de Colon, 11",
    "sg:city":"Agudo",
    "sg:orig_category":"Cerrajer\u00cda, Ferrallista",
    "sg:phone":"+34 926 73 00 55",
    "sg:postcode":"13410",
    "sg:province":"Ciudad Real",
    "wof:name":"Gentil Ruiz Victoriano",
    "wof:placetype":"venue"
},
  "geometry": {"coordinates":[-4.8694386482,38.9811897278],"type":"Point"}
}