{
  "type": "Feature",
  "properties": {
    "addr:full":"G.v. Corts Catalanes, 717 Barcelona Barcelona 08013",
    "addr:housenumber":"717",
    "addr:postcode":"08013",
    "addr:street":"Catalanes",
    "iso:country":"ES",
    "sg:address":"G.v. Corts Catalanes, 717",
    "sg:city":"Barcelona",
    "sg:orig_category":"Empresarios Y Productoras De Espect\u00c1culos",
    "sg:phone":"+34 932 45 97 85",
    "sg:postcode":"08013",
    "sg:province":"Barcelona",
    "wof:name":"Guedelac Produccio Esdeveniments Artistics",
    "wof:placetype":"venue"
},
  "geometry": {"coordinates":[2.1791388988,41.3980178833],"type":"Point"}
}