{
  "type": "Feature",
  "properties": {
    "addr:full":"Calle de Carlo Goldoni, 78 Malaga M\u00e1laga 29004",
    "addr:housenumber":"78",
    "addr:postcode":"29004",
    "addr:street":"Calle De Carlo Goldoni;Ma\u0301Laga",
    "iso:country":"ES",
    "sg:address":"Calle de Carlo Goldoni, 78",
    "sg:city":"Malaga",
    "sg:orig_category":"Comercio De Piezas De Recambio Y De Accesorios De Veh\u00cdculos, Veh\u00cdculos Industriales",
    "sg:phone":"+34 952 23 85 40",
    "sg:postcode":"29004",
    "sg:province":"M\u00e1laga",
    "wof:name":"Luis Moleon S.l.",
    "wof:placetype":"venue"
},
  "geometry": {"coordinates":[-4.4919047356,36.6981163025],"type":"Point"}
}