{
  "type": "Feature",
  "properties": {
    "iso:country":"ES",
    "sg:address":"Navas De Tolosa, 29",
    "sg:city":"Iru\u00f1a",
    "sg:orig_category":"Cl\u00cdnicas Dentales",
    "sg:phone":"+34 948 22 57 96",
    "sg:postcode":"31002",
    "sg:province":"Navarra",
    "wof:name":"Dutor Vidal Miguel",
    "wof:placetype":"venue"
},
  "geometry": {"coordinates":[-1.6509040594,42.8154602051],"type":"Point"}
}