{
  "type": "Feature",
  "properties": {
    "addr:full":"Carr Pi I Margall, 39 Lleida Lleida 25004",
    "addr:housenumber":"39",
    "addr:postcode":"25004",
    "addr:street":"Carr Pi I Margall",
    "iso:country":"ES",
    "sg:address":"Carr Pi I Margall, 39",
    "sg:city":"Lleida",
    "sg:orig_category":"Mercer\u00cda, Lencer\u00cda (al Por Menor)",
    "sg:phone":"+34 973 23 10 98",
    "sg:postcode":"25004",
    "sg:province":"Lleida",
    "wof:name":"Bosch Prim Juan",
    "wof:placetype":"venue"
},
  "geometry": {"coordinates":[0.6266490221,41.6223716736],"type":"Point"}
}