{
  "type": "Feature",
  "properties": {
    "iso:country":"ES",
    "sg:address":"Carr Sant Pasqual, 22",
    "sg:city":"Gandia",
    "sg:orig_category":"Moda",
    "sg:phone":"+34 962 87 25 71",
    "sg:postcode":"46700",
    "sg:province":"Valencia",
    "sg:website":"www.mamybaby.com",
    "wof:name":"A Proposito Y Mas S.l.",
    "wof:placetype":"venue"
},
  "geometry": {"coordinates":[-0.1852236986,38.9690284729],"type":"Point"}
}