{
  "type": "Feature",
  "properties": {
    "iso:country":"ES",
    "sg:address":"Avda Gran Via, 35",
    "sg:city":"Caravaca Cruz",
    "sg:orig_category":"M\u00c9dicos: Cirug\u00cda Ortop\u00c9dica Y Traumatolog\u00cda",
    "sg:phone":"+34 968 70 38 81",
    "sg:postcode":"30400",
    "sg:province":"Murcia",
    "wof:name":"Arranz Roa Agustin",
    "wof:placetype":"venue"
},
  "geometry": {"coordinates":[-1.8612672091,38.103427887],"type":"Point"}
}