{
  "type": "Feature",
  "properties": {
    "addr:full":"Rbla Sant Joan, 266 Badalona Barcelona 08917",
    "addr:housenumber":"266",
    "addr:postcode":"08917",
    "addr:street":"Rbla Sant Joan",
    "iso:country":"ES",
    "sg:address":"Rbla Sant Joan, 266",
    "sg:city":"Badalona",
    "sg:orig_category":"Fabricaci\u00d3n, Instalaci\u00d3n Y Reparaci\u00d3n De Bombas",
    "sg:phone":"+34 933 87 44 02",
    "sg:postcode":"08917",
    "sg:province":"Barcelona",
    "wof:name":"T. M. B. Serhid S.l.",
    "wof:placetype":"venue"
},
  "geometry": {"coordinates":[2.2328469753,41.4518737793],"type":"Point"}
}