{
  "type": "Feature",
  "properties": {
    "addr:full":"Calle de Blasco Iba\u00d1ez, S/n Ca\u00e7ada Rosal Sevilla 41439",
    "addr:housenumber":"s",
    "addr:postcode":"41439",
    "addr:street":"Calle De Blasco Iban\u0303Ez;/ N Cac\u0327Ada Rosal",
    "iso:country":"ES",
    "sg:address":"Calle de Blasco Iba\u00d1ez, S/n",
    "sg:city":"Ca\u00e7ada Rosal",
    "sg:orig_category":"Producci\u00d3n, Comercio De Cereales",
    "sg:phone":"+34 954 83 91 03",
    "sg:postcode":"41439",
    "sg:province":"Sevilla",
    "wof:name":"Sociedad Cooperativa Andaluza La Carrosale\u00f1a",
    "wof:placetype":"venue"
},
  "geometry": {"coordinates":[-5.2122092247,37.6004104614],"type":"Point"}
}