{
  "type": "Feature",
  "properties": {
    "iso:country":"ES",
    "sg:address":"Avda Canarias, 274",
    "sg:city":"Vecindario",
    "sg:orig_category":"Zapatos (al Por Menor)",
    "sg:phone":"+34 928 75 69 12",
    "sg:postcode":"35110",
    "sg:province":"Las Palmas",
    "wof:name":"Calzados Hermanos Alonso S.l.",
    "wof:placetype":"venue"
},
  "geometry": {"coordinates":[-15.4430789948,27.8479957581],"type":"Point"}
}