{
  "type": "Feature",
  "properties": {
    "iso:country":"ES",
    "sg:address":"Calle de Pepe El Carretero, 6",
    "sg:city":"Gran Tarajal",
    "sg:orig_category":"Electricidad Veh\u00cdculo",
    "sg:phone":"+34 928 87 07 92",
    "sg:postcode":"35620",
    "sg:province":"Las Palmas",
    "wof:name":"J.l.fumero S.l.",
    "wof:placetype":"venue"
},
  "geometry": {"coordinates":[-14.0232868195,28.2167663574],"type":"Point"}
}