{
  "type": "Feature",
  "properties": {
    "addr:full":"Calle de Rafael Alberti, S/n Algeciras C\u00e1diz 11204",
    "addr:housenumber":"s / n;ca\u0301diz",
    "addr:postcode":"11204",
    "addr:street":"Calle De Rafael Alberti",
    "iso:country":"ES",
    "sg:address":"Calle de Rafael Alberti, S/n",
    "sg:city":"Algeciras",
    "sg:orig_category":"Guarder\u00cdas",
    "sg:phone":"+34 956 66 81 03",
    "sg:postcode":"11204",
    "sg:province":"C\u00e1diz",
    "wof:name":"Asociacion De Vecinos El Mirador",
    "wof:placetype":"venue"
},
  "geometry": {"coordinates":[-5.4617843628,36.138130188],"type":"Point"}
}