{
  "type": "Feature",
  "properties": {
    "iso:country":"ES",
    "sg:address":"Carrer de Puigterra De Dalt, 40",
    "sg:city":"Manresa",
    "sg:orig_category":"Peluquer\u00cdas, Peluquer\u00cda Mixta",
    "sg:phone":"+34 938 75 71 98",
    "sg:postcode":"08241",
    "sg:province":"Barcelona",
    "wof:name":"Garcia Perez Luz Maria",
    "wof:placetype":"venue"
},
  "geometry": {"coordinates":[1.8249069452,41.7274284363],"type":"Point"}
}