{
  "type": "Feature",
  "properties": {
    "iso:country":"ES",
    "sg:address":"Carrer de Mig (del), 35",
    "sg:city":"Mas Rampinyo",
    "sg:orig_category":"Int\u00c9rpretes",
    "sg:phone":"+34 935 65 09 60",
    "sg:postcode":"08110",
    "sg:province":"Barcelona",
    "wof:name":"Dgm Sistemas De Cierre S.l.",
    "wof:placetype":"venue"
},
  "geometry": {"coordinates":[2.1817660332,41.4890899658],"type":"Point"}
}