{
  "type": "Feature",
  "properties": {
    "iso:country":"ES",
    "sg:address":"Calle de Tejera (la), 2",
    "sg:city":"Soria",
    "sg:orig_category":"Farmacias",
    "sg:phone":"+34 975 21 18 34",
    "sg:postcode":"42001",
    "sg:province":"Soria",
    "wof:name":"Jimenez Diez Maria Del Carmen",
    "wof:placetype":"venue"
},
  "geometry": {"coordinates":[-2.4681680202,41.7665977478],"type":"Point"}
}