{
  "type": "Feature",
  "properties": {
    "iso:country":"ES",
    "sg:address":"Calle de General Ricardos, 206",
    "sg:city":"Madrid",
    "sg:orig_category":"Farmacias",
    "sg:phone":"+34 914 65 19 81",
    "sg:postcode":"28025",
    "sg:province":"Madrid",
    "wof:name":"Martinez Jimenez Jacinto Jesus",
    "wof:placetype":"venue"
},
  "geometry": {"coordinates":[-3.7373669147,40.3853111267],"type":"Point"}
}