{
  "type": "Feature",
  "properties": {
    "iso:country":"ES",
    "sg:address":"Calle de Pez Austral, 3",
    "sg:city":"Madrid",
    "sg:orig_category":"Arquitectos",
    "sg:phone":"+34 914 09 38 18",
    "sg:postcode":"28007",
    "sg:province":"Madrid",
    "wof:name":"G.h.t. Arquitectura Y Urbanismo S.l.",
    "wof:placetype":"venue"
},
  "geometry": {"coordinates":[-3.6658809185,40.4135322571],"type":"Point"}
}