{
  "type": "Feature",
  "properties": {
    "iso:country":"ES",
    "sg:address":"Carrer de Reis Catolics, 119",
    "sg:city":"Sabadell",
    "sg:orig_category":"Mec\u00c1nico Del Autom\u00d3vil",
    "sg:phone":"+34 937 10 11 34",
    "sg:postcode":"08204",
    "sg:province":"Barcelona",
    "wof:name":"Mallofre Mayoral Josep",
    "wof:placetype":"venue"
},
  "geometry": {"coordinates":[2.1151890755,41.5240249634],"type":"Point"}
}