{
  "type": "Feature",
  "properties": {
    "iso:country":"ES",
    "sg:address":"Avda Rodriguez De Ledesma, 2",
    "sg:city":"Caceres",
    "sg:orig_category":"M\u00c9dicos: Alergolog\u00cda",
    "sg:phone":"+34 927 21 64 94",
    "sg:postcode":"10001",
    "sg:province":"C\u00e1ceres",
    "wof:name":"Polo Sanabria Dionisio",
    "wof:placetype":"venue"
},
  "geometry": {"coordinates":[-6.382060051,39.4718551636],"type":"Point"}
}