{
  "type": "Feature",
  "properties": {
    "addr:full":"Carrer de Notari Closells, 8 Olot Girona 17800",
    "addr:housenumber":"8",
    "addr:postcode":"17800",
    "addr:street":"Carrer De Notari Closells",
    "iso:country":"ES",
    "sg:address":"Carrer de Notari Closells, 8",
    "sg:city":"Olot",
    "sg:orig_category":"Institutos De Belleza",
    "sg:phone":"+34 972 26 20 14",
    "sg:postcode":"17800",
    "sg:province":"Girona",
    "wof:name":"Anne's S.cv.",
    "wof:placetype":"venue"
},
  "geometry": {"coordinates":[2.4834930897,42.1801948547],"type":"Point"}
}