{
  "type": "Feature",
  "properties": {
    "iso:country":"ES",
    "sg:address":"Pg Bonanova, 1",
    "sg:city":"Barcelona",
    "sg:orig_category":"Doctores En Medicina",
    "sg:phone":"+34 932 11 93 45",
    "sg:postcode":"08022",
    "sg:province":"Barcelona",
    "wof:name":"Saballs Radresa Pere",
    "wof:placetype":"venue"
},
  "geometry": {"coordinates":[2.1331019402,41.4063301086],"type":"Point"}
}