{
  "type": "Feature",
  "properties": {
    "iso:country":"ES",
    "sg:address":"Pla\u00c7 Espanya, 3",
    "sg:city":"Lleida",
    "sg:orig_category":"M\u00c9dicos: Otorrinolaringolog\u00cda",
    "sg:phone":"+34 973 26 20 00",
    "sg:postcode":"25002",
    "sg:province":"Lleida",
    "wof:name":"Garcia Rivas Jose",
    "wof:placetype":"venue"
},
  "geometry": {"coordinates":[0.6216008067,41.6107330322],"type":"Point"}
}