{
  "type": "Feature",
  "properties": {
    "addr:full":"Agustina De Arag\u00f3n, 17 Almenara Castell\u00f3n 12590",
    "addr:housenumber":"17",
    "addr:postcode":"12590",
    "addr:street":"Agustina;Arago\u0301N",
    "iso:country":"ES",
    "sg:address":"Agustina De Arag\u00f3n, 17",
    "sg:city":"Almenara",
    "sg:orig_category":"Frutas Y Legumbres Frescas (al Por Mayor)",
    "sg:phone":"+34 962 61 03 12",
    "sg:postcode":"12590",
    "sg:province":"Castell\u00f3n",
    "wof:name":"Forner Beltran Maria Rosa",
    "wof:placetype":"venue"
},
  "geometry": {"coordinates":[-0.224859193,39.7524642944],"type":"Point"}
}