{
  "type": "Feature",
  "properties": {
    "addr:full":"Bo Carbonaire, 3 Vall Uixo Castell\u00f3n 12600",
    "addr:housenumber":"3",
    "addr:postcode":"12600",
    "addr:street":"Carbonaire;Castello\u0301N",
    "iso:country":"ES",
    "sg:address":"Bo Carbonaire, 3",
    "sg:city":"Vall Uixo",
    "sg:orig_category":"Cultos Diversos",
    "sg:phone":"+34 964 69 13 18",
    "sg:postcode":"12600",
    "sg:province":"Castell\u00f3n",
    "wof:name":"Testigos Cristianos De Jehova",
    "wof:placetype":"venue"
},
  "geometry": {"coordinates":[-0.237146005,39.8277206421],"type":"Point"}
}