{
  "type": "Feature",
  "properties": {
    "iso:country":"ES",
    "sg:address":"Carrer de Castillejos, 385",
    "sg:city":"Barcelona",
    "sg:orig_category":"Bisuter\u00cda, Joyer\u00cda, Relojer\u00cda (al Por Menor)",
    "sg:phone":"+34 934 35 18 40",
    "sg:postcode":"08025",
    "sg:province":"Barcelona",
    "wof:name":"Lisandra Ca\u00f1ellas Laura",
    "wof:placetype":"venue"
},
  "geometry": {"coordinates":[2.1713330746,41.4116821289],"type":"Point"}
}