{
  "type": "Feature",
  "properties": {
    "addr:full":"Via Dos Castillas (de Las), 33 Pozuelo De Alarcon Madrid 28224",
    "addr:housenumber":"33",
    "addr:postcode":"28224",
    "addr:street":"Via Dos Castillas De Las",
    "iso:country":"ES",
    "sg:address":"Via Dos Castillas (de Las), 33",
    "sg:city":"Pozuelo De Alarcon",
    "sg:orig_category":"Inmobiliaria (agencias)",
    "sg:phone":"+34 917 09 01 30",
    "sg:postcode":"28224",
    "sg:province":"Madrid",
    "wof:name":"Next Pereda S.a.",
    "wof:placetype":"venue"
},
  "geometry": {"coordinates":[-3.7859261036,40.4402656555],"type":"Point"}
}