{
  "type": "Feature",
  "properties": {
    "iso:country":"ES",
    "sg:address":"Av Saloria, 97",
    "sg:city":"Seu D'urgell",
    "sg:orig_category":"Electricidad, Electr\u00d3nica: Suministros (al Por Menor)",
    "sg:phone":"+34 973 35 07 89",
    "sg:postcode":"25700",
    "sg:province":"Lleida",
    "wof:name":"Funollet Queixalos Jose",
    "wof:placetype":"venue"
},
  "geometry": {"coordinates":[0.6457189918,41.6027946472],"type":"Point"}
}