{
  "type": "Feature",
  "properties": {
    "addr:full":"Carrer de Arx Lluis Salvador, 91 Palma Islas Baleares 07004",
    "addr:housenumber":"91",
    "addr:postcode":"07004",
    "addr:street":"Carrer De Arx Lluis Salvador",
    "iso:country":"ES",
    "sg:address":"Carrer de Arx Lluis Salvador, 91",
    "sg:city":"Palma",
    "sg:orig_category":"Cajas De Ahorro",
    "sg:phone":"+34 971 76 47 00",
    "sg:postcode":"07004",
    "sg:province":"Islas Baleares",
    "wof:name":"Caja De Ahorros Y Monte De Piedad De Las Baleares",
    "wof:placetype":"venue"
},
  "geometry": {"coordinates":[2.657407999,39.5850028992],"type":"Point"}
}