{
  "type": "Feature",
  "properties": {
    "addr:full":"Ctra Lameiro, 18 Lameiro Pontevedra 36214",
    "addr:housenumber":"18",
    "addr:postcode":"36214",
    "addr:street":"Ctra Lameiro",
    "iso:country":"ES",
    "sg:address":"Ctra Lameiro, 18",
    "sg:city":"Lameiro",
    "sg:orig_category":"Inform\u00c1tica Equipo Y Programas (al Por Mayor)",
    "sg:phone":"+34 986 27 73 45",
    "sg:postcode":"36214",
    "sg:province":"Pontevedra",
    "sg:website":"www.suministrosinec.com",
    "wof:name":"Suministros Inec S.l.",
    "wof:placetype":"venue"
},
  "geometry": {"coordinates":[-8.5466747284,42.5389862061],"type":"Point"}
}