{
  "type": "Feature",
  "properties": {
    "iso:country":"ES",
    "sg:address":"Perimetral, S/n",
    "sg:city":"Montehermoso",
    "sg:classifiers":[
        {
            "category":"Manufacturing",
            "subcategory":"Metals",
            "type":"Manufacturing & Wholesale Goods"
        }
    ],
    "sg:phone":"+34 927 67 53 60",
    "sg:postcode":"10810",
    "sg:province":"C\u00e1ceres",
    "sg:tags":[
        "en",
        "fundiciones"
    ],
    "wof:name":"Campanas Rivera C.b.",
    "wof:placetype":"venue"
},
  "geometry": {"coordinates":[-6.3499889374,40.0894966125],"type":"Point"}
}