{
  "type": "Feature",
  "properties": {
    "iso:country":"ES",
    "sg:address":"Carrer de Neopatria, 70",
    "sg:city":"Barcelona",
    "sg:orig_category":"Fabricaci\u00d3n De Sobres, Bolsas Y Fundas",
    "sg:phone":"+34 932 74 14 46",
    "sg:postcode":"08030",
    "sg:province":"Barcelona",
    "wof:name":"Verdu Piqueras Juan",
    "wof:placetype":"venue"
},
  "geometry": {"coordinates":[2.1892139912,41.4294586182],"type":"Point"}
}