{
  "type": "Feature",
  "properties": {
    "addr:full":"Calle de Santisima Trinidad, 1 Antequera M\u00e1laga 29200",
    "addr:housenumber":"1",
    "addr:postcode":"29200",
    "addr:street":"Calle De Santisima Trinidad",
    "iso:country":"ES",
    "sg:address":"Calle de Santisima Trinidad, 1",
    "sg:city":"Antequera",
    "sg:orig_category":"Seguridad En El Trabajo Y Prevenci\u00d3n De Riesgos Laborales",
    "sg:phone":"+34 952 70 41 26",
    "sg:postcode":"29200",
    "sg:province":"M\u00e1laga",
    "wof:name":"Sur Prevencion S.l.",
    "wof:placetype":"venue"
},
  "geometry": {"coordinates":[-4.5628452301,37.0191268921],"type":"Point"}
}