{
  "type": "Feature",
  "properties": {
    "addr:full":"Rua Da Igrexa, 37 Cabreiros Lugo 27163",
    "addr:housenumber":"37",
    "addr:postcode":"27163",
    "addr:street":"Rua Da Igrexa",
    "iso:country":"ES",
    "sg:address":"Rua Da Igrexa, 37",
    "sg:city":"Cabreiros",
    "sg:orig_category":"M\u00c9dicos: Cirug\u00cda Maxilofacial",
    "sg:phone":"+34 982 30 04 15",
    "sg:postcode":"27163",
    "sg:province":"Lugo",
    "wof:name":"Menendez Mato Manuel",
    "wof:placetype":"venue"
},
  "geometry": {"coordinates":[-7.4318971634,42.9433937073],"type":"Point"}
}