{
  "type": "Feature",
  "properties": {
    "iso:country":"ES",
    "sg:address":"Plaz Circular, 7",
    "sg:city":"Vista Alegre",
    "sg:orig_category":"Abogados",
    "sg:phone":"+34 968 23 18 51",
    "sg:postcode":"30008",
    "sg:province":"Murcia",
    "wof:name":"Garcia Ruiz Antonio",
    "wof:placetype":"venue"
},
  "geometry": {"coordinates":[-1.1298867464,37.9834747314],"type":"Point"}
}