{
  "type": "Feature",
  "properties": {
    "iso:country":"ES",
    "sg:address":"Ctra Huetor Vega (de), 6",
    "sg:city":"Granada",
    "sg:orig_category":"Asilos De Ancianos. Centros Privados",
    "sg:phone":"+34 958 13 00 84",
    "sg:postcode":"18008",
    "sg:province":"Granada",
    "wof:name":"Hijas De La Caridad De San Vicente De Paul",
    "wof:placetype":"venue"
},
  "geometry": {"coordinates":[-3.5865900517,37.1611175537],"type":"Point"}
}