{
  "type": "Feature",
  "properties": {
    "iso:country":"ES",
    "sg:address":"Calle de Costa Rica, 2",
    "sg:city":"Malaga",
    "sg:orig_category":"Inmobiliaria (agencias)",
    "sg:phone":"+34 952 29 69 79",
    "sg:postcode":"29017",
    "sg:province":"M\u00e1laga",
    "wof:name":"Union Familiar Malacitana De Inversiones S.l.",
    "wof:placetype":"venue"
},
  "geometry": {"coordinates":[-4.3785190582,36.7234191895],"type":"Point"}
}