{
  "type": "Feature",
  "properties": {
    "iso:country":"ES",
    "sg:address":"Avda Libertad De La, 7",
    "sg:city":"Donostia-san Sebastian",
    "sg:orig_category":"Abogados",
    "sg:phone":"+34 943 42 26 86",
    "sg:postcode":"20004",
    "sg:province":"Guip\u00f9zcoa",
    "wof:name":"Larra\u00f1aga Bilbao Luis",
    "wof:placetype":"venue"
},
  "geometry": {"coordinates":[-1.9802559614,43.3201446533],"type":"Point"}
}