{
  "type": "Feature",
  "properties": {
    "iso:country":"ES",
    "sg:address":"Pavoa, S/n",
    "sg:city":"Aranda Duero",
    "sg:orig_category":"Ropa De Trabajo Y Profesionales (al Por Menor)",
    "sg:phone":"+34 947 51 33 47",
    "sg:postcode":"09400",
    "sg:province":"Burgos",
    "wof:name":"Udigas S.l.",
    "wof:placetype":"venue"
},
  "geometry": {"coordinates":[-3.7084739208,41.6695556641],"type":"Point"}
}