{
  "type": "Feature",
  "properties": {
    "iso:country":"ES",
    "sg:address":"Calle de Virgen De La Vega, 12",
    "sg:city":"Haro",
    "sg:orig_category":"Inmobiliaria (agencias)",
    "sg:phone":"+34 941 31 29 59",
    "sg:postcode":"26200",
    "sg:province":"La Rioja",
    "wof:name":"Fincas Urizar S.l.",
    "wof:placetype":"venue"
},
  "geometry": {"coordinates":[-2.8483970165,42.5771446228],"type":"Point"}
}