{
  "type": "Feature",
  "properties": {
    "iso:country":"ES",
    "sg:address":"Calle de Virgilio Navarro, 5",
    "sg:city":"Azuqueca Henares",
    "sg:orig_category":"Centros De Salud",
    "sg:phone":"+34 949 26 26 02",
    "sg:postcode":"19200",
    "sg:province":"Guadalajara",
    "wof:name":"Residencia Santa Maria Del Henares S.a.",
    "wof:placetype":"venue"
},
  "geometry": {"coordinates":[-3.2557489872,40.5731391907],"type":"Point"}
}