{
  "type": "Feature",
  "properties": {
    "addr:full":"Rua Juan Bautista Andrade, 50 Pontevedra Pontevedra 36005",
    "addr:housenumber":"50",
    "addr:postcode":"36005",
    "addr:street":"Rua Juan Bautista Andrade",
    "iso:country":"ES",
    "sg:address":"Rua Juan Bautista Andrade, 50",
    "sg:city":"Pontevedra",
    "sg:orig_category":"Agencias Y Agentes Comerciales, Representantes",
    "sg:phone":"+34 986 87 10 80",
    "sg:postcode":"36005",
    "sg:province":"Pontevedra",
    "wof:name":"Fernandez Neira Andres",
    "wof:placetype":"venue"
},
  "geometry": {"coordinates":[-8.6399583817,42.4429283142],"type":"Point"}
}