{
  "type": "Feature",
  "properties": {
    "iso:country":"ES",
    "sg:address":"Trans. L. Felipe, S/n",
    "sg:city":"Albolote",
    "sg:orig_category":"Asociaciones, Organismos Culturales Y Socioeducativos",
    "sg:phone":"+34 958 49 00 76",
    "sg:postcode":"18220",
    "sg:province":"Granada",
    "wof:name":"Ayuntamiento De Albolote",
    "wof:placetype":"venue"
},
  "geometry": {"coordinates":[-3.6521849632,37.3158683777],"type":"Point"}
}