{
  "type": "Feature",
  "properties": {
    "addr:full":"Calle de Moros, 14 Gijon Asturias 33206",
    "addr:housenumber":"14",
    "addr:postcode":"33206",
    "addr:street":"Calle De Moros",
    "iso:country":"ES",
    "sg:address":"Calle de Moros, 14",
    "sg:city":"Gijon",
    "sg:orig_category":"Bisuter\u00cda, Joyer\u00cda, Relojer\u00cda (al Por Menor)",
    "sg:phone":"+34 985 34 49 12",
    "sg:postcode":"33206",
    "sg:province":"Asturias",
    "wof:name":"Lastra Marcos Ubaldo",
    "wof:placetype":"venue"
},
  "geometry": {"coordinates":[-5.6633739471,43.541595459],"type":"Point"}
}