{
  "type": "Feature",
  "properties": {
    "addr:full":"Plaz Fuente Dorada, 4 Valladolid Valladolid 47001",
    "addr:housenumber":"4",
    "addr:postcode":"47001",
    "addr:street":"Plaz Fuente Dorada",
    "iso:country":"ES",
    "sg:address":"Plaz Fuente Dorada, 4",
    "sg:city":"Valladolid",
    "sg:orig_category":"Asistencia Y Consejos",
    "sg:phone":"+34 983 37 41 23",
    "sg:postcode":"47001",
    "sg:province":"Valladolid",
    "wof:name":"Alfiser Consulting S.l.",
    "wof:placetype":"venue"
},
  "geometry": {"coordinates":[-4.7258572578,41.6521377563],"type":"Point"}
}