{
  "type": "Feature",
  "properties": {
    "addr:full":"Calle de Goya, 48 Madrid Madrid 28001",
    "addr:housenumber":"48",
    "addr:postcode":"madrid;28001",
    "addr:street":"Calle De Goya",
    "iso:country":"ES",
    "sg:address":"Calle de Goya, 48",
    "sg:city":"Madrid",
    "sg:orig_category":"Inmobiliaria (agencias)",
    "sg:phone":"+34 914 41 04 27",
    "sg:postcode":"28001",
    "sg:province":"Madrid",
    "wof:name":"Gir Building Group S.l.",
    "wof:placetype":"venue"
},
  "geometry": {"coordinates":[-3.6789588928,40.4248123169],"type":"Point"}
}