{
  "type": "Feature",
  "properties": {
    "addr:full":"Calle de Luis Piernas, 36 Madrid Madrid 28017",
    "addr:housenumber":"36",
    "addr:postcode":"madrid;28017",
    "addr:street":"Calle De Luis Piernas",
    "iso:country":"ES",
    "sg:address":"Calle de Luis Piernas, 36",
    "sg:city":"Madrid",
    "sg:orig_category":"Plomeros",
    "sg:phone":"+34 914 03 16 98",
    "sg:postcode":"28017",
    "sg:province":"Madrid",
    "wof:name":"Focagas S.l.",
    "wof:placetype":"venue"
},
  "geometry": {"coordinates":[-3.6528329849,40.4266204834],"type":"Point"}
}