{
  "type": "Feature",
  "properties": {
    "iso:country":"ES",
    "sg:address":"Rond Guinardo, 53",
    "sg:city":"Barcelona",
    "sg:orig_category":"Marketing Directo",
    "sg:phone":"+34 934 33 43 11",
    "sg:postcode":"08024",
    "sg:province":"Barcelona",
    "sg:website":"www.integra-bdm.net",
    "wof:name":"Integra Servicios De Database Marketing S.l",
    "wof:placetype":"venue"
},
  "geometry": {"coordinates":[2.1677150726,41.4128379822],"type":"Point"}
}