{
  "type": "Feature",
  "properties": {
    "iso:country":"ES",
    "sg:address":"Calle de Granada, 15",
    "sg:city":"Puerto Serrano",
    "sg:orig_category":"Chapister\u00cda",
    "sg:phone":"+34 956 12 71 01",
    "sg:postcode":"11659",
    "sg:province":"C\u00e1diz",
    "wof:name":"Carrasco Soria Manuel",
    "wof:placetype":"venue"
},
  "geometry": {"coordinates":[-5.5378289223,36.923740387],"type":"Point"}
}