{
  "type": "Feature",
  "properties": {
    "iso:country":"ES",
    "sg:address":"Rbla Poblenou, 76",
    "sg:city":"Barcelona",
    "sg:orig_category":"M\u00c1quinas De Escribir, M\u00c1quinas De Oficina (al Por Menor, Reparaci\u00d3n)",
    "sg:phone":"+34 933 20 84 10",
    "sg:postcode":"08005",
    "sg:province":"Barcelona",
    "wof:name":"Canovas Office & Products S.l.",
    "wof:placetype":"venue"
},
  "geometry": {"coordinates":[2.2012629509,41.4013748169],"type":"Point"}
}