{
  "type": "Feature",
  "properties": {
    "iso:country":"ES",
    "sg:address":"Calle de Santa Barbara, 13",
    "sg:city":"Guardo",
    "sg:orig_category":"Doctores En Medicina",
    "sg:phone":"+34 979 85 03 07",
    "sg:postcode":"34880",
    "sg:province":"Palencia",
    "sg:website":"www.paginasamarillas.es",
    "wof:name":"Clinica De Fisioterapia Y Osteopatia S.l.",
    "wof:placetype":"venue"
},
  "geometry": {"coordinates":[-4.8424210548,42.7906188965],"type":"Point"}
}