{
  "type": "Feature",
  "properties": {
    "addr:full":"Calle de Olivar, 21 Madrid Madrid 28012",
    "addr:housenumber":"21",
    "addr:postcode":"madrid;28012",
    "addr:street":"Calle De Olivar",
    "iso:country":"ES",
    "sg:address":"Calle de Olivar, 21",
    "sg:city":"Madrid",
    "sg:orig_category":"Cine (producci\u00d3n, Realizaci\u00d3n)",
    "sg:phone":"+34 915 06 09 91",
    "sg:postcode":"28012",
    "sg:province":"Madrid",
    "wof:name":"Lolita Producciones Cinematograficas S.l.",
    "wof:placetype":"venue"
},
  "geometry": {"coordinates":[-3.7015140057,40.4107551575],"type":"Point"}
}