{
  "type": "Feature",
  "properties": {
    "addr:full":"Pase Martires, 49 Socuellamos Ciudad Real 13630",
    "addr:housenumber":"49",
    "addr:postcode":"13630",
    "addr:street":"Martires",
    "iso:country":"ES",
    "sg:address":"Pase Martires, 49",
    "sg:city":"Socuellamos",
    "sg:orig_category":"Escayola Y Productos De Escayola (fabricaci\u00d3n, Al Por Mayor)",
    "sg:phone":"+34 926 53 12 42",
    "sg:postcode":"13630",
    "sg:province":"Ciudad Real",
    "wof:name":"Alcolea Campos Julian",
    "wof:placetype":"venue"
},
  "geometry": {"coordinates":[-2.796557188,39.292098999],"type":"Point"}
}