{
  "type": "Feature",
  "properties": {
    "iso:country":"ES",
    "sg:address":"Calle de Paz (la), 12",
    "sg:city":"Casas-iba\u00e7ez",
    "sg:orig_category":"Inmobiliaria (agencias)",
    "sg:phone":"+34 967 46 13 51",
    "sg:postcode":"02200",
    "sg:province":"Albacete",
    "wof:name":"Ibainm Casas Iba\u00f1ez S.l.",
    "wof:placetype":"venue"
},
  "geometry": {"coordinates":[-1.4726890326,39.286567688],"type":"Point"}
}