{
  "type": "Feature",
  "properties": {
    "iso:country":"ES",
    "sg:address":"Calle de Mallorca, 2",
    "sg:city":"Onda",
    "sg:orig_category":"Asesor\u00cda Fiscal Y Jur\u00cddica",
    "sg:phone":"+34 964 77 00 55",
    "sg:postcode":"12200",
    "sg:province":"Castell\u00f3n",
    "wof:name":"Chorva Diago Jose",
    "wof:placetype":"venue"
},
  "geometry": {"coordinates":[-0.255795002,39.9655151367],"type":"Point"}
}