{
  "type": "Feature",
  "properties": {
    "addr:full":"Ctra Prats De Llu\u00c7anes, 188 Sabadell Barcelona 08208",
    "addr:housenumber":"188",
    "addr:postcode":"08208",
    "addr:street":"Ctra Prats De Lluc\u0327Anes",
    "iso:country":"ES",
    "sg:address":"Ctra Prats De Llu\u00c7anes, 188",
    "sg:city":"Sabadell",
    "sg:orig_category":"Cajas De Ahorro",
    "sg:phone":"+34 937 16 89 81",
    "sg:postcode":"08208",
    "sg:province":"Barcelona",
    "sg:website":"www.caixasabadell.es",
    "wof:name":"Caixa D'estalvis Sabadell",
    "wof:placetype":"venue"
},
  "geometry": {"coordinates":[2.101706028,41.559627533],"type":"Point"}
}