{
  "type": "Feature",
  "properties": {
    "addr:full":"Avda Pedro Carrasco, S/n Alosno Huelva 21520",
    "addr:housenumber":"s",
    "addr:postcode":"21520",
    "addr:street":"Avda Pedro Carrasco;/ N",
    "iso:country":"ES",
    "sg:address":"Avda Pedro Carrasco, S/n",
    "sg:city":"Alosno",
    "sg:orig_category":"Asilos De Ancianos. Centros Privados",
    "sg:phone":"+34 959 39 64 39",
    "sg:postcode":"21520",
    "sg:province":"Huelva",
    "wof:name":"Fundacion Nu\u00f1ez Limon Residencia",
    "wof:placetype":"venue"
},
  "geometry": {"coordinates":[-7.1190438271,37.5480003357],"type":"Point"}
}