{
  "type": "Feature",
  "properties": {
    "addr:full":"Calle de Maruja Garrido, 17 Caravaca Cruz Murcia 30400",
    "addr:housenumber":"17",
    "addr:postcode":"30400",
    "addr:street":"Calle De Maruja Garrido",
    "iso:country":"ES",
    "sg:address":"Calle de Maruja Garrido, 17",
    "sg:city":"Caravaca Cruz",
    "sg:orig_category":"Mec\u00c1nico Del Autom\u00d3vil",
    "sg:phone":"+34 968 70 06 91",
    "sg:postcode":"30400",
    "sg:province":"Murcia",
    "wof:name":"Sanchez Fernandez Valentin",
    "wof:placetype":"venue"
},
  "geometry": {"coordinates":[-1.8581240177,38.1043815613],"type":"Point"}
}