{
  "type": "Feature",
  "properties": {
    "iso:country":"ES",
    "sg:address":"Calle de Juntas Generales, 8",
    "sg:city":"Barakaldo",
    "sg:orig_category":"Asesor\u00cda Fiscal Y Jur\u00cddica",
    "sg:phone":"+34 944 04 72 43",
    "sg:postcode":"48901",
    "sg:province":"Vizcaya",
    "wof:name":"Consultoria Y Gestores Empresariales, S.l.",
    "wof:placetype":"venue"
},
  "geometry": {"coordinates":[-2.9875359535,43.2974700928],"type":"Point"}
}