{
  "type": "Feature",
  "properties": {
    "iso:country":"ES",
    "sg:address":"Rua Roberto Baamonde, 52",
    "sg:city":"Monforte De Lemos",
    "sg:orig_category":"Agencias Y Agentes Comerciales, Representantes",
    "sg:phone":"+34 982 40 12 41",
    "sg:postcode":"27400",
    "sg:province":"Lugo",
    "wof:name":"Alonso Diaz Victor",
    "wof:placetype":"venue"
},
  "geometry": {"coordinates":[-7.5104570389,42.5207214355],"type":"Point"}
}