{
  "type": "Feature",
  "properties": {
    "addr:full":"Calle de Sixto Celorrio, 1 Zaragoza Zaragoza 50015",
    "addr:housenumber":"1",
    "addr:postcode":"50015",
    "addr:street":"Calle De Sixto Celorrio",
    "iso:country":"ES",
    "sg:address":"Calle de Sixto Celorrio, 1",
    "sg:city":"Zaragoza",
    "sg:orig_category":"Florister\u00cdas",
    "sg:phone":"+34 976 52 21 51",
    "sg:postcode":"50015",
    "sg:province":"Zaragoza",
    "wof:name":"Torres Villar Jose Maria",
    "wof:placetype":"venue"
},
  "geometry": {"coordinates":[-0.8746895194,41.6583976746],"type":"Point"}
}