{
  "type": "Feature",
  "properties": {
    "iso:country":"ES",
    "sg:address":"Pol. Palancares, 7",
    "sg:city":"Cuenca",
    "sg:orig_category":"Cerrajer\u00cda, Ferrallista",
    "sg:phone":"+34 969 23 34 10",
    "sg:postcode":"16003",
    "sg:province":"Cuenca",
    "wof:name":"Cerrajeria Rm C.b.",
    "wof:placetype":"venue"
},
  "geometry": {"coordinates":[-2.1383280754,40.0619697571],"type":"Point"}
}