{
  "type": "Feature",
  "properties": {
    "iso:country":"ES",
    "sg:address":"Calle de Sangenis, 55",
    "sg:city":"Zaragoza",
    "sg:orig_category":"Importaci\u00d3n",
    "sg:phone":"+34 976 46 00 57",
    "sg:postcode":"50010",
    "sg:province":"Zaragoza",
    "wof:name":"Rufama S.a.",
    "wof:placetype":"venue"
},
  "geometry": {"coordinates":[-0.9032229781,41.65026474],"type":"Point"}
}