{
  "type": "Feature",
  "properties": {
    "iso:country":"ES",
    "sg:address":"Psaj Robledano, 3",
    "sg:city":"San Pedro Alcantara",
    "sg:orig_category":"Cl\u00cdnicas M\u00c9dicas",
    "sg:phone":"+34 952 78 93 16",
    "sg:postcode":"29670",
    "sg:province":"M\u00e1laga",
    "wof:name":"Cruz Reyes Luis Praxedes",
    "wof:placetype":"venue"
},
  "geometry": {"coordinates":[-4.9902391434,36.4866333008],"type":"Point"}
}