{
  "type": "Feature",
  "properties": {
    "addr:full":"Calle de Goya, 4 Consuegra Toledo 45700",
    "addr:housenumber":"4",
    "addr:postcode":"45700",
    "addr:street":"Calle De Goya",
    "iso:country":"ES",
    "sg:address":"Calle de Goya, 4",
    "sg:city":"Consuegra",
    "sg:orig_category":"Muebles, Minoristas",
    "sg:phone":"+34 925 48 24 07",
    "sg:postcode":"45700",
    "sg:province":"Toledo",
    "wof:name":"Carpidecor C.b.",
    "wof:placetype":"venue"
},
  "geometry": {"coordinates":[-3.6139309406,39.4591636658],"type":"Point"}
}