{
  "type": "Feature",
  "properties": {
    "addr:full":"Calle de Juan Bravo, 1 Puertollano Ciudad Real 13500",
    "addr:housenumber":"1",
    "addr:postcode":"13500",
    "addr:street":"Calle De Juan Bravo",
    "iso:country":"ES",
    "sg:address":"Calle de Juan Bravo, 1",
    "sg:city":"Puertollano",
    "sg:orig_category":"Venta, Instalaci\u00d3n De Calefacci\u00d3n",
    "sg:phone":"+34 926 41 20 84",
    "sg:postcode":"13500",
    "sg:province":"Ciudad Real",
    "wof:name":"Instalaciones Tecnicas Caba\u00f1ero S.l.",
    "wof:placetype":"venue"
},
  "geometry": {"coordinates":[-4.1065921783,38.6864395142],"type":"Point"}
}