{
  "type": "Feature",
  "properties": {
    "addr:full":"Sta. Reliquia, 28 Yepes Toledo 45313",
    "addr:housenumber":"28",
    "addr:postcode":"45313",
    "addr:street":"Reliquia",
    "iso:country":"ES",
    "sg:address":"Sta. Reliquia, 28",
    "sg:city":"Yepes",
    "sg:orig_category":"Sanatorios M\u00c9dico",
    "sg:phone":"+34 925 15 44 81",
    "sg:postcode":"45313",
    "sg:province":"Toledo",
    "wof:name":"Servicio De Salud De Castilla La Mancha",
    "wof:placetype":"venue"
},
  "geometry": {"coordinates":[-3.6221690178,39.9026794434],"type":"Point"}
}