{
  "type": "Feature",
  "properties": {
    "addr:full":"Calle de Luchana, 38 Madrid Madrid 28010",
    "addr:housenumber":"38",
    "addr:postcode":"madrid;28010",
    "addr:street":"Calle De Luchana",
    "iso:country":"ES",
    "sg:address":"Calle de Luchana, 38",
    "sg:city":"Madrid",
    "sg:orig_category":"Peluqueros: De Se\u00d1oras",
    "sg:phone":"+34 914 45 24 71",
    "sg:postcode":"28010",
    "sg:province":"Madrid",
    "wof:name":"Fuentes Cordoba Maria Teresa",
    "wof:placetype":"venue"
},
  "geometry": {"coordinates":[-3.6981790066,40.4319572449],"type":"Point"}
}