{
  "type": "Feature",
  "properties": {
    "addr:full":"Plaz Escamilla, 2 Coin M\u00e1laga 29100",
    "addr:housenumber":"2",
    "addr:postcode":"29100",
    "addr:street":"Plaz Escamilla;Ma\u0301Laga",
    "iso:country":"ES",
    "sg:address":"Plaz Escamilla, 2",
    "sg:city":"Coin",
    "sg:orig_category":"Bazares, Art\u00cdculos De Limpieza Y De Cocina (al Por Menor)",
    "sg:phone":"+34 952 45 11 92",
    "sg:postcode":"29100",
    "sg:province":"M\u00e1laga",
    "wof:name":"Bazar Super Hermanos S.l.",
    "wof:placetype":"venue"
},
  "geometry": {"coordinates":[-4.7576842308,36.659740448],"type":"Point"}
}