{
  "type": "Feature",
  "properties": {
    "addr:full":"Carrer de Major, 2 Molins Rei Barcelona 08750",
    "addr:housenumber":"2",
    "addr:postcode":"08750",
    "addr:street":"Carrer De Major;Barcelona",
    "iso:country":"ES",
    "sg:address":"Carrer de Major, 2",
    "sg:city":"Molins Rei",
    "sg:orig_category":"Perfumer\u00cda (al Por Menor)",
    "sg:phone":"+34 936 68 90 06",
    "sg:postcode":"08750",
    "sg:province":"Barcelona",
    "wof:name":"Nisa Nu\u00f1ez Francisco",
    "wof:placetype":"venue"
},
  "geometry": {"coordinates":[2.0164849758,41.414604187],"type":"Point"}
}