{
  "type": "Feature",
  "properties": {
    "addr:full":"Pg Rocamora, S/n Montcada Centre Barcelona 08110",
    "addr:housenumber":"s / n",
    "addr:postcode":"08110",
    "addr:street":"Rocamora",
    "iso:country":"ES",
    "sg:address":"Pg Rocamora, S/n",
    "sg:city":"Montcada Centre",
    "sg:orig_category":"Cajas De Ahorro",
    "sg:phone":"+34 935 64 21 25",
    "sg:postcode":"08110",
    "sg:province":"Barcelona",
    "wof:name":"Caixa D'estalvis De Catalunya",
    "wof:placetype":"venue"
},
  "geometry": {"coordinates":[2.1816670895,41.5039367676],"type":"Point"}
}