{
  "type": "Feature",
  "properties": {
    "iso:country":"ES",
    "sg:address":"Pase Estacion, 32",
    "sg:city":"Salamanca",
    "sg:orig_category":"Ingeniero",
    "sg:phone":"+34 923 25 85 29",
    "sg:postcode":"37004",
    "sg:province":"Salamanca",
    "wof:name":"Martin Rodriguez Miguel Angel",
    "wof:placetype":"venue"
},
  "geometry": {"coordinates":[-5.6550841331,40.969493866],"type":"Point"}
}