{
  "type": "Feature",
  "properties": {
    "addr:full":"Avda Castilla, 13 Guadalajara Guadalajara 19002",
    "addr:housenumber":"13",
    "addr:postcode":"19002",
    "addr:street":"Avda Castilla",
    "iso:country":"ES",
    "sg:address":"Avda Castilla, 13",
    "sg:city":"Guadalajara",
    "sg:orig_category":"Arquitectos",
    "sg:phone":"+34 949 22 60 96",
    "sg:postcode":"19002",
    "sg:province":"Guadalajara",
    "wof:name":"Perez Masia Santiago",
    "wof:placetype":"venue"
},
  "geometry": {"coordinates":[-3.1666829586,40.6260795593],"type":"Point"}
}