{
  "type": "Feature",
  "properties": {
    "iso:country":"ES",
    "sg:address":"Calle de Lozano Sidro, 32",
    "sg:city":"Priego Cordoba",
    "sg:orig_category":"Molduras, Junquillos, Listones Y Molduras Perforadas",
    "sg:phone":"+34 957 70 05 65",
    "sg:postcode":"14800",
    "sg:province":"C\u00f3rdoba",
    "wof:name":"Aguilera Serrano Tomas",
    "wof:placetype":"venue"
},
  "geometry": {"coordinates":[-4.1988191605,37.437538147],"type":"Point"}
}