{
  "type": "Feature",
  "properties": {
    "iso:country":"ES",
    "sg:address":"Calle de Veracruz, 5",
    "sg:city":"Mostoles",
    "sg:orig_category":"Quincaller\u00cda (al Por Menor)",
    "sg:phone":"+34 916 45 61 49",
    "sg:postcode":"28937",
    "sg:province":"Madrid",
    "wof:name":"Lawera  Jolanta Jadwiga",
    "wof:placetype":"venue"
},
  "geometry": {"coordinates":[-3.8560259342,40.3183135986],"type":"Point"}
}