{
  "type": "Feature",
  "properties": {
    "addr:full":"Praz Vigo, S/n Carballo A Coru\u00f1a 15100",
    "addr:housenumber":"s / n",
    "addr:postcode":"15100",
    "addr:street":"Corun\u0303A",
    "iso:country":"ES",
    "sg:address":"Praz Vigo, S/n",
    "sg:city":"Carballo",
    "sg:orig_category":"Ense\u00d1anza, Formaci\u00d3n Profesional: Aprendizaje",
    "sg:phone":"+34 981 70 32 56",
    "sg:postcode":"15100",
    "sg:province":"A Coru\u00f1a",
    "wof:name":"Xunta De Galicia",
    "wof:placetype":"venue"
},
  "geometry": {"coordinates":[-8.649058342,43.2047309875],"type":"Point"}
}