{
  "type": "Feature",
  "properties": {
    "addr:full":"Calle de Lanza, 4 Ciudad Real Ciudad Real 13004",
    "addr:housenumber":"4",
    "addr:postcode":"13004",
    "addr:street":"Calle De Lanza",
    "iso:country":"ES",
    "sg:address":"Calle de Lanza, 4",
    "sg:city":"Ciudad Real",
    "sg:orig_category":"Asociaciones Y Clubs Deportivos",
    "sg:phone":"+34 926 25 55 59",
    "sg:postcode":"13004",
    "sg:province":"Ciudad Real",
    "wof:name":"Condado Berrocal S.l.",
    "wof:placetype":"venue"
},
  "geometry": {"coordinates":[-3.9252929688,38.9850006104],"type":"Point"}
}