{
  "type": "Feature",
  "properties": {
    "iso:country":"ES",
    "sg:address":"Labeaga Kalea, 3",
    "sg:city":"Urretxu",
    "sg:orig_category":"Centros M\u00c9dicos Y Sociales, Dispensarios",
    "sg:phone":"+34 943 03 64 62",
    "sg:postcode":"20700",
    "sg:province":"Guip\u00f9zcoa",
    "wof:name":"Centro Medico Urola",
    "wof:placetype":"venue"
},
  "geometry": {"coordinates":[-2.3152959347,43.0918197632],"type":"Point"}
}