{
  "type": "Feature",
  "properties": {
    "addr:full":"Ptda Plana De Gensana, 8 Butsenit Lleida 25194",
    "addr:housenumber":"8",
    "addr:postcode":"25194",
    "addr:street":"Ptda Plana De Gensana",
    "iso:country":"ES",
    "sg:address":"Ptda Plana De Gensana, 8",
    "sg:city":"Butsenit",
    "sg:orig_category":"Producci\u00d3n, Venta De Productos De Agricultura Biol\u00d3gica",
    "sg:phone":"+34 973 26 55 95",
    "sg:postcode":"25194",
    "sg:province":"Lleida",
    "wof:name":"Alio Sarda Leoncio",
    "wof:placetype":"venue"
},
  "geometry": {"coordinates":[0.9937890172,41.7979164124],"type":"Point"}
}