{
  "type": "Feature",
  "properties": {
    "iso:country":"ES",
    "sg:address":"Carr Sant Jordi, 1",
    "sg:city":"Mao",
    "sg:orig_category":"Azafatas Para Recepciones",
    "sg:phone":"+34 971 35 00 62",
    "sg:postcode":"07702",
    "sg:province":"Islas Baleares",
    "wof:name":"Hostesses Menorca, S.l.",
    "wof:placetype":"venue"
},
  "geometry": {"coordinates":[4.2631220818,39.8880310059],"type":"Point"}
}