{
  "type": "Feature",
  "properties": {
    "iso:country":"ES",
    "sg:address":"Calle de Ferrandiz, 40",
    "sg:city":"Malaga",
    "sg:orig_category":"Promotores Constructores",
    "sg:phone":"+34 952 25 79 78",
    "sg:postcode":"29012",
    "sg:province":"M\u00e1laga",
    "wof:name":"Diaz Ruiz Ascencion",
    "wof:placetype":"venue"
},
  "geometry": {"coordinates":[-4.4109191895,36.7271537781],"type":"Point"}
}