{
  "type": "Feature",
  "properties": {
    "iso:country":"ES",
    "sg:address":"Carrer de Cotlliure, 4",
    "sg:city":"Palma",
    "sg:orig_category":"Venta, Montaje De Neum\u00c1ticos",
    "sg:phone":"+34 971 29 76 61",
    "sg:postcode":"07010",
    "sg:province":"Islas Baleares",
    "wof:name":"Gomez Perez Angel Gomez Perez",
    "wof:placetype":"venue"
},
  "geometry": {"coordinates":[2.6481308937,39.5880851746],"type":"Point"}
}