{
  "type": "Feature",
  "properties": {
    "iso:country":"ES",
    "sg:address":"Calle de Pages Del Corro, 83",
    "sg:city":"Sevilla",
    "sg:orig_category":"Audiovisuales (producci\u00d3n, Edici\u00d3n, Realizaci\u00d3n)",
    "sg:phone":"+34 954 33 00 67",
    "sg:postcode":"41010",
    "sg:province":"Sevilla",
    "wof:name":"Ruano Perez Juan Luis",
    "wof:placetype":"venue"
},
  "geometry": {"coordinates":[-6.0041408539,37.3831977844],"type":"Point"}
}