{
  "type": "Feature",
  "properties": {
    "addr:full":"Calle de San Miguel, 12 Nules Castell\u00f3n 12520",
    "addr:housenumber":"12",
    "addr:postcode":"12520",
    "addr:street":"Calle De San Miguel",
    "iso:country":"ES",
    "sg:address":"Calle de San Miguel, 12",
    "sg:city":"Nules",
    "sg:orig_category":"Relojer\u00cda (al Por Menor, Reparaci\u00d3n)",
    "sg:phone":"+34 964 67 06 93",
    "sg:postcode":"12520",
    "sg:province":"Castell\u00f3n",
    "wof:name":"Chicharro Vivas S.l.",
    "wof:placetype":"venue"
},
  "geometry": {"coordinates":[-0.1554089934,39.851940155],"type":"Point"}
}