{
  "type": "Feature",
  "properties": {
    "addr:full":"Reyes Catolicos, 1 Olvega Soria 42110",
    "addr:housenumber":"1",
    "addr:postcode":"42110",
    "addr:street":"Reyes Catolicos",
    "iso:country":"ES",
    "sg:address":"Reyes Catolicos, 1",
    "sg:city":"Olvega",
    "sg:orig_category":"Arreglo, Reparaci\u00d3n, Piezas Sueltas De Televisi\u00d3n, V\u00cddeo, Hi",
    "sg:phone":"+34 976 64 58 54",
    "sg:postcode":"42110",
    "sg:province":"Soria",
    "wof:name":"Checa Ruiz David",
    "wof:placetype":"venue"
},
  "geometry": {"coordinates":[-1.9828380346,41.7782897949],"type":"Point"}
}