{
  "type": "Feature",
  "properties": {
    "addr:full":"Finca El Encinar, S/n Villalba Alcores Valladolid 47639",
    "addr:housenumber":"s / n",
    "addr:postcode":"47639",
    "iso:country":"ES",
    "sg:address":"Finca El Encinar, S/n",
    "sg:city":"Villalba Alcores",
    "sg:orig_category":"Agricultores, Agricultores",
    "sg:phone":"+34 983 72 15 14",
    "sg:postcode":"47639",
    "sg:province":"Valladolid",
    "wof:name":"Vitorica Illera Cesar",
    "wof:placetype":"venue"
},
  "geometry": {"coordinates":[-4.7283878326,41.6529464722],"type":"Point"}
}