{
  "type": "Feature",
  "properties": {
    "addr:full":"C/ Jose Diez Mora, 81 Elche Alicante 03205",
    "addr:housenumber":"81",
    "addr:postcode":"03205",
    "addr:street":"C / Jose Diez Mora",
    "iso:country":"ES",
    "sg:address":"C/ Jose Diez Mora, 81",
    "sg:city":"Elche",
    "sg:orig_category":"Arreglo, Reparaci\u00d3n, Piezas Sueltas De Televisi\u00d3n, V\u00cddeo, Hi",
    "sg:phone":"+34 965 46 43 48",
    "sg:postcode":"03205",
    "sg:province":"Alicante",
    "wof:name":"Cerdan Sanchez Pedro",
    "wof:placetype":"venue"
},
  "geometry": {"coordinates":[-0.7150599957,38.2716293335],"type":"Point"}
}