{
  "type": "Feature",
  "properties": {
    "iso:country":"ES",
    "sg:address":"Calle de Ricardo Dacosta, 2",
    "sg:city":"Porcuna",
    "sg:orig_category":"Asesor\u00cda Fiscal Y Jur\u00cddica",
    "sg:phone":"+34 953 54 41 09",
    "sg:postcode":"23790",
    "sg:province":"Ja\u00e9n",
    "wof:name":"Torres Palomo Francisco Javier",
    "wof:placetype":"venue"
},
  "geometry": {"coordinates":[-4.1860837936,37.8723297119],"type":"Point"}
}