{
  "type": "Feature",
  "properties": {
    "iso:country":"ES",
    "sg:address":"Calle de Goieta, 50",
    "sg:city":"Elorrio",
    "sg:orig_category":"Abogados",
    "sg:phone":"+34 946 82 05 62",
    "sg:postcode":"48230",
    "sg:province":"Vizcaya",
    "wof:name":"Zubia Querejeta Daniel Maria",
    "wof:placetype":"venue"
},
  "geometry": {"coordinates":[-2.543949604,43.1287002563],"type":"Point"}
}