{
  "type": "Feature",
  "properties": {
    "addr:full":"Fca. Pelilla, S/n Pelilla Salamanca 37100",
    "addr:housenumber":"s",
    "addr:postcode":"37100",
    "addr:street":"/ N",
    "iso:country":"ES",
    "sg:address":"Fca. Pelilla, S/n",
    "sg:city":"Pelilla",
    "sg:orig_category":"Promotores Constructores",
    "sg:phone":"+34 923 16 61 05",
    "sg:postcode":"37100",
    "sg:province":"Salamanca",
    "wof:name":"Los Requiles S.a.",
    "wof:placetype":"venue"
},
  "geometry": {"coordinates":[-6.0535931587,41.1836967468],"type":"Point"}
}