{
  "type": "Feature",
  "properties": {
    "addr:full":"Carr Pau Casals, 6 Tremp Lleida 25620",
    "addr:housenumber":"6",
    "addr:postcode":"25620",
    "addr:street":"Carr Pau Casals",
    "iso:country":"ES",
    "sg:address":"Carr Pau Casals, 6",
    "sg:city":"Tremp",
    "sg:orig_category":"Doctores En Medicina",
    "sg:phone":"+34 973 65 03 04",
    "sg:postcode":"25620",
    "sg:province":"Lleida",
    "wof:name":"Remon Roman Jose Luis",
    "wof:placetype":"venue"
},
  "geometry": {"coordinates":[0.8974829912,42.1648635864],"type":"Point"}
}