{
  "type": "Feature",
  "properties": {
    "iso:country":"ES",
    "sg:address":"Carr Es Cos De Gracia, 10",
    "sg:city":"Mao",
    "sg:orig_category":"Ropa Para Se\u00d1oras (al Por Menor)",
    "sg:phone":"+34 971 36 65 59",
    "sg:postcode":"07702",
    "sg:province":"Islas Baleares",
    "wof:name":"Gil Sebastia Obdulia",
    "wof:placetype":"venue"
},
  "geometry": {"coordinates":[4.2618451118,39.8877677917],"type":"Point"}
}