{
  "type": "Feature",
  "properties": {
    "addr:full":"Avda Constitucion De La, 3 Arroyo De La Miel-benalmadena Costa M\u00e1laga 29630",
    "addr:housenumber":"3",
    "addr:postcode":"29630",
    "addr:street":"Avda Constitucion De La;Arroyo De La Miel-Benalmadena Costa Ma\u0301Laga",
    "iso:country":"ES",
    "sg:address":"Avda Constitucion De La, 3",
    "sg:city":"Arroyo De La Miel-benalmadena Costa",
    "sg:orig_category":"Inmobiliaria (agencias)",
    "sg:phone":"+34 952 44 77 51",
    "sg:postcode":"29630",
    "sg:province":"M\u00e1laga",
    "wof:name":"Inmobiliaria San Julian S.a.",
    "wof:placetype":"venue"
},
  "geometry": {"coordinates":[-4.5382881165,36.581993103],"type":"Point"}
}