{
  "type": "Feature",
  "properties": {
    "iso:country":"ES",
    "sg:address":"Pg Francesc Macia, 64",
    "sg:city":"S. Cugat Valles",
    "sg:orig_category":"Peluquer\u00cdas, Peluquer\u00cda Mixta",
    "sg:phone":"+34 935 89 26 01",
    "sg:postcode":"08173",
    "sg:province":"Barcelona",
    "wof:name":"Isabal Marimon S.l.",
    "wof:placetype":"venue"
},
  "geometry": {"coordinates":[2.0834739208,41.4785346985],"type":"Point"}
}