{
  "type": "Feature",
  "properties": {
    "addr:full":"Carrer de Catalunya, 108 Terrassa Barcelona 08225",
    "addr:housenumber":"108",
    "addr:postcode":"08225",
    "addr:street":"Carrer De Catalunya",
    "iso:country":"ES",
    "sg:address":"Carrer de Catalunya, 108",
    "sg:city":"Terrassa",
    "sg:orig_category":"Ropa Para Se\u00d1oras Y Caballeros (al Por Menor)",
    "sg:phone":"+34 937 35 72 00",
    "sg:postcode":"08225",
    "sg:province":"Barcelona",
    "wof:name":"Rubio Sazatornil Teofilo",
    "wof:placetype":"venue"
},
  "geometry": {"coordinates":[1.9948710203,41.613899231],"type":"Point"}
}