{
  "type": "Feature",
  "properties": {
    "addr:full":"Calle de Murcia, 6 Velez-malaga M\u00e1laga 29700",
    "addr:housenumber":"6",
    "addr:postcode":"29700",
    "addr:street":"Calle De Murcia",
    "iso:country":"ES",
    "sg:address":"Calle de Murcia, 6",
    "sg:city":"Velez-malaga",
    "sg:classifiers":[
        {
            "category":"Taxi",
            "type":"Transportation"
        }
    ],
    "sg:phone":"+34 952 50 13 94",
    "sg:postcode":"29700",
    "sg:province":"M\u00e1laga",
    "wof:name":"Gutierrez Segovia Francisco",
    "wof:placetype":"venue"
},
  "geometry": {"coordinates":[-4.1030650139,36.7802238464],"type":"Point"}
}