{
  "type": "Feature",
  "properties": {
    "iso:country":"ES",
    "sg:address":"Calle de Doctor Fleming, 28",
    "sg:city":"San Vicente Del Raspeig-sant Vicent Del Raspeig",
    "sg:orig_category":"Florister\u00cdas",
    "sg:phone":"+34 965 66 62 35",
    "sg:postcode":"03690",
    "sg:province":"Alicante",
    "wof:name":"Beltran Sirvent Maria Del Carmen",
    "wof:placetype":"venue"
},
  "geometry": {"coordinates":[-0.5210880041,38.3999633789],"type":"Point"}
}