{
  "type": "Feature",
  "properties": {
    "iso:country":"ES",
    "sg:address":"Calle de Puertas De Cordoba, 5",
    "sg:city":"Porcuna",
    "sg:orig_category":"Empresas De Carpinter\u00cda Met\u00c1lica",
    "sg:phone":"+34 953 54 49 29",
    "sg:postcode":"23790",
    "sg:province":"Ja\u00e9n",
    "wof:name":"Burgos Diaz Alberto",
    "wof:placetype":"venue"
},
  "geometry": {"coordinates":[-4.1866831779,37.8751564026],"type":"Point"}
}