{
  "type": "Feature",
  "properties": {
    "addr:full":"Calle de La Bondad, 7 Barakaldo Vizcaya 48901",
    "addr:housenumber":"7",
    "addr:postcode":"48901",
    "addr:street":"Calle De La Bondad",
    "iso:country":"ES",
    "sg:address":"Calle de La Bondad, 7",
    "sg:city":"Barakaldo",
    "sg:orig_category":"Peluqueros: De Se\u00d1oras",
    "sg:phone":"+34 944 00 00 75",
    "sg:postcode":"48901",
    "sg:province":"Vizcaya",
    "wof:name":"Peluqueria Fidalgo",
    "wof:placetype":"venue"
},
  "geometry": {"coordinates":[-2.9922556877,43.2973823547],"type":"Point"}
}