{
  "type": "Feature",
  "properties": {
    "addr:full":"Avda De Mayo, 5 Lugros Granada 18516",
    "addr:housenumber":"5",
    "addr:postcode":"18516",
    "addr:street":"Avda De Mayo",
    "iso:country":"ES",
    "sg:address":"Avda De Mayo, 5",
    "sg:city":"Lugros",
    "sg:orig_category":"Estancos",
    "sg:phone":"+34 958 67 48 20",
    "sg:postcode":"18516",
    "sg:province":"Granada",
    "wof:name":"Gomez Navarro Ana",
    "wof:placetype":"venue"
},
  "geometry": {"coordinates":[-3.2405591011,37.2296562195],"type":"Point"}
}