{
  "type": "Feature",
  "properties": {
    "iso:country":"ES",
    "sg:address":"Carrer de Teodora Lamadrid, 48",
    "sg:city":"Barcelona",
    "sg:orig_category":"Tapicer\u00cdas",
    "sg:phone":"+34 934 17 08 83",
    "sg:postcode":"08022",
    "sg:province":"Barcelona",
    "wof:name":"Martinez Diaz Ramon",
    "wof:placetype":"venue"
},
  "geometry": {"coordinates":[2.1353390217,41.4078063965],"type":"Point"}
}