{
  "type": "Feature",
  "properties": {
    "iso:country":"ES",
    "sg:address":"Av Onze De Setembre, 15",
    "sg:city":"Reus",
    "sg:orig_category":"Tapicer\u00cdas",
    "sg:phone":"+34 977 32 05 65",
    "sg:postcode":"43203",
    "sg:province":"Tarragona",
    "wof:name":"Vallverdu Carrillo Gerard",
    "wof:placetype":"venue"
},
  "geometry": {"coordinates":[1.1049309969,41.1624412537],"type":"Point"}
}