{
  "type": "Feature",
  "properties": {
    "iso:country":"ES",
    "sg:address":"Calle de Hernando De Acu\u00d1a, 36",
    "sg:city":"Valladolid",
    "sg:orig_category":"Peluquer\u00cdas, Peluquer\u00cda Mixta",
    "sg:phone":"+34 983 34 47 52",
    "sg:postcode":"47014",
    "sg:province":"Valladolid",
    "wof:name":"Elenma 2001 S.l.",
    "wof:placetype":"venue"
},
  "geometry": {"coordinates":[-4.7608108521,41.638168335],"type":"Point"}
}