{
  "type": "Feature",
  "properties": {
    "addr:full":"Calle de Fragua (la), 4 Collado Villalba Madrid 28400",
    "addr:housenumber":"4",
    "addr:postcode":"28400",
    "addr:street":"Calle De Fragua La",
    "iso:country":"ES",
    "sg:address":"Calle de Fragua (la), 4",
    "sg:city":"Collado Villalba",
    "sg:orig_category":"Comercio De Hierro",
    "sg:phone":"+34 918 51 62 89",
    "sg:postcode":"28400",
    "sg:province":"Madrid",
    "wof:name":"Cerrajeria Fausto Martinez S.l.",
    "wof:placetype":"venue"
},
  "geometry": {"coordinates":[-3.9924530983,40.6453857422],"type":"Point"}
}