{
  "type": "Feature",
  "properties": {
    "iso:country":"ES",
    "sg:address":"Calle de Rios Rosas, 44",
    "sg:city":"Madrid",
    "sg:orig_category":"Ense\u00d1anza, Formaci\u00d3n Profesional: Aprendizaje",
    "sg:phone":"+34 915 34 43 37",
    "sg:postcode":"28003",
    "sg:province":"Madrid",
    "wof:name":"Mutualidad General Judicial",
    "wof:placetype":"venue"
},
  "geometry": {"coordinates":[-3.6970050335,40.4416465759],"type":"Point"}
}