{
  "type": "Feature",
  "properties": {
    "iso:country":"ES",
    "sg:address":"Valle De Escombreras, S/n",
    "sg:city":"Valle Escombreras",
    "sg:orig_category":"Aceites Y Grasas Industriales (fabricaci\u00d3n, Al Por Mayor)",
    "sg:phone":"+34 968 16 70 88",
    "sg:postcode":"30350",
    "sg:province":"Murcia",
    "wof:name":"Aceites Especiales Del Mediterraneo S.a.",
    "wof:placetype":"venue"
},
  "geometry": {"coordinates":[-0.9392700195,37.5608940125],"type":"Point"}
}