{
  "type": "Feature",
  "properties": {
    "iso:country":"ES",
    "sg:address":"Calle de Kadiga, 1",
    "sg:city":"Granada",
    "sg:orig_category":"Ingeniero",
    "sg:phone":"+34 958 12 69 14",
    "sg:postcode":"18008",
    "sg:province":"Granada",
    "wof:name":"Jimenez Burkhardt Juan Pedro",
    "wof:placetype":"venue"
},
  "geometry": {"coordinates":[-3.5782539845,37.160484314],"type":"Point"}
}