{
  "type": "Feature",
  "properties": {
    "iso:country":"ES",
    "sg:address":"Avda Hispanidad, S/n",
    "sg:city":"Madrid",
    "sg:orig_category":"Contenedores (mercanc\u00cdas)",
    "sg:phone":"+34 917 47 30 01",
    "sg:postcode":"28042",
    "sg:province":"Madrid",
    "wof:name":"Aducotrans S.l.",
    "wof:placetype":"venue"
},
  "geometry": {"coordinates":[-3.5800209045,40.4591674805],"type":"Point"}
}