{
  "type": "Feature",
  "properties": {
    "addr:full":"Trva San Anton, S/n Miguel Esteban Toledo 45830",
    "addr:housenumber":"s / n",
    "addr:postcode":"45830",
    "addr:street":"Trva San Anton;Miguel Esteban",
    "iso:country":"ES",
    "sg:address":"Trva San Anton, S/n",
    "sg:city":"Miguel Esteban",
    "sg:orig_category":"Agentes Generales De Seguros",
    "sg:phone":"+34 925 17 24 12",
    "sg:postcode":"45830",
    "sg:province":"Toledo",
    "wof:name":"Bilbao Compa\u00f1ia Anonima De Seguros",
    "wof:placetype":"venue"
},
  "geometry": {"coordinates":[-3.0731639862,39.5223007202],"type":"Point"}
}