{
  "type": "Feature",
  "properties": {
    "addr:full":"Ctra. Del Puerto, Km. 0001,0 Sanlucar C\u00e1diz 11540",
    "addr:postcode":"11540",
    "addr:street":"Ctra. Del Puerto Km. 0001,0",
    "iso:country":"ES",
    "sg:address":"Ctra. Del Puerto, Km. 0001,0",
    "sg:city":"Sanlucar",
    "sg:orig_category":"Frutas Y Legumbres Frescas (al Por Mayor)",
    "sg:phone":"+34 956 38 51 63",
    "sg:postcode":"11540",
    "sg:province":"C\u00e1diz",
    "wof:name":"Frutas Y Hortalizas Sanluque\u00f1as S.l.",
    "wof:placetype":"venue"
},
  "geometry": {"coordinates":[-6.2902097702,36.5298614502],"type":"Point"}
}