{
  "type": "Feature",
  "properties": {
    "iso:country":"ES",
    "sg:address":"Avda Principes De Espa\u00d1a, 14",
    "sg:city":"Rota",
    "sg:orig_category":"Cajas De Ahorro",
    "sg:phone":"+34 956 81 03 93",
    "sg:postcode":"11520",
    "sg:province":"C\u00e1diz",
    "sg:website":"www.unicaja.es",
    "wof:name":"Unicaja",
    "wof:placetype":"venue"
},
  "geometry": {"coordinates":[-6.3603048325,36.6250152588],"type":"Point"}
}