{
  "type": "Feature",
  "properties": {
    "iso:country":"ES",
    "sg:address":"Carrer de Mas De Larrard, 20",
    "sg:city":"Reus",
    "sg:orig_category":"Promotores Constructores",
    "sg:phone":"+34 977 75 71 59",
    "sg:postcode":"43204",
    "sg:province":"Tarragona",
    "wof:name":"Cardona Torrents Juan",
    "wof:placetype":"venue"
},
  "geometry": {"coordinates":[1.1219769716,41.1492042542],"type":"Point"}
}