{
  "type": "Feature",
  "properties": {
    "iso:country":"ES",
    "sg:address":"Calle de Vallejo, 6",
    "sg:city":"Horche",
    "sg:orig_category":"Supermercados Y Hipermercados",
    "sg:phone":"+34 949 29 07 15",
    "sg:postcode":"19140",
    "sg:province":"Guadalajara",
    "wof:name":"Lozano Sanchez Ruben",
    "wof:placetype":"venue"
},
  "geometry": {"coordinates":[-3.0639119148,40.5658988953],"type":"Point"}
}