{
  "type": "Feature",
  "properties": {
    "addr:full":"Calle de Baleares (playa De Las Americas), 1 Torviscas Centro Santa Cruz De Tenerife 38660",
    "addr:housenumber":"1",
    "addr:postcode":"38660",
    "addr:street":"Calle De Baleares Playa De Las Americas",
    "iso:country":"ES",
    "sg:address":"Calle de Baleares (playa De Las Americas), 1",
    "sg:city":"Torviscas Centro",
    "sg:orig_category":"Centros Empresariales",
    "sg:phone":"+34 922 71 94 92",
    "sg:postcode":"38660",
    "sg:province":"Santa Cruz De Tenerife",
    "wof:name":"Circulo De Empresarios Tenerife Sur S.l.",
    "wof:placetype":"venue"
},
  "geometry": {"coordinates":[-16.2548561096,28.4698104858],"type":"Point"}
}