{
  "type": "Feature",
  "properties": {
    "addr:full":"Calle de Humanitarias, 23 Madrid Madrid 28025",
    "addr:housenumber":"23",
    "addr:postcode":"madrid;28025",
    "addr:street":"Calle De Humanitarias",
    "iso:country":"ES",
    "sg:address":"Calle de Humanitarias, 23",
    "sg:city":"Madrid",
    "sg:orig_category":"Fabricaci\u00d3n De Muebles",
    "sg:phone":"+34 915 25 26 53",
    "sg:postcode":"28025",
    "sg:province":"Madrid",
    "wof:name":"Lopez Del Rio Laureano",
    "wof:placetype":"venue"
},
  "geometry": {"coordinates":[-3.7403199673,40.3878173828],"type":"Point"}
}