{
  "type": "Feature",
  "properties": {
    "iso:country":"ES",
    "sg:address":"El Si, 1",
    "sg:city":"Sta Cruz Tenerife",
    "sg:orig_category":"Abogados",
    "sg:phone":"+34 922 24 33 22",
    "sg:postcode":"38002",
    "sg:province":"Santa Cruz De Tenerife",
    "wof:name":"Bango Arocha Julia",
    "wof:placetype":"venue"
},
  "geometry": {"coordinates":[-17.2191944122,28.1820106506],"type":"Point"}
}