{
  "type": "Feature",
  "properties": {
    "addr:full":"Pol. Llanos, 33 Zamora Zamora 49001",
    "addr:housenumber":"33",
    "addr:postcode":"49001",
    "addr:street":"Pol. Llanos",
    "iso:country":"ES",
    "sg:address":"Pol. Llanos, 33",
    "sg:city":"Zamora",
    "sg:orig_category":"Frutas Y Legumbres Frescas (al Por Mayor)",
    "sg:phone":"+34 980 53 82 37",
    "sg:postcode":"49001",
    "sg:province":"Zamora",
    "wof:name":"Flecha Barrio Carlos",
    "wof:placetype":"venue"
},
  "geometry": {"coordinates":[-5.7457342148,41.5033302307],"type":"Point"}
}