{
  "type": "Feature",
  "properties": {
    "addr:full":"Calle de Rio Cuzna, S/n Atalayuela Madrid 28906",
    "addr:housenumber":"s",
    "addr:postcode":"28906",
    "addr:street":"Calle De Rio Cuzna;/ N Atalayuela",
    "iso:country":"ES",
    "sg:address":"Calle de Rio Cuzna, S/n",
    "sg:city":"Atalayuela",
    "sg:orig_category":"Estudios, Instalaci\u00d3n De Climatizaci\u00d3n",
    "sg:phone":"+34 916 21 31 90",
    "sg:postcode":"28906",
    "sg:province":"Madrid",
    "wof:name":"Parmaz S.l.",
    "wof:placetype":"venue"
},
  "geometry": {"coordinates":[-3.6941070557,40.2783584595],"type":"Point"}
}