{
  "type": "Feature",
  "properties": {
    "addr:full":"Carr Mallols, 5 Escala Girona 17130",
    "addr:housenumber":"5",
    "addr:postcode":"17130",
    "addr:street":"Carr Mallols",
    "iso:country":"ES",
    "sg:address":"Carr Mallols, 5",
    "sg:city":"Escala",
    "sg:orig_category":"Agencias Y Agentes Comerciales, Representantes",
    "sg:phone":"+34 972 77 51 61",
    "sg:postcode":"17130",
    "sg:province":"Girona",
    "wof:name":"Lloyt  Pauline",
    "wof:placetype":"venue"
},
  "geometry": {"coordinates":[3.1321649551,42.1229934692],"type":"Point"}
}