{
  "type": "Feature",
  "properties": {
    "addr:full":"Calle de Blasco De Garay, 26 Madrid Madrid 28015",
    "addr:housenumber":"26",
    "addr:postcode":"madrid;28015",
    "addr:street":"Calle De Blasco De Garay",
    "iso:country":"ES",
    "sg:address":"Calle de Blasco De Garay, 26",
    "sg:city":"Madrid",
    "sg:orig_category":"Librer\u00cdas",
    "sg:phone":"+34 915 94 36 36",
    "sg:postcode":"28015",
    "sg:province":"Madrid",
    "wof:name":"Rodriguez Barba Isabel",
    "wof:placetype":"venue"
},
  "geometry": {"coordinates":[-3.7116904259,40.4321022034],"type":"Point"}
}