{
  "type": "Feature",
  "properties": {
    "addr:full":"Av J Ortega Y Gasset (p I Alameda), 208 Malaga M\u00e1laga 29...",
    "addr:housenumber":"208;29 ...",
    "addr:street":"Av J Ortega Y Gasset;Alameda;Ma\u0301Laga",
    "iso:country":"ES",
    "sg:address":"Av J Ortega Y Gasset (p I Alameda), 208",
    "sg:city":"Malaga",
    "sg:orig_category":"Ingeniero",
    "sg:phone":"+34 952 04 56 00",
    "sg:postcode":"29...",
    "sg:province":"M\u00e1laga",
    "sg:website":"www.buscperson.es",
    "wof:name":"Grupo Busc Person Telecomunicaciones S.l.",
    "wof:placetype":"venue"
},
  "geometry": {"coordinates":[-4.4689970016,36.7067756653],"type":"Point"}
}