{
  "type": "Feature",
  "properties": {
    "addr:full":"Calle de El Cruce, 7 Llanera Asturias 33424",
    "addr:housenumber":"7",
    "addr:postcode":"33424",
    "addr:street":"Calle De El Cruce",
    "iso:country":"ES",
    "sg:address":"Calle de El Cruce, 7",
    "sg:city":"Llanera",
    "sg:orig_category":"Mantenimiento Industrial",
    "sg:phone":"+34 985 77 30 06",
    "sg:postcode":"33424",
    "sg:province":"Asturias",
    "wof:name":"Electrollanera S.l.l",
    "wof:placetype":"venue"
},
  "geometry": {"coordinates":[-5.8462991714,43.4367218018],"type":"Point"}
}