{
  "type": "Feature",
  "properties": {
    "iso:country":"ES",
    "sg:address":"Carr Jacint Verdaguer, 2",
    "sg:city":"Mollerussa",
    "sg:orig_category":"Telas Y Sedas (al Por Menor)",
    "sg:phone":"+34 973 60 04 24",
    "sg:postcode":"25230",
    "sg:province":"Lleida",
    "wof:name":"Salvado Torrent Luis",
    "wof:placetype":"venue"
},
  "geometry": {"coordinates":[0.8947839737,41.6295700073],"type":"Point"}
}