{
  "type": "Feature",
  "properties": {
    "addr:full":"Calle de Cerro De San Cristobal, 40 Jaen Ja\u00e9n 23002",
    "addr:housenumber":"40;jae\u0301n",
    "addr:postcode":"23002",
    "addr:street":"Calle De Cerro De San Cristobal",
    "iso:country":"ES",
    "sg:address":"Calle de Cerro De San Cristobal, 40",
    "sg:city":"Jaen",
    "sg:orig_category":"Ingeniero",
    "sg:phone":"+34 953 24 38 37",
    "sg:postcode":"23002",
    "sg:province":"Ja\u00e9n",
    "wof:name":"Ramirez Ruiz Natividad",
    "wof:placetype":"venue"
},
  "geometry": {"coordinates":[-3.7858924866,37.7622146606],"type":"Point"}
}