{
  "type": "Feature",
  "properties": {
    "iso:country":"ES",
    "sg:address":"Calle de Torpedero Tucuman, 28",
    "sg:city":"Madrid",
    "sg:orig_category":"Molduras, Junquillos, Listones Y Molduras Perforadas",
    "sg:phone":"+34 913 59 12 93",
    "sg:postcode":"28016",
    "sg:province":"Madrid",
    "wof:name":"Estebanez Portillo Francisco Jose",
    "wof:placetype":"venue"
},
  "geometry": {"coordinates":[-3.6722519398,40.4625396729],"type":"Point"}
}