{
  "type": "Feature",
  "properties": {
    "addr:full":"Calle de Mayor, 10 Casas-iba\u00e7ez Albacete 02200",
    "addr:housenumber":"10",
    "addr:postcode":"02200",
    "addr:street":"Calle De Mayor",
    "iso:country":"ES",
    "sg:address":"Calle de Mayor, 10",
    "sg:city":"Casas-iba\u00e7ez",
    "sg:orig_category":"Asociaciones Y Clubs Deportivos",
    "sg:phone":"+34 967 46 04 74",
    "sg:postcode":"02200",
    "sg:province":"Albacete",
    "wof:name":"Garijo Jimenez Juan",
    "wof:placetype":"venue"
},
  "geometry": {"coordinates":[-1.4705489874,39.2872009277],"type":"Point"}
}