{
  "type": "Feature",
  "properties": {
    "iso:country":"ES",
    "sg:address":"Calle de Sierra Toledana, 11",
    "sg:city":"Madrid",
    "sg:orig_category":"Asociaciones Y Clubs Deportivos",
    "sg:phone":"+34 914 37 66 09",
    "sg:postcode":"28038",
    "sg:province":"Madrid",
    "wof:name":"Linea Femenina S.l.",
    "wof:placetype":"venue"
},
  "geometry": {"coordinates":[-3.6606810093,40.3999786377],"type":"Point"}
}