{
  "type": "Feature",
  "properties": {
    "addr:full":"Carrer de Joan Duch, 76 Terrassa Barcelona 08222",
    "addr:housenumber":"76",
    "addr:postcode":"08222",
    "addr:street":"Carrer De Joan Duch",
    "iso:country":"ES",
    "sg:address":"Carrer de Joan Duch, 76",
    "sg:city":"Terrassa",
    "sg:orig_category":"Electricidad: Equipos Industriales, Componentes (fabricaci\u00d3n)",
    "sg:phone":"+34 937 84 55 29",
    "sg:postcode":"08222",
    "sg:province":"Barcelona",
    "wof:name":"Sbi Connectors Espa\u00d1a S.a.",
    "wof:placetype":"venue"
},
  "geometry": {"coordinates":[2.0174100399,41.5689697266],"type":"Point"}
}