{
  "type": "Feature",
  "properties": {
    "iso:country":"ES",
    "sg:address":"Cmno Consuegra, 2",
    "sg:city":"Urda",
    "sg:orig_category":"Cerrajer\u00cda, Ferrallista",
    "sg:phone":"+34 925 47 40 21",
    "sg:postcode":"45480",
    "sg:province":"Toledo",
    "wof:name":"Moreno Comino Asuncion",
    "wof:placetype":"venue"
},
  "geometry": {"coordinates":[-3.7161819935,39.4132804871],"type":"Point"}
}