{
  "type": "Feature",
  "properties": {
    "addr:full":"La Glorieta (p I Pesquero Norte), S/n Huelva Huelva 21002",
    "addr:housenumber":"s / n",
    "addr:postcode":"21002",
    "addr:street":"P I Pesquero Norte",
    "iso:country":"ES",
    "sg:address":"La Glorieta (p I Pesquero Norte), S/n",
    "sg:city":"Huelva",
    "sg:orig_category":"Navegaci\u00d3n (equipos Fluviales)",
    "sg:phone":"+34 959 24 91 55",
    "sg:postcode":"21002",
    "sg:province":"Huelva",
    "wof:name":"Asociacion De Armadores De Buques De Pesca Fresca",
    "wof:placetype":"venue"
},
  "geometry": {"coordinates":[-6.9603133202,37.2688446045],"type":"Point"}
}