{
  "type": "Feature",
  "properties": {
    "iso:country":"ES",
    "sg:address":"Rua Santa Lucia (da), 26",
    "sg:city":"Rairo",
    "sg:orig_category":"Ingeniero",
    "sg:phone":"+34 988 25 23 44",
    "sg:postcode":"32971",
    "sg:province":"Ourense",
    "wof:name":"Mari\u00f1o Belascoain Ramon",
    "wof:placetype":"venue"
},
  "geometry": {"coordinates":[-7.8308048248,42.3189277649],"type":"Point"}
}