{
  "type": "Feature",
  "properties": {
    "iso:country":"ES",
    "sg:address":"Avda Alcalde Jose Ramirez Bethencourt, 32",
    "sg:city":"Palmas De Gran Canaria",
    "sg:orig_category":"Abogados",
    "sg:phone":"+34 928 24 25 24",
    "sg:postcode":"35004",
    "sg:province":"Las Palmas",
    "wof:name":"Ojeda Perez Alberto Juan",
    "wof:placetype":"venue"
},
  "geometry": {"coordinates":[-15.420425415,28.117433548],"type":"Point"}
}