{
  "type": "Feature",
  "properties": {
    "iso:country":"ES",
    "sg:address":"Carrer de Major, 68",
    "sg:city":"Mora Nova",
    "sg:orig_category":"Electricidad: Instaladores",
    "sg:phone":"+34 977 40 03 60",
    "sg:postcode":"43770",
    "sg:province":"Tarragona",
    "wof:name":"Electricitat Ayet Montamat S.c.p.",
    "wof:placetype":"venue"
},
  "geometry": {"coordinates":[0.6504110098,41.099697113],"type":"Point"}
}