{
  "type": "Feature",
  "properties": {
    "addr:full":"Calle de Irala, 34 Bilbao Vizcaya 48012",
    "addr:housenumber":"34",
    "addr:postcode":"48012",
    "addr:street":"Calle De Irala",
    "iso:country":"ES",
    "sg:address":"Calle de Irala, 34",
    "sg:city":"Bilbao",
    "sg:orig_category":"Cl\u00cdnicas Dentales",
    "sg:phone":"+34 944 10 05 30",
    "sg:postcode":"48012",
    "sg:province":"Vizcaya",
    "wof:name":"Abad Alonso Pedro",
    "wof:placetype":"venue"
},
  "geometry": {"coordinates":[-2.937697,43.251987],"type":"Point"}
}