{
  "type": "Feature",
  "properties": {
    "addr:full":"Calle de Juliobriga, 2 Reinosa Cantabria 39200",
    "addr:housenumber":"2",
    "addr:postcode":"39200",
    "addr:street":"Calle De Juliobriga",
    "iso:country":"ES",
    "sg:address":"Calle de Juliobriga, 2",
    "sg:city":"Reinosa",
    "sg:orig_category":"Confecci\u00d3n De Trajes Para Se\u00d1oras",
    "sg:phone":"+34 942 75 13 86",
    "sg:postcode":"39200",
    "sg:province":"Cantabria",
    "wof:name":"Torre Palacio Josefa",
    "wof:placetype":"venue"
},
  "geometry": {"coordinates":[-4.1395840645,42.9970397949],"type":"Point"}
}