{
  "type": "Feature",
  "properties": {
    "addr:full":"Calle de Vereda Fiscal, 28 Luz Santa Cruz De Tenerife 38340",
    "addr:housenumber":"28",
    "addr:postcode":"38340",
    "addr:street":"Calle De Vereda Fiscal",
    "iso:country":"ES",
    "sg:address":"Calle de Vereda Fiscal, 28",
    "sg:city":"Luz",
    "sg:orig_category":"Mataderos De Poller\u00cda",
    "sg:phone":"+34 922 57 18 79",
    "sg:postcode":"38340",
    "sg:province":"Santa Cruz De Tenerife",
    "wof:name":"Sada P.a. Canarias S.a.",
    "wof:placetype":"venue"
},
  "geometry": {"coordinates":[-16.388841629,28.4820804596],"type":"Point"}
}