{
  "type": "Feature",
  "properties": {
    "addr:full":"Avd. De Los Silos, 10 Pozoblanco C\u00f3rdoba 14400",
    "addr:housenumber":"10",
    "addr:postcode":"14400",
    "addr:street":"De Los Silos",
    "iso:country":"ES",
    "sg:address":"Avd. De Los Silos, 10",
    "sg:city":"Pozoblanco",
    "sg:orig_category":"Supermercados Y Hipermercados",
    "sg:phone":"+34 957 77 19 60",
    "sg:postcode":"14400",
    "sg:province":"C\u00f3rdoba",
    "sg:website":"www.mercadona.es",
    "wof:name":"Mercadona S.a.",
    "wof:placetype":"venue"
},
  "geometry": {"coordinates":[-4.8492288589,38.3810462952],"type":"Point"}
}