{
  "type": "Feature",
  "properties": {
    "addr:full":"Calle de Placilla, 4 Puerto De Santa Maria C\u00e1diz 11500",
    "addr:housenumber":"4",
    "addr:postcode":"11500",
    "addr:street":"Calle De Placilla;Ca\u0301Diz",
    "iso:country":"ES",
    "sg:address":"Calle de Placilla, 4",
    "sg:city":"Puerto De Santa Maria",
    "sg:orig_category":"Material Y Suministros Para Peluquer\u00cda",
    "sg:phone":"+34 956 85 50 50",
    "sg:postcode":"11500",
    "sg:province":"C\u00e1diz",
    "wof:name":"Galvez Alegre Ana Maria",
    "wof:placetype":"venue"
},
  "geometry": {"coordinates":[-6.2267608643,36.5999221802],"type":"Point"}
}