{
  "type": "Feature",
  "properties": {
    "addr:full":"Av Vila De Madrid, 18 Blanes Girona 17300",
    "addr:housenumber":"18",
    "addr:postcode":"17300",
    "addr:street":"Av Vila De Madrid",
    "iso:country":"ES",
    "sg:address":"Av Vila De Madrid, 18",
    "sg:city":"Blanes",
    "sg:orig_category":"Hoteles",
    "sg:phone":"+34 972 33 00 92",
    "sg:postcode":"17300",
    "sg:province":"Girona",
    "wof:name":"Hotestema S.l.",
    "wof:placetype":"venue"
},
  "geometry": {"coordinates":[2.7810211182,41.6616134644],"type":"Point"}
}