{
  "type": "Feature",
  "properties": {
    "iso:country":"ES",
    "sg:address":"Carr Alborache, 18",
    "sg:city":"Silla",
    "sg:orig_category":"Fabricaci\u00d3n De Muebles",
    "sg:phone":"+34 961 21 25 62",
    "sg:postcode":"46460",
    "sg:province":"Valencia",
    "wof:name":"Muebles Castejon S.l.",
    "wof:placetype":"venue"
},
  "geometry": {"coordinates":[-0.417858988,39.3685531616],"type":"Point"}
}