{
  "type": "Feature",
  "properties": {
    "addr:full":"Carrer de Sis, 3 Bonavista Tarragona 43100",
    "addr:housenumber":"3",
    "addr:postcode":"43100",
    "addr:street":"Carrer De Sis",
    "iso:country":"ES",
    "sg:address":"Carrer de Sis, 3",
    "sg:city":"Bonavista",
    "sg:orig_category":"Marketing Telef\u00d3nico",
    "sg:phone":"+34 977 55 41 17",
    "sg:postcode":"43100",
    "sg:province":"Tarragona",
    "wof:name":"Sistema De Qualitat D'aire Tarragona S.l.",
    "wof:placetype":"venue"
},
  "geometry": {"coordinates":[1.1939599514,41.1180839539],"type":"Point"}
}