{
  "type": "Feature",
  "properties": {
    "iso:country":"ES",
    "sg:address":"Calle de Rincon De Cabezuela, 2",
    "sg:city":"Plasencia",
    "sg:orig_category":"Electrodom\u00c9sticos (al Por Menor)",
    "sg:phone":"+34 927 41 39 75",
    "sg:postcode":"10600",
    "sg:province":"C\u00e1ceres",
    "wof:name":"Gutierrez Espada Manuel Candido",
    "wof:placetype":"venue"
},
  "geometry": {"coordinates":[-6.0951309204,40.0287055969],"type":"Point"}
}