{
  "type": "Feature",
  "properties": {
    "addr:full":"Cmno Claveria, 66 Garrapinillos Zaragoza 50190",
    "addr:housenumber":"66",
    "addr:postcode":"50190",
    "addr:street":"Cmno Claveria",
    "iso:country":"ES",
    "sg:address":"Cmno Claveria, 66",
    "sg:city":"Garrapinillos",
    "sg:orig_category":"Producci\u00d3n De Abonos Y De Fertilizantes",
    "sg:phone":"+34 976 78 05 48",
    "sg:postcode":"50190",
    "sg:province":"Zaragoza",
    "wof:name":"Agroluna S.l.",
    "wof:placetype":"venue"
},
  "geometry": {"coordinates":[-1.0283647776,41.6841888428],"type":"Point"}
}