{
  "type": "Feature",
  "properties": {
    "addr:full":"Avda Jarales, 4 Alacant Alicante 03010",
    "addr:housenumber":"4",
    "addr:postcode":"03010",
    "addr:street":"Avda Jarales",
    "iso:country":"ES",
    "sg:address":"Avda Jarales, 4",
    "sg:city":"Alacant",
    "sg:orig_category":"Inform\u00c1tica (estudios, Servicios, Asesor\u00cda, Formaci\u00d3n)",
    "sg:phone":"+34 965 16 71 34",
    "sg:postcode":"03010",
    "sg:province":"Alicante",
    "wof:name":"Servicios Informaticos De Software Y Telecomunicaciones S.l.",
    "wof:placetype":"venue"
},
  "geometry": {"coordinates":[-0.4949890077,38.3688697815],"type":"Point"}
}