{
  "type": "Feature",
  "properties": {
    "addr:full":"Calle de Chorrera (la), 13 Loeches Madrid 28890",
    "addr:housenumber":"13",
    "addr:postcode":"28890",
    "addr:street":"Calle De Chorrera La",
    "iso:country":"ES",
    "sg:address":"Calle de Chorrera (la), 13",
    "sg:city":"Loeches",
    "sg:orig_category":"Contables",
    "sg:phone":"+34 918 85 14 72",
    "sg:postcode":"28890",
    "sg:province":"Madrid",
    "wof:name":"Contabilidad Y Administracion Diaz S.l",
    "wof:placetype":"venue"
},
  "geometry": {"coordinates":[-3.4084396362,40.3845748901],"type":"Point"}
}