{
  "type": "Feature",
  "properties": {
    "iso:country":"ES",
    "sg:address":"Fusters, 8",
    "sg:city":"Alaquas",
    "sg:orig_category":"Productos Qu\u00cdmicos (fabricaci\u00d3n, Al Por Mayor)",
    "sg:phone":"+34 961 50 97 23",
    "sg:postcode":"46970",
    "sg:province":"Valencia",
    "wof:name":"Brugues S. A.",
    "wof:placetype":"venue"
},
  "geometry": {"coordinates":[-0.4749119878,39.4483718872],"type":"Point"}
}