{
  "type": "Feature",
  "properties": {
    "iso:country":"ES",
    "sg:address":"Avda La Barrosa, S/n",
    "sg:city":"Chiclana",
    "sg:orig_category":"Inmobiliaria (agencias)",
    "sg:phone":"+34 956 49 40 45",
    "sg:postcode":"11130",
    "sg:province":"C\u00e1diz",
    "sg:website":"www.barrosamar.com",
    "wof:name":"Barrosamar Gestion S.l.",
    "wof:placetype":"venue"
},
  "geometry": {"coordinates":[-6.1625790596,36.4035797119],"type":"Point"}
}