{
  "type": "Feature",
  "properties": {
    "addr:full":"Calle de San Torcuato, 43 Zamora Zamora 49014",
    "addr:housenumber":"43",
    "addr:postcode":"49014",
    "addr:street":"Calle De San Torcuato",
    "iso:country":"ES",
    "sg:address":"Calle de San Torcuato, 43",
    "sg:city":"Zamora",
    "sg:orig_category":"Formaci\u00d3n A Distancia, Por Correspondencia",
    "sg:phone":"+34 980 52 83 99",
    "sg:postcode":"49014",
    "sg:province":"Zamora",
    "wof:name":"Centro Asociado De La Uned",
    "wof:placetype":"venue"
},
  "geometry": {"coordinates":[-5.7434811592,41.5074386597],"type":"Point"}
}