{
  "type": "Feature",
  "properties": {
    "addr:full":"Calle de Cerro De Alamos Blancos, 57 Madrid Madrid 28035",
    "addr:housenumber":"57",
    "addr:postcode":"madrid;28035",
    "addr:street":"Calle De Cerro De Alamos Blancos",
    "iso:country":"ES",
    "sg:address":"Calle de Cerro De Alamos Blancos, 57",
    "sg:city":"Madrid",
    "sg:orig_category":"Inmobiliaria (agencias)",
    "sg:phone":"+34 913 76 70 18",
    "sg:postcode":"28035",
    "sg:province":"Madrid",
    "wof:name":"Santamaria Calvo Teodoro",
    "wof:placetype":"venue"
},
  "geometry": {"coordinates":[-3.7268760204,40.4887046814],"type":"Point"}
}