{
  "type": "Feature",
  "properties": {
    "iso:country":"ES",
    "sg:address":"Carrer de El.lipse, 16",
    "sg:city":"Hospitalet Llobregat",
    "sg:orig_category":"Centros Empresariales",
    "sg:phone":"+34 934 47 06 50",
    "sg:postcode":"08905",
    "sg:province":"Barcelona",
    "wof:name":"Mian  Waqar Haider",
    "wof:placetype":"venue"
},
  "geometry": {"coordinates":[2.1085779667,41.3732910156],"type":"Point"}
}