{
  "type": "Feature",
  "properties": {
    "iso:country":"ES",
    "sg:address":"Avda Jose Quintana, 4",
    "sg:city":"Salda\u00f1a",
    "sg:orig_category":"Asesor\u00cda Sobre Comunicaci\u00d3n De Empresas",
    "sg:phone":"+34 979 89 15 05",
    "sg:postcode":"34100",
    "sg:province":"Palencia",
    "wof:name":"Asesores Tecnicos Rurales S.l.",
    "wof:placetype":"venue"
},
  "geometry": {"coordinates":[-4.7417426109,42.5200233459],"type":"Point"}
}