{
  "type": "Feature",
  "properties": {
    "addr:full":"Calle de Jesus Noya, 4 Viveiro Lugo 27850",
    "addr:housenumber":"4",
    "addr:postcode":"27850",
    "addr:street":"Calle De Jesus Noya",
    "iso:country":"ES",
    "sg:address":"Calle de Jesus Noya, 4",
    "sg:city":"Viveiro",
    "sg:orig_category":"Agencias Y Agentes Comerciales, Representantes",
    "sg:phone":"+34 982 56 25 83",
    "sg:postcode":"27850",
    "sg:province":"Lugo",
    "wof:name":"Moreira Moledo Ernesto",
    "wof:placetype":"venue"
},
  "geometry": {"coordinates":[-7.5927791595,43.6631355286],"type":"Point"}
}