{
  "type": "Feature",
  "properties": {
    "iso:country":"ES",
    "sg:address":"Calle de Juslibol, 23",
    "sg:city":"Zaragoza",
    "sg:orig_category":"Iglesia Cat\u00d3lica",
    "sg:phone":"+34 976 51 39 82",
    "sg:postcode":"50015",
    "sg:province":"Zaragoza",
    "wof:name":"Parroquia De Nuestra Se\u00f1oa De Belen",
    "wof:placetype":"venue"
},
  "geometry": {"coordinates":[-0.8735010028,41.6705932617],"type":"Point"}
}