{
  "type": "Feature",
  "properties": {
    "addr:full":"Calle de Oca, 75 Madrid Madrid 28025",
    "addr:housenumber":"75",
    "addr:postcode":"madrid;28025",
    "addr:street":"Calle De Oca",
    "iso:country":"ES",
    "sg:address":"Calle de Oca, 75",
    "sg:city":"Madrid",
    "sg:orig_category":"Agencias Y Agentes Comerciales, Representantes",
    "sg:phone":"+34 914 62 17 15",
    "sg:postcode":"28025",
    "sg:province":"Madrid",
    "wof:name":"Aragoneses De Diego Eutiquio",
    "wof:placetype":"venue"
},
  "geometry": {"coordinates":[-3.7408664227,40.3885955811],"type":"Point"}
}