{
  "type": "Feature",
  "properties": {
    "addr:full":"Zuaznabar Kalea, 56 Ugaldetxo Guip\u00f9zcoa 20180",
    "addr:housenumber":"56",
    "addr:postcode":"20180",
    "addr:street":"Zuaznabar Kalea;Guipu\u0300Zcoa",
    "iso:country":"ES",
    "sg:address":"Zuaznabar Kalea, 56",
    "sg:city":"Ugaldetxo",
    "sg:orig_category":"Material Y Suministros Para Fabricar Y Transformar El Papel Y El Cart\u00d3n",
    "sg:phone":"+34 943 49 37 50",
    "sg:postcode":"20180",
    "sg:province":"Guip\u00f9zcoa",
    "wof:name":"Investigacion Sistemas Papeleros S.l.",
    "wof:placetype":"venue"
},
  "geometry": {"coordinates":[-1.8827621937,43.2982254028],"type":"Point"}
}