{
  "type": "Feature",
  "properties": {
    "iso:country":"ES",
    "sg:address":"Calle de Calvo Sotelo, 15",
    "sg:city":"Santander",
    "sg:orig_category":"Abogados",
    "sg:phone":"+34 942 31 36 20",
    "sg:postcode":"39002",
    "sg:province":"Cantabria",
    "wof:name":"Ruiz De Villa Gomez Setien Manuel",
    "wof:placetype":"venue"
},
  "geometry": {"coordinates":[-3.8077046871,43.4614715576],"type":"Point"}
}