{
  "type": "Feature",
  "properties": {
    "iso:country":"ES",
    "sg:address":"La Serna, S/n",
    "sg:city":"Sasamon",
    "sg:orig_category":"Piedra Natural",
    "sg:phone":"+34 947 37 05 00",
    "sg:postcode":"09123",
    "sg:province":"Burgos",
    "wof:name":"Carrasco Carrasco Uldarico",
    "wof:placetype":"venue"
},
  "geometry": {"coordinates":[-4.0432810783,42.4154052734],"type":"Point"}
}