{
  "type": "Feature",
  "properties": {
    "iso:country":"ES",
    "sg:address":"Avenida De Cantabria, 16",
    "sg:city":"Torrelavega",
    "sg:orig_category":"Arquitectos",
    "sg:phone":"+34 942 88 47 01",
    "sg:postcode":"39300",
    "sg:province":"Cantabria",
    "wof:name":"Arquitectura Tecnica Torrelavega S.l.",
    "wof:placetype":"venue"
},
  "geometry": {"coordinates":[-4.0540990829,43.3410377502],"type":"Point"}
}