{
  "type": "Feature",
  "properties": {
    "addr:full":"Carrer de Enric Granados, 44 Barcelona Barcelona 08008",
    "addr:housenumber":"44",
    "addr:postcode":"08008",
    "addr:street":"Carrer De Enric Granados",
    "iso:country":"ES",
    "sg:address":"Carrer de Enric Granados, 44",
    "sg:city":"Barcelona",
    "sg:orig_category":"Abogados",
    "sg:phone":"+34 934 39 93 13",
    "sg:postcode":"08008",
    "sg:province":"Barcelona",
    "wof:name":"Canalda-ramoneda S.l.",
    "wof:placetype":"venue"
},
  "geometry": {"coordinates":[2.1583139896,41.3910751343],"type":"Point"}
}