{
  "type": "Feature",
  "properties": {
    "addr:full":"Avda Borbolla (la), 45 Sevilla Sevilla 41013",
    "addr:housenumber":"45",
    "addr:postcode":"41013",
    "addr:street":"Avda Borbolla La",
    "iso:country":"ES",
    "sg:address":"Avda Borbolla (la), 45",
    "sg:city":"Sevilla",
    "sg:orig_category":"Mataderos Y Talleres De Despiezado",
    "sg:phone":"+34 954 23 46 57",
    "sg:postcode":"41013",
    "sg:province":"Sevilla",
    "wof:name":"Nicolas Gil Blanco S. L.",
    "wof:placetype":"venue"
},
  "geometry": {"coordinates":[-5.9852352142,37.3736724854],"type":"Point"}
}