{
  "type": "Feature",
  "properties": {
    "addr:full":"Calle de Saavedra, 51 Gijon Asturias 33208",
    "addr:housenumber":"51",
    "addr:postcode":"33208",
    "addr:street":"Calle De Saavedra",
    "iso:country":"ES",
    "sg:address":"Calle de Saavedra, 51",
    "sg:city":"Gijon",
    "sg:orig_category":"Rectificaci\u00d3n, Mecanizado, Fresado",
    "sg:phone":"+34 985 38 76 27",
    "sg:postcode":"33208",
    "sg:province":"Asturias",
    "wof:name":"Marin Gonzalez Francisco Javier",
    "wof:placetype":"venue"
},
  "geometry": {"coordinates":[-5.6644258499,43.5321311951],"type":"Point"}
}