{
  "type": "Feature",
  "properties": {
    "iso:country":"ES",
    "sg:address":"Gaiferos, 26",
    "sg:city":"Tomelloso",
    "sg:orig_category":"Promotores Constructores",
    "sg:phone":"+34 926 51 52 51",
    "sg:postcode":"13700",
    "sg:province":"Ciudad Real",
    "wof:name":"Reformas Diaz Nevado S.l.",
    "wof:placetype":"venue"
},
  "geometry": {"coordinates":[-3.0295090675,39.1581611633],"type":"Point"}
}