{
  "type": "Feature",
  "properties": {
    "addr:full":"Avda Madrid, 235 Zaragoza Zaragoza 50017",
    "addr:housenumber":"235",
    "addr:postcode":"50017",
    "addr:street":"Avda Madrid",
    "iso:country":"ES",
    "sg:address":"Avda Madrid, 235",
    "sg:city":"Zaragoza",
    "sg:orig_category":"Aparcamientos (infraestructuras, Accesorios)",
    "sg:phone":"+34 976 33 40 88",
    "sg:postcode":"50017",
    "sg:province":"Zaragoza",
    "wof:name":"Juste Y Otro C.b.",
    "wof:placetype":"venue"
},
  "geometry": {"coordinates":[-0.9113889933,41.6518516541],"type":"Point"}
}