{
  "type": "Feature",
  "properties": {
    "iso:country":"ES",
    "sg:address":"Calle de Tomas Romero De Castilla, 3",
    "sg:city":"Badajoz",
    "sg:orig_category":"Aud\u00cdfonos",
    "sg:phone":"+34 924 25 37 88",
    "sg:postcode":"06011",
    "sg:province":"Badajoz",
    "wof:name":"Gonzalez Garcia Patricio",
    "wof:placetype":"venue"
},
  "geometry": {"coordinates":[-6.9826412201,38.8707962036],"type":"Point"}
}