{
  "type": "Feature",
  "properties": {
    "iso:country":"ES",
    "sg:address":"Calle de Sotera De La Mier, 8",
    "sg:city":"Portugalete",
    "sg:orig_category":"Empresas De Carpinter\u00cda",
    "sg:phone":"+34 944 95 36 76",
    "sg:postcode":"48920",
    "sg:province":"Vizcaya",
    "wof:name":"Florencio Prado Jacinto",
    "wof:placetype":"venue"
},
  "geometry": {"coordinates":[-3.0144369602,43.3175048828],"type":"Point"}
}