{
  "type": "Feature",
  "properties": {
    "addr:full":"Calle de Mirador De La Reina, 93 Madrid Madrid 28035",
    "addr:housenumber":"93",
    "addr:postcode":"madrid;28035",
    "addr:street":"Calle De Mirador De La Reina",
    "iso:country":"ES",
    "sg:address":"Calle de Mirador De La Reina, 93",
    "sg:city":"Madrid",
    "sg:orig_category":"Arquitectos",
    "sg:phone":"+34 913 76 30 53",
    "sg:postcode":"28035",
    "sg:province":"Madrid",
    "wof:name":"Navares Gonzalez Jose Luis",
    "wof:placetype":"venue"
},
  "geometry": {"coordinates":[-3.7255170345,40.4889068604],"type":"Point"}
}