{
  "type": "Feature",
  "properties": {
    "addr:full":"Calle de Antonia Diaz, 23 Marchena Sevilla 41620",
    "addr:housenumber":"23",
    "addr:postcode":"41620",
    "addr:street":"Calle De Antonia Diaz",
    "iso:country":"ES",
    "sg:address":"Calle de Antonia Diaz, 23",
    "sg:city":"Marchena",
    "sg:orig_category":"Ense\u00d1anza: Profesiones Art\u00cdsticas",
    "sg:phone":"+34 954 84 34 29",
    "sg:postcode":"41620",
    "sg:province":"Sevilla",
    "wof:name":"Gomez Garcia Rosario",
    "wof:placetype":"venue"
},
  "geometry": {"coordinates":[-5.4170360565,37.3289031982],"type":"Point"}
}