{
  "type": "Feature",
  "properties": {
    "iso:country":"ES",
    "sg:address":"Luga Loma De Pando, 14",
    "sg:city":"Oviedo",
    "sg:orig_category":"Centros De Educaci\u00d3n Especial",
    "sg:phone":"+34 985 28 36 63",
    "sg:postcode":"33011",
    "sg:province":"Asturias",
    "wof:name":"Principado De Asturias",
    "wof:placetype":"venue"
},
  "geometry": {"coordinates":[-5.8241991997,43.3843231201],"type":"Point"}
}