{
  "type": "Feature",
  "properties": {
    "iso:country":"ES",
    "sg:address":"Calle de Fernandez De Los Rios, 61",
    "sg:city":"Yebenes",
    "sg:orig_category":"Estudios, Instalaci\u00d3n De Climatizaci\u00d3n",
    "sg:phone":"+34 925 34 81 24",
    "sg:postcode":"45470",
    "sg:province":"Toledo",
    "wof:name":"Bricolaje Y Clima S.l.",
    "wof:placetype":"venue"
},
  "geometry": {"coordinates":[-3.8631389141,39.5809211731],"type":"Point"}
}