{
  "type": "Feature",
  "properties": {
    "addr:full":"Avda Lorca, 37 Sangonera Seca Murcia 30835",
    "addr:housenumber":"37",
    "addr:postcode":"30835",
    "addr:street":"Avda Lorca",
    "iso:country":"ES",
    "sg:address":"Avda Lorca, 37",
    "sg:city":"Sangonera Seca",
    "sg:orig_category":"Reciclaje, Desguace De Veh\u00cdculos",
    "sg:phone":"+34 968 80 26 07",
    "sg:postcode":"30835",
    "sg:province":"Murcia",
    "wof:name":"Hilario Martinez S.l.",
    "wof:placetype":"venue"
},
  "geometry": {"coordinates":[-1.2273789644,37.9609642029],"type":"Point"}
}