{
  "type": "Feature",
  "properties": {
    "addr:full":"Calle de Almendralejo, 8 Merida Badajoz 06800",
    "addr:housenumber":"8",
    "addr:postcode":"06800",
    "addr:street":"Calle De Almendralejo",
    "iso:country":"ES",
    "sg:address":"Calle de Almendralejo, 8",
    "sg:city":"Merida",
    "sg:orig_category":"Panader\u00cdas, Panader\u00cdas",
    "sg:phone":"+34 924 31 29 96",
    "sg:postcode":"06800",
    "sg:province":"Badajoz",
    "wof:name":"Just Chocolat Cafe, S.l.",
    "wof:placetype":"venue"
},
  "geometry": {"coordinates":[-6.3489360809,38.9181137085],"type":"Point"}
}