{
  "type": "Feature",
  "properties": {
    "addr:full":"Consejo De Ciento, 2 Jaca Huesca 22700",
    "addr:postcode":"22700",
    "addr:street":"Ciento",
    "iso:country":"ES",
    "sg:address":"Consejo De Ciento, 2",
    "sg:city":"Jaca",
    "sg:orig_category":"Notarios",
    "sg:phone":"+34 974 36 07 02",
    "sg:postcode":"22700",
    "sg:province":"Huesca",
    "wof:name":"Yuste Gonzalez De Rueda Juan Antonio",
    "wof:placetype":"venue"
},
  "geometry": {"coordinates":[-0.5512686968,42.5747528076],"type":"Point"}
}