{
  "type": "Feature",
  "properties": {
    "addr:full":"Calle de Garcia Lorca, 78 Macael Almer\u00eda 04867",
    "addr:housenumber":"78",
    "addr:postcode":"04867",
    "addr:street":"Calle De Garcia Lorca",
    "iso:country":"ES",
    "sg:address":"Calle de Garcia Lorca, 78",
    "sg:city":"Macael",
    "sg:orig_category":"Agencias Y Agentes Comerciales, Representantes",
    "sg:phone":"+34 950 44 53 51",
    "sg:postcode":"04867",
    "sg:province":"Almer\u00eda",
    "wof:name":"Valera Garcia Cristobal",
    "wof:placetype":"venue"
},
  "geometry": {"coordinates":[-2.302241087,37.3343658447],"type":"Point"}
}