{
  "type": "Feature",
  "properties": {
    "iso:country":"ES",
    "sg:address":"Pl. Des Ramal, 11",
    "sg:city":"Alaior",
    "sg:orig_category":"Asilos De Ancianos. Centros Privados",
    "sg:phone":"+34 971 37 84 15",
    "sg:postcode":"07730",
    "sg:province":"Islas Baleares",
    "wof:name":"Club De Jubilados Y Entidad Cultural De Alaior",
    "wof:placetype":"venue"
},
  "geometry": {"coordinates":[4.1372509003,39.9336776733],"type":"Point"}
}