{
  "type": "Feature",
  "properties": {
    "addr:full":"Ptda Balafia, 23 Gualda Lleida 25191",
    "addr:housenumber":"23",
    "addr:postcode":"25191",
    "addr:street":"Ptda Balafia",
    "iso:country":"ES",
    "sg:address":"Ptda Balafia, 23",
    "sg:city":"Gualda",
    "sg:orig_category":"Producci\u00d3n, Venta De Productos De Agricultura Biol\u00d3gica",
    "sg:phone":"+34 973 23 47 05",
    "sg:postcode":"25191",
    "sg:province":"Lleida",
    "wof:name":"Menal Tremosa Antonio",
    "wof:placetype":"venue"
},
  "geometry": {"coordinates":[0.6831650138,41.5832138062],"type":"Point"}
}