{
  "type": "Feature",
  "properties": {
    "iso:country":"ES",
    "sg:address":"Carrer de Industria, 30",
    "sg:city":"Barcelona",
    "sg:orig_category":"Molduras, Junquillos, Listones Y Molduras Perforadas",
    "sg:phone":"+34 932 07 72 18",
    "sg:postcode":"08025",
    "sg:province":"Barcelona",
    "wof:name":"Guerra Pazos Soledad",
    "wof:placetype":"venue"
},
  "geometry": {"coordinates":[2.1664984226,41.4035606384],"type":"Point"}
}