{
  "type": "Feature",
  "properties": {
    "iso:country":"ES",
    "sg:address":"Calle de Olvido, 40",
    "sg:city":"Madrid",
    "sg:orig_category":"Edici\u00d3n De Diarios, Revistas, Boletines",
    "sg:phone":"+34 914 76 70 44",
    "sg:postcode":"28026",
    "sg:province":"Madrid",
    "wof:name":"Sanchez Mejias Jose",
    "wof:placetype":"venue"
},
  "geometry": {"coordinates":[-3.7027668953,40.3856964111],"type":"Point"}
}