{
  "type": "Feature",
  "properties": {
    "addr:full":"Cmno Iglesia, 38 Coru\u00d1a La Coru\u00f1a 15009",
    "addr:housenumber":"38",
    "addr:postcode":"15009",
    "addr:street":"Cmno Iglesia;Corun\u0303A",
    "iso:country":"ES",
    "sg:address":"Cmno Iglesia, 38",
    "sg:city":"Coru\u00d1a",
    "sg:orig_category":"Arquitectos",
    "sg:phone":"+34 981 13 46 70",
    "sg:postcode":"15009",
    "sg:province":"La Coru\u00f1a",
    "wof:name":"Mi\u00f1ones Corzon Jose",
    "wof:placetype":"venue"
},
  "geometry": {"coordinates":[-8.4012012482,43.3481216431],"type":"Point"}
}