{
  "type": "Feature",
  "properties": {
    "addr:full":"Cmno Jayena, S/n Alhendin Granada 18620",
    "addr:housenumber":"s",
    "addr:postcode":"18620",
    "addr:street":"Cmno Jayena;/ N Alhendin",
    "iso:country":"ES",
    "sg:address":"Cmno Jayena, S/n",
    "sg:city":"Alhendin",
    "sg:orig_category":"Piedra, Vidrio, Cer\u00c1mica Y Porcelana",
    "sg:phone":"+34 958 57 60 18",
    "sg:postcode":"18620",
    "sg:province":"Granada",
    "wof:name":"Ceramicas Manuel Torres S.l",
    "wof:placetype":"venue"
},
  "geometry": {"coordinates":[-3.6460690498,37.1050987244],"type":"Point"}
}