{
  "type": "Feature",
  "properties": {
    "iso:country":"ES",
    "sg:address":"Carrer de Torrassa (de La), 11",
    "sg:city":"Salou",
    "sg:orig_category":"Arquitectos",
    "sg:phone":"+34 977 38 21 49",
    "sg:postcode":"43840",
    "sg:province":"Tarragona",
    "wof:name":"Elorza Garcia Isabel",
    "wof:placetype":"venue"
},
  "geometry": {"coordinates":[1.1493250132,41.0666923523],"type":"Point"}
}