{
  "type": "Feature",
  "properties": {
    "addr:full":"Carrer de Isidre Vilaro, 40 Calaf Barcelona 08280",
    "addr:housenumber":"40",
    "addr:postcode":"08280",
    "addr:street":"Carrer De Isidre Vilaro",
    "iso:country":"ES",
    "sg:address":"Carrer de Isidre Vilaro, 40",
    "sg:city":"Calaf",
    "sg:orig_category":"M\u00c1quinas Y Herramientas Para Trabajar La Piedra",
    "sg:phone":"+34 938 69 83 50",
    "sg:postcode":"08280",
    "sg:province":"Barcelona",
    "wof:name":"Argerich Mecanica S.l.",
    "wof:placetype":"venue"
},
  "geometry": {"coordinates":[1.5152560472,41.7327308655],"type":"Point"}
}