{
  "type": "Feature",
  "properties": {
    "addr:full":"Grup San Ignacio Etxe Taldea, 5 Mungia Vizcaya 48100",
    "addr:housenumber":"5",
    "addr:postcode":"48100",
    "addr:street":"Taldea",
    "iso:country":"ES",
    "sg:address":"Grup San Ignacio Etxe Taldea, 5",
    "sg:city":"Mungia",
    "sg:orig_category":"Empresas De Carpinter\u00cda De Madera",
    "sg:phone":"+34 946 74 06 72",
    "sg:postcode":"48100",
    "sg:province":"Vizcaya",
    "wof:name":"Jose Luis Agirre-xabier Uriagereka",
    "wof:placetype":"venue"
},
  "geometry": {"coordinates":[-2.842869997,43.3547439575],"type":"Point"}
}