{
  "type": "Feature",
  "properties": {
    "iso:country":"ES",
    "sg:address":"Avda Santa Maria, 29",
    "sg:city":"Meliana",
    "sg:orig_category":"Quincaller\u00cda (al Por Menor)",
    "sg:phone":"+34 961 49 07 34",
    "sg:postcode":"46133",
    "sg:province":"Valencia",
    "wof:name":"Establecimientos Rel S. L.",
    "wof:placetype":"venue"
},
  "geometry": {"coordinates":[-0.3506929874,39.5296821594],"type":"Point"}
}