{
  "type": "Feature",
  "properties": {
    "addr:full":"Rua Basqui\u00d1os (dos), 43 Santiago De Compostela La Coru\u00f1a 15704",
    "addr:housenumber":"43",
    "addr:postcode":"15704",
    "addr:street":"Rua Basquin\u0303Os Dos;Corun\u0303A",
    "iso:country":"ES",
    "sg:address":"Rua Basqui\u00d1os (dos), 43",
    "sg:city":"Santiago De Compostela",
    "sg:orig_category":"Florister\u00cdas",
    "sg:phone":"+34 981 57 38 69",
    "sg:postcode":"15704",
    "sg:province":"La Coru\u00f1a",
    "wof:name":"Fernandez Agra Jose Antonio",
    "wof:placetype":"venue"
},
  "geometry": {"coordinates":[-8.5396366119,42.8870582581],"type":"Point"}
}