{
  "type": "Feature",
  "properties": {
    "iso:country":"ES",
    "sg:address":"Calle de Juan Ramon Jimenez (de), 10",
    "sg:city":"El Cruce",
    "sg:orig_category":"Diet\u00c9tica: Productos Biol\u00d3gicos, Naturales Y Diet\u00c9ticos (fabricaci\u00d3n, Al Por Mayor)",
    "sg:phone":"+34 916 58 03 93",
    "sg:postcode":"28860",
    "sg:province":"Madrid",
    "wof:name":"Biodistribuccion Agroalimentaria S.l",
    "wof:placetype":"venue"
},
  "geometry": {"coordinates":[-3.5491809845,40.505569458],"type":"Point"}
}