{
  "type": "Feature",
  "properties": {
    "addr:full":"Calle de Altos Del Duero, S/n Le\u00f3n Le\u00f3n 24008",
    "addr:housenumber":"s",
    "addr:postcode":"24008",
    "addr:street":"Calle De Altos Del Duero;/ N Leo\u0301N Leo\u0301N",
    "iso:country":"ES",
    "sg:address":"Calle de Altos Del Duero, S/n",
    "sg:city":"Le\u00f3n",
    "sg:orig_category":"Ambulancias",
    "sg:phone":"+34 987 23 49 49",
    "sg:postcode":"24008",
    "sg:province":"Le\u00f3n",
    "wof:name":"Transanit Leon Sl Ute",
    "wof:placetype":"venue"
},
  "geometry": {"coordinates":[-5.5550928116,42.6448745728],"type":"Point"}
}