{
  "type": "Feature",
  "properties": {
    "addr:full":"Calle de Plaza (de La), 38 Chiclana De La Frontera C\u00e1diz 11130",
    "addr:housenumber":"38",
    "addr:postcode":"11130",
    "addr:street":"Calle De Plaza De La",
    "iso:country":"ES",
    "sg:address":"Calle de Plaza (de La), 38",
    "sg:city":"Chiclana De La Frontera",
    "sg:orig_category":"Expertos Contables",
    "sg:phone":"+34 956 49 01 92",
    "sg:postcode":"11130",
    "sg:province":"C\u00e1diz",
    "wof:name":"Asistencia Asesoramiento Y Tasaciones Tosso S.l.",
    "wof:placetype":"venue"
},
  "geometry": {"coordinates":[-6.1504855156,36.4195785522],"type":"Point"}
}