{
  "type": "Feature",
  "properties": {
    "addr:full":"Calle de Correo, 12 Bilbao Vizcaya 48005",
    "addr:housenumber":"12",
    "addr:postcode":"48005",
    "addr:street":"Calle De Correo",
    "iso:country":"ES",
    "sg:address":"Calle de Correo, 12",
    "sg:city":"Bilbao",
    "sg:orig_category":"Confiter\u00cdas, Chocolater\u00cdas (al Por Menor)",
    "sg:phone":"+34 944 16 68 79",
    "sg:postcode":"48005",
    "sg:province":"Vizcaya",
    "wof:name":"Iva\u00f1ez Garcia Adelia",
    "wof:placetype":"venue"
},
  "geometry": {"coordinates":[-2.9235408306,43.2585525513],"type":"Point"}
}