{
  "type": "Feature",
  "properties": {
    "iso:country":"ES",
    "sg:address":"Sequeiros, 1",
    "sg:city":"Sequeiros",
    "sg:orig_category":"Empresas De Carpinter\u00cda",
    "sg:phone":"+34 986 64 41 86",
    "sg:postcode":"36867",
    "sg:province":"Pontevedra",
    "wof:name":"Aluarmo S.l.l.",
    "wof:placetype":"venue"
},
  "geometry": {"coordinates":[-8.4777698517,42.9121704102],"type":"Point"}
}