{
  "type": "Feature",
  "properties": {
    "addr:full":"Plaz San Antonio, 10 Cadiz C\u00e1diz 11001",
    "addr:housenumber":"10",
    "addr:postcode":"11001",
    "addr:street":"Plaz San Antonio",
    "iso:country":"ES",
    "sg:address":"Plaz San Antonio, 10",
    "sg:city":"Cadiz",
    "sg:orig_category":"Obras Y Organismos Sociales",
    "sg:phone":"+34 956 22 28 09",
    "sg:postcode":"11001",
    "sg:province":"C\u00e1diz",
    "wof:name":"Lumen Dei",
    "wof:placetype":"venue"
},
  "geometry": {"coordinates":[-6.2976894379,36.5320510864],"type":"Point"}
}