{
  "type": "Feature",
  "properties": {
    "iso:country":"ES",
    "sg:address":"Calle de Cristina (la), 38",
    "sg:city":"Arrecife",
    "sg:orig_category":"Mec\u00c1nico Del Autom\u00d3vil",
    "sg:phone":"+34 928 81 53 02",
    "sg:postcode":"35500",
    "sg:province":"Las Palmas",
    "wof:name":"Servicios Del Automovil Lofran S.l.",
    "wof:placetype":"venue"
},
  "geometry": {"coordinates":[-13.5519914627,28.9695167542],"type":"Point"}
}