{
  "type": "Feature",
  "properties": {
    "addr:full":"Ctra. Gral. Murias, 26 Mieres Asturias 33640",
    "addr:housenumber":"26",
    "addr:postcode":"33640",
    "addr:street":"Ctra. Gral. Murias",
    "iso:country":"ES",
    "sg:address":"Ctra. Gral. Murias, 26",
    "sg:city":"Mieres",
    "sg:orig_category":"Cajas De Ahorro",
    "sg:phone":"+34 985 42 00 02",
    "sg:postcode":"33640",
    "sg:province":"Asturias",
    "sg:website":"www.cajastur.es",
    "wof:name":"Caja De Ahorros De Asturias",
    "wof:placetype":"venue"
},
  "geometry": {"coordinates":[-5.7913818359,43.2042694092],"type":"Point"}
}