{
  "type": "Feature",
  "properties": {
    "iso:country":"ES",
    "sg:address":"Calle de Menendez Y Pelayo, 8",
    "sg:city":"Entrego",
    "sg:orig_category":"Electricidad: Instaladores",
    "sg:phone":"+34 985 66 02 59",
    "sg:postcode":"33940",
    "sg:province":"Asturias",
    "wof:name":"Electronalon S.l.",
    "wof:placetype":"venue"
},
  "geometry": {"coordinates":[-5.6384181976,43.2872505188],"type":"Point"}
}