{
  "type": "Feature",
  "properties": {
    "iso:country":"ES",
    "sg:address":"Calle de Bizkai, 83",
    "sg:city":"Kurtzea",
    "sg:orig_category":"Deportes Y Ocio: Art\u00cdculos Y Ropas (al Por Menor Y Accesorios)",
    "sg:phone":"+34 944 56 50 85",
    "sg:postcode":"48960",
    "sg:province":"Vizcaya",
    "wof:name":"Almudena Y Jose Luis Pe\u00f1a Juarez C.b.",
    "wof:placetype":"venue"
},
  "geometry": {"coordinates":[-2.6983869076,43.2204284668],"type":"Point"}
}