{
  "type": "Feature",
  "properties": {
    "addr:full":"Avgd Miguel Hernandez, 19 Benifaio Valencia 46450",
    "addr:housenumber":"19",
    "addr:postcode":"46450",
    "addr:street":"Miguel Hernandez",
    "iso:country":"ES",
    "sg:address":"Avgd Miguel Hernandez, 19",
    "sg:city":"Benifaio",
    "sg:orig_category":"Promotores Constructores",
    "sg:phone":"+34 961 78 39 76",
    "sg:postcode":"46450",
    "sg:province":"Valencia",
    "wof:name":"Comunidad De Propietarios Miguel Hernandez 19",
    "wof:placetype":"venue"
},
  "geometry": {"coordinates":[-0.4233140051,39.2839622498],"type":"Point"}
}