{
  "type": "Feature",
  "properties": {
    "iso:country":"ES",
    "sg:address":"Calle de Rio Oja, 63",
    "sg:city":"Santurde",
    "sg:orig_category":"Transportes Por Carretera: Lotes Completos, Mercanc\u00cdas Diversas",
    "sg:phone":"+34 941 42 67 91",
    "sg:postcode":"26260",
    "sg:province":"La Rioja",
    "wof:name":"Martinez Ruiz Cayo",
    "wof:placetype":"venue"
},
  "geometry": {"coordinates":[-2.9792940617,42.389415741],"type":"Point"}
}