{
  "type": "Feature",
  "properties": {
    "iso:country":"ES",
    "sg:address":"Calle de Mijares, 3",
    "sg:city":"Villanueva De Avila",
    "sg:orig_category":"Sanatorios M\u00c9dico",
    "sg:phone":"+34 920 29 57 14",
    "sg:postcode":"05114",
    "sg:province":"\u00c1vila",
    "wof:name":"Ayuntamiento De Villanueva De Avila",
    "wof:placetype":"venue"
},
  "geometry": {"coordinates":[-4.8205447197,40.3785133362],"type":"Point"}
}