{
  "type": "Feature",
  "properties": {
    "addr:full":"Eivissa, 64 S. Quirze Valles Barcelona 08192",
    "addr:housenumber":"64",
    "addr:postcode":"08192",
    "addr:street":"Eivissa",
    "iso:country":"ES",
    "sg:address":"Eivissa, 64",
    "sg:city":"S. Quirze Valles",
    "sg:orig_category":"Planchado",
    "sg:phone":"+34 937 21 32 08",
    "sg:postcode":"08192",
    "sg:province":"Barcelona",
    "wof:name":"Presser Sabadell S. L.",
    "wof:placetype":"venue"
},
  "geometry": {"coordinates":[2.0947608948,41.5229911804],"type":"Point"}
}