{
  "type": "Feature",
  "properties": {
    "iso:country":"ES",
    "sg:address":"Calle de Virgen De Los Milagros, 114",
    "sg:city":"Puerto De Santa Maria",
    "sg:orig_category":"Asesor\u00cda Sobre Comunicaci\u00d3n De Empresas",
    "sg:phone":"+34 956 85 18 72",
    "sg:postcode":"11500",
    "sg:province":"C\u00e1diz",
    "wof:name":"Asociacion De Empresarios Del Puerto De Santa Maria",
    "wof:placetype":"venue"
},
  "geometry": {"coordinates":[-6.2262578011,36.5981369019],"type":"Point"}
}