{
  "type": "Feature",
  "properties": {
    "iso:country":"ES",
    "sg:address":"Carrer de Sant Domingo, 6",
    "sg:city":"Palma",
    "sg:orig_category":"Bazares, Art\u00cdculos De Limpieza Y De Cocina (al Por Menor)",
    "sg:phone":"+34 971 72 19 01",
    "sg:postcode":"07001",
    "sg:province":"Islas Baleares",
    "wof:name":"Alvarez Gonzalez Jose Ramon",
    "wof:placetype":"venue"
},
  "geometry": {"coordinates":[2.6491641998,39.5697059631],"type":"Point"}
}