{
  "type": "Feature",
  "properties": {
    "iso:country":"ES",
    "sg:address":"Pl. San Pedro, 19",
    "sg:city":"San Pedro",
    "sg:orig_category":"Partidos Pol\u00cdticos",
    "sg:phone":"+34 946 50 40 58",
    "sg:postcode":"48191",
    "sg:province":"Vizcaya",
    "wof:name":"Partido Nacionalista Vasco",
    "wof:placetype":"venue"
},
  "geometry": {"coordinates":[-3.0992720127,43.2543907166],"type":"Point"}
}