{
  "type": "Feature",
  "properties": {
    "addr:full":"Rua Zaragoza, 55 Vigo Pontevedra 36211",
    "addr:housenumber":"55",
    "addr:postcode":"36211",
    "addr:street":"Rua Zaragoza",
    "iso:country":"ES",
    "sg:address":"Rua Zaragoza, 55",
    "sg:city":"Vigo",
    "sg:orig_category":"Postigos, Persianas Y Celos\u00cdas",
    "sg:phone":"+34 986 47 17 00",
    "sg:postcode":"36211",
    "sg:province":"Pontevedra",
    "wof:name":"Coalper S. L.",
    "wof:placetype":"venue"
},
  "geometry": {"coordinates":[-8.7285070419,42.2232704163],"type":"Point"}
}