{
  "type": "Feature",
  "properties": {
    "addr:full":"Plaz Ayuntamiento, 3 Vegadeo Asturias 33770",
    "addr:housenumber":"3",
    "addr:postcode":"33770",
    "addr:street":"Ayuntamiento",
    "iso:country":"ES",
    "sg:address":"Plaz Ayuntamiento, 3",
    "sg:city":"Vegadeo",
    "sg:orig_category":"Molduras, Junquillos, Listones Y Molduras Perforadas",
    "sg:phone":"+34 985 47 63 69",
    "sg:postcode":"33770",
    "sg:province":"Asturias",
    "wof:name":"Diaz Prieto Cesar",
    "wof:placetype":"venue"
},
  "geometry": {"coordinates":[-7.0507240295,43.464225769],"type":"Point"}
}