{
  "type": "Feature",
  "properties": {
    "addr:full":"Avda Moris Marrodan, S/n Martos Ja\u00e9n 23600",
    "addr:housenumber":"s / n",
    "addr:postcode":"23600",
    "addr:street":"Avda Moris Marrodan;Jae\u0301N",
    "iso:country":"ES",
    "sg:address":"Avda Moris Marrodan, S/n",
    "sg:city":"Martos",
    "sg:orig_category":"Restaurantes",
    "sg:phone":"+34 953 55 49 46",
    "sg:postcode":"23600",
    "sg:province":"Ja\u00e9n",
    "wof:name":"Gallardo Torres Juan",
    "wof:placetype":"venue"
},
  "geometry": {"coordinates":[-3.9711153507,37.7173271179],"type":"Point"}
}