{
  "type": "Feature",
  "properties": {
    "iso:country":"ES",
    "sg:address":"Ntra Sra La Antigua, 4",
    "sg:city":"Villanueva Infantes",
    "sg:orig_category":"Herboristas (al Por Menor)",
    "sg:phone":"+34 926 36 15 69",
    "sg:postcode":"13320",
    "sg:province":"Ciudad Real",
    "wof:name":"Fernandez De Sevilla Gutierrez Ramon",
    "wof:placetype":"venue"
},
  "geometry": {"coordinates":[-3.0150830746,38.7367362976],"type":"Point"}
}