{
  "type": "Feature",
  "properties": {
    "addr:full":"Calle de Julian Diez, 17 Palencia Palencia 34004",
    "addr:housenumber":"17",
    "addr:postcode":"34004",
    "addr:street":"Calle De Julian Diez",
    "iso:country":"ES",
    "sg:address":"Calle de Julian Diez, 17",
    "sg:city":"Palencia",
    "sg:orig_category":"Agencias Y Agentes Comerciales, Representantes",
    "sg:phone":"+34 979 71 30 39",
    "sg:postcode":"34004",
    "sg:province":"Palencia",
    "wof:name":"Izquierdo Nieto Modesto",
    "wof:placetype":"venue"
},
  "geometry": {"coordinates":[-4.5248670578,42.0041923523],"type":"Point"}
}