{
  "type": "Feature",
  "properties": {
    "iso:country":"ES",
    "sg:address":"Calle de Luxemburgo, 8",
    "sg:city":"Roquetas Mar",
    "sg:orig_category":"Mec\u00c1nico Del Autom\u00d3vil",
    "sg:phone":"+34 950 32 76 67",
    "sg:postcode":"04740",
    "sg:province":"Almer\u00eda",
    "wof:name":"Maldonado Berenguel Juan Antonio",
    "wof:placetype":"venue"
},
  "geometry": {"coordinates":[-2.6042039394,36.7746696472],"type":"Point"}
}