{
  "type": "Feature",
  "properties": {
    "iso:country":"ES",
    "sg:address":"Avda Maria Auxiliadora, 20",
    "sg:city":"Rota",
    "sg:orig_category":"Librer\u00cdas",
    "sg:phone":"+34 956 81 14 67",
    "sg:postcode":"11520",
    "sg:province":"C\u00e1diz",
    "wof:name":"Perez Fernandez Enrique",
    "wof:placetype":"venue"
},
  "geometry": {"coordinates":[-6.3613290787,36.620891571],"type":"Point"}
}