{
  "type": "Feature",
  "properties": {
    "iso:country":"ES",
    "sg:address":"Ctra Moraira A Calpe, 124",
    "sg:city":"Moraira",
    "sg:orig_category":"Doctores En Medicina",
    "sg:phone":"+34 965 74 56 24",
    "sg:postcode":"03724",
    "sg:province":"Alicante",
    "wof:name":"Willis  Bernard David",
    "wof:placetype":"venue"
},
  "geometry": {"coordinates":[0.1223276034,38.6830863953],"type":"Point"}
}