{
  "type": "Feature",
  "properties": {
    "iso:country":"ES",
    "sg:address":"Carr Escoles (de Les), 20",
    "sg:city":"Artesa Lleida",
    "sg:orig_category":"Material Y Herramientas Agr\u00cdcolas",
    "sg:phone":"+34 973 16 75 99",
    "sg:postcode":"25150",
    "sg:province":"Lleida",
    "wof:name":"Lorentano S.l.",
    "wof:placetype":"venue"
},
  "geometry": {"coordinates":[0.7057800293,41.5531044006],"type":"Point"}
}