{
  "type": "Feature",
  "properties": {
    "iso:country":"ES",
    "sg:address":"Calle de Pajares, S/n",
    "sg:city":"Santurtzi",
    "sg:orig_category":"Asociaciones Y Clubs Deportivos",
    "sg:phone":"+34 944 62 00 17",
    "sg:postcode":"48980",
    "sg:province":"Vizcaya",
    "wof:name":"Club Deportivo Santurtzi",
    "wof:placetype":"venue"
},
  "geometry": {"coordinates":[-3.038216114,43.3235359192],"type":"Point"}
}