{
  "type": "Feature",
  "properties": {
    "iso:country":"ES",
    "sg:address":"Pg Espronceda, 62",
    "sg:city":"Sabadell",
    "sg:orig_category":"Electrodom\u00c9sticos (al Por Menor)",
    "sg:phone":"+34 937 11 61 51",
    "sg:postcode":"08204",
    "sg:province":"Barcelona",
    "wof:name":"Remle S.a.",
    "wof:placetype":"venue"
},
  "geometry": {"coordinates":[2.1153318882,41.52866745],"type":"Point"}
}