{
  "type": "Feature",
  "properties": {
    "iso:country":"ES",
    "sg:address":"Avda Cristobal De Murrieta, 38",
    "sg:city":"Santurtzi",
    "sg:orig_category":"Moquetas, Alfombras (al Por Menor)",
    "sg:phone":"+34 944 83 52 00",
    "sg:postcode":"48980",
    "sg:province":"Vizcaya",
    "wof:name":"Miloudi Belhasoub",
    "wof:placetype":"venue"
},
  "geometry": {"coordinates":[-3.0402638912,43.3327636719],"type":"Point"}
}