{
  "type": "Feature",
  "properties": {
    "addr:full":"Calle de Luis De Cappa, 1 Melilla Melilla 52005",
    "addr:housenumber":"1",
    "addr:postcode":"52005",
    "addr:street":"Calle De Luis De Cappa",
    "iso:country":"ES",
    "sg:address":"Calle de Luis De Cappa, 1",
    "sg:city":"Melilla",
    "sg:orig_category":"Ropa Para Se\u00d1oras Y Caballeros (al Por Menor)",
    "sg:phone":"+34 952 67 49 51",
    "sg:postcode":"52005",
    "sg:province":"Melilla",
    "wof:name":"Mateo Vizcaino Maria Jose",
    "wof:placetype":"venue"
},
  "geometry": {"coordinates":[-2.9475820065,35.2895889282],"type":"Point"}
}