{
  "type": "Feature",
  "properties": {
    "addr:full":"Avda Antonio Sandi, 2 Santillana Cantabria 39330",
    "addr:housenumber":"2",
    "addr:postcode":"39330",
    "addr:street":"Avda Antonio Sandi",
    "iso:country":"ES",
    "sg:address":"Avda Antonio Sandi, 2",
    "sg:city":"Santillana",
    "sg:orig_category":"Molduras, Junquillos, Listones Y Molduras Perforadas",
    "sg:phone":"+34 942 81 80 02",
    "sg:postcode":"39330",
    "sg:province":"Cantabria",
    "wof:name":"Bustamante Ruiz Enrique",
    "wof:placetype":"venue"
},
  "geometry": {"coordinates":[-4.1099262238,43.3877334595],"type":"Point"}
}