{
  "type": "Feature",
  "properties": {
    "addr:full":"Avda Madre Paula Montalt, 19 Quinto Sevilla 41089",
    "addr:housenumber":"19",
    "addr:postcode":"41089",
    "addr:street":"Avda Madre Paula Montalt",
    "iso:country":"ES",
    "sg:address":"Avda Madre Paula Montalt, 19",
    "sg:city":"Quinto",
    "sg:orig_category":"Negocio De Madera",
    "sg:phone":"+34 954 12 65 46",
    "sg:postcode":"41089",
    "sg:province":"Sevilla",
    "wof:name":"Maderas Robesa S.l.",
    "wof:placetype":"venue"
},
  "geometry": {"coordinates":[-5.9962949753,37.3826408386],"type":"Point"}
}