{
  "type": "Feature",
  "properties": {
    "iso:country":"ES",
    "sg:address":"Calle de Corredera, 29",
    "sg:city":"Toro",
    "sg:orig_category":"Poller\u00cda Y Caza (al Por Menor)",
    "sg:phone":"+34 980 69 10 96",
    "sg:postcode":"49800",
    "sg:province":"Zamora",
    "wof:name":"Martin Gonzalez Francisco",
    "wof:placetype":"venue"
},
  "geometry": {"coordinates":[-5.3924078941,41.5235939026],"type":"Point"}
}