{
  "type": "Feature",
  "properties": {
    "addr:full":"Av Cister, 31 Secar De La Real Islas Baleares 07010",
    "addr:housenumber":"31",
    "addr:postcode":"07010",
    "addr:street":"Av Cister",
    "iso:country":"ES",
    "sg:address":"Av Cister, 31",
    "sg:city":"Secar De La Real",
    "sg:orig_category":"Agencias De Viajes",
    "sg:phone":"+34 971 76 82 50",
    "sg:postcode":"07010",
    "sg:province":"Islas Baleares",
    "wof:name":"Viajes Canals S.a.",
    "wof:placetype":"venue"
},
  "geometry": {"coordinates":[2.6363110542,39.6081161499],"type":"Point"}
}