{
  "type": "Feature",
  "properties": {
    "addr:full":"Calle de Joaquin Arellano, 1 Getxo Vizcaya 48930",
    "addr:housenumber":"1",
    "addr:postcode":"48930",
    "addr:street":"Calle De Joaquin Arellano",
    "iso:country":"ES",
    "sg:address":"Calle de Joaquin Arellano, 1",
    "sg:city":"Getxo",
    "sg:orig_category":"Disfraces",
    "sg:phone":"+34 944 63 36 65",
    "sg:postcode":"48930",
    "sg:province":"Vizcaya",
    "wof:name":"Libano Zumalakarregui Magdalena",
    "wof:placetype":"venue"
},
  "geometry": {"coordinates":[-3.0123949051,43.3258972168],"type":"Point"}
}