{
  "type": "Feature",
  "properties": {
    "addr:full":"Calle de Rocio, 3 Salamanca Salamanca 37004",
    "addr:housenumber":"3",
    "addr:postcode":"37004",
    "addr:street":"Calle De Rocio",
    "iso:country":"ES",
    "sg:address":"Calle de Rocio, 3",
    "sg:city":"Salamanca",
    "sg:orig_category":"Electricidad Veh\u00cdculo",
    "sg:phone":"+34 923 22 42 18",
    "sg:postcode":"37004",
    "sg:province":"Salamanca",
    "wof:name":"Briz Sanchez Jose",
    "wof:placetype":"venue"
},
  "geometry": {"coordinates":[-5.6525130272,40.9771957397],"type":"Point"}
}