{
  "type": "Feature",
  "properties": {
    "iso:country":"ES",
    "sg:address":"Calle de Dolores Rodriguez Sope\u00d1a, 4",
    "sg:city":"Almeria",
    "sg:orig_category":"Hoteles",
    "sg:phone":"+34 950 23 11 11",
    "sg:postcode":"04004",
    "sg:province":"Almer\u00eda",
    "wof:name":"Citymar Hoteles Y Apartamentos S.l.",
    "wof:placetype":"venue"
},
  "geometry": {"coordinates":[-2.4600090981,36.8412322998],"type":"Point"}
}