{
  "type": "Feature",
  "properties": {
    "addr:full":"Plaz Rinconada, 8 Valladolid Valladolid 47001",
    "addr:housenumber":"8",
    "addr:postcode":"47001",
    "addr:street":"Rinconada",
    "iso:country":"ES",
    "sg:address":"Plaz Rinconada, 8",
    "sg:city":"Valladolid",
    "sg:orig_category":"Telas Para Tapizar, Cortinas, Pasamaner\u00cda (fabricaci\u00d3n, Al Por Mayor)",
    "sg:phone":"+34 983 34 29 26",
    "sg:postcode":"47001",
    "sg:province":"Valladolid",
    "wof:name":"Armendia Pato Jose Antonio",
    "wof:placetype":"venue"
},
  "geometry": {"coordinates":[-4.7289447784,41.6531639099],"type":"Point"}
}