{
  "type": "Feature",
  "properties": {
    "addr:full":"Calle de Dolores, 36 Jerez De La Frontera C\u00e1diz 11401",
    "addr:housenumber":"36",
    "addr:postcode":"11401",
    "addr:street":"Calle De Dolores",
    "iso:country":"ES",
    "sg:address":"Calle de Dolores, 36",
    "sg:city":"Jerez De La Frontera",
    "sg:orig_category":"Laboratorios Dentales",
    "sg:phone":"+34 956 14 24 53",
    "sg:postcode":"11401",
    "sg:province":"C\u00e1diz",
    "wof:name":"Puertasur S.c.",
    "wof:placetype":"venue"
},
  "geometry": {"coordinates":[-6.1412324905,36.6773529053],"type":"Point"}
}