{
  "type": "Feature",
  "properties": {
    "addr:full":"Calle de Padre Polanco, 27 Zaragoza Zaragoza 50008",
    "addr:housenumber":"27",
    "addr:postcode":"50008",
    "addr:street":"Calle De Padre Polanco",
    "iso:country":"ES",
    "sg:address":"Calle de Padre Polanco, 27",
    "sg:city":"Zaragoza",
    "sg:orig_category":"Arreglo, Reparaci\u00d3n, Piezas Sueltas De Televisi\u00d3n, V\u00cddeo, Hi",
    "sg:phone":"+34 976 49 51 11",
    "sg:postcode":"50008",
    "sg:province":"Zaragoza",
    "wof:name":"Servicio Asistencia Tecnica Concertada S.l.",
    "wof:placetype":"venue"
},
  "geometry": {"coordinates":[-0.877515018,41.6391487122],"type":"Point"}
}