{
  "type": "Feature",
  "properties": {
    "addr:full":"Plaz Arenal Celestino M. Del, 14 Bilbao Vizcaya 48015",
    "addr:postcode":"48015",
    "addr:street":"Plaz",
    "iso:country":"ES",
    "sg:address":"Plaz Arenal Celestino M. Del, 14",
    "sg:city":"Bilbao",
    "sg:classifiers":[
        {
            "category":"Personal",
            "subcategory":"Barber",
            "type":"Services"
        }
    ],
    "sg:phone":"+34 944 47 08 44",
    "sg:postcode":"48015",
    "sg:province":"Vizcaya",
    "sg:tags":[
        "caballeros",
        "de",
        "peluqueros"
    ],
    "wof:name":"Villaran Andoain Oscar",
    "wof:placetype":"venue"
},
  "geometry": {"coordinates":[-2.9569990635,43.2757110596],"type":"Point"}
}