{
  "type": "Feature",
  "properties": {
    "iso:country":"ES",
    "sg:address":"Maisu Guridi Kalea, 3",
    "sg:city":"Arrasate",
    "sg:orig_category":"Frutas, Legumbres Frescas Y Tempranas (al Por Menor)",
    "sg:phone":"+34 943 71 29 99",
    "sg:postcode":"20500",
    "sg:province":"Guip\u00f9zcoa",
    "wof:name":"Perez Ma\u00f1anes , M\u00aa Jose",
    "wof:placetype":"venue"
},
  "geometry": {"coordinates":[-2.4930388927,43.0605773926],"type":"Point"}
}