{
  "type": "Feature",
  "properties": {
    "iso:country":"ES",
    "sg:address":"Pl Camp De Les Peces, S/n",
    "sg:city":"Casc Antic",
    "sg:orig_category":"Centros Empresariales",
    "sg:phone":"+34 935 62 05 14",
    "sg:postcode":"08150",
    "sg:province":"Barcelona",
    "wof:name":"Mateos Garcia Albert",
    "wof:placetype":"venue"
},
  "geometry": {"coordinates":[2.2293000221,41.5678787231],"type":"Point"}
}