{
  "type": "Feature",
  "properties": {
    "iso:country":"ES",
    "sg:address":"Calle de Nagusia, 19",
    "sg:city":"Arizgoiti",
    "sg:orig_category":"Librer\u00cdas",
    "sg:phone":"+34 944 49 39 10",
    "sg:postcode":"48970",
    "sg:province":"Vizcaya",
    "wof:name":"Vicente Garate Roberto",
    "wof:placetype":"venue"
},
  "geometry": {"coordinates":[-2.8847229481,43.2370414734],"type":"Point"}
}