{
  "type": "Feature",
  "properties": {
    "iso:country":"ES",
    "sg:address":"Carr Rosas (de Las), 6",
    "sg:city":"Manises",
    "sg:orig_category":"Enfermeras: Consultas, Atenci\u00d3n A Domicilio",
    "sg:phone":"+34 961 52 26 24",
    "sg:postcode":"46940",
    "sg:province":"Valencia",
    "wof:name":"Zamora De Los Dolores Ramon",
    "wof:placetype":"venue"
},
  "geometry": {"coordinates":[-0.4623320997,39.4909515381],"type":"Point"}
}