{
  "type": "Feature",
  "properties": {
    "iso:country":"ES",
    "sg:address":"Calle de Palomares, 30",
    "sg:city":"Iscar",
    "sg:orig_category":"Comercio, Reparaci\u00d3n De Motocicletas, Bicicletas Y Piezas Sueltas",
    "sg:phone":"+34 983 61 16 86",
    "sg:postcode":"47420",
    "sg:province":"Valladolid",
    "wof:name":"Rico Molina Roberto",
    "wof:placetype":"venue"
},
  "geometry": {"coordinates":[-4.5332689285,41.3613433838],"type":"Point"}
}