{
  "type": "Feature",
  "properties": {
    "addr:full":"Calle de Beatriz De Bobadilla, 13 Madrid Madrid 28040",
    "addr:housenumber":"13",
    "addr:postcode":"madrid;28040",
    "addr:street":"Calle De Beatriz De Bobadilla",
    "iso:country":"ES",
    "sg:address":"Calle de Beatriz De Bobadilla, 13",
    "sg:city":"Madrid",
    "sg:orig_category":"Arquitectos",
    "sg:phone":"+34 915 54 06 81",
    "sg:postcode":"28040",
    "sg:province":"Madrid",
    "wof:name":"Emaus S.l.",
    "wof:placetype":"venue"
},
  "geometry": {"coordinates":[-3.7153937817,40.4482383728],"type":"Point"}
}