{
  "type": "Feature",
  "properties": {
    "iso:country":"ES",
    "sg:address":"Calle de Reyes Huertas, S/n",
    "sg:city":"Merida",
    "sg:orig_category":"Pe\u00d1as Y Asociaciones Varias",
    "sg:phone":"+34 924 30 39 94",
    "sg:postcode":"06800",
    "sg:province":"Badajoz",
    "sg:website":"www.echaunamano.org",
    "wof:name":"Plataforma Del Voluntariado De Merida Y Comarca",
    "wof:placetype":"venue"
},
  "geometry": {"coordinates":[-6.3536338806,38.9106636047],"type":"Point"}
}