{
  "type": "Feature",
  "properties": {
    "iso:country":"ES",
    "sg:address":"Petritegi Bidea, 14",
    "sg:city":"Astigarraga",
    "sg:orig_category":"Aguas (distribuci\u00d3n, Servicios)",
    "sg:phone":"+34 943 47 05 88",
    "sg:postcode":"20115",
    "sg:province":"Guip\u00f9zcoa",
    "wof:name":"Aguas Del A\u00f1arbe S.a.-a\u00f1arbeko Urak S.a.",
    "wof:placetype":"venue"
},
  "geometry": {"coordinates":[-1.9394241571,43.2924079895],"type":"Point"}
}