{
  "type": "Feature",
  "properties": {
    "addr:full":"Carrer de Carrer de Europa, 2 Puerto Rico Las Palmas 35130",
    "addr:housenumber":"2",
    "addr:postcode":"35130",
    "addr:street":"Carrer;Carrer De Europa;Rico",
    "iso:country":"ES",
    "sg:address":"Carrer de Carrer de Europa, 2",
    "sg:city":"Puerto Rico",
    "sg:orig_category":"Peluquer\u00cdas, Peluquer\u00cda Mixta",
    "sg:phone":"+34 928 72 52 85",
    "sg:postcode":"35130",
    "sg:province":"Las Palmas",
    "wof:name":"Alamo Artiles Maria Jesus",
    "wof:placetype":"venue"
},
  "geometry": {"coordinates":[-15.7186183929,27.7882995605],"type":"Point"}
}