{
  "type": "Feature",
  "properties": {
    "addr:full":"Calle de Arturo Soria, 285 Madrid Madrid 28...",
    "addr:housenumber":"285;28 ...",
    "addr:street":"Calle De Arturo Soria;Madrid",
    "iso:country":"ES",
    "sg:address":"Calle de Arturo Soria, 285",
    "sg:city":"Madrid",
    "sg:orig_category":"Ense\u00d1anza, Formaci\u00d3n Profesional: Aprendizaje",
    "sg:phone":"+34 913 79 56 00",
    "sg:postcode":"28...",
    "sg:province":"Madrid",
    "wof:name":"Cuartel General De La Armada",
    "wof:placetype":"venue"
},
  "geometry": {"coordinates":[-3.6676456928,40.4722518921],"type":"Point"}
}