{
  "type": "Feature",
  "properties": {
    "iso:country":"ES",
    "sg:address":"Calle de Cervantes, 29",
    "sg:city":"Montoro",
    "sg:orig_category":"Muebles, Minoristas",
    "sg:phone":"+34 957 16 08 53",
    "sg:postcode":"14600",
    "sg:province":"C\u00f3rdoba",
    "wof:name":"Moreno Calero Martin",
    "wof:placetype":"venue"
},
  "geometry": {"coordinates":[-4.3830933571,38.0187187195],"type":"Point"}
}