{
  "type": "Feature",
  "properties": {
    "addr:full":"Avda Principe De Espa\u00d1a, 32 Mancha Santa Cruz De Tenerife 38430",
    "addr:housenumber":"32",
    "addr:postcode":"38430",
    "addr:street":"Avda Principe De Espan\u0303A",
    "iso:country":"ES",
    "sg:address":"Avda Principe De Espa\u00d1a, 32",
    "sg:city":"Mancha",
    "sg:orig_category":"Frutas Y Legumbres Frescas (al Por Mayor)",
    "sg:phone":"+34 922 12 25 11",
    "sg:postcode":"38430",
    "sg:province":"Santa Cruz De Tenerife",
    "wof:name":"Frutas De Calidad S.l.",
    "wof:placetype":"venue"
},
  "geometry": {"coordinates":[-16.7204761505,28.3677654266],"type":"Point"}
}