{
  "type": "Feature",
  "properties": {
    "addr:full":"Carr Concordia, 18 Alpicat Lleida 25110",
    "addr:housenumber":"18",
    "addr:postcode":"25110",
    "addr:street":"Carr Concordia",
    "iso:country":"ES",
    "sg:address":"Carr Concordia, 18",
    "sg:city":"Alpicat",
    "sg:orig_category":"Empresas De Electricidad En General",
    "sg:phone":"+34 973 73 73 79",
    "sg:postcode":"25110",
    "sg:province":"Lleida",
    "wof:name":"Insta%acions Electriques Catalanes S.a.",
    "wof:placetype":"venue"
},
  "geometry": {"coordinates":[0.5297340155,41.6597290039],"type":"Point"}
}