{
  "type": "Feature",
  "properties": {
    "iso:country":"ES",
    "sg:address":"Avda Alicante, 28",
    "sg:city":"Monforte Cid",
    "sg:orig_category":"Loter\u00cda Y T\u00d3mbola",
    "sg:phone":"+34 965 62 13 12",
    "sg:postcode":"03670",
    "sg:province":"Alicante",
    "wof:name":"Alberola Iborra Maria Reyes",
    "wof:placetype":"venue"
},
  "geometry": {"coordinates":[-0.7286331058,38.3800163269],"type":"Point"}
}