{
  "type": "Feature",
  "properties": {
    "iso:country":"ES",
    "sg:address":"Avda Galicia De, S/n",
    "sg:city":"Caridad",
    "sg:orig_category":"Asociaciones, Organismos Culturales Y Socioeducativos",
    "sg:phone":"+34 985 47 86 41",
    "sg:postcode":"33750",
    "sg:province":"Asturias",
    "wof:name":"Ayuntamiento De El Franco",
    "wof:placetype":"venue"
},
  "geometry": {"coordinates":[-6.8270339966,43.5506744385],"type":"Point"}
}