{
  "type": "Feature",
  "properties": {
    "iso:country":"ES",
    "sg:address":"Calle de Menorca, 1",
    "sg:city":"Humanes De Madrid",
    "sg:orig_category":"Peluquer\u00cdas, Peluquer\u00cda Mixta",
    "sg:phone":"+34 916 04 28 51",
    "sg:postcode":"28970",
    "sg:province":"Madrid",
    "wof:name":"Martinez Martinez Maria Rosa",
    "wof:placetype":"venue"
},
  "geometry": {"coordinates":[-3.8217840195,40.2542762756],"type":"Point"}
}