{
  "type": "Feature",
  "properties": {
    "iso:country":"ES",
    "sg:address":"Carrer de Fortuny (de), 23",
    "sg:city":"Tarragona",
    "sg:orig_category":"Cooperativas Agr\u00cdcolas",
    "sg:phone":"+34 977 21 11 48",
    "sg:postcode":"43001",
    "sg:province":"Tarragona",
    "wof:name":"Cooperativa Obrera Tarraconense",
    "wof:placetype":"venue"
},
  "geometry": {"coordinates":[1.2507230043,41.1145973206],"type":"Point"}
}