{
  "type": "Feature",
  "properties": {
    "iso:country":"ES",
    "sg:address":"Avgd Alacant, 2",
    "sg:city":"Lleida",
    "sg:orig_category":"Venta, Colocaci\u00d3n De Autoradios",
    "sg:phone":"+34 973 20 65 69",
    "sg:postcode":"25001",
    "sg:province":"Lleida",
    "wof:name":"Comercial Art S.a.",
    "wof:placetype":"venue"
},
  "geometry": {"coordinates":[0.631600976,41.6121520996],"type":"Point"}
}