{
  "type": "Feature",
  "properties": {
    "addr:full":"Calle de Carretera De Fuenterrabia, S/n Poblado Naval C\u00e1diz 11500",
    "addr:housenumber":"s",
    "addr:postcode":"11500",
    "addr:street":"Calle De Carretera De Fuenterrabia;/ N Poblado Naval Ca\u0301Diz",
    "iso:country":"ES",
    "sg:address":"Calle de Carretera De Fuenterrabia, S/n",
    "sg:city":"Poblado Naval",
    "sg:orig_category":"Agencias Y Agentes Comerciales, Representantes",
    "sg:phone":"+34 956 54 00 66",
    "sg:postcode":"11500",
    "sg:province":"C\u00e1diz",
    "wof:name":"Tesadero S.l.",
    "wof:placetype":"venue"
},
  "geometry": {"coordinates":[-6.2197542191,36.6056632996],"type":"Point"}
}