{
  "type": "Feature",
  "properties": {
    "addr:full":"Calle de Sao Paulo, 43 Palmas De Gran Canaria Las Palmas 35008",
    "addr:housenumber":"43",
    "addr:postcode":"35008",
    "addr:street":"Calle De Sao Paulo",
    "iso:country":"ES",
    "sg:address":"Calle de Sao Paulo, 43",
    "sg:city":"Palmas De Gran Canaria",
    "sg:orig_category":"Fabricaci\u00d3n De Mobiliario De Oficina",
    "sg:phone":"+34 928 47 56 71",
    "sg:postcode":"35008",
    "sg:province":"Las Palmas",
    "wof:name":"Samper Croissier S.l.",
    "wof:placetype":"venue"
},
  "geometry": {"coordinates":[-15.4191236496,28.1577663422],"type":"Point"}
}