{
  "type": "Feature",
  "properties": {
    "addr:full":"Pg Maritim, 299 Castelldefels Barcelona 08860",
    "addr:housenumber":"299",
    "addr:postcode":"08860",
    "addr:street":"Pg Maritim",
    "iso:country":"ES",
    "sg:address":"Pg Maritim, 299",
    "sg:city":"Castelldefels",
    "sg:orig_category":"Agencias Y Agentes Comerciales, Representantes",
    "sg:phone":"+34 936 64 43 99",
    "sg:postcode":"08860",
    "sg:province":"Barcelona",
    "wof:name":"Jimenez Fonteboa Oscar",
    "wof:placetype":"venue"
},
  "geometry": {"coordinates":[1.9576510191,41.2654495239],"type":"Point"}
}