{
  "type": "Feature",
  "properties": {
    "addr:full":"Pla\u00c7 Ricard Vi\u00d1es, 2 Lleida Lleida 25006",
    "addr:housenumber":"2",
    "addr:postcode":"25006",
    "addr:street":"Vin\u0303Es",
    "iso:country":"ES",
    "sg:address":"Pla\u00c7 Ricard Vi\u00d1es, 2",
    "sg:city":"Lleida",
    "sg:orig_category":"Carnicer\u00cdas, Carnicer\u00cdas",
    "sg:phone":"+34 973 23 18 77",
    "sg:postcode":"25006",
    "sg:province":"Lleida",
    "wof:name":"Boloix Salvatella Albert",
    "wof:placetype":"venue"
},
  "geometry": {"coordinates":[0.6191689968,41.6186103821],"type":"Point"}
}