{
  "type": "Feature",
  "properties": {
    "iso:country":"ES",
    "sg:address":"Pase Zorrilla, 85",
    "sg:city":"Valladolid",
    "sg:orig_category":"Florister\u00cdas",
    "sg:phone":"+34 983 23 41 42",
    "sg:postcode":"47007",
    "sg:province":"Valladolid",
    "wof:name":"Marcos Garcia Susana",
    "wof:placetype":"venue"
},
  "geometry": {"coordinates":[-4.7395977974,41.6347579956],"type":"Point"}
}