{
  "type": "Feature",
  "properties": {
    "addr:full":"Calle de Jose Maria Mortes Lerma, 14 Valencia Valencia 46014",
    "addr:housenumber":"14",
    "addr:postcode":"46014",
    "addr:street":"Calle De Jose Maria Mortes Lerma",
    "iso:country":"ES",
    "sg:address":"Calle de Jose Maria Mortes Lerma, 14",
    "sg:city":"Valencia",
    "sg:orig_category":"Mec\u00c1nico Del Autom\u00d3vil",
    "sg:phone":"+34 963 78 99 06",
    "sg:postcode":"46014",
    "sg:province":"Valencia",
    "wof:name":"Jose Miguel Navarro S.l.",
    "wof:placetype":"venue"
},
  "geometry": {"coordinates":[-0.3989520073,39.4631919861],"type":"Point"}
}