{
  "type": "Feature",
  "properties": {
    "iso:country":"ES",
    "sg:address":"Carrer de Bruc, 146",
    "sg:city":"Barcelona",
    "sg:orig_category":"Cl\u00cdnicas Dentales",
    "sg:phone":"+34 934 58 70 72",
    "sg:postcode":"08037",
    "sg:province":"Barcelona",
    "wof:name":"Asociacion Dental Espa\u00f1ola S.a.",
    "wof:placetype":"venue"
},
  "geometry": {"coordinates":[2.1654911041,41.3973922729],"type":"Point"}
}