{
  "type": "Feature",
  "properties": {
    "addr:full":"C/ Mestre Guell, S/n Tarrega Lleida 25300",
    "addr:housenumber":"s / n",
    "addr:postcode":"25300",
    "addr:street":"C / Mestre Guell",
    "iso:country":"ES",
    "sg:address":"C/ Mestre Guell, S/n",
    "sg:city":"Tarrega",
    "sg:orig_category":"Caf\u00c9s, Bares, Cervecer\u00cdas",
    "sg:phone":"+34 973 31 10 34",
    "sg:postcode":"25300",
    "sg:province":"Lleida",
    "wof:name":"Fundacio Privada Colegi Sant Josep Vedruna",
    "wof:placetype":"venue"
},
  "geometry": {"coordinates":[1.1475499868,41.6509094238],"type":"Point"}
}