{
  "type": "Feature",
  "properties": {
    "addr:full":"Calle de Ramon Y Cajal, 2 Sauces Santa Cruz De Tenerife 38720",
    "addr:housenumber":"2",
    "addr:postcode":"38720",
    "addr:street":"Calle De Ramon Y Cajal",
    "iso:country":"ES",
    "sg:address":"Calle de Ramon Y Cajal, 2",
    "sg:city":"Sauces",
    "sg:orig_category":"Librer\u00cdas",
    "sg:phone":"+34 922 45 03 56",
    "sg:postcode":"38720",
    "sg:province":"Santa Cruz De Tenerife",
    "wof:name":"Libreria Iriarte S.l.",
    "wof:placetype":"venue"
},
  "geometry": {"coordinates":[-17.7734355927,28.8043575287],"type":"Point"}
}