{
  "type": "Feature",
  "properties": {
    "addr:full":"Poli Talluntxe / Talluntze Industrialdea, 71 Noain Navarra 31110",
    "addr:housenumber":"71",
    "addr:postcode":"31110",
    "addr:street":"Industrialdea",
    "iso:country":"ES",
    "sg:address":"Poli Talluntxe / Talluntze Industrialdea, 71",
    "sg:city":"Noain",
    "sg:orig_category":"Deportes Y Ocio: Art\u00cdculos Y Equipos (al Por Mayor)",
    "sg:phone":"+34 948 31 60 39",
    "sg:postcode":"31110",
    "sg:province":"Navarra",
    "sg:website":"www.ranking.es",
    "wof:name":"Ranking La Tienda Del Deporte S.l.",
    "wof:placetype":"venue"
},
  "geometry": {"coordinates":[-1.6338239908,42.7598800659],"type":"Point"}
}