{
  "type": "Feature",
  "properties": {
    "iso:country":"ES",
    "sg:address":"La Congosta, 15",
    "sg:city":"Navelgas",
    "sg:orig_category":"Vinos Y Licores (venta Al Por Menor)",
    "sg:phone":"+34 985 80 62 55",
    "sg:postcode":"33873",
    "sg:province":"Asturias",
    "wof:name":"Rubio Pelaez Carlos Celestino",
    "wof:placetype":"venue"
},
  "geometry": {"coordinates":[-6.5324959755,43.4251785278],"type":"Point"}
}