{
  "type": "Feature",
  "properties": {
    "addr:full":"Calle de Pilar De Zaragoza, 104 Madrid Madrid 28028",
    "addr:housenumber":"104",
    "addr:postcode":"28028",
    "addr:street":"Calle De Pilar De Zaragoza",
    "iso:country":"ES",
    "sg:address":"Calle de Pilar De Zaragoza, 104",
    "sg:city":"Madrid",
    "sg:orig_category":"M\u00c9dicos: Ginecolog\u00cda Y Obstetricia",
    "sg:phone":"+34 917 26 66 52",
    "sg:postcode":"28028",
    "sg:province":"Madrid",
    "wof:name":"Paniagua Ruano Juan Jose",
    "wof:placetype":"venue"
},
  "geometry": {"coordinates":[-3.6744399071,40.4383087158],"type":"Point"}
}