{
  "type": "Feature",
  "properties": {
    "iso:country":"ES",
    "sg:address":"Cmno Virgen De La Merced, 58",
    "sg:city":"Valladolid",
    "sg:orig_category":"Higiene, Belleza: Art\u00cdculos (al Por Menor)",
    "sg:phone":"+34 983 35 71 45",
    "sg:postcode":"47009",
    "sg:province":"Valladolid",
    "wof:name":"Cannon Hygiene S.a.",
    "wof:placetype":"venue"
},
  "geometry": {"coordinates":[-4.743347168,41.6613731384],"type":"Point"}
}