{
  "type": "Feature",
  "properties": {
    "iso:country":"ES",
    "sg:address":"Pg Verdaguer, 110",
    "sg:city":"Igualada",
    "sg:orig_category":"Ortopedia General",
    "sg:phone":"+34 938 04 12 02",
    "sg:postcode":"08700",
    "sg:province":"Barcelona",
    "wof:name":"Cases Sebastia Maria Inmaculada",
    "wof:placetype":"venue"
},
  "geometry": {"coordinates":[1.622164011,41.5802993774],"type":"Point"}
}