{
  "type": "Feature",
  "properties": {
    "addr:full":"Carrer de Escultor Modest Gene, 43 Reus Tarragona 43204",
    "addr:housenumber":"43",
    "addr:postcode":"43204",
    "addr:street":"Carrer De Escultor Modest Gene",
    "iso:country":"ES",
    "sg:address":"Carrer de Escultor Modest Gene, 43",
    "sg:city":"Reus",
    "sg:orig_category":"Electricidad: Instaladores",
    "sg:phone":"+34 977 75 64 43",
    "sg:postcode":"43204",
    "sg:province":"Tarragona",
    "wof:name":"Insta%acions Jordi Casado S.l.",
    "wof:placetype":"venue"
},
  "geometry": {"coordinates":[1.1163740158,41.1542663574],"type":"Point"}
}