{
  "type": "Feature",
  "properties": {
    "addr:full":"Carr Sant Miquel, 9 Jonquera Girona 17700",
    "addr:housenumber":"9",
    "addr:postcode":"17700",
    "addr:street":"Carr Sant Miquel",
    "iso:country":"ES",
    "sg:address":"Carr Sant Miquel, 9",
    "sg:city":"Jonquera",
    "sg:orig_category":"Peluqueros: De Se\u00d1oras",
    "sg:phone":"+34 972 55 49 11",
    "sg:postcode":"17700",
    "sg:province":"Girona",
    "wof:name":"Alsina Llinas Maria",
    "wof:placetype":"venue"
},
  "geometry": {"coordinates":[2.8740158081,42.4170341492],"type":"Point"}
}