{
  "type": "Feature",
  "properties": {
    "addr:full":"Av Frederic Rahola, 60 Barcelona Barcelona 08032",
    "addr:housenumber":"60",
    "addr:postcode":"08032",
    "addr:street":"Av Frederic Rahola",
    "iso:country":"ES",
    "sg:address":"Av Frederic Rahola, 60",
    "sg:city":"Barcelona",
    "sg:orig_category":"Abogados",
    "sg:phone":"+34 934 20 95 92",
    "sg:postcode":"08032",
    "sg:province":"Barcelona",
    "wof:name":"Alday Gutierrez Lia Nora",
    "wof:placetype":"venue"
},
  "geometry": {"coordinates":[2.1689829826,41.4245071411],"type":"Point"}
}