{
  "type": "Feature",
  "properties": {
    "addr:full":"Cjto Romogar, 16 Torre Benagalbon M\u00e1laga 29738",
    "addr:housenumber":"16",
    "addr:postcode":"29738",
    "addr:street":"Ma\u0301Laga",
    "iso:country":"ES",
    "sg:address":"Cjto Romogar, 16",
    "sg:city":"Torre Benagalbon",
    "sg:orig_category":"Transportes De M\u00c1quinas Y Piezas Compactas",
    "sg:phone":"+34 952 40 84 88",
    "sg:postcode":"29738",
    "sg:province":"M\u00e1laga",
    "wof:name":"Gruas Adolfo Alvarez S.l.",
    "wof:placetype":"venue"
},
  "geometry": {"coordinates":[-4.2452349663,36.7380599976],"type":"Point"}
}