{
  "type": "Feature",
  "properties": {
    "iso:country":"ES",
    "sg:address":"Carrer de Mexic, 8",
    "sg:city":"Masnou",
    "sg:orig_category":"Venta, Localizaci\u00d3n, Reparaci\u00d3n De Material E Instrumental M\u00c9dico",
    "sg:phone":"+34 935 40 19 09",
    "sg:postcode":"08320",
    "sg:province":"Barcelona",
    "wof:name":"Bionic Iberica S.a.",
    "wof:placetype":"venue"
},
  "geometry": {"coordinates":[2.3270840645,41.4835472107],"type":"Point"}
}