{
  "type": "Feature",
  "properties": {
    "addr:full":"Carrer de Andorra, 5 Barcelona Barcelona 08030",
    "addr:housenumber":"5",
    "addr:postcode":"08030",
    "addr:street":"Carrer De Andorra",
    "iso:country":"ES",
    "sg:address":"Carrer de Andorra, 5",
    "sg:city":"Barcelona",
    "sg:orig_category":"Empresas De Limpieza",
    "sg:phone":"+34 932 74 05 65",
    "sg:postcode":"08030",
    "sg:province":"Barcelona",
    "wof:name":"Perez Martinez Antonia",
    "wof:placetype":"venue"
},
  "geometry": {"coordinates":[2.1847419739,41.4358062744],"type":"Point"}
}