{
  "type": "Feature",
  "properties": {
    "iso:country":"ES",
    "sg:address":"Calle de Juan Rejon, 15",
    "sg:city":"Palmas De Gran Canaria",
    "sg:orig_category":"Ropa De Hogar (al Por Menor)",
    "sg:phone":"+34 928 46 30 23",
    "sg:postcode":"35008",
    "sg:province":"Las Palmas",
    "wof:name":"Lareso S.l.",
    "wof:placetype":"venue"
},
  "geometry": {"coordinates":[-15.4291734695,28.1485004425],"type":"Point"}
}