{
  "type": "Feature",
  "properties": {
    "iso:country":"ES",
    "sg:address":"Calle de Teresa Berganza, 26",
    "sg:city":"Getafe",
    "sg:orig_category":"Impuestos, Tesoro P\u00dablico",
    "sg:phone":"+34 916 01 69 94",
    "sg:postcode":"28903",
    "sg:province":"Madrid",
    "wof:name":"Rojo Moza Pedro",
    "wof:placetype":"venue"
},
  "geometry": {"coordinates":[-3.7129709721,40.3224868774],"type":"Point"}
}