{
  "type": "Feature",
  "properties": {
    "iso:country":"ES",
    "sg:address":"Avgd Lleida, 14",
    "sg:city":"Isona",
    "sg:orig_category":"Chapister\u00cda",
    "sg:phone":"+34 973 66 41 61",
    "sg:postcode":"25650",
    "sg:province":"Lleida",
    "wof:name":"Benet Guardia Antonio",
    "wof:placetype":"venue"
},
  "geometry": {"coordinates":[1.0446749926,42.1168899536],"type":"Point"}
}