{
  "type": "Feature",
  "properties": {
    "addr:full":"Calle de Bergantin, 20 Palmones C\u00e1diz 11379",
    "addr:housenumber":"20",
    "addr:postcode":"11379",
    "addr:street":"Calle De Bergantin;Ca\u0301Diz",
    "iso:country":"ES",
    "sg:address":"Calle de Bergantin, 20",
    "sg:city":"Palmones",
    "sg:orig_category":"Construcciones Met\u00c1licas",
    "sg:phone":"+34 956 67 67 40",
    "sg:postcode":"11379",
    "sg:province":"C\u00e1diz",
    "wof:name":"Tubycal S.l.",
    "wof:placetype":"venue"
},
  "geometry": {"coordinates":[-5.4425640106,36.1778640747],"type":"Point"}
}