{
  "type": "Feature",
  "properties": {
    "iso:country":"ES",
    "sg:address":"Avda Cosculluela, 38",
    "sg:city":"Ejea De Los Caballeros",
    "sg:orig_category":"\u00d3ptica: Instrumentos (fabricaci\u00d3n)",
    "sg:phone":"+34 976 67 71 15",
    "sg:postcode":"50600",
    "sg:province":"Zaragoza",
    "wof:name":"Lamarca Labari Antonio",
    "wof:placetype":"venue"
},
  "geometry": {"coordinates":[-1.1388189793,42.1268081665],"type":"Point"}
}