{
  "type": "Feature",
  "properties": {
    "iso:country":"ES",
    "sg:address":"Calle de Doctor Gil Y Morte, 24",
    "sg:city":"Valencia",
    "sg:orig_category":"Droguer\u00cdas (al Por Menor)",
    "sg:phone":"+34 963 42 01 22",
    "sg:postcode":"46007",
    "sg:province":"Valencia",
    "wof:name":"Garrido Alepuz Antonio",
    "wof:placetype":"venue"
},
  "geometry": {"coordinates":[-0.3820767105,39.4620819092],"type":"Point"}
}