{
  "type": "Feature",
  "properties": {
    "iso:country":"ES",
    "sg:address":"Calle de Chica, 2",
    "sg:city":"Vitigudino",
    "sg:orig_category":"Promotores Constructores",
    "sg:phone":"+34 923 50 01 67",
    "sg:postcode":"37210",
    "sg:province":"Salamanca",
    "wof:name":"Sanchez Marcos Santos",
    "wof:placetype":"venue"
},
  "geometry": {"coordinates":[-6.4367814064,41.009552002],"type":"Point"}
}