{
  "type": "Feature",
  "properties": {
    "iso:country":"ES",
    "sg:address":"Avgd Sants Patrons, 45",
    "sg:city":"Alzira",
    "sg:orig_category":"Reposter\u00cdas",
    "sg:phone":"+34 962 41 01 21",
    "sg:postcode":"46600",
    "sg:province":"Valencia",
    "wof:name":"Llinares Mascarell Julio",
    "wof:placetype":"venue"
},
  "geometry": {"coordinates":[-0.4376829863,39.1533432007],"type":"Point"}
}