{
  "type": "Feature",
  "properties": {
    "iso:country":"ES",
    "sg:address":"Calle de Jaime Vera, 9",
    "sg:city":"Madrid",
    "sg:orig_category":"Maquinaria Para Industrias Diversas",
    "sg:phone":"+34 914 63 57 07",
    "sg:postcode":"28011",
    "sg:province":"Madrid",
    "wof:name":"Araque Cobo Bernardina",
    "wof:placetype":"venue"
},
  "geometry": {"coordinates":[-3.7287495136,40.4121284485],"type":"Point"}
}