{
  "type": "Feature",
  "properties": {
    "iso:country":"ES",
    "sg:address":"Av Nenufares, S/n",
    "sg:city":"Torrevieja",
    "sg:orig_category":"Alquiler De Gr\u00daas",
    "sg:phone":"+34 966 70 65 77",
    "sg:postcode":"03180",
    "sg:province":"Alicante",
    "wof:name":"Lozano Martinez Jose",
    "wof:placetype":"venue"
},
  "geometry": {"coordinates":[-0.6910539865,37.9947052002],"type":"Point"}
}