{
  "type": "Feature",
  "properties": {
    "addr:full":"Calle de Uria, 68 Oviedo Asturias 33003",
    "addr:housenumber":"68",
    "addr:postcode":"33003",
    "addr:street":"Calle De Uria",
    "iso:country":"ES",
    "sg:address":"Calle de Uria, 68",
    "sg:city":"Oviedo",
    "sg:orig_category":"Farmacias",
    "sg:phone":"+34 985 21 32 09",
    "sg:postcode":"33003",
    "sg:province":"Asturias",
    "wof:name":"Bra\u00f1a Cuesta Julio Cesar",
    "wof:placetype":"venue"
},
  "geometry": {"coordinates":[-5.8526887894,43.3649597168],"type":"Point"}
}