{
  "type": "Feature",
  "properties": {
    "addr:full":"Calle de Juan Antonio Vallejo Najera (de), 4 Boadilla Del Monte Madrid 28660",
    "addr:postcode":"28660",
    "addr:street":"Calle De Juan Antonio Vallejo",
    "iso:country":"ES",
    "sg:address":"Calle de Juan Antonio Vallejo Najera (de), 4",
    "sg:city":"Boadilla Del Monte",
    "sg:orig_category":"Arquitectos",
    "sg:phone":"+34 916 32 94 69",
    "sg:postcode":"28660",
    "sg:province":"Madrid",
    "wof:name":"Asesoria Tecnica De Arquitectura E Ingenieria S.l.",
    "wof:placetype":"venue"
},
  "geometry": {"coordinates":[-3.8960735798,40.4162750244],"type":"Point"}
}