{
  "type": "Feature",
  "properties": {
    "addr:full":"Calle de Catedratico Antonio Silva, 1 Caceres C\u00e1ceres 10002",
    "addr:housenumber":"1",
    "addr:postcode":"10002",
    "addr:street":"Calle De Catedratico Antonio Silva;Ca\u0301Ceres",
    "iso:country":"ES",
    "sg:address":"Calle de Catedratico Antonio Silva, 1",
    "sg:city":"Caceres",
    "sg:orig_category":"Sociedades, Compa\u00d1\u00cdas Aseguradoras",
    "sg:phone":"+34 927 22 25 84",
    "sg:postcode":"10002",
    "sg:province":"C\u00e1ceres",
    "wof:name":"La Alianza Espa\u00f1ola Sociedad Anonima De Seguros",
    "wof:placetype":"venue"
},
  "geometry": {"coordinates":[-6.3776335716,39.4700546265],"type":"Point"}
}