{
  "type": "Feature",
  "properties": {
    "iso:country":"ES",
    "sg:address":"Poli Industrial Pineda 'calle E', 3",
    "sg:city":"Sevilla",
    "sg:orig_category":"Frutas, Legumbres Frescas Y Tempranas (al Por Menor)",
    "sg:phone":"+34 954 68 92 35",
    "sg:postcode":"41013",
    "sg:province":"Sevilla",
    "wof:name":"Frutas Dominguez Garrido S.l.",
    "wof:placetype":"venue"
},
  "geometry": {"coordinates":[-5.9716711044,37.3525352478],"type":"Point"}
}