{
  "type": "Feature",
  "properties": {
    "iso:country":"ES",
    "sg:address":"Avda Cardenal Cisneros, 28",
    "sg:city":"Zamora",
    "sg:orig_category":"Abogados",
    "sg:phone":"+34 980 51 28 69",
    "sg:postcode":"49030",
    "sg:province":"Zamora",
    "wof:name":"Clavel Rivas Valentin",
    "wof:placetype":"venue"
},
  "geometry": {"coordinates":[-5.7345218658,41.5096054077],"type":"Point"}
}