{
  "type": "Feature",
  "properties": {
    "iso:country":"ES",
    "sg:address":"Urb Punta De La Mona, S/n",
    "sg:city":"Herradura",
    "sg:orig_category":"Promotores Constructores",
    "sg:phone":"+34 958 64 00 31",
    "sg:postcode":"18697",
    "sg:province":"Granada",
    "wof:name":"Projimosa S.l.",
    "wof:placetype":"venue"
},
  "geometry": {"coordinates":[-3.7390809059,36.7353096008],"type":"Point"}
}