{
  "type": "Feature",
  "properties": {
    "iso:country":"ES",
    "sg:address":"Av Beniarda, 59",
    "sg:city":"Benidorm",
    "sg:orig_category":"Sindicatos De Trabajadores",
    "sg:phone":"+34 965 85 82 75",
    "sg:postcode":"03500",
    "sg:province":"Alicante",
    "wof:name":"Comissions Obreres Del Pais Valencia",
    "wof:placetype":"venue"
},
  "geometry": {"coordinates":[-0.1333229989,38.5468788147],"type":"Point"}
}