{
  "type": "Feature",
  "properties": {
    "iso:country":"ES",
    "sg:address":"Calle de Amaniel, 20",
    "sg:city":"Madrid",
    "sg:orig_category":"Audiovisuales: Material Y Accesorios (al Por Menor)",
    "sg:phone":"+34 915 23 30 83",
    "sg:postcode":"28015",
    "sg:province":"Madrid",
    "sg:website":"www.castanedamusic.com",
    "wof:name":"Casta\u00f1eda Sanchez Fernando David",
    "wof:placetype":"venue"
},
  "geometry": {"coordinates":[-3.7093286514,40.4263458252],"type":"Point"}
}