{
  "type": "Feature",
  "properties": {
    "addr:full":"Calle de Ibiza, 31 Valencia Valencia 46024",
    "addr:housenumber":"31",
    "addr:postcode":"46024",
    "addr:street":"Calle De Ibiza",
    "iso:country":"ES",
    "sg:address":"Calle de Ibiza, 31",
    "sg:city":"Valencia",
    "sg:orig_category":"Distribuci\u00d3n De Petr\u00d3leo Y Derivados",
    "sg:phone":"+34 963 31 02 41",
    "sg:postcode":"46024",
    "sg:province":"Valencia",
    "wof:name":"Taygrao S.l.",
    "wof:placetype":"venue"
},
  "geometry": {"coordinates":[-0.3402839899,39.4589500427],"type":"Point"}
}