{
  "type": "Feature",
  "properties": {
    "iso:country":"ES",
    "sg:address":"Rua Do Magnolio, 5",
    "sg:city":"Ponteareas",
    "sg:orig_category":"Fisioterapia",
    "sg:phone":"+34 986 64 28 45",
    "sg:postcode":"36860",
    "sg:province":"Pontevedra",
    "wof:name":"Agrera Casas Elena",
    "wof:placetype":"venue"
},
  "geometry": {"coordinates":[-8.5083303452,42.1731948853],"type":"Point"}
}