{
  "type": "Feature",
  "properties": {
    "iso:country":"ES",
    "sg:address":"Carrer de Romani, S/n",
    "sg:city":"Mora Nova",
    "sg:orig_category":"Mec\u00c1nico Del Autom\u00d3vil",
    "sg:phone":"+34 977 40 09 49",
    "sg:postcode":"43770",
    "sg:province":"Tarragona",
    "wof:name":"Tallers Automotor S.a.",
    "wof:placetype":"venue"
},
  "geometry": {"coordinates":[0.6466150284,41.1058311462],"type":"Point"}
}