{
  "type": "Feature",
  "properties": {
    "iso:country":"ES",
    "sg:address":"Rua San Francisco, S/n",
    "sg:city":"Ribadavia",
    "sg:orig_category":"Reposter\u00cdas",
    "sg:phone":"+34 988 47 10 05",
    "sg:postcode":"32400",
    "sg:province":"Ourense",
    "wof:name":"Gomez Alvarez Francisco Ramon",
    "wof:placetype":"venue"
},
  "geometry": {"coordinates":[-8.1406106949,42.2904853821],"type":"Point"}
}