{
  "type": "Feature",
  "properties": {
    "iso:country":"ES",
    "sg:address":"V. Alegre, 69",
    "sg:city":"Venta Santos",
    "sg:orig_category":"Supermercados Y Hipermercados",
    "sg:phone":"+34 953 46 91 04",
    "sg:postcode":"23265",
    "sg:province":"Ja\u00e9n",
    "wof:name":"Lopez Montes Guillermo",
    "wof:placetype":"venue"
},
  "geometry": {"coordinates":[-3.073278904,38.3612709045],"type":"Point"}
}