{
  "type": "Feature",
  "properties": {
    "addr:full":"Rond General Mitre, 202 Barcelona Barcelona 08006",
    "addr:housenumber":"202",
    "addr:postcode":"08006",
    "addr:street":"Mitre",
    "iso:country":"ES",
    "sg:address":"Rond General Mitre, 202",
    "sg:city":"Barcelona",
    "sg:orig_category":"Abogados",
    "sg:phone":"+34 932 12 24 65",
    "sg:postcode":"08006",
    "sg:province":"Barcelona",
    "wof:name":"Auguet Sangra S.l.",
    "wof:placetype":"venue"
},
  "geometry": {"coordinates":[2.1452069283,41.4055290222],"type":"Point"}
}