{
  "type": "Feature",
  "properties": {
    "iso:country":"ES",
    "sg:address":"Ctra Bilbao-plentzia, 17",
    "sg:city":"Asua-lauroeta",
    "sg:classifiers":[
        {
            "category":"Banks & Credit Unions",
            "subcategory":"Bureau De Change",
            "type":"Services"
        }
    ],
    "sg:phone":"+34 944 53 11 66",
    "sg:postcode":"48950",
    "sg:province":"Vizcaya",
    "sg:tags":[
        "organismos",
        "control"
    ],
    "wof:name":"Spec S. A.",
    "wof:placetype":"venue"
},
  "geometry": {"coordinates":[-2.949037075,43.3001403809],"type":"Point"}
}