{
  "type": "Feature",
  "properties": {
    "addr:full":"Calle de Iglesia (de La), 8 Peguerinos \u00c1vila 05293",
    "addr:housenumber":"8",
    "addr:postcode":"05293",
    "addr:street":"Calle De Iglesia;La",
    "iso:country":"ES",
    "sg:address":"Calle de Iglesia (de La), 8",
    "sg:city":"Peguerinos",
    "sg:orig_category":"Supermercados Y Hipermercados",
    "sg:phone":"+34 918 98 32 39",
    "sg:postcode":"05293",
    "sg:province":"\u00c1vila",
    "wof:name":"Mu\u00f1oz Jimenez Antonio Jesus",
    "wof:placetype":"venue"
},
  "geometry": {"coordinates":[-4.2339849472,40.6266136169],"type":"Point"}
}