{
  "type": "Feature",
  "properties": {
    "addr:full":"Avda Castelao, 42 Cedeira La Coru\u00f1a 15350",
    "addr:housenumber":"42",
    "addr:postcode":"15350",
    "addr:street":"Avda Castelao;La Corun\u0303A",
    "iso:country":"ES",
    "sg:address":"Avda Castelao, 42",
    "sg:city":"Cedeira",
    "sg:orig_category":"Comercio, Reparaci\u00d3n De Motocicletas, Bicicletas Y Piezas Sueltas",
    "sg:phone":"+34 981 48 14 54",
    "sg:postcode":"15350",
    "sg:province":"La Coru\u00f1a",
    "wof:name":"Carbajal Alvarez Jose Luis",
    "wof:placetype":"venue"
},
  "geometry": {"coordinates":[-8.0511808395,43.6586380005],"type":"Point"}
}