{
  "type": "Feature",
  "properties": {
    "iso:country":"ES",
    "sg:address":"Calle de Romanilla, 72",
    "sg:city":"Roquetas Mar",
    "sg:orig_category":"Internados & Ense\u00d1anza Privada",
    "sg:phone":"+34 950 32 83 13",
    "sg:postcode":"04740",
    "sg:province":"Almer\u00eda",
    "wof:name":"Colegio Portomagno",
    "wof:placetype":"venue"
},
  "geometry": {"coordinates":[-2.6124989986,36.7638435364],"type":"Point"}
}