{
  "type": "Feature",
  "properties": {
    "iso:country":"ES",
    "sg:address":"Calle de San Pedro, 21",
    "sg:city":"Nueva-carteya",
    "sg:orig_category":"Abogados",
    "sg:phone":"+34 957 69 71 11",
    "sg:postcode":"14857",
    "sg:province":"C\u00f3rdoba",
    "wof:name":"Padillo Bellido Francisco",
    "wof:placetype":"venue"
},
  "geometry": {"coordinates":[-4.4680728912,37.5864830017],"type":"Point"}
}