{
  "type": "Feature",
  "properties": {
    "addr:full":"C/ Sant Marti, 93 Cerdanyola Valles Barcelona 08290",
    "addr:housenumber":"93",
    "addr:postcode":"08290",
    "addr:street":"C / Sant Marti;Valles Barcelona",
    "iso:country":"ES",
    "sg:address":"C/ Sant Marti, 93",
    "sg:city":"Cerdanyola Valles",
    "sg:orig_category":"Ropa Para Ni\u00d1os (al Por Menor)",
    "sg:phone":"+34 935 80 91 52",
    "sg:postcode":"08290",
    "sg:province":"Barcelona",
    "wof:name":"Bustamante Moreno Cristina",
    "wof:placetype":"venue"
},
  "geometry": {"coordinates":[2.1470150948,41.4924812317],"type":"Point"}
}