{
  "type": "Feature",
  "properties": {
    "addr:full":"Rua San Salvador, 2 Vigo Pontevedra 36204",
    "addr:housenumber":"2",
    "addr:postcode":"36204",
    "addr:street":"Rua San Salvador",
    "iso:country":"ES",
    "sg:address":"Rua San Salvador, 2",
    "sg:city":"Vigo",
    "sg:orig_category":"M\u00c9dicos: Evaluaci\u00d3n Y Tratamiento Del Dolor",
    "sg:phone":"+34 986 41 08 00",
    "sg:postcode":"36204",
    "sg:province":"Pontevedra",
    "wof:name":"Santos Cores S.l.",
    "wof:placetype":"venue"
},
  "geometry": {"coordinates":[-8.7117443085,42.2321739197],"type":"Point"}
}