{
  "type": "Feature",
  "properties": {
    "addr:full":"Olimpia, 6 Murcia Murcia 30007",
    "addr:housenumber":"6",
    "addr:postcode":"30007",
    "addr:street":"Olimpia",
    "iso:country":"ES",
    "sg:address":"Olimpia, 6",
    "sg:city":"Murcia",
    "sg:orig_category":"Promotores Constructores",
    "sg:phone":"+34 968 27 02 10",
    "sg:postcode":"30007",
    "sg:province":"Murcia",
    "wof:name":"Gran Murcia S.a.",
    "wof:placetype":"venue"
},
  "geometry": {"coordinates":[-1.1256760359,37.9996185303],"type":"Point"}
}