{
  "type": "Feature",
  "properties": {
    "iso:country":"ES",
    "sg:address":"Rbra Elorrieta, 5",
    "sg:city":"Bilbao",
    "sg:orig_category":"Acero: Productos Sider\u00dargicos Y Transformados (fabricaci\u00d3n, Negocio)",
    "sg:phone":"+34 944 74 54 44",
    "sg:postcode":"48015",
    "sg:province":"Vizcaya",
    "sg:website":"www.iberacero.es",
    "wof:name":"Iberacero S.l.",
    "wof:placetype":"venue"
},
  "geometry": {"coordinates":[-2.9669001102,43.2852401733],"type":"Point"}
}