{
  "type": "Feature",
  "properties": {
    "iso:country":"ES",
    "sg:address":"Calle de Morronguilleta, 8",
    "sg:city":"Errenteria",
    "sg:orig_category":"Peluquer\u00cdas, Peluquer\u00cda Mixta",
    "sg:phone":"+34 943 52 07 20",
    "sg:postcode":"20100",
    "sg:province":"Guip\u00f9zcoa",
    "wof:name":"Olga Argibai Blanco",
    "wof:placetype":"venue"
},
  "geometry": {"coordinates":[-1.9017720222,43.3126945496],"type":"Point"}
}