{
  "type": "Feature",
  "properties": {
    "addr:full":"Ctr Nacional 420, Km. 0251,0 Arenas S. Juan Ciudad Real 13679",
    "addr:postcode":"13679",
    "addr:street":"Nacional 420 Km. 0251,0 Arenas S. Juan Ciudad Real",
    "iso:country":"ES",
    "sg:address":"Ctr Nacional 420, Km. 0251,0",
    "sg:city":"Arenas S. Juan",
    "sg:orig_category":"Albergues",
    "sg:phone":"+34 926 89 30 19",
    "sg:postcode":"13679",
    "sg:province":"Ciudad Real",
    "wof:name":"Hostal Restaurante Ciguela S.l.",
    "wof:placetype":"venue"
},
  "geometry": {"coordinates":[-3.5009949207,39.221496582],"type":"Point"}
}