{
  "type": "Feature",
  "properties": {
    "addr:full":"Avda Gernikako Arbola, 31 San Vicente De Barakaldo Vizcaya 48902",
    "addr:housenumber":"31",
    "addr:postcode":"48902",
    "addr:street":"Avda Gernikako Arbola",
    "iso:country":"ES",
    "sg:address":"Avda Gernikako Arbola, 31",
    "sg:city":"San Vicente De Barakaldo",
    "sg:orig_category":"Electrodom\u00c9sticos (al Por Menor)",
    "sg:phone":"+34 944 78 00 48",
    "sg:postcode":"48902",
    "sg:province":"Vizcaya",
    "wof:name":"Puente Garcia Carlos",
    "wof:placetype":"venue"
},
  "geometry": {"coordinates":[-2.9929339886,43.2943763733],"type":"Point"}
}