{
  "type": "Feature",
  "properties": {
    "addr:full":"Carrer de Mas Ferrer, S/n Vilanova Valles Barcelona 08410",
    "addr:housenumber":"s",
    "addr:postcode":"08410",
    "addr:street":"Carrer De Mas Ferrer;/ N",
    "iso:country":"ES",
    "sg:address":"Carrer de Mas Ferrer, S/n",
    "sg:city":"Vilanova Valles",
    "sg:orig_category":"Empresas De Operaciones Portuarias Y Elevaci\u00d3n De Mercanc\u00cdas",
    "sg:phone":"+34 938 45 92 51",
    "sg:postcode":"08410",
    "sg:province":"Barcelona",
    "wof:name":"Rt Manipulados S.l.",
    "wof:placetype":"venue"
},
  "geometry": {"coordinates":[2.2852599621,41.5516586304],"type":"Point"}
}