{
  "type": "Feature",
  "properties": {
    "addr:full":"Calle de Gran Avenida, 39 Madrid Madrid 28041",
    "addr:housenumber":"39",
    "addr:postcode":"madrid;28041",
    "addr:street":"Calle De Gran Avenida",
    "iso:country":"ES",
    "sg:address":"Calle de Gran Avenida, 39",
    "sg:city":"Madrid",
    "sg:orig_category":"Molduras, Junquillos, Listones Y Molduras Perforadas",
    "sg:phone":"+34 917 46 43 49",
    "sg:postcode":"28041",
    "sg:province":"Madrid",
    "wof:name":"Las Mimosas C.b.",
    "wof:placetype":"venue"
},
  "geometry": {"coordinates":[-3.7052075863,40.3695907593],"type":"Point"}
}