{
  "type": "Feature",
  "properties": {
    "iso:country":"ES",
    "sg:address":"Calle de Rio (del), 10",
    "sg:city":"Miraflores De La Sierra",
    "sg:orig_category":"Cer\u00c1micas: Material Y Suministros",
    "sg:phone":"+34 918 44 34 15",
    "sg:postcode":"28792",
    "sg:province":"Madrid",
    "wof:name":"Alconsa S. A.",
    "wof:placetype":"venue"
},
  "geometry": {"coordinates":[-3.7496500015,40.8094520569],"type":"Point"}
}