{
  "type": "Feature",
  "properties": {
    "addr:full":"Mercat Sarria, S/n Barcelona Barcelona 08017",
    "addr:housenumber":"s / n",
    "addr:postcode":"08017",
    "iso:country":"ES",
    "sg:address":"Mercat Sarria, S/n",
    "sg:city":"Barcelona",
    "sg:orig_category":"Poller\u00cda Y Caza (al Por Menor)",
    "sg:phone":"+34 932 03 61 08",
    "sg:postcode":"08017",
    "sg:province":"Barcelona",
    "wof:name":"Solsona Muntane Rosa Maria",
    "wof:placetype":"venue"
},
  "geometry": {"coordinates":[2.1371200085,41.391494751],"type":"Point"}
}