{
  "type": "Feature",
  "properties": {
    "iso:country":"ES",
    "sg:address":"Avda Casalduch, 1",
    "sg:city":"Castellon",
    "sg:orig_category":"Doctores En Medicina",
    "sg:phone":"+34 964 22 14 16",
    "sg:postcode":"12005",
    "sg:province":"Castell\u00f3n",
    "wof:name":"Balaguer Belles Ismael",
    "wof:placetype":"venue"
},
  "geometry": {"coordinates":[-0.0357553996,39.981880188],"type":"Point"}
}