{
  "type": "Feature",
  "properties": {
    "addr:full":"Calle de Domingo Hergueta, 4 Haro La Rioja 26200",
    "addr:housenumber":"4",
    "addr:postcode":"26200",
    "addr:street":"Calle De Domingo Hergueta",
    "iso:country":"ES",
    "sg:address":"Calle de Domingo Hergueta, 4",
    "sg:city":"Haro",
    "sg:orig_category":"Electrodom\u00c9sticos (al Por Menor)",
    "sg:phone":"+34 941 31 17 74",
    "sg:postcode":"26200",
    "sg:province":"La Rioja",
    "wof:name":"Clemente Romero Jose Antonio",
    "wof:placetype":"venue"
},
  "geometry": {"coordinates":[-2.8476669788,42.5727119446],"type":"Point"}
}