{
  "type": "Feature",
  "properties": {
    "addr:full":"Carr Bailen, 8 Girona Girona 17002",
    "addr:housenumber":"8",
    "addr:postcode":"17002",
    "addr:street":"Carr Bailen",
    "iso:country":"ES",
    "sg:address":"Carr Bailen, 8",
    "sg:city":"Girona",
    "sg:orig_category":"Inmobiliaria (agencias)",
    "sg:phone":"+34 972 20 20 58",
    "sg:postcode":"17002",
    "sg:province":"Girona",
    "wof:name":"Immobiliaria Casastock S.l.",
    "wof:placetype":"venue"
},
  "geometry": {"coordinates":[2.8187448978,41.9808616638],"type":"Point"}
}