{
  "type": "Feature",
  "properties": {
    "addr:full":"Plaz Mayor, 5 Guardia Toledo 45760",
    "addr:housenumber":"5",
    "addr:postcode":"45760",
    "addr:street":"Plaz Mayor",
    "iso:country":"ES",
    "sg:address":"Plaz Mayor, 5",
    "sg:city":"Guardia",
    "sg:orig_category":"Supermercados Y Hipermercados",
    "sg:phone":"+34 925 13 83 43",
    "sg:postcode":"45760",
    "sg:province":"Toledo",
    "wof:name":"Panasu C.b.",
    "wof:placetype":"venue"
},
  "geometry": {"coordinates":[-3.4772589207,39.7863616943],"type":"Point"}
}