{
  "type": "Feature",
  "properties": {
    "addr:full":"Av Tibidabo, 6 Barcelona Barcelona 08022",
    "addr:housenumber":"6",
    "addr:postcode":"08022",
    "addr:street":"Av Tibidabo",
    "iso:country":"ES",
    "sg:address":"Av Tibidabo, 6",
    "sg:city":"Barcelona",
    "sg:orig_category":"Promotores Constructores",
    "sg:phone":"+34 932 11 49 01",
    "sg:postcode":"08022",
    "sg:province":"Barcelona",
    "wof:name":"Teyco S. L.",
    "wof:placetype":"venue"
},
  "geometry": {"coordinates":[2.1366939545,41.4109687805],"type":"Point"}
}