{
  "type": "Feature",
  "properties": {
    "iso:country":"ES",
    "sg:address":"Calle de Juan De Mesa, S/n",
    "sg:city":"Sevilla",
    "sg:orig_category":"Servicios Gsm",
    "sg:phone":"+34 954 21 23 74",
    "sg:postcode":"41003",
    "sg:province":"Sevilla",
    "wof:name":"Adytel Comunicaciones S.l.",
    "wof:placetype":"venue"
},
  "geometry": {"coordinates":[-5.9880275726,37.3929748535],"type":"Point"}
}