{
  "type": "Feature",
  "properties": {
    "iso:country":"ES",
    "sg:address":"Carr Mar, 52",
    "sg:city":"Pollen\u00e7a",
    "sg:orig_category":"Artes Gr\u00c1ficas, Artes Pl\u00c1sticas (curso)",
    "sg:phone":"+34 971 53 11 16",
    "sg:postcode":"07460",
    "sg:province":"Islas Baleares",
    "wof:name":"Arts Grafiques Binya S.r.l",
    "wof:placetype":"venue"
},
  "geometry": {"coordinates":[3.0192997456,39.8816871643],"type":"Point"}
}