{
  "type": "Feature",
  "properties": {
    "addr:full":"Calle de Cimbron, 11 Merida Badajoz 06800",
    "addr:housenumber":"11",
    "addr:postcode":"06800",
    "addr:street":"Calle De Cimbron",
    "iso:country":"ES",
    "sg:address":"Calle de Cimbron, 11",
    "sg:city":"Merida",
    "sg:orig_category":"Arquitectos",
    "sg:phone":"+34 924 30 01 57",
    "sg:postcode":"06800",
    "sg:province":"Badajoz",
    "wof:name":"Rafael Mesa Y Jesus Martinez S.l",
    "wof:placetype":"venue"
},
  "geometry": {"coordinates":[-6.3445062637,38.914981842],"type":"Point"}
}