{
  "type": "Feature",
  "properties": {
    "iso:country":"ES",
    "sg:address":"Calle de Isabel I De Castilla, 28",
    "sg:city":"Mota Cuervo",
    "sg:orig_category":"Telas Y Sedas (al Por Menor)",
    "sg:phone":"+34 967 18 09 00",
    "sg:postcode":"16630",
    "sg:province":"Cuenca",
    "wof:name":"Mota Manjavacas Maria Socorro",
    "wof:placetype":"venue"
},
  "geometry": {"coordinates":[-2.8685619831,39.5022964478],"type":"Point"}
}