{
  "type": "Feature",
  "properties": {
    "addr:full":"Pg Maragall, 397 Barcelona Barcelona 08032",
    "addr:housenumber":"397",
    "addr:postcode":"08032",
    "addr:street":"Pg Maragall",
    "iso:country":"ES",
    "sg:address":"Pg Maragall, 397",
    "sg:city":"Barcelona",
    "sg:orig_category":"Radiocomunicaciones, Telefon\u00cda M\u00d3vil, Radiomensajer\u00cda: Servicios, Comercializaci\u00d3n",
    "sg:phone":"+34 933 58 83 12",
    "sg:postcode":"08032",
    "sg:province":"Barcelona",
    "sg:website":"www.telyco.es",
    "wof:name":"Teleinformatica Y Comunicaciones S.a.",
    "wof:placetype":"venue"
},
  "geometry": {"coordinates":[2.1634778976,41.4281005859],"type":"Point"}
}