{
  "type": "Feature",
  "properties": {
    "iso:country":"ES",
    "sg:address":"Avda Estella, 18",
    "sg:city":"Tafalla",
    "sg:orig_category":"Madera Para Construcci\u00d3n E Industria",
    "sg:phone":"+34 948 70 10 98",
    "sg:postcode":"31300",
    "sg:province":"Navarra",
    "wof:name":"Olcoz Burgui Pedro",
    "wof:placetype":"venue"
},
  "geometry": {"coordinates":[-1.6787519455,42.5262718201],"type":"Point"}
}