{
  "type": "Feature",
  "properties": {
    "addr:full":"Pol S. Pancracio, S/n Puente-genil C\u00f3rdoba 14500",
    "addr:housenumber":"s / n",
    "addr:postcode":"14500",
    "addr:street":"Co\u0301Rdoba",
    "iso:country":"ES",
    "sg:address":"Pol S. Pancracio, S/n",
    "sg:city":"Puente-genil",
    "sg:orig_category":"Molduras, Junquillos, Listones Y Molduras Perforadas",
    "sg:phone":"+34 957 60 71 79",
    "sg:postcode":"14500",
    "sg:province":"C\u00f3rdoba",
    "wof:name":"Rivas Mu\u00f1oz Manuel",
    "wof:placetype":"venue"
},
  "geometry": {"coordinates":[-4.7465629578,37.3896102905],"type":"Point"}
}