{
  "type": "Feature",
  "properties": {
    "iso:country":"ES",
    "sg:address":"Calle de Amadeo Arias, 28",
    "sg:city":"Valladolid",
    "sg:orig_category":"Arquitectos",
    "sg:phone":"+34 983 37 80 79",
    "sg:postcode":"47014",
    "sg:province":"Valladolid",
    "wof:name":"Aparejo Oficina Tecnica S.l.u.",
    "wof:placetype":"venue"
},
  "geometry": {"coordinates":[-4.7600245476,41.6362953186],"type":"Point"}
}