{
  "type": "Feature",
  "properties": {
    "addr:full":"Calle de Torres Miranda, 14 Madrid Madrid 28045",
    "addr:housenumber":"14",
    "addr:postcode":"madrid;28045",
    "addr:street":"Calle De Torres Miranda",
    "iso:country":"ES",
    "sg:address":"Calle de Torres Miranda, 14",
    "sg:city":"Madrid",
    "sg:orig_category":"Mec\u00c1nico Del Autom\u00d3vil",
    "sg:phone":"+34 914 73 98 41",
    "sg:postcode":"28045",
    "sg:province":"Madrid",
    "wof:name":"Villamayor Robles Jesus",
    "wof:placetype":"venue"
},
  "geometry": {"coordinates":[-3.6997790337,40.3982048035],"type":"Point"}
}