{
  "type": "Feature",
  "properties": {
    "iso:country":"ES",
    "sg:address":"Avgd Vilella (de), S/n",
    "sg:city":"Sueca",
    "sg:orig_category":"Flores Y Plantas Naturales (al Por Mayor)",
    "sg:phone":"+34 961 71 04 87",
    "sg:postcode":"46410",
    "sg:province":"Valencia",
    "wof:name":"Marin Villanueva Jose Evaristo",
    "wof:placetype":"venue"
},
  "geometry": {"coordinates":[-0.3095490038,39.1971549988],"type":"Point"}
}