{
  "type": "Feature",
  "properties": {
    "addr:full":"Calle de Visconti, 30 Tarazona Zaragoza 50500",
    "addr:housenumber":"30",
    "addr:postcode":"50500",
    "addr:street":"Calle De Visconti",
    "iso:country":"ES",
    "sg:address":"Calle de Visconti, 30",
    "sg:city":"Tarazona",
    "sg:orig_category":"Frutas, Legumbres Frescas Y Tempranas (al Por Menor)",
    "sg:phone":"+34 976 64 14 95",
    "sg:postcode":"50500",
    "sg:province":"Zaragoza",
    "wof:name":"Garcia Milagro Marisa",
    "wof:placetype":"venue"
},
  "geometry": {"coordinates":[-1.7260789871,41.9052009583],"type":"Point"}
}