{
  "type": "Feature",
  "properties": {
    "addr:full":"Calle de San Jaime, 18 Torreblanca Castell\u00f3n 12596",
    "addr:housenumber":"18",
    "addr:postcode":"12596",
    "addr:street":"Calle De San Jaime;Castello\u0301N",
    "iso:country":"ES",
    "sg:address":"Calle de San Jaime, 18",
    "sg:city":"Torreblanca",
    "sg:orig_category":"Lencer\u00cda Femenina, Corseter\u00cda, Trajes De Ba\u00d1o (al Por Menor)",
    "sg:phone":"+34 964 42 04 47",
    "sg:postcode":"12596",
    "sg:province":"Castell\u00f3n",
    "wof:name":"Fabregat Llorens Jose Domingo",
    "wof:placetype":"venue"
},
  "geometry": {"coordinates":[0.1960400045,40.2205581665],"type":"Point"}
}