{
  "type": "Feature",
  "properties": {
    "iso:country":"ES",
    "sg:address":"Carr Josep Tarradellas, S/n",
    "sg:city":"Blanes",
    "sg:orig_category":"Asociaciones Y Clubs Deportivos",
    "sg:phone":"+34 972 35 56 80",
    "sg:postcode":"17300",
    "sg:province":"Girona",
    "wof:name":"Club Basquet Blanes",
    "wof:placetype":"venue"
},
  "geometry": {"coordinates":[2.7842950821,41.6680755615],"type":"Point"}
}