{
  "type": "Feature",
  "properties": {
    "iso:country":"ES",
    "sg:address":"Calle de Ramal (el), 15",
    "sg:city":"Orotava",
    "sg:orig_category":"Producci\u00d3n, Venta De Productos De Agricultura Biol\u00d3gica",
    "sg:phone":"+34 922 33 03 53",
    "sg:postcode":"38300",
    "sg:province":"Santa Cruz De Tenerife",
    "wof:name":"Suarez Baute Eduardo",
    "wof:placetype":"venue"
},
  "geometry": {"coordinates":[-16.519109726,28.3969612122],"type":"Point"}
}