{
  "type": "Feature",
  "properties": {
    "addr:full":"Ctra. Boadilla-brunete, Km. 0007,0 Boadilla Madrid 28660",
    "addr:postcode":"28660",
    "addr:street":"Ctra. Boadilla-Brunete Km. 0007,0",
    "iso:country":"ES",
    "sg:address":"Ctra. Boadilla-brunete, Km. 0007,0",
    "sg:city":"Boadilla",
    "sg:orig_category":"F\u00c1bricas De Ladrillo Y Tejas",
    "sg:phone":"+34 916 33 30 55",
    "sg:postcode":"28660",
    "sg:province":"Madrid",
    "wof:name":"Bt Espa\u00d1a Compa\u00d1ia De Servicios Globales De Telecomunicaciones S.a.u.",
    "wof:placetype":"venue"
},
  "geometry": {"coordinates":[-3.7057700157,40.42029953],"type":"Point"}
}