{
  "type": "Feature",
  "properties": {
    "addr:full":"Calle de Hernan Cortes, 25 Valencia Alcantara C\u00e1ceres 10500",
    "addr:housenumber":"25",
    "addr:postcode":"10500",
    "addr:street":"Calle De Hernan Cortes;Alcantara Ca\u0301Ceres",
    "iso:country":"ES",
    "sg:address":"Calle de Hernan Cortes, 25",
    "sg:city":"Valencia Alcantara",
    "sg:classifiers":[
        {
            "category":"Cinema",
            "subcategory":"Movie Theater",
            "type":"Entertainment"
        }
    ],
    "sg:phone":"+34 927 58 01 18",
    "sg:postcode":"10500",
    "sg:province":"C\u00e1ceres",
    "sg:tags":[
        "salas",
        "de",
        "cine"
    ],
    "wof:name":"Diaz Telecom S.l.",
    "wof:placetype":"venue"
},
  "geometry": {"coordinates":[-7.2454872131,39.4099311829],"type":"Point"}
}