{
  "type": "Feature",
  "properties": {
    "iso:country":"ES",
    "sg:address":"Mercado De Abastos, S/n",
    "sg:city":"Pe\u00f1arroya Pueblonuevo",
    "sg:orig_category":"Carnicer\u00cdas, Carnicer\u00cdas",
    "sg:phone":"+34 957 57 09 35",
    "sg:postcode":"14200",
    "sg:province":"C\u00f3rdoba",
    "wof:name":"Tapia Villarreal Antonia",
    "wof:placetype":"venue"
},
  "geometry": {"coordinates":[-5.2682538033,38.3007049561],"type":"Point"}
}