{
  "type": "Feature",
  "properties": {
    "iso:country":"ES",
    "sg:address":"Calle de Amargura, 1",
    "sg:city":"Teruel",
    "sg:orig_category":"Arquitectos",
    "sg:phone":"+34 978 61 82 91",
    "sg:postcode":"44001",
    "sg:province":"Teruel",
    "wof:name":"Inarse S.l.",
    "wof:placetype":"venue"
},
  "geometry": {"coordinates":[-1.1077475548,40.341835022],"type":"Point"}
}