{
  "type": "Feature",
  "properties": {
    "addr:full":"Rua Magallanes, 7 Vigo Pontevedra 36203",
    "addr:housenumber":"7",
    "addr:postcode":"36203",
    "addr:street":"Rua Magallanes",
    "iso:country":"ES",
    "sg:address":"Rua Magallanes, 7",
    "sg:city":"Vigo",
    "sg:orig_category":"Agencias Y Asesores De Publicidad",
    "sg:phone":"+34 986 43 31 77",
    "sg:postcode":"36203",
    "sg:province":"Pontevedra",
    "wof:name":"Jeabuch S.l.",
    "wof:placetype":"venue"
},
  "geometry": {"coordinates":[-8.7191820145,42.2348899841],"type":"Point"}
}