{
  "type": "Feature",
  "properties": {
    "addr:full":"Calle de Corredera, 38 Baza Granada 18800",
    "addr:housenumber":"38",
    "addr:postcode":"18800",
    "addr:street":"Calle De Corredera",
    "iso:country":"ES",
    "sg:address":"Calle de Corredera, 38",
    "sg:city":"Baza",
    "sg:orig_category":"Electromec\u00c1nica",
    "sg:phone":"+34 958 70 12 84",
    "sg:postcode":"18800",
    "sg:province":"Granada",
    "wof:name":"Hernandez Garcia Manuel Arturo",
    "wof:placetype":"venue"
},
  "geometry": {"coordinates":[-2.7715568542,37.4924583435],"type":"Point"}
}