{
  "type": "Feature",
  "properties": {
    "addr:full":"Calle de Jose Mina, 16 Burlada Navarra 31600",
    "addr:housenumber":"16",
    "addr:postcode":"31600",
    "addr:street":"Calle De Jose Mina",
    "iso:country":"ES",
    "sg:address":"Calle de Jose Mina, 16",
    "sg:city":"Burlada",
    "sg:orig_category":"Parques De Atracciones Y Centros De Esparcimiento",
    "sg:phone":"+34 948 15 23 15",
    "sg:postcode":"31600",
    "sg:province":"Navarra",
    "wof:name":"Valenzuela Gomez Maria Teresa",
    "wof:placetype":"venue"
},
  "geometry": {"coordinates":[-1.6153000593,42.8235435486],"type":"Point"}
}