{
  "type": "Feature",
  "properties": {
    "iso:country":"ES",
    "sg:address":"Carrer de Tallers, 48",
    "sg:city":"Barcelona",
    "sg:orig_category":"Fabricaci\u00d3n De Taburetes, Sillas Y Sillones",
    "sg:phone":"+34 933 18 63 98",
    "sg:postcode":"08001",
    "sg:province":"Barcelona",
    "sg:website":"www.clubdelsillon.com",
    "wof:name":"Perez Co Jose",
    "wof:placetype":"venue"
},
  "geometry": {"coordinates":[2.1675760746,41.3850135803],"type":"Point"}
}