{
  "type": "Feature",
  "properties": {
    "iso:country":"ES",
    "sg:address":"Pase Doctor Mara\u00d1on, 31",
    "sg:city":"Donostia-san Sebastian",
    "sg:orig_category":"M\u00c9dicos: Medicina General Orientada A La Homeopat\u00cda",
    "sg:phone":"+34 943 31 33 22",
    "sg:postcode":"20009",
    "sg:province":"Guip\u00f9zcoa",
    "wof:name":"Eguiburu Aranaga Edurne",
    "wof:placetype":"venue"
},
  "geometry": {"coordinates":[-1.9959330559,43.3082237244],"type":"Point"}
}