{
  "type": "Feature",
  "properties": {
    "iso:country":"ES",
    "sg:address":"Calle de Miguel De Cepeda, 10",
    "sg:city":"Palma Condado",
    "sg:orig_category":"Artesan\u00cda Y Trabajos Manuales: Suministros (al Por Menor)",
    "sg:phone":"+34 959 40 19 72",
    "sg:postcode":"21700",
    "sg:province":"Huelva",
    "wof:name":"Garcia Rasgado Dolores",
    "wof:placetype":"venue"
},
  "geometry": {"coordinates":[-6.556842804,37.3890342712],"type":"Point"}
}