{
  "type": "Feature",
  "properties": {
    "addr:full":"Calle de Lasierra Purroy, 32 Zaragoza Zaragoza 50007",
    "addr:housenumber":"32",
    "addr:postcode":"50007",
    "addr:street":"Calle De Lasierra Purroy",
    "iso:country":"ES",
    "sg:address":"Calle de Lasierra Purroy, 32",
    "sg:city":"Zaragoza",
    "sg:orig_category":"Cueros Y Pieles (al Por Mayor)",
    "sg:phone":"+34 976 27 15 75",
    "sg:postcode":"50007",
    "sg:province":"Zaragoza",
    "wof:name":"Pieles Y Cueros Larrosa S.l.",
    "wof:placetype":"venue"
},
  "geometry": {"coordinates":[-0.8843089938,41.6311302185],"type":"Point"}
}