{
  "type": "Feature",
  "properties": {
    "iso:country":"ES",
    "sg:address":"Pase Russafa, 5",
    "sg:city":"Valencia",
    "sg:orig_category":"Asesor\u00cda Sobre Comunicaci\u00d3n De Empresas",
    "sg:phone":"+34 963 51 72 79",
    "sg:postcode":"46002",
    "sg:province":"Valencia",
    "wof:name":"Roig Grupo Corporativo Sl",
    "wof:placetype":"venue"
},
  "geometry": {"coordinates":[-0.375169009,39.468460083],"type":"Point"}
}