{
  "type": "Feature",
  "properties": {
    "addr:full":"Calle de Jucar, S/n Pto. Rosario Las Palmas 35600",
    "addr:housenumber":"s / n",
    "addr:postcode":"35600",
    "addr:street":"Calle De Jucar;Pto. Rosario Las",
    "iso:country":"ES",
    "sg:address":"Calle de Jucar, S/n",
    "sg:city":"Pto. Rosario",
    "sg:orig_category":"Centros De Coordinaci\u00d3n",
    "sg:phone":"+34 928 85 00 01",
    "sg:postcode":"35600",
    "sg:province":"Las Palmas",
    "wof:name":"Alzola Gestores S.l.",
    "wof:placetype":"venue"
},
  "geometry": {"coordinates":[-13.8654165268,28.4934310913],"type":"Point"}
}