{
  "type": "Feature",
  "properties": {
    "addr:full":"Carrer de Barcelona, 57 Olesa Montserrat Barcelona 08640",
    "addr:housenumber":"57",
    "addr:postcode":"08640",
    "addr:street":"Carrer De Barcelona",
    "iso:country":"ES",
    "sg:address":"Carrer de Barcelona, 57",
    "sg:city":"Olesa Montserrat",
    "sg:orig_category":"Molduras, Junquillos, Listones Y Molduras Perforadas",
    "sg:phone":"+34 937 78 44 54",
    "sg:postcode":"08640",
    "sg:province":"Barcelona",
    "wof:name":"Asensio Llopart Jose",
    "wof:placetype":"venue"
},
  "geometry": {"coordinates":[1.8938649893,41.5400085449],"type":"Point"}
}