{
  "type": "Feature",
  "properties": {
    "iso:country":"ES",
    "sg:address":"Avda Brocense (el), S/n",
    "sg:city":"Caceres",
    "sg:orig_category":"Deportes Diversos",
    "sg:phone":"+34 927 21 40 50",
    "sg:postcode":"10002",
    "sg:province":"C\u00e1ceres",
    "wof:name":"Federacion Extreme\u00f1a De Atletismo",
    "wof:placetype":"venue"
},
  "geometry": {"coordinates":[-6.3726511002,39.4693145752],"type":"Point"}
}