{
  "type": "Feature",
  "properties": {
    "iso:country":"ES",
    "sg:address":"Cr Madrid-valencia, Km. 0080,0",
    "sg:city":"Tarancon",
    "sg:orig_category":"Centros Comerciales Y Grandes Tiendas",
    "sg:phone":"+34 969 32 24 89",
    "sg:postcode":"16400",
    "sg:province":"Cuenca",
    "wof:name":"Tractoimpex Sl",
    "wof:placetype":"venue"
},
  "geometry": {"coordinates":[-3.0046839714,40.0113143921],"type":"Point"}
}