{
  "type": "Feature",
  "properties": {
    "addr:full":"Monasterio Eunate, 6 Iru\u00f1a Navarra 31011",
    "addr:housenumber":"6",
    "addr:postcode":"31011",
    "addr:street":"Eunate",
    "iso:country":"ES",
    "sg:address":"Monasterio Eunate, 6",
    "sg:city":"Iru\u00f1a",
    "sg:orig_category":"Librer\u00cdas",
    "sg:phone":"+34 948 26 70 89",
    "sg:postcode":"31011",
    "sg:province":"Navarra",
    "wof:name":"Samanes Jusue Guadalupe",
    "wof:placetype":"venue"
},
  "geometry": {"coordinates":[-1.6612830162,42.8164787292],"type":"Point"}
}