{
  "type": "Feature",
  "properties": {
    "iso:country":"ES",
    "sg:address":"Cortes De Navarra, 3",
    "sg:city":"Iru\u00f1a",
    "sg:orig_category":"Complementos De Vestir (al Por Menor)",
    "sg:phone":"+34 948 22 03 45",
    "sg:postcode":"31002",
    "sg:province":"Navarra",
    "wof:name":"Archanco Udobro Rafael",
    "wof:placetype":"venue"
},
  "geometry": {"coordinates":[-1.6419678926,42.8151931763],"type":"Point"}
}