{
  "type": "Feature",
  "properties": {
    "addr:full":"Calle de Pedro Miguel Hernandez Camacho, 22 Llanos De Aridane Santa Cruz De Tenerife 38760",
    "addr:postcode":"38760",
    "addr:street":"Calle De Pedro;Camacho 22",
    "iso:country":"ES",
    "sg:address":"Calle de Pedro Miguel Hernandez Camacho, 22",
    "sg:city":"Llanos De Aridane",
    "sg:orig_category":"Electricidad: Equipos Industriales, Componentes (fabricaci\u00d3n)",
    "sg:phone":"+34 922 40 24 14",
    "sg:postcode":"38760",
    "sg:province":"Santa Cruz De Tenerife",
    "wof:name":"Comercial Electrica Canarias S.a.",
    "wof:placetype":"venue"
},
  "geometry": {"coordinates":[-17.9085597992,28.6563796997],"type":"Point"}
}