{
  "type": "Feature",
  "properties": {
    "iso:country":"ES",
    "sg:address":"Calle de Bolado El, 30",
    "sg:city":"Grado",
    "sg:orig_category":"Molduras, Junquillos, Listones Y Molduras Perforadas",
    "sg:phone":"+34 985 75 07 01",
    "sg:postcode":"33820",
    "sg:province":"Asturias",
    "wof:name":"Estrada Suarez Miguel Angel",
    "wof:placetype":"venue"
},
  "geometry": {"coordinates":[-6.0723614693,43.3870925903],"type":"Point"}
}