{
  "type": "Feature",
  "properties": {
    "addr:full":"Calle de Sauceda, 35 Madrid Madrid 28050",
    "addr:housenumber":"35",
    "addr:postcode":"madrid;28050",
    "addr:street":"Calle De Sauceda",
    "iso:country":"ES",
    "sg:address":"Calle de Sauceda, 35",
    "sg:city":"Madrid",
    "sg:orig_category":"Cerrajer\u00cda, Ferrallista",
    "sg:phone":"+34 917 66 04 51",
    "sg:postcode":"28050",
    "sg:province":"Madrid",
    "wof:name":"Garmar Construcciones Metalicas S. L.",
    "wof:placetype":"venue"
},
  "geometry": {"coordinates":[-3.6388890743,40.5049438477],"type":"Point"}
}