{
  "type": "Feature",
  "properties": {
    "addr:full":"Calle de Quart, 66 Valencia Valencia 46008",
    "addr:housenumber":"66",
    "addr:postcode":"46008",
    "addr:street":"Calle De Quart",
    "iso:country":"ES",
    "sg:address":"Calle de Quart, 66",
    "sg:city":"Valencia",
    "sg:orig_category":"Fisioterapia",
    "sg:phone":"+34 963 91 41 59",
    "sg:postcode":"46008",
    "sg:province":"Valencia",
    "wof:name":"Medicina Y Fisioterapia S.l.",
    "wof:placetype":"venue"
},
  "geometry": {"coordinates":[-0.3846819997,39.4757118225],"type":"Point"}
}