{
  "type": "Feature",
  "properties": {
    "iso:country":"ES",
    "sg:address":"Calle de Cervantes, 14",
    "sg:city":"Isla Mayor",
    "sg:orig_category":"Cervezas (negociantes Y Depositarios)",
    "sg:phone":"+34 954 77 74 70",
    "sg:postcode":"41140",
    "sg:province":"Sevilla",
    "wof:name":"Parra Arenas Rosario",
    "wof:placetype":"venue"
},
  "geometry": {"coordinates":[-6.1602983475,37.1360321045],"type":"Point"}
}