{
  "type": "Feature",
  "properties": {
    "addr:full":"Pl. Mayor, 1 Infiesto Asturias 33530",
    "addr:housenumber":"1",
    "addr:postcode":"33530",
    "addr:street":"Pl. Mayor",
    "iso:country":"ES",
    "sg:address":"Pl. Mayor, 1",
    "sg:city":"Infiesto",
    "sg:orig_category":"Autob\u00das (explotaci\u00d3n Y Servicios De)",
    "sg:phone":"+34 985 71 08 25",
    "sg:postcode":"33530",
    "sg:province":"Asturias",
    "wof:name":"Autocares Costa Verde S. A.",
    "wof:placetype":"venue"
},
  "geometry": {"coordinates":[-5.3640851974,43.3486022949],"type":"Point"}
}