{
  "type": "Feature",
  "properties": {
    "addr:full":"Calle de Poeta Fernando Gonzalez, 5 S.gregorio Las Palmas 35200",
    "addr:housenumber":"5",
    "addr:postcode":"35200",
    "addr:street":"Calle De Poeta Fernando Gonzalez;Las Palmas",
    "iso:country":"ES",
    "sg:address":"Calle de Poeta Fernando Gonzalez, 5",
    "sg:city":"S.gregorio",
    "sg:orig_category":"Bancos",
    "sg:phone":"+34 928 68 03 76",
    "sg:postcode":"35200",
    "sg:province":"Las Palmas",
    "wof:name":"Barclays Bank S.a.e.",
    "wof:placetype":"venue"
},
  "geometry": {"coordinates":[-15.4144220352,28.0029888153],"type":"Point"}
}