{
  "type": "Feature",
  "properties": {
    "iso:country":"ES",
    "sg:address":"C/ Valencia, De, 9",
    "sg:city":"S. Antoni Portmany",
    "sg:orig_category":"Electrodom\u00c9sticos (al Por Menor)",
    "sg:phone":"+34 971 34 09 45",
    "sg:postcode":"07820",
    "sg:province":"Islas Baleares",
    "wof:name":"Electro San Antonio S.l.",
    "wof:placetype":"venue"
},
  "geometry": {"coordinates":[1.5188339949,39.1094055176],"type":"Point"}
}