{
  "type": "Feature",
  "properties": {
    "iso:country":"ES",
    "sg:address":"Carretera De Cordoba, S/n",
    "sg:city":"Antequera",
    "sg:orig_category":"Semiller\u00cdas",
    "sg:phone":"+34 952 70 00 89",
    "sg:postcode":"29200",
    "sg:province":"M\u00e1laga",
    "wof:name":"Viveros La Estacion S.l",
    "wof:placetype":"venue"
},
  "geometry": {"coordinates":[-4.5514659882,37.0215644836],"type":"Point"}
}