{
  "type": "Feature",
  "properties": {
    "addr:full":"Avda Venezuela, 22 Lomo Roman Santa Cruz De Tenerife 38390",
    "addr:housenumber":"22 lomo",
    "addr:postcode":"38390",
    "addr:street":"Avda Venezuela;Roman",
    "iso:country":"ES",
    "sg:address":"Avda Venezuela, 22",
    "sg:city":"Lomo Roman",
    "sg:orig_category":"Transporte En General",
    "sg:phone":"+34 922 30 19 22",
    "sg:postcode":"38390",
    "sg:province":"Santa Cruz De Tenerife",
    "wof:name":"Distribuciones Exclusivas Sercois S.l.",
    "wof:placetype":"venue"
},
  "geometry": {"coordinates":[-16.4917697906,28.425359726],"type":"Point"}
}