{
  "type": "Feature",
  "properties": {
    "iso:country":"ES",
    "sg:address":"Calle de Francisco Maldonado, 2",
    "sg:city":"Santa Marta De Tormes",
    "sg:orig_category":"Construcciones Met\u00c1licas",
    "sg:phone":"+34 923 20 00 01",
    "sg:postcode":"37900",
    "sg:province":"Salamanca",
    "wof:name":"Transformacion Agroganaderas S.l.",
    "wof:placetype":"venue"
},
  "geometry": {"coordinates":[-5.626393795,40.9486846924],"type":"Point"}
}