{
  "type": "Feature",
  "properties": {
    "iso:country":"ES",
    "sg:address":"Carrer de Vila, 23",
    "sg:city":"Lloret Mar",
    "sg:orig_category":"Relojer\u00cda (al Por Menor, Reparaci\u00d3n)",
    "sg:phone":"+34 972 36 43 36",
    "sg:postcode":"17310",
    "sg:province":"Girona",
    "sg:website":"www.swatch.com",
    "wof:name":"Grau Lloret S.l.",
    "wof:placetype":"venue"
},
  "geometry": {"coordinates":[2.8486130238,41.6998672485],"type":"Point"}
}