{
  "type": "Feature",
  "properties": {
    "addr:full":"Calle de Primo De Rivera, S/n Vilvestre Salamanca 37258",
    "addr:housenumber":"s / n",
    "addr:postcode":"37258",
    "addr:street":"Calle De Primo De Rivera",
    "iso:country":"ES",
    "sg:address":"Calle de Primo De Rivera, S/n",
    "sg:city":"Vilvestre",
    "sg:orig_category":"Fabricaci\u00d3n De Quesos",
    "sg:phone":"+34 923 52 46 82",
    "sg:postcode":"37258",
    "sg:province":"Salamanca",
    "wof:name":"Garcia Gorjon Juan",
    "wof:placetype":"venue"
},
  "geometry": {"coordinates":[-6.7193341255,41.1056594849],"type":"Point"}
}