{
  "type": "Feature",
  "properties": {
    "iso:country":"ES",
    "sg:address":"Calle de Monte, 2",
    "sg:city":"Argamasilla Alba",
    "sg:orig_category":"Asesor\u00cda Sobre Comunicaci\u00d3n De Empresas",
    "sg:phone":"+34 926 52 35 26",
    "sg:postcode":"13710",
    "sg:province":"Ciudad Real",
    "sg:website":"www.atctorrealday.com",
    "wof:name":"Atc Gabinete Integral De Asesoria Integral De Empresas S.l.",
    "wof:placetype":"venue"
},
  "geometry": {"coordinates":[-3.0941419601,39.1260986328],"type":"Point"}
}