{
  "type": "Feature",
  "properties": {
    "iso:country":"ES",
    "sg:address":"Calle de Nazaret, 2",
    "sg:city":"Puerto",
    "sg:orig_category":"Inform\u00c1tica (estudios, Servicios, Asesor\u00cda, Formaci\u00d3n)",
    "sg:phone":"+34 962 69 81 69",
    "sg:postcode":"46520",
    "sg:province":"Valencia",
    "sg:website":"www.ideas-sistemas.es",
    "wof:name":"Ideas Sistemas Informaticos S.l.l.",
    "wof:placetype":"venue"
},
  "geometry": {"coordinates":[-0.233099997,39.668182373],"type":"Point"}
}