{
  "type": "Feature",
  "properties": {
    "addr:full":"Calle de Escalona, 88 Madrid Madrid 28024",
    "addr:housenumber":"88",
    "addr:postcode":"madrid;28024",
    "addr:street":"Calle De Escalona",
    "iso:country":"ES",
    "sg:address":"Calle de Escalona, 88",
    "sg:city":"Madrid",
    "sg:orig_category":"Frutas, Legumbres Frescas Y Tempranas (al Por Menor)",
    "sg:phone":"+34 917 11 79 82",
    "sg:postcode":"28024",
    "sg:province":"Madrid",
    "wof:name":"Moreta Sanchez Arturo",
    "wof:placetype":"venue"
},
  "geometry": {"coordinates":[-3.7665510178,40.395362854],"type":"Point"}
}