{
  "type": "Feature",
  "properties": {
    "addr:full":"Calle de General Mola, 4 Ramales Victoria Cantabria 39800",
    "addr:housenumber":"4",
    "addr:postcode":"39800",
    "addr:street":"Calle De General Mola",
    "iso:country":"ES",
    "sg:address":"Calle de General Mola, 4",
    "sg:city":"Ramales Victoria",
    "sg:orig_category":"Abogados",
    "sg:phone":"+34 942 67 83 35",
    "sg:postcode":"39800",
    "sg:province":"Cantabria",
    "wof:name":"Allende Quintano Soledad",
    "wof:placetype":"venue"
},
  "geometry": {"coordinates":[-3.4651834965,43.2572479248],"type":"Point"}
}