{
  "type": "Feature",
  "properties": {
    "iso:country":"ES",
    "sg:address":"Calle de Grecia, S/n",
    "sg:city":"Gri\u00f1on",
    "sg:orig_category":"Sonorizaci\u00d3n, Iluminaci\u00d3n Para Cine, Teatro Y Discotecas (al Por Mayor, Al Por Menor)",
    "sg:phone":"+34 918 14 11 69",
    "sg:postcode":"28971",
    "sg:province":"Madrid",
    "wof:name":"Antonio Cachinero Y Asociados S.l.",
    "wof:placetype":"venue"
},
  "geometry": {"coordinates":[-3.8595981598,40.2076301575],"type":"Point"}
}