{
  "type": "Feature",
  "properties": {
    "iso:country":"ES",
    "sg:address":"Via Laietana, 33",
    "sg:city":"Barcelona",
    "sg:orig_category":"Bancos",
    "sg:phone":"+34 933 10 58 12",
    "sg:postcode":"08003",
    "sg:province":"Barcelona",
    "wof:name":"Banco Popular Espa\u00f1ol",
    "wof:placetype":"venue"
},
  "geometry": {"coordinates":[2.1769959927,41.3851165771],"type":"Point"}
}