{
  "type": "Feature",
  "properties": {
    "addr:full":"Av Cami Dels Capellans, 92 Sitges Barcelona 08870",
    "addr:housenumber":"92",
    "addr:postcode":"08870",
    "addr:street":"Av Cami Dels Capellans",
    "iso:country":"ES",
    "sg:address":"Av Cami Dels Capellans, 92",
    "sg:city":"Sitges",
    "sg:orig_category":"Promotores Constructores",
    "sg:phone":"+34 938 94 28 05",
    "sg:postcode":"08870",
    "sg:province":"Barcelona",
    "wof:name":"Mediterrani Sitges-1 S. L.",
    "wof:placetype":"venue"
},
  "geometry": {"coordinates":[1.8064750433,41.2415885925],"type":"Point"}
}