{
  "type": "Feature",
  "properties": {
    "addr:full":"Paramo, 11 Burgos Burgos 09007",
    "addr:housenumber":"11",
    "addr:postcode":"09007",
    "addr:street":"Paramo",
    "iso:country":"ES",
    "sg:address":"Paramo, 11",
    "sg:city":"Burgos",
    "sg:orig_category":"Empresas De Pintura Y Revestimientos",
    "sg:phone":"+34 947 48 79 51",
    "sg:postcode":"09007",
    "sg:province":"Burgos",
    "wof:name":"Novoa Iglesias Felisindo",
    "wof:placetype":"venue"
},
  "geometry": {"coordinates":[-3.6527891159,42.3476219177],"type":"Point"}
}