{
  "type": "Feature",
  "properties": {
    "addr:full":"Calle de Corin Tellado, 2 Gijon Asturias 33204",
    "addr:housenumber":"2",
    "addr:postcode":"33204",
    "addr:street":"Calle De Corin Tellado",
    "iso:country":"ES",
    "sg:address":"Calle de Corin Tellado, 2",
    "sg:city":"Gijon",
    "sg:orig_category":"Impermeabilizantes",
    "sg:phone":"+34 985 36 00 40",
    "sg:postcode":"33204",
    "sg:province":"Asturias",
    "sg:website":"www.texsa.com",
    "wof:name":"Texsa S.a.",
    "wof:placetype":"venue"
},
  "geometry": {"coordinates":[-5.6431846619,43.5276222229],"type":"Point"}
}