{
  "type": "Feature",
  "properties": {
    "addr:full":"Rua Vicente Risco, 9 Xinzo De Limia Ourense 32630",
    "addr:housenumber":"9",
    "addr:postcode":"32630",
    "addr:street":"Rua Vicente Risco",
    "iso:country":"ES",
    "sg:address":"Rua Vicente Risco, 9",
    "sg:city":"Xinzo De Limia",
    "sg:orig_category":"Ense\u00d1anza, Formaci\u00d3n Profesional: Aprendizaje",
    "sg:phone":"+34 988 46 24 88",
    "sg:postcode":"32630",
    "sg:province":"Ourense",
    "wof:name":"Xunta De Galicia",
    "wof:placetype":"venue"
},
  "geometry": {"coordinates":[-7.7233090401,42.0626716614],"type":"Point"}
}