{
  "type": "Feature",
  "properties": {
    "addr:full":"Ctra Ecija-osuna, Km. 0001,5 Ecija Sevilla 41400",
    "addr:postcode":"41400",
    "addr:street":"Ctra Ecija-Osuna Km. 0001,5",
    "iso:country":"ES",
    "sg:address":"Ctra Ecija-osuna, Km. 0001,5",
    "sg:city":"Ecija",
    "sg:orig_category":"Panader\u00cdas, Panader\u00cdas",
    "sg:phone":"+34 955 90 47 90",
    "sg:postcode":"41400",
    "sg:province":"Sevilla",
    "wof:name":"Confiterias Del Sur S.l.",
    "wof:placetype":"venue"
},
  "geometry": {"coordinates":[-5.0782690048,37.5395584106],"type":"Point"}
}