{
  "type": "Feature",
  "properties": {
    "iso:country":"ES",
    "sg:address":"Calle de General Alava, 24",
    "sg:city":"Vitoria-gasteiz",
    "sg:orig_category":"Confecci\u00d3n (fabricaci\u00d3n, Al Por Mayor)",
    "sg:phone":"+34 945 14 86 08",
    "sg:postcode":"01005",
    "sg:province":"\u00c1lava",
    "wof:name":"Oysho Espa\u00d1a S.a.",
    "wof:placetype":"venue"
},
  "geometry": {"coordinates":[-2.6708610058,42.8447151184],"type":"Point"}
}