{
  "type": "Feature",
  "properties": {
    "addr:full":"Plaz Ventura Rodriguez, 1 Leganes Madrid 28911",
    "addr:housenumber":"1",
    "addr:postcode":"28911",
    "addr:street":"Plaz Ventura Rodriguez",
    "iso:country":"ES",
    "sg:address":"Plaz Ventura Rodriguez, 1",
    "sg:city":"Leganes",
    "sg:orig_category":"Alquiler De Veh\u00cdculos: Turismos Y Utilitarios",
    "sg:phone":"+34 914 98 77 72",
    "sg:postcode":"28911",
    "sg:province":"Madrid",
    "wof:name":"Ingron Gestion S.l.",
    "wof:placetype":"venue"
},
  "geometry": {"coordinates":[-3.7670919895,40.3299980164],"type":"Point"}
}