{
  "type": "Feature",
  "properties": {
    "iso:country":"ES",
    "sg:address":"Avda Aragon, 79",
    "sg:city":"Alto De La Muela",
    "sg:orig_category":"Edici\u00d3n De Diarios, Revistas, Boletines",
    "sg:phone":"+34 976 14 65 09",
    "sg:postcode":"50196",
    "sg:province":"Zaragoza",
    "sg:website":"www.ediciones94.com",
    "wof:name":"Ediciones 94 S.c.",
    "wof:placetype":"venue"
},
  "geometry": {"coordinates":[-1.0952290297,41.5870857239],"type":"Point"}
}