{
  "type": "Feature",
  "properties": {
    "iso:country":"ES",
    "sg:address":"Calle de Diciembre, 57",
    "sg:city":"Madrid",
    "sg:orig_category":"Madera Para Construcci\u00d3n E Industria",
    "sg:phone":"+34 917 47 50 31",
    "sg:postcode":"28022",
    "sg:province":"Madrid",
    "wof:name":"Hermanos Garcia Vega S.a.",
    "wof:placetype":"venue"
},
  "geometry": {"coordinates":[-3.5695083141,40.4443893433],"type":"Point"}
}