{
  "type": "Feature",
  "properties": {
    "addr:full":"Carretera Leon Collanzo, 168 Matallana Torio Le\u00f3n 24836",
    "addr:housenumber":"168",
    "addr:postcode":"24836",
    "addr:street":"Carretera Leon Collanzo;Torio Leo\u0301N",
    "iso:country":"ES",
    "sg:address":"Carretera Leon Collanzo, 168",
    "sg:city":"Matallana Torio",
    "sg:orig_category":"Panader\u00cdas, Panader\u00cdas",
    "sg:phone":"+34 987 59 11 74",
    "sg:postcode":"24836",
    "sg:province":"Le\u00f3n",
    "wof:name":"Panificadora Del Torio S. L.",
    "wof:placetype":"venue"
},
  "geometry": {"coordinates":[-5.5217638016,42.867275238],"type":"Point"}
}