{
  "type": "Feature",
  "properties": {
    "iso:country":"ES",
    "sg:address":"Rua Colombia, 31",
    "sg:city":"Vigo",
    "sg:orig_category":"Ambulancias",
    "sg:phone":"+34 986 42 24 47",
    "sg:postcode":"36204",
    "sg:province":"Pontevedra",
    "wof:name":"Ambulancias Do Atlantico S.l.",
    "wof:placetype":"venue"
},
  "geometry": {"coordinates":[-8.7091684341,42.2305412292],"type":"Point"}
}