{
  "type": "Feature",
  "properties": {
    "addr:full":"Plaz Estacion De La, S/n Aviles Asturias 33406",
    "addr:housenumber":"s",
    "addr:postcode":"33406",
    "addr:street":"/ N",
    "iso:country":"ES",
    "sg:address":"Plaz Estacion De La, S/n",
    "sg:city":"Aviles",
    "sg:orig_category":"Empresas De Carpinter\u00cda Met\u00c1lica",
    "sg:phone":"+34 985 57 14 59",
    "sg:postcode":"33406",
    "sg:province":"Asturias",
    "wof:name":"Alufebe S.l.",
    "wof:placetype":"venue"
},
  "geometry": {"coordinates":[-5.9026679993,43.5402412415],"type":"Point"}
}