{
  "type": "Feature",
  "properties": {
    "addr:full":"Calle de Bra\u00d1uelas, 34 Fuenlabrada Madrid 28947",
    "addr:housenumber":"34",
    "addr:postcode":"28947",
    "addr:street":"Calle De Bran\u0303Uelas",
    "iso:country":"ES",
    "sg:address":"Calle de Bra\u00d1uelas, 34",
    "sg:city":"Fuenlabrada",
    "sg:orig_category":"Construcciones Met\u00c1licas",
    "sg:phone":"+34 916 42 11 46",
    "sg:postcode":"28947",
    "sg:province":"Madrid",
    "wof:name":"Industrias Metalicas Del Centro S. A.",
    "wof:placetype":"venue"
},
  "geometry": {"coordinates":[-3.7520625591,40.2563934326],"type":"Point"}
}