{
  "type": "Feature",
  "properties": {
    "addr:full":"Calle de Convento, 2 Castilleja Cuesta Sevilla 41950",
    "addr:housenumber":"2",
    "addr:postcode":"41950",
    "addr:street":"Calle De Convento;Cuesta Sevilla",
    "iso:country":"ES",
    "sg:address":"Calle de Convento, 2",
    "sg:city":"Castilleja Cuesta",
    "sg:orig_category":"Instalaci\u00d3n, Reparaci\u00d3n De Calefacci\u00d3n El\u00c9ctrica",
    "sg:phone":"+34 954 16 23 77",
    "sg:postcode":"41950",
    "sg:province":"Sevilla",
    "wof:name":"G.s.b.ingenieros,s.c.",
    "wof:placetype":"venue"
},
  "geometry": {"coordinates":[-6.0525817871,37.387008667],"type":"Point"}
}