{
  "type": "Feature",
  "properties": {
    "addr:full":"Calle de Cirilo Amoros, 74 Valencia Valencia 46004",
    "addr:housenumber":"74",
    "addr:postcode":"46004",
    "addr:street":"Calle De Cirilo Amoros",
    "iso:country":"ES",
    "sg:address":"Calle de Cirilo Amoros, 74",
    "sg:city":"Valencia",
    "sg:orig_category":"Art\u00cdculos De Decoraci\u00d3n",
    "sg:phone":"+34 963 52 99 17",
    "sg:postcode":"46004",
    "sg:province":"Valencia",
    "wof:name":"Llansola Bellido Isabel",
    "wof:placetype":"venue"
},
  "geometry": {"coordinates":[-0.367038697,39.4691734314],"type":"Point"}
}