{
  "type": "Feature",
  "properties": {
    "addr:full":"Praz Europa (de), S/n Santiago De Compostela La Coru\u00f1a 15703",
    "addr:postcode":"15703",
    "addr:street":"Praz Europa De S / N;Corun\u0303A",
    "iso:country":"ES",
    "sg:address":"Praz Europa (de), S/n",
    "sg:city":"Santiago De Compostela",
    "sg:orig_category":"Lencer\u00cda Femenina, Corseter\u00cda, Trajes De Ba\u00d1o (al Por Menor)",
    "sg:phone":"+34 981 56 02 31",
    "sg:postcode":"15703",
    "sg:province":"La Coru\u00f1a",
    "wof:name":"Garcia Perez Maria Del Carmen",
    "wof:placetype":"venue"
},
  "geometry": {"coordinates":[-8.5240430832,42.8899269104],"type":"Point"}
}