{
  "type": "Feature",
  "properties": {
    "addr:full":"Calle de Virgen De La Vega, 42 Haro La Rioja 26200",
    "addr:housenumber":"42",
    "addr:postcode":"26200",
    "addr:street":"Calle De Virgen De La Vega",
    "iso:country":"ES",
    "sg:address":"Calle de Virgen De La Vega, 42",
    "sg:city":"Haro",
    "sg:orig_category":"Alquiler De V\u00cddeo",
    "sg:phone":"+34 941 30 34 44",
    "sg:postcode":"26200",
    "sg:province":"La Rioja",
    "wof:name":"Delgado Marion Jose Antonio",
    "wof:placetype":"venue"
},
  "geometry": {"coordinates":[-2.8508551121,42.5760993958],"type":"Point"}
}