{
  "type": "Feature",
  "properties": {
    "iso:country":"ES",
    "sg:address":"Pl Capellers, 1",
    "sg:city":"Palma",
    "sg:orig_category":"Confecci\u00d3n De Trajes Para Se\u00d1oras",
    "sg:phone":"+34 971 71 77 48",
    "sg:postcode":"07002",
    "sg:province":"Islas Baleares",
    "wof:name":"Llull Pi\u00f1a Bartolome",
    "wof:placetype":"venue"
},
  "geometry": {"coordinates":[2.6523199081,39.5710754395],"type":"Point"}
}