{
  "type": "Feature",
  "properties": {
    "addr:full":"Partida Carretera Ademuz, Km. 0022,0 Conarda Valencia 46185",
    "addr:postcode":"46185",
    "addr:street":"Partida Carretera Ademuz Km. 0022,0 Conarda",
    "iso:country":"ES",
    "sg:address":"Partida Carretera Ademuz, Km. 0022,0",
    "sg:city":"Conarda",
    "sg:orig_category":"M\u00c1rmoles, Granitos Y Piedras Naturales",
    "sg:phone":"+34 962 76 00 04",
    "sg:postcode":"46185",
    "sg:province":"Valencia",
    "wof:name":"Marmoles Pobla S.l.",
    "wof:placetype":"venue"
},
  "geometry": {"coordinates":[-0.5534440279,39.5925750732],"type":"Point"}
}