{
  "type": "Feature",
  "properties": {
    "addr:full":"Calle de Ribera De Curtidores, 34 Madrid Madrid 28005",
    "addr:housenumber":"34",
    "addr:postcode":"madrid;28005",
    "addr:street":"Calle De Ribera De Curtidores",
    "iso:country":"ES",
    "sg:address":"Calle de Ribera De Curtidores, 34",
    "sg:city":"Madrid",
    "sg:orig_category":"Institutos De Belleza",
    "sg:phone":"+34 914 68 29 56",
    "sg:postcode":"28005",
    "sg:province":"Madrid",
    "sg:website":"www.aires.es",
    "wof:name":"Aires Belleza Asociados S.l.u.",
    "wof:placetype":"venue"
},
  "geometry": {"coordinates":[-3.7067101002,40.4042167664],"type":"Point"}
}