{
  "type": "Feature",
  "properties": {
    "iso:country":"ES",
    "sg:address":"Plaz Cervantes, 5",
    "sg:city":"Palencia",
    "sg:orig_category":"Reciclaje De Aceites Y Grasas Industriales",
    "sg:phone":"+34 979 70 17 31",
    "sg:postcode":"34005",
    "sg:province":"Palencia",
    "wof:name":"Recuperacion De Residuos Petroliferos S.l.",
    "wof:placetype":"venue"
},
  "geometry": {"coordinates":[-4.5383758545,42.012348175],"type":"Point"}
}