{
  "type": "Feature",
  "properties": {
    "addr:full":"Ctra Adanero-gijon, Km. 0003,0 Zaratan Valladolid 47610",
    "addr:postcode":"47610",
    "addr:street":"Ctra Adanero-Gijon Km. 0003,0 Zaratan",
    "iso:country":"ES",
    "sg:address":"Ctra Adanero-gijon, Km. 0003,0",
    "sg:city":"Zaratan",
    "sg:orig_category":"\u00d3ptica: Instrumentos (fabricaci\u00d3n)",
    "sg:phone":"+34 983 36 20 17",
    "sg:postcode":"47610",
    "sg:province":"Valladolid",
    "sg:website":"www.visionlab.es",
    "wof:name":"Visionlab",
    "wof:placetype":"venue"
},
  "geometry": {"coordinates":[-4.7737565041,41.6607093811],"type":"Point"}
}