{
  "type": "Feature",
  "properties": {
    "addr:full":"Carrer de Pilar, 49 Premia Mar Barcelona 08330",
    "addr:housenumber":"49",
    "addr:postcode":"08330",
    "addr:street":"Carrer De Pilar",
    "iso:country":"ES",
    "sg:address":"Carrer de Pilar, 49",
    "sg:city":"Premia Mar",
    "sg:orig_category":"Mercer\u00cda, Lencer\u00cda (al Por Menor)",
    "sg:phone":"+34 937 51 76 04",
    "sg:postcode":"08330",
    "sg:province":"Barcelona",
    "wof:name":"Sanchez Castilla Isabel",
    "wof:placetype":"venue"
},
  "geometry": {"coordinates":[2.3562760353,41.4936523438],"type":"Point"}
}