{
  "type": "Feature",
  "properties": {
    "iso:country":"ES",
    "sg:address":"Calle de Pintor Sorolla, 5",
    "sg:city":"Valencia",
    "sg:orig_category":"Arquitectos",
    "sg:phone":"+34 963 74 35 11",
    "sg:postcode":"46002",
    "sg:province":"Valencia",
    "wof:name":"Alcon Traver Rafael",
    "wof:placetype":"venue"
},
  "geometry": {"coordinates":[-0.3737002015,39.4706230164],"type":"Point"}
}