{
  "type": "Feature",
  "properties": {
    "iso:country":"ES",
    "sg:address":"Calle de Luis Doreste Silva, 109",
    "sg:city":"Palmas De Gran Canaria",
    "sg:orig_category":"Caf\u00c9s, Bares, Cervecer\u00cdas",
    "sg:phone":"+34 928 24 47 43",
    "sg:postcode":"35004",
    "sg:province":"Las Palmas",
    "wof:name":"Hernandez Quintana Luis",
    "wof:placetype":"venue"
},
  "geometry": {"coordinates":[-15.4254589081,28.1206798553],"type":"Point"}
}