{
  "type": "Feature",
  "properties": {
    "addr:full":"Pl. Petita, 8 Riudoms Tarragona 43330",
    "addr:housenumber":"8",
    "addr:postcode":"43330",
    "addr:street":"Petita",
    "iso:country":"ES",
    "sg:address":"Pl. Petita, 8",
    "sg:city":"Riudoms",
    "sg:orig_category":"Cajas De Ahorro",
    "sg:phone":"+34 977 85 00 64",
    "sg:postcode":"43330",
    "sg:province":"Tarragona",
    "sg:website":"www.caixatarragona.es",
    "wof:name":"Caixa D'estalvis De Tarragona",
    "wof:placetype":"venue"
},
  "geometry": {"coordinates":[1.051838994,41.1383934021],"type":"Point"}
}