{
  "type": "Feature",
  "properties": {
    "iso:country":"ES",
    "sg:address":"Calle de Padre Perera, 3",
    "sg:city":"Valencia",
    "sg:orig_category":"Bisuter\u00cda, Joyer\u00cda, Relojer\u00cda (al Por Menor)",
    "sg:phone":"+34 963 34 66 45",
    "sg:postcode":"46006",
    "sg:province":"Valencia",
    "wof:name":"Alcaide Esteban Rosa Maria",
    "wof:placetype":"venue"
},
  "geometry": {"coordinates":[-0.371933192,39.463104248],"type":"Point"}
}