{
  "type": "Feature",
  "properties": {
    "addr:full":"Calle de Siervas De Jesus, 3 Logro\u00f1o La Rioja 26001",
    "addr:housenumber":"3",
    "addr:postcode":"26001",
    "addr:street":"Calle De Siervas;Jesus;Rioja",
    "iso:country":"ES",
    "sg:address":"Calle de Siervas De Jesus, 3",
    "sg:city":"Logro\u00f1o",
    "sg:orig_category":"Lencer\u00cda Femenina, Corseter\u00cda, Trajes De Ba\u00d1o (al Por Menor)",
    "sg:phone":"+34 941 22 50 02",
    "sg:postcode":"26001",
    "sg:province":"La Rioja",
    "wof:name":"Martin Lozano Maria Luisa",
    "wof:placetype":"venue"
},
  "geometry": {"coordinates":[-2.4506289959,42.4652290344],"type":"Point"}
}