{
  "type": "Feature",
  "properties": {
    "iso:country":"ES",
    "sg:address":"Carrer de Corunya (la), 97",
    "sg:city":"Sant Vicen\u00c7 Dels Horts",
    "sg:orig_category":"Molduras, Junquillos, Listones Y Molduras Perforadas",
    "sg:phone":"+34 936 56 25 61",
    "sg:postcode":"08620",
    "sg:province":"Barcelona",
    "wof:name":"Revelles Garcia Manuel",
    "wof:placetype":"venue"
},
  "geometry": {"coordinates":[2.0030100346,41.3905410767],"type":"Point"}
}