{
  "type": "Feature",
  "properties": {
    "iso:country":"ES",
    "sg:address":"Calle de Zenete, 2",
    "sg:city":"Malaga",
    "sg:orig_category":"Laboratorios Y Trabajos De Fotograf\u00cda, V\u00cddeo Y Cine",
    "sg:phone":"+34 952 26 20 79",
    "sg:postcode":"29013",
    "sg:province":"M\u00e1laga",
    "wof:name":"Sell Cristia Maria",
    "wof:placetype":"venue"
},
  "geometry": {"coordinates":[-4.4151477814,36.7301559448],"type":"Point"}
}