{
  "type": "Feature",
  "properties": {
    "addr:full":"Carrer de Castillejos, 395 Barcelona Barcelona 08025",
    "addr:housenumber":"395",
    "addr:postcode":"08025",
    "addr:street":"Carrer De Castillejos",
    "iso:country":"ES",
    "sg:address":"Carrer de Castillejos, 395",
    "sg:city":"Barcelona",
    "sg:orig_category":"Molduras, Junquillos, Listones Y Molduras Perforadas",
    "sg:phone":"+34 934 55 71 60",
    "sg:postcode":"08025",
    "sg:province":"Barcelona",
    "wof:name":"Josep Y Joan Soler Vives C.b.",
    "wof:placetype":"venue"
},
  "geometry": {"coordinates":[2.1707439423,41.4121246338],"type":"Point"}
}