{
  "type": "Feature",
  "properties": {
    "addr:full":"Calle de Torno, S/n Pilas Sevilla 41840",
    "addr:housenumber":"s / n",
    "addr:postcode":"41840",
    "addr:street":"Calle De Torno",
    "iso:country":"ES",
    "sg:address":"Calle de Torno, S/n",
    "sg:city":"Pilas",
    "sg:orig_category":"Empresas De Carpinter\u00cda Met\u00c1lica",
    "sg:phone":"+34 954 75 11 12",
    "sg:postcode":"41840",
    "sg:province":"Sevilla",
    "wof:name":"Carpinteria Metalica Ramon Barragan S.l.",
    "wof:placetype":"venue"
},
  "geometry": {"coordinates":[-6.2995848656,37.3090515137],"type":"Point"}
}