{
  "type": "Feature",
  "properties": {
    "addr:full":"Calle de Gran Via, 32 Hellin Albacete 02400",
    "addr:housenumber":"32",
    "addr:postcode":"02400",
    "addr:street":"Calle De Gran Via",
    "iso:country":"ES",
    "sg:address":"Calle de Gran Via, 32",
    "sg:city":"Hellin",
    "sg:orig_category":"Bisuter\u00cda, Joyer\u00cda, Relojer\u00cda (al Por Menor)",
    "sg:phone":"+34 967 30 14 30",
    "sg:postcode":"02400",
    "sg:province":"Albacete",
    "wof:name":"Cano Martinez Santiago",
    "wof:placetype":"venue"
},
  "geometry": {"coordinates":[-1.6965229511,38.5082244873],"type":"Point"}
}