{
  "type": "Feature",
  "properties": {
    "iso:country":"ES",
    "sg:address":"La Barca, 1",
    "sg:city":"San Pelayo",
    "sg:orig_category":"Agricultores, Agricultores",
    "sg:phone":"+34 987 37 63 18",
    "sg:postcode":"24356",
    "sg:province":"Le\u00f3n",
    "wof:name":"Gonzalez Ja\u00f1ez Francisco",
    "wof:placetype":"venue"
},
  "geometry": {"coordinates":[-5.8697090149,42.4076309204],"type":"Point"}
}