{
  "type": "Feature",
  "properties": {
    "addr:full":"Rua San Miguel, 2 Ourense Ourense 32005",
    "addr:housenumber":"2",
    "addr:postcode":"32005",
    "addr:street":"Rua San Miguel",
    "iso:country":"ES",
    "sg:address":"Rua San Miguel, 2",
    "sg:city":"Ourense",
    "sg:orig_category":"Bisuter\u00cda, Joyer\u00cda, Relojer\u00cda (al Por Menor)",
    "sg:phone":"+34 988 22 78 81",
    "sg:postcode":"32005",
    "sg:province":"Ourense",
    "wof:name":"Lorelzo  Maruxa",
    "wof:placetype":"venue"
},
  "geometry": {"coordinates":[-7.8633131981,42.3377227783],"type":"Point"}
}