{
  "type": "Feature",
  "properties": {
    "addr:full":"Calle de Leon Y Castillo, 169 Arrecife Las Palmas 35500",
    "addr:housenumber":"169",
    "addr:postcode":"35500",
    "addr:street":"Calle De Leon Y Castillo",
    "iso:country":"ES",
    "sg:address":"Calle de Leon Y Castillo, 169",
    "sg:city":"Arrecife",
    "sg:orig_category":"Cajas De Ahorro",
    "sg:phone":"+34 928 84 44 54",
    "sg:postcode":"35500",
    "sg:province":"Las Palmas",
    "sg:website":"www.lacajadecanarias.es",
    "wof:name":"Caja Insular De Ahorros De Canarias",
    "wof:placetype":"venue"
},
  "geometry": {"coordinates":[-13.5462427139,28.9740390778],"type":"Point"}
}