{
  "type": "Feature",
  "properties": {
    "addr:full":"Calle de Sombrereria, 11 Bilbao Vizcaya 48005",
    "addr:housenumber":"11",
    "addr:postcode":"48005",
    "addr:street":"Calle De Sombrereria",
    "iso:country":"ES",
    "sg:address":"Calle de Sombrereria, 11",
    "sg:city":"Bilbao",
    "sg:orig_category":"Complementos De Vestir (al Por Menor)",
    "sg:phone":"+34 944 15 70 00",
    "sg:postcode":"48005",
    "sg:province":"Vizcaya",
    "wof:name":"Alvarez Sanchez Natividad",
    "wof:placetype":"venue"
},
  "geometry": {"coordinates":[-2.9238379002,43.2571983337],"type":"Point"}
}