{
  "type": "Feature",
  "properties": {
    "iso:country":"ES",
    "sg:address":"Barr Hoya (la), S/n",
    "sg:city":"Argo\u00f1os",
    "sg:orig_category":"Muebles Y Accesorios Para Cocinas Y Cuartos De Ba\u00d1o (al Por Menor)",
    "sg:phone":"+34 942 62 62 82",
    "sg:postcode":"39197",
    "sg:province":"Cantabria",
    "wof:name":"Muebles Gofersan S.l.",
    "wof:placetype":"venue"
},
  "geometry": {"coordinates":[-3.4864890575,43.4572067261],"type":"Point"}
}