{
  "type": "Feature",
  "properties": {
    "addr:full":"Calle de Santiago De Compostela, 36 Madrid Madrid 28034",
    "addr:housenumber":"36",
    "addr:postcode":"madrid;28034",
    "addr:street":"Calle De Santiago De Compostela",
    "iso:country":"ES",
    "sg:address":"Calle de Santiago De Compostela, 36",
    "sg:city":"Madrid",
    "sg:orig_category":"Abogados",
    "sg:phone":"+34 917 39 40 98",
    "sg:postcode":"28034",
    "sg:province":"Madrid",
    "wof:name":"Arias Lopez Manuel",
    "wof:placetype":"venue"
},
  "geometry": {"coordinates":[-3.7021319866,40.4834022522],"type":"Point"}
}