{
  "type": "Feature",
  "properties": {
    "iso:country":"ES",
    "sg:address":"Carr Mercat, S/n",
    "sg:city":"Sueca",
    "sg:orig_category":"Carnicer\u00cdas, Carnicer\u00cdas",
    "sg:phone":"+34 961 71 07 01",
    "sg:postcode":"46410",
    "sg:province":"Valencia",
    "wof:name":"V.r.and B. 99 S.l.",
    "wof:placetype":"venue"
},
  "geometry": {"coordinates":[-0.311270386,39.2016906738],"type":"Point"}
}