{
  "type": "Feature",
  "properties": {
    "iso:country":"ES",
    "sg:address":"Pol Ind Poyo De Reva, S/n",
    "sg:city":"Riba-roja Turia",
    "sg:orig_category":"Maquinaria Para Industrias Diversas",
    "sg:phone":"+34 961 66 87 55",
    "sg:postcode":"46190",
    "sg:province":"Valencia",
    "sg:website":"www.itv.es",
    "wof:name":"Industria Tecnica Valenciana S. A.",
    "wof:placetype":"venue"
},
  "geometry": {"coordinates":[-0.5698940158,39.5458450317],"type":"Point"}
}