{
  "type": "Feature",
  "properties": {
    "addr:full":"Calle de Marcelo Macias, 1 Astorga Le\u00f3n 24700",
    "addr:postcode":"24700",
    "addr:street":"Calle De Marcelo Macias 1 Astorga Leo\u0301N",
    "iso:country":"ES",
    "sg:address":"Calle de Marcelo Macias, 1",
    "sg:city":"Astorga",
    "sg:orig_category":"Asesor\u00cda Fiscal Y Jur\u00cddica",
    "sg:phone":"+34 987 61 73 54",
    "sg:postcode":"24700",
    "sg:province":"Le\u00f3n",
    "wof:name":"Asesoria Jesus O. Del Campo S.l.",
    "wof:placetype":"venue"
},
  "geometry": {"coordinates":[-6.0536561012,42.4563713074],"type":"Point"}
}