{
  "type": "Feature",
  "properties": {
    "iso:country":"ES",
    "sg:address":"Calle de Real, 27",
    "sg:city":"Tielmes",
    "sg:orig_category":"Controles De Edificaci\u00d3n (construcci\u00d3n, Seguridad)",
    "sg:phone":"+34 918 74 62 21",
    "sg:postcode":"28550",
    "sg:province":"Madrid",
    "wof:name":"Duran Duran Luis",
    "wof:placetype":"venue"
},
  "geometry": {"coordinates":[-3.3170681,40.2448348999],"type":"Point"}
}