{
  "type": "Feature",
  "properties": {
    "addr:full":"Calle de Salvador Echeandia, 2 Irun Guip\u00f9zcoa 20304",
    "addr:housenumber":"2",
    "addr:postcode":"20304",
    "addr:street":"Calle De Salvador Echeandia;Guipu\u0300Zcoa",
    "iso:country":"ES",
    "sg:address":"Calle de Salvador Echeandia, 2",
    "sg:city":"Irun",
    "sg:orig_category":"Material Y Herramientas Agr\u00cdcolas",
    "sg:phone":"+34 943 62 73 31",
    "sg:postcode":"20304",
    "sg:province":"Guip\u00f9zcoa",
    "wof:name":"Manuel Querejeta Muguruza",
    "wof:placetype":"venue"
},
  "geometry": {"coordinates":[-1.7859319448,43.3389205933],"type":"Point"}
}