{
  "type": "Feature",
  "properties": {
    "addr:full":"Pg Sant Jordi, 12 Mas Rampinyo Barcelona 08110",
    "addr:housenumber":"12",
    "addr:postcode":"08110",
    "addr:street":"Pg Sant Jordi",
    "iso:country":"ES",
    "sg:address":"Pg Sant Jordi, 12",
    "sg:city":"Mas Rampinyo",
    "sg:orig_category":"Maquinaria Para Industrias Diversas",
    "sg:phone":"+34 935 64 36 38",
    "sg:postcode":"08110",
    "sg:province":"Barcelona",
    "wof:name":"Frances Ribera Juan",
    "wof:placetype":"venue"
},
  "geometry": {"coordinates":[2.1796360016,41.4942054749],"type":"Point"}
}