{
  "type": "Feature",
  "properties": {
    "iso:country":"ES",
    "sg:address":"Avda Prudencio Gonzalez, 21",
    "sg:city":"Posada",
    "sg:orig_category":"M\u00c9dicos: Estomatolog\u00cda",
    "sg:phone":"+34 985 77 01 93",
    "sg:postcode":"33424",
    "sg:province":"Asturias",
    "wof:name":"Diaz Fernandez Cesar Paulino",
    "wof:placetype":"venue"
},
  "geometry": {"coordinates":[-5.8523058891,43.4402923584],"type":"Point"}
}