{
  "type": "Feature",
  "properties": {
    "iso:country":"ES",
    "sg:address":"Polig. De Zies(fragosi\u00f1o), 37",
    "sg:city":"Vigo",
    "sg:orig_category":"Mec\u00c1nico Del Autom\u00d3vil",
    "sg:phone":"+34 986 47 32 06",
    "sg:postcode":"36214",
    "sg:province":"Pontevedra",
    "wof:name":"Davila Alvarez Antonio",
    "wof:placetype":"venue"
},
  "geometry": {"coordinates":[-8.7059106827,42.2124443054],"type":"Point"}
}