{
  "type": "Feature",
  "properties": {
    "addr:full":"Carr Maria Auxiliadora, 83 Badalona Barcelona 08912",
    "addr:housenumber":"83",
    "addr:postcode":"08912",
    "addr:street":"Carr Maria Auxiliadora",
    "iso:country":"ES",
    "sg:address":"Carr Maria Auxiliadora, 83",
    "sg:city":"Badalona",
    "sg:orig_category":"Fabricaci\u00d3n De Moldes Y Modelos",
    "sg:phone":"+34 933 88 76 80",
    "sg:postcode":"08912",
    "sg:province":"Barcelona",
    "wof:name":"Sola Moralla Andres",
    "wof:placetype":"venue"
},
  "geometry": {"coordinates":[2.2414050102,41.4416275024],"type":"Point"}
}