{
  "type": "Feature",
  "properties": {
    "addr:full":"Carrer de Germa Estruch, 5 Prat Llobregat Barcelona 08820",
    "addr:housenumber":"5",
    "addr:postcode":"08820",
    "addr:street":"Carrer De Germa Estruch;Llobregat",
    "iso:country":"ES",
    "sg:address":"Carrer de Germa Estruch, 5",
    "sg:city":"Prat Llobregat",
    "sg:orig_category":"Productos Qu\u00cdmicos (fabricaci\u00d3n, Al Por Mayor)",
    "sg:phone":"+34 933 78 92 10",
    "sg:postcode":"08820",
    "sg:province":"Barcelona",
    "wof:name":"Nch Espa\u00f1ola S.a.",
    "wof:placetype":"venue"
},
  "geometry": {"coordinates":[2.0901360512,41.3274116516],"type":"Point"}
}