{
  "type": "Feature",
  "properties": {
    "iso:country":"ES",
    "sg:address":"Amadeo, 2",
    "sg:city":"El Raal",
    "sg:orig_category":"Carnicer\u00cdas, Carnicer\u00cdas",
    "sg:phone":"+34 968 87 08 78",
    "sg:postcode":"30139",
    "sg:province":"Murcia",
    "wof:name":"Jamones El Cruce S.l.",
    "wof:placetype":"venue"
},
  "geometry": {"coordinates":[-1.0427490473,38.0317192078],"type":"Point"}
}