{
  "type": "Feature",
  "properties": {
    "addr:full":"Trav Dalt, 33 Barcelona Barcelona 08024",
    "addr:housenumber":"33",
    "addr:postcode":"08024",
    "addr:street":"Trav Dalt",
    "iso:country":"ES",
    "sg:address":"Trav Dalt, 33",
    "sg:city":"Barcelona",
    "sg:orig_category":"Expertos Contables, Revisores De Cuentas",
    "sg:phone":"+34 932 84 64 74",
    "sg:postcode":"08024",
    "sg:province":"Barcelona",
    "wof:name":"Orient Giner Pascual",
    "wof:placetype":"venue"
},
  "geometry": {"coordinates":[2.1526629925,41.4088172913],"type":"Point"}
}