{
  "type": "Feature",
  "properties": {
    "iso:country":"ES",
    "sg:address":"Plaz Fuerte (del), 15",
    "sg:city":"Calatayud",
    "sg:orig_category":"Bisuter\u00cda, Joyer\u00cda, Relojer\u00cda (al Por Menor)",
    "sg:phone":"+34 976 88 31 53",
    "sg:postcode":"50300",
    "sg:province":"Zaragoza",
    "wof:name":"Joyeria Relojeria Cintado E Hijos S.c.",
    "wof:placetype":"venue"
},
  "geometry": {"coordinates":[-1.6394540071,41.3522415161],"type":"Point"}
}