{
  "type": "Feature",
  "properties": {
    "iso:country":"ES",
    "sg:address":"Constitucion, S/n",
    "sg:city":"Madro\u00f1o",
    "sg:orig_category":"Administraciones Regionales, Departamentales Y Locales",
    "sg:phone":"+34 954 13 70 00",
    "sg:postcode":"41697",
    "sg:province":"Sevilla",
    "wof:name":"Ayuntamiento Del Madro\u00d1o",
    "wof:placetype":"venue"
},
  "geometry": {"coordinates":[-6.5124406815,37.6456413269],"type":"Point"}
}