{
  "type": "Feature",
  "properties": {
    "addr:full":"Calle de Bertsolari Uztapide, 5 Irun Guip\u00f9zcoa 20304",
    "addr:housenumber":"5",
    "addr:postcode":"20304",
    "addr:street":"Calle De Bertsolari Uztapide;Guipu\u0300Zcoa",
    "iso:country":"ES",
    "sg:address":"Calle de Bertsolari Uztapide, 5",
    "sg:city":"Irun",
    "sg:orig_category":"Lencer\u00cda Femenina, Corseter\u00cda, Trajes De Ba\u00d1o (al Por Menor)",
    "sg:phone":"+34 943 63 52 98",
    "sg:postcode":"20304",
    "sg:province":"Guip\u00f9zcoa",
    "wof:name":"Hernandez Garcia Loli",
    "wof:placetype":"venue"
},
  "geometry": {"coordinates":[-1.7823599577,43.3379402161],"type":"Point"}
}