{
  "type": "Feature",
  "properties": {
    "iso:country":"ES",
    "sg:address":"Avda Ribera De Axpe Etorbidea, 2 C",
    "sg:city":"Erandio",
    "sg:orig_category":"Inform\u00c1tica (estudios, Servicios, Asesor\u00cda, Formaci\u00d3n)",
    "sg:phone":"+34 944 53 31 32",
    "sg:postcode":"48950",
    "sg:province":"Vizcaya",
    "sg:website":"www.sarein.com",
    "wof:name":"Sarein Sistemas, S.l.",
    "wof:placetype":"venue"
},
  "geometry": {"coordinates":[-2.9769239426,43.302646637],"type":"Point"}
}