{
  "type": "Feature",
  "properties": {
    "addr:full":"Poligono Industrial, S/n Hiriberri Navarra 31850",
    "addr:postcode":"31850",
    "addr:street":"Industrial S / N;Navarra",
    "iso:country":"ES",
    "sg:address":"Poligono Industrial, S/n",
    "sg:city":"Hiriberri",
    "sg:orig_category":"Ferreter\u00cda (diversos)",
    "sg:phone":"+34 948 60 01 69",
    "sg:postcode":"31850",
    "sg:province":"Navarra",
    "wof:name":"Reciclajes Industriales Balda Y Otazo S.l",
    "wof:placetype":"venue"
},
  "geometry": {"coordinates":[-1.8943669796,42.9152870178],"type":"Point"}
}