{
  "type": "Feature",
  "properties": {
    "addr:full":"Calle de Platanos, 43 Valencia Valencia 46025",
    "addr:housenumber":"43",
    "addr:postcode":"46025",
    "addr:street":"Calle De Platanos",
    "iso:country":"ES",
    "sg:address":"Calle de Platanos, 43",
    "sg:city":"Valencia",
    "sg:orig_category":"Chapister\u00cda",
    "sg:phone":"+34 963 40 81 81",
    "sg:postcode":"46025",
    "sg:province":"Valencia",
    "wof:name":"Peis Auto S.c.",
    "wof:placetype":"venue"
},
  "geometry": {"coordinates":[-0.3888759017,39.4915733337],"type":"Point"}
}