{
  "type": "Feature",
  "properties": {
    "iso:country":"ES",
    "sg:address":"Calle de Central, 33",
    "sg:city":"Arroyo De La Miel-benalmadena Costa",
    "sg:orig_category":"Agencias Y Agentes Comerciales, Representantes",
    "sg:phone":"+34 952 56 01 14",
    "sg:postcode":"29631",
    "sg:province":"M\u00e1laga",
    "wof:name":"Little John  Keneth",
    "wof:placetype":"venue"
},
  "geometry": {"coordinates":[-4.5544900894,36.5993347168],"type":"Point"}
}