{
  "type": "Feature",
  "properties": {
    "addr:full":"Carrer de Pamplona, 81 Barcelona Barcelona 08018",
    "addr:housenumber":"81",
    "addr:postcode":"08018",
    "addr:street":"Carrer De Pamplona",
    "iso:country":"ES",
    "sg:address":"Carrer de Pamplona, 81",
    "sg:city":"Barcelona",
    "sg:orig_category":"Suministros Y Materiales Industriales",
    "sg:phone":"+34 933 09 77 77",
    "sg:postcode":"08018",
    "sg:province":"Barcelona",
    "wof:name":"Suministros Para El Vidrio S. A.",
    "wof:placetype":"venue"
},
  "geometry": {"coordinates":[2.1917080879,41.3962593079],"type":"Point"}
}