{
  "type": "Feature",
  "properties": {
    "addr:full":"Calle de Mayor, S/n Puente Tocinos Murcia 30006",
    "addr:housenumber":"s / n",
    "addr:postcode":"30006",
    "addr:street":"Calle De Mayor",
    "iso:country":"ES",
    "sg:address":"Calle de Mayor, S/n",
    "sg:city":"Puente Tocinos",
    "sg:orig_category":"Bisuter\u00cda, Joyer\u00cda, Relojer\u00cda (al Por Menor)",
    "sg:phone":"+34 968 30 07 63",
    "sg:postcode":"30006",
    "sg:province":"Murcia",
    "wof:name":"Isabel Y Rosario Jimenez Pellicer C.b.",
    "wof:placetype":"venue"
},
  "geometry": {"coordinates":[-1.0896769762,37.9981269836],"type":"Point"}
}