{
  "type": "Feature",
  "properties": {
    "iso:country":"ES",
    "sg:address":"Calle de San Miguel, 1",
    "sg:city":"Sonseca",
    "sg:orig_category":"Fabricaci\u00d3n De Art\u00cdculos Y Equipos Deportivos Y De Ocio",
    "sg:phone":"+34 925 38 26 86",
    "sg:postcode":"45100",
    "sg:province":"Toledo",
    "sg:website":"www paginasamarilals.es",
    "wof:name":"Textil Deporte Sonseca S.l.",
    "wof:placetype":"venue"
},
  "geometry": {"coordinates":[-3.9819674492,39.6760520935],"type":"Point"}
}