{
  "type": "Feature",
  "properties": {
    "iso:country":"ES",
    "sg:address":"Cmno Villaespesa, S/n",
    "sg:city":"Cruz De Caba\u00e7i",
    "sg:orig_category":"Frutos Y Legumbres",
    "sg:phone":"+34 968 44 25 95",
    "sg:postcode":"30815",
    "sg:province":"Murcia",
    "wof:name":"Morpreser S.%.",
    "wof:placetype":"venue"
},
  "geometry": {"coordinates":[-1.5774840117,37.5886192322],"type":"Point"}
}