{
  "type": "Feature",
  "properties": {
    "addr:full":"Trav. Casa De Ines, 6 Malpartida Plasencia C\u00e1ceres 10680",
    "addr:postcode":"10680",
    "addr:street":"Ca\u0301Ceres",
    "iso:country":"ES",
    "sg:address":"Trav. Casa De Ines, 6",
    "sg:city":"Malpartida Plasencia",
    "sg:orig_category":"Contenedores (mercanc\u00cdas)",
    "sg:phone":"+34 927 40 43 04",
    "sg:postcode":"10680",
    "sg:province":"C\u00e1ceres",
    "wof:name":"Transportes Y Gruas Malpartida S.l.",
    "wof:placetype":"venue"
},
  "geometry": {"coordinates":[-6.0495247841,39.9793624878],"type":"Point"}
}