{
  "type": "Feature",
  "properties": {
    "addr:full":"Carbon, 21 Leganes Madrid 28918",
    "addr:housenumber":"21",
    "addr:postcode":"28918",
    "addr:street":"Carbon",
    "iso:country":"ES",
    "sg:address":"Carbon, 21",
    "sg:city":"Leganes",
    "sg:orig_category":"Puertas Y Portales",
    "sg:phone":"+34 916 12 31 19",
    "sg:postcode":"28918",
    "sg:province":"Madrid",
    "wof:name":"Sanchez-manzanero Moreno Jesus",
    "wof:placetype":"venue"
},
  "geometry": {"coordinates":[-3.7989459038,40.348613739],"type":"Point"}
}