{
  "type": "Feature",
  "properties": {
    "iso:country":"ES",
    "sg:address":"Carrer de President Companys, 12",
    "sg:city":"Vendrell",
    "sg:orig_category":"Puertas Autom\u00c1ticas, Puertas De Garaje",
    "sg:phone":"+34 977 66 28 20",
    "sg:postcode":"43700",
    "sg:province":"Tarragona",
    "sg:website":"www.puertasmoreno.com",
    "wof:name":"Puertas Y Automatismos Moreno S.l.",
    "wof:placetype":"venue"
},
  "geometry": {"coordinates":[1.5319119692,41.2148132324],"type":"Point"}
}