{
  "type": "Feature",
  "properties": {
    "iso:country":"ES",
    "sg:address":"Urb Playa Del Arbeyal, 12",
    "sg:city":"Gijon",
    "sg:orig_category":"Promotores Constructores",
    "sg:phone":"+34 985 31 11 33",
    "sg:postcode":"33212",
    "sg:province":"Asturias",
    "sg:website":"www.constructorahispanica.com",
    "wof:name":"Constructora Hispanica S.a.",
    "wof:placetype":"venue"
},
  "geometry": {"coordinates":[-5.6637988091,43.5420341492],"type":"Point"}
}