{
  "type": "Feature",
  "properties": {
    "iso:country":"ES",
    "sg:address":"Calle de Cuadrones Los, 9",
    "sg:city":"Sari\u00f1ena",
    "sg:orig_category":"Contenedores (mercanc\u00cdas)",
    "sg:phone":"+34 974 57 11 98",
    "sg:postcode":"22200",
    "sg:province":"Huesca",
    "wof:name":"Huerva Andreu Francisco",
    "wof:placetype":"venue"
},
  "geometry": {"coordinates":[-0.164072305,41.7886161804],"type":"Point"}
}