{
  "type": "Feature",
  "properties": {
    "addr:full":"Calle de Ayala, 28 Madrid Madrid 28001",
    "addr:housenumber":"28",
    "addr:postcode":"madrid;28001",
    "addr:street":"Calle De Ayala",
    "iso:country":"ES",
    "sg:address":"Calle de Ayala, 28",
    "sg:city":"Madrid",
    "sg:orig_category":"Reposter\u00cdas",
    "sg:phone":"+34 914 35 49 47",
    "sg:postcode":"28001",
    "sg:province":"Madrid",
    "wof:name":"Blanco Fernandez Maria Jesus",
    "wof:placetype":"venue"
},
  "geometry": {"coordinates":[-3.6857919693,40.4277038574],"type":"Point"}
}