{
  "type": "Feature",
  "properties": {
    "addr:full":"Carr Pau Casals, 14 Soses Lleida 25181",
    "addr:housenumber":"14",
    "addr:postcode":"25181",
    "addr:street":"Carr Pau Casals",
    "iso:country":"ES",
    "sg:address":"Carr Pau Casals, 14",
    "sg:city":"Soses",
    "sg:orig_category":"Fabricaci\u00d3n, Venta, Instalaci\u00d3n De R\u00d3tulos, De R\u00d3tulos Luminosos",
    "sg:phone":"+34 973 79 73 59",
    "sg:postcode":"25181",
    "sg:province":"Lleida",
    "wof:name":"Retols Sanauja I Caus S.l.l.",
    "wof:placetype":"venue"
},
  "geometry": {"coordinates":[0.4848999977,41.5310134888],"type":"Point"}
}