{
  "type": "Feature",
  "properties": {
    "iso:country":"ES",
    "sg:address":"Calle de Ronquera, 19",
    "sg:city":"Mairena Alcor",
    "sg:orig_category":"Fotocopias, Reprograf\u00cda",
    "sg:phone":"+34 955 94 22 49",
    "sg:postcode":"41510",
    "sg:province":"Sevilla",
    "wof:name":"Copisteria Zeus S.l.",
    "wof:placetype":"venue"
},
  "geometry": {"coordinates":[-5.7458300591,37.378944397],"type":"Point"}
}