{
  "type": "Feature",
  "properties": {
    "addr:full":"Pl Llibertat, 1 Reus Tarragona 43201",
    "addr:housenumber":"1",
    "addr:postcode":"43201",
    "addr:street":"Pl Llibertat",
    "iso:country":"ES",
    "sg:address":"Pl Llibertat, 1",
    "sg:city":"Reus",
    "sg:orig_category":"M\u00c9dicos: Pediatr\u00cda. Enfermedades De Los Ni\u00d1os",
    "sg:phone":"+34 977 12 89 89",
    "sg:postcode":"43201",
    "sg:province":"Tarragona",
    "wof:name":"Jorfi 2007 S.l.",
    "wof:placetype":"venue"
},
  "geometry": {"coordinates":[1.1059759855,41.158164978],"type":"Point"}
}