{
  "type": "Feature",
  "properties": {
    "addr:full":"Calle de Antonio Antoranz, 28 Madrid Madrid 28025",
    "addr:housenumber":"28",
    "addr:postcode":"madrid;28025",
    "addr:street":"Calle De Antonio Antoranz",
    "iso:country":"ES",
    "sg:address":"Calle de Antonio Antoranz, 28",
    "sg:city":"Madrid",
    "sg:orig_category":"Estancos",
    "sg:phone":"+34 914 62 08 30",
    "sg:postcode":"28025",
    "sg:province":"Madrid",
    "wof:name":"Gonzalez Martinez Maria Angeles",
    "wof:placetype":"venue"
},
  "geometry": {"coordinates":[-3.7412385941,40.3808517456],"type":"Point"}
}