{
  "type": "Feature",
  "properties": {
    "iso:country":"ES",
    "sg:address":"Calle de Moret, 14",
    "sg:city":"Valencia",
    "sg:orig_category":"Oficinas Y Gesti\u00d3n De Inmuebles",
    "sg:phone":"+34 963 92 09 61",
    "sg:postcode":"46003",
    "sg:province":"Valencia",
    "wof:name":"Ini Mediterranea S.l.",
    "wof:placetype":"venue"
},
  "geometry": {"coordinates":[-0.3774490058,39.4796295166],"type":"Point"}
}