{
  "type": "Feature",
  "properties": {
    "iso:country":"ES",
    "sg:address":"Rbla Mendez Nu\u00d1ez, 37",
    "sg:city":"Alacant",
    "sg:orig_category":"Cl\u00cdnicas Dentales",
    "sg:phone":"+34 965 21 80 57",
    "sg:postcode":"03002",
    "sg:province":"Alicante",
    "wof:name":"Romano Navarro Manuel Ernesto",
    "wof:placetype":"venue"
},
  "geometry": {"coordinates":[-0.4846619964,38.3466186523],"type":"Point"}
}