{
  "type": "Feature",
  "properties": {
    "addr:full":"Rua Bellao (do), 9 Ourense Ourense 32001",
    "addr:housenumber":"9",
    "addr:postcode":"32001",
    "addr:street":"Rua Bellao Do",
    "iso:country":"ES",
    "sg:address":"Rua Bellao (do), 9",
    "sg:city":"Ourense",
    "sg:orig_category":"Alimentaci\u00d3n General (al Por Menor)",
    "sg:phone":"+34 988 21 23 04",
    "sg:postcode":"32001",
    "sg:province":"Ourense",
    "wof:name":"Ulla Lopez Juan Manuel",
    "wof:placetype":"venue"
},
  "geometry": {"coordinates":[-7.8814702034,42.3738327026],"type":"Point"}
}