{
  "type": "Feature",
  "properties": {
    "iso:country":"ES",
    "sg:address":"Plaz Escritores, 2",
    "sg:city":"Merida",
    "sg:orig_category":"Deportes Diversos",
    "sg:phone":"+34 924 30 13 31",
    "sg:postcode":"06800",
    "sg:province":"Badajoz",
    "wof:name":"Federacion Extreme\u00f1a De Futbol",
    "wof:placetype":"venue"
},
  "geometry": {"coordinates":[-6.3500027657,38.9179878235],"type":"Point"}
}