{
  "type": "Feature",
  "properties": {
    "addr:full":"Plaz Constitucion De La, 3 Mijas M\u00e1laga 29650",
    "addr:housenumber":"3",
    "addr:postcode":"29650",
    "iso:country":"ES",
    "sg:address":"Plaz Constitucion De La, 3",
    "sg:city":"Mijas",
    "sg:orig_category":"Artesan\u00cda",
    "sg:phone":"+34 952 59 01 28",
    "sg:postcode":"29650",
    "sg:province":"M\u00e1laga",
    "wof:name":"Lo Artesano De Mijas S.l.",
    "wof:placetype":"venue"
},
  "geometry": {"coordinates":[-4.6657028198,36.5399665833],"type":"Point"}
}