{
  "type": "Feature",
  "properties": {
    "addr:full":"Carr Picasso, 11 Mao Islas Baleares 07703",
    "addr:housenumber":"11",
    "addr:postcode":"07703",
    "addr:street":"Carr Picasso",
    "iso:country":"ES",
    "sg:address":"Carr Picasso, 11",
    "sg:city":"Mao",
    "sg:orig_category":"Empresas De Carpinter\u00cda De Madera",
    "sg:phone":"+34 971 35 22 91",
    "sg:postcode":"07703",
    "sg:province":"Islas Baleares",
    "wof:name":"Nieto Pons Manuel Lazaro",
    "wof:placetype":"venue"
},
  "geometry": {"coordinates":[4.265625,39.8903694153],"type":"Point"}
}