{
  "type": "Feature",
  "properties": {
    "addr:full":"Carrer de Muralla De Sant Francesc, 34 Manresa Barcelona 08241",
    "addr:housenumber":"34",
    "addr:postcode":"08241",
    "addr:street":"Carrer De Muralla De Sant Francesc",
    "iso:country":"ES",
    "sg:address":"Carrer de Muralla De Sant Francesc, 34",
    "sg:city":"Manresa",
    "sg:orig_category":"Molduras, Junquillos, Listones Y Molduras Perforadas",
    "sg:phone":"+34 938 72 97 15",
    "sg:postcode":"08241",
    "sg:province":"Barcelona",
    "wof:name":"Torrebadella Tapia Josep Maria",
    "wof:placetype":"venue"
},
  "geometry": {"coordinates":[1.8219799995,41.7223815918],"type":"Point"}
}