{
  "type": "Feature",
  "properties": {
    "addr:full":"Poli Industrial La Gelidense, 1 Gelida Barcelona 08790",
    "addr:housenumber":"1",
    "addr:postcode":"08790",
    "iso:country":"ES",
    "sg:address":"Poli Industrial La Gelidense, 1",
    "sg:city":"Gelida",
    "sg:orig_category":"Instalaci\u00d3n, Preparaci\u00d3n De Exposiciones, Ferias, Salones",
    "sg:phone":"+34 937 79 02 65",
    "sg:postcode":"08790",
    "sg:province":"Barcelona",
    "wof:name":"Demotronica S.l.",
    "wof:placetype":"venue"
},
  "geometry": {"coordinates":[1.8689490557,41.4427223206],"type":"Point"}
}