{
  "type": "Feature",
  "properties": {
    "iso:country":"ES",
    "sg:address":"Avda Real Academia De Medicina, 1",
    "sg:city":"Ranero",
    "sg:orig_category":"Inform\u00c1tica (estudios, Servicios, Asesor\u00cda, Formaci\u00d3n)",
    "sg:phone":"+34 968 27 42 08",
    "sg:postcode":"30100",
    "sg:province":"Murcia",
    "sg:website":"www.4glsp.com",
    "wof:name":"4g.l. S.l.",
    "wof:placetype":"venue"
},
  "geometry": {"coordinates":[-1.146842,38.000946],"type":"Point"}
}