{
  "type": "Feature",
  "properties": {
    "iso:country":"ES",
    "sg:address":"Rua Santisima Trinidad, 7",
    "sg:city":"Noia",
    "sg:orig_category":"Abogados",
    "sg:phone":"+34 981 82 52 24",
    "sg:postcode":"15200",
    "sg:province":"La Coru\u00f1a",
    "wof:name":"Atan Castro Carlos",
    "wof:placetype":"venue"
},
  "geometry": {"coordinates":[-8.8854961395,42.7836265564],"type":"Point"}
}