{
  "type": "Feature",
  "properties": {
    "iso:country":"ES",
    "sg:address":"Carrer de Urgell, 1",
    "sg:city":"Manresa",
    "sg:orig_category":"Mercer\u00cda, Lencer\u00cda (al Por Menor)",
    "sg:phone":"+34 938 72 39 17",
    "sg:postcode":"08241",
    "sg:province":"Barcelona",
    "wof:name":"Palomes Goya Josefa",
    "wof:placetype":"venue"
},
  "geometry": {"coordinates":[1.8244620562,41.7239532471],"type":"Point"}
}