{
  "type": "Feature",
  "properties": {
    "addr:full":"Calle de San Bernardo, 112 Madrid Madrid 28015",
    "addr:housenumber":"112",
    "addr:postcode":"28015",
    "addr:street":"Calle De San Bernardo",
    "iso:country":"ES",
    "sg:address":"Calle de San Bernardo, 112",
    "sg:city":"Madrid",
    "sg:orig_category":"Cajas De Ahorro",
    "sg:phone":"+34 915 93 96 66",
    "sg:postcode":"28015",
    "sg:province":"Madrid",
    "sg:website":"www.ibercaja.es",
    "wof:name":"Caja De Ahorros Y Monte De Piedad De Zaragoza Aragon Y Rioja",
    "wof:placetype":"venue"
},
  "geometry": {"coordinates":[-3.7050540447,40.431137085],"type":"Point"}
}