{
  "type": "Feature",
  "properties": {
    "iso:country":"ES",
    "sg:address":"Ctra. Jaca, S/n",
    "sg:city":"Martillue",
    "sg:orig_category":"Serrer\u00cdas De Madera",
    "sg:phone":"+34 974 36 48 67",
    "sg:postcode":"22714",
    "sg:province":"Huesca",
    "wof:name":"Sese Margalejo Alberto",
    "wof:placetype":"venue"
},
  "geometry": {"coordinates":[-0.5104119778,42.5869979858],"type":"Point"}
}