{
  "type": "Feature",
  "properties": {
    "iso:country":"ES",
    "sg:address":"Carrer de Portal De Remolins (del), 17",
    "sg:city":"Tortosa",
    "sg:orig_category":"Asociaciones Ecologistas",
    "sg:phone":"+34 977 44 13 99",
    "sg:postcode":"43500",
    "sg:province":"Tarragona",
    "wof:name":"Comunidad De Regantes Sindicato Agricola",
    "wof:placetype":"venue"
},
  "geometry": {"coordinates":[0.5250099897,40.8199195862],"type":"Point"}
}