{
  "type": "Feature",
  "properties": {
    "addr:full":"Avda Rodriguez De La Fuente, 7 Martos Ja\u00e9n 23600",
    "addr:housenumber":"7",
    "addr:postcode":"23600",
    "addr:street":"Avda Rodriguez De La Fuente;Jae\u0301N",
    "iso:country":"ES",
    "sg:address":"Avda Rodriguez De La Fuente, 7",
    "sg:city":"Martos",
    "sg:orig_category":"Servicios Gsm",
    "sg:phone":"+34 953 55 51 10",
    "sg:postcode":"23600",
    "sg:province":"Ja\u00e9n",
    "wof:name":"Linde Line S.l.l.",
    "wof:placetype":"venue"
},
  "geometry": {"coordinates":[-3.9637711048,37.7249641418],"type":"Point"}
}