{
  "type": "Feature",
  "properties": {
    "iso:country":"ES",
    "sg:address":"Zeharbide Kalea, 7",
    "sg:city":"Erribera",
    "sg:orig_category":"Navegaci\u00d3n (equipos Fluviales)",
    "sg:phone":"+34 946 83 16 08",
    "sg:postcode":"48710",
    "sg:province":"Vizcaya",
    "wof:name":"Marbasa S. A.",
    "wof:placetype":"venue"
},
  "geometry": {"coordinates":[-2.4660890102,43.3100662231],"type":"Point"}
}