{
  "type": "Feature",
  "properties": {
    "addr:full":"Ctra Fuentidue\u00d1a, S/n Sacramenia Segovia 40237",
    "addr:housenumber":"s / n",
    "addr:postcode":"40237",
    "addr:street":"Ctra Fuentiduen\u0303A",
    "iso:country":"ES",
    "sg:address":"Ctra Fuentidue\u00d1a, S/n",
    "sg:city":"Sacramenia",
    "sg:orig_category":"Empresas De Carpinter\u00cda De Madera",
    "sg:phone":"+34 921 52 75 05",
    "sg:postcode":"40237",
    "sg:province":"Segovia",
    "wof:name":"Sanz Lamas Jose Antonio",
    "wof:placetype":"venue"
},
  "geometry": {"coordinates":[-3.9625639915,41.4938316345],"type":"Point"}
}