{
  "type": "Feature",
  "properties": {
    "addr:full":"Carrer de Emporda (l'), 34 Casc Antic Barcelona 08150",
    "addr:housenumber":"34",
    "addr:postcode":"08150",
    "addr:street":"Carrer De Emporda L '",
    "iso:country":"ES",
    "sg:address":"Carrer de Emporda (l'), 34",
    "sg:city":"Casc Antic",
    "sg:orig_category":"Industria Qu\u00cdmica",
    "sg:phone":"+34 935 62 22 09",
    "sg:postcode":"08150",
    "sg:province":"Barcelona",
    "wof:name":"Hey'par Iberica S.l.",
    "wof:placetype":"venue"
},
  "geometry": {"coordinates":[2.2293000221,41.5678787231],"type":"Point"}
}