{
  "type": "Feature",
  "properties": {
    "iso:country":"ES",
    "sg:address":"S. Jovita, 14",
    "sg:city":"Carcaboso",
    "sg:orig_category":"Empresas De Carpinter\u00cda Met\u00c1lica",
    "sg:phone":"+34 927 40 22 00",
    "sg:postcode":"10670",
    "sg:province":"C\u00e1ceres",
    "wof:name":"Izquierdo Rodriguez Rufina",
    "wof:placetype":"venue"
},
  "geometry": {"coordinates":[-6.2117791176,40.0478935242],"type":"Point"}
}