{
  "type": "Feature",
  "properties": {
    "addr:full":"Calle de Corral De Cantos, 7 Madrid Madrid 28053",
    "addr:housenumber":"7",
    "addr:postcode":"madrid;28053",
    "addr:street":"Calle De Corral De Cantos",
    "iso:country":"ES",
    "sg:address":"Calle de Corral De Cantos, 7",
    "sg:city":"Madrid",
    "sg:orig_category":"Comercio De Piezas De Recambio Y De Accesorios De Veh\u00cdculos, Veh\u00cdculos Industriales",
    "sg:phone":"+34 914 77 64 79",
    "sg:postcode":"28053",
    "sg:province":"Madrid",
    "wof:name":"Autorecambios Fergusa S.l.l.",
    "wof:placetype":"venue"
},
  "geometry": {"coordinates":[-3.6695644855,40.390335083],"type":"Point"}
}