{
  "type": "Feature",
  "properties": {
    "addr:full":"Ctra Traiguera-s Rafael Rio, Km. 0006,0 Traiguera Castell\u00f3n 12330",
    "addr:postcode":"12330",
    "addr:street":"Ctra Traiguera-S Rafael Rio Km. 0006,0;Castello\u0301N",
    "iso:country":"ES",
    "sg:address":"Ctra Traiguera-s Rafael Rio, Km. 0006,0",
    "sg:city":"Traiguera",
    "sg:orig_category":"Cr\u00cda De Cerdos",
    "sg:phone":"+34 964 76 50 60",
    "sg:postcode":"12330",
    "sg:province":"Castell\u00f3n",
    "wof:name":"Granja Adell S.l.",
    "wof:placetype":"venue"
},
  "geometry": {"coordinates":[0.2892799973,40.5237693787],"type":"Point"}
}