{
  "type": "Feature",
  "properties": {
    "addr:full":"Carr 25 D'abril, 89 Cullera Valencia 46400",
    "addr:housenumber":"89",
    "addr:postcode":"46400",
    "addr:street":"Carr 25 D'Abril",
    "iso:country":"ES",
    "sg:address":"Carr 25 D'abril, 89",
    "sg:city":"Cullera",
    "sg:orig_category":"Peluqueros: De Se\u00d1oras",
    "sg:phone":"+34 961 72 13 73",
    "sg:postcode":"46400",
    "sg:province":"Valencia",
    "wof:name":"Olivares Tortajada Silvia",
    "wof:placetype":"venue"
},
  "geometry": {"coordinates":[-0.2480420023,39.1633262634],"type":"Point"}
}