{
  "type": "Feature",
  "properties": {
    "addr:full":"Carrer de Pau Casals, 62 Olesa Montserrat Barcelona 08640",
    "addr:housenumber":"62",
    "addr:postcode":"08640",
    "addr:street":"Carrer De Pau Casals;Barcelona",
    "iso:country":"ES",
    "sg:address":"Carrer de Pau Casals, 62",
    "sg:city":"Olesa Montserrat",
    "sg:orig_category":"Prot\u00c9sicos Dentales",
    "sg:phone":"+34 937 75 70 08",
    "sg:postcode":"08640",
    "sg:province":"Barcelona",
    "wof:name":"Coronel Artigas Miguel",
    "wof:placetype":"venue"
},
  "geometry": {"coordinates":[1.8885519505,41.5415420532],"type":"Point"}
}