{
  "type": "Feature",
  "properties": {
    "addr:full":"Calle de Tomas Pelayo, 43 Zaragoza Zaragoza 50009",
    "addr:housenumber":"43",
    "addr:postcode":"50009",
    "addr:street":"Calle De Tomas Pelayo",
    "iso:country":"ES",
    "sg:address":"Calle de Tomas Pelayo, 43",
    "sg:city":"Zaragoza",
    "sg:orig_category":"Confecci\u00d3n (fabricaci\u00d3n, Al Por Mayor)",
    "sg:phone":"+34 976 30 60 78",
    "sg:postcode":"50009",
    "sg:province":"Zaragoza",
    "wof:name":"Dise\u00f1os Jandro S.a.",
    "wof:placetype":"venue"
},
  "geometry": {"coordinates":[-0.9100869894,41.6328468323],"type":"Point"}
}