{
  "type": "Feature",
  "properties": {
    "addr:full":"Carrer de Samaritana, 4 Palma Islas Baleares 07001",
    "addr:housenumber":"4",
    "addr:postcode":"07001",
    "addr:street":"Carrer De Samaritana",
    "iso:country":"ES",
    "sg:address":"Carrer de Samaritana, 4",
    "sg:city":"Palma",
    "sg:orig_category":"Ingenier\u00cda, Centros De Estudios (diversos)",
    "sg:phone":"+34 971 71 35 81",
    "sg:postcode":"07001",
    "sg:province":"Islas Baleares",
    "wof:name":"Dameto Squella Nicolas",
    "wof:placetype":"venue"
},
  "geometry": {"coordinates":[2.6530909538,39.5696983337],"type":"Point"}
}