{
  "type": "Feature",
  "properties": {
    "iso:country":"ES",
    "sg:address":"Calle de Principe De Vergara, 206",
    "sg:city":"Madrid",
    "sg:orig_category":"Laboratorios Y Trabajos De Fotograf\u00cda, V\u00cddeo Y Cine",
    "sg:phone":"+34 915 63 86 59",
    "sg:postcode":"28002",
    "sg:province":"Madrid",
    "wof:name":"Po Chu Sik Kay",
    "wof:placetype":"venue"
},
  "geometry": {"coordinates":[-3.6777002811,40.4502563477],"type":"Point"}
}