{
  "type": "Feature",
  "properties": {
    "iso:country":"ES",
    "sg:address":"Carrer de Mina, 22",
    "sg:city":"Terrassa",
    "sg:orig_category":"Fabricaci\u00d3n De Telas Y Sedas",
    "sg:phone":"+34 937 83 23 28",
    "sg:postcode":"08221",
    "sg:province":"Barcelona",
    "wof:name":"Carreras Feiner Laura",
    "wof:placetype":"venue"
},
  "geometry": {"coordinates":[2.0147130489,41.567073822],"type":"Point"}
}