{
  "type": "Feature",
  "properties": {
    "iso:country":"ES",
    "sg:address":"Maria Azpilicueta, S/n",
    "sg:city":"Elizondo",
    "sg:orig_category":"Plomeros",
    "sg:phone":"+34 948 58 01 34",
    "sg:postcode":"31700",
    "sg:province":"Navarra",
    "wof:name":"Ballarena Erramuzpe Vicente",
    "wof:placetype":"venue"
},
  "geometry": {"coordinates":[-1.5172307491,43.1468276978],"type":"Point"}
}