{
  "type": "Feature",
  "properties": {
    "iso:country":"ES",
    "sg:address":"Carr Jaume I, 42",
    "sg:city":"Girona",
    "sg:orig_category":"Empresarios",
    "sg:phone":"+34 972 22 65 27",
    "sg:postcode":"17001",
    "sg:province":"Girona",
    "wof:name":"Fundacio Valvi",
    "wof:placetype":"venue"
},
  "geometry": {"coordinates":[2.8195309639,41.9835014343],"type":"Point"}
}