{
  "type": "Feature",
  "properties": {
    "iso:country":"ES",
    "sg:address":"Pol Ind El Lirio, S/n",
    "sg:city":"Bollullos Par Condado",
    "sg:orig_category":"Transporte En General",
    "sg:phone":"+34 959 40 82 23",
    "sg:postcode":"21710",
    "sg:province":"Huelva",
    "wof:name":"Distribuidora Internacional De Alimentacion S.a.",
    "wof:placetype":"venue"
},
  "geometry": {"coordinates":[-6.5409269333,37.3387069702],"type":"Point"}
}