{
  "type": "Feature",
  "properties": {
    "addr:full":"Carrer de Llobregat, 90 Hospitalet Llobregat Barcelona 08904",
    "addr:housenumber":"90",
    "addr:postcode":"08904",
    "addr:street":"Carrer De Llobregat",
    "iso:country":"ES",
    "sg:address":"Carrer de Llobregat, 90",
    "sg:city":"Hospitalet Llobregat",
    "sg:orig_category":"Peluqueros: De Se\u00d1oras",
    "sg:phone":"+34 934 48 20 06",
    "sg:postcode":"08904",
    "sg:province":"Barcelona",
    "wof:name":"Cortes Gonzalez Dolores",
    "wof:placetype":"venue"
},
  "geometry": {"coordinates":[2.1199700832,41.3722381592],"type":"Point"}
}