{
  "type": "Feature",
  "properties": {
    "addr:full":"Av Lluis Companys, 30 S. Cugat Valles Barcelona 08172",
    "addr:housenumber":"30",
    "addr:postcode":"08172",
    "addr:street":"Av Lluis Companys;S. Cugat Valles Barcelona",
    "iso:country":"ES",
    "sg:address":"Av Lluis Companys, 30",
    "sg:city":"S. Cugat Valles",
    "sg:orig_category":"Centros Empresariales",
    "sg:phone":"+34 935 87 93 73",
    "sg:postcode":"08172",
    "sg:province":"Barcelona",
    "wof:name":"Marzo Diez S.l.",
    "wof:placetype":"venue"
},
  "geometry": {"coordinates":[2.0788538456,41.4708480835],"type":"Point"}
}