{
  "type": "Feature",
  "properties": {
    "addr:full":"Carretera Las Negras, 1 Campohermoso Almer\u00eda 04110",
    "addr:housenumber":"1",
    "addr:postcode":"04110",
    "addr:street":"Carretera Las Negras;Almeri\u0301A",
    "iso:country":"ES",
    "sg:address":"Carretera Las Negras, 1",
    "sg:city":"Campohermoso",
    "sg:orig_category":"Cajas De Ahorro",
    "sg:phone":"+34 950 38 54 22",
    "sg:postcode":"04110",
    "sg:province":"Almer\u00eda",
    "wof:name":"Unicaja",
    "wof:placetype":"venue"
},
  "geometry": {"coordinates":[-2.1384088993,36.9406242371],"type":"Point"}
}