{
  "type": "Feature",
  "properties": {
    "addr:full":"Calle de Valldemosa, 1 Madrid Madrid 28039",
    "addr:housenumber":"1",
    "addr:postcode":"28039",
    "addr:street":"Calle De Valldemosa",
    "iso:country":"ES",
    "sg:address":"Calle de Valldemosa, 1",
    "sg:city":"Madrid",
    "sg:orig_category":"Caf\u00c9s, Bares, Cervecer\u00cdas",
    "sg:phone":"+34 914 59 99 02",
    "sg:postcode":"28039",
    "sg:province":"Madrid",
    "wof:name":"Aranda Caceres Jose Luis",
    "wof:placetype":"venue"
},
  "geometry": {"coordinates":[-3.7102458477,40.4651679993],"type":"Point"}
}