{
  "type": "Feature",
  "properties": {
    "addr:full":"Carrer de Comer\u00c7, 21 Barcelona Barcelona 08003",
    "addr:housenumber":"21",
    "addr:postcode":"08003",
    "addr:street":"Carrer De Comerc\u0327",
    "iso:country":"ES",
    "sg:address":"Carrer de Comer\u00c7, 21",
    "sg:city":"Barcelona",
    "sg:orig_category":"Fabricaci\u00d3n De Telas Y Sedas",
    "sg:phone":"+34 933 10 63 44",
    "sg:postcode":"08003",
    "sg:province":"Barcelona",
    "wof:name":"Tixcom S.l.",
    "wof:placetype":"venue"
},
  "geometry": {"coordinates":[2.1825459003,41.3865127563],"type":"Point"}
}