{
  "type": "Feature",
  "properties": {
    "addr:full":"Avda Federico Garcia Lorca, 13 Salobre\u00f1a Granada 18680",
    "addr:housenumber":"13",
    "addr:postcode":"18680",
    "addr:street":"Avda Federico Garcia Lorca",
    "iso:country":"ES",
    "sg:address":"Avda Federico Garcia Lorca, 13",
    "sg:city":"Salobre\u00f1a",
    "sg:classifiers":[
        {
            "category":"Autos & Motor Vehicles",
            "subcategory":"Automobile Sales",
            "type":"Retail Goods"
        }
    ],
    "sg:phone":"+34 958 61 05 10",
    "sg:postcode":"18680",
    "sg:province":"Granada",
    "wof:name":"Autoescuela Divina Pastora S.l.",
    "wof:placetype":"venue"
},
  "geometry": {"coordinates":[-3.5843775272,36.7426376343],"type":"Point"}
}