{
  "type": "Feature",
  "properties": {
    "iso:country":"ES",
    "sg:address":"Varadero, S/n",
    "sg:city":"Maspalomas",
    "sg:orig_category":"Peluquer\u00cdas, Peluquer\u00cda Mixta",
    "sg:phone":"+34 928 14 54 19",
    "sg:postcode":"35100",
    "sg:province":"Las Palmas",
    "wof:name":"Ramirez Peluqueros S.l.",
    "wof:placetype":"venue"
},
  "geometry": {"coordinates":[-15.5830888748,27.7700748444],"type":"Point"}
}