{
  "type": "Feature",
  "properties": {
    "addr:full":"Calle de Agustin Fernandez Garcia, 34 Iniesta Cuenca 16235",
    "addr:housenumber":"34",
    "addr:postcode":"16235",
    "addr:street":"Calle De Agustin Fernandez Garcia",
    "iso:country":"ES",
    "sg:address":"Calle de Agustin Fernandez Garcia, 34",
    "sg:city":"Iniesta",
    "sg:orig_category":"M\u00c9dicos: An\u00c1lisis Cl\u00cdnicos",
    "sg:phone":"+34 967 49 00 04",
    "sg:postcode":"16235",
    "sg:province":"Cuenca",
    "wof:name":"Fernandez Garcia Ana",
    "wof:placetype":"venue"
},
  "geometry": {"coordinates":[-1.7493573427,39.4442367554],"type":"Point"}
}