{
  "type": "Feature",
  "properties": {
    "addr:full":"Av Castilla Mancha(p I Colador), 5 Onda Castell\u00f3n 12200",
    "addr:housenumber":"5",
    "addr:postcode":"12200",
    "addr:street":"Av Castilla Mancha P I Colador;Castello\u0301N",
    "iso:country":"ES",
    "sg:address":"Av Castilla Mancha(p I Colador), 5",
    "sg:city":"Onda",
    "sg:orig_category":"Hoteles",
    "sg:phone":"+34 964 77 62 30",
    "sg:postcode":"12200",
    "sg:province":"Castell\u00f3n",
    "wof:name":"Onda Hotel S.l.",
    "wof:placetype":"venue"
},
  "geometry": {"coordinates":[-0.2470179945,39.9657173157],"type":"Point"}
}