{
  "type": "Feature",
  "properties": {
    "iso:country":"ES",
    "sg:address":"Carrer de Corsega, 685",
    "sg:city":"Barcelona",
    "sg:orig_category":"Peluqueros: De Se\u00d1oras",
    "sg:phone":"+34 934 35 32 04",
    "sg:postcode":"08026",
    "sg:province":"Barcelona",
    "wof:name":"Martinez Santin Elisenda",
    "wof:placetype":"venue"
},
  "geometry": {"coordinates":[2.1792860031,41.4117546082],"type":"Point"}
}