{
  "type": "Feature",
  "properties": {
    "addr:full":"Pase Adarves (los), 1 Molina Guadalajara 19300",
    "addr:housenumber":"1",
    "addr:postcode":"19300",
    "addr:street":"Pase Adarves Los",
    "iso:country":"ES",
    "sg:address":"Pase Adarves (los), 1",
    "sg:city":"Molina",
    "sg:orig_category":"Molduras, Junquillos, Listones Y Molduras Perforadas",
    "sg:phone":"+34 949 83 22 94",
    "sg:postcode":"19300",
    "sg:province":"Guadalajara",
    "wof:name":"Perez Algar Manuel",
    "wof:placetype":"venue"
},
  "geometry": {"coordinates":[-1.8168599606,40.8542098999],"type":"Point"}
}