{
  "type": "Feature",
  "properties": {
    "iso:country":"ES",
    "sg:address":"Ptor. Sorolla, S/n",
    "sg:city":"Museros",
    "sg:orig_category":"Farmacias",
    "sg:phone":"+34 961 44 29 00",
    "sg:postcode":"46136",
    "sg:province":"Valencia",
    "wof:name":"Soler Folgado Maria Isabel",
    "wof:placetype":"venue"
},
  "geometry": {"coordinates":[-0.3364939988,39.5627708435],"type":"Point"}
}