{
  "type": "Feature",
  "properties": {
    "iso:country":"ES",
    "sg:address":"Pase Curas (de Los), 22",
    "sg:city":"Alcala Henares",
    "sg:orig_category":"Iglesia Cat\u00d3lica",
    "sg:phone":"+34 918 89 16 56",
    "sg:postcode":"28803",
    "sg:province":"Madrid",
    "wof:name":"Obispado De Alcala De Henares",
    "wof:placetype":"venue"
},
  "geometry": {"coordinates":[-3.3684239388,40.4773674011],"type":"Point"}
}