{
  "type": "Feature",
  "properties": {
    "addr:full":"Avda Madrid (de), 42 Jaen Ja\u00e9n 23003",
    "addr:housenumber":"42;jae\u0301n",
    "addr:postcode":"23003",
    "addr:street":"Avda Madrid De",
    "iso:country":"ES",
    "sg:address":"Avda Madrid (de), 42",
    "sg:city":"Jaen",
    "sg:orig_category":"Asesor\u00cda De Formaci\u00d3n Y Gesti\u00d3n De Personal",
    "sg:phone":"+34 953 25 49 27",
    "sg:postcode":"23003",
    "sg:province":"Ja\u00e9n",
    "wof:name":"Zapata Reyes Jesus Antonio",
    "wof:placetype":"venue"
},
  "geometry": {"coordinates":[-3.7861235142,37.7734489441],"type":"Point"}
}