{
  "type": "Feature",
  "properties": {
    "addr:full":"Carr Serra (de), 1 Lliria Valencia 46160",
    "addr:housenumber":"1",
    "addr:postcode":"46160",
    "addr:street":"Carr Serra De",
    "iso:country":"ES",
    "sg:address":"Carr Serra (de), 1",
    "sg:city":"Lliria",
    "sg:orig_category":"Diet\u00c9tica: Productos Biol\u00d3gicos, Naturales Y Diet\u00c9ticos (fabricaci\u00d3n, Al Por Mayor)",
    "sg:phone":"+34 962 79 81 89",
    "sg:postcode":"46160",
    "sg:province":"Valencia",
    "wof:name":"Nutrispain S.l.",
    "wof:placetype":"venue"
},
  "geometry": {"coordinates":[-0.5837709904,39.6349372864],"type":"Point"}
}