{
  "type": "Feature",
  "properties": {
    "iso:country":"ES",
    "sg:address":"Calle de Virgen De Belen, 4",
    "sg:city":"Orihuela",
    "sg:orig_category":"Alimentaci\u00d3n General (al Por Menor)",
    "sg:phone":"+34 966 73 91 31",
    "sg:postcode":"03300",
    "sg:province":"Alicante",
    "wof:name":"Benioriol.s.l.",
    "wof:placetype":"venue"
},
  "geometry": {"coordinates":[-0.9425100088,38.0826950073],"type":"Point"}
}