{
  "type": "Feature",
  "properties": {
    "addr:full":"Calle de Claudio Coello, 4 Plasencia C\u00e1ceres 10600",
    "addr:housenumber":"4",
    "addr:postcode":"10600",
    "addr:street":"Calle De Claudio Coello;Ca\u0301Ceres",
    "iso:country":"ES",
    "sg:address":"Calle de Claudio Coello, 4",
    "sg:city":"Plasencia",
    "sg:orig_category":"Enfermeras: Consultas, Atenci\u00d3n A Domicilio",
    "sg:phone":"+34 927 41 24 87",
    "sg:postcode":"10600",
    "sg:province":"C\u00e1ceres",
    "wof:name":"Martin Azabal Nicolas",
    "wof:placetype":"venue"
},
  "geometry": {"coordinates":[-6.091129303,40.0339355469],"type":"Point"}
}