{
  "type": "Feature",
  "properties": {
    "iso:country":"ES",
    "sg:address":"Calle de San Agustin, 4",
    "sg:city":"Requena",
    "sg:orig_category":"Estancos",
    "sg:phone":"+34 962 30 14 83",
    "sg:postcode":"46340",
    "sg:province":"Valencia",
    "wof:name":"Martinez Cubillos Maria Del Pilar",
    "wof:placetype":"venue"
},
  "geometry": {"coordinates":[-1.291967988,39.4185447693],"type":"Point"}
}