{
  "type": "Feature",
  "properties": {
    "iso:country":"ES",
    "sg:address":"Calle de Silvestre Perez, 4",
    "sg:city":"Zaragoza",
    "sg:orig_category":"Fabricaci\u00d3n De Enlosados, Soler\u00cdas",
    "sg:phone":"+34 976 42 35 39",
    "sg:postcode":"50002",
    "sg:province":"Zaragoza",
    "wof:name":"Mosaicos Valdelvira S.l.",
    "wof:placetype":"venue"
},
  "geometry": {"coordinates":[-0.8618839979,41.6481018066],"type":"Point"}
}