{
  "type": "Feature",
  "properties": {
    "addr:full":"Avda Villalba, 92 Muimenta Lugo 27377",
    "addr:housenumber":"92",
    "addr:postcode":"27377",
    "addr:street":"Avda Villalba",
    "iso:country":"ES",
    "sg:address":"Avda Villalba, 92",
    "sg:city":"Muimenta",
    "sg:orig_category":"Electricidad (montaje, Ensamblaje De Componentes)",
    "sg:phone":"+34 982 52 80 61",
    "sg:postcode":"27377",
    "sg:province":"Lugo",
    "wof:name":"Moran Puente Jose Antonio",
    "wof:placetype":"venue"
},
  "geometry": {"coordinates":[-7.4298791885,43.2525482178],"type":"Point"}
}