{
  "type": "Feature",
  "properties": {
    "addr:full":"Avda Alfonso Pe\u00d1a, S/n Zamora Zamora 49010",
    "addr:housenumber":"s",
    "addr:postcode":"49010",
    "addr:street":"Avda Alfonso Pen\u0303A;/ N",
    "iso:country":"ES",
    "sg:address":"Avda Alfonso Pe\u00d1a, S/n",
    "sg:city":"Zamora",
    "sg:orig_category":"Autob\u00das (explotaci\u00d3n Y Servicios De)",
    "sg:phone":"+34 980 52 03 77",
    "sg:postcode":"49010",
    "sg:province":"Zamora",
    "wof:name":"Martin Macias Julian",
    "wof:placetype":"venue"
},
  "geometry": {"coordinates":[-5.7392640114,41.5145568848],"type":"Point"}
}