{
  "type": "Feature",
  "properties": {
    "iso:country":"ES",
    "sg:address":"Calle de Juan Alegre, S/n",
    "sg:city":"Villel",
    "sg:orig_category":"Farmacias",
    "sg:phone":"+34 978 68 02 36",
    "sg:postcode":"44131",
    "sg:province":"Teruel",
    "wof:name":"Galve Martin Maria Belen",
    "wof:placetype":"venue"
},
  "geometry": {"coordinates":[-1.185379982,40.2322273254],"type":"Point"}
}