{
  "type": "Feature",
  "properties": {
    "addr:full":"Calle de Santiago Vegas Arranz, 3 Ciudad Rodrigo Salamanca 37500",
    "addr:housenumber":"3",
    "addr:postcode":"37500",
    "addr:street":"Calle De Santiago Vegas Arranz",
    "iso:country":"ES",
    "sg:address":"Calle de Santiago Vegas Arranz, 3",
    "sg:city":"Ciudad Rodrigo",
    "sg:orig_category":"Cl\u00cdnicas Dentales",
    "sg:phone":"+34 923 46 00 21",
    "sg:postcode":"37500",
    "sg:province":"Salamanca",
    "wof:name":"Vicente Molinero Justo",
    "wof:placetype":"venue"
},
  "geometry": {"coordinates":[-6.533645153,40.6012420654],"type":"Point"}
}