{
  "type": "Feature",
  "properties": {
    "addr:full":"Pascual Carrion, 4 Requena Valencia 46340",
    "addr:housenumber":"4",
    "addr:postcode":"46340",
    "addr:street":"Pascual Carrion",
    "iso:country":"ES",
    "sg:address":"Pascual Carrion, 4",
    "sg:city":"Requena",
    "sg:orig_category":"Agricultura: Abastecimiento Y Cosechado (negocio)",
    "sg:phone":"+34 962 30 33 51",
    "sg:postcode":"46340",
    "sg:province":"Valencia",
    "wof:name":"Cnag Jovenes Agricultores",
    "wof:placetype":"venue"
},
  "geometry": {"coordinates":[-1.099766016,39.4903945923],"type":"Point"}
}