{
  "type": "Feature",
  "properties": {
    "iso:country":"ES",
    "sg:address":"Av Rei Jaume I, 5",
    "sg:city":"Benidorm",
    "sg:orig_category":"Zapatos (al Por Menor)",
    "sg:phone":"+34 965 86 64 76",
    "sg:postcode":"03500",
    "sg:province":"Alicante",
    "wof:name":"Mejias Rivas Francisco",
    "wof:placetype":"venue"
},
  "geometry": {"coordinates":[-0.1368910074,38.5383148193],"type":"Point"}
}