{
  "type": "Feature",
  "properties": {
    "iso:country":"ES",
    "sg:address":"Ptda Milagro, 7",
    "sg:city":"Alboraya",
    "sg:orig_category":"Alquiler De Gr\u00daas",
    "sg:phone":"+34 961 85 73 08",
    "sg:postcode":"46120",
    "sg:province":"Valencia",
    "sg:website":"www.eleve.es",
    "wof:name":"Eleve S.l.",
    "wof:placetype":"venue"
},
  "geometry": {"coordinates":[-0.3487760127,39.5009651184],"type":"Point"}
}