{
  "type": "Feature",
  "properties": {
    "iso:country":"ES",
    "sg:address":"Calle de Mayor, 29",
    "sg:city":"Garrucha",
    "sg:orig_category":"Zapatos (al Por Menor)",
    "sg:phone":"+34 950 13 32 95",
    "sg:postcode":"04630",
    "sg:province":"Almer\u00eda",
    "wof:name":"Martinez Molina Francisca",
    "wof:placetype":"venue"
},
  "geometry": {"coordinates":[-1.8213800192,37.1819458008],"type":"Point"}
}