{
  "type": "Feature",
  "properties": {
    "iso:country":"ES",
    "sg:address":"Carrer de Marinada, 15",
    "sg:city":"Esplugues Llobregat",
    "sg:orig_category":"Productos Qu\u00cdmicos (fabricaci\u00d3n, Al Por Mayor)",
    "sg:phone":"+34 934 73 92 19",
    "sg:postcode":"08950",
    "sg:province":"Barcelona",
    "wof:name":"Ce-chimia S.l.",
    "wof:placetype":"venue"
},
  "geometry": {"coordinates":[2.0852940083,41.3673553467],"type":"Point"}
}