{
  "type": "Feature",
  "properties": {
    "iso:country":"ES",
    "sg:address":"Pardo Bazan, 58",
    "sg:city":"Pontes Garcia Rodriguez",
    "sg:orig_category":"Reposter\u00cdas",
    "sg:phone":"+34 981 45 10 41",
    "sg:postcode":"15320",
    "sg:province":"A Coru\u00f1a",
    "wof:name":"Viuda De Domingo Lopez S.l.",
    "wof:placetype":"venue"
},
  "geometry": {"coordinates":[-7.8599414825,43.4526062012],"type":"Point"}
}