{
  "type": "Feature",
  "properties": {
    "iso:country":"ES",
    "sg:address":"Avda Mediterraneo, S/n",
    "sg:city":"Urbanizacion Roquetas De Mar",
    "sg:orig_category":"Bazares, Art\u00cdculos De Limpieza Y De Cocina (al Por Menor)",
    "sg:phone":"+34 950 33 45 73",
    "sg:postcode":"04740",
    "sg:province":"Almer\u00eda",
    "wof:name":"Palacin Waissen Gema",
    "wof:placetype":"venue"
},
  "geometry": {"coordinates":[-2.622729063,36.7349815369],"type":"Point"}
}