{
  "type": "Feature",
  "properties": {
    "iso:country":"ES",
    "sg:address":"Barr Sedillo (el), S/n",
    "sg:city":"Entrambasaguas",
    "sg:orig_category":"Producci\u00d3n, Distribuci\u00d3n De Electricidad",
    "sg:phone":"+34 942 52 59 80",
    "sg:postcode":"39715",
    "sg:province":"Cantabria",
    "wof:name":"Rioz Cagigas Julian",
    "wof:placetype":"venue"
},
  "geometry": {"coordinates":[-3.6829760075,43.3787002563],"type":"Point"}
}