{
  "type": "Feature",
  "properties": {
    "addr:full":"Plaz Ca\u00d1o (del), 17 Galapagar Madrid 28260",
    "addr:postcode":"28260",
    "addr:street":"Plaz;Del;Galapagar",
    "iso:country":"ES",
    "sg:address":"Plaz Ca\u00d1o (del), 17",
    "sg:city":"Galapagar",
    "sg:orig_category":"Cl\u00cdnicas M\u00c9dicas",
    "sg:phone":"+34 918 58 14 11",
    "sg:postcode":"28260",
    "sg:province":"Madrid",
    "wof:name":"Rico Beltri Pedro",
    "wof:placetype":"venue"
},
  "geometry": {"coordinates":[-4.0020170212,40.5765609741],"type":"Point"}
}