{
  "type": "Feature",
  "properties": {
    "iso:country":"ES",
    "sg:address":"Carrer de Cid, 19",
    "sg:city":"Vilafranca Penedes",
    "sg:orig_category":"Venta, Colocaci\u00d3n, Reparaci\u00d3n De Radiadores Para Veh\u00cdculos",
    "sg:phone":"+34 938 92 18 90",
    "sg:postcode":"08720",
    "sg:province":"Barcelona",
    "wof:name":"Rubio Romero Jaume",
    "wof:placetype":"venue"
},
  "geometry": {"coordinates":[1.7039990425,41.3467216492],"type":"Point"}
}