{
  "type": "Feature",
  "properties": {
    "iso:country":"ES",
    "sg:address":"La Rosa, 1",
    "sg:city":"Sta Cruz Tenerife",
    "sg:orig_category":"Partidos Pol\u00cdticos",
    "sg:phone":"+34 922 24 86 88",
    "sg:postcode":"38002",
    "sg:province":"Santa Cruz De Tenerife",
    "wof:name":"Centro Canario Nacionalista",
    "wof:placetype":"venue"
},
  "geometry": {"coordinates":[-16.2506809235,28.4696121216],"type":"Point"}
}