{
  "type": "Feature",
  "properties": {
    "iso:country":"ES",
    "sg:address":"Plaz Mondariz, 15",
    "sg:city":"Madrid",
    "sg:orig_category":"Tapicer\u00cdas",
    "sg:phone":"+34 917 39 23 93",
    "sg:postcode":"28029",
    "sg:province":"Madrid",
    "wof:name":"Mendez Martinez Antonio",
    "wof:placetype":"venue"
},
  "geometry": {"coordinates":[-3.7052989006,40.4783592224],"type":"Point"}
}