{
  "type": "Feature",
  "properties": {
    "iso:country":"ES",
    "sg:address":"Calle de Americo Castro, 86",
    "sg:city":"Madrid",
    "sg:orig_category":"M\u00c9dicos: Estomatolog\u00cda",
    "sg:phone":"+34 917 50 11 80",
    "sg:postcode":"28050",
    "sg:province":"Madrid",
    "wof:name":"Lucciani Tamaro Liliana",
    "wof:placetype":"venue"
},
  "geometry": {"coordinates":[-3.6525101662,40.4976043701],"type":"Point"}
}