{
  "type": "Feature",
  "properties": {
    "addr:full":"Carrer de Raseta, 15 Molins Rei Barcelona 08750",
    "addr:housenumber":"15",
    "addr:postcode":"08750",
    "addr:street":"Carrer De Raseta;Barcelona",
    "iso:country":"ES",
    "sg:address":"Carrer de Raseta, 15",
    "sg:city":"Molins Rei",
    "sg:orig_category":"Electrodom\u00c9sticos (al Por Menor)",
    "sg:phone":"+34 936 68 13 61",
    "sg:postcode":"08750",
    "sg:province":"Barcelona",
    "wof:name":"Maxe Garcia Salvador",
    "wof:placetype":"venue"
},
  "geometry": {"coordinates":[2.0164849758,41.414604187],"type":"Point"}
}