{
  "type": "Feature",
  "properties": {
    "iso:country":"ES",
    "sg:address":"Pla\u00c7 Espanya, 33",
    "sg:city":"Inca",
    "sg:orig_category":"Confecci\u00d3n De Trajes Para Se\u00d1oras",
    "sg:phone":"+34 971 50 41 13",
    "sg:postcode":"07300",
    "sg:province":"Islas Baleares",
    "wof:name":"Cuatro Cubitos S. A.",
    "wof:placetype":"venue"
},
  "geometry": {"coordinates":[2.9208989143,39.7179527283],"type":"Point"}
}