{
  "type": "Feature",
  "properties": {
    "iso:country":"ES",
    "sg:address":"Calle de Guipuzcoa, 41",
    "sg:city":"Gijon",
    "sg:orig_category":"Organizaciones Profesionales",
    "sg:phone":"+34 985 39 10 69",
    "sg:postcode":"33210",
    "sg:province":"Asturias",
    "wof:name":"A.i.c.a.",
    "wof:placetype":"venue"
},
  "geometry": {"coordinates":[-5.6744160652,43.5256195068],"type":"Point"}
}