{
  "type": "Feature",
  "properties": {
    "iso:country":"ES",
    "sg:address":"Calle de Garcia Cabrelles, S/n",
    "sg:city":"Melilla",
    "sg:orig_category":"Ense\u00d1anza Secundaria: Colegios Y Escuelas Privadas",
    "sg:phone":"+34 952 68 35 39",
    "sg:postcode":"52002",
    "sg:province":"Melilla",
    "wof:name":"Ies N7",
    "wof:placetype":"venue"
},
  "geometry": {"coordinates":[-2.9431738853,35.2951431274],"type":"Point"}
}