{
  "type": "Feature",
  "properties": {
    "addr:full":"Trva Uribarri A, 2 Bilbao Vizcaya 48007",
    "addr:housenumber":"2",
    "addr:postcode":"48007",
    "addr:street":"Trva Uribarri A",
    "iso:country":"ES",
    "sg:address":"Trva Uribarri A, 2",
    "sg:city":"Bilbao",
    "sg:orig_category":"Molduras, Junquillos, Listones Y Molduras Perforadas",
    "sg:phone":"+34 944 13 08 33",
    "sg:postcode":"48007",
    "sg:province":"Vizcaya",
    "wof:name":"Ferrer Martinez Jose Luis",
    "wof:placetype":"venue"
},
  "geometry": {"coordinates":[-2.9216849804,43.2676048279],"type":"Point"}
}