{
  "type": "Feature",
  "properties": {
    "addr:full":"Carr Pau Casals, 30 Girona Girona 17001",
    "addr:housenumber":"30",
    "addr:postcode":"17001",
    "addr:street":"Carr Pau Casals",
    "iso:country":"ES",
    "sg:address":"Carr Pau Casals, 30",
    "sg:city":"Girona",
    "sg:orig_category":"Agencias Y Agentes Comerciales, Representantes",
    "sg:phone":"+34 972 21 64 79",
    "sg:postcode":"17001",
    "sg:province":"Girona",
    "wof:name":"Silva Gonzalez Joan",
    "wof:placetype":"venue"
},
  "geometry": {"coordinates":[2.8126819134,41.9829444885],"type":"Point"}
}