{
  "type": "Feature",
  "properties": {
    "addr:full":"Calle de Santander, 18 Castro Urdiales Cantabria 39700",
    "addr:housenumber":"18",
    "addr:postcode":"39700",
    "addr:street":"Calle De Santander",
    "iso:country":"ES",
    "sg:address":"Calle de Santander, 18",
    "sg:city":"Castro Urdiales",
    "sg:orig_category":"Droguer\u00cdas (al Por Menor)",
    "sg:phone":"+34 942 86 14 44",
    "sg:postcode":"39700",
    "sg:province":"Cantabria",
    "wof:name":"Gutierrez Zapatero Jose",
    "wof:placetype":"venue"
},
  "geometry": {"coordinates":[-3.2207798958,43.3835830688],"type":"Point"}
}