{
  "type": "Feature",
  "properties": {
    "addr:full":"Calle de Bautismo, 13 Valladolid Valladolid 47005",
    "addr:housenumber":"13",
    "addr:postcode":"47005",
    "addr:street":"Calle De Bautismo",
    "iso:country":"ES",
    "sg:address":"Calle de Bautismo, 13",
    "sg:city":"Valladolid",
    "sg:orig_category":"Iglesia Cat\u00d3lica",
    "sg:phone":"+34 983 29 13 08",
    "sg:postcode":"47005",
    "sg:province":"Valladolid",
    "wof:name":"Parroquia De San Juan Bautista",
    "wof:placetype":"venue"
},
  "geometry": {"coordinates":[-4.716565609,41.650478363],"type":"Point"}
}