{
  "type": "Feature",
  "properties": {
    "iso:country":"ES",
    "sg:address":"Carrer de Sant Isidre, 20",
    "sg:city":"Mollet Valles",
    "sg:orig_category":"Mec\u00c1nico Del Autom\u00d3vil",
    "sg:phone":"+34 935 93 58 71",
    "sg:postcode":"08100",
    "sg:province":"Barcelona",
    "wof:name":"Soler Serra Jose",
    "wof:placetype":"venue"
},
  "geometry": {"coordinates":[2.2070059776,41.5338439941],"type":"Point"}
}