{
  "type": "Feature",
  "properties": {
    "iso:country":"ES",
    "sg:address":"Ctra Toledo Oca\u00d1a, Km. 0011,0",
    "sg:city":"Poligono Sta M. De Benquerencia",
    "sg:orig_category":"Distribuci\u00d3n De Petr\u00d3leo Y Derivados",
    "sg:phone":"+34 925 59 01 10",
    "sg:postcode":"45007",
    "sg:province":"Toledo",
    "sg:website":"www paginasamarillas.es",
    "wof:name":"Gonzalez Aranda Mariano",
    "wof:placetype":"venue"
},
  "geometry": {"coordinates":[-3.9474089146,39.8690643311],"type":"Point"}
}