{
  "type": "Feature",
  "properties": {
    "addr:full":"Plaz Cesar Manrique, 11 Olivos-la Postura Santa Cruz De Tenerife 38670",
    "addr:housenumber":"11",
    "addr:postcode":"38670",
    "addr:street":"Olivos-La Postura",
    "iso:country":"ES",
    "sg:address":"Plaz Cesar Manrique, 11",
    "sg:city":"Olivos-la Postura",
    "sg:orig_category":"Peluquer\u00cdas, Peluquer\u00cda Mixta",
    "sg:phone":"+34 922 78 27 96",
    "sg:postcode":"38670",
    "sg:province":"Santa Cruz De Tenerife",
    "wof:name":"Tafice\u00f1o S.l.",
    "wof:placetype":"venue"
},
  "geometry": {"coordinates":[-16.7305717468,28.1214084625],"type":"Point"}
}