{
  "type": "Feature",
  "properties": {
    "iso:country":"ES",
    "sg:address":"Calle de Estudios, 9",
    "sg:city":"Madrid",
    "sg:orig_category":"Ingenier\u00cda, Centros De Estudios (diversos)",
    "sg:phone":"+34 913 64 16 09",
    "sg:postcode":"28012",
    "sg:province":"Madrid",
    "sg:website":"www.alatzas.com",
    "wof:name":"Alatzas Asociados S.a.",
    "wof:placetype":"venue"
},
  "geometry": {"coordinates":[-3.7072520256,40.4116516113],"type":"Point"}
}