{
  "type": "Feature",
  "properties": {
    "iso:country":"ES",
    "sg:address":"C/ Doctor Fleming, 25",
    "sg:city":"Manacor",
    "sg:orig_category":"Ense\u00d1anza, Formaci\u00d3n Profesional: Aprendizaje",
    "sg:phone":"+34 971 55 32 43",
    "sg:postcode":"07500",
    "sg:province":"Islas Baleares",
    "wof:name":"Tesoreria General De La Seguridad Social-direccion Provincial De Baleares",
    "wof:placetype":"venue"
},
  "geometry": {"coordinates":[3.2073159218,39.5740966797],"type":"Point"}
}