{
  "type": "Feature",
  "properties": {
    "addr:full":"Calle de Torrelaguna, 106 Madrid Madrid 28043",
    "addr:housenumber":"106",
    "addr:postcode":"28043",
    "addr:street":"Calle De Torrelaguna",
    "iso:country":"ES",
    "sg:address":"Calle de Torrelaguna, 106",
    "sg:city":"Madrid",
    "sg:orig_category":"Artes Gr\u00c1ficas, Artes Pl\u00c1sticas: Material Y Suministros (al Por Menor)",
    "sg:phone":"+34 914 16 78 39",
    "sg:postcode":"28043",
    "sg:province":"Madrid",
    "wof:name":"Carrero Diaz-pintado Jose Luis",
    "wof:placetype":"venue"
},
  "geometry": {"coordinates":[-3.6604530811,40.4547653198],"type":"Point"}
}