{
  "type": "Feature",
  "properties": {
    "addr:full":"Carrer de Corrals Nous, S/n Torre-romeu Barcelona 08202",
    "addr:housenumber":"s / n",
    "addr:postcode":"08202",
    "addr:street":"Carrer De Corrals Nous",
    "iso:country":"ES",
    "sg:address":"Carrer de Corrals Nous, S/n",
    "sg:city":"Torre-romeu",
    "sg:orig_category":"Contenedores (mercanc\u00cdas)",
    "sg:phone":"+34 937 25 56 40",
    "sg:postcode":"08202",
    "sg:province":"Barcelona",
    "wof:name":"Transportes Magal S.a.",
    "wof:placetype":"venue"
},
  "geometry": {"coordinates":[2.1286709309,41.5617256165],"type":"Point"}
}