{
  "type": "Feature",
  "properties": {
    "addr:full":"I\u00f1igo Arista, 19 Iru\u00f1a Navarra 31007",
    "addr:housenumber":"19",
    "addr:postcode":"31007",
    "addr:street":"Arista",
    "iso:country":"ES",
    "sg:address":"I\u00f1igo Arista, 19",
    "sg:city":"Iru\u00f1a",
    "sg:orig_category":"Farmacias",
    "sg:phone":"+34 948 27 25 05",
    "sg:postcode":"31007",
    "sg:province":"Navarra",
    "wof:name":"Urielrubiomariajoseybelens.c.p.",
    "wof:placetype":"venue"
},
  "geometry": {"coordinates":[-1.6548110247,42.8051567078],"type":"Point"}
}