{
  "type": "Feature",
  "properties": {
    "addr:full":"Plaz Coru\u00d1a (de La), 10 Fuenlabrada Madrid 28942",
    "addr:postcode":"28942",
    "addr:street":"Plaz",
    "iso:country":"ES",
    "sg:address":"Plaz Coru\u00d1a (de La), 10",
    "sg:city":"Fuenlabrada",
    "sg:orig_category":"Bisuter\u00cda, Joyer\u00cda, Relojer\u00cda (al Por Menor)",
    "sg:phone":"+34 916 08 14 45",
    "sg:postcode":"28942",
    "sg:province":"Madrid",
    "wof:name":"Alvarez Bola\u00f1os Jesus",
    "wof:placetype":"venue"
},
  "geometry": {"coordinates":[-3.8299105167,40.3017883301],"type":"Point"}
}