{
  "type": "Feature",
  "properties": {
    "addr:full":"Plaz Felix Azpilicueta, 12 Fuenmayor La Rioja 26360",
    "addr:housenumber":"12",
    "addr:postcode":"26360",
    "addr:street":"Plaz Felix Azpilicueta;Rioja",
    "iso:country":"ES",
    "sg:address":"Plaz Felix Azpilicueta, 12",
    "sg:city":"Fuenmayor",
    "sg:orig_category":"Bares, Piano",
    "sg:phone":"+34 941 45 14 15",
    "sg:postcode":"26360",
    "sg:province":"La Rioja",
    "wof:name":"Hosteleria Horubia Roldan S.l.",
    "wof:placetype":"venue"
},
  "geometry": {"coordinates":[-2.5618860722,42.467502594],"type":"Point"}
}