{
  "type": "Feature",
  "properties": {
    "addr:full":"Calle de Arco De Caperuza, 2 Llerena Badajoz 06900",
    "addr:housenumber":"2",
    "addr:postcode":"06900",
    "addr:street":"Calle De Arco De Caperuza",
    "iso:country":"ES",
    "sg:address":"Calle de Arco De Caperuza, 2",
    "sg:city":"Llerena",
    "sg:orig_category":"Empresas De Carpinter\u00cda",
    "sg:phone":"+34 924 87 15 26",
    "sg:postcode":"06900",
    "sg:province":"Badajoz",
    "wof:name":"Gonzalez Martin Jose",
    "wof:placetype":"venue"
},
  "geometry": {"coordinates":[-6.014330864,38.2398529053],"type":"Point"}
}