{
  "type": "Feature",
  "properties": {
    "iso:country":"ES",
    "sg:address":"Carrer de Pare Pere De Piera, 16",
    "sg:city":"S. Boi Llobregat",
    "sg:orig_category":"Molduras, Junquillos, Listones Y Molduras Perforadas",
    "sg:phone":"+34 936 40 10 72",
    "sg:postcode":"08830",
    "sg:province":"Barcelona",
    "wof:name":"Vidueira Couso Dolores",
    "wof:placetype":"venue"
},
  "geometry": {"coordinates":[2.0385699272,41.3433914185],"type":"Point"}
}