{
  "type": "Feature",
  "properties": {
    "addr:full":"Mercat, S/n Tortosa Tarragona 43500",
    "addr:housenumber":"s / n",
    "addr:postcode":"43500",
    "iso:country":"ES",
    "sg:address":"Mercat, S/n",
    "sg:city":"Tortosa",
    "sg:orig_category":"Carnicer\u00cdas, Carnicer\u00cdas",
    "sg:phone":"+34 977 44 29 24",
    "sg:postcode":"43500",
    "sg:province":"Tarragona",
    "wof:name":"Fores Estrada Jose",
    "wof:placetype":"venue"
},
  "geometry": {"coordinates":[0.5233290195,40.8138427734],"type":"Point"}
}