{
  "type": "Feature",
  "properties": {
    "addr:full":"Calle de Peregrinos Los, 96 Goro Las Palmas 35215",
    "addr:housenumber":"96",
    "addr:postcode":"35215",
    "addr:street":"Calle De Peregrinos Los",
    "iso:country":"ES",
    "sg:address":"Calle de Peregrinos Los, 96",
    "sg:city":"Goro",
    "sg:orig_category":"Productos Qu\u00cdmicos (fabricaci\u00d3n, Al Por Mayor)",
    "sg:phone":"+34 928 70 06 31",
    "sg:postcode":"35215",
    "sg:province":"Las Palmas",
    "sg:website":"www.krafft.es",
    "wof:name":"Krafft S.l. (unipersonal",
    "wof:placetype":"venue"
},
  "geometry": {"coordinates":[-15.398223877,27.9939899445],"type":"Point"}
}