{
  "type": "Feature",
  "properties": {
    "addr:full":"Calle de Virgen, 8 Alfafar Valencia 46910",
    "addr:housenumber":"8",
    "addr:postcode":"46910",
    "addr:street":"Calle De Virgen",
    "iso:country":"ES",
    "sg:address":"Calle de Virgen, 8",
    "sg:city":"Alfafar",
    "sg:orig_category":"Abogados",
    "sg:phone":"+34 963 75 09 48",
    "sg:postcode":"46910",
    "sg:province":"Valencia",
    "wof:name":"Lafora Moreno Amparo",
    "wof:placetype":"venue"
},
  "geometry": {"coordinates":[-0.3908630013,39.4229469299],"type":"Point"}
}