{
  "type": "Feature",
  "properties": {
    "iso:country":"ES",
    "sg:address":"Carr Alcalde Juan Sancho, 4",
    "sg:city":"Oliva",
    "sg:orig_category":"Pr\u00c9stamos Personales E Hipotecarios",
    "sg:phone":"+34 962 85 88 13",
    "sg:postcode":"46780",
    "sg:province":"Valencia",
    "wof:name":"Navarro Diaz Maria Rosa",
    "wof:placetype":"venue"
},
  "geometry": {"coordinates":[-0.118313998,38.9224739075],"type":"Point"}
}