{
  "type": "Feature",
  "properties": {
    "iso:country":"ES",
    "sg:address":"Carrer de Gran Canaria, 27",
    "sg:city":"Granja",
    "sg:orig_category":"Inmobiliaria (agencias)",
    "sg:phone":"+34 977 54 88 00",
    "sg:postcode":"43006",
    "sg:province":"Tarragona",
    "sg:website":"www.pisoperfecto.com",
    "wof:name":"Piso Perfecto S.l.",
    "wof:placetype":"venue"
},
  "geometry": {"coordinates":[1.2209249735,41.1154441833],"type":"Point"}
}