{
  "type": "Feature",
  "properties": {
    "addr:full":"Ctra Lleida, 1 Ponts Lleida 25740",
    "addr:housenumber":"1",
    "addr:postcode":"25740",
    "addr:street":"Ctra Lleida",
    "iso:country":"ES",
    "sg:address":"Ctra Lleida, 1",
    "sg:city":"Ponts",
    "sg:orig_category":"Panader\u00cdas, Panader\u00cdas",
    "sg:phone":"+34 973 46 04 58",
    "sg:postcode":"25740",
    "sg:province":"Lleida",
    "wof:name":"Zaldo Viladrich Maria Natividad",
    "wof:placetype":"venue"
},
  "geometry": {"coordinates":[1.1848535538,41.9154205322],"type":"Point"}
}