{
  "type": "Feature",
  "properties": {
    "iso:country":"ES",
    "sg:address":"Calle de Santa Ana, 18",
    "sg:city":"Soraluze-placencia Armas",
    "sg:orig_category":"Cajas De Ahorro",
    "sg:phone":"+34 943 75 12 38",
    "sg:postcode":"20590",
    "sg:province":"Guip\u00f9zcoa",
    "wof:name":"Caja Laboral Popular",
    "wof:placetype":"venue"
},
  "geometry": {"coordinates":[-2.4123980999,43.1730880737],"type":"Point"}
}