{
  "type": "Feature",
  "properties": {
    "addr:full":"Pso. Maritimo, S/n Torrox-costa M\u00e1laga 29793",
    "addr:housenumber":"s",
    "addr:postcode":"29793",
    "addr:street":"Maritimo;/ N Torrox-Costa Ma\u0301Laga",
    "iso:country":"ES",
    "sg:address":"Pso. Maritimo, S/n",
    "sg:city":"Torrox-costa",
    "sg:orig_category":"Reposter\u00cdas",
    "sg:phone":"+34 952 53 48 56",
    "sg:postcode":"29793",
    "sg:province":"M\u00e1laga",
    "wof:name":"Castro Nu\u00f1ez Maria Angeles",
    "wof:placetype":"venue"
},
  "geometry": {"coordinates":[-3.9646790028,36.729309082],"type":"Point"}
}