{
  "type": "Feature",
  "properties": {
    "iso:country":"ES",
    "sg:address":"Calle de Comandante Villar, 1",
    "sg:city":"Laredo",
    "sg:orig_category":"Estudios De Fotograf\u00cda",
    "sg:phone":"+34 942 60 71 40",
    "sg:postcode":"39770",
    "sg:province":"Cantabria",
    "wof:name":"Fernandez Cano Juan Manuel",
    "wof:placetype":"venue"
},
  "geometry": {"coordinates":[-3.4164376259,43.409488678],"type":"Point"}
}