{
  "type": "Feature",
  "properties": {
    "addr:full":"Calle de Angel Lozano, 18 Alacant Alicante 03001",
    "addr:housenumber":"18",
    "addr:postcode":"03001",
    "addr:street":"Calle De Angel Lozano",
    "iso:country":"ES",
    "sg:address":"Calle de Angel Lozano, 18",
    "sg:city":"Alacant",
    "sg:orig_category":"Zapatos (al Por Menor)",
    "sg:phone":"+34 965 21 31 47",
    "sg:postcode":"03001",
    "sg:province":"Alicante",
    "wof:name":"Belmonte Lorenzo Olga Maria",
    "wof:placetype":"venue"
},
  "geometry": {"coordinates":[-0.4883550107,38.3466911316],"type":"Point"}
}