{
  "type": "Feature",
  "properties": {
    "addr:full":"Calle de Otero Blas De, 27 Bilbao Vizcaya 48014",
    "addr:housenumber":"27",
    "addr:postcode":"48014",
    "addr:street":"Calle De Otero Blas De",
    "iso:country":"ES",
    "sg:address":"Calle de Otero Blas De, 27",
    "sg:city":"Bilbao",
    "sg:orig_category":"Peluqueros: De Se\u00d1oras",
    "sg:phone":"+34 944 75 60 18",
    "sg:postcode":"48014",
    "sg:province":"Vizcaya",
    "wof:name":"Gorostegui Arrieta Ainoa",
    "wof:placetype":"venue"
},
  "geometry": {"coordinates":[-2.9478731155,43.269859314],"type":"Point"}
}