{
  "type": "Feature",
  "properties": {
    "iso:country":"ES",
    "sg:address":"Calle de Granada, 42",
    "sg:city":"Malaga",
    "sg:orig_category":"Prensas Industriales",
    "sg:phone":"+34 952 12 62 00",
    "sg:postcode":"29...",
    "sg:province":"M\u00e1laga",
    "wof:name":"La Opinion De Malaga S.l.",
    "wof:placetype":"venue"
},
  "geometry": {"coordinates":[-4.4192790985,36.7219161987],"type":"Point"}
}