{
  "type": "Feature",
  "properties": {
    "iso:country":"ES",
    "sg:address":"Ptda Torrello, S/n",
    "sg:city":"Onda",
    "sg:orig_category":"Arboricultura Y Producci\u00d3n De Frutas",
    "sg:phone":"+34 964 76 62 55",
    "sg:postcode":"12200",
    "sg:province":"Castell\u00f3n",
    "wof:name":"Agricola Valenciana Pla Dels Olivars S.l.",
    "wof:placetype":"venue"
},
  "geometry": {"coordinates":[-0.2432307005,39.9604454041],"type":"Point"}
}