{
  "type": "Feature",
  "properties": {
    "iso:country":"ES",
    "sg:address":"Port Del Comte-est. Alta Muntanya, S/n",
    "sg:city":"Port Comte",
    "sg:orig_category":"Asociaciones Y Clubs Deportivos",
    "sg:phone":"+34 973 49 25 96",
    "sg:postcode":"25284",
    "sg:province":"Lleida",
    "wof:name":"375 Nurjon 25 S.l.",
    "wof:placetype":"venue"
},
  "geometry": {"coordinates":[1.058614,42.073315],"type":"Point"}
}