{
  "type": "Feature",
  "properties": {
    "addr:full":"Blas Infante, 5 Pechina Almer\u00eda 04250",
    "addr:housenumber":"5",
    "addr:postcode":"04250",
    "addr:street":"Blas Infante;Almeri\u0301A",
    "iso:country":"ES",
    "sg:address":"Blas Infante, 5",
    "sg:city":"Pechina",
    "sg:orig_category":"Promotores Constructores",
    "sg:phone":"+34 950 31 76 00",
    "sg:postcode":"04250",
    "sg:province":"Almer\u00eda",
    "wof:name":"Pechina Residencial S.l.",
    "wof:placetype":"venue"
},
  "geometry": {"coordinates":[-2.4415290356,36.914730072],"type":"Point"}
}