{
  "type": "Feature",
  "properties": {
    "iso:country":"ES",
    "sg:address":"Calle de Federico Tapia, 14",
    "sg:city":"Coru\u00d1a",
    "sg:orig_category":"Agencias De Viajes",
    "sg:phone":"+34 981 12 00 34",
    "sg:postcode":"15005",
    "sg:province":"A Coru\u00f1a",
    "wof:name":"Viajes Airbus Galicia S.a.",
    "wof:placetype":"venue"
},
  "geometry": {"coordinates":[-8.4066047668,43.3636550903],"type":"Point"}
}