{
  "type": "Feature",
  "properties": {
    "addr:full":"Calle de Carlos Iii, 24 Cartagena Murcia 30201",
    "addr:housenumber":"24",
    "addr:postcode":"30201",
    "addr:street":"Calle De Carlos Iii",
    "iso:country":"ES",
    "sg:address":"Calle de Carlos Iii, 24",
    "sg:city":"Cartagena",
    "sg:orig_category":"Centros De Adelgazamiento Y De Est\u00c9tica",
    "sg:phone":"+34 968 52 70 20",
    "sg:postcode":"30201",
    "sg:province":"Murcia",
    "wof:name":"\u00d1iguez Soriano Juana",
    "wof:placetype":"venue"
},
  "geometry": {"coordinates":[-0.983890295,37.6058540344],"type":"Point"}
}