{
  "type": "Feature",
  "properties": {
    "iso:country":"ES",
    "sg:address":"Avda Prim, S/n",
    "sg:city":"Lora Rio",
    "sg:orig_category":"Panader\u00cdas, Panader\u00cdas",
    "sg:phone":"+34 955 80 23 43",
    "sg:postcode":"41440",
    "sg:province":"Sevilla",
    "wof:name":"Confiteria Galvez S.c.",
    "wof:placetype":"venue"
},
  "geometry": {"coordinates":[-5.5294389725,37.659778595],"type":"Point"}
}