{
  "type": "Feature",
  "properties": {
    "iso:country":"ES",
    "sg:address":"Calle de Juliobriga, 8",
    "sg:city":"Matamorosa",
    "sg:orig_category":"Carnicer\u00cdas, Carnicer\u00cdas",
    "sg:phone":"+34 942 75 44 35",
    "sg:postcode":"39200",
    "sg:province":"Cantabria",
    "wof:name":"Fuente Merino Justino",
    "wof:placetype":"venue"
},
  "geometry": {"coordinates":[-4.1447191238,42.9870986938],"type":"Point"}
}