{
  "type": "Feature",
  "properties": {
    "addr:full":"Donapea, 4 Atarrabia Navarra 31610",
    "addr:housenumber":"4",
    "addr:postcode":"31610",
    "addr:street":"Donapea",
    "iso:country":"ES",
    "sg:address":"Donapea, 4",
    "sg:city":"Atarrabia",
    "sg:orig_category":"Artes Gr\u00c1ficas, Artes Pl\u00c1sticas: Material Y Suministros (al Por Menor)",
    "sg:phone":"+34 948 14 12 17",
    "sg:postcode":"31610",
    "sg:province":"Navarra",
    "wof:name":"Talleres Reyco S.l.",
    "wof:placetype":"venue"
},
  "geometry": {"coordinates":[-1.6067359447,42.8283653259],"type":"Point"}
}