{
  "type": "Feature",
  "properties": {
    "addr:full":"Avda Paz (de La), 6 Burgos Burgos 09004",
    "addr:housenumber":"6",
    "addr:postcode":"09004",
    "addr:street":"Avda Paz De La",
    "iso:country":"ES",
    "sg:address":"Avda Paz (de La), 6",
    "sg:city":"Burgos",
    "sg:orig_category":"Asesor\u00cda Fiscal Y Jur\u00cddica",
    "sg:phone":"+34 947 27 05 00",
    "sg:postcode":"09004",
    "sg:province":"Burgos",
    "wof:name":"Vander Vorst Bienvenu Juan",
    "wof:placetype":"venue"
},
  "geometry": {"coordinates":[-3.6906518936,42.3452072144],"type":"Point"}
}