{
  "type": "Feature",
  "properties": {
    "iso:country":"ES",
    "sg:address":"Carr Felip Ii, 27",
    "sg:city":"Eivissa",
    "sg:orig_category":"Laboratorios Y Trabajos De Fotograf\u00cda, V\u00cddeo Y Cine",
    "sg:phone":"+34 971 19 01 55",
    "sg:postcode":"07800",
    "sg:province":"Islas Baleares",
    "sg:website":"www.printart-digital.com",
    "wof:name":"Pomar Bofill Antoni Angel",
    "wof:placetype":"venue"
},
  "geometry": {"coordinates":[1.4321889877,38.911277771],"type":"Point"}
}