{
  "type": "Feature",
  "properties": {
    "addr:full":"Pase Matarredo, 6 Samaniego \u00c1lava 01307",
    "addr:housenumber":"6",
    "addr:postcode":"01307",
    "addr:street":"Matarredo;A\u0301Lava",
    "iso:country":"ES",
    "sg:address":"Pase Matarredo, 6",
    "sg:city":"Samaniego",
    "sg:orig_category":"Comerciantes Al Por Mayor De Vinos, Licores Y Alcoholes",
    "sg:phone":"+34 945 62 33 31",
    "sg:postcode":"01307",
    "sg:province":"\u00c1lava",
    "wof:name":"Escribano Pascual Antonio",
    "wof:placetype":"venue"
},
  "geometry": {"coordinates":[-2.6776390076,42.5300865173],"type":"Point"}
}