{
  "type": "Feature",
  "properties": {
    "iso:country":"ES",
    "sg:address":"Carrer de Mila, 72",
    "sg:city":"Santa Coloma De Gramenet",
    "sg:orig_category":"Negocio De Enlosados, Soler\u00cdas",
    "sg:phone":"+34 934 68 33 79",
    "sg:postcode":"08921",
    "sg:province":"Barcelona",
    "wof:name":"Cataso S.l.",
    "wof:placetype":"venue"
},
  "geometry": {"coordinates":[2.219422102,41.4555091858],"type":"Point"}
}