{
  "type": "Feature",
  "properties": {
    "addr:full":"Pl Joaquim Bau (de), 13 Tortosa Tarragona 43500",
    "addr:postcode":"43500",
    "addr:street":"Pl",
    "iso:country":"ES",
    "sg:address":"Pl Joaquim Bau (de), 13",
    "sg:city":"Tortosa",
    "sg:orig_category":"Quiropr\u00c1cticos",
    "sg:phone":"+34 977 58 11 11",
    "sg:postcode":"43500",
    "sg:province":"Tarragona",
    "wof:name":"Massatge A 11 Punt 11 S.l.",
    "wof:placetype":"venue"
},
  "geometry": {"coordinates":[0.5161370039,40.8137016296],"type":"Point"}
}