{
  "type": "Feature",
  "properties": {
    "iso:country":"ES",
    "sg:address":"Calle de Extramuros, S/n",
    "sg:city":"Sig\u00fcenza",
    "sg:orig_category":"Organizaciones Profesionales",
    "sg:phone":"+34 949 39 02 91",
    "sg:postcode":"19250",
    "sg:province":"Guadalajara",
    "wof:name":"Donoso Garcia Jesus Damian",
    "wof:placetype":"venue"
},
  "geometry": {"coordinates":[-2.6919779778,41.0896644592],"type":"Point"}
}