{
  "type": "Feature",
  "properties": {
    "addr:full":"Calle de San Francisco Solano, 22 Montilla C\u00f3rdoba 14550",
    "addr:housenumber":"22",
    "addr:postcode":"14550",
    "addr:street":"Calle De San Francisco Solano;Co\u0301Rdoba",
    "iso:country":"ES",
    "sg:address":"Calle de San Francisco Solano, 22",
    "sg:city":"Montilla",
    "sg:orig_category":"Peluqueros: De Se\u00d1oras",
    "sg:phone":"+34 957 65 22 02",
    "sg:postcode":"14550",
    "sg:province":"C\u00f3rdoba",
    "wof:name":"Pedrosa Calderon Dulce",
    "wof:placetype":"venue"
},
  "geometry": {"coordinates":[-4.6387910843,37.5855178833],"type":"Point"}
}