{
  "type": "Feature",
  "properties": {
    "addr:full":"Urbaniz. Baldio, S/n Urb. El Baldio C\u00f3rdoba 14700",
    "addr:housenumber":"s",
    "addr:postcode":"14700",
    "addr:street":"/ N Urb. El;Co\u0301Rdoba",
    "iso:country":"ES",
    "sg:address":"Urbaniz. Baldio, S/n",
    "sg:city":"Urb. El Baldio",
    "sg:orig_category":"Arboricultura Y Producci\u00d3n De Frutas",
    "sg:phone":"+34 957 71 60 71",
    "sg:postcode":"14700",
    "sg:province":"C\u00f3rdoba",
    "wof:name":"Necfruit Sat",
    "wof:placetype":"venue"
},
  "geometry": {"coordinates":[-5.2795991898,37.7004241943],"type":"Point"}
}