{
  "type": "Feature",
  "properties": {
    "iso:country":"ES",
    "sg:address":"Calle de Garcia Morato, 18",
    "sg:city":"Alacant",
    "sg:orig_category":"Centros P\u00dablicos De Formaci\u00d3n Profesional Y T\u00c9cnica",
    "sg:phone":"+34 965 14 53 65",
    "sg:postcode":"03004",
    "sg:province":"Alicante",
    "wof:name":"Colegio Oficial De Gestores Administrativos De Alicante",
    "wof:placetype":"venue"
},
  "geometry": {"coordinates":[-0.4871360064,38.3489532471],"type":"Point"}
}