{
  "type": "Feature",
  "properties": {
    "addr:full":"Av Platja, 18 Santa Margarida-salatar Girona 17480",
    "addr:housenumber":"18",
    "addr:postcode":"17480",
    "addr:street":"Av Platja",
    "iso:country":"ES",
    "sg:address":"Av Platja, 18",
    "sg:city":"Santa Margarida-salatar",
    "sg:orig_category":"Estancos",
    "sg:phone":"+34 972 25 59 06",
    "sg:postcode":"17480",
    "sg:province":"Girona",
    "wof:name":"Casals Colomer Francisco",
    "wof:placetype":"venue"
},
  "geometry": {"coordinates":[3.1522800922,42.2632293701],"type":"Point"}
}