{
  "type": "Feature",
  "properties": {
    "iso:country":"ES",
    "sg:address":"Avgd Prat De La Riba, 82",
    "sg:city":"Lleida",
    "sg:orig_category":"Cr\u00cda De Animales",
    "sg:phone":"+34 973 23 59 83",
    "sg:postcode":"25004",
    "sg:province":"Lleida",
    "wof:name":"Morancho Morancho Ramon",
    "wof:placetype":"venue"
},
  "geometry": {"coordinates":[0.6280360222,41.6224594116],"type":"Point"}
}