{
  "type": "Feature",
  "properties": {
    "iso:country":"ES",
    "sg:address":"Carrer de Mestre Joan Corrales, 104",
    "sg:city":"Esplugues Llobregat",
    "sg:orig_category":"Artes Gr\u00c1ficas, Artes Pl\u00c1sticas: Material Y Suministros (al Por Menor)",
    "sg:phone":"+34 934 73 76 77",
    "sg:postcode":"08950",
    "sg:province":"Barcelona",
    "sg:website":"www.kba-print.com",
    "wof:name":"Lauvic S.l.",
    "wof:placetype":"venue"
},
  "geometry": {"coordinates":[2.088203907,41.3702087402],"type":"Point"}
}