{
  "type": "Feature",
  "properties": {
    "addr:full":"C/ Porta De La Morera, 33 Elche Alicante 03203",
    "addr:housenumber":"33",
    "addr:postcode":"03203",
    "addr:street":"C / Porta De La Morera",
    "iso:country":"ES",
    "sg:address":"C/ Porta De La Morera, 33",
    "sg:city":"Elche",
    "sg:orig_category":"Molduras, Junquillos, Listones Y Molduras Perforadas",
    "sg:phone":"+34 965 42 04 86",
    "sg:postcode":"03203",
    "sg:province":"Alicante",
    "wof:name":"Ortiz Marhuenda Francisco Antonio",
    "wof:placetype":"venue"
},
  "geometry": {"coordinates":[-0.6925690174,38.2643241882],"type":"Point"}
}