{
  "type": "Feature",
  "properties": {
    "addr:full":"Avda Espa\u00d1a, 22 Plasencia C\u00e1ceres 10600",
    "addr:housenumber":"22",
    "addr:postcode":"10600",
    "addr:street":"Avda Espan\u0303A;Ca\u0301Ceres",
    "iso:country":"ES",
    "sg:address":"Avda Espa\u00d1a, 22",
    "sg:city":"Plasencia",
    "sg:orig_category":"Restaurantes",
    "sg:phone":"+34 927 41 82 57",
    "sg:postcode":"10600",
    "sg:province":"C\u00e1ceres",
    "wof:name":"Llorente Pereira David",
    "wof:placetype":"venue"
},
  "geometry": {"coordinates":[-6.0952925682,40.0251121521],"type":"Point"}
}