{
  "type": "Feature",
  "properties": {
    "iso:country":"ES",
    "sg:address":"Juan L. Pia Martinez, S/n",
    "sg:city":"Ortigueira",
    "sg:orig_category":"Aguas (distribuci\u00d3n, Servicios)",
    "sg:phone":"+34 981 42 23 76",
    "sg:postcode":"15330",
    "sg:province":"La Coru\u00f1a",
    "wof:name":"Investimentos Urbanisticos Do Noroeste S.l.",
    "wof:placetype":"venue"
},
  "geometry": {"coordinates":[-7.8177599907,43.6668701172],"type":"Point"}
}