{
  "type": "Feature",
  "properties": {
    "iso:country":"ES",
    "sg:address":"Calle de Don Jose Pe\u00d1a, S/n",
    "sg:city":"Oca\u00f1a",
    "sg:orig_category":"Ense\u00d1anza Variada",
    "sg:phone":"+34 925 12 08 68",
    "sg:postcode":"45300",
    "sg:province":"Toledo",
    "wof:name":"Centro De Profesores De Oca\u00f1a",
    "wof:placetype":"venue"
},
  "geometry": {"coordinates":[-3.4958789349,39.9543838501],"type":"Point"}
}