{
  "type": "Feature",
  "properties": {
    "addr:full":"Avda Daniel Ayala, 1 Archena Murcia 30600",
    "addr:housenumber":"1",
    "addr:postcode":"30600",
    "addr:street":"Avda Daniel Ayala",
    "iso:country":"ES",
    "sg:address":"Avda Daniel Ayala, 1",
    "sg:city":"Archena",
    "sg:orig_category":"Ense\u00d1anza Secundaria: Colegios Y Escuelas Privadas",
    "sg:phone":"+34 968 67 11 44",
    "sg:postcode":"30600",
    "sg:province":"Murcia",
    "wof:name":"Instituto De Bachillerato Vicente Medina",
    "wof:placetype":"venue"
},
  "geometry": {"coordinates":[-1.2989120483,38.1174659729],"type":"Point"}
}