{
  "type": "Feature",
  "properties": {
    "iso:country":"ES",
    "sg:address":"Calle de Delicias, 54",
    "sg:city":"Zaragoza",
    "sg:orig_category":"Ropa Y Art\u00cdculos Pre",
    "sg:phone":"+34 976 53 67 34",
    "sg:postcode":"50017",
    "sg:province":"Zaragoza",
    "wof:name":"Piera Garay Cristina",
    "wof:placetype":"venue"
},
  "geometry": {"coordinates":[-0.9046630859,41.6499710083],"type":"Point"}
}