{
  "type": "Feature",
  "properties": {
    "iso:country":"ES",
    "sg:address":"Calle de San Pedro, 12",
    "sg:city":"Pasai S. Pedro",
    "sg:orig_category":"Motores Diessel",
    "sg:phone":"+34 943 40 40 35",
    "sg:postcode":"20110",
    "sg:province":"Guip\u00f9zcoa",
    "sg:website":"www.tecomar.es",
    "wof:name":"Tecomar S. L.",
    "wof:placetype":"venue"
},
  "geometry": {"coordinates":[-1.9238840342,43.325302124],"type":"Point"}
}