{
  "type": "Feature",
  "properties": {
    "addr:full":"Calle de San Pedro, 12 Pasai S. Pedro Guip\u00f9zcoa 20110",
    "addr:housenumber":"12",
    "addr:postcode":"20110",
    "addr:street":"Calle De San Pedro;Guipu\u0300Zcoa",
    "iso:country":"ES",
    "sg:address":"Calle de San Pedro, 12",
    "sg:city":"Pasai S. Pedro",
    "sg:orig_category":"Motores Diessel",
    "sg:phone":"+34 943 40 40 35",
    "sg:postcode":"20110",
    "sg:province":"Guip\u00f9zcoa",
    "sg:website":"www.tecomar.es",
    "wof:name":"Tecomar S. L.",
    "wof:placetype":"venue"
},
  "geometry": {"coordinates":[-1.9238840342,43.325302124],"type":"Point"}
}