{
  "type": "Feature",
  "properties": {
    "iso:country":"ES",
    "sg:address":"Calle de Ramiro El Monje, 16",
    "sg:city":"Huesca",
    "sg:orig_category":"Empresas De Limpieza",
    "sg:phone":"+34 974 23 12 31",
    "sg:postcode":"22001",
    "sg:province":"Huesca",
    "wof:name":"Sigma Servicios Integrales S.l.",
    "wof:placetype":"venue"
},
  "geometry": {"coordinates":[-0.4065929949,42.1378669739],"type":"Point"}
}