{
  "type": "Feature",
  "properties": {
    "iso:country":"ES",
    "sg:address":"Avda Diputacion (de La), 4",
    "sg:city":"Chiclana De La Frontera",
    "sg:orig_category":"Ense\u00d1anza: Profesiones Art\u00cdsticas",
    "sg:phone":"+34 956 53 29 57",
    "sg:postcode":"11130",
    "sg:province":"C\u00e1diz",
    "wof:name":"Belizon Rivas Pedro Luis",
    "wof:placetype":"venue"
},
  "geometry": {"coordinates":[-6.1555709839,36.4215087891],"type":"Point"}
}