{
  "type": "Feature",
  "properties": {
    "addr:full":"Avda Torrelaguna (de), 10 Azuqueca Henares Guadalajara 19200",
    "addr:housenumber":"10",
    "addr:postcode":"19200",
    "addr:street":"Avda Torrelaguna De",
    "iso:country":"ES",
    "sg:address":"Avda Torrelaguna (de), 10",
    "sg:city":"Azuqueca Henares",
    "sg:orig_category":"Asesor\u00cda De Formaci\u00d3n Y Gesti\u00d3n De Personal",
    "sg:phone":"+34 949 34 80 95",
    "sg:postcode":"19200",
    "sg:province":"Guadalajara",
    "wof:name":"United Services Spain Back-office S.l.",
    "wof:placetype":"venue"
},
  "geometry": {"coordinates":[-3.2654750347,40.5639190674],"type":"Point"}
}