{
  "type": "Feature",
  "properties": {
    "addr:full":"Urb Maigmo, 29 Urbanizacion Maigmo Alicante 03109",
    "addr:housenumber":"29",
    "addr:postcode":"03109",
    "addr:street":"Urb Maigmo;Urbanizacion",
    "iso:country":"ES",
    "sg:address":"Urb Maigmo, 29",
    "sg:city":"Urbanizacion Maigmo",
    "sg:orig_category":"Deportes N\u00c1uticos, Acu\u00c1ticos Y Subacu\u00c1ticos: Art\u00cdculos Y Equipo (al Por Menor)",
    "sg:phone":"+34 965 61 71 27",
    "sg:postcode":"03109",
    "sg:province":"Alicante",
    "wof:name":"Kecarluysl",
    "wof:placetype":"venue"
},
  "geometry": {"coordinates":[-0.5752289891,38.5324134827],"type":"Point"}
}