{
  "type": "Feature",
  "properties": {
    "iso:country":"ES",
    "sg:address":"Plaz Domingo Alegria, 1",
    "sg:city":"Gernika-lumo",
    "sg:orig_category":"\u00d3ptica: Instrumentos (fabricaci\u00d3n)",
    "sg:phone":"+34 946 25 03 23",
    "sg:postcode":"48300",
    "sg:province":"Vizcaya",
    "wof:name":"Optica Eguren S.a.",
    "wof:placetype":"venue"
},
  "geometry": {"coordinates":[-97.78224945069999,45.7040786743],"type":"Point"}
}