{
  "type": "Feature",
  "properties": {
    "iso:country":"ES",
    "sg:address":"Calle de Montesinos (de), 50",
    "sg:city":"Aranjuez",
    "sg:orig_category":"Asesor\u00cda Sobre Comunicaci\u00d3n De Empresas",
    "sg:phone":"+34 918 92 50 50",
    "sg:postcode":"28300",
    "sg:province":"Madrid",
    "wof:name":"Gestion De Empresas Estrada S.l.",
    "wof:placetype":"venue"
},
  "geometry": {"coordinates":[-3.5995490551,40.0323944092],"type":"Point"}
}