{
  "type": "Feature",
  "properties": {
    "addr:full":"Avda San Martin De Porres, 3 Cabo Blanco Santa Cruz De Tenerife 38626",
    "addr:housenumber":"3",
    "addr:postcode":"38626",
    "addr:street":"Avda San Martin De Porres;Cabo Blanco",
    "iso:country":"ES",
    "sg:address":"Avda San Martin De Porres, 3",
    "sg:city":"Cabo Blanco",
    "sg:orig_category":"Mec\u00c1nico Del Autom\u00d3vil",
    "sg:phone":"+34 922 72 02 05",
    "sg:postcode":"38626",
    "sg:province":"Santa Cruz De Tenerife",
    "wof:name":"Automecanica Fran S.l.l.",
    "wof:placetype":"venue"
},
  "geometry": {"coordinates":[-16.670879364,28.0742702484],"type":"Point"}
}