{
  "type": "Feature",
  "properties": {
    "addr:full":"Calle de Doctor Jimenez Diaz, 3 Ogijares Granada 18151",
    "addr:housenumber":"3",
    "addr:postcode":"18151",
    "addr:street":"Calle De Doctor Jimenez Diaz",
    "iso:country":"ES",
    "sg:address":"Calle de Doctor Jimenez Diaz, 3",
    "sg:city":"Ogijares",
    "sg:orig_category":"Fabrica, Negocio De Vidrieras, Productos Vidriados Y Espejos",
    "sg:phone":"+34 958 50 39 73",
    "sg:postcode":"18151",
    "sg:province":"Granada",
    "wof:name":"Reformas Pou Nou S.l.",
    "wof:placetype":"venue"
},
  "geometry": {"coordinates":[-3.6194014549,37.1158485413],"type":"Point"}
}