{
  "type": "Feature",
  "properties": {
    "iso:country":"ES",
    "sg:address":"Ronda Norte, S/n",
    "sg:city":"Valladolid",
    "sg:orig_category":"Carnicer\u00cdas, Carnicer\u00cdas",
    "sg:phone":"+34 983 36 31 94",
    "sg:postcode":"47009",
    "sg:province":"Valladolid",
    "wof:name":"Castellana De Carnes S.a.",
    "wof:placetype":"venue"
},
  "geometry": {"coordinates":[-4.7224311829,41.6785202026],"type":"Point"}
}