{
  "type": "Feature",
  "properties": {
    "iso:country":"ES",
    "sg:address":"Carrer de Enric Borras, 7",
    "sg:city":"Prat Llobregat",
    "sg:orig_category":"Confecci\u00d3n De Trajes Para Se\u00d1oras",
    "sg:phone":"+34 933 79 74 82",
    "sg:postcode":"08820",
    "sg:province":"Barcelona",
    "wof:name":"Sangoz S.l.",
    "wof:placetype":"venue"
},
  "geometry": {"coordinates":[2.0971989632,41.3325881958],"type":"Point"}
}