{
  "type": "Feature",
  "properties": {
    "addr:full":"Ctra General Del Norte, 55 Cantillo Santa Cruz De Tenerife 38350",
    "addr:housenumber":"55",
    "addr:postcode":"38350",
    "addr:street":"Ctra General Del Norte",
    "iso:country":"ES",
    "sg:address":"Ctra General Del Norte, 55",
    "sg:city":"Cantillo",
    "sg:orig_category":"Perfumer\u00cda (al Por Menor)",
    "sg:phone":"+34 922 56 28 65",
    "sg:postcode":"38350",
    "sg:province":"Santa Cruz De Tenerife",
    "wof:name":"Perez Garcia Margarita",
    "wof:placetype":"venue"
},
  "geometry": {"coordinates":[-16.4174289703,28.4756546021],"type":"Point"}
}