{
  "type": "Feature",
  "properties": {
    "addr:full":"Calle de Acebo, 1 Hellin Albacete 02400",
    "addr:housenumber":"1",
    "addr:postcode":"02400",
    "addr:street":"Calle De Acebo",
    "iso:country":"ES",
    "sg:address":"Calle de Acebo, 1",
    "sg:city":"Hellin",
    "sg:orig_category":"Empresas De Carpinter\u00cda De Madera",
    "sg:phone":"+34 967 30 56 98",
    "sg:postcode":"02400",
    "sg:province":"Albacete",
    "wof:name":"Carpinteria Pino Hellin S.l.",
    "wof:placetype":"venue"
},
  "geometry": {"coordinates":[-1.6967796087,38.5180511475],"type":"Point"}
}