{
  "type": "Feature",
  "properties": {
    "addr:full":"Calle de Limonero, 6 Palma Murcia 30593",
    "addr:housenumber":"6",
    "addr:postcode":"30593",
    "addr:street":"Calle De Limonero",
    "iso:country":"ES",
    "sg:address":"Calle de Limonero, 6",
    "sg:city":"Palma",
    "sg:orig_category":"Promotores Constructores",
    "sg:phone":"+34 968 55 46 39",
    "sg:postcode":"30593",
    "sg:province":"Murcia",
    "wof:name":"Construcciones Sanchez E Hijo De La Palma S.l.",
    "wof:placetype":"venue"
},
  "geometry": {"coordinates":[-0.9620990157,37.6914596558],"type":"Point"}
}