{
  "type": "Feature",
  "properties": {
    "iso:country":"ES",
    "sg:address":"Av Maria Fortuny, 68",
    "sg:city":"Reus",
    "sg:orig_category":"Agentes, Concesionarios Y Sucursales De Veh\u00cdculos",
    "sg:phone":"+34 977 34 26 84",
    "sg:postcode":"43203",
    "sg:province":"Tarragona",
    "wof:name":"Nissan Motor Espa\u00d1a S.a.",
    "wof:placetype":"venue"
},
  "geometry": {"coordinates":[1.1154030561,41.1603546143],"type":"Point"}
}