{
  "type": "Feature",
  "properties": {
    "iso:country":"ES",
    "sg:address":"Plaz Mayor, S/n",
    "sg:city":"Villalobos",
    "sg:orig_category":"Centros De Educaci\u00d3n Especial",
    "sg:phone":"+34 980 66 63 20",
    "sg:postcode":"49134",
    "sg:province":"Zamora",
    "wof:name":"Colegio Publico",
    "wof:placetype":"venue"
},
  "geometry": {"coordinates":[-5.4762740135,41.9452629089],"type":"Point"}
}