{
  "type": "Feature",
  "properties": {
    "addr:full":"Calle de Toneleros, 1 Miguelturra Ciudad Real 13170",
    "addr:housenumber":"1",
    "addr:postcode":"13170",
    "addr:street":"Calle De Toneleros",
    "iso:country":"ES",
    "sg:address":"Calle de Toneleros, 1",
    "sg:city":"Miguelturra",
    "sg:orig_category":"Fabricaci\u00d3n, Instalaci\u00d3n Y Reparaci\u00d3n De Bombas",
    "sg:phone":"+34 926 24 25 28",
    "sg:postcode":"13170",
    "sg:province":"Ciudad Real",
    "wof:name":"Agua Y Maquinaria S.l.",
    "wof:placetype":"venue"
},
  "geometry": {"coordinates":[-3.8985247612,38.971157074],"type":"Point"}
}