{
  "type": "Feature",
  "properties": {
    "iso:country":"ES",
    "sg:address":"Avda Constitucion, 56",
    "sg:city":"Gijon",
    "sg:orig_category":"Molduras, Junquillos, Listones Y Molduras Perforadas",
    "sg:phone":"+34 985 17 24 54",
    "sg:postcode":"33207",
    "sg:province":"Asturias",
    "wof:name":"Sistelcom-telemensaje",
    "wof:placetype":"venue"
},
  "geometry": {"coordinates":[-5.6709089279,43.5326347351],"type":"Point"}
}