{
  "type": "Feature",
  "properties": {
    "iso:country":"ES",
    "sg:address":"Calle de Federico Garcia Lorca, S/n",
    "sg:city":"Fuente",
    "sg:orig_category":"Bazares, Art\u00cdculos De Limpieza Y De Cocina (al Por Menor)",
    "sg:phone":"+34 950 61 93 60",
    "sg:postcode":"04640",
    "sg:province":"Almer\u00eda",
    "wof:name":"Egea Guerrero Maria Del Carmen",
    "wof:placetype":"venue"
},
  "geometry": {"coordinates":[-1.7452540398,37.3896865845],"type":"Point"}
}