{
  "type": "Feature",
  "properties": {
    "iso:country":"ES",
    "sg:address":"Rond Constitucio, 43",
    "sg:city":"Monovar",
    "sg:orig_category":"Empresas De Carpinter\u00cda De Madera",
    "sg:phone":"+34 965 47 06 51",
    "sg:postcode":"03640",
    "sg:province":"Alicante",
    "wof:name":"Ripay Cdad",
    "wof:placetype":"venue"
},
  "geometry": {"coordinates":[-0.8290240169,38.4391365051],"type":"Point"}
}