{
  "type": "Feature",
  "properties": {
    "addr:full":"Avda Americas (das), S/n Lugo Lugo 27004",
    "addr:housenumber":"s / n",
    "addr:postcode":"27004",
    "addr:street":"Avda Americas Das",
    "iso:country":"ES",
    "sg:address":"Avda Americas (das), S/n",
    "sg:city":"Lugo",
    "sg:orig_category":"Promotores Constructores",
    "sg:phone":"+34 982 21 59 75",
    "sg:postcode":"27004",
    "sg:province":"Lugo",
    "wof:name":"Construcciones Lopez Castro S.l.",
    "wof:placetype":"venue"
},
  "geometry": {"coordinates":[-7.569381237,43.0095176697],"type":"Point"}
}