{
  "type": "Feature",
  "properties": {
    "iso:country":"ES",
    "sg:address":"Calle de Rafael Salazar Alonso, 16",
    "sg:city":"Madrid",
    "sg:orig_category":"Fisioterapia",
    "sg:phone":"+34 915 73 40 46",
    "sg:postcode":"28007",
    "sg:province":"Madrid",
    "wof:name":"Herrera Alonso Jose Manuel",
    "wof:placetype":"venue"
},
  "geometry": {"coordinates":[-3.6683840752,40.4156036377],"type":"Point"}
}