{
  "type": "Feature",
  "properties": {
    "iso:country":"ES",
    "sg:address":"Carrer de Berenguer De Palou, 31",
    "sg:city":"Barcelona",
    "sg:orig_category":"Persianas Interiores, Exteriores",
    "sg:phone":"+34 934 08 64 15",
    "sg:postcode":"08027",
    "sg:province":"Barcelona",
    "sg:website":"www.empresas.futurnet.es/livimastoldos",
    "wof:name":"Livimas Toldos S.l.",
    "wof:placetype":"venue"
},
  "geometry": {"coordinates":[2.1915779114,41.4235649109],"type":"Point"}
}