{
  "type": "Feature",
  "properties": {
    "iso:country":"ES",
    "sg:address":"Ctra Dolores, 97",
    "sg:city":"Almoradi",
    "sg:orig_category":"Muebles Y Accesorios Para Cocinas Y Cuartos De Ba\u00d1o (al Por Menor)",
    "sg:phone":"+34 965 70 26 99",
    "sg:postcode":"03160",
    "sg:province":"Alicante",
    "wof:name":"Coyba S.l.",
    "wof:placetype":"venue"
},
  "geometry": {"coordinates":[-0.7921590209,38.1102905273],"type":"Point"}
}