{
  "type": "Feature",
  "properties": {
    "iso:country":"ES",
    "sg:address":"Plaz Cultura, 6",
    "sg:city":"Soto De Ribera",
    "sg:orig_category":"Partidos Pol\u00cdticos",
    "sg:phone":"+34 985 79 68 38",
    "sg:postcode":"33172",
    "sg:province":"Asturias",
    "wof:name":"Partido Socialista Obrero Espa\u00f1ol",
    "wof:placetype":"venue"
},
  "geometry": {"coordinates":[-5.8755578995,43.309387207],"type":"Point"}
}