{
  "type": "Feature",
  "properties": {
    "addr:full":"Carrer de Concordia, 4 Granollers Barcelona 08402",
    "addr:housenumber":"4",
    "addr:postcode":"08402",
    "addr:street":"Carrer De Concordia",
    "iso:country":"ES",
    "sg:address":"Carrer de Concordia, 4",
    "sg:city":"Granollers",
    "sg:orig_category":"Estudios, Instalaci\u00d3n De Climatizaci\u00d3n",
    "sg:phone":"+34 938 46 85 40",
    "sg:postcode":"08402",
    "sg:province":"Barcelona",
    "wof:name":"Comercial Victor-manuel S.a.",
    "wof:placetype":"venue"
},
  "geometry": {"coordinates":[2.2913780212,41.6138000488],"type":"Point"}
}