{
  "type": "Feature",
  "properties": {
    "iso:country":"ES",
    "sg:address":"Ctra Madrigal, Km. 0001,6",
    "sg:city":"Candeleda",
    "sg:orig_category":"Muebles, Minoristas",
    "sg:phone":"+34 920 38 04 98",
    "sg:postcode":"05480",
    "sg:province":"\u00c1vila",
    "wof:name":"Muebles Valero S.l.",
    "wof:placetype":"venue"
},
  "geometry": {"coordinates":[-5.240790844,40.1553764343],"type":"Point"}
}