{
  "type": "Feature",
  "properties": {
    "addr:full":"Plaz Castillejos, 1 Maracena Granada 18200",
    "addr:housenumber":"1",
    "addr:postcode":"18200",
    "addr:street":"Plaz Castillejos",
    "iso:country":"ES",
    "sg:address":"Plaz Castillejos, 1",
    "sg:city":"Maracena",
    "sg:orig_category":"Promotores Constructores",
    "sg:phone":"+34 958 41 09 08",
    "sg:postcode":"18200",
    "sg:province":"Granada",
    "wof:name":"Promociones Alisano S.l.",
    "wof:placetype":"venue"
},
  "geometry": {"coordinates":[-3.6319019794,37.2079811096],"type":"Point"}
}