{
  "type": "Feature",
  "properties": {
    "iso:country":"ES",
    "sg:address":"Carr Santander, 2",
    "sg:city":"Girona",
    "sg:orig_category":"Centros Comerciales Y Grandes Tiendas",
    "sg:phone":"+34 972 40 54 29",
    "sg:postcode":"17005",
    "sg:province":"Girona",
    "wof:name":"Regals Qiutao Sl",
    "wof:placetype":"venue"
},
  "geometry": {"coordinates":[2.8135619164,41.9759101868],"type":"Point"}
}