{
  "type": "Feature",
  "properties": {
    "addr:full":"Carrer de Prat De La Riba, 27 Santa Coloma De Gramenet Barcelona 08921",
    "addr:housenumber":"27",
    "addr:postcode":"08921",
    "addr:street":"Carrer De Prat De La Riba",
    "iso:country":"ES",
    "sg:address":"Carrer de Prat De La Riba, 27",
    "sg:city":"Santa Coloma De Gramenet",
    "sg:orig_category":"Cerrajer\u00cda, Ferrallista",
    "sg:phone":"+34 933 91 54 03",
    "sg:postcode":"08921",
    "sg:province":"Barcelona",
    "wof:name":"Cerrajeria Lopez S.c.p.",
    "wof:placetype":"venue"
},
  "geometry": {"coordinates":[2.2074530125,41.4553108215],"type":"Point"}
}