{
  "type": "Feature",
  "properties": {
    "addr:full":"Calle de Almacellas, 106 Binefar Huesca 22500",
    "addr:housenumber":"106",
    "addr:postcode":"22500",
    "addr:street":"Calle De Almacellas",
    "iso:country":"ES",
    "sg:address":"Calle de Almacellas, 106",
    "sg:city":"Binefar",
    "sg:orig_category":"Empresas De Desmonte",
    "sg:phone":"+34 974 43 07 86",
    "sg:postcode":"22500",
    "sg:province":"Huesca",
    "sg:website":"www.construccionesmarco.com",
    "wof:name":"Construcciones Y Desmontes Marco S.a.",
    "wof:placetype":"venue"
},
  "geometry": {"coordinates":[0.2980583906,41.8435668945],"type":"Point"}
}