{
  "type": "Feature",
  "properties": {
    "addr:full":"Ctra. Jerez-arcos, S/n Jerez C\u00e1diz 11406",
    "addr:housenumber":"s",
    "addr:postcode":"11406",
    "addr:street":"Ctra. Jerez-Arcos;/ N",
    "iso:country":"ES",
    "sg:address":"Ctra. Jerez-arcos, S/n",
    "sg:city":"Jerez",
    "sg:orig_category":"Molduras, Junquillos, Listones Y Molduras Perforadas",
    "sg:phone":"+34 956 30 65 40",
    "sg:postcode":"11406",
    "sg:province":"C\u00e1diz",
    "wof:name":"Pe\u00f1a Flores Francisco",
    "wof:placetype":"venue"
},
  "geometry": {"coordinates":[-6.118683815,36.6686515808],"type":"Point"}
}