{
  "type": "Feature",
  "properties": {
    "addr:full":"Carrer de Menorca, 72 Barcelona Barcelona 08020",
    "addr:housenumber":"72",
    "addr:postcode":"08020",
    "addr:street":"Carrer De Menorca",
    "iso:country":"ES",
    "sg:address":"Carrer de Menorca, 72",
    "sg:city":"Barcelona",
    "sg:orig_category":"Institutos De Belleza",
    "sg:phone":"+34 932 78 19 04",
    "sg:postcode":"08020",
    "sg:province":"Barcelona",
    "wof:name":"Vi\u00f1as Novella Pilar",
    "wof:placetype":"venue"
},
  "geometry": {"coordinates":[2.1983942986,41.4206809998],"type":"Point"}
}