{
  "type": "Feature",
  "properties": {
    "addr:full":"Calle de Oca, 8 Madrid Madrid 28025",
    "addr:housenumber":"8",
    "addr:postcode":"madrid;28025",
    "addr:street":"Calle De Oca",
    "iso:country":"ES",
    "sg:address":"Calle de Oca, 8",
    "sg:city":"Madrid",
    "sg:orig_category":"Arreglo, Reparaci\u00d3n, Piezas Sueltas De Televisi\u00d3n, V\u00cddeo, Hi",
    "sg:phone":"+34 914 72 09 77",
    "sg:postcode":"28025",
    "sg:province":"Madrid",
    "wof:name":"Romero Cabello Angel",
    "wof:placetype":"venue"
},
  "geometry": {"coordinates":[-3.7327439785,40.3890914917],"type":"Point"}
}