{
  "type": "Feature",
  "properties": {
    "addr:full":"Carrer de Johann Sebastian Bach, 15 Tarragona Tarragona 43007",
    "addr:housenumber":"15",
    "addr:postcode":"43007",
    "addr:street":"Carrer De Johann Sebastian Bach",
    "iso:country":"ES",
    "sg:address":"Carrer de Johann Sebastian Bach, 15",
    "sg:city":"Tarragona",
    "sg:orig_category":"Agencias Y Agentes Comerciales, Representantes",
    "sg:phone":"+34 977 29 03 15",
    "sg:postcode":"43007",
    "sg:province":"Tarragona",
    "wof:name":"Homs Sant Jose",
    "wof:placetype":"venue"
},
  "geometry": {"coordinates":[1.2642229795,41.1206932068],"type":"Point"}
}