{
  "type": "Feature",
  "properties": {
    "addr:full":"Avgd Alcalde Porqueres, 28 Lleida Lleida 25008",
    "addr:housenumber":"28",
    "addr:postcode":"25008",
    "addr:street":"Alcalde Porqueres",
    "iso:country":"ES",
    "sg:address":"Avgd Alcalde Porqueres, 28",
    "sg:city":"Lleida",
    "sg:orig_category":"Inmobiliaria (agencias)",
    "sg:phone":"+34 973 22 36 22",
    "sg:postcode":"25008",
    "sg:province":"Lleida",
    "wof:name":"Pool Consulting Ilerda S. L.",
    "wof:placetype":"venue"
},
  "geometry": {"coordinates":[0.6231579781,41.6226882935],"type":"Point"}
}