{
  "type": "Feature",
  "properties": {
    "addr:full":"Calle de Sor Angela De La Cruz, 14 Chiclana De La Frontera C\u00e1diz 11130",
    "addr:housenumber":"14",
    "addr:postcode":"11130",
    "addr:street":"Calle De Sor Angela De La Cruz",
    "iso:country":"ES",
    "sg:address":"Calle de Sor Angela De La Cruz, 14",
    "sg:city":"Chiclana De La Frontera",
    "sg:orig_category":"Zapater\u00cdas",
    "sg:phone":"+34 956 53 23 57",
    "sg:postcode":"11130",
    "sg:province":"C\u00e1diz",
    "wof:name":"Alonso Calvente Miguel",
    "wof:placetype":"venue"
},
  "geometry": {"coordinates":[-6.1432881355,36.422039032],"type":"Point"}
}