{
  "type": "Feature",
  "properties": {
    "addr:full":"Avda Aldehuela, S/n Salamanca Salamanca 37008",
    "addr:housenumber":"s / n",
    "addr:postcode":"37008",
    "addr:street":"Avda Aldehuela",
    "iso:country":"ES",
    "sg:address":"Avda Aldehuela, S/n",
    "sg:city":"Salamanca",
    "sg:orig_category":"Reciclaje Y Tratamiento De Desechos Varios",
    "sg:phone":"+34 923 18 49 71",
    "sg:postcode":"37008",
    "sg:province":"Salamanca",
    "wof:name":"Reciclajes Salamanca S.l.",
    "wof:placetype":"venue"
},
  "geometry": {"coordinates":[-5.6582660675,40.95936203],"type":"Point"}
}