{
  "type": "Feature",
  "properties": {
    "iso:country":"ES",
    "sg:address":"Pg Fabra I Puig, 30",
    "sg:city":"Barcelona",
    "sg:orig_category":"Molduras, Junquillos, Listones Y Molduras Perforadas",
    "sg:phone":"+34 933 11 38 53",
    "sg:postcode":"08030",
    "sg:province":"Barcelona",
    "wof:name":"Saumell Ventura Magin",
    "wof:placetype":"venue"
},
  "geometry": {"coordinates":[2.1877739429,41.4303817749],"type":"Point"}
}