{
  "type": "Feature",
  "properties": {
    "addr:full":"Carrer de Monges, 21 S. Adria Besos Barcelona 08930",
    "addr:housenumber":"21",
    "addr:postcode":"08930",
    "addr:street":"Carrer De Monges;S. Adria Besos Barcelona",
    "iso:country":"ES",
    "sg:address":"Carrer de Monges, 21",
    "sg:city":"S. Adria Besos",
    "sg:orig_category":"Molduras, Junquillos, Listones Y Molduras Perforadas",
    "sg:phone":"+34 933 81 36 79",
    "sg:postcode":"08930",
    "sg:province":"Barcelona",
    "wof:name":"Angel Maldonado Maria",
    "wof:placetype":"venue"
},
  "geometry": {"coordinates":[2.1877346039,41.4312095642],"type":"Point"}
}