{
  "type": "Feature",
  "properties": {
    "addr:full":"Plaz Jose Antonio, 1 Martin De Yeltes Salamanca 37494",
    "addr:housenumber":"1",
    "addr:postcode":"37494",
    "addr:street":"Jose Antonio;Martin De Yeltes",
    "iso:country":"ES",
    "sg:address":"Plaz Jose Antonio, 1",
    "sg:city":"Martin De Yeltes",
    "sg:orig_category":"Administraciones Regionales, Departamentales Y Locales",
    "sg:phone":"+34 923 44 03 20",
    "sg:postcode":"37494",
    "sg:province":"Salamanca",
    "wof:name":"Ayuntamiento",
    "wof:placetype":"venue"
},
  "geometry": {"coordinates":[-6.2907290459,40.7765693665],"type":"Point"}
}