{
  "type": "Feature",
  "properties": {
    "iso:country":"ES",
    "sg:address":"Calle de Muelle, S/n",
    "sg:city":"Palma",
    "sg:orig_category":"Transportes Mar\u00cdtimos",
    "sg:phone":"+34 971 22 91 00",
    "sg:postcode":"07012",
    "sg:province":"Islas Baleares",
    "sg:website":"www.iscomar.com",
    "wof:name":"Iscomar S. A.",
    "wof:placetype":"venue"
},
  "geometry": {"coordinates":[2.6447570324,39.5667762756],"type":"Point"}
}