{
  "type": "Feature",
  "properties": {
    "iso:country":"ES",
    "sg:address":"Rua Porta Da Pena (da), 9",
    "sg:city":"Santiago De Compostela",
    "sg:orig_category":"Arquitectos",
    "sg:phone":"+34 981 57 38 67",
    "sg:postcode":"15704",
    "sg:province":"La Coru\u00f1a",
    "wof:name":"Redondo Valladares Y Rodriguez Arquitectos S.c",
    "wof:placetype":"venue"
},
  "geometry": {"coordinates":[-8.5435600281,42.8828849792],"type":"Point"}
}