{
  "type": "Feature",
  "properties": {
    "iso:country":"ES",
    "sg:address":"Cmno Conforcos, 1",
    "sg:city":"Corbillos Sobarriba",
    "sg:orig_category":"Productos L\u00c1cteos Y Av\u00cdcolas (al Por Mayor)",
    "sg:phone":"+34 987 26 90 11",
    "sg:postcode":"24228",
    "sg:province":"Le\u00f3n",
    "wof:name":"Mani S.c.",
    "wof:placetype":"venue"
},
  "geometry": {"coordinates":[-5.4931898117,42.5947647095],"type":"Point"}
}