{
  "type": "Feature",
  "properties": {
    "iso:country":"ES",
    "sg:address":"Avda Valladolid Soria, Km. 0155,0",
    "sg:city":"Pe\u00f1afiel",
    "sg:orig_category":"Producci\u00d3n De Abonos Y De Fertilizantes",
    "sg:phone":"+34 983 88 03 11",
    "sg:postcode":"47300",
    "sg:province":"Valladolid",
    "wof:name":"Antonio Moran E Hijos S.l.",
    "wof:placetype":"venue"
},
  "geometry": {"coordinates":[-4.1206746101,41.5973625183],"type":"Point"}
}