{
  "type": "Feature",
  "properties": {
    "addr:full":"Avda Juventud, 11 Cabezo Torres Murcia 30110",
    "addr:housenumber":"11",
    "addr:postcode":"30110",
    "addr:street":"Avda Juventud",
    "iso:country":"ES",
    "sg:address":"Avda Juventud, 11",
    "sg:city":"Cabezo Torres",
    "sg:orig_category":"Venta, Montaje De Neum\u00c1ticos",
    "sg:phone":"+34 968 85 66 25",
    "sg:postcode":"30110",
    "sg:province":"Murcia",
    "wof:name":"Neumaticos Roda C.b.",
    "wof:placetype":"venue"
},
  "geometry": {"coordinates":[-1.1266640425,38.0308074951],"type":"Point"}
}