{
  "type": "Feature",
  "properties": {
    "iso:country":"ES",
    "sg:address":"Calle de Tenis, 1",
    "sg:city":"Villanueva Alcardete",
    "sg:orig_category":"Estudios, Instalaci\u00d3n De Climatizaci\u00d3n",
    "sg:phone":"+34 925 16 63 93",
    "sg:postcode":"45810",
    "sg:province":"Toledo",
    "sg:website":"www.iespana.es/climar",
    "wof:name":"Rodrigo Chaves Miguel Angel",
    "wof:placetype":"venue"
},
  "geometry": {"coordinates":[-3.0214850903,39.6718025208],"type":"Point"}
}