{
  "type": "Feature",
  "properties": {
    "addr:full":"Carr Argenteria, 23 Girona Girona 17004",
    "addr:housenumber":"23",
    "addr:postcode":"17004",
    "addr:street":"Carr Argenteria",
    "iso:country":"ES",
    "sg:address":"Carr Argenteria, 23",
    "sg:city":"Girona",
    "sg:orig_category":"Zapatos (al Por Menor)",
    "sg:phone":"+34 972 20 63 98",
    "sg:postcode":"17004",
    "sg:province":"Girona",
    "sg:website":"www.zhoanedifferent.com",
    "wof:name":"Serveis Turistics Elaema 2000 S.l.",
    "wof:placetype":"venue"
},
  "geometry": {"coordinates":[2.8245201111,41.9851951599],"type":"Point"}
}