{
  "type": "Feature",
  "properties": {
    "addr:full":"Calle de Berlin, 4 Pozuelo De Alarcon Madrid 28224",
    "addr:housenumber":"4",
    "addr:postcode":"28224",
    "addr:street":"Calle De Berlin",
    "iso:country":"ES",
    "sg:address":"Calle de Berlin, 4",
    "sg:city":"Pozuelo De Alarcon",
    "sg:orig_category":"Transportes Mar\u00cdtimos",
    "sg:phone":"+34 913 51 86 02",
    "sg:postcode":"28224",
    "sg:province":"Madrid",
    "sg:website":"www.jsvlogisti.com",
    "wof:name":"J.s.v. Logisti S.l.",
    "wof:placetype":"venue"
},
  "geometry": {"coordinates":[-3.7893953323,40.4416542053],"type":"Point"}
}