{
  "type": "Feature",
  "properties": {
    "addr:full":"Avda Elche, S/n Alacant Alicante 03008",
    "addr:housenumber":"s / n",
    "addr:postcode":"03008",
    "addr:street":"Avda Elche",
    "iso:country":"ES",
    "sg:address":"Avda Elche, S/n",
    "sg:city":"Alacant",
    "sg:orig_category":"Doctores En Medicina",
    "sg:phone":"+34 965 28 42 78",
    "sg:postcode":"03008",
    "sg:province":"Alicante",
    "wof:name":"Albert Guillen Alfredo",
    "wof:placetype":"venue"
},
  "geometry": {"coordinates":[-0.5352352858,38.3008804321],"type":"Point"}
}