{
  "type": "Feature",
  "properties": {
    "addr:full":"Calle de Sargentos Provisionales, 62 Lanzahita \u00c1vila 05490",
    "addr:housenumber":"62",
    "addr:postcode":"05490",
    "addr:street":"Calle De Sargentos Provisionales;A\u0301Vila",
    "iso:country":"ES",
    "sg:address":"Calle de Sargentos Provisionales, 62",
    "sg:city":"Lanzahita",
    "sg:orig_category":"Reparaciones Y Remolcado De Veh\u00cdculos",
    "sg:phone":"+34 920 37 87 47",
    "sg:postcode":"05490",
    "sg:province":"\u00c1vila",
    "wof:name":"Diaz Ruiz Eloy",
    "wof:placetype":"venue"
},
  "geometry": {"coordinates":[-4.933950901,40.2055587769],"type":"Point"}
}