{
  "type": "Feature",
  "properties": {
    "addr:full":"Calle de Comandante Zorita, 39 Madrid Madrid 28020",
    "addr:housenumber":"39",
    "addr:postcode":"madrid;28020",
    "addr:street":"Calle De Comandante Zorita",
    "iso:country":"ES",
    "sg:address":"Calle de Comandante Zorita, 39",
    "sg:city":"Madrid",
    "sg:orig_category":"M\u00c9dicos: Oftalmolog\u00cda",
    "sg:phone":"+34 915 35 84 74",
    "sg:postcode":"28020",
    "sg:province":"Madrid",
    "wof:name":"Perez Pi\u00f1o Maria Dolores",
    "wof:placetype":"venue"
},
  "geometry": {"coordinates":[-3.6982584,40.4508743286],"type":"Point"}
}