{
  "type": "Feature",
  "properties": {
    "iso:country":"ES",
    "sg:address":"Rua Cronista Rodriguez Elias, 2",
    "sg:city":"Vigo",
    "sg:orig_category":"Cerrajer\u00cda, Ferrallista",
    "sg:phone":"+34 986 24 43 82",
    "sg:postcode":"36209",
    "sg:province":"Pontevedra",
    "wof:name":"Azbe B. Zubia S. A.",
    "wof:placetype":"venue"
},
  "geometry": {"coordinates":[-8.7463226318,42.2122612],"type":"Point"}
}