{
  "type": "Feature",
  "properties": {
    "addr:full":"Avda Aragon (de), 16 Valdeltormo Teruel 44620",
    "addr:housenumber":"16",
    "addr:postcode":"44620",
    "addr:street":"Avda Aragon De",
    "iso:country":"ES",
    "sg:address":"Avda Aragon (de), 16",
    "sg:city":"Valdeltormo",
    "sg:orig_category":"Promotores Constructores",
    "sg:phone":"+34 978 85 80 23",
    "sg:postcode":"44620",
    "sg:province":"Teruel",
    "wof:name":"Iba\u00f1ez Mompel Jose",
    "wof:placetype":"venue"
},
  "geometry": {"coordinates":[0.0837090015,40.9863166809],"type":"Point"}
}