{
  "type": "Feature",
  "properties": {
    "addr:full":"Calle de Ferrari, 30 Valladolid Valladolid 47001",
    "addr:housenumber":"30",
    "addr:postcode":"47001",
    "addr:street":"Calle De Ferrari",
    "iso:country":"ES",
    "sg:address":"Calle de Ferrari, 30",
    "sg:city":"Valladolid",
    "sg:orig_category":"Perfumer\u00cda (al Por Menor)",
    "sg:phone":"+34 983 37 60 23",
    "sg:postcode":"47001",
    "sg:province":"Valladolid",
    "wof:name":"Perfumeria Ercilla S. L.",
    "wof:placetype":"venue"
},
  "geometry": {"coordinates":[-4.7267384529,41.6520233154],"type":"Point"}
}