{
  "type": "Feature",
  "properties": {
    "iso:country":"ES",
    "sg:address":"Plaz Biombo, 5",
    "sg:city":"Madrid",
    "sg:orig_category":"Organismos De Reclutamiento",
    "sg:phone":"+34 915 48 30 79",
    "sg:postcode":"28013",
    "sg:province":"Madrid",
    "wof:name":"Montejo & Pernas Asociados",
    "wof:placetype":"venue"
},
  "geometry": {"coordinates":[-3.7123200893,40.4158592224],"type":"Point"}
}