{
  "type": "Feature",
  "properties": {
    "iso:country":"ES",
    "sg:address":"Carrer de Berlin (de), 18",
    "sg:city":"Salou",
    "sg:orig_category":"Agencias Y Agentes Comerciales, Representantes",
    "sg:phone":"+34 977 35 28 04",
    "sg:postcode":"43840",
    "sg:province":"Tarragona",
    "wof:name":"Joan Carreras Interhome S.l.",
    "wof:placetype":"venue"
},
  "geometry": {"coordinates":[1.137141943,41.0772895813],"type":"Point"}
}