{
  "type": "Feature",
  "properties": {
    "addr:full":"Pase Delicias, 62 Madrid Madrid 28045",
    "addr:housenumber":"62",
    "addr:postcode":"madrid;28045",
    "addr:street":"Delicias",
    "iso:country":"ES",
    "sg:address":"Pase Delicias, 62",
    "sg:city":"Madrid",
    "sg:orig_category":"Laboratorios Y Trabajos De Fotograf\u00cda, V\u00cddeo Y Cine",
    "sg:phone":"+34 915 30 01 61",
    "sg:postcode":"28045",
    "sg:province":"Madrid",
    "wof:name":"Chang Le S.l.",
    "wof:placetype":"venue"
},
  "geometry": {"coordinates":[-3.6942520142,40.3996887207],"type":"Point"}
}