{
  "type": "Feature",
  "properties": {
    "addr:full":"Praz Constitucion, 10 Vigo Pontevedra 36202",
    "addr:housenumber":"10",
    "addr:postcode":"36202",
    "addr:street":"Constitucion",
    "iso:country":"ES",
    "sg:address":"Praz Constitucion, 10",
    "sg:city":"Vigo",
    "sg:orig_category":"Cester\u00cda (fabricaci\u00d3n)",
    "sg:phone":"+34 986 43 17 51",
    "sg:postcode":"36202",
    "sg:province":"Pontevedra",
    "wof:name":"Faustino Davila Mercedes Luz",
    "wof:placetype":"venue"
},
  "geometry": {"coordinates":[-8.7261037827,42.2385787964],"type":"Point"}
}