{
  "type": "Feature",
  "properties": {
    "iso:country":"ES",
    "sg:address":"C/ Gonzalez, 22",
    "sg:city":"Cerdanyola Valles",
    "sg:orig_category":"M\u00c9dicos: Medicina General",
    "sg:phone":"+34 936 92 41 23",
    "sg:postcode":"08290",
    "sg:province":"Barcelona",
    "wof:name":"Servicios Oftalmologicos Libres S. L.",
    "wof:placetype":"venue"
},
  "geometry": {"coordinates":[2.1443989277,41.4906272888],"type":"Point"}
}