{
  "type": "Feature",
  "properties": {
    "addr:full":"Carr Alcaduf, S/n Raval Valencia 46680",
    "addr:housenumber":"s",
    "addr:postcode":"46680",
    "addr:street":"Carr Alcaduf;/ N Raval",
    "iso:country":"ES",
    "sg:address":"Carr Alcaduf, S/n",
    "sg:city":"Raval",
    "sg:orig_category":"Transportes Internacionales",
    "sg:phone":"+34 962 48 30 73",
    "sg:postcode":"46680",
    "sg:province":"Valencia",
    "wof:name":"Salvador Dasi Cardete S.l.",
    "wof:placetype":"venue"
},
  "geometry": {"coordinates":[-0.4383490086,39.1962852478],"type":"Point"}
}