{
  "type": "Feature",
  "properties": {
    "iso:country":"ES",
    "sg:address":"Pase General Davila, 17",
    "sg:city":"Santander",
    "sg:orig_category":"Doctores En Medicina",
    "sg:phone":"+34 942 27 09 31",
    "sg:postcode":"39005",
    "sg:province":"Cantabria",
    "wof:name":"Martinez Perez Vicente",
    "wof:placetype":"venue"
},
  "geometry": {"coordinates":[-3.792288065,43.4683647156],"type":"Point"}
}