{
  "type": "Feature",
  "properties": {
    "addr:full":"Polig. De Boutaron, 18 S. Tirso Abres Asturias 33774",
    "addr:housenumber":"18",
    "addr:postcode":"33774",
    "addr:street":"S. Tirso",
    "iso:country":"ES",
    "sg:address":"Polig. De Boutaron, 18",
    "sg:city":"S. Tirso Abres",
    "sg:orig_category":"Maquinaria Para Industrias Diversas",
    "sg:phone":"+34 985 47 65 89",
    "sg:postcode":"33774",
    "sg:province":"Asturias",
    "wof:name":"Talleres Lastra S.l.",
    "wof:placetype":"venue"
},
  "geometry": {"coordinates":[-7.1420388222,43.4099617004],"type":"Point"}
}