{
  "type": "Feature",
  "properties": {
    "iso:country":"ES",
    "sg:address":"Calle de Cura Iba\u00d1ez, 2",
    "sg:city":"Yecla",
    "sg:orig_category":"Tapiceros Y Tapiceros",
    "sg:phone":"+34 968 75 30 90",
    "sg:postcode":"30510",
    "sg:province":"Murcia",
    "wof:name":"Navarro Lorente Jose Luis",
    "wof:placetype":"venue"
},
  "geometry": {"coordinates":[-1.1101356745,38.6107025146],"type":"Point"}
}