{
  "type": "Feature",
  "properties": {
    "addr:full":"Av Constitucio, 13 Xixona Alicante 03100",
    "addr:housenumber":"13",
    "addr:postcode":"03100",
    "addr:street":"Av Constitucio",
    "iso:country":"ES",
    "sg:address":"Av Constitucio, 13",
    "sg:city":"Xixona",
    "sg:orig_category":"Bancos",
    "sg:phone":"+34 965 61 28 78",
    "sg:postcode":"03100",
    "sg:province":"Alicante",
    "sg:website":"www.bancodevalencia.es",
    "wof:name":"Banco De Valencia S.a.",
    "wof:placetype":"venue"
},
  "geometry": {"coordinates":[-0.5071809888,38.5399055481],"type":"Point"}
}