{
  "type": "Feature",
  "properties": {
    "iso:country":"ES",
    "sg:address":"Calle de Ramiro Campos Turmo, 10",
    "sg:city":"Marbella",
    "sg:orig_category":"M\u00c9dicos: Estomatolog\u00cda",
    "sg:phone":"+34 952 77 31 90",
    "sg:postcode":"29600",
    "sg:province":"M\u00e1laga",
    "wof:name":"Zavala Lara Victor",
    "wof:placetype":"venue"
},
  "geometry": {"coordinates":[-4.8880867958,36.5085296631],"type":"Point"}
}