{
  "type": "Feature",
  "properties": {
    "iso:country":"ES",
    "sg:address":"Calle de General Barroso, 79",
    "sg:city":"Valencia",
    "sg:orig_category":"Fachadas",
    "sg:phone":"+34 963 77 99 80",
    "sg:postcode":"46017",
    "sg:province":"Valencia",
    "sg:website":"www.torremar.net",
    "wof:name":"Restauracion De Fachadas Torremar S.l.",
    "wof:placetype":"venue"
},
  "geometry": {"coordinates":[-0.3926419914,39.4493789673],"type":"Point"}
}