{
  "type": "Feature",
  "properties": {
    "iso:country":"ES",
    "sg:address":"Calle de Sacerdote Isidro Albert, S/n",
    "sg:city":"Alacant",
    "sg:orig_category":"Parques De Atracciones Y Centros De Esparcimiento",
    "sg:phone":"+34 965 25 97 61",
    "sg:postcode":"03010",
    "sg:province":"Alicante",
    "wof:name":"Prosede S.l.",
    "wof:placetype":"venue"
},
  "geometry": {"coordinates":[-0.4895642102,38.365070343],"type":"Point"}
}