{
  "type": "Feature",
  "properties": {
    "addr:full":"Uriburu Kalea, 9 Arrasate Guip\u00f9zcoa 20500",
    "addr:housenumber":"9",
    "addr:postcode":"20500",
    "addr:street":"Uriburu Kalea;Guipu\u0300Zcoa",
    "iso:country":"ES",
    "sg:address":"Uriburu Kalea, 9",
    "sg:city":"Arrasate",
    "sg:orig_category":"Asesor\u00cda Fiscal Y Jur\u00cddica",
    "sg:phone":"+34 943 79 34 26",
    "sg:postcode":"20500",
    "sg:province":"Guip\u00f9zcoa",
    "sg:website":"www.emun.com",
    "wof:name":"Emun Koop.e.",
    "wof:placetype":"venue"
},
  "geometry": {"coordinates":[-2.4996950626,43.0624351501],"type":"Point"}
}