{
  "type": "Feature",
  "properties": {
    "iso:country":"ES",
    "sg:address":"Pl Pau Picasso, 1",
    "sg:city":"Reus",
    "sg:orig_category":"Art\u00cdculos Funerarios (al Por Menor)",
    "sg:phone":"+34 977 75 04 22",
    "sg:postcode":"43204",
    "sg:province":"Tarragona",
    "wof:name":"Gestio De Serveis Funeraris Reus S.a.",
    "wof:placetype":"venue"
},
  "geometry": {"coordinates":[1.1139450073,41.1514587402],"type":"Point"}
}