{
  "type": "Feature",
  "properties": {
    "addr:full":"Avda Pio Xii, 34 Sig\u00fcenza Guadalajara 19250",
    "addr:housenumber":"34",
    "addr:postcode":"19250",
    "addr:street":"Avda Pio Xii",
    "iso:country":"ES",
    "sg:address":"Avda Pio Xii, 34",
    "sg:city":"Sig\u00fcenza",
    "sg:orig_category":"Muebles, Minoristas",
    "sg:phone":"+34 949 39 07 01",
    "sg:postcode":"19250",
    "sg:province":"Guadalajara",
    "wof:name":"Punta Parrilla Vicente De La",
    "wof:placetype":"venue"
},
  "geometry": {"coordinates":[-2.6447989941,41.0684318542],"type":"Point"}
}