{
  "type": "Feature",
  "properties": {
    "addr:full":"Carretera Vella De Banyoles-olot, S/n Porqueres Girona 17834",
    "addr:housenumber":"s / n",
    "addr:postcode":"17834",
    "addr:street":"Carretera Vella De Banyoles-Olot",
    "iso:country":"ES",
    "sg:address":"Carretera Vella De Banyoles-olot, S/n",
    "sg:city":"Porqueres",
    "sg:orig_category":"Fabricaci\u00d3n De Productos L\u00c1cteos Y Derivados",
    "sg:phone":"+34 972 57 03 18",
    "sg:postcode":"17834",
    "sg:province":"Girona",
    "wof:name":"Codemat S.l.",
    "wof:placetype":"venue"
},
  "geometry": {"coordinates":[2.7599539757,42.1430511475],"type":"Point"}
}