{
  "type": "Feature",
  "properties": {
    "iso:country":"ES",
    "sg:address":"Luga Lendoiro, S/n",
    "sg:city":"Lendoiro",
    "sg:orig_category":"Semiller\u00cdas",
    "sg:phone":"+34 981 61 31 49",
    "sg:postcode":"15640",
    "sg:province":"A Coru\u00f1a",
    "sg:website":"www.viveroslagarantia.com",
    "wof:name":"Viveros La Garantia S.l.",
    "wof:placetype":"venue"
},
  "geometry": {"coordinates":[-8.3020505905,43.2997169495],"type":"Point"}
}