{
  "type": "Feature",
  "properties": {
    "addr:full":"Ctra Vieja De La Puebla, S/n Zafra Badajoz 06300",
    "addr:housenumber":"/ n",
    "addr:postcode":"06300",
    "addr:street":"Ctra Vieja De La Puebla S",
    "iso:country":"ES",
    "sg:address":"Ctra Vieja De La Puebla, S/n",
    "sg:city":"Zafra",
    "sg:orig_category":"Farmacias",
    "sg:phone":"+34 924 55 45 10",
    "sg:postcode":"06300",
    "sg:province":"Badajoz",
    "wof:name":"Alonso Sanchez Maria Luisa",
    "wof:placetype":"venue"
},
  "geometry": {"coordinates":[-6.4157567024,38.4151725769],"type":"Point"}
}