{
  "type": "Feature",
  "properties": {
    "addr:full":"Avda Doctor Fleming, 26 Le\u00f3n Le\u00f3n 24009",
    "addr:housenumber":"26",
    "addr:postcode":"24009",
    "addr:street":"Avda Doctor Fleming;Leo\u0301N",
    "iso:country":"ES",
    "sg:address":"Avda Doctor Fleming, 26",
    "sg:city":"Le\u00f3n",
    "sg:orig_category":"Confecci\u00d3n (fabricaci\u00d3n, Al Por Mayor)",
    "sg:phone":"+34 987 80 36 20",
    "sg:postcode":"24009",
    "sg:province":"Le\u00f3n",
    "wof:name":"Alvarez Gutierrez Pedro",
    "wof:placetype":"venue"
},
  "geometry": {"coordinates":[-5.5855355263,42.5978088379],"type":"Point"}
}