{
  "type": "Feature",
  "properties": {
    "iso:country":"ES",
    "sg:address":"Calle de Calvo Sotelo, 73",
    "sg:city":"Orotava",
    "sg:orig_category":"Transporte En General",
    "sg:phone":"+34 922 33 10 96",
    "sg:postcode":"38300",
    "sg:province":"Santa Cruz De Tenerife",
    "wof:name":"Cruz Lorenzo Cenobia De La",
    "wof:placetype":"venue"
},
  "geometry": {"coordinates":[-16.5262947083,28.3848075867],"type":"Point"}
}