{
  "type": "Feature",
  "properties": {
    "addr:full":"Av Mas De L'oli, 56 P. I. La Cova Valencia 46940",
    "addr:housenumber":"56 p.",
    "addr:postcode":"46940",
    "addr:street":"Av Mas De L'Oli;I. La Cova",
    "iso:country":"ES",
    "sg:address":"Av Mas De L'oli, 56",
    "sg:city":"P. I. La Cova",
    "sg:orig_category":"Albergues",
    "sg:phone":"+34 961 52 63 06",
    "sg:postcode":"46940",
    "sg:province":"Valencia",
    "wof:name":"Joyoto S.l",
    "wof:placetype":"venue"
},
  "geometry": {"coordinates":[-0.376819998,39.4691886902],"type":"Point"}
}