{
  "type": "Feature",
  "properties": {
    "iso:country":"ES",
    "sg:address":"Avda Reyes Catolicos, 1",
    "sg:city":"Alcala Henares",
    "sg:orig_category":"Veh\u00cdculos De Ocasi\u00d3n",
    "sg:phone":"+34 918 83 18 61",
    "sg:postcode":"28802",
    "sg:province":"Madrid",
    "wof:name":"Soria Ca\u00f1as Ricardo",
    "wof:placetype":"venue"
},
  "geometry": {"coordinates":[-3.3725960255,40.4781913757],"type":"Point"}
}