{
  "type": "Feature",
  "properties": {
    "addr:full":"Calle de Martin Fernandez Villaran, 7 Portugalete Vizcaya 48920",
    "addr:housenumber":"7",
    "addr:postcode":"48920",
    "addr:street":"Calle De Martin;Villaran",
    "iso:country":"ES",
    "sg:address":"Calle de Martin Fernandez Villaran, 7",
    "sg:city":"Portugalete",
    "sg:orig_category":"Bisuter\u00cda, Joyer\u00cda, Relojer\u00cda (al Por Menor)",
    "sg:phone":"+34 944 83 81 73",
    "sg:postcode":"48920",
    "sg:province":"Vizcaya",
    "wof:name":"Jesus Marco Garde",
    "wof:placetype":"venue"
},
  "geometry": {"coordinates":[-3.0200750828,43.3222045898],"type":"Point"}
}