{
  "type": "Feature",
  "properties": {
    "iso:country":"ES",
    "sg:address":"Calle de Islas Cies, 34",
    "sg:city":"Madrid",
    "sg:orig_category":"Agencias Y Agentes Comerciales, Representantes",
    "sg:phone":"+34 917 38 10 08",
    "sg:postcode":"28035",
    "sg:province":"Madrid",
    "wof:name":"Villa Bordallo Emilio",
    "wof:placetype":"venue"
},
  "geometry": {"coordinates":[-3.7211968899,40.4797134399],"type":"Point"}
}