{
  "type": "Feature",
  "properties": {
    "addr:full":"Calle de Carmen, 6 Bujalance C\u00f3rdoba 14650",
    "addr:housenumber":"6",
    "addr:postcode":"14650",
    "addr:street":"Calle De Carmen",
    "iso:country":"ES",
    "sg:address":"Calle de Carmen, 6",
    "sg:city":"Bujalance",
    "sg:orig_category":"Molduras, Junquillos, Listones Y Molduras Perforadas",
    "sg:phone":"+34 957 17 07 54",
    "sg:postcode":"14650",
    "sg:province":"C\u00f3rdoba",
    "wof:name":"Toledano Mu\u00f1oz Martin",
    "wof:placetype":"venue"
},
  "geometry": {"coordinates":[-4.3842849731,37.8983917236],"type":"Point"}
}