{
  "type": "Feature",
  "properties": {
    "iso:country":"ES",
    "sg:address":"Carrer de Catalunya, 20",
    "sg:city":"Granollers",
    "sg:orig_category":"Centros Empresariales",
    "sg:phone":"+34 938 70 49 66",
    "sg:postcode":"08401",
    "sg:province":"Barcelona",
    "wof:name":"Marprim S.l.",
    "wof:placetype":"venue"
},
  "geometry": {"coordinates":[2.2870819569,41.6101226807],"type":"Point"}
}