{
  "type": "Feature",
  "properties": {
    "iso:country":"ES",
    "sg:address":"Ctra De Caceres(p I Las Arenas), Km. 0006,6",
    "sg:city":"Malpartida Caceres",
    "sg:orig_category":"Ense\u00d1anza, Formaci\u00d3n Profesional: Aprendizaje",
    "sg:phone":"+34 927 27 63 83",
    "sg:postcode":"10910",
    "sg:province":"C\u00e1ceres",
    "wof:name":"Servicio Extreme\u00d1o De Salud",
    "wof:placetype":"venue"
},
  "geometry": {"coordinates":[-6.5076742172,39.4432449341],"type":"Point"}
}