{
  "type": "Feature",
  "properties": {
    "addr:full":"Cmno Almendros, S/n Villarrubia Santiago Toledo 45360",
    "addr:housenumber":"/ n",
    "addr:postcode":"45360",
    "addr:street":"Cmno Almendros S;Villarrubia",
    "iso:country":"ES",
    "sg:address":"Cmno Almendros, S/n",
    "sg:city":"Villarrubia Santiago",
    "sg:orig_category":"Ba\u00d1os Y Duchas P\u00dablicos",
    "sg:phone":"+34 925 15 06 00",
    "sg:postcode":"45360",
    "sg:province":"Toledo",
    "wof:name":"Ayuntamiento De Villarrubia De Santiago",
    "wof:placetype":"venue"
},
  "geometry": {"coordinates":[-3.3680739403,39.9837913513],"type":"Point"}
}