{
  "type": "Feature",
  "properties": {
    "iso:country":"ES",
    "sg:address":"Avda Regne De Valencia, 17",
    "sg:city":"Valencia",
    "sg:orig_category":"Empresarios",
    "sg:phone":"+34 963 73 78 61",
    "sg:postcode":"46005",
    "sg:province":"Valencia",
    "wof:name":"Fundacion Pascual Tomas",
    "wof:placetype":"venue"
},
  "geometry": {"coordinates":[-0.3709850013,39.4645729065],"type":"Point"}
}