{
  "type": "Feature",
  "properties": {
    "addr:full":"Rua Carreira, 9 Cambados Pontevedra 36630",
    "addr:housenumber":"9",
    "addr:postcode":"36630",
    "addr:street":"Rua Carreira",
    "iso:country":"ES",
    "sg:address":"Rua Carreira, 9",
    "sg:city":"Cambados",
    "sg:orig_category":"Laboratorios Dentales",
    "sg:phone":"+34 986 52 40 15",
    "sg:postcode":"36630",
    "sg:province":"Pontevedra",
    "wof:name":"Servico Gallego De Prevencion De Riesgos Laborales S.l.",
    "wof:placetype":"venue"
},
  "geometry": {"coordinates":[-8.8134145737,42.5211257935],"type":"Point"}
}