{
  "type": "Feature",
  "properties": {
    "iso:country":"ES",
    "sg:address":"Calle de Santa Amalia, 3",
    "sg:city":"Teruel",
    "sg:orig_category":"Molduras, Junquillos, Listones Y Molduras Perforadas",
    "sg:phone":"+34 978 61 16 54",
    "sg:postcode":"44003",
    "sg:province":"Teruel",
    "wof:name":"Alba Ruz Jose",
    "wof:placetype":"venue"
},
  "geometry": {"coordinates":[-1.1110663414,40.349395752],"type":"Point"}
}