{
  "type": "Feature",
  "properties": {
    "iso:country":"ES",
    "sg:address":"Avda Juan Xxiii, 2",
    "sg:city":"Logro\u00f1o",
    "sg:orig_category":"Bordado, Marcado A Medida",
    "sg:phone":"+34 941 24 83 99",
    "sg:postcode":"26003",
    "sg:province":"La Rioja",
    "wof:name":"Bordados Cadetor S.l.",
    "wof:placetype":"venue"
},
  "geometry": {"coordinates":[-2.4419898987,42.4648208618],"type":"Point"}
}