{
  "type": "Feature",
  "properties": {
    "addr:full":"Carrer de Clot, 141 Barcelona Barcelona 08026",
    "addr:housenumber":"141",
    "addr:postcode":"08026",
    "addr:street":"Carrer De Clot",
    "iso:country":"ES",
    "sg:address":"Carrer de Clot, 141",
    "sg:city":"Barcelona",
    "sg:orig_category":"\u00d3ptica: Instrumentos (fabricaci\u00d3n)",
    "sg:phone":"+34 932 46 65 43",
    "sg:postcode":"08026",
    "sg:province":"Barcelona",
    "wof:name":"Martinez Montesinos Angel",
    "wof:placetype":"venue"
},
  "geometry": {"coordinates":[2.189563036,41.4116973877],"type":"Point"}
}