{
  "type": "Feature",
  "properties": {
    "addr:full":"Ctra Circunvalacion, S/n Benidorm Alicante 03500",
    "addr:postcode":"03500",
    "addr:street":"Ctra Circunvalacion S / N",
    "iso:country":"ES",
    "sg:address":"Ctra Circunvalacion, S/n",
    "sg:city":"Benidorm",
    "sg:orig_category":"Confecci\u00d3n De Trajes Para Se\u00d1oras",
    "sg:phone":"+34 965 85 89 19",
    "sg:postcode":"03500",
    "sg:province":"Alicante",
    "wof:name":"Leyva Romero Francisca",
    "wof:placetype":"venue"
},
  "geometry": {"coordinates":[-0.1740590036,38.5364303589],"type":"Point"}
}