{
  "type": "Feature",
  "properties": {
    "addr:full":"Calle de Sierra Bermeja, S/n Madrid Madrid 28018",
    "addr:housenumber":"s / n",
    "addr:postcode":"28018",
    "addr:street":"Calle De Sierra Bermeja",
    "iso:country":"ES",
    "sg:address":"Calle de Sierra Bermeja, S/n",
    "sg:city":"Madrid",
    "sg:orig_category":"Edici\u00d3n De Diarios, Revistas, Boletines",
    "sg:phone":"+34 914 78 50 09",
    "sg:postcode":"28018",
    "sg:province":"Madrid",
    "wof:name":"Quicios Millan Felicia",
    "wof:placetype":"venue"
},
  "geometry": {"coordinates":[-3.6615419388,40.3901939392],"type":"Point"}
}