{
  "type": "Feature",
  "properties": {
    "iso:country":"ES",
    "sg:address":"Ptda Serratella, 45",
    "sg:city":"Canals",
    "sg:orig_category":"M\u00c1rmoles, Granitos Y Piedras Naturales",
    "sg:phone":"+34 962 24 08 96",
    "sg:postcode":"46650",
    "sg:province":"Valencia",
    "wof:name":"Gomez Grau S.l.",
    "wof:placetype":"venue"
},
  "geometry": {"coordinates":[-0.5920026898,38.9339981079],"type":"Point"}
}