{
  "type": "Feature",
  "properties": {
    "iso:country":"ES",
    "sg:address":"Urb Coto De San Isidro, S/n",
    "sg:city":"Ituero Y Lama",
    "sg:orig_category":"Grafistas",
    "sg:phone":"+34 921 19 86 83",
    "sg:postcode":"40151",
    "sg:province":"Segovia",
    "wof:name":"Pharly Inversiones S.l.",
    "wof:placetype":"venue"
},
  "geometry": {"coordinates":[-4.3741078377,40.7903556824],"type":"Point"}
}