{
  "type": "Feature",
  "properties": {
    "addr:full":"Cra. Medi\u00f1a A Cornella, Km. 0001,0 Medinya Girona 17482",
    "addr:postcode":"17482",
    "addr:street":"Cornella Km. 0001,0 Medinya",
    "iso:country":"ES",
    "sg:address":"Cra. Medi\u00f1a A Cornella, Km. 0001,0",
    "sg:city":"Medinya",
    "sg:orig_category":"Poller\u00cda Y Caza (al Por Menor)",
    "sg:phone":"+34 972 49 81 27",
    "sg:postcode":"17482",
    "sg:province":"Girona",
    "wof:name":"Granja Avicola Tarradas S.l.",
    "wof:placetype":"venue"
},
  "geometry": {"coordinates":[2.8702967167,42.0490531921],"type":"Point"}
}