{
  "type": "Feature",
  "properties": {
    "addr:full":"Montecasino, 1 Campillos M\u00e1laga 29320",
    "addr:housenumber":"1",
    "addr:postcode":"29320",
    "addr:street":"Montecasino",
    "iso:country":"ES",
    "sg:address":"Montecasino, 1",
    "sg:city":"Campillos",
    "sg:orig_category":"Contenedores Para Transporte De Mercanc\u00cdas",
    "sg:phone":"+34 952 72 29 72",
    "sg:postcode":"29320",
    "sg:province":"M\u00e1laga",
    "wof:name":"Valle-98 S.l.",
    "wof:placetype":"venue"
},
  "geometry": {"coordinates":[-4.8634610176,37.0531158447],"type":"Point"}
}