{
  "type": "Feature",
  "properties": {
    "addr:full":"Vicente Conca Blasco, 44 Benejama Alicante 03460",
    "addr:housenumber":"44",
    "addr:postcode":"03460",
    "addr:street":"Blasco",
    "iso:country":"ES",
    "sg:address":"Vicente Conca Blasco, 44",
    "sg:city":"Benejama",
    "sg:orig_category":"Ebanister\u00cda",
    "sg:phone":"+34 965 82 21 00",
    "sg:postcode":"03460",
    "sg:province":"Alicante",
    "wof:name":"Conca Gracia Daniel",
    "wof:placetype":"venue"
},
  "geometry": {"coordinates":[-0.7665590048,38.7039909363],"type":"Point"}
}