{
  "type": "Feature",
  "properties": {
    "iso:country":"ES",
    "sg:address":"Carrer de Pallars, 232",
    "sg:city":"Barcelona",
    "sg:orig_category":"Muebles Y Accesorios Para Cocinas Y Cuartos De Ba\u00d1o (al Por Menor)",
    "sg:phone":"+34 933 00 32 57",
    "sg:postcode":"08005",
    "sg:province":"Barcelona",
    "wof:name":"Cocinas Plaza S.l",
    "wof:placetype":"venue"
},
  "geometry": {"coordinates":[2.2002429962,41.4028205872],"type":"Point"}
}