{
  "type": "Feature",
  "properties": {
    "addr:full":"Plaz Fosal, 1 Olite Navarra 31390",
    "addr:housenumber":"1",
    "addr:postcode":"31390",
    "addr:street":"Plaz Fosal",
    "iso:country":"ES",
    "sg:address":"Plaz Fosal, 1",
    "sg:city":"Olite",
    "sg:orig_category":"Farmacias",
    "sg:phone":"+34 948 74 18 30",
    "sg:postcode":"31390",
    "sg:province":"Navarra",
    "wof:name":"Pellejero Balduz Maria Jose",
    "wof:placetype":"venue"
},
  "geometry": {"coordinates":[-1.6518290043,42.4796409607],"type":"Point"}
}