{
  "type": "Feature",
  "properties": {
    "addr:full":"Calle de Manuel De Falla, 29 Herencia Ciudad Real 13640",
    "addr:housenumber":"29",
    "addr:postcode":"13640",
    "addr:street":"Calle De Manuel De Falla",
    "iso:country":"ES",
    "sg:address":"Calle de Manuel De Falla, 29",
    "sg:city":"Herencia",
    "sg:orig_category":"Inform\u00c1tica: Material Y Suministros",
    "sg:phone":"+34 926 57 25 36",
    "sg:postcode":"13640",
    "sg:province":"Ciudad Real",
    "sg:website":"www.nuevopc.com",
    "wof:name":"Neo Computers S.l.u.",
    "wof:placetype":"venue"
},
  "geometry": {"coordinates":[-3.3505239487,39.3685951233],"type":"Point"}
}