{
  "type": "Feature",
  "properties": {
    "addr:full":"Ctra Corte De Peleas, 71 Badajoz Badajoz 06009",
    "addr:housenumber":"71",
    "addr:postcode":"06009",
    "addr:street":"Ctra Corte De Peleas",
    "iso:country":"ES",
    "sg:address":"Ctra Corte De Peleas, 71",
    "sg:city":"Badajoz",
    "sg:classifiers":[
        {
            "category":"Autos & Motor Vehicles",
            "subcategory":"Automobile Sales",
            "type":"Retail Goods"
        }
    ],
    "sg:phone":"+34 924 26 13 14",
    "sg:postcode":"06009",
    "sg:province":"Badajoz",
    "wof:name":"Autoescuela Dario S.l.",
    "wof:placetype":"venue"
},
  "geometry": {"coordinates":[-6.9572229385,38.876411438],"type":"Point"}
}