{
  "type": "Feature",
  "properties": {
    "addr:full":"Avda Joaquin Loriga, 1 Agolada Pontevedra 36520",
    "addr:housenumber":"1",
    "addr:postcode":"36520",
    "addr:street":"Avda Joaquin Loriga",
    "iso:country":"ES",
    "sg:address":"Avda Joaquin Loriga, 1",
    "sg:city":"Agolada",
    "sg:orig_category":"Empresas De Electricidad En General",
    "sg:phone":"+34 986 78 80 22",
    "sg:postcode":"36520",
    "sg:province":"Pontevedra",
    "wof:name":"Meijide Mendez Fernando",
    "wof:placetype":"venue"
},
  "geometry": {"coordinates":[-8.01902771,42.7635345459],"type":"Point"}
}