{
  "type": "Feature",
  "properties": {
    "iso:country":"ES",
    "sg:address":"Calle de Uria, 9",
    "sg:city":"Oviedo",
    "sg:orig_category":"\u00d3ptica: Instrumentos (fabricaci\u00d3n)",
    "sg:phone":"+34 985 23 89 10",
    "sg:postcode":"33003",
    "sg:province":"Asturias",
    "wof:name":"Optica 2000 S.l.",
    "wof:placetype":"venue"
},
  "geometry": {"coordinates":[-5.8518028259,43.3642082214],"type":"Point"}
}