{
  "type": "Feature",
  "properties": {
    "iso:country":"ES",
    "sg:address":"Urb Cala Salions, S/n",
    "sg:city":"Salions",
    "sg:orig_category":"Asociaciones Y Clubs Deportivos",
    "sg:phone":"+34 972 34 24 50",
    "sg:postcode":"17320",
    "sg:province":"Girona",
    "wof:name":"Club Nautico Cala Salions",
    "wof:placetype":"venue"
},
  "geometry": {"coordinates":[2.9606289864,41.747795105],"type":"Point"}
}