{
  "type": "Feature",
  "properties": {
    "iso:country":"ES",
    "sg:address":"Carrer de Lope De Vega, 1",
    "sg:city":"Sitges",
    "sg:orig_category":"Molduras, Junquillos, Listones Y Molduras Perforadas",
    "sg:phone":"+34 938 94 37 93",
    "sg:postcode":"08870",
    "sg:province":"Barcelona",
    "wof:name":"Camps Olle Andres",
    "wof:placetype":"venue"
},
  "geometry": {"coordinates":[1.813945055,41.2390327454],"type":"Point"}
}