{
  "type": "Feature",
  "properties": {
    "addr:full":"Calle de Marques De Villores, 10 Albacete Albacete 02001",
    "addr:housenumber":"10",
    "addr:postcode":"02001",
    "addr:street":"Calle De Marques De Villores",
    "iso:country":"ES",
    "sg:address":"Calle de Marques De Villores, 10",
    "sg:city":"Albacete",
    "sg:orig_category":"C\u00c1maras De Comercio E Industria, Oficios, Agricultura",
    "sg:phone":"+34 967 23 82 24",
    "sg:postcode":"02001",
    "sg:province":"Albacete",
    "wof:name":"Junta De Comunidades Castilla-la Mancha",
    "wof:placetype":"venue"
},
  "geometry": {"coordinates":[-1.8570940495,38.9922103882],"type":"Point"}
}