{
  "type": "Feature",
  "properties": {
    "addr:full":"Calle de Jovellanos, 11 Oviedo Asturias 33003",
    "addr:housenumber":"11",
    "addr:postcode":"33003",
    "addr:street":"Calle De Jovellanos",
    "iso:country":"ES",
    "sg:address":"Calle de Jovellanos, 11",
    "sg:city":"Oviedo",
    "sg:orig_category":"Ense\u00d1anza, Formaci\u00d3n Profesional: Aprendizaje",
    "sg:phone":"+34 985 22 97 48",
    "sg:postcode":"33003",
    "sg:province":"Asturias",
    "wof:name":"Principado De Asturias",
    "wof:placetype":"venue"
},
  "geometry": {"coordinates":[-5.843100071,43.3635864258],"type":"Point"}
}