{
  "type": "Feature",
  "properties": {
    "iso:country":"ES",
    "sg:address":"Calle de Balendin Berriotxoa, 15",
    "sg:city":"Basauri",
    "sg:orig_category":"Droguer\u00cdas (al Por Menor)",
    "sg:phone":"+34 944 02 88 91",
    "sg:postcode":"48970",
    "sg:province":"Vizcaya",
    "wof:name":"Javier Martinez Sainz",
    "wof:placetype":"venue"
},
  "geometry": {"coordinates":[-2.8833613396,43.2360191345],"type":"Point"}
}