{
  "type": "Feature",
  "properties": {
    "iso:country":"ES",
    "sg:address":"La Posada, 2",
    "sg:city":"Fuensavi\u00f1an",
    "sg:orig_category":"Molduras, Junquillos, Listones Y Molduras Perforadas",
    "sg:phone":"+34 949 82 82 98",
    "sg:postcode":"19268",
    "sg:province":"Guadalajara",
    "wof:name":"Peral Ferrero Concha",
    "wof:placetype":"venue"
},
  "geometry": {"coordinates":[-2.5828828812,40.9647369385],"type":"Point"}
}