{
  "type": "Feature",
  "properties": {
    "addr:full":"Plaz Espa\u00d1a, 9 Badajoz Badajoz 06002",
    "addr:housenumber":"9",
    "addr:postcode":"06002",
    "addr:street":"Plaz Espan\u0303A",
    "iso:country":"ES",
    "sg:address":"Plaz Espa\u00d1a, 9",
    "sg:city":"Badajoz",
    "sg:orig_category":"Centros P\u00dablicos De Formaci\u00d3n Profesional Y T\u00c9cnica",
    "sg:phone":"+34 924 22 42 64",
    "sg:postcode":"06002",
    "sg:province":"Badajoz",
    "wof:name":"Colegio Oficial De Secretarios Interventores Y Depositarios Administracion Local",
    "wof:placetype":"venue"
},
  "geometry": {"coordinates":[-6.9704060555,38.8780937195],"type":"Point"}
}