{
  "type": "Feature",
  "properties": {
    "iso:country":"ES",
    "sg:address":"Avda Andalucia, 5",
    "sg:city":"Palmones",
    "sg:orig_category":"Sales (al Por Mayor)",
    "sg:phone":"+34 956 67 78 17",
    "sg:postcode":"11379",
    "sg:province":"C\u00e1diz",
    "wof:name":"Hijos De Sanchez Lara S.l.",
    "wof:placetype":"venue"
},
  "geometry": {"coordinates":[-5.4402542114,36.1763267517],"type":"Point"}
}