{
  "type": "Feature",
  "properties": {
    "addr:full":"Rego Do Campo, 44 Pontes Garcia Rodriguez La Coru\u00f1a 15320",
    "addr:housenumber":"44",
    "addr:postcode":"15320",
    "addr:street":"Campo;Corun\u0303A",
    "iso:country":"ES",
    "sg:address":"Rego Do Campo, 44",
    "sg:city":"Pontes Garcia Rodriguez",
    "sg:orig_category":"Electrodom\u00c9sticos (al Por Menor)",
    "sg:phone":"+34 981 45 19 18",
    "sg:postcode":"15320",
    "sg:province":"La Coru\u00f1a",
    "wof:name":"Javier Cocinas Y Ba\u00f1o S.l.",
    "wof:placetype":"venue"
},
  "geometry": {"coordinates":[-7.8553490639,43.452495575],"type":"Point"}
}