{
  "type": "Feature",
  "properties": {
    "addr:full":"Trav Corts, 371 Barcelona Barcelona 08029",
    "addr:housenumber":"371",
    "addr:postcode":"08029",
    "addr:street":"Trav Corts",
    "iso:country":"ES",
    "sg:address":"Trav Corts, 371",
    "sg:city":"Barcelona",
    "sg:orig_category":"Inmobiliaria (agencias)",
    "sg:phone":"+34 934 30 78 99",
    "sg:postcode":"08029",
    "sg:province":"Barcelona",
    "wof:name":"Inmo Catacor S.l.",
    "wof:placetype":"venue"
},
  "geometry": {"coordinates":[2.14041996,41.390083313],"type":"Point"}
}