{
  "type": "Feature",
  "properties": {
    "iso:country":"ES",
    "sg:address":"Calle de Campomanes, 26",
    "sg:city":"Oviedo",
    "sg:orig_category":"Arquitectos",
    "sg:phone":"+34 985 21 73 85",
    "sg:postcode":"33008",
    "sg:province":"Asturias",
    "wof:name":"Alonso Diaz Jose Ramon",
    "wof:placetype":"venue"
},
  "geometry": {"coordinates":[-5.8474125862,43.3577728271],"type":"Point"}
}