{
  "type": "Feature",
  "properties": {
    "iso:country":"ES",
    "sg:address":"Cno. Cementerio, 18",
    "sg:city":"Alfajarin",
    "sg:orig_category":"Fabricaci\u00d3n De Harinas, S\u00c9molas, Productos De Elaboraci\u00d3n Del Grano",
    "sg:phone":"+34 976 10 11 77",
    "sg:postcode":"50172",
    "sg:province":"Zaragoza",
    "wof:name":"Alfajarin Agricola S. L.",
    "wof:placetype":"venue"
},
  "geometry": {"coordinates":[-0.6992288232,41.6113586426],"type":"Point"}
}