{
  "type": "Feature",
  "properties": {
    "iso:country":"ES",
    "sg:address":"Avda Alcora, 1",
    "sg:city":"Ribesalbes",
    "sg:orig_category":"Supermercados Y Hipermercados",
    "sg:phone":"+34 964 62 52 51",
    "sg:postcode":"12210",
    "sg:province":"Castell\u00f3n",
    "wof:name":"Oset Edo Jose",
    "wof:placetype":"venue"
},
  "geometry": {"coordinates":[-0.2734799981,40.0295410156],"type":"Point"}
}