{
  "type": "Feature",
  "properties": {
    "addr:full":"Calle de Socrates, 15 Pto. Rosario Las Palmas 35600",
    "addr:housenumber":"15",
    "addr:postcode":"35600",
    "addr:street":"Calle De Socrates;Pto. Rosario Las",
    "iso:country":"ES",
    "sg:address":"Calle de Socrates, 15",
    "sg:city":"Pto. Rosario",
    "sg:orig_category":"Comercio, Reparaci\u00d3n De Motocicletas, Bicicletas Y Piezas Sueltas",
    "sg:phone":"+34 928 85 82 83",
    "sg:postcode":"35600",
    "sg:province":"Las Palmas",
    "wof:name":"Fuertemotor S.l.",
    "wof:placetype":"venue"
},
  "geometry": {"coordinates":[-13.8632440567,28.5024089813],"type":"Point"}
}