{
  "type": "Feature",
  "properties": {
    "addr:full":"Carrer de Espanya, 6 Colonia Argentina Barcelona 08390",
    "addr:housenumber":"6",
    "addr:postcode":"08390",
    "addr:street":"Carrer De Espanya;Barcelona",
    "iso:country":"ES",
    "sg:address":"Carrer de Espanya, 6",
    "sg:city":"Colonia Argentina",
    "sg:orig_category":"Cajas De Ahorro",
    "sg:phone":"+34 934 69 26 65",
    "sg:postcode":"08390",
    "sg:province":"Barcelona",
    "wof:name":"Caixa D'estalvis De Catalunya",
    "wof:placetype":"venue"
},
  "geometry": {"coordinates":[2.2786700726,41.4704208374],"type":"Point"}
}