{
  "type": "Feature",
  "properties": {
    "addr:full":"Carrer de Marques, 10 Coll De'n Rabassa Islas Baleares 07007",
    "addr:housenumber":"10",
    "addr:postcode":"07007",
    "addr:street":"Carrer De Marques",
    "iso:country":"ES",
    "sg:address":"Carrer de Marques, 10",
    "sg:city":"Coll De'n Rabassa",
    "sg:orig_category":"Internados & Ense\u00d1anza Privada",
    "sg:phone":"+34 971 26 26 95",
    "sg:postcode":"07007",
    "sg:province":"Islas Baleares",
    "wof:name":"Hermanas De La Caridad",
    "wof:placetype":"venue"
},
  "geometry": {"coordinates":[2.9117100239,39.6136398315],"type":"Point"}
}