{
  "type": "Feature",
  "properties": {
    "iso:country":"ES",
    "sg:address":"Poli Olibet, 5",
    "sg:city":"Errenteria",
    "sg:orig_category":"Asociaciones Y Clubs Deportivos",
    "sg:phone":"+34 943 51 37 67",
    "sg:postcode":"20100",
    "sg:province":"Guip\u00f9zcoa",
    "wof:name":"Sociedad Deportiva Cultural Lagunak",
    "wof:placetype":"venue"
},
  "geometry": {"coordinates":[-1.8996850252,43.314365387],"type":"Point"}
}