{
  "type": "Feature",
  "properties": {
    "iso:country":"ES",
    "sg:address":"Carr Mar, De La, 30",
    "sg:city":"Son Servera",
    "sg:orig_category":"Ingenier\u00cda, Centros De Estudios (diversos)",
    "sg:phone":"+34 971 81 74 53",
    "sg:postcode":"07550",
    "sg:province":"Islas Baleares",
    "wof:name":"Consulting Balear De Ingenieria S.l.",
    "wof:placetype":"venue"
},
  "geometry": {"coordinates":[3.3548560143,39.6253509521],"type":"Point"}
}