{
  "type": "Feature",
  "properties": {
    "iso:country":"ES",
    "sg:address":"Calle de Mora, 1",
    "sg:city":"Jerez De La Frontera",
    "sg:orig_category":"Inform\u00c1tica Equipo Y Programas (al Por Mayor)",
    "sg:phone":"+34 956 18 21 34",
    "sg:postcode":"11402",
    "sg:province":"C\u00e1diz",
    "sg:website":"www.wperito.com",
    "wof:name":"Informatica De Gestion Pericial S.l.l.",
    "wof:placetype":"venue"
},
  "geometry": {"coordinates":[-6.1358509064,36.6848831177],"type":"Point"}
}