{
  "type": "Feature",
  "properties": {
    "addr:full":"Calle de Javier De Miguel, 5 Madrid Madrid 28018",
    "addr:housenumber":"5",
    "addr:postcode":"28018",
    "addr:street":"Calle De Javier De Miguel",
    "iso:country":"ES",
    "sg:address":"Calle de Javier De Miguel, 5",
    "sg:city":"Madrid",
    "sg:orig_category":"Molduras, Junquillos, Listones Y Molduras Perforadas",
    "sg:phone":"+34 914 78 63 53",
    "sg:postcode":"28018",
    "sg:province":"Madrid",
    "wof:name":"Pedro E.gomez Barrio Y Jesus Arribas Gonzalez C.b",
    "wof:placetype":"venue"
},
  "geometry": {"coordinates":[-3.663752079,40.3890686035],"type":"Point"}
}