{
  "type": "Feature",
  "properties": {
    "iso:country":"ES",
    "sg:address":"Calle de Sancha De Lara, 13",
    "sg:city":"Malaga",
    "sg:orig_category":"M\u00c9dicos: Ginecolog\u00cda Y Obstetricia",
    "sg:phone":"+34 952 22 93 07",
    "sg:postcode":"29015",
    "sg:province":"M\u00e1laga",
    "wof:name":"Calderon Ruiz Olga",
    "wof:placetype":"venue"
},
  "geometry": {"coordinates":[-4.4201908112,36.7190322876],"type":"Point"}
}