{
  "type": "Feature",
  "properties": {
    "iso:country":"ES",
    "sg:address":"Carrer de Rafael De Casanova, 52",
    "sg:city":"Molins Rei",
    "sg:orig_category":"Fabricaci\u00d3n De Cortinas Y Visillos",
    "sg:phone":"+34 936 68 48 27",
    "sg:postcode":"08750",
    "sg:province":"Barcelona",
    "wof:name":"Nohales I Casain S.l.",
    "wof:placetype":"venue"
},
  "geometry": {"coordinates":[2.0164759159,41.4123344421],"type":"Point"}
}