{
  "type": "Feature",
  "properties": {
    "addr:full":"Calle de Leonardo Torres Quevedo, S/n Santander Cantabria 39011",
    "addr:housenumber":"s / n",
    "addr:postcode":"39011",
    "addr:street":"Calle De Leonardo Torres Quevedo",
    "iso:country":"ES",
    "sg:address":"Calle de Leonardo Torres Quevedo, S/n",
    "sg:city":"Santander",
    "sg:orig_category":"Ense\u00d1anza Secundaria: Colegios Y Escuelas Privadas",
    "sg:phone":"+34 942 33 62 22",
    "sg:postcode":"39011",
    "sg:province":"Cantabria",
    "wof:name":"Instituto De Educacion Secundaria Leonardo Torres Quevedo",
    "wof:placetype":"venue"
},
  "geometry": {"coordinates":[-3.8379540443,43.4573097229],"type":"Point"}
}