{
  "type": "Feature",
  "properties": {
    "iso:country":"ES",
    "sg:address":"Calle de Badajoz, 1",
    "sg:city":"Bilbao",
    "sg:orig_category":"Molduras, Junquillos, Listones Y Molduras Perforadas",
    "sg:phone":"+34 944 47 72 12",
    "sg:postcode":"48015",
    "sg:province":"Vizcaya",
    "wof:name":"Sanchez Pulido Fernando",
    "wof:placetype":"venue"
},
  "geometry": {"coordinates":[-2.9610483646,43.2821731567],"type":"Point"}
}