{
  "type": "Feature",
  "properties": {
    "iso:country":"ES",
    "sg:address":"Calle de Pages Del Corro, 150",
    "sg:city":"Sevilla",
    "sg:orig_category":"M\u00c9dicos: Ginecolog\u00cda Y Obstetricia",
    "sg:phone":"+34 954 27 14 76",
    "sg:postcode":"41010",
    "sg:province":"Sevilla",
    "wof:name":"Barranco Moreno Jose Carlos",
    "wof:placetype":"venue"
},
  "geometry": {"coordinates":[-6.0004878044,37.3812980652],"type":"Point"}
}