{
  "type": "Feature",
  "properties": {
    "addr:full":"Av. Can Font (can Font), 43 Can Font I Ca N'avellaneda Barcelona 08211",
    "addr:postcode":"08211",
    "addr:street":"Av. Can Font;Ca N'Avellaneda",
    "iso:country":"ES",
    "sg:address":"Av. Can Font (can Font), 43",
    "sg:city":"Can Font I Ca N'avellaneda",
    "sg:orig_category":"Fabricaci\u00d3n De Motores El\u00c9ctricos",
    "sg:phone":"+34 937 14 82 03",
    "sg:postcode":"08211",
    "sg:province":"Barcelona",
    "wof:name":"Electromecanica Ferrando S.l.",
    "wof:placetype":"venue"
},
  "geometry": {"coordinates":[2.0566551685,41.5993080139],"type":"Point"}
}