{
  "type": "Feature",
  "properties": {
    "addr:full":"Calle de Escorial, 1 Majadahonda Madrid 28220",
    "addr:housenumber":"1",
    "addr:postcode":"28220",
    "addr:street":"Calle De Escorial",
    "iso:country":"ES",
    "sg:address":"Calle de Escorial, 1",
    "sg:city":"Majadahonda",
    "sg:orig_category":"Molduras, Junquillos, Listones Y Molduras Perforadas",
    "sg:phone":"+34 916 34 15 60",
    "sg:postcode":"28220",
    "sg:province":"Madrid",
    "wof:name":"Ugia Gimenez Santiago",
    "wof:placetype":"venue"
},
  "geometry": {"coordinates":[-3.8758010864,40.4731521606],"type":"Point"}
}