{
  "type": "Feature",
  "properties": {
    "iso:country":"ES",
    "sg:address":"Calle de Hermosilla, 43",
    "sg:city":"Madrid",
    "sg:orig_category":"Ropa Para Se\u00d1oras (al Por Menor)",
    "sg:phone":"+34 914 35 32 09",
    "sg:postcode":"28001",
    "sg:province":"Madrid",
    "sg:website":"www.theextremecollection.com",
    "wof:name":"Garcia Magari\u00f1os Jorge",
    "wof:placetype":"venue"
},
  "geometry": {"coordinates":[-3.6829180717,40.4264183044],"type":"Point"}
}