{
  "type": "Feature",
  "properties": {
    "addr:full":"Plaz Musico Albeniz, 2 Valencia Valencia 46010",
    "addr:housenumber":"2",
    "addr:postcode":"46010",
    "addr:street":"Plaz Musico Albeniz",
    "iso:country":"ES",
    "sg:address":"Plaz Musico Albeniz, 2",
    "sg:city":"Valencia",
    "sg:orig_category":"Asesor\u00cdas Y Estudios Financieros",
    "sg:phone":"+34 963 60 47 60",
    "sg:postcode":"46010",
    "sg:province":"Valencia",
    "wof:name":"Marin Lasalle Felipe",
    "wof:placetype":"venue"
},
  "geometry": {"coordinates":[-0.3637979925,39.4838523865],"type":"Point"}
}