{
  "type": "Feature",
  "properties": {
    "addr:full":"Carrer de Aulestia I Pijoan, 15 Barcelona Barcelona 08012",
    "addr:housenumber":"15",
    "addr:postcode":"08012",
    "addr:street":"Carrer De Aulestia;Pijoan",
    "iso:country":"ES",
    "sg:address":"Carrer de Aulestia I Pijoan, 15",
    "sg:city":"Barcelona",
    "sg:orig_category":"Fabricaci\u00d3n De Sobres, Bolsas Y Fundas",
    "sg:phone":"+34 932 37 74 76",
    "sg:postcode":"08012",
    "sg:province":"Barcelona",
    "sg:website":"www.rtc-optica.com",
    "wof:name":"Creaciones R.t.c.s.a.",
    "wof:placetype":"venue"
},
  "geometry": {"coordinates":[2.1510109901,41.402759552],"type":"Point"}
}