{
  "type": "Feature",
  "properties": {
    "addr:full":"Calle de Molino (el), 29 Caudete Albacete 02660",
    "addr:postcode":"02660",
    "addr:street":"Calle De Molino El",
    "iso:country":"ES",
    "sg:address":"Calle de Molino (el), 29",
    "sg:city":"Caudete",
    "sg:orig_category":"Hielo Artificial (fabricaci\u00d3n, Distribuci\u00d3n)",
    "sg:phone":"+34 965 82 52 39",
    "sg:postcode":"02660",
    "sg:province":"Albacete",
    "wof:name":"Bodegas La Goleta S.l.",
    "wof:placetype":"venue"
},
  "geometry": {"coordinates":[-0.9875680208,38.7060432434],"type":"Point"}
}