{
  "type": "Feature",
  "properties": {
    "iso:country":"ES",
    "sg:address":"Calle de Bachiller Sanson Carrasco, 9",
    "sg:city":"Salamanca",
    "sg:orig_category":"Mec\u00c1nico Del Autom\u00d3vil",
    "sg:phone":"+34 923 22 84 98",
    "sg:postcode":"37006",
    "sg:province":"Salamanca",
    "wof:name":"F 1 Mecanica Rapida S L",
    "wof:placetype":"venue"
},
  "geometry": {"coordinates":[-5.6713204384,40.9804115295],"type":"Point"}
}