{
  "type": "Feature",
  "properties": {
    "addr:full":"Avda Tolosa De, 87 Donostia-san Sebastian Guip\u00f9zcoa 20018",
    "addr:housenumber":"87",
    "addr:postcode":"20018",
    "addr:street":"Avda Tolosa De",
    "iso:country":"ES",
    "sg:address":"Avda Tolosa De, 87",
    "sg:city":"Donostia-san Sebastian",
    "sg:orig_category":"Asesor\u00cda Sobre Comunicaci\u00d3n De Empresas",
    "sg:phone":"+34 943 21 10 72",
    "sg:postcode":"20018",
    "sg:province":"Guip\u00f9zcoa",
    "wof:name":"Asinter Tres S.l.",
    "wof:placetype":"venue"
},
  "geometry": {"coordinates":[-2.0083413124,43.3071975708],"type":"Point"}
}