{
  "type": "Feature",
  "properties": {
    "iso:country":"ES",
    "sg:address":"Calle de San Martin, 35",
    "sg:city":"Algorta",
    "sg:orig_category":"Reparaci\u00d3n Y Restauraci\u00d3n De Objetos Diversos",
    "sg:phone":"+34 944 60 64 22",
    "sg:postcode":"48993",
    "sg:province":"Vizcaya",
    "wof:name":"Del Campo Lopez Berta",
    "wof:placetype":"venue"
},
  "geometry": {"coordinates":[-3.0129799843,43.3555412292],"type":"Point"}
}