{
  "type": "Feature",
  "properties": {
    "addr:full":"Calle de Lorenza Correa, 14 Malaga M\u00e1laga 29014",
    "addr:housenumber":"14",
    "addr:postcode":"29014",
    "addr:street":"Calle De Lorenza Correa;Ma\u0301Laga",
    "iso:country":"ES",
    "sg:address":"Calle de Lorenza Correa, 14",
    "sg:city":"Malaga",
    "sg:orig_category":"Laboratorios Y Trabajos De Fotograf\u00cda, V\u00cddeo Y Cine",
    "sg:phone":"+34 952 25 12 47",
    "sg:postcode":"29014",
    "sg:province":"M\u00e1laga",
    "wof:name":"Vera Guerrero Ana Maria",
    "wof:placetype":"venue"
},
  "geometry": {"coordinates":[-4.4225521088,36.7382507324],"type":"Point"}
}