{
  "type": "Feature",
  "properties": {
    "iso:country":"ES",
    "sg:address":"Avda Comuneros, 83",
    "sg:city":"Salamanca",
    "sg:orig_category":"M\u00c9dicos: Medicina Legal, Peritajes M\u00c9dicos",
    "sg:phone":"+34 923 18 07 18",
    "sg:postcode":"37003",
    "sg:province":"Salamanca",
    "wof:name":"Jose Alberto Gonzalez Peritaciones Medicas",
    "wof:placetype":"venue"
},
  "geometry": {"coordinates":[-5.6515221596,40.96875],"type":"Point"}
}