{
  "type": "Feature",
  "properties": {
    "iso:country":"ES",
    "sg:address":"Cra Cordoba-valencia-pi La Vicaria, S/n",
    "sg:city":"Puente Genave",
    "sg:orig_category":"Conservas De Legumbres (fabricaci\u00d3n, Al Por Mayor)",
    "sg:phone":"+34 953 43 52 52",
    "sg:postcode":"23350",
    "sg:province":"Ja\u00e9n",
    "wof:name":"Sdad Coop Andaluza -cortijo Del Gavilan-",
    "wof:placetype":"venue"
},
  "geometry": {"coordinates":[-2.8030788898,38.3562431335],"type":"Point"}
}