{
  "type": "Feature",
  "properties": {
    "addr:full":"Calle de Brocense, 2 Salamanca Salamanca 37002",
    "addr:housenumber":"2",
    "addr:postcode":"37002",
    "addr:street":"Calle De Brocense",
    "iso:country":"ES",
    "sg:address":"Calle de Brocense, 2",
    "sg:city":"Salamanca",
    "sg:orig_category":"Bisuter\u00cda, Joyer\u00cda, Relojer\u00cda (al Por Menor)",
    "sg:phone":"+34 923 21 65 14",
    "sg:postcode":"37002",
    "sg:province":"Salamanca",
    "wof:name":"Manacor S. L.",
    "wof:placetype":"venue"
},
  "geometry": {"coordinates":[-5.6640334129,40.9667892456],"type":"Point"}
}