{
  "type": "Feature",
  "properties": {
    "addr:full":"Carr Josep Maria Pellicer, 43 Centre Urba Girona 17500",
    "addr:housenumber":"43",
    "addr:postcode":"17500",
    "addr:street":"Carr Josep Maria Pellicer;Centre Urba",
    "iso:country":"ES",
    "sg:address":"Carr Josep Maria Pellicer, 43",
    "sg:city":"Centre Urba",
    "sg:orig_category":"Material Y Suministros Para Perforaciones, Sondeos",
    "sg:phone":"+34 972 70 19 62",
    "sg:postcode":"17500",
    "sg:province":"Girona",
    "wof:name":"Marty Vidal Juan",
    "wof:placetype":"venue"
},
  "geometry": {"coordinates":[2.1959049702,42.1965866089],"type":"Point"}
}