{
  "type": "Feature",
  "properties": {
    "iso:country":"ES",
    "sg:address":"Avda Navarra, 13",
    "sg:city":"Oyon-oion",
    "sg:orig_category":"Metalurgia",
    "sg:phone":"+34 945 60 13 34",
    "sg:postcode":"01320",
    "sg:province":"\u00c1lava",
    "wof:name":"Cespedes Astorga Maria Aquilina",
    "wof:placetype":"venue"
},
  "geometry": {"coordinates":[-2.4357419014,42.4969329834],"type":"Point"}
}