{
  "type": "Feature",
  "properties": {
    "addr:full":"Calle de Amor De Dios, 14 Sevilla Sevilla 41002",
    "addr:housenumber":"14",
    "addr:postcode":"41002",
    "addr:street":"Calle De Amor De Dios",
    "iso:country":"ES",
    "sg:address":"Calle de Amor De Dios, 14",
    "sg:city":"Sevilla",
    "sg:orig_category":"Art\u00cdculos De Decoraci\u00d3n",
    "sg:phone":"+34 954 91 51 94",
    "sg:postcode":"41002",
    "sg:province":"Sevilla",
    "wof:name":"Fernandez Fernandez Patricia",
    "wof:placetype":"venue"
},
  "geometry": {"coordinates":[-5.9946069717,37.3945617676],"type":"Point"}
}