{
  "type": "Feature",
  "properties": {
    "addr:full":"Cmno Ronda (de), 106 Granada Granada 18004",
    "addr:housenumber":"106",
    "addr:postcode":"18004",
    "addr:street":"Cmno Ronda De",
    "iso:country":"ES",
    "sg:address":"Cmno Ronda (de), 106",
    "sg:city":"Granada",
    "sg:orig_category":"Inmobiliaria (agencias)",
    "sg:phone":"+34 958 25 52 26",
    "sg:postcode":"18004",
    "sg:province":"Granada",
    "wof:name":"Construcciones Salvatierra S.l.",
    "wof:placetype":"venue"
},
  "geometry": {"coordinates":[-3.6078391075,37.1735534668],"type":"Point"}
}