{
  "type": "Feature",
  "properties": {
    "addr:full":"Calle de Virgen De Los Milagros, 114 Puerto De Santa Maria C\u00e1diz 11500",
    "addr:housenumber":"114",
    "addr:postcode":"11500",
    "addr:street":"Calle De Virgen De Los Milagros;Ca\u0301Diz",
    "iso:country":"ES",
    "sg:address":"Calle de Virgen De Los Milagros, 114",
    "sg:city":"Puerto De Santa Maria",
    "sg:orig_category":"Arquitectos",
    "sg:phone":"+34 956 85 58 71",
    "sg:postcode":"11500",
    "sg:province":"C\u00e1diz",
    "wof:name":"Rodriguez Rendon Tomas",
    "wof:placetype":"venue"
},
  "geometry": {"coordinates":[-6.2263121605,36.5983085632],"type":"Point"}
}