{
  "type": "Feature",
  "properties": {
    "addr:full":"Ctra Valls, 23 Vendrell Tarragona 43700",
    "addr:housenumber":"23",
    "addr:postcode":"43700",
    "addr:street":"Ctra Valls",
    "iso:country":"ES",
    "sg:address":"Ctra Valls, 23",
    "sg:city":"Vendrell",
    "sg:orig_category":"Mec\u00c1nico Del Autom\u00d3vil",
    "sg:phone":"+34 977 66 35 06",
    "sg:postcode":"43700",
    "sg:province":"Tarragona",
    "wof:name":"Tallers Jarama S.c.p.",
    "wof:placetype":"venue"
},
  "geometry": {"coordinates":[1.5371439457,41.2232971191],"type":"Point"}
}