{
  "type": "Feature",
  "properties": {
    "iso:country":"ES",
    "sg:address":"Calle de Doctor Juan De Padilla, 41",
    "sg:city":"Palmas De Gran Canaria",
    "sg:orig_category":"Agencias Y Agentes Comerciales, Representantes",
    "sg:phone":"+34 928 36 24 57",
    "sg:postcode":"35002",
    "sg:province":"Las Palmas",
    "wof:name":"Velazquez Estevez Diego",
    "wof:placetype":"venue"
},
  "geometry": {"coordinates":[-15.4190387726,28.1055202484],"type":"Point"}
}