{
  "type": "Feature",
  "properties": {
    "iso:country":"ES",
    "sg:address":"Roferos, 3",
    "sg:city":"Puerto Del Carmen",
    "sg:orig_category":"Ropa Para Ni\u00d1os (al Por Menor)",
    "sg:phone":"+34 928 51 10 07",
    "sg:postcode":"35510",
    "sg:province":"Las Palmas",
    "wof:name":"Gil Rodriguez Julia",
    "wof:placetype":"venue"
},
  "geometry": {"coordinates":[-13.6645021439,28.9277076721],"type":"Point"}
}