{
  "type": "Feature",
  "properties": {
    "iso:country":"ES",
    "sg:address":"Avda Buenos Aires, 45",
    "sg:city":"Lalin",
    "sg:orig_category":"Molduras, Junquillos, Listones Y Molduras Perforadas",
    "sg:phone":"+34 986 78 14 80",
    "sg:postcode":"36500",
    "sg:province":"Pontevedra",
    "wof:name":"Comunidad De Propietarios Del Edificio Costi\u00f1a",
    "wof:placetype":"venue"
},
  "geometry": {"coordinates":[-8.1131591797,42.6578407288],"type":"Point"}
}