{
  "type": "Feature",
  "properties": {
    "iso:country":"ES",
    "sg:address":"Calle de Batalla De Clavijo, 39",
    "sg:city":"Le\u00f3n",
    "sg:orig_category":"Encuadernaci\u00d3n E Impresi\u00d3n De Folletos",
    "sg:phone":"+34 987 26 25 90",
    "sg:postcode":"24006",
    "sg:province":"Le\u00f3n",
    "wof:name":"Copelen S.l.",
    "wof:placetype":"venue"
},
  "geometry": {"coordinates":[-5.5605487823,42.5991096497],"type":"Point"}
}