{
  "type": "Feature",
  "properties": {
    "addr:full":"Calle de Maestro (el), S/n Villastar Teruel 44130",
    "addr:postcode":"44130",
    "addr:street":"Calle De Maestro El S / N",
    "iso:country":"ES",
    "sg:address":"Calle de Maestro (el), S/n",
    "sg:city":"Villastar",
    "sg:orig_category":"Centros De Educaci\u00d3n Especial",
    "sg:phone":"+34 978 68 03 20",
    "sg:postcode":"44130",
    "sg:province":"Teruel",
    "wof:name":"Diputacion General De Aragon",
    "wof:placetype":"venue"
},
  "geometry": {"coordinates":[-1.1515840292,40.2807159424],"type":"Point"}
}