{
  "type": "Feature",
  "properties": {
    "addr:full":"Ctra Granada Murcia, Km. 0176,0 Baza Granada 18800",
    "addr:postcode":"18800",
    "addr:street":"Ctra Granada Murcia Km. 0176,0",
    "iso:country":"ES",
    "sg:address":"Ctra Granada Murcia, Km. 0176,0",
    "sg:city":"Baza",
    "sg:orig_category":"Maquinaria Para Industrias Diversas",
    "sg:phone":"+34 958 86 08 19",
    "sg:postcode":"18800",
    "sg:province":"Granada",
    "wof:name":"Carretillas Baza S.l.",
    "wof:placetype":"venue"
},
  "geometry": {"coordinates":[-2.7704091072,37.4930038452],"type":"Point"}
}