{
  "type": "Feature",
  "properties": {
    "addr:full":"Carrer de Col.legi, 5 Terrassa Barcelona 08221",
    "addr:housenumber":"5",
    "addr:postcode":"08221",
    "addr:street":"Carrer De Col.Legi",
    "iso:country":"ES",
    "sg:address":"Carrer de Col.legi, 5",
    "sg:city":"Terrassa",
    "sg:orig_category":"Carnicer\u00cdas, Carnicer\u00cdas",
    "sg:phone":"+34 937 80 86 03",
    "sg:postcode":"08221",
    "sg:province":"Barcelona",
    "wof:name":"Marsol Burgos Javier",
    "wof:placetype":"venue"
},
  "geometry": {"coordinates":[2.0107779503,41.5605697632],"type":"Point"}
}