{
  "type": "Feature",
  "properties": {
    "addr:full":"Calle de Alemania, 9 Estacion M\u00e1laga 29580",
    "addr:housenumber":"9 estacion",
    "addr:postcode":"29580",
    "addr:street":"Calle De Alemania;Ma\u0301Laga",
    "iso:country":"ES",
    "sg:address":"Calle de Alemania, 9",
    "sg:city":"Estacion",
    "sg:orig_category":"Tapiceros Y Tapiceros",
    "sg:phone":"+34 952 42 46 71",
    "sg:postcode":"29580",
    "sg:province":"M\u00e1laga",
    "wof:name":"Galvez Gomez Maria Victoria",
    "wof:placetype":"venue"
},
  "geometry": {"coordinates":[-4.6153550148,36.7362709045],"type":"Point"}
}