{
  "type": "Feature",
  "properties": {
    "iso:country":"ES",
    "sg:address":"Avda Palencia, 35",
    "sg:city":"Valladolid",
    "sg:orig_category":"Laboratorios Y Cl\u00cdnicas Veterinarias",
    "sg:phone":"+34 983 25 17 11",
    "sg:postcode":"47010",
    "sg:province":"Valladolid",
    "wof:name":"Veteclinic S.l.",
    "wof:placetype":"venue"
},
  "geometry": {"coordinates":[-4.7175059319,41.660774231],"type":"Point"}
}