{
  "type": "Feature",
  "properties": {
    "iso:country":"ES",
    "sg:address":"Carrer de Marquesa Caldes De Montbui, 18",
    "sg:city":"Barcelona",
    "sg:orig_category":"Compraventa De Antig\u00dcedades",
    "sg:phone":"+34 934 36 53 21",
    "sg:postcode":"08032",
    "sg:province":"Barcelona",
    "wof:name":"Cuadras Pons Montserrat",
    "wof:placetype":"venue"
},
  "geometry": {"coordinates":[2.1745240688,41.4253005981],"type":"Point"}
}