{
  "type": "Feature",
  "properties": {
    "iso:country":"ES",
    "sg:address":"C/ Pirineus, S/n",
    "sg:city":"Celra",
    "sg:orig_category":"Ingeniero",
    "sg:phone":"+34 972 49 29 14",
    "sg:postcode":"17460",
    "sg:province":"Girona",
    "wof:name":"Centre D'estudis De La Construccio I Ana",
    "wof:placetype":"venue"
},
  "geometry": {"coordinates":[2.8779149055,42.0308189392],"type":"Point"}
}