{
  "type": "Feature",
  "properties": {
    "iso:country":"ES",
    "sg:address":"Rua Principe, 14",
    "sg:city":"Muros",
    "sg:orig_category":"Sociedades, Compa\u00d1\u00cdas Aseguradoras",
    "sg:phone":"+34 981 82 75 09",
    "sg:postcode":"15250",
    "sg:province":"La Coru\u00f1a",
    "wof:name":"Nobel Gestion S.l.",
    "wof:placetype":"venue"
},
  "geometry": {"coordinates":[-9.0593690872,42.7760696411],"type":"Point"}
}