{
  "type": "Feature",
  "properties": {
    "addr:full":"Rbla Blas Infante, 7 Castelldefels Barcelona 08860",
    "addr:housenumber":"7",
    "addr:postcode":"08860",
    "addr:street":"Rbla Blas Infante",
    "iso:country":"ES",
    "sg:address":"Rbla Blas Infante, 7",
    "sg:city":"Castelldefels",
    "sg:orig_category":"Supermercados Y Hipermercados",
    "sg:phone":"+34 936 64 58 45",
    "sg:postcode":"08860",
    "sg:province":"Barcelona",
    "wof:name":"Ordo\u00d1ez Benitez S.l.",
    "wof:placetype":"venue"
},
  "geometry": {"coordinates":[1.9779700041,41.2872047424],"type":"Point"}
}