{
  "type": "Feature",
  "properties": {
    "addr:full":"Calle de Arroyo Bueno, 2 Madrid Madrid 28021",
    "addr:housenumber":"2",
    "addr:postcode":"28021",
    "addr:street":"Calle De Arroyo Bueno",
    "iso:country":"ES",
    "sg:address":"Calle de Arroyo Bueno, 2",
    "sg:city":"Madrid",
    "sg:orig_category":"Lavado, Limpieza De Veh\u00cdculos",
    "sg:phone":"+34 917 96 63 03",
    "sg:postcode":"28021",
    "sg:province":"Madrid",
    "wof:name":"Carmona Carmona Enrique",
    "wof:placetype":"venue"
},
  "geometry": {"coordinates":[-3.7026391029,40.3484611511],"type":"Point"}
}