{
  "type": "Feature",
  "properties": {
    "iso:country":"ES",
    "sg:address":"Grup Bego\u00d1alde, 1",
    "sg:city":"Bilbao",
    "sg:orig_category":"Perfumer\u00cda, Art\u00cdculos De Ba\u00d1o (fabricaci\u00d3n, Al Por Mayor)",
    "sg:phone":"+34 944 46 26 39",
    "sg:postcode":"48007",
    "sg:province":"Vizcaya",
    "wof:name":"Vidal Cruz Juan Carlos",
    "wof:placetype":"venue"
},
  "geometry": {"coordinates":[-2.9148929119,43.261554718],"type":"Point"}
}