{
  "type": "Feature",
  "properties": {
    "iso:country":"ES",
    "sg:address":"Calle de Lopan, 13",
    "sg:city":"Almeria",
    "sg:orig_category":"M\u00c9dicos: An\u00c1lisis Cl\u00cdnicos",
    "sg:phone":"+34 950 28 10 11",
    "sg:postcode":"04008",
    "sg:province":"Almer\u00eda",
    "wof:name":"Zapata Sanchez Francisco",
    "wof:placetype":"venue"
},
  "geometry": {"coordinates":[-2.4587807655,36.8476295471],"type":"Point"}
}