{
  "type": "Feature",
  "properties": {
    "addr:full":"Calle de Teruel, 4 Burgos Burgos 09001",
    "addr:housenumber":"4",
    "addr:postcode":"09001",
    "addr:street":"Calle De Teruel",
    "iso:country":"ES",
    "sg:address":"Calle de Teruel, 4",
    "sg:city":"Burgos",
    "sg:orig_category":"Abogados",
    "sg:phone":"+34 947 27 50 65",
    "sg:postcode":"09001",
    "sg:province":"Burgos",
    "wof:name":"Gonzalez Cubillo Santiago",
    "wof:placetype":"venue"
},
  "geometry": {"coordinates":[-3.7063639164,42.3304634094],"type":"Point"}
}