{
  "type": "Feature",
  "properties": {
    "iso:country":"ES",
    "sg:address":"Avda Madrid (de), S/n",
    "sg:city":"Granada",
    "sg:orig_category":"Obras Y Organismos Sociales",
    "sg:phone":"+34 958 20 65 07",
    "sg:postcode":"18012",
    "sg:province":"Granada",
    "wof:name":"Fundacion Benefica San Francisco Javier Y Santa Candida",
    "wof:placetype":"venue"
},
  "geometry": {"coordinates":[-3.6071689129,37.190826416],"type":"Point"}
}