{
  "type": "Feature",
  "properties": {
    "addr:full":"Carrer de Gavina, 9 Rubi Barcelona 08191",
    "addr:housenumber":"9",
    "addr:postcode":"08191",
    "addr:street":"Carrer De Gavina",
    "iso:country":"ES",
    "sg:address":"Carrer de Gavina, 9",
    "sg:city":"Rubi",
    "sg:orig_category":"Empresas De Pintura Y Revestimientos",
    "sg:phone":"+34 936 99 39 08",
    "sg:postcode":"08191",
    "sg:province":"Barcelona",
    "wof:name":"Fernandez Abella Faustino",
    "wof:placetype":"venue"
},
  "geometry": {"coordinates":[2.0161559582,41.4870185852],"type":"Point"}
}