{
  "type": "Feature",
  "properties": {
    "addr:full":"Calle de Marruecos, 35 Sevilla Sevilla 41015",
    "addr:housenumber":"35",
    "addr:postcode":"41015",
    "addr:street":"Calle De Marruecos",
    "iso:country":"ES",
    "sg:address":"Calle de Marruecos, 35",
    "sg:city":"Sevilla",
    "sg:orig_category":"Arenas, Guijarros Y Granulados",
    "sg:phone":"+34 954 37 72 49",
    "sg:postcode":"41015",
    "sg:province":"Sevilla",
    "wof:name":"Castro Bravo Manuel",
    "wof:placetype":"venue"
},
  "geometry": {"coordinates":[-5.985599041,37.4231987],"type":"Point"}
}