{
  "type": "Feature",
  "properties": {
    "addr:full":"Calle de Concepcion Arenal, S/n Loranca Madrid 28942",
    "addr:housenumber":"s / n",
    "addr:postcode":"28942",
    "addr:street":"Calle De Concepcion Arenal",
    "iso:country":"ES",
    "sg:address":"Calle de Concepcion Arenal, S/n",
    "sg:city":"Loranca",
    "sg:orig_category":"Centros De Educaci\u00d3n Especial",
    "sg:phone":"+34 914 86 42 38",
    "sg:postcode":"28942",
    "sg:province":"Madrid",
    "wof:name":"Colegio Publico La Ca\u00d1ada",
    "wof:placetype":"venue"
},
  "geometry": {"coordinates":[-3.8378236294,40.292930603],"type":"Point"}
}