{
  "type": "Feature",
  "properties": {
    "addr:full":"Calle de Tina (de La), S/n Valdepe\u00f1as Ciudad Real 13300",
    "addr:postcode":"13300",
    "addr:street":"Calle De Tina De La S / N Valdepen\u0303As",
    "iso:country":"ES",
    "sg:address":"Calle de Tina (de La), S/n",
    "sg:city":"Valdepe\u00f1as",
    "sg:orig_category":"Agentes, Concesionarios Y Sucursales De Veh\u00cdculos",
    "sg:phone":"+34 926 31 11 99",
    "sg:postcode":"13300",
    "sg:province":"Ciudad Real",
    "wof:name":"Best Motor Wright S.l.",
    "wof:placetype":"venue"
},
  "geometry": {"coordinates":[-3.3980588913,38.7749557495],"type":"Point"}
}