{
  "type": "Feature",
  "properties": {
    "addr:full":"Calle de 28 De Febrero, 93 Berja Almer\u00eda 04760",
    "addr:housenumber":"28;93",
    "addr:postcode":"04760",
    "addr:street":"Calle De;De Febrero",
    "iso:country":"ES",
    "sg:address":"Calle de 28 De Febrero, 93",
    "sg:city":"Berja",
    "sg:orig_category":"Farmacias",
    "sg:phone":"+34 950 49 23 31",
    "sg:postcode":"04760",
    "sg:province":"Almer\u00eda",
    "wof:name":"Baumela Flores Maria Magdalena",
    "wof:placetype":"venue"
},
  "geometry": {"coordinates":[-2.9483876228,36.8437995911],"type":"Point"}
}