{
  "type": "Feature",
  "properties": {
    "addr:full":"Carrer de Corsega, 403 Barcelona Barcelona 08037",
    "addr:housenumber":"403",
    "addr:postcode":"08037",
    "addr:street":"Carrer De Corsega",
    "iso:country":"ES",
    "sg:address":"Carrer de Corsega, 403",
    "sg:city":"Barcelona",
    "sg:orig_category":"Molduras, Junquillos, Listones Y Molduras Perforadas",
    "sg:phone":"+34 934 57 65 91",
    "sg:postcode":"08037",
    "sg:province":"Barcelona",
    "wof:name":"Esteve Albella Miguel",
    "wof:placetype":"venue"
},
  "geometry": {"coordinates":[2.1636860371,41.4000091553],"type":"Point"}
}