{
  "type": "Feature",
  "properties": {
    "iso:country":"ES",
    "sg:address":"Calle de Artana, S/n",
    "sg:city":"Nules",
    "sg:orig_category":"Bares, Piano",
    "sg:phone":"+34 964 67 29 94",
    "sg:postcode":"12520",
    "sg:province":"Castell\u00f3n",
    "wof:name":"Navarro Martinez Jose",
    "wof:placetype":"venue"
},
  "geometry": {"coordinates":[-0.1608072966,39.8515281677],"type":"Point"}
}