{
  "type": "Feature",
  "properties": {
    "addr:full":"Carrer de Sant Miquel (de), 9 S. Carles Rapita Tarragona 43540",
    "addr:postcode":"43540",
    "addr:street":"Carrer De Sant Miquel De 9 S. Carles Rapita",
    "iso:country":"ES",
    "sg:address":"Carrer de Sant Miquel (de), 9",
    "sg:city":"S. Carles Rapita",
    "sg:orig_category":"Trabajos De Soldaduras",
    "sg:phone":"+34 977 74 13 45",
    "sg:postcode":"43540",
    "sg:province":"Tarragona",
    "wof:name":"Starweld S.l.",
    "wof:placetype":"venue"
},
  "geometry": {"coordinates":[0.5946850181,40.6204986572],"type":"Point"}
}