{
  "type": "Feature",
  "properties": {
    "iso:country":"ES",
    "sg:address":"Calle de San Cristobal, 40",
    "sg:city":"Vall D'uixo",
    "sg:orig_category":"Postigos, Persianas Y Celos\u00cdas",
    "sg:phone":"+34 964 66 10 01",
    "sg:postcode":"12600",
    "sg:province":"Castell\u00f3n",
    "wof:name":"Rodriguez Martin Jose Manuel",
    "wof:placetype":"venue"
},
  "geometry": {"coordinates":[-0.0403679982,39.9834518433],"type":"Point"}
}