{
  "type": "Feature",
  "properties": {
    "iso:country":"ES",
    "sg:address":"Calle de Arquitecto Rey Pedreira, 4",
    "sg:city":"Coru\u00d1a",
    "sg:orig_category":"Carnicer\u00cdas, Carnicer\u00cdas",
    "sg:phone":"+34 981 14 10 28",
    "sg:postcode":"15011",
    "sg:province":"La Coru\u00f1a",
    "wof:name":"Becerra Gende Margarita",
    "wof:placetype":"venue"
},
  "geometry": {"coordinates":[-8.4219865799,43.3679237366],"type":"Point"}
}