{
  "type": "Feature",
  "properties": {
    "iso:country":"ES",
    "sg:address":"Ctra Tacoronte Tejina, 38",
    "sg:city":"Tacoronte",
    "sg:orig_category":"Inmobiliaria (agencias)",
    "sg:phone":"+34 922 57 21 28",
    "sg:postcode":"38350",
    "sg:province":"Santa Cruz De Tenerife",
    "sg:website":"www.inpla.es/ocampo",
    "wof:name":"Inpla S.a.",
    "wof:placetype":"venue"
},
  "geometry": {"coordinates":[-16.4115200043,28.4800510406],"type":"Point"}
}