{
  "type": "Feature",
  "properties": {
    "iso:country":"ES",
    "sg:address":"Calle de Amadeo I, 2",
    "sg:city":"Madrid",
    "sg:orig_category":"Promotores Constructores",
    "sg:phone":"+34 914 34 13 31",
    "sg:postcode":"28038",
    "sg:province":"Madrid",
    "wof:name":"Morbayca,s.l.",
    "wof:placetype":"venue"
},
  "geometry": {"coordinates":[-3.6580858231,40.4039421082],"type":"Point"}
}