{
  "type": "Feature",
  "properties": {
    "addr:full":"Ctra Sax, S/n Castalla Alicante 03420",
    "addr:housenumber":"s",
    "addr:postcode":"03420",
    "addr:street":"Ctra Sax;/ N",
    "iso:country":"ES",
    "sg:address":"Ctra Sax, S/n",
    "sg:city":"Castalla",
    "sg:orig_category":"Art\u00cdculos Funerarios (al Por Menor)",
    "sg:phone":"+34 965 56 15 36",
    "sg:postcode":"03420",
    "sg:province":"Alicante",
    "wof:name":"Funeraria Tanatorio San Vicente Ferrer S.l.",
    "wof:placetype":"venue"
},
  "geometry": {"coordinates":[-0.6705290079,38.5981864929],"type":"Point"}
}