{
  "type": "Feature",
  "properties": {
    "addr:full":"Avda San Jose, 69 Cuarte Huerva Zaragoza 50410",
    "addr:housenumber":"69",
    "addr:postcode":"50410",
    "addr:street":"Avda San Jose",
    "iso:country":"ES",
    "sg:address":"Avda San Jose, 69",
    "sg:city":"Cuarte Huerva",
    "sg:orig_category":"Reciclaje Y Tratamiento De Desechos Varios",
    "sg:phone":"+34 976 46 38 81",
    "sg:postcode":"50410",
    "sg:province":"Zaragoza",
    "wof:name":"Tecnicas Medioambientales Hospitalarias",
    "wof:placetype":"venue"
},
  "geometry": {"coordinates":[-0.9297879934,41.5948524475],"type":"Point"}
}