{
  "type": "Feature",
  "properties": {
    "addr:full":"Plaz Prado (del), S/n Villanueva Trabuco M\u00e1laga 29313",
    "addr:postcode":"29313",
    "addr:street":"S / N Villanueva",
    "iso:country":"ES",
    "sg:address":"Plaz Prado (del), S/n",
    "sg:city":"Villanueva Trabuco",
    "sg:orig_category":"Empresarios",
    "sg:phone":"+34 952 75 24 62",
    "sg:postcode":"29313",
    "sg:province":"M\u00e1laga",
    "wof:name":"Fundacion Red Andalucia Emprende",
    "wof:placetype":"venue"
},
  "geometry": {"coordinates":[-4.3364291191,37.0291900635],"type":"Point"}
}