{
  "type": "Feature",
  "properties": {
    "iso:country":"ES",
    "sg:address":"Setsa, 4",
    "sg:city":"Llangreu",
    "sg:orig_category":"Caf\u00c9s, Bares, Cervecer\u00cdas",
    "sg:phone":"+34 985 67 70 49",
    "sg:postcode":"33900",
    "sg:province":"Asturias",
    "wof:name":"Sistelcom-telemensaj",
    "wof:placetype":"venue"
},
  "geometry": {"coordinates":[-5.649711132,43.2761459351],"type":"Point"}
}