{
  "type": "Feature",
  "properties": {
    "iso:country":"ES",
    "sg:address":"Carr Cristofol Colom, 32",
    "sg:city":"Bellvis",
    "sg:orig_category":"Comercio De Cuadros, L\u00c1minas Y Reproducciones De Obras De Arte",
    "sg:phone":"+34 973 56 55 40",
    "sg:postcode":"25142",
    "sg:province":"Lleida",
    "wof:name":"Rosa Baro Tiburci",
    "wof:placetype":"venue"
},
  "geometry": {"coordinates":[0.8189340234,41.6743431091],"type":"Point"}
}