{
  "type": "Feature",
  "properties": {
    "iso:country":"ES",
    "sg:address":"Pla\u00c7 Regne De Valencia, 3",
    "sg:city":"Llombai",
    "sg:orig_category":"Peleter\u00cdas",
    "sg:phone":"+34 962 55 04 38",
    "sg:postcode":"46195",
    "sg:province":"Valencia",
    "wof:name":"Sanz Cardona Josefa",
    "wof:placetype":"venue"
},
  "geometry": {"coordinates":[-0.5719540119,39.2796516418],"type":"Point"}
}