{
  "type": "Feature",
  "properties": {
    "iso:country":"ES",
    "sg:address":"Avda Perez Galdos, 3",
    "sg:city":"Castellon",
    "sg:orig_category":"Formaci\u00d3n Continuada (variada)",
    "sg:phone":"+34 964 21 56 61",
    "sg:postcode":"12002",
    "sg:province":"Castell\u00f3n",
    "wof:name":"Perez Grau Rosa",
    "wof:placetype":"venue"
},
  "geometry": {"coordinates":[-0.0439219996,39.9861717224],"type":"Point"}
}