{
  "type": "Feature",
  "properties": {
    "iso:country":"ES",
    "sg:address":"Carr Major, 183",
    "sg:city":"Manises",
    "sg:orig_category":"Cl\u00cdnicas M\u00c9dicas",
    "sg:phone":"+34 961 52 19 26",
    "sg:postcode":"46940",
    "sg:province":"Valencia",
    "wof:name":"Clinica Manises Cdad.",
    "wof:placetype":"venue"
},
  "geometry": {"coordinates":[-0.4661900103,39.4945678711],"type":"Point"}
}