{
  "type": "Feature",
  "properties": {
    "iso:country":"ES",
    "sg:address":"Rbla Raval, 22",
    "sg:city":"Barcelona",
    "sg:orig_category":"Comerciantes Al Por Mayor De Vinos, Licores Y Alcoholes",
    "sg:phone":"+34 933 29 60 46",
    "sg:postcode":"08001",
    "sg:province":"Barcelona",
    "wof:name":"Gonzalez Barrios Prudencio",
    "wof:placetype":"venue"
},
  "geometry": {"coordinates":[2.1697409153,41.377910614],"type":"Point"}
}