{
  "type": "Feature",
  "properties": {
    "addr:full":"A Rua Da Cal, 68 Rua Da Cal Pontevedra 36760",
    "addr:housenumber":"68",
    "addr:postcode":"36760",
    "addr:street":"Rua Da Cal;Rua Da Cal Pontevedra",
    "iso:country":"ES",
    "sg:address":"A Rua Da Cal, 68",
    "sg:city":"Rua Da Cal",
    "sg:orig_category":"Comercio Y Bancos",
    "sg:phone":"+34 986 61 15 15",
    "sg:postcode":"36760",
    "sg:province":"Pontevedra",
    "wof:name":"Alvarez Souto Maria Luz",
    "wof:placetype":"venue"
},
  "geometry": {"coordinates":[-8.6480531693,42.4336204529],"type":"Point"}
}