{
  "type": "Feature",
  "properties": {
    "addr:full":"Calle de San Antonio, 41 Alginet Valencia 46230",
    "addr:housenumber":"41",
    "addr:postcode":"46230",
    "addr:street":"Calle De San Antonio",
    "iso:country":"ES",
    "sg:address":"Calle de San Antonio, 41",
    "sg:city":"Alginet",
    "sg:orig_category":"M\u00c9dicos: Estomatolog\u00cda",
    "sg:phone":"+34 961 75 23 98",
    "sg:postcode":"46230",
    "sg:province":"Valencia",
    "wof:name":"Niederleytne Llorca Rafael",
    "wof:placetype":"venue"
},
  "geometry": {"coordinates":[-0.4719539881,39.2619476318],"type":"Point"}
}