{
  "type": "Feature",
  "properties": {
    "addr:full":"Calle de Ancora, 23 Madrid Madrid 28045",
    "addr:housenumber":"23",
    "addr:postcode":"madrid;28045",
    "addr:street":"Calle De Ancora",
    "iso:country":"ES",
    "sg:address":"Calle de Ancora, 23",
    "sg:city":"Madrid",
    "sg:orig_category":"Artes Gr\u00c1ficas, Artes Pl\u00c1sticas (curso)",
    "sg:phone":"+34 915 28 72 75",
    "sg:postcode":"28045",
    "sg:province":"Madrid",
    "wof:name":"Artes Graficas Gandolfo S.a.",
    "wof:placetype":"venue"
},
  "geometry": {"coordinates":[-3.6909627914,40.402885437],"type":"Point"}
}