{
  "type": "Feature",
  "properties": {
    "addr:full":"Calle de Tirez, 19 Villaca\u00f1as Toledo 45860",
    "addr:housenumber":"19",
    "addr:postcode":"45860",
    "addr:street":"Calle De Tirez",
    "iso:country":"ES",
    "sg:address":"Calle de Tirez, 19",
    "sg:city":"Villaca\u00f1as",
    "sg:orig_category":"Doctores En Medicina",
    "sg:phone":"+34 925 16 08 38",
    "sg:postcode":"45860",
    "sg:province":"Toledo",
    "wof:name":"Crespo Rodriguez Jose Javier",
    "wof:placetype":"venue"
},
  "geometry": {"coordinates":[-3.3340680599,39.6142349243],"type":"Point"}
}