{
  "type": "Feature",
  "properties": {
    "addr:full":"Cm\u00d1o Troncal, 18 Vigo Pontevedra 36207",
    "addr:housenumber":"18",
    "addr:postcode":"36207",
    "addr:street":"Troncal",
    "iso:country":"ES",
    "sg:address":"Cm\u00d1o Troncal, 18",
    "sg:city":"Vigo",
    "sg:orig_category":"Textil",
    "sg:phone":"+34 986 27 07 28",
    "sg:postcode":"36207",
    "sg:province":"Pontevedra",
    "wof:name":"Fabrica De Botones Hisla S.l.",
    "wof:placetype":"venue"
},
  "geometry": {"coordinates":[-8.6967086792,42.242149353],"type":"Point"}
}