{
  "type": "Feature",
  "properties": {
    "addr:full":"Calle de Vital Aza, 88 Madrid Madrid 28017",
    "addr:housenumber":"88",
    "addr:postcode":"madrid;28017",
    "addr:street":"Calle De Vital Aza",
    "iso:country":"ES",
    "sg:address":"Calle de Vital Aza, 88",
    "sg:city":"Madrid",
    "sg:orig_category":"Promotores Constructores",
    "sg:phone":"+34 914 07 11 25",
    "sg:postcode":"28017",
    "sg:province":"Madrid",
    "wof:name":"Ramos Lopez Venancio",
    "wof:placetype":"venue"
},
  "geometry": {"coordinates":[-3.6372170448,40.43384552],"type":"Point"}
}