{
  "type": "Feature",
  "properties": {
    "iso:country":"ES",
    "sg:address":"Cami Mig (del), 19",
    "sg:city":"Premia Mar",
    "sg:orig_category":"Tratamiento De Metales",
    "sg:phone":"+34 937 52 42 77",
    "sg:postcode":"08330",
    "sg:province":"Barcelona",
    "wof:name":"Pulidos Premia S.c.p",
    "wof:placetype":"venue"
},
  "geometry": {"coordinates":[2.3595600128,41.4969902039],"type":"Point"}
}