{
  "type": "Feature",
  "properties": {
    "addr:full":"Avda Regne De Valencia, 47 Valencia Valencia 46005",
    "addr:housenumber":"47",
    "addr:postcode":"46005",
    "addr:street":"Avda Regne De Valencia",
    "iso:country":"ES",
    "sg:address":"Avda Regne De Valencia, 47",
    "sg:city":"Valencia",
    "sg:orig_category":"Arquitectos",
    "sg:phone":"+34 963 33 93 77",
    "sg:postcode":"46005",
    "sg:province":"Valencia",
    "wof:name":"Lendinez Viedma Andres",
    "wof:placetype":"venue"
},
  "geometry": {"coordinates":[-0.3674030006,39.4637947083],"type":"Point"}
}