{
  "type": "Feature",
  "properties": {
    "addr:full":"Fca. Bernoy, S/n Bernoy Salamanca 37183",
    "addr:housenumber":"s",
    "addr:postcode":"37183",
    "addr:street":"/ N",
    "iso:country":"ES",
    "sg:address":"Fca. Bernoy, S/n",
    "sg:city":"Bernoy",
    "sg:orig_category":"Cr\u00cda De Animales",
    "sg:phone":"+34 923 17 03 13",
    "sg:postcode":"37183",
    "sg:province":"Salamanca",
    "wof:name":"Bernoy S.coop.",
    "wof:placetype":"venue"
},
  "geometry": {"coordinates":[-5.7561211586,40.7696876526],"type":"Point"}
}