{
  "type": "Feature",
  "properties": {
    "addr:full":"Avda Baron De Carcer, 31 Valencia Valencia 46001",
    "addr:housenumber":"31",
    "addr:postcode":"46001",
    "addr:street":"Avda Baron De Carcer",
    "iso:country":"ES",
    "sg:address":"Avda Baron De Carcer, 31",
    "sg:city":"Valencia",
    "sg:orig_category":"Cl\u00cdnicas M\u00c9dicas",
    "sg:phone":"+34 963 52 36 17",
    "sg:postcode":"46001",
    "sg:province":"Valencia",
    "wof:name":"Quinza Cases Mercedes",
    "wof:placetype":"venue"
},
  "geometry": {"coordinates":[-0.3795270026,39.471370697],"type":"Point"}
}