{
  "type": "Feature",
  "properties": {
    "iso:country":"ES",
    "sg:address":"Calle de Francisco Gomez, 9",
    "sg:city":"San Vicente De Barakaldo",
    "sg:orig_category":"Confecci\u00d3n De Trajes Para Se\u00d1oras",
    "sg:phone":"+34 944 37 94 05",
    "sg:postcode":"48902",
    "sg:province":"Vizcaya",
    "wof:name":"Rodriguez Lorca Jacinto",
    "wof:placetype":"venue"
},
  "geometry": {"coordinates":[-2.9915471077,43.2958450317],"type":"Point"}
}