{
  "type": "Feature",
  "properties": {
    "iso:country":"ES",
    "sg:address":"Calle de Vicario Manresa, 33",
    "sg:city":"Redovan",
    "sg:orig_category":"Bordado, Marcado A Medida",
    "sg:phone":"+34 966 75 54 72",
    "sg:postcode":"03370",
    "sg:province":"Alicante",
    "wof:name":"Creaciones Mervitex S.l.",
    "wof:placetype":"venue"
},
  "geometry": {"coordinates":[-0.9077960253,38.1159057617],"type":"Point"}
}