{
  "type": "Feature",
  "properties": {
    "iso:country":"ES",
    "sg:address":"Cra. Nacional Ii, Km. 0679,5",
    "sg:city":"Ve\u00efnat Sant Pere",
    "sg:orig_category":"Fabricaci\u00d3n De Bordados, Encajes Y Tules",
    "sg:phone":"+34 937 64 37 37",
    "sg:postcode":"08490",
    "sg:province":"Barcelona",
    "wof:name":"Indesmalla S. A.",
    "wof:placetype":"venue"
},
  "geometry": {"coordinates":[2.7179350853,41.6998901367],"type":"Point"}
}