{
  "type": "Feature",
  "properties": {
    "addr:full":"Calle de Cenit, 45 Malaga M\u00e1laga 29190",
    "addr:housenumber":"45",
    "addr:postcode":"29190",
    "addr:street":"Calle De Cenit;Ma\u0301Laga",
    "iso:country":"ES",
    "sg:address":"Calle de Cenit, 45",
    "sg:city":"Malaga",
    "sg:orig_category":"Reposter\u00cdas",
    "sg:phone":"+34 952 43 17 72",
    "sg:postcode":"29190",
    "sg:province":"M\u00e1laga",
    "wof:name":"Martos Sanchez Juan",
    "wof:placetype":"venue"
},
  "geometry": {"coordinates":[-4.4843883514,36.7455177307],"type":"Point"}
}