{
  "type": "Feature",
  "properties": {
    "iso:country":"ES",
    "sg:address":"Calle de Rio Jarama, S/n",
    "sg:city":"Poligono Sta M. De Benquerencia",
    "sg:orig_category":"Calefacci\u00d3n Central: Material (fabricaci\u00d3n, Al Por Mayor)",
    "sg:phone":"+34 925 24 01 60",
    "sg:postcode":"45007",
    "sg:province":"Toledo",
    "wof:name":"Saneamientos Barroso Y Fricalor S.l.",
    "wof:placetype":"venue"
},
  "geometry": {"coordinates":[-3.9589040279,39.8693008423],"type":"Point"}
}