{
  "type": "Feature",
  "properties": {
    "addr:full":"Lugar El Se\u00f1or, S/n Sanlucar C\u00e1diz 11540",
    "addr:housenumber":"s / n",
    "addr:postcode":"11540",
    "addr:street":"Lugar El Sen\u0303Or",
    "iso:country":"ES",
    "sg:address":"Lugar El Se\u00f1or, S/n",
    "sg:city":"Sanlucar",
    "sg:orig_category":"Contenedores (mercanc\u00cdas)",
    "sg:phone":"+34 956 36 32 60",
    "sg:postcode":"11540",
    "sg:province":"C\u00e1diz",
    "wof:name":"Bernal Maceas Jose",
    "wof:placetype":"venue"
},
  "geometry": {"coordinates":[-6.2902097702,36.5298614502],"type":"Point"}
}