{
  "type": "Feature",
  "properties": {
    "iso:country":"ES",
    "sg:address":"Villa Madrid, 15",
    "sg:city":"Huelva",
    "sg:orig_category":"Asociaciones, Organismos Culturales Y Socioeducativos",
    "sg:phone":"+34 959 24 07 97",
    "sg:postcode":"21001",
    "sg:province":"Huelva",
    "wof:name":"Asociacion Provincial De Amas De Casa Virgen De La Cinta",
    "wof:placetype":"venue"
},
  "geometry": {"coordinates":[-6.9542031288,37.2526931763],"type":"Point"}
}