{
  "type": "Feature",
  "properties": {
    "iso:country":"ES",
    "sg:address":"Calle de Ayala, 73",
    "sg:city":"Madrid",
    "sg:orig_category":"Asesor\u00cda Sobre Comunicaci\u00d3n De Empresas",
    "sg:phone":"+34 915 64 33 58",
    "sg:postcode":"28001",
    "sg:province":"Madrid",
    "sg:website":"www.foronorte.com",
    "wof:name":"Foro Norte S.l.",
    "wof:placetype":"venue"
},
  "geometry": {"coordinates":[-3.6756014824,40.4273223877],"type":"Point"}
}