{
  "type": "Feature",
  "properties": {
    "iso:country":"ES",
    "sg:address":"Avda Espa\u00d1a (de), 90",
    "sg:city":"Dos Hermanas",
    "sg:orig_category":"Empresas De Pintura Y Revestimientos",
    "sg:phone":"+34 955 66 74 14",
    "sg:postcode":"41700",
    "sg:province":"Sevilla",
    "wof:name":"Pinturas Busto E Hijos S.l.",
    "wof:placetype":"venue"
},
  "geometry": {"coordinates":[-5.9146227837,37.2830352783],"type":"Point"}
}