{
  "type": "Feature",
  "properties": {
    "iso:country":"ES",
    "sg:address":"Av Pirineus, 105",
    "sg:city":"Puigcerda",
    "sg:orig_category":"Quincaller\u00cda (al Por Menor)",
    "sg:phone":"+34 972 14 14 45",
    "sg:postcode":"17520",
    "sg:province":"Girona",
    "wof:name":"Ferreteria Franur S.l.",
    "wof:placetype":"venue"
},
  "geometry": {"coordinates":[1.9253900051,42.4297904968],"type":"Point"}
}