{
  "type": "Feature",
  "properties": {
    "iso:country":"ES",
    "sg:address":"Calle de Fernandez De Los Rios, 106",
    "sg:city":"Madrid",
    "sg:orig_category":"Venta, Instalaci\u00d3n De Calefacci\u00d3n",
    "sg:phone":"+34 915 43 95 19",
    "sg:postcode":"28015",
    "sg:province":"Madrid",
    "wof:name":"Maseda Cuadrado Julian",
    "wof:placetype":"venue"
},
  "geometry": {"coordinates":[-3.717315197,40.4354934692],"type":"Point"}
}