{
  "type": "Feature",
  "properties": {
    "addr:full":"Carrer de Costa De Carbonell, 20 Lloret Mar Girona 17310",
    "addr:housenumber":"20",
    "addr:postcode":"17310",
    "addr:street":"Carrer De Costa De Carbonell",
    "iso:country":"ES",
    "sg:address":"Carrer de Costa De Carbonell, 20",
    "sg:city":"Lloret Mar",
    "sg:orig_category":"Importaci\u00d3n",
    "sg:phone":"+34 972 37 30 28",
    "sg:postcode":"17310",
    "sg:province":"Girona",
    "wof:name":"Heymelot Emp S.l.",
    "wof:placetype":"venue"
},
  "geometry": {"coordinates":[2.8416149616,41.6999931335],"type":"Point"}
}