{
  "type": "Feature",
  "properties": {
    "addr:full":"Rbla General Franco, 5 Santa Cruz De Tenerife Santa Cruz De Tenerife 38006",
    "addr:housenumber":"5",
    "addr:postcode":"38006",
    "addr:street":"Rbla General Franco",
    "iso:country":"ES",
    "sg:address":"Rbla General Franco, 5",
    "sg:city":"Santa Cruz De Tenerife",
    "sg:orig_category":"Moda",
    "sg:phone":"+34 922 27 62 25",
    "sg:postcode":"38006",
    "sg:province":"Santa Cruz De Tenerife",
    "wof:name":"Ramos Ramos Antonio",
    "wof:placetype":"venue"
},
  "geometry": {"coordinates":[-16.2612323761,28.4683742523],"type":"Point"}
}