{
  "type": "Feature",
  "properties": {
    "iso:country":"ES",
    "sg:address":"Calle de Cuesta Moreras, 1",
    "sg:city":"Letur",
    "sg:orig_category":"Cajas De Ahorro",
    "sg:phone":"+34 967 42 60 79",
    "sg:postcode":"02434",
    "sg:province":"Albacete",
    "wof:name":"Caja De Ahorros De Castilla La Mancha",
    "wof:placetype":"venue"
},
  "geometry": {"coordinates":[-2.102009058,38.3653106689],"type":"Point"}
}