{
  "type": "Feature",
  "properties": {
    "addr:full":"Juan Pablo Ii, S/n Jedula C\u00e1diz 11620",
    "addr:housenumber":"s / n",
    "addr:postcode":"11620",
    "addr:street":"Juan Pablo Ii;Ca\u0301Diz",
    "iso:country":"ES",
    "sg:address":"Juan Pablo Ii, S/n",
    "sg:city":"Jedula",
    "sg:orig_category":"Producci\u00d3n, Venta De Productos De Agricultura Biol\u00d3gica",
    "sg:phone":"+34 956 72 22 27",
    "sg:postcode":"11620",
    "sg:province":"C\u00e1diz",
    "wof:name":"Molinillo Sanchez Antonio",
    "wof:placetype":"venue"
},
  "geometry": {"coordinates":[-5.9306740761,36.7245635986],"type":"Point"}
}