{
  "type": "Feature",
  "properties": {
    "addr:full":"Carrer de Napols, 173 Barcelona Barcelona 08013",
    "addr:housenumber":"173",
    "addr:postcode":"08013",
    "addr:street":"Carrer De Napols",
    "iso:country":"ES",
    "sg:address":"Carrer de Napols, 173",
    "sg:city":"Barcelona",
    "sg:orig_category":"Molduras, Junquillos, Listones Y Molduras Perforadas",
    "sg:phone":"+34 932 45 39 55",
    "sg:postcode":"08013",
    "sg:province":"Barcelona",
    "wof:name":"Gallego Ba\u00f1os Aurora",
    "wof:placetype":"venue"
},
  "geometry": {"coordinates":[2.1758699417,41.3978652954],"type":"Point"}
}