{
  "type": "Feature",
  "properties": {
    "addr:full":"Cllo Mota, 4 Arucas Las Palmas 35400",
    "addr:housenumber":"4",
    "addr:postcode":"35400",
    "addr:street":"Mota",
    "iso:country":"ES",
    "sg:address":"Cllo Mota, 4",
    "sg:city":"Arucas",
    "sg:orig_category":"Negocio De Materiales De Construcci\u00d3n",
    "sg:phone":"+34 928 60 00 76",
    "sg:postcode":"35400",
    "sg:province":"Las Palmas",
    "wof:name":"Perez Marrero Feliciana",
    "wof:placetype":"venue"
},
  "geometry": {"coordinates":[-15.5152540207,28.1135654449],"type":"Point"}
}