{
  "type": "Feature",
  "properties": {
    "addr:full":"Fundacion Marques Dos Aigues, S/n Massanassa Valencia 46470",
    "addr:housenumber":"s / n",
    "addr:postcode":"46470",
    "iso:country":"ES",
    "sg:address":"Fundacion Marques Dos Aigues, S/n",
    "sg:city":"Massanassa",
    "sg:orig_category":"Frutas, Legumbres Frescas Y Tempranas (al Por Menor)",
    "sg:phone":"+34 961 25 03 64",
    "sg:postcode":"46470",
    "sg:province":"Valencia",
    "wof:name":"Frutas Y Verduras Massanassa",
    "wof:placetype":"venue"
},
  "geometry": {"coordinates":[-0.3874189854,39.4068145752],"type":"Point"}
}