{
  "type": "Feature",
  "properties": {
    "addr:full":"Urbanizacion Las Lomas, 137 Golpejar Sobarriba Le\u00f3n 24195",
    "addr:housenumber":"137",
    "addr:postcode":"24195",
    "addr:street":"Lomas;Leo\u0301N",
    "iso:country":"ES",
    "sg:address":"Urbanizacion Las Lomas, 137",
    "sg:city":"Golpejar Sobarriba",
    "sg:orig_category":"Impuestos, Tesoro P\u00dablico",
    "sg:phone":"+34 987 26 35 24",
    "sg:postcode":"24195",
    "sg:province":"Le\u00f3n",
    "wof:name":"Tasaciones Diez S.l.",
    "wof:placetype":"venue"
},
  "geometry": {"coordinates":[-5.506526947,42.6181373596],"type":"Point"}
}