{
  "type": "Feature",
  "properties": {
    "addr:full":"Calle de Cuesta Castillo, S/n Caravaca Cruz Murcia 30400",
    "addr:housenumber":"s",
    "addr:postcode":"30400",
    "addr:street":"Calle De Cuesta Castillo;/ N Caravaca Cruz",
    "iso:country":"ES",
    "sg:address":"Calle de Cuesta Castillo, S/n",
    "sg:city":"Caravaca Cruz",
    "sg:orig_category":"Museos",
    "sg:phone":"+34 968 70 00 02",
    "sg:postcode":"30400",
    "sg:province":"Murcia",
    "sg:website":"www.caravacajubilar.net",
    "wof:name":"Caravaca Jubilar S.a.",
    "wof:placetype":"venue"
},
  "geometry": {"coordinates":[-1.1298867464,37.9834747314],"type":"Point"}
}