{
  "type": "Feature",
  "properties": {
    "addr:full":"Calle de Carretera, 40 Conil De La Frontera C\u00e1diz 11140",
    "addr:housenumber":"40",
    "addr:postcode":"11140",
    "addr:street":"Calle De Carretera",
    "iso:country":"ES",
    "sg:address":"Calle de Carretera, 40",
    "sg:city":"Conil De La Frontera",
    "sg:orig_category":"Quincaller\u00cda (al Por Menor)",
    "sg:phone":"+34 956 44 32 72",
    "sg:postcode":"11140",
    "sg:province":"C\u00e1diz",
    "wof:name":"Maquinaria Industrial Y Ferreteria Reyes S.l.",
    "wof:placetype":"venue"
},
  "geometry": {"coordinates":[-6.0851888657,36.279548645],"type":"Point"}
}