{
  "type": "Feature",
  "properties": {
    "iso:country":"ES",
    "sg:address":"Calle de Molina De Segura, 1",
    "sg:city":"Madrid",
    "sg:orig_category":"Centros De Coordinaci\u00d3n",
    "sg:phone":"+34 913 01 50 08",
    "sg:postcode":"28030",
    "sg:province":"Madrid",
    "wof:name":"Galfin Asesores S.l",
    "wof:placetype":"venue"
},
  "geometry": {"coordinates":[-3.6380009651,40.4083862305],"type":"Point"}
}