{
  "type": "Feature",
  "properties": {
    "addr:full":"Calle de Aguacate, 21 Madrid Madrid 28044",
    "addr:housenumber":"21",
    "addr:postcode":"madrid;28044",
    "addr:street":"Calle De Aguacate",
    "iso:country":"ES",
    "sg:address":"Calle de Aguacate, 21",
    "sg:city":"Madrid",
    "sg:orig_category":"Empresas De Limpieza",
    "sg:phone":"+34 915 08 60 02",
    "sg:postcode":"28044",
    "sg:province":"Madrid",
    "wof:name":"Limpiezas Stella S.l.",
    "wof:placetype":"venue"
},
  "geometry": {"coordinates":[-3.7464408875,40.3707733154],"type":"Point"}
}