{
  "type": "Feature",
  "properties": {
    "addr:full":"C/ Pintor Joan Gris, 15 Manacor Islas Baleares 07500",
    "addr:housenumber":"15",
    "addr:postcode":"07500",
    "addr:street":"C / Pintor Joan Gris",
    "iso:country":"ES",
    "sg:address":"C/ Pintor Joan Gris, 15",
    "sg:city":"Manacor",
    "sg:orig_category":"Porcelanas, Azulejos (fabricaci\u00d3n, Al Por Mayor)",
    "sg:phone":"+34 971 55 15 69",
    "sg:postcode":"07500",
    "sg:province":"Islas Baleares",
    "wof:name":"Aguilo Bonnin Gaspar",
    "wof:placetype":"venue"
},
  "geometry": {"coordinates":[3.203086853,39.5728340149],"type":"Point"}
}