{
  "type": "Feature",
  "properties": {
    "iso:country":"ES",
    "sg:address":"Carr Juan De La Cierva, 3",
    "sg:city":"Badalona",
    "sg:orig_category":"Iglesia Cat\u00d3lica",
    "sg:phone":"+34 933 95 35 54",
    "sg:postcode":"08915",
    "sg:province":"Barcelona",
    "wof:name":"Parroquia De Santa Clara",
    "wof:placetype":"venue"
},
  "geometry": {"coordinates":[2.2490589619,41.4591789246],"type":"Point"}
}