{
  "type": "Feature",
  "properties": {
    "addr:full":"Avda Juan Xxiii, S/n Barbate C\u00e1diz 11160",
    "addr:housenumber":"s / n",
    "addr:postcode":"11160",
    "addr:street":"Avda Juan Xxiii",
    "iso:country":"ES",
    "sg:address":"Avda Juan Xxiii, S/n",
    "sg:city":"Barbate",
    "sg:orig_category":"Centros De Educaci\u00d3n Especial",
    "sg:phone":"+34 956 43 09 50",
    "sg:postcode":"11160",
    "sg:province":"C\u00e1diz",
    "wof:name":"Junta De Andalucia",
    "wof:placetype":"venue"
},
  "geometry": {"coordinates":[-5.9162940979,36.1948051453],"type":"Point"}
}