{
  "type": "Feature",
  "properties": {
    "iso:country":"ES",
    "sg:address":"Pase Alberto Palacios, 46",
    "sg:city":"Madrid",
    "sg:orig_category":"M\u00c9dicos: Estomatolog\u00cda",
    "sg:phone":"+34 917 97 28 40",
    "sg:postcode":"28021",
    "sg:province":"Madrid",
    "wof:name":"Esquivel Carballo Julio Jesus",
    "wof:placetype":"venue"
},
  "geometry": {"coordinates":[-3.7130949497,40.3447418213],"type":"Point"}
}