{
  "type": "Feature",
  "properties": {
    "addr:full":"Calle de Huertas, 3 Pe\u00f1afiel Valladolid 47300",
    "addr:housenumber":"3",
    "addr:postcode":"47300",
    "addr:street":"Calle De Huertas",
    "iso:country":"ES",
    "sg:address":"Calle de Huertas, 3",
    "sg:city":"Pe\u00f1afiel",
    "sg:orig_category":"Pescader\u00cdas (al Por Menor)",
    "sg:phone":"+34 983 88 16 69",
    "sg:postcode":"47300",
    "sg:province":"Valladolid",
    "wof:name":"Garcia Molinero Faustino",
    "wof:placetype":"venue"
},
  "geometry": {"coordinates":[-4.1243419647,41.5986022949],"type":"Point"}
}