{
  "type": "Feature",
  "properties": {
    "addr:full":"Calle de Doctor Domingo Goas, 16 Vilalba Lugo 27800",
    "addr:housenumber":"16",
    "addr:postcode":"27800",
    "addr:street":"Calle De Doctor Domingo Goas",
    "iso:country":"ES",
    "sg:address":"Calle de Doctor Domingo Goas, 16",
    "sg:city":"Vilalba",
    "sg:orig_category":"Asociaciones Y Clubs Deportivos",
    "sg:phone":"+34 982 51 15 82",
    "sg:postcode":"27800",
    "sg:province":"Lugo",
    "wof:name":"Clube Deportivo Jansu",
    "wof:placetype":"venue"
},
  "geometry": {"coordinates":[-7.6331129074,43.2868766785],"type":"Point"}
}