{
  "type": "Feature",
  "properties": {
    "addr:full":"Avda Galicia, 263 Fuentes Nuevas Le\u00f3n 24411",
    "addr:housenumber":"263",
    "addr:postcode":"24411",
    "addr:street":"Avda Galicia",
    "iso:country":"ES",
    "sg:address":"Avda Galicia, 263",
    "sg:city":"Fuentes Nuevas",
    "sg:orig_category":"Chapister\u00cda",
    "sg:phone":"+34 987 45 53 12",
    "sg:postcode":"24411",
    "sg:province":"Le\u00f3n",
    "wof:name":"Talleres Elite Sport S.l.",
    "wof:placetype":"venue"
},
  "geometry": {"coordinates":[-6.6439290047,42.5685310364],"type":"Point"}
}