{
  "type": "Feature",
  "properties": {
    "iso:country":"ES",
    "sg:address":"Calle de General Alava, 10",
    "sg:city":"Vitoria-gasteiz",
    "sg:orig_category":"Tiendas De Grano, Frutas Y Legumbres Secas (al Por Menor)",
    "sg:phone":"+34 945 23 26 38",
    "sg:postcode":"01005",
    "sg:province":"\u00c1lava",
    "wof:name":"Gretel Distribuciones S.a.",
    "wof:placetype":"venue"
},
  "geometry": {"coordinates":[-2.6731100082,42.8449440002],"type":"Point"}
}