{
  "type": "Feature",
  "properties": {
    "iso:country":"ES",
    "sg:address":"Carrer de Mallorca, 51",
    "sg:city":"Rubi",
    "sg:classifiers":[
        {
            "category":"Food & Beverages",
            "subcategory":"Candy",
            "type":"Retail Goods"
        }
    ],
    "sg:phone":"+34 936 97 84 82",
    "sg:postcode":"08191",
    "sg:province":"Barcelona",
    "sg:tags":[
        "confiter\u00cdas",
        "y",
        "de",
        "fabricaci\u00d3n",
        "chocolate"
    ],
    "wof:name":"Dulces Rubi S.l.",
    "wof:placetype":"venue"
},
  "geometry": {"coordinates":[2.0427610874,41.4962348938],"type":"Point"}
}