{
  "type": "Feature",
  "properties": {
    "addr:full":"Calle de Hornos, 11 Caldas De Reis Pontevedra 36650",
    "addr:housenumber":"11",
    "addr:postcode":"36650",
    "addr:street":"Calle De Hornos",
    "iso:country":"ES",
    "sg:address":"Calle de Hornos, 11",
    "sg:city":"Caldas De Reis",
    "sg:orig_category":"Abogados",
    "sg:phone":"+34 986 54 05 05",
    "sg:postcode":"36650",
    "sg:province":"Pontevedra",
    "wof:name":"Rey Figueiras Ana",
    "wof:placetype":"venue"
},
  "geometry": {"coordinates":[-8.6429891586,42.604850769],"type":"Point"}
}