{
  "type": "Feature",
  "properties": {
    "addr:full":"Carrer de Doctor Fleming, 20 Manlleu Barcelona 08560",
    "addr:housenumber":"20",
    "addr:postcode":"08560",
    "addr:street":"Carrer De Doctor Fleming",
    "iso:country":"ES",
    "sg:address":"Carrer de Doctor Fleming, 20",
    "sg:city":"Manlleu",
    "sg:orig_category":"Carnicer\u00cdas, Carnicer\u00cdas",
    "sg:phone":"+34 938 51 09 90",
    "sg:postcode":"08560",
    "sg:province":"Barcelona",
    "wof:name":"Molist Guell Jaime",
    "wof:placetype":"venue"
},
  "geometry": {"coordinates":[2.2827899456,42.0019302368],"type":"Point"}
}