{
  "type": "Feature",
  "properties": {
    "iso:country":"ES",
    "sg:address":"Calle de Doctor Manuel Villegas, 6",
    "sg:city":"Cordoba",
    "sg:orig_category":"Laboratorios Y Trabajos De Fotograf\u00cda, V\u00cddeo Y Cine",
    "sg:phone":"+34 957 43 85 73",
    "sg:postcode":"14007",
    "sg:province":"C\u00f3rdoba",
    "wof:name":"Cordobesa De Produccion Digital S.r.l.l.",
    "wof:placetype":"venue"
},
  "geometry": {"coordinates":[-4.764893055,37.8933982849],"type":"Point"}
}