{
  "type": "Feature",
  "properties": {
    "iso:country":"ES",
    "sg:address":"Calle de Penelope, 2",
    "sg:city":"Narejos",
    "sg:orig_category":"Internados & Ense\u00d1anza Privada",
    "sg:phone":"+34 968 17 05 51",
    "sg:postcode":"30710",
    "sg:province":"Murcia",
    "sg:website":"www.lasclarasdelmarmenor.com",
    "wof:name":"Colegio Mar Menor S.l.",
    "wof:placetype":"venue"
},
  "geometry": {"coordinates":[-0.8489990234,37.7447319031],"type":"Point"}
}