{
  "type": "Feature",
  "properties": {
    "addr:full":"Calle de Fernando El Catolico, 24 Castellon Castell\u00f3n 12005",
    "addr:housenumber":"24",
    "addr:postcode":"12005",
    "addr:street":"Calle De Fernando El Catolico",
    "iso:country":"ES",
    "sg:address":"Calle de Fernando El Catolico, 24",
    "sg:city":"Castellon",
    "sg:orig_category":"Contables",
    "sg:phone":"+34 964 23 41 00",
    "sg:postcode":"12005",
    "sg:province":"Castell\u00f3n",
    "wof:name":"Asesoria Celma & Ballester S.l.",
    "wof:placetype":"venue"
},
  "geometry": {"coordinates":[-0.0318014994,39.9774742126],"type":"Point"}
}