{
  "type": "Feature",
  "properties": {
    "addr:full":"Calle de Santa Catalina, 29 Majadahonda Madrid 28220",
    "addr:housenumber":"29",
    "addr:postcode":"28220",
    "addr:street":"Calle De Santa Catalina",
    "iso:country":"ES",
    "sg:address":"Calle de Santa Catalina, 29",
    "sg:city":"Majadahonda",
    "sg:orig_category":"Art\u00cdculos De Regalo (al Por Menor)",
    "sg:phone":"+34 916 38 98 59",
    "sg:postcode":"28220",
    "sg:province":"Madrid",
    "wof:name":"R.p.g. Virtual S.l.",
    "wof:placetype":"venue"
},
  "geometry": {"coordinates":[-3.8711600304,40.4695053101],"type":"Point"}
}