{
  "type": "Feature",
  "properties": {
    "iso:country":"ES",
    "sg:address":"Calle de Rio Deba, 4",
    "sg:city":"Donostia-san Sebastian",
    "sg:orig_category":"Abogados",
    "sg:phone":"+34 943 32 24 84",
    "sg:postcode":"20012",
    "sg:province":"Guip\u00f9zcoa",
    "wof:name":"Gomez Ormaetxea Francisco Javier",
    "wof:placetype":"venue"
},
  "geometry": {"coordinates":[-1.9689350128,43.3163642883],"type":"Point"}
}