{
  "type": "Feature",
  "properties": {
    "addr:full":"La Rioja, 2 Iru\u00f1a Navarra 31008",
    "addr:housenumber":"2",
    "addr:postcode":"31008",
    "addr:street":"La Rioja",
    "iso:country":"ES",
    "sg:address":"La Rioja, 2",
    "sg:city":"Iru\u00f1a",
    "sg:orig_category":"Laboratorios Y Trabajos De Fotograf\u00cda, V\u00cddeo Y Cine",
    "sg:phone":"+34 948 26 50 72",
    "sg:postcode":"31008",
    "sg:province":"Navarra",
    "wof:name":"Garcia Pato Amancio",
    "wof:placetype":"venue"
},
  "geometry": {"coordinates":[-1.6596437693,42.8089485168],"type":"Point"}
}