{
  "type": "Feature",
  "properties": {
    "addr:full":"Ibn Al-abbar, 14 Onda Castell\u00f3n 12200",
    "addr:housenumber":"14",
    "addr:postcode":"12200",
    "addr:street":"Al-Abbar;Castello\u0301N",
    "iso:country":"ES",
    "sg:address":"Ibn Al-abbar, 14",
    "sg:city":"Onda",
    "sg:orig_category":"Peluqueros: De Se\u00d1oras",
    "sg:phone":"+34 964 60 36 12",
    "sg:postcode":"12200",
    "sg:province":"Castell\u00f3n",
    "wof:name":"Baraces Benhammou Jacinta Jana",
    "wof:placetype":"venue"
},
  "geometry": {"coordinates":[-0.2620640099,39.9651794434],"type":"Point"}
}