{
  "type": "Feature",
  "properties": {
    "addr:full":"Pl Mercat, 3 Palma Islas Baleares 07001",
    "addr:housenumber":"3",
    "addr:postcode":"07001",
    "addr:street":"Pl Mercat",
    "iso:country":"ES",
    "sg:address":"Pl Mercat, 3",
    "sg:city":"Palma",
    "sg:orig_category":"Iglesia Cat\u00d3lica",
    "sg:phone":"+34 971 71 45 10",
    "sg:postcode":"07001",
    "sg:province":"Islas Baleares",
    "wof:name":"Obispado De Mallorca",
    "wof:placetype":"venue"
},
  "geometry": {"coordinates":[2.648597002,39.5711631775],"type":"Point"}
}