{
  "type": "Feature",
  "properties": {
    "addr:full":"Calle de Txorraburu, 1 Gernika-lumo Vizcaya 48300",
    "addr:housenumber":"1",
    "addr:postcode":"48300",
    "addr:street":"Calle De Txorraburu",
    "iso:country":"ES",
    "sg:address":"Calle de Txorraburu, 1",
    "sg:city":"Gernika-lumo",
    "sg:orig_category":"Arquitectos",
    "sg:phone":"+34 946 25 48 11",
    "sg:postcode":"48300",
    "sg:province":"Vizcaya",
    "wof:name":"Crespo Gonzalez Jose",
    "wof:placetype":"venue"
},
  "geometry": {"coordinates":[-2.5366230011,43.3311347961],"type":"Point"}
}