{
  "type": "Feature",
  "properties": {
    "iso:country":"ES",
    "sg:address":"Calle de Micer Masco, 6",
    "sg:city":"Valencia",
    "sg:orig_category":"Librer\u00cdas",
    "sg:phone":"+34 963 69 90 21",
    "sg:postcode":"46010",
    "sg:province":"Valencia",
    "wof:name":"Font Ferrando Natalia",
    "wof:placetype":"venue"
},
  "geometry": {"coordinates":[-0.3653630018,39.4760856628],"type":"Point"}
}