{
  "type": "Feature",
  "properties": {
    "addr:full":"Carr Del Rector Antonio Sancho Bueno, 4 Alaquas Valencia 46970",
    "addr:housenumber":"4",
    "addr:postcode":"46970",
    "addr:street":"Carr Del Rector Antonio Sancho Bueno",
    "iso:country":"ES",
    "sg:address":"Carr Del Rector Antonio Sancho Bueno, 4",
    "sg:city":"Alaquas",
    "sg:orig_category":"Promotores Constructores",
    "sg:phone":"+34 961 51 64 95",
    "sg:postcode":"46970",
    "sg:province":"Valencia",
    "wof:name":"Construcciones Y Promociones Emilio Y Ramon 2002 S.l.",
    "wof:placetype":"venue"
},
  "geometry": {"coordinates":[-0.4619469941,39.4541664124],"type":"Point"}
}