{
  "type": "Feature",
  "properties": {
    "addr:full":"Calle de Canarias, 62 Madrid Madrid 28045",
    "addr:housenumber":"62",
    "addr:postcode":"madrid;28045",
    "addr:street":"Calle De Canarias",
    "iso:country":"ES",
    "sg:address":"Calle de Canarias, 62",
    "sg:city":"Madrid",
    "sg:orig_category":"Cl\u00cdnicas Dentales",
    "sg:phone":"+34 915 27 86 80",
    "sg:postcode":"28045",
    "sg:province":"Madrid",
    "wof:name":"Frances Foz Nuria",
    "wof:placetype":"venue"
},
  "geometry": {"coordinates":[-3.6891937256,40.4016418457],"type":"Point"}
}