{
  "type": "Feature",
  "properties": {
    "iso:country":"ES",
    "sg:address":"Grupo Pio Xii, 21",
    "sg:city":"Almassora",
    "sg:orig_category":"Carnicer\u00cdas, Carnicer\u00cdas",
    "sg:phone":"+34 964 56 15 03",
    "sg:postcode":"12550",
    "sg:province":"Castell\u00f3n",
    "wof:name":"Oca\u00f1a Lopez Jose",
    "wof:placetype":"venue"
},
  "geometry": {"coordinates":[-0.0728809983,39.9505615234],"type":"Point"}
}