{
  "type": "Feature",
  "properties": {
    "iso:country":"ES",
    "sg:address":"Avda Tenor Fleta, 64",
    "sg:city":"Zaragoza",
    "sg:classifiers":[
        {
            "category":"Personal",
            "subcategory":"Barber",
            "type":"Services"
        }
    ],
    "sg:phone":"+34 976 27 79 30",
    "sg:postcode":"50007",
    "sg:province":"Zaragoza",
    "sg:tags":[
        "caballeros",
        "de",
        "peluqueros"
    ],
    "wof:name":"Lozano Tejada Fernando",
    "wof:placetype":"venue"
},
  "geometry": {"coordinates":[-0.8791890144,41.6386299133],"type":"Point"}
}