{
  "type": "Feature",
  "properties": {
    "iso:country":"ES",
    "sg:address":"Carrer de Llessui, 10",
    "sg:city":"Calafell-park",
    "sg:orig_category":"Perfumer\u00cda: Materias Primas Y Esencias",
    "sg:phone":"+34 977 69 27 44",
    "sg:postcode":"43820",
    "sg:province":"Tarragona",
    "wof:name":"Ordo\u00f1ez Benitez Cristian",
    "wof:placetype":"venue"
},
  "geometry": {"coordinates":[1.5893969536,41.2281990051],"type":"Point"}
}