{
  "type": "Feature",
  "properties": {
    "addr:full":"Pase Damas (las), 36 Zaragoza Zaragoza 50008",
    "addr:housenumber":"36",
    "addr:postcode":"50008",
    "addr:street":"Las",
    "iso:country":"ES",
    "sg:address":"Pase Damas (las), 36",
    "sg:city":"Zaragoza",
    "sg:orig_category":"Centros Empresariales",
    "sg:phone":"+34 976 15 84 86",
    "sg:postcode":"50008",
    "sg:province":"Zaragoza",
    "wof:name":"Iniciativas De Desarrollo Y Medioambiente",
    "wof:placetype":"venue"
},
  "geometry": {"coordinates":[-0.883062005,41.6436386108],"type":"Point"}
}