{
  "type": "Feature",
  "properties": {
    "iso:country":"ES",
    "sg:address":"Calle de Limitacion, 5",
    "sg:city":"Malaga",
    "sg:orig_category":"Maquinaria Para Industrias Diversas",
    "sg:phone":"+34 952 17 81 07",
    "sg:postcode":"29196",
    "sg:province":"M\u00e1laga",
    "wof:name":"Resami Malague\u00f1a S.l.",
    "wof:placetype":"venue"
},
  "geometry": {"coordinates":[-4.5081791878,36.7042427063],"type":"Point"}
}