{
  "type": "Feature",
  "properties": {
    "addr:full":"Os Mui\u00f1os(moraime), 26 Quintans A Coru\u00f1a 15126",
    "addr:housenumber":"26",
    "addr:postcode":"15126",
    "addr:street":"Muin\u0303Os Moraime;Corun\u0303A",
    "iso:country":"ES",
    "sg:address":"Os Mui\u00f1os(moraime), 26",
    "sg:city":"Quintans",
    "sg:orig_category":"Lavado, Limpieza De Veh\u00cdculos",
    "sg:phone":"+34 981 75 06 96",
    "sg:postcode":"15126",
    "sg:province":"A Coru\u00f1a",
    "wof:name":"Santos Lopez Jose Ramon",
    "wof:placetype":"venue"
},
  "geometry": {"coordinates":[-9.1278076172,43.0932540894],"type":"Point"}
}