{
  "type": "Feature",
  "properties": {
    "iso:country":"ES",
    "sg:address":"Avda Pintor Joaquin Sorolla, 39",
    "sg:city":"Malaga",
    "sg:orig_category":"Farmacias",
    "sg:phone":"+34 952 60 20 60",
    "sg:postcode":"29016",
    "sg:province":"M\u00e1laga",
    "wof:name":"Morales Soler Juan",
    "wof:placetype":"venue"
},
  "geometry": {"coordinates":[-4.3939909935,36.7236442566],"type":"Point"}
}