{
  "type": "Feature",
  "properties": {
    "iso:country":"ES",
    "sg:address":"Cmno Cementerio, 18",
    "sg:city":"Fuentes Ebro",
    "sg:orig_category":"M\u00c1rmoles, Granitos Y Piedras Naturales",
    "sg:phone":"+34 976 16 91 41",
    "sg:postcode":"50740",
    "sg:province":"Zaragoza",
    "wof:name":"Granymat 2001 S.l.",
    "wof:placetype":"venue"
},
  "geometry": {"coordinates":[-0.6268740296,41.5112380981],"type":"Point"}
}