{
  "type": "Feature",
  "properties": {
    "addr:full":"Calle de Juan Xxiii, 56 Chantada Lugo 27500",
    "addr:housenumber":"56",
    "addr:postcode":"27500",
    "addr:street":"Calle De Juan Xxiii",
    "iso:country":"ES",
    "sg:address":"Calle de Juan Xxiii, 56",
    "sg:city":"Chantada",
    "sg:orig_category":"Aguas (distribuci\u00d3n, Servicios)",
    "sg:phone":"+34 982 44 13 80",
    "sg:postcode":"27500",
    "sg:province":"Lugo",
    "wof:name":"Aquagest",
    "wof:placetype":"venue"
},
  "geometry": {"coordinates":[-7.7679076195,42.6067047119],"type":"Point"}
}