{
  "type": "Feature",
  "properties": {
    "iso:country":"ES",
    "sg:address":"Avda Espa\u00d1a (de), 56",
    "sg:city":"Alcobendas",
    "sg:orig_category":"Equitaci\u00d3n Y Centros De H\u00cdpica",
    "sg:phone":"+34 916 54 60 89",
    "sg:postcode":"28100",
    "sg:province":"Madrid",
    "wof:name":"Perez Martin Maria Del Mar",
    "wof:placetype":"venue"
},
  "geometry": {"coordinates":[-3.6287100315,40.5437049866],"type":"Point"}
}