{
  "type": "Feature",
  "properties": {
    "addr:full":"Calle de Juan Ramon Jimenez, 12 Madrid Madrid 28036",
    "addr:housenumber":"12",
    "addr:postcode":"madrid;28036",
    "addr:street":"Calle De Juan Ramon Jimenez",
    "iso:country":"ES",
    "sg:address":"Calle de Juan Ramon Jimenez, 12",
    "sg:city":"Madrid",
    "sg:orig_category":"Cl\u00cdnicas M\u00c9dicas",
    "sg:phone":"+34 913 45 25 36",
    "sg:postcode":"28036",
    "sg:province":"Madrid",
    "wof:name":"L.i. Recasens S.l.",
    "wof:placetype":"venue"
},
  "geometry": {"coordinates":[-3.6865389347,40.4592399597],"type":"Point"}
}