{
  "type": "Feature",
  "properties": {
    "addr:full":"Rua Urzaiz, 131 Vigo Pontevedra 36204",
    "addr:housenumber":"131",
    "addr:postcode":"36204",
    "addr:street":"Rua Urzaiz",
    "iso:country":"ES",
    "sg:address":"Rua Urzaiz, 131",
    "sg:city":"Vigo",
    "sg:orig_category":"Ingeniero",
    "sg:phone":"+34 986 25 12 78",
    "sg:postcode":"36204",
    "sg:province":"Pontevedra",
    "wof:name":"Lucent Technologies Network Systems Espa\u00d1a S.a.",
    "wof:placetype":"venue"
},
  "geometry": {"coordinates":[-8.7092485428,42.2317008972],"type":"Point"}
}