{
  "type": "Feature",
  "properties": {
    "addr:full":"Calle de Cortijo, 6 Yebenes Toledo 45470",
    "addr:housenumber":"6",
    "addr:postcode":"45470",
    "addr:street":"Calle De Cortijo",
    "iso:country":"ES",
    "sg:address":"Calle de Cortijo, 6",
    "sg:city":"Yebenes",
    "sg:orig_category":"Relojer\u00cda (al Por Menor, Reparaci\u00d3n)",
    "sg:phone":"+34 925 32 05 41",
    "sg:postcode":"45470",
    "sg:province":"Toledo",
    "wof:name":"Merino Calderon Angela",
    "wof:placetype":"venue"
},
  "geometry": {"coordinates":[-3.8710808754,39.5810813904],"type":"Point"}
}