{
  "type": "Feature",
  "properties": {
    "iso:country":"ES",
    "sg:address":"Calle de San Lorenzo, 4",
    "sg:city":"Le\u00f3n",
    "sg:orig_category":"Caf\u00c9s, Bares, Cervecer\u00cdas",
    "sg:phone":"+34 987 22 81 00",
    "sg:postcode":"24007",
    "sg:province":"Le\u00f3n",
    "wof:name":"Mate Galan S.l.",
    "wof:placetype":"venue"
},
  "geometry": {"coordinates":[-5.565844059,42.6002311707],"type":"Point"}
}