{
  "type": "Feature",
  "properties": {
    "addr:full":"Calle de Ruiz De Alda, 8 Valdemoro Madrid 28340",
    "addr:housenumber":"8",
    "addr:postcode":"28340",
    "addr:street":"Calle De Ruiz De Alda",
    "iso:country":"ES",
    "sg:address":"Calle de Ruiz De Alda, 8",
    "sg:city":"Valdemoro",
    "sg:orig_category":"Carnicer\u00cdas, Carnicer\u00cdas",
    "sg:phone":"+34 918 08 45 14",
    "sg:postcode":"28340",
    "sg:province":"Madrid",
    "wof:name":"Sumcarne C.b.",
    "wof:placetype":"venue"
},
  "geometry": {"coordinates":[-3.6803898811,40.1911621094],"type":"Point"}
}