{
  "type": "Feature",
  "properties": {
    "iso:country":"ES",
    "sg:address":"Calle de Martires, 118",
    "sg:city":"Roda",
    "sg:orig_category":"Veh\u00cdculos De Ocasi\u00d3n",
    "sg:phone":"+34 967 44 38 46",
    "sg:postcode":"02630",
    "sg:province":"Albacete",
    "wof:name":"Talleres Perez Escribano S.l.",
    "wof:placetype":"venue"
},
  "geometry": {"coordinates":[-2.1667189598,39.2107086182],"type":"Point"}
}