{
  "type": "Feature",
  "properties": {
    "iso:country":"ES",
    "sg:address":"Av Generalitat, 36",
    "sg:city":"Campello",
    "sg:orig_category":"Material Y Suministros Para Perforaciones, Sondeos",
    "sg:phone":"+34 965 63 00 66",
    "sg:postcode":"03560",
    "sg:province":"Alicante",
    "wof:name":"Soler Espinos Carlos",
    "wof:placetype":"venue"
},
  "geometry": {"coordinates":[-0.3961899877,38.4277801514],"type":"Point"}
}