{
  "type": "Feature",
  "properties": {
    "addr:full":"Calle de Ruiz De Alda, 9 Valdemoro Madrid 28340",
    "addr:housenumber":"9",
    "addr:postcode":"28340",
    "addr:street":"Calle De Ruiz De Alda",
    "iso:country":"ES",
    "sg:address":"Calle de Ruiz De Alda, 9",
    "sg:city":"Valdemoro",
    "sg:orig_category":"Cl\u00cdnicas Dentales",
    "sg:phone":"+34 918 95 48 53",
    "sg:postcode":"28340",
    "sg:province":"Madrid",
    "wof:name":"Clinica Dental Valdemoro S.l.",
    "wof:placetype":"venue"
},
  "geometry": {"coordinates":[-3.6805479527,40.1910972595],"type":"Point"}
}