{
  "type": "Feature",
  "properties": {
    "addr:full":"Calle de Panaderos, 81 Competa M\u00e1laga 29754",
    "addr:housenumber":"81",
    "addr:postcode":"29754",
    "addr:street":"Calle De Panaderos;Ma\u0301Laga",
    "iso:country":"ES",
    "sg:address":"Calle de Panaderos, 81",
    "sg:city":"Competa",
    "sg:orig_category":"Panader\u00cdas, Panader\u00cdas",
    "sg:phone":"+34 952 51 60 78",
    "sg:postcode":"29754",
    "sg:province":"M\u00e1laga",
    "wof:name":"Hijos De Cordobilla S.l.",
    "wof:placetype":"venue"
},
  "geometry": {"coordinates":[-3.9732189178,36.8335914612],"type":"Point"}
}