{
  "type": "Feature",
  "properties": {
    "iso:country":"ES",
    "sg:address":"Pg Saladar, 35",
    "sg:city":"Denia",
    "sg:orig_category":"Parafarmacias",
    "sg:phone":"+34 966 43 14 07",
    "sg:postcode":"03700",
    "sg:province":"Alicante",
    "sg:website":"www.farmarosa.es",
    "wof:name":"Rosello Bertomeu Irene",
    "wof:placetype":"venue"
},
  "geometry": {"coordinates":[0.1071129963,38.8375740051],"type":"Point"}
}