{
  "type": "Feature",
  "properties": {
    "iso:country":"ES",
    "sg:address":"A Covi\u00f1a, S/n",
    "sg:city":"Covi\u00d1a",
    "sg:orig_category":"Delegados, Agentes De Tr\u00c1nsito, Auxiliares De Transporte Internacional",
    "sg:phone":"+34 981 86 12 78",
    "sg:postcode":"15985",
    "sg:province":"La Coru\u00f1a",
    "wof:name":"Bures Suarez Jose",
    "wof:placetype":"venue"
},
  "geometry": {"coordinates":[-8.8350944519,42.6831436157],"type":"Point"}
}