{
  "type": "Feature",
  "properties": {
    "addr:full":"Calle de Puerta De La Muela, 13 Iznajar C\u00f3rdoba 14970",
    "addr:housenumber":"13",
    "addr:postcode":"14970",
    "addr:street":"Calle De Puerta De La Muela;Co\u0301Rdoba",
    "iso:country":"ES",
    "sg:address":"Calle de Puerta De La Muela, 13",
    "sg:city":"Iznajar",
    "sg:orig_category":"Art\u00cdculos De Regalo (al Por Menor)",
    "sg:phone":"+34 957 53 46 74",
    "sg:postcode":"14970",
    "sg:province":"C\u00f3rdoba",
    "wof:name":"Borrego Llamas Antonio",
    "wof:placetype":"venue"
},
  "geometry": {"coordinates":[-4.3073921204,37.2569732666],"type":"Point"}
}