{
  "type": "Feature",
  "properties": {
    "addr:full":"Calle de Manuel Aza\u00d1a, 57 Valladolid Valladolid 47014",
    "addr:housenumber":"57",
    "addr:postcode":"47014",
    "addr:street":"Calle De Manuel Azan\u0303A",
    "iso:country":"ES",
    "sg:address":"Calle de Manuel Aza\u00d1a, 57",
    "sg:city":"Valladolid",
    "sg:orig_category":"Cajas De Ahorro",
    "sg:phone":"+34 983 38 08 80",
    "sg:postcode":"47014",
    "sg:province":"Valladolid",
    "sg:website":"www.cajadeburgos.es",
    "wof:name":"Caja De Ahorros Municipal De Burgos",
    "wof:placetype":"venue"
},
  "geometry": {"coordinates":[-4.7613558769,41.6360397339],"type":"Point"}
}