{
  "type": "Feature",
  "properties": {
    "addr:full":"Av Barcelona, 126 Terrassa Barcelona 08222",
    "addr:housenumber":"126",
    "addr:postcode":"08222",
    "addr:street":"Av Barcelona",
    "iso:country":"ES",
    "sg:address":"Av Barcelona, 126",
    "sg:city":"Terrassa",
    "sg:orig_category":"Comercio, Reparaci\u00d3n De Motocicletas, Bicicletas Y Piezas Sueltas",
    "sg:phone":"+34 937 85 42 38",
    "sg:postcode":"08222",
    "sg:province":"Barcelona",
    "wof:name":"Julibert Poyo Jaume",
    "wof:placetype":"venue"
},
  "geometry": {"coordinates":[2.0278980732,41.5627784729],"type":"Point"}
}