{
  "type": "Feature",
  "properties": {
    "iso:country":"ES",
    "sg:address":"Calle de San Vicente, 3",
    "sg:city":"Talavera Reina",
    "sg:orig_category":"Agencias Y Agentes Comerciales, Representantes",
    "sg:phone":"+34 925 80 94 10",
    "sg:postcode":"45600",
    "sg:province":"Toledo",
    "wof:name":"Aguado Ollero Jose Maria",
    "wof:placetype":"venue"
},
  "geometry": {"coordinates":[-4.8283753395,39.9653015137],"type":"Point"}
}