{
  "type": "Feature",
  "properties": {
    "iso:country":"ES",
    "sg:address":"Calle de Ca\u00d1ada Real, 6",
    "sg:city":"Berrioplano",
    "sg:orig_category":"Puros, Cigarrillos Y Tabaco (fabricaci\u00d3n, Al Por Mayor)",
    "sg:phone":"+34 948 30 90 50",
    "sg:postcode":"31195",
    "sg:province":"Navarra",
    "sg:website":"www.logista.es",
    "wof:name":"Gomez-pineda Goizueta Alfonso",
    "wof:placetype":"venue"
},
  "geometry": {"coordinates":[-1.6875333786,42.8469352722],"type":"Point"}
}