{
  "type": "Feature",
  "properties": {
    "addr:full":"Avgd Maria Jolonch (de), 4 Agramunt Lleida 25310",
    "addr:postcode":"25310",
    "iso:country":"ES",
    "sg:address":"Avgd Maria Jolonch (de), 4",
    "sg:city":"Agramunt",
    "sg:orig_category":"Agencias De Viajes",
    "sg:phone":"+34 973 39 26 32",
    "sg:postcode":"25310",
    "sg:province":"Lleida",
    "wof:name":"Viatges Gris Expres S.l",
    "wof:placetype":"venue"
},
  "geometry": {"coordinates":[1.0975320339,41.7861404419],"type":"Point"}
}