{
  "type": "Feature",
  "properties": {
    "addr:full":"Calle de San Antonio, 19 Almansa Albacete 02640",
    "addr:housenumber":"19",
    "addr:postcode":"02640",
    "addr:street":"Calle De San Antonio",
    "iso:country":"ES",
    "sg:address":"Calle de San Antonio, 19",
    "sg:city":"Almansa",
    "sg:orig_category":"Empresas De Carpinter\u00cda De Madera",
    "sg:phone":"+34 967 34 07 40",
    "sg:postcode":"02640",
    "sg:province":"Albacete",
    "wof:name":"Carpinteria Gil Almansa S.l.",
    "wof:placetype":"venue"
},
  "geometry": {"coordinates":[-1.0997710228,38.8684234619],"type":"Point"}
}