{
  "type": "Feature",
  "properties": {
    "iso:country":"ES",
    "sg:address":"El Calvario, 12",
    "sg:city":"Silos, Los",
    "sg:orig_category":"\u00c1rboles Frutales",
    "sg:phone":"+34 922 84 18 09",
    "sg:postcode":"38470",
    "sg:province":"Santa Cruz De Tenerife",
    "wof:name":"S.a.t.frutas Proa(euro Platano",
    "wof:placetype":"venue"
},
  "geometry": {"coordinates":[-16.8013553619,28.3545227051],"type":"Point"}
}