{
  "type": "Feature",
  "properties": {
    "iso:country":"ES",
    "sg:address":"Calle de Brasil, 18",
    "sg:city":"Motril",
    "sg:orig_category":"Iglesias Cristianas Diversas",
    "sg:phone":"+34 958 82 18 81",
    "sg:postcode":"18600",
    "sg:province":"Granada",
    "wof:name":"Testigos Cristianos De Jehova",
    "wof:placetype":"venue"
},
  "geometry": {"coordinates":[-3.5153489113,36.7504692078],"type":"Point"}
}