{
  "type": "Feature",
  "properties": {
    "iso:country":"ES",
    "sg:address":"Avgd Colon, 12",
    "sg:city":"Alcasser",
    "sg:orig_category":"Molduras, Junquillos, Listones Y Molduras Perforadas",
    "sg:phone":"+34 961 23 52 43",
    "sg:postcode":"46290",
    "sg:province":"Valencia",
    "wof:name":"Saiz Saiz Juan Carlos",
    "wof:placetype":"venue"
},
  "geometry": {"coordinates":[-0.4453490078,39.3651695251],"type":"Point"}
}