{
  "type": "Feature",
  "properties": {
    "iso:country":"ES",
    "sg:address":"Carrer de Alqueria Blanca, 11",
    "sg:city":"Secar De La Real",
    "sg:orig_category":"Arquitectos",
    "sg:phone":"+34 971 76 95 02",
    "sg:postcode":"07010",
    "sg:province":"Islas Baleares",
    "wof:name":"Pascual Munar Andres",
    "wof:placetype":"venue"
},
  "geometry": {"coordinates":[2.6345620155,39.6081962585],"type":"Point"}
}