{
  "type": "Feature",
  "properties": {
    "iso:country":"ES",
    "sg:address":"Calle de Doctor Ferran, 68",
    "sg:city":"Alzira",
    "sg:orig_category":"Talasoterapia",
    "sg:phone":"+34 962 22 99 33",
    "sg:postcode":"46600",
    "sg:province":"Valencia",
    "wof:name":"Altius Gestion De Instalaciones Deportivas S.l.",
    "wof:placetype":"venue"
},
  "geometry": {"coordinates":[-0.4328874052,39.1543807983],"type":"Point"}
}