{
  "type": "Feature",
  "properties": {
    "iso:country":"ES",
    "sg:address":"Carrer de Berenguer De Palou (de), 6",
    "sg:city":"Salou",
    "sg:orig_category":"Molduras, Junquillos, Listones Y Molduras Perforadas",
    "sg:phone":"+34 977 38 84 03",
    "sg:postcode":"43840",
    "sg:province":"Tarragona",
    "wof:name":"Gonzalez Iglesias Alexandre",
    "wof:placetype":"venue"
},
  "geometry": {"coordinates":[1.1322300434,41.0799026489],"type":"Point"}
}