{
  "type": "Feature",
  "properties": {
    "addr:full":"Calle de Tomas Zerolo, 25 Orotava Santa Cruz De Tenerife 38300",
    "addr:housenumber":"25",
    "addr:postcode":"38300",
    "addr:street":"Calle De Tomas Zerolo",
    "iso:country":"ES",
    "sg:address":"Calle de Tomas Zerolo, 25",
    "sg:city":"Orotava",
    "sg:orig_category":"Asociaciones, Instituciones De Consumidores Y Usuarios",
    "sg:phone":"+34 922 33 04 17",
    "sg:postcode":"38300",
    "sg:province":"Santa Cruz De Tenerife",
    "wof:name":"Asociacion De Amas De Casa De Consumidores Atlantica",
    "wof:placetype":"venue"
},
  "geometry": {"coordinates":[-16.5247764587,28.3919849396],"type":"Point"}
}