{
  "type": "Feature",
  "properties": {
    "iso:country":"ES",
    "sg:address":"Calle de Odra, 6",
    "sg:city":"Bosque",
    "sg:orig_category":"Inversiones",
    "sg:phone":"+34 916 16 72 76",
    "sg:postcode":"28670",
    "sg:province":"Madrid",
    "wof:name":"Gestu-3 S.l.",
    "wof:placetype":"venue"
},
  "geometry": {"coordinates":[-3.9280819893,40.3852920532],"type":"Point"}
}