{
  "type": "Feature",
  "properties": {
    "addr:full":"Pl Jaume I, 12 Granollers Barcelona 08402",
    "addr:housenumber":"12",
    "addr:postcode":"08402",
    "addr:street":"Pl;I",
    "iso:country":"ES",
    "sg:address":"Pl Jaume I, 12",
    "sg:city":"Granollers",
    "sg:orig_category":"Servicios Gsm",
    "sg:phone":"+34 938 70 54 54",
    "sg:postcode":"08402",
    "sg:province":"Barcelona",
    "wof:name":"Telefonia Danti S.l.",
    "wof:placetype":"venue"
},
  "geometry": {"coordinates":[2.2889099121,41.6079521179],"type":"Point"}
}