{
  "type": "Feature",
  "properties": {
    "iso:country":"ES",
    "sg:address":"Avda Fermina Sevillano, S/n",
    "sg:city":"Madrid",
    "sg:orig_category":"Transportes Especiales",
    "sg:phone":"+34 913 29 17 68",
    "sg:postcode":"28022",
    "sg:province":"Madrid",
    "sg:website":"www.tgadi.com",
    "wof:name":"Transportes Gadi S.l.",
    "wof:placetype":"venue"
},
  "geometry": {"coordinates":[-3.5656909943,40.4471359253],"type":"Point"}
}