{
  "type": "Feature",
  "properties": {
    "iso:country":"ES",
    "sg:address":"Pl Las Vi\u00f1uelas, 1",
    "sg:city":"Losar Vera",
    "sg:orig_category":"Bancos",
    "sg:phone":"+34 927 57 04 91",
    "sg:postcode":"10460",
    "sg:province":"C\u00e1ceres",
    "sg:website":"www.bancosimeon.com",
    "wof:name":"Banco Caixa Geral S.a.",
    "wof:placetype":"venue"
},
  "geometry": {"coordinates":[-5.6067008972,40.1221199036],"type":"Point"}
}