{
  "type": "Feature",
  "properties": {
    "addr:full":"Carrer de Mariano Benlliure, 7 Ondara Alicante 03760",
    "addr:housenumber":"7",
    "addr:postcode":"03760",
    "addr:street":"Carrer De Mariano Benlliure",
    "iso:country":"ES",
    "sg:address":"Carrer de Mariano Benlliure, 7",
    "sg:city":"Ondara",
    "sg:orig_category":"Flores Y Plantas Naturales (al Por Mayor)",
    "sg:phone":"+34 966 47 62 52",
    "sg:postcode":"03760",
    "sg:province":"Alicante",
    "wof:name":"Ausina Llacer Angeles",
    "wof:placetype":"venue"
},
  "geometry": {"coordinates":[0.0142099997,38.8283500671],"type":"Point"}
}