{
  "type": "Feature",
  "properties": {
    "addr:full":"Uriburu Kalea, 12 Arrasate Guip\u00f9zcoa 20500",
    "addr:housenumber":"12",
    "addr:postcode":"20500",
    "addr:street":"Uriburu Kalea;Guipu\u0300Zcoa",
    "iso:country":"ES",
    "sg:address":"Uriburu Kalea, 12",
    "sg:city":"Arrasate",
    "sg:orig_category":"Sociedades, Compa\u00d1\u00cdas Aseguradoras",
    "sg:phone":"+34 943 79 60 08",
    "sg:postcode":"20500",
    "sg:province":"Guip\u00f9zcoa",
    "wof:name":"Conde Prol Andoni",
    "wof:placetype":"venue"
},
  "geometry": {"coordinates":[-2.4995980263,43.0621681213],"type":"Point"}
}