{
  "type": "Feature",
  "properties": {
    "iso:country":"ES",
    "sg:address":"Calle de Division Azul, 2",
    "sg:city":"Coru\u00d1a",
    "sg:orig_category":"Arquitectos",
    "sg:phone":"+34 981 25 51 72",
    "sg:postcode":"15005",
    "sg:province":"A Coru\u00f1a",
    "wof:name":"Torres Padin Jose Luis",
    "wof:placetype":"venue"
},
  "geometry": {"coordinates":[-8.4074115753,43.3607177734],"type":"Point"}
}