{
  "type": "Feature",
  "properties": {
    "addr:full":"Avda Juan Carlos I, 53 Santiago Murcia 30800",
    "addr:housenumber":"53",
    "addr:postcode":"30800",
    "addr:street":"Avda Juan Carlos I",
    "iso:country":"ES",
    "sg:address":"Avda Juan Carlos I, 53",
    "sg:city":"Santiago",
    "sg:orig_category":"Zapatos (al Por Menor)",
    "sg:phone":"+34 968 47 25 97",
    "sg:postcode":"30800",
    "sg:province":"Murcia",
    "wof:name":"Rubio Gutierrez Maria Luisa",
    "wof:placetype":"venue"
},
  "geometry": {"coordinates":[-1.6905640364,37.680557251],"type":"Point"}
}