{
  "type": "Feature",
  "properties": {
    "addr:full":"Av Saloria, 71 Seu D'urgell Lleida 25700",
    "addr:housenumber":"71",
    "addr:postcode":"25700",
    "addr:street":"Av Saloria",
    "iso:country":"ES",
    "sg:address":"Av Saloria, 71",
    "sg:city":"Seu D'urgell",
    "sg:orig_category":"Electrodom\u00c9sticos (al Por Menor)",
    "sg:phone":"+34 973 35 32 02",
    "sg:postcode":"25700",
    "sg:province":"Lleida",
    "wof:name":"Colell Vidal Jose",
    "wof:placetype":"venue"
},
  "geometry": {"coordinates":[0.6457189918,41.6027946472],"type":"Point"}
}