{
  "type": "Feature",
  "properties": {
    "iso:country":"ES",
    "sg:address":"Calle de Don Miguel Eza, 15",
    "sg:city":"Tudela",
    "sg:orig_category":"Bazares, Art\u00cdculos De Limpieza Y De Cocina (al Por Menor)",
    "sg:phone":"+34 948 82 01 93",
    "sg:postcode":"31500",
    "sg:province":"Navarra",
    "wof:name":"Melero Almacenes S.l.",
    "wof:placetype":"venue"
},
  "geometry": {"coordinates":[-1.6045444012,42.0600509644],"type":"Point"}
}