{
  "type": "Feature",
  "properties": {
    "addr:full":"Carr Sant Joan Baptista La Salle, 38 Girona Girona 17002",
    "addr:housenumber":"38",
    "addr:postcode":"17002",
    "addr:street":"Carr Sant Joan Baptista La Salle",
    "iso:country":"ES",
    "sg:address":"Carr Sant Joan Baptista La Salle, 38",
    "sg:city":"Girona",
    "sg:orig_category":"Venta, Colocaci\u00d3n De Autoradios",
    "sg:phone":"+34 972 22 30 40",
    "sg:postcode":"17002",
    "sg:province":"Girona",
    "wof:name":"Auto-radio Tecno-so S.l.",
    "wof:placetype":"venue"
},
  "geometry": {"coordinates":[2.8181300163,41.9780273438],"type":"Point"}
}