{
  "type": "Feature",
  "properties": {
    "iso:country":"ES",
    "sg:address":"Calle de Magistral Dominguez, 7",
    "sg:city":"Almeria",
    "sg:orig_category":"Agencias De Viajes",
    "sg:phone":"+34 950 26 84 93",
    "sg:postcode":"04003",
    "sg:province":"Almer\u00eda",
    "sg:website":"www.viajesvertical.com",
    "wof:name":"Hernandez Granados Augusto",
    "wof:placetype":"venue"
},
  "geometry": {"coordinates":[-2.4643969536,36.8429374695],"type":"Point"}
}