{
  "type": "Feature",
  "properties": {
    "addr:full":"Carrer de Maria Vidal (de), 204 Vilassar De Mar Barcelona 08340",
    "addr:housenumber":"204",
    "addr:postcode":"08340",
    "addr:street":"Carrer De Maria Vidal De",
    "iso:country":"ES",
    "sg:address":"Carrer de Maria Vidal (de), 204",
    "sg:city":"Vilassar De Mar",
    "sg:orig_category":"Reposter\u00cdas",
    "sg:phone":"+34 937 59 58 40",
    "sg:postcode":"08340",
    "sg:province":"Barcelona",
    "wof:name":"Panificadora Santa Rita S.l.",
    "wof:placetype":"venue"
},
  "geometry": {"coordinates":[2.3879899979,41.5020217896],"type":"Point"}
}