{
  "type": "Feature",
  "properties": {
    "addr:full":"Calle de Tocina, 55 Viso Del Alcor Sevilla 41520",
    "addr:housenumber":"55",
    "addr:postcode":"41520",
    "addr:street":"Calle De Tocina",
    "iso:country":"ES",
    "sg:address":"Calle de Tocina, 55",
    "sg:city":"Viso Del Alcor",
    "sg:orig_category":"Inform\u00c1tica (estudios, Servicios, Asesor\u00cda, Formaci\u00d3n)",
    "sg:phone":"+34 955 74 04 71",
    "sg:postcode":"41520",
    "sg:province":"Sevilla",
    "sg:website":"www.compiuter.com",
    "wof:name":"Servicios Informaticos Pavon S.l.",
    "wof:placetype":"venue"
},
  "geometry": {"coordinates":[-5.7213392258,37.3916664124],"type":"Point"}
}