{
  "type": "Feature",
  "properties": {
    "iso:country":"ES",
    "sg:address":"Calle de Puerta De Murcia, 4",
    "sg:city":"Cartagena",
    "sg:orig_category":"\u00d3ptica: Instrumentos (fabricaci\u00d3n)",
    "sg:phone":"+34 968 50 93 15",
    "sg:postcode":"30201",
    "sg:province":"Murcia",
    "wof:name":"General Optica S.a.",
    "wof:placetype":"venue"
},
  "geometry": {"coordinates":[-0.9871510267,37.6022605896],"type":"Point"}
}