{
  "type": "Feature",
  "properties": {
    "iso:country":"ES",
    "sg:address":"Calle de Max Planck, S/n",
    "sg:city":"Sevilla",
    "sg:orig_category":"Inform\u00c1tica (estudios, Servicios, Asesor\u00cda, Formaci\u00d3n)",
    "sg:phone":"+34 954 99 04 10",
    "sg:postcode":"41092",
    "sg:province":"Sevilla",
    "wof:name":"S Y H S. A.",
    "wof:placetype":"venue"
},
  "geometry": {"coordinates":[-6.0053639412,37.4032363892],"type":"Point"}
}