{
  "type": "Feature",
  "properties": {
    "addr:full":"Calle de Casino, 1 Pastrana Guadalajara 19100",
    "addr:housenumber":"1",
    "addr:postcode":"19100",
    "addr:street":"Calle De Casino",
    "iso:country":"ES",
    "sg:address":"Calle de Casino, 1",
    "sg:city":"Pastrana",
    "sg:orig_category":"Notarios",
    "sg:phone":"+34 949 37 11 25",
    "sg:postcode":"19100",
    "sg:province":"Guadalajara",
    "wof:name":"Arangonzillo Ibeas Maria Alicia",
    "wof:placetype":"venue"
},
  "geometry": {"coordinates":[-2.9231226444,40.4178276062],"type":"Point"}
}