{
  "type": "Feature",
  "properties": {
    "iso:country":"ES",
    "sg:address":"Calle de Bengolea, 21",
    "sg:city":"San Vicente De Barakaldo",
    "sg:orig_category":"Comerciantes Al Por Mayor De Vinos, Licores Y Alcoholes",
    "sg:phone":"+34 944 99 91 83",
    "sg:postcode":"48903",
    "sg:province":"Vizcaya",
    "wof:name":"Barbazan Blanco Carlos",
    "wof:placetype":"venue"
},
  "geometry": {"coordinates":[-2.9960589409,43.2807235718],"type":"Point"}
}