{
  "type": "Feature",
  "properties": {
    "iso:country":"ES",
    "sg:address":"Ctra Ribes, Km. 0049,5",
    "sg:city":"Aiguafreda",
    "sg:orig_category":"Venta, Instalaci\u00d3n, Mantenimiento De Chimeneas De Interior Y Accesorios",
    "sg:phone":"+34 938 44 07 18",
    "sg:postcode":"08591",
    "sg:province":"Barcelona",
    "wof:name":"Tercota S.l.",
    "wof:placetype":"venue"
},
  "geometry": {"coordinates":[2.2465429306,41.7779464722],"type":"Point"}
}