{
  "type": "Feature",
  "properties": {
    "iso:country":"ES",
    "sg:address":"Cami Fondo, 6",
    "sg:city":"Burriana",
    "sg:orig_category":"Empresas De Carpinter\u00cda De Madera",
    "sg:phone":"+34 964 51 16 22",
    "sg:postcode":"12530",
    "sg:province":"Castell\u00f3n",
    "wof:name":"Bou Llorens Felix",
    "wof:placetype":"venue"
},
  "geometry": {"coordinates":[-0.0671259984,39.8696899414],"type":"Point"}
}