{
  "type": "Feature",
  "properties": {
    "addr:full":"Avda Cid, 32 Valencia Valencia 46018",
    "addr:housenumber":"32",
    "addr:postcode":"46018",
    "addr:street":"Avda Cid",
    "iso:country":"ES",
    "sg:address":"Avda Cid, 32",
    "sg:city":"Valencia",
    "sg:orig_category":"Asesor\u00cda De Formaci\u00d3n Y Gesti\u00d3n De Personal",
    "sg:phone":"+34 963 82 50 81",
    "sg:postcode":"46018",
    "sg:province":"Valencia",
    "wof:name":"United Services Spain Back-office S.l.",
    "wof:placetype":"venue"
},
  "geometry": {"coordinates":[-0.3946590126,39.4679679871],"type":"Point"}
}