{
  "type": "Feature",
  "properties": {
    "addr:full":"Cno Torre, S/n El Raal Murcia 30139",
    "addr:housenumber":"s / n",
    "addr:postcode":"30139",
    "addr:street":"Cno Torre",
    "iso:country":"ES",
    "sg:address":"Cno Torre, S/n",
    "sg:city":"El Raal",
    "sg:orig_category":"Centros De Educaci\u00d3n Especial",
    "sg:phone":"+34 968 60 15 54",
    "sg:postcode":"30139",
    "sg:province":"Murcia",
    "wof:name":"Comunidad Autonoma De La Region De Murcia",
    "wof:placetype":"venue"
},
  "geometry": {"coordinates":[-1.0326590538,38.0375366211],"type":"Point"}
}