{
  "type": "Feature",
  "properties": {
    "addr:full":"Carrer de Pau, 2 Vendrell Tarragona 43700",
    "addr:housenumber":"2",
    "addr:postcode":"43700",
    "addr:street":"Carrer De Pau",
    "iso:country":"ES",
    "sg:address":"Carrer de Pau, 2",
    "sg:city":"Vendrell",
    "sg:orig_category":"Organizaciones Internacionales",
    "sg:phone":"+34 977 66 21 93",
    "sg:postcode":"43700",
    "sg:province":"Tarragona",
    "wof:name":"Caritas Diocesana De Tarragona",
    "wof:placetype":"venue"
},
  "geometry": {"coordinates":[1.5340130329,41.222618103],"type":"Point"}
}