{
  "type": "Feature",
  "properties": {
    "addr:full":"Carrer de Joan Bosch, 2 S. Andreu Barca Barcelona 08740",
    "addr:housenumber":"2",
    "addr:postcode":"08740",
    "addr:street":"Carrer De Joan Bosch;S. Andreu;Barcelona",
    "iso:country":"ES",
    "sg:address":"Carrer de Joan Bosch, 2",
    "sg:city":"S. Andreu Barca",
    "sg:orig_category":"M\u00c9dicos: Pediatr\u00cda. Enfermedades De Los Ni\u00d1os",
    "sg:phone":"+34 936 82 17 28",
    "sg:postcode":"08740",
    "sg:province":"Barcelona",
    "wof:name":"Elettrico Persico Anna",
    "wof:placetype":"venue"
},
  "geometry": {"coordinates":[1.9744470119,41.4470100403],"type":"Point"}
}