{
  "type": "Feature",
  "properties": {
    "addr:full":"Pla\u00c7 Major, 4 Albesa Lleida 25135",
    "addr:housenumber":"4",
    "addr:postcode":"25135",
    "iso:country":"ES",
    "sg:address":"Pla\u00c7 Major, 4",
    "sg:city":"Albesa",
    "sg:orig_category":"Farmacias",
    "sg:phone":"+34 973 18 60 33",
    "sg:postcode":"25135",
    "sg:province":"Lleida",
    "wof:name":"Macia Parisi Teresa",
    "wof:placetype":"venue"
},
  "geometry": {"coordinates":[0.6678177118,41.7686653137],"type":"Point"}
}