{
  "type": "Feature",
  "properties": {
    "addr:full":"Calle de Ramon Y Cajal, S/n Coru\u00d1a La Coru\u00f1a 15006",
    "addr:housenumber":"s",
    "addr:postcode":"15006",
    "addr:street":"Calle De Ramon Y Cajal;/ N Corun\u0303A La Corun\u0303A",
    "iso:country":"ES",
    "sg:address":"Calle de Ramon Y Cajal, S/n",
    "sg:city":"Coru\u00d1a",
    "sg:orig_category":"Panader\u00cdas, Panader\u00cdas",
    "sg:phone":"+34 981 23 97 69",
    "sg:postcode":"15006",
    "sg:province":"La Coru\u00f1a",
    "wof:name":"Gonzalez Pinos Ismael",
    "wof:placetype":"venue"
},
  "geometry": {"coordinates":[-8.4033336639,43.3547935486],"type":"Point"}
}