{
  "type": "Feature",
  "properties": {
    "addr:full":"Av Gabriel Roca, 41 Palma Islas Baleares 07014",
    "addr:housenumber":"41",
    "addr:postcode":"07014",
    "addr:street":"Av Gabriel Roca",
    "iso:country":"ES",
    "sg:address":"Av Gabriel Roca, 41",
    "sg:city":"Palma",
    "sg:orig_category":"Centros De Coordinaci\u00d3n",
    "sg:phone":"+34 971 28 49 06",
    "sg:postcode":"07014",
    "sg:province":"Islas Baleares",
    "wof:name":"Miolal Gestion Gastronomica S.l. Unipersonal",
    "wof:placetype":"venue"
},
  "geometry": {"coordinates":[2.6261119843,39.5595054626],"type":"Point"}
}