{
  "type": "Feature",
  "properties": {
    "addr:full":"Rua Pazos Fontenla, 11 Bueu Pontevedra 36930",
    "addr:housenumber":"11",
    "addr:postcode":"36930",
    "addr:street":"Rua Pazos Fontenla",
    "iso:country":"ES",
    "sg:address":"Rua Pazos Fontenla, 11",
    "sg:city":"Bueu",
    "sg:orig_category":"Carnicer\u00cdas, Carnicer\u00cdas",
    "sg:phone":"+34 986 32 07 55",
    "sg:postcode":"36930",
    "sg:province":"Pontevedra",
    "wof:name":"Gra\u00f1a Gra\u00f1a Antonio Lorenzo",
    "wof:placetype":"venue"
},
  "geometry": {"coordinates":[-8.7825784683,42.3263168335],"type":"Point"}
}