{
  "type": "Feature",
  "properties": {
    "iso:country":"ES",
    "sg:address":"Calle de Palleter, S/n",
    "sg:city":"Puerto",
    "sg:orig_category":"Transportes Por Carretera: Lotes Completos, Mercanc\u00cdas Diversas",
    "sg:phone":"+34 962 68 31 80",
    "sg:postcode":"46520",
    "sg:province":"Valencia",
    "wof:name":"Consum Sociedad Cooperativa Limitada",
    "wof:placetype":"venue"
},
  "geometry": {"coordinates":[-0.2261590064,39.6625061035],"type":"Point"}
}