{
  "type": "Feature",
  "properties": {
    "addr:full":"Av Parc Tecnologic, 4 Cerdanyola Valles Barcelona 08290",
    "addr:housenumber":"4",
    "addr:postcode":"08290",
    "addr:street":"Av Parc Tecnologic;Valles Barcelona",
    "iso:country":"ES",
    "sg:address":"Av Parc Tecnologic, 4",
    "sg:city":"Cerdanyola Valles",
    "sg:orig_category":"Venta, Colocaci\u00d3n De Amortiguadores",
    "sg:phone":"+34 935 88 27 12",
    "sg:postcode":"08290",
    "sg:province":"Barcelona",
    "sg:website":"www.sogefifiltration.com",
    "wof:name":"Sogefi Filtration S.a.",
    "wof:placetype":"venue"
},
  "geometry": {"coordinates":[2.1242799759,41.4854507446],"type":"Point"}
}