{
  "type": "Feature",
  "properties": {
    "iso:country":"ES",
    "sg:address":"Plaz Espa\u00d1a, 5",
    "sg:city":"Valencia",
    "sg:orig_category":"Cl\u00cdnicas Dentales",
    "sg:phone":"+34 963 80 34 65",
    "sg:postcode":"46007",
    "sg:province":"Valencia",
    "wof:name":"Esorib S.l.",
    "wof:placetype":"venue"
},
  "geometry": {"coordinates":[-0.3812130094,39.4658088684],"type":"Point"}
}