{
  "type": "Feature",
  "properties": {
    "addr:full":"Avda A\u00d1orga De, 44 A\u00d1orga Guip\u00f9zcoa 20009",
    "addr:housenumber":"44",
    "addr:postcode":"20009",
    "addr:street":"Avda An\u0303Orga De;Guipu\u0300Zcoa",
    "iso:country":"ES",
    "sg:address":"Avda A\u00d1orga De, 44",
    "sg:city":"A\u00d1orga",
    "sg:orig_category":"Asociaciones, Organismos Culturales Y Socioeducativos",
    "sg:phone":"+34 943 36 37 91",
    "sg:postcode":"20009",
    "sg:province":"Guip\u00f9zcoa",
    "wof:name":"A\u00f1orga Kultu Etakirol Elkartea",
    "wof:placetype":"venue"
},
  "geometry": {"coordinates":[-1.9952147007,43.2915000916],"type":"Point"}
}