{
  "type": "Feature",
  "properties": {
    "addr:full":"Calle de Poeta Sanchez Bautista, S/n Llano De Brujas Murcia 30161",
    "addr:housenumber":"s / n",
    "addr:postcode":"30161",
    "addr:street":"Calle De Poeta Sanchez Bautista",
    "iso:country":"ES",
    "sg:address":"Calle de Poeta Sanchez Bautista, S/n",
    "sg:city":"Llano De Brujas",
    "sg:orig_category":"Iglesia Cat\u00d3lica",
    "sg:phone":"+34 968 81 14 13",
    "sg:postcode":"30161",
    "sg:province":"Murcia",
    "wof:name":"Parroquia Nuestra Se\u00f1ora De Las Buenas Lagrimas",
    "wof:placetype":"venue"
},
  "geometry": {"coordinates":[-1.0712989569,38.005241394],"type":"Point"}
}