{
  "type": "Feature",
  "properties": {
    "iso:country":"ES",
    "sg:address":"Paris, 1",
    "sg:city":"Denia",
    "sg:orig_category":"Empresas De Pintura Y Revestimientos",
    "sg:phone":"+34 965 78 28 22",
    "sg:postcode":"03700",
    "sg:province":"Alicante",
    "wof:name":"Morera Cervera Joaquin",
    "wof:placetype":"venue"
},
  "geometry": {"coordinates":[0.1036920026,38.8363876343],"type":"Point"}
}