{
  "type": "Feature",
  "properties": {
    "addr:full":"Carrer de Pallars, 489 Barcelona Barcelona 08019",
    "addr:housenumber":"489",
    "addr:postcode":"08019",
    "addr:street":"Carrer De Pallars",
    "iso:country":"ES",
    "sg:address":"Carrer de Pallars, 489",
    "sg:city":"Barcelona",
    "sg:orig_category":"Perfumer\u00cda Y Cosm\u00c9tica (fabricaci\u00d3n, Al Por Mayor)",
    "sg:phone":"+34 932 66 38 41",
    "sg:postcode":"08019",
    "sg:province":"Barcelona",
    "wof:name":"La Brosse Et Dupont Iberica S.a.",
    "wof:placetype":"venue"
},
  "geometry": {"coordinates":[2.213570118,41.4132537842],"type":"Point"}
}