{
  "type": "Feature",
  "properties": {
    "addr:full":"Calle de Masequera, 55 Palmas De Gran Canaria Las Palmas 35015",
    "addr:housenumber":"55",
    "addr:postcode":"35015",
    "addr:street":"Calle De Masequera",
    "iso:country":"ES",
    "sg:address":"Calle de Masequera, 55",
    "sg:city":"Palmas De Gran Canaria",
    "sg:orig_category":"Fabricaci\u00d3n De Pernos, Tornillos Y Clavos",
    "sg:phone":"+34 928 31 84 15",
    "sg:postcode":"35015",
    "sg:province":"Las Palmas",
    "wof:name":"Tornilleria Y Herramientas De Canarias S.l.",
    "wof:placetype":"venue"
},
  "geometry": {"coordinates":[-15.430847168,28.094751358],"type":"Point"}
}