{
  "type": "Feature",
  "properties": {
    "addr:full":"Carr Balears, 6 Vilanova I La Geltru Barcelona 08800",
    "addr:housenumber":"6",
    "addr:postcode":"08800",
    "addr:street":"Carr Balears",
    "iso:country":"ES",
    "sg:address":"Carr Balears, 6",
    "sg:city":"Vilanova I La Geltru",
    "sg:orig_category":"Transportes Por Carretera: Lotes Completos, Mercanc\u00cdas Diversas",
    "sg:phone":"+34 938 10 61 17",
    "sg:postcode":"08800",
    "sg:province":"Barcelona",
    "wof:name":"Exclusives L'unic Sl",
    "wof:placetype":"venue"
},
  "geometry": {"coordinates":[1.7301809788,41.2188491821],"type":"Point"}
}