{
  "type": "Feature",
  "properties": {
    "iso:country":"ES",
    "sg:address":"Calle de Bolivia, 25",
    "sg:city":"Sevilla",
    "sg:orig_category":"Doctores En Medicina",
    "sg:phone":"+34 954 23 88 15",
    "sg:postcode":"41012",
    "sg:province":"Sevilla",
    "wof:name":"Serrano Gomez Francisco",
    "wof:placetype":"venue"
},
  "geometry": {"coordinates":[-5.986743927,37.3524894714],"type":"Point"}
}