{
  "type": "Feature",
  "properties": {
    "iso:country":"ES",
    "sg:address":"Av Catalunya, S/n",
    "sg:city":"Sant Joan De Palamos",
    "sg:orig_category":"Cajas De Ahorro",
    "sg:phone":"+34 972 31 60 62",
    "sg:postcode":"17230",
    "sg:province":"Girona",
    "wof:name":"Caixa D'estalvis I Pensions De Barcelona",
    "wof:placetype":"venue"
},
  "geometry": {"coordinates":[3.1210360527,41.8528404236],"type":"Point"}
}