{
  "type": "Feature",
  "properties": {
    "addr:full":"Calle de Don Ramon De La Cruz, 39 Madrid Madrid 28001",
    "addr:housenumber":"39",
    "addr:postcode":"madrid;28001",
    "addr:street":"Calle De Don Ramon De La Cruz",
    "iso:country":"ES",
    "sg:address":"Calle de Don Ramon De La Cruz, 39",
    "sg:city":"Madrid",
    "sg:orig_category":"M\u00c9dicos: Medicina Legal, Peritajes M\u00c9dicos",
    "sg:phone":"+34 917 00 01 63",
    "sg:postcode":"28001",
    "sg:province":"Madrid",
    "sg:website":"www.vaypem.com",
    "wof:name":"Valoracion Y Peritajes Medicos S.l.",
    "wof:placetype":"venue"
},
  "geometry": {"coordinates":[-3.6806430817,40.4290847778],"type":"Point"}
}