{
  "type": "Feature",
  "properties": {
    "iso:country":"ES",
    "sg:address":"Calle de Camara La, 12",
    "sg:city":"Aviles",
    "sg:orig_category":"Inmobiliaria (agencias)",
    "sg:phone":"+34 985 56 22 00",
    "sg:postcode":"33402",
    "sg:province":"Asturias",
    "wof:name":"Gonzalez Galan Jorge",
    "wof:placetype":"venue"
},
  "geometry": {"coordinates":[-5.9230570793,43.5560646057],"type":"Point"}
}