{
  "type": "Feature",
  "properties": {
    "addr:full":"Calle de San Benito, 17 San Benito Santa Cruz De Tenerife 38410",
    "addr:housenumber":"17",
    "addr:postcode":"38410",
    "addr:street":"Calle De San Benito",
    "iso:country":"ES",
    "sg:address":"Calle de San Benito, 17",
    "sg:city":"San Benito",
    "sg:orig_category":"Alimentaci\u00d3n General (al Por Menor)",
    "sg:phone":"+34 922 34 38 56",
    "sg:postcode":"38410",
    "sg:province":"Santa Cruz De Tenerife",
    "wof:name":"Donate Perez Pedro",
    "wof:placetype":"venue"
},
  "geometry": {"coordinates":[-16.5807914734,28.3678131104],"type":"Point"}
}