{
  "type": "Feature",
  "properties": {
    "iso:country":"ES",
    "sg:address":"Calle de Luis De Salazar, 8",
    "sg:city":"Madrid",
    "sg:orig_category":"Molduras, Junquillos, Listones Y Molduras Perforadas",
    "sg:phone":"+34 915 19 64 49",
    "sg:postcode":"28002",
    "sg:province":"Madrid",
    "wof:name":"Eduardo Barman S.l.",
    "wof:placetype":"venue"
},
  "geometry": {"coordinates":[-3.6666820049,40.4472961426],"type":"Point"}
}