{
  "type": "Feature",
  "properties": {
    "iso:country":"ES",
    "sg:address":"Carrer de Girona, 2",
    "sg:city":"Sant Vicen\u00c7 Dels Horts",
    "sg:orig_category":"Iglesia Cat\u00d3lica",
    "sg:phone":"+34 936 76 99 10",
    "sg:postcode":"08620",
    "sg:province":"Barcelona",
    "wof:name":"Parroquia De San Jose",
    "wof:placetype":"venue"
},
  "geometry": {"coordinates":[2.002986908,41.4021453857],"type":"Point"}
}