{
  "type": "Feature",
  "properties": {
    "iso:country":"ES",
    "sg:address":"Carr Metge En Joan Garces, 43",
    "sg:city":"Cullera",
    "sg:orig_category":"Mec\u00c1nico Del Autom\u00d3vil",
    "sg:phone":"+34 961 72 53 66",
    "sg:postcode":"46400",
    "sg:province":"Valencia",
    "wof:name":"Auto Cullera S.l.",
    "wof:placetype":"venue"
},
  "geometry": {"coordinates":[-0.2538999915,39.1610603333],"type":"Point"}
}