{
  "type": "Feature",
  "properties": {
    "addr:full":"Finc Perala (la), S/n Navahermosa Toledo 45150",
    "addr:postcode":"45150",
    "addr:street":"La S / N Navahermosa",
    "iso:country":"ES",
    "sg:address":"Finc Perala (la), S/n",
    "sg:city":"Navahermosa",
    "sg:orig_category":"Venta Al Preg\u00d3n",
    "sg:phone":"+34 925 59 10 93",
    "sg:postcode":"45150",
    "sg:province":"Toledo",
    "wof:name":"Cama\u00f1o Peces Vidal",
    "wof:placetype":"venue"
},
  "geometry": {"coordinates":[-4.4862990379,39.6367340088],"type":"Point"}
}