{
  "type": "Feature",
  "properties": {
    "addr:full":"Calle de Zubiaur, 5 Llodio \u00c1lava 01400",
    "addr:housenumber":"5",
    "addr:postcode":"01400",
    "addr:street":"Calle De Zubiaur",
    "iso:country":"ES",
    "sg:address":"Calle de Zubiaur, 5",
    "sg:city":"Llodio",
    "sg:orig_category":"Ense\u00d1anza: Idiomas",
    "sg:phone":"+34 946 72 67 22",
    "sg:postcode":"01400",
    "sg:province":"\u00c1lava",
    "wof:name":"Euskaraz Koop. E.",
    "wof:placetype":"venue"
},
  "geometry": {"coordinates":[-2.9643659592,43.1408538818],"type":"Point"}
}