{
  "type": "Feature",
  "properties": {
    "addr:full":"Av Catalunya, 370 Palau-solita I Plegamans Barcelona 08184",
    "addr:housenumber":"370",
    "addr:postcode":"08184",
    "addr:street":"Av Catalunya",
    "iso:country":"ES",
    "sg:address":"Av Catalunya, 370",
    "sg:city":"Palau-solita I Plegamans",
    "sg:orig_category":"Negocio De Materiales De Construcci\u00d3n",
    "sg:phone":"+34 938 63 90 42",
    "sg:postcode":"08184",
    "sg:province":"Barcelona",
    "wof:name":"Ma\u00d1osa S.l.",
    "wof:placetype":"venue"
},
  "geometry": {"coordinates":[2.1805229187,41.594619751],"type":"Point"}
}