{
  "type": "Feature",
  "properties": {
    "addr:full":"Calle de Fenix, 10 Puerto De Santa Maria C\u00e1diz 11500",
    "addr:housenumber":"10",
    "addr:postcode":"11500",
    "addr:street":"Calle De Fenix;Ca\u0301Diz",
    "iso:country":"ES",
    "sg:address":"Calle de Fenix, 10",
    "sg:city":"Puerto De Santa Maria",
    "sg:orig_category":"Supermercados Y Hipermercados",
    "sg:phone":"+34 956 85 93 00",
    "sg:postcode":"11500",
    "sg:province":"C\u00e1diz",
    "wof:name":"Centro Comercial Crevillet S.l.",
    "wof:placetype":"venue"
},
  "geometry": {"coordinates":[-6.2161879539,36.607093811],"type":"Point"}
}