{
  "type": "Feature",
  "properties": {
    "addr:full":"Carrer de Sant Blai (de), 20 Tortosa Tarragona 43500",
    "addr:housenumber":"20",
    "addr:postcode":"43500",
    "addr:street":"Carrer De Sant Blai De",
    "iso:country":"ES",
    "sg:address":"Carrer de Sant Blai (de), 20",
    "sg:city":"Tortosa",
    "sg:orig_category":"Dietistas",
    "sg:phone":"+34 977 51 09 93",
    "sg:postcode":"43500",
    "sg:province":"Tarragona",
    "wof:name":"Royo Cervera Enrique",
    "wof:placetype":"venue"
},
  "geometry": {"coordinates":[0.5216069818,40.8112220764],"type":"Point"}
}