{
  "type": "Feature",
  "properties": {
    "iso:country":"ES",
    "sg:address":"Calle de Tahivilla, 13",
    "sg:city":"Pto Real",
    "sg:orig_category":"Promotores Constructores",
    "sg:phone":"+34 956 47 52 44",
    "sg:postcode":"11510",
    "sg:province":"C\u00e1diz",
    "wof:name":"Promociones Y Construcciones Portuenses",
    "wof:placetype":"venue"
},
  "geometry": {"coordinates":[-6.1757788658,36.5252418518],"type":"Point"}
}