{
  "type": "Feature",
  "properties": {
    "addr:full":"Calle de Cristo (del), S/n Soto En Cameros La Rioja 26132",
    "addr:housenumber":"/ n",
    "addr:postcode":"26132",
    "addr:street":"Calle De Cristo Del S;Rioja",
    "iso:country":"ES",
    "sg:address":"Calle de Cristo (del), S/n",
    "sg:city":"Soto En Cameros",
    "sg:orig_category":"Ense\u00d1anza, Formaci\u00d3n Profesional: Aprendizaje",
    "sg:phone":"+34 941 43 90 18",
    "sg:postcode":"26132",
    "sg:province":"La Rioja",
    "wof:name":"Ayuntamiento De Soto En Cameros",
    "wof:placetype":"venue"
},
  "geometry": {"coordinates":[-2.4268429279,42.2854347229],"type":"Point"}
}