{
  "type": "Feature",
  "properties": {
    "addr:full":"Calle de Hernan Cortes, 10 Valdelacalzada Badajoz 06185",
    "addr:housenumber":"10",
    "addr:postcode":"06185",
    "addr:street":"Calle De Hernan Cortes",
    "iso:country":"ES",
    "sg:address":"Calle de Hernan Cortes, 10",
    "sg:city":"Valdelacalzada",
    "sg:orig_category":"Semiller\u00cdas",
    "sg:phone":"+34 924 44 62 25",
    "sg:postcode":"06185",
    "sg:province":"Badajoz",
    "wof:name":"Fernandez Cobos Juan",
    "wof:placetype":"venue"
},
  "geometry": {"coordinates":[-6.7017388344,38.8889083862],"type":"Point"}
}