{
  "type": "Feature",
  "properties": {
    "iso:country":"ES",
    "sg:address":"Carrer de Cap Del Pla, 2",
    "sg:city":"Gironella",
    "sg:orig_category":"Explotaci\u00d3n De Bosques",
    "sg:phone":"+34 938 22 82 48",
    "sg:postcode":"08680",
    "sg:province":"Barcelona",
    "wof:name":"Explotaciones Forestales S.l.",
    "wof:placetype":"venue"
},
  "geometry": {"coordinates":[1.8837189674,42.042514801],"type":"Point"}
}