{
  "type": "Feature",
  "properties": {
    "addr:full":"Calle de Sorolla, 4 Miguel Esteban Toledo 45830",
    "addr:housenumber":"4",
    "addr:postcode":"45830",
    "addr:street":"Calle De Sorolla;Miguel Esteban",
    "iso:country":"ES",
    "sg:address":"Calle de Sorolla, 4",
    "sg:city":"Miguel Esteban",
    "sg:orig_category":"Muebles Y Accesorios Para Cocinas Y Cuartos De Ba\u00d1o (al Por Menor)",
    "sg:phone":"+34 925 56 74 39",
    "sg:postcode":"45830",
    "sg:province":"Toledo",
    "wof:name":"Servicios Fresnada Boldo S.l.",
    "wof:placetype":"venue"
},
  "geometry": {"coordinates":[-3.0804009438,39.5203399658],"type":"Point"}
}