{
  "type": "Feature",
  "properties": {
    "iso:country":"ES",
    "sg:address":"Av Santiago Rusi\u00d1ol, 34",
    "sg:city":"Sitges",
    "sg:orig_category":"Colchones (fabricaci\u00d3n, Al Por Mayor, Al Por Menor)",
    "sg:phone":"+34 938 11 20 48",
    "sg:postcode":"08870",
    "sg:province":"Barcelona",
    "wof:name":"Berlanga Repullo Manuel",
    "wof:placetype":"venue"
},
  "geometry": {"coordinates":[1.8115119934,41.2375679016],"type":"Point"}
}