{
  "type": "Feature",
  "properties": {
    "iso:country":"ES",
    "sg:address":"Calle de San Juan, 14",
    "sg:city":"Segovia",
    "sg:orig_category":"Bares, Piano",
    "sg:phone":"+34 921 46 29 15",
    "sg:postcode":"40001",
    "sg:province":"Segovia",
    "wof:name":"Torres Sacristan Gloria",
    "wof:placetype":"venue"
},
  "geometry": {"coordinates":[-4.1177444458,40.9481887817],"type":"Point"}
}