{
  "type": "Feature",
  "properties": {
    "addr:full":"Calle de Sequeros (los), S/n Llanos Las Palmas 35330",
    "addr:postcode":"35330",
    "addr:street":"Calle De Sequeros Los S / N Llanos Las",
    "iso:country":"ES",
    "sg:address":"Calle de Sequeros (los), S/n",
    "sg:city":"Llanos",
    "sg:orig_category":"Asociaciones Y Clubs Deportivos",
    "sg:phone":"+34 928 63 25 61",
    "sg:postcode":"35330",
    "sg:province":"Las Palmas",
    "wof:name":"Lenaf Sdad. Coop.",
    "wof:placetype":"venue"
},
  "geometry": {"coordinates":[-15.5523738861,28.060464859],"type":"Point"}
}