{
  "type": "Feature",
  "properties": {
    "iso:country":"ES",
    "sg:address":"Calle de Marques De Monasterio, 5",
    "sg:city":"Madrid",
    "sg:orig_category":"Peluquer\u00cdas, Peluquer\u00cda Mixta",
    "sg:phone":"+34 913 19 66 59",
    "sg:postcode":"28004",
    "sg:province":"Madrid",
    "wof:name":"Xiquena Peluqueros S.c.",
    "wof:placetype":"venue"
},
  "geometry": {"coordinates":[-3.6934742928,40.4230461121],"type":"Point"}
}