{
  "type": "Feature",
  "properties": {
    "addr:full":"Calle de Mayor, 20 Santa Cruz De Moya Cuenca 16336",
    "addr:housenumber":"20",
    "addr:postcode":"16336",
    "addr:street":"Calle De Mayor",
    "iso:country":"ES",
    "sg:address":"Calle de Mayor, 20",
    "sg:city":"Santa Cruz De Moya",
    "sg:orig_category":"Albergues",
    "sg:phone":"+34 969 36 50 75",
    "sg:postcode":"16336",
    "sg:province":"Cuenca",
    "wof:name":"Anton Moliner Julian",
    "wof:placetype":"venue"
},
  "geometry": {"coordinates":[-1.2553567886,39.9554290771],"type":"Point"}
}