{
  "type": "Feature",
  "properties": {
    "iso:country":"ES",
    "sg:address":"Cmno Hondo, 52",
    "sg:city":"Campillo",
    "sg:orig_category":"Industria Qu\u00cdmica",
    "sg:phone":"+34 968 46 32 81",
    "sg:postcode":"30815",
    "sg:province":"Murcia",
    "wof:name":"Ruiz Poveda Matias",
    "wof:placetype":"venue"
},
  "geometry": {"coordinates":[-1.6491039991,37.6809234619],"type":"Point"}
}