{
  "type": "Feature",
  "properties": {
    "addr:full":"Calle de Galtzareta Kalea, 11 Durango Vizcaya 48200",
    "addr:housenumber":"11",
    "addr:postcode":"48200",
    "addr:street":"Calle De Galtzareta Kalea",
    "iso:country":"ES",
    "sg:address":"Calle de Galtzareta Kalea, 11",
    "sg:city":"Durango",
    "sg:orig_category":"Arquitectos",
    "sg:phone":"+34 946 21 51 04",
    "sg:postcode":"48200",
    "sg:province":"Vizcaya",
    "wof:name":"Maurtua Hormaechea Carlos",
    "wof:placetype":"venue"
},
  "geometry": {"coordinates":[-2.6368091106,43.1655960083],"type":"Point"}
}