{
  "type": "Feature",
  "properties": {
    "iso:country":"ES",
    "sg:address":"Calle de Mainavas, 12",
    "sg:city":"Motril",
    "sg:orig_category":"Imprenta",
    "sg:phone":"+34 958 60 88 61",
    "sg:postcode":"18600",
    "sg:province":"Granada",
    "wof:name":"Imprenta Motril S.l.l.",
    "wof:placetype":"venue"
},
  "geometry": {"coordinates":[-3.5180089474,36.7478103638],"type":"Point"}
}