{
  "type": "Feature",
  "properties": {
    "addr:full":"Avda Se\u00d1ores Baselga, 10 Utrillas Teruel 44760",
    "addr:housenumber":"10",
    "addr:postcode":"44760",
    "addr:street":"Avda Sen\u0303Ores Baselga",
    "iso:country":"ES",
    "sg:address":"Avda Se\u00d1ores Baselga, 10",
    "sg:city":"Utrillas",
    "sg:orig_category":"Inform\u00c1tica (estudios, Servicios, Asesor\u00cda, Formaci\u00d3n)",
    "sg:phone":"+34 978 75 75 65",
    "sg:postcode":"44760",
    "sg:province":"Teruel",
    "wof:name":"Rds Informatica Siglo Xxi S.l.",
    "wof:placetype":"venue"
},
  "geometry": {"coordinates":[-0.8491280079,40.8121070862],"type":"Point"}
}