{
  "type": "Feature",
  "properties": {
    "addr:full":"Ermida, 3 Ourense Ourense 32005",
    "addr:postcode":"32005",
    "addr:street":"Ermida",
    "iso:country":"ES",
    "sg:address":"Ermida, 3",
    "sg:city":"Ourense",
    "sg:orig_category":"Contenedores (mercanc\u00cdas)",
    "sg:phone":"+34 988 22 01 98",
    "sg:postcode":"32005",
    "sg:province":"Ourense",
    "wof:name":"Sabucedo Valdes Ramon",
    "wof:placetype":"venue"
},
  "geometry": {"coordinates":[-7.8648018837,42.3221969604],"type":"Point"}
}