{
  "type": "Feature",
  "properties": {
    "addr:full":"Avda Pintor Baeza, 4 Alacant Alicante 03010",
    "addr:housenumber":"4",
    "addr:postcode":"03010",
    "addr:street":"Avda Pintor Baeza",
    "iso:country":"ES",
    "sg:address":"Avda Pintor Baeza, 4",
    "sg:city":"Alacant",
    "sg:orig_category":"Supermercados Y Hipermercados",
    "sg:phone":"+34 965 24 80 09",
    "sg:postcode":"03010",
    "sg:province":"Alicante",
    "wof:name":"Consum Sociedad Cooperativa Limitada",
    "wof:placetype":"venue"
},
  "geometry": {"coordinates":[-0.4858599901,38.3603591919],"type":"Point"}
}