{
  "type": "Feature",
  "properties": {
    "iso:country":"ES",
    "sg:address":"Ctra. Cadiz, Km. 0215,0",
    "sg:city":"Benalmadena",
    "sg:orig_category":"Enfermeras: Consultas, Atenci\u00d3n A Domicilio",
    "sg:phone":"+34 952 44 91 11",
    "sg:postcode":"29639",
    "sg:province":"M\u00e1laga",
    "wof:name":"Salas Silva Antonio",
    "wof:placetype":"venue"
},
  "geometry": {"coordinates":[-4.5734581947,36.5951728821],"type":"Point"}
}