{
  "type": "Feature",
  "properties": {
    "iso:country":"ES",
    "sg:address":"Feria Del Tres, 7",
    "sg:city":"Vilarmaior",
    "sg:orig_category":"Centros Empresariales",
    "sg:phone":"+34 981 78 19 37",
    "sg:postcode":"15637",
    "sg:province":"La Coru\u00f1a",
    "wof:name":"Mosquera Baluja Agustin",
    "wof:placetype":"venue"
},
  "geometry": {"coordinates":[-8.154045105,43.3448257446],"type":"Point"}
}