{
  "type": "Feature",
  "properties": {
    "addr:full":"Carrer de Major, 5 Riba-roja D'ebre Tarragona 43790",
    "addr:housenumber":"5",
    "addr:postcode":"43790",
    "addr:street":"Carrer De Major",
    "iso:country":"ES",
    "sg:address":"Carrer de Major, 5",
    "sg:city":"Riba-roja D'ebre",
    "sg:orig_category":"Panader\u00cdas, Panader\u00cdas",
    "sg:phone":"+34 977 41 61 07",
    "sg:postcode":"43790",
    "sg:province":"Tarragona",
    "wof:name":"Munte Hernandez Valero",
    "wof:placetype":"venue"
},
  "geometry": {"coordinates":[1.277755022,41.1211547852],"type":"Point"}
}