{
  "type": "Feature",
  "properties": {
    "iso:country":"ES",
    "sg:address":"Carrer de Sant Joan, 14",
    "sg:city":"Hospitalet Llobregat",
    "sg:orig_category":"Florister\u00cdas",
    "sg:phone":"+34 933 37 15 86",
    "sg:postcode":"08901",
    "sg:province":"Barcelona",
    "wof:name":"Floristeria Josefa Y Teresa Rovira S.c.p.",
    "wof:placetype":"venue"
},
  "geometry": {"coordinates":[2.0984220505,41.3624191284],"type":"Point"}
}