{
  "type": "Feature",
  "properties": {
    "iso:country":"ES",
    "sg:address":"Pase Nuestra Se\u00d1ora Mercedes De Roja, 26",
    "sg:city":"Medano",
    "sg:orig_category":"Bazares, Art\u00cdculos De Limpieza Y De Cocina (al Por Menor)",
    "sg:phone":"+34 922 17 72 98",
    "sg:postcode":"38612",
    "sg:province":"Santa Cruz De Tenerife",
    "wof:name":"Poco Loco Islas Canarias S.l.",
    "wof:placetype":"venue"
},
  "geometry": {"coordinates":[-16.5262241364,28.0532035828],"type":"Point"}
}