{
  "type": "Feature",
  "properties": {
    "iso:country":"ES",
    "sg:address":"Calle de Conde De Halcon, 19",
    "sg:city":"Sevilla",
    "sg:orig_category":"Mercer\u00cda, Lencer\u00cda (al Por Menor)",
    "sg:phone":"+34 954 35 19 97",
    "sg:postcode":"41008",
    "sg:province":"Sevilla",
    "wof:name":"Marmol Gomez Victor",
    "wof:placetype":"venue"
},
  "geometry": {"coordinates":[-5.9789614677,37.4046707153],"type":"Point"}
}