{
  "type": "Feature",
  "properties": {
    "iso:country":"ES",
    "sg:address":"Rua Castelao, 67",
    "sg:city":"Grove",
    "sg:orig_category":"Ropa Para Se\u00d1oras Y Caballeros (al Por Menor)",
    "sg:phone":"+34 986 73 07 62",
    "sg:postcode":"36980",
    "sg:province":"Pontevedra",
    "wof:name":"Pi\u00f1eiro Fernandez Jose Manuel",
    "wof:placetype":"venue"
},
  "geometry": {"coordinates":[-8.858259201,42.4904518127],"type":"Point"}
}