{
  "type": "Feature",
  "properties": {
    "iso:country":"ES",
    "sg:address":"Carrer de Raco, 12",
    "sg:city":"Vendrell",
    "sg:orig_category":"Librer\u00cdas",
    "sg:phone":"+34 977 66 74 51",
    "sg:postcode":"43700",
    "sg:province":"Tarragona",
    "wof:name":"Pell Soldevila Jaime",
    "wof:placetype":"venue"
},
  "geometry": {"coordinates":[1.5347859859,41.2208862305],"type":"Point"}
}