{
  "type": "Feature",
  "properties": {
    "addr:full":"Calle de Jose Rivera Forner, S/n Oropesa Castell\u00f3n 12594",
    "addr:housenumber":"s / n",
    "addr:postcode":"12594",
    "addr:street":"Calle De Jose Rivera Forner",
    "iso:country":"ES",
    "sg:address":"Calle de Jose Rivera Forner, S/n",
    "sg:city":"Oropesa",
    "sg:orig_category":"Producci\u00d3n De Abonos Y De Fertilizantes",
    "sg:phone":"+34 964 31 02 82",
    "sg:postcode":"12594",
    "sg:province":"Castell\u00f3n",
    "wof:name":"Oroagro S.l.",
    "wof:placetype":"venue"
},
  "geometry": {"coordinates":[0.1353400052,40.0945281982],"type":"Point"}
}