{
  "type": "Feature",
  "properties": {
    "iso:country":"ES",
    "sg:address":"Pase Melancolicos, 29",
    "sg:city":"Madrid",
    "sg:orig_category":"Empresas De Limpieza",
    "sg:phone":"+34 913 65 85 28",
    "sg:postcode":"28005",
    "sg:province":"Madrid",
    "wof:name":"Limpiezas Bari S.l.",
    "wof:placetype":"venue"
},
  "geometry": {"coordinates":[-3.7200260162,40.4069328308],"type":"Point"}
}