{
  "type": "Feature",
  "properties": {
    "iso:country":"ES",
    "sg:address":"Avda Zarauz (de), 26",
    "sg:city":"San Fernando De Henares",
    "sg:orig_category":"Ropa Para Ni\u00d1os (al Por Menor)",
    "sg:phone":"+34 916 72 58 77",
    "sg:postcode":"28830",
    "sg:province":"Madrid",
    "wof:name":"Gonzalez Viejo Carmen",
    "wof:placetype":"venue"
},
  "geometry": {"coordinates":[-3.5273029804,40.4188346863],"type":"Point"}
}