{
  "type": "Feature",
  "properties": {
    "iso:country":"ES",
    "sg:address":"Pl Major De La Vila, 9",
    "sg:city":"Benaguasil",
    "sg:orig_category":"Ense\u00d1ante, Direcci\u00d3n",
    "sg:phone":"+34 962 73 09 40",
    "sg:postcode":"46180",
    "sg:province":"Valencia",
    "wof:name":"Segarra Garrido Maria Teresa",
    "wof:placetype":"venue"
},
  "geometry": {"coordinates":[-0.5846890211,39.5935783386],"type":"Point"}
}