{
  "type": "Feature",
  "properties": {
    "iso:country":"ES",
    "sg:address":"Carrer de Arc De Sant Marti, 43",
    "sg:city":"Can Cebria",
    "sg:orig_category":"Fabricaci\u00d3n De Transformadores, De M\u00c1quinas Giratorias De Peque\u00d1a Y Media Potencia",
    "sg:phone":"+34 938 45 80 17",
    "sg:postcode":"08410",
    "sg:province":"Barcelona",
    "wof:name":"Flores Molano Guillermo",
    "wof:placetype":"venue"
},
  "geometry": {"coordinates":[2.2983250618,41.5506744385],"type":"Point"}
}