{
  "type": "Feature",
  "properties": {
    "addr:full":"Calle de Proyecto, 1 Requena Valencia 46340",
    "addr:housenumber":"1",
    "addr:postcode":"46340",
    "addr:street":"Calle De Proyecto",
    "iso:country":"ES",
    "sg:address":"Calle de Proyecto, 1",
    "sg:city":"Requena",
    "sg:orig_category":"Mec\u00c1nico Del Autom\u00d3vil",
    "sg:phone":"+34 962 30 44 44",
    "sg:postcode":"46340",
    "sg:province":"Valencia",
    "wof:name":"Perez Armero Enrique",
    "wof:placetype":"venue"
},
  "geometry": {"coordinates":[-1.0998990536,39.4906158447],"type":"Point"}
}