{
  "type": "Feature",
  "properties": {
    "iso:country":"ES",
    "sg:address":"Rua Montero Rios (de), 27",
    "sg:city":"Santiago De Compostela",
    "sg:classifiers":[
        {
            "category":"Personal",
            "subcategory":"Barber",
            "type":"Services"
        }
    ],
    "sg:phone":"+34 981 59 27 97",
    "sg:postcode":"15706",
    "sg:province":"La Coru\u00f1a",
    "sg:tags":[
        "caballeros",
        "de",
        "peluqueros"
    ],
    "wof:name":"Cardeso Maro\u00f1as Juan Jose",
    "wof:placetype":"venue"
},
  "geometry": {"coordinates":[-8.5470895767,42.8754463196],"type":"Point"}
}