{
  "type": "Feature",
  "properties": {
    "iso:country":"ES",
    "sg:address":"Calle de Camp De Turia, 26",
    "sg:city":"Valencia",
    "sg:orig_category":"M\u00c9dicos: Medicina General Orientada A La Acupuntura",
    "sg:phone":"+34 963 48 32 10",
    "sg:postcode":"46015",
    "sg:province":"Valencia",
    "wof:name":"Cerro Gabarrs Joaquin Antonio Del",
    "wof:placetype":"venue"
},
  "geometry": {"coordinates":[-0.404538393,39.4939002991],"type":"Point"}
}