{
  "type": "Feature",
  "properties": {
    "iso:country":"ES",
    "sg:address":"Calle de Velazquez, 2",
    "sg:city":"S. Roque",
    "sg:orig_category":"Discotecas Y Salas De Baile",
    "sg:phone":"+34 956 78 09 77",
    "sg:postcode":"11360",
    "sg:province":"C\u00e1diz",
    "wof:name":"Negocios E Inversiones Merro S.l.",
    "wof:placetype":"venue"
},
  "geometry": {"coordinates":[-5.3870692253,36.209197998],"type":"Point"}
}