{
  "type": "Feature",
  "properties": {
    "iso:country":"ES",
    "sg:address":"Calle de Herreria, 26",
    "sg:city":"Vitoria-gasteiz",
    "sg:orig_category":"Cervecer\u00cdas",
    "sg:phone":"+34 945 28 33 72",
    "sg:postcode":"01001",
    "sg:province":"\u00c1lava",
    "wof:name":"Cerveceria Gorbea C.b.",
    "wof:placetype":"venue"
},
  "geometry": {"coordinates":[-2.6743290424,42.8472900391],"type":"Point"}
}