{
  "type": "Feature",
  "properties": {
    "addr:full":"Calle de Manuel Simo, 40 Valencia Valencia 46018",
    "addr:housenumber":"40",
    "addr:postcode":"46018",
    "addr:street":"Calle De Manuel Simo",
    "iso:country":"ES",
    "sg:address":"Calle de Manuel Simo, 40",
    "sg:city":"Valencia",
    "sg:orig_category":"\u00d3ptica: Instrumentos (fabricaci\u00d3n)",
    "sg:phone":"+34 963 57 35 46",
    "sg:postcode":"46018",
    "sg:province":"Valencia",
    "wof:name":"Monserrat Ramajo Maria Del Consuelo",
    "wof:placetype":"venue"
},
  "geometry": {"coordinates":[-0.3929640055,39.4609794617],"type":"Point"}
}