{
  "type": "Feature",
  "properties": {
    "addr:full":"Rua Carlos Iii, S/n Becerrea Lugo 27640",
    "addr:housenumber":"s",
    "addr:postcode":"27640",
    "addr:street":"Rua Carlos Iii;/ N",
    "iso:country":"ES",
    "sg:address":"Rua Carlos Iii, S/n",
    "sg:city":"Becerrea",
    "sg:orig_category":"Distribuci\u00d3n De Petr\u00d3leo Y Derivados",
    "sg:phone":"+34 982 36 10 01",
    "sg:postcode":"27640",
    "sg:province":"Lugo",
    "wof:name":"Estacion De Servicio Rutancares S.l.",
    "wof:placetype":"venue"
},
  "geometry": {"coordinates":[-7.1613059044,42.8526229858],"type":"Point"}
}