{
  "type": "Feature",
  "properties": {
    "iso:country":"ES",
    "sg:address":"Calle de Conde, 24",
    "sg:city":"Ecija",
    "sg:orig_category":"Cajas De Ahorro",
    "sg:phone":"+34 954 83 21 21",
    "sg:postcode":"41400",
    "sg:province":"Sevilla",
    "wof:name":"Cajagranada",
    "wof:placetype":"venue"
},
  "geometry": {"coordinates":[-5.0821099281,37.5404319763],"type":"Point"}
}