{
  "type": "Feature",
  "properties": {
    "iso:country":"ES",
    "sg:address":"Calle de San Pio X, 34",
    "sg:city":"Pilas",
    "sg:orig_category":"Empresas De Carpinter\u00cda De Madera",
    "sg:phone":"+34 954 75 03 10",
    "sg:postcode":"41840",
    "sg:province":"Sevilla",
    "wof:name":"Campos Barragan Luis",
    "wof:placetype":"venue"
},
  "geometry": {"coordinates":[-6.2987642288,37.3032073975],"type":"Point"}
}