{
  "type": "Feature",
  "properties": {
    "iso:country":"ES",
    "sg:address":"Carr Moreres (les), 12",
    "sg:city":"Oliva",
    "sg:orig_category":"Poller\u00cda Y Caza (al Por Menor)",
    "sg:phone":"+34 962 83 98 79",
    "sg:postcode":"46780",
    "sg:province":"Valencia",
    "wof:name":"Vicente Mi\u00f1ana S.l.",
    "wof:placetype":"venue"
},
  "geometry": {"coordinates":[-0.1179220006,38.9189491272],"type":"Point"}
}