{
  "type": "Feature",
  "properties": {
    "iso:country":"ES",
    "sg:address":"Carrer de Arimon, 68",
    "sg:city":"Barcelona",
    "sg:orig_category":"Empresas De Pintura Y Revestimientos",
    "sg:phone":"+34 934 17 59 16",
    "sg:postcode":"08022",
    "sg:province":"Barcelona",
    "wof:name":"Monjonell Baquero Antonio",
    "wof:placetype":"venue"
},
  "geometry": {"coordinates":[2.1348969936,41.4026260376],"type":"Point"}
}