{
  "type": "Feature",
  "properties": {
    "addr:full":"Calle de Camino De Murcia, 39 Cieza Murcia 30530",
    "addr:housenumber":"39",
    "addr:postcode":"30530",
    "addr:street":"Calle De Camino De Murcia",
    "iso:country":"ES",
    "sg:address":"Calle de Camino De Murcia, 39",
    "sg:city":"Cieza",
    "sg:orig_category":"Estancos",
    "sg:phone":"+34 968 76 03 24",
    "sg:postcode":"30530",
    "sg:province":"Murcia",
    "wof:name":"Rodriguez Lucas Josefa",
    "wof:placetype":"venue"
},
  "geometry": {"coordinates":[-1.413844347,38.2368812561],"type":"Point"}
}