{
  "type": "Feature",
  "properties": {
    "addr:full":"Carrer de Iluro, 40 Mataro Barcelona 08302",
    "addr:housenumber":"40",
    "addr:postcode":"08302",
    "addr:street":"Carrer De Iluro",
    "iso:country":"ES",
    "sg:address":"Carrer de Iluro, 40",
    "sg:city":"Mataro",
    "sg:orig_category":"Artes Gr\u00c1ficas, Artes Pl\u00c1sticas (curso)",
    "sg:phone":"+34 937 98 56 61",
    "sg:postcode":"08302",
    "sg:province":"Barcelona",
    "wof:name":"Treballs Grafics Paco Lopez S.l.",
    "wof:placetype":"venue"
},
  "geometry": {"coordinates":[2.4396309853,41.5367469788],"type":"Point"}
}