{
  "type": "Feature",
  "properties": {
    "iso:country":"ES",
    "sg:address":"Avda Barcelona, 8",
    "sg:city":"Guadalajara",
    "sg:orig_category":"Bancos",
    "sg:phone":"+34 949 21 11 21",
    "sg:postcode":"19005",
    "sg:province":"Guadalajara",
    "sg:website":"www.lacaixa.es",
    "wof:name":"Caixa D'estalvis I Pensions De Barcelona",
    "wof:placetype":"venue"
},
  "geometry": {"coordinates":[-3.1589090824,40.6336593628],"type":"Point"}
}