{
  "type": "Feature",
  "properties": {
    "iso:country":"ES",
    "sg:address":"Domingo Unanue Plaza, 1",
    "sg:city":"Ordizia",
    "sg:orig_category":"Frutas, Legumbres Frescas Y Tempranas (al Por Menor)",
    "sg:phone":"+34 943 88 82 56",
    "sg:postcode":"20240",
    "sg:province":"Guip\u00f9zcoa",
    "wof:name":"Alonso Marin Angel",
    "wof:placetype":"venue"
},
  "geometry": {"coordinates":[-2.1782026291,43.0530815125],"type":"Point"}
}