{
  "type": "Feature",
  "properties": {
    "iso:country":"ES",
    "sg:address":"Calle de Silvestre Ochoa, 36",
    "sg:city":"Castro Urdiales",
    "sg:orig_category":"Caf\u00c9s, Bares, Cervecer\u00cdas",
    "sg:phone":"+34 942 86 48 01",
    "sg:postcode":"39700",
    "sg:province":"Cantabria",
    "wof:name":"Capitan Haddock S.cv",
    "wof:placetype":"venue"
},
  "geometry": {"coordinates":[-3.2254989147,43.3851203918],"type":"Point"}
}