{
  "type": "Feature",
  "properties": {
    "iso:country":"ES",
    "sg:address":"Carrer de Llorenc Vicens, 3",
    "sg:city":"Palma",
    "sg:orig_category":"M\u00c9dicos: Termomedicina (hidrolog\u00cda Y Climatolog\u00cda M\u00c9dicas)",
    "sg:phone":"+34 971 22 72 04",
    "sg:postcode":"07002",
    "sg:province":"Islas Baleares",
    "wof:name":"Centro De Negocios Avenidas S.l.",
    "wof:placetype":"venue"
},
  "geometry": {"coordinates":[2.6554009914,39.5737571716],"type":"Point"}
}