{
  "type": "Feature",
  "properties": {
    "iso:country":"ES",
    "sg:address":"Poligono De El Raposal, S/n",
    "sg:city":"Arnedo",
    "sg:orig_category":"Agencias Y Agentes Comerciales, Representantes",
    "sg:phone":"+34 941 38 70 89",
    "sg:postcode":"26580",
    "sg:province":"La Rioja",
    "wof:name":"Iba\u00f1ez Gonzalez Jesus Ramos",
    "wof:placetype":"venue"
},
  "geometry": {"coordinates":[-2.0899488926,42.2300453186],"type":"Point"}
}