{
  "type": "Feature",
  "properties": {
    "addr:full":"Rbla Castell, 71 Vilanova I La Geltru Barcelona 08800",
    "addr:housenumber":"71",
    "addr:postcode":"08800",
    "addr:street":"Rbla Castell",
    "iso:country":"ES",
    "sg:address":"Rbla Castell, 71",
    "sg:city":"Vilanova I La Geltru",
    "sg:orig_category":"Sociedades, Compa\u00d1\u00cdas Aseguradoras",
    "sg:phone":"+34 938 14 26 76",
    "sg:postcode":"08800",
    "sg:province":"Barcelona",
    "wof:name":"Segur-quatre S.l.",
    "wof:placetype":"venue"
},
  "geometry": {"coordinates":[1.7305459976,41.2233772278],"type":"Point"}
}