{
  "type": "Feature",
  "properties": {
    "iso:country":"ES",
    "sg:address":"Calle de Conquista, 8",
    "sg:city":"Valencia",
    "sg:orig_category":"Molduras, Junquillos, Listones Y Molduras Perforadas",
    "sg:phone":"+34 963 92 54 47",
    "sg:postcode":"46001",
    "sg:province":"Valencia",
    "wof:name":"Peris & Partner S.l.",
    "wof:placetype":"venue"
},
  "geometry": {"coordinates":[-0.3808912933,39.4759674072],"type":"Point"}
}