{
  "type": "Feature",
  "properties": {
    "addr:full":"C/ Major Del Pla, 38 Elche Alicante 03201",
    "addr:housenumber":"38",
    "addr:postcode":"03201",
    "addr:street":"C / Major Del Pla",
    "iso:country":"ES",
    "sg:address":"C/ Major Del Pla, 38",
    "sg:city":"Elche",
    "sg:orig_category":"Edici\u00d3n De Diarios, Revistas, Boletines",
    "sg:phone":"+34 965 46 01 26",
    "sg:postcode":"03201",
    "sg:province":"Alicante",
    "sg:website":"www.prensaynoticias.com",
    "wof:name":"Bloc Nacionalista Valencia",
    "wof:placetype":"venue"
},
  "geometry": {"coordinates":[-0.702647984,38.2629852295],"type":"Point"}
}