{
  "type": "Feature",
  "properties": {
    "addr:full":"Carrer de Jaume I, 27 Amposta Tarragona 43870",
    "addr:housenumber":"27",
    "addr:postcode":"43870",
    "addr:street":"Carrer De Jaume I",
    "iso:country":"ES",
    "sg:address":"Carrer de Jaume I, 27",
    "sg:city":"Amposta",
    "sg:orig_category":"Ingeniero",
    "sg:phone":"+34 977 70 49 95",
    "sg:postcode":"43870",
    "sg:province":"Tarragona",
    "wof:name":"Engitec Innovacio S.l.",
    "wof:placetype":"venue"
},
  "geometry": {"coordinates":[0.5815370083,40.7122993469],"type":"Point"}
}