{
  "type": "Feature",
  "properties": {
    "addr:full":"Calle de Ezequiel Solana, 24 Madrid Madrid 28017",
    "addr:housenumber":"24",
    "addr:postcode":"madrid;28017",
    "addr:street":"Calle De Ezequiel Solana",
    "iso:country":"ES",
    "sg:address":"Calle de Ezequiel Solana, 24",
    "sg:city":"Madrid",
    "sg:orig_category":"Agencias Y Agentes Comerciales, Representantes",
    "sg:phone":"+34 913 77 17 50",
    "sg:postcode":"28017",
    "sg:province":"Madrid",
    "wof:name":"Escudero Morales Adolfo",
    "wof:placetype":"venue"
},
  "geometry": {"coordinates":[-3.6467649937,40.4327545166],"type":"Point"}
}