{
  "type": "Feature",
  "properties": {
    "addr:full":"Calle de Camino Viejo De Leganes, 56 Madrid Madrid 28019",
    "addr:housenumber":"56",
    "addr:postcode":"madrid;28019",
    "addr:street":"Calle De Camino Viejo De Leganes",
    "iso:country":"ES",
    "sg:address":"Calle de Camino Viejo De Leganes, 56",
    "sg:city":"Madrid",
    "sg:orig_category":"Laboratorios Y Cl\u00cdnicas Veterinarias",
    "sg:phone":"+34 914 72 27 54",
    "sg:postcode":"28019",
    "sg:province":"Madrid",
    "wof:name":"Ayuso Ramos Juan Pedro",
    "wof:placetype":"venue"
},
  "geometry": {"coordinates":[-3.7266499996,40.3889656067],"type":"Point"}
}