{
  "type": "Feature",
  "properties": {
    "addr:full":"Calle de Rey Pastor, 26 Logro\u00f1o La Rioja 26005",
    "addr:housenumber":"26",
    "addr:postcode":"26005",
    "addr:street":"Calle De Rey Pastor;Rioja",
    "iso:country":"ES",
    "sg:address":"Calle de Rey Pastor, 26",
    "sg:city":"Logro\u00f1o",
    "sg:orig_category":"Asesor\u00cda Fiscal Y Jur\u00cddica",
    "sg:phone":"+34 941 20 14 34",
    "sg:postcode":"26005",
    "sg:province":"La Rioja",
    "wof:name":"Quevedo Y Montenegro Sc",
    "wof:placetype":"venue"
},
  "geometry": {"coordinates":[-2.4562220573,42.4635162354],"type":"Point"}
}