{
  "type": "Feature",
  "properties": {
    "iso:country":"ES",
    "sg:address":"Calle de Madame Curie, 4",
    "sg:city":"Grela",
    "sg:orig_category":"Ingenier\u00cda, Centros De Estudios (diversos)",
    "sg:phone":"+34 981 23 99 89",
    "sg:postcode":"15008",
    "sg:province":"A Coru\u00f1a",
    "sg:website":"www.tranor.com",
    "wof:name":"Tratamientos Del Norte S.l.",
    "wof:placetype":"venue"
},
  "geometry": {"coordinates":[-8.4512443542,43.3434753418],"type":"Point"}
}