{
  "type": "Feature",
  "properties": {
    "iso:country":"ES",
    "sg:address":"Avda Cesar Augusto, 25",
    "sg:city":"Zaragoza",
    "sg:orig_category":"Pod\u00d3logos: Pedicuros",
    "sg:phone":"+34 976 44 27 71",
    "sg:postcode":"50004",
    "sg:province":"Zaragoza",
    "wof:name":"Pueyo Marquina Jose Javier",
    "wof:placetype":"venue"
},
  "geometry": {"coordinates":[-0.8846210241,41.652961731],"type":"Point"}
}