{
  "type": "Feature",
  "properties": {
    "iso:country":"ES",
    "sg:address":"Calle de Tejerias, 4",
    "sg:city":"Alfaro",
    "sg:orig_category":"Venta, Alquiler De Toldos",
    "sg:phone":"+34 941 18 08 35",
    "sg:postcode":"26540",
    "sg:province":"La Rioja",
    "wof:name":"Tejados Maroma S.l.",
    "wof:placetype":"venue"
},
  "geometry": {"coordinates":[-1.749497056,42.1748123169],"type":"Point"}
}