{
  "type": "Feature",
  "properties": {
    "addr:full":"Carr Baro De Maials, 30 Lleida Lleida 25005",
    "addr:housenumber":"30",
    "addr:postcode":"25005",
    "addr:street":"Carr Baro De Maials",
    "iso:country":"ES",
    "sg:address":"Carr Baro De Maials, 30",
    "sg:city":"Lleida",
    "sg:orig_category":"Loter\u00cda Y T\u00d3mbola",
    "sg:phone":"+34 973 24 64 33",
    "sg:postcode":"25005",
    "sg:province":"Lleida",
    "wof:name":"Cuesta Jimenez Antonia",
    "wof:placetype":"venue"
},
  "geometry": {"coordinates":[0.6353979707,41.6225700378],"type":"Point"}
}