{
  "type": "Feature",
  "properties": {
    "iso:country":"ES",
    "sg:address":"Calle de Parroco Miguel Tarin, 35",
    "sg:city":"Benimamet-beniferri",
    "sg:orig_category":"Maquinaria Para Industrias Diversas",
    "sg:phone":"+34 963 40 38 03",
    "sg:postcode":"46035",
    "sg:province":"Valencia",
    "wof:name":"Escriche Puigcerver Ramon",
    "wof:placetype":"venue"
},
  "geometry": {"coordinates":[-0.4160400033,39.4980506897],"type":"Point"}
}