{
  "type": "Feature",
  "properties": {
    "addr:full":"Calle de Empedrado, 107 Alginet Valencia 46230",
    "addr:housenumber":"107",
    "addr:postcode":"46230",
    "addr:street":"Calle De Empedrado",
    "iso:country":"ES",
    "sg:address":"Calle de Empedrado, 107",
    "sg:city":"Alginet",
    "sg:orig_category":"Restaurantes",
    "sg:phone":"+34 961 75 07 69",
    "sg:postcode":"46230",
    "sg:province":"Valencia",
    "wof:name":"Sistelcom-telemensaje S.a.",
    "wof:placetype":"venue"
},
  "geometry": {"coordinates":[-0.4727599919,39.2650756836],"type":"Point"}
}