{
  "type": "Feature",
  "properties": {
    "addr:full":"Carrer de Vene\u00c7uela, 65 Barcelona Barcelona 08019",
    "addr:housenumber":"65",
    "addr:postcode":"08019",
    "addr:street":"Carrer De Venec\u0327Uela",
    "iso:country":"ES",
    "sg:address":"Carrer de Vene\u00c7uela, 65",
    "sg:city":"Barcelona",
    "sg:orig_category":"Cerrajer\u00cda, Ferrallista",
    "sg:phone":"+34 933 08 65 54",
    "sg:postcode":"08019",
    "sg:province":"Barcelona",
    "wof:name":"Garcia Lloret Carles",
    "wof:placetype":"venue"
},
  "geometry": {"coordinates":[2.2080171108,41.4107704163],"type":"Point"}
}