{
  "type": "Feature",
  "properties": {
    "addr:full":"Cmno Ca\u00d1adillas, S/n Alcaudete Ja\u00e9n 23660",
    "addr:housenumber":"s / n",
    "addr:postcode":"23660",
    "addr:street":"Cmno Can\u0303Adillas;Jae\u0301N",
    "iso:country":"ES",
    "sg:address":"Cmno Ca\u00d1adillas, S/n",
    "sg:city":"Alcaudete",
    "sg:orig_category":"Maquinaria Para Industrias Diversas",
    "sg:phone":"+34 953 56 03 64",
    "sg:postcode":"23660",
    "sg:province":"Ja\u00e9n",
    "wof:name":"Tejero Panadero Pablo",
    "wof:placetype":"venue"
},
  "geometry": {"coordinates":[-4.0790190697,37.5946884155],"type":"Point"}
}