{
  "type": "Feature",
  "properties": {
    "addr:full":"Calle de Castello, 115 Madrid Madrid 28006",
    "addr:housenumber":"115",
    "addr:postcode":"28006",
    "addr:street":"Calle De Castello",
    "iso:country":"ES",
    "sg:address":"Calle de Castello, 115",
    "sg:city":"Madrid",
    "sg:orig_category":"Inform\u00c1tica: Material Y Suministros",
    "sg:phone":"+34 915 64 05 47",
    "sg:postcode":"28006",
    "sg:province":"Madrid",
    "wof:name":"Trading Systems & Techiniques S.l.",
    "wof:placetype":"venue"
},
  "geometry": {"coordinates":[-3.6806483269,40.4364624023],"type":"Point"}
}