{
  "type": "Feature",
  "properties": {
    "addr:full":"Avda Lusitania, 21 Merida Badajoz 06800",
    "addr:housenumber":"21",
    "addr:postcode":"06800",
    "addr:street":"Avda Lusitania",
    "iso:country":"ES",
    "sg:address":"Avda Lusitania, 21",
    "sg:city":"Merida",
    "sg:orig_category":"Ingenier\u00cda, Centros De Estudios (diversos)",
    "sg:phone":"+34 924 30 21 28",
    "sg:postcode":"06800",
    "sg:province":"Badajoz",
    "wof:name":"J.c.estudio S.c.",
    "wof:placetype":"venue"
},
  "geometry": {"coordinates":[-6.3365869522,38.9110145569],"type":"Point"}
}