{
  "type": "Feature",
  "properties": {
    "iso:country":"ES",
    "sg:address":"Carrer de Batlle Serrallonga, S/n",
    "sg:city":"S. Hipolit Voltrega",
    "sg:orig_category":"Electricidad (montaje, Ensamblaje De Componentes)",
    "sg:phone":"+34 938 57 10 75",
    "sg:postcode":"08512",
    "sg:province":"Barcelona",
    "wof:name":"Deseuras Gallifa Ramon",
    "wof:placetype":"venue"
},
  "geometry": {"coordinates":[2.2404439449,42.0170516968],"type":"Point"}
}