{
  "type": "Feature",
  "properties": {
    "iso:country":"ES",
    "sg:address":"Carrer de Casp, 61",
    "sg:city":"Barcelona",
    "sg:orig_category":"Embajadas, Consulados Y Otras Representaciones Diplom\u00c1ticas",
    "sg:phone":"+34 932 65 37 96",
    "sg:postcode":"08010",
    "sg:province":"Barcelona",
    "wof:name":"Consulado De La Republica The Gambia",
    "wof:placetype":"venue"
},
  "geometry": {"coordinates":[2.1758909225,41.3934440613],"type":"Point"}
}