{
  "type": "Feature",
  "properties": {
    "iso:country":"ES",
    "sg:address":"Calle de Monjas De Santa Catalina, 8",
    "sg:city":"Valencia",
    "sg:orig_category":"Notarios",
    "sg:phone":"+34 963 51 33 66",
    "sg:postcode":"46002",
    "sg:province":"Valencia",
    "wof:name":"Badia Escriche Francisco",
    "wof:placetype":"venue"
},
  "geometry": {"coordinates":[-0.371863097,39.4704666138],"type":"Point"}
}