{
  "type": "Feature",
  "properties": {
    "iso:country":"ES",
    "sg:address":"Pase Alberto Palacios, 5",
    "sg:city":"Madrid",
    "sg:orig_category":"Telas Y Sedas (al Por Menor)",
    "sg:phone":"+34 917 98 81 17",
    "sg:postcode":"28021",
    "sg:province":"Madrid",
    "wof:name":"Cadena Q Comercial S.l.",
    "wof:placetype":"venue"
},
  "geometry": {"coordinates":[-3.7126219273,40.3444290161],"type":"Point"}
}