{
  "type": "Feature",
  "properties": {
    "iso:country":"ES",
    "sg:address":"Avda Esla (el), 45",
    "sg:city":"Santa Maria Del Paramo",
    "sg:orig_category":"Distribuci\u00d3n De Petr\u00d3leo Y Derivados",
    "sg:phone":"+34 987 36 01 26",
    "sg:postcode":"24240",
    "sg:province":"Le\u00f3n",
    "wof:name":"Estacion De Servicio Nuevo Paramo S. A.",
    "wof:placetype":"venue"
},
  "geometry": {"coordinates":[-5.7478938103,42.3557701111],"type":"Point"}
}