{
  "type": "Feature",
  "properties": {
    "iso:country":"ES",
    "sg:address":"Calle de San Antonio, 30",
    "sg:city":"Albacete",
    "sg:orig_category":"Promotores Constructores",
    "sg:phone":"+34 967 19 11 22",
    "sg:postcode":"02001",
    "sg:province":"Albacete",
    "wof:name":"Camporroso S.l.u.",
    "wof:placetype":"venue"
},
  "geometry": {"coordinates":[-1.8531310558,38.9977035522],"type":"Point"}
}