{
  "type": "Feature",
  "properties": {
    "addr:full":"Calle de Juan Duque, 35 Madrid Madrid 28005",
    "addr:housenumber":"35",
    "addr:postcode":"madrid;28005",
    "addr:street":"Calle De Juan Duque",
    "iso:country":"ES",
    "sg:address":"Calle de Juan Duque, 35",
    "sg:city":"Madrid",
    "sg:orig_category":"Retoques De Vestidos",
    "sg:phone":"+34 913 66 89 01",
    "sg:postcode":"28005",
    "sg:province":"Madrid",
    "wof:name":"Sastreria Gerpe S.l. G.r.t.e",
    "wof:placetype":"venue"
},
  "geometry": {"coordinates":[-3.719381094,40.410068512],"type":"Point"}
}