{
  "type": "Feature",
  "properties": {
    "addr:full":"Calle de Mayor, 195 Alcantarilla Murcia 30820",
    "addr:housenumber":"195",
    "addr:postcode":"30820",
    "addr:street":"Calle De Mayor",
    "iso:country":"ES",
    "sg:address":"Calle de Mayor, 195",
    "sg:city":"Alcantarilla",
    "sg:orig_category":"Fabricaci\u00d3n De Muebles",
    "sg:phone":"+34 968 80 02 58",
    "sg:postcode":"30820",
    "sg:province":"Murcia",
    "wof:name":"Muebles Vicre S.l.l.",
    "wof:placetype":"venue"
},
  "geometry": {"coordinates":[-1.2193889618,37.966468811],"type":"Point"}
}