{
  "type": "Feature",
  "properties": {
    "addr:full":"Carrer de Cartella, 40 Barcelona Barcelona 08031",
    "addr:housenumber":"40",
    "addr:postcode":"08031",
    "addr:street":"Carrer De Cartella",
    "iso:country":"ES",
    "sg:address":"Carrer de Cartella, 40",
    "sg:city":"Barcelona",
    "sg:orig_category":"Cajas De Ahorro",
    "sg:phone":"+34 934 20 31 58",
    "sg:postcode":"08031",
    "sg:province":"Barcelona",
    "sg:website":"www.lacaixa.es",
    "wof:name":"Caixa D'estalvis De Catalunya",
    "wof:placetype":"venue"
},
  "geometry": {"coordinates":[2.1726748943,41.4278678894],"type":"Point"}
}