{
  "type": "Feature",
  "properties": {
    "addr:full":"Carr Sant Pau, 141 Figueres Girona 17600",
    "addr:housenumber":"141",
    "addr:postcode":"17600",
    "addr:street":"Carr Sant Pau",
    "iso:country":"ES",
    "sg:address":"Carr Sant Pau, 141",
    "sg:city":"Figueres",
    "sg:orig_category":"Molduras, Junquillos, Listones Y Molduras Perforadas",
    "sg:phone":"+34 972 51 11 89",
    "sg:postcode":"17600",
    "sg:province":"Girona",
    "wof:name":"Arenas Gutierrez Dolores",
    "wof:placetype":"venue"
},
  "geometry": {"coordinates":[2.9636566639,42.2588424683],"type":"Point"}
}