{
  "type": "Feature",
  "properties": {
    "addr:full":"Bule Jose Prat, 11 Madrid Madrid 28032",
    "addr:housenumber":"11",
    "addr:postcode":"madrid;28032",
    "addr:street":"Prat",
    "iso:country":"ES",
    "sg:address":"Bule Jose Prat, 11",
    "sg:city":"Madrid",
    "sg:orig_category":"Ropa Y Accesorios",
    "sg:phone":"+34 917 51 08 07",
    "sg:postcode":"28032",
    "sg:province":"Madrid",
    "wof:name":"Aurora Gonzalez Daniel De",
    "wof:placetype":"venue"
},
  "geometry": {"coordinates":[-3.8960812092,40.518409729],"type":"Point"}
}