{
  "type": "Feature",
  "properties": {
    "iso:country":"ES",
    "sg:address":"Av Catalunya, 45",
    "sg:city":"Cerdanyola Valles",
    "sg:orig_category":"Peluquer\u00cdas, Peluquer\u00cda Mixta",
    "sg:phone":"+34 936 92 79 04",
    "sg:postcode":"08290",
    "sg:province":"Barcelona",
    "wof:name":"Peluqueria Montull S.l.",
    "wof:placetype":"venue"
},
  "geometry": {"coordinates":[2.144217968,41.4929771423],"type":"Point"}
}