{
  "type": "Feature",
  "properties": {
    "iso:country":"ES",
    "sg:address":"Calle de Ramirez De Arellano, 15",
    "sg:city":"Madrid",
    "sg:orig_category":"Electricidad: Instaladores",
    "sg:phone":"+34 915 19 88 35",
    "sg:postcode":"28043",
    "sg:province":"Madrid",
    "wof:name":"Emte S.a.",
    "wof:placetype":"venue"
},
  "geometry": {"coordinates":[-3.6551299095,40.4486541748],"type":"Point"}
}