{
  "type": "Feature",
  "properties": {
    "iso:country":"ES",
    "sg:address":"Ctra La Coru\u00d1a, Km. 0160,0",
    "sg:city":"Medina Campo",
    "sg:orig_category":"Maquinaria Y Herramientas Para Madera, Pvc, Aluminio Y Aperos (fabricaci\u00d3n, Comercio)",
    "sg:phone":"+34 983 81 24 07",
    "sg:postcode":"47400",
    "sg:province":"Valladolid",
    "wof:name":"Juan Carlos Pariente De Avila C.b.",
    "wof:placetype":"venue"
},
  "geometry": {"coordinates":[-4.913184166,41.3120155334],"type":"Point"}
}