{
  "type": "Feature",
  "properties": {
    "addr:full":"Carr Les Roses, 25 Lleida Lleida 25001",
    "addr:housenumber":"25",
    "addr:postcode":"25001",
    "addr:street":"Carr Les Roses",
    "iso:country":"ES",
    "sg:address":"Carr Les Roses, 25",
    "sg:city":"Lleida",
    "sg:orig_category":"Venta, Instalaci\u00d3n De Calefacci\u00d3n",
    "sg:phone":"+34 973 21 06 29",
    "sg:postcode":"25001",
    "sg:province":"Lleida",
    "wof:name":"Insta%acions Roure Dominguez S.l.",
    "wof:placetype":"venue"
},
  "geometry": {"coordinates":[0.6414020061,41.604057312],"type":"Point"}
}