{
  "type": "Feature",
  "properties": {
    "iso:country":"ES",
    "sg:address":"Av Alacant, Km. 0197,0",
    "sg:city":"Ondara",
    "sg:orig_category":"Albergues",
    "sg:phone":"+34 966 47 70 01",
    "sg:postcode":"03760",
    "sg:province":"Alicante",
    "sg:website":"www.clavedenia.com",
    "wof:name":"Clave Denia S.a.",
    "wof:placetype":"venue"
},
  "geometry": {"coordinates":[0.0230459999,38.8211326599],"type":"Point"}
}