{
  "type": "Feature",
  "properties": {
    "iso:country":"ES",
    "sg:address":"Jacarilla, S/n",
    "sg:city":"Elche",
    "sg:orig_category":"Ropa Para Ni\u00d1os (al Por Menor)",
    "sg:phone":"+34 966 67 27 07",
    "sg:postcode":"03205",
    "sg:province":"Alicante",
    "wof:name":"Juego De Ni\u00f1os S.l.",
    "wof:placetype":"venue"
},
  "geometry": {"coordinates":[-0.7190579772,38.2639083862],"type":"Point"}
}