{
  "type": "Feature",
  "properties": {
    "iso:country":"ES",
    "sg:address":"Calle de Severo Ochoa, 11",
    "sg:city":"Arrigorriaga",
    "sg:orig_category":"Alimentaci\u00d3n General (al Por Menor)",
    "sg:phone":"+34 946 71 08 10",
    "sg:postcode":"48480",
    "sg:province":"Vizcaya",
    "wof:name":"Supermercado Pedro Echeverria S.c.",
    "wof:placetype":"venue"
},
  "geometry": {"coordinates":[-2.8864417076,43.2078323364],"type":"Point"}
}