{
  "type": "Feature",
  "properties": {
    "iso:country":"ES",
    "sg:address":"Avda. Los Almendros, 2",
    "sg:city":"Cartama",
    "sg:orig_category":"Higiene, Belleza: Art\u00cdculos (al Por Menor)",
    "sg:phone":"+34 952 42 70 35",
    "sg:postcode":"29580",
    "sg:province":"M\u00e1laga",
    "sg:website":"www.dumher.com",
    "wof:name":"Dumher S.l.",
    "wof:placetype":"venue"
},
  "geometry": {"coordinates":[-4.6132087708,36.731628418],"type":"Point"}
}