{
  "type": "Feature",
  "properties": {
    "addr:full":"El Bosco, 4 Ejido Almer\u00eda 04700",
    "addr:postcode":"04700",
    "addr:street":"Bosco;Ejido Almeri\u0301A",
    "iso:country":"ES",
    "sg:address":"El Bosco, 4",
    "sg:city":"Ejido",
    "sg:orig_category":"T\u00c9cnicos Veterinarios",
    "sg:phone":"+34 950 48 58 23",
    "sg:postcode":"04700",
    "sg:province":"Almer\u00eda",
    "sg:website":"www.consultavet.es/santodomingo",
    "wof:name":"Cortes Perez Manuel Francisco",
    "wof:placetype":"venue"
},
  "geometry": {"coordinates":[-2.8058309555,36.7609977722],"type":"Point"}
}