{
  "type": "Feature",
  "properties": {
    "iso:country":"ES",
    "sg:address":"Carrer de Xipreret, 56",
    "sg:city":"Hospitalet Llobregat",
    "sg:orig_category":"Fabricaci\u00d3n, Importaci\u00d3n De L\u00c1mparas Y Bombillas",
    "sg:phone":"+34 933 38 07 89",
    "sg:postcode":"08901",
    "sg:province":"Barcelona",
    "wof:name":"Molins Vidre S.l.",
    "wof:placetype":"venue"
},
  "geometry": {"coordinates":[2.0968959332,41.3618965149],"type":"Point"}
}