{
  "type": "Feature",
  "properties": {
    "iso:country":"ES",
    "sg:address":"Rbla Francesc Macia, 49",
    "sg:city":"Terrassa",
    "sg:orig_category":"Art\u00cdculos De Decoraci\u00d3n",
    "sg:phone":"+34 937 35 18 78",
    "sg:postcode":"08226",
    "sg:province":"Barcelona",
    "wof:name":"Fernandez Del Viso Jil Joaquin",
    "wof:placetype":"venue"
},
  "geometry": {"coordinates":[2.0192670822,41.5765533447],"type":"Point"}
}