{
  "type": "Feature",
  "properties": {
    "addr:full":"F. Claveria, S/n Membrio C\u00e1ceres 10580",
    "addr:housenumber":"s / n",
    "addr:postcode":"10580",
    "addr:street":"F. Claveria;Ca\u0301Ceres",
    "iso:country":"ES",
    "sg:address":"F. Claveria, S/n",
    "sg:city":"Membrio",
    "sg:orig_category":"Producci\u00d3n, Venta De Productos De Agricultura Biol\u00d3gica",
    "sg:phone":"+34 927 49 10 24",
    "sg:postcode":"10580",
    "sg:province":"C\u00e1ceres",
    "wof:name":"Falco Anchorena Mercedes",
    "wof:placetype":"venue"
},
  "geometry": {"coordinates":[-7.0881090164,39.5760040283],"type":"Point"}
}