{
  "type": "Feature",
  "properties": {
    "iso:country":"ES",
    "sg:address":"Ctra Farhana, 70",
    "sg:city":"Melilla",
    "sg:orig_category":"Asesor\u00cdas Y Estudios Financieros",
    "sg:phone":"+34 952 69 60 12",
    "sg:postcode":"52005",
    "sg:province":"Melilla",
    "wof:name":"Ortiz De Zarate Meliveo Adolfo",
    "wof:placetype":"venue"
},
  "geometry": {"coordinates":[-2.9630439281,35.2927627563],"type":"Point"}
}