{
  "type": "Feature",
  "properties": {
    "iso:country":"ES",
    "sg:address":"Calle de Esteban Salazar Chapela, 117",
    "sg:city":"Malaga",
    "sg:orig_category":"Comercio De Cuadros, L\u00c1minas Y Reproducciones De Obras De Arte",
    "sg:phone":"+34 952 24 00 58",
    "sg:postcode":"29004",
    "sg:province":"M\u00e1laga",
    "sg:website":"www.cuarosyportafotos.com",
    "wof:name":"Espejo Carmona Rafael",
    "wof:placetype":"venue"
},
  "geometry": {"coordinates":[-4.4779419899,36.693157196],"type":"Point"}
}