{
  "type": "Feature",
  "properties": {
    "addr:full":"Avda Fragata Almansa, 34 Real Pontevedra 36950",
    "addr:housenumber":"34",
    "addr:postcode":"36950",
    "addr:street":"Avda Fragata Almansa",
    "iso:country":"ES",
    "sg:address":"Avda Fragata Almansa, 34",
    "sg:city":"Real",
    "sg:orig_category":"Cueros Y Pieles (al Por Mayor)",
    "sg:phone":"+34 986 39 30 25",
    "sg:postcode":"36950",
    "sg:province":"Pontevedra",
    "wof:name":"M Y M Piel S.l.",
    "wof:placetype":"venue"
},
  "geometry": {"coordinates":[-8.738442421,42.2772254944],"type":"Point"}
}