{
  "type": "Feature",
  "properties": {
    "iso:country":"ES",
    "sg:address":"Ctra Sant Bartomeu Del Grau, 1",
    "sg:city":"Gurb",
    "sg:orig_category":"Material Y Herramientas Agr\u00cdcolas",
    "sg:phone":"+34 938 86 30 22",
    "sg:postcode":"08518",
    "sg:province":"Barcelona",
    "sg:website":"www.vernis-sl.com",
    "wof:name":"Maquinaria Agricola Vernis S.l.",
    "wof:placetype":"venue"
},
  "geometry": {"coordinates":[2.0596010685,41.9344711304],"type":"Point"}
}