{
  "type": "Feature",
  "properties": {
    "iso:country":"ES",
    "sg:address":"Pl Pare Carles Perello, S/n",
    "sg:city":"Tarrega",
    "sg:orig_category":"Instalaci\u00d3n De Aspiraci\u00d3n De Gases Y Humos",
    "sg:phone":"+34 973 50 20 91",
    "sg:postcode":"25300",
    "sg:province":"Lleida",
    "wof:name":"Ilerd Energy Consulting S.l.",
    "wof:placetype":"venue"
},
  "geometry": {"coordinates":[1.1375750303,41.6475448608],"type":"Point"}
}