{
  "type": "Feature",
  "properties": {
    "iso:country":"ES",
    "sg:address":"Avia Madrid Andalucia, Km. 0200,0",
    "sg:city":"Valdepe\u00f1as",
    "sg:orig_category":"Mataderos Y Talleres De Despiezado",
    "sg:phone":"+34 926 31 09 50",
    "sg:postcode":"13300",
    "sg:province":"Ciudad Real",
    "sg:website":"www.frimancha.com",
    "wof:name":"Frimancha Industrias Carnicas S.a.",
    "wof:placetype":"venue"
},
  "geometry": {"coordinates":[-3.3877990246,38.7597694397],"type":"Point"}
}