{
  "type": "Feature",
  "properties": {
    "addr:full":"Ctra Manresa, 24 Igualada Barcelona 08700",
    "addr:housenumber":"24",
    "addr:postcode":"08700",
    "addr:street":"Ctra Manresa",
    "iso:country":"ES",
    "sg:address":"Ctra Manresa, 24",
    "sg:city":"Igualada",
    "sg:orig_category":"Inform\u00c1tica (estudios, Servicios, Asesor\u00cda, Formaci\u00d3n)",
    "sg:phone":"+34 938 05 56 40",
    "sg:postcode":"08700",
    "sg:province":"Barcelona",
    "sg:website":"www.inforgest.com",
    "wof:name":"Infurgest S.l.",
    "wof:placetype":"venue"
},
  "geometry": {"coordinates":[1.6136879921,41.5838127136],"type":"Point"}
}