{
  "type": "Feature",
  "properties": {
    "iso:country":"ES",
    "sg:address":"Carrer de Fiveller, 71",
    "sg:city":"Sabadell",
    "sg:orig_category":"Molduras, Junquillos, Listones Y Molduras Perforadas",
    "sg:phone":"+34 937 12 09 49",
    "sg:postcode":"08205",
    "sg:province":"Barcelona",
    "wof:name":"Filella Olesana Maria Carmen",
    "wof:placetype":"venue"
},
  "geometry": {"coordinates":[2.103276968,41.5387496948],"type":"Point"}
}