{
  "type": "Feature",
  "properties": {
    "iso:country":"ES",
    "sg:address":"Carrer de Bartrina, 1",
    "sg:city":"Rubi",
    "sg:orig_category":"Droguer\u00cdas (al Por Menor)",
    "sg:phone":"+34 936 97 36 02",
    "sg:postcode":"08191",
    "sg:province":"Barcelona",
    "wof:name":"Zafra Gallardo Jose Antonio",
    "wof:placetype":"venue"
},
  "geometry": {"coordinates":[2.0360319614,41.4889755249],"type":"Point"}
}