{
  "type": "Feature",
  "properties": {
    "addr:full":"Ctra Rubi, 135 Terrassa Barcelona 08228",
    "addr:housenumber":"135",
    "addr:postcode":"08228",
    "addr:street":"Ctra Rubi",
    "iso:country":"ES",
    "sg:address":"Ctra Rubi, 135",
    "sg:city":"Terrassa",
    "sg:orig_category":"M\u00c1quinas Textiles, Accesorios Y Suministros (fabricaci\u00d3n)",
    "sg:phone":"+34 937 84 44 09",
    "sg:postcode":"08228",
    "sg:province":"Barcelona",
    "wof:name":"Porcar Trade S. L.",
    "wof:placetype":"venue"
},
  "geometry": {"coordinates":[2.0352640152,41.5329399109],"type":"Point"}
}