{
  "type": "Feature",
  "properties": {
    "iso:country":"ES",
    "sg:address":"Avda Espa\u00d1a, 6",
    "sg:city":"Caceres",
    "sg:orig_category":"M\u00c9dicos: Otorrinolaringolog\u00cda",
    "sg:phone":"+34 927 22 44 27",
    "sg:postcode":"10001",
    "sg:province":"C\u00e1ceres",
    "wof:name":"Garcia Garcia Benjamin",
    "wof:placetype":"venue"
},
  "geometry": {"coordinates":[-6.3777279854,39.4714622498],"type":"Point"}
}