{
  "type": "Feature",
  "properties": {
    "addr:full":"Vall Nou(urb. Can Salva), 353 Riells Girona 17404",
    "addr:housenumber":"353",
    "addr:postcode":"17404",
    "addr:street":"Riells Girona",
    "iso:country":"ES",
    "sg:address":"Vall Nou(urb. Can Salva), 353",
    "sg:city":"Riells",
    "sg:orig_category":"Centros Empresariales",
    "sg:phone":"+34 972 87 19 56",
    "sg:postcode":"17404",
    "sg:province":"Girona",
    "wof:name":"Martinez Sanchez Rosa",
    "wof:placetype":"venue"
},
  "geometry": {"coordinates":[2.5116300583,41.7771339417],"type":"Point"}
}