{
  "type": "Feature",
  "properties": {
    "addr:full":"Calle de Heroe Romeu, 7 Valencia Valencia 46008",
    "addr:housenumber":"7",
    "addr:postcode":"46008",
    "addr:street":"Calle De Heroe Romeu",
    "iso:country":"ES",
    "sg:address":"Calle de Heroe Romeu, 7",
    "sg:city":"Valencia",
    "sg:orig_category":"Inmobiliaria (agencias)",
    "sg:phone":"+34 963 82 26 26",
    "sg:postcode":"46008",
    "sg:province":"Valencia",
    "sg:website":"www.inmobelsa.com",
    "wof:name":"Inmobelsa S.a.",
    "wof:placetype":"venue"
},
  "geometry": {"coordinates":[-0.3902109861,39.4682312012],"type":"Point"}
}