{
  "type": "Feature",
  "properties": {
    "iso:country":"ES",
    "sg:address":"Calle de Doctor Fleming, 1",
    "sg:city":"Sax",
    "sg:orig_category":"Postigos, Persianas Y Celos\u00cdas",
    "sg:phone":"+34 965 47 56 89",
    "sg:postcode":"03630",
    "sg:province":"Alicante",
    "wof:name":"Pastor Cartagena Rosa Maria",
    "wof:placetype":"venue"
},
  "geometry": {"coordinates":[-0.8213965893,38.5365524292],"type":"Point"}
}