{
  "type": "Feature",
  "properties": {
    "addr:full":"Carrer de Bellit, 7 Caldes Montbui Barcelona 08140",
    "addr:housenumber":"7",
    "addr:postcode":"08140",
    "addr:street":"Carrer De Bellit;Montbui Barcelona",
    "iso:country":"ES",
    "sg:address":"Carrer de Bellit, 7",
    "sg:city":"Caldes Montbui",
    "sg:orig_category":"Internados & Ense\u00d1anza Privada",
    "sg:phone":"+34 938 62 66 07",
    "sg:postcode":"08140",
    "sg:province":"Barcelona",
    "wof:name":"Escolas Pias De Caldes",
    "wof:placetype":"venue"
},
  "geometry": {"coordinates":[2.1622860432,41.6351623535],"type":"Point"}
}