{
  "type": "Feature",
  "properties": {
    "addr:full":"Calle de Motril, 47 Almeria Almer\u00eda 04007",
    "addr:housenumber":"47",
    "addr:postcode":"04007",
    "addr:street":"Calle De Motril",
    "iso:country":"ES",
    "sg:address":"Calle de Motril, 47",
    "sg:city":"Almeria",
    "sg:orig_category":"Muebles Y Accesorios Para Cocinas Y Cuartos De Ba\u00d1o (al Por Menor)",
    "sg:phone":"+34 950 26 71 33",
    "sg:postcode":"04007",
    "sg:province":"Almer\u00eda",
    "wof:name":"Comercial Y Montajes Estadio S.l.",
    "wof:placetype":"venue"
},
  "geometry": {"coordinates":[-2.4495201111,36.8304023743],"type":"Point"}
}