{
  "type": "Feature",
  "properties": {
    "iso:country":"ES",
    "sg:address":"Avda Ciudad De Barcelona, 148",
    "sg:city":"Madrid",
    "sg:orig_category":"Asociaciones Y Clubs Deportivos",
    "sg:phone":"+34 915 02 00 99",
    "sg:postcode":"28007",
    "sg:province":"Madrid",
    "wof:name":"C-4 Invest S.l.",
    "wof:placetype":"venue"
},
  "geometry": {"coordinates":[-3.6782360077,40.4029273987],"type":"Point"}
}