{
  "type": "Feature",
  "properties": {
    "addr:full":"Calle de Pintor Teodoro Dublang, 17 Vitoria-gasteiz \u00c1lava 01008",
    "addr:housenumber":"17",
    "addr:postcode":"01008",
    "addr:street":"Calle De Pintor Teodoro Dublang",
    "iso:country":"ES",
    "sg:address":"Calle de Pintor Teodoro Dublang, 17",
    "sg:city":"Vitoria-gasteiz",
    "sg:orig_category":"Abogados",
    "sg:phone":"+34 945 01 14 99",
    "sg:postcode":"01008",
    "sg:province":"\u00c1lava",
    "wof:name":"Silvia Aldekoa Onaindia",
    "wof:placetype":"venue"
},
  "geometry": {"coordinates":[-2.68551898,42.8433189392],"type":"Point"}
}