{
  "type": "Feature",
  "properties": {
    "addr:full":"Calle de Pino (del), 28 Yuncos Toledo 45210",
    "addr:housenumber":"28",
    "addr:postcode":"45210",
    "addr:street":"Calle De Pino Del",
    "iso:country":"ES",
    "sg:address":"Calle de Pino (del), 28",
    "sg:city":"Yuncos",
    "sg:orig_category":"M\u00c1rmoles, Granitos Y Piedras Naturales",
    "sg:phone":"+34 925 55 74 70",
    "sg:postcode":"45210",
    "sg:province":"Toledo",
    "wof:name":"Neogranit S.l.",
    "wof:placetype":"venue"
},
  "geometry": {"coordinates":[-3.8866889477,40.0756912231],"type":"Point"}
}