{
  "type": "Feature",
  "properties": {
    "iso:country":"ES",
    "sg:address":"Carrer de Camp, 7",
    "sg:city":"Barcelona",
    "sg:orig_category":"Venta, Instalaci\u00d3n De Calefacci\u00d3n",
    "sg:phone":"+34 932 11 63 60",
    "sg:postcode":"08021",
    "sg:province":"Barcelona",
    "wof:name":"Pedrosa Gomez Oscar",
    "wof:placetype":"venue"
},
  "geometry": {"coordinates":[2.1378469467,41.4017333984],"type":"Point"}
}