{
  "type": "Feature",
  "properties": {
    "addr:full":"G.v. Corts Catalanes, 594 Barcelona Barcelona 08007",
    "addr:housenumber":"594",
    "addr:postcode":"08007",
    "addr:street":"Catalanes",
    "iso:country":"ES",
    "sg:address":"G.v. Corts Catalanes, 594",
    "sg:city":"Barcelona",
    "sg:orig_category":"Urbanistas",
    "sg:phone":"+34 933 18 00 80",
    "sg:postcode":"08007",
    "sg:province":"Barcelona",
    "wof:name":"Macia Monros Antonio",
    "wof:placetype":"venue"
},
  "geometry": {"coordinates":[2.1647479534,41.3863487244],"type":"Point"}
}