{
  "type": "Feature",
  "properties": {
    "addr:full":"Kondeko Aldapa, 5 San Blas Guip\u00f9zcoa 20400",
    "addr:housenumber":"5",
    "addr:postcode":"20400",
    "addr:street":"Aldapa",
    "iso:country":"ES",
    "sg:address":"Kondeko Aldapa, 5",
    "sg:city":"San Blas",
    "sg:orig_category":"Aguas (distribuci\u00d3n, Servicios)",
    "sg:phone":"+34 943 65 06 02",
    "sg:postcode":"20400",
    "sg:province":"Guip\u00f9zcoa",
    "sg:website":"www.insalus.es",
    "wof:name":"Agua De Insalus S. A.",
    "wof:placetype":"venue"
},
  "geometry": {"coordinates":[-2.0730090141,43.1336326599],"type":"Point"}
}