{
  "type": "Feature",
  "properties": {
    "addr:full":"Avda Moratalaz, 137 Madrid Madrid 28030",
    "addr:housenumber":"137",
    "addr:postcode":"28030",
    "addr:street":"Avda Moratalaz",
    "iso:country":"ES",
    "sg:address":"Avda Moratalaz, 137",
    "sg:city":"Madrid",
    "sg:orig_category":"Bancos",
    "sg:phone":"+34 914 39 90 16",
    "sg:postcode":"28030",
    "sg:province":"Madrid",
    "wof:name":"Banco Popular Espa\u00f1ol",
    "wof:placetype":"venue"
},
  "geometry": {"coordinates":[-3.6492590904,40.4066238403],"type":"Point"}
}