{
  "type": "Feature",
  "properties": {
    "addr:full":"Urdaneta Kalea, 2 Zarautz Guip\u00f9zcoa 20800",
    "addr:housenumber":"2",
    "addr:postcode":"20800",
    "addr:street":"Urdaneta Kalea;Guipu\u0300Zcoa",
    "iso:country":"ES",
    "sg:address":"Urdaneta Kalea, 2",
    "sg:city":"Zarautz",
    "sg:orig_category":"Moquetas, Alfombras (al Por Menor)",
    "sg:phone":"+34 943 02 12 32",
    "sg:postcode":"20800",
    "sg:province":"Guip\u00f9zcoa",
    "wof:name":"Aitor Loidi Y Otra C.b.",
    "wof:placetype":"venue"
},
  "geometry": {"coordinates":[-2.174608469,43.2806930542],"type":"Point"}
}