{
  "type": "Feature",
  "properties": {
    "addr:full":"Ctra M-316 (villarejo De Salvanes), Km. 0007,0 Valdelaguna Madrid 28391",
    "addr:postcode":"28391",
    "addr:street":"Ctra M-316 Villarejo;Salvanes Km. 0007,0",
    "iso:country":"ES",
    "sg:address":"Ctra M-316 (villarejo De Salvanes), Km. 0007,0",
    "sg:city":"Valdelaguna",
    "sg:orig_category":"M\u00c1rmoles, Granitos Y Piedras Naturales",
    "sg:phone":"+34 918 93 72 66",
    "sg:postcode":"28391",
    "sg:province":"Madrid",
    "wof:name":"Gutierrez Sanchez Mariano",
    "wof:placetype":"venue"
},
  "geometry": {"coordinates":[-3.369549036,40.1615486145],"type":"Point"}
}