{
  "type": "Feature",
  "properties": {
    "iso:country":"ES",
    "sg:address":"Carrer de Bisbe Morgades, 30",
    "sg:city":"Vic",
    "sg:classifiers":[
        {
            "category":"Professional",
            "subcategory":"Business Services",
            "type":"Services"
        }
    ],
    "sg:phone":"+34 938 83 35 39",
    "sg:postcode":"08500",
    "sg:province":"Barcelona",
    "sg:tags":[
        "control",
        "asesor\u00cda",
        "organizaci\u00d3n",
        "la",
        "de",
        "gesti\u00d3n",
        "y"
    ],
    "wof:name":"Iberbanda S.a.",
    "wof:placetype":"venue"
},
  "geometry": {"coordinates":[2.250868082,41.9313240051],"type":"Point"}
}