{
  "type": "Feature",
  "properties": {
    "iso:country":"ES",
    "sg:address":"Ctra Gijon Sevilla, 272",
    "sg:city":"Roales",
    "sg:orig_category":"Centros Empresariales",
    "sg:phone":"+34 980 53 87 43",
    "sg:postcode":"49192",
    "sg:province":"Zamora",
    "sg:website":"www.trenzametal.es",
    "wof:name":"Trenzametal S.l.",
    "wof:placetype":"venue"
},
  "geometry": {"coordinates":[-5.8029990196,41.550819397],"type":"Point"}
}