{
  "type": "Feature",
  "properties": {
    "addr:full":"Carr Sant Cristofol, De, 14 Carcaixent Valencia 46740",
    "addr:housenumber":"14",
    "addr:postcode":"46740",
    "addr:street":"Carr Sant Cristofol De",
    "iso:country":"ES",
    "sg:address":"Carr Sant Cristofol, De, 14",
    "sg:city":"Carcaixent",
    "sg:orig_category":"Psic\u00d3logos",
    "sg:phone":"+34 962 43 35 38",
    "sg:postcode":"46740",
    "sg:province":"Valencia",
    "wof:name":"Magraner Gil Bernardo",
    "wof:placetype":"venue"
},
  "geometry": {"coordinates":[-0.4517009854,39.1241912842],"type":"Point"}
}