{
  "type": "Feature",
  "properties": {
    "addr:full":"Calle de Barquillo, 49 Madrid Madrid 28004",
    "addr:housenumber":"49",
    "addr:postcode":"madrid;28004",
    "addr:street":"Calle De Barquillo",
    "iso:country":"ES",
    "sg:address":"Calle de Barquillo, 49",
    "sg:city":"Madrid",
    "sg:classifiers":[
        {
            "category":"Professional",
            "subcategory":"Research",
            "type":"Services"
        }
    ],
    "sg:phone":"+34 913 10 40 85",
    "sg:postcode":"28004",
    "sg:province":"Madrid",
    "sg:tags":[
        "mercado",
        "de",
        "estudios"
    ],
    "wof:name":"C.i.pe\u00f1a-oli S.l.",
    "wof:placetype":"venue"
},
  "geometry": {"coordinates":[-3.695530653,40.424369812],"type":"Point"}
}