{
  "type": "Feature",
  "properties": {
    "addr:full":"Calle de Ildefonso Sanchez Del Rio, 4 Oviedo Asturias 33011",
    "addr:housenumber":"4",
    "addr:postcode":"33011",
    "addr:street":"Calle De Ildefonso Sanchez Del Rio",
    "iso:country":"ES",
    "sg:address":"Calle de Ildefonso Sanchez Del Rio, 4",
    "sg:city":"Oviedo",
    "sg:orig_category":"Inform\u00c1tica, Ofim\u00c1tica (estudios, Asesor\u00cda, Ingenier\u00cda, Formaci\u00d3n)",
    "sg:phone":"+34 985 11 65 00",
    "sg:postcode":"33011",
    "sg:province":"Asturias",
    "sg:website":"www.grupoab.com",
    "wof:name":"Abnet Sistemas S.l.",
    "wof:placetype":"venue"
},
  "geometry": {"coordinates":[-5.84104,43.367588],"type":"Point"}
}