{
  "type": "Feature",
  "properties": {
    "iso:country":"ES",
    "sg:address":"Calle de Sevilla, 67",
    "sg:city":"Puebla Cazalla",
    "sg:orig_category":"Autob\u00das (explotaci\u00d3n Y Servicios De)",
    "sg:phone":"+34 954 84 70 18",
    "sg:postcode":"41540",
    "sg:province":"Sevilla",
    "wof:name":"Transportes Linesur S.l.",
    "wof:placetype":"venue"
},
  "geometry": {"coordinates":[-5.3128490448,37.2229881287],"type":"Point"}
}