{
  "type": "Feature",
  "properties": {
    "iso:country":"ES",
    "sg:address":"Calle de San Roque, 6",
    "sg:city":"Ermua",
    "sg:orig_category":"Material Y Suministros Para Imprenta E Industrias Gr\u00c1ficas",
    "sg:phone":"+34 943 17 02 14",
    "sg:postcode":"48260",
    "sg:province":"Vizcaya",
    "wof:name":"Garcia Carracedo Jose Angel",
    "wof:placetype":"venue"
},
  "geometry": {"coordinates":[-2.5013110638,43.1868171692],"type":"Point"}
}