{
  "type": "Feature",
  "properties": {
    "addr:full":"Rua Nosa Sra. Da Sainza, 26 Ourense Ourense 32005",
    "addr:housenumber":"26",
    "addr:postcode":"32005",
    "addr:street":"Rua Nosa Sra. Da Sainza",
    "iso:country":"ES",
    "sg:address":"Rua Nosa Sra. Da Sainza, 26",
    "sg:city":"Ourense",
    "sg:orig_category":"Iglesia Cat\u00d3lica",
    "sg:phone":"+34 988 22 12 80",
    "sg:postcode":"32005",
    "sg:province":"Ourense",
    "wof:name":"Comunidad Religiosas Franciscanas",
    "wof:placetype":"venue"
},
  "geometry": {"coordinates":[-7.8622808456,42.3280563354],"type":"Point"}
}