{
  "type": "Feature",
  "properties": {
    "addr:full":"Avda Sevilla, 6 Salteras Sevilla 41909",
    "addr:housenumber":"6",
    "addr:postcode":"41909",
    "addr:street":"Avda Sevilla",
    "iso:country":"ES",
    "sg:address":"Avda Sevilla, 6",
    "sg:city":"Salteras",
    "sg:orig_category":"Molduras, Junquillos, Listones Y Molduras Perforadas",
    "sg:phone":"+34 955 70 76 11",
    "sg:postcode":"41909",
    "sg:province":"Sevilla",
    "wof:name":"Fernandez Ridruejo Jose Luis",
    "wof:placetype":"venue"
},
  "geometry": {"coordinates":[-6.1073617935,37.4179649353],"type":"Point"}
}