{
  "type": "Feature",
  "properties": {
    "addr:full":"Calle de San Miguel, 38 Estepona M\u00e1laga 29680",
    "addr:housenumber":"38",
    "addr:postcode":"29680",
    "addr:street":"Calle De San Miguel",
    "iso:country":"ES",
    "sg:address":"Calle de San Miguel, 38",
    "sg:city":"Estepona",
    "sg:orig_category":"Carnicer\u00cdas, Carnicer\u00cdas",
    "sg:phone":"+34 952 80 26 48",
    "sg:postcode":"29680",
    "sg:province":"M\u00e1laga",
    "wof:name":"Montes Marquez Josefa",
    "wof:placetype":"venue"
},
  "geometry": {"coordinates":[-5.1432909966,36.427406311],"type":"Point"}
}