{
  "type": "Feature",
  "properties": {
    "iso:country":"ES",
    "sg:address":"Praj La Colmenilla, 3",
    "sg:city":"Gibraleon",
    "sg:orig_category":"Cerrajer\u00cda, Ferrallista",
    "sg:phone":"+34 959 30 02 94",
    "sg:postcode":"21500",
    "sg:province":"Huelva",
    "wof:name":"Talleres Gonzalez Chavarria S.l.",
    "wof:placetype":"venue"
},
  "geometry": {"coordinates":[-6.9744291306,37.3773460388],"type":"Point"}
}