{
  "type": "Feature",
  "properties": {
    "iso:country":"ES",
    "sg:address":"Crt. Madrid, Km. 0195,7",
    "sg:city":"Motilla Palancar",
    "sg:orig_category":"Reparaciones Y Remolcado De Veh\u00cdculos",
    "sg:phone":"+34 969 33 10 96",
    "sg:postcode":"16200",
    "sg:province":"Cuenca",
    "wof:name":"Talleres Lopez De Motilla S. L.",
    "wof:placetype":"venue"
},
  "geometry": {"coordinates":[-1.9062039852,39.5607185364],"type":"Point"}
}