{
  "type": "Feature",
  "properties": {
    "iso:country":"ES",
    "sg:address":"Plaz Fuente, 13",
    "sg:city":"Fuente Alamo",
    "sg:orig_category":"Colchones (fabricaci\u00d3n, Al Por Mayor, Al Por Menor)",
    "sg:phone":"+34 968 59 87 35",
    "sg:postcode":"30320",
    "sg:province":"Murcia",
    "wof:name":"Aznar Izquierdo Juan",
    "wof:placetype":"venue"
},
  "geometry": {"coordinates":[-1.1695870161,37.7226905823],"type":"Point"}
}