{
  "type": "Feature",
  "properties": {
    "addr:full":"Plaz Autonomia Aragonesa, 1 Andorra Teruel 44500",
    "addr:housenumber":"1",
    "addr:postcode":"44500",
    "addr:street":"Aragonesa",
    "iso:country":"ES",
    "sg:address":"Plaz Autonomia Aragonesa, 1",
    "sg:city":"Andorra",
    "sg:orig_category":"Alimentaci\u00d3n General (al Por Menor)",
    "sg:phone":"+34 978 84 28 89",
    "sg:postcode":"44500",
    "sg:province":"Teruel",
    "wof:name":"Leal Llanos Felix",
    "wof:placetype":"venue"
},
  "geometry": {"coordinates":[-0.4398390055,40.9772491455],"type":"Point"}
}