{
  "type": "Feature",
  "properties": {
    "iso:country":"ES",
    "sg:address":"Calle de Isaac Peral, 1",
    "sg:city":"Mazarron",
    "sg:orig_category":"Institutos De Belleza",
    "sg:phone":"+34 968 59 16 52",
    "sg:postcode":"30870",
    "sg:province":"Murcia",
    "wof:name":"Palazon Arroyo Maria Angeles",
    "wof:placetype":"venue"
},
  "geometry": {"coordinates":[-1.3147699833,37.600227356],"type":"Point"}
}