{
  "type": "Feature",
  "properties": {
    "addr:full":"Carrer de La Colonia, S/n Castalla Alicante 03420",
    "addr:housenumber":"s / n",
    "addr:postcode":"03420",
    "addr:street":"Carrer De La Colonia",
    "iso:country":"ES",
    "sg:address":"Carrer de La Colonia, S/n",
    "sg:city":"Castalla",
    "sg:orig_category":"Artes Gr\u00c1ficas, Artes Pl\u00c1sticas (curso)",
    "sg:phone":"+34 966 56 01 88",
    "sg:postcode":"03420",
    "sg:province":"Alicante",
    "wof:name":"Manipulados Castalla S.l.",
    "wof:placetype":"venue"
},
  "geometry": {"coordinates":[-0.6692039967,38.6014442444],"type":"Point"}
}