{
  "type": "Feature",
  "properties": {
    "addr:full":"Ctra Raval De Crist, 9 Roquetes Tarragona 43520",
    "addr:housenumber":"9",
    "addr:postcode":"43520",
    "addr:street":"Ctra Raval De Crist",
    "iso:country":"ES",
    "sg:address":"Ctra Raval De Crist, 9",
    "sg:city":"Roquetes",
    "sg:orig_category":"Empresas De Carpinter\u00cda De Madera",
    "sg:phone":"+34 977 50 11 56",
    "sg:postcode":"43520",
    "sg:province":"Tarragona",
    "wof:name":"Moiban Roquetes S.l.",
    "wof:placetype":"venue"
},
  "geometry": {"coordinates":[0.5002449751,40.8249855042],"type":"Point"}
}