{
  "type": "Feature",
  "properties": {
    "addr:full":"Buentarron, 5 Ca\u00f1ada \u00c1vila 05294",
    "addr:housenumber":"5",
    "addr:postcode":"05294",
    "addr:street":"Buentarron;A\u0301Vila",
    "iso:country":"ES",
    "sg:address":"Buentarron, 5",
    "sg:city":"Ca\u00f1ada",
    "sg:orig_category":"Peluquer\u00cdas, Peluquer\u00cda Mixta",
    "sg:phone":"+34 920 27 24 62",
    "sg:postcode":"05294",
    "sg:province":"\u00c1vila",
    "wof:name":"Palomo Martin Maria Angeles",
    "wof:placetype":"venue"
},
  "geometry": {"coordinates":[-4.4980988503,40.5960922241],"type":"Point"}
}