{
  "type": "Feature",
  "properties": {
    "addr:full":"Pl Constitucio, 10 Rubi Barcelona 08191",
    "addr:housenumber":"10",
    "addr:postcode":"08191",
    "addr:street":"Pl Constitucio",
    "iso:country":"ES",
    "sg:address":"Pl Constitucio, 10",
    "sg:city":"Rubi",
    "sg:orig_category":"Bazares, Art\u00cdculos De Limpieza Y De Cocina (al Por Menor)",
    "sg:phone":"+34 935 88 79 65",
    "sg:postcode":"08191",
    "sg:province":"Barcelona",
    "wof:name":"Mahmood Chaudhar Nasar",
    "wof:placetype":"venue"
},
  "geometry": {"coordinates":[2.0302100182,41.4846916199],"type":"Point"}
}