{
  "type": "Feature",
  "properties": {
    "addr:full":"Avda Victor Gallego, 9 Zamora Zamora 49009",
    "addr:housenumber":"9",
    "addr:postcode":"49009",
    "addr:street":"Avda Victor Gallego",
    "iso:country":"ES",
    "sg:address":"Avda Victor Gallego, 9",
    "sg:city":"Zamora",
    "sg:orig_category":"Procuradores",
    "sg:phone":"+34 980 52 40 51",
    "sg:postcode":"49009",
    "sg:province":"Zamora",
    "sg:website":"www.autoescuelarias.com",
    "wof:name":"Arias Rodriguez Elisa",
    "wof:placetype":"venue"
},
  "geometry": {"coordinates":[-5.7427530289,41.5089683533],"type":"Point"}
}