{
  "type": "Feature",
  "properties": {
    "addr:full":"Avda Voltaire (de), S/n Jerez De La Frontera C\u00e1diz 11405",
    "addr:postcode":"11405",
    "addr:street":"Avda Voltaire De S / N",
    "iso:country":"ES",
    "sg:address":"Avda Voltaire (de), S/n",
    "sg:city":"Jerez De La Frontera",
    "sg:orig_category":"Sociedades, Compa\u00d1\u00cdas Aseguradoras",
    "sg:phone":"+34 956 34 19 97",
    "sg:postcode":"11405",
    "sg:province":"C\u00e1diz",
    "wof:name":"Serviseg Consulting Sl",
    "wof:placetype":"venue"
},
  "geometry": {"coordinates":[-6.1128082275,36.7036743164],"type":"Point"}
}