{
  "type": "Feature",
  "properties": {
    "iso:country":"ES",
    "sg:address":"Ctra San Juan, 19",
    "sg:city":"Navaluenga",
    "sg:orig_category":"Agencias Y Asesores De Publicidad",
    "sg:phone":"+34 920 29 82 15",
    "sg:postcode":"05100",
    "sg:province":"\u00c1vila",
    "wof:name":"Montero Sanchez Jose Luis",
    "wof:placetype":"venue"
},
  "geometry": {"coordinates":[-4.7072281837,40.4173583984],"type":"Point"}
}