{
  "type": "Feature",
  "properties": {
    "iso:country":"ES",
    "sg:address":"Carrer de Esglesia, 3",
    "sg:city":"Sabadell",
    "sg:orig_category":"Restaurantes",
    "sg:phone":"+34 937 27 58 36",
    "sg:postcode":"08204",
    "sg:province":"Barcelona",
    "wof:name":"Iniciativas Maroto S.l.",
    "wof:placetype":"venue"
},
  "geometry": {"coordinates":[2.1082909107,41.5472373962],"type":"Point"}
}