{
  "type": "Feature",
  "properties": {
    "iso:country":"ES",
    "sg:address":"Calle de Alfredo Kraus, 2",
    "sg:city":"Alcala Guadaira",
    "sg:orig_category":"Venta, Montaje De Neum\u00c1ticos",
    "sg:phone":"+34 955 68 00 21",
    "sg:postcode":"41500",
    "sg:province":"Sevilla",
    "wof:name":"Garrido Lopez Jose Ivan",
    "wof:placetype":"venue"
},
  "geometry": {"coordinates":[-5.8500952721,37.3402290344],"type":"Point"}
}