{
  "type": "Feature",
  "properties": {
    "addr:full":"Calle de Faustino Osorio, 18 Madrid Madrid 28047",
    "addr:housenumber":"18",
    "addr:postcode":"madrid;28047",
    "addr:street":"Calle De Faustino Osorio",
    "iso:country":"ES",
    "sg:address":"Calle de Faustino Osorio, 18",
    "sg:city":"Madrid",
    "sg:orig_category":"Empresas De Portes Y Mensajer\u00cda",
    "sg:phone":"+34 915 26 03 52",
    "sg:postcode":"28047",
    "sg:province":"Madrid",
    "wof:name":"Mensajeria Carrasco Martin S.l.",
    "wof:placetype":"venue"
},
  "geometry": {"coordinates":[-3.7321109772,40.4037857056],"type":"Point"}
}