{
  "type": "Feature",
  "properties": {
    "iso:country":"ES",
    "sg:address":"Carrer de Doctor Arruga, 42",
    "sg:city":"Roses",
    "sg:orig_category":"Institutos De Belleza",
    "sg:phone":"+34 972 25 42 98",
    "sg:postcode":"17480",
    "sg:province":"Girona",
    "wof:name":"Wallscheid  Christiane",
    "wof:placetype":"venue"
},
  "geometry": {"coordinates":[3.1773147583,42.2650299072],"type":"Point"}
}