{
  "type": "Feature",
  "properties": {
    "iso:country":"ES",
    "sg:address":"Avda San Isidro, 2",
    "sg:city":"Malaga",
    "sg:orig_category":"Agencias Y Agentes Comerciales, Representantes",
    "sg:phone":"+34 952 29 66 75",
    "sg:postcode":"29018",
    "sg:province":"M\u00e1laga",
    "wof:name":"Santiago Lopez Bernardino",
    "wof:placetype":"venue"
},
  "geometry": {"coordinates":[-4.3650951385,36.7259178162],"type":"Point"}
}