{
  "type": "Feature",
  "properties": {
    "iso:country":"ES",
    "sg:address":"Calle de Esperanza, 26",
    "sg:city":"Molina Segura",
    "sg:orig_category":"Ense\u00d1anza: Peluquer\u00cda Est\u00c9tica",
    "sg:phone":"+34 968 64 01 23",
    "sg:postcode":"30500",
    "sg:province":"Murcia",
    "wof:name":"Perez Andreu Maria Angeles",
    "wof:placetype":"venue"
},
  "geometry": {"coordinates":[-1.2056889534,38.0588188171],"type":"Point"}
}