{
  "type": "Feature",
  "properties": {
    "addr:full":"Calle de Huertas, 1 Arnedo La Rioja 26580",
    "addr:housenumber":"1",
    "addr:postcode":"26580",
    "addr:street":"Calle De Huertas;Rioja",
    "iso:country":"ES",
    "sg:address":"Calle de Huertas, 1",
    "sg:city":"Arnedo",
    "sg:orig_category":"Fisioterapia",
    "sg:phone":"+34 941 38 48 09",
    "sg:postcode":"26580",
    "sg:province":"La Rioja",
    "wof:name":"Fernandez Moreno Luis Alberto",
    "wof:placetype":"venue"
},
  "geometry": {"coordinates":[-2.101031065,42.2254753113],"type":"Point"}
}