{
  "type": "Feature",
  "properties": {
    "iso:country":"ES",
    "sg:address":"Calle de Sagunto, 15",
    "sg:city":"Madrid",
    "sg:orig_category":"Sindicatos De Trabajadores",
    "sg:phone":"+34 914 45 31 32",
    "sg:postcode":"28010",
    "sg:province":"Madrid",
    "wof:name":"Confederacion General Del Trabajo",
    "wof:placetype":"venue"
},
  "geometry": {"coordinates":[-3.6993150711,40.4339027405],"type":"Point"}
}