{
  "type": "Feature",
  "properties": {
    "iso:country":"ES",
    "sg:address":"Avda Dolores Ibarruri, 25",
    "sg:city":"Plasencia",
    "sg:orig_category":"Frutas, Legumbres Frescas Y Tempranas (al Por Menor)",
    "sg:phone":"+34 927 41 85 12",
    "sg:postcode":"10600",
    "sg:province":"C\u00e1ceres",
    "wof:name":"Rubio Martin Francisco",
    "wof:placetype":"venue"
},
  "geometry": {"coordinates":[-6.0647478104,40.0477523804],"type":"Point"}
}