{
  "type": "Feature",
  "properties": {
    "addr:full":"Avda Portugal (de), S/n San Jose Murcia 30800",
    "addr:housenumber":"/ n",
    "addr:postcode":"30800",
    "addr:street":"Avda Portugal De S",
    "iso:country":"ES",
    "sg:address":"Avda Portugal (de), S/n",
    "sg:city":"San Jose",
    "sg:orig_category":"Bisuter\u00cda, Joyer\u00cda, Relojer\u00cda (al Por Menor)",
    "sg:phone":"+34 968 46 23 50",
    "sg:postcode":"30800",
    "sg:province":"Murcia",
    "wof:name":"Ibarra Domenech Enrique",
    "wof:placetype":"venue"
},
  "geometry": {"coordinates":[-1.6905640364,37.680557251],"type":"Point"}
}