{
  "type": "Feature",
  "properties": {
    "iso:country":"ES",
    "sg:address":"Calle de Magantina (la), 13",
    "sg:city":"Huesca",
    "sg:orig_category":"Aparatos E Instalaci\u00d3n De Regad\u00cdos",
    "sg:phone":"+34 974 21 89 19",
    "sg:postcode":"22006",
    "sg:province":"Huesca",
    "wof:name":"Sermeri S L",
    "wof:placetype":"venue"
},
  "geometry": {"coordinates":[-0.4068149924,42.1458206177],"type":"Point"}
}