{
  "type": "Feature",
  "properties": {
    "iso:country":"ES",
    "sg:address":"Cordoba (p I La Fuente), S/n",
    "sg:city":"Fuente Vaqueros",
    "sg:orig_category":"Empresas De Carpinter\u00cda De Madera",
    "sg:phone":"+34 958 43 47 53",
    "sg:postcode":"18340",
    "sg:province":"Granada",
    "wof:name":"Ramogo S.l.",
    "wof:placetype":"venue"
},
  "geometry": {"coordinates":[-3.7856690884,37.2234115601],"type":"Point"}
}