{
  "type": "Feature",
  "properties": {
    "addr:full":"Carrer de Begonia, 18 Vendrell Tarragona 43700",
    "addr:housenumber":"18",
    "addr:postcode":"43700",
    "addr:street":"Carrer De Begonia",
    "iso:country":"ES",
    "sg:address":"Carrer de Begonia, 18",
    "sg:city":"Vendrell",
    "sg:orig_category":"Transportes Por V\u00cdas Navegables",
    "sg:phone":"+34 977 66 34 79",
    "sg:postcode":"43700",
    "sg:province":"Tarragona",
    "wof:name":"Ramirez Roca Jose Luis",
    "wof:placetype":"venue"
},
  "geometry": {"coordinates":[1.5147969723,41.2299156189],"type":"Point"}
}