{
  "type": "Feature",
  "properties": {
    "iso:country":"ES",
    "sg:address":"Calle de Ayala, 116",
    "sg:city":"Madrid",
    "sg:orig_category":"Financiaci\u00d3n Y Cr\u00c9ditos",
    "sg:phone":"+34 915 77 15 98",
    "sg:postcode":"28006",
    "sg:province":"Madrid",
    "wof:name":"Grupo Tefin De Gestion S.l.",
    "wof:placetype":"venue"
},
  "geometry": {"coordinates":[-3.6737248898,40.4272041321],"type":"Point"}
}