{
  "type": "Feature",
  "properties": {
    "addr:full":"Avda Principe Felipe, 20 Martos Ja\u00e9n 23600",
    "addr:housenumber":"20",
    "addr:postcode":"23600",
    "addr:street":"Avda Principe Felipe;Jae\u0301N",
    "iso:country":"ES",
    "sg:address":"Avda Principe Felipe, 20",
    "sg:city":"Martos",
    "sg:orig_category":"Aceites Y Grasas Alimentarias (fabricaci\u00d3n, Al Por Mayor)",
    "sg:phone":"+34 953 55 00 57",
    "sg:postcode":"23600",
    "sg:province":"Ja\u00e9n",
    "wof:name":"Cooperativa Y Caja Rural San Amador",
    "wof:placetype":"venue"
},
  "geometry": {"coordinates":[-3.9707090855,37.7195472717],"type":"Point"}
}