{
  "type": "Feature",
  "properties": {
    "iso:country":"ES",
    "sg:address":"Calle de Aragon, 11",
    "sg:city":"Ejea De Los Caballeros",
    "sg:orig_category":"Empresas De Desmonte",
    "sg:phone":"+34 976 66 08 25",
    "sg:postcode":"50600",
    "sg:province":"Zaragoza",
    "wof:name":"Excavaciones Arilla S.l.",
    "wof:placetype":"venue"
},
  "geometry": {"coordinates":[-1.137006402,42.1234016418],"type":"Point"}
}