{
  "type": "Feature",
  "properties": {
    "iso:country":"ES",
    "sg:address":"Calle de Doctor Fleming, 27",
    "sg:city":"Navas San Juan",
    "sg:orig_category":"Contenedores (mercanc\u00cdas)",
    "sg:phone":"+34 953 68 93 76",
    "sg:postcode":"23240",
    "sg:province":"Ja\u00e9n",
    "wof:name":"Torralba Medina Lucredio",
    "wof:placetype":"venue"
},
  "geometry": {"coordinates":[-3.312308073,38.1843948364],"type":"Point"}
}