{
  "type": "Feature",
  "properties": {
    "addr:full":"Carrer de Sant Gregori, 28 Roquetes Tarragona 43520",
    "addr:housenumber":"28",
    "addr:postcode":"43520",
    "addr:street":"Carrer De Sant Gregori",
    "iso:country":"ES",
    "sg:address":"Carrer de Sant Gregori, 28",
    "sg:city":"Roquetes",
    "sg:orig_category":"Relojer\u00cda (fabricaci\u00d3n, Al Por Mayor)",
    "sg:phone":"+34 977 50 05 34",
    "sg:postcode":"43520",
    "sg:province":"Tarragona",
    "wof:name":"Ferre Garzon Federico",
    "wof:placetype":"venue"
},
  "geometry": {"coordinates":[0.5050449967,40.8206443787],"type":"Point"}
}