{
  "type": "Feature",
  "properties": {
    "addr:full":"Calle de Martires, 2 Almendralejo Badajoz 06200",
    "addr:housenumber":"2",
    "addr:postcode":"06200",
    "addr:street":"Calle De Martires",
    "iso:country":"ES",
    "sg:address":"Calle de Martires, 2",
    "sg:city":"Almendralejo",
    "sg:orig_category":"Arquitectos",
    "sg:phone":"+34 924 67 07 07",
    "sg:postcode":"06200",
    "sg:province":"Badajoz",
    "wof:name":"Grupo Inmobiliario Alchal S.l.",
    "wof:placetype":"venue"
},
  "geometry": {"coordinates":[-6.4088959694,38.6810951233],"type":"Point"}
}