{
  "type": "Feature",
  "properties": {
    "addr:full":"Calle de Veigas Las, 3 Navia Asturias 33710",
    "addr:housenumber":"3",
    "addr:postcode":"33710",
    "addr:street":"Calle De Veigas Las",
    "iso:country":"ES",
    "sg:address":"Calle de Veigas Las, 3",
    "sg:city":"Navia",
    "sg:orig_category":"Agencias Y Agentes Comerciales, Representantes",
    "sg:phone":"+34 985 63 15 09",
    "sg:postcode":"33710",
    "sg:province":"Asturias",
    "wof:name":"Fernandez Fernandez Alberto",
    "wof:placetype":"venue"
},
  "geometry": {"coordinates":[-6.719124794,43.5420684814],"type":"Point"}
}