{
  "type": "Feature",
  "properties": {
    "addr:full":"Les Palmeretes, 38 Alfas Pi Alicante 03580",
    "addr:housenumber":"38",
    "addr:postcode":"03580",
    "addr:street":"Alfas Pi Alicante",
    "iso:country":"ES",
    "sg:address":"Les Palmeretes, 38",
    "sg:city":"Alfas Pi",
    "sg:orig_category":"Reposter\u00cdas",
    "sg:phone":"+34 965 88 85 89",
    "sg:postcode":"03580",
    "sg:province":"Alicante",
    "wof:name":"Cano  Graziela",
    "wof:placetype":"venue"
},
  "geometry": {"coordinates":[-0.1124010012,38.5868492126],"type":"Point"}
}