{
  "type": "Feature",
  "properties": {
    "addr:full":"Alamos, 37 Casanueva Granada 18291",
    "addr:housenumber":"37",
    "addr:postcode":"18291",
    "addr:street":"Alamos",
    "iso:country":"ES",
    "sg:address":"Alamos, 37",
    "sg:city":"Casanueva",
    "sg:classifiers":[
        {
            "category":"Taxi",
            "type":"Transportation"
        }
    ],
    "sg:phone":"+34 958 46 16 97",
    "sg:postcode":"18291",
    "sg:province":"Granada",
    "wof:name":"Mu\u00f1oz Pe\u00f1a Juan",
    "wof:placetype":"venue"
},
  "geometry": {"coordinates":[-3.7914540768,37.257270813],"type":"Point"}
}