{
  "type": "Feature",
  "properties": {
    "addr:full":"Pol. Ind. Valle G\u00fcimar, 11 Pol.ind. Guimar Santa Cruz De Tenerife 38509",
    "addr:housenumber":"11",
    "addr:postcode":"38509",
    "addr:street":"Gueimar;Guimar",
    "iso:country":"ES",
    "sg:address":"Pol. Ind. Valle G\u00fcimar, 11",
    "sg:city":"Pol.ind. Guimar",
    "sg:orig_category":"M\u00c1rmoles, Granitos Y Piedras Naturales",
    "sg:phone":"+34 922 50 45 20",
    "sg:postcode":"38509",
    "sg:province":"Santa Cruz De Tenerife",
    "wof:name":"Venus Watch S.l.",
    "wof:placetype":"venue"
},
  "geometry": {"coordinates":[-16.3740177155,28.3587932587],"type":"Point"}
}