{
  "type": "Feature",
  "properties": {
    "iso:country":"ES",
    "sg:address":"Calle de Maria Estrada, 13",
    "sg:city":"Pto. Rosario",
    "sg:orig_category":"Metalurgia",
    "sg:phone":"+34 928 85 98 51",
    "sg:postcode":"35600",
    "sg:province":"Las Palmas",
    "wof:name":"Rojas Gonzalez Maria Jose",
    "wof:placetype":"venue"
},
  "geometry": {"coordinates":[-13.8732919693,28.5037250519],"type":"Point"}
}