{
  "type": "Feature",
  "properties": {
    "addr:full":"Avda Reino Unido, S/n Sevilla Sevilla 41012",
    "addr:housenumber":"s / n",
    "addr:postcode":"41012",
    "addr:street":"Avda Reino Unido",
    "iso:country":"ES",
    "sg:address":"Avda Reino Unido, S/n",
    "sg:city":"Sevilla",
    "sg:orig_category":"Promotores Constructores",
    "sg:phone":"+34 954 61 97 32",
    "sg:postcode":"41012",
    "sg:province":"Sevilla",
    "wof:name":"Corsan Corvian S.a.",
    "wof:placetype":"venue"
},
  "geometry": {"coordinates":[-5.9767341614,37.3472900391],"type":"Point"}
}