{
  "type": "Feature",
  "properties": {
    "addr:full":"Calle de Carabela La Pinta, 14 Baiona Pontevedra 36300",
    "addr:housenumber":"14",
    "addr:postcode":"36300",
    "addr:street":"Calle De Carabela La Pinta",
    "iso:country":"ES",
    "sg:address":"Calle de Carabela La Pinta, 14",
    "sg:city":"Baiona",
    "sg:orig_category":"Bisuter\u00cda, Joyer\u00cda, Relojer\u00cda (al Por Menor)",
    "sg:phone":"+34 986 35 59 16",
    "sg:postcode":"36300",
    "sg:province":"Pontevedra",
    "wof:name":"Rodriguez Grandal Ramona",
    "wof:placetype":"venue"
},
  "geometry": {"coordinates":[-8.8510303497,42.120300293],"type":"Point"}
}