{
  "type": "Feature",
  "properties": {
    "addr:full":"Calle de Domingo Beltran De Otazu, 29 Vitoria-gasteiz \u00c1lava 01012",
    "addr:housenumber":"29",
    "addr:postcode":"01012",
    "addr:street":"Calle De Domingo Beltran De Otazu",
    "iso:country":"ES",
    "sg:address":"Calle de Domingo Beltran De Otazu, 29",
    "sg:city":"Vitoria-gasteiz",
    "sg:orig_category":"Ropa Para Se\u00d1oras Y Caballeros (al Por Menor)",
    "sg:phone":"+34 945 22 62 44",
    "sg:postcode":"01012",
    "sg:province":"\u00c1lava",
    "wof:name":"Coslada Sanchez Martina",
    "wof:placetype":"venue"
},
  "geometry": {"coordinates":[-2.6772649288,42.8526000977],"type":"Point"}
}