{
  "type": "Feature",
  "properties": {
    "iso:country":"ES",
    "sg:address":"Santiago Apostol, 4",
    "sg:city":"Algemesi",
    "sg:orig_category":"Lavado, Limpieza De Veh\u00cdculos",
    "sg:phone":"+34 962 48 46 03",
    "sg:postcode":"46680",
    "sg:province":"Valencia",
    "wof:name":"Centre Del Llabat El Pont S.l",
    "wof:placetype":"venue"
},
  "geometry": {"coordinates":[-0.4329439998,39.1920776367],"type":"Point"}
}