{
  "type": "Feature",
  "properties": {
    "addr:full":"Calle de Extremadura, 6 Jerez De Los Caballeros Badajoz 06380",
    "addr:housenumber":"6",
    "addr:postcode":"06380",
    "addr:street":"Calle De Extremadura",
    "iso:country":"ES",
    "sg:address":"Calle de Extremadura, 6",
    "sg:city":"Jerez De Los Caballeros",
    "sg:orig_category":"Agricultura: Abastecimiento Y Cosechado (negocio)",
    "sg:phone":"+34 924 75 11 87",
    "sg:postcode":"06380",
    "sg:province":"Badajoz",
    "wof:name":"Union De Peque\u00f1os Agricultores De Extremadura",
    "wof:placetype":"venue"
},
  "geometry": {"coordinates":[-6.7720041275,38.3228111267],"type":"Point"}
}