{
  "type": "Feature",
  "properties": {
    "iso:country":"ES",
    "sg:address":"Carr General Guell, 25",
    "sg:city":"Cervera",
    "sg:orig_category":"Caf\u00c9s, Bares, Cervecer\u00cdas",
    "sg:phone":"+34 973 53 12 23",
    "sg:postcode":"25200",
    "sg:province":"Lleida",
    "wof:name":"Tastalletres Scp",
    "wof:placetype":"venue"
},
  "geometry": {"coordinates":[1.2740459442,41.6720123291],"type":"Point"}
}