{
  "type": "Feature",
  "properties": {
    "iso:country":"ES",
    "sg:address":"Calle de Alberto Aguilera, 10",
    "sg:city":"Madrid",
    "sg:orig_category":"Artes Gr\u00c1ficas, Artes Pl\u00c1sticas (curso)",
    "sg:phone":"+34 914 46 34 41",
    "sg:postcode":"28015",
    "sg:province":"Madrid",
    "wof:name":"Lopez Moya Luis",
    "wof:placetype":"venue"
},
  "geometry": {"coordinates":[-3.7074224949,40.4298095703],"type":"Point"}
}