{
  "type": "Feature",
  "properties": {
    "addr:full":"Calle de Gabriel Y Galan, S/n Piornal C\u00e1ceres 10615",
    "addr:housenumber":"s / n",
    "addr:postcode":"10615",
    "addr:street":"Calle De Gabriel Y Galan;Ca\u0301Ceres",
    "iso:country":"ES",
    "sg:address":"Calle de Gabriel Y Galan, S/n",
    "sg:city":"Piornal",
    "sg:orig_category":"Arquitectos",
    "sg:phone":"+34 927 47 62 19",
    "sg:postcode":"10615",
    "sg:province":"C\u00e1ceres",
    "wof:name":"Moreno Fernandez Jose Antonio",
    "wof:placetype":"venue"
},
  "geometry": {"coordinates":[-5.8495240211,40.1169548035],"type":"Point"}
}