{
  "type": "Feature",
  "properties": {
    "iso:country":"ES",
    "sg:address":"Calle de Francisco Iglesias, 50",
    "sg:city":"Madrid",
    "sg:orig_category":"Electrodom\u00c9sticos (al Por Menor)",
    "sg:phone":"+34 914 30 42 69",
    "sg:postcode":"28038",
    "sg:province":"Madrid",
    "wof:name":"Sanchez Armenteros Juan",
    "wof:placetype":"venue"
},
  "geometry": {"coordinates":[-3.6629679203,40.3981666565],"type":"Point"}
}