{
  "type": "Feature",
  "properties": {
    "iso:country":"ES",
    "sg:address":"Via Rio Tremor, 1",
    "sg:city":"Ponferrada",
    "sg:orig_category":"Inform\u00c1tica (estudios, Servicios, Asesor\u00cda, Formaci\u00d3n)",
    "sg:phone":"+34 987 42 98 22",
    "sg:postcode":"24400",
    "sg:province":"Le\u00f3n",
    "sg:website":"www.bis.es",
    "wof:name":"Buenas Ideas De Software S.l.",
    "wof:placetype":"venue"
},
  "geometry": {"coordinates":[-6.5958590508,42.5511665344],"type":"Point"}
}