{
  "type": "Feature",
  "properties": {
    "iso:country":"ES",
    "sg:address":"Plaz Espa\u00d1a, 5",
    "sg:city":"Alameda",
    "sg:orig_category":"Ense\u00d1anza, Formaci\u00d3n Profesional: Aprendizaje",
    "sg:phone":"+34 952 71 00 25",
    "sg:postcode":"29530",
    "sg:province":"M\u00e1laga",
    "wof:name":"Ayuntamiento De Alameda",
    "wof:placetype":"venue"
},
  "geometry": {"coordinates":[-4.6579809189,37.2077293396],"type":"Point"}
}