{
  "type": "Feature",
  "properties": {
    "iso:country":"ES",
    "sg:address":"Calle de Pico Almanzor (del), 57",
    "sg:city":"Humanes De Madrid",
    "sg:orig_category":"Conservas De Carnes (fabricaci\u00d3n, Al Por Mayor)",
    "sg:phone":"+34 916 04 94 93",
    "sg:postcode":"28970",
    "sg:province":"Madrid",
    "wof:name":"Hermanos Moreno Blazquez S.l.",
    "wof:placetype":"venue"
},
  "geometry": {"coordinates":[-3.8118948936,40.2626876831],"type":"Point"}
}