{
  "type": "Feature",
  "properties": {
    "addr:full":"Calle de General Millan Astray, 32 Madrid Madrid 28044",
    "addr:housenumber":"32",
    "addr:postcode":"madrid;28044",
    "addr:street":"Calle De General Millan Astray",
    "iso:country":"ES",
    "sg:address":"Calle de General Millan Astray, 32",
    "sg:city":"Madrid",
    "sg:orig_category":"Farmacias",
    "sg:phone":"+34 917 05 26 58",
    "sg:postcode":"28044",
    "sg:province":"Madrid",
    "wof:name":"Perez-hidalgo Garach Maria Angustias",
    "wof:placetype":"venue"
},
  "geometry": {"coordinates":[-3.766356945,40.37707901],"type":"Point"}
}