{
  "type": "Feature",
  "properties": {
    "addr:full":"Rbla Sant Sebastia, 47 Santa Coloma De Gramenet Barcelona 08921",
    "addr:housenumber":"47",
    "addr:postcode":"08921",
    "addr:street":"Rbla Sant Sebastia",
    "iso:country":"ES",
    "sg:address":"Rbla Sant Sebastia, 47",
    "sg:city":"Santa Coloma De Gramenet",
    "sg:orig_category":"Cajas Para Embalar",
    "sg:phone":"+34 933 85 11 26",
    "sg:postcode":"08921",
    "sg:province":"Barcelona",
    "wof:name":"Cajamar",
    "wof:placetype":"venue"
},
  "geometry": {"coordinates":[2.2135899067,41.4505615234],"type":"Point"}
}