{
  "type": "Feature",
  "properties": {
    "iso:country":"ES",
    "sg:address":"Calle de Ricardo Romero, 28",
    "sg:city":"Almendralejo",
    "sg:orig_category":"M\u00c9dicos: Ginecolog\u00cda Y Obstetricia",
    "sg:phone":"+34 924 66 25 73",
    "sg:postcode":"06200",
    "sg:province":"Badajoz",
    "wof:name":"Garcia Hurtado Luis",
    "wof:placetype":"venue"
},
  "geometry": {"coordinates":[-6.4071397781,38.6841201782],"type":"Point"}
}