{
  "type": "Feature",
  "properties": {
    "iso:country":"ES",
    "sg:address":"Av Pais Valencia, 54",
    "sg:city":"Alcoi",
    "sg:orig_category":"Asociaciones, Organismos Culturales Y Socioeducativos",
    "sg:phone":"+34 965 54 37 65",
    "sg:postcode":"03801",
    "sg:province":"Alicante",
    "wof:name":"Circulo Industrial",
    "wof:placetype":"venue"
},
  "geometry": {"coordinates":[-0.4774259925,38.6960601807],"type":"Point"}
}