{
  "type": "Feature",
  "properties": {
    "iso:country":"ES",
    "sg:address":"Pol Ind Los Pontones, 40",
    "sg:city":"Sese\u00f1a Nuevo",
    "sg:orig_category":"Agencias De Viajes",
    "sg:phone":"+34 918 01 31 08",
    "sg:postcode":"45224",
    "sg:province":"Toledo",
    "wof:name":"Marbet Viajes S.a.",
    "wof:placetype":"venue"
},
  "geometry": {"coordinates":[-3.6464540958,40.1091346741],"type":"Point"}
}