{
  "type": "Feature",
  "properties": {
    "iso:country":"ES",
    "sg:address":"Calle de Padre Vicent, 6",
    "sg:city":"Valencia",
    "sg:orig_category":"Plomeros",
    "sg:phone":"+34 963 33 07 64",
    "sg:postcode":"46006",
    "sg:province":"Valencia",
    "wof:name":"Sanchez Bernal Francisco",
    "wof:placetype":"venue"
},
  "geometry": {"coordinates":[-0.3723120093,39.4572257996],"type":"Point"}
}