{
  "type": "Feature",
  "properties": {
    "addr:full":"Calle de Corredera De San Marcos, 23 Linares Ja\u00e9n 23700",
    "addr:housenumber":"23",
    "addr:postcode":"23700",
    "addr:street":"Calle De Corredera De San Marcos;Jae\u0301N",
    "iso:country":"ES",
    "sg:address":"Calle de Corredera De San Marcos, 23",
    "sg:city":"Linares",
    "sg:orig_category":"Abogados",
    "sg:phone":"+34 953 69 19 59",
    "sg:postcode":"23700",
    "sg:province":"Ja\u00e9n",
    "wof:name":"Sanz Gutierrez Mariano",
    "wof:placetype":"venue"
},
  "geometry": {"coordinates":[-3.6342000961,38.0968475342],"type":"Point"}
}