{
  "type": "Feature",
  "properties": {
    "addr:full":"Carr Doctor Moliner, S/n Burjassot Valencia 46100",
    "addr:housenumber":"s / n",
    "addr:postcode":"46100",
    "addr:street":"Carr Doctor Moliner",
    "iso:country":"ES",
    "sg:address":"Carr Doctor Moliner, S/n",
    "sg:city":"Burjassot",
    "sg:orig_category":"Polideportivos",
    "sg:phone":"+34 963 64 34 65",
    "sg:postcode":"46100",
    "sg:province":"Valencia",
    "wof:name":"Ayuntamiento De Burjasot",
    "wof:placetype":"venue"
},
  "geometry": {"coordinates":[-0.4168108106,39.507774353],"type":"Point"}
}