{
  "type": "Feature",
  "properties": {
    "addr:full":"Pol. Ind. Comte De Sert, S/n Castellbisbal Barcelona 08755",
    "addr:housenumber":"s / n",
    "addr:postcode":"08755",
    "addr:street":"Sert",
    "iso:country":"ES",
    "sg:address":"Pol. Ind. Comte De Sert, S/n",
    "sg:city":"Castellbisbal",
    "sg:orig_category":"Minerales (al Por Mayor)",
    "sg:phone":"+34 937 72 18 27",
    "sg:postcode":"08755",
    "sg:province":"Barcelona",
    "wof:name":"Distribuidora De Talco S.a.",
    "wof:placetype":"venue"
},
  "geometry": {"coordinates":[1.9527029991,41.4898147583],"type":"Point"}
}