{
  "type": "Feature",
  "properties": {
    "addr:full":"Calle de Victoria (la), 3 Cenicero La Rioja 26350",
    "addr:housenumber":"3",
    "addr:postcode":"26350",
    "addr:street":"Calle De Victoria La;Rioja",
    "iso:country":"ES",
    "sg:address":"Calle de Victoria (la), 3",
    "sg:city":"Cenicero",
    "sg:orig_category":"Asociaciones, Organismos Culturales Y Socioeducativos",
    "sg:phone":"+34 941 45 46 72",
    "sg:postcode":"26350",
    "sg:province":"La Rioja",
    "wof:name":"Ayuntamiento De Cenicero",
    "wof:placetype":"venue"
},
  "geometry": {"coordinates":[-2.6421272755,42.4813499451],"type":"Point"}
}