{
  "type": "Feature",
  "properties": {
    "iso:country":"ES",
    "sg:address":"Calle de Eugenia Astur, 48",
    "sg:city":"Tineo",
    "sg:orig_category":"Inform\u00c1tica (estudios, Servicios, Asesor\u00cda, Formaci\u00d3n)",
    "sg:phone":"+34 985 90 06 19",
    "sg:postcode":"33870",
    "sg:province":"Asturias",
    "wof:name":"Computer Set S.a.",
    "wof:placetype":"venue"
},
  "geometry": {"coordinates":[-6.4128389359,43.3349685669],"type":"Point"}
}