{
  "type": "Feature",
  "properties": {
    "iso:country":"ES",
    "sg:address":"Carrer de Regomir, 10",
    "sg:city":"Barcelona",
    "sg:orig_category":"Carnicer\u00cdas, Carnicer\u00cdas",
    "sg:phone":"+34 933 15 20 08",
    "sg:postcode":"08002",
    "sg:province":"Barcelona",
    "wof:name":"Corominas Collell Jaime",
    "wof:placetype":"venue"
},
  "geometry": {"coordinates":[2.1793088913,41.3812026978],"type":"Point"}
}