{
  "type": "Feature",
  "properties": {
    "iso:country":"ES",
    "sg:address":"Calle de Carrera Chica, 18",
    "sg:city":"Villafranca De Los Barros",
    "sg:orig_category":"Procuradores",
    "sg:phone":"+34 924 52 03 34",
    "sg:postcode":"06220",
    "sg:province":"Badajoz",
    "wof:name":"Lopez-navarrete Lopez Javier",
    "wof:placetype":"venue"
},
  "geometry": {"coordinates":[-6.341963768,38.5610313416],"type":"Point"}
}