{
  "type": "Feature",
  "properties": {
    "addr:full":"Plaz Constitucion, 5 S. Fulgencio Alicante 03177",
    "addr:postcode":"03177",
    "addr:street":"Constitucion 5 S. Fulgencio Alicante",
    "iso:country":"ES",
    "sg:address":"Plaz Constitucion, 5",
    "sg:city":"S. Fulgencio",
    "sg:orig_category":"Cajas De Ahorro",
    "sg:phone":"+34 966 79 40 01",
    "sg:postcode":"03177",
    "sg:province":"Alicante",
    "wof:name":"Caja De Ahorros Del Mediterraneo",
    "wof:placetype":"venue"
},
  "geometry": {"coordinates":[-0.7383440137,38.1049537659],"type":"Point"}
}