{
  "type": "Feature",
  "properties": {
    "iso:country":"ES",
    "sg:address":"Calle de Projecte 21 - Poligono Industrial, 15",
    "sg:city":"Catarroja",
    "sg:orig_category":"Parques De Atracciones Y Centros De Esparcimiento",
    "sg:phone":"+34 961 26 91 00",
    "sg:postcode":"46470",
    "sg:province":"Valencia",
    "wof:name":"Amusement Machines Grupo Comatel S.l.",
    "wof:placetype":"venue"
},
  "geometry": {"coordinates":[-0.4035184085,39.4027366638],"type":"Point"}
}