{
  "type": "Feature",
  "properties": {
    "iso:country":"ES",
    "sg:address":"Calle de Capitan Angosto Gomez Castrillon (del), 56",
    "sg:city":"Aranjuez",
    "sg:orig_category":"Peluquer\u00cdas, Peluquer\u00cda Mixta",
    "sg:phone":"+34 918 92 05 09",
    "sg:postcode":"28300",
    "sg:province":"Madrid",
    "wof:name":"Anton Galiano Felix",
    "wof:placetype":"venue"
},
  "geometry": {"coordinates":[-3.6019208431,40.0335540771],"type":"Point"}
}