{
  "type": "Feature",
  "properties": {
    "addr:full":"Ctra Burgos-portugal, Km. 0182,3 Alaejos Valladolid 47510",
    "addr:postcode":"47510",
    "addr:street":"Ctra Burgos-Portugal Km. 0182,3",
    "iso:country":"ES",
    "sg:address":"Ctra Burgos-portugal, Km. 0182,3",
    "sg:city":"Alaejos",
    "sg:orig_category":"Empresas De Electricidad En General",
    "sg:phone":"+34 983 86 72 98",
    "sg:postcode":"47510",
    "sg:province":"Valladolid",
    "wof:name":"Hijo De Jorge Martin S. A.",
    "wof:placetype":"venue"
},
  "geometry": {"coordinates":[-5.2193279266,41.3066864014],"type":"Point"}
}