{
  "type": "Feature",
  "properties": {
    "addr:full":"Carrer de Madrazo, 27 Barcelona Barcelona 08006",
    "addr:housenumber":"27",
    "addr:postcode":"08006",
    "addr:street":"Carrer De Madrazo",
    "iso:country":"ES",
    "sg:address":"Carrer de Madrazo, 27",
    "sg:city":"Barcelona",
    "sg:orig_category":"Abogados",
    "sg:phone":"+34 934 15 44 71",
    "sg:postcode":"08006",
    "sg:province":"Barcelona",
    "wof:name":"Vilaclara Fatjo Eulalia",
    "wof:placetype":"venue"
},
  "geometry": {"coordinates":[2.1495909691,41.4005737305],"type":"Point"}
}