{
  "type": "Feature",
  "properties": {
    "addr:full":"Calle de Iglesia, 2 Lomoviejo Valladolid 47494",
    "addr:housenumber":"2",
    "addr:postcode":"47494",
    "addr:street":"Calle De Iglesia",
    "iso:country":"ES",
    "sg:address":"Calle de Iglesia, 2",
    "sg:city":"Lomoviejo",
    "sg:orig_category":"Cr\u00cda De Bovinos",
    "sg:phone":"+34 983 82 43 07",
    "sg:postcode":"47494",
    "sg:province":"Valladolid",
    "wof:name":"Los Labajos Del Corral S.l.",
    "wof:placetype":"venue"
},
  "geometry": {"coordinates":[-4.9181919098,41.1488113403],"type":"Point"}
}