{
  "type": "Feature",
  "properties": {
    "addr:full":"Pol Ind (marismas De Bengoa), S/n Santo\u00f1a Cantabria 39740",
    "addr:housenumber":"s / n",
    "addr:postcode":"39740",
    "iso:country":"ES",
    "sg:address":"Pol Ind (marismas De Bengoa), S/n",
    "sg:city":"Santo\u00f1a",
    "sg:orig_category":"Agencias Y Agentes Comerciales, Representantes",
    "sg:phone":"+34 942 67 13 91",
    "sg:postcode":"39740",
    "sg:province":"Cantabria",
    "wof:name":"Conservas Angelachu S.l.",
    "wof:placetype":"venue"
},
  "geometry": {"coordinates":[-3.4538080692,43.4452705383],"type":"Point"}
}