{
  "type": "Feature",
  "properties": {
    "iso:country":"ES",
    "sg:address":"Calle de Isabel La Catolica, 10",
    "sg:city":"Aguilas",
    "sg:orig_category":"Molduras, Junquillos, Listones Y Molduras Perforadas",
    "sg:phone":"+34 968 41 37 71",
    "sg:postcode":"30880",
    "sg:province":"Murcia",
    "wof:name":"Perez Ortega Miguel",
    "wof:placetype":"venue"
},
  "geometry": {"coordinates":[-1.5823119879,37.4028282166],"type":"Point"}
}