{
  "type": "Feature",
  "properties": {
    "iso:country":"ES",
    "sg:address":"Carrer de Espronceda, 84",
    "sg:city":"Barcelona",
    "sg:orig_category":"Reposter\u00cdas",
    "sg:phone":"+34 933 07 14 01",
    "sg:postcode":"08005",
    "sg:province":"Barcelona",
    "wof:name":"Bon-gra Fleca I Pastisserias S.l.",
    "wof:placetype":"venue"
},
  "geometry": {"coordinates":[2.2052810192,41.4049072266],"type":"Point"}
}