{
  "type": "Feature",
  "properties": {
    "iso:country":"ES",
    "sg:address":"Ctra. Zaragoza-portugal, Km. 0292,5",
    "sg:city":"Valdezate",
    "sg:orig_category":"Productores Recolectores, Venta Directa De Vinos",
    "sg:phone":"+34 947 55 00 64",
    "sg:postcode":"09318",
    "sg:province":"Burgos",
    "wof:name":"Pomar Vi\u00f1edos S.l",
    "wof:placetype":"venue"
},
  "geometry": {"coordinates":[-3.942152977,41.6167030334],"type":"Point"}
}