{
  "type": "Feature",
  "properties": {
    "addr:full":"Calle de Gardeazabal Juan, 2 Bilbao Vizcaya 48004",
    "addr:housenumber":"2",
    "addr:postcode":"48004",
    "addr:street":"Calle De Gardeazabal Juan",
    "iso:country":"ES",
    "sg:address":"Calle de Gardeazabal Juan, 2",
    "sg:city":"Bilbao",
    "sg:orig_category":"Asociaciones Y Clubs Deportivos",
    "sg:phone":"+34 944 33 33 69",
    "sg:postcode":"48004",
    "sg:province":"Vizcaya",
    "wof:name":"Body Teach.-lidia Rodriguez Pereda",
    "wof:placetype":"venue"
},
  "geometry": {"coordinates":[-2.9149889946,43.2515907288],"type":"Point"}
}