{
  "type": "Feature",
  "properties": {
    "addr:full":"Avda Ferrol (del), 1 Viveiro Lugo 27850",
    "addr:housenumber":"1",
    "addr:postcode":"27850",
    "addr:street":"Avda Ferrol Del",
    "iso:country":"ES",
    "sg:address":"Avda Ferrol (del), 1",
    "sg:city":"Viveiro",
    "sg:orig_category":"M\u00c9dicos: Estomatolog\u00cda",
    "sg:phone":"+34 982 56 20 02",
    "sg:postcode":"27850",
    "sg:province":"Lugo",
    "wof:name":"Fernandez Portilla Francisco",
    "wof:placetype":"venue"
},
  "geometry": {"coordinates":[-7.5992488861,43.6569519043],"type":"Point"}
}