{
  "type": "Feature",
  "properties": {
    "iso:country":"ES",
    "sg:address":"Av Diagonal, 21",
    "sg:city":"Gava",
    "sg:orig_category":"Aparatos, Material Y Suministros Para Laboratorios",
    "sg:phone":"+34 936 38 20 56",
    "sg:postcode":"08850",
    "sg:province":"Barcelona",
    "wof:name":"Tecnologia Difusion Iberica S.l.",
    "wof:placetype":"venue"
},
  "geometry": {"coordinates":[1.9966390133,41.3051300049],"type":"Point"}
}