{
  "type": "Feature",
  "properties": {
    "iso:country":"ES",
    "sg:address":"Canosa, S/n",
    "sg:city":"Rus",
    "sg:orig_category":"Cooperativas Agr\u00cdcolas",
    "sg:phone":"+34 981 70 55 00",
    "sg:postcode":"15109",
    "sg:province":"La Coru\u00f1a",
    "wof:name":"Coreber S.c.g.",
    "wof:placetype":"venue"
},
  "geometry": {"coordinates":[-8.6633071899,43.2020225525],"type":"Point"}
}