{
  "type": "Feature",
  "properties": {
    "iso:country":"ES",
    "sg:address":"Calle de Almonte, 105",
    "sg:city":"Hinojos",
    "sg:orig_category":"Negocio De Materiales De Construcci\u00d3n",
    "sg:phone":"+34 959 45 92 77",
    "sg:postcode":"21740",
    "sg:province":"Huelva",
    "wof:name":"Polvero Los Naranjo S.l.",
    "wof:placetype":"venue"
},
  "geometry": {"coordinates":[-6.3817205429,37.2891654968],"type":"Point"}
}