{
  "type": "Feature",
  "properties": {
    "iso:country":"ES",
    "sg:address":"Calle de Juan Pantoja, 23",
    "sg:city":"Madrid",
    "sg:orig_category":"Molduras, Junquillos, Listones Y Molduras Perforadas",
    "sg:phone":"+34 915 33 43 85",
    "sg:postcode":"28039",
    "sg:province":"Madrid",
    "wof:name":"Cabrera De Leon Aneudy",
    "wof:placetype":"venue"
},
  "geometry": {"coordinates":[-3.7055699825,40.4500312805],"type":"Point"}
}