{
  "type": "Feature",
  "properties": {
    "iso:country":"ES",
    "sg:address":"Calle de Hermanos Carpi, 4",
    "sg:city":"Madrid",
    "sg:orig_category":"Lavado, Limpieza De Veh\u00cdculos",
    "sg:phone":"+34 915 52 11 79",
    "sg:postcode":"28038",
    "sg:province":"Madrid",
    "wof:name":"Cerrada Carpi Eugenio",
    "wof:placetype":"venue"
},
  "geometry": {"coordinates":[-3.6658399105,40.4012680054],"type":"Point"}
}