{
  "type": "Feature",
  "properties": {
    "addr:full":"Calle de Pintor Murillo, 16 Montijo Badajoz 06480",
    "addr:housenumber":"16",
    "addr:postcode":"06480",
    "addr:street":"Calle De Pintor Murillo",
    "iso:country":"ES",
    "sg:address":"Calle de Pintor Murillo, 16",
    "sg:city":"Montijo",
    "sg:orig_category":"Centros De Educaci\u00d3n Especial",
    "sg:phone":"+34 924 45 67 77",
    "sg:postcode":"06480",
    "sg:province":"Badajoz",
    "wof:name":"Ayuntamiento De Montijo",
    "wof:placetype":"venue"
},
  "geometry": {"coordinates":[-6.6204452515,38.9083938599],"type":"Point"}
}