{
  "type": "Feature",
  "properties": {
    "addr:full":"Plaz Esperanza (de La), 1 Puerto De Santa Maria C\u00e1diz 11500",
    "addr:postcode":"11500",
    "addr:street":"Plaz;1;Ca\u0301Diz",
    "iso:country":"ES",
    "sg:address":"Plaz Esperanza (de La), 1",
    "sg:city":"Puerto De Santa Maria",
    "sg:orig_category":"Laboratorios Y Cl\u00cdnicas Veterinarias",
    "sg:phone":"+34 956 87 07 17",
    "sg:postcode":"11500",
    "sg:province":"C\u00e1diz",
    "wof:name":"Jose Maria Avila Fornell S.l.",
    "wof:placetype":"venue"
},
  "geometry": {"coordinates":[-6.2269763947,36.6302452087],"type":"Point"}
}