{
  "type": "Feature",
  "properties": {
    "iso:country":"ES",
    "sg:address":"Ctra Fuente En Corts, 186",
    "sg:city":"Valencia",
    "sg:orig_category":"Producci\u00d3n De Abonos Y De Fertilizantes",
    "sg:phone":"+34 963 34 41 36",
    "sg:postcode":"46013",
    "sg:province":"Valencia",
    "wof:name":"Nacher Cubells Jose Ramon",
    "wof:placetype":"venue"
},
  "geometry": {"coordinates":[-0.3553819954,39.4369506836],"type":"Point"}
}