{
  "type": "Feature",
  "properties": {
    "iso:country":"ES",
    "sg:address":"Calle de Geltoki, S/n",
    "sg:city":"Mundaka",
    "sg:orig_category":"Importaci\u00d3n",
    "sg:phone":"+34 946 87 67 97",
    "sg:postcode":"48360",
    "sg:province":"Vizcaya",
    "wof:name":"Data Export S.l.",
    "wof:placetype":"venue"
},
  "geometry": {"coordinates":[-2.7006220818,43.4092292786],"type":"Point"}
}