{
  "type": "Feature",
  "properties": {
    "iso:country":"ES",
    "sg:address":"Cami Moli Vinyals, 1",
    "sg:city":"Terrassola",
    "sg:orig_category":"Panader\u00cdas, Pasteler\u00cdas, Boller\u00cda Industriale (fabricaci\u00d3n, Al Por Mayor)",
    "sg:phone":"+34 938 99 53 77",
    "sg:postcode":"08775",
    "sg:province":"Barcelona",
    "wof:name":"Inbopal S.a.",
    "wof:placetype":"venue"
},
  "geometry": {"coordinates":[1.7272900343,41.4427185059],"type":"Point"}
}