{
  "type": "Feature",
  "properties": {
    "addr:full":"Calle de Iglesia, 1 Fuentes Ebro Zaragoza 50740",
    "addr:housenumber":"1",
    "addr:postcode":"50740",
    "addr:street":"Calle De Iglesia",
    "iso:country":"ES",
    "sg:address":"Calle de Iglesia, 1",
    "sg:city":"Fuentes Ebro",
    "sg:orig_category":"Electricidad: Instaladores",
    "sg:phone":"+34 976 16 08 92",
    "sg:postcode":"50740",
    "sg:province":"Zaragoza",
    "wof:name":"Artajona Viamonte S.l",
    "wof:placetype":"venue"
},
  "geometry": {"coordinates":[-0.630787611,41.5126266479],"type":"Point"}
}