{
  "type": "Feature",
  "properties": {
    "iso:country":"ES",
    "sg:address":"Ctra M-103, Km. 0022,6",
    "sg:city":"Moraleja",
    "sg:orig_category":"Organizaci\u00d3n De Actos, Seminarios Y Congresos",
    "sg:phone":"+34 918 41 72 82",
    "sg:postcode":"28160",
    "sg:province":"Madrid",
    "sg:website":"www.elmanjardetalamanca.com",
    "wof:name":"El Manjar De Talamanca S.l.",
    "wof:placetype":"venue"
},
  "geometry": {"coordinates":[-3.5078120232,40.7456016541],"type":"Point"}
}