{
  "type": "Feature",
  "properties": {
    "iso:country":"ES",
    "sg:address":"Carrer de Calvet, 26",
    "sg:city":"Barcelona",
    "sg:orig_category":"Ropa Para Se\u00d1oras (al Por Menor)",
    "sg:phone":"+34 934 14 68 06",
    "sg:postcode":"08021",
    "sg:province":"Barcelona",
    "wof:name":"Luna Batista S.l.",
    "wof:placetype":"venue"
},
  "geometry": {"coordinates":[2.144464016,41.3941497803],"type":"Point"}
}