{
  "type": "Feature",
  "properties": {
    "iso:country":"ES",
    "sg:address":"Carrer de Alcalde Marian Fonts I Ciurana, 42",
    "sg:city":"Canonja",
    "sg:orig_category":"Peluquer\u00cdas, Peluquer\u00cda Mixta",
    "sg:phone":"+34 977 55 21 04",
    "sg:postcode":"43110",
    "sg:province":"Tarragona",
    "wof:name":"Dominguez Cuadrado Maria Jose",
    "wof:placetype":"venue"
},
  "geometry": {"coordinates":[1.1811039448,41.1230506897],"type":"Point"}
}