{
  "type": "Feature",
  "properties": {
    "iso:country":"ES",
    "sg:address":"Carrer de Bages, 10",
    "sg:city":"Calafell",
    "sg:orig_category":"Partidos Pol\u00cdticos",
    "sg:phone":"+34 977 69 46 76",
    "sg:postcode":"43820",
    "sg:province":"Tarragona",
    "wof:name":"Convergencia Democratica Calafell",
    "wof:placetype":"venue"
},
  "geometry": {"coordinates":[1.5666409731,41.2010192871],"type":"Point"}
}