{
  "type": "Feature",
  "properties": {
    "iso:country":"ES",
    "sg:address":"Calle de Jesualdo Dominguez (de), 1",
    "sg:city":"Santorcaz",
    "sg:orig_category":"Farmacias",
    "sg:phone":"+34 918 84 03 01",
    "sg:postcode":"28818",
    "sg:province":"Madrid",
    "wof:name":"Suarez Muelas Sagrario",
    "wof:placetype":"venue"
},
  "geometry": {"coordinates":[-3.232614994,40.4725112915],"type":"Point"}
}