{
  "type": "Feature",
  "properties": {
    "iso:country":"ES",
    "sg:address":"Pso. Maritimo, S/n",
    "sg:city":"Torrox-costa",
    "sg:orig_category":"Doctores En Medicina",
    "sg:phone":"+34 952 52 76 36",
    "sg:postcode":"29793",
    "sg:province":"M\u00e1laga",
    "wof:name":"Med-connection S.l.",
    "wof:placetype":"venue"
},
  "geometry": {"coordinates":[-3.9456365108,36.7326087952],"type":"Point"}
}