{
  "type": "Feature",
  "properties": {
    "addr:full":"Mayor-nagusia Kalea, 16 Iru\u00f1a Navarra 31001",
    "addr:housenumber":"16",
    "addr:postcode":"31001",
    "addr:street":"Mayor-Nagusia Kalea",
    "iso:country":"ES",
    "sg:address":"Mayor-nagusia Kalea, 16",
    "sg:city":"Iru\u00f1a",
    "sg:orig_category":"Empresas De Desmonte",
    "sg:phone":"+34 948 22 93 06",
    "sg:postcode":"31001",
    "sg:province":"Navarra",
    "wof:name":"Eguiluz Yoldi Maria Cruz",
    "wof:placetype":"venue"
},
  "geometry": {"coordinates":[-1.6460829973,42.8181724548],"type":"Point"}
}