{
  "type": "Feature",
  "properties": {
    "addr:full":"Plaz Caidos En La Guerra Civil, 4 Guadalajara Guadalajara 19001",
    "addr:postcode":"19001",
    "iso:country":"ES",
    "sg:address":"Plaz Caidos En La Guerra Civil, 4",
    "sg:city":"Guadalajara",
    "sg:orig_category":"Centros De Coordinaci\u00d3n",
    "sg:phone":"+34 949 21 69 13",
    "sg:postcode":"19001",
    "sg:province":"Guadalajara",
    "wof:name":"Asesoria Busons S.l.",
    "wof:placetype":"venue"
},
  "geometry": {"coordinates":[-3.1666707993,40.6332778931],"type":"Point"}
}