{
  "type": "Feature",
  "properties": {
    "addr:full":"Calle de Balmes, 10 Hellin Albacete 02400",
    "addr:housenumber":"10",
    "addr:postcode":"02400",
    "addr:street":"Calle De Balmes",
    "iso:country":"ES",
    "sg:address":"Calle de Balmes, 10",
    "sg:city":"Hellin",
    "sg:orig_category":"Electrodom\u00c9sticos (al Por Menor)",
    "sg:phone":"+34 967 30 17 68",
    "sg:postcode":"02400",
    "sg:province":"Albacete",
    "sg:website":"www.seertecnic-hellin.com",
    "wof:name":"Seertecnic Balmes Hellin S.l.l.",
    "wof:placetype":"venue"
},
  "geometry": {"coordinates":[-1.6959040165,38.507648468],"type":"Point"}
}