{
  "type": "Feature",
  "properties": {
    "addr:full":"Avgd Blondel, 3 Lleida Lleida 25002",
    "addr:housenumber":"3",
    "addr:postcode":"25002",
    "addr:street":"Blondel",
    "iso:country":"ES",
    "sg:address":"Avgd Blondel, 3",
    "sg:city":"Lleida",
    "sg:orig_category":"Empresarios",
    "sg:phone":"+34 973 27 07 88",
    "sg:postcode":"25002",
    "sg:province":"Lleida",
    "wof:name":"Fundacio 'la Caixa'",
    "wof:placetype":"venue"
},
  "geometry": {"coordinates":[0.6244519949,41.6127281189],"type":"Point"}
}