{
  "type": "Feature",
  "properties": {
    "addr:full":"Calle de Franciscas, 17 Almagro Ciudad Real 13270",
    "addr:housenumber":"17",
    "addr:postcode":"13270",
    "addr:street":"Calle De Franciscas",
    "iso:country":"ES",
    "sg:address":"Calle de Franciscas, 17",
    "sg:city":"Almagro",
    "sg:orig_category":"Arquitectos",
    "sg:phone":"+34 926 88 20 07",
    "sg:postcode":"13270",
    "sg:province":"Ciudad Real",
    "wof:name":"Garcia Navarro Estudio S.l.",
    "wof:placetype":"venue"
},
  "geometry": {"coordinates":[-3.7143011093,38.8876037598],"type":"Point"}
}