{
  "type": "Feature",
  "properties": {
    "addr:full":"Plaz Don Blasco, 21 Benasal Castell\u00f3n 12160",
    "addr:housenumber":"21",
    "addr:postcode":"12160",
    "addr:street":"Blasco;Castello\u0301N",
    "iso:country":"ES",
    "sg:address":"Plaz Don Blasco, 21",
    "sg:city":"Benasal",
    "sg:orig_category":"Promotores Constructores",
    "sg:phone":"+34 964 43 11 80",
    "sg:postcode":"12160",
    "sg:province":"Castell\u00f3n",
    "wof:name":"Severino Belles E Hijos S.l.",
    "wof:placetype":"venue"
},
  "geometry": {"coordinates":[-0.1405189931,40.3801345825],"type":"Point"}
}