{
  "type": "Feature",
  "properties": {
    "addr:full":"Carrer de Bartomeu Rossello, 7 Palma Islas Baleares 07014",
    "addr:housenumber":"7",
    "addr:postcode":"07014",
    "addr:street":"Carrer De Bartomeu Rossello",
    "iso:country":"ES",
    "sg:address":"Carrer de Bartomeu Rossello, 7",
    "sg:city":"Palma",
    "sg:orig_category":"Arquitectos",
    "sg:phone":"+34 971 45 64 48",
    "sg:postcode":"07014",
    "sg:province":"Islas Baleares",
    "wof:name":"Fontenla Esquivias Jose Maria",
    "wof:placetype":"venue"
},
  "geometry": {"coordinates":[2.6317610741,39.572807312],"type":"Point"}
}