{
  "type": "Feature",
  "properties": {
    "addr:full":"Avda Galicia De, 4 Oviedo Asturias 33005",
    "addr:housenumber":"4",
    "addr:postcode":"33005",
    "addr:street":"Avda Galicia De",
    "iso:country":"ES",
    "sg:address":"Avda Galicia De, 4",
    "sg:city":"Oviedo",
    "sg:orig_category":"Peluqueros: De Se\u00d1oras",
    "sg:phone":"+34 985 24 32 49",
    "sg:postcode":"33005",
    "sg:province":"Asturias",
    "wof:name":"Ascode S.l.",
    "wof:placetype":"venue"
},
  "geometry": {"coordinates":[-5.8540635109,43.361618042],"type":"Point"}
}