{
  "type": "Feature",
  "properties": {
    "iso:country":"ES",
    "sg:address":"Calle de Parroco Carlos Fernandez, 2",
    "sg:city":"Gondomar",
    "sg:orig_category":"Panader\u00cdas, Panader\u00cdas",
    "sg:phone":"+34 986 36 00 38",
    "sg:postcode":"36380",
    "sg:province":"Pontevedra",
    "wof:name":"Alvarez Alvarez Rosa Maria",
    "wof:placetype":"venue"
},
  "geometry": {"coordinates":[-8.7596702576,42.1120223999],"type":"Point"}
}