{
  "type": "Feature",
  "properties": {
    "addr:full":"Calle de Carretera Alta, S/n Esplus Huesca 22535",
    "addr:housenumber":"s / n",
    "addr:postcode":"22535",
    "addr:street":"Calle De Carretera Alta",
    "iso:country":"ES",
    "sg:address":"Calle de Carretera Alta, S/n",
    "sg:city":"Esplus",
    "sg:orig_category":"Cajas De Ahorro",
    "sg:phone":"+34 974 43 51 46",
    "sg:postcode":"22535",
    "sg:province":"Huesca",
    "wof:name":"Caja De Ahorros Y Monte De Piedad De Zaragoza Aragon Y Rioja",
    "wof:placetype":"venue"
},
  "geometry": {"coordinates":[0.2787741125,41.8062667847],"type":"Point"}
}