{
  "type": "Feature",
  "properties": {
    "addr:full":"Ctra Sur, S/n S. Agustin-playa Ingles Las Palmas 35100",
    "addr:housenumber":"s",
    "addr:postcode":"35100",
    "addr:street":"Ctra Sur;/ N S. Agustin-Playa",
    "iso:country":"ES",
    "sg:address":"Ctra Sur, S/n",
    "sg:city":"S. Agustin-playa Ingles",
    "sg:orig_category":"Cerrajer\u00cda, Ferrallista",
    "sg:phone":"+34 928 76 94 65",
    "sg:postcode":"35100",
    "sg:province":"Las Palmas",
    "wof:name":"Santiago Saleh Simon",
    "wof:placetype":"venue"
},
  "geometry": {"coordinates":[-15.4397096634,28.1302204132],"type":"Point"}
}