{
  "type": "Feature",
  "properties": {
    "iso:country":"ES",
    "sg:address":"Rua Ramiranes, 20",
    "sg:city":"Porri\u00f1o",
    "sg:orig_category":"Carnicer\u00cdas, Carnicer\u00cdas",
    "sg:phone":"+34 986 33 00 60",
    "sg:postcode":"36400",
    "sg:province":"Pontevedra",
    "wof:name":"Ben Ledo Alejo",
    "wof:placetype":"venue"
},
  "geometry": {"coordinates":[-8.6208286285,42.1646385193],"type":"Point"}
}