{
  "type": "Feature",
  "properties": {
    "addr:full":"Calle de Batalla De Teruel, 36 Palmas De Gran Canaria Las Palmas 35013",
    "addr:housenumber":"36",
    "addr:postcode":"35013",
    "addr:street":"Calle De Batalla De Teruel",
    "iso:country":"ES",
    "sg:address":"Calle de Batalla De Teruel, 36",
    "sg:city":"Palmas De Gran Canaria",
    "sg:orig_category":"Inform\u00c1tica, Ofim\u00c1tica (estudios, Asesor\u00cda, Ingenier\u00cda, Formaci\u00d3n)",
    "sg:phone":"+34 928 41 26 92",
    "sg:postcode":"35013",
    "sg:province":"Las Palmas",
    "sg:website":"www.copicanarias.com",
    "wof:name":"Tdi Canarias S.l.",
    "wof:placetype":"venue"
},
  "geometry": {"coordinates":[-15.4495286942,28.0961513519],"type":"Point"}
}