{
  "type": "Feature",
  "properties": {
    "addr:full":"Urb Pa\u00d1o Cabeza-calle Primera, 18 San Bartolome Santa Cruz De Tenerife 38314",
    "addr:housenumber":"18",
    "addr:postcode":"38314",
    "addr:street":"Urb;Primera",
    "iso:country":"ES",
    "sg:address":"Urb Pa\u00d1o Cabeza-calle Primera, 18",
    "sg:city":"San Bartolome",
    "sg:orig_category":"Industria Qu\u00cdmica",
    "sg:phone":"+34 922 33 46 66",
    "sg:postcode":"38314",
    "sg:province":"Santa Cruz De Tenerife",
    "wof:name":"Canarias Agua Limpia S.l.",
    "wof:placetype":"venue"
},
  "geometry": {"coordinates":[-16.5165729523,28.4114284515],"type":"Point"}
}