{
  "type": "Feature",
  "properties": {
    "addr:full":"Ctra Nacional V, Km. 0344,5 Merida Badajoz 06800",
    "addr:postcode":"06800",
    "addr:street":"Ctra Nacional V Km. 0344,5",
    "iso:country":"ES",
    "sg:address":"Ctra Nacional V, Km. 0344,5",
    "sg:city":"Merida",
    "sg:orig_category":"Juegos Y Juguetes (al Por Menor)",
    "sg:phone":"+34 924 37 12 84",
    "sg:postcode":"06800",
    "sg:province":"Badajoz",
    "wof:name":"Hermanas Casado Sarti S.l.",
    "wof:placetype":"venue"
},
  "geometry": {"coordinates":[-6.255551815,38.9500350952],"type":"Point"}
}