{
  "type": "Feature",
  "properties": {
    "iso:country":"ES",
    "sg:address":"Carrer de Biscaia, 356",
    "sg:city":"Barcelona",
    "sg:orig_category":"Comercio De Piezas De Recambio Y De Accesorios De Veh\u00cdculos, Veh\u00cdculos Industriales",
    "sg:phone":"+34 933 51 93 50",
    "sg:postcode":"08027",
    "sg:province":"Barcelona",
    "wof:name":"Exserauto S.l.",
    "wof:placetype":"venue"
},
  "geometry": {"coordinates":[2.1888859272,41.4157104492],"type":"Point"}
}