{
  "type": "Feature",
  "properties": {
    "addr:full":"Calle de Mocan, 2 Almatriche Bajo Las Palmas 35018",
    "addr:housenumber":"2",
    "addr:postcode":"35018",
    "addr:street":"Calle De Mocan;Las",
    "iso:country":"ES",
    "sg:address":"Calle de Mocan, 2",
    "sg:city":"Almatriche Bajo",
    "sg:orig_category":"Enfermeras: Consultas, Atenci\u00d3n A Domicilio",
    "sg:phone":"+34 928 43 96 88",
    "sg:postcode":"35018",
    "sg:province":"Las Palmas",
    "wof:name":"Santana Cardenes Desideria",
    "wof:placetype":"venue"
},
  "geometry": {"coordinates":[-15.4784650803,28.0919818878],"type":"Point"}
}