{
  "type": "Feature",
  "properties": {
    "iso:country":"ES",
    "sg:address":"Avda San Andres, 9",
    "sg:city":"Le\u00f3n",
    "sg:orig_category":"Farmacias",
    "sg:phone":"+34 987 22 08 15",
    "sg:postcode":"24009",
    "sg:province":"Le\u00f3n",
    "wof:name":"Garcia Calvo Antonio",
    "wof:placetype":"venue"
},
  "geometry": {"coordinates":[-5.5896925926,42.6018981934],"type":"Point"}
}