{
  "type": "Feature",
  "properties": {
    "iso:country":"ES",
    "sg:address":"Atxubiaga Kalea, 5",
    "sg:city":"Azpeitia",
    "sg:orig_category":"Electricidad: Instaladores",
    "sg:phone":"+34 943 15 05 77",
    "sg:postcode":"20730",
    "sg:province":"Guip\u00f9zcoa",
    "wof:name":"Aramburu Corta Jose Maria",
    "wof:placetype":"venue"
},
  "geometry": {"coordinates":[-2.2585637569,43.1767921448],"type":"Point"}
}