{
  "type": "Feature",
  "properties": {
    "iso:country":"ES",
    "sg:address":"Playa Salero, S/n",
    "sg:city":"Frias",
    "sg:orig_category":"Zonas De Acampada, Aparcamiento Para Caravanas",
    "sg:phone":"+34 947 35 71 98",
    "sg:postcode":"09211",
    "sg:province":"Burgos",
    "wof:name":"Camping De Frias",
    "wof:placetype":"venue"
},
  "geometry": {"coordinates":[-3.2702929974,42.7375183105],"type":"Point"}
}