{
  "type": "Feature",
  "properties": {
    "addr:full":"Calle de Doce De Octubre, 9 Valladolid Valladolid 47005",
    "addr:housenumber":"9",
    "addr:postcode":"47005",
    "addr:street":"Calle De Doce De Octubre",
    "iso:country":"ES",
    "sg:address":"Calle de Doce De Octubre, 9",
    "sg:city":"Valladolid",
    "sg:orig_category":"Molduras, Junquillos, Listones Y Molduras Perforadas",
    "sg:phone":"+34 983 30 99 86",
    "sg:postcode":"47005",
    "sg:province":"Valladolid",
    "wof:name":"Martinez Perez Luis Manuel",
    "wof:placetype":"venue"
},
  "geometry": {"coordinates":[-4.7099752426,41.6555633545],"type":"Point"}
}