{
  "type": "Feature",
  "properties": {
    "addr:full":"Plaz Mayoral, 14 Motril Granada 18600",
    "addr:housenumber":"14",
    "addr:postcode":"18600",
    "addr:street":"Mayoral",
    "iso:country":"ES",
    "sg:address":"Plaz Mayoral, 14",
    "sg:city":"Motril",
    "sg:orig_category":"Molduras, Junquillos, Listones Y Molduras Perforadas",
    "sg:phone":"+34 958 60 07 95",
    "sg:postcode":"18600",
    "sg:province":"Granada",
    "wof:name":"Castro Espinosa Jose",
    "wof:placetype":"venue"
},
  "geometry": {"coordinates":[-3.5152790546,36.7456130981],"type":"Point"}
}