{
  "type": "Feature",
  "properties": {
    "iso:country":"ES",
    "sg:address":"Carrer de Santa Teresa, 30",
    "sg:city":"Mataro",
    "sg:orig_category":"Transporte En General",
    "sg:phone":"+34 937 96 25 69",
    "sg:postcode":"08302",
    "sg:province":"Barcelona",
    "wof:name":"Lorenzo Noguera Judith",
    "wof:placetype":"venue"
},
  "geometry": {"coordinates":[2.4436910152,41.5380363464],"type":"Point"}
}