{
  "type": "Feature",
  "properties": {
    "iso:country":"ES",
    "sg:address":"Calle de Sabino Arana, 5",
    "sg:city":"Ugao-miraballes",
    "sg:orig_category":"Institutos De Belleza",
    "sg:phone":"+34 946 48 05 73",
    "sg:postcode":"48490",
    "sg:province":"Vizcaya",
    "wof:name":"Baltanas Leiva Carmen",
    "wof:placetype":"venue"
},
  "geometry": {"coordinates":[-2.9049639702,43.1779060364],"type":"Point"}
}