{
  "type": "Feature",
  "properties": {
    "addr:full":"Avda Severo Ochoa, 24 Marbella M\u00e1laga 29600",
    "addr:housenumber":"24",
    "addr:postcode":"29600",
    "addr:street":"Avda Severo Ochoa;Ma\u0301Laga",
    "iso:country":"ES",
    "sg:address":"Avda Severo Ochoa, 24",
    "sg:city":"Marbella",
    "sg:orig_category":"M\u00c9dicos: Anestesiolog\u00cda Y Reanimaci\u00d3n Quir\u00dargica",
    "sg:phone":"+34 952 82 92 74",
    "sg:postcode":"29600",
    "sg:province":"M\u00e1laga",
    "wof:name":"Pe\u00f1agaricano Vazquez Daniel",
    "wof:placetype":"venue"
},
  "geometry": {"coordinates":[-4.8735837936,36.5092658997],"type":"Point"}
}