{
  "type": "Feature",
  "properties": {
    "addr:full":"Av Golf, 8 Santa Pon\u00c7a Islas Baleares 07180",
    "addr:housenumber":"8",
    "addr:postcode":"07180",
    "addr:street":"Golf",
    "iso:country":"ES",
    "sg:address":"Av Golf, 8",
    "sg:city":"Santa Pon\u00c7a",
    "sg:orig_category":"Agencias Y Agentes Comerciales, Representantes",
    "sg:phone":"+34 971 69 29 07",
    "sg:postcode":"07180",
    "sg:province":"Islas Baleares",
    "wof:name":"Industrial Consejeros Mallorca S.l.",
    "wof:placetype":"venue"
},
  "geometry": {"coordinates":[2.4985899925,39.5253143311],"type":"Point"}
}