{
  "type": "Feature",
  "properties": {
    "addr:full":"Calle de Andres Mellado, 31 Madrid Madrid 28015",
    "addr:housenumber":"31",
    "addr:postcode":"madrid;28015",
    "addr:street":"Calle De Andres Mellado",
    "iso:country":"ES",
    "sg:address":"Calle de Andres Mellado, 31",
    "sg:city":"Madrid",
    "sg:orig_category":"Fabricaci\u00d3n, Distribuci\u00d3n De Discos, V\u00cddeodiscos Y Musicassettes",
    "sg:phone":"+34 915 43 17 57",
    "sg:postcode":"28015",
    "sg:province":"Madrid",
    "wof:name":"Martin Mariscal,manuel",
    "wof:placetype":"venue"
},
  "geometry": {"coordinates":[-3.7144734859,40.4335403442],"type":"Point"}
}