{
  "type": "Feature",
  "properties": {
    "iso:country":"ES",
    "sg:address":"Rbla Joaquim Vayreda, 43",
    "sg:city":"Gava",
    "sg:orig_category":"Servicios Gsm",
    "sg:phone":"+34 936 33 31 09",
    "sg:postcode":"08850",
    "sg:province":"Barcelona",
    "wof:name":"Sercomtel Comunicaciones S.%.",
    "wof:placetype":"venue"
},
  "geometry": {"coordinates":[2.0081150532,41.3048057556],"type":"Point"}
}