{
  "type": "Feature",
  "properties": {
    "addr:full":"Cmno San Roque, 4 Abalos La Rioja 26339",
    "addr:housenumber":"4",
    "addr:postcode":"26339",
    "addr:street":"Cmno San Roque;Abalos;Rioja",
    "iso:country":"ES",
    "sg:address":"Cmno San Roque, 4",
    "sg:city":"Abalos",
    "sg:orig_category":"Productores Recolectores, Venta Directa De Vinos",
    "sg:phone":"+34 941 33 43 92",
    "sg:postcode":"26339",
    "sg:province":"La Rioja",
    "wof:name":"Bodegas Abeica S.l.",
    "wof:placetype":"venue"
},
  "geometry": {"coordinates":[-2.7115590572,42.5706443787],"type":"Point"}
}