{
  "type": "Feature",
  "properties": {
    "iso:country":"ES",
    "sg:address":"Calle de San Sebastian, 2",
    "sg:city":"Huetor-tajar",
    "sg:orig_category":"Muebles, Minoristas",
    "sg:phone":"+34 958 33 25 59",
    "sg:postcode":"18360",
    "sg:province":"Granada",
    "wof:name":"Decomobel H.t.decoracion Integral S.l.l.",
    "wof:placetype":"venue"
},
  "geometry": {"coordinates":[-4.0460810661,37.1945953369],"type":"Point"}
}