{
  "type": "Feature",
  "properties": {
    "iso:country":"ES",
    "sg:address":"Av Mar De La, 31",
    "sg:city":"Bellreguard",
    "sg:orig_category":"Fabricaci\u00d3n De Productos L\u00c1cteos Y Derivados",
    "sg:phone":"+34 962 81 64 88",
    "sg:postcode":"46713",
    "sg:province":"Valencia",
    "wof:name":"Representaciones Monduber Sl",
    "wof:placetype":"venue"
},
  "geometry": {"coordinates":[-0.1629119962,38.9464607239],"type":"Point"}
}