{
  "type": "Feature",
  "properties": {
    "iso:country":"ES",
    "sg:address":"Calle de Mendez Nu\u00d1ez, 84",
    "sg:city":"Santa Cruz De Tenerife",
    "sg:orig_category":"Sindicatos De Trabajadores",
    "sg:phone":"+34 922 29 04 10",
    "sg:postcode":"38001",
    "sg:province":"Santa Cruz De Tenerife",
    "wof:name":"Sindicato Administracion Publica Cc.oo.",
    "wof:placetype":"venue"
},
  "geometry": {"coordinates":[-16.2515487671,28.4727573395],"type":"Point"}
}