{
  "type": "Feature",
  "properties": {
    "iso:country":"ES",
    "sg:address":"Carr Progres, 44",
    "sg:city":"Centre Urba",
    "sg:orig_category":"Cl\u00cdnicas M\u00c9dicas",
    "sg:phone":"+34 972 70 30 37",
    "sg:postcode":"17500",
    "sg:province":"Girona",
    "wof:name":"Centre De Revisions Mediques Del Ripolles S. A.",
    "wof:placetype":"venue"
},
  "geometry": {"coordinates":[2.1959049702,42.1965866089],"type":"Point"}
}