{
  "type": "Feature",
  "properties": {
    "iso:country":"ES",
    "sg:address":"Carrer de Prat, 5",
    "sg:city":"Hospitalet Llobregat",
    "sg:orig_category":"Loter\u00cda Y T\u00d3mbola",
    "sg:phone":"+34 933 36 62 10",
    "sg:postcode":"08907",
    "sg:province":"Barcelona",
    "wof:name":"Guiu Gonzalez Rosario Maria",
    "wof:placetype":"venue"
},
  "geometry": {"coordinates":[2.1065120697,41.351650238],"type":"Point"}
}