{
  "type": "Feature",
  "properties": {
    "addr:full":"Calle de Quero, 73 Madrid Madrid 28024",
    "addr:housenumber":"73",
    "addr:postcode":"madrid;28024",
    "addr:street":"Calle De Quero",
    "iso:country":"ES",
    "sg:address":"Calle de Quero, 73",
    "sg:city":"Madrid",
    "sg:orig_category":"Electrodom\u00c9sticos (al Por Menor)",
    "sg:phone":"+34 917 17 48 06",
    "sg:postcode":"28024",
    "sg:province":"Madrid",
    "wof:name":"Jimenez Garcia Jose Luis",
    "wof:placetype":"venue"
},
  "geometry": {"coordinates":[-3.7611589432,40.3894271851],"type":"Point"}
}