{
  "type": "Feature",
  "properties": {
    "addr:full":"Carrer de Garrotxa, 27 Urbanitzacio El Pinar Tarragona 43206",
    "addr:housenumber":"27",
    "addr:postcode":"43206",
    "addr:street":"Carrer De Garrotxa;Urbanitzacio",
    "iso:country":"ES",
    "sg:address":"Carrer de Garrotxa, 27",
    "sg:city":"Urbanitzacio El Pinar",
    "sg:orig_category":"Inmobiliaria (agencias)",
    "sg:phone":"+34 977 33 25 00",
    "sg:postcode":"43206",
    "sg:province":"Tarragona",
    "wof:name":"Solgan 2000 S.l.",
    "wof:placetype":"venue"
},
  "geometry": {"coordinates":[1.1086339951,41.17370224],"type":"Point"}
}