{
  "type": "Feature",
  "properties": {
    "iso:country":"ES",
    "sg:address":"Calle de Fomento, 1",
    "sg:city":"Cangas",
    "sg:orig_category":"M\u00c9dicos: Psicopedagogos",
    "sg:phone":"+34 986 30 55 32",
    "sg:postcode":"36940",
    "sg:province":"Pontevedra",
    "wof:name":"Pi\u00f1eiro Vilari\u00f1o Julia",
    "wof:placetype":"venue"
},
  "geometry": {"coordinates":[-8.7860126495,42.2599220276],"type":"Point"}
}