{
  "type": "Feature",
  "properties": {
    "addr:full":"Calle de Emilia Pardo Bazan, 7 Coru\u00d1a La Coru\u00f1a 15005",
    "addr:housenumber":"7",
    "addr:postcode":"15005",
    "addr:street":"Calle De Emilia Pardo Bazan;La Corun\u0303A",
    "iso:country":"ES",
    "sg:address":"Calle de Emilia Pardo Bazan, 7",
    "sg:city":"Coru\u00d1a",
    "sg:orig_category":"Abogados",
    "sg:phone":"+34 981 12 21 27",
    "sg:postcode":"15005",
    "sg:province":"La Coru\u00f1a",
    "wof:name":"Prieto Riera Militza Josefina",
    "wof:placetype":"venue"
},
  "geometry": {"coordinates":[-8.4069108963,43.363609314],"type":"Point"}
}