{
  "type": "Feature",
  "properties": {
    "iso:country":"ES",
    "sg:address":"Rua Folicheiro, 20",
    "sg:city":"Melide",
    "sg:orig_category":"Material Y Suministros Para Veterinarios",
    "sg:phone":"+34 981 50 56 52",
    "sg:postcode":"15800",
    "sg:province":"La Coru\u00f1a",
    "wof:name":"Melide Veterinaria S.l.",
    "wof:placetype":"venue"
},
  "geometry": {"coordinates":[-8.0151319504,42.9088058472],"type":"Point"}
}