{
  "type": "Feature",
  "properties": {
    "iso:country":"ES",
    "sg:address":"Rbla Rambla, 198",
    "sg:city":"Sabadell",
    "sg:orig_category":"Reposter\u00cdas",
    "sg:phone":"+34 937 25 28 13",
    "sg:postcode":"08201",
    "sg:province":"Barcelona",
    "wof:name":"Sales Armengol S.l.",
    "wof:placetype":"venue"
},
  "geometry": {"coordinates":[2.1121940613,41.5397262573],"type":"Point"}
}