{
  "type": "Feature",
  "properties": {
    "addr:full":"Pase Romeral (del), 17 Puente-genil C\u00f3rdoba 14500",
    "addr:postcode":"14500",
    "addr:street":"Co\u0301Rdoba",
    "iso:country":"ES",
    "sg:address":"Pase Romeral (del), 17",
    "sg:city":"Puente-genil",
    "sg:orig_category":"Bancos",
    "sg:phone":"+34 957 60 92 95",
    "sg:postcode":"14500",
    "sg:province":"C\u00f3rdoba",
    "wof:name":"Banco Bilbao Vizcaya Argentaria S.a.",
    "wof:placetype":"venue"
},
  "geometry": {"coordinates":[-4.7779579163,37.3909187317],"type":"Point"}
}