{
  "type": "Feature",
  "properties": {
    "addr:full":"Calle de Afueras A Valverde, 18 Madrid Madrid 28034",
    "addr:housenumber":"18",
    "addr:postcode":"madrid;28034",
    "addr:street":"Calle De Afueras A Valverde",
    "iso:country":"ES",
    "sg:address":"Calle de Afueras A Valverde, 18",
    "sg:city":"Madrid",
    "sg:orig_category":"Art\u00cdculos De Regalo (al Por Menor)",
    "sg:phone":"+34 917 34 79 29",
    "sg:postcode":"28034",
    "sg:province":"Madrid",
    "wof:name":"Parrilla Gomez Maria Jose",
    "wof:placetype":"venue"
},
  "geometry": {"coordinates":[-3.6893696785,40.4978561401],"type":"Point"}
}