{
  "type": "Feature",
  "properties": {
    "iso:country":"ES",
    "sg:address":"Carrer de Menorca, 32",
    "sg:city":"Barcelona",
    "sg:orig_category":"Empresas De Carpinter\u00cda Met\u00c1lica",
    "sg:phone":"+34 933 07 72 93",
    "sg:postcode":"08020",
    "sg:province":"Barcelona",
    "wof:name":"Llano Ortiz Francisco",
    "wof:placetype":"venue"
},
  "geometry": {"coordinates":[2.195194006,41.4181556702],"type":"Point"}
}