{
  "type": "Feature",
  "properties": {
    "iso:country":"ES",
    "sg:address":"Carrer de Cadaques, 14",
    "sg:city":"Prat Llobregat",
    "sg:orig_category":"Alimentaci\u00d3n General (al Por Menor)",
    "sg:phone":"+34 933 70 53 01",
    "sg:postcode":"08820",
    "sg:province":"Barcelona",
    "wof:name":"Illescas Lorenzo Diego",
    "wof:placetype":"venue"
},
  "geometry": {"coordinates":[2.1001143456,41.3247489929],"type":"Point"}
}