{
  "type": "Feature",
  "properties": {
    "addr:full":"Carrer de Solsona, 20 Terrassa Barcelona 08227",
    "addr:housenumber":"20",
    "addr:postcode":"08227",
    "addr:street":"Carrer De Solsona",
    "iso:country":"ES",
    "sg:address":"Carrer de Solsona, 20",
    "sg:city":"Terrassa",
    "sg:orig_category":"Droguer\u00cdas (al Por Menor)",
    "sg:phone":"+34 937 31 11 74",
    "sg:postcode":"08227",
    "sg:province":"Barcelona",
    "wof:name":"Benitez Pujol Josep Maria",
    "wof:placetype":"venue"
},
  "geometry": {"coordinates":[2.0338869095,41.5763015747],"type":"Point"}
}