{
  "type": "Feature",
  "properties": {
    "iso:country":"ES",
    "sg:address":"Rond Alta De Benyamina, 10",
    "sg:city":"Torremolinos",
    "sg:orig_category":"Supermercados Y Hipermercados",
    "sg:phone":"+34 952 38 93 97",
    "sg:postcode":"29620",
    "sg:province":"M\u00e1laga",
    "wof:name":"Torres Gonzalez Eugenio",
    "wof:placetype":"venue"
},
  "geometry": {"coordinates":[-4.4971671104,36.6328697205],"type":"Point"}
}