{
  "type": "Feature",
  "properties": {
    "iso:country":"ES",
    "sg:address":"Calle de Fernando Galvan, 10",
    "sg:city":"Palmas De Gran Canaria",
    "sg:orig_category":"Abogados",
    "sg:phone":"+34 928 33 41 53",
    "sg:postcode":"35001",
    "sg:province":"Las Palmas",
    "wof:name":"Ramos Perez Esteban",
    "wof:placetype":"venue"
},
  "geometry": {"coordinates":[-15.415307045,28.0977478027],"type":"Point"}
}