{
  "type": "Feature",
  "properties": {
    "addr:full":"Calle de Enriquez, 1 Mayorga Valladolid 47680",
    "addr:housenumber":"1",
    "addr:postcode":"47680",
    "addr:street":"Calle De Enriquez",
    "iso:country":"ES",
    "sg:address":"Calle de Enriquez, 1",
    "sg:city":"Mayorga",
    "sg:orig_category":"Carnicer\u00cdas, Carnicer\u00cdas",
    "sg:phone":"+34 983 75 14 47",
    "sg:postcode":"47680",
    "sg:province":"Valladolid",
    "wof:name":"Redondo Martinez Jose",
    "wof:placetype":"venue"
},
  "geometry": {"coordinates":[-5.2600860596,42.1663475037],"type":"Point"}
}