{
  "type": "Feature",
  "properties": {
    "addr:full":"Calle de Ronda Martires, 23 Bola\u00e7os De Calatrava Ciudad Real 13260",
    "addr:housenumber":"23",
    "addr:postcode":"13260",
    "addr:street":"Calle De Ronda Martires",
    "iso:country":"ES",
    "sg:address":"Calle de Ronda Martires, 23",
    "sg:city":"Bola\u00e7os De Calatrava",
    "sg:orig_category":"Alimentaci\u00d3n General (al Por Menor)",
    "sg:phone":"+34 926 87 15 57",
    "sg:postcode":"13260",
    "sg:province":"Ciudad Real",
    "wof:name":"Alimentacion Nuestra Se\u00f1ora Del Monte S.l.",
    "wof:placetype":"venue"
},
  "geometry": {"coordinates":[-3.6683027744,38.904964447],"type":"Point"}
}