{
  "type": "Feature",
  "properties": {
    "addr:full":"Calle de Manilva, S/n San Pedro Alcantara M\u00e1laga 29670",
    "addr:housenumber":"s / n",
    "addr:postcode":"29670",
    "addr:street":"Calle De Manilva",
    "iso:country":"ES",
    "sg:address":"Calle de Manilva, S/n",
    "sg:city":"San Pedro Alcantara",
    "sg:orig_category":"M\u00c1rmoles, Granitos Y Piedras Naturales",
    "sg:phone":"+34 952 78 65 23",
    "sg:postcode":"29670",
    "sg:province":"M\u00e1laga",
    "wof:name":"Nu\u00f1ez Benitez Juan",
    "wof:placetype":"venue"
},
  "geometry": {"coordinates":[-4.9902391434,36.4866333008],"type":"Point"}
}