{
  "type": "Feature",
  "properties": {
    "iso:country":"ES",
    "sg:address":"Calle de Leopoldo Romeo, 11",
    "sg:city":"Zaragoza",
    "sg:orig_category":"Caf\u00c9s, Bares, Cervecer\u00cdas",
    "sg:phone":"+34 976 49 12 19",
    "sg:postcode":"50002",
    "sg:province":"Zaragoza",
    "wof:name":"Garces Martin Jose Ignacio",
    "wof:placetype":"venue"
},
  "geometry": {"coordinates":[-0.8634679914,41.6466331482],"type":"Point"}
}