{
  "type": "Feature",
  "properties": {
    "addr:full":"Calle de Zaragoza, 12 Arganda Madrid 28500",
    "addr:housenumber":"12",
    "addr:postcode":"28500",
    "addr:street":"Calle De Zaragoza",
    "iso:country":"ES",
    "sg:address":"Calle de Zaragoza, 12",
    "sg:city":"Arganda",
    "sg:orig_category":"Fabricaci\u00d3n De Sobres, Bolsas Y Fundas",
    "sg:phone":"+34 918 71 09 50",
    "sg:postcode":"28500",
    "sg:province":"Madrid",
    "sg:website":"www.sobreindustrial.com",
    "wof:name":"Sobre Industrial S.l.",
    "wof:placetype":"venue"
},
  "geometry": {"coordinates":[-3.4552609921,40.3073692322],"type":"Point"}
}