{
  "type": "Feature",
  "properties": {
    "iso:country":"ES",
    "sg:address":"Carrer de Ramon Moncada, 4",
    "sg:city":"Santa Pon\u00c7a",
    "sg:orig_category":"Fabricaci\u00d3n De Sobres, Bolsas Y Fundas",
    "sg:phone":"+34 971 69 38 93",
    "sg:postcode":"07180",
    "sg:province":"Islas Baleares",
    "wof:name":"Creaciones Camal S.l.",
    "wof:placetype":"venue"
},
  "geometry": {"coordinates":[2.4985899925,39.5253143311],"type":"Point"}
}