{
  "type": "Feature",
  "properties": {
    "addr:full":"G.v. Corts Catalanes, 679 Barcelona Barcelona 08013",
    "addr:housenumber":"679",
    "addr:postcode":"08013",
    "addr:street":"Catalanes",
    "iso:country":"ES",
    "sg:address":"G.v. Corts Catalanes, 679",
    "sg:city":"Barcelona",
    "sg:orig_category":"Droguer\u00cdas (al Por Menor)",
    "sg:phone":"+34 932 31 40 12",
    "sg:postcode":"08013",
    "sg:province":"Barcelona",
    "wof:name":"Drogueria Camps S. A.",
    "wof:placetype":"venue"
},
  "geometry": {"coordinates":[2.1770200729,41.3964424133],"type":"Point"}
}