{
  "type": "Feature",
  "properties": {
    "iso:country":"ES",
    "sg:address":"Manuel Rodriguez Manolete, 2",
    "sg:city":"Montilla",
    "sg:orig_category":"Asesor\u00cda De Formaci\u00d3n Y Gesti\u00d3n De Personal",
    "sg:phone":"+34 957 65 20 63",
    "sg:postcode":"14550",
    "sg:province":"C\u00f3rdoba",
    "wof:name":"Gomez Cardenas Rosa Maria",
    "wof:placetype":"venue"
},
  "geometry": {"coordinates":[-4.6404590607,37.58177948],"type":"Point"}
}