{
  "type": "Feature",
  "properties": {
    "addr:full":"Calle de Juan Carlos I, 10 Casar Guadalajara 19170",
    "addr:housenumber":"10",
    "addr:postcode":"19170",
    "addr:street":"Calle De Juan Carlos I",
    "iso:country":"ES",
    "sg:address":"Calle de Juan Carlos I, 10",
    "sg:city":"Casar",
    "sg:orig_category":"Agentes Generales De Seguros",
    "sg:phone":"+34 949 33 58 66",
    "sg:postcode":"19170",
    "sg:province":"Guadalajara",
    "wof:name":"Diaz Anton Francisco Javier",
    "wof:placetype":"venue"
},
  "geometry": {"coordinates":[-3.4276928902,40.7039260864],"type":"Point"}
}