{
  "type": "Feature",
  "properties": {
    "addr:full":"Placa, 1 Vilademuls Girona 17468",
    "addr:housenumber":"1",
    "addr:postcode":"17468",
    "addr:street":"Placa",
    "iso:country":"ES",
    "sg:address":"Placa, 1",
    "sg:city":"Vilademuls",
    "sg:orig_category":"Iglesia Cat\u00d3lica",
    "sg:phone":"+34 972 56 02 25",
    "sg:postcode":"17468",
    "sg:province":"Girona",
    "wof:name":"Bisbat De Girona",
    "wof:placetype":"venue"
},
  "geometry": {"coordinates":[2.8884160519,42.1389427185],"type":"Point"}
}