{
  "type": "Feature",
  "properties": {
    "addr:full":"Crt Roda-tarazona, S/n Fuensanta Albacete 02637",
    "addr:housenumber":"/ n",
    "addr:postcode":"02637",
    "addr:street":"Roda-Tarazona S;Fuensanta",
    "iso:country":"ES",
    "sg:address":"Crt Roda-tarazona, S/n",
    "sg:city":"Fuensanta",
    "sg:orig_category":"Explotaci\u00d3n De Canteras",
    "sg:phone":"+34 967 57 00 20",
    "sg:postcode":"02637",
    "sg:province":"Albacete",
    "wof:name":"Aridos Perez Simarro S.l.",
    "wof:placetype":"venue"
},
  "geometry": {"coordinates":[-2.067892313,39.3013496399],"type":"Point"}
}