{
  "type": "Feature",
  "properties": {
    "iso:country":"ES",
    "sg:address":"Calle de Miravalles, 6",
    "sg:city":"Vitoria-gasteiz",
    "sg:orig_category":"Droguer\u00cdas (al Por Mayor)",
    "sg:phone":"+34 945 27 33 55",
    "sg:postcode":"01013",
    "sg:province":"\u00c1lava",
    "wof:name":"Eguren Basterra Ramon",
    "wof:placetype":"venue"
},
  "geometry": {"coordinates":[-2.641988039,42.8678703308],"type":"Point"}
}