{
  "type": "Feature",
  "properties": {
    "iso:country":"ES",
    "sg:address":"Plg. Industrial De Manzanares, 55",
    "sg:city":"Manzanares",
    "sg:orig_category":"Mec\u00c1nico Del Autom\u00d3vil",
    "sg:phone":"+34 926 64 76 40",
    "sg:postcode":"13200",
    "sg:province":"Ciudad Real",
    "sg:website":"www.tmarbu.com",
    "wof:name":"Talleres Marbu S.l.",
    "wof:placetype":"venue"
},
  "geometry": {"coordinates":[-3.373128891,38.994140625],"type":"Point"}
}