{
  "type": "Feature",
  "properties": {
    "iso:country":"ES",
    "sg:address":"Avda Reina Victoria, 5",
    "sg:city":"Madrid",
    "sg:orig_category":"Empresarios",
    "sg:phone":"+34 915 33 56 26",
    "sg:postcode":"28003",
    "sg:province":"Madrid",
    "wof:name":"Muserma S.l.",
    "wof:placetype":"venue"
},
  "geometry": {"coordinates":[-3.7054169178,40.446685791],"type":"Point"}
}