{
  "type": "Feature",
  "properties": {
    "iso:country":"ES",
    "sg:address":"Calle de Los Mesejo, 5",
    "sg:city":"Madrid",
    "sg:orig_category":"Agencias De Aduana",
    "sg:phone":"+34 914 33 51 01",
    "sg:postcode":"28007",
    "sg:province":"Madrid",
    "wof:name":"Hilario Lozano Carlos Marino",
    "wof:placetype":"venue"
},
  "geometry": {"coordinates":[-3.6702570915,40.3991966248],"type":"Point"}
}