{
  "type": "Feature",
  "properties": {
    "iso:country":"ES",
    "sg:address":"Calle de Jimenez Baeza, 6",
    "sg:city":"San Pedro",
    "sg:orig_category":"Abogados",
    "sg:phone":"+34 968 22 32 19",
    "sg:postcode":"30004",
    "sg:province":"Murcia",
    "wof:name":"Palazon Tomas Jose",
    "wof:placetype":"venue"
},
  "geometry": {"coordinates":[-1.1335690022,37.9848403931],"type":"Point"}
}