{
  "type": "Feature",
  "properties": {
    "addr:full":"Avda Isabel Ii De, 5 Donostia-san Sebastian Guip\u00f9zcoa 20011",
    "addr:housenumber":"5",
    "addr:postcode":"20011",
    "addr:street":"Avda Isabel Ii De",
    "iso:country":"ES",
    "sg:address":"Avda Isabel Ii De, 5",
    "sg:city":"Donostia-san Sebastian",
    "sg:orig_category":"Mercer\u00cda, Lencer\u00cda (al Por Menor)",
    "sg:phone":"+34 943 47 46 57",
    "sg:postcode":"20011",
    "sg:province":"Guip\u00f9zcoa",
    "wof:name":"Labores Bohemia, S.l.",
    "wof:placetype":"venue"
},
  "geometry": {"coordinates":[-1.9752639532,43.3046188354],"type":"Point"}
}