{
  "type": "Feature",
  "properties": {
    "iso:country":"ES",
    "sg:address":"Av Comas I Sola, 30",
    "sg:city":"Rubi",
    "sg:orig_category":"Plomeros",
    "sg:phone":"+34 935 86 24 12",
    "sg:postcode":"08191",
    "sg:province":"Barcelona",
    "wof:name":"Les Masies Del Valles S.c.p.",
    "wof:placetype":"venue"
},
  "geometry": {"coordinates":[2.0418610573,41.4898223877],"type":"Point"}
}