{
  "type": "Feature",
  "properties": {
    "iso:country":"ES",
    "sg:address":"Trav De Gracia, 86",
    "sg:city":"Barcelona",
    "sg:orig_category":"Abogados",
    "sg:phone":"+34 932 17 05 26",
    "sg:postcode":"08006",
    "sg:province":"Barcelona",
    "wof:name":"Torres Espa\u00f1ola Julian",
    "wof:placetype":"venue"
},
  "geometry": {"coordinates":[2.1523768902,41.397731781],"type":"Point"}
}