{
  "type": "Feature",
  "properties": {
    "iso:country":"ES",
    "sg:address":"Calle de Londres, S/n",
    "sg:city":"Alacant",
    "sg:orig_category":"Alimentaci\u00d3n General (al Por Menor)",
    "sg:phone":"+34 965 16 00 54",
    "sg:postcode":"03540",
    "sg:province":"Alicante",
    "wof:name":"Garcia Martinez Ana Maria",
    "wof:placetype":"venue"
},
  "geometry": {"coordinates":[-0.4111840129,38.369594574],"type":"Point"}
}