{
  "type": "Feature",
  "properties": {
    "iso:country":"ES",
    "sg:address":"Avda Geranios (de Los), 26",
    "sg:city":"Maneje",
    "sg:orig_category":"Promotores Constructores",
    "sg:phone":"+34 928 81 56 40",
    "sg:postcode":"35500",
    "sg:province":"Las Palmas",
    "wof:name":"Guillen Morales Angel",
    "wof:placetype":"venue"
},
  "geometry": {"coordinates":[-13.5490036011,28.9582099915],"type":"Point"}
}