{
  "type": "Feature",
  "properties": {
    "iso:country":"ES",
    "sg:address":"Calle de Doctores Castroviejo, 30",
    "sg:city":"Logro\u00f1o",
    "sg:orig_category":"Droguer\u00cdas (al Por Menor)",
    "sg:phone":"+34 941 25 46 24",
    "sg:postcode":"26003",
    "sg:province":"La Rioja",
    "wof:name":"Droguerias Gonsi S.l.",
    "wof:placetype":"venue"
},
  "geometry": {"coordinates":[-2.4413609505,42.4623908997],"type":"Point"}
}