{
  "type": "Feature",
  "properties": {
    "iso:country":"ES",
    "sg:address":"Calle de San Ildefonso, 20",
    "sg:city":"Iniesta",
    "sg:orig_category":"Empresas De Carpinter\u00cda De Madera",
    "sg:phone":"+34 967 49 08 88",
    "sg:postcode":"16235",
    "sg:province":"Cuenca",
    "wof:name":"Aroca Soriano Tomas",
    "wof:placetype":"venue"
},
  "geometry": {"coordinates":[-1.7513421774,39.4422264099],"type":"Point"}
}