{
  "type": "Feature",
  "properties": {
    "addr:full":"Republica Argentina, 19 Sada La Coru\u00f1a 15160",
    "addr:housenumber":"19",
    "addr:postcode":"15160",
    "addr:street":"Argentina;La",
    "iso:country":"ES",
    "sg:address":"Republica Argentina, 19",
    "sg:city":"Sada",
    "sg:orig_category":"Laboratorios Y Trabajos De Fotograf\u00cda, V\u00cddeo Y Cine",
    "sg:phone":"+34 981 62 38 57",
    "sg:postcode":"15160",
    "sg:province":"La Coru\u00f1a",
    "wof:name":"Locos Por La Red S.l.",
    "wof:placetype":"venue"
},
  "geometry": {"coordinates":[-8.2521877289,43.3486404419],"type":"Point"}
}