{
  "type": "Feature",
  "properties": {
    "addr:full":"Carrer de Esglesia, 25 Hospitalet Llobregat Barcelona 08901",
    "addr:housenumber":"25",
    "addr:postcode":"08901",
    "addr:street":"Carrer De Esglesia",
    "iso:country":"ES",
    "sg:address":"Carrer de Esglesia, 25",
    "sg:city":"Hospitalet Llobregat",
    "sg:orig_category":"Deportes Y Ocio: Art\u00cdculos Y Ropas (al Por Menor Y Accesorios)",
    "sg:phone":"+34 933 37 13 45",
    "sg:postcode":"08901",
    "sg:province":"Barcelona",
    "wof:name":"Salvador Campama Anton",
    "wof:placetype":"venue"
},
  "geometry": {"coordinates":[2.0989251137,41.3605995178],"type":"Point"}
}