{
  "type": "Feature",
  "properties": {
    "iso:country":"ES",
    "sg:address":"Ctra Novelda, 40",
    "sg:city":"Aspe",
    "sg:orig_category":"Goma: Productos De Uso Industrial (fabricaci\u00d3n, Al Por Mayor)",
    "sg:phone":"+34 965 49 00 94",
    "sg:postcode":"03680",
    "sg:province":"Alicante",
    "wof:name":"Triturados De Goma Cremades Pastor S.l.",
    "wof:placetype":"venue"
},
  "geometry": {"coordinates":[-0.7713569999,38.3503456116],"type":"Point"}
}