{
  "type": "Feature",
  "properties": {
    "iso:country":"ES",
    "sg:address":"Av. Marques Villanueva Del Prado, S/n",
    "sg:city":"Puerto Cruz",
    "sg:orig_category":"Bazares, Art\u00cdculos De Limpieza Y De Cocina (al Por Menor)",
    "sg:phone":"+34 922 36 85 57",
    "sg:postcode":"38400",
    "sg:province":"Santa Cruz De Tenerife",
    "wof:name":"Suajanani  Kanchand Manghram",
    "wof:placetype":"venue"
},
  "geometry": {"coordinates":[-16.5422172546,28.4132347107],"type":"Point"}
}