{
  "type": "Feature",
  "properties": {
    "addr:full":"Calle de Primero De Mayo, S/n Yecla Murcia 30510",
    "addr:housenumber":"s / n",
    "addr:postcode":"30510",
    "addr:street":"Calle De Primero;Mayo",
    "iso:country":"ES",
    "sg:address":"Calle de Primero De Mayo, S/n",
    "sg:city":"Yecla",
    "sg:orig_category":"Promotores Constructores",
    "sg:phone":"+34 968 79 61 53",
    "sg:postcode":"30510",
    "sg:province":"Murcia",
    "wof:name":"Promociones Inmobiliarias Gran Yecla S.l.",
    "wof:placetype":"venue"
},
  "geometry": {"coordinates":[-1.1092853546,38.6070175171],"type":"Point"}
}