{
  "type": "Feature",
  "properties": {
    "iso:country":"ES",
    "sg:address":"Calle de Argentina, 11",
    "sg:city":"Caceres",
    "sg:orig_category":"Cristaler\u00cdas",
    "sg:phone":"+34 927 24 71 71",
    "sg:postcode":"10001",
    "sg:province":"C\u00e1ceres",
    "wof:name":"Cristaleria Ibiza S. A.",
    "wof:placetype":"venue"
},
  "geometry": {"coordinates":[-6.3815202713,39.467502594],"type":"Point"}
}