{
  "type": "Feature",
  "properties": {
    "iso:country":"ES",
    "sg:address":"Trva Monreal, 2",
    "sg:city":"Villaviciosa Odon",
    "sg:orig_category":"Arreglo, Reparaci\u00d3n, Piezas Sueltas De Televisi\u00d3n, V\u00cddeo, Hi",
    "sg:phone":"+34 916 16 24 16",
    "sg:postcode":"28670",
    "sg:province":"Madrid",
    "wof:name":"Miguela\u00f1ez Martin Mariano Jose",
    "wof:placetype":"venue"
},
  "geometry": {"coordinates":[-3.9073560238,40.3557243347],"type":"Point"}
}