{
  "type": "Feature",
  "properties": {
    "addr:full":"Calle de Eduardo Ferreras, 5 Marchena Sevilla 41620",
    "addr:housenumber":"5",
    "addr:postcode":"41620",
    "addr:street":"Calle De Eduardo Ferreras",
    "iso:country":"ES",
    "sg:address":"Calle de Eduardo Ferreras, 5",
    "sg:city":"Marchena",
    "sg:orig_category":"Zapatos (al Por Menor)",
    "sg:phone":"+34 955 84 73 60",
    "sg:postcode":"41620",
    "sg:province":"Sevilla",
    "wof:name":"Camero Trigo Rosario",
    "wof:placetype":"venue"
},
  "geometry": {"coordinates":[-5.4155621529,37.3283958435],"type":"Point"}
}