{
  "type": "Feature",
  "properties": {
    "iso:country":"ES",
    "sg:address":"Calle de Poza De La Sal, 9",
    "sg:city":"Madrid",
    "sg:orig_category":"Maquinaria Para Industrias Diversas",
    "sg:phone":"+34 913 32 02 81",
    "sg:postcode":"28031",
    "sg:province":"Madrid",
    "wof:name":"Innovaciones Marieta S.l.",
    "wof:placetype":"venue"
},
  "geometry": {"coordinates":[-3.6042580605,40.3784980774],"type":"Point"}
}