{
  "type": "Feature",
  "properties": {
    "iso:country":"ES",
    "sg:address":"Barr Quintana (trema\u00d1es), S/n",
    "sg:city":"Gijon",
    "sg:orig_category":"Chapister\u00cda",
    "sg:phone":"+34 985 31 05 68",
    "sg:postcode":"33211",
    "sg:province":"Asturias",
    "wof:name":"Arnaldo Cuevas Manuel",
    "wof:placetype":"venue"
},
  "geometry": {"coordinates":[-5.6852426529,43.5228233337],"type":"Point"}
}