{
  "type": "Feature",
  "properties": {
    "addr:full":"Calle de Ejercito Espa\u00d1ol, S/n Candeleda \u00c1vila 05480",
    "addr:housenumber":"s / n",
    "addr:postcode":"05480",
    "addr:street":"Calle De Ejercito Espan\u0303Ol",
    "iso:country":"ES",
    "sg:address":"Calle de Ejercito Espa\u00d1ol, S/n",
    "sg:city":"Candeleda",
    "sg:orig_category":"Molduras, Junquillos, Listones Y Molduras Perforadas",
    "sg:phone":"+34 920 38 22 66",
    "sg:postcode":"05480",
    "sg:province":"\u00c1vila",
    "wof:name":"Sanchez Rodriguez Morcon M Josefa",
    "wof:placetype":"venue"
},
  "geometry": {"coordinates":[-5.2407188416,40.1568260193],"type":"Point"}
}