{
  "type": "Feature",
  "properties": {
    "addr:full":"Poli Poliviso, 3 Viso Del Alcor Sevilla 41520",
    "addr:housenumber":"3",
    "addr:postcode":"41520",
    "addr:street":"Poliviso",
    "iso:country":"ES",
    "sg:address":"Poli Poliviso, 3",
    "sg:city":"Viso Del Alcor",
    "sg:orig_category":"Agentes, Concesionarios Y Sucursales De Camiones Y Veh\u00cdculos Industriales",
    "sg:phone":"+34 955 74 20 36",
    "sg:postcode":"41520",
    "sg:province":"Sevilla",
    "wof:name":"Moreno Marquez Manuel",
    "wof:placetype":"venue"
},
  "geometry": {"coordinates":[-5.7224740982,37.3872108459],"type":"Point"}
}