{
  "type": "Feature",
  "properties": {
    "addr:full":"Carrer de Joan Puig, 3 Rubi Barcelona 08191",
    "addr:housenumber":"3",
    "addr:postcode":"08191",
    "addr:street":"Carrer De Joan Puig",
    "iso:country":"ES",
    "sg:address":"Carrer de Joan Puig, 3",
    "sg:city":"Rubi",
    "sg:orig_category":"Iglesia Cat\u00d3lica",
    "sg:phone":"+34 936 99 47 28",
    "sg:postcode":"08191",
    "sg:province":"Barcelona",
    "wof:name":"Parroquia De Santa Maria",
    "wof:placetype":"venue"
},
  "geometry": {"coordinates":[2.0327429771,41.4838867188],"type":"Point"}
}