{
  "type": "Feature",
  "properties": {
    "iso:country":"ES",
    "sg:address":"Ctra. Santanyi, S/n",
    "sg:city":"Felanitx",
    "sg:orig_category":"Controles De Edificaci\u00d3n (construcci\u00d3n, Seguridad)",
    "sg:phone":"+34 971 18 52 71",
    "sg:postcode":"07200",
    "sg:province":"Islas Baleares",
    "wof:name":"Rusticas Es Moli S.l.",
    "wof:placetype":"venue"
},
  "geometry": {"coordinates":[3.147949934,39.4647827148],"type":"Point"}
}