{
  "type": "Feature",
  "properties": {
    "iso:country":"ES",
    "sg:address":"Francisco Tomas Y Valiente, 23",
    "sg:city":"Santander",
    "sg:orig_category":"Inmobiliaria (agencias)",
    "sg:phone":"+34 942 32 46 10",
    "sg:postcode":"39011",
    "sg:province":"Cantabria",
    "wof:name":"Raimconsa S.a.",
    "wof:placetype":"venue"
},
  "geometry": {"coordinates":[-3.8427510262,43.4390296936],"type":"Point"}
}