{
  "type": "Feature",
  "properties": {
    "addr:full":"Ctra. Murcia, Km. 0340,0 Huercal-overa Almer\u00eda 04600",
    "addr:postcode":"04600",
    "addr:street":"Ctra. Murcia Km. 0340,0 Huercal-Overa Almeri\u0301A",
    "iso:country":"ES",
    "sg:address":"Ctra. Murcia, Km. 0340,0",
    "sg:city":"Huercal-overa",
    "sg:orig_category":"Molduras, Junquillos, Listones Y Molduras Perforadas",
    "sg:phone":"+34 950 47 05 83",
    "sg:postcode":"04600",
    "sg:province":"Almer\u00eda",
    "wof:name":"Parra Garcia Jose",
    "wof:placetype":"venue"
},
  "geometry": {"coordinates":[-1.7358249426,37.4396438599],"type":"Point"}
}