{
  "type": "Feature",
  "properties": {
    "addr:full":"Grta. Musica, 2 Aranjuez Madrid 28300",
    "addr:housenumber":"2",
    "addr:postcode":"28300",
    "iso:country":"ES",
    "sg:address":"Grta. Musica, 2",
    "sg:city":"Aranjuez",
    "sg:orig_category":"Inmobiliaria (agencias)",
    "sg:phone":"+34 918 91 45 63",
    "sg:postcode":"28300",
    "sg:province":"Madrid",
    "wof:name":"Promociones Inmobiliarias Aranjuez S.l.",
    "wof:placetype":"venue"
},
  "geometry": {"coordinates":[-3.6042790413,40.0360946655],"type":"Point"}
}