{
  "type": "Feature",
  "properties": {
    "addr:full":"Calle de Antonio Moreno, 3 Madrid Madrid 28025",
    "addr:housenumber":"3",
    "addr:postcode":"28025",
    "addr:street":"Calle De Antonio Moreno",
    "iso:country":"ES",
    "sg:address":"Calle de Antonio Moreno, 3",
    "sg:city":"Madrid",
    "sg:orig_category":"Frutas, Legumbres Frescas Y Tempranas (al Por Menor)",
    "sg:phone":"+34 915 25 09 17",
    "sg:postcode":"28025",
    "sg:province":"Madrid",
    "wof:name":"Diaz Novo Josefina",
    "wof:placetype":"venue"
},
  "geometry": {"coordinates":[-3.728456974,40.3844604492],"type":"Point"}
}