{
  "type": "Feature",
  "properties": {
    "iso:country":"ES",
    "sg:address":"C/ Pablo Picasso, 72",
    "sg:city":"Elche",
    "sg:orig_category":"Zapatos: Material, Suministros, Accesorios (fabricaci\u00d3n, Al Por Mayor)",
    "sg:phone":"+34 966 63 08 83",
    "sg:postcode":"03204",
    "sg:province":"Alicante",
    "wof:name":"Ramos Perez Jose Manuel",
    "wof:placetype":"venue"
},
  "geometry": {"coordinates":[-0.7040519714,38.2558441162],"type":"Point"}
}