{
  "type": "Feature",
  "properties": {
    "addr:full":"Plaz Campo Santo De Los Martires, 8 Cordoba C\u00f3rdoba 14004",
    "addr:housenumber":"8",
    "addr:postcode":"14004",
    "addr:street":"Los Martires;Co\u0301Rdoba",
    "iso:country":"ES",
    "sg:address":"Plaz Campo Santo De Los Martires, 8",
    "sg:city":"Cordoba",
    "sg:orig_category":"Bisuteros (fabricaci\u00d3n, Al Por Mayor)",
    "sg:phone":"+34 957 29 89 33",
    "sg:postcode":"14004",
    "sg:province":"C\u00f3rdoba",
    "wof:name":"Natera Hidalgo Juan Luis",
    "wof:placetype":"venue"
},
  "geometry": {"coordinates":[-4.7819590569,37.87758255],"type":"Point"}
}