{
  "type": "Feature",
  "properties": {
    "iso:country":"ES",
    "sg:address":"Av Catalunya, 43",
    "sg:city":"Anglesola",
    "sg:orig_category":"Mec\u00c1nico Del Autom\u00d3vil",
    "sg:phone":"+34 973 30 84 96",
    "sg:postcode":"25320",
    "sg:province":"Lleida",
    "wof:name":"Farre Bertran Francisco",
    "wof:placetype":"venue"
},
  "geometry": {"coordinates":[1.0830800533,41.6570396423],"type":"Point"}
}