{
  "type": "Feature",
  "properties": {
    "addr:full":"Carrer de Ortiz De La Vega, 32 S. Feliu Guixols Girona 17220",
    "addr:housenumber":"32",
    "addr:postcode":"17220",
    "addr:street":"Carrer De Ortiz De La Vega;S. Feliu Guixols",
    "iso:country":"ES",
    "sg:address":"Carrer de Ortiz De La Vega, 32",
    "sg:city":"S. Feliu Guixols",
    "sg:orig_category":"Inmobiliaria (agencias)",
    "sg:phone":"+34 972 32 18 03",
    "sg:postcode":"17220",
    "sg:province":"Girona",
    "wof:name":"Construccions Silgem S.l.",
    "wof:placetype":"venue"
},
  "geometry": {"coordinates":[3.0340559483,41.7854347229],"type":"Point"}
}