{
  "type": "Feature",
  "properties": {
    "iso:country":"ES",
    "sg:address":"Avda Andalucia, 32",
    "sg:city":"Luisiana",
    "sg:classifiers":[
        {
            "category":"Taxi",
            "type":"Transportation"
        }
    ],
    "sg:phone":"+34 955 90 73 79",
    "sg:postcode":"41430",
    "sg:province":"Sevilla",
    "wof:name":"Selfa Rodriguez Jose Manuel",
    "wof:placetype":"venue"
},
  "geometry": {"coordinates":[-5.2483911514,37.526058197],"type":"Point"}
}