{
  "type": "Feature",
  "properties": {
    "addr:full":"Calle de San Jose, 6 Guadix Granada 18500",
    "addr:housenumber":"6",
    "addr:postcode":"18500",
    "addr:street":"Calle De San Jose",
    "iso:country":"ES",
    "sg:address":"Calle de San Jose, 6",
    "sg:city":"Guadix",
    "sg:orig_category":"Renovaci\u00d3n Inmobiliaria",
    "sg:phone":"+34 958 66 17 30",
    "sg:postcode":"18500",
    "sg:province":"Granada",
    "wof:name":"Lazaro Guil Maria Angeles",
    "wof:placetype":"venue"
},
  "geometry": {"coordinates":[-3.1337919235,37.2993850708],"type":"Point"}
}