{
  "type": "Feature",
  "properties": {
    "addr:full":"Avda Condes De San Isidro, 3 Fuengirola M\u00e1laga 29640",
    "addr:housenumber":"3",
    "addr:postcode":"29640",
    "addr:street":"Avda Condes De San Isidro;Ma\u0301Laga",
    "iso:country":"ES",
    "sg:address":"Avda Condes De San Isidro, 3",
    "sg:city":"Fuengirola",
    "sg:orig_category":"M\u00c9dicos: An\u00c1lisis Cl\u00cdnicos",
    "sg:phone":"+34 952 47 48 50",
    "sg:postcode":"29640",
    "sg:province":"M\u00e1laga",
    "wof:name":"Nestares Garcia-trevijano Jose Antonio",
    "wof:placetype":"venue"
},
  "geometry": {"coordinates":[-4.6267127991,36.5329475403],"type":"Point"}
}