{
  "type": "Feature",
  "properties": {
    "addr:full":"Pase Ezequiel Gonzalez, S/n Segovia Segovia 40002",
    "addr:housenumber":"/ n",
    "addr:postcode":"40002",
    "addr:street":"Gonzalez S",
    "iso:country":"ES",
    "sg:address":"Pase Ezequiel Gonzalez, S/n",
    "sg:city":"Segovia",
    "sg:orig_category":"Art\u00cdculos De Regalo (al Por Menor)",
    "sg:phone":"+34 921 43 07 53",
    "sg:postcode":"40002",
    "sg:province":"Segovia",
    "wof:name":"Figueroa Intriago Ricardo Ivan",
    "wof:placetype":"venue"
},
  "geometry": {"coordinates":[-4.1199789047,40.9435081482],"type":"Point"}
}