{
  "type": "Feature",
  "properties": {
    "addr:full":"Carrer de L'hospital, 79 Barcelona Barcelona 08001",
    "addr:housenumber":"79",
    "addr:postcode":"08001",
    "addr:street":"Carrer De L'Hospital",
    "iso:country":"ES",
    "sg:address":"Carrer de L'hospital, 79",
    "sg:city":"Barcelona",
    "sg:orig_category":"Cueros Y Pieles (al Por Mayor)",
    "sg:phone":"+34 933 17 63 84",
    "sg:postcode":"08001",
    "sg:province":"Barcelona",
    "sg:website":"www.curtidospinos.com",
    "wof:name":"Vidal Vives Maria Del Carmen",
    "wof:placetype":"venue"
},
  "geometry": {"coordinates":[2.1702394485,41.3803977966],"type":"Point"}
}