{
  "type": "Feature",
  "properties": {
    "addr:full":"Ctra Santpedor, 47 Manresa Barcelona 08242",
    "addr:housenumber":"47",
    "addr:postcode":"08242",
    "addr:street":"Ctra Santpedor",
    "iso:country":"ES",
    "sg:address":"Ctra Santpedor, 47",
    "sg:city":"Manresa",
    "sg:orig_category":"Confecci\u00d3n De Trajes Para Se\u00d1oras",
    "sg:phone":"+34 938 73 79 37",
    "sg:postcode":"08242",
    "sg:province":"Barcelona",
    "wof:name":"Onna Costuras S.c.p.",
    "wof:placetype":"venue"
},
  "geometry": {"coordinates":[1.8313909769,41.7320480347],"type":"Point"}
}