{
  "type": "Feature",
  "properties": {
    "addr:full":"Calle de Pergamino, 26 Madrid Madrid 28032",
    "addr:housenumber":"26",
    "addr:postcode":"madrid;28032",
    "addr:street":"Calle De Pergamino",
    "iso:country":"ES",
    "sg:address":"Calle de Pergamino, 26",
    "sg:city":"Madrid",
    "sg:orig_category":"Caf\u00c9s, Bares, Cervecer\u00cdas",
    "sg:phone":"+34 917 51 20 60",
    "sg:postcode":"28032",
    "sg:province":"Madrid",
    "wof:name":"Hermanos Zamora Villacis S.l",
    "wof:placetype":"venue"
},
  "geometry": {"coordinates":[-3.6244940758,40.3946876526],"type":"Point"}
}