{
  "type": "Feature",
  "properties": {
    "iso:country":"ES",
    "sg:address":"Calle de Sevilla, 43",
    "sg:city":"Algeciras",
    "sg:orig_category":"Centros De Educaci\u00d3n Especial",
    "sg:phone":"+34 956 66 96 65",
    "sg:postcode":"11201",
    "sg:province":"C\u00e1diz",
    "wof:name":"Asoc.para Gestion De La Integrac Social S.l.",
    "wof:placetype":"venue"
},
  "geometry": {"coordinates":[-5.4488434792,36.1309738159],"type":"Point"}
}