{
  "type": "Feature",
  "properties": {
    "iso:country":"ES",
    "sg:address":"Rua Calvo Sotelo, 122",
    "sg:city":"Sarria",
    "sg:orig_category":"Frutas, Legumbres Frescas Y Tempranas (al Por Menor)",
    "sg:phone":"+34 982 53 35 57",
    "sg:postcode":"27600",
    "sg:province":"Lugo",
    "wof:name":"Dapena Mendez Purificacion",
    "wof:placetype":"venue"
},
  "geometry": {"coordinates":[-7.4109911919,42.7786598206],"type":"Point"}
}