{
  "type": "Feature",
  "properties": {
    "iso:country":"ES",
    "sg:address":"Calle de Mohices, 2",
    "sg:city":"Caridad",
    "sg:orig_category":"Empresarios Y Productoras De Espect\u00c1culos",
    "sg:phone":"+34 985 63 72 50",
    "sg:postcode":"33750",
    "sg:province":"Asturias",
    "wof:name":"Esmace Sl",
    "wof:placetype":"venue"
},
  "geometry": {"coordinates":[-6.8281412125,43.5497016907],"type":"Point"}
}