{
  "type": "Feature",
  "properties": {
    "addr:full":"Calle de Orzan, 31 Coru\u00d1a La Coru\u00f1a 15003",
    "addr:housenumber":"31",
    "addr:postcode":"15003",
    "addr:street":"Calle De Orzan;La Corun\u0303A",
    "iso:country":"ES",
    "sg:address":"Calle de Orzan, 31",
    "sg:city":"Coru\u00d1a",
    "sg:orig_category":"Molduras, Junquillos, Listones Y Molduras Perforadas",
    "sg:phone":"+34 981 22 78 89",
    "sg:postcode":"15003",
    "sg:province":"La Coru\u00f1a",
    "wof:name":"Rodriguez Ferreiro Jose Antonio",
    "wof:placetype":"venue"
},
  "geometry": {"coordinates":[-8.4011421204,43.3715515137],"type":"Point"}
}