{
  "type": "Feature",
  "properties": {
    "iso:country":"ES",
    "sg:address":"Baladres(urb Les Palmeres), 5",
    "sg:city":"Reus",
    "sg:orig_category":"Farmacias",
    "sg:phone":"+34 977 12 07 00",
    "sg:postcode":"43206",
    "sg:province":"Tarragona",
    "wof:name":"Do\u00f1ate Palos Oscar",
    "wof:placetype":"venue"
},
  "geometry": {"coordinates":[1.1039400101,41.1745300293],"type":"Point"}
}