{
  "type": "Feature",
  "properties": {
    "iso:country":"ES",
    "sg:address":"Calle de Don Juan De Austria, 4",
    "sg:city":"Valencia",
    "sg:orig_category":"Ropa Para Ni\u00d1os (al Por Menor)",
    "sg:phone":"+34 963 52 32 96",
    "sg:postcode":"46002",
    "sg:province":"Valencia",
    "sg:website":"www.e-stradivarius.com",
    "wof:name":"Stradivarius Espa\u00f1a S.a.",
    "wof:placetype":"venue"
},
  "geometry": {"coordinates":[-0.3736953139,39.4703788757],"type":"Point"}
}