{
  "type": "Feature",
  "properties": {
    "addr:full":"Calle de San Pedro, 59 Zuera Zaragoza 50800",
    "addr:housenumber":"59",
    "addr:postcode":"50800",
    "addr:street":"Calle De San Pedro",
    "iso:country":"ES",
    "sg:address":"Calle de San Pedro, 59",
    "sg:city":"Zuera",
    "sg:classifiers":[
        {
            "category":"Taxi",
            "type":"Transportation"
        }
    ],
    "sg:phone":"+34 976 68 08 97",
    "sg:postcode":"50800",
    "sg:province":"Zaragoza",
    "wof:name":"Molina Sanz Jesus",
    "wof:placetype":"venue"
},
  "geometry": {"coordinates":[-0.786781013,41.8691368103],"type":"Point"}
}