{
  "type": "Feature",
  "properties": {
    "addr:full":"Calle de Zubiaurre, 23 Ermua Vizcaya 48260",
    "addr:housenumber":"23",
    "addr:postcode":"48260",
    "addr:street":"Calle De Zubiaurre",
    "iso:country":"ES",
    "sg:address":"Calle de Zubiaurre, 23",
    "sg:city":"Ermua",
    "sg:orig_category":"Molduras, Junquillos, Listones Y Molduras Perforadas",
    "sg:phone":"+34 943 17 00 58",
    "sg:postcode":"48260",
    "sg:province":"Vizcaya",
    "wof:name":"Canton Vega Maria Aranzazu",
    "wof:placetype":"venue"
},
  "geometry": {"coordinates":[-2.5031371117,43.1876792908],"type":"Point"}
}