{
  "type": "Feature",
  "properties": {
    "iso:country":"ES",
    "sg:address":"Carretera, 12",
    "sg:city":"Cozvijar",
    "sg:orig_category":"Negocio De Materiales De Construcci\u00d3n",
    "sg:phone":"+34 958 78 07 61",
    "sg:postcode":"18659",
    "sg:province":"Granada",
    "sg:website":"www.paginasamarillas.es",
    "wof:name":"Saneamientos La Mezquita S.l.",
    "wof:placetype":"venue"
},
  "geometry": {"coordinates":[-3.627644062,36.9289894104],"type":"Point"}
}