{
  "type": "Feature",
  "properties": {
    "addr:full":"Calle de Antonio Trueba, 1 Altzaga Vizcaya 48950",
    "addr:housenumber":"1",
    "addr:postcode":"48950",
    "addr:street":"Calle De Antonio Trueba",
    "iso:country":"ES",
    "sg:address":"Calle de Antonio Trueba, 1",
    "sg:city":"Altzaga",
    "sg:orig_category":"Decoraci\u00d3n: Instalaci\u00d3n Y Talleres",
    "sg:phone":"+34 944 67 43 23",
    "sg:postcode":"48950",
    "sg:province":"Vizcaya",
    "wof:name":"Loft Deco S.l.",
    "wof:placetype":"venue"
},
  "geometry": {"coordinates":[-2.9765436649,43.301700592],"type":"Point"}
}