{
  "type": "Feature",
  "properties": {
    "addr:full":"Calle de Pintor Aparicio, 31 Alacant Alicante 03003",
    "addr:housenumber":"31",
    "addr:postcode":"03003",
    "addr:street":"Calle De Pintor Aparicio",
    "iso:country":"ES",
    "sg:address":"Calle de Pintor Aparicio, 31",
    "sg:city":"Alacant",
    "sg:orig_category":"Agencias De Viajes",
    "sg:phone":"+34 965 92 07 92",
    "sg:postcode":"03003",
    "sg:province":"Alicante",
    "sg:website":"www.halconviajes.com",
    "wof:name":"Viajes Halcon S.a.",
    "wof:placetype":"venue"
},
  "geometry": {"coordinates":[-0.4916490018,38.3418617249],"type":"Point"}
}