{
  "type": "Feature",
  "properties": {
    "iso:country":"ES",
    "sg:address":"Olaz-chipi, S/n",
    "sg:city":"Huarte",
    "sg:orig_category":"Ense\u00d1anza Secundaria: Colegios Y Escuelas Privadas",
    "sg:phone":"+34 948 33 77 72",
    "sg:postcode":"31620",
    "sg:province":"Navarra",
    "wof:name":"Gobierno De Navarra",
    "wof:placetype":"venue"
},
  "geometry": {"coordinates":[-1.5948990583,42.8247756958],"type":"Point"}
}