{
  "type": "Feature",
  "properties": {
    "addr:full":"Calle de Ecija, 7 Madrid Madrid 28008",
    "addr:housenumber":"7",
    "addr:postcode":"madrid;28008",
    "addr:street":"Calle De Ecija",
    "iso:country":"ES",
    "sg:address":"Calle de Ecija, 7",
    "sg:city":"Madrid",
    "sg:orig_category":"Promotores Constructores",
    "sg:phone":"+34 915 44 18 16",
    "sg:postcode":"28008",
    "sg:province":"Madrid",
    "wof:name":"Construccion Y Gestion Baobab S.a.",
    "wof:placetype":"venue"
},
  "geometry": {"coordinates":[-3.7237174511,40.4314613342],"type":"Point"}
}