{
  "type": "Feature",
  "properties": {
    "iso:country":"ES",
    "sg:address":"Calle de Plata (la), 24",
    "sg:city":"Barrios",
    "sg:orig_category":"Fotograf\u00cda Art\u00cdstica Y Retratos",
    "sg:phone":"+34 956 62 08 04",
    "sg:postcode":"11370",
    "sg:province":"C\u00e1diz",
    "wof:name":"Rios Camacho Manuel Angel",
    "wof:placetype":"venue"
},
  "geometry": {"coordinates":[-5.4924612045,36.1847038269],"type":"Point"}
}