{
  "type": "Feature",
  "properties": {
    "addr:full":"Avgd Tortosa, 2 Lleida Lleida 25005",
    "addr:housenumber":"2",
    "addr:postcode":"25005",
    "addr:street":"Tortosa",
    "iso:country":"ES",
    "sg:address":"Avgd Tortosa, 2",
    "sg:city":"Lleida",
    "sg:orig_category":"Frutas, Legumbres Frescas Y Tempranas (al Por Menor)",
    "sg:phone":"+34 973 23 90 86",
    "sg:postcode":"25005",
    "sg:province":"Lleida",
    "sg:website":"www.asofruit.es",
    "wof:name":"Asociacion Profesional De Frutas Y Hortalizas De Lerida",
    "wof:placetype":"venue"
},
  "geometry": {"coordinates":[0.6375755072,41.6201896667],"type":"Point"}
}