{
  "type": "Feature",
  "properties": {
    "addr:full":"Calle de Santiago Ramon Y Cajal, 12 Cartagena Murcia 30204",
    "addr:housenumber":"12",
    "addr:postcode":"30204",
    "addr:street":"Calle De Santiago Ramon Y Cajal",
    "iso:country":"ES",
    "sg:address":"Calle de Santiago Ramon Y Cajal, 12",
    "sg:city":"Cartagena",
    "sg:orig_category":"Ingeniero",
    "sg:phone":"+34 968 52 69 96",
    "sg:postcode":"30204",
    "sg:province":"Murcia",
    "wof:name":"Martinez Conesa Antonio",
    "wof:placetype":"venue"
},
  "geometry": {"coordinates":[-0.9908649921,37.6088829041],"type":"Point"}
}