{
  "type": "Feature",
  "properties": {
    "addr:full":"Calle de Fuentecilla, 29 Andorra Teruel 44500",
    "addr:housenumber":"29",
    "addr:postcode":"44500",
    "addr:street":"Calle De Fuentecilla",
    "iso:country":"ES",
    "sg:address":"Calle de Fuentecilla, 29",
    "sg:city":"Andorra",
    "sg:orig_category":"Contenedores (mercanc\u00cdas)",
    "sg:phone":"+34 978 84 36 49",
    "sg:postcode":"44500",
    "sg:province":"Teruel",
    "wof:name":"Mateo Espallargas Jose Luis",
    "wof:placetype":"venue"
},
  "geometry": {"coordinates":[-0.4491479993,40.9777946472],"type":"Point"}
}