{
  "type": "Feature",
  "properties": {
    "addr:full":"Carrer de Ametlla De Mar (de L'), 17 Salou Tarragona 43840",
    "addr:housenumber":"17",
    "addr:postcode":"43840",
    "addr:street":"Carrer De Ametlla De Mar De L '",
    "iso:country":"ES",
    "sg:address":"Carrer de Ametlla De Mar (de L'), 17",
    "sg:city":"Salou",
    "sg:orig_category":"Empresarios",
    "sg:phone":"+34 977 38 09 57",
    "sg:postcode":"43840",
    "sg:province":"Tarragona",
    "wof:name":"Garrido Torres Diego",
    "wof:placetype":"venue"
},
  "geometry": {"coordinates":[1.1322549582,41.086063385],"type":"Point"}
}