{
  "type": "Feature",
  "properties": {
    "iso:country":"ES",
    "sg:address":"Plaz Juan Ramon Jimenez, 8",
    "sg:city":"Camas",
    "sg:orig_category":"Asociaciones, Organismos Culturales Y Socioeducativos",
    "sg:phone":"+34 955 98 08 65",
    "sg:postcode":"41900",
    "sg:province":"Sevilla",
    "wof:name":"Pe\u00f1a Cultural Rociera",
    "wof:placetype":"venue"
},
  "geometry": {"coordinates":[-6.0344491005,37.4007263184],"type":"Point"}
}