{
  "type": "Feature",
  "properties": {
    "iso:country":"ES",
    "sg:address":"Calle de Santiago, 20",
    "sg:city":"Valladolid",
    "sg:orig_category":"Fabricaci\u00d3n, Instalaci\u00d3n De Estufas",
    "sg:phone":"+34 983 34 47 37",
    "sg:postcode":"47001",
    "sg:province":"Valladolid",
    "wof:name":"Garicano Toron Celia Maria",
    "wof:placetype":"venue"
},
  "geometry": {"coordinates":[-4.7291789055,41.6496047974],"type":"Point"}
}