{
  "type": "Feature",
  "properties": {
    "iso:country":"ES",
    "sg:address":"Calle de Mayor, 23",
    "sg:city":"Puebla De Almenara",
    "sg:orig_category":"Centros M\u00c9dicos Y Sociales, Dispensarios",
    "sg:phone":"+34 969 13 11 10",
    "sg:postcode":"16421",
    "sg:province":"Cuenca",
    "wof:name":"Ayuntamiento De Puebla De Almenara",
    "wof:placetype":"venue"
},
  "geometry": {"coordinates":[-2.814551115,39.7843132019],"type":"Point"}
}