{
  "type": "Feature",
  "properties": {
    "addr:full":"Calle de San Antonio, 14 Totana Murcia 30850",
    "addr:housenumber":"14",
    "addr:postcode":"30850",
    "addr:street":"Calle De San Antonio",
    "iso:country":"ES",
    "sg:address":"Calle de San Antonio, 14",
    "sg:city":"Totana",
    "sg:orig_category":"Agencias De Viajes",
    "sg:phone":"+34 968 42 54 45",
    "sg:postcode":"30850",
    "sg:province":"Murcia",
    "wof:name":"Aldemur S.l.",
    "wof:placetype":"venue"
},
  "geometry": {"coordinates":[-1.5008199215,37.7713928223],"type":"Point"}
}