{
  "type": "Feature",
  "properties": {
    "iso:country":"ES",
    "sg:address":"Avda Espa\u00d1a (de), S/n",
    "sg:city":"Coslada",
    "sg:classifiers":[
        {
            "category":"Casinos & Gambling",
            "type":"Entertainment"
        }
    ],
    "sg:phone":"+34 916 73 95 14",
    "sg:postcode":"28820",
    "sg:province":"Madrid",
    "sg:tags":[
        "locale",
        "de",
        "juego"
    ],
    "wof:name":"Henar Azar S.a",
    "wof:placetype":"venue"
},
  "geometry": {"coordinates":[-3.5621058941,40.4211845398],"type":"Point"}
}