{
  "type": "Feature",
  "properties": {
    "iso:country":"ES",
    "sg:address":"Carrer de Joan Maragall, 8",
    "sg:city":"S. Joan Despi",
    "sg:orig_category":"Caf\u00c9s, Bares, Cervecer\u00cdas",
    "sg:phone":"+34 934 77 15 57",
    "sg:postcode":"08970",
    "sg:province":"Barcelona",
    "wof:name":"Espejo Perez Jose",
    "wof:placetype":"venue"
},
  "geometry": {"coordinates":[2.0733239651,41.3679084778],"type":"Point"}
}