{
  "type": "Feature",
  "properties": {
    "iso:country":"ES",
    "sg:address":"Calle de Zabalgain Kalea, 6",
    "sg:city":"Zizur Mayor",
    "sg:orig_category":"Estancos",
    "sg:phone":"+34 948 18 26 09",
    "sg:postcode":"31180",
    "sg:province":"Navarra",
    "wof:name":"Estanco Arangura",
    "wof:placetype":"venue"
},
  "geometry": {"coordinates":[-1.6934690475,42.7876739502],"type":"Point"}
}