{
  "type": "Feature",
  "properties": {
    "iso:country":"ES",
    "sg:address":"Calle de Alcala, 211",
    "sg:city":"Madrid",
    "sg:orig_category":"Ingeniero",
    "sg:phone":"+34 913 56 96 03",
    "sg:postcode":"28028",
    "sg:province":"Madrid",
    "wof:name":"Lozano Carreras Alberto",
    "wof:placetype":"venue"
},
  "geometry": {"coordinates":[-3.6664690971,40.4292564392],"type":"Point"}
}