{
  "type": "Feature",
  "properties": {
    "addr:full":"Av Diputacio, 175 Cambrils Tarragona 43850",
    "addr:housenumber":"175",
    "addr:postcode":"43850",
    "addr:street":"Av Diputacio",
    "iso:country":"ES",
    "sg:address":"Av Diputacio, 175",
    "sg:city":"Cambrils",
    "sg:orig_category":"Asociaciones Y Clubs Deportivos",
    "sg:phone":"+34 977 35 29 20",
    "sg:postcode":"43850",
    "sg:province":"Tarragona",
    "wof:name":"Das  Narayan",
    "wof:placetype":"venue"
},
  "geometry": {"coordinates":[1.0737299919,41.0664405823],"type":"Point"}
}