{
  "type": "Feature",
  "properties": {
    "addr:full":"Pase Oria (de), 27 San Fernando De Henares Madrid 28830",
    "addr:postcode":"28830",
    "iso:country":"ES",
    "sg:address":"Pase Oria (de), 27",
    "sg:city":"San Fernando De Henares",
    "sg:orig_category":"Inform\u00c1tica Equipo Y Programas (al Por Mayor)",
    "sg:phone":"+34 916 73 63 99",
    "sg:postcode":"28830",
    "sg:province":"Madrid",
    "wof:name":"Manzano De La Cruz Raul",
    "wof:placetype":"venue"
},
  "geometry": {"coordinates":[-3.5353159904,40.4256858826],"type":"Point"}
}