{
  "type": "Feature",
  "properties": {
    "addr:full":"Diamante, 3 Valdemoro Madrid 28340",
    "addr:housenumber":"3",
    "addr:postcode":"28340",
    "addr:street":"Diamante",
    "iso:country":"ES",
    "sg:address":"Diamante, 3",
    "sg:city":"Valdemoro",
    "sg:orig_category":"Transportes Especiales",
    "sg:phone":"+34 918 08 02 39",
    "sg:postcode":"28340",
    "sg:province":"Madrid",
    "wof:name":"Vilchez Navarro Antonio",
    "wof:placetype":"venue"
},
  "geometry": {"coordinates":[-3.664329052,40.1736984253],"type":"Point"}
}