{
  "type": "Feature",
  "properties": {
    "iso:country":"ES",
    "sg:address":"Calle de Orion, 7",
    "sg:city":"Estrella",
    "sg:orig_category":"Abogados",
    "sg:phone":"+34 922 78 38 32",
    "sg:postcode":"38631",
    "sg:province":"Santa Cruz De Tenerife",
    "wof:name":"Diaz Melian Maria Ines",
    "wof:placetype":"venue"
},
  "geometry": {"coordinates":[-16.670463562,28.0141906738],"type":"Point"}
}