{
  "type": "Feature",
  "properties": {
    "iso:country":"ES",
    "sg:address":"Carrer de Garrofers, 21",
    "sg:city":"Castellar Valles",
    "sg:orig_category":"Negocio De Madera",
    "sg:phone":"+34 937 14 30 84",
    "sg:postcode":"08211",
    "sg:province":"Barcelona",
    "wof:name":"Comercas S L Representacions I Serveis",
    "wof:placetype":"venue"
},
  "geometry": {"coordinates":[2.0857300758,41.6151885986],"type":"Point"}
}