{
  "type": "Feature",
  "properties": {
    "addr:full":"Calle de Benavente, 2 Alija Infantado Le\u00f3n 24761",
    "addr:housenumber":"2",
    "addr:postcode":"24761",
    "addr:street":"Calle De Benavente;Infantado Leo\u0301N",
    "iso:country":"ES",
    "sg:address":"Calle de Benavente, 2",
    "sg:city":"Alija Infantado",
    "sg:orig_category":"Material Y Equipo Para Vinificaci\u00d3n",
    "sg:phone":"+34 987 66 79 13",
    "sg:postcode":"24761",
    "sg:province":"Le\u00f3n",
    "wof:name":"Iberica De Multiplicacion Aviar S.l.",
    "wof:placetype":"venue"
},
  "geometry": {"coordinates":[-5.8323197365,42.1340713501],"type":"Point"}
}