{
  "type": "Feature",
  "properties": {
    "addr:full":"Pase Santa Maria De La Cabeza, 77 Madrid Madrid 28045",
    "addr:housenumber":"77",
    "addr:postcode":"madrid;28045",
    "addr:street":"Cabeza",
    "iso:country":"ES",
    "sg:address":"Pase Santa Maria De La Cabeza, 77",
    "sg:city":"Madrid",
    "sg:orig_category":"M\u00c9dicos: Pediatr\u00cda. Enfermedades De Los Ni\u00d1os",
    "sg:phone":"+34 914 73 83 48",
    "sg:postcode":"28045",
    "sg:province":"Madrid",
    "wof:name":"Ortu\u00f1o Maqueda Antonio",
    "wof:placetype":"venue"
},
  "geometry": {"coordinates":[-3.701059103,40.3990097046],"type":"Point"}
}