{
  "type": "Feature",
  "properties": {
    "iso:country":"ES",
    "sg:address":"Calle de Pintor Barjola, 17",
    "sg:city":"Badajoz",
    "sg:orig_category":"Complementos De Vestir (al Por Menor)",
    "sg:phone":"+34 924 27 78 01",
    "sg:postcode":"06007",
    "sg:province":"Badajoz",
    "wof:name":"Duran Ramirez Rafael",
    "wof:placetype":"venue"
},
  "geometry": {"coordinates":[-6.9802317619,38.8873901367],"type":"Point"}
}