{
  "type": "Feature",
  "properties": {
    "addr:full":"Calle de Carretera Beniel, Km. 0005,0 Desamparados Alicante 03312",
    "addr:postcode":"03312",
    "addr:street":"Calle De Carretera Beniel Km. 0005,0",
    "iso:country":"ES",
    "sg:address":"Calle de Carretera Beniel, Km. 0005,0",
    "sg:city":"Desamparados",
    "sg:orig_category":"Electricidad Veh\u00cdculo",
    "sg:phone":"+34 966 74 08 66",
    "sg:postcode":"03312",
    "sg:province":"Alicante",
    "wof:name":"Talleres Mu\u00f1oz Vera S.l.",
    "wof:placetype":"venue"
},
  "geometry": {"coordinates":[-0.9420070052,38.0560684204],"type":"Point"}
}