{
  "type": "Feature",
  "properties": {
    "addr:full":"Calle de San Jose, 74 Yecla Murcia 30510",
    "addr:housenumber":"74",
    "addr:postcode":"30510",
    "addr:street":"Calle De San",
    "iso:country":"ES",
    "sg:address":"Calle de San Jose, 74",
    "sg:city":"Yecla",
    "sg:orig_category":"Bisuter\u00cda, Joyer\u00cda, Relojer\u00cda (al Por Menor)",
    "sg:phone":"+34 968 75 37 86",
    "sg:postcode":"30510",
    "sg:province":"Murcia",
    "wof:name":"Diaz Soriano Isabel",
    "wof:placetype":"venue"
},
  "geometry": {"coordinates":[-1.1122000217,38.6128921509],"type":"Point"}
}