{
  "type": "Feature",
  "properties": {
    "addr:full":"Calle de Mayor, S/n Uceda Guadalajara 19187",
    "addr:housenumber":"s",
    "addr:postcode":"19187",
    "addr:street":"Calle De Mayor;/ N Uceda",
    "iso:country":"ES",
    "sg:address":"Calle de Mayor, S/n",
    "sg:city":"Uceda",
    "sg:orig_category":"Farmacias",
    "sg:phone":"+34 949 85 60 96",
    "sg:postcode":"19187",
    "sg:province":"Guadalajara",
    "wof:name":"Perez Torralba Maria Dolores",
    "wof:placetype":"venue"
},
  "geometry": {"coordinates":[-3.4627535343,40.8413887024],"type":"Point"}
}