{
  "type": "Feature",
  "properties": {
    "addr:full":"Calle de Rosario Pereda, 22 Valladolid Valladolid 47007",
    "addr:housenumber":"22",
    "addr:postcode":"47007",
    "addr:street":"Calle De Rosario Pereda",
    "iso:country":"ES",
    "sg:address":"Calle de Rosario Pereda, 22",
    "sg:city":"Valladolid",
    "sg:orig_category":"Electrodom\u00c9sticos (al Por Menor)",
    "sg:phone":"+34 983 47 77 21",
    "sg:postcode":"47007",
    "sg:province":"Valladolid",
    "wof:name":"Bernaldez Orejon Angel",
    "wof:placetype":"venue"
},
  "geometry": {"coordinates":[-4.7386059761,41.6350975037],"type":"Point"}
}