{
  "type": "Feature",
  "properties": {
    "iso:country":"ES",
    "sg:address":"Calle de Isaac Peral, 36",
    "sg:city":"Santander",
    "sg:orig_category":"Electricidad: Instaladores",
    "sg:phone":"+34 942 37 52 32",
    "sg:postcode":"39008",
    "sg:province":"Cantabria",
    "wof:name":"Electricidad Berasa S.l.",
    "wof:placetype":"venue"
},
  "geometry": {"coordinates":[-3.8204200268,43.4591255188],"type":"Point"}
}