{
  "type": "Feature",
  "properties": {
    "iso:country":"ES",
    "sg:address":"Calle de Juana Elorza, 4",
    "sg:city":"Madrid",
    "sg:orig_category":"Confecci\u00d3n De Trajes Para Se\u00d1oras",
    "sg:phone":"+34 914 78 19 19",
    "sg:postcode":"28053",
    "sg:province":"Madrid",
    "wof:name":"Modelajes Artemoda S.l.",
    "wof:placetype":"venue"
},
  "geometry": {"coordinates":[-3.6664979458,40.3928565979],"type":"Point"}
}