{
  "type": "Feature",
  "properties": {
    "iso:country":"ES",
    "sg:address":"Calle de Buenos Aires, 107",
    "sg:city":"Muela",
    "sg:orig_category":"Construcciones Met\u00c1licas",
    "sg:phone":"+34 976 14 45 35",
    "sg:postcode":"50196",
    "sg:province":"Zaragoza",
    "wof:name":"Arper Inox S.l",
    "wof:placetype":"venue"
},
  "geometry": {"coordinates":[-1.0742878914,41.6119194031],"type":"Point"}
}