{
  "type": "Feature",
  "properties": {
    "iso:country":"ES",
    "sg:address":"Carrer de Dalmases, 73",
    "sg:city":"Barcelona",
    "sg:orig_category":"Centros M\u00c9dicos Y Sociales, Dispensarios",
    "sg:phone":"+34 934 18 29 07",
    "sg:postcode":"08022",
    "sg:province":"Barcelona",
    "wof:name":"Camps Surroca Maria Dolores",
    "wof:placetype":"venue"
},
  "geometry": {"coordinates":[2.1301760674,41.4038352966],"type":"Point"}
}