{
  "type": "Feature",
  "properties": {
    "addr:full":"Calle de Corporales, S/n Corporales Le\u00f3n 24740",
    "addr:housenumber":"s",
    "addr:postcode":"24740",
    "addr:street":"Calle De Corporales;/ N Corporales Leo\u0301N",
    "iso:country":"ES",
    "sg:address":"Calle de Corporales, S/n",
    "sg:city":"Corporales",
    "sg:orig_category":"Asociaciones, Organismos Culturales Y Socioeducativos",
    "sg:phone":"+34 987 66 47 00",
    "sg:postcode":"24740",
    "sg:province":"Le\u00f3n",
    "wof:name":"Asociacion Juvenil Colonia Las Rivas",
    "wof:placetype":"venue"
},
  "geometry": {"coordinates":[-6.4600949287,42.2878074646],"type":"Point"}
}