{
  "type": "Feature",
  "properties": {
    "addr:full":"Calle de Pedro Alcazar, 14 Nules Castell\u00f3n 12520",
    "addr:housenumber":"14",
    "addr:postcode":"12520",
    "addr:street":"Calle De Pedro Alcazar",
    "iso:country":"ES",
    "sg:address":"Calle de Pedro Alcazar, 14",
    "sg:city":"Nules",
    "sg:classifiers":[
        {
            "category":"Utilities",
            "subcategory":"Natural Gas",
            "type":"Services"
        }
    ],
    "sg:phone":"+34 964 67 13 94",
    "sg:postcode":"12520",
    "sg:province":"Castell\u00f3n",
    "wof:name":"Castellonense De Calefaccion Y Gas S.l.",
    "wof:placetype":"venue"
},
  "geometry": {"coordinates":[-0.1555999964,39.8538475037],"type":"Point"}
}