{
  "type": "Feature",
  "properties": {
    "iso:country":"ES",
    "sg:address":"Rua Espi\u00d1eira (da), 4",
    "sg:city":"Santiago De Compostela",
    "sg:orig_category":"Ense\u00d1anza Variada",
    "sg:phone":"+34 981 53 40 55",
    "sg:postcode":"15706",
    "sg:province":"La Coru\u00f1a",
    "sg:website":"www.premir.es",
    "wof:name":"Premir-oposiciones Medicas S.l.",
    "wof:placetype":"venue"
},
  "geometry": {"coordinates":[-8.5567827225,42.8716545105],"type":"Point"}
}