{
  "type": "Feature",
  "properties": {
    "iso:country":"ES",
    "sg:address":"Calle de Santutxu, 35",
    "sg:city":"Bilbao",
    "sg:orig_category":"Relojer\u00cda (al Por Menor, Reparaci\u00d3n)",
    "sg:phone":"+34 944 33 17 76",
    "sg:postcode":"48004",
    "sg:province":"Vizcaya",
    "wof:name":"Maria Elvira Valencia Abril",
    "wof:placetype":"venue"
},
  "geometry": {"coordinates":[-2.9148519039,43.2521705627],"type":"Point"}
}