{
  "type": "Feature",
  "properties": {
    "addr:full":"Crta. Nal. 420, S/n Argamasilla Calatrava Ciudad Real 13440",
    "addr:housenumber":"s / n",
    "addr:postcode":"13440",
    "addr:street":"Crta. Nal. 420",
    "iso:country":"ES",
    "sg:address":"Crta. Nal. 420, S/n",
    "sg:city":"Argamasilla Calatrava",
    "sg:orig_category":"Hoteles",
    "sg:phone":"+34 926 47 71 34",
    "sg:postcode":"13440",
    "sg:province":"Ciudad Real",
    "wof:name":"2004 Godisa S.l..u.",
    "wof:placetype":"venue"
},
  "geometry": {"coordinates":[-3.927263,38.986095],"type":"Point"}
}