{
  "type": "Feature",
  "properties": {
    "addr:full":"Calle de San Antonio Maria Claret, 30 Zaragoza Zaragoza 50005",
    "addr:housenumber":"30",
    "addr:postcode":"50005",
    "addr:street":"Calle De San;Maria Claret",
    "iso:country":"ES",
    "sg:address":"Calle de San Antonio Maria Claret, 30",
    "sg:city":"Zaragoza",
    "sg:orig_category":"Prot\u00c9sicos Dentales",
    "sg:phone":"+34 976 55 15 67",
    "sg:postcode":"50005",
    "sg:province":"Zaragoza",
    "wof:name":"Moliner Andres Juan Carlos",
    "wof:placetype":"venue"
},
  "geometry": {"coordinates":[-0.8952590227,41.6448059082],"type":"Point"}
}