{
  "type": "Feature",
  "properties": {
    "iso:country":"ES",
    "sg:address":"Avda Solvay, 52",
    "sg:city":"Barreda",
    "sg:orig_category":"Peluquer\u00cdas, Peluquer\u00cda Mixta",
    "sg:phone":"+34 942 88 85 01",
    "sg:postcode":"39300",
    "sg:province":"Cantabria",
    "wof:name":"Palencia Gutierrez Elisa Isabel",
    "wof:placetype":"venue"
},
  "geometry": {"coordinates":[-4.0451221466,43.3643989563],"type":"Point"}
}