{
  "type": "Feature",
  "properties": {
    "iso:country":"ES",
    "sg:address":"Carrer de Rocafort, 111",
    "sg:city":"Barcelona",
    "sg:classifiers":[
        {
            "category":"Taxi",
            "type":"Transportation"
        }
    ],
    "sg:phone":"+34 934 24 89 30",
    "sg:postcode":"08015",
    "sg:province":"Barcelona",
    "wof:name":"Romani Forteza Joan",
    "wof:placetype":"venue"
},
  "geometry": {"coordinates":[2.1522080898,41.3799324036],"type":"Point"}
}