{
  "type": "Feature",
  "properties": {
    "addr:full":"Avda Ordesa, 29 Broto Huesca 22370",
    "addr:housenumber":"29",
    "addr:postcode":"22370",
    "addr:street":"Avda Ordesa",
    "iso:country":"ES",
    "sg:address":"Avda Ordesa, 29",
    "sg:city":"Broto",
    "sg:orig_category":"Distribuci\u00d3n De Petr\u00d3leo Y Derivados",
    "sg:phone":"+34 974 48 63 44",
    "sg:postcode":"22370",
    "sg:province":"Huesca",
    "wof:name":"Cosculluela Noguero Ricardo",
    "wof:placetype":"venue"
},
  "geometry": {"coordinates":[-0.122266002,42.6043128967],"type":"Point"}
}