{
  "type": "Feature",
  "properties": {
    "iso:country":"ES",
    "sg:address":"Plaz San Juan, S/n",
    "sg:city":"Burgos",
    "sg:orig_category":"Museos",
    "sg:phone":"+34 947 20 56 87",
    "sg:postcode":"09004",
    "sg:province":"Burgos",
    "wof:name":"Ayuntamiento De Burgos",
    "wof:placetype":"venue"
},
  "geometry": {"coordinates":[-3.6979780197,42.3427734375],"type":"Point"}
}