{
  "type": "Feature",
  "properties": {
    "iso:country":"ES",
    "sg:address":"Carrer de Joan Torras, 2",
    "sg:city":"Barcelona",
    "sg:orig_category":"Loter\u00cda Y T\u00d3mbola",
    "sg:phone":"+34 932 74 05 77",
    "sg:postcode":"08030",
    "sg:province":"Barcelona",
    "wof:name":"Sanchis Pascual Maria Teresa",
    "wof:placetype":"venue"
},
  "geometry": {"coordinates":[2.1893460751,41.4375457764],"type":"Point"}
}