{
  "type": "Feature",
  "properties": {
    "addr:full":"Avda Presidente Carmona, 7 Madrid Madrid 28020",
    "addr:housenumber":"7",
    "addr:postcode":"madrid;28020",
    "addr:street":"Avda Presidente Carmona",
    "iso:country":"ES",
    "sg:address":"Avda Presidente Carmona, 7",
    "sg:city":"Madrid",
    "sg:orig_category":"El Hogar: Amueblado, Acondicionamiento, Decoraci\u00d3n Y Mantenimiento",
    "sg:phone":"+34 915 70 54 42",
    "sg:postcode":"28020",
    "sg:province":"Madrid",
    "wof:name":"F.a.e. Fomento De Las Artes S.l",
    "wof:placetype":"venue"
},
  "geometry": {"coordinates":[-3.6973850727,40.4542579651],"type":"Point"}
}