{
  "type": "Feature",
  "properties": {
    "addr:full":"Pol. Ind. Mijares, S/n Almassora Castell\u00f3n 12550",
    "addr:housenumber":"s / n",
    "addr:postcode":"12550",
    "addr:street":"Mijares;Almassora Castello\u0301N",
    "iso:country":"ES",
    "sg:address":"Pol. Ind. Mijares, S/n",
    "sg:city":"Almassora",
    "sg:orig_category":"Vidrio, Fabricaci\u00d3n Y Comercio",
    "sg:phone":"+34 964 50 30 94",
    "sg:postcode":"12550",
    "sg:province":"Castell\u00f3n",
    "sg:website":"www.bisazza.it",
    "wof:name":"Bisazza Espa\u00f1a S.l.",
    "wof:placetype":"venue"
},
  "geometry": {"coordinates":[-0.0631700009,39.9439582825],"type":"Point"}
}