{
  "type": "Feature",
  "properties": {
    "iso:country":"ES",
    "sg:address":"Rbla Fabra I Puig, 64",
    "sg:city":"Barcelona",
    "sg:orig_category":"Dietistas",
    "sg:phone":"+34 933 11 21 42",
    "sg:postcode":"08030",
    "sg:province":"Barcelona",
    "sg:website":"www.olympus-sport.com",
    "wof:name":"Olympus Sport Nutricion S.a.",
    "wof:placetype":"venue"
},
  "geometry": {"coordinates":[2.1867260933,41.4303894043],"type":"Point"}
}