{
  "type": "Feature",
  "properties": {
    "iso:country":"ES",
    "sg:address":"Avda Nuestra Se\u00d1ora De Las Guias, 1",
    "sg:city":"Malaga",
    "sg:orig_category":"Agencias Y Asesores De Publicidad",
    "sg:phone":"+34 952 25 09 25",
    "sg:postcode":"29014",
    "sg:province":"M\u00e1laga",
    "wof:name":"Carnero Ramiro Juan",
    "wof:placetype":"venue"
},
  "geometry": {"coordinates":[-4.4215607643,36.7381210327],"type":"Point"}
}