{
  "type": "Feature",
  "properties": {
    "iso:country":"ES",
    "sg:address":"Calle de Blas Infante, 9",
    "sg:city":"Lora Rio",
    "sg:orig_category":"Heladeros",
    "sg:phone":"+34 955 80 29 92",
    "sg:postcode":"41440",
    "sg:province":"Sevilla",
    "wof:name":"Andrade Sirvent Jose Enrique",
    "wof:placetype":"venue"
},
  "geometry": {"coordinates":[-5.5307688713,37.6552963257],"type":"Point"}
}