{
  "type": "Feature",
  "properties": {
    "iso:country":"ES",
    "sg:address":"Calle de Horizonte, 7",
    "sg:city":"Mairena Aljarafe",
    "sg:orig_category":"Fabricaci\u00d3n, Instalaci\u00d3n De Armarios",
    "sg:phone":"+34 955 60 21 15",
    "sg:postcode":"41927",
    "sg:province":"Sevilla",
    "wof:name":"Arquiarmarios S.l.",
    "wof:placetype":"venue"
},
  "geometry": {"coordinates":[-6.0581693649,37.3535652161],"type":"Point"}
}