{
  "type": "Feature",
  "properties": {
    "iso:country":"ES",
    "sg:address":"Avda Reconquista, S/n",
    "sg:city":"Hervas",
    "sg:orig_category":"Fabricaci\u00d3n De Muebles",
    "sg:phone":"+34 927 48 11 50",
    "sg:postcode":"10700",
    "sg:province":"C\u00e1ceres",
    "wof:name":"Montero Peralejo Antonio",
    "wof:placetype":"venue"
},
  "geometry": {"coordinates":[-5.866256237,40.2719039917],"type":"Point"}
}