{
  "type": "Feature",
  "properties": {
    "addr:full":"Calle de Palomar, 4 Macotera Salamanca 37310",
    "addr:housenumber":"4",
    "addr:postcode":"37310",
    "addr:street":"Calle De Palomar",
    "iso:country":"ES",
    "sg:address":"Calle de Palomar, 4",
    "sg:city":"Macotera",
    "sg:orig_category":"Electricidad: Instaladores",
    "sg:phone":"+34 923 55 52 37",
    "sg:postcode":"37310",
    "sg:province":"Salamanca",
    "wof:name":"Hernandez Zaballos Manuel",
    "wof:placetype":"venue"
},
  "geometry": {"coordinates":[-5.281484127,40.8316040039],"type":"Point"}
}