{
  "type": "Feature",
  "properties": {
    "iso:country":"ES",
    "sg:address":"Calle de Colon, 13",
    "sg:city":"Tui",
    "sg:orig_category":"Bazares, Art\u00cdculos De Limpieza Y De Cocina (al Por Menor)",
    "sg:phone":"+34 986 62 79 54",
    "sg:postcode":"36700",
    "sg:province":"Pontevedra",
    "wof:name":"Verde Gonzalez Jose Antonio",
    "wof:placetype":"venue"
},
  "geometry": {"coordinates":[-8.6503238678,42.0517311096],"type":"Point"}
}