{
  "type": "Feature",
  "properties": {
    "addr:full":"Carrer de Andrade, 47 Barcelona Barcelona 08018",
    "addr:housenumber":"47",
    "addr:postcode":"08018",
    "addr:street":"Carrer De Andrade",
    "iso:country":"ES",
    "sg:address":"Carrer de Andrade, 47",
    "sg:city":"Barcelona",
    "sg:classifiers":[
        {
            "category":"Autos & Motor Vehicles",
            "subcategory":"Automobile Sales",
            "type":"Retail Goods"
        }
    ],
    "sg:phone":"+34 933 03 15 90",
    "sg:postcode":"08018",
    "sg:province":"Barcelona",
    "wof:name":"Autoescuela Herrera S.c.p.",
    "wof:placetype":"venue"
},
  "geometry": {"coordinates":[2.1959331036,41.4123039246],"type":"Point"}
}