{
  "type": "Feature",
  "properties": {
    "iso:country":"ES",
    "sg:address":"Carrer de Enric Granados, 155",
    "sg:city":"Barcelona",
    "sg:orig_category":"Farmacias",
    "sg:phone":"+34 932 09 99 37",
    "sg:postcode":"08008",
    "sg:province":"Barcelona",
    "wof:name":"Segon Cucurull Maria Inmaculada",
    "wof:placetype":"venue"
},
  "geometry": {"coordinates":[2.1533238888,41.3944816589],"type":"Point"}
}