{
  "type": "Feature",
  "properties": {
    "iso:country":"ES",
    "sg:address":"Ctra Valladolid, Km. 0001,3",
    "sg:city":"Avila",
    "sg:orig_category":"Agentes, Concesionarios Y Sucursales De Veh\u00cdculos",
    "sg:phone":"+34 920 22 18 62",
    "sg:postcode":"05004",
    "sg:province":"\u00c1vila",
    "wof:name":"Manso Motor S. A.",
    "wof:placetype":"venue"
},
  "geometry": {"coordinates":[-4.6800055504,40.6617622375],"type":"Point"}
}