{
  "type": "Feature",
  "properties": {
    "iso:country":"ES",
    "sg:address":"Plaz San Francisco, 1",
    "sg:city":"Linares",
    "sg:orig_category":"Florister\u00cdas",
    "sg:phone":"+34 953 60 10 77",
    "sg:postcode":"23700",
    "sg:province":"Ja\u00e9n",
    "wof:name":"Hermanos Jurado Molina C.b.",
    "wof:placetype":"venue"
},
  "geometry": {"coordinates":[-3.6319830418,38.0947647095],"type":"Point"}
}