{
  "type": "Feature",
  "properties": {
    "iso:country":"ES",
    "sg:address":"Calle de Amaniel, 18",
    "sg:city":"Madrid",
    "sg:orig_category":"Estudios De Grabaci\u00d3n Sonora",
    "sg:phone":"+34 915 23 77 35",
    "sg:postcode":"28015",
    "sg:province":"Madrid",
    "wof:name":"Orixe Veinte S.l.",
    "wof:placetype":"venue"
},
  "geometry": {"coordinates":[-3.7093150616,40.426235199],"type":"Point"}
}