{
  "type": "Feature",
  "properties": {
    "addr:full":"Calle de Las Parras, 10 Coria C\u00e1ceres 10800",
    "addr:housenumber":"10",
    "addr:postcode":"10800",
    "addr:street":"Calle De Las Parras;Ca\u0301Ceres",
    "iso:country":"ES",
    "sg:address":"Calle de Las Parras, 10",
    "sg:city":"Coria",
    "sg:orig_category":"Fabricaci\u00d3n, Venta, Instalaci\u00d3n De R\u00d3tulos, De R\u00d3tulos Luminosos",
    "sg:phone":"+34 927 50 02 89",
    "sg:postcode":"10800",
    "sg:province":"C\u00e1ceres",
    "wof:name":"Seguravic De Coria S.l.",
    "wof:placetype":"venue"
},
  "geometry": {"coordinates":[-6.5368189812,39.9854393005],"type":"Point"}
}