{
  "type": "Feature",
  "properties": {
    "iso:country":"ES",
    "sg:address":"Avda Generalisimo, 84",
    "sg:city":"Meira",
    "sg:orig_category":"Material Y Herramientas Agr\u00cdcolas",
    "sg:phone":"+34 982 33 01 59",
    "sg:postcode":"27240",
    "sg:province":"Lugo",
    "wof:name":"Agricola Acevedo S.l.",
    "wof:placetype":"venue"
},
  "geometry": {"coordinates":[-7.2943172455,43.2154541016],"type":"Point"}
}