{
  "type": "Feature",
  "properties": {
    "iso:country":"ES",
    "sg:address":"Calle de Joaquin Costa, 35",
    "sg:city":"Teruel",
    "sg:orig_category":"Mercer\u00cda, Lencer\u00cda (al Por Menor)",
    "sg:phone":"+34 978 60 85 35",
    "sg:postcode":"44001",
    "sg:province":"Teruel",
    "wof:name":"Iba\u00f1ez Fabre Maria Victoria",
    "wof:placetype":"venue"
},
  "geometry": {"coordinates":[-1.1060420275,40.3438606262],"type":"Point"}
}