{
  "type": "Feature",
  "properties": {
    "iso:country":"ES",
    "sg:address":"C/ Abat Oliba, 1",
    "sg:city":"Salt",
    "sg:orig_category":"Fabricaci\u00d3n De Telas Y Sedas",
    "sg:phone":"+34 972 40 56 94",
    "sg:postcode":"17190",
    "sg:province":"Girona",
    "wof:name":"Falguera-sacrest S.a.",
    "wof:placetype":"venue"
},
  "geometry": {"coordinates":[2.7983050346,41.9759979248],"type":"Point"}
}