{
  "type": "Feature",
  "properties": {
    "iso:country":"ES",
    "sg:address":"Calle de Pamplona, 2",
    "sg:city":"Camas",
    "sg:orig_category":"Bisuter\u00cda, Joyer\u00cda, Relojer\u00cda (al Por Menor)",
    "sg:phone":"+34 954 39 14 65",
    "sg:postcode":"41900",
    "sg:province":"Sevilla",
    "wof:name":"Alonso Varela Maria Isabel",
    "wof:placetype":"venue"
},
  "geometry": {"coordinates":[-6.0332555771,37.3987045288],"type":"Point"}
}