{
  "type": "Feature",
  "properties": {
    "iso:country":"ES",
    "sg:address":"Calle de Explanada De La Estacion, S/n",
    "sg:city":"Iznalloz",
    "sg:orig_category":"Aceites Y Grasas Alimentarias (fabricaci\u00d3n, Al Por Mayor)",
    "sg:phone":"+34 958 38 41 79",
    "sg:postcode":"18550",
    "sg:province":"Granada",
    "sg:website":"www.iznaoliva.com",
    "wof:name":"Sociedad Cooperativa Del Campo Nuestra Se\u00f1ora De Los Remedios De Iznalloz",
    "wof:placetype":"venue"
},
  "geometry": {"coordinates":[-3.5285038948,37.3990287781],"type":"Point"}
}