{
  "type": "Feature",
  "properties": {
    "addr:full":"J Poligono, 4 Soria Soria 42005",
    "addr:housenumber":"4",
    "addr:postcode":"42005",
    "addr:street":"Poligono",
    "iso:country":"ES",
    "sg:address":"J Poligono, 4",
    "sg:city":"Soria",
    "sg:orig_category":"Muebles Y Accesorios Para Cocinas Y Cuartos De Ba\u00d1o (al Por Menor)",
    "sg:phone":"+34 975 23 35 40",
    "sg:postcode":"42005",
    "sg:province":"Soria",
    "wof:name":"Garces Garcia Jose Maria",
    "wof:placetype":"venue"
},
  "geometry": {"coordinates":[-2.4798560143,41.9514465332],"type":"Point"}
}