{
  "type": "Feature",
  "properties": {
    "addr:full":"Calle de Lepanto, 8 Port D'andratx Islas Baleares 07157",
    "addr:housenumber":"8",
    "addr:postcode":"07157",
    "addr:street":"Calle De Lepanto",
    "iso:country":"ES",
    "sg:address":"Calle de Lepanto, 8",
    "sg:city":"Port D'andratx",
    "sg:orig_category":"Ingenier\u00cda, Centros De Estudios (diversos)",
    "sg:phone":"+34 971 67 29 06",
    "sg:postcode":"07157",
    "sg:province":"Islas Baleares",
    "wof:name":"Alemany Bosch Jose",
    "wof:placetype":"venue"
},
  "geometry": {"coordinates":[2.3855702877,39.5420036316],"type":"Point"}
}