{
  "type": "Feature",
  "properties": {
    "iso:country":"ES",
    "sg:address":"Ctra Zubia (de La), 41",
    "sg:city":"Granada",
    "sg:orig_category":"Pintura Y Barniz (al Por Menor)",
    "sg:phone":"+34 958 13 39 00",
    "sg:postcode":"18008",
    "sg:province":"Granada",
    "wof:name":"Drogueria Hermanos Arenas S.l.",
    "wof:placetype":"venue"
},
  "geometry": {"coordinates":[-3.5939190388,37.15599823],"type":"Point"}
}