{
  "type": "Feature",
  "properties": {
    "addr:full":"Carrer de Bigai, 12 Barcelona Barcelona 08022",
    "addr:housenumber":"12",
    "addr:postcode":"08022",
    "addr:street":"Carrer De Bigai",
    "iso:country":"ES",
    "sg:address":"Carrer de Bigai, 12",
    "sg:city":"Barcelona",
    "sg:orig_category":"Iglesia Cat\u00d3lica",
    "sg:phone":"+34 934 17 82 36",
    "sg:postcode":"08022",
    "sg:province":"Barcelona",
    "wof:name":"Parroquia Santa Maria De La Bonanova",
    "wof:placetype":"venue"
},
  "geometry": {"coordinates":[2.1332540512,41.4054336548],"type":"Point"}
}