{
  "type": "Feature",
  "properties": {
    "iso:country":"ES",
    "sg:address":"Carr Bernat Alzina, 18",
    "sg:city":"Migjorn Gran",
    "sg:orig_category":"Quincaller\u00cda (al Por Menor)",
    "sg:phone":"+34 971 37 03 63",
    "sg:postcode":"07749",
    "sg:province":"Islas Baleares",
    "wof:name":"Pons Gomila Juan",
    "wof:placetype":"venue"
},
  "geometry": {"coordinates":[4.0503702164,39.9455299377],"type":"Point"}
}