{
  "type": "Feature",
  "properties": {
    "addr:full":"Poli Industrial Autopista Sur, Km. 0064,2 Castellon De La Plana Castell\u00f3n 12006",
    "addr:postcode":"12006",
    "addr:street":"Km. 0064,2",
    "iso:country":"ES",
    "sg:address":"Poli Industrial Autopista Sur, Km. 0064,2",
    "sg:city":"Castellon De La Plana",
    "sg:orig_category":"Cer\u00c1micas: Material Y Suministros",
    "sg:phone":"+34 964 24 23 57",
    "sg:postcode":"12006",
    "sg:province":"Castell\u00f3n",
    "wof:name":"Talleres Mecanicos De Castellon S.l.",
    "wof:placetype":"venue"
},
  "geometry": {"coordinates":[-0.1404139996,40.0213813782],"type":"Point"}
}