{
  "type": "Feature",
  "properties": {
    "addr:full":"Iturrama, 3 Iru\u00f1a Navarra 31007",
    "addr:housenumber":"3",
    "addr:postcode":"31007",
    "addr:street":"Iturrama",
    "iso:country":"ES",
    "sg:address":"Iturrama, 3",
    "sg:city":"Iru\u00f1a",
    "sg:orig_category":"Agencias De Trabajo Temporal",
    "sg:phone":"+34 948 17 01 66",
    "sg:postcode":"31007",
    "sg:province":"Navarra",
    "wof:name":"Synergie T.t. E.t.t. S.a.",
    "wof:placetype":"venue"
},
  "geometry": {"coordinates":[-1.6520609856,42.8044395447],"type":"Point"}
}