{
  "type": "Feature",
  "properties": {
    "iso:country":"ES",
    "sg:address":"Carr Ferrocarril D'alcoi, 38",
    "sg:city":"Gandia",
    "sg:orig_category":"Farmacias",
    "sg:phone":"+34 962 95 05 98",
    "sg:postcode":"46700",
    "sg:province":"Valencia",
    "wof:name":"Molto Femenia Carmen",
    "wof:placetype":"venue"
},
  "geometry": {"coordinates":[-0.1852419972,38.9650650024],"type":"Point"}
}