{
  "type": "Feature",
  "properties": {
    "addr:full":"Calle de Tinajas, 15 Palacios De Goda \u00c1vila 05297",
    "addr:housenumber":"15",
    "addr:postcode":"05297",
    "addr:street":"Calle De Tinajas;A\u0301Vila",
    "iso:country":"ES",
    "sg:address":"Calle de Tinajas, 15",
    "sg:city":"Palacios De Goda",
    "sg:orig_category":"Maquinaria Para Industrias Diversas",
    "sg:phone":"+34 920 30 80 18",
    "sg:postcode":"05297",
    "sg:province":"\u00c1vila",
    "wof:name":"Martin Ruiz Francisco",
    "wof:placetype":"venue"
},
  "geometry": {"coordinates":[-4.7861590385,41.1184501648],"type":"Point"}
}