{
  "type": "Feature",
  "properties": {
    "addr:full":"Calle de Sierra Espu\u00d1a, 4 Puente Tocinos Murcia 30006",
    "addr:housenumber":"4",
    "addr:postcode":"30006",
    "addr:street":"Calle De Sierra Espun\u0303A",
    "iso:country":"ES",
    "sg:address":"Calle de Sierra Espu\u00d1a, 4",
    "sg:city":"Puente Tocinos",
    "sg:orig_category":"Neum\u00c1ticos (fabricaci\u00d3n, Al Por Mayor)",
    "sg:phone":"+34 968 30 40 97",
    "sg:postcode":"30006",
    "sg:province":"Murcia",
    "wof:name":"Bridgestone Hispania S.a.",
    "wof:placetype":"venue"
},
  "geometry": {"coordinates":[-1.1009550095,37.9955940247],"type":"Point"}
}