{
  "type": "Feature",
  "properties": {
    "addr:full":"Calle de Real De La Jara (el), 24 Sevilla Sevilla 41008",
    "addr:postcode":"41008",
    "addr:street":"Calle De Real De La Jara El",
    "iso:country":"ES",
    "sg:address":"Calle de Real De La Jara (el), 24",
    "sg:city":"Sevilla",
    "sg:orig_category":"Carnicer\u00cdas, Carnicer\u00cdas",
    "sg:phone":"+34 954 95 94 74",
    "sg:postcode":"41008",
    "sg:province":"Sevilla",
    "wof:name":"Mu\u00f1oz Vega Eduardo",
    "wof:placetype":"venue"
},
  "geometry": {"coordinates":[-5.9745001793,37.4095573425],"type":"Point"}
}