{
  "type": "Feature",
  "properties": {
    "addr:full":"Calle de Mercurio, S/n Maracena Granada 18200",
    "addr:housenumber":"/ n",
    "addr:postcode":"18200",
    "addr:street":"Calle De Mercurio S",
    "iso:country":"ES",
    "sg:address":"Calle de Mercurio, S/n",
    "sg:city":"Maracena",
    "sg:orig_category":"Publicidad (soportes Y Gesti\u00d3n)",
    "sg:phone":"+34 958 80 67 98",
    "sg:postcode":"18200",
    "sg:province":"Granada",
    "wof:name":"Promociones Inmobiliarias Romero Victori",
    "wof:placetype":"venue"
},
  "geometry": {"coordinates":[-3.6366639137,37.2042007446],"type":"Point"}
}