{
  "type": "Feature",
  "properties": {
    "iso:country":"ES",
    "sg:address":"Avda Conde De Guadalhorce, S/n",
    "sg:city":"Aviles",
    "sg:orig_category":"Pescader\u00cdas (al Por Menor)",
    "sg:phone":"+34 985 52 27 16",
    "sg:postcode":"33401",
    "sg:province":"Asturias",
    "wof:name":"Marenri S.l.",
    "wof:placetype":"venue"
},
  "geometry": {"coordinates":[-5.9242491722,43.577583313],"type":"Point"}
}