{
  "type": "Feature",
  "properties": {
    "addr:full":"Plaz Mayor, 9 Baza Granada 18800",
    "addr:housenumber":"9",
    "addr:postcode":"18800",
    "addr:street":"Plaz Mayor",
    "iso:country":"ES",
    "sg:address":"Plaz Mayor, 9",
    "sg:city":"Baza",
    "sg:orig_category":"Bisuter\u00cda, Joyer\u00cda, Relojer\u00cda (al Por Menor)",
    "sg:phone":"+34 958 70 05 32",
    "sg:postcode":"18800",
    "sg:province":"Granada",
    "wof:name":"Valdivieso Alvarez Carmen",
    "wof:placetype":"venue"
},
  "geometry": {"coordinates":[-2.7737998962,37.490272522],"type":"Point"}
}