{
  "type": "Feature",
  "properties": {
    "iso:country":"ES",
    "sg:address":"Avda Pierre Cibie, 61",
    "sg:city":"Martos",
    "sg:orig_category":"Abogados",
    "sg:phone":"+34 953 55 00 07",
    "sg:postcode":"23600",
    "sg:province":"Ja\u00e9n",
    "wof:name":"Mu\u00f1oz Ortega Encarnacion",
    "wof:placetype":"venue"
},
  "geometry": {"coordinates":[-3.9743089676,37.7169303894],"type":"Point"}
}