{
  "type": "Feature",
  "properties": {
    "addr:full":"Calle de Amor De Dios, 25 Sevilla Sevilla 41002",
    "addr:housenumber":"25",
    "addr:postcode":"41002",
    "addr:street":"Calle De Amor De Dios",
    "iso:country":"ES",
    "sg:address":"Calle de Amor De Dios, 25",
    "sg:city":"Sevilla",
    "sg:orig_category":"Centros P\u00dablicos De Formaci\u00d3n Profesional Y T\u00c9cnica",
    "sg:phone":"+34 954 41 52 06",
    "sg:postcode":"41002",
    "sg:province":"Sevilla",
    "wof:name":"Colegio Oficial De Graduados Sociales De Sevilla",
    "wof:placetype":"venue"
},
  "geometry": {"coordinates":[-5.9945616722,37.3950233459],"type":"Point"}
}