{
  "type": "Feature",
  "properties": {
    "addr:full":"Calle de Badajoz, 2 Fuentes Leon Badajoz 06280",
    "addr:housenumber":"2",
    "addr:postcode":"06280",
    "addr:street":"Calle De Badajoz",
    "iso:country":"ES",
    "sg:address":"Calle de Badajoz, 2",
    "sg:city":"Fuentes Leon",
    "sg:orig_category":"Quincaller\u00cda (al Por Menor)",
    "sg:phone":"+34 924 72 44 25",
    "sg:postcode":"06280",
    "sg:province":"Badajoz",
    "wof:name":"Valero Hidalgo Miguel Antonio",
    "wof:placetype":"venue"
},
  "geometry": {"coordinates":[-6.5365748405,38.0706748962],"type":"Point"}
}