{
  "type": "Feature",
  "properties": {
    "addr:full":"Calle de Victoria Merida Y Piret, 2 Malaga M\u00e1laga 29004",
    "addr:housenumber":"2",
    "addr:postcode":"29004",
    "addr:street":"Calle De Victoria Merida Y Piret;Ma\u0301Laga",
    "iso:country":"ES",
    "sg:address":"Calle de Victoria Merida Y Piret, 2",
    "sg:city":"Malaga",
    "sg:orig_category":"Peluquer\u00cdas, Peluquer\u00cda Mixta",
    "sg:phone":"+34 952 24 05 35",
    "sg:postcode":"29004",
    "sg:province":"M\u00e1laga",
    "wof:name":"Pablo L. Peluqueros S.l.",
    "wof:placetype":"venue"
},
  "geometry": {"coordinates":[-4.4447607994,36.6939239502],"type":"Point"}
}