{
  "type": "Feature",
  "properties": {
    "addr:full":"Avda Pego, 70 Monte Pego Alicante 03780",
    "addr:housenumber":"70",
    "addr:postcode":"03780",
    "addr:street":"Avda Pego",
    "iso:country":"ES",
    "sg:address":"Avda Pego, 70",
    "sg:city":"Monte Pego",
    "sg:orig_category":"Promotores Constructores",
    "sg:phone":"+34 965 97 71 26",
    "sg:postcode":"03780",
    "sg:province":"Alicante",
    "wof:name":"Yvonne Krizon Silvia",
    "wof:placetype":"venue"
},
  "geometry": {"coordinates":[-0.0945188999,38.8265075684],"type":"Point"}
}