{
  "type": "Feature",
  "properties": {
    "addr:full":"Avda Democracia, 7 Madrid Madrid 28031",
    "addr:housenumber":"7",
    "addr:postcode":"madrid;28031",
    "addr:street":"Avda Democracia",
    "iso:country":"ES",
    "sg:address":"Avda Democracia, 7",
    "sg:city":"Madrid",
    "sg:orig_category":"Asesor\u00cda Sobre Comunicaci\u00d3n De Empresas",
    "sg:phone":"+34 913 01 31 56",
    "sg:postcode":"28031",
    "sg:province":"Madrid",
    "wof:name":"Estudios De Decisiones De Empresa S.a",
    "wof:placetype":"venue"
},
  "geometry": {"coordinates":[-3.6250369549,40.3839263916],"type":"Point"}
}