{
  "type": "Feature",
  "properties": {
    "addr:full":"Calle de Marques De Santa Cruz, 10 Oviedo Asturias 33007",
    "addr:housenumber":"10",
    "addr:postcode":"33007",
    "addr:street":"Calle De Marques De Santa Cruz",
    "iso:country":"ES",
    "sg:address":"Calle de Marques De Santa Cruz, 10",
    "sg:city":"Oviedo",
    "sg:orig_category":"Ingenier\u00cda, Centros De Estudios (diversos)",
    "sg:phone":"+34 985 22 03 96",
    "sg:postcode":"33007",
    "sg:province":"Asturias",
    "wof:name":"Asturagua S. A.",
    "wof:placetype":"venue"
},
  "geometry": {"coordinates":[-5.8496718407,43.3601799011],"type":"Point"}
}