{
  "type": "Feature",
  "properties": {
    "iso:country":"ES",
    "sg:address":"Cra. Nacional 230, Km. 0007,0",
    "sg:city":"Torrefarrera",
    "sg:orig_category":"Frutas, Legumbres Frescas Y Tempranas (al Por Menor)",
    "sg:phone":"+34 973 75 00 36",
    "sg:postcode":"25123",
    "sg:province":"Lleida",
    "wof:name":"Agrufruto S. A.",
    "wof:placetype":"venue"
},
  "geometry": {"coordinates":[0.5588787198,41.7045288086],"type":"Point"}
}