{
  "type": "Feature",
  "properties": {
    "addr:full":"Calle de Historiador Vedia, 23 Coru\u00d1a A Coru\u00f1a 15004",
    "addr:housenumber":"23",
    "addr:postcode":"15004",
    "addr:street":"Calle De Historiador Vedia;Corun\u0303A",
    "iso:country":"ES",
    "sg:address":"Calle de Historiador Vedia, 23",
    "sg:city":"Coru\u00d1a",
    "sg:orig_category":"Centros Empresariales",
    "sg:phone":"+34 981 25 78 01",
    "sg:postcode":"15004",
    "sg:province":"A Coru\u00f1a",
    "wof:name":"Sociedad Bibliografica De Galicia S.l.",
    "wof:placetype":"venue"
},
  "geometry": {"coordinates":[-8.4112501144,43.3641090393],"type":"Point"}
}