{
  "type": "Feature",
  "properties": {
    "iso:country":"ES",
    "sg:address":"Abarrio, 23",
    "sg:city":"Posada De Llanera-rondiella",
    "sg:orig_category":"Asilos De Ancianos. Centros Privados",
    "sg:phone":"+34 985 77 21 02",
    "sg:postcode":"33424",
    "sg:province":"Asturias",
    "wof:name":"Geriatrica Frabel S.l.",
    "wof:placetype":"venue"
},
  "geometry": {"coordinates":[-5.8513188362,43.4396247864],"type":"Point"}
}