{
  "type": "Feature",
  "properties": {
    "iso:country":"ES",
    "sg:address":"Avda Primero De Mayo, 54",
    "sg:city":"Palmas De Gran Canaria",
    "sg:orig_category":"Bazares, Art\u00cdculos De Limpieza Y De Cocina (al Por Menor)",
    "sg:phone":"+34 928 38 02 28",
    "sg:postcode":"35002",
    "sg:province":"Las Palmas",
    "wof:name":"Medina Rodriguez Elena",
    "wof:placetype":"venue"
},
  "geometry": {"coordinates":[-15.4198942184,28.1059513092],"type":"Point"}
}