{
  "type": "Feature",
  "properties": {
    "iso:country":"ES",
    "sg:address":"Avda Principe De Asturias, 10",
    "sg:city":"Villaviciosa Odon",
    "sg:orig_category":"Veh\u00cdculos De Ocasi\u00d3n",
    "sg:phone":"+34 916 16 95 53",
    "sg:postcode":"28670",
    "sg:province":"Madrid",
    "sg:website":"www.grupoecumotor.com",
    "wof:name":"Grupo Ecumotor S.l.",
    "wof:placetype":"venue"
},
  "geometry": {"coordinates":[-3.8907361031,40.3524246216],"type":"Point"}
}