{
  "type": "Feature",
  "properties": {
    "iso:country":"ES",
    "sg:address":"Calle de Eleuterio Quintanilla, 47",
    "sg:city":"Gijon",
    "sg:orig_category":"Venta, Colocaci\u00d3n De Tubos De Escape",
    "sg:phone":"+34 985 38 61 46",
    "sg:postcode":"33208",
    "sg:province":"Asturias",
    "wof:name":"Laviana Fernandez Aurelio",
    "wof:placetype":"venue"
},
  "geometry": {"coordinates":[-5.665242672,43.5310745239],"type":"Point"}
}