{
  "type": "Feature",
  "properties": {
    "addr:full":"Ctra Circunvalacion, S/n Recas Toledo 45211",
    "addr:postcode":"45211",
    "addr:street":"Ctra Circunvalacion S / N",
    "iso:country":"ES",
    "sg:address":"Ctra Circunvalacion, S/n",
    "sg:city":"Recas",
    "sg:orig_category":"Ba\u00d1os Y Duchas P\u00dablicos",
    "sg:phone":"+34 925 54 71 12",
    "sg:postcode":"45211",
    "sg:province":"Toledo",
    "wof:name":"Ayuntamiento De Recas",
    "wof:placetype":"venue"
},
  "geometry": {"coordinates":[-3.9921610355,40.0591125488],"type":"Point"}
}