{
  "type": "Feature",
  "properties": {
    "addr:full":"Carr Manuel De Falla, 5 Oliva Valencia 46780",
    "addr:housenumber":"5",
    "addr:postcode":"46780",
    "addr:street":"Carr Manuel De Falla",
    "iso:country":"ES",
    "sg:address":"Carr Manuel De Falla, 5",
    "sg:city":"Oliva",
    "sg:orig_category":"Electricidad: Instaladores",
    "sg:phone":"+34 962 96 30 42",
    "sg:postcode":"46780",
    "sg:province":"Valencia",
    "wof:name":"Llorca Santapau Jose",
    "wof:placetype":"venue"
},
  "geometry": {"coordinates":[-0.1147169992,38.9175872803],"type":"Point"}
}