{
  "type": "Feature",
  "properties": {
    "addr:full":"Calle de Peso (el), 43 Lucena C\u00f3rdoba 14900",
    "addr:housenumber":"43",
    "addr:postcode":"14900",
    "addr:street":"Calle De Peso El",
    "iso:country":"ES",
    "sg:address":"Calle de Peso (el), 43",
    "sg:city":"Lucena",
    "sg:orig_category":"Abogados",
    "sg:phone":"+34 957 50 13 59",
    "sg:postcode":"14900",
    "sg:province":"C\u00f3rdoba",
    "wof:name":"Osuna Ortiz Isidro",
    "wof:placetype":"venue"
},
  "geometry": {"coordinates":[-4.4886698723,37.40883255],"type":"Point"}
}