{
  "type": "Feature",
  "properties": {
    "iso:country":"ES",
    "sg:address":"Carrer de Lanzarote, 10",
    "sg:city":"Barcelona",
    "sg:orig_category":"Zapatos (al Por Menor)",
    "sg:phone":"+34 933 46 65 66",
    "sg:postcode":"08030",
    "sg:province":"Barcelona",
    "wof:name":"J.k. 29 Distribucion Calzado S.l.",
    "wof:placetype":"venue"
},
  "geometry": {"coordinates":[2.1901359558,41.4385566711],"type":"Point"}
}