{
  "type": "Feature",
  "properties": {
    "iso:country":"ES",
    "sg:address":"Urb Bouganvillas, 3",
    "sg:city":"Gracia",
    "sg:orig_category":"Peluquer\u00cdas, Peluquer\u00cda Mixta",
    "sg:phone":"+34 922 25 72 69",
    "sg:postcode":"38205",
    "sg:province":"Santa Cruz De Tenerife",
    "wof:name":"Joteteyu S.l.l.",
    "wof:placetype":"venue"
},
  "geometry": {"coordinates":[-16.298746109,28.4750785828],"type":"Point"}
}