{
  "type": "Feature",
  "properties": {
    "iso:country":"ES",
    "sg:address":"Calle de Tomas Lopez Torregrosa, 17",
    "sg:city":"Alacant",
    "sg:orig_category":"Panader\u00cdas, Panader\u00cdas",
    "sg:phone":"+34 965 21 44 41",
    "sg:postcode":"03002",
    "sg:province":"Alicante",
    "wof:name":"Espi Ramos Angel",
    "wof:placetype":"venue"
},
  "geometry": {"coordinates":[-0.4854820073,38.347782135],"type":"Point"}
}