{
  "type": "Feature",
  "properties": {
    "iso:country":"ES",
    "sg:address":"Calle de Angel Lozano, 9",
    "sg:city":"Alacant",
    "sg:orig_category":"Molduras, Junquillos, Listones Y Molduras Perforadas",
    "sg:phone":"+34 965 14 19 54",
    "sg:postcode":"03001",
    "sg:province":"Alicante",
    "wof:name":"Cuntin Gonzalez Pilar",
    "wof:placetype":"venue"
},
  "geometry": {"coordinates":[-0.4884566069,38.3460617065],"type":"Point"}
}