{
  "type": "Feature",
  "properties": {
    "iso:country":"ES",
    "sg:address":"Plaz San Esteban, 5",
    "sg:city":"Guadalajara",
    "sg:orig_category":"Pescader\u00cdas (al Por Menor)",
    "sg:phone":"+34 949 21 15 43",
    "sg:postcode":"19001",
    "sg:province":"Guadalajara",
    "wof:name":"Martinez De Lis Miguel Angel",
    "wof:placetype":"venue"
},
  "geometry": {"coordinates":[-3.1637349129,40.6339797974],"type":"Point"}
}