{
  "type": "Feature",
  "properties": {
    "iso:country":"ES",
    "sg:address":"Carrer de Muntaner, 340",
    "sg:city":"Barcelona",
    "sg:orig_category":"Centros Empresariales",
    "sg:phone":"+34 932 41 23 51",
    "sg:postcode":"08021",
    "sg:province":"Barcelona",
    "wof:name":"Manum Management Group S.l.",
    "wof:placetype":"venue"
},
  "geometry": {"coordinates":[2.1443920135,41.3981742859],"type":"Point"}
}