{
  "type": "Feature",
  "properties": {
    "addr:full":"Carretera De Aranda-palencia, Km. 0012,0 Ventosilla Burgos 09443",
    "addr:postcode":"09443",
    "addr:street":"Carretera De Aranda-Palencia Km. 0012,0 Ventosilla",
    "iso:country":"ES",
    "sg:address":"Carretera De Aranda-palencia, Km. 0012,0",
    "sg:city":"Ventosilla",
    "sg:classifiers":[
        {
            "category":"Manufacturing",
            "subcategory":"Building Materials",
            "type":"Manufacturing & Wholesale Goods"
        }
    ],
    "sg:phone":"+34 947 54 69 00",
    "sg:postcode":"09443",
    "sg:province":"Burgos",
    "sg:tags":[
        "bebidas",
        "para",
        "la",
        "de",
        "y",
        "equipo",
        "industria"
    ],
    "sg:website":"www.pradorey.com",
    "wof:name":"Real Sitio De Ventosilla S.a.",
    "wof:placetype":"venue"
},
  "geometry": {"coordinates":[-3.7957720757,41.7083969116],"type":"Point"}
}