{
  "type": "Feature",
  "properties": {
    "addr:full":"Pg Mare De Deu Del Coll, 119 Barcelona Barcelona 08032",
    "addr:housenumber":"119",
    "addr:postcode":"08032",
    "addr:street":"Pg Mare De Deu Del Coll",
    "iso:country":"ES",
    "sg:address":"Pg Mare De Deu Del Coll, 119",
    "sg:city":"Barcelona",
    "sg:orig_category":"Peluquer\u00cdas, Peluquer\u00cda Mixta",
    "sg:phone":"+34 934 20 60 56",
    "sg:postcode":"08032",
    "sg:province":"Barcelona",
    "wof:name":"Alfonsea Terron Eva Maria",
    "wof:placetype":"venue"
},
  "geometry": {"coordinates":[2.1503787041,41.4216346741],"type":"Point"}
}