{
  "type": "Feature",
  "properties": {
    "iso:country":"ES",
    "sg:address":"Calle de Barrio Nuevo, 65",
    "sg:city":"Caceres",
    "sg:orig_category":"Estancos",
    "sg:phone":"+34 927 24 45 54",
    "sg:postcode":"10004",
    "sg:province":"C\u00e1ceres",
    "wof:name":"Navarro Municio Salvador",
    "wof:placetype":"venue"
},
  "geometry": {"coordinates":[-6.3747215271,39.4787483215],"type":"Point"}
}