{
  "type": "Feature",
  "properties": {
    "addr:full":"Ctra Huelva-ayamonte, S/n Huelva Huelva 21002",
    "addr:housenumber":"s / n",
    "addr:postcode":"21002",
    "addr:street":"Ctra Huelva-Ayamonte",
    "iso:country":"ES",
    "sg:address":"Ctra Huelva-ayamonte, S/n",
    "sg:city":"Huelva",
    "sg:orig_category":"Distribuci\u00d3n De Petr\u00d3leo Y Derivados",
    "sg:phone":"+34 959 15 37 64",
    "sg:postcode":"21002",
    "sg:province":"Huelva",
    "wof:name":"Lorsa",
    "wof:placetype":"venue"
},
  "geometry": {"coordinates":[-6.9461240768,37.2834815979],"type":"Point"}
}