{
  "type": "Feature",
  "properties": {
    "iso:country":"ES",
    "sg:address":"Calle de Doctor Facundo Tomas, 11",
    "sg:city":"Bu\u00f1ol",
    "sg:orig_category":"Panader\u00cdas, Panader\u00cdas",
    "sg:phone":"+34 962 50 38 47",
    "sg:postcode":"46360",
    "sg:province":"Valencia",
    "wof:name":"Estelles Chapa Jesus Miguel",
    "wof:placetype":"venue"
},
  "geometry": {"coordinates":[-0.7905309796,39.4233474731],"type":"Point"}
}