{
  "type": "Feature",
  "properties": {
    "iso:country":"ES",
    "sg:address":"Calle de Santa Barbara, 10",
    "sg:city":"Cangas Narcea",
    "sg:orig_category":"Negocio De Materiales De Construcci\u00d3n",
    "sg:phone":"+34 985 81 35 00",
    "sg:postcode":"33800",
    "sg:province":"Asturias",
    "wof:name":"Asfalfos Cangas S.l.",
    "wof:placetype":"venue"
},
  "geometry": {"coordinates":[-6.5485620499,43.1783828735],"type":"Point"}
}