{
  "type": "Feature",
  "properties": {
    "addr:full":"Calle de Sinceridad, 33 Sevilla Sevilla 41006",
    "addr:housenumber":"33",
    "addr:postcode":"41006",
    "addr:street":"Calle De Sinceridad",
    "iso:country":"ES",
    "sg:address":"Calle de Sinceridad, 33",
    "sg:city":"Sevilla",
    "sg:orig_category":"Pescader\u00cdas (al Por Menor)",
    "sg:phone":"+34 954 52 99 97",
    "sg:postcode":"41006",
    "sg:province":"Sevilla",
    "wof:name":"Viana Rodriguez Victor Manuel",
    "wof:placetype":"venue"
},
  "geometry": {"coordinates":[-5.9297327995,37.3713798523],"type":"Point"}
}