{
  "type": "Feature",
  "properties": {
    "addr:full":"Rua Real, 8 Ponteareas Pontevedra 36860",
    "addr:housenumber":"8",
    "addr:postcode":"36860",
    "addr:street":"Rua Real",
    "iso:country":"ES",
    "sg:address":"Rua Real, 8",
    "sg:city":"Ponteareas",
    "sg:orig_category":"Farmacias",
    "sg:phone":"+34 986 64 08 32",
    "sg:postcode":"36860",
    "sg:province":"Pontevedra",
    "wof:name":"Candeira Alonso Maria Dolores",
    "wof:placetype":"venue"
},
  "geometry": {"coordinates":[-8.5059213638,42.1772727966],"type":"Point"}
}