{
  "type": "Feature",
  "properties": {
    "addr:full":"Calle de Fray Marcos De Niza, 11 Sevilla Sevilla 41007",
    "addr:housenumber":"11",
    "addr:postcode":"41007",
    "addr:street":"Calle De Fray Marcos De Niza",
    "iso:country":"ES",
    "sg:address":"Calle de Fray Marcos De Niza, 11",
    "sg:city":"Sevilla",
    "sg:orig_category":"Arquitectos",
    "sg:phone":"+34 954 51 57 36",
    "sg:postcode":"41007",
    "sg:province":"Sevilla",
    "wof:name":"Mu\u00f1oz Mu\u00f1oz Juan Luis",
    "wof:placetype":"venue"
},
  "geometry": {"coordinates":[-5.954100132,37.4029006958],"type":"Point"}
}