{
  "type": "Feature",
  "properties": {
    "iso:country":"ES",
    "sg:address":"Calle de Hermanos Del Rio Rodriguez, 2",
    "sg:city":"Sevilla",
    "sg:orig_category":"Maquinaria Para Industrias Diversas",
    "sg:phone":"+34 954 35 25 61",
    "sg:postcode":"41009",
    "sg:province":"Sevilla",
    "wof:name":"Atracciones Gutierrez Ba\u00f1uls S.l.",
    "wof:placetype":"venue"
},
  "geometry": {"coordinates":[-5.9830198288,37.4025917053],"type":"Point"}
}