{
  "type": "Feature",
  "properties": {
    "iso:country":"ES",
    "sg:address":"Calle de Sargento Provisional, 2",
    "sg:city":"Santa Cruz De Tenerife",
    "sg:orig_category":"Institutos De Belleza",
    "sg:phone":"+34 922 65 61 68",
    "sg:postcode":"38010",
    "sg:province":"Santa Cruz De Tenerife",
    "wof:name":"Perez Machado Maria Del Carmen",
    "wof:placetype":"venue"
},
  "geometry": {"coordinates":[-16.2874145508,28.4523582458],"type":"Point"}
}