{
  "type": "Feature",
  "properties": {
    "iso:country":"ES",
    "sg:address":"Plaz Santiago Arolo Vi\u00d1as, 5",
    "sg:city":"Badajoz",
    "sg:orig_category":"Carnicer\u00cdas, Carnicer\u00cdas",
    "sg:phone":"+34 924 25 45 86",
    "sg:postcode":"06008",
    "sg:province":"Badajoz",
    "wof:name":"Garcia Pulido Jose Maria",
    "wof:placetype":"venue"
},
  "geometry": {"coordinates":[-6.6745042801,38.9741096497],"type":"Point"}
}