{
  "type": "Feature",
  "properties": {
    "addr:full":"Calle de Juan Xxiii, 9 Santander Cantabria 39001",
    "addr:housenumber":"9",
    "addr:postcode":"39001",
    "addr:street":"Calle De Juan Xxiii",
    "iso:country":"ES",
    "sg:address":"Calle de Juan Xxiii, 9",
    "sg:city":"Santander",
    "sg:orig_category":"Papeler\u00cdas, Librer\u00cdas",
    "sg:phone":"+34 942 23 51 97",
    "sg:postcode":"39001",
    "sg:province":"Cantabria",
    "wof:name":"Bellido Angulo Silvia",
    "wof:placetype":"venue"
},
  "geometry": {"coordinates":[-3.8127200603,43.4650268555],"type":"Point"}
}