{
  "type": "Feature",
  "properties": {
    "addr:full":"Calle de Doctor Jose Altolaguirre, 5 Cordoba C\u00f3rdoba 14004",
    "addr:housenumber":"5",
    "addr:postcode":"14004",
    "addr:street":"Calle De Doctor Jose Altolaguirre;Co\u0301Rdoba",
    "iso:country":"ES",
    "sg:address":"Calle de Doctor Jose Altolaguirre, 5",
    "sg:city":"Cordoba",
    "sg:orig_category":"Molduras, Junquillos, Listones Y Molduras Perforadas",
    "sg:phone":"+34 957 29 09 29",
    "sg:postcode":"14004",
    "sg:province":"C\u00f3rdoba",
    "wof:name":"Nieto Ariza Antonio",
    "wof:placetype":"venue"
},
  "geometry": {"coordinates":[-4.7934913635,37.872341156],"type":"Point"}
}