{
  "type": "Feature",
  "properties": {
    "iso:country":"ES",
    "sg:address":"Avda Casalduch, 16",
    "sg:city":"Castellon",
    "sg:orig_category":"M\u00c9dicos: Cardiolog\u00cda Y Afecciones Cardiovasculares",
    "sg:phone":"+34 964 22 76 07",
    "sg:postcode":"12005",
    "sg:province":"Castell\u00f3n",
    "wof:name":"Moreno Rosado Juan",
    "wof:placetype":"venue"
},
  "geometry": {"coordinates":[-0.0367010012,39.9812583923],"type":"Point"}
}