{
  "type": "Feature",
  "properties": {
    "iso:country":"ES",
    "sg:address":"Plaz Martires, 5",
    "sg:city":"Almonacid Toledo",
    "sg:orig_category":"Cajas Para Embalar",
    "sg:phone":"+34 925 31 40 75",
    "sg:postcode":"45420",
    "sg:province":"Toledo",
    "sg:website":"www.cajaruraldetoledo.es",
    "wof:name":"Caja Rural Provincial De Toledo",
    "wof:placetype":"venue"
},
  "geometry": {"coordinates":[-3.8545980453,39.7551574707],"type":"Point"}
}