{
  "type": "Feature",
  "properties": {
    "iso:country":"ES",
    "sg:address":"Calle de Padre Saturnino Lopez Novoa, 37",
    "sg:city":"Sig\u00fcenza",
    "sg:orig_category":"M\u00c1rmoles, Granitos Y Piedras Naturales",
    "sg:phone":"+34 949 39 03 74",
    "sg:postcode":"19250",
    "sg:province":"Guadalajara",
    "wof:name":"Alonso Merino Alejandro",
    "wof:placetype":"venue"
},
  "geometry": {"coordinates":[-2.6465668678,41.0644340515],"type":"Point"}
}