{
  "type": "Feature",
  "properties": {
    "addr:full":"Pg Taulat, 187 Barcelona Barcelona 08005",
    "addr:housenumber":"187",
    "addr:postcode":"08005",
    "addr:street":"Pg Taulat",
    "iso:country":"ES",
    "sg:address":"Pg Taulat, 187",
    "sg:city":"Barcelona",
    "sg:orig_category":"Protecci\u00d3n Contra Incendios: Material, Instalaci\u00d3n, Mantenimiento",
    "sg:phone":"+34 932 66 20 67",
    "sg:postcode":"08005",
    "sg:province":"Barcelona",
    "wof:name":"Pefipresa S. A.",
    "wof:placetype":"venue"
},
  "geometry": {"coordinates":[2.2083990574,41.4018516541],"type":"Point"}
}