{
  "type": "Feature",
  "properties": {
    "addr:full":"Calle de Lertxuna, 15 Irun Guip\u00f9zcoa 20305",
    "addr:housenumber":"15",
    "addr:postcode":"20305",
    "addr:street":"Calle De Lertxuna;Guipu\u0300Zcoa",
    "iso:country":"ES",
    "sg:address":"Calle de Lertxuna, 15",
    "sg:city":"Irun",
    "sg:orig_category":"Venta, Alquiler De Toldos",
    "sg:phone":"+34 943 53 58 90",
    "sg:postcode":"20305",
    "sg:province":"Guip\u00f9zcoa",
    "wof:name":"Obras Y Construcciones Esycu S.l.",
    "wof:placetype":"venue"
},
  "geometry": {"coordinates":[-1.8146899939,43.3382949829],"type":"Point"}
}