{
  "type": "Feature",
  "properties": {
    "addr:full":"Avda Felipe Iv De, 7 Donostia-san Sebastian Guip\u00f9zcoa 20011",
    "addr:housenumber":"7",
    "addr:postcode":"20011",
    "addr:street":"Avda Felipe Iv De",
    "iso:country":"ES",
    "sg:address":"Avda Felipe Iv De, 7",
    "sg:city":"Donostia-san Sebastian",
    "sg:orig_category":"Venta, Instalaci\u00d3n, Reparaci\u00d3n De Antenas Para Televisi\u00d3n",
    "sg:phone":"+34 943 44 41 78",
    "sg:postcode":"20011",
    "sg:province":"Guip\u00f9zcoa",
    "wof:name":"Comunicaciones Telsat S.l.",
    "wof:placetype":"venue"
},
  "geometry": {"coordinates":[-1.9755740166,43.305896759],"type":"Point"}
}