{
  "type": "Feature",
  "properties": {
    "iso:country":"ES",
    "sg:address":"Calle de Perez Galdos, 3",
    "sg:city":"Guia Isora",
    "sg:orig_category":"Florister\u00cdas",
    "sg:phone":"+34 922 85 05 06",
    "sg:postcode":"38680",
    "sg:province":"Santa Cruz De Tenerife",
    "wof:name":"Martin Perez Maria De Los Angeles",
    "wof:placetype":"venue"
},
  "geometry": {"coordinates":[-16.7820930481,28.2130641937],"type":"Point"}
}