{
  "type": "Feature",
  "properties": {
    "addr:full":"Calle de Horno Marina, 2 Granada Granada 18001",
    "addr:housenumber":"2",
    "addr:postcode":"18001",
    "addr:street":"Calle De Horno Marina",
    "iso:country":"ES",
    "sg:address":"Calle de Horno Marina, 2",
    "sg:city":"Granada",
    "sg:orig_category":"Servicios De Telecomunicaciones",
    "sg:phone":"+34 958 27 33 70",
    "sg:postcode":"18001",
    "sg:province":"Granada",
    "wof:name":"Intercomunicaciones Al-andalus S.l.",
    "wof:placetype":"venue"
},
  "geometry": {"coordinates":[-3.6008489132,37.1777000427],"type":"Point"}
}