{
  "type": "Feature",
  "properties": {
    "addr:full":"Calle de Orion, 6 Gracia Santa Cruz De Tenerife 38295",
    "addr:housenumber":"6",
    "addr:postcode":"38295",
    "addr:street":"Calle De Orion",
    "iso:country":"ES",
    "sg:address":"Calle de Orion, 6",
    "sg:city":"Gracia",
    "sg:orig_category":"Confecci\u00d3n De Trajes Para Se\u00d1oras",
    "sg:phone":"+34 922 63 14 32",
    "sg:postcode":"38295",
    "sg:province":"Santa Cruz De Tenerife",
    "wof:name":"Inoan S.l.",
    "wof:placetype":"venue"
},
  "geometry": {"coordinates":[-16.3025226593,28.4732723236],"type":"Point"}
}