{
  "type": "Feature",
  "properties": {
    "iso:country":"ES",
    "sg:address":"Rua Gran Via, 168",
    "sg:city":"Carballo",
    "sg:orig_category":"Limpieza Con Chorro De Arena Y Con Granalla, Pulido",
    "sg:phone":"+34 981 70 08 00",
    "sg:postcode":"15100",
    "sg:province":"La Coru\u00f1a",
    "wof:name":"Limpiezas Berganti\u00f1os S.l.",
    "wof:placetype":"venue"
},
  "geometry": {"coordinates":[-8.6860876083,43.2186393738],"type":"Point"}
}