{
  "type": "Feature",
  "properties": {
    "iso:country":"ES",
    "sg:address":"Calle de Betanzos, 3",
    "sg:city":"Alcorcon",
    "sg:orig_category":"Molduras, Junquillos, Listones Y Molduras Perforadas",
    "sg:phone":"+34 916 12 51 01",
    "sg:postcode":"28925",
    "sg:province":"Madrid",
    "wof:name":"Parra Collado Jose Luis",
    "wof:placetype":"venue"
},
  "geometry": {"coordinates":[-3.8123567104,40.3566322327],"type":"Point"}
}