{
  "type": "Feature",
  "properties": {
    "addr:full":"Ctra Murcia, Km. 0052,5 Elche Alicante 03205",
    "addr:postcode":"03205",
    "addr:street":"Ctra Murcia Km. 0052,5",
    "iso:country":"ES",
    "sg:address":"Ctra Murcia, Km. 0052,5",
    "sg:city":"Elche",
    "sg:orig_category":"Acero: Productos Sider\u00dargicos Y Transformados (fabricaci\u00d3n, Negocio)",
    "sg:phone":"+34 965 43 94 65",
    "sg:postcode":"03205",
    "sg:province":"Alicante",
    "wof:name":"Aceros Y Bronces Torres S.l.",
    "wof:placetype":"venue"
},
  "geometry": {"coordinates":[-0.7248290777,38.2596321106],"type":"Point"}
}