{
  "type": "Feature",
  "properties": {
    "iso:country":"ES",
    "sg:address":"Calle de Isabel Colbrand, S/n",
    "sg:city":"Madrid",
    "sg:orig_category":"Electricidad, Electr\u00d3nica: Material Y Suministros (al Por Mayor)",
    "sg:phone":"+34 913 58 86 92",
    "sg:postcode":"28050",
    "sg:province":"Madrid",
    "wof:name":"J H Rorden Y Compa\u00d1ia S.a.",
    "wof:placetype":"venue"
},
  "geometry": {"coordinates":[-3.6789939404,40.5098991394],"type":"Point"}
}