{
  "type": "Feature",
  "properties": {
    "addr:full":"Calle de San Segundo, 8 Avila \u00c1vila 05001",
    "addr:housenumber":"8",
    "addr:postcode":"05001",
    "addr:street":"Calle De San Segundo;A\u0301Vila",
    "iso:country":"ES",
    "sg:address":"Calle de San Segundo, 8",
    "sg:city":"Avila",
    "sg:orig_category":"Ropa Para Ni\u00d1os (al Por Menor)",
    "sg:phone":"+34 920 22 33 20",
    "sg:postcode":"05001",
    "sg:province":"\u00c1vila",
    "wof:name":"Dominguez Mijan Manuel",
    "wof:placetype":"venue"
},
  "geometry": {"coordinates":[-4.6965579987,40.6548194885],"type":"Point"}
}