{
  "type": "Feature",
  "properties": {
    "addr:full":"Pg Montjuic, 46 Barcelona Barcelona 08004",
    "addr:housenumber":"46",
    "addr:postcode":"08004",
    "addr:street":"Pg Montjuic",
    "iso:country":"ES",
    "sg:address":"Pg Montjuic, 46",
    "sg:city":"Barcelona",
    "sg:orig_category":"Papeler\u00cdas, Librer\u00cdas",
    "sg:phone":"+34 933 24 80 04",
    "sg:postcode":"08004",
    "sg:province":"Barcelona",
    "wof:name":"Pepa Paper Bcn S.l.",
    "wof:placetype":"venue"
},
  "geometry": {"coordinates":[2.1696720123,41.3719863892],"type":"Point"}
}