{
  "type": "Feature",
  "properties": {
    "addr:full":"Carrer de Menendez Pelayo, 21 Senia Tarragona 43560",
    "addr:housenumber":"21",
    "addr:postcode":"43560",
    "addr:street":"Carrer De Menendez Pelayo",
    "iso:country":"ES",
    "sg:address":"Carrer de Menendez Pelayo, 21",
    "sg:city":"Senia",
    "sg:orig_category":"Empresas De Carpinter\u00cda De Madera",
    "sg:phone":"+34 977 57 02 95",
    "sg:postcode":"43560",
    "sg:province":"Tarragona",
    "wof:name":"Baranes Tornejades Belvi S.l.",
    "wof:placetype":"venue"
},
  "geometry": {"coordinates":[0.284525007,40.63306427],"type":"Point"}
}