{
  "type": "Feature",
  "properties": {
    "addr:full":"Carrer de Consell De Cent, 90 Barcelona Barcelona 08015",
    "addr:housenumber":"90",
    "addr:postcode":"08015",
    "addr:street":"Carrer De Consell De Cent",
    "iso:country":"ES",
    "sg:address":"Carrer de Consell De Cent, 90",
    "sg:city":"Barcelona",
    "sg:orig_category":"Centros Pms (psico",
    "sg:phone":"+34 934 24 25 89",
    "sg:postcode":"08015",
    "sg:province":"Barcelona",
    "sg:website":"www.towandadreams.com",
    "wof:name":"Towanda Dreams S.l",
    "wof:placetype":"venue"
},
  "geometry": {"coordinates":[2.1511530876,41.3799552917],"type":"Point"}
}