{
  "type": "Feature",
  "properties": {
    "iso:country":"ES",
    "sg:address":"Calle de Alava, 4",
    "sg:city":"San Sebastian De Los Reyes",
    "sg:orig_category":"Electrodom\u00c9sticos (al Por Menor)",
    "sg:phone":"+34 916 54 63 86",
    "sg:postcode":"28700",
    "sg:province":"Madrid",
    "wof:name":"Green Cat S.a.",
    "wof:placetype":"venue"
},
  "geometry": {"coordinates":[-3.6374874115,40.55286026],"type":"Point"}
}