{
  "type": "Feature",
  "properties": {
    "iso:country":"ES",
    "sg:address":"Pol Ind La Paz, S/n",
    "sg:city":"Maracena",
    "sg:orig_category":"Adaptaciones, Acondicionamientos Especiales Para Veh\u00cdculos, Veh\u00cdculos Industriales",
    "sg:phone":"+34 958 41 00 08",
    "sg:postcode":"18200",
    "sg:province":"Granada",
    "wof:name":"Talleres Palma Y Aporta S.l.",
    "wof:placetype":"venue"
},
  "geometry": {"coordinates":[-3.6371719837,37.2051467896],"type":"Point"}
}