{
  "type": "Feature",
  "properties": {
    "iso:country":"ES",
    "sg:address":"Carrer de L'almirall Churruca, 5",
    "sg:city":"Barcelona",
    "sg:orig_category":"Vinos Y Licores (venta Al Por Menor)",
    "sg:phone":"+34 932 21 66 70",
    "sg:postcode":"08003",
    "sg:province":"Barcelona",
    "wof:name":"Ferrerons Ferran Ramon",
    "wof:placetype":"venue"
},
  "geometry": {"coordinates":[2.1898117065,41.3788986206],"type":"Point"}
}