{
  "type": "Feature",
  "properties": {
    "addr:full":"Avda Generalisimo - Curtis-estacion, 13 Curtis-estacion La Coru\u00f1a 15379",
    "addr:housenumber":"13",
    "addr:postcode":"15379",
    "addr:street":"Avda Generalisimo Curtis-Estacion;La Corun\u0303A",
    "iso:country":"ES",
    "sg:address":"Avda Generalisimo - Curtis-estacion, 13",
    "sg:city":"Curtis-estacion",
    "sg:orig_category":"Reposter\u00cdas",
    "sg:phone":"+34 981 78 60 34",
    "sg:postcode":"15379",
    "sg:province":"La Coru\u00f1a",
    "wof:name":"Lopez Estraviz Manuel",
    "wof:placetype":"venue"
},
  "geometry": {"coordinates":[-8.1419210434,43.1253395081],"type":"Point"}
}