{
  "type": "Feature",
  "properties": {
    "iso:country":"ES",
    "sg:address":"Pla\u00c7 Maria Aurelia Capmany, 5",
    "sg:city":"Lleida",
    "sg:orig_category":"Agentes Generales De Seguros",
    "sg:phone":"+34 973 26 05 04",
    "sg:postcode":"25005",
    "sg:province":"Lleida",
    "wof:name":"Miranda & Serrat Associats S.l.",
    "wof:placetype":"venue"
},
  "geometry": {"coordinates":[0.6279799938,41.6270713806],"type":"Point"}
}