{
  "type": "Feature",
  "properties": {
    "iso:country":"ES",
    "sg:address":"Ctra De La Junta, S/n",
    "sg:city":"Higuera Sierra",
    "sg:orig_category":"Producci\u00d3n, Distribuci\u00d3n De Gas Butano Y Propano",
    "sg:phone":"+34 959 19 62 34",
    "sg:postcode":"21220",
    "sg:province":"Huelva",
    "wof:name":"Ramos Galvez Maria Josefa",
    "wof:placetype":"venue"
},
  "geometry": {"coordinates":[-6.4506020546,37.8369140625],"type":"Point"}
}