{
  "type": "Feature",
  "properties": {
    "iso:country":"ES",
    "sg:address":"Carrer de Proven\u00c7a, 66",
    "sg:city":"Barcelona",
    "sg:orig_category":"Art\u00cdculos De Decoraci\u00d3n (fabricaci\u00d3n Y Al Por Mayor)",
    "sg:phone":"+34 934 10 02 37",
    "sg:postcode":"08029",
    "sg:province":"Barcelona",
    "wof:name":"Acu\u00f1a Silva Rene Rodrigo",
    "wof:placetype":"venue"
},
  "geometry": {"coordinates":[2.1467041969,41.3835945129],"type":"Point"}
}