{
  "type": "Feature",
  "properties": {
    "iso:country":"ES",
    "sg:address":"Calle de Pablo Picasso, S/n",
    "sg:city":"Jumilla",
    "sg:orig_category":"Electricidad: Instaladores",
    "sg:phone":"+34 968 75 78 30",
    "sg:postcode":"30520",
    "sg:province":"Murcia",
    "wof:name":"Lozano Tomas Antonio",
    "wof:placetype":"venue"
},
  "geometry": {"coordinates":[-1.3174940348,38.4747009277],"type":"Point"}
}