{
  "type": "Feature",
  "properties": {
    "addr:full":"Avda America, 65 Zaragoza Zaragoza 50007",
    "addr:housenumber":"65",
    "addr:postcode":"50007",
    "addr:street":"Avda America",
    "iso:country":"ES",
    "sg:address":"Avda America, 65",
    "sg:city":"Zaragoza",
    "sg:orig_category":"Alimentaci\u00d3n General (al Por Menor)",
    "sg:phone":"+34 976 38 51 18",
    "sg:postcode":"50007",
    "sg:province":"Zaragoza",
    "wof:name":"Frutos Secos El Rincon S.l.",
    "wof:placetype":"venue"
},
  "geometry": {"coordinates":[-0.8858559728,41.6296768188],"type":"Point"}
}