{
  "type": "Feature",
  "properties": {
    "iso:country":"ES",
    "sg:address":"Rua Castelao, 13",
    "sg:city":"Grove",
    "sg:orig_category":"Panader\u00cdas, Panader\u00cdas",
    "sg:phone":"+34 986 73 03 18",
    "sg:postcode":"36980",
    "sg:province":"Pontevedra",
    "wof:name":"Gonzalez Fernandez Carmen",
    "wof:placetype":"venue"
},
  "geometry": {"coordinates":[-8.8597536087,42.4916725159],"type":"Point"}
}