{
  "type": "Feature",
  "properties": {
    "iso:country":"ES",
    "sg:address":"Ctra Pego (de), 41",
    "sg:city":"Oliva",
    "sg:orig_category":"Reposter\u00cdas",
    "sg:phone":"+34 962 85 01 28",
    "sg:postcode":"46780",
    "sg:province":"Valencia",
    "wof:name":"Montagud Ciscar Antonio",
    "wof:placetype":"venue"
},
  "geometry": {"coordinates":[-0.114060998,38.9135398865],"type":"Point"}
}