{
  "type": "Feature",
  "properties": {
    "addr:full":"Calle de Ramon Y Cajal, 101 Calzada Oropesa Toledo 45580",
    "addr:housenumber":"101",
    "addr:postcode":"45580",
    "addr:street":"Calle De Ramon Y Cajal",
    "iso:country":"ES",
    "sg:address":"Calle de Ramon Y Cajal, 101",
    "sg:city":"Calzada Oropesa",
    "sg:orig_category":"Plomeros",
    "sg:phone":"+34 925 43 53 26",
    "sg:postcode":"45580",
    "sg:province":"Toledo",
    "wof:name":"Ramos Igual Vicente",
    "wof:placetype":"venue"
},
  "geometry": {"coordinates":[-5.3104839325,39.8948860168],"type":"Point"}
}