{
  "type": "Feature",
  "properties": {
    "addr:full":"Calle de San Bartolome, 7 Petrer Alicante 03610",
    "addr:housenumber":"7",
    "addr:postcode":"03610",
    "addr:street":"Calle De San Bartolome",
    "iso:country":"ES",
    "sg:address":"Calle de San Bartolome, 7",
    "sg:city":"Petrer",
    "sg:orig_category":"Asociaciones Y Clubs Deportivos",
    "sg:phone":"+34 965 37 02 81",
    "sg:postcode":"03610",
    "sg:province":"Alicante",
    "wof:name":"Sociedad De Cazadores La Union",
    "wof:placetype":"venue"
},
  "geometry": {"coordinates":[-0.7721269727,38.4847640991],"type":"Point"}
}