{
  "type": "Feature",
  "properties": {
    "iso:country":"ES",
    "sg:address":"Carr Lluis Millet, 39",
    "sg:city":"Lleida",
    "sg:orig_category":"Empresas De Carpinter\u00cda De Madera",
    "sg:phone":"+34 973 28 96 93",
    "sg:postcode":"25003",
    "sg:province":"Lleida",
    "wof:name":"Carpinteria Delmar S.l.",
    "wof:placetype":"venue"
},
  "geometry": {"coordinates":[0.6117659807,41.6115379333],"type":"Point"}
}