{
  "type": "Feature",
  "properties": {
    "iso:country":"ES",
    "sg:address":"Calle de I\u00d1aki Deuna, 33",
    "sg:city":"Ondarroa",
    "sg:orig_category":"Institutos De Belleza",
    "sg:phone":"+34 946 83 03 95",
    "sg:postcode":"48700",
    "sg:province":"Vizcaya",
    "wof:name":"Alejandra Burga\u00f1a Aldarondo-laura Burga\u00f1a Aldarondo Cdad",
    "wof:placetype":"venue"
},
  "geometry": {"coordinates":[-2.4266550541,43.3198699951],"type":"Point"}
}