{
  "type": "Feature",
  "properties": {
    "iso:country":"ES",
    "sg:address":"C/ Santa Margarida, 31",
    "sg:city":"Vilobi D'onyar",
    "sg:orig_category":"Comerciantes Al Por Mayor De Vinos, Licores Y Alcoholes",
    "sg:phone":"+34 972 47 36 04",
    "sg:postcode":"17185",
    "sg:province":"Girona",
    "wof:name":"Celler Raimada S.l.",
    "wof:placetype":"venue"
},
  "geometry": {"coordinates":[2.8187398911,41.9808616638],"type":"Point"}
}