{
  "type": "Feature",
  "properties": {
    "addr:full":"Carrer de Violeta La, 6 Valls Tarragona 43800",
    "addr:housenumber":"6",
    "addr:postcode":"43800",
    "addr:street":"Carrer De Violeta La",
    "iso:country":"ES",
    "sg:address":"Carrer de Violeta La, 6",
    "sg:city":"Valls",
    "sg:orig_category":"Agencias Y Asesores De Publicidad",
    "sg:phone":"+34 977 61 43 57",
    "sg:postcode":"43800",
    "sg:province":"Tarragona",
    "wof:name":"Imatge 9 S.l.",
    "wof:placetype":"venue"
},
  "geometry": {"coordinates":[1.2461429834,41.2817611694],"type":"Point"}
}