{
  "type": "Feature",
  "properties": {
    "addr:full":"Calle de Pelayo, 22 San Vicente Del Raspeig-sant Vicent Del Raspeig Alicante 03690",
    "addr:housenumber":"22",
    "addr:postcode":"03690",
    "addr:street":"Calle De Pelayo",
    "iso:country":"ES",
    "sg:address":"Calle de Pelayo, 22",
    "sg:city":"San Vicente Del Raspeig-sant Vicent Del Raspeig",
    "sg:orig_category":"Supermercados Y Hipermercados",
    "sg:phone":"+34 965 66 98 64",
    "sg:postcode":"03690",
    "sg:province":"Alicante",
    "wof:name":"Supermercado Haygon S.l.",
    "wof:placetype":"venue"
},
  "geometry": {"coordinates":[-0.5182074904,38.395198822],"type":"Point"}
}