{
  "type": "Feature",
  "properties": {
    "iso:country":"ES",
    "sg:address":"Alam Colon, 17",
    "sg:city":"Malaga",
    "sg:orig_category":"Psic\u00d3logos",
    "sg:phone":"+34 952 21 77 76",
    "sg:postcode":"29001",
    "sg:province":"M\u00e1laga",
    "wof:name":"Mena Dimas Rocio",
    "wof:placetype":"venue"
},
  "geometry": {"coordinates":[-4.4240989685,36.7141799927],"type":"Point"}
}