{
  "type": "Feature",
  "properties": {
    "iso:country":"ES",
    "sg:address":"Trva Sal, 2",
    "sg:city":"Toledo",
    "sg:orig_category":"Florister\u00cdas",
    "sg:phone":"+34 925 22 28 47",
    "sg:postcode":"45001",
    "sg:province":"Toledo",
    "sg:website":"www.paginasamarillas.es",
    "wof:name":"Vielsa Aguilera Alicia",
    "wof:placetype":"venue"
},
  "geometry": {"coordinates":[-4.0233569145,39.8585357666],"type":"Point"}
}