{
  "type": "Feature",
  "properties": {
    "addr:full":"Plaz Plaza Mayor, 19 Trujillo C\u00e1ceres 10200",
    "addr:postcode":"10200",
    "addr:street":"Mayor;Trujillo Ca\u0301Ceres",
    "iso:country":"ES",
    "sg:address":"Plaz Plaza Mayor, 19",
    "sg:city":"Trujillo",
    "sg:orig_category":"Tiendas De Grano, Frutas Y Legumbres Secas (al Por Menor)",
    "sg:phone":"+34 927 32 19 11",
    "sg:postcode":"10200",
    "sg:province":"C\u00e1ceres",
    "wof:name":"Mellado Rubio Maria Del Carmen",
    "wof:placetype":"venue"
},
  "geometry": {"coordinates":[-5.8758888245,39.4581871033],"type":"Point"}
}