{
  "type": "Feature",
  "properties": {
    "addr:full":"Calle de Campo (del), 52 Almansa Albacete 02640",
    "addr:postcode":"02640",
    "addr:street":"Calle De Campo Del",
    "iso:country":"ES",
    "sg:address":"Calle de Campo (del), 52",
    "sg:city":"Almansa",
    "sg:orig_category":"Confecci\u00d3n De Zapatos",
    "sg:phone":"+34 967 31 15 45",
    "sg:postcode":"02640",
    "sg:province":"Albacete",
    "wof:name":"Toquelados Deves S.l",
    "wof:placetype":"venue"
},
  "geometry": {"coordinates":[-1.0991517305,38.8715515137],"type":"Point"}
}