{
  "type": "Feature",
  "properties": {
    "iso:country":"ES",
    "sg:address":"Avda Libertad De La, 18",
    "sg:city":"Donostia-san Sebastian",
    "sg:orig_category":"Abogados",
    "sg:phone":"+34 943 43 06 73",
    "sg:postcode":"20004",
    "sg:province":"Guip\u00f9zcoa",
    "wof:name":"Martin Pilar Javier",
    "wof:placetype":"venue"
},
  "geometry": {"coordinates":[-1.9814050198,43.3199501038],"type":"Point"}
}