{
  "type": "Feature",
  "properties": {
    "addr:full":"Carrer de Antoni Llopis, 14 Olot Girona 17800",
    "addr:housenumber":"14",
    "addr:postcode":"17800",
    "addr:street":"Carrer De Antoni Llopis",
    "iso:country":"ES",
    "sg:address":"Carrer de Antoni Llopis, 14",
    "sg:city":"Olot",
    "sg:orig_category":"Ropa De Hogar (al Por Menor)",
    "sg:phone":"+34 972 26 91 61",
    "sg:postcode":"17800",
    "sg:province":"Girona",
    "wof:name":"Joan Prat S.a.",
    "wof:placetype":"venue"
},
  "geometry": {"coordinates":[2.4879069328,42.1814460754],"type":"Point"}
}