{
  "type": "Feature",
  "properties": {
    "iso:country":"ES",
    "sg:address":"Pase Cervantes (de), 3",
    "sg:city":"Pontevedra",
    "sg:orig_category":"Promotores Constructores",
    "sg:phone":"+34 986 85 94 09",
    "sg:postcode":"36099",
    "sg:province":"Pontevedra",
    "wof:name":"Esperon Sertal Benigno",
    "wof:placetype":"venue"
},
  "geometry": {"coordinates":[-8.6427993774,42.4304656982],"type":"Point"}
}