{
  "type": "Feature",
  "properties": {
    "iso:country":"ES",
    "sg:address":"Zuazobidea, 14",
    "sg:city":"Jundiz",
    "sg:orig_category":"Gatos, Tornos Y Poleas A Motor, Hidr\u00c1ulicas Y Neum\u00c1ticas",
    "sg:phone":"+34 945 18 41 00",
    "sg:postcode":"01015",
    "sg:province":"\u00c1lava",
    "sg:website":"www.smceu.com",
    "wof:name":"Smc Espa\u00d1a S.a.",
    "wof:placetype":"venue"
},
  "geometry": {"coordinates":[-6.1999697685,43.3617782593],"type":"Point"}
}