{
  "type": "Feature",
  "properties": {
    "addr:full":"Rua Marques De Riestra, 11 Pontevedra Pontevedra 36002",
    "addr:housenumber":"11",
    "addr:postcode":"36002",
    "addr:street":"Rua Marques De Riestra",
    "iso:country":"ES",
    "sg:address":"Rua Marques De Riestra, 11",
    "sg:city":"Pontevedra",
    "sg:orig_category":"Electricidad: Instaladores",
    "sg:phone":"+34 986 85 70 64",
    "sg:postcode":"36002",
    "sg:province":"Pontevedra",
    "sg:website":"www.setga.es",
    "wof:name":"Setga S.l.",
    "wof:placetype":"venue"
},
  "geometry": {"coordinates":[-8.6466407776,42.4302825928],"type":"Point"}
}