{
  "type": "Feature",
  "properties": {
    "addr:full":"Calle de Velazquez, S/n Huecas Toledo 45511",
    "addr:housenumber":"s",
    "addr:postcode":"45511",
    "addr:street":"Calle De Velazquez;/ N Huecas",
    "iso:country":"ES",
    "sg:address":"Calle de Velazquez, S/n",
    "sg:city":"Huecas",
    "sg:orig_category":"Confecci\u00d3n De Zapatos",
    "sg:phone":"+34 925 78 57 72",
    "sg:postcode":"45511",
    "sg:province":"Toledo",
    "wof:name":"Moreno Herrero Francisco",
    "wof:placetype":"venue"
},
  "geometry": {"coordinates":[-4.2014918327,40.0263748169],"type":"Point"}
}