{
  "type": "Feature",
  "properties": {
    "addr:full":"Calle de Palleter, 83 Valencia Valencia 46008",
    "addr:housenumber":"83",
    "addr:postcode":"46008",
    "addr:street":"Calle De Palleter",
    "iso:country":"ES",
    "sg:address":"Calle de Palleter, 83",
    "sg:city":"Valencia",
    "sg:orig_category":"Diet\u00c9tica: Productos Biol\u00d3gicos, Naturales Y Diet\u00c9ticos (fabricaci\u00d3n, Al Por Mayor)",
    "sg:phone":"+34 963 84 49 20",
    "sg:postcode":"46008",
    "sg:province":"Valencia",
    "wof:name":"Distribuciones Exclusivas Pardo S.l.",
    "wof:placetype":"venue"
},
  "geometry": {"coordinates":[-0.3896529973,39.4735984802],"type":"Point"}
}