{
  "type": "Feature",
  "properties": {
    "iso:country":"ES",
    "sg:address":"Calle de Covarrubias, 20",
    "sg:city":"Madrid",
    "sg:orig_category":"Escultores, Estatuarios E Imagineros",
    "sg:phone":"+34 914 47 71 95",
    "sg:postcode":"28010",
    "sg:province":"Madrid",
    "wof:name":"Orno C.b.",
    "wof:placetype":"venue"
},
  "geometry": {"coordinates":[-3.6976709366,40.4300346375],"type":"Point"}
}