{
  "type": "Feature",
  "properties": {
    "iso:country":"ES",
    "sg:address":"Calle de Cristobal Colon, 36",
    "sg:city":"Sanlucar Mayor",
    "sg:orig_category":"Agencias Y Asesores De Publicidad",
    "sg:phone":"+34 955 70 31 66",
    "sg:postcode":"41800",
    "sg:province":"Sevilla",
    "wof:name":"Gonzalez Granda Marga",
    "wof:placetype":"venue"
},
  "geometry": {"coordinates":[-6.1999440193,37.3871612549],"type":"Point"}
}