{
  "type": "Feature",
  "properties": {
    "iso:country":"ES",
    "sg:address":"Ctra. Almeria, S/n",
    "sg:city":"Alcudia Guadix",
    "sg:orig_category":"Carnicer\u00cdas, Carnicer\u00cdas",
    "sg:phone":"+34 958 69 82 23",
    "sg:postcode":"18511",
    "sg:province":"Granada",
    "wof:name":"Sierra Sanchez Jose",
    "wof:placetype":"venue"
},
  "geometry": {"coordinates":[-3.098238945,37.2561378479],"type":"Point"}
}