{
  "type": "Feature",
  "properties": {
    "addr:full":"Calle de Alcala Del Rio, 30 Alcala Guadaira Sevilla 41500",
    "addr:housenumber":"30",
    "addr:postcode":"41500",
    "addr:street":"Calle De Alcala Del Rio",
    "iso:country":"ES",
    "sg:address":"Calle de Alcala Del Rio, 30",
    "sg:city":"Alcala Guadaira",
    "sg:orig_category":"Empresas De Carpinter\u00cda",
    "sg:phone":"+34 955 68 20 01",
    "sg:postcode":"41500",
    "sg:province":"Sevilla",
    "wof:name":"Andrade E Hijos S.l.",
    "wof:placetype":"venue"
},
  "geometry": {"coordinates":[-5.8269467354,37.3315315247],"type":"Point"}
}