{
  "type": "Feature",
  "properties": {
    "addr:full":"Cno. Cala Cranc, S/n Urb. Biniorella Islas Baleares 07160",
    "addr:housenumber":"s",
    "addr:postcode":"07160",
    "addr:street":"Cno. Cala Cranc;/ N Urb. Biniorella",
    "iso:country":"ES",
    "sg:address":"Cno. Cala Cranc, S/n",
    "sg:city":"Urb. Biniorella",
    "sg:orig_category":"Asociaciones Y Clubs Deportivos",
    "sg:phone":"+34 971 67 39 17",
    "sg:postcode":"07160",
    "sg:province":"Islas Baleares",
    "wof:name":"Biniorella Holdings S.a.",
    "wof:placetype":"venue"
},
  "geometry": {"coordinates":[2.444740057,39.5373916626],"type":"Point"}
}