{
  "type": "Feature",
  "properties": {
    "iso:country":"ES",
    "sg:address":"Av Pais Valencia (del), 112",
    "sg:city":"Cocentaina",
    "sg:orig_category":"Bancos",
    "sg:phone":"+34 965 59 14 52",
    "sg:postcode":"03820",
    "sg:province":"Alicante",
    "wof:name":"Banco Popular Espa\u00f1ol S.a.",
    "wof:placetype":"venue"
},
  "geometry": {"coordinates":[-0.4392449856,38.7404556274],"type":"Point"}
}