{
  "type": "Feature",
  "properties": {
    "addr:full":"Escuelas, 1 Pobo Due\u00f1as Guadalajara 19326",
    "addr:housenumber":"1",
    "addr:postcode":"19326",
    "addr:street":"Escuelas",
    "iso:country":"ES",
    "sg:address":"Escuelas, 1",
    "sg:city":"Pobo Due\u00f1as",
    "sg:orig_category":"Cajas De Ahorro",
    "sg:phone":"+34 949 84 11 29",
    "sg:postcode":"19326",
    "sg:province":"Guadalajara",
    "wof:name":"Caja De Ahorro Provincial De Guadalajara",
    "wof:placetype":"venue"
},
  "geometry": {"coordinates":[-1.6508669853,40.7771110535],"type":"Point"}
}