{
  "type": "Feature",
  "properties": {
    "iso:country":"ES",
    "sg:address":"Rua Vigo, 42",
    "sg:city":"Amoeiro",
    "sg:orig_category":"Chapister\u00cda",
    "sg:phone":"+34 988 28 12 26",
    "sg:postcode":"32170",
    "sg:province":"Ourense",
    "wof:name":"Gonzalez Iglesias Jose",
    "wof:placetype":"venue"
},
  "geometry": {"coordinates":[-7.9498472214,42.4143867493],"type":"Point"}
}