{
  "type": "Feature",
  "properties": {
    "addr:full":"Calle de Matadero, S/n Brihuega Guadalajara 19400",
    "addr:housenumber":"/ n",
    "addr:postcode":"19400",
    "addr:street":"Calle De Matadero S",
    "iso:country":"ES",
    "sg:address":"Calle de Matadero, S/n",
    "sg:city":"Brihuega",
    "sg:orig_category":"Sanatorios M\u00c9dico",
    "sg:phone":"+34 949 28 06 30",
    "sg:postcode":"19400",
    "sg:province":"Guadalajara",
    "wof:name":"Servicio De Salud De Castilla La Mancha",
    "wof:placetype":"venue"
},
  "geometry": {"coordinates":[-2.8703289032,40.7592315674],"type":"Point"}
}