{
  "type": "Feature",
  "properties": {
    "addr:full":"Calle de San Marcial, 2 Donostia-san Sebastian Guip\u00f9zcoa 20005",
    "addr:housenumber":"2",
    "addr:postcode":"20005",
    "addr:street":"Calle De San Marcial",
    "iso:country":"ES",
    "sg:address":"Calle de San Marcial, 2",
    "sg:city":"Donostia-san Sebastian",
    "sg:orig_category":"Centros De Coordinaci\u00d3n",
    "sg:phone":"+34 943 42 33 96",
    "sg:postcode":"20005",
    "sg:province":"Guip\u00f9zcoa",
    "wof:name":"Gestion Jesval S.l.",
    "wof:placetype":"venue"
},
  "geometry": {"coordinates":[-1.979352951,43.3198623657],"type":"Point"}
}