{
  "type": "Feature",
  "properties": {
    "addr:full":"Miralcamp, S/n Mollerussa Lleida 25230",
    "addr:housenumber":"/ n",
    "addr:postcode":"25230",
    "addr:street":"S",
    "iso:country":"ES",
    "sg:address":"Miralcamp, S/n",
    "sg:city":"Mollerussa",
    "sg:orig_category":"Asociaciones Y Clubs Deportivos",
    "sg:phone":"+34 973 60 30 36",
    "sg:postcode":"25230",
    "sg:province":"Lleida",
    "wof:name":"C.f.j. Mollerussa",
    "wof:placetype":"venue"
},
  "geometry": {"coordinates":[0.8930749893,41.6239814758],"type":"Point"}
}