{
  "type": "Feature",
  "properties": {
    "addr:full":"Calle de Joaquin Costa, 47 Madrid Madrid 28002",
    "addr:housenumber":"47",
    "addr:postcode":"madrid;28002",
    "addr:street":"Calle De Joaquin Costa",
    "iso:country":"ES",
    "sg:address":"Calle de Joaquin Costa, 47",
    "sg:city":"Madrid",
    "sg:orig_category":"M\u00c9dicos: Oftalmolog\u00cda",
    "sg:phone":"+34 915 64 55 79",
    "sg:postcode":"28002",
    "sg:province":"Madrid",
    "wof:name":"Garcia-franco Zu\u00f1iga Carmen",
    "wof:placetype":"venue"
},
  "geometry": {"coordinates":[-3.6811869144,40.4414787292],"type":"Point"}
}