{
  "type": "Feature",
  "properties": {
    "iso:country":"ES",
    "sg:address":"Calle de Iglesia, 32",
    "sg:city":"Tembleque",
    "sg:orig_category":"Arquitectos",
    "sg:phone":"+34 925 14 50 09",
    "sg:postcode":"45780",
    "sg:province":"Toledo",
    "wof:name":"Gil Bueno S.l.",
    "wof:placetype":"venue"
},
  "geometry": {"coordinates":[-3.5034489632,39.6969604492],"type":"Point"}
}