{
  "type": "Feature",
  "properties": {
    "addr:full":"Carr Sant Vicen\u00c7, 3 Vila Girona 17490",
    "addr:housenumber":"3",
    "addr:postcode":"17490",
    "addr:street":"Carr Sant Vicenc\u0327",
    "iso:country":"ES",
    "sg:address":"Carr Sant Vicen\u00c7, 3",
    "sg:city":"Vila",
    "sg:orig_category":"Carnicer\u00cdas, Carnicer\u00cdas",
    "sg:phone":"+34 972 38 01 29",
    "sg:postcode":"17490",
    "sg:province":"Girona",
    "wof:name":"Carnisseria Valls S.c",
    "wof:placetype":"venue"
},
  "geometry": {"coordinates":[3.1481759548,42.3640785217],"type":"Point"}
}