{
  "type": "Feature",
  "properties": {
    "iso:country":"ES",
    "sg:address":"Calle de San Luis, 22",
    "sg:city":"Almansa",
    "sg:orig_category":"Centros De Educaci\u00d3n Especial",
    "sg:phone":"+34 967 34 19 76",
    "sg:postcode":"02640",
    "sg:province":"Albacete",
    "wof:name":"Colegio Publico Duque De Alba",
    "wof:placetype":"venue"
},
  "geometry": {"coordinates":[-1.0960299969,38.8713111877],"type":"Point"}
}