{
  "type": "Feature",
  "properties": {
    "addr:full":"Pol Ind Aljoroque, 28 Antas Almer\u00eda 04628",
    "addr:housenumber":"28",
    "addr:postcode":"04628",
    "addr:street":"Aljoroque",
    "iso:country":"ES",
    "sg:address":"Pol Ind Aljoroque, 28",
    "sg:city":"Antas",
    "sg:orig_category":"Reposter\u00cdas",
    "sg:phone":"+34 950 45 35 18",
    "sg:postcode":"04628",
    "sg:province":"Almer\u00eda",
    "wof:name":"Mojacar Pan",
    "wof:placetype":"venue"
},
  "geometry": {"coordinates":[-1.9588006735,37.2703666687],"type":"Point"}
}