{
  "type": "Feature",
  "properties": {
    "iso:country":"ES",
    "sg:address":"Barr Abajo, S/n",
    "sg:city":"Barrio De Abajo",
    "sg:orig_category":"Art\u00cdculos De Madera (fabricaci\u00d3n Y Al Por Mayor)",
    "sg:phone":"+34 942 70 90 88",
    "sg:postcode":"39512",
    "sg:province":"Cantabria",
    "wof:name":"Maximo Castro S.l.",
    "wof:placetype":"venue"
},
  "geometry": {"coordinates":[-4.0014500618,43.1361885071],"type":"Point"}
}