{
  "type": "Feature",
  "properties": {
    "iso:country":"ES",
    "sg:address":"Avda. Arteixo, 11",
    "sg:city":"A Coru\u00f1a",
    "sg:orig_category":"Librer\u00cdas",
    "sg:phone":"+34 981 26 42 59",
    "sg:postcode":"15004",
    "sg:province":"La Coru\u00f1a",
    "sg:website":"www.everest.es",
    "wof:name":"Everest De Ediciones Y Distribucion S.l.",
    "wof:placetype":"venue"
},
  "geometry": {"coordinates":[-8.4095277786,43.3628692627],"type":"Point"}
}