{
  "type": "Feature",
  "properties": {
    "addr:full":"Avda Marques De Lacy, S/n Murada Alicante 03315",
    "addr:housenumber":"s",
    "addr:postcode":"03315",
    "addr:street":"Avda Marques De Lacy;/ N Murada",
    "iso:country":"ES",
    "sg:address":"Avda Marques De Lacy, S/n",
    "sg:city":"Murada",
    "sg:orig_category":"Cooperativas Agr\u00cdcolas",
    "sg:phone":"+34 966 77 90 29",
    "sg:postcode":"03315",
    "sg:province":"Alicante",
    "wof:name":"Cooperativa Agricola Catolica De Orihuela S.c.",
    "wof:placetype":"venue"
},
  "geometry": {"coordinates":[-0.9635040164,38.1699981689],"type":"Point"}
}