{
  "type": "Feature",
  "properties": {
    "iso:country":"ES",
    "sg:address":"A Igrexa, 24",
    "sg:city":"Breto\u00f1a",
    "sg:orig_category":"Alimentaci\u00d3n General (al Por Menor)",
    "sg:phone":"+34 982 34 91 03",
    "sg:postcode":"27286",
    "sg:province":"Lugo",
    "wof:name":"Rodriguez Alvarez Celestino",
    "wof:placetype":"venue"
},
  "geometry": {"coordinates":[-7.3240408897,43.3316688538],"type":"Point"}
}