{
  "type": "Feature",
  "properties": {
    "addr:full":"Aguila, 6 Son Ferrer Islas Baleares 07182",
    "addr:postcode":"07182",
    "addr:street":"Aguila",
    "iso:country":"ES",
    "sg:address":"Aguila, 6",
    "sg:city":"Son Ferrer",
    "sg:orig_category":"Negocio De Materiales De Construcci\u00d3n",
    "sg:phone":"+34 971 23 00 00",
    "sg:postcode":"07182",
    "sg:province":"Islas Baleares",
    "sg:website":"www.almacenesferragut.com",
    "wof:name":"Ferragut Ferra Jaime",
    "wof:placetype":"venue"
},
  "geometry": {"coordinates":[2.5028591156,39.494140625],"type":"Point"}
}