{
  "type": "Feature",
  "properties": {
    "iso:country":"ES",
    "sg:address":"Calle de Antxeta Juan De, 15",
    "sg:city":"Bilbao",
    "sg:orig_category":"Pescader\u00cdas (al Por Menor)",
    "sg:phone":"+34 944 47 37 45",
    "sg:postcode":"48015",
    "sg:province":"Vizcaya",
    "wof:name":"Zaballa Martinez Maria Cristina",
    "wof:placetype":"venue"
},
  "geometry": {"coordinates":[-2.960631609,43.2833595276],"type":"Point"}
}