{
  "type": "Feature",
  "properties": {
    "addr:full":"Ptge Mossota (la), 8 S. Joan Despi Barcelona 08970",
    "addr:postcode":"08970",
    "addr:street":"Ptge Mossota La 8 S. Joan Despi",
    "iso:country":"ES",
    "sg:address":"Ptge Mossota (la), 8",
    "sg:city":"S. Joan Despi",
    "sg:orig_category":"Art\u00cdculos De Limpieza Y De Cocina (fabricaci\u00d3n, Al Por Mayor)",
    "sg:phone":"+34 934 77 01 25",
    "sg:postcode":"08970",
    "sg:province":"Barcelona",
    "wof:name":"Import-mec S.a.",
    "wof:placetype":"venue"
},
  "geometry": {"coordinates":[2.058412075,41.3723602295],"type":"Point"}
}