{
  "type": "Feature",
  "properties": {
    "addr:full":"Carrer de Mollet, 28 Llagosta Barcelona 08120",
    "addr:housenumber":"28",
    "addr:postcode":"08120",
    "addr:street":"Carrer De Mollet",
    "iso:country":"ES",
    "sg:address":"Carrer de Mollet, 28",
    "sg:city":"Llagosta",
    "sg:orig_category":"Fabricaci\u00d3n, Instalaci\u00d3n Y Reparaci\u00d3n De Bombas",
    "sg:phone":"+34 935 74 36 55",
    "sg:postcode":"08120",
    "sg:province":"Barcelona",
    "wof:name":"Bezares S. A.",
    "wof:placetype":"venue"
},
  "geometry": {"coordinates":[2.1970200539,41.5155792236],"type":"Point"}
}