{
  "type": "Feature",
  "properties": {
    "addr:full":"Calle de Monte Perdido, 115 Madrid Madrid 28053",
    "addr:housenumber":"115",
    "addr:postcode":"28053",
    "addr:street":"Calle De Monte Perdido",
    "iso:country":"ES",
    "sg:address":"Calle de Monte Perdido, 115",
    "sg:city":"Madrid",
    "sg:orig_category":"Farmacias",
    "sg:phone":"+34 914 77 54 43",
    "sg:postcode":"28053",
    "sg:province":"Madrid",
    "wof:name":"Sena Peralta Carmen",
    "wof:placetype":"venue"
},
  "geometry": {"coordinates":[-3.6637070179,40.3926620483],"type":"Point"}
}