{
  "type": "Feature",
  "properties": {
    "iso:country":"ES",
    "sg:address":"Calle de Sierra De Cabrera, 4",
    "sg:city":"Parador Hortichuelas",
    "sg:orig_category":"Inmobiliaria (agencias)",
    "sg:phone":"+34 950 34 20 66",
    "sg:postcode":"04720",
    "sg:province":"Almer\u00eda",
    "wof:name":"Jahan Anguita Liliana Esther",
    "wof:placetype":"venue"
},
  "geometry": {"coordinates":[-2.5988790989,36.8061332703],"type":"Point"}
}