{
  "type": "Feature",
  "properties": {
    "addr:full":"Pl Verdum(urb Torre Conill), 15 Betera Valencia 46117",
    "addr:housenumber":"15",
    "addr:postcode":"46117",
    "addr:street":"Pl Verdum Urb Torre Conill",
    "iso:country":"ES",
    "sg:address":"Pl Verdum(urb Torre Conill), 15",
    "sg:city":"Betera",
    "sg:orig_category":"Peluquer\u00cdas, Peluquer\u00cda Mixta",
    "sg:phone":"+34 961 60 80 12",
    "sg:postcode":"46117",
    "sg:province":"Valencia",
    "wof:name":"Herraiz Del Moral Raquel",
    "wof:placetype":"venue"
},
  "geometry": {"coordinates":[-0.473668009,39.5664749146],"type":"Point"}
}