{
  "type": "Feature",
  "properties": {
    "iso:country":"ES",
    "sg:address":"Avda Galaxia, 24",
    "sg:city":"Madrid",
    "sg:orig_category":"Abogados",
    "sg:phone":"+34 913 57 24 80",
    "sg:postcode":"28023",
    "sg:province":"Madrid",
    "wof:name":"Cruz Hernandez Maria De La",
    "wof:placetype":"venue"
},
  "geometry": {"coordinates":[-3.7852749825,40.4575462341],"type":"Point"}
}