{
  "type": "Feature",
  "properties": {
    "addr:full":"Pg Industria, 25 Banyoles Girona 17820",
    "addr:housenumber":"25",
    "addr:postcode":"17820",
    "addr:street":"Industria",
    "iso:country":"ES",
    "sg:address":"Pg Industria, 25",
    "sg:city":"Banyoles",
    "sg:orig_category":"Administraciones Regionales, Departamentales Y Locales",
    "sg:phone":"+34 972 57 00 50",
    "sg:postcode":"17820",
    "sg:province":"Girona",
    "sg:website":"www.banyoles.org",
    "wof:name":"Ajuntament De Banyoles",
    "wof:placetype":"venue"
},
  "geometry": {"coordinates":[2.7629351616,42.1159858704],"type":"Point"}
}