{
  "type": "Feature",
  "properties": {
    "iso:country":"ES",
    "sg:address":"Plaza Solobarria, 5",
    "sg:city":"Basauri",
    "sg:orig_category":"\u00d3ptica: Instrumentos (fabricaci\u00d3n)",
    "sg:phone":"+34 944 26 20 20",
    "sg:postcode":"48970",
    "sg:province":"Vizcaya",
    "wof:name":"Stylo-bizkaia S.l.",
    "wof:placetype":"venue"
},
  "geometry": {"coordinates":[-2.8837900162,43.2382583618],"type":"Point"}
}