{
  "type": "Feature",
  "properties": {
    "iso:country":"ES",
    "sg:address":"Calle de Arquitecto Urteaga, 3",
    "sg:city":"Javea",
    "sg:orig_category":"Electricidad: Instalaciones Industriales",
    "sg:phone":"+34 966 46 20 96",
    "sg:postcode":"03730",
    "sg:province":"Alicante",
    "wof:name":"Euroelectro Xabia S.l.",
    "wof:placetype":"venue"
},
  "geometry": {"coordinates":[0.1652877033,38.7897644043],"type":"Point"}
}