{
  "type": "Feature",
  "properties": {
    "iso:country":"ES",
    "sg:address":"Carrer de Sant Miquel, 8",
    "sg:city":"Argentona",
    "sg:orig_category":"Carnicer\u00cdas, Carnicer\u00cdas",
    "sg:phone":"+34 937 56 16 68",
    "sg:postcode":"08310",
    "sg:province":"Barcelona",
    "wof:name":"Osorio Ferrer Maria Luisa",
    "wof:placetype":"venue"
},
  "geometry": {"coordinates":[2.4020819664,41.5547218323],"type":"Point"}
}