{
  "type": "Feature",
  "properties": {
    "iso:country":"ES",
    "sg:address":"Carr Arxiduc Lluis Salvador, 11",
    "sg:city":"Eivissa",
    "sg:orig_category":"Bisuter\u00cda, Joyer\u00cda, Relojer\u00cda (al Por Menor)",
    "sg:phone":"+34 971 39 20 04",
    "sg:postcode":"07800",
    "sg:province":"Islas Baleares",
    "sg:website":"www.ibermax.com",
    "wof:name":"Eurosterling S.l.",
    "wof:placetype":"venue"
},
  "geometry": {"coordinates":[1.4278529882,38.906829834],"type":"Point"}
}