{
  "type": "Feature",
  "properties": {
    "iso:country":"ES",
    "sg:address":"Calle de Jose Maria Lacasa, 19",
    "sg:city":"Huesca",
    "sg:orig_category":"Peluquer\u00cdas, Peluquer\u00cda Mixta",
    "sg:phone":"+34 974 24 52 12",
    "sg:postcode":"22001",
    "sg:province":"Huesca",
    "wof:name":"Angusto Ferraz Maria Pilar",
    "wof:placetype":"venue"
},
  "geometry": {"coordinates":[-0.4022499919,42.136882782],"type":"Point"}
}