{
  "type": "Feature",
  "properties": {
    "iso:country":"ES",
    "sg:address":"Calle de Dolores (los), 1",
    "sg:city":"Sarrion",
    "sg:orig_category":"Abogados",
    "sg:phone":"+34 978 78 10 94",
    "sg:postcode":"44460",
    "sg:province":"Teruel",
    "wof:name":"Mendizabal Navarro Pilar",
    "wof:placetype":"venue"
},
  "geometry": {"coordinates":[-0.8165839911,40.1424636841],"type":"Point"}
}