{
  "type": "Feature",
  "properties": {
    "iso:country":"ES",
    "sg:address":"Poligono La Vega, 62",
    "sg:city":"Reinosa",
    "sg:orig_category":"Calderer\u00cda",
    "sg:phone":"+34 942 75 05 23",
    "sg:postcode":"39200",
    "sg:province":"Cantabria",
    "wof:name":"Caldereria Reinosa S.l",
    "wof:placetype":"venue"
},
  "geometry": {"coordinates":[-4.1391940117,43.0004043579],"type":"Point"}
}