{
  "type": "Feature",
  "properties": {
    "iso:country":"ES",
    "sg:address":"Avda Bilbao, 3",
    "sg:city":"Torrelavega",
    "sg:orig_category":"Art\u00cdculos Para Fumadores (al Por Menor)",
    "sg:phone":"+34 942 88 28 38",
    "sg:postcode":"39300",
    "sg:province":"Cantabria",
    "wof:name":"Ceballos Abascal Aquilino",
    "wof:placetype":"venue"
},
  "geometry": {"coordinates":[-4.0437169075,43.3473091125],"type":"Point"}
}