{
  "type": "Feature",
  "properties": {
    "addr:full":"Carrer de Foc Follet, 10 Barcelona Barcelona 08030",
    "addr:housenumber":"10",
    "addr:postcode":"08030",
    "addr:street":"Carrer De Foc Follet",
    "iso:country":"ES",
    "sg:address":"Carrer de Foc Follet, 10",
    "sg:city":"Barcelona",
    "sg:orig_category":"M\u00c1quinas Para Trabajar El Caucho",
    "sg:phone":"+34 933 05 60 53",
    "sg:postcode":"08030",
    "sg:province":"Barcelona",
    "wof:name":"Duce Flores Juan",
    "wof:placetype":"venue"
},
  "geometry": {"coordinates":[2.2025508881,41.434135437],"type":"Point"}
}