{
  "type": "Feature",
  "properties": {
    "iso:country":"ES",
    "sg:address":"Rua Calzada, 27",
    "sg:city":"Cee",
    "sg:orig_category":"Peluqueros: De Se\u00d1oras",
    "sg:phone":"+34 981 74 61 52",
    "sg:postcode":"15270",
    "sg:province":"La Coru\u00f1a",
    "wof:name":"Casti\u00f1eira Touri\u00f1an Maria Teresa",
    "wof:placetype":"venue"
},
  "geometry": {"coordinates":[-9.1894292831,42.9596862793],"type":"Point"}
}