{
  "type": "Feature",
  "properties": {
    "addr:full":"Calle de Gonzalo Jimenez De Quesada, 2 Madrid Madrid 28004",
    "addr:housenumber":"2",
    "addr:postcode":"28004",
    "addr:street":"Calle De Gonzalo Jimenez De Quesada",
    "iso:country":"ES",
    "sg:address":"Calle de Gonzalo Jimenez De Quesada, 2",
    "sg:city":"Madrid",
    "sg:orig_category":"Psic\u00d3logos",
    "sg:phone":"+34 915 31 85 50",
    "sg:postcode":"28004",
    "sg:province":"Madrid",
    "wof:name":"Castrillo Mirat Dolores",
    "wof:placetype":"venue"
},
  "geometry": {"coordinates":[-3.702796936,40.4203071594],"type":"Point"}
}