{
  "type": "Feature",
  "properties": {
    "iso:country":"ES",
    "sg:address":"Folgueras, 22",
    "sg:city":"Granda",
    "sg:orig_category":"Contenedores (mercanc\u00cdas)",
    "sg:phone":"+34 985 79 29 24",
    "sg:postcode":"33199",
    "sg:province":"Asturias",
    "wof:name":"Transportes Monica Auvia\u00f1o S.l.",
    "wof:placetype":"venue"
},
  "geometry": {"coordinates":[-5.7986898422,43.3584632874],"type":"Point"}
}