{
  "type": "Feature",
  "properties": {
    "iso:country":"ES",
    "sg:address":"Calle de Sant Jaume, 39",
    "sg:city":"Santa Eulalia",
    "sg:orig_category":"Promotores Constructores",
    "sg:phone":"+34 971 33 15 19",
    "sg:postcode":"07840",
    "sg:province":"Islas Baleares",
    "wof:name":"Construbau Ibiza S.l",
    "wof:placetype":"venue"
},
  "geometry": {"coordinates":[1.5293949842,38.9824829102],"type":"Point"}
}