{
  "type": "Feature",
  "properties": {
    "addr:full":"Calle de Jardines, 1 Melilla Melilla 52001",
    "addr:housenumber":"1",
    "addr:postcode":"52001",
    "addr:street":"Calle De Jardines",
    "iso:country":"ES",
    "sg:address":"Calle de Jardines, 1",
    "sg:city":"Melilla",
    "sg:orig_category":"Estancos",
    "sg:phone":"+34 952 68 34 36",
    "sg:postcode":"52001",
    "sg:province":"Melilla",
    "wof:name":"Hernandez Belmonte Rafael",
    "wof:placetype":"venue"
},
  "geometry": {"coordinates":[-2.935781002,35.2927436829],"type":"Point"}
}