{
  "type": "Feature",
  "properties": {
    "addr:full":"Avda Pio Xii, S/n Huelva Huelva 21004",
    "addr:housenumber":"s / n",
    "addr:postcode":"21004",
    "addr:street":"Avda Pio Xii",
    "iso:country":"ES",
    "sg:address":"Avda Pio Xii, S/n",
    "sg:city":"Huelva",
    "sg:orig_category":"Alimentaci\u00d3n General (al Por Menor)",
    "sg:phone":"+34 959 22 12 63",
    "sg:postcode":"21004",
    "sg:province":"Huelva",
    "wof:name":"Conde Romero Domingo",
    "wof:placetype":"venue"
},
  "geometry": {"coordinates":[-6.9402041435,37.2587089539],"type":"Point"}
}