{
  "type": "Feature",
  "properties": {
    "addr:full":"Carretera General, 69 Padron La Coru\u00f1a 15900",
    "addr:housenumber":"69",
    "addr:postcode":"15900",
    "addr:street":"Carretera General;Padron La Corun\u0303A",
    "iso:country":"ES",
    "sg:address":"Carretera General, 69",
    "sg:city":"Padron",
    "sg:orig_category":"Panader\u00cdas, Panader\u00cdas",
    "sg:phone":"+34 981 81 06 13",
    "sg:postcode":"15900",
    "sg:province":"La Coru\u00f1a",
    "wof:name":"Iglesias Catoira Eugenio",
    "wof:placetype":"venue"
},
  "geometry": {"coordinates":[-8.6591444016,42.7387466431],"type":"Point"}
}