{
  "type": "Feature",
  "properties": {
    "addr:full":"Calle de Juan Jose Rodrigo, 7 Tomelloso Ciudad Real 13700",
    "addr:housenumber":"7",
    "addr:postcode":"13700",
    "addr:street":"Calle De Juan Jose Rodrigo",
    "iso:country":"ES",
    "sg:address":"Calle de Juan Jose Rodrigo, 7",
    "sg:city":"Tomelloso",
    "sg:orig_category":"Frutas Y Legumbres Frescas (al Por Mayor)",
    "sg:phone":"+34 926 51 06 14",
    "sg:postcode":"13700",
    "sg:province":"Ciudad Real",
    "wof:name":"Bautista Sampedro Reyes Antoliano Sampedro Reyes Y Otro Cdad",
    "wof:placetype":"venue"
},
  "geometry": {"coordinates":[-3.0209009647,39.1602592468],"type":"Point"}
}