{
  "type": "Feature",
  "properties": {
    "iso:country":"ES",
    "sg:address":"Calle de Carretera De Almeria, 50",
    "sg:city":"Adra",
    "sg:orig_category":"Molduras, Junquillos, Listones Y Molduras Perforadas",
    "sg:phone":"+34 950 40 01 71",
    "sg:postcode":"04770",
    "sg:province":"Almer\u00eda",
    "wof:name":"Moreno Brabezo Pedro",
    "wof:placetype":"venue"
},
  "geometry": {"coordinates":[-3.0057294369,36.7483558655],"type":"Point"}
}