{
  "type": "Feature",
  "properties": {
    "addr:full":"Pl Espanya, 13 Cambrils Tarragona 43850",
    "addr:housenumber":"13",
    "addr:postcode":"43850",
    "addr:street":"Pl Espanya",
    "iso:country":"ES",
    "sg:address":"Pl Espanya, 13",
    "sg:city":"Cambrils",
    "sg:orig_category":"Asociaciones Y Clubs Deportivos",
    "sg:phone":"+34 977 36 34 02",
    "sg:postcode":"43850",
    "sg:province":"Tarragona",
    "wof:name":"Llorente Vallejo Silvino",
    "wof:placetype":"venue"
},
  "geometry": {"coordinates":[1.0531300306,41.0741996765],"type":"Point"}
}