{
  "type": "Feature",
  "properties": {
    "addr:full":"Ctra. Chipiona-sanlucar, Km. 0001,7 Chipiona C\u00e1diz 11550",
    "addr:postcode":"11550",
    "addr:street":"Ctra. Chipiona-Sanlucar Km. 0001,7",
    "iso:country":"ES",
    "sg:address":"Ctra. Chipiona-sanlucar, Km. 0001,7",
    "sg:city":"Chipiona",
    "sg:orig_category":"Flores Y Plantas Naturales (al Por Mayor)",
    "sg:phone":"+34 956 37 48 48",
    "sg:postcode":"11550",
    "sg:province":"C\u00e1diz",
    "sg:website":"www.flordechipiona.com",
    "wof:name":"Asociacion De Comercializadores Y Productores De Flor Cortada",
    "wof:placetype":"venue"
},
  "geometry": {"coordinates":[-6.3605136871,36.7659912109],"type":"Point"}
}