{
  "type": "Feature",
  "properties": {
    "addr:full":"Carrer de Padilla, 196 Barcelona Barcelona 08013",
    "addr:housenumber":"196",
    "addr:postcode":"08013",
    "addr:street":"Carrer De Padilla",
    "iso:country":"ES",
    "sg:address":"Carrer de Padilla, 196",
    "sg:city":"Barcelona",
    "sg:orig_category":"Arquitectos",
    "sg:phone":"+34 932 45 21 32",
    "sg:postcode":"08013",
    "sg:province":"Barcelona",
    "wof:name":"Triartek S.l.",
    "wof:placetype":"venue"
},
  "geometry": {"coordinates":[2.1805379391,41.4033164978],"type":"Point"}
}