{
  "type": "Feature",
  "properties": {
    "iso:country":"ES",
    "sg:address":"Cra San Jeronimo, 16",
    "sg:city":"Madrid",
    "sg:classifiers":[
        {
            "category":"Government",
            "subcategory":"Post Office",
            "type":"Public Place"
        }
    ],
    "sg:phone":"+34 915 32 27 85",
    "sg:postcode":"28014",
    "sg:province":"Madrid",
    "sg:tags":[
        "de",
        "yoga",
        "clases"
    ],
    "wof:name":"Lizardi Camarero-nu\u00f1ez Francisco Maria",
    "wof:placetype":"venue"
},
  "geometry": {"coordinates":[-3.7001590729,40.4165382385],"type":"Point"}
}