{
  "type": "Feature",
  "properties": {
    "addr:full":"Calle de Real, 10 Alcala De Los Gazules C\u00e1diz 11180",
    "addr:housenumber":"10",
    "addr:postcode":"11180",
    "addr:street":"Calle De Real;De Los Gazules Ca\u0301Diz",
    "iso:country":"ES",
    "sg:address":"Calle de Real, 10",
    "sg:city":"Alcala De Los Gazules",
    "sg:orig_category":"Televisi\u00d3n, V\u00cddeo: Aparatos Y Accesorios (venta)",
    "sg:phone":"+34 956 41 33 67",
    "sg:postcode":"11180",
    "sg:province":"C\u00e1diz",
    "wof:name":"Chica Marquez Rogelio",
    "wof:placetype":"venue"
},
  "geometry": {"coordinates":[-5.722630024,36.4619026184],"type":"Point"}
}