{
  "type": "Feature",
  "properties": {
    "iso:country":"ES",
    "sg:address":"Carrer de Corral De Sauner (del), 7",
    "sg:city":"Cap De Salou-nostra Senyora De Nuria",
    "sg:orig_category":"Impuestos, Tesoro P\u00dablico",
    "sg:phone":"+34 977 37 30 38",
    "sg:postcode":"43840",
    "sg:province":"Tarragona",
    "wof:name":"Celsp Vilaseca S.l.",
    "wof:placetype":"venue"
},
  "geometry": {"coordinates":[1.1726499796,41.0632743835],"type":"Point"}
}