{
  "type": "Feature",
  "properties": {
    "iso:country":"ES",
    "sg:address":"Calle de Andres Mellado, 79",
    "sg:city":"Madrid",
    "sg:orig_category":"Arquitectos",
    "sg:phone":"+34 914 41 21 07",
    "sg:postcode":"28003",
    "sg:province":"Madrid",
    "wof:name":"Quijano Pernia Manuel",
    "wof:placetype":"venue"
},
  "geometry": {"coordinates":[-3.7140815258,40.4397354126],"type":"Point"}
}