{
  "type": "Feature",
  "properties": {
    "iso:country":"ES",
    "sg:address":"Calle de Capitan Carlos Haya, 8",
    "sg:city":"Getafe",
    "sg:orig_category":"Almacenes Frigor\u00cdficos",
    "sg:phone":"+34 916 95 23 96",
    "sg:postcode":"28901",
    "sg:province":"Madrid",
    "wof:name":"Frimarrod S.l",
    "wof:placetype":"venue"
},
  "geometry": {"coordinates":[-3.7259719372,40.3077316284],"type":"Point"}
}