{
  "type": "Feature",
  "properties": {
    "iso:country":"ES",
    "sg:address":"Calle de Parras, 28",
    "sg:city":"Alfacar",
    "sg:orig_category":"Ropa Para Se\u00d1oras Y Caballeros (al Por Menor)",
    "sg:phone":"+34 958 54 02 44",
    "sg:postcode":"18170",
    "sg:province":"Granada",
    "wof:name":"Garcia Altea Monica",
    "wof:placetype":"venue"
},
  "geometry": {"coordinates":[-3.5671520233,37.2362976074],"type":"Point"}
}