{
  "type": "Feature",
  "properties": {
    "iso:country":"ES",
    "sg:address":"Ctra. Andujar, S/n",
    "sg:city":"Arjona",
    "sg:orig_category":"Producci\u00d3n, Venta De Productos De Agricultura Biol\u00d3gica",
    "sg:phone":"+34 953 12 20 60",
    "sg:postcode":"23760",
    "sg:province":"Ja\u00e9n",
    "wof:name":"Los Alamillos C.b.",
    "wof:placetype":"venue"
},
  "geometry": {"coordinates":[-4.064218998,37.9369697571],"type":"Point"}
}