{
  "type": "Feature",
  "properties": {
    "addr:full":"Avda Constitucion (la), 11 Sevilla Sevilla 41004",
    "addr:housenumber":"11",
    "addr:postcode":"41004",
    "addr:street":"Avda Constitucion La",
    "iso:country":"ES",
    "sg:address":"Avda Constitucion (la), 11",
    "sg:city":"Sevilla",
    "sg:orig_category":"Organismos De Reclutamiento",
    "sg:phone":"+34 954 56 02 84",
    "sg:postcode":"41004",
    "sg:province":"Sevilla",
    "wof:name":"Progosa Gestion Internacional S.l",
    "wof:placetype":"venue"
},
  "geometry": {"coordinates":[-5.9941291809,37.3866500854],"type":"Point"}
}