{
  "type": "Feature",
  "properties": {
    "addr:full":"Carrer de Sant Antoni, 29 Denia Alicante 03700",
    "addr:housenumber":"29",
    "addr:postcode":"03700",
    "addr:street":"Carrer De Sant Antoni",
    "iso:country":"ES",
    "sg:address":"Carrer de Sant Antoni, 29",
    "sg:city":"Denia",
    "sg:orig_category":"Grafistas",
    "sg:phone":"+34 966 42 12 11",
    "sg:postcode":"03700",
    "sg:province":"Alicante",
    "wof:name":"Escortell Garcia Maria Dolores",
    "wof:placetype":"venue"
},
  "geometry": {"coordinates":[0.1026199982,38.8406333923],"type":"Point"}
}