{
  "type": "Feature",
  "properties": {
    "iso:country":"ES",
    "sg:address":"Calle de Portillo De Balboa, 7",
    "sg:city":"Valladolid",
    "sg:orig_category":"Inform\u00c1tica: Mantenimiento Y Reparaci\u00d3n De Ordenadores",
    "sg:phone":"+34 983 26 24 84",
    "sg:postcode":"47010",
    "sg:province":"Valladolid",
    "sg:website":"www.oli-service.es",
    "wof:name":"Oli-servi Castilla S.l.",
    "wof:placetype":"venue"
},
  "geometry": {"coordinates":[-4.721807003,41.6592216492],"type":"Point"}
}