{
  "type": "Feature",
  "properties": {
    "addr:full":"Avda Peris Y Valero, 186 Valencia Valencia 46006",
    "addr:housenumber":"186",
    "addr:postcode":"46006",
    "addr:street":"Avda Peris Y Valero",
    "iso:country":"ES",
    "sg:address":"Avda Peris Y Valero, 186",
    "sg:city":"Valencia",
    "sg:orig_category":"Centros Empresariales",
    "sg:phone":"+34 963 33 61 48",
    "sg:postcode":"46006",
    "sg:province":"Valencia",
    "wof:name":"Asociacion Propietarios Empresarios Parque Natural De La Albufera",
    "wof:placetype":"venue"
},
  "geometry": {"coordinates":[-0.3709344864,39.4589653015],"type":"Point"}
}