{
  "type": "Feature",
  "properties": {
    "iso:country":"ES",
    "sg:address":"Canteras, 6",
    "sg:city":"Torremendo",
    "sg:orig_category":"Inmobiliaria (agencias)",
    "sg:phone":"+34 965 36 82 68",
    "sg:postcode":"03313",
    "sg:province":"Alicante",
    "wof:name":"Pal View Properties Sl",
    "wof:placetype":"venue"
},
  "geometry": {"coordinates":[-0.8666229844,37.9913482666],"type":"Point"}
}