{
  "type": "Feature",
  "properties": {
    "iso:country":"ES",
    "sg:address":"Calle de Alcal.marcial Franco, 4",
    "sg:city":"San Fernando",
    "sg:orig_category":"Cajas Para Embalar",
    "sg:phone":"+34 928 77 45 12",
    "sg:postcode":"35100",
    "sg:province":"Las Palmas",
    "wof:name":"Caja Rural De Canarias",
    "wof:placetype":"venue"
},
  "geometry": {"coordinates":[-15.5837392807,28.090631485],"type":"Point"}
}