{
  "type": "Feature",
  "properties": {
    "addr:full":"Carrer de Samalus, 2 Garriga Barcelona 08530",
    "addr:housenumber":"2",
    "addr:postcode":"08530",
    "addr:street":"Carrer De Samalus",
    "iso:country":"ES",
    "sg:address":"Carrer de Samalus, 2",
    "sg:city":"Garriga",
    "sg:orig_category":"M\u00c9dicos: Estomatolog\u00cda",
    "sg:phone":"+34 938 71 58 04",
    "sg:postcode":"08530",
    "sg:province":"Barcelona",
    "wof:name":"Cordero Buchmann Susana-josefina",
    "wof:placetype":"venue"
},
  "geometry": {"coordinates":[2.2858450413,41.6842765808],"type":"Point"}
}