{
  "type": "Feature",
  "properties": {
    "addr:full":"Mayor-nagusia Kalea, 3 Iru\u00f1a Navarra 31001",
    "addr:housenumber":"3",
    "addr:postcode":"31001",
    "addr:street":"Mayor-Nagusia Kalea",
    "iso:country":"ES",
    "sg:address":"Mayor-nagusia Kalea, 3",
    "sg:city":"Iru\u00f1a",
    "sg:orig_category":"Perfumer\u00cda (al Por Menor)",
    "sg:phone":"+34 948 22 53 45",
    "sg:postcode":"31001",
    "sg:province":"Navarra",
    "wof:name":"Esparza Ecay Maria",
    "wof:placetype":"venue"
},
  "geometry": {"coordinates":[-1.645318985,42.8181190491],"type":"Point"}
}