{
  "type": "Feature",
  "properties": {
    "addr:full":"Calle de Andalucia, 30 Malaga M\u00e1laga 29009",
    "addr:housenumber":"30",
    "addr:postcode":"29009",
    "addr:street":"Calle De Andalucia;Ma\u0301Laga",
    "iso:country":"ES",
    "sg:address":"Calle de Andalucia, 30",
    "sg:city":"Malaga",
    "sg:orig_category":"Inmobiliaria (agencias)",
    "sg:phone":"+34 952 64 07 80",
    "sg:postcode":"29009",
    "sg:province":"M\u00e1laga",
    "wof:name":"Ropely 1999 S.l.",
    "wof:placetype":"venue"
},
  "geometry": {"coordinates":[-4.4353117943,36.7238578796],"type":"Point"}
}