{
  "type": "Feature",
  "properties": {
    "addr:full":"Calle de Ambrosio Cotes, 4 Villena Alicante 03400",
    "addr:housenumber":"4",
    "addr:postcode":"03400",
    "addr:street":"Calle De Ambrosio Cotes",
    "iso:country":"ES",
    "sg:address":"Calle de Ambrosio Cotes, 4",
    "sg:city":"Villena",
    "sg:orig_category":"Confecci\u00d3n De Zapatos",
    "sg:phone":"+34 965 80 29 51",
    "sg:postcode":"03400",
    "sg:province":"Alicante",
    "wof:name":"Ruespino S. L.",
    "wof:placetype":"venue"
},
  "geometry": {"coordinates":[-0.8698260784,38.6451148987],"type":"Point"}
}