{
  "type": "Feature",
  "properties": {
    "iso:country":"ES",
    "sg:address":"Sierra De Carrascoy, S/n",
    "sg:city":"Alhama Murcia",
    "sg:orig_category":"Explotaci\u00d3n De Canteras",
    "sg:phone":"+34 968 43 15 08",
    "sg:postcode":"30840",
    "sg:province":"Murcia",
    "wof:name":"Porfidos Internacionales De Alhama S.l.",
    "wof:placetype":"venue"
},
  "geometry": {"coordinates":[-1.4241490364,37.8507995605],"type":"Point"}
}