{
  "type": "Feature",
  "properties": {
    "iso:country":"ES",
    "sg:address":"Carrer de Pallars, 5",
    "sg:city":"Sabadell",
    "sg:orig_category":"Bebidas",
    "sg:phone":"+34 937 16 90 00",
    "sg:postcode":"08207",
    "sg:province":"Barcelona",
    "wof:name":"Abad Herranz Daniel",
    "wof:placetype":"venue"
},
  "geometry": {"coordinates":[2.092975,41.566532],"type":"Point"}
}