{
  "type": "Feature",
  "properties": {
    "iso:country":"ES",
    "sg:address":"Calle de Silos, 20",
    "sg:city":"Aracena",
    "sg:orig_category":"Chapister\u00cda",
    "sg:phone":"+34 959 12 87 18",
    "sg:postcode":"21200",
    "sg:province":"Huelva",
    "wof:name":"Gonzalez Barbudo Victoriano",
    "wof:placetype":"venue"
},
  "geometry": {"coordinates":[-6.5638837814,37.8973922729],"type":"Point"}
}