{
  "type": "Feature",
  "properties": {
    "iso:country":"ES",
    "sg:address":"Calle de Madre Antonia Paris, 4",
    "sg:city":"Madrid",
    "sg:orig_category":"Sociedades, Compa\u00d1\u00cdas Aseguradoras",
    "sg:phone":"+34 914 05 07 29",
    "sg:postcode":"28027",
    "sg:province":"Madrid",
    "wof:name":"Fiasegur S.l.",
    "wof:placetype":"venue"
},
  "geometry": {"coordinates":[-3.6515569687,40.4445762634],"type":"Point"}
}