{
  "type": "Feature",
  "properties": {
    "iso:country":"ES",
    "sg:address":"Avda Andalucia (de), 87",
    "sg:city":"Estepa",
    "sg:orig_category":"M\u00c9dicos: Estomatolog\u00cda",
    "sg:phone":"+34 955 91 40 27",
    "sg:postcode":"41560",
    "sg:province":"Sevilla",
    "wof:name":"Gil Martin Dolores",
    "wof:placetype":"venue"
},
  "geometry": {"coordinates":[-4.8810219765,37.2944984436],"type":"Point"}
}