{
  "type": "Feature",
  "properties": {
    "addr:full":"Carrer de Antoni Gaudi, 16 Reus Tarragona 43202",
    "addr:housenumber":"16",
    "addr:postcode":"43202",
    "addr:street":"Carrer De Antoni Gaudi",
    "iso:country":"ES",
    "sg:address":"Carrer de Antoni Gaudi, 16",
    "sg:city":"Reus",
    "sg:orig_category":"Asesor\u00cda Fiscal Y Jur\u00cddica",
    "sg:phone":"+34 977 31 47 67",
    "sg:postcode":"43202",
    "sg:province":"Tarragona",
    "wof:name":"Ventura Assessors S.l.",
    "wof:placetype":"venue"
},
  "geometry": {"coordinates":[1.1050950289,41.1594467163],"type":"Point"}
}