{
  "type": "Feature",
  "properties": {
    "iso:country":"ES",
    "sg:address":"Gral. Mola, 5",
    "sg:city":"Chiloeches",
    "sg:orig_category":"Iglesia Cat\u00d3lica",
    "sg:phone":"+34 949 27 10 23",
    "sg:postcode":"19160",
    "sg:province":"Guadalajara",
    "wof:name":"Parroquia De Santa Eulalia De Merida",
    "wof:placetype":"venue"
},
  "geometry": {"coordinates":[-3.1623818874,40.5727577209],"type":"Point"}
}