{
  "type": "Feature",
  "properties": {
    "addr:full":"Plaz Constitucion (de La), 6 Torrevieja Alicante 03180",
    "addr:postcode":"03180",
    "iso:country":"ES",
    "sg:address":"Plaz Constitucion (de La), 6",
    "sg:city":"Torrevieja",
    "sg:orig_category":"Cervecer\u00cdas",
    "sg:phone":"+34 965 71 37 81",
    "sg:postcode":"03180",
    "sg:province":"Alicante",
    "wof:name":"Lalaguna Marin Jorge",
    "wof:placetype":"venue"
},
  "geometry": {"coordinates":[-0.6536790133,38.0173606873],"type":"Point"}
}