{
  "type": "Feature",
  "properties": {
    "iso:country":"ES",
    "sg:address":"Calle de Arenal, 10",
    "sg:city":"Puebla Almoradiel",
    "sg:orig_category":"Trabajos De Soldaduras",
    "sg:phone":"+34 925 17 88 34",
    "sg:postcode":"45840",
    "sg:province":"Toledo",
    "wof:name":"Solados Alicatados S.l.",
    "wof:placetype":"venue"
},
  "geometry": {"coordinates":[-3.1196208,39.5977478027],"type":"Point"}
}