{
  "type": "Feature",
  "properties": {
    "addr:full":"Calle de Rua Zapateria, 22 Plasencia C\u00e1ceres 10600",
    "addr:housenumber":"22",
    "addr:postcode":"10600",
    "addr:street":"Calle De Rua Zapateria;Ca\u0301Ceres",
    "iso:country":"ES",
    "sg:address":"Calle de Rua Zapateria, 22",
    "sg:city":"Plasencia",
    "sg:orig_category":"Art\u00cdculos De Decoraci\u00d3n",
    "sg:phone":"+34 927 41 24 11",
    "sg:postcode":"10600",
    "sg:province":"C\u00e1ceres",
    "wof:name":"Castro Sanchez Ernesto",
    "wof:placetype":"venue"
},
  "geometry": {"coordinates":[-6.0914030075,40.0295562744],"type":"Point"}
}