{
  "type": "Feature",
  "properties": {
    "addr:full":"Carrer de Pons I Gallarza, 60 Barcelona Barcelona 08030",
    "addr:housenumber":"60",
    "addr:postcode":"08030",
    "addr:street":"Carrer De Pons;Gallarza",
    "iso:country":"ES",
    "sg:address":"Carrer de Pons I Gallarza, 60",
    "sg:city":"Barcelona",
    "sg:orig_category":"Tapiceros Y Tapiceros",
    "sg:phone":"+34 933 46 87 05",
    "sg:postcode":"08030",
    "sg:province":"Barcelona",
    "wof:name":"Serrano Palleja Hermenegildo",
    "wof:placetype":"venue"
},
  "geometry": {"coordinates":[2.186355114,41.4356536865],"type":"Point"}
}