{
  "type": "Feature",
  "properties": {
    "addr:full":"Avda Miguel Rodriguez Bautista, 9 Santa Uxia De Ribeira La Coru\u00f1a 15960",
    "addr:housenumber":"9",
    "addr:postcode":"15960",
    "addr:street":"Avda Miguel Rodriguez Bautista;Corun\u0303A",
    "iso:country":"ES",
    "sg:address":"Avda Miguel Rodriguez Bautista, 9",
    "sg:city":"Santa Uxia De Ribeira",
    "sg:orig_category":"Agentes Generales De Seguros",
    "sg:phone":"+34 981 87 20 52",
    "sg:postcode":"15960",
    "sg:province":"La Coru\u00f1a",
    "wof:name":"Arnoso Monteagudo Jose Angel",
    "wof:placetype":"venue"
},
  "geometry": {"coordinates":[-8.9945173264,42.5560493469],"type":"Point"}
}