{
  "type": "Feature",
  "properties": {
    "iso:country":"ES",
    "sg:address":"Calle de Luis Rodriguez, 11",
    "sg:city":"Piedrabuena",
    "sg:orig_category":"Estancos",
    "sg:phone":"+34 926 76 00 69",
    "sg:postcode":"13100",
    "sg:province":"Ciudad Real",
    "wof:name":"Hidalgo Garcia Agustina Eduarda",
    "wof:placetype":"venue"
},
  "geometry": {"coordinates":[-4.1747298241,39.0347099304],"type":"Point"}
}