{
  "type": "Feature",
  "properties": {
    "addr:full":"Calle de San Juan, 22 Pozo Ca\u00e7ada Albacete 02510",
    "addr:housenumber":"22",
    "addr:postcode":"02510",
    "addr:street":"Calle De San Juan",
    "iso:country":"ES",
    "sg:address":"Calle de San Juan, 22",
    "sg:city":"Pozo Ca\u00e7ada",
    "sg:orig_category":"Reposter\u00cdas",
    "sg:phone":"+34 967 25 01 05",
    "sg:postcode":"02510",
    "sg:province":"Albacete",
    "wof:name":"Davia Sanchez Jose",
    "wof:placetype":"venue"
},
  "geometry": {"coordinates":[-1.7358789444,38.8025093079],"type":"Point"}
}