{
  "type": "Feature",
  "properties": {
    "iso:country":"ES",
    "sg:address":"Calle de Aristoteles, 10",
    "sg:city":"Madrid",
    "sg:orig_category":"Agencias Y Agentes Comerciales, Representantes",
    "sg:phone":"+34 914 03 71 04",
    "sg:postcode":"28027",
    "sg:province":"Madrid",
    "wof:name":"Lastra Jimenez Maria Julia",
    "wof:placetype":"venue"
},
  "geometry": {"coordinates":[-3.6514463425,40.4424514771],"type":"Point"}
}