{
  "type": "Feature",
  "properties": {
    "addr:full":"Calle de San Antolin, 5 Madrid Madrid 28025",
    "addr:housenumber":"5",
    "addr:postcode":"28025",
    "addr:street":"Calle De San Antolin",
    "iso:country":"ES",
    "sg:address":"Calle de San Antolin, 5",
    "sg:city":"Madrid",
    "sg:orig_category":"Ropa Para Se\u00d1oras Y Caballeros (al Por Menor)",
    "sg:phone":"+34 914 62 90 95",
    "sg:postcode":"28025",
    "sg:province":"Madrid",
    "wof:name":"Juvenal Gaviria S.l.",
    "wof:placetype":"venue"
},
  "geometry": {"coordinates":[-3.748183012,40.3789863586],"type":"Point"}
}