{
  "type": "Feature",
  "properties": {
    "addr:full":"Calle de Rafael Canogar, 4 Parla Madrid 28980",
    "addr:housenumber":"4",
    "addr:postcode":"28980",
    "addr:street":"Calle De Rafael Canogar",
    "iso:country":"ES",
    "sg:address":"Calle de Rafael Canogar, 4",
    "sg:city":"Parla",
    "sg:orig_category":"Empresas De Limpieza",
    "sg:phone":"+34 916 99 29 86",
    "sg:postcode":"28980",
    "sg:province":"Madrid",
    "wof:name":"Limpiezas Jockey S.l.",
    "wof:placetype":"venue"
},
  "geometry": {"coordinates":[-3.7598330975,40.2438011169],"type":"Point"}
}