{
  "type": "Feature",
  "properties": {
    "iso:country":"ES",
    "sg:address":"Ctra Boadilla-majadahonda (de), 34",
    "sg:city":"Boadilla Del Monte",
    "sg:orig_category":"Cl\u00cdnicas Dentales",
    "sg:phone":"+34 916 32 69 64",
    "sg:postcode":"28660",
    "sg:province":"Madrid",
    "wof:name":"Stetident Boadilla S.l.",
    "wof:placetype":"venue"
},
  "geometry": {"coordinates":[-3.8742079735,40.4075012207],"type":"Point"}
}