{
  "type": "Feature",
  "properties": {
    "iso:country":"ES",
    "sg:address":"Avda Alcalde Federico Molina, 30",
    "sg:city":"Huelva",
    "sg:orig_category":"Centros De Adelgazamiento Y De Est\u00c9tica",
    "sg:phone":"+34 959 27 09 72",
    "sg:postcode":"21006",
    "sg:province":"Huelva",
    "wof:name":"Perez Alvendiz Dolores",
    "wof:placetype":"venue"
},
  "geometry": {"coordinates":[-6.9349379539,37.2578353882],"type":"Point"}
}