{
  "type": "Feature",
  "properties": {
    "iso:country":"ES",
    "sg:address":"Plaz Constitucion (la), 5",
    "sg:city":"Laredo",
    "sg:orig_category":"Zapatos (al Por Menor)",
    "sg:phone":"+34 942 61 27 35",
    "sg:postcode":"39770",
    "sg:province":"Cantabria",
    "wof:name":"Baranda Pedraja Veronica",
    "wof:placetype":"venue"
},
  "geometry": {"coordinates":[-3.4123589993,43.4112815857],"type":"Point"}
}