{
  "type": "Feature",
  "properties": {
    "addr:full":"Calle de Petrer, 11 Elda Alicante 03600",
    "addr:housenumber":"11",
    "addr:postcode":"03600",
    "addr:street":"Calle De Petrer",
    "iso:country":"ES",
    "sg:address":"Calle de Petrer, 11",
    "sg:city":"Elda",
    "sg:orig_category":"Peluqueros: De Se\u00d1oras",
    "sg:phone":"+34 965 39 01 97",
    "sg:postcode":"03600",
    "sg:province":"Alicante",
    "wof:name":"Cantos Cano Ana Bel",
    "wof:placetype":"venue"
},
  "geometry": {"coordinates":[-0.7918609977,38.4795684814],"type":"Point"}
}