{
  "type": "Feature",
  "properties": {
    "addr:full":"Avda Aeronautica (la), 10 Sevilla Sevilla 41020",
    "addr:housenumber":"10",
    "addr:postcode":"41020",
    "addr:street":"Avda Aeronautica La",
    "iso:country":"ES",
    "sg:address":"Avda Aeronautica (la), 10",
    "sg:city":"Sevilla",
    "sg:orig_category":"Impuestos, Tesoro P\u00dablico",
    "sg:phone":"+34 954 40 93 39",
    "sg:postcode":"41020",
    "sg:province":"Sevilla",
    "wof:name":"Melgar Ezqueta S.l.",
    "wof:placetype":"venue"
},
  "geometry": {"coordinates":[-5.9197850227,37.3885612488],"type":"Point"}
}