{
  "type": "Feature",
  "properties": {
    "addr:full":"Calle de Burgo Nuevo, 14 Le\u00f3n Le\u00f3n 24001",
    "addr:housenumber":"14",
    "addr:postcode":"24001",
    "addr:street":"Calle De Burgo Nuevo;Leo\u0301N",
    "iso:country":"ES",
    "sg:address":"Calle de Burgo Nuevo, 14",
    "sg:city":"Le\u00f3n",
    "sg:orig_category":"Doctores En Medicina",
    "sg:phone":"+34 987 20 72 22",
    "sg:postcode":"24001",
    "sg:province":"Le\u00f3n",
    "wof:name":"Castro Garcia Julian",
    "wof:placetype":"venue"
},
  "geometry": {"coordinates":[-5.5725121498,42.5967025757],"type":"Point"}
}