{
  "type": "Feature",
  "properties": {
    "addr:full":"Carr Exercits Espanyols, 54 Alfas Pi Alicante 03580",
    "addr:housenumber":"54",
    "addr:postcode":"03580",
    "addr:street":"Carr Exercits Espanyols",
    "iso:country":"ES",
    "sg:address":"Carr Exercits Espanyols, 54",
    "sg:city":"Alfas Pi",
    "sg:orig_category":"Heladeros",
    "sg:phone":"+34 965 88 97 28",
    "sg:postcode":"03580",
    "sg:province":"Alicante",
    "wof:name":"Pla Jerez Inocencio Juan",
    "wof:placetype":"venue"
},
  "geometry": {"coordinates":[-0.1106439978,38.5881652832],"type":"Point"}
}