{
  "type": "Feature",
  "properties": {
    "addr:full":"Pso. Maritimo, 88 Torre Mar M\u00e1laga 29740",
    "addr:housenumber":"88",
    "addr:postcode":"29740",
    "addr:street":"Maritimo;Ma\u0301Laga",
    "iso:country":"ES",
    "sg:address":"Pso. Maritimo, 88",
    "sg:city":"Torre Mar",
    "sg:orig_category":"Cl\u00cdnicas M\u00c9dicas",
    "sg:phone":"+34 952 54 42 32",
    "sg:postcode":"29740",
    "sg:province":"M\u00e1laga",
    "wof:name":"Gambro Healthcare Espa\u00f1a S.l.",
    "wof:placetype":"venue"
},
  "geometry": {"coordinates":[-4.0865721703,36.7439498901],"type":"Point"}
}