{
  "type": "Feature",
  "properties": {
    "addr:full":"Calle de Jorge Guillen, 16 Albacete Albacete 02003",
    "addr:housenumber":"16",
    "addr:postcode":"02003",
    "addr:street":"Calle De Jorge Guillen",
    "iso:country":"ES",
    "sg:address":"Calle de Jorge Guillen, 16",
    "sg:city":"Albacete",
    "sg:orig_category":"Cajas De Ahorro",
    "sg:phone":"+34 967 50 56 17",
    "sg:postcode":"02003",
    "sg:province":"Albacete",
    "sg:website":"www.ccm.es",
    "wof:name":"Caja De Ahorros De Castilla La Mancha",
    "wof:placetype":"venue"
},
  "geometry": {"coordinates":[-1.8616499901,38.9909324646],"type":"Point"}
}