{
  "type": "Feature",
  "properties": {
    "addr:full":"Calle de Carlos Ramirez De Arellano, 19 Melilla Melilla 52004",
    "addr:housenumber":"19",
    "addr:postcode":"52004",
    "addr:street":"Calle De Carlos Ramirez De Arellano",
    "iso:country":"ES",
    "sg:address":"Calle de Carlos Ramirez De Arellano, 19",
    "sg:city":"Melilla",
    "sg:orig_category":"Carnicer\u00cdas, Carnicer\u00cdas",
    "sg:phone":"+34 952 68 22 13",
    "sg:postcode":"52004",
    "sg:province":"Melilla",
    "wof:name":"Bueno Bonilla Jose",
    "wof:placetype":"venue"
},
  "geometry": {"coordinates":[-2.9445855618,35.2914009094],"type":"Point"}
}