{
  "type": "Feature",
  "properties": {
    "iso:country":"ES",
    "sg:address":"Calle de Montemar, 46",
    "sg:city":"Torremolinos",
    "sg:orig_category":"Juegos Y Juguetes (al Por Menor)",
    "sg:phone":"+34 952 38 67 27",
    "sg:postcode":"29620",
    "sg:province":"M\u00e1laga",
    "wof:name":"Hoteles Dimona S. A.",
    "wof:placetype":"venue"
},
  "geometry": {"coordinates":[-4.5082092285,36.6100311279],"type":"Point"}
}