{
  "type": "Feature",
  "properties": {
    "addr:full":"Calle de Corredera (la), 11 Montilla C\u00f3rdoba 14550",
    "addr:housenumber":"11",
    "addr:postcode":"14550",
    "addr:street":"Calle De Corredera La;Co\u0301Rdoba",
    "iso:country":"ES",
    "sg:address":"Calle de Corredera (la), 11",
    "sg:city":"Montilla",
    "sg:orig_category":"Electrodom\u00c9sticos (al Por Menor)",
    "sg:phone":"+34 957 65 14 20",
    "sg:postcode":"14550",
    "sg:province":"C\u00f3rdoba",
    "wof:name":"Hermanos Fernandez Cordoba S.l.",
    "wof:placetype":"venue"
},
  "geometry": {"coordinates":[-4.638361454,37.5891990662],"type":"Point"}
}