{
  "type": "Feature",
  "properties": {
    "iso:country":"ES",
    "sg:address":"Calle de Concilio, 2",
    "sg:city":"Valencia De Don Juan",
    "sg:orig_category":"Bancos",
    "sg:phone":"+34 987 75 21 13",
    "sg:postcode":"24200",
    "sg:province":"Le\u00f3n",
    "wof:name":"Vitalicio Seguros",
    "wof:placetype":"venue"
},
  "geometry": {"coordinates":[-5.520277977,42.2920265198],"type":"Point"}
}