{
  "type": "Feature",
  "properties": {
    "addr:full":"Calle de Clavel, 1 Union Murcia 30360",
    "addr:housenumber":"1",
    "addr:postcode":"30360",
    "addr:street":"Calle De Clavel",
    "iso:country":"ES",
    "sg:address":"Calle de Clavel, 1",
    "sg:city":"Union",
    "sg:orig_category":"Aguas (distribuci\u00d3n, Servicios)",
    "sg:phone":"+34 968 54 07 39",
    "sg:postcode":"30360",
    "sg:province":"Murcia",
    "wof:name":"La Union De Servicios Municipales S.a.",
    "wof:placetype":"venue"
},
  "geometry": {"coordinates":[-0.8745942116,37.6176071167],"type":"Point"}
}