{
  "type": "Feature",
  "properties": {
    "iso:country":"ES",
    "sg:address":"Ctra San Martin De Montalban, S/n",
    "sg:city":"Puebla Montalban",
    "sg:orig_category":"M\u00c1rmoles, Granitos Y Piedras Naturales",
    "sg:phone":"+34 925 75 13 66",
    "sg:postcode":"45516",
    "sg:province":"Toledo",
    "wof:name":"Ingemarto S.a.",
    "wof:placetype":"venue"
},
  "geometry": {"coordinates":[-4.3606085777,39.8533782959],"type":"Point"}
}