{
  "type": "Feature",
  "properties": {
    "iso:country":"ES",
    "sg:address":"Calle de Garci Perez De Vargas, 1",
    "sg:city":"Fuente Del Rey",
    "sg:orig_category":"Farmacias",
    "sg:phone":"+34 954 69 10 50",
    "sg:postcode":"41700",
    "sg:province":"Sevilla",
    "wof:name":"Visuerte Sanchez Antonio Felix",
    "wof:placetype":"venue"
},
  "geometry": {"coordinates":[-5.9756040573,37.3112182617],"type":"Point"}
}