{
  "type": "Feature",
  "properties": {
    "iso:country":"ES",
    "sg:address":"Calle de General Pardi\u00d1as, 57",
    "sg:city":"Madrid",
    "sg:orig_category":"Frutas, Legumbres Frescas Y Tempranas (al Por Menor)",
    "sg:phone":"+34 915 77 20 61",
    "sg:postcode":"28006",
    "sg:province":"Madrid",
    "wof:name":"Garcia Bartolome Lucio",
    "wof:placetype":"venue"
},
  "geometry": {"coordinates":[-3.6782689095,40.4315109253],"type":"Point"}
}