{
  "type": "Feature",
  "properties": {
    "addr:full":"Calle de Matacan (de), 15 Colmenar Viejo Madrid 28770",
    "addr:postcode":"28770",
    "addr:street":"Calle De Matacan De",
    "iso:country":"ES",
    "sg:address":"Calle de Matacan (de), 15",
    "sg:city":"Colmenar Viejo",
    "sg:orig_category":"Molduras, Junquillos, Listones Y Molduras Perforadas",
    "sg:phone":"+34 918 45 39 89",
    "sg:postcode":"28770",
    "sg:province":"Madrid",
    "wof:name":"Doral Chapado Aurora",
    "wof:placetype":"venue"
},
  "geometry": {"coordinates":[-3.76790905,40.6640472412],"type":"Point"}
}