{
  "type": "Feature",
  "properties": {
    "iso:country":"ES",
    "sg:address":"Carrer de Tarragona, 42",
    "sg:city":"Mataro",
    "sg:orig_category":"Perfumer\u00cda, Art\u00cdculos De Ba\u00d1o (fabricaci\u00d3n, Al Por Mayor)",
    "sg:phone":"+34 937 41 13 23",
    "sg:postcode":"08303",
    "sg:province":"Barcelona",
    "wof:name":"Displamer S.a.",
    "wof:placetype":"venue"
},
  "geometry": {"coordinates":[2.4241709709,41.5446281433],"type":"Point"}
}