{
  "type": "Feature",
  "properties": {
    "addr:full":"Carrer de Nord, 11 Vendrell Tarragona 43700",
    "addr:housenumber":"11",
    "addr:postcode":"43700",
    "addr:street":"Carrer De Nord",
    "iso:country":"ES",
    "sg:address":"Carrer de Nord, 11",
    "sg:city":"Vendrell",
    "sg:orig_category":"Sindicatos De Trabajadores",
    "sg:phone":"+34 977 66 09 32",
    "sg:postcode":"43700",
    "sg:province":"Tarragona",
    "wof:name":"Confederacio General Del Treball De Catalunya",
    "wof:placetype":"venue"
},
  "geometry": {"coordinates":[1.5361380577,41.2214584351],"type":"Point"}
}