{
  "type": "Feature",
  "properties": {
    "iso:country":"ES",
    "sg:address":"Carrer de Doctor Trueta, 176",
    "sg:city":"Barcelona",
    "sg:orig_category":"Molduras, Junquillos, Listones Y Molduras Perforadas",
    "sg:phone":"+34 932 25 07 83",
    "sg:postcode":"08005",
    "sg:province":"Barcelona",
    "wof:name":"Perez Perez Miguel",
    "wof:placetype":"venue"
},
  "geometry": {"coordinates":[2.2013309002,41.3968276978],"type":"Point"}
}