{
  "type": "Feature",
  "properties": {
    "iso:country":"ES",
    "sg:address":"Carrer de Prat De La Riba, 30",
    "sg:city":"Santa Perpetua De Mogoda",
    "sg:orig_category":"Notarios",
    "sg:phone":"+34 935 74 90 15",
    "sg:postcode":"08130",
    "sg:province":"Barcelona",
    "wof:name":"Querol Martin Josefa",
    "wof:placetype":"venue"
},
  "geometry": {"coordinates":[2.1814520359,41.5354614258],"type":"Point"}
}