{
  "type": "Feature",
  "properties": {
    "addr:full":"Calle de Villaverde, 9 Getafe Madrid 28902",
    "addr:housenumber":"9",
    "addr:postcode":"28902",
    "addr:street":"Calle De Villaverde",
    "iso:country":"ES",
    "sg:address":"Calle de Villaverde, 9",
    "sg:city":"Getafe",
    "sg:orig_category":"Oficinas: Suministros Para (fabricaci\u00d3n, Al Por Mayor)",
    "sg:phone":"+34 916 83 17 80",
    "sg:postcode":"28902",
    "sg:province":"Madrid",
    "wof:name":"Fernandez Fernandez Francisco",
    "wof:placetype":"venue"
},
  "geometry": {"coordinates":[-3.7285289764,40.3093757629],"type":"Point"}
}