{
  "type": "Feature",
  "properties": {
    "addr:full":"Avda Habaneras (de Las), 93 Torrevieja Alicante 03180",
    "addr:housenumber":"93",
    "addr:postcode":"03180",
    "addr:street":"Avda Habaneras De Las",
    "iso:country":"ES",
    "sg:address":"Avda Habaneras (de Las), 93",
    "sg:city":"Torrevieja",
    "sg:orig_category":"Promotores Constructores",
    "sg:phone":"+34 965 71 73 06",
    "sg:postcode":"03180",
    "sg:province":"Alicante",
    "wof:name":"Construcciones San Joaquin S.l.",
    "wof:placetype":"venue"
},
  "geometry": {"coordinates":[-0.6668170094,37.9806632996],"type":"Point"}
}