{
  "type": "Feature",
  "properties": {
    "addr:full":"Rua Regueiro, 7 Vigo Pontevedra 36211",
    "addr:housenumber":"7",
    "addr:postcode":"36211",
    "addr:street":"Rua Regueiro",
    "iso:country":"ES",
    "sg:address":"Rua Regueiro, 7",
    "sg:city":"Vigo",
    "sg:orig_category":"Agencias De Viajes",
    "sg:phone":"+34 986 49 30 62",
    "sg:postcode":"36211",
    "sg:province":"Pontevedra",
    "wof:name":"Viajes Iberia S.a.",
    "wof:placetype":"venue"
},
  "geometry": {"coordinates":[-8.7289953232,42.2227859497],"type":"Point"}
}