{
  "type": "Feature",
  "properties": {
    "iso:country":"ES",
    "sg:address":"Calle de Gaunas (las), 1",
    "sg:city":"Logro\u00f1o",
    "sg:orig_category":"Iglesia Cat\u00d3lica",
    "sg:phone":"+34 941 21 29 17",
    "sg:postcode":"26002",
    "sg:province":"La Rioja",
    "wof:name":"Moreno Martinez Jose Luis",
    "wof:placetype":"venue"
},
  "geometry": {"coordinates":[-2.4500966072,42.4571075439],"type":"Point"}
}