{
  "type": "Feature",
  "properties": {
    "iso:country":"ES",
    "sg:address":"Pase Fernando El Catolico, 8",
    "sg:city":"Zaragoza",
    "sg:orig_category":"Loter\u00cda Y T\u00d3mbola",
    "sg:phone":"+34 976 35 62 08",
    "sg:postcode":"50005",
    "sg:province":"Zaragoza",
    "wof:name":"Ara Collados Maria Teresa Rosario Felisa",
    "wof:placetype":"venue"
},
  "geometry": {"coordinates":[-0.8927074075,41.6435012817],"type":"Point"}
}