{
  "type": "Feature",
  "properties": {
    "iso:country":"ES",
    "sg:address":"Rua Sagasta, 2",
    "sg:city":"Pontevedra",
    "sg:orig_category":"Notarios",
    "sg:phone":"+34 986 85 23 12",
    "sg:postcode":"36001",
    "sg:province":"Pontevedra",
    "wof:name":"Diaz Gonzalez Mariano",
    "wof:placetype":"venue"
},
  "geometry": {"coordinates":[-8.6411190033,42.4301757812],"type":"Point"}
}