{
  "type": "Feature",
  "properties": {
    "addr:full":"Calle de Embajador Vich, 3 Valencia Valencia 46002",
    "addr:housenumber":"3",
    "addr:postcode":"46002",
    "addr:street":"Calle De Embajador Vich",
    "iso:country":"ES",
    "sg:address":"Calle de Embajador Vich, 3",
    "sg:city":"Valencia",
    "sg:classifiers":[
        {
            "category":"Communications",
            "type":"Services"
        }
    ],
    "sg:phone":"+34 963 51 27 11",
    "sg:postcode":"46002",
    "sg:province":"Valencia",
    "sg:tags":[
        "televisiones",
        "y",
        "radio"
    ],
    "wof:name":"Centre De Telecomunicaciones De Catalunya",
    "wof:placetype":"venue"
},
  "geometry": {"coordinates":[-0.3753600121,39.4726104736],"type":"Point"}
}