{
  "type": "Feature",
  "properties": {
    "addr:full":"Crespo Quintana, 11 Torrelavega Cantabria 39300",
    "addr:housenumber":"11",
    "addr:postcode":"39300",
    "addr:street":"Crespo Quintana",
    "iso:country":"ES",
    "sg:address":"Crespo Quintana, 11",
    "sg:city":"Torrelavega",
    "sg:orig_category":"Centros De Coordinaci\u00d3n",
    "sg:phone":"+34 942 80 80 40",
    "sg:postcode":"39300",
    "sg:province":"Cantabria",
    "wof:name":"Empresa De Servicios Confisges S.l.",
    "wof:placetype":"venue"
},
  "geometry": {"coordinates":[-4.0520391464,43.34897995],"type":"Point"}
}