{
  "type": "Feature",
  "properties": {
    "addr:full":"Calle de Alegria De La Huerta, 5 Sangonera Seca Murcia 30835",
    "addr:housenumber":"5",
    "addr:postcode":"30835",
    "addr:street":"Calle De Alegria De La Huerta",
    "iso:country":"ES",
    "sg:address":"Calle de Alegria De La Huerta, 5",
    "sg:city":"Sangonera Seca",
    "sg:orig_category":"Electricidad: Instaladores",
    "sg:phone":"+34 968 80 35 70",
    "sg:postcode":"30835",
    "sg:province":"Murcia",
    "wof:name":"Frabalsan S.l.",
    "wof:placetype":"venue"
},
  "geometry": {"coordinates":[-1.2412611246,37.955078125],"type":"Point"}
}