{
  "type": "Feature",
  "properties": {
    "addr:full":"Bouzavedra (san Jorge), 1 Bouzavedra Pontevedra 36473",
    "addr:housenumber":"1",
    "addr:postcode":"36473",
    "addr:street":"Jorge",
    "iso:country":"ES",
    "sg:address":"Bouzavedra (san Jorge), 1",
    "sg:city":"Bouzavedra",
    "sg:orig_category":"Explotaci\u00d3n De Canteras",
    "sg:phone":"+34 986 34 72 98",
    "sg:postcode":"36473",
    "sg:province":"Pontevedra",
    "wof:name":"Francisco Lemos Romero S.l.",
    "wof:placetype":"venue"
},
  "geometry": {"coordinates":[-8.5753936768,42.1124839783],"type":"Point"}
}