{
  "type": "Feature",
  "properties": {
    "addr:full":"Bo. Seixabre, 14 Seixabre Pontevedra 36417",
    "addr:housenumber":"14",
    "addr:postcode":"36417",
    "addr:street":"Bo. Seixabre",
    "iso:country":"ES",
    "sg:address":"Bo. Seixabre, 14",
    "sg:city":"Seixabre",
    "sg:orig_category":"Asociaciones Humanitarias, De Cooperaci\u00d3n, De Acci\u00d3n Social",
    "sg:phone":"+34 986 48 68 92",
    "sg:postcode":"36417",
    "sg:province":"Pontevedra",
    "wof:name":"Asociacion Disminuidos Fisicos Y Psiquicos De Mos",
    "wof:placetype":"venue"
},
  "geometry": {"coordinates":[-8.6480531693,42.4336204529],"type":"Point"}
}