{
  "type": "Feature",
  "properties": {
    "addr:full":"Calle de Duquesa De Parcent, 12 Malaga M\u00e1laga 29001",
    "addr:housenumber":"12",
    "addr:postcode":"29001",
    "addr:street":"Calle De Duquesa De Parcent;Ma\u0301Laga",
    "iso:country":"ES",
    "sg:address":"Calle de Duquesa De Parcent, 12",
    "sg:city":"Malaga",
    "sg:classifiers":[
        {
            "category":"Arts & Performance",
            "subcategory":"Art Gallery",
            "type":"Entertainment"
        }
    ],
    "sg:phone":"+34 952 21 65 92",
    "sg:postcode":"29001",
    "sg:province":"M\u00e1laga",
    "sg:tags":[
        "arte",
        "de",
        "galer\u00cdas"
    ],
    "wof:name":"Marin Alonso Javier",
    "wof:placetype":"venue"
},
  "geometry": {"coordinates":[-4.4237213135,36.71434021],"type":"Point"}
}