{
  "type": "Feature",
  "properties": {
    "iso:country":"ES",
    "sg:address":"Calle de Galicia, 88",
    "sg:city":"Mancha Real",
    "sg:orig_category":"Quincaller\u00cda (al Por Menor)",
    "sg:phone":"+34 953 35 26 68",
    "sg:postcode":"23100",
    "sg:province":"Ja\u00e9n",
    "wof:name":"Formas Y Perfiles S.l.",
    "wof:placetype":"venue"
},
  "geometry": {"coordinates":[-3.6074290276,37.7809829712],"type":"Point"}
}