{
  "type": "Feature",
  "properties": {
    "iso:country":"ES",
    "sg:address":"Cmno Basozabal De, 79",
    "sg:city":"Donostia-san Sebastian",
    "sg:orig_category":"Perreras, Pensiones Para Perros, Gatos Y Otros Animales",
    "sg:phone":"+34 943 33 18 98",
    "sg:postcode":"20014",
    "sg:province":"Guip\u00f9zcoa",
    "wof:name":"Akazeta Elkartea S.cv.",
    "wof:placetype":"venue"
},
  "geometry": {"coordinates":[-1.9652154446,43.2807426453],"type":"Point"}
}