{
  "type": "Feature",
  "properties": {
    "addr:full":"Calle de Pablo Picasso, S/n Pinto Madrid 28320",
    "addr:housenumber":"s / n",
    "addr:postcode":"28320",
    "addr:street":"Calle De Pablo Picasso;Pinto",
    "iso:country":"ES",
    "sg:address":"Calle de Pablo Picasso, S/n",
    "sg:city":"Pinto",
    "sg:orig_category":"Barbacoas Y Accesorios",
    "sg:phone":"+34 916 92 51 48",
    "sg:postcode":"28320",
    "sg:province":"Madrid",
    "wof:name":"H R G S L S U",
    "wof:placetype":"venue"
},
  "geometry": {"coordinates":[-3.6949789524,40.2378349304],"type":"Point"}
}