{
  "type": "Feature",
  "properties": {
    "addr:full":"Calle de Manuel De Falla, 9 Almonte Huelva 21730",
    "addr:housenumber":"9",
    "addr:postcode":"21730",
    "addr:street":"Calle De Manuel De Falla",
    "iso:country":"ES",
    "sg:address":"Calle de Manuel De Falla, 9",
    "sg:city":"Almonte",
    "sg:orig_category":"Telas Y Sedas (al Por Menor)",
    "sg:phone":"+34 959 45 12 28",
    "sg:postcode":"21730",
    "sg:province":"Huelva",
    "wof:name":"Lopez Alba Daniel",
    "wof:placetype":"venue"
},
  "geometry": {"coordinates":[-6.5142102242,37.262260437],"type":"Point"}
}