{
  "type": "Feature",
  "properties": {
    "iso:country":"ES",
    "sg:address":"Pol Alaplana, S/n",
    "sg:city":"Vila-real",
    "sg:orig_category":"Aparatos De Iluminaci\u00d3n (al Por Menor)",
    "sg:phone":"+34 964 05 28 20",
    "sg:postcode":"12540",
    "sg:province":"Castell\u00f3n",
    "wof:name":"Proinsta Vila Real S.l.l.",
    "wof:placetype":"venue"
},
  "geometry": {"coordinates":[-0.0952899978,39.9453010559],"type":"Point"}
}