{
  "type": "Feature",
  "properties": {
    "addr:full":"Bo. Palmeral, 30 Callosa Segura Alicante 03360",
    "addr:housenumber":"30",
    "addr:postcode":"03360",
    "addr:street":"Palmeral",
    "iso:country":"ES",
    "sg:address":"Bo. Palmeral, 30",
    "sg:city":"Callosa Segura",
    "sg:orig_category":"Muebles, Minoristas",
    "sg:phone":"+34 966 75 64 08",
    "sg:postcode":"03360",
    "sg:province":"Alicante",
    "wof:name":"Rives Manresa Cayetano",
    "wof:placetype":"venue"
},
  "geometry": {"coordinates":[-0.8776689768,38.1256752014],"type":"Point"}
}