{
  "type": "Feature",
  "properties": {
    "addr:full":"Calle de Pe\u00d1a De La Atalaya, 31 Madrid Madrid 28053",
    "addr:housenumber":"31",
    "addr:postcode":"madrid;28053",
    "addr:street":"Calle De Pen\u0303A De La Atalaya",
    "iso:country":"ES",
    "sg:address":"Calle de Pe\u00d1a De La Atalaya, 31",
    "sg:city":"Madrid",
    "sg:orig_category":"Veh\u00cdculos De Ocasi\u00d3n",
    "sg:phone":"+34 914 37 48 44",
    "sg:postcode":"28053",
    "sg:province":"Madrid",
    "wof:name":"Garcia Mendez Juan",
    "wof:placetype":"venue"
},
  "geometry": {"coordinates":[-3.6653978825,40.3875732422],"type":"Point"}
}