{
  "type": "Feature",
  "properties": {
    "iso:country":"ES",
    "sg:address":"Ligallo Del Roig, S/n",
    "sg:city":"Ligallo Del Roig",
    "sg:orig_category":"Mec\u00c1nico Del Autom\u00d3vil",
    "sg:phone":"+34 977 47 02 19",
    "sg:postcode":"43894",
    "sg:province":"Tarragona",
    "wof:name":"Mecanica J.p. Guarts.l.",
    "wof:placetype":"venue"
},
  "geometry": {"coordinates":[0.6723750234,40.7711791992],"type":"Point"}
}