{
  "type": "Feature",
  "properties": {
    "addr:full":"Major, 64 Masquefa Barcelona 08783",
    "addr:housenumber":"64",
    "addr:postcode":"08783",
    "addr:street":"Major",
    "iso:country":"ES",
    "sg:address":"Major, 64",
    "sg:city":"Masquefa",
    "sg:classifiers":[
        {
            "category":"Utilities",
            "subcategory":"Natural Gas",
            "type":"Services"
        }
    ],
    "sg:phone":"+34 937 72 80 30",
    "sg:postcode":"08783",
    "sg:province":"Barcelona",
    "sg:tags":[
        "te",
        "de",
        "salones"
    ],
    "wof:name":"Lopez Sancho Jose Maria",
    "wof:placetype":"venue"
},
  "geometry": {"coordinates":[1.8117879629,41.5021934509],"type":"Point"}
}