{
  "type": "Feature",
  "properties": {
    "addr:full":"Carrer de Sant Elm, 22 Roses Girona 17480",
    "addr:housenumber":"22",
    "addr:postcode":"17480",
    "addr:street":"Carrer De Sant Elm",
    "iso:country":"ES",
    "sg:address":"Carrer de Sant Elm, 22",
    "sg:city":"Roses",
    "sg:orig_category":"Peluqueros: De Se\u00d1oras",
    "sg:phone":"+34 972 25 62 69",
    "sg:postcode":"17480",
    "sg:province":"Girona",
    "wof:name":"Compte Fages Ana Maria",
    "wof:placetype":"venue"
},
  "geometry": {"coordinates":[3.1768870354,42.2612876892],"type":"Point"}
}