{
  "type": "Feature",
  "properties": {
    "addr:full":"Calle de Grande, 25 Calahorra La Rioja 26500",
    "addr:housenumber":"25",
    "addr:postcode":"26500",
    "addr:street":"Calle De Grande",
    "iso:country":"ES",
    "sg:address":"Calle de Grande, 25",
    "sg:city":"Calahorra",
    "sg:orig_category":"Confecci\u00d3n De Trajes Para Se\u00d1oras",
    "sg:phone":"+34 941 13 00 84",
    "sg:postcode":"26500",
    "sg:province":"La Rioja",
    "wof:name":"Damita S.cv.",
    "wof:placetype":"venue"
},
  "geometry": {"coordinates":[-1.9626430273,42.3021965027],"type":"Point"}
}