{
  "type": "Feature",
  "properties": {
    "iso:country":"ES",
    "sg:address":"Calle de Micer Masco, 19",
    "sg:city":"Valencia",
    "sg:orig_category":"Molduras, Junquillos, Listones Y Molduras Perforadas",
    "sg:phone":"+34 963 69 55 20",
    "sg:postcode":"46010",
    "sg:province":"Valencia",
    "wof:name":"Vidal Berni Concepcion",
    "wof:placetype":"venue"
},
  "geometry": {"coordinates":[-0.3621389866,39.4754676819],"type":"Point"}
}