{
  "type": "Feature",
  "properties": {
    "addr:full":"Carr Sant Pau, 25 Figueres Girona 17600",
    "addr:housenumber":"25",
    "addr:postcode":"17600",
    "addr:street":"Carr Sant Pau",
    "iso:country":"ES",
    "sg:address":"Carr Sant Pau, 25",
    "sg:city":"Figueres",
    "sg:orig_category":"M\u00c9dicos: An\u00c1lisis Cl\u00cdnicos",
    "sg:phone":"+34 972 50 09 73",
    "sg:postcode":"17600",
    "sg:province":"Girona",
    "wof:name":"Alcina Laine Luis",
    "wof:placetype":"venue"
},
  "geometry": {"coordinates":[2.9616689682,42.26512146],"type":"Point"}
}