{
  "type": "Feature",
  "properties": {
    "addr:full":"Lu Lomas, S/n Albujon Murcia 30330",
    "addr:housenumber":"s",
    "addr:postcode":"30330",
    "addr:street":"/ N",
    "iso:country":"ES",
    "sg:address":"Lu Lomas, S/n",
    "sg:city":"Albujon",
    "sg:orig_category":"Tractores Agr\u00cdcolas Y Remolques",
    "sg:phone":"+34 968 55 01 40",
    "sg:postcode":"30330",
    "sg:province":"Murcia",
    "wof:name":"Conesa Sanchez Andres",
    "wof:placetype":"venue"
},
  "geometry": {"coordinates":[-1.0482540131,37.7187614441],"type":"Point"}
}