{
  "type": "Feature",
  "properties": {
    "addr:full":"Avda Sinforiano Madro\u00d1ero, 14 Badajoz Badajoz 06011",
    "addr:housenumber":"14",
    "addr:postcode":"06011",
    "addr:street":"Avda Sinforiano Madron\u0303Ero",
    "iso:country":"ES",
    "sg:address":"Avda Sinforiano Madro\u00d1ero, 14",
    "sg:city":"Badajoz",
    "sg:orig_category":"Inmobiliaria (agencias)",
    "sg:phone":"+34 924 24 60 00",
    "sg:postcode":"06011",
    "sg:province":"Badajoz",
    "sg:website":"www.tecnicasa.net",
    "wof:name":"Tecnicasa S.l.",
    "wof:placetype":"venue"
},
  "geometry": {"coordinates":[-6.9881148338,38.8701400757],"type":"Point"}
}