{
  "type": "Feature",
  "properties": {
    "iso:country":"ES",
    "sg:address":"Calle de Real De Motril, 75",
    "sg:city":"Armilla",
    "sg:classifiers":[
        {
            "category":"Autos & Motor Vehicles",
            "subcategory":"Automobile Sales",
            "type":"Retail Goods"
        }
    ],
    "sg:phone":"+34 958 55 01 99",
    "sg:postcode":"18100",
    "sg:province":"Granada",
    "wof:name":"Lara Peinado Francisca",
    "wof:placetype":"venue"
},
  "geometry": {"coordinates":[-3.6273889542,37.1413269043],"type":"Point"}
}