{
  "type": "Feature",
  "properties": {
    "iso:country":"ES",
    "sg:address":"Calle de Dos De Mayo, 43",
    "sg:city":"Utiel",
    "sg:orig_category":"Contenedores (mercanc\u00cdas)",
    "sg:phone":"+34 962 17 07 74",
    "sg:postcode":"46300",
    "sg:province":"Valencia",
    "wof:name":"Berlanga Lorente Pilar",
    "wof:placetype":"venue"
},
  "geometry": {"coordinates":[-1.2064390182,39.5707588196],"type":"Point"}
}