{
  "type": "Feature",
  "properties": {
    "iso:country":"ES",
    "sg:address":"Carrer de Gavines (peguera), 19",
    "sg:city":"Peguera",
    "sg:orig_category":"Peluqueros: De Se\u00d1oras",
    "sg:phone":"+34 971 68 74 10",
    "sg:postcode":"07160",
    "sg:province":"Islas Baleares",
    "wof:name":"Soler Servera Antonia",
    "wof:placetype":"venue"
},
  "geometry": {"coordinates":[2.4566810131,39.5374336243],"type":"Point"}
}