{
  "type": "Feature",
  "properties": {
    "addr:full":"Ctra Jaen (de), 6 Granada Granada 18013",
    "addr:housenumber":"6",
    "addr:postcode":"18013",
    "addr:street":"Ctra Jaen De",
    "iso:country":"ES",
    "sg:address":"Ctra Jaen (de), 6",
    "sg:city":"Granada",
    "sg:orig_category":"Centros M\u00c9dicos Y Sociales, Dispensarios",
    "sg:phone":"+34 958 15 65 75",
    "sg:postcode":"18013",
    "sg:province":"Granada",
    "wof:name":"Tellez Subiza Wifredo",
    "wof:placetype":"venue"
},
  "geometry": {"coordinates":[-3.6117789745,37.1989517212],"type":"Point"}
}