{
  "type": "Feature",
  "properties": {
    "addr:full":"Calle de Lenguas, 6 Madrid Madrid 28021",
    "addr:housenumber":"6",
    "addr:postcode":"28021",
    "addr:street":"Calle De Lenguas",
    "iso:country":"ES",
    "sg:address":"Calle de Lenguas, 6",
    "sg:city":"Madrid",
    "sg:orig_category":"Serigraf\u00cda (material Y Suministros)",
    "sg:phone":"+34 917 95 62 98",
    "sg:postcode":"28021",
    "sg:province":"Madrid",
    "wof:name":"Promociones Serigraficas S.a.",
    "wof:placetype":"venue"
},
  "geometry": {"coordinates":[-3.70540905,40.3425636292],"type":"Point"}
}