{
  "type": "Feature",
  "properties": {
    "iso:country":"ES",
    "sg:address":"Calle de Marques, 11",
    "sg:city":"S. Clemente",
    "sg:orig_category":"Fabricaci\u00d3n De Muebles",
    "sg:phone":"+34 969 30 12 09",
    "sg:postcode":"16600",
    "sg:province":"Cuenca",
    "wof:name":"Muebles Arribas Y Escribano S.l.",
    "wof:placetype":"venue"
},
  "geometry": {"coordinates":[-2.4282689095,39.403175354],"type":"Point"}
}