{
  "type": "Feature",
  "properties": {
    "addr:full":"Carrer de Pedraforca, 105 Hospitalet Llobregat Barcelona 08905",
    "addr:housenumber":"105",
    "addr:postcode":"08905",
    "addr:street":"Carrer De Pedraforca",
    "iso:country":"ES",
    "sg:address":"Carrer de Pedraforca, 105",
    "sg:city":"Hospitalet Llobregat",
    "sg:orig_category":"Loter\u00cda Y T\u00d3mbola",
    "sg:phone":"+34 933 34 71 94",
    "sg:postcode":"08905",
    "sg:province":"Barcelona",
    "wof:name":"Nu\u00f1ez Rodriguez Silvia",
    "wof:placetype":"venue"
},
  "geometry": {"coordinates":[2.1075570583,41.3706703186],"type":"Point"}
}