{
  "type": "Feature",
  "properties": {
    "addr:full":"Calle de Mayor, 25 Albatera Alicante 03340",
    "addr:housenumber":"25",
    "addr:postcode":"03340",
    "addr:street":"Calle De Mayor",
    "iso:country":"ES",
    "sg:address":"Calle de Mayor, 25",
    "sg:city":"Albatera",
    "sg:orig_category":"Prot\u00c9sicos Dentales",
    "sg:phone":"+34 965 48 77 08",
    "sg:postcode":"03340",
    "sg:province":"Alicante",
    "wof:name":"Serna Pont Orismed S.l.",
    "wof:placetype":"venue"
},
  "geometry": {"coordinates":[-0.8706259727,38.1798973083],"type":"Point"}
}