{
  "type": "Feature",
  "properties": {
    "iso:country":"ES",
    "sg:address":"Calle de Cueto, 20",
    "sg:city":"San Mateo",
    "sg:orig_category":"Agencias Y Asesores De Publicidad",
    "sg:phone":"+34 968 40 73 33",
    "sg:postcode":"30800",
    "sg:province":"Murcia",
    "wof:name":"Alcazar Terrones Diego",
    "wof:placetype":"venue"
},
  "geometry": {"coordinates":[-1.1298867464,37.9834747314],"type":"Point"}
}