{
  "type": "Feature",
  "properties": {
    "iso:country":"ES",
    "sg:address":"Pl Real, 5",
    "sg:city":"Lorca",
    "sg:orig_category":"Asociaciones Y Clubs Deportivos",
    "sg:phone":"+34 968 47 36 12",
    "sg:postcode":"30800",
    "sg:province":"Murcia",
    "wof:name":"Sociedad Cinegetica Deportiva San Huberto",
    "wof:placetype":"venue"
},
  "geometry": {"coordinates":[-1.6905640364,37.680557251],"type":"Point"}
}