{
  "type": "Feature",
  "properties": {
    "iso:country":"ES",
    "sg:address":"Carr Prat De La Riba, 18",
    "sg:city":"Miralcamp",
    "sg:orig_category":"Ebanister\u00cda",
    "sg:phone":"+34 973 71 03 73",
    "sg:postcode":"25242",
    "sg:province":"Lleida",
    "wof:name":"Pons Catala S.a.",
    "wof:placetype":"venue"
},
  "geometry": {"coordinates":[0.8790990114,41.6061134338],"type":"Point"}
}