{
  "type": "Feature",
  "properties": {
    "addr:full":"Calle de Peral, 19 Marbella M\u00e1laga 29600",
    "addr:housenumber":"19",
    "addr:postcode":"29600",
    "addr:street":"Calle De Peral;Ma\u0301Laga",
    "iso:country":"ES",
    "sg:address":"Calle de Peral, 19",
    "sg:city":"Marbella",
    "sg:orig_category":"Moda",
    "sg:phone":"+34 952 82 53 19",
    "sg:postcode":"29600",
    "sg:province":"M\u00e1laga",
    "wof:name":"Effefrancisca S.l.",
    "wof:placetype":"venue"
},
  "geometry": {"coordinates":[-4.8860020638,36.510471344],"type":"Point"}
}