{
  "type": "Feature",
  "properties": {
    "iso:country":"ES",
    "sg:address":"Calle de Asuncion, 75",
    "sg:city":"Sevilla",
    "sg:orig_category":"Fabricaci\u00d3n De Instrumentos Y Accesorios Musicales",
    "sg:phone":"+34 954 45 25 24",
    "sg:postcode":"41011",
    "sg:province":"Sevilla",
    "wof:name":"Gonzalez Ruano Miguel Angel",
    "wof:placetype":"venue"
},
  "geometry": {"coordinates":[-5.9973897934,37.3719940186],"type":"Point"}
}