{
  "type": "Feature",
  "properties": {
    "addr:full":"Calle de General Valdes, 7 Puebla Castro Huesca 22435",
    "addr:housenumber":"7",
    "addr:postcode":"22435",
    "addr:street":"Calle De General Valdes",
    "iso:country":"ES",
    "sg:address":"Calle de General Valdes, 7",
    "sg:city":"Puebla Castro",
    "sg:orig_category":"Charcuter\u00cdas (al Por Mayor)",
    "sg:phone":"+34 974 54 50 13",
    "sg:postcode":"22435",
    "sg:province":"Huesca",
    "wof:name":"Garuz Perez Jose",
    "wof:placetype":"venue"
},
  "geometry": {"coordinates":[0.2881431878,42.1444854736],"type":"Point"}
}