{
  "type": "Feature",
  "properties": {
    "iso:country":"ES",
    "sg:address":"Calle de Doctor Valenciano, 4",
    "sg:city":"San Antonio Abad",
    "sg:orig_category":"Perfumer\u00cda, Art\u00cdculos De Ba\u00d1o (fabricaci\u00d3n, Al Por Mayor)",
    "sg:phone":"+34 968 53 48 80",
    "sg:postcode":"30205",
    "sg:province":"Murcia",
    "wof:name":"Exclusivas Del Mediteraneo Jpm Xxi S.l",
    "wof:placetype":"venue"
},
  "geometry": {"coordinates":[-0.9946302176,37.6191482544],"type":"Point"}
}