{
  "type": "Feature",
  "properties": {
    "iso:country":"ES",
    "sg:address":"Calle de Campana (la), S/n",
    "sg:city":"Chorrillo",
    "sg:orig_category":"Art\u00cdculos De Regalo (al Por Menor)",
    "sg:phone":"+34 922 62 10 13",
    "sg:postcode":"38108",
    "sg:province":"Santa Cruz De Tenerife",
    "wof:name":"M.r.m.import.co.s.l.",
    "wof:placetype":"venue"
},
  "geometry": {"coordinates":[-16.3173675537,28.4172515869],"type":"Point"}
}