{
  "type": "Feature",
  "properties": {
    "addr:full":"Av Baix Llobregat, 19 Cornella Llobregat Barcelona 08940",
    "addr:housenumber":"19",
    "addr:postcode":"08940",
    "addr:street":"Av Baix Llobregat",
    "iso:country":"ES",
    "sg:address":"Av Baix Llobregat, 19",
    "sg:city":"Cornella Llobregat",
    "sg:orig_category":"Promotores Constructores",
    "sg:phone":"+34 933 77 18 27",
    "sg:postcode":"08940",
    "sg:province":"Barcelona",
    "wof:name":"Soto-quesada S.l.",
    "wof:placetype":"venue"
},
  "geometry": {"coordinates":[2.0693869591,41.3508911133],"type":"Point"}
}