{
  "type": "Feature",
  "properties": {
    "addr:full":"Col San Rafael, 14 Ubeda Ja\u00e9n 23400",
    "addr:housenumber":"14",
    "addr:postcode":"23400",
    "addr:street":"Col San Rafael;Jae\u0301N",
    "iso:country":"ES",
    "sg:address":"Col San Rafael, 14",
    "sg:city":"Ubeda",
    "sg:orig_category":"M\u00c9dicos: Neurocirug\u00cda",
    "sg:phone":"+34 953 75 03 25",
    "sg:postcode":"23400",
    "sg:province":"Ja\u00e9n",
    "wof:name":"Ortiz Ruiz Antonio",
    "wof:placetype":"venue"
},
  "geometry": {"coordinates":[-3.3777289391,38.0143699646],"type":"Point"}
}