{
  "type": "Feature",
  "properties": {
    "iso:country":"ES",
    "sg:address":"Av. Colon, 1",
    "sg:city":"S. Sebastian Gomera",
    "sg:orig_category":"Estancos",
    "sg:phone":"+34 922 14 16 95",
    "sg:postcode":"38800",
    "sg:province":"Santa Cruz De Tenerife",
    "wof:name":"Hernandez Herrera Jose Antonio",
    "wof:placetype":"venue"
},
  "geometry": {"coordinates":[-17.1113586426,28.0925102234],"type":"Point"}
}