{
  "type": "Feature",
  "properties": {
    "addr:full":"Matadero, 15 Beniparrell Valencia 46469",
    "addr:housenumber":"15",
    "addr:postcode":"46469",
    "addr:street":"Matadero",
    "iso:country":"ES",
    "sg:address":"Matadero, 15",
    "sg:city":"Beniparrell",
    "sg:orig_category":"Alumbrados",
    "sg:phone":"+34 961 21 42 46",
    "sg:postcode":"46469",
    "sg:province":"Valencia",
    "sg:website":"www.cristalexport.com",
    "wof:name":"Cristal Export S.l.",
    "wof:placetype":"venue"
},
  "geometry": {"coordinates":[-0.4035919905,39.3803863525],"type":"Point"}
}