{
  "type": "Feature",
  "properties": {
    "iso:country":"ES",
    "sg:address":"Rua Policarpo Sanz, 22",
    "sg:city":"Vigo",
    "sg:orig_category":"Droguer\u00cdas (al Por Menor)",
    "sg:phone":"+34 986 43 72 86",
    "sg:postcode":"36202",
    "sg:province":"Pontevedra",
    "wof:name":"Decogar S.a.",
    "wof:placetype":"venue"
},
  "geometry": {"coordinates":[-8.722949028,42.2375106812],"type":"Point"}
}