{
  "type": "Feature",
  "properties": {
    "addr:full":"Calle de Catalu\u00d1a, 3 Sevilla Sevilla 41015",
    "addr:housenumber":"3",
    "addr:postcode":"41015",
    "addr:street":"Calle De Catalun\u0303A",
    "iso:country":"ES",
    "sg:address":"Calle de Catalu\u00d1a, 3",
    "sg:city":"Sevilla",
    "sg:orig_category":"Supermercados Y Hipermercados",
    "sg:phone":"+34 954 37 30 04",
    "sg:postcode":"41015",
    "sg:province":"Sevilla",
    "wof:name":"Dinosol Supermercados S.l.",
    "wof:placetype":"venue"
},
  "geometry": {"coordinates":[-5.9838991165,37.424659729],"type":"Point"}
}