{
  "type": "Feature",
  "properties": {
    "iso:country":"ES",
    "sg:address":"Poli Industrial C/c, 13",
    "sg:city":"Rozas De Madrid",
    "sg:orig_category":"Ense\u00d1anza: Profesiones Art\u00cdsticas",
    "sg:phone":"+34 916 40 72 99",
    "sg:postcode":"28230",
    "sg:province":"Madrid",
    "wof:name":"Sociedad Didactico Musical",
    "wof:placetype":"venue"
},
  "geometry": {"coordinates":[-3.8913800716,40.5247497559],"type":"Point"}
}