{
  "type": "Feature",
  "properties": {
    "iso:country":"ES",
    "sg:address":"Rua Republica Argentina, 24",
    "sg:city":"Noia",
    "sg:orig_category":"Panader\u00cdas, Panader\u00cdas",
    "sg:phone":"+34 981 82 46 88",
    "sg:postcode":"15200",
    "sg:province":"La Coru\u00f1a",
    "wof:name":"Panaderia Blanco Rey",
    "wof:placetype":"venue"
},
  "geometry": {"coordinates":[-8.8883037567,42.788608551],"type":"Point"}
}