{
  "type": "Feature",
  "properties": {
    "addr:full":"Avda Alvaro Cunqueiro, 7 Foz Lugo 27780",
    "addr:housenumber":"7",
    "addr:postcode":"27780",
    "addr:street":"Avda Alvaro Cunqueiro",
    "iso:country":"ES",
    "sg:address":"Avda Alvaro Cunqueiro, 7",
    "sg:city":"Foz",
    "sg:classifiers":[
        {
            "category":"Autos & Motor Vehicles",
            "subcategory":"Automobile Sales",
            "type":"Retail Goods"
        }
    ],
    "sg:phone":"+34 982 14 03 64",
    "sg:postcode":"27780",
    "sg:province":"Lugo",
    "wof:name":"Auto-escuela Foz C. B.",
    "wof:placetype":"venue"
},
  "geometry": {"coordinates":[-7.259803772,43.5675849915],"type":"Point"}
}