{
  "type": "Feature",
  "properties": {
    "iso:country":"ES",
    "sg:address":"Avda Martinez Alejos, 4",
    "sg:city":"Benidorm",
    "sg:orig_category":"Abogados",
    "sg:phone":"+34 966 80 56 07",
    "sg:postcode":"03500",
    "sg:province":"Alicante",
    "wof:name":"Jimenez Mallorquin Francisca",
    "wof:placetype":"venue"
},
  "geometry": {"coordinates":[-0.129091993,38.5366210938],"type":"Point"}
}