{
  "type": "Feature",
  "properties": {
    "addr:full":"Calle de Alcala Galiano, 3 Alacant Alicante 03012",
    "addr:housenumber":"3",
    "addr:postcode":"03012",
    "addr:street":"Calle De Alcala Galiano",
    "iso:country":"ES",
    "sg:address":"Calle de Alcala Galiano, 3",
    "sg:city":"Alacant",
    "sg:orig_category":"Electricidad: Instaladores",
    "sg:phone":"+34 965 25 48 28",
    "sg:postcode":"03012",
    "sg:province":"Alicante",
    "wof:name":"Instalacant Montajes Electricos S.l.",
    "wof:placetype":"venue"
},
  "geometry": {"coordinates":[-0.4843606949,38.3535652161],"type":"Point"}
}