{
  "type": "Feature",
  "properties": {
    "addr:full":"Barr Sant Joan, 1 Granollers Barcelona 08402",
    "addr:housenumber":"1",
    "addr:postcode":"08402",
    "addr:street":"Sant Joan",
    "iso:country":"ES",
    "sg:address":"Barr Sant Joan, 1",
    "sg:city":"Granollers",
    "sg:orig_category":"Alimentaci\u00d3n General (al Por Menor)",
    "sg:phone":"+34 938 70 05 60",
    "sg:postcode":"08402",
    "sg:province":"Barcelona",
    "wof:name":"Pocurull Antelet Eulalia",
    "wof:placetype":"venue"
},
  "geometry": {"coordinates":[2.2832479477,41.5791625977],"type":"Point"}
}