{
  "type": "Feature",
  "properties": {
    "addr:full":"Plaz Baldomero Iglesias, S/n Torrelavega Cantabria 39300",
    "addr:postcode":"39300",
    "addr:street":"Iglesias S / N",
    "iso:country":"ES",
    "sg:address":"Plaz Baldomero Iglesias, S/n",
    "sg:city":"Torrelavega",
    "sg:orig_category":"Organizaciones Internacionales",
    "sg:phone":"+34 942 88 33 09",
    "sg:postcode":"39300",
    "sg:province":"Cantabria",
    "wof:name":"Caritas Parroquial",
    "wof:placetype":"venue"
},
  "geometry": {"coordinates":[-4.0484142303,43.347858429],"type":"Point"}
}