{
  "type": "Feature",
  "properties": {
    "iso:country":"ES",
    "sg:address":"Calle de Torres Miranda, 4",
    "sg:city":"Madrid",
    "sg:orig_category":"Pescader\u00cdas (al Por Menor)",
    "sg:phone":"+34 914 73 13 01",
    "sg:postcode":"28045",
    "sg:province":"Madrid",
    "wof:name":"Alvarez Nu\u00f1ez Elicio",
    "wof:placetype":"venue"
},
  "geometry": {"coordinates":[-3.6984345913,40.3980293274],"type":"Point"}
}