{
  "type": "Feature",
  "properties": {
    "addr:full":"Carrer de Joan Carles I, 8 Roda De Bara Tarragona 43883",
    "addr:housenumber":"8",
    "addr:postcode":"43883",
    "addr:street":"Carrer De Joan Carles I",
    "iso:country":"ES",
    "sg:address":"Carrer de Joan Carles I, 8",
    "sg:city":"Roda De Bara",
    "sg:orig_category":"Molduras, Junquillos, Listones Y Molduras Perforadas",
    "sg:phone":"+34 977 80 94 25",
    "sg:postcode":"43883",
    "sg:province":"Tarragona",
    "wof:name":"Lebron Aguilar Fernando",
    "wof:placetype":"venue"
},
  "geometry": {"coordinates":[1.4562339783,41.1852416992],"type":"Point"}
}