{
  "type": "Feature",
  "properties": {
    "addr:full":"Avgd Espioca, 16 Silla Valencia 46460",
    "addr:housenumber":"16",
    "addr:postcode":"46460",
    "addr:street":"Espioca",
    "iso:country":"ES",
    "sg:address":"Avgd Espioca, 16",
    "sg:city":"Silla",
    "sg:orig_category":"Patatas (al Por Mayor)",
    "sg:phone":"+34 961 20 19 23",
    "sg:postcode":"46460",
    "sg:province":"Valencia",
    "wof:name":"Asociacion De Exportadores De Patatas S.a.",
    "wof:placetype":"venue"
},
  "geometry": {"coordinates":[-0.4192695022,39.3652458191],"type":"Point"}
}