{
  "type": "Feature",
  "properties": {
    "addr:full":"Calle de Arga\u00d1osa, 86 Oviedo Asturias 33013",
    "addr:housenumber":"86",
    "addr:postcode":"33013",
    "addr:street":"Calle De Argan\u0303Osa",
    "iso:country":"ES",
    "sg:address":"Calle de Arga\u00d1osa, 86",
    "sg:city":"Oviedo",
    "sg:orig_category":"Mercer\u00cda, Lencer\u00cda (al Por Menor)",
    "sg:phone":"+34 985 23 29 26",
    "sg:postcode":"33013",
    "sg:province":"Asturias",
    "wof:name":"Garcia Alvarez Margarita",
    "wof:placetype":"venue"
},
  "geometry": {"coordinates":[-5.8661284447,43.3652000427],"type":"Point"}
}