{
  "type": "Feature",
  "properties": {
    "iso:country":"ES",
    "sg:address":"Ctra Ecija-jerez, Km. 0005,0",
    "sg:city":"Utrera",
    "sg:orig_category":"Empresas De Carpinter\u00cda Met\u00c1lica",
    "sg:phone":"+34 955 86 18 95",
    "sg:postcode":"41710",
    "sg:province":"Sevilla",
    "wof:name":"Aluminios Los Juanes S.l.",
    "wof:placetype":"venue"
},
  "geometry": {"coordinates":[-5.7747311592,37.174621582],"type":"Point"}
}