{
  "type": "Feature",
  "properties": {
    "addr:full":"Grup Nueva Europa, S/n Sevilla Sevilla 41020",
    "addr:housenumber":"s / n",
    "addr:postcode":"41020",
    "iso:country":"ES",
    "sg:address":"Grup Nueva Europa, S/n",
    "sg:city":"Sevilla",
    "sg:orig_category":"Peluqueros: De Se\u00d1oras",
    "sg:phone":"+34 954 40 15 79",
    "sg:postcode":"41020",
    "sg:province":"Sevilla",
    "wof:name":"Gomez Perez Josefa",
    "wof:placetype":"venue"
},
  "geometry": {"coordinates":[-5.9333291054,37.4165763855],"type":"Point"}
}