{
  "type": "Feature",
  "properties": {
    "addr:full":"Pg Sant Joan, 17 Crevillent Alicante 03330",
    "addr:housenumber":"17",
    "addr:postcode":"03330",
    "addr:street":"Pg Sant Joan",
    "iso:country":"ES",
    "sg:address":"Pg Sant Joan, 17",
    "sg:city":"Crevillent",
    "sg:orig_category":"M\u00c9dicos: Estomatolog\u00cda",
    "sg:phone":"+34 965 40 44 34",
    "sg:postcode":"03330",
    "sg:province":"Alicante",
    "wof:name":"Diaz Diaz Mario",
    "wof:placetype":"venue"
},
  "geometry": {"coordinates":[-0.8054789901,38.2465591431],"type":"Point"}
}