{
  "type": "Feature",
  "properties": {
    "iso:country":"ES",
    "sg:address":"Calle de Marques De Zuya, 5",
    "sg:city":"Andra Mari",
    "sg:orig_category":"Tapicer\u00cdas",
    "sg:phone":"+34 944 91 54 39",
    "sg:postcode":"48993",
    "sg:province":"Vizcaya",
    "wof:name":"Pemasa 2000 S.l.",
    "wof:placetype":"venue"
},
  "geometry": {"coordinates":[-2.7541499138,43.2982711792],"type":"Point"}
}