{
  "type": "Feature",
  "properties": {
    "addr:full":"Calle de Cuba De Abajo, 4 Suances Cantabria 39340",
    "addr:housenumber":"4",
    "addr:postcode":"39340",
    "addr:street":"Calle De Cuba De Abajo",
    "iso:country":"ES",
    "sg:address":"Calle de Cuba De Abajo, 4",
    "sg:city":"Suances",
    "sg:orig_category":"Comerciantes Al Por Mayor De Vinos, Licores Y Alcoholes",
    "sg:phone":"+34 942 84 45 57",
    "sg:postcode":"39340",
    "sg:province":"Cantabria",
    "wof:name":"Ruiz Ruiz Raul",
    "wof:placetype":"venue"
},
  "geometry": {"coordinates":[-4.0366559029,43.4238014221],"type":"Point"}
}