{
  "type": "Feature",
  "properties": {
    "addr:full":"El Egido, S/n Almarza Soria 42160",
    "addr:housenumber":"s",
    "addr:postcode":"42160",
    "addr:street":"El Egido;/ N Almarza",
    "iso:country":"ES",
    "sg:address":"El Egido, S/n",
    "sg:city":"Almarza",
    "sg:orig_category":"Transportes De Material De Construcci\u00d3n",
    "sg:phone":"+34 975 25 00 12",
    "sg:postcode":"42160",
    "sg:province":"Soria",
    "wof:name":"Sanz Gomez Marcelino",
    "wof:placetype":"venue"
},
  "geometry": {"coordinates":[-2.4681560993,41.9460067749],"type":"Point"}
}