{
  "type": "Feature",
  "properties": {
    "iso:country":"ES",
    "sg:address":"Calle de Alvarez Garaya, 13",
    "sg:city":"Gijon",
    "sg:orig_category":"Quincaller\u00cda (al Por Menor)",
    "sg:phone":"+34 985 34 49 18",
    "sg:postcode":"33206",
    "sg:province":"Asturias",
    "wof:name":"Leal Mata Carmen",
    "wof:placetype":"venue"
},
  "geometry": {"coordinates":[-5.665699482,43.5408935547],"type":"Point"}
}