{
  "type": "Feature",
  "properties": {
    "iso:country":"ES",
    "sg:address":"Avda Federico Silva, 142",
    "sg:city":"Benavente",
    "sg:orig_category":"Aluminio Y Aleaciones (producci\u00d3n, Transformaci\u00d3n, Negocio)",
    "sg:phone":"+34 980 63 38 25",
    "sg:postcode":"49600",
    "sg:province":"Zamora",
    "sg:website":"www.laminex.es",
    "wof:name":"Laminex Madrid S. A",
    "wof:placetype":"venue"
},
  "geometry": {"coordinates":[-5.660929203,41.998008728],"type":"Point"}
}