{
  "type": "Feature",
  "properties": {
    "iso:country":"ES",
    "sg:address":"Calle de Cristobal Colon, 8",
    "sg:city":"Bailen",
    "sg:orig_category":"Talleres De Corte Y Confecci\u00d3n",
    "sg:phone":"+34 953 67 66 37",
    "sg:postcode":"23710",
    "sg:province":"Ja\u00e9n",
    "wof:name":"Garcia Jurado Ines",
    "wof:placetype":"venue"
},
  "geometry": {"coordinates":[-3.7768082619,38.0962524414],"type":"Point"}
}