{
  "type": "Feature",
  "properties": {
    "iso:country":"ES",
    "sg:address":"Calle de Hervas Y Buendia, 5",
    "sg:city":"Ciudad Real",
    "sg:orig_category":"Centros Empresariales",
    "sg:phone":"+34 926 25 69 89",
    "sg:postcode":"13003",
    "sg:province":"Ciudad Real",
    "wof:name":"Sevilla Torrijos Juan Carlos",
    "wof:placetype":"venue"
},
  "geometry": {"coordinates":[-3.9273090363,38.9905509949],"type":"Point"}
}