{
  "type": "Feature",
  "properties": {
    "addr:full":"Calle de Easo, 9 Donostia-san Sebastian Guip\u00f9zcoa 20006",
    "addr:housenumber":"9",
    "addr:postcode":"20006",
    "addr:street":"Calle De Easo",
    "iso:country":"ES",
    "sg:address":"Calle de Easo, 9",
    "sg:city":"Donostia-san Sebastian",
    "sg:orig_category":"Asociaciones Y Clubs Deportivos",
    "sg:phone":"+34 943 43 11 88",
    "sg:postcode":"20006",
    "sg:province":"Guip\u00f9zcoa",
    "wof:name":"Gomez Dorronsoro Jose Ramon",
    "wof:placetype":"venue"
},
  "geometry": {"coordinates":[-1.9844764471,43.3176765442],"type":"Point"}
}