{
  "type": "Feature",
  "properties": {
    "addr:full":"Plaz Espa\u00d1a, 1 Langreo Asturias 33900",
    "addr:housenumber":"1",
    "addr:postcode":"33900",
    "addr:street":"Plaz Espan\u0303A",
    "iso:country":"ES",
    "sg:address":"Plaz Espa\u00d1a, 1",
    "sg:city":"Langreo",
    "sg:orig_category":"Camiser\u00cda Y Ropa Interior Masculina (al Por Menor)",
    "sg:phone":"+34 985 69 21 48",
    "sg:postcode":"33900",
    "sg:province":"Asturias",
    "wof:name":"Leon Solares Jose Carlos",
    "wof:placetype":"venue"
},
  "geometry": {"coordinates":[-5.6841778755,43.2957115173],"type":"Point"}
}