{
  "type": "Feature",
  "properties": {
    "iso:country":"ES",
    "sg:address":"Calle de Sauce, 22",
    "sg:city":"Calabaza",
    "sg:orig_category":"Motores Diessel",
    "sg:phone":"+34 947 50 48 47",
    "sg:postcode":"09400",
    "sg:province":"Burgos",
    "wof:name":"Curiel Diago Valentin",
    "wof:placetype":"venue"
},
  "geometry": {"coordinates":[-3.6275238991,41.6730613708],"type":"Point"}
}