{
  "type": "Feature",
  "properties": {
    "iso:country":"ES",
    "sg:address":"Calle de Teniente Gonzalez, 2",
    "sg:city":"Cuenca",
    "sg:orig_category":"M\u00c9dicos: Gastroenterolog\u00cda Y Hepatolog\u00cda (aparato Digestivo)",
    "sg:phone":"+34 969 21 44 50",
    "sg:postcode":"16002",
    "sg:province":"Cuenca",
    "wof:name":"Jimenez Torrijos Amador",
    "wof:placetype":"venue"
},
  "geometry": {"coordinates":[-2.1366779804,40.0722236633],"type":"Point"}
}