{
  "type": "Feature",
  "properties": {
    "addr:full":"Ctra. Las Galletas, Km. 0014,0 Las Chafiras Santa Cruz De Tenerife 38639",
    "addr:postcode":"38639",
    "addr:street":"Ctra. Las Galletas Km. 0014,0",
    "iso:country":"ES",
    "sg:address":"Ctra. Las Galletas, Km. 0014,0",
    "sg:city":"Las Chafiras",
    "sg:orig_category":"Restaurantes",
    "sg:phone":"+34 922 73 08 83",
    "sg:postcode":"38639",
    "sg:province":"Santa Cruz De Tenerife",
    "wof:name":"Ramos Correa Jose",
    "wof:placetype":"venue"
},
  "geometry": {"coordinates":[-16.6115474701,28.0350246429],"type":"Point"}
}