{
  "type": "Feature",
  "properties": {
    "addr:full":"Calle de Pintor Rosales, 6 Colindres Cantabria 39750",
    "addr:housenumber":"6",
    "addr:postcode":"39750",
    "addr:street":"Calle De Pintor Rosales",
    "iso:country":"ES",
    "sg:address":"Calle de Pintor Rosales, 6",
    "sg:city":"Colindres",
    "sg:orig_category":"Caf\u00c9s, Bares, Cervecer\u00cdas",
    "sg:phone":"+34 942 65 05 59",
    "sg:postcode":"39750",
    "sg:province":"Cantabria",
    "wof:name":"Cafeteria Galicia C.b.",
    "wof:placetype":"venue"
},
  "geometry": {"coordinates":[-3.4513700008,43.3963470459],"type":"Point"}
}