{
  "type": "Feature",
  "properties": {
    "addr:full":"Calle de Pe\u00d1a Y Go\u00d1i, 11 Donostia-san Sebastian Guip\u00f9zcoa 20002",
    "addr:housenumber":"11",
    "addr:postcode":"20002",
    "addr:street":"Calle De Pen\u0303A Y Gon\u0303I",
    "iso:country":"ES",
    "sg:address":"Calle de Pe\u00d1a Y Go\u00d1i, 11",
    "sg:city":"Donostia-san Sebastian",
    "sg:orig_category":"Vinos Y Licores (venta Al Por Menor)",
    "sg:phone":"+34 943 27 01 83",
    "sg:postcode":"20002",
    "sg:province":"Guip\u00f9zcoa",
    "wof:name":"Suso Arostegui Nicolas",
    "wof:placetype":"venue"
},
  "geometry": {"coordinates":[-1.9774340391,43.3232498169],"type":"Point"}
}