{
  "type": "Feature",
  "properties": {
    "addr:full":"Calle de Boteros, 30 S. Clemente Cuenca 16600",
    "addr:housenumber":"30",
    "addr:postcode":"16600",
    "addr:street":"Calle De Boteros;S. Clemente Cuenca",
    "iso:country":"ES",
    "sg:address":"Calle de Boteros, 30",
    "sg:city":"S. Clemente",
    "sg:orig_category":"Asociaciones Y Clubs Deportivos",
    "sg:phone":"+34 969 30 06 81",
    "sg:postcode":"16600",
    "sg:province":"Cuenca",
    "wof:name":"Montoya Toledo Manoli",
    "wof:placetype":"venue"
},
  "geometry": {"coordinates":[-2.4274408817,39.4049911499],"type":"Point"}
}