{
  "type": "Feature",
  "properties": {
    "addr:full":"Avda Granada, S/n Santa Pola Alicante 03130",
    "addr:housenumber":"/ n",
    "addr:postcode":"03130",
    "addr:street":"Avda Granada S",
    "iso:country":"ES",
    "sg:address":"Avda Granada, S/n",
    "sg:city":"Santa Pola",
    "sg:orig_category":"Promotores Constructores",
    "sg:phone":"+34 966 69 32 92",
    "sg:postcode":"03130",
    "sg:province":"Alicante",
    "wof:name":"Promociones La Gaviota S.a.",
    "wof:placetype":"venue"
},
  "geometry": {"coordinates":[-0.5640090108,38.1912994385],"type":"Point"}
}