{
  "type": "Feature",
  "properties": {
    "iso:country":"ES",
    "sg:address":"Stu Nta Sra Sierra, S/n",
    "sg:city":"Malagon",
    "sg:orig_category":"Ense\u00d1anza, Formaci\u00d3n Profesional: Aprendizaje",
    "sg:phone":"+34 926 80 13 25",
    "sg:postcode":"13420",
    "sg:province":"Ciudad Real",
    "wof:name":"Ayuntamiento.santuario N S De La Sierra",
    "wof:placetype":"venue"
},
  "geometry": {"coordinates":[-4.0082564354,39.2311096191],"type":"Point"}
}