{
  "type": "Feature",
  "properties": {
    "iso:country":"ES",
    "sg:address":"Calle de Europa, S/n",
    "sg:city":"Alcorcon",
    "sg:orig_category":"Fabricaci\u00d3n, Importaci\u00d3n, Venta De Material De Telefon\u00cda, Peritelefon\u00cda",
    "sg:phone":"+34 916 89 14 55",
    "sg:postcode":"28922",
    "sg:province":"Madrid",
    "wof:name":"Xtra Telecom S.a.",
    "wof:placetype":"venue"
},
  "geometry": {"coordinates":[-3.8487091064,40.3491897583],"type":"Point"}
}