{
  "type": "Feature",
  "properties": {
    "iso:country":"ES",
    "sg:address":"Calle de Naranjo, 6",
    "sg:city":"Rinconada",
    "sg:orig_category":"T\u00c9cnicos Veterinarios",
    "sg:phone":"+34 955 79 84 08",
    "sg:postcode":"41309",
    "sg:province":"Sevilla",
    "wof:name":"Serganvet La Paz S.c.",
    "wof:placetype":"venue"
},
  "geometry": {"coordinates":[-5.9831252098,37.4888114929],"type":"Point"}
}