{
  "type": "Feature",
  "properties": {
    "iso:country":"ES",
    "sg:address":"Pg Sant Joan, 70",
    "sg:city":"Barcelona",
    "sg:orig_category":"Ense\u00d1ante, Direcci\u00d3n",
    "sg:phone":"+34 932 45 63 78",
    "sg:postcode":"08009",
    "sg:province":"Barcelona",
    "wof:name":"Renart Cava Juan Bautista",
    "wof:placetype":"venue"
},
  "geometry": {"coordinates":[2.1730248928,41.3970184326],"type":"Point"}
}