{
  "type": "Feature",
  "properties": {
    "iso:country":"ES",
    "sg:address":"Plaz Espa\u00d1a, 16",
    "sg:city":"Salamanca",
    "sg:orig_category":"Bisuter\u00cda, Joyer\u00cda, Relojer\u00cda (al Por Menor)",
    "sg:phone":"+34 923 26 11 50",
    "sg:postcode":"37004",
    "sg:province":"Salamanca",
    "wof:name":"Taller De Joyeria Cruz C.b.",
    "wof:placetype":"venue"
},
  "geometry": {"coordinates":[-5.6592512131,40.9688491821],"type":"Point"}
}