{
  "type": "Feature",
  "properties": {
    "addr:full":"Calle de Martin De Vargas, 19 Madrid Madrid 28005",
    "addr:housenumber":"19",
    "addr:postcode":"madrid;28005",
    "addr:street":"Calle De Martin De Vargas",
    "iso:country":"ES",
    "sg:address":"Calle de Martin De Vargas, 19",
    "sg:city":"Madrid",
    "sg:orig_category":"Grabados",
    "sg:phone":"+34 915 17 87 46",
    "sg:postcode":"28005",
    "sg:province":"Madrid",
    "wof:name":"Carrasco Tejeiro Luis",
    "wof:placetype":"venue"
},
  "geometry": {"coordinates":[-3.7016479969,40.4028091431],"type":"Point"}
}