{
  "type": "Feature",
  "properties": {
    "iso:country":"ES",
    "sg:address":"Calle de Ancora, 8",
    "sg:city":"Madrid",
    "sg:orig_category":"Administradores De Bienes Y Delegados De Comunidades De Propietarios",
    "sg:phone":"+34 914 67 82 02",
    "sg:postcode":"28045",
    "sg:province":"Madrid",
    "wof:name":"Gutierrez Negredo Cesar",
    "wof:placetype":"venue"
},
  "geometry": {"coordinates":[-3.6926810741,40.4029502869],"type":"Point"}
}