{
  "type": "Feature",
  "properties": {
    "iso:country":"ES",
    "sg:address":"Pla\u00c7 Catalunya, 28",
    "sg:city":"Girona",
    "sg:orig_category":"Trajes Y Adornos De Boda (confecci\u00d3n, Al Por Menor)",
    "sg:phone":"+34 972 21 00 58",
    "sg:postcode":"17002",
    "sg:province":"Girona",
    "wof:name":"Marpato, S.l.",
    "wof:placetype":"venue"
},
  "geometry": {"coordinates":[2.8190748692,41.9780960083],"type":"Point"}
}