{
  "type": "Feature",
  "properties": {
    "iso:country":"ES",
    "sg:address":"Otalora Lizentziaduna Kalea, 22",
    "sg:city":"Arrasate",
    "sg:orig_category":"Promotores Constructores",
    "sg:phone":"+34 943 79 60 53",
    "sg:postcode":"20500",
    "sg:province":"Guip\u00f9zcoa",
    "wof:name":"Construcciones Irgala S.a.",
    "wof:placetype":"venue"
},
  "geometry": {"coordinates":[-2.4876449108,43.0665588379],"type":"Point"}
}