{
  "type": "Feature",
  "properties": {
    "iso:country":"ES",
    "sg:address":"Uparan, 1",
    "sg:city":"Aduna",
    "sg:orig_category":"Ropa Y Art\u00cdculos Pre",
    "sg:phone":"+34 943 69 40 00",
    "sg:postcode":"20150",
    "sg:province":"Guip\u00f9zcoa",
    "wof:name":"Manufacturas Infantiles S.a.l.",
    "wof:placetype":"venue"
},
  "geometry": {"coordinates":[-2.047976017,43.1982650757],"type":"Point"}
}