{
  "type": "Feature",
  "properties": {
    "addr:full":"Avda Agirre Lehendakaria, 93 Basauri Vizcaya 48970",
    "addr:housenumber":"93",
    "addr:postcode":"48970",
    "addr:street":"Avda Agirre Lehendakaria",
    "iso:country":"ES",
    "sg:address":"Avda Agirre Lehendakaria, 93",
    "sg:city":"Basauri",
    "sg:orig_category":"Ense\u00d1anza Secundaria: Colegios Y Escuelas Privadas",
    "sg:phone":"+34 944 26 38 52",
    "sg:postcode":"48970",
    "sg:province":"Vizcaya",
    "sg:website":"www.urbibasauri.net",
    "wof:name":"I.e.s. Urbi",
    "wof:placetype":"venue"
},
  "geometry": {"coordinates":[-2.8827011585,43.2364501953],"type":"Point"}
}