{
  "type": "Feature",
  "properties": {
    "iso:country":"ES",
    "sg:address":"Avda Principe De Asturias, 5",
    "sg:city":"Fuenmayor",
    "sg:orig_category":"Ense\u00d1anza Secundaria: Colegios Y Escuelas Privadas",
    "sg:phone":"+34 941 45 08 06",
    "sg:postcode":"26360",
    "sg:province":"La Rioja",
    "wof:name":"Comunidad Autonoma De La Rioja",
    "wof:placetype":"venue"
},
  "geometry": {"coordinates":[-2.564786911,42.4695358276],"type":"Point"}
}