{
  "type": "Feature",
  "properties": {
    "iso:country":"ES",
    "sg:address":"Carrer de Tarragona, 19",
    "sg:city":"Gava",
    "sg:orig_category":"Vallados Y Barreras",
    "sg:phone":"+34 936 62 65 83",
    "sg:postcode":"08850",
    "sg:province":"Barcelona",
    "wof:name":"Cer-cat 2000 S.l.",
    "wof:placetype":"venue"
},
  "geometry": {"coordinates":[2.010821104,41.3013114929],"type":"Point"}
}