{
  "type": "Feature",
  "properties": {
    "addr:full":"Calle de Aparisi Y Guijarro, 6 Mislata Valencia 46920",
    "addr:housenumber":"6",
    "addr:postcode":"46920",
    "addr:street":"Calle De Aparisi Y Guijarro",
    "iso:country":"ES",
    "sg:address":"Calle de Aparisi Y Guijarro, 6",
    "sg:city":"Mislata",
    "sg:orig_category":"Agentes, Concesionarios Y Sucursales De Veh\u00cdculos",
    "sg:phone":"+34 963 79 12 20",
    "sg:postcode":"46920",
    "sg:province":"Valencia",
    "wof:name":"Talleres Marti S. L.",
    "wof:placetype":"venue"
},
  "geometry": {"coordinates":[-0.411865294,39.4722976685],"type":"Point"}
}