{
  "type": "Feature",
  "properties": {
    "iso:country":"ES",
    "sg:address":"Esperanza, 12",
    "sg:city":"Villaricos",
    "sg:orig_category":"Deportes Y Programas De Aventura",
    "sg:phone":"+34 950 46 77 17",
    "sg:postcode":"04618",
    "sg:province":"Almer\u00eda",
    "wof:name":"Ahedo Cuarasa Juan Antonio",
    "wof:placetype":"venue"
},
  "geometry": {"coordinates":[-1.7760591507,37.2463340759],"type":"Point"}
}