{
  "type": "Feature",
  "properties": {
    "iso:country":"ES",
    "sg:address":"Plaz Santi Brouard, 1",
    "sg:city":"Kurtzea",
    "sg:orig_category":"Peluquer\u00cdas, Peluquer\u00cda Mixta",
    "sg:phone":"+34 944 57 10 98",
    "sg:postcode":"48960",
    "sg:province":"Vizcaya",
    "wof:name":"Perez Martin Elisabeth",
    "wof:placetype":"venue"
},
  "geometry": {"coordinates":[-2.8470389843,43.2298049927],"type":"Point"}
}