{
  "type": "Feature",
  "properties": {
    "addr:full":"Rua Loureiros (dos), 29 Santiago De Compostela A Coru\u00f1a 15704",
    "addr:housenumber":"29",
    "addr:postcode":"15704",
    "addr:street":"Rua Loureiros Dos;Corun\u0303A",
    "iso:country":"ES",
    "sg:address":"Rua Loureiros (dos), 29",
    "sg:city":"Santiago De Compostela",
    "sg:orig_category":"Audiovisuales, Tv, Hi",
    "sg:phone":"+34 981 57 62 49",
    "sg:postcode":"15704",
    "sg:province":"A Coru\u00f1a",
    "sg:website":"www.tresdeseoscgi.com",
    "wof:name":"Tresdeseos Animacion S.l.",
    "wof:placetype":"venue"
},
  "geometry": {"coordinates":[-8.5422019958,42.8845329285],"type":"Point"}
}