{
  "type": "Feature",
  "properties": {
    "addr:full":"Avda Enrique Mederos, 31 Llanos De Aridane Santa Cruz De Tenerife 38760",
    "addr:housenumber":"31",
    "addr:postcode":"38760",
    "addr:street":"Avda Enrique Mederos",
    "iso:country":"ES",
    "sg:address":"Avda Enrique Mederos, 31",
    "sg:city":"Llanos De Aridane",
    "sg:orig_category":"Supermercados Y Hipermercados",
    "sg:phone":"+34 922 46 34 00",
    "sg:postcode":"38760",
    "sg:province":"Santa Cruz De Tenerife",
    "wof:name":"Centros De Ahorro San Martin S.l.",
    "wof:placetype":"venue"
},
  "geometry": {"coordinates":[-17.9085597992,28.6563796997],"type":"Point"}
}