{
  "type": "Feature",
  "properties": {
    "iso:country":"ES",
    "sg:address":"Leyre-leire Kalea, 13",
    "sg:city":"Iru\u00f1a",
    "sg:orig_category":"Muebles Y Accesorios Para Cocinas Y Cuartos De Ba\u00d1o (al Por Menor)",
    "sg:phone":"+34 948 24 43 54",
    "sg:postcode":"31003",
    "sg:province":"Navarra",
    "wof:name":"Gn Electrodomesticos S.l.",
    "wof:placetype":"venue"
},
  "geometry": {"coordinates":[-1.6415679455,42.812461853],"type":"Point"}
}