{
  "type": "Feature",
  "properties": {
    "iso:country":"ES",
    "sg:address":"Calle de Raimundo Fernandez Villaverde, 30",
    "sg:city":"Madrid",
    "sg:orig_category":"Ciencias Ocultas",
    "sg:phone":"+34 914 45 68 21",
    "sg:postcode":"28003",
    "sg:province":"Madrid",
    "wof:name":"Estudios Astrales Karvides S.l",
    "wof:placetype":"venue"
},
  "geometry": {"coordinates":[-3.6991529465,40.4464874268],"type":"Point"}
}