{
  "type": "Feature",
  "properties": {
    "addr:full":"Calle de Arco, 4 Consuegra Toledo 45700",
    "addr:housenumber":"4",
    "addr:postcode":"45700",
    "addr:street":"Calle De Arco",
    "iso:country":"ES",
    "sg:address":"Calle de Arco, 4",
    "sg:city":"Consuegra",
    "sg:orig_category":"T\u00c9cnicos Veterinarios",
    "sg:phone":"+34 925 47 54 96",
    "sg:postcode":"45700",
    "sg:province":"Toledo",
    "wof:name":"Lara Sanchez Francisco",
    "wof:placetype":"venue"
},
  "geometry": {"coordinates":[-3.6073656082,39.4609909058],"type":"Point"}
}