{
  "type": "Feature",
  "properties": {
    "iso:country":"ES",
    "sg:address":"Calle de Maestro Puig Valera, 12",
    "sg:city":"Santomera",
    "sg:orig_category":"Muebles, Minoristas",
    "sg:phone":"+34 968 86 46 03",
    "sg:postcode":"30140",
    "sg:province":"Murcia",
    "wof:name":"Dece Muebles, C.b.",
    "wof:placetype":"venue"
},
  "geometry": {"coordinates":[-1.0482859612,38.0596885681],"type":"Point"}
}