{
  "type": "Feature",
  "properties": {
    "iso:country":"ES",
    "sg:address":"Avda Pontevedra, 58",
    "sg:city":"Vilagarcia",
    "sg:orig_category":"Agentes, Concesionarios Y Sucursales De Camiones Y Veh\u00cdculos Industriales",
    "sg:phone":"+34 986 50 15 02",
    "sg:postcode":"36600",
    "sg:province":"Pontevedra",
    "wof:name":"Autos Buenos Aires Galicia S.l.",
    "wof:placetype":"venue"
},
  "geometry": {"coordinates":[-8.7347011566,42.5774307251],"type":"Point"}
}