{
  "type": "Feature",
  "properties": {
    "addr:full":"Calle de Arzobispo Morcillo, 52 Madrid Madrid 28029",
    "addr:housenumber":"52",
    "addr:postcode":"madrid;28029",
    "addr:street":"Calle De Arzobispo Morcillo",
    "iso:country":"ES",
    "sg:address":"Calle de Arzobispo Morcillo, 52",
    "sg:city":"Madrid",
    "sg:orig_category":"Psicoterapeutas",
    "sg:phone":"+34 913 14 61 53",
    "sg:postcode":"28029",
    "sg:province":"Madrid",
    "wof:name":"Malo Gonzalez Luis Carlos",
    "wof:placetype":"venue"
},
  "geometry": {"coordinates":[-3.6977624893,40.4833221436],"type":"Point"}
}