{
  "type": "Feature",
  "properties": {
    "iso:country":"ES",
    "sg:address":"Calle de Gomez Avellaneda, 33",
    "sg:city":"Zaragoza",
    "sg:orig_category":"Alimentaci\u00d3n General (al Por Menor)",
    "sg:phone":"+34 976 52 12 80",
    "sg:postcode":"50018",
    "sg:province":"Zaragoza",
    "wof:name":"Perez Cascan Fernando",
    "wof:placetype":"venue"
},
  "geometry": {"coordinates":[-0.8896785975,41.668636322],"type":"Point"}
}