{
  "type": "Feature",
  "properties": {
    "iso:country":"ES",
    "sg:address":"Carrer de Argenteria (l'), 2",
    "sg:city":"Poligon Industrial Riera De Caldes",
    "sg:orig_category":"Electrolisis, Depurado Del Aluminio Y De Aleaciones",
    "sg:phone":"+34 938 64 57 30",
    "sg:postcode":"08184",
    "sg:province":"Barcelona",
    "wof:name":"Lacados Del Valles S. A.",
    "wof:placetype":"venue"
},
  "geometry": {"coordinates":[2.181032896,41.5802307129],"type":"Point"}
}