{
  "type": "Feature",
  "properties": {
    "iso:country":"ES",
    "sg:address":"Ctra. Alcazar, Km. 0002,0",
    "sg:city":"Cuenca",
    "sg:orig_category":"Resinas Sint\u00c9ticas (fabricaci\u00d3n, Al Por Mayor)",
    "sg:phone":"+34 969 22 05 26",
    "sg:postcode":"16001",
    "sg:province":"Cuenca",
    "wof:name":"Industrial Resinera Valcan S. A.",
    "wof:placetype":"venue"
},
  "geometry": {"coordinates":[-2.1362390518,40.0720710754],"type":"Point"}
}