{
  "type": "Feature",
  "properties": {
    "addr:full":"Carrer de Garcilaso, S/n Barcelona Barcelona 08027",
    "addr:housenumber":"s / n",
    "addr:postcode":"08027",
    "addr:street":"Carrer De Garcilaso",
    "iso:country":"ES",
    "sg:address":"Carrer de Garcilaso, S/n",
    "sg:city":"Barcelona",
    "sg:orig_category":"Centros De Educaci\u00d3n Especial",
    "sg:phone":"+34 933 40 46 25",
    "sg:postcode":"08027",
    "sg:province":"Barcelona",
    "wof:name":"Ajuntament De Barcelona",
    "wof:placetype":"venue"
},
  "geometry": {"coordinates":[2.1875584126,41.4228019714],"type":"Point"}
}