{
  "type": "Feature",
  "properties": {
    "iso:country":"ES",
    "sg:address":"Carrer de Sant Carles, 39",
    "sg:city":"Santa Coloma De Gramenet",
    "sg:orig_category":"Mec\u00c1nico Del Autom\u00d3vil",
    "sg:phone":"+34 933 86 85 42",
    "sg:postcode":"08922",
    "sg:province":"Barcelona",
    "wof:name":"Riera Lopez Maria Lourdes",
    "wof:placetype":"venue"
},
  "geometry": {"coordinates":[2.2088301182,41.4500694275],"type":"Point"}
}