{
  "type": "Feature",
  "properties": {
    "iso:country":"ES",
    "sg:address":"Calle de Bajo Sombra, 38",
    "sg:city":"Hondon Nieves",
    "sg:orig_category":"Fabricaci\u00d3n De Moldes Y Modelos",
    "sg:phone":"+34 965 48 06 77",
    "sg:postcode":"03688",
    "sg:province":"Alicante",
    "wof:name":"Perez Cerdan Enrique",
    "wof:placetype":"venue"
},
  "geometry": {"coordinates":[-0.4810059965,38.3452033997],"type":"Point"}
}