{
  "type": "Feature",
  "properties": {
    "addr:full":"Calle de Blanca De Navarra, 2 Caparroso Navarra 31380",
    "addr:housenumber":"2",
    "addr:postcode":"31380",
    "addr:street":"Calle De Blanca De Navarra",
    "iso:country":"ES",
    "sg:address":"Calle de Blanca De Navarra, 2",
    "sg:city":"Caparroso",
    "sg:orig_category":"Ense\u00d1anza, Formaci\u00d3n Profesional: Aprendizaje",
    "sg:phone":"+34 948 71 08 19",
    "sg:postcode":"31380",
    "sg:province":"Navarra",
    "wof:name":"Ayuntamiento De Caparroso",
    "wof:placetype":"venue"
},
  "geometry": {"coordinates":[-1.6491609812,42.3412895203],"type":"Point"}
}