{
  "type": "Feature",
  "properties": {
    "addr:full":"Calle de Mayor, 17 Alfaro La Rioja 26540",
    "addr:housenumber":"17",
    "addr:postcode":"26540",
    "addr:street":"Calle De Mayor;Rioja",
    "iso:country":"ES",
    "sg:address":"Calle de Mayor, 17",
    "sg:city":"Alfaro",
    "sg:orig_category":"Peluqueros: De Se\u00d1oras",
    "sg:phone":"+34 941 18 42 24",
    "sg:postcode":"26540",
    "sg:province":"La Rioja",
    "wof:name":"Ladron Fraile Maria Cristina",
    "wof:placetype":"venue"
},
  "geometry": {"coordinates":[-1.7511600256,42.1779785156],"type":"Point"}
}