{
  "type": "Feature",
  "properties": {
    "iso:country":"ES",
    "sg:address":"El Rincon, S/n",
    "sg:city":"San Miguel",
    "sg:orig_category":"Asociaciones Y Clubs Deportivos",
    "sg:phone":"+34 922 16 72 39",
    "sg:postcode":"38620",
    "sg:province":"Santa Cruz De Tenerife",
    "wof:name":"Island Image S.l.",
    "wof:placetype":"venue"
},
  "geometry": {"coordinates":[-16.6325435638,28.0912017822],"type":"Point"}
}