{
  "type": "Feature",
  "properties": {
    "addr:full":"Calle de Florian Rey, 6 Zaragoza Zaragoza 50002",
    "addr:housenumber":"6",
    "addr:postcode":"50002",
    "addr:street":"Calle De Florian Rey",
    "iso:country":"ES",
    "sg:address":"Calle de Florian Rey, 6",
    "sg:city":"Zaragoza",
    "sg:orig_category":"Tapiceros Y Tapiceros",
    "sg:phone":"+34 976 39 35 81",
    "sg:postcode":"50002",
    "sg:province":"Zaragoza",
    "wof:name":"Frago Del Hoyo Jesus",
    "wof:placetype":"venue"
},
  "geometry": {"coordinates":[-0.8619003892,41.649356842],"type":"Point"}
}