{
  "type": "Feature",
  "properties": {
    "iso:country":"ES",
    "sg:address":"Calle de Vicente Innerarity, 7",
    "sg:city":"Gijon",
    "sg:orig_category":"Farmacias",
    "sg:phone":"+34 985 36 52 69",
    "sg:postcode":"33204",
    "sg:province":"Asturias",
    "wof:name":"Suarez Gonzalez Nuria",
    "wof:placetype":"venue"
},
  "geometry": {"coordinates":[-5.6503820419,43.5363616943],"type":"Point"}
}