{
  "type": "Feature",
  "properties": {
    "iso:country":"ES",
    "sg:address":"Avda Europa, 15",
    "sg:city":"Malaga",
    "sg:orig_category":"Comercio De Piezas De Recambio Y De Accesorios De Veh\u00cdculos, Veh\u00cdculos Industriales",
    "sg:phone":"+34 952 34 26 50",
    "sg:postcode":"29003",
    "sg:province":"M\u00e1laga",
    "wof:name":"Eurorecambio Al.landalus Sociedad Cooperativa Andaluza",
    "wof:placetype":"venue"
},
  "geometry": {"coordinates":[-4.4420871735,36.7034034729],"type":"Point"}
}