{
  "type": "Feature",
  "properties": {
    "iso:country":"ES",
    "sg:address":"Calle de Fernan Nu\u00d1ez, 6",
    "sg:city":"Malaga",
    "sg:orig_category":"Guarder\u00cdas",
    "sg:phone":"+34 952 34 34 81",
    "sg:postcode":"29002",
    "sg:province":"M\u00e1laga",
    "wof:name":"Fernandez Quijada Cristina",
    "wof:placetype":"venue"
},
  "geometry": {"coordinates":[-4.4301528931,36.7100105286],"type":"Point"}
}