{
  "type": "Feature",
  "properties": {
    "iso:country":"ES",
    "sg:address":"Calle de Miguel De Cervantes, S/n",
    "sg:city":"Santovenia Pisuerga",
    "sg:orig_category":"Centros De Educaci\u00d3n Especial",
    "sg:phone":"+34 983 40 00 47",
    "sg:postcode":"47155",
    "sg:province":"Valladolid",
    "wof:name":"Colegio Publico Nicomedes Sanz",
    "wof:placetype":"venue"
},
  "geometry": {"coordinates":[-4.6877570152,41.6926040649],"type":"Point"}
}