{
  "type": "Feature",
  "properties": {
    "addr:full":"Avda Albufera, 40 Alfafar Valencia 46910",
    "addr:housenumber":"40",
    "addr:postcode":"46910",
    "addr:street":"Avda Albufera",
    "iso:country":"ES",
    "sg:address":"Avda Albufera, 40",
    "sg:city":"Alfafar",
    "sg:orig_category":"Inmobiliaria (agencias)",
    "sg:phone":"+34 963 76 46 43",
    "sg:postcode":"46910",
    "sg:province":"Valencia",
    "sg:website":"www.vivalalfafar.com",
    "wof:name":"Actuaciones Espenta",
    "wof:placetype":"venue"
},
  "geometry": {"coordinates":[-0.3845663965,39.4223556519],"type":"Point"}
}