{
  "type": "Feature",
  "properties": {
    "addr:full":"Plaz Mayor, 18 Burgos Burgos 09003",
    "addr:housenumber":"18",
    "addr:postcode":"09003",
    "addr:street":"Plaz Mayor",
    "iso:country":"ES",
    "sg:address":"Plaz Mayor, 18",
    "sg:city":"Burgos",
    "sg:orig_category":"Ropa De Hogar (al Por Menor)",
    "sg:phone":"+34 947 25 75 35",
    "sg:postcode":"09003",
    "sg:province":"Burgos",
    "sg:website":"www.descamps.com",
    "wof:name":"Pueblanueva Y Pedrajas S.l.",
    "wof:placetype":"venue"
},
  "geometry": {"coordinates":[-3.7009689808,42.3413505554],"type":"Point"}
}