{
  "type": "Feature",
  "properties": {
    "iso:country":"ES",
    "sg:address":"Carrer de Creu Dels Molers, 15",
    "sg:city":"Barcelona",
    "sg:orig_category":"Pelucas Y Postizos",
    "sg:phone":"+34 934 41 26 74",
    "sg:postcode":"08004",
    "sg:province":"Barcelona",
    "wof:name":"Peluqueria New Look Import Export S.l.",
    "wof:placetype":"venue"
},
  "geometry": {"coordinates":[2.1620340347,41.3741798401],"type":"Point"}
}