{
  "type": "Feature",
  "properties": {
    "addr:full":"Plaz Almirante Bastarreche, 3 Aduanas Alicante 03730",
    "addr:housenumber":"3",
    "addr:postcode":"03730",
    "addr:street":"Bastarreche",
    "iso:country":"ES",
    "sg:address":"Plaz Almirante Bastarreche, 3",
    "sg:city":"Aduanas",
    "sg:orig_category":"Loter\u00cda Y T\u00d3mbola",
    "sg:phone":"+34 965 79 27 47",
    "sg:postcode":"03730",
    "sg:province":"Alicante",
    "wof:name":"Mari Ern Antonio",
    "wof:placetype":"venue"
},
  "geometry": {"coordinates":[0.1818622947,38.79504776],"type":"Point"}
}