{
  "type": "Feature",
  "properties": {
    "iso:country":"ES",
    "sg:address":"Pol Ind San Cayetano, 17",
    "sg:city":"Churriana Vega",
    "sg:orig_category":"Empresas De Carpinter\u00cda De Madera",
    "sg:phone":"+34 958 55 29 67",
    "sg:postcode":"18194",
    "sg:province":"Granada",
    "wof:name":"Talleres Bubinda S.l.",
    "wof:placetype":"venue"
},
  "geometry": {"coordinates":[-3.6773679256,37.1503562927],"type":"Point"}
}