{
  "type": "Feature",
  "properties": {
    "iso:country":"ES",
    "sg:address":"Calle de Garcia Morato, 23",
    "sg:city":"Valladolid",
    "sg:orig_category":"Escayola Y Productos De Escayola (fabricaci\u00d3n, Al Por Mayor)",
    "sg:phone":"+34 983 23 26 90",
    "sg:postcode":"47007",
    "sg:province":"Valladolid",
    "wof:name":"Lopez Villarreal Zosimo",
    "wof:placetype":"venue"
},
  "geometry": {"coordinates":[-4.7333469391,41.6430854797],"type":"Point"}
}