{
  "type": "Feature",
  "properties": {
    "iso:country":"ES",
    "sg:address":"Avda Espa\u00d1a (de), S/n",
    "sg:city":"San Eugenio Bajo",
    "sg:orig_category":"Ropa Para Se\u00d1oras Y Caballeros (al Por Menor)",
    "sg:phone":"+34 922 71 25 97",
    "sg:postcode":"38660",
    "sg:province":"Santa Cruz De Tenerife",
    "sg:website":"www.saratenea.es",
    "wof:name":"Inversiones Sara Atenea S.l.",
    "wof:placetype":"venue"
},
  "geometry": {"coordinates":[-16.7335681915,28.0807247162],"type":"Point"}
}