{
  "type": "Feature",
  "properties": {
    "iso:country":"ES",
    "sg:address":"Calle de Poeta Miguel Hernandez, 23",
    "sg:city":"Montilla",
    "sg:classifiers":[
        {
            "category":"Taxi",
            "type":"Transportation"
        }
    ],
    "sg:phone":"+34 957 65 47 75",
    "sg:postcode":"14550",
    "sg:province":"C\u00f3rdoba",
    "wof:name":"Delgado Tejada Manuel",
    "wof:placetype":"venue"
},
  "geometry": {"coordinates":[-4.6302409172,37.5872039795],"type":"Point"}
}