{
  "type": "Feature",
  "properties": {
    "addr:full":"Calle de Mateo Inurria, 31 Madrid Madrid 28036",
    "addr:housenumber":"31",
    "addr:postcode":"madrid;28036",
    "addr:street":"Calle De Mateo Inurria",
    "iso:country":"ES",
    "sg:address":"Calle de Mateo Inurria, 31",
    "sg:city":"Madrid",
    "sg:orig_category":"Ingenier\u00cda, Centros De Estudios (diversos)",
    "sg:phone":"+34 913 50 55 48",
    "sg:postcode":"28036",
    "sg:province":"Madrid",
    "wof:name":"Bernabeu Martinez Eusebio",
    "wof:placetype":"venue"
},
  "geometry": {"coordinates":[-3.6815719604,40.4675521851],"type":"Point"}
}