{
  "type": "Feature",
  "properties": {
    "iso:country":"ES",
    "sg:address":"Avda Bulevar De El Ejido, 218",
    "sg:city":"Ejido",
    "sg:orig_category":"Abogados",
    "sg:phone":"+34 950 48 51 03",
    "sg:postcode":"04700",
    "sg:province":"Almer\u00eda",
    "wof:name":"Aguilera Barranco Salvador",
    "wof:placetype":"venue"
},
  "geometry": {"coordinates":[-2.8177680969,36.7725830078],"type":"Point"}
}