{
  "type": "Feature",
  "properties": {
    "iso:country":"ES",
    "sg:address":"Calle de Matadero, 42",
    "sg:city":"Coin",
    "sg:orig_category":"Promotores Constructores",
    "sg:phone":"+34 952 45 04 70",
    "sg:postcode":"29100",
    "sg:province":"M\u00e1laga",
    "wof:name":"Construcciones Josacri S L",
    "wof:placetype":"venue"
},
  "geometry": {"coordinates":[-4.7590069771,36.6617546082],"type":"Point"}
}