{
  "type": "Feature",
  "properties": {
    "iso:country":"ES",
    "sg:address":"Avda Enrique Martin Cuevas, 101",
    "sg:city":"Motril",
    "sg:orig_category":"Dorados, Plater\u00cda (orfebrer\u00cda)",
    "sg:phone":"+34 958 82 03 36",
    "sg:postcode":"18600",
    "sg:province":"Granada",
    "wof:name":"Pineda Rodriguez Carolina",
    "wof:placetype":"venue"
},
  "geometry": {"coordinates":[-3.5200490952,36.7505493164],"type":"Point"}
}