{
  "type": "Feature",
  "properties": {
    "iso:country":"ES",
    "sg:address":"Calle de Molino (el), 61",
    "sg:city":"Casas Benitez",
    "sg:orig_category":"Bancos",
    "sg:phone":"+34 969 38 24 51",
    "sg:postcode":"16707",
    "sg:province":"Cuenca",
    "wof:name":"Banco Espa\u00f1ol De Credito S.a.",
    "wof:placetype":"venue"
},
  "geometry": {"coordinates":[-2.127177,39.3599967957],"type":"Point"}
}