{
  "type": "Feature",
  "properties": {
    "addr:full":"Carrer de Manila, 63 Barcelona Barcelona 08034",
    "addr:housenumber":"63",
    "addr:postcode":"08034",
    "addr:street":"Carrer De Manila",
    "iso:country":"ES",
    "sg:address":"Carrer de Manila, 63",
    "sg:city":"Barcelona",
    "sg:orig_category":"Inmobiliaria (agencias)",
    "sg:phone":"+34 932 04 12 52",
    "sg:postcode":"08034",
    "sg:province":"Barcelona",
    "wof:name":"Esgal Holding Inversion Y Gestion De Activos Inmobiliarios S.l",
    "wof:placetype":"venue"
},
  "geometry": {"coordinates":[2.1273140907,41.3903198242],"type":"Point"}
}