{
  "type": "Feature",
  "properties": {
    "iso:country":"ES",
    "sg:address":"Calle de Alfonso Xiii, S/n",
    "sg:city":"Fuengirola",
    "sg:orig_category":"Abogados",
    "sg:phone":"+34 952 58 29 82",
    "sg:postcode":"29640",
    "sg:province":"M\u00e1laga",
    "wof:name":"Abalos Nuevo Rafael",
    "wof:placetype":"venue"
},
  "geometry": {"coordinates":[-4.623077,36.541759],"type":"Point"}
}