{
  "type": "Feature",
  "properties": {
    "addr:full":"Calle de Alguer, L', 3 Valencia Valencia 46022",
    "addr:housenumber":"3",
    "addr:postcode":"46022",
    "addr:street":"Calle De Alguer L '",
    "iso:country":"ES",
    "sg:address":"Calle de Alguer, L', 3",
    "sg:city":"Valencia",
    "sg:orig_category":"Asilos De Ancianos. Centros Privados",
    "sg:phone":"+34 963 56 11 88",
    "sg:postcode":"46022",
    "sg:province":"Valencia",
    "wof:name":"Asociacion De Jubilados Y Pensionistas Isla Perdida",
    "wof:placetype":"venue"
},
  "geometry": {"coordinates":[-0.3417536914,39.4706611633],"type":"Point"}
}