{
  "type": "Feature",
  "properties": {
    "iso:country":"ES",
    "sg:address":"Carrer de Sol I Padris, 116",
    "sg:city":"Sabadell",
    "sg:orig_category":"Peluqueros: De Se\u00d1oras",
    "sg:phone":"+34 937 10 39 24",
    "sg:postcode":"08203",
    "sg:province":"Barcelona",
    "wof:name":"Minguez Llorente Santiago",
    "wof:placetype":"venue"
},
  "geometry": {"coordinates":[2.119385004,41.5354690552],"type":"Point"}
}