{
  "type": "Feature",
  "properties": {
    "iso:country":"ES",
    "sg:address":"Avda Gran Via Juan Carlos I, 88",
    "sg:city":"Cieza",
    "sg:orig_category":"Heladeros",
    "sg:phone":"+34 968 76 19 00",
    "sg:postcode":"30530",
    "sg:province":"Murcia",
    "wof:name":"Esteve Hita S.l.",
    "wof:placetype":"venue"
},
  "geometry": {"coordinates":[-1.4170730114,38.2371177673],"type":"Point"}
}