{
  "type": "Feature",
  "properties": {
    "addr:full":"Avda Castilla-la Mancha (de), 160 San Sebastian De Los Reyes Madrid 28700",
    "addr:housenumber":"160",
    "addr:postcode":"28700",
    "addr:street":"Avda Castilla-La Mancha De",
    "iso:country":"ES",
    "sg:address":"Avda Castilla-la Mancha (de), 160",
    "sg:city":"San Sebastian De Los Reyes",
    "sg:orig_category":"Inform\u00c1tica (estudios, Servicios, Asesor\u00cda, Formaci\u00d3n)",
    "sg:phone":"+34 916 53 42 28",
    "sg:postcode":"28700",
    "sg:province":"Madrid",
    "wof:name":"Perez Furdada Jorge",
    "wof:placetype":"venue"
},
  "geometry": {"coordinates":[-3.6386330128,40.55884552],"type":"Point"}
}