{
  "type": "Feature",
  "properties": {
    "addr:full":"Calle de Virgen De La Pe\u00d1a, 30 Pto. Rosario Las Palmas 35600",
    "addr:housenumber":"30",
    "addr:postcode":"35600",
    "addr:street":"Calle De Virgen De La Pen\u0303A;Pto. Rosario Las",
    "iso:country":"ES",
    "sg:address":"Calle de Virgen De La Pe\u00d1a, 30",
    "sg:city":"Pto. Rosario",
    "sg:orig_category":"Quincaller\u00cda (al Por Menor)",
    "sg:phone":"+34 928 53 22 16",
    "sg:postcode":"35600",
    "sg:province":"Las Palmas",
    "wof:name":"Cabrera Marrero Pedro",
    "wof:placetype":"venue"
},
  "geometry": {"coordinates":[-13.8672428131,28.5006904602],"type":"Point"}
}