{
  "type": "Feature",
  "properties": {
    "iso:country":"ES",
    "sg:address":"Rua Rio Limia, 1",
    "sg:city":"Ourense",
    "sg:orig_category":"Molduras, Junquillos, Listones Y Molduras Perforadas",
    "sg:phone":"+34 988 21 34 36",
    "sg:postcode":"32001",
    "sg:province":"Ourense",
    "wof:name":"Breta\u00f1a Lopez Antonio",
    "wof:placetype":"venue"
},
  "geometry": {"coordinates":[-7.8656158447,42.3570251465],"type":"Point"}
}