{
  "type": "Feature",
  "properties": {
    "iso:country":"ES",
    "sg:address":"Ctra Moraleja De Enmedio, 4",
    "sg:city":"Fuenlabrada",
    "sg:orig_category":"Negocio De Madera",
    "sg:phone":"+34 916 85 60 73",
    "sg:postcode":"28944",
    "sg:province":"Madrid",
    "wof:name":"Las 3 Jotas S.l.",
    "wof:placetype":"venue"
},
  "geometry": {"coordinates":[-3.8036530018,40.2771949768],"type":"Point"}
}