{
  "type": "Feature",
  "properties": {
    "addr:full":"Carr Ildefonso Fierro, 28 Pu\u00e7ol Valencia 46530",
    "addr:housenumber":"28",
    "addr:postcode":"46530",
    "addr:street":"Carr Ildefonso Fierro",
    "iso:country":"ES",
    "sg:address":"Carr Ildefonso Fierro, 28",
    "sg:city":"Pu\u00e7ol",
    "sg:orig_category":"Panader\u00cdas, Panader\u00cdas",
    "sg:phone":"+34 961 42 07 53",
    "sg:postcode":"46530",
    "sg:province":"Valencia",
    "wof:name":"Duato Ramos Julio",
    "wof:placetype":"venue"
},
  "geometry": {"coordinates":[-0.3073309958,39.618686676],"type":"Point"}
}