{
  "type": "Feature",
  "properties": {
    "addr:full":"Pase Tilos Los, 13 Malaga M\u00e1laga 29006",
    "addr:postcode":"29006",
    "addr:street":"Ma\u0301Laga",
    "iso:country":"ES",
    "sg:address":"Pase Tilos Los, 13",
    "sg:city":"Malaga",
    "sg:orig_category":"M\u00c9dicos: Radiolog\u00cda (radiodiagn\u00d3stico E Im\u00c1genes En Medicina)",
    "sg:phone":"+34 952 36 39 83",
    "sg:postcode":"29006",
    "sg:province":"M\u00e1laga",
    "wof:name":"Medios Y Asesoramiento Dental S.l.",
    "wof:placetype":"venue"
},
  "geometry": {"coordinates":[-4.4201588631,36.7183189392],"type":"Point"}
}