{
  "type": "Feature",
  "properties": {
    "addr:full":"Avda Pio Xii, 5 Logro\u00f1o La Rioja 26003",
    "addr:housenumber":"5",
    "addr:postcode":"26003",
    "addr:street":"Avda Pio Xii;Rioja",
    "iso:country":"ES",
    "sg:address":"Avda Pio Xii, 5",
    "sg:city":"Logro\u00f1o",
    "sg:orig_category":"Cajas De Ahorro",
    "sg:phone":"+34 941 26 32 08",
    "sg:postcode":"26003",
    "sg:province":"La Rioja",
    "sg:website":"www.cajarioja.es",
    "wof:name":"Caja De Ahorros De La Rioja",
    "wof:placetype":"venue"
},
  "geometry": {"coordinates":[-2.4450480938,42.460723877],"type":"Point"}
}