{
  "type": "Feature",
  "properties": {
    "addr:full":"Calle de Juan De Garay, 46 Valencia Valencia 46017",
    "addr:housenumber":"46",
    "addr:postcode":"46017",
    "addr:street":"Calle De Juan De Garay",
    "iso:country":"ES",
    "sg:address":"Calle de Juan De Garay, 46",
    "sg:city":"Valencia",
    "sg:orig_category":"Agencias Y Agentes Comerciales, Representantes",
    "sg:phone":"+34 963 78 59 26",
    "sg:postcode":"46017",
    "sg:province":"Valencia",
    "wof:name":"Serra Calatayud Jose",
    "wof:placetype":"venue"
},
  "geometry": {"coordinates":[-0.3945530057,39.4547538757],"type":"Point"}
}