{
  "type": "Feature",
  "properties": {
    "iso:country":"ES",
    "sg:address":"Calle de Suarez Guerra, 39",
    "sg:city":"Santa Cruz De Tenerife",
    "sg:orig_category":"Ropa De Trabajo Y Profesionales (fabricaci\u00d3n, Al Por Mayor)",
    "sg:phone":"+34 922 24 38 57",
    "sg:postcode":"38002",
    "sg:province":"Santa Cruz De Tenerife",
    "wof:name":"Gonzalez Gonzalez De Chavez Alberto",
    "wof:placetype":"venue"
},
  "geometry": {"coordinates":[-16.2523860931,28.4682750702],"type":"Point"}
}