{
  "type": "Feature",
  "properties": {
    "iso:country":"ES",
    "sg:address":"Calle de Ten-bel, 7",
    "sg:city":"Costa Del Silencio",
    "sg:orig_category":"Parafarmacias",
    "sg:phone":"+34 922 73 34 72",
    "sg:postcode":"38630",
    "sg:province":"Santa Cruz De Tenerife",
    "wof:name":"Verasana S.l.",
    "wof:placetype":"venue"
},
  "geometry": {"coordinates":[-16.649187088,28.010471344],"type":"Point"}
}