{
  "type": "Feature",
  "properties": {
    "addr:full":"Calle de Bujalance, S/n Montoro C\u00f3rdoba 14600",
    "addr:housenumber":"s / n",
    "addr:postcode":"14600",
    "addr:street":"Calle De Bujalance;Co\u0301Rdoba",
    "iso:country":"ES",
    "sg:address":"Calle de Bujalance, S/n",
    "sg:city":"Montoro",
    "sg:orig_category":"Cooperativas Agr\u00cdcolas",
    "sg:phone":"+34 957 16 03 89",
    "sg:postcode":"14600",
    "sg:province":"C\u00f3rdoba",
    "wof:name":"Cooperativa Olivarera Nuestra Se\u00f1ora De La Merced",
    "wof:placetype":"venue"
},
  "geometry": {"coordinates":[-4.3787941933,38.01171875],"type":"Point"}
}