{
  "type": "Feature",
  "properties": {
    "addr:full":"Calle de Obispo Perez Mu\u00d1oz, 17 Priego Cordoba C\u00f3rdoba 14800",
    "addr:housenumber":"17",
    "addr:postcode":"14800",
    "addr:street":"Calle De Obispo Perez Mun\u0303Oz;Cordoba Co\u0301Rdoba",
    "iso:country":"ES",
    "sg:address":"Calle de Obispo Perez Mu\u00d1oz, 17",
    "sg:city":"Priego Cordoba",
    "sg:orig_category":"Peluquer\u00cdas, Peluquer\u00cda Mixta",
    "sg:phone":"+34 957 54 24 68",
    "sg:postcode":"14800",
    "sg:province":"C\u00f3rdoba",
    "wof:name":"Aguilera Cano Antonia",
    "wof:placetype":"venue"
},
  "geometry": {"coordinates":[-4.1974654198,37.4367027283],"type":"Point"}
}