{
  "type": "Feature",
  "properties": {
    "addr:full":"Carrer de Sot Dels Pradals, 12 Vic Barcelona 08500",
    "addr:housenumber":"12",
    "addr:postcode":"08500",
    "addr:street":"Carrer De Sot Dels Pradals",
    "iso:country":"ES",
    "sg:address":"Carrer de Sot Dels Pradals, 12",
    "sg:city":"Vic",
    "sg:orig_category":"Promotores Constructores",
    "sg:phone":"+34 938 86 92 92",
    "sg:postcode":"08500",
    "sg:province":"Barcelona",
    "wof:name":"Quimica Per A La Construccio S.l.",
    "wof:placetype":"venue"
},
  "geometry": {"coordinates":[2.2492439747,41.9385719299],"type":"Point"}
}