{
  "type": "Feature",
  "properties": {
    "addr:full":"B\u00aa Montemolin, 51 Zaragoza Zaragoza 50013",
    "addr:housenumber":"51",
    "addr:postcode":"50013",
    "addr:street":"Montemolin",
    "iso:country":"ES",
    "sg:address":"B\u00aa Montemolin, 51",
    "sg:city":"Zaragoza",
    "sg:orig_category":"Carb\u00d3n, Carb\u00d3n De Madera (al Por Mayor)",
    "sg:phone":"+34 976 59 85 72",
    "sg:postcode":"50013",
    "sg:province":"Zaragoza",
    "wof:name":"Suministros Energeticos Aragoneses S.l.",
    "wof:placetype":"venue"
},
  "geometry": {"coordinates":[-0.8813189864,41.6517295837],"type":"Point"}
}