{
  "type": "Feature",
  "properties": {
    "addr:full":"Calle de Beraqueta, 1 Irun Guip\u00f9zcoa 20302",
    "addr:housenumber":"1",
    "addr:postcode":"20302",
    "addr:street":"Calle De Beraqueta;Guipu\u0300Zcoa",
    "iso:country":"ES",
    "sg:address":"Calle de Beraqueta, 1",
    "sg:city":"Irun",
    "sg:orig_category":"Servicio De Salud",
    "sg:phone":"+34 943 62 16 92",
    "sg:postcode":"20302",
    "sg:province":"Guip\u00f9zcoa",
    "wof:name":"Fontaneria Y Calefaccion Txingudi S.coop.",
    "wof:placetype":"venue"
},
  "geometry": {"coordinates":[-1.7895389795,43.3401412964],"type":"Point"}
}