{
  "type": "Feature",
  "properties": {
    "addr:full":"Carrer de Bailen, 180 Barcelona Barcelona 08037",
    "addr:housenumber":"180",
    "addr:postcode":"08037",
    "addr:street":"Carrer De Bailen",
    "iso:country":"ES",
    "sg:address":"Carrer de Bailen, 180",
    "sg:city":"Barcelona",
    "sg:orig_category":"Ingeniero De Sonido",
    "sg:phone":"+34 934 59 13 32",
    "sg:postcode":"08037",
    "sg:province":"Barcelona",
    "wof:name":"Servicios Tecnicos Y Organizacion Comercial S.a.",
    "wof:placetype":"venue"
},
  "geometry": {"coordinates":[2.1655979156,41.4008026123],"type":"Point"}
}