{
  "type": "Feature",
  "properties": {
    "addr:full":"Rua Concepcion Arenal, 1 Grove Pontevedra 36980",
    "addr:housenumber":"1",
    "addr:postcode":"36980",
    "addr:street":"Rua Concepcion Arenal",
    "iso:country":"ES",
    "sg:address":"Rua Concepcion Arenal, 1",
    "sg:city":"Grove",
    "sg:orig_category":"Bisuter\u00cda, Joyer\u00cda, Relojer\u00cda (al Por Menor)",
    "sg:phone":"+34 986 73 33 04",
    "sg:postcode":"36980",
    "sg:province":"Pontevedra",
    "wof:name":"Fernandez Rodriguez Benjamin",
    "wof:placetype":"venue"
},
  "geometry": {"coordinates":[-8.8650903702,42.4936790466],"type":"Point"}
}