{
  "type": "Feature",
  "properties": {
    "iso:country":"ES",
    "sg:address":"Carrer de Josep Anselm Clave, 47",
    "sg:city":"S. Just Desvern",
    "sg:orig_category":"Cristaler\u00cdas",
    "sg:phone":"+34 933 71 49 15",
    "sg:postcode":"08960",
    "sg:province":"Barcelona",
    "wof:name":"Collantes Andreu Antonio",
    "wof:placetype":"venue"
},
  "geometry": {"coordinates":[2.0741550922,41.3833694458],"type":"Point"}
}