{
  "type": "Feature",
  "properties": {
    "iso:country":"ES",
    "sg:address":"Calle de Lopez Chicheri, 2",
    "sg:city":"Cehegin",
    "sg:orig_category":"Molduras, Junquillos, Listones Y Molduras Perforadas",
    "sg:phone":"+34 968 74 05 31",
    "sg:postcode":"30430",
    "sg:province":"Murcia",
    "wof:name":"Tudela Abril Francisco",
    "wof:placetype":"venue"
},
  "geometry": {"coordinates":[-1.7986479998,38.0961608887],"type":"Point"}
}