{
  "type": "Feature",
  "properties": {
    "iso:country":"ES",
    "sg:address":"Calle de Pintor Gisbert, 19",
    "sg:city":"Alacant",
    "sg:orig_category":"Droguer\u00cdas (al Por Menor)",
    "sg:phone":"+34 965 13 08 10",
    "sg:postcode":"03005",
    "sg:province":"Alicante",
    "wof:name":"Bernabeu Esclapes Josefa",
    "wof:placetype":"venue"
},
  "geometry": {"coordinates":[-0.4957509935,38.3479576111],"type":"Point"}
}