{
  "type": "Feature",
  "properties": {
    "addr:full":"B, 22 P. I. El Romeral Valencia 46340",
    "addr:housenumber":"22",
    "addr:postcode":"46340",
    "addr:street":"P. I. El",
    "iso:country":"ES",
    "sg:address":"B, 22",
    "sg:city":"P. I. El Romeral",
    "sg:orig_category":"Transportes Por Carretera: Lotes Completos, Mercanc\u00cdas Diversas",
    "sg:phone":"+34 962 30 27 48",
    "sg:postcode":"46340",
    "sg:province":"Valencia",
    "wof:name":"J.cebrian S.l.",
    "wof:placetype":"venue"
},
  "geometry": {"coordinates":[-1.0998990536,39.4906158447],"type":"Point"}
}