{
  "type": "Feature",
  "properties": {
    "iso:country":"ES",
    "sg:address":"Ctra Nacional 340, Km. 0060,8",
    "sg:city":"Villarreal",
    "sg:orig_category":"Muebles, Minoristas",
    "sg:phone":"+34 964 53 81 46",
    "sg:postcode":"12540",
    "sg:province":"Castell\u00f3n",
    "sg:website":"www.andreuworld.com",
    "wof:name":"Albani Mobiliario S.l.",
    "wof:placetype":"venue"
},
  "geometry": {"coordinates":[-0.1214234978,39.9298171997],"type":"Point"}
}