{
  "type": "Feature",
  "properties": {
    "iso:country":"ES",
    "sg:address":"Calle de Alcaiceria De La Loza, 6",
    "sg:city":"Sevilla",
    "sg:orig_category":"Bisuter\u00cda, Joyer\u00cda, Relojer\u00cda (al Por Menor)",
    "sg:phone":"+34 954 22 43 22",
    "sg:postcode":"41004",
    "sg:province":"Sevilla",
    "wof:name":"Arrabal Arcos Fernando",
    "wof:placetype":"venue"
},
  "geometry": {"coordinates":[-5.9920339584,37.3903656006],"type":"Point"}
}