{
  "type": "Feature",
  "properties": {
    "addr:full":"Calle de Kandinsky, S/n Malaga M\u00e1laga 29010",
    "addr:housenumber":"s / n",
    "addr:postcode":"29010",
    "addr:street":"Calle De Kandinsky;Ma\u0301Laga",
    "iso:country":"ES",
    "sg:address":"Calle de Kandinsky, S/n",
    "sg:city":"Malaga",
    "sg:orig_category":"Librer\u00cdas",
    "sg:phone":"+34 952 10 43 11",
    "sg:postcode":"29010",
    "sg:province":"M\u00e1laga",
    "wof:name":"Rivas Gil Milagros",
    "wof:placetype":"venue"
},
  "geometry": {"coordinates":[-4.4831008911,36.75157547],"type":"Point"}
}