{
  "type": "Feature",
  "properties": {
    "iso:country":"ES",
    "sg:address":"Calle de Gran Canaria (de), 9",
    "sg:city":"Humanes De Madrid",
    "sg:orig_category":"Papel Pintado (al Por Menor)",
    "sg:phone":"+34 914 92 05 47",
    "sg:postcode":"28970",
    "sg:province":"Madrid",
    "wof:name":"Exclusivas Lisan S.l.",
    "wof:placetype":"venue"
},
  "geometry": {"coordinates":[-3.8150277138,40.2729187012],"type":"Point"}
}