{
  "type": "Feature",
  "properties": {
    "iso:country":"ES",
    "sg:address":"Carrer de Costa Brava, 73",
    "sg:city":"Torreta",
    "sg:orig_category":"Mec\u00c1nico Del Autom\u00d3vil",
    "sg:phone":"+34 938 70 56 91",
    "sg:postcode":"08430",
    "sg:province":"Barcelona",
    "wof:name":"Ruiz Pavon Marcos",
    "wof:placetype":"venue"
},
  "geometry": {"coordinates":[2.3016400337,41.600063324],"type":"Point"}
}