{
  "type": "Feature",
  "properties": {
    "addr:full":"Cami Ral, 151 Mataro Barcelona 08301",
    "addr:housenumber":"151",
    "addr:postcode":"08301",
    "addr:street":"Ral",
    "iso:country":"ES",
    "sg:address":"Cami Ral, 151",
    "sg:city":"Mataro",
    "sg:orig_category":"Librer\u00cdas",
    "sg:phone":"+34 937 90 47 90",
    "sg:postcode":"08301",
    "sg:province":"Barcelona",
    "wof:name":"Blanchart Conejos Xavier",
    "wof:placetype":"venue"
},
  "geometry": {"coordinates":[2.4515440464,41.539981842],"type":"Point"}
}