{
  "type": "Feature",
  "properties": {
    "iso:country":"ES",
    "sg:address":"Calle de Silos, 16",
    "sg:city":"Aracena",
    "sg:orig_category":"Comercio De Piezas De Recambio Y De Accesorios De Veh\u00cdculos, Veh\u00cdculos Industriales",
    "sg:phone":"+34 959 12 84 60",
    "sg:postcode":"21200",
    "sg:province":"Huelva",
    "wof:name":"Fernandez Romero Antonio",
    "wof:placetype":"venue"
},
  "geometry": {"coordinates":[-6.5638051033,37.8972854614],"type":"Point"}
}