{
  "type": "Feature",
  "properties": {
    "iso:country":"ES",
    "sg:address":"Calle de Concepcion, 21",
    "sg:city":"Almonte",
    "sg:orig_category":"Alquiler De Apartamentos",
    "sg:phone":"+34 959 45 19 19",
    "sg:postcode":"21730",
    "sg:province":"Huelva",
    "wof:name":"Concesion 21 Servicios Inmobiliarios S.l.",
    "wof:placetype":"venue"
},
  "geometry": {"coordinates":[-6.5193929672,37.2611846924],"type":"Point"}
}