{
  "type": "Feature",
  "properties": {
    "addr:full":"Calle de Camino De Murcia, 90 Cieza Murcia 30530",
    "addr:housenumber":"90",
    "addr:postcode":"30530",
    "addr:street":"Calle De Camino De Murcia",
    "iso:country":"ES",
    "sg:address":"Calle de Camino De Murcia, 90",
    "sg:city":"Cieza",
    "sg:orig_category":"Reposter\u00cdas",
    "sg:phone":"+34 968 45 68 64",
    "sg:postcode":"30530",
    "sg:province":"Murcia",
    "wof:name":"Garcia Cano Jose",
    "wof:placetype":"venue"
},
  "geometry": {"coordinates":[-1.4192639589,38.2368927002],"type":"Point"}
}