{
  "type": "Feature",
  "properties": {
    "iso:country":"ES",
    "sg:address":"Rua Doutor Xerman Alonso Hortas, 40",
    "sg:city":"Lugo",
    "sg:orig_category":"Cajas De Ahorro",
    "sg:phone":"+34 982 26 30 38",
    "sg:postcode":"27004",
    "sg:province":"Lugo",
    "sg:website":"www.caixanova.es",
    "wof:name":"Caixa De Aforros De Vigo Ourense E Pontevedra",
    "wof:placetype":"venue"
},
  "geometry": {"coordinates":[-7.5648112297,43.0126647949],"type":"Point"}
}