{
  "type": "Feature",
  "properties": {
    "addr:full":"Ama\u00d1a Kalea, 6 Eibar Guip\u00f9zcoa 20600",
    "addr:housenumber":"6",
    "addr:postcode":"20600",
    "addr:street":"Aman\u0303A Kalea;Guipu\u0300Zcoa",
    "iso:country":"ES",
    "sg:address":"Ama\u00d1a Kalea, 6",
    "sg:city":"Eibar",
    "sg:orig_category":"Asociaciones, Organismos Culturales Y Socioeducativos",
    "sg:phone":"+34 943 70 09 92",
    "sg:postcode":"20600",
    "sg:province":"Guip\u00f9zcoa",
    "wof:name":"Sociedad Cultural Recreativa Ama\u00f1a",
    "wof:placetype":"venue"
},
  "geometry": {"coordinates":[-2.4792289734,43.1854438782],"type":"Point"}
}