{
  "type": "Feature",
  "properties": {
    "addr:full":"Calle de Violeta, 6 Guadalcacin Del Caudillo C\u00e1diz 11591",
    "addr:housenumber":"6",
    "addr:postcode":"11591",
    "addr:street":"Calle De Violeta",
    "iso:country":"ES",
    "sg:address":"Calle de Violeta, 6",
    "sg:city":"Guadalcacin Del Caudillo",
    "sg:orig_category":"Peluquer\u00cdas",
    "sg:phone":"+34 956 15 75 40",
    "sg:postcode":"11591",
    "sg:province":"C\u00e1diz",
    "wof:name":"Garcia De Quiros Alvarez Miguel",
    "wof:placetype":"venue"
},
  "geometry": {"coordinates":[-6.0867471695,36.7148094177],"type":"Point"}
}