{
  "type": "Feature",
  "properties": {
    "addr:full":"Trva Meicende, 117 Meicende La Coru\u00f1a 15140",
    "addr:housenumber":"117",
    "addr:postcode":"15140",
    "addr:street":"Trva Meicende;La Corun\u0303A",
    "iso:country":"ES",
    "sg:address":"Trva Meicende, 117",
    "sg:city":"Meicende",
    "sg:orig_category":"Estancos",
    "sg:phone":"+34 981 26 25 37",
    "sg:postcode":"15140",
    "sg:province":"La Coru\u00f1a",
    "wof:name":"Cedeira Veira Pilar",
    "wof:placetype":"venue"
},
  "geometry": {"coordinates":[-8.4497098923,43.3446998596],"type":"Point"}
}