{
  "type": "Feature",
  "properties": {
    "addr:full":"Calle de Burriana, 1 Alquerias Del Ni\u00e7o Perdido Castell\u00f3n 12539",
    "addr:housenumber":"1",
    "addr:postcode":"12539",
    "addr:street":"Calle De Burriana;Castello\u0301N",
    "iso:country":"ES",
    "sg:address":"Calle de Burriana, 1",
    "sg:city":"Alquerias Del Ni\u00e7o Perdido",
    "sg:orig_category":"Empresarios",
    "sg:phone":"+34 964 51 17 29",
    "sg:postcode":"12539",
    "sg:province":"Castell\u00f3n",
    "wof:name":"Franch Ferrer Pascual",
    "wof:placetype":"venue"
},
  "geometry": {"coordinates":[-0.1119284034,39.8983879089],"type":"Point"}
}