{
  "type": "Feature",
  "properties": {
    "addr:full":"Parc Font Quintos, S/n La Golondrina C\u00f3rdoba 14710",
    "addr:housenumber":"s / n",
    "addr:postcode":"14710",
    "addr:street":"Quintos;La Golondrina Co\u0301Rdoba",
    "iso:country":"ES",
    "sg:address":"Parc Font Quintos, S/n",
    "sg:city":"La Golondrina",
    "sg:orig_category":"Rectificaci\u00d3n, Mecanizado, Fresado",
    "sg:phone":"+34 957 72 31 14",
    "sg:postcode":"14710",
    "sg:province":"C\u00f3rdoba",
    "wof:name":"Mecanizados Tecnomotor S.l.",
    "wof:placetype":"venue"
},
  "geometry": {"coordinates":[-4.9146289825,37.8490753174],"type":"Point"}
}