{
  "type": "Feature",
  "properties": {
    "addr:full":"Calle de Mayor, 42 Garrucha Almer\u00eda 04630",
    "addr:housenumber":"42",
    "addr:postcode":"04630",
    "addr:street":"Calle De Mayor;Almeri\u0301A",
    "iso:country":"ES",
    "sg:address":"Calle de Mayor, 42",
    "sg:city":"Garrucha",
    "sg:orig_category":"Art\u00cdculos De Regalo (al Por Menor)",
    "sg:phone":"+34 950 13 33 25",
    "sg:postcode":"04630",
    "sg:province":"Almer\u00eda",
    "wof:name":"Sanchez-toscano Barbero Carlos",
    "wof:placetype":"venue"
},
  "geometry": {"coordinates":[-1.8207700253,37.184589386],"type":"Point"}
}