{
  "type": "Feature",
  "properties": {
    "iso:country":"ES",
    "sg:address":"Ctra Cordoba-malaga, Km. 0043,3",
    "sg:city":"Montilla",
    "sg:orig_category":"Toneles Y Barriles",
    "sg:phone":"+34 957 65 41 25",
    "sg:postcode":"14550",
    "sg:province":"C\u00f3rdoba",
    "sg:website":"www.toneleriajlrodriguez.com",
    "wof:name":"Toneleria Jose Luis Rodriguez S.l.",
    "wof:placetype":"venue"
},
  "geometry": {"coordinates":[-4.6605410576,37.5884437561],"type":"Point"}
}