{
  "type": "Feature",
  "properties": {
    "addr:full":"Calle de Oro, 24 Aimayr Madrid 28320",
    "addr:housenumber":"24",
    "addr:postcode":"28320",
    "addr:street":"Calle De Oro",
    "iso:country":"ES",
    "sg:address":"Calle de Oro, 24",
    "sg:city":"Aimayr",
    "sg:orig_category":"Reciclaje, Desguace De Veh\u00cdculos",
    "sg:phone":"+34 916 91 70 20",
    "sg:postcode":"28320",
    "sg:province":"Madrid",
    "wof:name":"Perucha Dimayr S.l.",
    "wof:placetype":"venue"
},
  "geometry": {"coordinates":[-3.6342790127,40.2281684875],"type":"Point"}
}