{
  "type": "Feature",
  "properties": {
    "iso:country":"ES",
    "sg:address":"Rond Molinal, 8",
    "sg:city":"Agramunt",
    "sg:orig_category":"Venta, Alquiler De Plataformas Y Barquillas Elevadoras",
    "sg:phone":"+34 973 39 27 13",
    "sg:postcode":"25310",
    "sg:province":"Lleida",
    "wof:name":"Plataformes De Ponent S C P",
    "wof:placetype":"venue"
},
  "geometry": {"coordinates":[1.1054149866,41.784526825],"type":"Point"}
}