{
  "type": "Feature",
  "properties": {
    "addr:full":"A Igrexa, 81 Redondela Pontevedra 36815",
    "addr:housenumber":"81",
    "addr:postcode":"36815",
    "addr:street":"A Igrexa",
    "iso:country":"ES",
    "sg:address":"A Igrexa, 81",
    "sg:city":"Redondela",
    "sg:orig_category":"Abrasivos Y Superabrasivos (fabricaci\u00d3n, Al Por Mayor)",
    "sg:phone":"+34 986 40 05 11",
    "sg:postcode":"36815",
    "sg:province":"Pontevedra",
    "wof:name":"Pferd Ruggeberg S. A.",
    "wof:placetype":"venue"
},
  "geometry": {"coordinates":[-8.6142187119,42.238861084],"type":"Point"}
}