{
  "type": "Feature",
  "properties": {
    "iso:country":"ES",
    "sg:address":"Plaz Easo De, 19",
    "sg:city":"Donostia-san Sebastian",
    "sg:orig_category":"Peluqueros: De Se\u00d1oras",
    "sg:phone":"+34 943 42 43 92",
    "sg:postcode":"20006",
    "sg:province":"Guip\u00f9zcoa",
    "wof:name":"Peluqueria Edima (egurza Aguirreurreta, Edurne)",
    "wof:placetype":"venue"
},
  "geometry": {"coordinates":[-1.9793989658,43.3173866272],"type":"Point"}
}