{
  "type": "Feature",
  "properties": {
    "iso:country":"ES",
    "sg:address":"Calle de Tiermas, 11",
    "sg:city":"Zaragoza",
    "sg:orig_category":"Goma: Materias Primas (producci\u00d3n, Distribuci\u00d3n)",
    "sg:phone":"+34 976 29 65 19",
    "sg:postcode":"50002",
    "sg:province":"Zaragoza",
    "wof:name":"Cintas Adhesivas Ubis S.a.",
    "wof:placetype":"venue"
},
  "geometry": {"coordinates":[-0.8624290228,41.6501579285],"type":"Point"}
}