{
  "type": "Feature",
  "properties": {
    "addr:full":"Av Alacant, 54 Elche Alicante 03203",
    "addr:housenumber":"54",
    "addr:postcode":"03203",
    "addr:street":"Alacant",
    "iso:country":"ES",
    "sg:address":"Av Alacant, 54",
    "sg:city":"Elche",
    "sg:orig_category":"Reposter\u00cdas",
    "sg:phone":"+34 965 42 41 19",
    "sg:postcode":"03203",
    "sg:province":"Alicante",
    "wof:name":"Maria Jose Sanchez Y Jesus Soto C.b.",
    "wof:placetype":"venue"
},
  "geometry": {"coordinates":[-0.6844360232,38.2689666748],"type":"Point"}
}