{
  "type": "Feature",
  "properties": {
    "iso:country":"ES",
    "sg:address":"Poligono Ventilla, S/n",
    "sg:city":"Sotillo Adrada",
    "sg:orig_category":"Agentes, Concesionarios Y Sucursales De Veh\u00cdculos",
    "sg:phone":"+34 918 66 84 62",
    "sg:postcode":"05420",
    "sg:province":"\u00c1vila",
    "wof:name":"Herramar S. A.",
    "wof:placetype":"venue"
},
  "geometry": {"coordinates":[-4.700322628,40.6564216614],"type":"Point"}
}