{
  "type": "Feature",
  "properties": {
    "iso:country":"ES",
    "sg:address":"Carrer de Vilamari, 104",
    "sg:city":"Barcelona",
    "sg:orig_category":"Inmobiliaria (agencias)",
    "sg:phone":"+34 932 26 22 44",
    "sg:postcode":"08015",
    "sg:province":"Barcelona",
    "wof:name":"Barrios Y Bennasar Asociats Sl",
    "wof:placetype":"venue"
},
  "geometry": {"coordinates":[2.1480710506,41.380027771],"type":"Point"}
}