{
  "type": "Feature",
  "properties": {
    "iso:country":"ES",
    "sg:address":"Mikel Arregui, 4",
    "sg:city":"Lakuntza",
    "sg:orig_category":"Pescader\u00cdas (al Por Menor)",
    "sg:phone":"+34 948 57 63 00",
    "sg:postcode":"31830",
    "sg:province":"Navarra",
    "wof:name":"Gamboa Saez De Adana Tania",
    "wof:placetype":"venue"
},
  "geometry": {"coordinates":[-2.0224161148,42.9220542908],"type":"Point"}
}