{
  "type": "Feature",
  "properties": {
    "addr:full":"Calle de Martires, 155 Roda Albacete 02630",
    "addr:housenumber":"155",
    "addr:postcode":"02630",
    "addr:street":"Calle De Martires",
    "iso:country":"ES",
    "sg:address":"Calle de Martires, 155",
    "sg:city":"Roda",
    "sg:orig_category":"Venta, Colocaci\u00d3n, Reparaci\u00d3n De Radiadores Para Veh\u00cdculos",
    "sg:phone":"+34 967 44 04 59",
    "sg:postcode":"02630",
    "sg:province":"Albacete",
    "wof:name":"Roda Diesel S.l.",
    "wof:placetype":"venue"
},
  "geometry": {"coordinates":[-2.1685919762,39.2111320496],"type":"Point"}
}