{
  "type": "Feature",
  "properties": {
    "addr:full":"Calle de Ballen, 4 Montilla C\u00f3rdoba 14550",
    "addr:housenumber":"4",
    "addr:postcode":"14550",
    "addr:street":"Calle De Ballen;Co\u0301Rdoba",
    "iso:country":"ES",
    "sg:address":"Calle de Ballen, 4",
    "sg:city":"Montilla",
    "sg:orig_category":"Confecci\u00d3n (fabricaci\u00d3n, Al Por Mayor)",
    "sg:phone":"+34 957 65 35 04",
    "sg:postcode":"14550",
    "sg:province":"C\u00f3rdoba",
    "wof:name":"Rafael Rodriguez Romero Y Jose Espejo Espejo Cdad.",
    "wof:placetype":"venue"
},
  "geometry": {"coordinates":[-4.6393408775,37.5868186951],"type":"Point"}
}