{
  "type": "Feature",
  "properties": {
    "addr:full":"Av Remolar, 31 Prat Llobregat Barcelona 08820",
    "addr:housenumber":"31",
    "addr:postcode":"08820",
    "addr:street":"Av Remolar;Llobregat",
    "iso:country":"ES",
    "sg:address":"Av Remolar, 31",
    "sg:city":"Prat Llobregat",
    "sg:orig_category":"Energ\u00cda Solar Y Nuevas Energ\u00cdas (equipo, Estudios)",
    "sg:phone":"+34 934 78 58 42",
    "sg:postcode":"08820",
    "sg:province":"Barcelona",
    "sg:website":"www.sensotran.com",
    "wof:name":"Sensotran S.l.",
    "wof:placetype":"venue"
},
  "geometry": {"coordinates":[2.0871789455,41.3262786865],"type":"Point"}
}