{
  "type": "Feature",
  "properties": {
    "iso:country":"ES",
    "sg:address":"Ctra Sentmenat, Km. 0000,5",
    "sg:city":"Santa Perpetua De Mogoda",
    "sg:orig_category":"Inform\u00c1tica: Mantenimiento Y Reparaci\u00d3n De Ordenadores",
    "sg:phone":"+34 935 44 37 49",
    "sg:postcode":"08130",
    "sg:province":"Barcelona",
    "wof:name":"Asistencia Tecnica Mollet Del Valles S.l.",
    "wof:placetype":"venue"
},
  "geometry": {"coordinates":[2.1552245617,41.5646018982],"type":"Point"}
}