{
  "type": "Feature",
  "properties": {
    "addr:full":"Playa Arenillas, 13 Islares Cantabria 39798",
    "addr:housenumber":"13",
    "addr:postcode":"39798",
    "addr:street":"Arenillas",
    "iso:country":"ES",
    "sg:address":"Playa Arenillas, 13",
    "sg:city":"Islares",
    "sg:orig_category":"Estudios De Grabaci\u00d3n Sonora",
    "sg:phone":"+34 942 86 73 65",
    "sg:postcode":"39798",
    "sg:province":"Cantabria",
    "wof:name":"Romeo Molinero Pedro",
    "wof:placetype":"venue"
},
  "geometry": {"coordinates":[-3.3002378941,43.4040870667],"type":"Point"}
}