{
  "type": "Feature",
  "properties": {
    "addr:full":"Carr Alaro, D', 56 Port Islas Baleares 07108",
    "addr:housenumber":"56",
    "addr:postcode":"07108",
    "addr:street":"Carr Alaro D '",
    "iso:country":"ES",
    "sg:address":"Carr Alaro, D', 56",
    "sg:city":"Port",
    "sg:orig_category":"Marketing Directo",
    "sg:phone":"+34 971 63 45 86",
    "sg:postcode":"07108",
    "sg:province":"Islas Baleares",
    "wof:name":"Cms Creativ Marketing Soller S.l.",
    "wof:placetype":"venue"
},
  "geometry": {"coordinates":[2.9117100239,39.6136398315],"type":"Point"}
}