{
  "type": "Feature",
  "properties": {
    "addr:full":"Calle de Alferez Verda, 7 Cabanillas Campo Guadalajara 19171",
    "addr:housenumber":"7",
    "addr:postcode":"19171",
    "addr:street":"Calle De Alferez Verda",
    "iso:country":"ES",
    "sg:address":"Calle de Alferez Verda, 7",
    "sg:city":"Cabanillas Campo",
    "sg:orig_category":"Laboratorios Y Cl\u00cdnicas Veterinarias",
    "sg:phone":"+34 949 33 71 55",
    "sg:postcode":"19171",
    "sg:province":"Guadalajara",
    "wof:name":"Clinica Veterinaria Cabanillas",
    "wof:placetype":"venue"
},
  "geometry": {"coordinates":[-3.2361180782,40.6384811401],"type":"Point"}
}