{
  "type": "Feature",
  "properties": {
    "addr:full":"Calle de Doce Ligero De Artilleria, 15 Logro\u00f1o La Rioja 26004",
    "addr:housenumber":"15",
    "addr:postcode":"26004",
    "addr:street":"Calle De Doce;Logron\u0303O;Rioja",
    "iso:country":"ES",
    "sg:address":"Calle de Doce Ligero De Artilleria, 15",
    "sg:city":"Logro\u00f1o",
    "sg:orig_category":"Mec\u00c1nico Del Autom\u00d3vil",
    "sg:phone":"+34 941 24 51 82",
    "sg:postcode":"26004",
    "sg:province":"La Rioja",
    "wof:name":"Ocon Aramayo Jose Luis",
    "wof:placetype":"venue"
},
  "geometry": {"coordinates":[-2.4378736019,42.4674415588],"type":"Point"}
}