{
  "type": "Feature",
  "properties": {
    "iso:country":"ES",
    "sg:address":"Av Pais Valencia, 56",
    "sg:city":"Benissa",
    "sg:orig_category":"Edici\u00d3n De Diarios, Revistas, Boletines",
    "sg:phone":"+34 965 73 30 03",
    "sg:postcode":"03720",
    "sg:province":"Alicante",
    "sg:website":"www.csn-malaga.com",
    "wof:name":"Rotativos Del Mediterraneo S.l.",
    "wof:placetype":"venue"
},
  "geometry": {"coordinates":[0.0547819994,38.7156448364],"type":"Point"}
}