{
  "type": "Feature",
  "properties": {
    "addr:full":"Calle de Costa Rica, S/n Alcantarilla Murcia 30820",
    "addr:housenumber":"s",
    "addr:postcode":"30820",
    "addr:street":"Calle De Costa Rica;/ N",
    "iso:country":"ES",
    "sg:address":"Calle de Costa Rica, S/n",
    "sg:city":"Alcantarilla",
    "sg:orig_category":"Maquinaria Para Industrias Diversas",
    "sg:phone":"+34 968 80 28 12",
    "sg:postcode":"30820",
    "sg:province":"Murcia",
    "wof:name":"Foisa Levante S.a.",
    "wof:placetype":"venue"
},
  "geometry": {"coordinates":[-1.2378226519,37.9573783875],"type":"Point"}
}