{
  "type": "Feature",
  "properties": {
    "addr:full":"Carrer de Santiago Rusi\u00d1ol, 2 Castelldefels Barcelona 08860",
    "addr:housenumber":"2",
    "addr:postcode":"08860",
    "addr:street":"Carrer De Santiago Rusin\u0303Ol",
    "iso:country":"ES",
    "sg:address":"Carrer de Santiago Rusi\u00d1ol, 2",
    "sg:city":"Castelldefels",
    "sg:orig_category":"Supermercados Y Hipermercados",
    "sg:phone":"+34 936 34 21 70",
    "sg:postcode":"08860",
    "sg:province":"Barcelona",
    "wof:name":"Caprabo S.a.",
    "wof:placetype":"venue"
},
  "geometry": {"coordinates":[1.9758199453,41.2809410095],"type":"Point"}
}