{
  "type": "Feature",
  "properties": {
    "addr:full":"Rua Santo Domingo, 47 Ourense Ourense 32003",
    "addr:housenumber":"47",
    "addr:postcode":"32003",
    "addr:street":"Rua Santo Domingo",
    "iso:country":"ES",
    "sg:address":"Rua Santo Domingo, 47",
    "sg:city":"Ourense",
    "sg:orig_category":"T\u00c9cnicos Veterinarios",
    "sg:phone":"+34 988 23 43 23",
    "sg:postcode":"32003",
    "sg:province":"Ourense",
    "wof:name":"Rodriguez Gonzalez Eugenio",
    "wof:placetype":"venue"
},
  "geometry": {"coordinates":[-7.8631339073,42.3404960632],"type":"Point"}
}