{
  "type": "Feature",
  "properties": {
    "iso:country":"ES",
    "sg:address":"Calle de Hermanos Pinzon, 25",
    "sg:city":"San Antonio Abad",
    "sg:orig_category":"Farmacias",
    "sg:phone":"+34 968 51 29 62",
    "sg:postcode":"30205",
    "sg:province":"Murcia",
    "wof:name":"Moreno Baro Antonio Francisco",
    "wof:placetype":"venue"
},
  "geometry": {"coordinates":[-1.1302499771,37.9829597473],"type":"Point"}
}