{
  "type": "Feature",
  "properties": {
    "iso:country":"ES",
    "sg:address":"Avda Generalisimo, 8",
    "sg:city":"Cabez\u00f3n Sal",
    "sg:orig_category":"Pesca Y Caza: Art\u00cdculos (al Por Menor)",
    "sg:phone":"+34 942 70 18 45",
    "sg:postcode":"39500",
    "sg:province":"Cantabria",
    "wof:name":"Lopez Callejo Eva Maria",
    "wof:placetype":"venue"
},
  "geometry": {"coordinates":[-4.2353463173,43.3080558777],"type":"Point"}
}