{
  "type": "Feature",
  "properties": {
    "addr:full":"Plaz Melendra (de La), 2 Fuenlabrada Madrid 28944",
    "addr:postcode":"28944",
    "addr:street":"Plaz",
    "iso:country":"ES",
    "sg:address":"Plaz Melendra (de La), 2",
    "sg:city":"Fuenlabrada",
    "sg:orig_category":"Cajas De Ahorro",
    "sg:phone":"+34 916 90 22 45",
    "sg:postcode":"28944",
    "sg:province":"Madrid",
    "wof:name":"Cajamar",
    "wof:placetype":"venue"
},
  "geometry": {"coordinates":[-3.7928040028,40.2826004028],"type":"Point"}
}