{
  "type": "Feature",
  "properties": {
    "iso:country":"ES",
    "sg:address":"Sequeiro(s. Xiao), S/n",
    "sg:city":"Sequeiro",
    "sg:orig_category":"Promotores Constructores",
    "sg:phone":"+34 981 38 09 02",
    "sg:postcode":"15578",
    "sg:province":"La Coru\u00f1a",
    "wof:name":"Construcciones Eshor S.l.",
    "wof:placetype":"venue"
},
  "geometry": {"coordinates":[-8.1806354523,43.5493278503],"type":"Point"}
}