{
  "type": "Feature",
  "properties": {
    "addr:full":"Avda Aguirre Lehendakari, 151 Bilbao Vizcaya 48015",
    "addr:housenumber":"151",
    "addr:postcode":"48015",
    "addr:street":"Avda Aguirre Lehendakari",
    "iso:country":"ES",
    "sg:address":"Avda Aguirre Lehendakari, 151",
    "sg:city":"Bilbao",
    "sg:orig_category":"Cajas De Ahorro",
    "sg:phone":"+34 944 75 25 57",
    "sg:postcode":"48015",
    "sg:province":"Vizcaya",
    "wof:name":"Bilbao Bizkaia Kutxa",
    "wof:placetype":"venue"
},
  "geometry": {"coordinates":[-2.9609720707,43.2779159546],"type":"Point"}
}