{
  "type": "Feature",
  "properties": {
    "iso:country":"ES",
    "sg:address":"Carrer de Montserrat, 10",
    "sg:city":"Caldes Montbui",
    "sg:orig_category":"Agencias De Viajes",
    "sg:phone":"+34 938 62 69 21",
    "sg:postcode":"08140",
    "sg:province":"Barcelona",
    "wof:name":"Ridia Viatges S.l.",
    "wof:placetype":"venue"
},
  "geometry": {"coordinates":[2.1661939621,41.6310272217],"type":"Point"}
}