{
  "type": "Feature",
  "properties": {
    "iso:country":"ES",
    "sg:address":"Calle de Fueros De Leon, 1",
    "sg:city":"Ponferrada",
    "sg:orig_category":"M\u00c9dicos: Estomatolog\u00cda",
    "sg:phone":"+34 987 42 76 26",
    "sg:postcode":"24400",
    "sg:province":"Le\u00f3n",
    "wof:name":"Mendez Diaz Ramon",
    "wof:placetype":"venue"
},
  "geometry": {"coordinates":[-6.6008868217,42.5485687256],"type":"Point"}
}