{
  "type": "Feature",
  "properties": {
    "iso:country":"ES",
    "sg:address":"Avda Salle (de La), 26",
    "sg:city":"Santa Cruz De Tenerife",
    "sg:orig_category":"Asesor\u00cda De Formaci\u00d3n Y Gesti\u00d3n De Personal",
    "sg:phone":"+34 922 20 31 41",
    "sg:postcode":"38005",
    "sg:province":"Santa Cruz De Tenerife",
    "wof:name":"J.g. Padilla Maldonado S.l.",
    "wof:placetype":"venue"
},
  "geometry": {"coordinates":[-16.2570667267,28.4612522125],"type":"Point"}
}