{
  "type": "Feature",
  "properties": {
    "iso:country":"ES",
    "sg:address":"Calle de Ordo\u00d1ez, 2",
    "sg:city":"Leganes",
    "sg:orig_category":"Abogados",
    "sg:phone":"+34 916 93 05 27",
    "sg:postcode":"28911",
    "sg:province":"Madrid",
    "wof:name":"Rodriguez Vicente Juan Jose",
    "wof:placetype":"venue"
},
  "geometry": {"coordinates":[-3.7665779591,40.3289451599],"type":"Point"}
}