{
  "type": "Feature",
  "properties": {
    "iso:country":"ES",
    "sg:address":"Poli Industrial Autopista Sur, S/n",
    "sg:city":"Castellon De La Plana",
    "sg:orig_category":"Fabricaci\u00d3n De Juegos Y Juguetes",
    "sg:phone":"+34 964 20 40 00",
    "sg:postcode":"12006",
    "sg:province":"Castell\u00f3n",
    "wof:name":"Juguetes Y Baratijas Martinez S. L.",
    "wof:placetype":"venue"
},
  "geometry": {"coordinates":[-0.1404139996,40.0213813782],"type":"Point"}
}