{
  "type": "Feature",
  "properties": {
    "iso:country":"ES",
    "sg:address":"Real, S/n",
    "sg:city":"Santiago Del Arroyo",
    "sg:orig_category":"Empresarios",
    "sg:phone":"+34 983 69 71 77",
    "sg:postcode":"47164",
    "sg:province":"Valladolid",
    "wof:name":"Sastre Sastre Cayo",
    "wof:placetype":"venue"
},
  "geometry": {"coordinates":[-4.5189490318,41.4500198364],"type":"Point"}
}