{
  "type": "Feature",
  "properties": {
    "addr:full":"Carrer de Calma, S/n Ca\u00f1ada Rio Las Palmas 35627",
    "addr:postcode":"35627",
    "addr:street":"Carrer De Calma S / N Can\u0303Ada Rio Las Palmas",
    "iso:country":"ES",
    "sg:address":"Carrer de Calma, S/n",
    "sg:city":"Ca\u00f1ada Rio",
    "sg:orig_category":"Asociaciones Y Clubs Deportivos",
    "sg:phone":"+34 928 87 54 71",
    "sg:postcode":"35627",
    "sg:province":"Las Palmas",
    "wof:name":"Hodge Podge S.l.",
    "wof:placetype":"venue"
},
  "geometry": {"coordinates":[-14.1530008316,28.1882152557],"type":"Point"}
}