{
  "type": "Feature",
  "properties": {
    "iso:country":"ES",
    "sg:address":"Carr Ramon I Cajal, 44",
    "sg:city":"Cabanes",
    "sg:orig_category":"Asociaciones Y Clubs Deportivos",
    "sg:phone":"+34 964 33 14 36",
    "sg:postcode":"12180",
    "sg:province":"Castell\u00f3n",
    "wof:name":"Amela Siurana Jesus Maria",
    "wof:placetype":"venue"
},
  "geometry": {"coordinates":[0.0440785997,40.1567764282],"type":"Point"}
}