{
  "type": "Feature",
  "properties": {
    "iso:country":"ES",
    "sg:address":"Calle de Mayor, 19",
    "sg:city":"Cartagena",
    "sg:orig_category":"Molduras, Junquillos, Listones Y Molduras Perforadas",
    "sg:phone":"+34 968 50 50 12",
    "sg:postcode":"30205",
    "sg:province":"Murcia",
    "wof:name":"Pagan Perez Juan Carlos",
    "wof:placetype":"venue"
},
  "geometry": {"coordinates":[-0.9971899986,37.6035461426],"type":"Point"}
}