{
  "type": "Feature",
  "properties": {
    "addr:full":"Calle de Carmen, 15 S. Clemente Cuenca 16600",
    "addr:housenumber":"15",
    "addr:postcode":"16600",
    "addr:street":"Calle De Carmen;S. Clemente Cuenca",
    "iso:country":"ES",
    "sg:address":"Calle de Carmen, 15",
    "sg:city":"S. Clemente",
    "sg:orig_category":"Fotograf\u00cda Art\u00cdstica Y Retratos",
    "sg:phone":"+34 969 30 03 70",
    "sg:postcode":"16600",
    "sg:province":"Cuenca",
    "wof:name":"Mesas Pa\u00f1os Carmen",
    "wof:placetype":"venue"
},
  "geometry": {"coordinates":[-2.4228579998,39.4070472717],"type":"Point"}
}