{
  "type": "Feature",
  "properties": {
    "addr:full":"Calle de Calzada De Castro, 69 Almeria Almer\u00eda 04006",
    "addr:housenumber":"69",
    "addr:postcode":"04006",
    "addr:street":"Calle De Calzada De Castro",
    "iso:country":"ES",
    "sg:address":"Calle de Calzada De Castro, 69",
    "sg:city":"Almeria",
    "sg:orig_category":"Lencer\u00cda Femenina, Corseter\u00cda, Trajes De Ba\u00d1o (al Por Menor)",
    "sg:phone":"+34 950 25 90 65",
    "sg:postcode":"04006",
    "sg:province":"Almer\u00eda",
    "wof:name":"Balsalobre Garcia Pilar",
    "wof:placetype":"venue"
},
  "geometry": {"coordinates":[-2.4505488873,36.8383636475],"type":"Point"}
}