{
  "type": "Feature",
  "properties": {
    "iso:country":"ES",
    "sg:address":"Calle de San Francisco, 24",
    "sg:city":"Donostia-san Sebastian",
    "sg:orig_category":"Electricidad: Equipos Industriales, Componentes (fabricaci\u00d3n)",
    "sg:phone":"+34 943 32 15 62",
    "sg:postcode":"20002",
    "sg:province":"Guip\u00f9zcoa",
    "wof:name":"Erka S.l.",
    "wof:placetype":"venue"
},
  "geometry": {"coordinates":[-1.9733749628,43.3240127563],"type":"Point"}
}