{
  "type": "Feature",
  "properties": {
    "addr:full":"Calle de Campillo, S/n Villalbilla De Gumiel Burgos 09453",
    "addr:housenumber":"s / n",
    "addr:postcode":"09453",
    "addr:street":"Calle De Campillo",
    "iso:country":"ES",
    "sg:address":"Calle de Campillo, S/n",
    "sg:city":"Villalbilla De Gumiel",
    "sg:orig_category":"Cooperativas Agr\u00cdcolas",
    "sg:phone":"+34 947 55 70 60",
    "sg:postcode":"09453",
    "sg:province":"Burgos",
    "wof:name":"Cooperativa Del Campo Santiago Apostol",
    "wof:placetype":"venue"
},
  "geometry": {"coordinates":[-3.6261239052,41.8056488037],"type":"Point"}
}