{
  "type": "Feature",
  "properties": {
    "addr:full":"Avda Federico Garcia Lorca, 15 Cabezas S. Juan Sevilla 41730",
    "addr:housenumber":"15",
    "addr:postcode":"41730",
    "addr:street":"Avda Federico Garcia Lorca;S.",
    "iso:country":"ES",
    "sg:address":"Avda Federico Garcia Lorca, 15",
    "sg:city":"Cabezas S. Juan",
    "sg:orig_category":"Comercio, Reparaci\u00d3n De Motocicletas, Bicicletas Y Piezas Sueltas",
    "sg:phone":"+34 955 87 13 75",
    "sg:postcode":"41730",
    "sg:province":"Sevilla",
    "wof:name":"Bernal Repullo Juan Jose",
    "wof:placetype":"venue"
},
  "geometry": {"coordinates":[-5.9371008873,36.9867248535],"type":"Point"}
}