{
  "type": "Feature",
  "properties": {
    "iso:country":"ES",
    "sg:address":"Calle de Boggiero, 136",
    "sg:city":"Zaragoza",
    "sg:orig_category":"Aceites Y Grasas Alimentarias (fabricaci\u00d3n, Al Por Mayor)",
    "sg:phone":"+34 976 43 66 24",
    "sg:postcode":"50003",
    "sg:province":"Zaragoza",
    "wof:name":"Jerez Cebrian Jose Raul",
    "wof:placetype":"venue"
},
  "geometry": {"coordinates":[-0.8900737166,41.6561431885],"type":"Point"}
}