{
  "type": "Feature",
  "properties": {
    "iso:country":"ES",
    "sg:address":"Tv. Bayona, 1",
    "sg:city":"Iru\u00f1a",
    "sg:orig_category":"Ingeniero",
    "sg:phone":"+34 948 25 33 93",
    "sg:postcode":"31011",
    "sg:province":"Navarra",
    "wof:name":"Hualde Oloriz Jose Luis",
    "wof:placetype":"venue"
},
  "geometry": {"coordinates":[-1.6563849449,42.8147087097],"type":"Point"}
}