{
  "type": "Feature",
  "properties": {
    "iso:country":"ES",
    "sg:address":"Calle de San Leon, 40",
    "sg:city":"Santomera",
    "sg:orig_category":"Loter\u00cda Y T\u00d3mbola",
    "sg:phone":"+34 968 86 11 05",
    "sg:postcode":"30140",
    "sg:province":"Murcia",
    "wof:name":"Cano Garcia Teresa Florentina",
    "wof:placetype":"venue"
},
  "geometry": {"coordinates":[-1.0511790514,38.0630187988],"type":"Point"}
}