{
  "type": "Feature",
  "properties": {
    "iso:country":"ES",
    "sg:address":"Carrer de Xiprer, 9",
    "sg:city":"Barcelona",
    "sg:orig_category":"Telas Y Sedas (al Por Menor)",
    "sg:phone":"+34 934 55 82 50",
    "sg:postcode":"08041",
    "sg:province":"Barcelona",
    "wof:name":"Soler Fernandez Montserrat",
    "wof:placetype":"venue"
},
  "geometry": {"coordinates":[2.178155899,41.4169044495],"type":"Point"}
}