{
  "type": "Feature",
  "properties": {
    "addr:full":"Calle de San Isidro, 26 Daimiel Ciudad Real 13250",
    "addr:housenumber":"26",
    "addr:postcode":"13250",
    "addr:street":"Calle De San Isidro",
    "iso:country":"ES",
    "sg:address":"Calle de San Isidro, 26",
    "sg:city":"Daimiel",
    "sg:orig_category":"Empresas De Carpinter\u00cda Met\u00c1lica",
    "sg:phone":"+34 926 85 12 49",
    "sg:postcode":"13250",
    "sg:province":"Ciudad Real",
    "wof:name":"Hierro Y Pvc Hermanos Romero S.l.",
    "wof:placetype":"venue"
},
  "geometry": {"coordinates":[-3.6059188843,39.0641403198],"type":"Point"}
}