{
  "type": "Feature",
  "properties": {
    "addr:full":"Av Madrid, 179 Barcelona Barcelona 08028",
    "addr:housenumber":"179",
    "addr:postcode":"08028",
    "addr:street":"Av Madrid",
    "iso:country":"ES",
    "sg:address":"Av Madrid, 179",
    "sg:city":"Barcelona",
    "sg:orig_category":"Asesor\u00cda Fiscal Y Jur\u00cddica",
    "sg:phone":"+34 933 39 86 00",
    "sg:postcode":"08028",
    "sg:province":"Barcelona",
    "sg:website":"www.sole-balp.com",
    "wof:name":"Sole Balp Jose Maria",
    "wof:placetype":"venue"
},
  "geometry": {"coordinates":[2.1329278946,41.3810958862],"type":"Point"}
}