{
  "type": "Feature",
  "properties": {
    "addr:full":"Carrer de Amilcar, 119 Barcelona Barcelona 08032",
    "addr:housenumber":"119",
    "addr:postcode":"08032",
    "addr:street":"Carrer De Amilcar",
    "iso:country":"ES",
    "sg:address":"Carrer de Amilcar, 119",
    "sg:city":"Barcelona",
    "sg:orig_category":"Fabricaci\u00d3n, Distribuci\u00d3n De Discos, V\u00cddeodiscos Y Musicassettes",
    "sg:phone":"+34 934 55 26 56",
    "sg:postcode":"08032",
    "sg:province":"Barcelona",
    "wof:name":"Star Music S.l.",
    "wof:placetype":"venue"
},
  "geometry": {"coordinates":[2.1725718975,41.4256858826],"type":"Point"}
}