{
  "type": "Feature",
  "properties": {
    "addr:full":"Calle de Menendez Pidal, 5 Madrid Madrid 28036",
    "addr:housenumber":"5",
    "addr:postcode":"28036",
    "addr:street":"Calle De Menendez Pidal",
    "iso:country":"ES",
    "sg:address":"Calle de Menendez Pidal, 5",
    "sg:city":"Madrid",
    "sg:orig_category":"Asociaciones, Organismos Culturales Y Socioeducativos",
    "sg:phone":"+34 913 59 47 24",
    "sg:postcode":"28036",
    "sg:province":"Madrid",
    "wof:name":"Fundacion Ramon Menendez Pidal",
    "wof:placetype":"venue"
},
  "geometry": {"coordinates":[-3.6825740337,40.4601364136],"type":"Point"}
}