{
  "type": "Feature",
  "properties": {
    "addr:full":"Calle de Rafael Finat, 58 Madrid Madrid 28044",
    "addr:housenumber":"58",
    "addr:postcode":"madrid;28044",
    "addr:street":"Calle De Rafael Finat",
    "iso:country":"ES",
    "sg:address":"Calle de Rafael Finat, 58",
    "sg:city":"Madrid",
    "sg:orig_category":"Caf\u00c9s, Bares, Cervecer\u00cdas",
    "sg:phone":"+34 917 06 44 08",
    "sg:postcode":"28044",
    "sg:province":"Madrid",
    "wof:name":"Sevillano Gonzalez Luis",
    "wof:placetype":"venue"
},
  "geometry": {"coordinates":[-3.7728600502,40.3761520386],"type":"Point"}
}