{
  "type": "Feature",
  "properties": {
    "addr:full":"Plaz Rabasa, 9 Madrid Madrid 28044",
    "addr:housenumber":"9",
    "addr:postcode":"madrid;28044",
    "addr:street":"Plaz Rabasa",
    "iso:country":"ES",
    "sg:address":"Plaz Rabasa, 9",
    "sg:city":"Madrid",
    "sg:orig_category":"Estancos",
    "sg:phone":"+34 917 10 70 94",
    "sg:postcode":"28044",
    "sg:province":"Madrid",
    "wof:name":"Izquierdo Rodriguez Jose",
    "wof:placetype":"venue"
},
  "geometry": {"coordinates":[-3.7652740479,40.3753662109],"type":"Point"}
}