{
  "type": "Feature",
  "properties": {
    "addr:full":"Calle de Comercio (del), 49 San Fernando De Henares Madrid 28830",
    "addr:postcode":"28830",
    "addr:street":"Calle De;Del 49",
    "iso:country":"ES",
    "sg:address":"Calle de Comercio (del), 49",
    "sg:city":"San Fernando De Henares",
    "sg:orig_category":"Carnicer\u00cdas, Carnicer\u00cdas",
    "sg:phone":"+34 916 71 39 88",
    "sg:postcode":"28830",
    "sg:province":"Madrid",
    "wof:name":"Trujillo Camacho Agustin",
    "wof:placetype":"venue"
},
  "geometry": {"coordinates":[-3.5300788879,40.4287147522],"type":"Point"}
}