{
  "type": "Feature",
  "properties": {
    "iso:country":"ES",
    "sg:address":"Plaz San Agustin, 27",
    "sg:city":"Coru\u00d1a",
    "sg:orig_category":"Carnicer\u00cdas, Carnicer\u00cdas",
    "sg:phone":"+34 981 22 75 30",
    "sg:postcode":"15001",
    "sg:province":"La Coru\u00f1a",
    "wof:name":"Ares Lois Avelina",
    "wof:placetype":"venue"
},
  "geometry": {"coordinates":[-8.3951234818,43.3712844849],"type":"Point"}
}