{
  "type": "Feature",
  "properties": {
    "iso:country":"ES",
    "sg:address":"Pg Clotada (de La), 70",
    "sg:city":"Senia",
    "sg:orig_category":"Art\u00cdculos De Quincaller\u00cda, Herramientas Y Maquinaria",
    "sg:phone":"+34 977 57 04 96",
    "sg:postcode":"43560",
    "sg:province":"Tarragona",
    "sg:website":"www.jeivsa.com",
    "wof:name":"Jeivsa Brochas Y Pinceles S.l.",
    "wof:placetype":"venue"
},
  "geometry": {"coordinates":[0.2861900032,40.637588501],"type":"Point"}
}