{
  "type": "Feature",
  "properties": {
    "iso:country":"ES",
    "sg:address":"Pase Colon De, 52",
    "sg:city":"Donostia-san Sebastian",
    "sg:orig_category":"M\u00c9dicos: Dermatolog\u00cda Y Venereolog\u00cda",
    "sg:phone":"+34 943 28 35 67",
    "sg:postcode":"20002",
    "sg:province":"Guip\u00f9zcoa",
    "wof:name":"Martinez De Lisarduy I\u00f1igo",
    "wof:placetype":"venue"
},
  "geometry": {"coordinates":[-1.9794000387,43.3173789978],"type":"Point"}
}