{
  "type": "Feature",
  "properties": {
    "iso:country":"ES",
    "sg:address":"Calle de Libertadores Carrera O'higgins, 1",
    "sg:city":"Cordoba",
    "sg:orig_category":"Servicio De Salud",
    "sg:phone":"+34 957 29 80 37",
    "sg:postcode":"14013",
    "sg:province":"C\u00f3rdoba",
    "wof:name":"Saneamientos De Cordoba",
    "wof:placetype":"venue"
},
  "geometry": {"coordinates":[-4.7779159546,37.8573722839],"type":"Point"}
}