{
  "type": "Feature",
  "properties": {
    "addr:full":"Rua Irlanda, S/n Pontevedra Pontevedra 36162",
    "addr:housenumber":"s / n",
    "addr:postcode":"36162",
    "addr:street":"Rua Irlanda",
    "iso:country":"ES",
    "sg:address":"Rua Irlanda, S/n",
    "sg:city":"Pontevedra",
    "sg:orig_category":"Asociaciones Y Clubs Deportivos",
    "sg:phone":"+34 986 84 33 99",
    "sg:postcode":"36162",
    "sg:province":"Pontevedra",
    "wof:name":"Federacion Gallega De Futbol Sala",
    "wof:placetype":"venue"
},
  "geometry": {"coordinates":[-8.6195659637,42.4496269226],"type":"Point"}
}