{
  "type": "Feature",
  "properties": {
    "iso:country":"ES",
    "sg:address":"Calle de Salvador Rueda, S/n",
    "sg:city":"Marbella",
    "sg:orig_category":"Clases De M\u00dasica Y Canto",
    "sg:phone":"+34 952 92 46 88",
    "sg:postcode":"29600",
    "sg:province":"M\u00e1laga",
    "wof:name":"Liceo Artistico Musical Marbella S.l.",
    "wof:placetype":"venue"
},
  "geometry": {"coordinates":[-4.8871788979,36.5128059387],"type":"Point"}
}