{
  "type": "Feature",
  "properties": {
    "iso:country":"ES",
    "sg:address":"Calle de Doctor Fleming, 17",
    "sg:city":"San Vicente Del Raspeig-sant Vicent Del Raspeig",
    "sg:orig_category":"Pod\u00d3logos: Pedicuros",
    "sg:phone":"+34 965 66 22 57",
    "sg:postcode":"03690",
    "sg:province":"Alicante",
    "wof:name":"Romero Palencia Tomas",
    "wof:placetype":"venue"
},
  "geometry": {"coordinates":[-0.520801127,38.3993453979],"type":"Point"}
}