{
  "type": "Feature",
  "properties": {
    "addr:full":"Expl Aeropuerto Carlos Haya, S/n Basozabal Vizcaya 48150",
    "addr:housenumber":"s",
    "addr:postcode":"48150",
    "addr:street":"/ N",
    "iso:country":"ES",
    "sg:address":"Expl Aeropuerto Carlos Haya, S/n",
    "sg:city":"Basozabal",
    "sg:orig_category":"Asociaciones Y Clubs Deportivos",
    "sg:phone":"+34 944 53 01 56",
    "sg:postcode":"48150",
    "sg:province":"Vizcaya",
    "wof:name":"Real Aero-club De Vizcaya",
    "wof:placetype":"venue"
},
  "geometry": {"coordinates":[-2.9244790077,43.2990455627],"type":"Point"}
}