{
  "type": "Feature",
  "properties": {
    "iso:country":"ES",
    "sg:address":"Cmno Elotxelerri Bidea, 2",
    "sg:city":"Elotxelerri",
    "sg:orig_category":"Maquinaria Para Industrias Diversas",
    "sg:phone":"+34 944 53 03 20",
    "sg:postcode":"48180",
    "sg:province":"Vizcaya",
    "wof:name":"Bego\u00f1a Ibarra Jesus",
    "wof:placetype":"venue"
},
  "geometry": {"coordinates":[-2.932158947,43.3143386841],"type":"Point"}
}