{
  "type": "Feature",
  "properties": {
    "addr:full":"Poli Industrial, 74 Guarnizo Cantabria 39611",
    "addr:housenumber":"74",
    "addr:postcode":"39611",
    "iso:country":"ES",
    "sg:address":"Poli Industrial, 74",
    "sg:city":"Guarnizo",
    "sg:orig_category":"Mec\u00c1nico Del Autom\u00d3vil",
    "sg:phone":"+34 942 55 85 88",
    "sg:postcode":"39611",
    "sg:province":"Cantabria",
    "wof:name":"Martin Cuevas Agustin",
    "wof:placetype":"venue"
},
  "geometry": {"coordinates":[-3.8271050453,43.4014930725],"type":"Point"}
}