{
  "type": "Feature",
  "properties": {
    "addr:full":"Avda Calvo Sotelo, S/n Villafranca Bierzo Le\u00f3n 24500",
    "addr:housenumber":"s / n",
    "addr:postcode":"24500",
    "addr:street":"Avda Calvo Sotelo",
    "iso:country":"ES",
    "sg:address":"Avda Calvo Sotelo, S/n",
    "sg:city":"Villafranca Bierzo",
    "sg:orig_category":"Peluquer\u00cdas, Peluquer\u00cda Mixta",
    "sg:phone":"+34 987 54 02 50",
    "sg:postcode":"24500",
    "sg:province":"Le\u00f3n",
    "wof:name":"Peluqueria Corcoba S.l",
    "wof:placetype":"venue"
},
  "geometry": {"coordinates":[-6.8134288788,42.6034355164],"type":"Point"}
}