{
  "type": "Feature",
  "properties": {
    "iso:country":"ES",
    "sg:address":"Calle de Ca\u00d1alizo, 21",
    "sg:city":"Viso Del Alcor",
    "sg:classifiers":[
        {
            "category":"Autos & Motor Vehicles",
            "subcategory":"Automobile Sales",
            "type":"Retail Goods"
        }
    ],
    "sg:phone":"+34 955 94 53 17",
    "sg:postcode":"41520",
    "sg:province":"Sevilla",
    "wof:name":"Autoescuela El Viso S.c.v.",
    "wof:placetype":"venue"
},
  "geometry": {"coordinates":[-5.7233586311,37.3830986023],"type":"Point"}
}