{
  "type": "Feature",
  "properties": {
    "addr:full":"Calle de Ca\u00d1adas (las) San Isidro, 1 San Isidro Santa Cruz De Tenerife 38611",
    "addr:postcode":"38611",
    "addr:street":"Calle De Can\u0303Adas Las San Isidro",
    "iso:country":"ES",
    "sg:address":"Calle de Ca\u00d1adas (las) San Isidro, 1",
    "sg:city":"San Isidro",
    "sg:orig_category":"Inmobiliaria (agencias)",
    "sg:phone":"+34 922 39 42 13",
    "sg:postcode":"38611",
    "sg:province":"Santa Cruz De Tenerife",
    "wof:name":"Arista Gestion Integral S.l.",
    "wof:placetype":"venue"
},
  "geometry": {"coordinates":[-16.56316185,28.0709209442],"type":"Point"}
}