{
  "type": "Feature",
  "properties": {
    "addr:full":"Calle de Purisima (la), 1 Albacete Albacete 02002",
    "addr:housenumber":"1",
    "addr:postcode":"02002",
    "addr:street":"Calle De Purisima La",
    "iso:country":"ES",
    "sg:address":"Calle de Purisima (la), 1",
    "sg:city":"Albacete",
    "sg:orig_category":"Abogados",
    "sg:phone":"+34 967 52 34 27",
    "sg:postcode":"02002",
    "sg:province":"Albacete",
    "wof:name":"Jimenez Tolosa Justo",
    "wof:placetype":"venue"
},
  "geometry": {"coordinates":[-1.8526569605,38.9929122925],"type":"Point"}
}