{
  "type": "Feature",
  "properties": {
    "iso:country":"ES",
    "sg:address":"Calle de Portal Del Rey, 9",
    "sg:city":"Vitoria-gasteiz",
    "sg:orig_category":"Restaurantes",
    "sg:phone":"+34 945 25 66 85",
    "sg:postcode":"01001",
    "sg:province":"\u00c1lava",
    "wof:name":"Albeniz Iturbe Jesus",
    "wof:placetype":"venue"
},
  "geometry": {"coordinates":[-2.6687755585,42.8470573425],"type":"Point"}
}