{
  "type": "Feature",
  "properties": {
    "addr:full":"Calle de Mexico, 5 Arrecife Las Palmas 35500",
    "addr:housenumber":"5",
    "addr:postcode":"35500",
    "addr:street":"Calle De Mexico",
    "iso:country":"ES",
    "sg:address":"Calle de Mexico, 5",
    "sg:city":"Arrecife",
    "sg:orig_category":"Pe\u00d1as Y Asociaciones Varias",
    "sg:phone":"+34 928 80 43 21",
    "sg:postcode":"35500",
    "sg:province":"Las Palmas",
    "wof:name":"Asociacion De Empresarios De Construccio",
    "wof:placetype":"venue"
},
  "geometry": {"coordinates":[-13.561044693,28.9756126404],"type":"Point"}
}