{
  "type": "Feature",
  "properties": {
    "addr:full":"Avda Antonio Tore Tore, S/n Torre Mar M\u00e1laga 29740",
    "addr:housenumber":"s / n",
    "addr:postcode":"29740",
    "addr:street":"Avda Antonio Tore Tore;Ma\u0301Laga",
    "iso:country":"ES",
    "sg:address":"Avda Antonio Tore Tore, S/n",
    "sg:city":"Torre Mar",
    "sg:orig_category":"Arquitectos",
    "sg:phone":"+34 952 96 53 49",
    "sg:postcode":"29740",
    "sg:province":"M\u00e1laga",
    "wof:name":"Mendez Herrera Salvador",
    "wof:placetype":"venue"
},
  "geometry": {"coordinates":[-4.0975542068,36.7368202209],"type":"Point"}
}