{
  "type": "Feature",
  "properties": {
    "iso:country":"ES",
    "sg:address":"Calle de Maestro Marques, 74",
    "sg:city":"Alacant",
    "sg:orig_category":"Electricidad: Instaladores",
    "sg:phone":"+34 965 20 31 62",
    "sg:postcode":"03004",
    "sg:province":"Alicante",
    "wof:name":"Vinal Rocamora Francisco",
    "wof:placetype":"venue"
},
  "geometry": {"coordinates":[-0.4920679927,38.3486289978],"type":"Point"}
}