{
  "type": "Feature",
  "properties": {
    "iso:country":"ES",
    "sg:address":"Barr Vista Alegre, S/n",
    "sg:city":"Cabez\u00f3n Sal",
    "sg:orig_category":"Albergues",
    "sg:phone":"+34 942 70 03 12",
    "sg:postcode":"39500",
    "sg:province":"Cantabria",
    "wof:name":"Calderon Gutierrez Ana Maria",
    "wof:placetype":"venue"
},
  "geometry": {"coordinates":[-4.2374691963,43.3085784912],"type":"Point"}
}