{
  "type": "Feature",
  "properties": {
    "addr:full":"Pl Teresa Valls I Divi, 10 S. Boi Llobregat Barcelona 08830",
    "addr:housenumber":"10",
    "addr:postcode":"08830",
    "addr:street":"Pl;Divi",
    "iso:country":"ES",
    "sg:address":"Pl Teresa Valls I Divi, 10",
    "sg:city":"S. Boi Llobregat",
    "sg:orig_category":"Agencias Y Agentes Comerciales, Representantes",
    "sg:phone":"+34 936 40 85 34",
    "sg:postcode":"08830",
    "sg:province":"Barcelona",
    "wof:name":"Gimenez Fort Oscar",
    "wof:placetype":"venue"
},
  "geometry": {"coordinates":[2.0301780701,41.3513717651],"type":"Point"}
}