{
  "type": "Feature",
  "properties": {
    "addr:full":"Rbla Arago, 35 Lleida Lleida 25003",
    "addr:housenumber":"35",
    "addr:postcode":"25003",
    "addr:street":"Rbla Arago",
    "iso:country":"ES",
    "sg:address":"Rbla Arago, 35",
    "sg:city":"Lleida",
    "sg:orig_category":"Servidores Y Editores De Bases De Datos",
    "sg:phone":"+34 973 26 10 40",
    "sg:postcode":"25003",
    "sg:province":"Lleida",
    "sg:website":"www.irc-hispano.org",
    "wof:name":"Asociacion Irc Hispano",
    "wof:placetype":"venue"
},
  "geometry": {"coordinates":[0.6201590896,41.6140670776],"type":"Point"}
}