{
  "type": "Feature",
  "properties": {
    "addr:full":"Calle de Magallanes, 3 San Vicente De Barakaldo Vizcaya 48903",
    "addr:housenumber":"3",
    "addr:postcode":"48903",
    "addr:street":"Calle De Magallanes",
    "iso:country":"ES",
    "sg:address":"Calle de Magallanes, 3",
    "sg:city":"San Vicente De Barakaldo",
    "sg:orig_category":"Centros M\u00c9dicos Y Sociales, Dispensarios",
    "sg:phone":"+34 944 82 00 94",
    "sg:postcode":"48903",
    "sg:province":"Vizcaya",
    "sg:website":"www.grupoalbor-cohs.com",
    "wof:name":"Cohs Consultores En Cc. Humanas S.l.",
    "wof:placetype":"venue"
},
  "geometry": {"coordinates":[-2.9811499119,43.2819862366],"type":"Point"}
}