{
  "type": "Feature",
  "properties": {
    "iso:country":"ES",
    "sg:address":"Calle de Juan De Las Vi\u00d1as, S/n",
    "sg:city":"Cartuja Baja",
    "sg:orig_category":"Centros De Educaci\u00d3n Especial",
    "sg:phone":"+34 976 50 04 84",
    "sg:postcode":"50720",
    "sg:province":"Zaragoza",
    "wof:name":"Delegacion Provincial Del Ministerio De Educacion Y Ciencia",
    "wof:placetype":"venue"
},
  "geometry": {"coordinates":[-0.8246139884,41.6071166992],"type":"Point"}
}