{
  "type": "Feature",
  "properties": {
    "addr:full":"Las Erillas, S/n Iznalloz Granada 18550",
    "addr:housenumber":"/ n",
    "addr:postcode":"18550",
    "addr:street":"Erillas S",
    "iso:country":"ES",
    "sg:address":"Las Erillas, S/n",
    "sg:city":"Iznalloz",
    "sg:orig_category":"Centros De Educaci\u00d3n Especial",
    "sg:phone":"+34 958 38 42 13",
    "sg:postcode":"18550",
    "sg:province":"Granada",
    "wof:name":"Junta De Andalucia",
    "wof:placetype":"venue"
},
  "geometry": {"coordinates":[-3.5267839432,37.3938217163],"type":"Point"}
}