{
  "type": "Feature",
  "properties": {
    "addr:full":"Ctra. Malaga, Km. 0389,6 Adra Almer\u00eda 04770",
    "addr:postcode":"04770",
    "addr:street":"Ctra. Malaga Km. 0389,6;Almeri\u0301A",
    "iso:country":"ES",
    "sg:address":"Ctra. Malaga, Km. 0389,6",
    "sg:city":"Adra",
    "sg:orig_category":"Distribuci\u00d3n De Petr\u00d3leo Y Derivados",
    "sg:phone":"+34 950 40 05 03",
    "sg:postcode":"04770",
    "sg:province":"Almer\u00eda",
    "wof:name":"Estacion De Servicio Adrasoil S.l.",
    "wof:placetype":"venue"
},
  "geometry": {"coordinates":[-3.0056390762,36.7545166016],"type":"Point"}
}