{
  "type": "Feature",
  "properties": {
    "addr:full":"Calle de Postas, 28 Soria Soria 42002",
    "addr:housenumber":"28",
    "addr:postcode":"42002",
    "addr:street":"Calle De Postas",
    "iso:country":"ES",
    "sg:address":"Calle de Postas, 28",
    "sg:city":"Soria",
    "sg:orig_category":"Motocicletas (agentes, Concesionarios)",
    "sg:phone":"+34 975 21 46 88",
    "sg:postcode":"42002",
    "sg:province":"Soria",
    "wof:name":"Neves Cruz Benedita Rosa",
    "wof:placetype":"venue"
},
  "geometry": {"coordinates":[-2.4591469765,41.7649650574],"type":"Point"}
}