{
  "type": "Feature",
  "properties": {
    "addr:full":"Calle de Julio Larra\u00d1aga, 1 Cuenca Cuenca 16004",
    "addr:housenumber":"1",
    "addr:postcode":"16004",
    "addr:street":"Calle De Julio Larran\u0303Aga",
    "iso:country":"ES",
    "sg:address":"Calle de Julio Larra\u00d1aga, 1",
    "sg:city":"Cuenca",
    "sg:orig_category":"Carnicer\u00cdas, Carnicer\u00cdas",
    "sg:phone":"+34 969 23 70 09",
    "sg:postcode":"16004",
    "sg:province":"Cuenca",
    "wof:name":"Carnicas Ferro S.l.",
    "wof:placetype":"venue"
},
  "geometry": {"coordinates":[-2.1350009441,40.0674972534],"type":"Point"}
}