{
  "type": "Feature",
  "properties": {
    "iso:country":"ES",
    "sg:address":"Rua Damas Apostolicas, 17",
    "sg:city":"Ramallosa",
    "sg:orig_category":"Ropa Para Ni\u00d1os (al Por Menor)",
    "sg:phone":"+34 986 38 60 70",
    "sg:postcode":"36379",
    "sg:province":"Pontevedra",
    "wof:name":"Tartine C.b.",
    "wof:placetype":"venue"
},
  "geometry": {"coordinates":[-8.810918808,42.1176185608],"type":"Point"}
}