{
  "type": "Feature",
  "properties": {
    "iso:country":"ES",
    "sg:address":"Ctra Madrid-cartagena (antigua N-301), Km. 0307,5",
    "sg:city":"Hellin",
    "sg:orig_category":"Aparatos E Instalaci\u00d3n De Regad\u00cdos",
    "sg:phone":"+34 967 30 71 66",
    "sg:postcode":"02400",
    "sg:province":"Albacete",
    "wof:name":"Ingesagua S.l.",
    "wof:placetype":"venue"
},
  "geometry": {"coordinates":[-1.7107850313,38.5228538513],"type":"Point"}
}