{
  "type": "Feature",
  "properties": {
    "iso:country":"ES",
    "sg:address":"Calle de Taquigrafo Marti, 14",
    "sg:city":"Alacant",
    "sg:orig_category":"Inform\u00c1tica, Ofim\u00c1tica (estudios, Asesor\u00cda, Ingenier\u00cda, Formaci\u00d3n)",
    "sg:phone":"+34 965 21 05 96",
    "sg:postcode":"03004",
    "sg:province":"Alicante",
    "wof:name":"Datavideo Novas Tecnologias S.l.",
    "wof:placetype":"venue"
},
  "geometry": {"coordinates":[-0.4884110093,38.3520851135],"type":"Point"}
}