{
  "type": "Feature",
  "properties": {
    "addr:full":"Carrer de Jaume Balmes, 56 S. Pere Ribes Barcelona 08810",
    "addr:housenumber":"56",
    "addr:postcode":"08810",
    "addr:street":"Carrer De Jaume Balmes;S. Pere Ribes Barcelona",
    "iso:country":"ES",
    "sg:address":"Carrer de Jaume Balmes, 56",
    "sg:city":"S. Pere Ribes",
    "sg:orig_category":"Ingenier\u00cda, Centros De Estudios (diversos)",
    "sg:phone":"+34 938 96 30 90",
    "sg:postcode":"08810",
    "sg:province":"Barcelona",
    "wof:name":"Damians Damians S.c.p.",
    "wof:placetype":"venue"
},
  "geometry": {"coordinates":[1.771288991,41.2593269348],"type":"Point"}
}