{
  "type": "Feature",
  "properties": {
    "addr:full":"Calle de Nescania, 8 Sevilla Sevilla 41006",
    "addr:housenumber":"8",
    "addr:postcode":"41006",
    "addr:street":"Calle De Nescania",
    "iso:country":"ES",
    "sg:address":"Calle de Nescania, 8",
    "sg:city":"Sevilla",
    "sg:classifiers":[
        {
            "category":"Autos & Motor Vehicles",
            "subcategory":"Automobile Sales",
            "type":"Retail Goods"
        }
    ],
    "sg:phone":"+34 954 66 06 29",
    "sg:postcode":"41006",
    "sg:province":"Sevilla",
    "wof:name":"Vazquez Alvarez Carlos",
    "wof:placetype":"venue"
},
  "geometry": {"coordinates":[-5.9473171234,37.3756523132],"type":"Point"}
}