{
  "type": "Feature",
  "properties": {
    "iso:country":"ES",
    "sg:address":"Carr Vassallo, 61",
    "sg:city":"Mao",
    "sg:orig_category":"Molduras, Junquillos, Listones Y Molduras Perforadas",
    "sg:phone":"+34 971 35 03 30",
    "sg:postcode":"07703",
    "sg:province":"Islas Baleares",
    "wof:name":"Carretero Pons Irene",
    "wof:placetype":"venue"
},
  "geometry": {"coordinates":[4.2557759285,39.8871574402],"type":"Point"}
}