{
  "type": "Feature",
  "properties": {
    "iso:country":"ES",
    "sg:address":"Plaz Francisco Perojo Cagigas, 13",
    "sg:city":"Solares",
    "sg:orig_category":"Imprenta",
    "sg:phone":"+34 942 52 13 46",
    "sg:postcode":"39710",
    "sg:province":"Cantabria",
    "wof:name":"Garcia Martin Miguel Angel",
    "wof:placetype":"venue"
},
  "geometry": {"coordinates":[-3.7375760078,43.3840255737],"type":"Point"}
}