{
  "type": "Feature",
  "properties": {
    "iso:country":"ES",
    "sg:address":"Calle de Libertad (de La), 29",
    "sg:city":"Mostoles",
    "sg:orig_category":"Muebles, Minoristas",
    "sg:phone":"+34 916 45 65 09",
    "sg:postcode":"28936",
    "sg:province":"Madrid",
    "wof:name":"Mero\u00f1o Garcia Federico",
    "wof:placetype":"venue"
},
  "geometry": {"coordinates":[-3.853853941,40.3272094727],"type":"Point"}
}