{
  "type": "Feature",
  "properties": {
    "iso:country":"ES",
    "sg:address":"Calle de Dali, 16",
    "sg:city":"Olivares",
    "sg:orig_category":"Promotores Constructores",
    "sg:phone":"+34 954 11 05 52",
    "sg:postcode":"41804",
    "sg:province":"Sevilla",
    "wof:name":"Construcciones Hermanos Mu\u00f1oz Gonzalez Cb",
    "wof:placetype":"venue"
},
  "geometry": {"coordinates":[-6.1503982544,37.4202384949],"type":"Point"}
}