{
  "type": "Feature",
  "properties": {
    "addr:full":"Calle de Mu\u00d1oz Crespo, 29 Azuaga Badajoz 06920",
    "addr:housenumber":"29",
    "addr:postcode":"06920",
    "addr:street":"Calle De Mun\u0303Oz Crespo",
    "iso:country":"ES",
    "sg:address":"Calle de Mu\u00d1oz Crespo, 29",
    "sg:city":"Azuaga",
    "sg:orig_category":"Asesor\u00cda Fiscal Y Jur\u00cddica",
    "sg:phone":"+34 924 89 05 78",
    "sg:postcode":"06920",
    "sg:province":"Badajoz",
    "wof:name":"Gabinete Tecnico Dima S.l.",
    "wof:placetype":"venue"
},
  "geometry": {"coordinates":[-5.6759700775,38.2584838867],"type":"Point"}
}