{
  "type": "Feature",
  "properties": {
    "iso:country":"ES",
    "sg:address":"Rond Zamenhof, 149",
    "sg:city":"Sabadell",
    "sg:orig_category":"M\u00c9dicos: Estomatolog\u00cda",
    "sg:phone":"+34 937 27 84 22",
    "sg:postcode":"08201",
    "sg:province":"Barcelona",
    "wof:name":"Espinoza Garcia Jose",
    "wof:placetype":"venue"
},
  "geometry": {"coordinates":[2.0996160507,41.5503196716],"type":"Point"}
}