{
  "type": "Feature",
  "properties": {
    "iso:country":"ES",
    "sg:address":"Calle de Canaleja (la), 4",
    "sg:city":"Alcorcon",
    "sg:orig_category":"Electrodom\u00c9sticos (al Por Menor)",
    "sg:phone":"+34 916 11 84 07",
    "sg:postcode":"28921",
    "sg:province":"Madrid",
    "wof:name":"Garcia De Agueda Oscar",
    "wof:placetype":"venue"
},
  "geometry": {"coordinates":[-3.8255271912,40.3502426147],"type":"Point"}
}