{
  "type": "Feature",
  "properties": {
    "iso:country":"ES",
    "sg:address":"Avda Andalucia, S/n",
    "sg:city":"Peal Becerro",
    "sg:orig_category":"Fabricaci\u00d3n De Productos Textiles Sin Tejer",
    "sg:phone":"+34 953 73 05 00",
    "sg:postcode":"23460",
    "sg:province":"Ja\u00e9n",
    "wof:name":"Fernandez Hernandez Pedro",
    "wof:placetype":"venue"
},
  "geometry": {"coordinates":[-3.1102941036,37.9139595032],"type":"Point"}
}