{
  "type": "Feature",
  "properties": {
    "iso:country":"ES",
    "sg:address":"Calle de General Vives, 35",
    "sg:city":"Palmas De Gran Canaria",
    "sg:orig_category":"Ingenier\u00cda, Centros De Estudios (industria)",
    "sg:phone":"+34 928 27 58 07",
    "sg:postcode":"35007",
    "sg:province":"Las Palmas",
    "wof:name":"Medina Toledo Antonio Luis",
    "wof:placetype":"venue"
},
  "geometry": {"coordinates":[-15.4313220978,28.1371936798],"type":"Point"}
}