{
  "type": "Feature",
  "properties": {
    "addr:full":"Avda Tres De Agosto, 96 Aspe Alicante 03680",
    "addr:housenumber":"96",
    "addr:postcode":"03680",
    "addr:street":"Avda Tres De Agosto",
    "iso:country":"ES",
    "sg:address":"Avda Tres De Agosto, 96",
    "sg:city":"Aspe",
    "sg:orig_category":"Muebles Y Accesorios Para Cocinas Y Cuartos De Ba\u00d1o (al Por Menor)",
    "sg:phone":"+34 965 49 14 43",
    "sg:postcode":"03680",
    "sg:province":"Alicante",
    "wof:name":"Eliba\u00f1o S.l.",
    "wof:placetype":"venue"
},
  "geometry": {"coordinates":[-0.775947988,38.3402938843],"type":"Point"}
}