{
  "type": "Feature",
  "properties": {
    "iso:country":"ES",
    "sg:address":"Calle de Pocillo, 1",
    "sg:city":"Calvarrasa Abajo",
    "sg:classifiers":[
        {
            "category":"Taxi",
            "type":"Transportation"
        }
    ],
    "sg:phone":"+34 923 30 60 73",
    "sg:postcode":"37181",
    "sg:province":"Salamanca",
    "wof:name":"Hernandez Juanes Abel",
    "wof:placetype":"venue"
},
  "geometry": {"coordinates":[-5.5526099205,40.944683075],"type":"Point"}
}