{
  "type": "Feature",
  "properties": {
    "addr:full":"Carrer de Casanova, 1 Barcelona Barcelona 08011",
    "addr:housenumber":"1",
    "addr:postcode":"08011",
    "addr:street":"Carrer De Casanova",
    "iso:country":"ES",
    "sg:address":"Carrer de Casanova, 1",
    "sg:city":"Barcelona",
    "sg:orig_category":"Colchones (fabricaci\u00d3n, Al Por Mayor, Al Por Menor)",
    "sg:phone":"+34 934 26 62 63",
    "sg:postcode":"08011",
    "sg:province":"Barcelona",
    "wof:name":"Multicolchon S.l.",
    "wof:placetype":"venue"
},
  "geometry": {"coordinates":[2.1632580757,41.3818511963],"type":"Point"}
}