{
  "type": "Feature",
  "properties": {
    "addr:full":"Carrer de Viladomat, 206 Barcelona Barcelona 08029",
    "addr:housenumber":"206",
    "addr:postcode":"08029",
    "addr:street":"Carrer De Viladomat",
    "iso:country":"ES",
    "sg:address":"Carrer de Viladomat, 206",
    "sg:city":"Barcelona",
    "sg:orig_category":"Reposter\u00cdas",
    "sg:phone":"+34 934 30 90 99",
    "sg:postcode":"08029",
    "sg:province":"Barcelona",
    "wof:name":"Viladomat Food S.l.",
    "wof:placetype":"venue"
},
  "geometry": {"coordinates":[2.1504070759,41.3850860596],"type":"Point"}
}