{
  "type": "Feature",
  "properties": {
    "addr:full":"Avda San Rogelio, 10 Illora Granada 18260",
    "addr:housenumber":"10",
    "addr:postcode":"18260",
    "addr:street":"Avda San Rogelio",
    "iso:country":"ES",
    "sg:address":"Avda San Rogelio, 10",
    "sg:city":"Illora",
    "sg:orig_category":"Art\u00cdculos Funerarios (al Por Menor)",
    "sg:phone":"+34 958 46 31 06",
    "sg:postcode":"18260",
    "sg:province":"Granada",
    "wof:name":"Palma Lopez Francisco",
    "wof:placetype":"venue"
},
  "geometry": {"coordinates":[-3.8777999878,37.2873420715],"type":"Point"}
}