{
  "type": "Feature",
  "properties": {
    "iso:country":"ES",
    "sg:address":"Avda Libertad De La, 25",
    "sg:city":"Donostia-san Sebastian",
    "sg:orig_category":"Zapatos (al Por Menor)",
    "sg:phone":"+34 943 42 70 00",
    "sg:postcode":"20004",
    "sg:province":"Guip\u00f9zcoa",
    "wof:name":"Javier Ayestaran S.l.",
    "wof:placetype":"venue"
},
  "geometry": {"coordinates":[-1.9827469587,43.3191413879],"type":"Point"}
}