{
  "type": "Feature",
  "properties": {
    "iso:country":"ES",
    "sg:address":"Calle de Virgen Milagrosa, 4",
    "sg:city":"Irun",
    "sg:orig_category":"Plomeros",
    "sg:phone":"+34 943 62 24 45",
    "sg:postcode":"20304",
    "sg:province":"Guip\u00f9zcoa",
    "wof:name":"Suministros Jon S.l.",
    "wof:placetype":"venue"
},
  "geometry": {"coordinates":[-1.7872999907,43.3362350464],"type":"Point"}
}