{
  "type": "Feature",
  "properties": {
    "addr:full":"Barrio Velhoco, S/n Santa Cruz Palma Santa Cruz De Tenerife 38700",
    "addr:housenumber":"s / n",
    "addr:postcode":"38700",
    "addr:street":"Barrio Velhoco",
    "iso:country":"ES",
    "sg:address":"Barrio Velhoco, S/n",
    "sg:city":"Santa Cruz Palma",
    "sg:orig_category":"Restaurantes",
    "sg:phone":"+34 922 41 12 88",
    "sg:postcode":"38700",
    "sg:province":"Santa Cruz De Tenerife",
    "wof:name":"Pepejuancho S.l.l.",
    "wof:placetype":"venue"
},
  "geometry": {"coordinates":[-17.7833518982,28.6913528442],"type":"Point"}
}