{
  "type": "Feature",
  "properties": {
    "iso:country":"ES",
    "sg:address":"Plaz Marques De Aracena, 8",
    "sg:city":"Aracena",
    "sg:orig_category":"Zapatos (al Por Menor)",
    "sg:phone":"+34 959 12 82 65",
    "sg:postcode":"21200",
    "sg:province":"Huelva",
    "wof:name":"Calzados Roncero S.c.",
    "wof:placetype":"venue"
},
  "geometry": {"coordinates":[-6.5608458519,37.8939094543],"type":"Point"}
}