{
  "type": "Feature",
  "properties": {
    "addr:full":"Calle de Hernan Cortes, 2 Puerto Mazarron Murcia 30860",
    "addr:housenumber":"2",
    "addr:postcode":"30860",
    "addr:street":"Calle De Hernan Cortes",
    "iso:country":"ES",
    "sg:address":"Calle de Hernan Cortes, 2",
    "sg:city":"Puerto Mazarron",
    "sg:orig_category":"\u00d3ptica: Instrumentos (fabricaci\u00d3n)",
    "sg:phone":"+34 968 15 34 13",
    "sg:postcode":"30860",
    "sg:province":"Murcia",
    "wof:name":"Perez Garcia Maria Jesus",
    "wof:placetype":"venue"
},
  "geometry": {"coordinates":[-1.2588479519,37.5635108948],"type":"Point"}
}