{
  "type": "Feature",
  "properties": {
    "iso:country":"ES",
    "sg:address":"Calle de Averroes, 5",
    "sg:city":"Bormujos",
    "sg:orig_category":"Empresarios",
    "sg:phone":"+34 954 78 97 56",
    "sg:postcode":"41930",
    "sg:province":"Sevilla",
    "wof:name":"Sevillana De Reformas S.l.",
    "wof:placetype":"venue"
},
  "geometry": {"coordinates":[-6.0820689201,37.3729362488],"type":"Point"}
}