{
  "type": "Feature",
  "properties": {
    "iso:country":"ES",
    "sg:address":"Trav Dalt, 17",
    "sg:city":"Barcelona",
    "sg:orig_category":"Asesor\u00cda Sobre Comunicaci\u00d3n De Empresas",
    "sg:phone":"+34 932 17 34 76",
    "sg:postcode":"08024",
    "sg:province":"Barcelona",
    "wof:name":"J.d.q. Serveis S.l.",
    "wof:placetype":"venue"
},
  "geometry": {"coordinates":[2.1518080235,41.4085197449],"type":"Point"}
}