{
  "type": "Feature",
  "properties": {
    "addr:full":"Calle de Viriato, S/n Pto. Rosario Las Palmas 35600",
    "addr:housenumber":"s / n",
    "addr:postcode":"35600",
    "addr:street":"Calle De Viriato;Pto. Rosario Las",
    "iso:country":"ES",
    "sg:address":"Calle de Viriato, S/n",
    "sg:city":"Pto. Rosario",
    "sg:orig_category":"Transportes Por V\u00cdas Navegables",
    "sg:phone":"+34 928 85 02 41",
    "sg:postcode":"35600",
    "sg:province":"Las Palmas",
    "wof:name":"Rodriguez Umpierrez Valentin",
    "wof:placetype":"venue"
},
  "geometry": {"coordinates":[-13.8487243652,28.5038795471],"type":"Point"}
}