{
  "type": "Feature",
  "properties": {
    "addr:full":"Poli Paz (la), S/n Teruel Teruel 44195",
    "addr:postcode":"44195",
    "addr:street":"La S / N;Teruel",
    "iso:country":"ES",
    "sg:address":"Poli Paz (la), S/n",
    "sg:city":"Teruel",
    "sg:orig_category":"Control T\u00c9cnico De Veh\u00cdculos",
    "sg:phone":"+34 978 60 29 64",
    "sg:postcode":"44195",
    "sg:province":"Teruel",
    "wof:name":"Itv Barbastro S.a.",
    "wof:placetype":"venue"
},
  "geometry": {"coordinates":[-1.1755470037,40.358417511],"type":"Point"}
}