{
  "type": "Feature",
  "properties": {
    "addr:full":"Lugar La Jara, S/n Sanlucar C\u00e1diz 11540",
    "addr:housenumber":"s / n",
    "addr:postcode":"11540",
    "addr:street":"Lugar La Jara",
    "iso:country":"ES",
    "sg:address":"Lugar La Jara, S/n",
    "sg:city":"Sanlucar",
    "sg:orig_category":"T\u00c9cnicos Veterinarios",
    "sg:phone":"+34 956 38 92 05",
    "sg:postcode":"11540",
    "sg:province":"C\u00e1diz",
    "wof:name":"Bustillo Del Rio Maria Regla",
    "wof:placetype":"venue"
},
  "geometry": {"coordinates":[-6.2902097702,36.5298614502],"type":"Point"}
}