{
  "type": "Feature",
  "properties": {
    "addr:full":"Calle de Barrionuevo, 12 Cordoba C\u00f3rdoba 14002",
    "addr:housenumber":"12",
    "addr:postcode":"14002",
    "addr:street":"Calle De Barrionuevo;Co\u0301Rdoba",
    "iso:country":"ES",
    "sg:address":"Calle de Barrionuevo, 12",
    "sg:city":"Cordoba",
    "sg:orig_category":"Comercio De Muebles De Estilo Y Contempor\u00c1neos",
    "sg:phone":"+34 957 25 35 26",
    "sg:postcode":"14002",
    "sg:province":"C\u00f3rdoba",
    "wof:name":"Valverde Lujan Andres",
    "wof:placetype":"venue"
},
  "geometry": {"coordinates":[-4.767411232,37.8836936951],"type":"Point"}
}