{
  "type": "Feature",
  "properties": {
    "iso:country":"ES",
    "sg:address":"Calle de Nueva Avenida, 4",
    "sg:city":"Navalmoral Mata",
    "sg:orig_category":"Masajistas Kinesiterapeutas",
    "sg:phone":"+34 927 53 01 49",
    "sg:postcode":"10300",
    "sg:province":"C\u00e1ceres",
    "wof:name":"Nieto Gonzalez Angela",
    "wof:placetype":"venue"
},
  "geometry": {"coordinates":[-5.5331192017,39.8893547058],"type":"Point"}
}