{
  "type": "Feature",
  "properties": {
    "addr:full":"Calle de Nueva Avenida, 4 Navalmoral Mata C\u00e1ceres 10300",
    "addr:postcode":"10300",
    "addr:street":"Calle De;Avenida 4 Navalmoral Mata Ca\u0301Ceres",
    "iso:country":"ES",
    "sg:address":"Calle de Nueva Avenida, 4",
    "sg:city":"Navalmoral Mata",
    "sg:orig_category":"Masajistas Kinesiterapeutas",
    "sg:phone":"+34 927 53 01 49",
    "sg:postcode":"10300",
    "sg:province":"C\u00e1ceres",
    "wof:name":"Nieto Gonzalez Angela",
    "wof:placetype":"venue"
},
  "geometry": {"coordinates":[-5.5331192017,39.8893547058],"type":"Point"}
}