{
  "type": "Feature",
  "properties": {
    "iso:country":"ES",
    "sg:address":"Avda Ciudad De Barcelona, 101",
    "sg:city":"Madrid",
    "sg:orig_category":"Farmacias",
    "sg:phone":"+34 915 51 28 55",
    "sg:postcode":"28007",
    "sg:province":"Madrid",
    "wof:name":"Fernandez-montes Moraleda Angel",
    "wof:placetype":"venue"
},
  "geometry": {"coordinates":[-3.6716558933,40.3997421265],"type":"Point"}
}