{
  "type": "Feature",
  "properties": {
    "iso:country":"ES",
    "sg:address":"Calle de Crucero, 8",
    "sg:city":"Luarca",
    "sg:orig_category":"Frutas, Legumbres Frescas Y Tempranas (al Por Menor)",
    "sg:phone":"+34 985 64 09 61",
    "sg:postcode":"33700",
    "sg:province":"Asturias",
    "wof:name":"Suarez Garcia Marino Arturo",
    "wof:placetype":"venue"
},
  "geometry": {"coordinates":[-6.4823179245,43.5019721985],"type":"Point"}
}