{
  "type": "Feature",
  "properties": {
    "addr:full":"Calle de Santa Ana, 12 Carcabuey C\u00f3rdoba 14810",
    "addr:housenumber":"12",
    "addr:postcode":"14810",
    "addr:street":"Calle De Santa Ana",
    "iso:country":"ES",
    "sg:address":"Calle de Santa Ana, 12",
    "sg:city":"Carcabuey",
    "sg:orig_category":"Farmacias",
    "sg:phone":"+34 957 55 30 07",
    "sg:postcode":"14810",
    "sg:province":"C\u00f3rdoba",
    "wof:name":"Serrano Funes Maria Dolores",
    "wof:placetype":"venue"
},
  "geometry": {"coordinates":[-4.2740797997,37.4433708191],"type":"Point"}
}