{
  "type": "Feature",
  "properties": {
    "iso:country":"ES",
    "sg:address":"Mercaderes, 21",
    "sg:city":"Iru\u00f1a",
    "sg:orig_category":"Ingenier\u00cda, Centros De Estudios (diversos)",
    "sg:phone":"+34 948 22 17 11",
    "sg:postcode":"31001",
    "sg:province":"Navarra",
    "wof:name":"Yako Ingenieros",
    "wof:placetype":"venue"
},
  "geometry": {"coordinates":[-1.6431227922,42.8184890747],"type":"Point"}
}