{
  "type": "Feature",
  "properties": {
    "addr:full":"Luga Atalaya (la), S/n Adeje Santa Cruz De Tenerife 38670",
    "addr:postcode":"38670",
    "addr:street":"La S / N",
    "iso:country":"ES",
    "sg:address":"Luga Atalaya (la), S/n",
    "sg:city":"Adeje",
    "sg:orig_category":"Cristaler\u00cdas",
    "sg:phone":"+34 922 71 13 02",
    "sg:postcode":"38670",
    "sg:province":"Santa Cruz De Tenerife",
    "wof:name":"Cristaleria Adeje S.l.l.",
    "wof:placetype":"venue"
},
  "geometry": {"coordinates":[-16.7403354645,28.1287555695],"type":"Point"}
}