{
  "type": "Feature",
  "properties": {
    "iso:country":"ES",
    "sg:address":"Calle de Jacinto, 1",
    "sg:city":"Navalmoral Mata",
    "sg:orig_category":"Inform\u00c1tica: Material Y Suministros",
    "sg:phone":"+34 927 53 80 37",
    "sg:postcode":"10300",
    "sg:province":"C\u00e1ceres",
    "sg:website":"www.micro-sip.com",
    "wof:name":"Micro Sip Sistemas S.l.",
    "wof:placetype":"venue"
},
  "geometry": {"coordinates":[-5.5416040421,39.8925857544],"type":"Point"}
}