{
  "type": "Feature",
  "properties": {
    "addr:full":"Carr Jorge Juan, 109 Burjassot Valencia 46100",
    "addr:housenumber":"109",
    "addr:postcode":"46100",
    "addr:street":"Carr Jorge Juan",
    "iso:country":"ES",
    "sg:address":"Carr Jorge Juan, 109",
    "sg:city":"Burjassot",
    "sg:orig_category":"Cajas De Ahorro",
    "sg:phone":"+34 963 63 70 16",
    "sg:postcode":"46100",
    "sg:province":"Valencia",
    "sg:website":"www.bancaja.es",
    "wof:name":"Caja De Ahorros De Valencia Castellon Y Alicante",
    "wof:placetype":"venue"
},
  "geometry": {"coordinates":[-0.4109350145,39.5084991455],"type":"Point"}
}