{
  "type": "Feature",
  "properties": {
    "addr:full":"Av Barbera, 328 Sabadell Barcelona 08203",
    "addr:housenumber":"328",
    "addr:postcode":"08203",
    "addr:street":"Av Barbera",
    "iso:country":"ES",
    "sg:address":"Av Barbera, 328",
    "sg:city":"Sabadell",
    "sg:orig_category":"Fabricaci\u00d3n De Cortinas Y Visillos",
    "sg:phone":"+34 937 12 01 45",
    "sg:postcode":"08203",
    "sg:province":"Barcelona",
    "wof:name":"L'estor S.l.",
    "wof:placetype":"venue"
},
  "geometry": {"coordinates":[2.1138060093,41.5364494324],"type":"Point"}
}