{
  "type": "Feature",
  "properties": {
    "addr:full":"Calle de Buen Aire, S/n Camas Sevilla 41900",
    "addr:housenumber":"s / n",
    "addr:postcode":"41900",
    "addr:street":"Calle De Buen Aire",
    "iso:country":"ES",
    "sg:address":"Calle de Buen Aire, S/n",
    "sg:city":"Camas",
    "sg:orig_category":"Iglesia Cat\u00d3lica",
    "sg:phone":"+34 955 98 05 56",
    "sg:postcode":"41900",
    "sg:province":"Sevilla",
    "wof:name":"Parroquia Nuestra Se\u00f1ora De La Fuente",
    "wof:placetype":"venue"
},
  "geometry": {"coordinates":[-6.0422034264,37.4016189575],"type":"Point"}
}