{
  "type": "Feature",
  "properties": {
    "iso:country":"ES",
    "sg:address":"Pg. Tres Germanas, 3",
    "sg:city":"Campins",
    "sg:orig_category":"Alimentaci\u00d3n General (al Por Menor)",
    "sg:phone":"+34 938 47 52 50",
    "sg:postcode":"08470",
    "sg:province":"Barcelona",
    "wof:name":"Pujadas Planas Maria Del Puig",
    "wof:placetype":"venue"
},
  "geometry": {"coordinates":[2.464247942,41.7253646851],"type":"Point"}
}