{
  "type": "Feature",
  "properties": {
    "addr:full":"Rua Isidro Parga Pondal (de), 2 Santiago De Compostela La Coru\u00f1a 15702",
    "addr:housenumber":"2",
    "addr:postcode":"15702",
    "addr:street":"Rua Isidro Parga Pondal De;Corun\u0303A",
    "iso:country":"ES",
    "sg:address":"Rua Isidro Parga Pondal (de), 2",
    "sg:city":"Santiago De Compostela",
    "sg:orig_category":"Urbanistas",
    "sg:phone":"+34 981 53 41 65",
    "sg:postcode":"15702",
    "sg:province":"La Coru\u00f1a",
    "sg:website":"www.arqo.com",
    "wof:name":"Arqo Arquitectura E Urbanismo S.l.",
    "wof:placetype":"venue"
},
  "geometry": {"coordinates":[-8.5435857773,42.8642425537],"type":"Point"}
}