{
  "type": "Feature",
  "properties": {
    "iso:country":"ES",
    "sg:address":"Pla\u00c7 Major, 9",
    "sg:city":"Pollen\u00e7a",
    "sg:orig_category":"Hoteles",
    "sg:phone":"+34 971 53 50 02",
    "sg:postcode":"07460",
    "sg:province":"Islas Baleares",
    "wof:name":"Illa D'or S.a.",
    "wof:placetype":"venue"
},
  "geometry": {"coordinates":[3.0160710812,39.8770332336],"type":"Point"}
}