{
  "type": "Feature",
  "properties": {
    "iso:country":"ES",
    "sg:address":"Avda Betanzos, 52",
    "sg:city":"Madrid",
    "sg:orig_category":"Colchones (fabricaci\u00d3n, Al Por Mayor, Al Por Menor)",
    "sg:phone":"+34 917 38 50 71",
    "sg:postcode":"28029",
    "sg:province":"Madrid",
    "wof:name":"De Domingo Juarros Alejandro",
    "wof:placetype":"venue"
},
  "geometry": {"coordinates":[-3.7117950916,40.4773826599],"type":"Point"}
}