{
  "type": "Feature",
  "properties": {
    "iso:country":"ES",
    "sg:address":"Calle de Covadonga, 20",
    "sg:city":"Oviedo",
    "sg:classifiers":[
        {
            "category":"Tea Room",
            "subcategory":"None",
            "type":"Food & Drink"
        }
    ],
    "sg:phone":"+34 984 28 01 24",
    "sg:postcode":"33002",
    "sg:province":"Asturias",
    "sg:tags":[
        "snack"
    ],
    "wof:name":"Luis Fernandez Cadenas",
    "wof:placetype":"venue"
},
  "geometry": {"coordinates":[-5.8487281799,43.3643455505],"type":"Point"}
}