{
  "type": "Feature",
  "properties": {
    "iso:country":"ES",
    "sg:address":"Carrer de Pare Xiberta, 5",
    "sg:city":"Olot",
    "sg:orig_category":"Alimentaci\u00d3n General (al Por Menor)",
    "sg:phone":"+34 972 26 27 80",
    "sg:postcode":"17800",
    "sg:province":"Girona",
    "wof:name":"Esquena Ribas Enrique",
    "wof:placetype":"venue"
},
  "geometry": {"coordinates":[2.4790639877,42.184463501],"type":"Point"}
}