{
  "type": "Feature",
  "properties": {
    "iso:country":"ES",
    "sg:address":"Calle de Corregidor Juan Francisco De Lujan, 97",
    "sg:city":"Madrid",
    "sg:orig_category":"Colchones (fabricaci\u00d3n, Al Por Mayor, Al Por Menor)",
    "sg:phone":"+34 917 73 27 41",
    "sg:postcode":"28030",
    "sg:province":"Madrid",
    "wof:name":"Jimenez Momblant Blas",
    "wof:placetype":"venue"
},
  "geometry": {"coordinates":[-3.6461167336,40.4017982483],"type":"Point"}
}