{
  "type": "Feature",
  "properties": {
    "addr:full":"Avda Carabanchel Alto, 78 Madrid Madrid 28044",
    "addr:housenumber":"78",
    "addr:postcode":"madrid;28044",
    "addr:street":"Avda Carabanchel Alto",
    "iso:country":"ES",
    "sg:address":"Avda Carabanchel Alto, 78",
    "sg:city":"Madrid",
    "sg:orig_category":"Fabricaci\u00d3n De Muebles",
    "sg:phone":"+34 915 08 62 59",
    "sg:postcode":"28044",
    "sg:province":"Madrid",
    "wof:name":"El Bosque Interiorismo S.l.l.",
    "wof:placetype":"venue"
},
  "geometry": {"coordinates":[-3.7534821033,40.3686218262],"type":"Point"}
}