{
  "type": "Feature",
  "properties": {
    "iso:country":"ES",
    "sg:address":"Avda Alcalde Jose Ramirez Bethencourt, 10",
    "sg:city":"Palmas De Gran Canaria",
    "sg:orig_category":"M\u00c9dicos: Medicina General",
    "sg:phone":"+34 928 37 00 34",
    "sg:postcode":"35003",
    "sg:province":"Las Palmas",
    "wof:name":"Medica De Conductores S. A.",
    "wof:placetype":"venue"
},
  "geometry": {"coordinates":[-15.4164590836,28.1095600128],"type":"Point"}
}