{
  "type": "Feature",
  "properties": {
    "iso:country":"ES",
    "sg:address":"Calle de Doctor Comino, 9",
    "sg:city":"Montefrio",
    "sg:orig_category":"Productos Alimentarios",
    "sg:phone":"+34 958 33 62 41",
    "sg:postcode":"18270",
    "sg:province":"Granada",
    "wof:name":"Aviles Mercado Juan",
    "wof:placetype":"venue"
},
  "geometry": {"coordinates":[-4.0086159706,37.3207168579],"type":"Point"}
}