{
  "type": "Feature",
  "properties": {
    "addr:full":"Carr Serra De Prades, S/n Lleida Lleida 25006",
    "addr:housenumber":"s / n",
    "addr:postcode":"25006",
    "addr:street":"Carr Serra De Prades",
    "iso:country":"ES",
    "sg:address":"Carr Serra De Prades, S/n",
    "sg:city":"Lleida",
    "sg:orig_category":"Ense\u00d1anza, Formaci\u00d3n Profesional: Aprendizaje",
    "sg:phone":"+34 973 23 63 44",
    "sg:postcode":"25006",
    "sg:province":"Lleida",
    "wof:name":"Centre De Telecomunicaciones De Catalunya",
    "wof:placetype":"venue"
},
  "geometry": {"coordinates":[0.6180250049,41.6196670532],"type":"Point"}
}