{
  "type": "Feature",
  "properties": {
    "iso:country":"ES",
    "sg:address":"Ctra Collblanc, 27",
    "sg:city":"Hospitalet Llobregat",
    "sg:orig_category":"Bazares, Art\u00cdculos De Limpieza Y De Cocina (al Por Menor)",
    "sg:phone":"+34 933 33 97 38",
    "sg:postcode":"08903",
    "sg:province":"Barcelona",
    "wof:name":"Msm-4 S.l.",
    "wof:placetype":"venue"
},
  "geometry": {"coordinates":[2.1200799942,41.375667572],"type":"Point"}
}