{
  "type": "Feature",
  "properties": {
    "addr:full":"Carrer de Major, 44 Montornes Centre Barcelona 08170",
    "addr:housenumber":"44",
    "addr:postcode":"08170",
    "addr:street":"Carrer De Major;Centre Barcelona",
    "iso:country":"ES",
    "sg:address":"Carrer de Major, 44",
    "sg:city":"Montornes Centre",
    "sg:orig_category":"Peluqueros: De Se\u00d1oras",
    "sg:phone":"+34 935 68 08 88",
    "sg:postcode":"08170",
    "sg:province":"Barcelona",
    "wof:name":"Cambronero Molina Raquel",
    "wof:placetype":"venue"
},
  "geometry": {"coordinates":[2.2668309212,41.5422515869],"type":"Point"}
}