{
  "type": "Feature",
  "properties": {
    "addr:full":"Cam. De La Virgen, Km. 0006,0 Yunquera Henares Guadalajara 19210",
    "addr:postcode":"19210",
    "addr:street":"Cam. De La Virgen Km. 0006,0",
    "iso:country":"ES",
    "sg:address":"Cam. De La Virgen, Km. 0006,0",
    "sg:city":"Yunquera Henares",
    "sg:orig_category":"Promotores Constructores",
    "sg:phone":"+34 949 82 34 08",
    "sg:postcode":"19210",
    "sg:province":"Guadalajara",
    "wof:name":"Hocensa Empresa Constructora S.a.",
    "wof:placetype":"venue"
},
  "geometry": {"coordinates":[-3.1650300026,40.7522735596],"type":"Point"}
}