{
  "type": "Feature",
  "properties": {
    "iso:country":"ES",
    "sg:address":"Mercat Unio, S/n",
    "sg:city":"Barcelona",
    "sg:orig_category":"Poller\u00cda Y Caza (al Por Menor)",
    "sg:phone":"+34 932 25 40 59",
    "sg:postcode":"08005",
    "sg:province":"Barcelona",
    "wof:name":"Devesa Campins Josep",
    "wof:placetype":"venue"
},
  "geometry": {"coordinates":[2.2052350044,41.4011573792],"type":"Point"}
}