{
  "type": "Feature",
  "properties": {
    "iso:country":"ES",
    "sg:address":"Rua Ronda Don Bosco, 49",
    "sg:city":"Vigo",
    "sg:orig_category":"Ropa Para Se\u00d1oras (al Por Menor)",
    "sg:phone":"+34 986 43 21 49",
    "sg:postcode":"36202",
    "sg:province":"Pontevedra",
    "wof:name":"Pico Alvarez S.l.",
    "wof:placetype":"venue"
},
  "geometry": {"coordinates":[-8.7211236954,42.2351455688],"type":"Point"}
}