{
  "type": "Feature",
  "properties": {
    "iso:country":"ES",
    "sg:address":"Calle de Suero De Qui\u00d1ones, 40",
    "sg:city":"Madrid",
    "sg:orig_category":"Impuestos, Tesoro P\u00dablico",
    "sg:phone":"+34 915 64 86 85",
    "sg:postcode":"28002",
    "sg:province":"Madrid",
    "sg:website":"www.tasamadrid.com",
    "wof:name":"Tasamadrid",
    "wof:placetype":"venue"
},
  "geometry": {"coordinates":[-3.6773240566,40.4474487305],"type":"Point"}
}