{
  "type": "Feature",
  "properties": {
    "addr:full":"Calle de Fernando El Catolico, 46 Madrid Madrid 28015",
    "addr:housenumber":"46",
    "addr:postcode":"madrid;28015",
    "addr:street":"Calle De Fernando El Catolico",
    "iso:country":"ES",
    "sg:address":"Calle de Fernando El Catolico, 46",
    "sg:city":"Madrid",
    "sg:orig_category":"Inform\u00c1tica Equipo Y Programas (al Por Mayor)",
    "sg:phone":"+34 915 44 24 01",
    "sg:postcode":"28015",
    "sg:province":"Madrid",
    "wof:name":"Serconsys S.l.",
    "wof:placetype":"venue"
},
  "geometry": {"coordinates":[-3.712446928,40.4343490601],"type":"Point"}
}