{
  "type": "Feature",
  "properties": {
    "addr:full":"Calle de Corrida, 5 Gijon Asturias 33206",
    "addr:housenumber":"5",
    "addr:postcode":"33206",
    "addr:street":"Calle De Corrida",
    "iso:country":"ES",
    "sg:address":"Calle de Corrida, 5",
    "sg:city":"Gijon",
    "sg:orig_category":"Psicoanalistas",
    "sg:phone":"+34 985 35 84 94",
    "sg:postcode":"33206",
    "sg:province":"Asturias",
    "wof:name":"Torres Carbajo Victoria",
    "wof:placetype":"venue"
},
  "geometry": {"coordinates":[-5.6641421318,43.5421447754],"type":"Point"}
}