{
  "type": "Feature",
  "properties": {
    "addr:full":"Carr Atlantic, S/n Grau I Platja Valencia 46730",
    "addr:housenumber":"s / n",
    "addr:postcode":"46730",
    "addr:street":"Carr Atlantic",
    "iso:country":"ES",
    "sg:address":"Carr Atlantic, S/n",
    "sg:city":"Grau I Platja",
    "sg:orig_category":"Ingeniero",
    "sg:phone":"+34 962 84 18 76",
    "sg:postcode":"46730",
    "sg:province":"Valencia",
    "wof:name":"Oria Aranda Enrique",
    "wof:placetype":"venue"
},
  "geometry": {"coordinates":[-0.1586389989,38.9962692261],"type":"Point"}
}