{
  "type": "Feature",
  "properties": {
    "addr:full":"San Juan Kalea, 9 Eibar Guip\u00f9zcoa 20600",
    "addr:housenumber":"9",
    "addr:postcode":"20600",
    "addr:street":"San Juan Kalea;Guipu\u0300Zcoa",
    "iso:country":"ES",
    "sg:address":"San Juan Kalea, 9",
    "sg:city":"Eibar",
    "sg:orig_category":"Medias Y Calcetines (al Por Menor)",
    "sg:phone":"+34 943 20 68 40",
    "sg:postcode":"20600",
    "sg:province":"Guip\u00f9zcoa",
    "wof:name":"Maruri Badiola Jone",
    "wof:placetype":"venue"
},
  "geometry": {"coordinates":[-2.4732489586,43.184841156],"type":"Point"}
}