{
  "type": "Feature",
  "properties": {
    "iso:country":"ES",
    "sg:address":"Puerto Deportivo, S/n",
    "sg:city":"Sta. Eularia Riu",
    "sg:orig_category":"Limpieza Industrial",
    "sg:phone":"+34 971 31 94 77",
    "sg:postcode":"07840",
    "sg:province":"Islas Baleares",
    "wof:name":"Hermanas Gonzalez C.b.",
    "wof:placetype":"venue"
},
  "geometry": {"coordinates":[1.5341850519,38.9850311279],"type":"Point"}
}