{
  "type": "Feature",
  "properties": {
    "addr:full":"Calle de Esteban Amaya, 1 Montijo Badajoz 06480",
    "addr:housenumber":"1",
    "addr:postcode":"06480",
    "addr:street":"Calle De Esteban Amaya",
    "iso:country":"ES",
    "sg:address":"Calle de Esteban Amaya, 1",
    "sg:city":"Montijo",
    "sg:orig_category":"Agencias De Viajes",
    "sg:phone":"+34 924 45 90 92",
    "sg:postcode":"06480",
    "sg:province":"Badajoz",
    "wof:name":"Cedrum Del Viejo Maria Angeles",
    "wof:placetype":"venue"
},
  "geometry": {"coordinates":[-6.6157650948,38.9098358154],"type":"Point"}
}