{
  "type": "Feature",
  "properties": {
    "addr:full":"Pase Habana, 4 Madrid Madrid 28036",
    "addr:housenumber":"4",
    "addr:postcode":"28036",
    "iso:country":"ES",
    "sg:address":"Pase Habana, 4",
    "sg:city":"Madrid",
    "sg:orig_category":"Abogados",
    "sg:phone":"+34 915 61 22 28",
    "sg:postcode":"28036",
    "sg:province":"Madrid",
    "wof:name":"Enrile Aleix Julio Antonio",
    "wof:placetype":"venue"
},
  "geometry": {"coordinates":[-3.6902720928,40.4473457336],"type":"Point"}
}