{
  "type": "Feature",
  "properties": {
    "iso:country":"ES",
    "sg:address":"Leyre-leire Kalea, 22",
    "sg:city":"Iru\u00f1a",
    "sg:orig_category":"Marroquiner\u00cda Y Art\u00cdculos De Viaje (al Por Menor)",
    "sg:phone":"+34 948 24 41 87",
    "sg:postcode":"31003",
    "sg:province":"Navarra",
    "wof:name":"Santiago Aparicio S.l.",
    "wof:placetype":"venue"
},
  "geometry": {"coordinates":[-1.6419620514,42.8125762939],"type":"Point"}
}