{
  "type": "Feature",
  "properties": {
    "addr:full":"Calle de Sierra Gorda, 28 Madrid Madrid 28031",
    "addr:housenumber":"28",
    "addr:postcode":"madrid;28031",
    "addr:street":"Calle De Sierra Gorda",
    "iso:country":"ES",
    "sg:address":"Calle de Sierra Gorda, 28",
    "sg:city":"Madrid",
    "sg:orig_category":"Carnicer\u00cdas, Carnicer\u00cdas",
    "sg:phone":"+34 913 31 51 19",
    "sg:postcode":"28031",
    "sg:province":"Madrid",
    "wof:name":"Maria Del Pilar Tomas Cervi\u00f1o C.b.",
    "wof:placetype":"venue"
},
  "geometry": {"coordinates":[-3.6187810898,40.3804931641],"type":"Point"}
}