{
  "type": "Feature",
  "properties": {
    "iso:country":"ES",
    "sg:address":"Rua Mendez Nu\u00d1ez, 39",
    "sg:city":"Marin",
    "sg:orig_category":"Abogados",
    "sg:phone":"+34 986 89 11 70",
    "sg:postcode":"36900",
    "sg:province":"Pontevedra",
    "wof:name":"Perez Villaverde Francisco Javier",
    "wof:placetype":"venue"
},
  "geometry": {"coordinates":[-8.6977834702,42.3922195435],"type":"Point"}
}