{
  "type": "Feature",
  "properties": {
    "iso:country":"ES",
    "sg:address":"Carrer de Major, 42",
    "sg:city":"Montcada Centre",
    "sg:orig_category":"Gas: Botellas Y Contenedores",
    "sg:phone":"+34 935 75 28 60",
    "sg:postcode":"08110",
    "sg:province":"Barcelona",
    "wof:name":"Villalobos Calero Montse",
    "wof:placetype":"venue"
},
  "geometry": {"coordinates":[2.188024044,41.4869880676],"type":"Point"}
}