{
  "type": "Feature",
  "properties": {
    "iso:country":"ES",
    "sg:address":"Industrialdea, S/n",
    "sg:city":"Itziar",
    "sg:orig_category":"Fabricaci\u00d3n Y Comercio De M\u00c1quinas",
    "sg:phone":"+34 943 19 91 32",
    "sg:postcode":"20829",
    "sg:province":"Guip\u00f9zcoa",
    "sg:website":"www.morkaiko.com",
    "wof:name":"Morkaiko S.a.",
    "wof:placetype":"venue"
},
  "geometry": {"coordinates":[-2.3308770657,43.276473999],"type":"Point"}
}