{
  "type": "Feature",
  "properties": {
    "addr:full":"Calle de O\u00d1a, 105 Madrid Madrid 28050",
    "addr:housenumber":"105",
    "addr:postcode":"28050",
    "addr:street":"Calle De On\u0303A",
    "iso:country":"ES",
    "sg:address":"Calle de O\u00d1a, 105",
    "sg:city":"Madrid",
    "sg:orig_category":"Estudios, Instalaci\u00d3n De Climatizaci\u00d3n",
    "sg:phone":"+34 913 83 80 51",
    "sg:postcode":"28050",
    "sg:province":"Madrid",
    "wof:name":"Conimair S.l.",
    "wof:placetype":"venue"
},
  "geometry": {"coordinates":[-3.6635270119,40.4893951416],"type":"Point"}
}