{
  "type": "Feature",
  "properties": {
    "addr:full":"Plaz Talavera De La Reina, 8 Mora Toledo 45400",
    "addr:housenumber":"8",
    "addr:postcode":"45400",
    "addr:street":"Reina",
    "iso:country":"ES",
    "sg:address":"Plaz Talavera De La Reina, 8",
    "sg:city":"Mora",
    "sg:orig_category":"Frutas, Legumbres Frescas Y Tempranas (al Por Menor)",
    "sg:phone":"+34 925 30 03 40",
    "sg:postcode":"45400",
    "sg:province":"Toledo",
    "wof:name":"Martin Moreno David",
    "wof:placetype":"venue"
},
  "geometry": {"coordinates":[-3.7692060471,39.6824417114],"type":"Point"}
}