{
  "type": "Feature",
  "properties": {
    "addr:full":"Pg Fabra I Puig, 372 Barcelona Barcelona 08031",
    "addr:housenumber":"372",
    "addr:postcode":"08031",
    "addr:street":"Pg Fabra I Puig",
    "iso:country":"ES",
    "sg:address":"Pg Fabra I Puig, 372",
    "sg:city":"Barcelona",
    "sg:orig_category":"Bisuter\u00cda, Joyer\u00cda, Relojer\u00cda (al Por Menor)",
    "sg:phone":"+34 933 58 14 56",
    "sg:postcode":"08031",
    "sg:province":"Barcelona",
    "wof:name":"Prats I Barreda Antoni",
    "wof:placetype":"venue"
},
  "geometry": {"coordinates":[2.1639881134,41.431427002],"type":"Point"}
}