{
  "type": "Feature",
  "properties": {
    "addr:full":"Carrer de Josep Pla, 12 Martorell Barcelona 08760",
    "addr:housenumber":"12",
    "addr:postcode":"08760",
    "addr:street":"Carrer De Josep Pla",
    "iso:country":"ES",
    "sg:address":"Carrer de Josep Pla, 12",
    "sg:city":"Martorell",
    "sg:orig_category":"Ropa Para Ni\u00d1os (al Por Menor)",
    "sg:phone":"+34 937 74 51 51",
    "sg:postcode":"08760",
    "sg:province":"Barcelona",
    "wof:name":"Kaotica S.c.p.",
    "wof:placetype":"venue"
},
  "geometry": {"coordinates":[1.9169969559,41.476348877],"type":"Point"}
}