{
  "type": "Feature",
  "properties": {
    "addr:full":"Carr Hostal De La Bordeta, 36 Lleida Lleida 25001",
    "addr:housenumber":"36",
    "addr:postcode":"25001",
    "addr:street":"Carr Hostal De La Bordeta",
    "iso:country":"ES",
    "sg:address":"Carr Hostal De La Bordeta, 36",
    "sg:city":"Lleida",
    "sg:orig_category":"Electricidad: Instaladores",
    "sg:phone":"+34 973 20 09 56",
    "sg:postcode":"25001",
    "sg:province":"Lleida",
    "wof:name":"Herrero Llata Antonio",
    "wof:placetype":"venue"
},
  "geometry": {"coordinates":[0.6437088251,41.6034240723],"type":"Point"}
}