{
  "type": "Feature",
  "properties": {
    "iso:country":"ES",
    "sg:address":"Calle de Sanclemente, 6",
    "sg:city":"Zaragoza",
    "sg:orig_category":"Abogados",
    "sg:phone":"+34 976 22 13 60",
    "sg:postcode":"50001",
    "sg:province":"Zaragoza",
    "wof:name":"Abenia Pera Maria Pilar",
    "wof:placetype":"venue"
},
  "geometry": {"coordinates":[-0.88208,41.649765],"type":"Point"}
}