{
  "type": "Feature",
  "properties": {
    "iso:country":"ES",
    "sg:address":"Carrer de Doctor Ferran, 15",
    "sg:city":"Rubi",
    "sg:orig_category":"Institutos De Belleza",
    "sg:phone":"+34 936 99 84 74",
    "sg:postcode":"08191",
    "sg:province":"Barcelona",
    "wof:name":"Sensacions S.c.p.",
    "wof:placetype":"venue"
},
  "geometry": {"coordinates":[2.0359919071,41.4811210632],"type":"Point"}
}