{
  "type": "Feature",
  "properties": {
    "iso:country":"ES",
    "sg:address":"Calle de Cruces, 17",
    "sg:city":"Puebla Almoradiel",
    "sg:orig_category":"M\u00c1rmoles, Granitos Y Piedras Naturales",
    "sg:phone":"+34 925 20 51 53",
    "sg:postcode":"45840",
    "sg:province":"Toledo",
    "wof:name":"Contratas Sepulveda Martinez S.l.",
    "wof:placetype":"venue"
},
  "geometry": {"coordinates":[-3.1118893623,39.59948349],"type":"Point"}
}