{
  "type": "Feature",
  "properties": {
    "addr:full":"Rbla Joaquim Ruyra, 87 Blanes Girona 17300",
    "addr:housenumber":"87",
    "addr:postcode":"17300",
    "addr:street":"Rbla Joaquim Ruyra",
    "iso:country":"ES",
    "sg:address":"Rbla Joaquim Ruyra, 87",
    "sg:city":"Blanes",
    "sg:orig_category":"Confecci\u00d3n (fabricaci\u00d3n, Al Por Mayor)",
    "sg:phone":"+34 972 33 18 24",
    "sg:postcode":"17300",
    "sg:province":"Girona",
    "wof:name":"Fernandez Freitas Jacinto",
    "wof:placetype":"venue"
},
  "geometry": {"coordinates":[2.7900218964,41.6729393005],"type":"Point"}
}