{
  "type": "Feature",
  "properties": {
    "iso:country":"ES",
    "sg:address":"Pase Adarves (los), 34",
    "sg:city":"Molina",
    "sg:orig_category":"Seguros",
    "sg:phone":"+34 949 83 25 28",
    "sg:postcode":"19300",
    "sg:province":"Guadalajara",
    "wof:name":"Mapfre Servicios De Informatica",
    "wof:placetype":"venue"
},
  "geometry": {"coordinates":[-1.8168599606,40.8542098999],"type":"Point"}
}