{
  "type": "Feature",
  "properties": {
    "addr:full":"Pla\u00c7 Canal, De Sa, 18 Santanyi Islas Baleares 07650",
    "addr:housenumber":"18",
    "addr:postcode":"07650",
    "addr:street":"Santanyi Islas",
    "iso:country":"ES",
    "sg:address":"Pla\u00c7 Canal, De Sa, 18",
    "sg:city":"Santanyi",
    "sg:orig_category":"Inmobiliaria (agencias)",
    "sg:phone":"+34 971 65 44 20",
    "sg:postcode":"07650",
    "sg:province":"Islas Baleares",
    "wof:name":"Fincas Con Corazon",
    "wof:placetype":"venue"
},
  "geometry": {"coordinates":[3.1274299622,39.3544082642],"type":"Point"}
}