{
  "type": "Feature",
  "properties": {
    "addr:full":"Calle de Padre Cuevas, 22 Sanlucar De Barrameda C\u00e1diz 11540",
    "addr:housenumber":"22",
    "addr:postcode":"11540",
    "addr:street":"Calle De Padre Cuevas;Ca\u0301Diz",
    "iso:country":"ES",
    "sg:address":"Calle de Padre Cuevas, 22",
    "sg:city":"Sanlucar De Barrameda",
    "sg:orig_category":"M\u00c9dicos: Ginecolog\u00cda M\u00c9dica, Obstetricia",
    "sg:phone":"+34 956 96 06 76",
    "sg:postcode":"11540",
    "sg:province":"C\u00e1diz",
    "wof:name":"Rodriguez Braza Teresa",
    "wof:placetype":"venue"
},
  "geometry": {"coordinates":[-6.3529191017,36.7834968567],"type":"Point"}
}