{
  "type": "Feature",
  "properties": {
    "addr:full":"Calle de Mesones, 57 Constantina Sevilla 41450",
    "addr:housenumber":"57",
    "addr:postcode":"41450",
    "addr:street":"Calle De Mesones",
    "iso:country":"ES",
    "sg:address":"Calle de Mesones, 57",
    "sg:city":"Constantina",
    "sg:orig_category":"Laboratorios Y Trabajos De Fotograf\u00cda, V\u00cddeo Y Cine",
    "sg:phone":"+34 955 88 13 07",
    "sg:postcode":"41450",
    "sg:province":"Sevilla",
    "wof:name":"Ordo\u00f1ez Luque Antonio",
    "wof:placetype":"venue"
},
  "geometry": {"coordinates":[-5.6195530891,37.8732566833],"type":"Point"}
}