{
  "type": "Feature",
  "properties": {
    "addr:full":"Calle de Portuetxe, 55 Donostia-san Sebastian Guip\u00f9zcoa 20018",
    "addr:housenumber":"55",
    "addr:postcode":"20018",
    "addr:street":"Calle De Portuetxe",
    "iso:country":"ES",
    "sg:address":"Calle de Portuetxe, 55",
    "sg:city":"Donostia-san Sebastian",
    "sg:classifiers":[
        {
            "category":"Building & Trades",
            "subcategory":"Construction",
            "type":"Services"
        }
    ],
    "sg:phone":"+34 943 21 66 79",
    "sg:postcode":"20018",
    "sg:province":"Guip\u00f9zcoa",
    "sg:tags":[
        "calefacci\u00d3n",
        "central",
        "para",
        "de",
        "fabricaci\u00d3n",
        "caldera"
    ],
    "wof:name":"Sematec Gipuzkoa S.l.",
    "wof:placetype":"venue"
},
  "geometry": {"coordinates":[-2.016949892,43.3012962341],"type":"Point"}
}