{
  "type": "Feature",
  "properties": {
    "iso:country":"ES",
    "sg:address":"Poli Industrial, 36",
    "sg:city":"Aguilar Campoo",
    "sg:orig_category":"Empresas De Carpinter\u00cda De Madera",
    "sg:phone":"+34 979 12 57 08",
    "sg:postcode":"34800",
    "sg:province":"Palencia",
    "wof:name":"Carpinteria Ebanisteria Ruper S.l.",
    "wof:placetype":"venue"
},
  "geometry": {"coordinates":[-4.3009209633,42.6296615601],"type":"Point"}
}