{
  "type": "Feature",
  "properties": {
    "iso:country":"ES",
    "sg:address":"Ctra. Mojados, Km. 0008,7",
    "sg:city":"Megeces",
    "sg:orig_category":"Materias Pl\u00c1sticas: Productos De Consumo Masivo (fabricaci\u00d3n, Al Por Mayor)",
    "sg:phone":"+34 983 60 41 65",
    "sg:postcode":"47440",
    "sg:province":"Valladolid",
    "wof:name":"Plasticos Y Embalajes Ojeda S.l.",
    "wof:placetype":"venue"
},
  "geometry": {"coordinates":[-4.5675888062,41.4071617126],"type":"Point"}
}