{
  "type": "Feature",
  "properties": {
    "addr:full":"Avda Adeje 300, S/n Playa Paraiso Santa Cruz De Tenerife 38678",
    "addr:housenumber":"s / n",
    "addr:postcode":"38678",
    "addr:street":"Avda Adeje 300",
    "iso:country":"ES",
    "sg:address":"Avda Adeje 300, S/n",
    "sg:city":"Playa Paraiso",
    "sg:orig_category":"Inmobiliaria (agencias)",
    "sg:phone":"+34 922 72 33 74",
    "sg:postcode":"38678",
    "sg:province":"Santa Cruz De Tenerife",
    "wof:name":"Tenerife Servicios De Negocios S.l.",
    "wof:placetype":"venue"
},
  "geometry": {"coordinates":[-16.7754306793,28.1215591431],"type":"Point"}
}