{
  "type": "Feature",
  "properties": {
    "iso:country":"ES",
    "sg:address":"Calle de Sdo Ramis Bover, 3",
    "sg:city":"Palma",
    "sg:orig_category":"Embalajes",
    "sg:phone":"+34 971 29 78 59",
    "sg:postcode":"07004",
    "sg:province":"Islas Baleares",
    "sg:website":"www.mudanzaslidon.com",
    "wof:name":"Lidon Moreno Pascual",
    "wof:placetype":"venue"
},
  "geometry": {"coordinates":[2.6566250324,39.5910682678],"type":"Point"}
}