{
  "type": "Feature",
  "properties": {
    "iso:country":"ES",
    "sg:address":"Ctra Carranque, Km. 0023,0",
    "sg:city":"Palominos Mimosas",
    "sg:orig_category":"Muebles",
    "sg:phone":"+34 925 53 30 65",
    "sg:postcode":"45217",
    "sg:province":"Toledo",
    "sg:website":"www.eurosilla.net",
    "wof:name":"Eurosilla S.c.l",
    "wof:placetype":"venue"
},
  "geometry": {"coordinates":[-3.877669096,40.1581344604],"type":"Point"}
}