{
  "type": "Feature",
  "properties": {
    "iso:country":"ES",
    "sg:address":"Calle de Iptuci, 2",
    "sg:city":"Prado Del Rey",
    "sg:orig_category":"Material Y Herramientas Agr\u00cdcolas",
    "sg:phone":"+34 956 71 81 41",
    "sg:postcode":"11660",
    "sg:province":"C\u00e1diz",
    "wof:name":"Ortega Blanco Antonio Raul",
    "wof:placetype":"venue"
},
  "geometry": {"coordinates":[-5.55900383,36.784362793],"type":"Point"}
}