{
  "type": "Feature",
  "properties": {
    "iso:country":"ES",
    "sg:address":"Calle de San Lorenzo, 12",
    "sg:city":"Donostia-san Sebastian",
    "sg:orig_category":"Prot\u00c9sicos Dentales",
    "sg:phone":"+34 943 42 22 77",
    "sg:postcode":"20003",
    "sg:province":"Guip\u00f9zcoa",
    "wof:name":"Berrondo Varela Francisco",
    "wof:placetype":"venue"
},
  "geometry": {"coordinates":[-1.9839049578,43.3231506348],"type":"Point"}
}