{
  "type": "Feature",
  "properties": {
    "addr:full":"Calle de Arroyo Belincoso, 34 Madrid Madrid 28030",
    "addr:housenumber":"34",
    "addr:postcode":"madrid;28030",
    "addr:street":"Calle De Arroyo Belincoso",
    "iso:country":"ES",
    "sg:address":"Calle de Arroyo Belincoso, 34",
    "sg:city":"Madrid",
    "sg:orig_category":"Cl\u00cdnicas M\u00c9dicas",
    "sg:phone":"+34 914 39 19 74",
    "sg:postcode":"28030",
    "sg:province":"Madrid",
    "wof:name":"Villar Santos Etelvina",
    "wof:placetype":"venue"
},
  "geometry": {"coordinates":[-3.6524579525,40.409954071],"type":"Point"}
}