{
  "type": "Feature",
  "properties": {
    "iso:country":"ES",
    "sg:address":"Calle de Flor Baja, 6",
    "sg:city":"Madrid",
    "sg:orig_category":"Discotecas Y Salas De Baile",
    "sg:phone":"+34 915 42 30 96",
    "sg:postcode":"28013",
    "sg:province":"Madrid",
    "wof:name":"Montero Gonzalez Jose Luis",
    "wof:placetype":"venue"
},
  "geometry": {"coordinates":[-3.7100119591,40.4224700928],"type":"Point"}
}