{
  "type": "Feature",
  "properties": {
    "addr:full":"Av Catalunya, 36 Santa Coloma De Gramenet Barcelona 08924",
    "addr:housenumber":"36",
    "addr:postcode":"08924",
    "addr:street":"Av Catalunya",
    "iso:country":"ES",
    "sg:address":"Av Catalunya, 36",
    "sg:city":"Santa Coloma De Gramenet",
    "sg:orig_category":"Material Y Suministros Para Peluquer\u00cda",
    "sg:phone":"+34 933 91 76 59",
    "sg:postcode":"08924",
    "sg:province":"Barcelona",
    "wof:name":"Gonzalez Chica Maria Jose",
    "wof:placetype":"venue"
},
  "geometry": {"coordinates":[2.2044610977,41.458316803],"type":"Point"}
}