{
  "type": "Feature",
  "properties": {
    "addr:full":"Avda Pablo Iglesias, 13 Tarancon Cuenca 16400",
    "addr:housenumber":"13",
    "addr:postcode":"16400",
    "addr:street":"Avda Pablo Iglesias",
    "iso:country":"ES",
    "sg:address":"Avda Pablo Iglesias, 13",
    "sg:city":"Tarancon",
    "sg:orig_category":"Pod\u00d3logos: Pedicuros",
    "sg:phone":"+34 969 32 19 03",
    "sg:postcode":"16400",
    "sg:province":"Cuenca",
    "wof:name":"Clinica General De Podologia",
    "wof:placetype":"venue"
},
  "geometry": {"coordinates":[-3.0186090469,40.0075416565],"type":"Point"}
}