{
  "type": "Feature",
  "properties": {
    "addr:full":"Ctra Nules (diseminado), S/n Alquerias Valencia Castell\u00f3n 12530",
    "addr:housenumber":"s / n",
    "addr:postcode":"12530",
    "addr:street":"Ctra Nules Diseminado",
    "iso:country":"ES",
    "sg:address":"Ctra Nules (diseminado), S/n",
    "sg:city":"Alquerias Valencia",
    "sg:orig_category":"Empresas De Carpinter\u00cda De Madera",
    "sg:phone":"+34 964 59 20 10",
    "sg:postcode":"12530",
    "sg:province":"Castell\u00f3n",
    "wof:name":"Moidecar S.l.",
    "wof:placetype":"venue"
},
  "geometry": {"coordinates":[-0.0852660015,39.8894195557],"type":"Point"}
}