{
  "type": "Feature",
  "properties": {
    "iso:country":"ES",
    "sg:address":"Calle de Llana (la), 41",
    "sg:city":"Urioste",
    "sg:orig_category":"Promotores Constructores",
    "sg:phone":"+34 946 35 35 98",
    "sg:postcode":"48530",
    "sg:province":"Vizcaya",
    "wof:name":"Fonorte Empresa Constructora S.a.",
    "wof:placetype":"venue"
},
  "geometry": {"coordinates":[-3.0566248894,43.3107376099],"type":"Point"}
}