{
  "type": "Feature",
  "properties": {
    "addr:full":"Avda Constitucion, 7 Villanueva Arzobispo Ja\u00e9n 23330",
    "addr:housenumber":"7",
    "addr:postcode":"23330",
    "addr:street":"Avda Constitucion",
    "iso:country":"ES",
    "sg:address":"Avda Constitucion, 7",
    "sg:city":"Villanueva Arzobispo",
    "sg:orig_category":"Agencias Y Asesores De Publicidad",
    "sg:phone":"+34 953 45 00 56",
    "sg:postcode":"23330",
    "sg:province":"Ja\u00e9n",
    "wof:name":"Sanchez Arribas Ramon",
    "wof:placetype":"venue"
},
  "geometry": {"coordinates":[-3.010051012,38.1694450378],"type":"Point"}
}