{
  "type": "Feature",
  "properties": {
    "addr:full":"Carrer de Saragossa (de), 15 Salou Tarragona 43840",
    "addr:housenumber":"15",
    "addr:postcode":"43840",
    "addr:street":"Carrer De Saragossa De",
    "iso:country":"ES",
    "sg:address":"Carrer de Saragossa (de), 15",
    "sg:city":"Salou",
    "sg:orig_category":"Regalos, Souvenires (fabricaci\u00d3n, Al Por Mayor)",
    "sg:phone":"+34 977 35 21 10",
    "sg:postcode":"43840",
    "sg:province":"Tarragona",
    "wof:name":"Arnau Cabanes Emilio",
    "wof:placetype":"venue"
},
  "geometry": {"coordinates":[1.1465046406,41.0748443604],"type":"Point"}
}