{
  "type": "Feature",
  "properties": {
    "addr:full":"C/ Agoders, 25 Tarrega Lleida 25300",
    "addr:housenumber":"25",
    "addr:postcode":"25300",
    "addr:street":"C / Agoders",
    "iso:country":"ES",
    "sg:address":"C/ Agoders, 25",
    "sg:city":"Tarrega",
    "sg:orig_category":"Complementos De Vestir (al Por Menor)",
    "sg:phone":"+34 973 50 20 11",
    "sg:postcode":"25300",
    "sg:province":"Lleida",
    "wof:name":"Brautwal S.l.",
    "wof:placetype":"venue"
},
  "geometry": {"coordinates":[1.1406610012,41.6469802856],"type":"Point"}
}