{
  "type": "Feature",
  "properties": {
    "iso:country":"ES",
    "sg:address":"Carrer de Esteve Barange, 3",
    "sg:city":"Cardedeu",
    "sg:orig_category":"Fotocopias, Reprograf\u00cda",
    "sg:phone":"+34 938 71 10 77",
    "sg:postcode":"08440",
    "sg:province":"Barcelona",
    "wof:name":"Mu\u00f1oz Freixas Nuria",
    "wof:placetype":"venue"
},
  "geometry": {"coordinates":[2.3602409363,41.6380805969],"type":"Point"}
}