{
  "type": "Feature",
  "properties": {
    "iso:country":"ES",
    "sg:address":"Calle de Hermandad De Donantes De Sangre, 21",
    "sg:city":"Madrid",
    "sg:orig_category":"Abogados",
    "sg:phone":"+34 917 95 00 13",
    "sg:postcode":"28041",
    "sg:province":"Madrid",
    "wof:name":"Serrano Escalera Juan Angel",
    "wof:placetype":"venue"
},
  "geometry": {"coordinates":[-3.7012889385,40.3543281555],"type":"Point"}
}