{
  "type": "Feature",
  "properties": {
    "addr:full":"Calle de Colon, 1 Ugarte Vizcaya 48510",
    "addr:housenumber":"1",
    "addr:postcode":"48510",
    "addr:street":"Calle De Colon",
    "iso:country":"ES",
    "sg:address":"Calle de Colon, 1",
    "sg:city":"Ugarte",
    "sg:orig_category":"Mec\u00c1nico Del Autom\u00d3vil",
    "sg:phone":"+34 944 92 21 85",
    "sg:postcode":"48510",
    "sg:province":"Vizcaya",
    "wof:name":"Torrientes Rodriguez Julio",
    "wof:placetype":"venue"
},
  "geometry": {"coordinates":[-3.0369338989,43.3047294617],"type":"Point"}
}