{
  "type": "Feature",
  "properties": {
    "iso:country":"ES",
    "sg:address":"Pol Ind Messell, 14",
    "sg:city":"El Campello",
    "sg:orig_category":"M\u00c1quinas Textiles, Accesorios Y Suministros (fabricaci\u00d3n)",
    "sg:phone":"+34 965 63 07 35",
    "sg:postcode":"03560",
    "sg:province":"Alicante",
    "sg:website":"www.printexpress.es",
    "wof:name":"Sistema Global Inoxidables Sl Eb Constitucion",
    "wof:placetype":"venue"
},
  "geometry": {"coordinates":[-0.3906340003,38.4271888733],"type":"Point"}
}