{
  "type": "Feature",
  "properties": {
    "iso:country":"ES",
    "sg:address":"Plaz Zocodover, 7",
    "sg:city":"Toledo",
    "sg:orig_category":"Panader\u00cdas, Panader\u00cdas",
    "sg:phone":"+34 925 22 11 68",
    "sg:postcode":"45001",
    "sg:province":"Toledo",
    "sg:website":"www.mazapan.com",
    "wof:name":"Santo Tome S. A.",
    "wof:placetype":"venue"
},
  "geometry": {"coordinates":[-4.025138855,39.8618774414],"type":"Point"}
}