{
  "type": "Feature",
  "properties": {
    "addr:full":"Rbla Sant Jordi, 42 Torrefarrera Lleida 25123",
    "addr:housenumber":"42",
    "addr:postcode":"25123",
    "addr:street":"Rbla Sant Jordi",
    "iso:country":"ES",
    "sg:address":"Rbla Sant Jordi, 42",
    "sg:city":"Torrefarrera",
    "sg:orig_category":"Inform\u00c1tica (estudios, Servicios, Asesor\u00cda, Formaci\u00d3n)",
    "sg:phone":"+34 973 75 14 26",
    "sg:postcode":"25123",
    "sg:province":"Lleida",
    "wof:name":"Centre D'invest. I Dese.de Ponent S.l.",
    "wof:placetype":"venue"
},
  "geometry": {"coordinates":[0.6103600264,41.6708717346],"type":"Point"}
}