{
  "type": "Feature",
  "properties": {
    "iso:country":"ES",
    "sg:address":"Calle de Menorca, 2",
    "sg:city":"Matas-pinar-monte Rozas",
    "sg:orig_category":"Doctores En Medicina",
    "sg:phone":"+34 916 40 02 71",
    "sg:postcode":"28290",
    "sg:province":"Madrid",
    "wof:name":"Abaly S.l.",
    "wof:placetype":"venue"
},
  "geometry": {"coordinates":[-3.892527,40.535812],"type":"Point"}
}