{
  "type": "Feature",
  "properties": {
    "addr:full":"Calle de Olma, 31 San Anton Murcia 30005",
    "addr:housenumber":"31",
    "addr:postcode":"30005",
    "addr:street":"Calle De Olma",
    "iso:country":"ES",
    "sg:address":"Calle de Olma, 31",
    "sg:city":"San Anton",
    "sg:orig_category":"Procuradores",
    "sg:phone":"+34 968 28 13 49",
    "sg:postcode":"30005",
    "sg:province":"Murcia",
    "wof:name":"Marcilla Onate Vicente",
    "wof:placetype":"venue"
},
  "geometry": {"coordinates":[-1.1415389776,37.9875106812],"type":"Point"}
}