{
  "type": "Feature",
  "properties": {
    "iso:country":"ES",
    "sg:address":"Calle de Fontilles, 8",
    "sg:city":"Valencia",
    "sg:orig_category":"Estudios, Instalaci\u00d3n De Climatizaci\u00d3n",
    "sg:phone":"+34 963 67 72 96",
    "sg:postcode":"46024",
    "sg:province":"Valencia",
    "wof:name":"Osvalclimart S.l.u",
    "wof:placetype":"venue"
},
  "geometry": {"coordinates":[-0.3347690105,39.4497947693],"type":"Point"}
}