{
  "type": "Feature",
  "properties": {
    "addr:full":"Avda Pedro Romero, S/n Sevilla Sevilla 41007",
    "addr:housenumber":"s / n",
    "addr:postcode":"41007",
    "addr:street":"Avda Pedro Romero",
    "iso:country":"ES",
    "sg:address":"Avda Pedro Romero, S/n",
    "sg:city":"Sevilla",
    "sg:orig_category":"Perfumer\u00cda Y Cosm\u00c9tica (fabricaci\u00d3n, Al Por Mayor)",
    "sg:phone":"+34 954 51 95 14",
    "sg:postcode":"41007",
    "sg:province":"Sevilla",
    "wof:name":"Sanchez-jauregui Jimenez Encarnacion",
    "wof:placetype":"venue"
},
  "geometry": {"coordinates":[-5.9590067863,37.3987617493],"type":"Point"}
}