{
  "type": "Feature",
  "properties": {
    "addr:full":"Carr Mitja-galta, De, 35 Casco Urbano Valencia 46760",
    "addr:housenumber":"35",
    "addr:postcode":"46760",
    "addr:street":"Carr Mitja-Galta De",
    "iso:country":"ES",
    "sg:address":"Carr Mitja-galta, De, 35",
    "sg:city":"Casco Urbano",
    "sg:orig_category":"Panader\u00cdas, Panader\u00cdas",
    "sg:phone":"+34 962 82 20 42",
    "sg:postcode":"46760",
    "sg:province":"Valencia",
    "wof:name":"Hernandez Grau Purificacion Rosa",
    "wof:placetype":"venue"
},
  "geometry": {"coordinates":[-0.2594090104,39.0749702454],"type":"Point"}
}