{
  "type": "Feature",
  "properties": {
    "addr:full":"Calle de Principe De Vergara, 254 Madrid Madrid 28016",
    "addr:housenumber":"254",
    "addr:postcode":"28016",
    "addr:street":"Calle De Principe De Vergara",
    "iso:country":"ES",
    "sg:address":"Calle de Principe De Vergara, 254",
    "sg:city":"Madrid",
    "sg:orig_category":"Traductores",
    "sg:phone":"+34 913 44 10 13",
    "sg:postcode":"28016",
    "sg:province":"Madrid",
    "wof:name":"Luso Espa\u00f1ola De Traducciones S.l.",
    "wof:placetype":"venue"
},
  "geometry": {"coordinates":[-3.6769249439,40.4561195374],"type":"Point"}
}