{
  "type": "Feature",
  "properties": {
    "iso:country":"ES",
    "sg:address":"Ctra Moraira-calpe, 167",
    "sg:city":"Teulada",
    "sg:orig_category":"Alquiler De Veh\u00cdculos: Turismos Y Utilitarios",
    "sg:phone":"+34 966 49 86 03",
    "sg:postcode":"03725",
    "sg:province":"Alicante",
    "wof:name":"Francisco Devesa S.l.",
    "wof:placetype":"venue"
},
  "geometry": {"coordinates":[0.1012500003,38.7296409607],"type":"Point"}
}