{
  "type": "Feature",
  "properties": {
    "addr:full":"Rua Irmans Moreno Ulloa, 3 Ribadeo Lugo 27700",
    "addr:housenumber":"3",
    "addr:postcode":"27700",
    "addr:street":"Rua Irmans;Ulloa",
    "iso:country":"ES",
    "sg:address":"Rua Irmans Moreno Ulloa, 3",
    "sg:city":"Ribadeo",
    "sg:orig_category":"Administradores De Bienes Y Delegados De Comunidades De Propietarios",
    "sg:phone":"+34 982 12 96 40",
    "sg:postcode":"27700",
    "sg:province":"Lugo",
    "wof:name":"Gesmape S.l.",
    "wof:placetype":"venue"
},
  "geometry": {"coordinates":[-7.0403847694,43.5336265564],"type":"Point"}
}