{
  "type": "Feature",
  "properties": {
    "iso:country":"ES",
    "sg:address":"Ptda L'arpella, S/n",
    "sg:city":"Muro Alcoy",
    "sg:orig_category":"Fabricaci\u00d3n, Venta De Cuadros, Accesorios Para Enmarcar",
    "sg:phone":"+34 966 51 60 72",
    "sg:postcode":"03830",
    "sg:province":"Alicante",
    "wof:name":"Molduras El Comtat S.a.",
    "wof:placetype":"venue"
},
  "geometry": {"coordinates":[-0.4640209973,38.7071800232],"type":"Point"}
}