{
  "type": "Feature",
  "properties": {
    "addr:full":"Calle de Salvador Dali, 1 Don Benito Badajoz 06400",
    "addr:housenumber":"1",
    "addr:postcode":"06400",
    "addr:street":"Calle De Salvador Dali",
    "iso:country":"ES",
    "sg:address":"Calle de Salvador Dali, 1",
    "sg:city":"Don Benito",
    "sg:classifiers":[
        {
            "category":"Casinos & Gambling",
            "type":"Entertainment"
        }
    ],
    "sg:phone":"+34 924 81 24 50",
    "sg:postcode":"06400",
    "sg:province":"Badajoz",
    "sg:tags":[
        "locale",
        "de",
        "juego"
    ],
    "wof:name":"Exjuco 2000 S.a.",
    "wof:placetype":"venue"
},
  "geometry": {"coordinates":[-5.8579888344,38.9624633789],"type":"Point"}
}