{
  "type": "Feature",
  "properties": {
    "addr:full":"Calle de Naval La, 152 Palmas De Gran Canaria Las Palmas 35008",
    "addr:housenumber":"152",
    "addr:postcode":"35008",
    "addr:street":"Calle De Naval La",
    "iso:country":"ES",
    "sg:address":"Calle de Naval La, 152",
    "sg:city":"Palmas De Gran Canaria",
    "sg:orig_category":"Inform\u00c1tica (estudios, Servicios, Asesor\u00cda, Formaci\u00d3n)",
    "sg:phone":"+34 928 23 10 09",
    "sg:postcode":"35008",
    "sg:province":"Las Palmas",
    "wof:name":"Celular Telecom S.a.",
    "wof:placetype":"venue"
},
  "geometry": {"coordinates":[-15.4228219986,28.1502609253],"type":"Point"}
}