{
  "type": "Feature",
  "properties": {
    "iso:country":"ES",
    "sg:address":"Calle de Pi Y Margall, 16",
    "sg:city":"Palmas De Gran Canaria",
    "sg:orig_category":"Profesiones M\u00c9dicas, Param\u00c9dicas",
    "sg:phone":"+34 928 23 19 26",
    "sg:postcode":"35006",
    "sg:province":"Las Palmas",
    "wof:name":"Kineost S.l.gabinete Terapeutico",
    "wof:placetype":"venue"
},
  "geometry": {"coordinates":[-15.4330053329,28.1324443817],"type":"Point"}
}