{
  "type": "Feature",
  "properties": {
    "addr:full":"Carr Assutzena, S/n Urbanitzacio Els Griells-la Pletera Girona 17258",
    "addr:housenumber":"s",
    "addr:postcode":"17258",
    "addr:street":"Carr Assutzena;/ N Urbanitzacio Els Griells-La Pletera",
    "iso:country":"ES",
    "sg:address":"Carr Assutzena, S/n",
    "sg:city":"Urbanitzacio Els Griells-la Pletera",
    "sg:orig_category":"Supermercados Y Hipermercados",
    "sg:phone":"+34 972 75 07 36",
    "sg:postcode":"17258",
    "sg:province":"Girona",
    "wof:name":"Supermercat Griells S.l.",
    "wof:placetype":"venue"
},
  "geometry": {"coordinates":[3.1995449066,42.053730011],"type":"Point"}
}