{
  "type": "Feature",
  "properties": {
    "addr:full":"C/ Marededeu Dels Desamparat, 8 Elche Alicante 03203",
    "addr:housenumber":"8",
    "addr:postcode":"03203",
    "addr:street":"C / Marededeu Dels Desamparat",
    "iso:country":"ES",
    "sg:address":"C/ Marededeu Dels Desamparat, 8",
    "sg:city":"Elche",
    "sg:orig_category":"Centros Empresariales",
    "sg:phone":"+34 965 42 77 87",
    "sg:postcode":"03203",
    "sg:province":"Alicante",
    "wof:name":"Pascual Martinez Sonia",
    "wof:placetype":"venue"
},
  "geometry": {"coordinates":[-0.6697670221,38.2703895569],"type":"Point"}
}