{
  "type": "Feature",
  "properties": {
    "iso:country":"ES",
    "sg:address":"Calle de Joaquin Achucarro Arisqueta, 35",
    "sg:city":"Negurigane",
    "sg:orig_category":"Escuelas De Maternidad P\u00dablicas",
    "sg:phone":"+34 944 60 87 13",
    "sg:postcode":"48940",
    "sg:province":"Vizcaya",
    "wof:name":"Rodriguez Eguidazu Maria Del Pilar",
    "wof:placetype":"venue"
},
  "geometry": {"coordinates":[-2.9860789776,43.3275489807],"type":"Point"}
}