{
  "type": "Feature",
  "properties": {
    "iso:country":"ES",
    "sg:address":"Avda Asturias Regimiento Almansa, Km. 0141,0",
    "sg:city":"Le\u00f3n",
    "sg:orig_category":"Promotores Constructores",
    "sg:phone":"+34 987 24 32 00",
    "sg:postcode":"24008",
    "sg:province":"Le\u00f3n",
    "wof:name":"Parque Rey Ordo\u00f1o S.a.",
    "wof:placetype":"venue"
},
  "geometry": {"coordinates":[-5.5550928116,42.6448745728],"type":"Point"}
}