{
  "type": "Feature",
  "properties": {
    "addr:full":"Calle de Nueva, S/n Paniza Zaragoza 50480",
    "addr:housenumber":"s / n",
    "addr:postcode":"50480",
    "addr:street":"Calle De Nueva;Paniza",
    "iso:country":"ES",
    "sg:address":"Calle de Nueva, S/n",
    "sg:city":"Paniza",
    "sg:orig_category":"Centros De Educaci\u00d3n Especial",
    "sg:phone":"+34 976 62 29 40",
    "sg:postcode":"50480",
    "sg:province":"Zaragoza",
    "wof:name":"C. R. A. La Cepa D. G. A. Paniza",
    "wof:placetype":"venue"
},
  "geometry": {"coordinates":[-1.2099740505,41.2832450867],"type":"Point"}
}