{
  "type": "Feature",
  "properties": {
    "iso:country":"ES",
    "sg:address":"Av Catalunya, 45",
    "sg:city":"Amposta",
    "sg:orig_category":"Laboratorios Y Cl\u00cdnicas Veterinarias",
    "sg:phone":"+34 977 70 00 11",
    "sg:postcode":"43870",
    "sg:province":"Tarragona",
    "wof:name":"Ribergan S.l.",
    "wof:placetype":"venue"
},
  "geometry": {"coordinates":[0.5769510269,40.7073249817],"type":"Point"}
}