{
  "type": "Feature",
  "properties": {
    "iso:country":"ES",
    "sg:address":"Carrer de Jovara, 2",
    "sg:city":"Calella",
    "sg:orig_category":"Asociaciones Y Clubs Deportivos",
    "sg:phone":"+34 937 69 44 36",
    "sg:postcode":"08370",
    "sg:province":"Barcelona",
    "wof:name":"Shoes Gestion S.a.",
    "wof:placetype":"venue"
},
  "geometry": {"coordinates":[2.6554191113,41.6115951538],"type":"Point"}
}