{
  "type": "Feature",
  "properties": {
    "iso:country":"ES",
    "sg:address":"Calle de Fernando Martin, 22",
    "sg:city":"Priego Cordoba",
    "sg:orig_category":"Pintura Y Barniz (al Por Menor)",
    "sg:phone":"+34 957 54 23 82",
    "sg:postcode":"14800",
    "sg:province":"C\u00f3rdoba",
    "wof:name":"Pinturas Tarrias S.l.",
    "wof:placetype":"venue"
},
  "geometry": {"coordinates":[-4.2063961029,37.4427490234],"type":"Point"}
}