{
  "type": "Feature",
  "properties": {
    "addr:full":"Av Granvia, 49 Hospitalet Llobregat Barcelona 08908",
    "addr:housenumber":"49",
    "addr:postcode":"08908",
    "addr:street":"Av Granvia",
    "iso:country":"ES",
    "sg:address":"Av Granvia, 49",
    "sg:city":"Hospitalet Llobregat",
    "sg:orig_category":"Molduras, Junquillos, Listones Y Molduras Perforadas",
    "sg:phone":"+34 934 22 89 33",
    "sg:postcode":"08908",
    "sg:province":"Barcelona",
    "wof:name":"Blaya Gambin Juan",
    "wof:placetype":"venue"
},
  "geometry": {"coordinates":[2.1318199635,41.3614807129],"type":"Point"}
}