{
  "type": "Feature",
  "properties": {
    "iso:country":"ES",
    "sg:address":"Calle de Vinaroz, 16",
    "sg:city":"Madrid",
    "sg:orig_category":"Asesor\u00cda Fiscal Y Jur\u00cddica",
    "sg:phone":"+34 914 13 84 05",
    "sg:postcode":"28002",
    "sg:province":"Madrid",
    "wof:name":"Pancorbo Millan S.l.",
    "wof:placetype":"venue"
},
  "geometry": {"coordinates":[-3.6761009693,40.4462280273],"type":"Point"}
}