{
  "type": "Feature",
  "properties": {
    "iso:country":"ES",
    "sg:address":"Av. Son Matias, 3",
    "sg:city":"Palmanova",
    "sg:orig_category":"Comerciantes Al Por Mayor De Vinos, Licores Y Alcoholes",
    "sg:phone":"+34 971 68 33 67",
    "sg:postcode":"07181",
    "sg:province":"Islas Baleares",
    "wof:name":"Segui Llobera Fernando Antonio",
    "wof:placetype":"venue"
},
  "geometry": {"coordinates":[2.5366148949,39.5149726868],"type":"Point"}
}