{
  "type": "Feature",
  "properties": {
    "iso:country":"ES",
    "sg:address":"Calle de Hilario Marco, 3",
    "sg:city":"Cazorla",
    "sg:orig_category":"Laboratorios Y Trabajos De Fotograf\u00cda, V\u00cddeo Y Cine",
    "sg:phone":"+34 953 72 09 34",
    "sg:postcode":"23470",
    "sg:province":"Ja\u00e9n",
    "wof:name":"San Antonio Serrano Joaquin",
    "wof:placetype":"venue"
},
  "geometry": {"coordinates":[-3.0032091141,37.9134292603],"type":"Point"}
}