{
  "type": "Feature",
  "properties": {
    "addr:full":"Calle de Antonio Navajas Ruiz, 2 Torremolinos M\u00e1laga 29620",
    "addr:housenumber":"2",
    "addr:postcode":"29620",
    "addr:street":"Calle De Antonio Navajas Ruiz;Ma\u0301Laga",
    "iso:country":"ES",
    "sg:address":"Calle de Antonio Navajas Ruiz, 2",
    "sg:city":"Torremolinos",
    "sg:orig_category":"Centros Comerciales Y Grandes Tiendas",
    "sg:phone":"+34 952 37 00 52",
    "sg:postcode":"29620",
    "sg:province":"M\u00e1laga",
    "wof:name":"Miguel Angel Dura S.l.",
    "wof:placetype":"venue"
},
  "geometry": {"coordinates":[-4.4943585396,36.624332428],"type":"Point"}
}