{
  "type": "Feature",
  "properties": {
    "addr:full":"Calle de Carmen, 23 Almonacid De La Sierra Zaragoza 50108",
    "addr:housenumber":"23",
    "addr:postcode":"50108",
    "addr:street":"Calle De Carmen",
    "iso:country":"ES",
    "sg:address":"Calle de Carmen, 23",
    "sg:city":"Almonacid De La Sierra",
    "sg:orig_category":"Asilos De Ancianos. Centros Privados",
    "sg:phone":"+34 976 62 74 08",
    "sg:postcode":"50108",
    "sg:province":"Zaragoza",
    "wof:name":"Residencia Nuestra Se\u00f1ora Del Carmen De Almonacid S.l.",
    "wof:placetype":"venue"
},
  "geometry": {"coordinates":[-1.3230826855,41.3986053467],"type":"Point"}
}