{
  "type": "Feature",
  "properties": {
    "iso:country":"ES",
    "sg:address":"Calle de Circe, 6",
    "sg:city":"Majadahonda",
    "sg:orig_category":"Arquitectos",
    "sg:phone":"+34 916 38 40 21",
    "sg:postcode":"28220",
    "sg:province":"Madrid",
    "wof:name":"Vazquez Prieto Amadeo",
    "wof:placetype":"venue"
},
  "geometry": {"coordinates":[-3.8564460278,40.455783844],"type":"Point"}
}