{
  "type": "Feature",
  "properties": {
    "addr:full":"Calle de Javier Espronceda, 5 Zubia Granada 18140",
    "addr:housenumber":"5",
    "addr:postcode":"18140",
    "addr:street":"Calle De Javier Espronceda",
    "iso:country":"ES",
    "sg:address":"Calle de Javier Espronceda, 5",
    "sg:city":"Zubia",
    "sg:orig_category":"Reposter\u00cdas",
    "sg:phone":"+34 958 59 01 84",
    "sg:postcode":"18140",
    "sg:province":"Granada",
    "wof:name":"Panaderia Pasteleria El Angel S.l.",
    "wof:placetype":"venue"
},
  "geometry": {"coordinates":[-3.5814299583,37.1130256653],"type":"Point"}
}