{
  "type": "Feature",
  "properties": {
    "addr:full":"Pg Comte De Vilardaga, 71 Sant Feliu Llobregat Barcelona 08980",
    "addr:housenumber":"71",
    "addr:postcode":"08980",
    "addr:street":"Pg Comte De Vilardaga",
    "iso:country":"ES",
    "sg:address":"Pg Comte De Vilardaga, 71",
    "sg:city":"Sant Feliu Llobregat",
    "sg:orig_category":"Asesor\u00cdas Y Estudios Financieros",
    "sg:phone":"+34 936 85 55 12",
    "sg:postcode":"08980",
    "sg:province":"Barcelona",
    "wof:name":"Rqest Asesores S.l.",
    "wof:placetype":"venue"
},
  "geometry": {"coordinates":[2.0521149635,41.3862228394],"type":"Point"}
}