{
  "type": "Feature",
  "properties": {
    "addr:full":"Calle de Santa Natalia, 92 Nules Castell\u00f3n 12520",
    "addr:housenumber":"92",
    "addr:postcode":"12520",
    "addr:street":"Calle De Santa Natalia",
    "iso:country":"ES",
    "sg:address":"Calle de Santa Natalia, 92",
    "sg:city":"Nules",
    "sg:orig_category":"Empresas De Carpinter\u00cda Met\u00c1lica",
    "sg:phone":"+34 964 67 06 41",
    "sg:postcode":"12520",
    "sg:province":"Castell\u00f3n",
    "wof:name":"Hermanos Casino Adsuara S.l.",
    "wof:placetype":"venue"
},
  "geometry": {"coordinates":[-0.1606860012,39.8559684753],"type":"Point"}
}