{
  "type": "Feature",
  "properties": {
    "iso:country":"ES",
    "sg:address":"Carrer de Victor Catala, 2",
    "sg:city":"Canyelles-almadrava-puig-rom",
    "sg:orig_category":"Librer\u00cdas",
    "sg:phone":"+34 972 15 31 79",
    "sg:postcode":"17480",
    "sg:province":"Girona",
    "wof:name":"Pacreu Ruiz Amelia",
    "wof:placetype":"venue"
},
  "geometry": {"coordinates":[3.1663351059,42.2661399841],"type":"Point"}
}