{
  "type": "Feature",
  "properties": {
    "iso:country":"ES",
    "sg:address":"Plaz Europa, 6",
    "sg:city":"Nuevo Poblado",
    "sg:orig_category":"Gu\u00cdas Y Gu\u00cdas",
    "sg:phone":"+34 923 47 30 80",
    "sg:postcode":"37480",
    "sg:province":"Salamanca",
    "wof:name":"Lorenzo Bonilla Clara",
    "wof:placetype":"venue"
},
  "geometry": {"coordinates":[-6.8109388351,40.5948791504],"type":"Point"}
}