{
  "type": "Feature",
  "properties": {
    "addr:full":"Calle de Velazquez, 5 Arroyo De La Miel-benalmadena Costa M\u00e1laga 29630",
    "addr:housenumber":"5",
    "addr:postcode":"29630",
    "addr:street":"Calle De Velazquez;Arroyo De La Miel-Benalmadena Costa Ma\u0301Laga",
    "iso:country":"ES",
    "sg:address":"Calle de Velazquez, 5",
    "sg:city":"Arroyo De La Miel-benalmadena Costa",
    "sg:orig_category":"M\u00c9dicos: Medicina Interna",
    "sg:phone":"+34 952 44 20 85",
    "sg:postcode":"29630",
    "sg:province":"M\u00e1laga",
    "wof:name":"Cifrian Vera Gerardo",
    "wof:placetype":"venue"
},
  "geometry": {"coordinates":[-4.5152239799,36.6002883911],"type":"Point"}
}