{
  "type": "Feature",
  "properties": {
    "addr:full":"Calle de Nueva, 10 Alcorcon Madrid 28921",
    "addr:housenumber":"10",
    "addr:postcode":"28921",
    "addr:street":"Calle De Nueva",
    "iso:country":"ES",
    "sg:address":"Calle de Nueva, 10",
    "sg:city":"Alcorcon",
    "sg:orig_category":"Fotocopias, Reprograf\u00cda",
    "sg:phone":"+34 916 43 94 00",
    "sg:postcode":"28921",
    "sg:province":"Madrid",
    "wof:name":"Jimenez Palomares Miguel Angel",
    "wof:placetype":"venue"
},
  "geometry": {"coordinates":[-3.826212883,40.3482894897],"type":"Point"}
}