{
  "type": "Feature",
  "properties": {
    "addr:full":"Rond San Jose (de), 3 Cuenca Cuenca 16004",
    "addr:postcode":"16004",
    "addr:street":"Jose",
    "iso:country":"ES",
    "sg:address":"Rond San Jose (de), 3",
    "sg:city":"Cuenca",
    "sg:orig_category":"Importaci\u00d3n, Exportaci\u00d3n Y Comercios De Productos Textiles",
    "sg:phone":"+34 969 23 21 93",
    "sg:postcode":"16004",
    "sg:province":"Cuenca",
    "wof:name":"Noviabella C.b.",
    "wof:placetype":"venue"
},
  "geometry": {"coordinates":[-2.1342260838,40.0614776611],"type":"Point"}
}