{
  "type": "Feature",
  "properties": {
    "addr:full":"Av Alacant, 1 Pego Alicante 03780",
    "addr:housenumber":"1",
    "addr:postcode":"03780",
    "addr:street":"Alacant",
    "iso:country":"ES",
    "sg:address":"Av Alacant, 1",
    "sg:city":"Pego",
    "sg:orig_category":"Caf\u00c9s, Bares, Cervecer\u00cdas",
    "sg:phone":"+34 965 57 12 01",
    "sg:postcode":"03780",
    "sg:province":"Alicante",
    "wof:name":"Faraig Tamarit Francisco",
    "wof:placetype":"venue"
},
  "geometry": {"coordinates":[-0.1155449972,38.8417167664],"type":"Point"}
}