{
  "type": "Feature",
  "properties": {
    "addr:full":"Rbla Josep Tomas Ventosa, 10 Vilanova I La Geltru Barcelona 08800",
    "addr:housenumber":"10",
    "addr:postcode":"08800",
    "addr:street":"Rbla Josep Tomas Ventosa",
    "iso:country":"ES",
    "sg:address":"Rbla Josep Tomas Ventosa, 10",
    "sg:city":"Vilanova I La Geltru",
    "sg:orig_category":"Mec\u00c1nico Del Autom\u00d3vil",
    "sg:phone":"+34 938 93 79 13",
    "sg:postcode":"08800",
    "sg:province":"Barcelona",
    "wof:name":"Navarro Mu\u00f1oz Jose Luis",
    "wof:placetype":"venue"
},
  "geometry": {"coordinates":[1.7285679579,41.2217559814],"type":"Point"}
}