{
  "type": "Feature",
  "properties": {
    "iso:country":"ES",
    "sg:address":"Carrer de Serra Del Canigo, 10",
    "sg:city":"Prat Llobregat",
    "sg:orig_category":"Mec\u00c1nico Del Autom\u00d3vil",
    "sg:phone":"+34 933 70 89 54",
    "sg:postcode":"08820",
    "sg:province":"Barcelona",
    "wof:name":"Barreira Vicente Jose Luis",
    "wof:placetype":"venue"
},
  "geometry": {"coordinates":[2.0871639252,41.3229598999],"type":"Point"}
}