{
  "type": "Feature",
  "properties": {
    "addr:full":"Carr Antoni Maura, 12 Pollen\u00e7a Islas Baleares 07460",
    "addr:housenumber":"12",
    "addr:postcode":"07460",
    "addr:street":"Carr Antoni Maura;Islas",
    "iso:country":"ES",
    "sg:address":"Carr Antoni Maura, 12",
    "sg:city":"Pollen\u00e7a",
    "sg:orig_category":"Molduras, Junquillos, Listones Y Molduras Perforadas",
    "sg:phone":"+34 971 53 02 24",
    "sg:postcode":"07460",
    "sg:province":"Islas Baleares",
    "wof:name":"Jianwei  Zhang",
    "wof:placetype":"venue"
},
  "geometry": {"coordinates":[3.0153670311,39.8773765564],"type":"Point"}
}