{
  "type": "Feature",
  "properties": {
    "addr:full":"Paseo Del Sol, 1 Infiesto Asturias 33530",
    "addr:housenumber":"1",
    "addr:postcode":"33530",
    "addr:street":"Paseo Del Sol",
    "iso:country":"ES",
    "sg:address":"Paseo Del Sol, 1",
    "sg:city":"Infiesto",
    "sg:orig_category":"Plomeros",
    "sg:phone":"+34 985 71 04 51",
    "sg:postcode":"33530",
    "sg:province":"Asturias",
    "wof:name":"Rios Fernandez Alberto Emilio",
    "wof:placetype":"venue"
},
  "geometry": {"coordinates":[-5.3611588478,43.3452949524],"type":"Point"}
}