{
  "type": "Feature",
  "properties": {
    "iso:country":"ES",
    "sg:address":"Plaz Candelaria (la), 8",
    "sg:city":"Santa Cruz De Tenerife",
    "sg:orig_category":"Ropa Para Se\u00d1oras (al Por Menor)",
    "sg:phone":"+34 922 24 50 20",
    "sg:postcode":"38002",
    "sg:province":"Santa Cruz De Tenerife",
    "sg:website":"www.zara.com",
    "wof:name":"Zara Espa\u00f1a S.a.",
    "wof:placetype":"venue"
},
  "geometry": {"coordinates":[-16.2485370636,28.4683971405],"type":"Point"}
}