{
  "type": "Feature",
  "properties": {
    "addr:full":"Carrer de Mercat, S/n Llagosta Barcelona 08120",
    "addr:housenumber":"s / n",
    "addr:postcode":"08120",
    "addr:street":"Carrer De Mercat",
    "iso:country":"ES",
    "sg:address":"Carrer de Mercat, S/n",
    "sg:city":"Llagosta",
    "sg:orig_category":"Librer\u00cdas",
    "sg:phone":"+34 935 74 48 07",
    "sg:postcode":"08120",
    "sg:province":"Barcelona",
    "wof:name":"Pinto Garcia Dolores",
    "wof:placetype":"venue"
},
  "geometry": {"coordinates":[2.1935200691,41.513469696],"type":"Point"}
}