{
  "type": "Feature",
  "properties": {
    "iso:country":"ES",
    "sg:address":"Calle de Covadonga, 13",
    "sg:city":"Langreo",
    "sg:orig_category":"Electricidad: Instaladores",
    "sg:phone":"+34 985 69 28 30",
    "sg:postcode":"33900",
    "sg:province":"Asturias",
    "wof:name":"Fernandez Cano Juan Luis",
    "wof:placetype":"venue"
},
  "geometry": {"coordinates":[-5.6855835915,43.2981262207],"type":"Point"}
}