{
  "type": "Feature",
  "properties": {
    "addr:full":"Carrer de Puigcerda, 239 Barcelona Barcelona 08020",
    "addr:housenumber":"239",
    "addr:postcode":"08020",
    "addr:street":"Carrer De Puigcerda",
    "iso:country":"ES",
    "sg:address":"Carrer de Puigcerda, 239",
    "sg:city":"Barcelona",
    "sg:orig_category":"Peluquer\u00cdas, Peluquer\u00cda Mixta",
    "sg:phone":"+34 932 78 19 31",
    "sg:postcode":"08020",
    "sg:province":"Barcelona",
    "wof:name":"Ruiz Martinez Susana",
    "wof:placetype":"venue"
},
  "geometry": {"coordinates":[2.2035210133,41.4197044373],"type":"Point"}
}