{
  "type": "Feature",
  "properties": {
    "addr:full":"Calle de Ipertegui, 3 Orkoien Navarra 31160",
    "addr:housenumber":"3",
    "addr:postcode":"31160",
    "addr:street":"Calle De Ipertegui",
    "iso:country":"ES",
    "sg:address":"Calle de Ipertegui, 3",
    "sg:city":"Orkoien",
    "sg:orig_category":"Iglesia Cat\u00d3lica",
    "sg:phone":"+34 948 32 51 58",
    "sg:postcode":"31160",
    "sg:province":"Navarra",
    "wof:name":"Parroquia De San Jose Obrero",
    "wof:placetype":"venue"
},
  "geometry": {"coordinates":[-1.6934679747,42.8225479126],"type":"Point"}
}