{
  "type": "Feature",
  "properties": {
    "addr:full":"Pi\u00f1eiras, 9 Pi\u00d1eiras Lugo 27186",
    "addr:housenumber":"9",
    "addr:postcode":"27186",
    "addr:street":"Pin\u0303Eiras",
    "iso:country":"ES",
    "sg:address":"Pi\u00f1eiras, 9",
    "sg:city":"Pi\u00d1eiras",
    "sg:orig_category":"Cr\u00cda De Animales",
    "sg:phone":"+34 982 16 01 71",
    "sg:postcode":"27186",
    "sg:province":"Lugo",
    "wof:name":"Rodriguez Gomez Jose",
    "wof:placetype":"venue"
},
  "geometry": {"coordinates":[-7.6086130142,42.853012085],"type":"Point"}
}