{
  "type": "Feature",
  "properties": {
    "iso:country":"ES",
    "sg:address":"Pg Marti I, L'huma, 10",
    "sg:city":"Sector E",
    "sg:orig_category":"Aguas (distribuci\u00d3n, Servicios)",
    "sg:phone":"+34 977 73 73 98",
    "sg:postcode":"43530",
    "sg:province":"Tarragona",
    "wof:name":"Infilco Espa\u00d1ola S.a.",
    "wof:placetype":"venue"
},
  "geometry": {"coordinates":[1.2540999651,41.1169281006],"type":"Point"}
}