{
  "type": "Feature",
  "properties": {
    "addr:full":"Carrer de Apulia, 3 Sabadell Barcelona 08206",
    "addr:housenumber":"3",
    "addr:postcode":"08206",
    "addr:street":"Carrer De Apulia",
    "iso:country":"ES",
    "sg:address":"Carrer de Apulia, 3",
    "sg:city":"Sabadell",
    "sg:orig_category":"Peluquer\u00cdas, Peluquer\u00cda Mixta",
    "sg:phone":"+34 937 23 02 21",
    "sg:postcode":"08206",
    "sg:province":"Barcelona",
    "wof:name":"Blanes Dominguez Azahara",
    "wof:placetype":"venue"
},
  "geometry": {"coordinates":[2.0944330692,41.5558357239],"type":"Point"}
}