{
  "type": "Feature",
  "properties": {
    "addr:full":"C/ Alfons Xii, 17 Banyoles Girona 17820",
    "addr:housenumber":"17",
    "addr:postcode":"17820",
    "addr:street":"C / Alfons Xii",
    "iso:country":"ES",
    "sg:address":"C/ Alfons Xii, 17",
    "sg:city":"Banyoles",
    "sg:orig_category":"Tapicer\u00cdas",
    "sg:phone":"+34 972 57 07 58",
    "sg:postcode":"17820",
    "sg:province":"Girona",
    "wof:name":"Tapisseria I Decoracio Boix S.l.",
    "wof:placetype":"venue"
},
  "geometry": {"coordinates":[2.7640829086,42.1173973083],"type":"Point"}
}