{
  "type": "Feature",
  "properties": {
    "iso:country":"ES",
    "sg:address":"Alam Salvador (del)/el Salbador Zumardia, S/n",
    "sg:city":"Amurrio",
    "sg:orig_category":"Centros Empresariales",
    "sg:phone":"+34 945 89 08 69",
    "sg:postcode":"01470",
    "sg:province":"\u00c1lava",
    "wof:name":"Lezama Consultores S.c.",
    "wof:placetype":"venue"
},
  "geometry": {"coordinates":[-2.9991700649,43.0439071655],"type":"Point"}
}