{
  "type": "Feature",
  "properties": {
    "iso:country":"ES",
    "sg:address":"La Comillera-rioseco, S/n",
    "sg:city":"Ovi\u00f1ana",
    "sg:orig_category":"Acuicultura",
    "sg:phone":"+34 985 60 91 98",
    "sg:postcode":"33993",
    "sg:province":"Asturias",
    "sg:website":"www.piscifactoriadelalba.com",
    "wof:name":"Piscifactoria Del Alba S.a.",
    "wof:placetype":"venue"
},
  "geometry": {"coordinates":[-5.4554481506,43.2214393616],"type":"Point"}
}