{
  "type": "Feature",
  "properties": {
    "addr:full":"Plaz Blas Infante, 5 Carpio C\u00f3rdoba 14620",
    "addr:housenumber":"5",
    "addr:postcode":"14620",
    "addr:street":"Plaz Blas Infante;Co\u0301Rdoba",
    "iso:country":"ES",
    "sg:address":"Plaz Blas Infante, 5",
    "sg:city":"Carpio",
    "sg:orig_category":"Estancos",
    "sg:phone":"+34 957 18 01 46",
    "sg:postcode":"14620",
    "sg:province":"C\u00f3rdoba",
    "wof:name":"Bioque Gaitan Jose",
    "wof:placetype":"venue"
},
  "geometry": {"coordinates":[-4.4973101616,37.9406318665],"type":"Point"}
}