{
  "type": "Feature",
  "properties": {
    "addr:full":"Av Francesc Macia, 100 Vilanova I La Geltru Barcelona 08800",
    "addr:housenumber":"100",
    "addr:postcode":"08800",
    "addr:street":"Av Francesc Macia",
    "iso:country":"ES",
    "sg:address":"Av Francesc Macia, 100",
    "sg:city":"Vilanova I La Geltru",
    "sg:orig_category":"Molduras, Junquillos, Listones Y Molduras Perforadas",
    "sg:phone":"+34 938 15 82 48",
    "sg:postcode":"08800",
    "sg:province":"Barcelona",
    "wof:name":"Gutierrez Molina Rosario",
    "wof:placetype":"venue"
},
  "geometry": {"coordinates":[1.7185219526,41.2219696045],"type":"Point"}
}