{
  "type": "Feature",
  "properties": {
    "iso:country":"ES",
    "sg:address":"Calle de Garcia Morato, 34",
    "sg:city":"Valladolid",
    "sg:orig_category":"Ropa Para Se\u00d1oras Y Caballeros (al Por Menor)",
    "sg:phone":"+34 983 36 30 29",
    "sg:postcode":"47006",
    "sg:province":"Valladolid",
    "wof:name":"Berrocal Rivada Javier",
    "wof:placetype":"venue"
},
  "geometry": {"coordinates":[-4.7350511551,41.6444358826],"type":"Point"}
}