{
  "type": "Feature",
  "properties": {
    "iso:country":"ES",
    "sg:address":"Calle de Gran Via, 10",
    "sg:city":"Almazan",
    "sg:orig_category":"Retoques De Vestidos",
    "sg:phone":"+34 975 30 12 35",
    "sg:postcode":"42200",
    "sg:province":"Soria",
    "wof:name":"Garcia Jimenez Florencio",
    "wof:placetype":"venue"
},
  "geometry": {"coordinates":[-2.5299739838,41.4875831604],"type":"Point"}
}