{
  "type": "Feature",
  "properties": {
    "iso:country":"ES",
    "sg:address":"Calle de Fraile, 2",
    "sg:city":"Llerena",
    "sg:orig_category":"Bebidas",
    "sg:phone":"+34 924 87 07 50",
    "sg:postcode":"06900",
    "sg:province":"Badajoz",
    "wof:name":"Mena Rubiano Rufino",
    "wof:placetype":"venue"
},
  "geometry": {"coordinates":[-6.0110731125,38.2328872681],"type":"Point"}
}