{
  "type": "Feature",
  "properties": {
    "iso:country":"ES",
    "sg:address":"Calle de Jacinto Benavente, 62",
    "sg:city":"Brenes",
    "sg:orig_category":"Farmacias",
    "sg:phone":"+34 954 79 62 38",
    "sg:postcode":"41310",
    "sg:province":"Sevilla",
    "wof:name":"Martinez Sarmiento Diego",
    "wof:placetype":"venue"
},
  "geometry": {"coordinates":[-5.8669090271,37.551361084],"type":"Point"}
}