{
  "type": "Feature",
  "properties": {
    "addr:full":"Pl Porxada, 24 Granollers Barcelona 08401",
    "addr:housenumber":"24",
    "addr:postcode":"08401",
    "addr:street":"Pl Porxada",
    "iso:country":"ES",
    "sg:address":"Pl Porxada, 24",
    "sg:city":"Granollers",
    "sg:orig_category":"Zapatos (al Por Menor)",
    "sg:phone":"+34 938 79 68 74",
    "sg:postcode":"08401",
    "sg:province":"Barcelona",
    "wof:name":"Comercial Miralles S.l.",
    "wof:placetype":"venue"
},
  "geometry": {"coordinates":[2.2878420353,41.6079139709],"type":"Point"}
}