{
  "type": "Feature",
  "properties": {
    "addr:full":"Carrer de Cozvijar, S/n Durcal Granada 18650",
    "addr:housenumber":"s",
    "addr:postcode":"18650",
    "addr:street":"Carrer De Cozvijar;/ N",
    "iso:country":"ES",
    "sg:address":"Carrer de Cozvijar, S/n",
    "sg:city":"Durcal",
    "sg:orig_category":"Ense\u00d1anza Agr\u00cdcola",
    "sg:phone":"+34 958 78 05 19",
    "sg:postcode":"18650",
    "sg:province":"Granada",
    "wof:name":"El Molino De Lecrin S.c.a.",
    "wof:placetype":"venue"
},
  "geometry": {"coordinates":[-3.5704190731,36.9924316406],"type":"Point"}
}