{
  "type": "Feature",
  "properties": {
    "addr:full":"Ctra. Extremadura, Km. 0036,8 Calipo Ii Madrid 28600",
    "addr:postcode":"28600",
    "addr:street":"Ctra. Extremadura Km. 0036,8 Calipo",
    "iso:country":"ES",
    "sg:address":"Ctra. Extremadura, Km. 0036,8",
    "sg:city":"Calipo Ii",
    "sg:orig_category":"Organizaci\u00d3n De Actos, Seminarios Y Congresos",
    "sg:phone":"+34 918 13 94 20",
    "sg:postcode":"28600",
    "sg:province":"Madrid",
    "wof:name":"Carriba S.a.",
    "wof:placetype":"venue"
},
  "geometry": {"coordinates":[-4.0136671066,40.28490448],"type":"Point"}
}