{
  "type": "Feature",
  "properties": {
    "iso:country":"ES",
    "sg:address":"Calle de Pasajes, 7",
    "sg:city":"Errenteria",
    "sg:orig_category":"Peluqueros: De Se\u00d1oras",
    "sg:phone":"+34 943 52 00 68",
    "sg:postcode":"20100",
    "sg:province":"Guip\u00f9zcoa",
    "wof:name":"Baraibar Gogorza Milagros",
    "wof:placetype":"venue"
},
  "geometry": {"coordinates":[-1.9019949436,43.3155708313],"type":"Point"}
}