{
  "type": "Feature",
  "properties": {
    "iso:country":"ES",
    "sg:address":"Pl Esglesia, 14",
    "sg:city":"Montcada Centre",
    "sg:orig_category":"Perfumer\u00cda (al Por Menor)",
    "sg:phone":"+34 935 64 25 79",
    "sg:postcode":"08110",
    "sg:province":"Barcelona",
    "wof:name":"Fontanals Mestres Jose",
    "wof:placetype":"venue"
},
  "geometry": {"coordinates":[2.1879301071,41.4865341187],"type":"Point"}
}