{
  "type": "Feature",
  "properties": {
    "addr:full":"Calle de Titanio, 1 Valladolid Valladolid 47012",
    "addr:housenumber":"1",
    "addr:postcode":"47012",
    "addr:street":"Calle De Titanio",
    "iso:country":"ES",
    "sg:address":"Calle de Titanio, 1",
    "sg:city":"Valladolid",
    "sg:orig_category":"Muebles, Minoristas",
    "sg:phone":"+34 983 39 42 93",
    "sg:postcode":"47012",
    "sg:province":"Valladolid",
    "wof:name":"Hipercolchon Muebles S.l.",
    "wof:placetype":"venue"
},
  "geometry": {"coordinates":[-4.7048840523,41.6289596558],"type":"Point"}
}