{
  "type": "Feature",
  "properties": {
    "iso:country":"ES",
    "sg:address":"Calle de San Martin De Finojosa, S/n",
    "sg:city":"Soria",
    "sg:orig_category":"Promotores Constructores",
    "sg:phone":"+34 975 22 19 45",
    "sg:postcode":"42003",
    "sg:province":"Soria",
    "wof:name":"Europea De Viviendas Duero Soria S.l",
    "wof:placetype":"venue"
},
  "geometry": {"coordinates":[-2.4689939022,41.7599143982],"type":"Point"}
}