{
  "type": "Feature",
  "properties": {
    "addr:full":"Calle de Braulio Martin, 5 Iscar Valladolid 47420",
    "addr:housenumber":"5",
    "addr:postcode":"47420",
    "addr:street":"Calle De Braulio Martin",
    "iso:country":"ES",
    "sg:address":"Calle de Braulio Martin, 5",
    "sg:city":"Iscar",
    "sg:orig_category":"Asesor\u00cda Fiscal Y Jur\u00cddica",
    "sg:phone":"+34 983 61 12 10",
    "sg:postcode":"47420",
    "sg:province":"Valladolid",
    "wof:name":"Alonso Carrera Maria Jesus",
    "wof:placetype":"venue"
},
  "geometry": {"coordinates":[-4.5314397812,41.3621139526],"type":"Point"}
}