{
  "type": "Feature",
  "properties": {
    "addr:full":"Calle de Calera, 35 Burgos Burgos 09002",
    "addr:housenumber":"35",
    "addr:postcode":"09002",
    "addr:street":"Calle De Calera",
    "iso:country":"ES",
    "sg:address":"Calle de Calera, 35",
    "sg:city":"Burgos",
    "sg:orig_category":"Empresarios Y Productoras De Espect\u00c1culos",
    "sg:phone":"+34 947 20 70 49",
    "sg:postcode":"09002",
    "sg:province":"Burgos",
    "wof:name":"Rodriguez Giron Eleuterio",
    "wof:placetype":"venue"
},
  "geometry": {"coordinates":[-3.6991043091,42.33852005],"type":"Point"}
}