{
  "type": "Feature",
  "properties": {
    "iso:country":"ES",
    "sg:address":"Calle de Churruca, 2",
    "sg:city":"Dos Hermanas",
    "sg:orig_category":"Asesor\u00cda De Formaci\u00d3n Y Gesti\u00d3n De Personal",
    "sg:phone":"+34 955 67 58 88",
    "sg:postcode":"41700",
    "sg:province":"Sevilla",
    "wof:name":"Ruiz Farfan Jose Antonio",
    "wof:placetype":"venue"
},
  "geometry": {"coordinates":[-5.9199051857,37.2799224854],"type":"Point"}
}