{
  "type": "Feature",
  "properties": {
    "addr:full":"Carrer de Cerdanya, 26 Vendrell Tarragona 43700",
    "addr:housenumber":"26",
    "addr:postcode":"43700",
    "addr:street":"Carrer De Cerdanya",
    "iso:country":"ES",
    "sg:address":"Carrer de Cerdanya, 26",
    "sg:city":"Vendrell",
    "sg:orig_category":"Artes Gr\u00c1ficas, Artes Pl\u00c1sticas (curso)",
    "sg:phone":"+34 977 66 27 94",
    "sg:postcode":"43700",
    "sg:province":"Tarragona",
    "wof:name":"Ferre Planas Eulalia",
    "wof:placetype":"venue"
},
  "geometry": {"coordinates":[1.535662055,41.218170166],"type":"Point"}
}