{
  "type": "Feature",
  "properties": {
    "addr:full":"Gale Oliva (la), 2 Pontevedra Pontevedra 36001",
    "addr:postcode":"36001",
    "addr:street":"La 2",
    "iso:country":"ES",
    "sg:address":"Gale Oliva (la), 2",
    "sg:city":"Pontevedra",
    "sg:orig_category":"Complementos De Vestir (al Por Menor)",
    "sg:phone":"+34 986 86 24 36",
    "sg:postcode":"36001",
    "sg:province":"Pontevedra",
    "wof:name":"Meiga C.b.",
    "wof:placetype":"venue"
},
  "geometry": {"coordinates":[-8.6442260742,42.4307174683],"type":"Point"}
}