{
  "type": "Feature",
  "properties": {
    "addr:full":"Avda Gerardo Diego, S/n Segovia Segovia 40006",
    "addr:housenumber":"s / n",
    "addr:postcode":"40006",
    "addr:street":"Avda Gerardo Diego",
    "iso:country":"ES",
    "sg:address":"Avda Gerardo Diego, S/n",
    "sg:city":"Segovia",
    "sg:orig_category":"Centros De Educaci\u00d3n Especial",
    "sg:phone":"+34 921 44 53 83",
    "sg:postcode":"40006",
    "sg:province":"Segovia",
    "wof:name":"Colegio Publico Nueva Segovia",
    "wof:placetype":"venue"
},
  "geometry": {"coordinates":[-4.1026592255,40.9342956543],"type":"Point"}
}