{
  "type": "Feature",
  "properties": {
    "addr:full":"Cra Cirera (de), S/n Mataro Barcelona 08304",
    "addr:housenumber":"s",
    "addr:postcode":"08304",
    "addr:street":"/ N Mataro Barcelona",
    "iso:country":"ES",
    "sg:address":"Cra Cirera (de), S/n",
    "sg:city":"Mataro",
    "sg:orig_category":"Reposter\u00cdas",
    "sg:phone":"+34 937 58 80 86",
    "sg:postcode":"08304",
    "sg:province":"Barcelona",
    "wof:name":"Aromas Selectos S.l.",
    "wof:placetype":"venue"
},
  "geometry": {"coordinates":[2.4299488068,41.5544090271],"type":"Point"}
}