{
  "type": "Feature",
  "properties": {
    "addr:full":"Carrer de Valencia, 538 Barcelona Barcelona 08013",
    "addr:housenumber":"538",
    "addr:postcode":"08013",
    "addr:street":"Carrer De Valencia",
    "iso:country":"ES",
    "sg:address":"Carrer de Valencia, 538",
    "sg:city":"Barcelona",
    "sg:orig_category":"Fabricaci\u00d3n, Importaci\u00d3n De L\u00c1mparas Y Bombillas",
    "sg:phone":"+34 932 46 38 91",
    "sg:postcode":"08013",
    "sg:province":"Barcelona",
    "wof:name":"Guimera Pueyo Oscar",
    "wof:placetype":"venue"
},
  "geometry": {"coordinates":[2.1818199158,41.4063911438],"type":"Point"}
}