{
  "type": "Feature",
  "properties": {
    "iso:country":"ES",
    "sg:address":"Barr Cajigona (la), S/n",
    "sg:city":"Quijas",
    "sg:orig_category":"Ba\u00d1os Y Duchas P\u00dablicos",
    "sg:phone":"+34 942 83 86 67",
    "sg:postcode":"39590",
    "sg:province":"Cantabria",
    "wof:name":"Ayuntamiento De Reocin",
    "wof:placetype":"venue"
},
  "geometry": {"coordinates":[-4.1317028999,43.3504219055],"type":"Point"}
}