{
  "type": "Feature",
  "properties": {
    "iso:country":"ES",
    "sg:address":"Carrer de Provenca, 26",
    "sg:city":"Mataro",
    "sg:orig_category":"Empresas De Carpinter\u00cda De Madera",
    "sg:phone":"+34 937 99 40 38",
    "sg:postcode":"08303",
    "sg:province":"Barcelona",
    "wof:name":"Fusteria Berna S.l.",
    "wof:placetype":"venue"
},
  "geometry": {"coordinates":[2.423199892,41.5400505066],"type":"Point"}
}