{
  "type": "Feature",
  "properties": {
    "iso:country":"ES",
    "sg:address":"C/ Raval De Sant Agusti, 44",
    "sg:city":"Tarrega",
    "sg:orig_category":"Empresas De Carpinter\u00cda De Madera",
    "sg:phone":"+34 973 31 04 98",
    "sg:postcode":"25300",
    "sg:province":"Lleida",
    "wof:name":"Fusteria Pm S.l.",
    "wof:placetype":"venue"
},
  "geometry": {"coordinates":[1.1410850286,41.6482696533],"type":"Point"}
}