{
  "type": "Feature",
  "properties": {
    "iso:country":"ES",
    "sg:address":"Avda Vegas Los, 47",
    "sg:city":"Malaga",
    "sg:orig_category":"Art\u00cdculos De Decoraci\u00d3n",
    "sg:phone":"+34 952 36 18 73",
    "sg:postcode":"29006",
    "sg:province":"M\u00e1laga",
    "wof:name":"Survalen S.l.",
    "wof:placetype":"venue"
},
  "geometry": {"coordinates":[-4.4765920639,36.7119941711],"type":"Point"}
}