{
  "type": "Feature",
  "properties": {
    "addr:full":"Carrer de Jacint Verdaguer, 154 Sabadell Barcelona 08205",
    "addr:housenumber":"154",
    "addr:postcode":"08205",
    "addr:street":"Carrer De Jacint Verdaguer",
    "iso:country":"ES",
    "sg:address":"Carrer de Jacint Verdaguer, 154",
    "sg:city":"Sabadell",
    "sg:orig_category":"Discotecas Y Salas De Baile",
    "sg:phone":"+34 937 12 09 06",
    "sg:postcode":"08205",
    "sg:province":"Barcelona",
    "wof:name":"Four Box S.l.",
    "wof:placetype":"venue"
},
  "geometry": {"coordinates":[2.1038239002,41.53465271],"type":"Point"}
}