{
  "type": "Feature",
  "properties": {
    "addr:full":"Carr Serreta, 18 Massamagrell Valencia 46130",
    "addr:housenumber":"18",
    "addr:postcode":"46130",
    "addr:street":"Carr Serreta",
    "iso:country":"ES",
    "sg:address":"Carr Serreta, 18",
    "sg:city":"Massamagrell",
    "sg:orig_category":"Molduras, Junquillos, Listones Y Molduras Perforadas",
    "sg:phone":"+34 961 44 07 15",
    "sg:postcode":"46130",
    "sg:province":"Valencia",
    "wof:name":"Villarroya Suesta Manuel",
    "wof:placetype":"venue"
},
  "geometry": {"coordinates":[-0.3329139948,39.5671310425],"type":"Point"}
}