{
  "type": "Feature",
  "properties": {
    "iso:country":"ES",
    "sg:address":"Carr Conde De Rodezno, 15",
    "sg:city":"Quart Poblet",
    "sg:orig_category":"Muebles, Minoristas",
    "sg:phone":"+34 961 54 77 97",
    "sg:postcode":"46930",
    "sg:province":"Valencia",
    "wof:name":"Aquilino Sociedad Cooperativa Valenciana",
    "wof:placetype":"venue"
},
  "geometry": {"coordinates":[-0.4482499063,39.4806594849],"type":"Point"}
}