{
  "type": "Feature",
  "properties": {
    "addr:full":"Avda Andalucia, 23 Malaga M\u00e1laga 29006",
    "addr:housenumber":"23",
    "addr:postcode":"29006",
    "addr:street":"Avda Andalucia;Ma\u0301Laga",
    "iso:country":"ES",
    "sg:address":"Avda Andalucia, 23",
    "sg:city":"Malaga",
    "sg:orig_category":"Arquitectos",
    "sg:phone":"+34 952 34 00 99",
    "sg:postcode":"29006",
    "sg:province":"M\u00e1laga",
    "wof:name":"Tejero Mateo Ricardo",
    "wof:placetype":"venue"
},
  "geometry": {"coordinates":[-4.4396891594,36.716506958],"type":"Point"}
}