{
  "type": "Feature",
  "properties": {
    "iso:country":"ES",
    "sg:address":"Calle de Doctor Fleming, 50",
    "sg:city":"Madrid",
    "sg:orig_category":"Arquitectos",
    "sg:phone":"+34 913 45 22 03",
    "sg:postcode":"28036",
    "sg:province":"Madrid",
    "wof:name":"Ibarrondo Garcia Jose Luis",
    "wof:placetype":"venue"
},
  "geometry": {"coordinates":[-3.6877715588,40.462097168],"type":"Point"}
}