{
  "type": "Feature",
  "properties": {
    "addr:full":"Calle de Bizkaia, 4 Legizamon Vizcaya 48450",
    "addr:housenumber":"4",
    "addr:postcode":"48450",
    "addr:street":"Calle De Bizkaia",
    "iso:country":"ES",
    "sg:address":"Calle de Bizkaia, 4",
    "sg:city":"Legizamon",
    "sg:orig_category":"Cristaler\u00cdas",
    "sg:phone":"+34 944 40 62 12",
    "sg:postcode":"48450",
    "sg:province":"Vizcaya",
    "wof:name":"Cristaleria Gonzalez E Hijos",
    "wof:placetype":"venue"
},
  "geometry": {"coordinates":[-2.8924908638,43.2519378662],"type":"Point"}
}