{
  "type": "Feature",
  "properties": {
    "iso:country":"ES",
    "sg:address":"Calle de Hemingway, 31",
    "sg:city":"Malaga",
    "sg:orig_category":"Almacenes Frigor\u00cdficos",
    "sg:phone":"+34 952 17 31 41",
    "sg:postcode":"29004",
    "sg:province":"M\u00e1laga",
    "wof:name":"Frigorificos Guadalquivir S.l.",
    "wof:placetype":"venue"
},
  "geometry": {"coordinates":[-4.4785413742,36.6894836426],"type":"Point"}
}