{
  "type": "Feature",
  "properties": {
    "iso:country":"ES",
    "sg:address":"Rier Salut, S/n",
    "sg:city":"Sant Feliu Llobregat",
    "sg:classifiers":[
        {
            "category":"Manufacturing",
            "subcategory":"Metals",
            "type":"Manufacturing & Wholesale Goods"
        }
    ],
    "sg:phone":"+34 936 85 00 42",
    "sg:postcode":"08980",
    "sg:province":"Barcelona",
    "sg:tags":[
        "en",
        "fundiciones"
    ],
    "wof:name":"Obiols Carbo Concepcion",
    "wof:placetype":"venue"
},
  "geometry": {"coordinates":[2.0435750484,41.3816261292],"type":"Point"}
}