{
  "type": "Feature",
  "properties": {
    "iso:country":"ES",
    "sg:address":"Calle de Corredera, 22",
    "sg:city":"Jerez De La Frontera",
    "sg:orig_category":"Farmacias",
    "sg:phone":"+34 956 34 21 28",
    "sg:postcode":"11402",
    "sg:province":"C\u00e1diz",
    "wof:name":"Alonso Cortiguera Gregorio",
    "wof:placetype":"venue"
},
  "geometry": {"coordinates":[-6.1363978386,36.6812667847],"type":"Point"}
}