{
  "type": "Feature",
  "properties": {
    "addr:full":"Calle de Artesania, 21 Mairena Aljarafe Sevilla 41927",
    "addr:housenumber":"21",
    "addr:postcode":"41927",
    "addr:street":"Calle De Artesania",
    "iso:country":"ES",
    "sg:address":"Calle de Artesania, 21",
    "sg:city":"Mairena Aljarafe",
    "sg:orig_category":"Fabricaci\u00d3n De Juguetes Autom\u00c1ticos",
    "sg:phone":"+34 954 18 02 51",
    "sg:postcode":"41927",
    "sg:province":"Sevilla",
    "wof:name":"Recreativos Castilleja S.l.",
    "wof:placetype":"venue"
},
  "geometry": {"coordinates":[-6.0557184219,37.3572540283],"type":"Point"}
}