{
  "type": "Feature",
  "properties": {
    "iso:country":"ES",
    "sg:address":"Calle de Cerrada Santa Cruz, 25",
    "sg:city":"Benavente",
    "sg:orig_category":"Bancos",
    "sg:phone":"+34 980 63 01 55",
    "sg:postcode":"49600",
    "sg:province":"Zamora",
    "wof:name":"Caja Rural De Zamora",
    "wof:placetype":"venue"
},
  "geometry": {"coordinates":[-5.6754231453,42.0028915405],"type":"Point"}
}