{
  "type": "Feature",
  "properties": {
    "addr:full":"Calle de Torres Quevedo, 90 Sevilla Sevilla 41016",
    "addr:housenumber":"90",
    "addr:postcode":"41016",
    "addr:street":"Calle De Torres Quevedo",
    "iso:country":"ES",
    "sg:address":"Calle de Torres Quevedo, 90",
    "sg:city":"Sevilla",
    "sg:orig_category":"Negocio De Materiales De Construcci\u00d3n",
    "sg:phone":"+34 954 40 41 38",
    "sg:postcode":"41016",
    "sg:province":"Sevilla",
    "wof:name":"Jimenez Mu\u00f1oz Manuel Jesus",
    "wof:placetype":"venue"
},
  "geometry": {"coordinates":[-5.9057388306,37.3839378357],"type":"Point"}
}