{
  "type": "Feature",
  "properties": {
    "addr:full":"Calle de Biosca, 2 Madrid Madrid 28043",
    "addr:housenumber":"2",
    "addr:postcode":"28043",
    "addr:street":"Calle De Biosca",
    "iso:country":"ES",
    "sg:address":"Calle de Biosca, 2",
    "sg:city":"Madrid",
    "sg:orig_category":"Peluquer\u00cdas, Peluquer\u00cda Mixta",
    "sg:phone":"+34 913 81 59 96",
    "sg:postcode":"28043",
    "sg:province":"Madrid",
    "wof:name":"Palomo Barrasa Juan Carlos",
    "wof:placetype":"venue"
},
  "geometry": {"coordinates":[-3.6499295235,40.4705810547],"type":"Point"}
}