{
  "type": "Feature",
  "properties": {
    "iso:country":"ES",
    "sg:address":"Avda Olimpica, 4",
    "sg:city":"Mostoles",
    "sg:orig_category":"Alquiler De V\u00cddeo",
    "sg:phone":"+34 916 17 99 11",
    "sg:postcode":"28935",
    "sg:province":"Madrid",
    "wof:name":"Gomez Granado Miguel Angel",
    "wof:placetype":"venue"
},
  "geometry": {"coordinates":[-3.8838489056,40.3264045715],"type":"Point"}
}