{
  "type": "Feature",
  "properties": {
    "addr:full":"Calle de General Luis Alarcon De La Lastra, 6 Sevilla Sevilla 41006",
    "addr:housenumber":"6",
    "addr:postcode":"41006",
    "addr:street":"Calle De General Luis Alarcon De La Lastra",
    "iso:country":"ES",
    "sg:address":"Calle de General Luis Alarcon De La Lastra, 6",
    "sg:city":"Sevilla",
    "sg:orig_category":"Pintura, Barniz, Productos Asimilables (fabricaci\u00d3n, Al Por Mayor)",
    "sg:phone":"+34 954 66 01 74",
    "sg:postcode":"41006",
    "sg:province":"Sevilla",
    "wof:name":"Jurado Brioso Rosa",
    "wof:placetype":"venue"
},
  "geometry": {"coordinates":[-5.9507598877,37.3857955933],"type":"Point"}
}