{
  "type": "Feature",
  "properties": {
    "iso:country":"ES",
    "sg:address":"Carr Llarg, 78",
    "sg:city":"Santa Maria Del Cami",
    "sg:orig_category":"Ropa Para Se\u00d1oras Y Caballeros (al Por Menor)",
    "sg:phone":"+34 971 62 00 28",
    "sg:postcode":"07320",
    "sg:province":"Islas Baleares",
    "wof:name":"Mas Dols Carmen",
    "wof:placetype":"venue"
},
  "geometry": {"coordinates":[2.7748808861,39.6501998901],"type":"Point"}
}