{
  "type": "Feature",
  "properties": {
    "iso:country":"ES",
    "sg:address":"Ctra. Lluc, 51",
    "sg:city":"Inca",
    "sg:orig_category":"Molduras, Junquillos, Listones Y Molduras Perforadas",
    "sg:phone":"+34 971 50 00 41",
    "sg:postcode":"07300",
    "sg:province":"Islas Baleares",
    "wof:name":"Distribuciones Hermanos Bujalance S.l.",
    "wof:placetype":"venue"
},
  "geometry": {"coordinates":[2.9118299484,39.7250518799],"type":"Point"}
}