{
  "type": "Feature",
  "properties": {
    "iso:country":"ES",
    "sg:address":"Calle de Melchor Fernandez Almagro, 52",
    "sg:city":"Madrid",
    "sg:orig_category":"Muebles, Minoristas",
    "sg:phone":"+34 917 39 61 07",
    "sg:postcode":"28029",
    "sg:province":"Madrid",
    "wof:name":"Picon Martinez Maria",
    "wof:placetype":"venue"
},
  "geometry": {"coordinates":[-3.7052431107,40.4766845703],"type":"Point"}
}