{
  "type": "Feature",
  "properties": {
    "addr:full":"Calle de Empedrada, 23 Palacios Arzobispo Salamanca 37111",
    "addr:housenumber":"23",
    "addr:postcode":"37111",
    "addr:street":"Calle De Empedrada",
    "iso:country":"ES",
    "sg:address":"Calle de Empedrada, 23",
    "sg:city":"Palacios Arzobispo",
    "sg:orig_category":"Centros De Educaci\u00d3n Especial",
    "sg:phone":"+34 923 32 09 79",
    "sg:postcode":"37111",
    "sg:province":"Salamanca",
    "wof:name":"Ayuntamiento De Palacios Del Arzobispo",
    "wof:placetype":"venue"
},
  "geometry": {"coordinates":[-5.8898191452,41.1661491394],"type":"Point"}
}