{
  "type": "Feature",
  "properties": {
    "addr:full":"Carrer de Pintor Tapiro, 22 Barcelona Barcelona 08028",
    "addr:housenumber":"22",
    "addr:postcode":"08028",
    "addr:street":"Carrer De Pintor Tapiro",
    "iso:country":"ES",
    "sg:address":"Carrer de Pintor Tapiro, 22",
    "sg:city":"Barcelona",
    "sg:orig_category":"Inform\u00c1tica (estudios, Servicios, Asesor\u00cda, Formaci\u00d3n)",
    "sg:phone":"+34 934 40 04 05",
    "sg:postcode":"08028",
    "sg:province":"Barcelona",
    "wof:name":"Hsb S.a.",
    "wof:placetype":"venue"
},
  "geometry": {"coordinates":[2.1184160709,41.3780517578],"type":"Point"}
}