{
  "type": "Feature",
  "properties": {
    "iso:country":"ES",
    "sg:address":"Calle de Garcia Lorca, 4",
    "sg:city":"Rozas De Madrid",
    "sg:classifiers":[
        {
            "category":"Professional",
            "subcategory":"Research",
            "type":"Services"
        }
    ],
    "sg:phone":"+34 916 37 45 12",
    "sg:postcode":"28230",
    "sg:province":"Madrid",
    "sg:tags":[
        "mercado",
        "de",
        "estudios"
    ],
    "wof:name":"Cordero Garcia Victor",
    "wof:placetype":"venue"
},
  "geometry": {"coordinates":[-3.8699419498,40.4890975952],"type":"Point"}
}