{
  "type": "Feature",
  "properties": {
    "iso:country":"ES",
    "sg:address":"Calle de Molinos, 11",
    "sg:city":"Torrijos",
    "sg:orig_category":"Contenedores (mercanc\u00cdas)",
    "sg:phone":"+34 925 76 22 35",
    "sg:postcode":"45500",
    "sg:province":"Toledo",
    "wof:name":"Logistica Rafana S.l.",
    "wof:placetype":"venue"
},
  "geometry": {"coordinates":[-4.2847929001,39.9831886292],"type":"Point"}
}