{
  "type": "Feature",
  "properties": {
    "iso:country":"ES",
    "sg:address":"Carr Hospital, 16",
    "sg:city":"Blanes",
    "sg:orig_category":"Confecci\u00d3n De Trajes Para Se\u00d1oras",
    "sg:phone":"+34 972 35 13 29",
    "sg:postcode":"17300",
    "sg:province":"Girona",
    "wof:name":"Costa Villar Maria Concepcion",
    "wof:placetype":"venue"
},
  "geometry": {"coordinates":[2.7912778854,41.6733894348],"type":"Point"}
}