{
  "type": "Feature",
  "properties": {
    "addr:full":"Puente, 17 Pontevedra Pontevedra 36002",
    "addr:housenumber":"17",
    "addr:postcode":"36002",
    "addr:street":"Puente",
    "iso:country":"ES",
    "sg:address":"Puente, 17",
    "sg:city":"Pontevedra",
    "sg:orig_category":"Molduras, Junquillos, Listones Y Molduras Perforadas",
    "sg:phone":"+34 986 85 31 56",
    "sg:postcode":"36002",
    "sg:province":"Pontevedra",
    "wof:name":"Pazos Dieguez Jose Luis",
    "wof:placetype":"venue"
},
  "geometry": {"coordinates":[-8.6233987808,42.4448699951],"type":"Point"}
}