{
  "type": "Feature",
  "properties": {
    "addr:full":"Pase La Epitafia, 3 Briviesca Burgos 09240",
    "addr:housenumber":"3",
    "addr:postcode":"09240",
    "iso:country":"ES",
    "sg:address":"Pase La Epitafia, 3",
    "sg:city":"Briviesca",
    "sg:orig_category":"Zapater\u00cdas",
    "sg:phone":"+34 947 59 15 17",
    "sg:postcode":"09240",
    "sg:province":"Burgos",
    "wof:name":"Calzados Kigar S.l.",
    "wof:placetype":"venue"
},
  "geometry": {"coordinates":[-3.3240199089,42.5523300171],"type":"Point"}
}