{
  "type": "Feature",
  "properties": {
    "iso:country":"ES",
    "sg:address":"Avda Madrid, 10",
    "sg:city":"Moraira",
    "sg:orig_category":"Inmobiliaria (agencias)",
    "sg:phone":"+34 965 74 55 05",
    "sg:postcode":"03724",
    "sg:province":"Alicante",
    "wof:name":"Granit Casa S.l.",
    "wof:placetype":"venue"
},
  "geometry": {"coordinates":[0.1336974055,38.6880226135],"type":"Point"}
}