{
  "type": "Feature",
  "properties": {
    "addr:full":"Bo Cipreses, S/n Aspe Alicante 03680",
    "addr:housenumber":"s / n",
    "addr:postcode":"03680",
    "iso:country":"ES",
    "sg:address":"Bo Cipreses, S/n",
    "sg:city":"Aspe",
    "sg:orig_category":"Confecci\u00d3n De Zapatos",
    "sg:phone":"+34 965 49 01 48",
    "sg:postcode":"03680",
    "sg:province":"Alicante",
    "wof:name":"Calzados Maker's S.l.",
    "wof:placetype":"venue"
},
  "geometry": {"coordinates":[-0.7691239715,38.3373603821],"type":"Point"}
}