{
  "type": "Feature",
  "properties": {
    "iso:country":"ES",
    "sg:address":"Avda General Aviles, 3",
    "sg:city":"Valencia",
    "sg:orig_category":"Veh\u00cdculos De Ocasi\u00d3n",
    "sg:phone":"+34 963 49 81 00",
    "sg:postcode":"46015",
    "sg:province":"Valencia",
    "wof:name":"Avilescar S.l.",
    "wof:placetype":"venue"
},
  "geometry": {"coordinates":[-0.3908688128,39.4879302979],"type":"Point"}
}