{
  "type": "Feature",
  "properties": {
    "iso:country":"ES",
    "sg:address":"Calle de Doctor Gomez Ferrer, 8",
    "sg:city":"Onda",
    "sg:orig_category":"Plomeros",
    "sg:phone":"+34 964 60 16 79",
    "sg:postcode":"12200",
    "sg:province":"Castell\u00f3n",
    "wof:name":"Instalaciones Y Suministros C.b.",
    "wof:placetype":"venue"
},
  "geometry": {"coordinates":[-0.2663610876,39.9654541016],"type":"Point"}
}