{
  "type": "Feature",
  "properties": {
    "iso:country":"ES",
    "sg:address":"Calle de Pozo Alegria, 9",
    "sg:city":"Castellon De La Plana",
    "sg:orig_category":"Delegados, Agentes De Tr\u00c1nsito, Auxiliares De Transporte Internacional",
    "sg:phone":"+34 964 20 81 73",
    "sg:postcode":"12006",
    "sg:province":"Castell\u00f3n",
    "wof:name":"Bernat Beltran Francisco",
    "wof:placetype":"venue"
},
  "geometry": {"coordinates":[-0.1404139996,40.0213813782],"type":"Point"}
}