{
  "type": "Feature",
  "properties": {
    "addr:full":"Fca. Fresneras, S/n Navacarros Salamanca 37716",
    "addr:housenumber":"s / n",
    "addr:postcode":"37716",
    "iso:country":"ES",
    "sg:address":"Fca. Fresneras, S/n",
    "sg:city":"Navacarros",
    "sg:orig_category":"M\u00c1rmoles, Granitos Y Piedras Naturales",
    "sg:phone":"+34 923 16 10 48",
    "sg:postcode":"37716",
    "sg:province":"Salamanca",
    "wof:name":"Parmagra S.l.",
    "wof:placetype":"venue"
},
  "geometry": {"coordinates":[-97.78224945069999,45.7040786743],"type":"Point"}
}