{
  "type": "Feature",
  "properties": {
    "addr:full":"Pg Bonanova, 50 Barcelona Barcelona 08017",
    "addr:housenumber":"50",
    "addr:postcode":"08017",
    "addr:street":"Pg Bonanova",
    "iso:country":"ES",
    "sg:address":"Pg Bonanova, 50",
    "sg:city":"Barcelona",
    "sg:orig_category":"Agencias Y Asesores De Publicidad",
    "sg:phone":"+34 934 17 17 09",
    "sg:postcode":"08017",
    "sg:province":"Barcelona",
    "wof:name":"Microfoam S.l.",
    "wof:placetype":"venue"
},
  "geometry": {"coordinates":[2.1281929016,41.4038734436],"type":"Point"}
}