{
  "type": "Feature",
  "properties": {
    "addr:full":"Ctra Salteras-olivares, S/n Salteras Sevilla 41909",
    "addr:housenumber":"s / n",
    "addr:postcode":"41909",
    "addr:street":"Ctra Salteras-Olivares",
    "iso:country":"ES",
    "sg:address":"Ctra Salteras-olivares, S/n",
    "sg:city":"Salteras",
    "sg:orig_category":"Productos Fitosanitarios (negocio, Aplicaci\u00d3n)",
    "sg:phone":"+34 955 70 77 20",
    "sg:postcode":"41909",
    "sg:province":"Sevilla",
    "wof:name":"Industrial Quimica Key S. A.",
    "wof:placetype":"venue"
},
  "geometry": {"coordinates":[-6.1071691513,37.4179992676],"type":"Point"}
}