{
  "type": "Feature",
  "properties": {
    "iso:country":"ES",
    "sg:address":"Calle de Villabaso Camilo, 10",
    "sg:city":"Bilbao",
    "sg:orig_category":"Peluquer\u00cdas, Peluquer\u00cda Mixta",
    "sg:phone":"+34 944 21 30 43",
    "sg:postcode":"48002",
    "sg:province":"Vizcaya",
    "wof:name":"Fortes Del Pozo Sayoa",
    "wof:placetype":"venue"
},
  "geometry": {"coordinates":[-2.9475739002,43.2535438538],"type":"Point"}
}