{
  "type": "Feature",
  "properties": {
    "iso:country":"ES",
    "sg:address":"Bda Llibreteria, 10",
    "sg:city":"Barcelona",
    "sg:orig_category":"Zapatos (al Por Menor)",
    "sg:phone":"+34 933 15 07 05",
    "sg:postcode":"08002",
    "sg:province":"Barcelona",
    "wof:name":"Iglesias Vilalta Juan",
    "wof:placetype":"venue"
},
  "geometry": {"coordinates":[2.1781721115,41.3836746216],"type":"Point"}
}