{
  "type": "Feature",
  "properties": {
    "addr:full":"Avda Juan Carlos I, 40 Torre-pacheco Murcia 30700",
    "addr:housenumber":"40",
    "addr:postcode":"30700",
    "addr:street":"Avda Juan Carlos I",
    "iso:country":"ES",
    "sg:address":"Avda Juan Carlos I, 40",
    "sg:city":"Torre-pacheco",
    "sg:orig_category":"Pintura, Barniz, Productos Asimilables (fabricaci\u00d3n, Al Por Mayor)",
    "sg:phone":"+34 968 58 58 73",
    "sg:postcode":"30700",
    "sg:province":"Murcia",
    "sg:website":"www.pinturasbriz.es",
    "wof:name":"Comercial De Pinturas Briz S.l.",
    "wof:placetype":"venue"
},
  "geometry": {"coordinates":[-1.0759320259,37.8180580139],"type":"Point"}
}