{
  "type": "Feature",
  "properties": {
    "iso:country":"ES",
    "sg:address":"Calle de Montecristo, 8",
    "sg:city":"Adra",
    "sg:orig_category":"Contenedores (mercanc\u00cdas)",
    "sg:phone":"+34 950 40 00 62",
    "sg:postcode":"04770",
    "sg:province":"Almer\u00eda",
    "wof:name":"Transportes Generales Ortega Sanchez E Hijos S.l.",
    "wof:placetype":"venue"
},
  "geometry": {"coordinates":[-3.009718895,36.7507400513],"type":"Point"}
}