{
  "type": "Feature",
  "properties": {
    "addr:full":"Calle de Honsario, 21 Jerez De La Frontera C\u00e1diz 11402",
    "addr:housenumber":"21",
    "addr:postcode":"11402",
    "addr:street":"Calle De Honsario",
    "iso:country":"ES",
    "sg:address":"Calle de Honsario, 21",
    "sg:city":"Jerez De La Frontera",
    "sg:orig_category":"Molduras, Junquillos, Listones Y Molduras Perforadas",
    "sg:phone":"+34 956 34 73 02",
    "sg:postcode":"11402",
    "sg:province":"C\u00e1diz",
    "wof:name":"Braza Navarro Francisco",
    "wof:placetype":"venue"
},
  "geometry": {"coordinates":[-6.132352829,36.6849594116],"type":"Point"}
}