{
  "type": "Feature",
  "properties": {
    "iso:country":"ES",
    "sg:address":"Cmno Hormigueras, 169",
    "sg:city":"Madrid",
    "sg:orig_category":"Electricidad: Equipos Industriales, Componentes (fabricaci\u00d3n)",
    "sg:phone":"+34 913 03 12 02",
    "sg:postcode":"28031",
    "sg:province":"Madrid",
    "wof:name":"Abantia Mantenimiento S.a.",
    "wof:placetype":"venue"
},
  "geometry": {"coordinates":[-3.634063,40.377041],"type":"Point"}
}