{
  "type": "Feature",
  "properties": {
    "addr:full":"Ctra Espa\u00d1a, 1 Vera Santa Cruz De Tenerife 38390",
    "addr:housenumber":"1",
    "addr:postcode":"38390",
    "addr:street":"Ctra Espan\u0303A",
    "iso:country":"ES",
    "sg:address":"Ctra Espa\u00d1a, 1",
    "sg:city":"Vera",
    "sg:orig_category":"Servicios Gsm",
    "sg:phone":"+34 922 30 40 74",
    "sg:postcode":"38390",
    "sg:province":"Santa Cruz De Tenerife",
    "wof:name":"Telefonia Maxitel S.l.",
    "wof:placetype":"venue"
},
  "geometry": {"coordinates":[-16.4917697906,28.425359726],"type":"Point"}
}