{
  "type": "Feature",
  "properties": {
    "addr:full":"Via Enlace Norte Sur, 1 Sta Cruz Tenerife Santa Cruz De Tenerife 38009",
    "addr:housenumber":"1",
    "addr:postcode":"38009",
    "addr:street":"Via Enlace Norte Sur;Sta Cruz Tenerife",
    "iso:country":"ES",
    "sg:address":"Via Enlace Norte Sur, 1",
    "sg:city":"Sta Cruz Tenerife",
    "sg:orig_category":"Panader\u00cdas, Panader\u00cdas",
    "sg:phone":"+34 922 22 32 78",
    "sg:postcode":"38009",
    "sg:province":"Santa Cruz De Tenerife",
    "wof:name":"Rodriguez Ravelo Benigno Jose",
    "wof:placetype":"venue"
},
  "geometry": {"coordinates":[-17.7755756378,28.6416091919],"type":"Point"}
}