{
  "type": "Feature",
  "properties": {
    "iso:country":"ES",
    "sg:address":"Calle de Ruavieja, 19",
    "sg:city":"Logro\u00f1o",
    "sg:orig_category":"Productores Recolectores, Venta Directa De Vinos",
    "sg:phone":"+34 941 23 69 80",
    "sg:postcode":"26001",
    "sg:province":"La Rioja",
    "sg:website":"www.factoryw.com/rejadorada",
    "wof:name":"La Reja Dorada C.b.",
    "wof:placetype":"venue"
},
  "geometry": {"coordinates":[-2.4456100464,42.4681358337],"type":"Point"}
}