{
  "type": "Feature",
  "properties": {
    "iso:country":"ES",
    "sg:address":"Calle de Gas, 2",
    "sg:city":"Cadiz",
    "sg:orig_category":"Empresarios",
    "sg:phone":"+34 956 27 33 11",
    "sg:postcode":"11008",
    "sg:province":"C\u00e1diz",
    "wof:name":"F.hevia General De Construcciones S.l.",
    "wof:placetype":"venue"
},
  "geometry": {"coordinates":[-6.2804493904,36.515335083],"type":"Point"}
}