{
  "type": "Feature",
  "properties": {
    "iso:country":"ES",
    "sg:address":"Calle de Cartagena, 164",
    "sg:city":"Madrid",
    "sg:orig_category":"Muebles Y Accesorios Para Cocinas Y Cuartos De Ba\u00d1o (al Por Menor)",
    "sg:phone":"+34 915 62 59 17",
    "sg:postcode":"28002",
    "sg:province":"Madrid",
    "wof:name":"Perez Jimenez Jesus",
    "wof:placetype":"venue"
},
  "geometry": {"coordinates":[-3.6768174171,40.443523407],"type":"Point"}
}