{
  "type": "Feature",
  "properties": {
    "iso:country":"ES",
    "sg:address":"Carrer de Mexic, 24",
    "sg:city":"Barcelona",
    "sg:orig_category":"Servicios De Telecomunicaciones",
    "sg:phone":"+34 933 63 21 63",
    "sg:postcode":"08004",
    "sg:province":"Barcelona",
    "wof:name":"Network Europa S.l.",
    "wof:placetype":"venue"
},
  "geometry": {"coordinates":[2.1486060619,41.3724822998],"type":"Point"}
}