{
  "type": "Feature",
  "properties": {
    "iso:country":"ES",
    "sg:address":"Calle de Telletxe, 13",
    "sg:city":"Getxo",
    "sg:orig_category":"Zapatos (al Por Menor)",
    "sg:phone":"+34 944 66 18 90",
    "sg:postcode":"48990",
    "sg:province":"Vizcaya",
    "wof:name":"Nuria Martinez Diez",
    "wof:placetype":"venue"
},
  "geometry": {"coordinates":[-3.0103042126,43.3525352478],"type":"Point"}
}