{
  "type": "Feature",
  "properties": {
    "iso:country":"ES",
    "sg:address":"Calle de Ramon Y Cajal, 12",
    "sg:city":"Castellon",
    "sg:orig_category":"M\u00c9dicos: Foniatr\u00cda Y Logopedia",
    "sg:phone":"+34 964 26 96 00",
    "sg:postcode":"12002",
    "sg:province":"Castell\u00f3n",
    "wof:name":"Llau Arcusa Maria Jose",
    "wof:placetype":"venue"
},
  "geometry": {"coordinates":[-0.0379020013,39.9819412231],"type":"Point"}
}