{
  "type": "Feature",
  "properties": {
    "iso:country":"ES",
    "sg:address":"Carrer de Nord, 62",
    "sg:city":"Terrassa",
    "sg:orig_category":"M\u00c9dicos: Pediatr\u00cda. Enfermedades De Los Ni\u00d1os",
    "sg:phone":"+34 937 83 71 33",
    "sg:postcode":"08221",
    "sg:province":"Barcelona",
    "wof:name":"Mumany Simo Juan",
    "wof:placetype":"venue"
},
  "geometry": {"coordinates":[2.0135679245,41.5669555664],"type":"Point"}
}