{
  "type": "Feature",
  "properties": {
    "iso:country":"ES",
    "sg:address":"Ctra Santa Cruz Laguna, 366",
    "sg:city":"Santa Cruz De Tenerife",
    "sg:orig_category":"Inmobiliaria (agencias)",
    "sg:phone":"+34 922 67 20 74",
    "sg:postcode":"38293",
    "sg:province":"Santa Cruz De Tenerife",
    "wof:name":"Compa\u00d1ia De Inversion Y Financiacion Canaria S.l.",
    "wof:placetype":"venue"
},
  "geometry": {"coordinates":[-16.2907238007,28.5156917572],"type":"Point"}
}