{
  "type": "Feature",
  "properties": {
    "addr:full":"Calle de Arquitecto Emilio Pi\u00d1ero, 6 Vista Alegre Murcia 30007",
    "addr:housenumber":"6",
    "addr:postcode":"30007",
    "addr:street":"Calle De Arquitecto Emilio Pin\u0303Ero",
    "iso:country":"ES",
    "sg:address":"Calle de Arquitecto Emilio Pi\u00d1ero, 6",
    "sg:city":"Vista Alegre",
    "sg:orig_category":"Caf\u00c9s, Bares, Cervecer\u00cdas",
    "sg:phone":"+34 968 24 05 14",
    "sg:postcode":"30007",
    "sg:province":"Murcia",
    "wof:name":"Barcelo Murcia Francisco",
    "wof:placetype":"venue"
},
  "geometry": {"coordinates":[-1.1142389774,37.9970092773],"type":"Point"}
}