{
  "type": "Feature",
  "properties": {
    "iso:country":"ES",
    "sg:address":"Calle de Virgen De Las Aguas, 38",
    "sg:city":"Viveros",
    "sg:orig_category":"Delegados, Agentes De Tr\u00c1nsito, Auxiliares De Transporte Internacional",
    "sg:phone":"+34 967 38 71 92",
    "sg:postcode":"02310",
    "sg:province":"Albacete",
    "wof:name":"Sanchez Garcia Elias",
    "wof:placetype":"venue"
},
  "geometry": {"coordinates":[-2.5716350079,38.770980835],"type":"Point"}
}