{
  "type": "Feature",
  "properties": {
    "iso:country":"ES",
    "sg:address":"Calle de Arenal, 22",
    "sg:city":"Madrid",
    "sg:orig_category":"Empresarios Y Productoras De Espect\u00c1culos",
    "sg:phone":"+34 915 21 73 65",
    "sg:postcode":"28013",
    "sg:province":"Madrid",
    "wof:name":"Rial De Lema Jose",
    "wof:placetype":"venue"
},
  "geometry": {"coordinates":[-3.7076227665,40.4175376892],"type":"Point"}
}