{
  "type": "Feature",
  "properties": {
    "addr:full":"Avda Jesus Rescatado (de), 15 Cordoba C\u00f3rdoba 14007",
    "addr:housenumber":"15",
    "addr:postcode":"14007",
    "addr:street":"Avda Jesus Rescatado De;Co\u0301Rdoba",
    "iso:country":"ES",
    "sg:address":"Avda Jesus Rescatado (de), 15",
    "sg:city":"Cordoba",
    "sg:orig_category":"Fabricaci\u00d3n De Sobres, Bolsas Y Fundas",
    "sg:phone":"+34 957 26 75 52",
    "sg:postcode":"14007",
    "sg:province":"C\u00f3rdoba",
    "wof:name":"Cortes Martinez Jose Maria",
    "wof:placetype":"venue"
},
  "geometry": {"coordinates":[-4.7600212097,37.8907394409],"type":"Point"}
}