{
  "type": "Feature",
  "properties": {
    "iso:country":"ES",
    "sg:address":"Avda Valladolid, 139",
    "sg:city":"S. Esteban Gormaz",
    "sg:orig_category":"Carnes De Carnicer\u00cda (al Por Mayor)",
    "sg:phone":"+34 975 35 05 82",
    "sg:postcode":"42330",
    "sg:province":"Soria",
    "wof:name":"Distribuciones Espinel Martin S.l.",
    "wof:placetype":"venue"
},
  "geometry": {"coordinates":[-3.192579031,41.5691719055],"type":"Point"}
}