{
  "type": "Feature",
  "properties": {
    "addr:full":"Avda Gregorio Gea, 30 Mislata Valencia 46920",
    "addr:housenumber":"30",
    "addr:postcode":"46920",
    "addr:street":"Avda Gregorio Gea",
    "iso:country":"ES",
    "sg:address":"Avda Gregorio Gea, 30",
    "sg:city":"Mislata",
    "sg:orig_category":"Cajas De Ahorro",
    "sg:phone":"+34 963 70 15 11",
    "sg:postcode":"46920",
    "sg:province":"Valencia",
    "wof:name":"Caixa D'estalvis I Pensions De Barcelona",
    "wof:placetype":"venue"
},
  "geometry": {"coordinates":[-0.4164519906,39.4736862183],"type":"Point"}
}