{
  "type": "Feature",
  "properties": {
    "addr:full":"Calle de Valle Inclan, 10 Almeria Almer\u00eda 04006",
    "addr:housenumber":"10",
    "addr:postcode":"04006",
    "addr:street":"Calle De Valle Inclan",
    "iso:country":"ES",
    "sg:address":"Calle de Valle Inclan, 10",
    "sg:city":"Almeria",
    "sg:orig_category":"Agencias De Viajes",
    "sg:phone":"+34 950 22 53 28",
    "sg:postcode":"04006",
    "sg:province":"Almer\u00eda",
    "wof:name":"Almeritours Aventuras Y Vacaciones S.l",
    "wof:placetype":"venue"
},
  "geometry": {"coordinates":[-2.4492726326,36.8425521851],"type":"Point"}
}