{
  "type": "Feature",
  "properties": {
    "iso:country":"ES",
    "sg:address":"Calle de Rua Oscura, 10",
    "sg:city":"Valladolid",
    "sg:orig_category":"Abogados",
    "sg:phone":"+34 983 35 09 90",
    "sg:postcode":"47003",
    "sg:province":"Valladolid",
    "wof:name":"Orejudo Agudiez Jose",
    "wof:placetype":"venue"
},
  "geometry": {"coordinates":[-4.7259402275,41.6538925171],"type":"Point"}
}