{
  "type": "Feature",
  "properties": {
    "iso:country":"ES",
    "sg:address":"Calle de Algeciras, 34",
    "sg:city":"Tomares",
    "sg:orig_category":"Artes Gr\u00c1ficas, Artes Pl\u00c1sticas (curso)",
    "sg:phone":"+34 954 15 61 82",
    "sg:postcode":"41940",
    "sg:province":"Sevilla",
    "wof:name":"Etiquetas Mairena S.l.",
    "wof:placetype":"venue"
},
  "geometry": {"coordinates":[-6.0302610397,37.3759613037],"type":"Point"}
}