{
  "type": "Feature",
  "properties": {
    "iso:country":"ES",
    "sg:address":"Calle de Cifuentes, 50",
    "sg:city":"Guadalajara",
    "sg:classifiers":[
        {
            "category":"Autos & Motor Vehicles",
            "subcategory":"Automobile Sales",
            "type":"Retail Goods"
        }
    ],
    "sg:phone":"+34 949 23 28 35",
    "sg:postcode":"19003",
    "sg:province":"Guadalajara",
    "wof:name":"San Cristobal Guadalajara S.a.l.",
    "wof:placetype":"venue"
},
  "geometry": {"coordinates":[-3.1743011475,40.6324615479],"type":"Point"}
}