{
  "type": "Feature",
  "properties": {
    "iso:country":"ES",
    "sg:address":"Afueras, S/n",
    "sg:city":"Pollen\u00e7a",
    "sg:orig_category":"Polideportivos",
    "sg:phone":"+34 971 53 39 90",
    "sg:postcode":"07460",
    "sg:province":"Islas Baleares",
    "wof:name":"Ajuntament De Pollenca",
    "wof:placetype":"venue"
},
  "geometry": {"coordinates":[3.0375914574,39.8799629211],"type":"Point"}
}