{
  "type": "Feature",
  "properties": {
    "iso:country":"ES",
    "sg:address":"Calle de Somera, 22",
    "sg:city":"Siles",
    "sg:orig_category":"M\u00c9dicos: Estomatolog\u00cda",
    "sg:phone":"+34 953 49 00 07",
    "sg:postcode":"23380",
    "sg:province":"Ja\u00e9n",
    "wof:name":"Fernandez Quijano Francisco Jose",
    "wof:placetype":"venue"
},
  "geometry": {"coordinates":[-2.5816819668,38.3883705139],"type":"Point"}
}