{
  "type": "Feature",
  "properties": {
    "addr:full":"Pl Vila (la), 17 Prat Llobregat Barcelona 08820",
    "addr:housenumber":"17",
    "addr:postcode":"08820",
    "addr:street":"Pl Vila La;Llobregat",
    "iso:country":"ES",
    "sg:address":"Pl Vila (la), 17",
    "sg:city":"Prat Llobregat",
    "sg:orig_category":"Distribuci\u00d3n De Petr\u00d3leo Y Derivados",
    "sg:phone":"+34 933 70 61 01",
    "sg:postcode":"08820",
    "sg:province":"Barcelona",
    "wof:name":"Gil Martinez Emilio",
    "wof:placetype":"venue"
},
  "geometry": {"coordinates":[2.0930960178,41.3307914734],"type":"Point"}
}