{
  "type": "Feature",
  "properties": {
    "iso:country":"ES",
    "sg:address":"Carrer de Dos De Maig, 26",
    "sg:city":"Manresa",
    "sg:orig_category":"Asilos De Ancianos. Centros Privados",
    "sg:phone":"+34 938 72 48 89",
    "sg:postcode":"08241",
    "sg:province":"Barcelona",
    "wof:name":"Asociacion De Vecinos De Valldaura De Ma",
    "wof:placetype":"venue"
},
  "geometry": {"coordinates":[1.817656517,41.7246589661],"type":"Point"}
}