{
  "type": "Feature",
  "properties": {
    "iso:country":"ES",
    "sg:address":"Avda Espa\u00f1a-calahonda, 4",
    "sg:city":"Mijas Costa",
    "sg:orig_category":"Agencias Y Agentes Comerciales, Representantes",
    "sg:phone":"+34 952 93 36 81",
    "sg:postcode":"29649",
    "sg:province":"M\u00e1laga",
    "wof:name":"Hewitt  Agness Mccalm",
    "wof:placetype":"venue"
},
  "geometry": {"coordinates":[-4.7267189026,36.4947929382],"type":"Point"}
}