{
  "type": "Feature",
  "properties": {
    "iso:country":"ES",
    "sg:address":"C/ Diagonal, 56",
    "sg:city":"Elche",
    "sg:orig_category":"Servicios De Telecomunicaciones",
    "sg:phone":"+34 966 67 49 50",
    "sg:postcode":"03206",
    "sg:province":"Alicante",
    "wof:name":"Sanleandro Comunicaciones S.l.u.",
    "wof:placetype":"venue"
},
  "geometry": {"coordinates":[-0.7087630033,38.2727394104],"type":"Point"}
}