{
  "type": "Feature",
  "properties": {
    "iso:country":"ES",
    "sg:address":"Avda Paz (la), 87",
    "sg:city":"Sevilla",
    "sg:orig_category":"Confiter\u00cdas, Chocolater\u00cdas (al Por Menor)",
    "sg:phone":"+34 954 61 89 81",
    "sg:postcode":"41013",
    "sg:province":"Sevilla",
    "wof:name":"Alvarez Monta\u00f1o Jose Ramon",
    "wof:placetype":"venue"
},
  "geometry": {"coordinates":[-5.9664373398,37.3677062988],"type":"Point"}
}