{
  "type": "Feature",
  "properties": {
    "addr:full":"Avda Jose De Mora, S/n Baza Granada 18800",
    "addr:housenumber":"s",
    "addr:postcode":"18800",
    "addr:street":"Avda Jose De Mora;/ N",
    "iso:country":"ES",
    "sg:address":"Avda Jose De Mora, S/n",
    "sg:city":"Baza",
    "sg:orig_category":"Asistencia Social",
    "sg:phone":"+34 958 86 02 56",
    "sg:postcode":"18800",
    "sg:province":"Granada",
    "wof:name":"Ayuntamiento De Baza",
    "wof:placetype":"venue"
},
  "geometry": {"coordinates":[-2.7691690922,37.4847335815],"type":"Point"}
}