{
  "type": "Feature",
  "properties": {
    "iso:country":"ES",
    "sg:address":"Calle de Reina Mercedes, 1",
    "sg:city":"Cordoba",
    "sg:orig_category":"Molduras, Junquillos, Listones Y Molduras Perforadas",
    "sg:phone":"+34 957 25 25 67",
    "sg:postcode":"14007",
    "sg:province":"C\u00f3rdoba",
    "wof:name":"Leon Rodriguez Rafael",
    "wof:placetype":"venue"
},
  "geometry": {"coordinates":[-4.7628641129,37.8936882019],"type":"Point"}
}