{
  "type": "Feature",
  "properties": {
    "addr:full":"Feces De Abajo, S/n Feces Abaixo Ourense 32699",
    "addr:housenumber":"s",
    "addr:postcode":"32699",
    "addr:street":"Feces;Abajo;/ N Feces",
    "iso:country":"ES",
    "sg:address":"Feces De Abajo, S/n",
    "sg:city":"Feces Abaixo",
    "sg:orig_category":"Ropa De Hogar (al Por Menor)",
    "sg:phone":"+34 988 42 65 60",
    "sg:postcode":"32699",
    "sg:province":"Ourense",
    "wof:name":"Adegas Y Nieto S.l.",
    "wof:placetype":"venue"
},
  "geometry": {"coordinates":[-7.8646407127,42.340007782],"type":"Point"}
}