{
  "type": "Feature",
  "properties": {
    "addr:full":"Calle de Ronda Del Tenis, 6 Vera Almer\u00eda 04620",
    "addr:housenumber":"6;almeri\u0301a",
    "addr:postcode":"04620",
    "addr:street":"Calle De Ronda Del Tenis",
    "iso:country":"ES",
    "sg:address":"Calle de Ronda Del Tenis, 6",
    "sg:city":"Vera",
    "sg:orig_category":"Mec\u00c1nico Del Autom\u00d3vil",
    "sg:phone":"+34 950 39 22 10",
    "sg:postcode":"04620",
    "sg:province":"Almer\u00eda",
    "wof:name":"Taller Julio Ronda Del Tenis S.l.l.",
    "wof:placetype":"venue"
},
  "geometry": {"coordinates":[-1.84869802,37.2382888794],"type":"Point"}
}