{
  "type": "Feature",
  "properties": {
    "addr:full":"Extramuros, S/n Monasterio Vega Valladolid 47688",
    "addr:postcode":"47688",
    "addr:street":"Extramuros S / N Monasterio",
    "iso:country":"ES",
    "sg:address":"Extramuros, S/n",
    "sg:city":"Monasterio Vega",
    "sg:orig_category":"Agricultura: Abastecimiento Y Cosechado (negocio)",
    "sg:phone":"+34 983 78 51 03",
    "sg:postcode":"47688",
    "sg:province":"Valladolid",
    "wof:name":"Morate Y Franco Jose Maria",
    "wof:placetype":"venue"
},
  "geometry": {"coordinates":[-5.1807589531,42.2305374146],"type":"Point"}
}