{
  "type": "Feature",
  "properties": {
    "iso:country":"ES",
    "sg:address":"Calle de Lavadero, S/n",
    "sg:city":"Varea",
    "sg:orig_category":"Delegados, Agentes De Tr\u00c1nsito, Auxiliares De Transporte Internacional",
    "sg:phone":"+34 941 74 00 70",
    "sg:postcode":"26006",
    "sg:province":"La Rioja",
    "wof:name":"Cabrera Conlosa S.l.",
    "wof:placetype":"venue"
},
  "geometry": {"coordinates":[-2.4076590538,42.4644241333],"type":"Point"}
}