{
  "type": "Feature",
  "properties": {
    "iso:country":"ES",
    "sg:address":"Calle de Somera, 2",
    "sg:city":"Malaga",
    "sg:orig_category":"Empresas De Limpieza",
    "sg:phone":"+34 952 21 71 93",
    "sg:postcode":"29001",
    "sg:province":"M\u00e1laga",
    "wof:name":"Criluz S.a.",
    "wof:placetype":"venue"
},
  "geometry": {"coordinates":[-4.4237828255,36.7158660889],"type":"Point"}
}