{
  "type": "Feature",
  "properties": {
    "addr:full":"Calle de Magdalena, 2 Vitoria-gasteiz \u00c1lava 01008",
    "addr:housenumber":"2",
    "addr:postcode":"01008",
    "addr:street":"Calle De Magdalena",
    "iso:country":"ES",
    "sg:address":"Calle de Magdalena, 2",
    "sg:city":"Vitoria-gasteiz",
    "sg:orig_category":"Agencias Y Asesores De Publicidad",
    "sg:phone":"+34 945 13 40 86",
    "sg:postcode":"01008",
    "sg:province":"\u00c1lava",
    "wof:name":"Alfaro Allona Juan Manuel",
    "wof:placetype":"venue"
},
  "geometry": {"coordinates":[-2.6769874096,42.8458175659],"type":"Point"}
}