{
  "type": "Feature",
  "properties": {
    "iso:country":"ES",
    "sg:address":"Ctra Menarguens, Km. 0001,5",
    "sg:city":"Albesa",
    "sg:orig_category":"Hormigonados",
    "sg:phone":"+34 973 18 67 01",
    "sg:postcode":"25135",
    "sg:province":"Lleida",
    "sg:website":"www.cemolins.es",
    "wof:name":"Promotora Mediterranea 2 S.a.",
    "wof:placetype":"venue"
},
  "geometry": {"coordinates":[0.6592000127,41.7513084412],"type":"Point"}
}