{
  "type": "Feature",
  "properties": {
    "addr:full":"Calle de Flor De Acebo, 4 Valladolid Valladolid 47012",
    "addr:housenumber":"4",
    "addr:postcode":"47012",
    "addr:street":"Calle De Flor De Acebo",
    "iso:country":"ES",
    "sg:address":"Calle de Flor De Acebo, 4",
    "sg:city":"Valladolid",
    "sg:orig_category":"Chapister\u00cda",
    "sg:phone":"+34 983 30 56 74",
    "sg:postcode":"47012",
    "sg:province":"Valladolid",
    "wof:name":"Talleres Tome-garfia S.l.",
    "wof:placetype":"venue"
},
  "geometry": {"coordinates":[-4.6939101219,41.6457901001],"type":"Point"}
}