{
  "type": "Feature",
  "properties": {
    "iso:country":"ES",
    "sg:address":"Calle de Torquemada, 10",
    "sg:city":"Madrid",
    "sg:orig_category":"Cl\u00cdnicas Dentales",
    "sg:phone":"+34 913 81 09 94",
    "sg:postcode":"28043",
    "sg:province":"Madrid",
    "wof:name":"Milane Diaz Norma Iris",
    "wof:placetype":"venue"
},
  "geometry": {"coordinates":[-3.6396861076,40.4659996033],"type":"Point"}
}