{
  "type": "Feature",
  "properties": {
    "iso:country":"ES",
    "sg:address":"Rua Santiago De Chile (de), 2",
    "sg:city":"Santiago De Compostela",
    "sg:orig_category":"Peluquer\u00cdas, Peluquer\u00cda Mixta",
    "sg:phone":"+34 981 59 72 69",
    "sg:postcode":"15706",
    "sg:province":"La Coru\u00f1a",
    "wof:name":"Fernandez Cambon Dorinda",
    "wof:placetype":"venue"
},
  "geometry": {"coordinates":[-8.5517015457,42.8734092712],"type":"Point"}
}