{
  "type": "Feature",
  "properties": {
    "addr:full":"Rua Progreso, 36 Mondo\u00f1edo Lugo 27740",
    "addr:housenumber":"36",
    "addr:postcode":"27740",
    "addr:street":"Rua Progreso",
    "iso:country":"ES",
    "sg:address":"Rua Progreso, 36",
    "sg:city":"Mondo\u00f1edo",
    "sg:orig_category":"Confecci\u00d3n (fabricaci\u00d3n, Al Por Mayor)",
    "sg:phone":"+34 982 52 18 53",
    "sg:postcode":"27740",
    "sg:province":"Lugo",
    "wof:name":"Diaz Diaz Jaime",
    "wof:placetype":"venue"
},
  "geometry": {"coordinates":[-7.3634691238,43.4284896851],"type":"Point"}
}