{
  "type": "Feature",
  "properties": {
    "addr:full":"Calle de Covadonga, 18 Castellon Castell\u00f3n 12004",
    "addr:housenumber":"18",
    "addr:postcode":"12004",
    "addr:street":"Calle De Covadonga",
    "iso:country":"ES",
    "sg:address":"Calle de Covadonga, 18",
    "sg:city":"Castellon",
    "sg:orig_category":"Centros Empresariales",
    "sg:phone":"+34 964 20 12 71",
    "sg:postcode":"12004",
    "sg:province":"Castell\u00f3n",
    "wof:name":"Tip-top Serveis C.b.",
    "wof:placetype":"venue"
},
  "geometry": {"coordinates":[-0.0257600006,40.0253791809],"type":"Point"}
}