{
  "type": "Feature",
  "properties": {
    "addr:full":"Av Mistral, 18 Barcelona Barcelona 08015",
    "addr:housenumber":"18",
    "addr:postcode":"08015",
    "addr:street":"Av Mistral",
    "iso:country":"ES",
    "sg:address":"Av Mistral, 18",
    "sg:city":"Barcelona",
    "sg:orig_category":"Institutos De Belleza",
    "sg:phone":"+34 934 26 50 21",
    "sg:postcode":"08015",
    "sg:province":"Barcelona",
    "wof:name":"Gonzalez Fernandez Clemente",
    "wof:placetype":"venue"
},
  "geometry": {"coordinates":[2.15812397,41.377281189],"type":"Point"}
}