{
  "type": "Feature",
  "properties": {
    "addr:full":"P Sarasate, 21 Iru\u00f1a Navarra 31001",
    "addr:housenumber":"21",
    "addr:postcode":"31001",
    "addr:street":"Sarasate",
    "iso:country":"ES",
    "sg:address":"P Sarasate, 21",
    "sg:city":"Iru\u00f1a",
    "sg:orig_category":"Tapiceros Y Tapiceros",
    "sg:phone":"+34 948 22 55 98",
    "sg:postcode":"31001",
    "sg:province":"Navarra",
    "wof:name":"Laspalas Cambra Andres",
    "wof:placetype":"venue"
},
  "geometry": {"coordinates":[-1.6432440281,42.8160362244],"type":"Point"}
}