{
  "type": "Feature",
  "properties": {
    "iso:country":"ES",
    "sg:address":"Carrer de Pi, 25",
    "sg:city":"S. Pere Ribes",
    "sg:orig_category":"Asociaciones, Organismos Culturales Y Socioeducativos",
    "sg:phone":"+34 938 96 12 00",
    "sg:postcode":"08810",
    "sg:province":"Barcelona",
    "wof:name":"Sociedad Recreativa Y Cultutal San Pedro De Ribas",
    "wof:placetype":"venue"
},
  "geometry": {"coordinates":[1.7736350298,41.262588501],"type":"Point"}
}