{
  "type": "Feature",
  "properties": {
    "addr:full":"Calle de Guadiana, 11 Almagro Ciudad Real 13270",
    "addr:housenumber":"11",
    "addr:postcode":"13270",
    "addr:street":"Calle De Guadiana",
    "iso:country":"ES",
    "sg:address":"Calle de Guadiana, 11",
    "sg:city":"Almagro",
    "sg:orig_category":"Agencias Y Agentes Comerciales, Representantes",
    "sg:phone":"+34 926 86 09 84",
    "sg:postcode":"13270",
    "sg:province":"Ciudad Real",
    "wof:name":"Gascon Bella Vicente",
    "wof:placetype":"venue"
},
  "geometry": {"coordinates":[-3.7178690434,38.891418457],"type":"Point"}
}