{
  "type": "Feature",
  "properties": {
    "addr:full":"Calle de Humilladero, 3 Estepa Sevilla 41560",
    "addr:housenumber":"3",
    "addr:postcode":"41560",
    "addr:street":"Calle De Humilladero;Sevilla",
    "iso:country":"ES",
    "sg:address":"Calle de Humilladero, 3",
    "sg:city":"Estepa",
    "sg:orig_category":"Electricidad, Electr\u00d3nica: Material Y Suministros (al Por Mayor)",
    "sg:phone":"+34 954 82 06 09",
    "sg:postcode":"41560",
    "sg:province":"Sevilla",
    "wof:name":"Hijos De Garcia Pineda S.l.",
    "wof:placetype":"venue"
},
  "geometry": {"coordinates":[-4.8806939125,37.2907562256],"type":"Point"}
}