{
  "type": "Feature",
  "properties": {
    "addr:full":"Calle de Padre Barea, 25 Paradas Sevilla 41610",
    "addr:housenumber":"25",
    "addr:postcode":"41610",
    "addr:street":"Calle De Padre Barea",
    "iso:country":"ES",
    "sg:address":"Calle de Padre Barea, 25",
    "sg:city":"Paradas",
    "sg:orig_category":"Fabricaci\u00d3n De Productos Textiles Sin Tejer",
    "sg:phone":"+34 954 84 90 56",
    "sg:postcode":"41610",
    "sg:province":"Sevilla",
    "wof:name":"Romero Nu\u00f1ez Jose Luis",
    "wof:placetype":"venue"
},
  "geometry": {"coordinates":[-5.4962592125,37.2896499634],"type":"Point"}
}