{
  "type": "Feature",
  "properties": {
    "addr:full":"Calle de Antonio Suarez, 29 Valencia Valencia 46021",
    "addr:housenumber":"29",
    "addr:postcode":"46021",
    "addr:street":"Calle De Antonio Suarez",
    "iso:country":"ES",
    "sg:address":"Calle de Antonio Suarez, 29",
    "sg:city":"Valencia",
    "sg:orig_category":"Empresas De Portes Y Mensajer\u00cda",
    "sg:phone":"+34 963 93 00 44",
    "sg:postcode":"46021",
    "sg:province":"Valencia",
    "wof:name":"Ave Fenix Mensajeros S.l.",
    "wof:placetype":"venue"
},
  "geometry": {"coordinates":[-0.3566730022,39.469959259],"type":"Point"}
}