{
  "type": "Feature",
  "properties": {
    "addr:full":"Calle de Ramon Y Cajal, 53 Santa Cruz De Tenerife Santa Cruz De Tenerife 38004",
    "addr:housenumber":"53",
    "addr:postcode":"38004",
    "addr:street":"Calle De Ramon Y Cajal",
    "iso:country":"ES",
    "sg:address":"Calle de Ramon Y Cajal, 53",
    "sg:city":"Santa Cruz De Tenerife",
    "sg:orig_category":"Agentes, Concesionarios Y Sucursales De Veh\u00cdculos",
    "sg:phone":"+34 922 15 22 76",
    "sg:postcode":"38004",
    "sg:province":"Santa Cruz De Tenerife",
    "wof:name":"Comercial De Automoviles Nacionales S.a.",
    "wof:placetype":"venue"
},
  "geometry": {"coordinates":[-16.2602176666,28.4665145874],"type":"Point"}
}