{
  "type": "Feature",
  "properties": {
    "iso:country":"ES",
    "sg:address":"Carrer de Cerdanya, 54",
    "sg:city":"Prat Llobregat",
    "sg:orig_category":"Fabricaci\u00d3n De Quesos",
    "sg:phone":"+34 933 70 43 58",
    "sg:postcode":"08820",
    "sg:province":"Barcelona",
    "sg:website":"www.quesosmanso.com",
    "wof:name":"Manso S.a.",
    "wof:placetype":"venue"
},
  "geometry": {"coordinates":[2.0877530575,41.3268203735],"type":"Point"}
}