{
  "type": "Feature",
  "properties": {
    "addr:full":"Calle de Larga, S/n Castellon De La Plana Castell\u00f3n 12005",
    "addr:housenumber":"s / n",
    "addr:postcode":"12005",
    "addr:street":"Calle De Larga",
    "iso:country":"ES",
    "sg:address":"Calle de Larga, S/n",
    "sg:city":"Castellon De La Plana",
    "sg:orig_category":"Sanatorios M\u00c9dico",
    "sg:phone":"+34 964 25 50 08",
    "sg:postcode":"12005",
    "sg:province":"Castell\u00f3n",
    "wof:name":"Generalitat Valenciana",
    "wof:placetype":"venue"
},
  "geometry": {"coordinates":[-0.0581840016,39.9568748474],"type":"Point"}
}