{
  "type": "Feature",
  "properties": {
    "iso:country":"ES",
    "sg:address":"Calle de Real, S/n",
    "sg:city":"Valdemaluque",
    "sg:orig_category":"Farmacias",
    "sg:phone":"+34 975 36 36 71",
    "sg:postcode":"42318",
    "sg:province":"Soria",
    "wof:name":"Dominguez Cruz Manuel",
    "wof:placetype":"venue"
},
  "geometry": {"coordinates":[-97.78224945069999,45.7040786743],"type":"Point"}
}