{
  "type": "Feature",
  "properties": {
    "iso:country":"ES",
    "sg:address":"Los Parrales, 121",
    "sg:city":"Parador Hortichuelas",
    "sg:orig_category":"Transportes Por V\u00cdas Navegables",
    "sg:phone":"+34 950 34 93 30",
    "sg:postcode":"04720",
    "sg:province":"Almer\u00eda",
    "wof:name":"Cargo Roquetas S.l.",
    "wof:placetype":"venue"
},
  "geometry": {"coordinates":[-2.5741510391,36.8138160706],"type":"Point"}
}