{
  "type": "Feature",
  "properties": {
    "iso:country":"ES",
    "sg:address":"Calle de General Sueiro, 3",
    "sg:city":"Zaragoza",
    "sg:orig_category":"Camiser\u00cda Y Ropa Interior Masculina (al Por Menor)",
    "sg:phone":"+34 976 21 82 85",
    "sg:postcode":"50008",
    "sg:province":"Zaragoza",
    "wof:name":"Mirave Udina Mercedes",
    "wof:placetype":"venue"
},
  "geometry": {"coordinates":[-0.8833069801,41.6466026306],"type":"Point"}
}