{
  "type": "Feature",
  "properties": {
    "addr:full":"Carrer de Francesc Fiol I Ju, 8 Palma Islas Baleares 07010",
    "addr:housenumber":"8",
    "addr:postcode":"07010",
    "addr:street":"Carrer De Francesc Fiol I Ju",
    "iso:country":"ES",
    "sg:address":"Carrer de Francesc Fiol I Ju, 8",
    "sg:city":"Palma",
    "sg:orig_category":"Bisuter\u00cda, Joyer\u00cda, Relojer\u00cda (al Por Menor)",
    "sg:phone":"+34 971 20 19 88",
    "sg:postcode":"07010",
    "sg:province":"Islas Baleares",
    "wof:name":"Sanchez Jensen Annette",
    "wof:placetype":"venue"
},
  "geometry": {"coordinates":[2.6502680779,39.5842514038],"type":"Point"}
}