{
  "type": "Feature",
  "properties": {
    "addr:full":"Carrer de Tuset, 10 Barcelona Barcelona 08006",
    "addr:housenumber":"10",
    "addr:postcode":"08006",
    "addr:street":"Carrer De Tuset",
    "iso:country":"ES",
    "sg:address":"Carrer de Tuset, 10",
    "sg:city":"Barcelona",
    "sg:orig_category":"Inmobiliaria (agencias)",
    "sg:phone":"+34 932 18 04 64",
    "sg:postcode":"08006",
    "sg:province":"Barcelona",
    "wof:name":"Simeon Fincas S.a.",
    "wof:placetype":"venue"
},
  "geometry": {"coordinates":[2.1527609825,41.3955574036],"type":"Point"}
}