{
  "type": "Feature",
  "properties": {
    "iso:country":"ES",
    "sg:address":"Plaz Antonio Moreda (de), 1",
    "sg:city":"Valdeolmos",
    "sg:orig_category":"Organizaci\u00d3n De Actos, Seminarios Y Congresos",
    "sg:phone":"+34 916 20 23 49",
    "sg:postcode":"28130",
    "sg:province":"Madrid",
    "wof:name":"Martin Moreda Javier",
    "wof:placetype":"venue"
},
  "geometry": {"coordinates":[-3.4548680782,40.6381759644],"type":"Point"}
}