{
  "type": "Feature",
  "properties": {
    "iso:country":"ES",
    "sg:address":"Calle de Doctor Facundo Tomas, 12",
    "sg:city":"Bu\u00f1ol",
    "sg:orig_category":"Alimentaci\u00d3n General (al Por Menor)",
    "sg:phone":"+34 962 50 24 47",
    "sg:postcode":"46360",
    "sg:province":"Valencia",
    "wof:name":"Alimentacion Ventas-layana S.l.",
    "wof:placetype":"venue"
},
  "geometry": {"coordinates":[-0.7901425958,39.424030304],"type":"Point"}
}