{
  "type": "Feature",
  "properties": {
    "addr:full":"Calle de Real, 30 Ubeda Ja\u00e9n 23400",
    "addr:housenumber":"30",
    "addr:postcode":"23400",
    "addr:street":"Calle De Real;Jae\u0301N",
    "iso:country":"ES",
    "sg:address":"Calle de Real, 30",
    "sg:city":"Ubeda",
    "sg:orig_category":"Farmacias",
    "sg:phone":"+34 953 75 03 90",
    "sg:postcode":"23400",
    "sg:province":"Ja\u00e9n",
    "wof:name":"Fuentes Miranda Antonio",
    "wof:placetype":"venue"
},
  "geometry": {"coordinates":[-3.3699378967,38.0102729797],"type":"Point"}
}