{
  "type": "Feature",
  "properties": {
    "addr:full":"Calle de Embajadores, 160 Madrid Madrid 28045",
    "addr:housenumber":"160",
    "addr:postcode":"28045",
    "addr:street":"Calle De Embajadores",
    "iso:country":"ES",
    "sg:address":"Calle de Embajadores, 160",
    "sg:city":"Madrid",
    "sg:orig_category":"Pescader\u00cdas (al Por Menor)",
    "sg:phone":"+34 914 73 16 74",
    "sg:postcode":"28045",
    "sg:province":"Madrid",
    "wof:name":"San Jose Monge Timoteo",
    "wof:placetype":"venue"
},
  "geometry": {"coordinates":[-3.6964859962,40.3964805603],"type":"Point"}
}