{
  "type": "Feature",
  "properties": {
    "addr:full":"Av Catalunya, 14 S. Adria Besos Barcelona 08930",
    "addr:housenumber":"14",
    "addr:postcode":"08930",
    "addr:street":"Av Catalunya;S. Adria Besos Barcelona",
    "iso:country":"ES",
    "sg:address":"Av Catalunya, 14",
    "sg:city":"S. Adria Besos",
    "sg:orig_category":"Ropa Para Caballeros (al Por Menor)",
    "sg:phone":"+34 934 62 12 40",
    "sg:postcode":"08930",
    "sg:province":"Barcelona",
    "wof:name":"Olba Serres Pedro",
    "wof:placetype":"venue"
},
  "geometry": {"coordinates":[2.2161839008,41.4319953918],"type":"Point"}
}