{
  "type": "Feature",
  "properties": {
    "iso:country":"ES",
    "sg:address":"Av Pais Valencia, 237",
    "sg:city":"Benissa",
    "sg:orig_category":"Restaurantes",
    "sg:phone":"+34 965 73 06 29",
    "sg:postcode":"03720",
    "sg:province":"Alicante",
    "wof:name":"Ivars Crespo Joaquin",
    "wof:placetype":"venue"
},
  "geometry": {"coordinates":[0.0456110016,38.7129859924],"type":"Point"}
}