{
  "type": "Feature",
  "properties": {
    "addr:full":"Calle de Capitan Herrera, 9 Brozas C\u00e1ceres 10950",
    "addr:housenumber":"9",
    "addr:postcode":"10950",
    "addr:street":"Calle De Capitan Herrera;Ca\u0301Ceres",
    "iso:country":"ES",
    "sg:address":"Calle de Capitan Herrera, 9",
    "sg:city":"Brozas",
    "sg:classifiers":[
        {
            "category":"Taxi",
            "type":"Transportation"
        }
    ],
    "sg:phone":"+34 927 39 51 37",
    "sg:postcode":"10950",
    "sg:province":"C\u00e1ceres",
    "wof:name":"Acedo Cilleros Fidel",
    "wof:placetype":"venue"
},
  "geometry": {"coordinates":[-6.7763285637,39.6106910706],"type":"Point"}
}