{
  "type": "Feature",
  "properties": {
    "iso:country":"ES",
    "sg:address":"Calle de Pelayo, 77",
    "sg:city":"San Vicente Del Raspeig-sant Vicent Del Raspeig",
    "sg:orig_category":"Pescader\u00cdas (al Por Menor)",
    "sg:phone":"+34 965 66 70 80",
    "sg:postcode":"03690",
    "sg:province":"Alicante",
    "wof:name":"Burgos Rodriguez Juan Francisco",
    "wof:placetype":"venue"
},
  "geometry": {"coordinates":[-0.5164390206,38.3961105347],"type":"Point"}
}