{
  "type": "Feature",
  "properties": {
    "iso:country":"ES",
    "sg:address":"Calle de Eusebio Navarro, 62",
    "sg:city":"Palmas De Gran Canaria",
    "sg:orig_category":"Venta, Alquiler De Instrumentos Y Accesorios De M\u00dasica",
    "sg:phone":"+34 928 38 03 88",
    "sg:postcode":"35003",
    "sg:province":"Las Palmas",
    "wof:name":"Rodriguez Redondo Victor",
    "wof:placetype":"venue"
},
  "geometry": {"coordinates":[-15.4215021133,28.1119213104],"type":"Point"}
}