{
  "type": "Feature",
  "properties": {
    "iso:country":"ES",
    "sg:address":"Calle de Blas Infante, 2",
    "sg:city":"Palacios Y Villafranca",
    "sg:orig_category":"Electrodom\u00c9sticos (al Por Menor)",
    "sg:phone":"+34 955 81 63 13",
    "sg:postcode":"41720",
    "sg:province":"Sevilla",
    "sg:website":"www.redelite.es",
    "wof:name":"Vali\u00f1o Alvarez Rafael",
    "wof:placetype":"venue"
},
  "geometry": {"coordinates":[-5.9240880013,37.1600227356],"type":"Point"}
}