{
  "type": "Feature",
  "properties": {
    "iso:country":"ES",
    "sg:address":"Plaz Santo Tomas, 13",
    "sg:city":"Malpartida De Corneja",
    "sg:orig_category":"Iglesia Cat\u00d3lica",
    "sg:phone":"+34 920 36 44 02",
    "sg:postcode":"05512",
    "sg:province":"\u00c1vila",
    "wof:name":"Parroquia De Santo Tomas Apostol",
    "wof:placetype":"venue"
},
  "geometry": {"coordinates":[-5.3485898972,40.5224609375],"type":"Point"}
}