{
  "type": "Feature",
  "properties": {
    "iso:country":"ES",
    "sg:address":"Ctra. Valencia, Km. 0011,0",
    "sg:city":"Cadrete",
    "sg:orig_category":"Estudios Y Construcci\u00d3n De Acuarios Y Viveros",
    "sg:phone":"+34 976 12 66 25",
    "sg:postcode":"50420",
    "sg:province":"Zaragoza",
    "wof:name":"Mu\u00f1oz Trullen Cipriano",
    "wof:placetype":"venue"
},
  "geometry": {"coordinates":[-0.9601830244,41.5556411743],"type":"Point"}
}