{
  "type": "Feature",
  "properties": {
    "addr:full":"Av Collserola, 35 Molins Rei Barcelona 08750",
    "addr:housenumber":"35",
    "addr:postcode":"08750",
    "addr:street":"Av Collserola;Barcelona",
    "iso:country":"ES",
    "sg:address":"Av Collserola, 35",
    "sg:city":"Molins Rei",
    "sg:orig_category":"Fabricaci\u00d3n De Moldes Y Modelos",
    "sg:phone":"+34 936 68 48 78",
    "sg:postcode":"08750",
    "sg:province":"Barcelona",
    "wof:name":"Moldes Visamol S.l.",
    "wof:placetype":"venue"
},
  "geometry": {"coordinates":[2.0201001167,41.4208488464],"type":"Point"}
}