{
  "type": "Feature",
  "properties": {
    "addr:full":"Ctra Tarragona-san Sebastian, Km. 0129,0 Binefar Huesca 22500",
    "addr:postcode":"22500",
    "addr:street":"Ctra Tarragona-San Sebastian Km. 0129,0",
    "iso:country":"ES",
    "sg:address":"Ctra Tarragona-san Sebastian, Km. 0129,0",
    "sg:city":"Binefar",
    "sg:orig_category":"Promotores Constructores",
    "sg:phone":"+34 974 43 09 12",
    "sg:postcode":"22500",
    "sg:province":"Huesca",
    "wof:name":"Caldereria Y Silos Metaga S.l.",
    "wof:placetype":"venue"
},
  "geometry": {"coordinates":[0.2927800119,41.8499412537],"type":"Point"}
}