{
  "type": "Feature",
  "properties": {
    "iso:country":"ES",
    "sg:address":"Carrer de Generalitat, 4",
    "sg:city":"Alcanar",
    "sg:orig_category":"Cajas De Ahorro",
    "sg:phone":"+34 977 73 00 35",
    "sg:postcode":"43530",
    "sg:province":"Tarragona",
    "sg:website":"www.lacaixa.es",
    "wof:name":"Caixa D'estalvis I Pensions De Barcelona",
    "wof:placetype":"venue"
},
  "geometry": {"coordinates":[0.481186986,40.5430030823],"type":"Point"}
}