{
  "type": "Feature",
  "properties": {
    "addr:full":"La Riva, S/n Puerto De Vega Asturias 33790",
    "addr:housenumber":"/ n",
    "addr:postcode":"33790",
    "addr:street":"Riva S",
    "iso:country":"ES",
    "sg:address":"La Riva, S/n",
    "sg:city":"Puerto De Vega",
    "sg:orig_category":"Pescader\u00cdas (al Por Menor)",
    "sg:phone":"+34 985 64 84 06",
    "sg:postcode":"33790",
    "sg:province":"Asturias",
    "wof:name":"Lanza Lanza Vicente",
    "wof:placetype":"venue"
},
  "geometry": {"coordinates":[-6.6467437744,43.5650634766],"type":"Point"}
}