{
  "type": "Feature",
  "properties": {
    "addr:full":"Calle de Andalucia, 17 Moguer Huelva 21800",
    "addr:housenumber":"17",
    "addr:postcode":"21800",
    "addr:street":"Calle De Andalucia",
    "iso:country":"ES",
    "sg:address":"Calle de Andalucia, 17",
    "sg:city":"Moguer",
    "sg:orig_category":"Teatros Y Salas De Espect\u00c1culos",
    "sg:phone":"+34 959 37 28 23",
    "sg:postcode":"21800",
    "sg:province":"Huelva",
    "wof:name":"Fundacion Municipal De Cultura",
    "wof:placetype":"venue"
},
  "geometry": {"coordinates":[-6.8402099609,37.2751235962],"type":"Point"}
}