{
  "type": "Feature",
  "properties": {
    "addr:full":"Calle de Cristo Del Refugio, 33 Castellar-oliveral Valencia 46026",
    "addr:housenumber":"33",
    "addr:postcode":"46026",
    "addr:street":"Calle De Cristo Del Refugio",
    "iso:country":"ES",
    "sg:address":"Calle de Cristo Del Refugio, 33",
    "sg:city":"Castellar-oliveral",
    "sg:classifiers":[
        {
            "category":"Personal",
            "subcategory":"Barber",
            "type":"Services"
        }
    ],
    "sg:phone":"+34 963 96 37 82",
    "sg:postcode":"46026",
    "sg:province":"Valencia",
    "sg:tags":[
        "caballeros",
        "de",
        "peluqueros"
    ],
    "wof:name":"Montoro Gimeno Juan Vicente",
    "wof:placetype":"venue"
},
  "geometry": {"coordinates":[-0.364207387,39.4255104065],"type":"Point"}
}