{
  "type": "Feature",
  "properties": {
    "addr:full":"Calle de Santa Maria, 22 Madrid Madrid 28014",
    "addr:housenumber":"22",
    "addr:postcode":"madrid;28014",
    "addr:street":"Calle De Santa Maria",
    "iso:country":"ES",
    "sg:address":"Calle de Santa Maria, 22",
    "sg:city":"Madrid",
    "sg:orig_category":"Agencias Y Agentes Comerciales, Representantes",
    "sg:phone":"+34 914 29 50 12",
    "sg:postcode":"28014",
    "sg:province":"Madrid",
    "wof:name":"Nu\u00f1ez Pe\u00f1a Francisco",
    "wof:placetype":"venue"
},
  "geometry": {"coordinates":[-3.697701931,40.4128875732],"type":"Point"}
}