{
  "type": "Feature",
  "properties": {
    "iso:country":"ES",
    "sg:address":"Carr Creu, 47",
    "sg:city":"Badalona",
    "sg:orig_category":"Inform\u00c1tica (estudios, Servicios, Asesor\u00cda, Formaci\u00d3n)",
    "sg:phone":"+34 934 64 02 25",
    "sg:postcode":"08912",
    "sg:province":"Barcelona",
    "sg:website":"www.6bdn.com",
    "wof:name":"6 Bdn S.l.",
    "wof:placetype":"venue"
},
  "geometry": {"coordinates":[2.244438,41.448727],"type":"Point"}
}