{
  "type": "Feature",
  "properties": {
    "addr:full":"Av J Ortega Y Gasset (mercamalaga), Km. 0007,0 Malaga M\u00e1laga 29196",
    "addr:postcode":"29196",
    "addr:street":"Av J Ortega Y Gasset Mercamalaga Km. 0007,0;Ma\u0301Laga",
    "iso:country":"ES",
    "sg:address":"Av J Ortega Y Gasset (mercamalaga), Km. 0007,0",
    "sg:city":"Malaga",
    "sg:orig_category":"Frutas Y Legumbres Frescas (al Por Mayor)",
    "sg:phone":"+34 952 17 90 19",
    "sg:postcode":"29196",
    "sg:province":"M\u00e1laga",
    "wof:name":"Andres Garcia Calderon E Hijos S.l.",
    "wof:placetype":"venue"
},
  "geometry": {"coordinates":[-4.5149121284,36.6967582703],"type":"Point"}
}