{
  "type": "Feature",
  "properties": {
    "addr:full":"Calle de Illescas, 5 Madrid Madrid 28024",
    "addr:housenumber":"5",
    "addr:postcode":"28024",
    "addr:street":"Calle De Illescas",
    "iso:country":"ES",
    "sg:address":"Calle de Illescas, 5",
    "sg:city":"Madrid",
    "sg:orig_category":"Abogados",
    "sg:phone":"+34 915 18 53 42",
    "sg:postcode":"28024",
    "sg:province":"Madrid",
    "wof:name":"Becerra Pascual Ana Isabel",
    "wof:placetype":"venue"
},
  "geometry": {"coordinates":[-3.7658998966,40.3972625732],"type":"Point"}
}