{
  "type": "Feature",
  "properties": {
    "iso:country":"ES",
    "sg:address":"Calle de Rio, 12",
    "sg:city":"Algarrobo",
    "sg:orig_category":"Centros De Educaci\u00d3n Especial",
    "sg:phone":"+34 952 55 28 63",
    "sg:postcode":"29750",
    "sg:province":"M\u00e1laga",
    "wof:name":"Junta De Andalucia",
    "wof:placetype":"venue"
},
  "geometry": {"coordinates":[-4.0368289948,36.7739486694],"type":"Point"}
}