{
  "type": "Feature",
  "properties": {
    "addr:full":"Pl Ponent (de), 2 Tarragona Tarragona 43001",
    "addr:postcode":"43001",
    "addr:street":"Pl Ponent De 2",
    "iso:country":"ES",
    "sg:address":"Pl Ponent (de), 2",
    "sg:city":"Tarragona",
    "sg:orig_category":"Ropa Para Se\u00d1oras (al Por Menor)",
    "sg:phone":"+34 977 22 47 17",
    "sg:postcode":"43001",
    "sg:province":"Tarragona",
    "wof:name":"Montcusi Valldosera Maria Neus",
    "wof:placetype":"venue"
},
  "geometry": {"coordinates":[1.2473189831,41.1145553589],"type":"Point"}
}