{
  "type": "Feature",
  "properties": {
    "iso:country":"ES",
    "sg:address":"El Pla, S/n",
    "sg:city":"Pol. Ind. Pla",
    "sg:orig_category":"Alumbrados",
    "sg:phone":"+34 961 24 03 13",
    "sg:postcode":"46290",
    "sg:province":"Valencia",
    "sg:website":"www.rogu.es",
    "wof:name":"H. Rogu S. L.",
    "wof:placetype":"venue"
},
  "geometry": {"coordinates":[-0.4453490078,39.3651695251],"type":"Point"}
}