{
  "type": "Feature",
  "properties": {
    "addr:full":"Calle de Tiepolo, 2 Torremolinos M\u00e1laga 29620",
    "addr:housenumber":"2",
    "addr:postcode":"29620",
    "addr:street":"Calle De Tiepolo;Ma\u0301Laga",
    "iso:country":"ES",
    "sg:address":"Calle de Tiepolo, 2",
    "sg:city":"Torremolinos",
    "sg:orig_category":"Reciclaje Y Tratamiento De Desechos Varios",
    "sg:phone":"+34 952 37 04 48",
    "sg:postcode":"29620",
    "sg:province":"M\u00e1laga",
    "wof:name":"Melwani  Anup Ramchand",
    "wof:placetype":"venue"
},
  "geometry": {"coordinates":[-4.500770092,36.6256027222],"type":"Point"}
}