{
  "type": "Feature",
  "properties": {
    "iso:country":"ES",
    "sg:address":"Energia (pol Ind La Drecera), S/n",
    "sg:city":"Selva Del Camp",
    "sg:orig_category":"Producci\u00d3n De Cart\u00d3n",
    "sg:phone":"+34 977 84 49 04",
    "sg:postcode":"43470",
    "sg:province":"Tarragona",
    "wof:name":"Avicarton S.l.",
    "wof:placetype":"venue"
},
  "geometry": {"coordinates":[1.1257082224,41.2050590515],"type":"Point"}
}