{
  "type": "Feature",
  "properties": {
    "addr:full":"Avda Constitucion, 20 Hernan-perez C\u00e1ceres 10868",
    "addr:housenumber":"20",
    "addr:postcode":"10868",
    "addr:street":"Avda Constitucion;Ca\u0301Ceres",
    "iso:country":"ES",
    "sg:address":"Avda Constitucion, 20",
    "sg:city":"Hernan-perez",
    "sg:orig_category":"Hoteles",
    "sg:phone":"+34 927 44 51 32",
    "sg:postcode":"10868",
    "sg:province":"C\u00e1ceres",
    "wof:name":"Benito Gonzalez Felipe",
    "wof:placetype":"venue"
},
  "geometry": {"coordinates":[-6.4653968811,40.2127037048],"type":"Point"}
}