{
  "type": "Feature",
  "properties": {
    "iso:country":"ES",
    "sg:address":"Calle de Valencia, S/n",
    "sg:city":"Dolores",
    "sg:orig_category":"Empresas De Carpinter\u00cda De Madera",
    "sg:phone":"+34 966 71 14 90",
    "sg:postcode":"03150",
    "sg:province":"Alicante",
    "wof:name":"Vieli C.b.",
    "wof:placetype":"venue"
},
  "geometry": {"coordinates":[-0.7699540257,38.1424064636],"type":"Point"}
}