{
  "type": "Feature",
  "properties": {
    "iso:country":"ES",
    "sg:address":"Avda Alcalde Francisco Gomez, S/n",
    "sg:city":"Salda\u00f1a",
    "sg:orig_category":"Ense\u00d1anza Secundaria: Colegios Y Escuelas Privadas",
    "sg:phone":"+34 979 89 06 90",
    "sg:postcode":"34100",
    "sg:province":"Palencia",
    "wof:name":"Instituto De Educacion Secundaria De Salda\u00d1a",
    "wof:placetype":"venue"
},
  "geometry": {"coordinates":[-4.7338600159,42.5220756531],"type":"Point"}
}