{
  "type": "Feature",
  "properties": {
    "addr:full":"Avda Juan Luis Peralta, 22 Benalmadena M\u00e1laga 29639",
    "addr:housenumber":"22",
    "addr:postcode":"29639",
    "addr:street":"Avda Juan Luis Peralta",
    "iso:country":"ES",
    "sg:address":"Avda Juan Luis Peralta, 22",
    "sg:city":"Benalmadena",
    "sg:orig_category":"Inmobiliaria (agencias)",
    "sg:phone":"+34 952 56 84 97",
    "sg:postcode":"29639",
    "sg:province":"M\u00e1laga",
    "wof:name":"Alros Investiments S.l.",
    "wof:placetype":"venue"
},
  "geometry": {"coordinates":[-4.5701098442,36.5985374451],"type":"Point"}
}