{
  "type": "Feature",
  "properties": {
    "addr:full":"Avgd De Jacinto Benavente, 25 Benicarlo Castell\u00f3n 12580",
    "addr:housenumber":"25",
    "addr:postcode":"12580",
    "addr:street":"Benavente",
    "iso:country":"ES",
    "sg:address":"Avgd De Jacinto Benavente, 25",
    "sg:city":"Benicarlo",
    "sg:orig_category":"Comercio, Reparaci\u00d3n De Motocicletas, Bicicletas Y Piezas Sueltas",
    "sg:phone":"+34 964 47 11 05",
    "sg:postcode":"12580",
    "sg:province":"Castell\u00f3n",
    "wof:name":"Fores Motos Blo C.b.",
    "wof:placetype":"venue"
},
  "geometry": {"coordinates":[0.4042100012,40.4457893372],"type":"Point"}
}