{
  "type": "Feature",
  "properties": {
    "iso:country":"ES",
    "sg:address":"Calle de Nicomedes Pastor Diaz, 1",
    "sg:city":"Coru\u00d1a",
    "sg:orig_category":"Arreglo, Reparaci\u00d3n, Piezas Sueltas De Televisi\u00d3n, V\u00cddeo, Hi",
    "sg:phone":"+34 981 29 87 19",
    "sg:postcode":"15006",
    "sg:province":"La Coru\u00f1a",
    "wof:name":"Rabu\u00f1al Cedeira Jose Maria",
    "wof:placetype":"venue"
},
  "geometry": {"coordinates":[-8.4000988007,43.3564414978],"type":"Point"}
}