{
  "type": "Feature",
  "properties": {
    "iso:country":"ES",
    "sg:address":"Plaz Aurora (de La), 3",
    "sg:city":"Montilla",
    "sg:orig_category":"Plomeros",
    "sg:phone":"+34 957 65 04 77",
    "sg:postcode":"14550",
    "sg:province":"C\u00f3rdoba",
    "wof:name":"Hermanos Fernandez Cordoba S.l.",
    "wof:placetype":"venue"
},
  "geometry": {"coordinates":[-4.6465201378,37.5809631348],"type":"Point"}
}