{
  "type": "Feature",
  "properties": {
    "iso:country":"ES",
    "sg:address":"Ptda L'ambarsa, S/n",
    "sg:city":"Ador",
    "sg:orig_category":"Producci\u00d3n De Huevos",
    "sg:phone":"+34 962 80 84 48",
    "sg:postcode":"46724",
    "sg:province":"Valencia",
    "wof:name":"Dulgandia S.l.",
    "wof:placetype":"venue"
},
  "geometry": {"coordinates":[-0.2230300009,38.9214286804],"type":"Point"}
}