{
  "type": "Feature",
  "properties": {
    "addr:full":"Carrer de Comte Borrell, 30 Barcelona Barcelona 08015",
    "addr:housenumber":"30",
    "addr:postcode":"08015",
    "addr:street":"Carrer De Comte Borrell",
    "iso:country":"ES",
    "sg:address":"Carrer de Comte Borrell, 30",
    "sg:city":"Barcelona",
    "sg:orig_category":"Carnicer\u00cdas, Carnicer\u00cdas",
    "sg:phone":"+34 934 41 33 95",
    "sg:postcode":"08015",
    "sg:province":"Barcelona",
    "wof:name":"Fernandez Alvarez Modesto",
    "wof:placetype":"venue"
},
  "geometry": {"coordinates":[2.1636819839,41.3767776489],"type":"Point"}
}