{
  "type": "Feature",
  "properties": {
    "iso:country":"ES",
    "sg:address":"Carrer de Llibertat, 10",
    "sg:city":"S. Boi Llobregat",
    "sg:orig_category":"Fisioterapia",
    "sg:phone":"+34 936 40 07 21",
    "sg:postcode":"08830",
    "sg:province":"Barcelona",
    "wof:name":"Hernandez Monfort Luis",
    "wof:placetype":"venue"
},
  "geometry": {"coordinates":[2.0313439369,41.3469657898],"type":"Point"}
}