{
  "type": "Feature",
  "properties": {
    "addr:full":"Carrer de Joan De Peguera, 69 Barcelona Barcelona 08026",
    "addr:housenumber":"69",
    "addr:postcode":"08026",
    "addr:street":"Carrer De Joan De Peguera",
    "iso:country":"ES",
    "sg:address":"Carrer de Joan De Peguera, 69",
    "sg:city":"Barcelona",
    "sg:orig_category":"Chapister\u00cda",
    "sg:phone":"+34 934 56 47 73",
    "sg:postcode":"08026",
    "sg:province":"Barcelona",
    "wof:name":"Cancho Cancho Calixto",
    "wof:placetype":"venue"
},
  "geometry": {"coordinates":[2.1823379993,41.4142532349],"type":"Point"}
}