{
  "type": "Feature",
  "properties": {
    "iso:country":"ES",
    "sg:address":"La Figuera, 2",
    "sg:city":"Barrio San Ramon",
    "sg:orig_category":"Inform\u00c1tica (estudios, Servicios, Asesor\u00cda, Formaci\u00d3n)",
    "sg:phone":"+34 961 23 06 05",
    "sg:postcode":"46220",
    "sg:province":"Valencia",
    "wof:name":"Amigo Li\u00f1ana Dolores",
    "wof:placetype":"venue"
},
  "geometry": {"coordinates":[-0.4722138047,39.386013031],"type":"Point"}
}