{
  "type": "Feature",
  "properties": {
    "addr:full":"Calle de Julian Calderon Moreno, 120 Villanueva Serena Badajoz 06700",
    "addr:housenumber":"120",
    "addr:postcode":"06700",
    "addr:street":"Calle De Julian Calderon Moreno",
    "iso:country":"ES",
    "sg:address":"Calle de Julian Calderon Moreno, 120",
    "sg:city":"Villanueva Serena",
    "sg:orig_category":"Metalurgia",
    "sg:phone":"+34 924 84 40 15",
    "sg:postcode":"06700",
    "sg:province":"Badajoz",
    "wof:name":"Jara Centeno Francisco",
    "wof:placetype":"venue"
},
  "geometry": {"coordinates":[-5.7911911011,38.9812011719],"type":"Point"}
}