{
  "type": "Feature",
  "properties": {
    "addr:full":"Poli Industrial, 10 Dos-torres C\u00f3rdoba 14460",
    "addr:housenumber":"10",
    "addr:postcode":"14460",
    "addr:street":"Dos-Torres Co\u0301Rdoba",
    "iso:country":"ES",
    "sg:address":"Poli Industrial, 10",
    "sg:city":"Dos-torres",
    "sg:orig_category":"M\u00c1rmoles, Granitos Y Piedras Naturales",
    "sg:phone":"+34 957 13 42 46",
    "sg:postcode":"14460",
    "sg:province":"C\u00f3rdoba",
    "wof:name":"Marmoles Y Granitos Del Valle,s.c.a.",
    "wof:placetype":"venue"
},
  "geometry": {"coordinates":[-4.8991341591,38.4452056885],"type":"Point"}
}