{
  "type": "Feature",
  "properties": {
    "addr:full":"Carrer de Bruguera, 268 Calella Barcelona 08370",
    "addr:housenumber":"268",
    "addr:postcode":"08370",
    "addr:street":"Carrer De Bruguera",
    "iso:country":"ES",
    "sg:address":"Carrer de Bruguera, 268",
    "sg:city":"Calella",
    "sg:orig_category":"Comercio, Reparaci\u00d3n De Motocicletas, Bicicletas Y Piezas Sueltas",
    "sg:phone":"+34 937 69 55 99",
    "sg:postcode":"08370",
    "sg:province":"Barcelona",
    "wof:name":"Roura Cano Xavier",
    "wof:placetype":"venue"
},
  "geometry": {"coordinates":[2.6670498848,41.6169776917],"type":"Point"}
}