{
  "type": "Feature",
  "properties": {
    "iso:country":"ES",
    "sg:address":"Carrer de Escudellers, 48",
    "sg:city":"Barcelona",
    "sg:orig_category":"Comercio, Reparaci\u00d3n De Bicicletas, De Motocicletas, De Accesorios",
    "sg:phone":"+34 933 01 36 12",
    "sg:postcode":"08002",
    "sg:province":"Barcelona",
    "sg:website":"www.bikerentalbarcelona.com",
    "wof:name":"Mikes Bike Tours S.l.",
    "wof:placetype":"venue"
},
  "geometry": {"coordinates":[2.1775050163,41.3802680969],"type":"Point"}
}