{
  "type": "Feature",
  "properties": {
    "iso:country":"ES",
    "sg:address":"Avda Pablo Gargallo, 15",
    "sg:city":"Zaragoza",
    "sg:orig_category":"Asesor\u00cda De Formaci\u00d3n Y Gesti\u00d3n De Personal",
    "sg:phone":"+34 976 28 47 83",
    "sg:postcode":"50003",
    "sg:province":"Zaragoza",
    "wof:name":"Serrano Y Capape Sl",
    "wof:placetype":"venue"
},
  "geometry": {"coordinates":[-0.897349,41.660369873],"type":"Point"}
}