{
  "type": "Feature",
  "properties": {
    "iso:country":"ES",
    "sg:address":"Calle de San Roman, 5",
    "sg:city":"Cirauqui",
    "sg:orig_category":"Cr\u00cda De Animales",
    "sg:phone":"+34 948 34 20 13",
    "sg:postcode":"31131",
    "sg:province":"Navarra",
    "wof:name":"Goldaraz Nagore Aurelio",
    "wof:placetype":"venue"
},
  "geometry": {"coordinates":[-1.8914289474,42.6753730774],"type":"Point"}
}