{
  "type": "Feature",
  "properties": {
    "addr:full":"Rua Seixalbo (de), S/n Seixalbo Ourense 32970",
    "addr:postcode":"32970",
    "addr:street":"Rua Seixalbo De S / N",
    "iso:country":"ES",
    "sg:address":"Rua Seixalbo (de), S/n",
    "sg:city":"Seixalbo",
    "sg:orig_category":"Centros De Educaci\u00d3n Especial",
    "sg:phone":"+34 988 23 70 00",
    "sg:postcode":"32970",
    "sg:province":"Ourense",
    "wof:name":"Colexio Publico De E.x.b. De Seixalbo",
    "wof:placetype":"venue"
},
  "geometry": {"coordinates":[-7.8547267914,42.3026542664],"type":"Point"}
}