{
  "type": "Feature",
  "properties": {
    "iso:country":"ES",
    "sg:address":"Carr President Macia, 137",
    "sg:city":"Palamos",
    "sg:orig_category":"Peluqueros: De Se\u00d1oras",
    "sg:phone":"+34 972 31 54 34",
    "sg:postcode":"17230",
    "sg:province":"Girona",
    "wof:name":"Hidalgo Gomez Inmaculada",
    "wof:placetype":"venue"
},
  "geometry": {"coordinates":[3.1208000183,41.8500099182],"type":"Point"}
}