{
  "type": "Feature",
  "properties": {
    "iso:country":"ES",
    "sg:address":"Crril. Salazar, S/n",
    "sg:city":"Llano De Brujas",
    "sg:orig_category":"Asociaciones Y Clubs Deportivos",
    "sg:phone":"+34 968 30 43 70",
    "sg:postcode":"30161",
    "sg:province":"Murcia",
    "wof:name":"Madrid Garcia Roland",
    "wof:placetype":"venue"
},
  "geometry": {"coordinates":[-1.0709140301,38.0056495667],"type":"Point"}
}