{
  "type": "Feature",
  "properties": {
    "iso:country":"ES",
    "sg:address":"Gregorio Mara\u00f1on(p I Las Teresas), 12",
    "sg:city":"Yecla",
    "sg:orig_category":"Muebles",
    "sg:phone":"+34 968 75 21 58",
    "sg:postcode":"30510",
    "sg:province":"Murcia",
    "sg:website":"www.tapizadosdomingo.com",
    "wof:name":"Tapizados Domingo S.l.",
    "wof:placetype":"venue"
},
  "geometry": {"coordinates":[-1.0750370026,38.6200256348],"type":"Point"}
}