{
  "type": "Feature",
  "properties": {
    "addr:full":"Calle de Dehesa De Mari-martin, 41 Dehesa De Marimartin Madrid 28600",
    "addr:housenumber":"41",
    "addr:postcode":"28600",
    "addr:street":"Calle De Dehesa;Mari-Martin",
    "iso:country":"ES",
    "sg:address":"Calle de Dehesa De Mari-martin, 41",
    "sg:city":"Dehesa De Marimartin",
    "sg:orig_category":"Maquinaria Para Industrias Diversas",
    "sg:phone":"+34 918 10 10 30",
    "sg:postcode":"28600",
    "sg:province":"Madrid",
    "sg:website":"www.langaindustrial.es",
    "wof:name":"Langa Industrial S.a.",
    "wof:placetype":"venue"
},
  "geometry": {"coordinates":[-3.7003455162,40.4166908264],"type":"Point"}
}