{
  "type": "Feature",
  "properties": {
    "iso:country":"ES",
    "sg:address":"Av Catalunya, 26",
    "sg:city":"Blanes",
    "sg:orig_category":"Carnicer\u00cdas, Carnicer\u00cdas",
    "sg:phone":"+34 972 33 27 20",
    "sg:postcode":"17300",
    "sg:province":"Girona",
    "wof:name":"Fernandez Aranda Carmen",
    "wof:placetype":"venue"
},
  "geometry": {"coordinates":[2.7754120827,41.6667518616],"type":"Point"}
}