{
  "type": "Feature",
  "properties": {
    "addr:full":"Velazquez, 99 Madrid Madrid 28006",
    "addr:housenumber":"99",
    "addr:postcode":"madrid;28006",
    "addr:street":"Velazquez",
    "iso:country":"ES",
    "sg:address":"Velazquez, 99",
    "sg:city":"Madrid",
    "sg:orig_category":"Bancos",
    "sg:phone":"+34 915 63 91 17",
    "sg:postcode":"28006",
    "sg:province":"Madrid",
    "sg:website":"www.bancopopular-e.com",
    "wof:name":"Banco Popular E.com",
    "wof:placetype":"venue"
},
  "geometry": {"coordinates":[-3.6834490299,40.4353179932],"type":"Point"}
}