{
  "type": "Feature",
  "properties": {
    "iso:country":"ES",
    "sg:address":"Carrer de Banys, 19",
    "sg:city":"Garriga",
    "sg:orig_category":"Administradores De Bienes Y Delegados De Comunidades De Propietarios",
    "sg:phone":"+34 938 41 81 55",
    "sg:postcode":"08530",
    "sg:province":"Barcelona",
    "wof:name":"Olle Bufi Joan",
    "wof:placetype":"venue"
},
  "geometry": {"coordinates":[2.2859430313,41.6838684082],"type":"Point"}
}