{
  "type": "Feature",
  "properties": {
    "addr:full":"Urb. Bau-hoffman, S/n Torrox-costa M\u00e1laga 29793",
    "addr:housenumber":"s",
    "addr:postcode":"29793",
    "addr:street":"/ N Torrox-Costa Ma\u0301Laga",
    "iso:country":"ES",
    "sg:address":"Urb. Bau-hoffman, S/n",
    "sg:city":"Torrox-costa",
    "sg:orig_category":"Molduras, Junquillos, Listones Y Molduras Perforadas",
    "sg:phone":"+34 952 53 08 80",
    "sg:postcode":"29793",
    "sg:province":"M\u00e1laga",
    "wof:name":"Luque Fernandez Francisco",
    "wof:placetype":"venue"
},
  "geometry": {"coordinates":[-3.9456365108,36.7326087952],"type":"Point"}
}