{
  "type": "Feature",
  "properties": {
    "iso:country":"ES",
    "sg:address":"Carrer de Cap Norfeu, 65",
    "sg:city":"Roses",
    "sg:orig_category":"Promotores Constructores",
    "sg:phone":"+34 972 25 73 92",
    "sg:postcode":"17480",
    "sg:province":"Girona",
    "wof:name":"Draser C. R. Obras Maritimas S.l.",
    "wof:placetype":"venue"
},
  "geometry": {"coordinates":[3.1825749874,42.2592658997],"type":"Point"}
}