{
  "type": "Feature",
  "properties": {
    "iso:country":"ES",
    "sg:address":"Calle de Eulalia Gil, 5",
    "sg:city":"Madrid",
    "sg:orig_category":"Tiendas De Grano, Frutas Y Legumbres Secas (al Por Menor)",
    "sg:phone":"+34 914 61 80 89",
    "sg:postcode":"28025",
    "sg:province":"Madrid",
    "wof:name":"Yin  Yanna",
    "wof:placetype":"venue"
},
  "geometry": {"coordinates":[-3.7421629429,40.385635376],"type":"Point"}
}