{
  "type": "Feature",
  "properties": {
    "iso:country":"ES",
    "sg:address":"Avda San Jose, 166",
    "sg:city":"Zaragoza",
    "sg:orig_category":"Confecci\u00d3n De Trajes Para Se\u00d1oras",
    "sg:phone":"+34 976 27 74 17",
    "sg:postcode":"50007",
    "sg:province":"Zaragoza",
    "wof:name":"Manero Sangros Jose Luis",
    "wof:placetype":"venue"
},
  "geometry": {"coordinates":[-0.8785039783,41.6363334656],"type":"Point"}
}