{
  "type": "Feature",
  "properties": {
    "iso:country":"ES",
    "sg:address":"Av Sant Esteve, 1",
    "sg:city":"Castellar Valles",
    "sg:orig_category":"Centros Empresariales",
    "sg:phone":"+34 937 14 57 16",
    "sg:postcode":"08211",
    "sg:province":"Barcelona",
    "wof:name":"Alemany Associats Professionals S.l.",
    "wof:placetype":"venue"
},
  "geometry": {"coordinates":[2.0864953995,41.6129264832],"type":"Point"}
}