{
  "type": "Feature",
  "properties": {
    "iso:country":"ES",
    "sg:address":"Urb. Las Adelfas, S/n",
    "sg:city":"San Pedro Alcantara",
    "sg:orig_category":"Agencias Y Agentes Comerciales, Representantes",
    "sg:phone":"+34 952 92 70 49",
    "sg:postcode":"29670",
    "sg:province":"M\u00e1laga",
    "wof:name":"Tejon Martinez Manuel",
    "wof:placetype":"venue"
},
  "geometry": {"coordinates":[-4.9902391434,36.4866333008],"type":"Point"}
}