{
  "type": "Feature",
  "properties": {
    "iso:country":"ES",
    "sg:address":"Ctr De Navalpino, 120",
    "sg:city":"Piedrabuena",
    "sg:orig_category":"Negocio De Materiales De Construcci\u00d3n",
    "sg:phone":"+34 926 76 01 81",
    "sg:postcode":"13100",
    "sg:province":"Ciudad Real",
    "wof:name":"Fernandez Paton Emilio",
    "wof:placetype":"venue"
},
  "geometry": {"coordinates":[-4.1716189384,39.0333557129],"type":"Point"}
}