{
  "type": "Feature",
  "properties": {
    "addr:full":"Avda Alcazar, 20 Herencia Ciudad Real 13640",
    "addr:housenumber":"20",
    "addr:postcode":"13640",
    "addr:street":"Avda Alcazar",
    "iso:country":"ES",
    "sg:address":"Avda Alcazar, 20",
    "sg:city":"Herencia",
    "sg:orig_category":"Comercio De Carburantes",
    "sg:phone":"+34 926 57 33 83",
    "sg:postcode":"13640",
    "sg:province":"Ciudad Real",
    "wof:name":"Bujan Bola\u00f1os Jose Maria",
    "wof:placetype":"venue"
},
  "geometry": {"coordinates":[-3.3525490761,39.3694114685],"type":"Point"}
}