{
  "type": "Feature",
  "properties": {
    "addr:full":"Calle de San Pedro, 2 Tias Las Palmas 35572",
    "addr:housenumber":"2",
    "addr:postcode":"35572",
    "addr:street":"Calle De San Pedro",
    "iso:country":"ES",
    "sg:address":"Calle de San Pedro, 2",
    "sg:city":"Tias",
    "sg:orig_category":"Higiene, Belleza: Art\u00cdculos (al Por Menor)",
    "sg:phone":"+34 928 83 44 11",
    "sg:postcode":"35572",
    "sg:province":"Las Palmas",
    "wof:name":"Santana De La Fe Marco Aurelio",
    "wof:placetype":"venue"
},
  "geometry": {"coordinates":[-13.6556987762,28.9547538757],"type":"Point"}
}