{
  "type": "Feature",
  "properties": {
    "iso:country":"ES",
    "sg:address":"Avda Jose Izquierdo, 61",
    "sg:city":"Alquerias Del Ni\u00e7o Perdido",
    "sg:orig_category":"Instalaci\u00d3n De Sanitarios",
    "sg:phone":"+34 964 51 36 05",
    "sg:postcode":"12539",
    "sg:province":"Castell\u00f3n",
    "sg:website":"www.hidromoles.com",
    "wof:name":"Hidromasajes Castellon S.l",
    "wof:placetype":"venue"
},
  "geometry": {"coordinates":[-0.1214139983,39.8971862793],"type":"Point"}
}