{
  "type": "Feature",
  "properties": {
    "addr:full":"Calle de Santa Maria, 22 Cacabelos Le\u00f3n 24540",
    "addr:housenumber":"22",
    "addr:postcode":"24540",
    "addr:street":"Calle De Santa Maria",
    "iso:country":"ES",
    "sg:address":"Calle de Santa Maria, 22",
    "sg:city":"Cacabelos",
    "sg:orig_category":"Reposter\u00cdas",
    "sg:phone":"+34 987 54 71 58",
    "sg:postcode":"24540",
    "sg:province":"Le\u00f3n",
    "wof:name":"Prado Garcia Lisardo",
    "wof:placetype":"venue"
},
  "geometry": {"coordinates":[-6.7222590446,42.5996894836],"type":"Point"}
}