{
  "type": "Feature",
  "properties": {
    "iso:country":"ES",
    "sg:address":"Plaz Espa\u00d1a, 3",
    "sg:city":"Castell De Ferro",
    "sg:orig_category":"Bazares, Art\u00cdculos De Limpieza Y De Cocina (al Por Menor)",
    "sg:phone":"+34 958 65 61 80",
    "sg:postcode":"18740",
    "sg:province":"Granada",
    "wof:name":"Serrano Alonso Faustino",
    "wof:placetype":"venue"
},
  "geometry": {"coordinates":[-3.3561279774,36.7243499756],"type":"Point"}
}