{
  "type": "Feature",
  "properties": {
    "addr:full":"Avda Aragon, 41 Binefar Huesca 22500",
    "addr:housenumber":"41",
    "addr:postcode":"22500",
    "addr:street":"Avda Aragon",
    "iso:country":"ES",
    "sg:address":"Avda Aragon, 41",
    "sg:city":"Binefar",
    "sg:orig_category":"Librer\u00cdas",
    "sg:phone":"+34 974 42 86 29",
    "sg:postcode":"22500",
    "sg:province":"Huesca",
    "sg:website":"www.casapuyol.com",
    "wof:name":"Puyol Amello Maria Del Carmen",
    "wof:placetype":"venue"
},
  "geometry": {"coordinates":[0.2949700058,41.8488006592],"type":"Point"}
}