{
  "type": "Feature",
  "properties": {
    "addr:full":"Cerdelo, S/n Muniferral La Coru\u00f1a 15317",
    "addr:postcode":"15317",
    "addr:street":"Cerdelo S / N Muniferral La Corun\u0303A",
    "iso:country":"ES",
    "sg:address":"Cerdelo, S/n",
    "sg:city":"Muniferral",
    "sg:orig_category":"Fabricaci\u00d3n De Quesos",
    "sg:phone":"+34 981 78 93 03",
    "sg:postcode":"15317",
    "sg:province":"La Coru\u00f1a",
    "wof:name":"Arquega Sociedad Cooperativa Limitada",
    "wof:placetype":"venue"
},
  "geometry": {"coordinates":[-8.3959693909,43.3714904785],"type":"Point"}
}