{
  "type": "Feature",
  "properties": {
    "iso:country":"ES",
    "sg:address":"Calle de Beato Tomas De Zumarraga, 27 A",
    "sg:city":"Vitoria-gasteiz",
    "sg:orig_category":"Ense\u00d1anza Variada",
    "sg:phone":"+34 945 24 69 22",
    "sg:postcode":"01008",
    "sg:province":"\u00c1lava",
    "wof:name":"Maria Jesus Bermudez Olano",
    "wof:placetype":"venue"
},
  "geometry": {"coordinates":[-2.6841642857,42.8505554199],"type":"Point"}
}