{
  "type": "Feature",
  "properties": {
    "iso:country":"ES",
    "sg:address":"Calle de Poeta Aurea Galindo, 1",
    "sg:city":"Malaga",
    "sg:orig_category":"Inmobiliaria (agencias)",
    "sg:phone":"+34 952 20 37 56",
    "sg:postcode":"29016",
    "sg:province":"M\u00e1laga",
    "wof:name":"Merav Iberica Inversiones S.l.",
    "wof:placetype":"venue"
},
  "geometry": {"coordinates":[-4.4070591927,36.7463569641],"type":"Point"}
}