{
  "type": "Feature",
  "properties": {
    "iso:country":"ES",
    "sg:address":"Carr Unic, S/n",
    "sg:city":"Estaon",
    "sg:orig_category":"Gu\u00cdas De Monta\u00d1a, Monitores De Esqu\u00cd, Acompa\u00d1antes En Monta\u00d1a",
    "sg:phone":"+34 973 62 32 87",
    "sg:postcode":"25572",
    "sg:province":"Lleida",
    "wof:name":"Ronquillo Alferez Saray",
    "wof:placetype":"venue"
},
  "geometry": {"coordinates":[1.2131580114,42.5763206482],"type":"Point"}
}