{
  "type": "Feature",
  "properties": {
    "addr:full":"Calle de Sierra Blanca, 24 Marbella M\u00e1laga 29600",
    "addr:housenumber":"24",
    "addr:postcode":"29600",
    "addr:street":"Calle De Sierra Blanca;Ma\u0301Laga",
    "iso:country":"ES",
    "sg:address":"Calle de Sierra Blanca, 24",
    "sg:city":"Marbella",
    "sg:orig_category":"Promotores Constructores",
    "sg:phone":"+34 952 85 71 20",
    "sg:postcode":"29600",
    "sg:province":"M\u00e1laga",
    "wof:name":"Marbella Property & Investiment S.l.",
    "wof:placetype":"venue"
},
  "geometry": {"coordinates":[-4.8900289536,36.50963974],"type":"Point"}
}