{
  "type": "Feature",
  "properties": {
    "addr:full":"Calle de Cirilo Amoros, 82 Valencia Valencia 46004",
    "addr:housenumber":"82",
    "addr:postcode":"46004",
    "addr:street":"Calle De Cirilo Amoros",
    "iso:country":"ES",
    "sg:address":"Calle de Cirilo Amoros, 82",
    "sg:city":"Valencia",
    "sg:orig_category":"Procuradores",
    "sg:phone":"+34 963 34 93 30",
    "sg:postcode":"46004",
    "sg:province":"Valencia",
    "wof:name":"Garcia Reyes Comino Antonio",
    "wof:placetype":"venue"
},
  "geometry": {"coordinates":[-0.3663820028,39.4694480896],"type":"Point"}
}