{
  "type": "Feature",
  "properties": {
    "iso:country":"ES",
    "sg:address":"Calle de Torremolinos, 46",
    "sg:city":"Churriana",
    "sg:classifiers":[
        {
            "category":"Autos & Motor Vehicles",
            "subcategory":"Automobile Sales",
            "type":"Retail Goods"
        }
    ],
    "sg:phone":"+34 952 62 32 81",
    "sg:postcode":"29140",
    "sg:province":"M\u00e1laga",
    "wof:name":"Autoescuela Nueva Paz S.l.",
    "wof:placetype":"venue"
},
  "geometry": {"coordinates":[-4.5041055679,36.6654624939],"type":"Point"}
}