{
  "type": "Feature",
  "properties": {
    "addr:full":"Calle de Mu\u00d1oz De Sepulveda, 35 Pozoblanco C\u00f3rdoba 14400",
    "addr:housenumber":"35",
    "addr:postcode":"14400",
    "addr:street":"Calle De Mun\u0303Oz De Sepulveda",
    "iso:country":"ES",
    "sg:address":"Calle de Mu\u00d1oz De Sepulveda, 35",
    "sg:city":"Pozoblanco",
    "sg:orig_category":"Muebles, Minoristas",
    "sg:phone":"+34 957 77 23 09",
    "sg:postcode":"14400",
    "sg:province":"C\u00f3rdoba",
    "wof:name":"Los Pa\u00f1eros S.l.",
    "wof:placetype":"venue"
},
  "geometry": {"coordinates":[-4.8507509232,38.3760604858],"type":"Point"}
}