{
  "type": "Feature",
  "properties": {
    "addr:full":"Plaz Primero De Mayo, 2 Burlada Navarra 31600",
    "addr:housenumber":"2",
    "addr:postcode":"31600",
    "addr:street":"Plaz Primero;Mayo",
    "iso:country":"ES",
    "sg:address":"Plaz Primero De Mayo, 2",
    "sg:city":"Burlada",
    "sg:orig_category":"Agentes, Concesionarios Y Sucursales De Veh\u00cdculos",
    "sg:phone":"+34 948 14 44 42",
    "sg:postcode":"31600",
    "sg:province":"Navarra",
    "wof:name":"Automoviles Zaray S.l.",
    "wof:placetype":"venue"
},
  "geometry": {"coordinates":[-1.620511055,42.8260650635],"type":"Point"}
}