{
  "type": "Feature",
  "properties": {
    "iso:country":"ES",
    "sg:address":"Carrer de Gomis, 20",
    "sg:city":"Barcelona",
    "sg:orig_category":"Tintorer\u00cdas, Limpieza En Seco",
    "sg:phone":"+34 934 17 67 94",
    "sg:postcode":"08023",
    "sg:province":"Barcelona",
    "wof:name":"Brugada Miquel Consuelo",
    "wof:placetype":"venue"
},
  "geometry": {"coordinates":[2.1428389549,41.4119300842],"type":"Point"}
}