{
  "type": "Feature",
  "properties": {
    "iso:country":"ES",
    "sg:address":"Carrer de Rossello, 298",
    "sg:city":"Barcelona",
    "sg:orig_category":"Cultos Diversos",
    "sg:phone":"+34 934 57 07 88",
    "sg:postcode":"08037",
    "sg:province":"Barcelona",
    "wof:name":"Centro Nagaryuna",
    "wof:placetype":"venue"
},
  "geometry": {"coordinates":[2.1667768955,41.4002685547],"type":"Point"}
}