{
  "type": "Feature",
  "properties": {
    "iso:country":"ES",
    "sg:address":"Avda Parador (del), 8",
    "sg:city":"Bailen",
    "sg:orig_category":"Lavado, Limpieza De Veh\u00cdculos",
    "sg:phone":"+34 953 67 16 62",
    "sg:postcode":"23710",
    "sg:province":"Ja\u00e9n",
    "wof:name":"Gomez Gamez Pedro",
    "wof:placetype":"venue"
},
  "geometry": {"coordinates":[-3.7710540295,38.0965309143],"type":"Point"}
}