{
  "type": "Feature",
  "properties": {
    "iso:country":"ES",
    "sg:address":"Calle de Alicante, 2",
    "sg:city":"Segorbe",
    "sg:classifiers":[
        {
            "category":"Personal",
            "subcategory":"Barber",
            "type":"Services"
        }
    ],
    "sg:phone":"+34 964 71 21 09",
    "sg:postcode":"12400",
    "sg:province":"Castell\u00f3n",
    "sg:tags":[
        "caballeros",
        "de",
        "peluqueros"
    ],
    "wof:name":"Devesa Torres Carlos",
    "wof:placetype":"venue"
},
  "geometry": {"coordinates":[-0.4878678024,39.849647522],"type":"Point"}
}