{
  "type": "Feature",
  "properties": {
    "iso:country":"ES",
    "sg:address":"Calle de Ronda De Gracia, 3",
    "sg:city":"Medina Campo",
    "sg:orig_category":"Asociaciones Humanitarias, De Cooperaci\u00d3n, De Acci\u00d3n Social",
    "sg:phone":"+34 983 80 12 42",
    "sg:postcode":"47400",
    "sg:province":"Valladolid",
    "wof:name":"Organizacion Nacional De Ciegos",
    "wof:placetype":"venue"
},
  "geometry": {"coordinates":[-4.913184166,41.3120155334],"type":"Point"}
}