{
  "type": "Feature",
  "properties": {
    "iso:country":"ES",
    "sg:address":"Anastasio Fdez Rivas, S/n",
    "sg:city":"Est. Linares-baeza",
    "sg:orig_category":"Sindicatos De Trabajadores",
    "sg:phone":"+34 953 60 15 34",
    "sg:postcode":"23490",
    "sg:province":"Ja\u00e9n",
    "wof:name":"Comisiones Obreras De Andalucia",
    "wof:placetype":"venue"
},
  "geometry": {"coordinates":[-3.5893540382,38.0692329407],"type":"Point"}
}