{
  "type": "Feature",
  "properties": {
    "iso:country":"ES",
    "sg:address":"Calle de Constantino, 6",
    "sg:city":"Ejido",
    "sg:orig_category":"Desinfecci\u00d3n, Desinsectaci\u00d3n, Desratizaci\u00d3n",
    "sg:phone":"+34 950 48 96 23",
    "sg:postcode":"04700",
    "sg:province":"Almer\u00eda",
    "sg:website":"www.legionellaprevencion.com",
    "wof:name":"Legionella Prevencion Y Control S.l.",
    "wof:placetype":"venue"
},
  "geometry": {"coordinates":[-2.8118453026,36.7744865417],"type":"Point"}
}