{
  "type": "Feature",
  "properties": {
    "addr:full":"Calle de Elcano, 11 San Vicente De Barakaldo Vizcaya 48901",
    "addr:housenumber":"11",
    "addr:postcode":"48901",
    "addr:street":"Calle De Elcano",
    "iso:country":"ES",
    "sg:address":"Calle de Elcano, 11",
    "sg:city":"San Vicente De Barakaldo",
    "sg:orig_category":"Ense\u00d1anza Variada",
    "sg:phone":"+34 944 78 12 72",
    "sg:postcode":"48901",
    "sg:province":"Vizcaya",
    "sg:website":"www.grupoedison.com",
    "wof:name":"Ikaslan Tecnicas De Estudio S.l.",
    "wof:placetype":"venue"
},
  "geometry": {"coordinates":[-2.9858388901,43.2973098755],"type":"Point"}
}