{
  "type": "Feature",
  "properties": {
    "iso:country":"ES",
    "sg:address":"Rua Dez De Marzo, 2",
    "sg:city":"Vigo",
    "sg:orig_category":"Peluqueros: De Se\u00d1oras",
    "sg:phone":"+34 986 20 30 96",
    "sg:postcode":"36210",
    "sg:province":"Pontevedra",
    "wof:name":"Fernandez Pi\u00f1eiro Olivia",
    "wof:placetype":"venue"
},
  "geometry": {"coordinates":[-8.7391853333,42.214717865],"type":"Point"}
}