{
  "type": "Feature",
  "properties": {
    "iso:country":"ES",
    "sg:address":"Calle de General Prim, 21",
    "sg:city":"Alcala Guadaira",
    "sg:orig_category":"Puertas Y Portales",
    "sg:phone":"+34 954 10 04 04",
    "sg:postcode":"41500",
    "sg:province":"Sevilla",
    "wof:name":"Gonzalez Garcia Leovigildo",
    "wof:placetype":"venue"
},
  "geometry": {"coordinates":[-5.8377170563,37.3429946899],"type":"Point"}
}