{
  "type": "Feature",
  "properties": {
    "addr:full":"Calle de Doctor Serafin Bohorquez, 49 Ubrique C\u00e1diz 11600",
    "addr:housenumber":"49",
    "addr:postcode":"11600",
    "addr:street":"Calle De Doctor Serafin Bohorquez;Ca\u0301Diz",
    "iso:country":"ES",
    "sg:address":"Calle de Doctor Serafin Bohorquez, 49",
    "sg:city":"Ubrique",
    "sg:orig_category":"Marroquiner\u00cda (confecci\u00d3n)",
    "sg:phone":"+34 956 46 02 73",
    "sg:postcode":"11600",
    "sg:province":"C\u00e1diz",
    "wof:name":"Gino Vittorio S.l.",
    "wof:placetype":"venue"
},
  "geometry": {"coordinates":[-5.4439263344,36.6793174744],"type":"Point"}
}