{
  "type": "Feature",
  "properties": {
    "iso:country":"ES",
    "sg:address":"Ctra Valladolid, Km. 0005,8",
    "sg:city":"Villalbilla De Burgos",
    "sg:orig_category":"Distribuci\u00d3n De Petr\u00d3leo Y Derivados",
    "sg:phone":"+34 947 29 11 04",
    "sg:postcode":"09197",
    "sg:province":"Burgos",
    "wof:name":"Estacion De Servicio Los Brezos S. A.",
    "wof:placetype":"venue"
},
  "geometry": {"coordinates":[-3.7522571087,42.3791885376],"type":"Point"}
}