{
  "type": "Feature",
  "properties": {
    "iso:country":"ES",
    "sg:address":"Av Mare Deu De Montserrat, 60",
    "sg:city":"Barcelona",
    "sg:orig_category":"Alquiler De Casas Y Habitaciones Amuebladas",
    "sg:phone":"+34 932 19 79 03",
    "sg:postcode":"08024",
    "sg:province":"Barcelona",
    "wof:name":"Iglesia De Jesucristo De Los Santos De Los Ultimos Dias",
    "wof:placetype":"venue"
},
  "geometry": {"coordinates":[2.1641039848,41.4144973755],"type":"Point"}
}