{
  "type": "Feature",
  "properties": {
    "addr:full":"Calle de Alto De Amara, 7 Donostia-san Sebastian Guip\u00f9zcoa 20006",
    "addr:housenumber":"7",
    "addr:postcode":"20006",
    "addr:street":"Calle De Alto De Amara",
    "iso:country":"ES",
    "sg:address":"Calle de Alto De Amara, 7",
    "sg:city":"Donostia-san Sebastian",
    "sg:orig_category":"Comercio, Reparaci\u00d3n De Motocicletas, Bicicletas Y Piezas Sueltas",
    "sg:phone":"+34 943 45 77 39",
    "sg:postcode":"20006",
    "sg:province":"Guip\u00f9zcoa",
    "wof:name":"Neme Motos 2, S.l.",
    "wof:placetype":"venue"
},
  "geometry": {"coordinates":[-1.9835618734,43.313243866],"type":"Point"}
}