{
  "type": "Feature",
  "properties": {
    "addr:full":"Calle de Hernando De Acu\u00d1a, S/n Valladolid Valladolid 47014",
    "addr:housenumber":"s / n",
    "addr:postcode":"47014",
    "addr:street":"Calle De Hernando De Acun\u0303A",
    "iso:country":"ES",
    "sg:address":"Calle de Hernando De Acu\u00d1a, S/n",
    "sg:city":"Valladolid",
    "sg:orig_category":"Asociaciones Y Clubs Deportivos",
    "sg:phone":"+34 983 37 70 09",
    "sg:postcode":"47014",
    "sg:province":"Valladolid",
    "wof:name":"Hernandez Mu\u00f1oz Herminia",
    "wof:placetype":"venue"
},
  "geometry": {"coordinates":[-4.7622241974,41.6380233765],"type":"Point"}
}