{
  "type": "Feature",
  "properties": {
    "addr:full":"Ctra Oca\u00d1a, Km. 0006,7 Mentrida Toledo 45930",
    "addr:postcode":"45930",
    "addr:street":"Ctra Ocan\u0303A Km. 0006,7",
    "iso:country":"ES",
    "sg:address":"Ctra Oca\u00d1a, Km. 0006,7",
    "sg:city":"Mentrida",
    "sg:orig_category":"Distribuci\u00d3n De Petr\u00d3leo Y Derivados",
    "sg:phone":"+34 918 17 87 77",
    "sg:postcode":"45930",
    "sg:province":"Toledo",
    "wof:name":"Luis Francisco Vaquero E Hijos C.b.",
    "wof:placetype":"venue"
},
  "geometry": {"coordinates":[-4.1951050758,40.2356834412],"type":"Point"}
}