{
  "type": "Feature",
  "properties": {
    "iso:country":"ES",
    "sg:address":"Ctra Arneva-mojon, Km. 0002,0",
    "sg:city":"Orihuela",
    "sg:orig_category":"Frutas Y Legumbres Frescas (al Por Mayor)",
    "sg:phone":"+34 965 30 44 18",
    "sg:postcode":"03300",
    "sg:province":"Alicante",
    "wof:name":"Frubesol S.l.",
    "wof:placetype":"venue"
},
  "geometry": {"coordinates":[-0.9448040128,38.0817642212],"type":"Point"}
}