{
  "type": "Feature",
  "properties": {
    "iso:country":"ES",
    "sg:address":"Avda Jahn Reisen, S/n",
    "sg:city":"Urbanizacion Ca\u00e7ada Del Rio",
    "sg:orig_category":"Agencias De Viajes",
    "sg:phone":"+34 928 54 72 69",
    "sg:postcode":"35627",
    "sg:province":"Las Palmas",
    "wof:name":"Viajes Allsun S.a.",
    "wof:placetype":"venue"
},
  "geometry": {"coordinates":[-14.1530008316,28.1882152557],"type":"Point"}
}