{
  "type": "Feature",
  "properties": {
    "addr:full":"Plaz Alfonso X El Sabio, 16 Pola De Lena Asturias 33630",
    "addr:housenumber":"16",
    "addr:postcode":"33630",
    "addr:street":"Plaz Alfonso X El Sabio",
    "iso:country":"ES",
    "sg:address":"Plaz Alfonso X El Sabio, 16",
    "sg:city":"Pola De Lena",
    "sg:orig_category":"Electrodom\u00c9sticos (al Por Menor)",
    "sg:phone":"+34 985 49 05 14",
    "sg:postcode":"33630",
    "sg:province":"Asturias",
    "wof:name":"Gabala S.l.l.",
    "wof:placetype":"venue"
},
  "geometry": {"coordinates":[-5.8290290833,43.1575241089],"type":"Point"}
}