{
  "type": "Feature",
  "properties": {
    "addr:full":"Calle de Meson, 27 Alozaina M\u00e1laga 29567",
    "addr:housenumber":"27",
    "addr:postcode":"29567",
    "addr:street":"Calle De Meson;Ma\u0301Laga",
    "iso:country":"ES",
    "sg:address":"Calle de Meson, 27",
    "sg:city":"Alozaina",
    "sg:orig_category":"Empresarios",
    "sg:phone":"+34 952 48 10 99",
    "sg:postcode":"29567",
    "sg:province":"M\u00e1laga",
    "wof:name":"Rubio Rueda Tomas",
    "wof:placetype":"venue"
},
  "geometry": {"coordinates":[-4.8575339317,36.7281646729],"type":"Point"}
}