{
  "type": "Feature",
  "properties": {
    "iso:country":"ES",
    "sg:address":"Avda Bilbao, 84",
    "sg:city":"Torrelavega",
    "sg:orig_category":"Mec\u00c1nico Del Autom\u00d3vil",
    "sg:phone":"+34 942 80 22 14",
    "sg:postcode":"39300",
    "sg:province":"Cantabria",
    "wof:name":"Gonzalez Barreda Mariano",
    "wof:placetype":"venue"
},
  "geometry": {"coordinates":[-4.0323047638,43.3431358337],"type":"Point"}
}