{
  "type": "Feature",
  "properties": {
    "iso:country":"ES",
    "sg:address":"Calle de San Jose, 22",
    "sg:city":"Benejuzar",
    "sg:orig_category":"Empresas De Pintura Y Revestimientos",
    "sg:phone":"+34 965 35 62 47",
    "sg:postcode":"03390",
    "sg:province":"Alicante",
    "wof:name":"Garcia Cases Manuel",
    "wof:placetype":"venue"
},
  "geometry": {"coordinates":[-0.8376579881,38.0760307312],"type":"Point"}
}