{
  "type": "Feature",
  "properties": {
    "addr:full":"Urba Icomar, 8 Icomar Tarragona 43006",
    "addr:housenumber":"8",
    "addr:postcode":"43006",
    "addr:street":"Icomar",
    "iso:country":"ES",
    "sg:address":"Urba Icomar, 8",
    "sg:city":"Icomar",
    "sg:orig_category":"Empresas De Carpinter\u00cda",
    "sg:phone":"+34 977 54 23 11",
    "sg:postcode":"43006",
    "sg:province":"Tarragona",
    "wof:name":"Fernandez Castro Juan",
    "wof:placetype":"venue"
},
  "geometry": {"coordinates":[1.2209249735,41.1154441833],"type":"Point"}
}