{
  "type": "Feature",
  "properties": {
    "iso:country":"ES",
    "sg:address":"Plaz Santiago, 7",
    "sg:city":"Jerez De La Frontera",
    "sg:orig_category":"Alimentaci\u00d3n General (al Por Menor)",
    "sg:phone":"+34 956 18 16 64",
    "sg:postcode":"11404",
    "sg:province":"C\u00e1diz",
    "wof:name":"Padilla Mu\u00f1oz Manuel",
    "wof:placetype":"venue"
},
  "geometry": {"coordinates":[-6.1430478096,36.6877403259],"type":"Point"}
}