{
  "type": "Feature",
  "properties": {
    "addr:full":"Avda Victor Gallego, 19 Zamora Zamora 49009",
    "addr:housenumber":"19",
    "addr:postcode":"49009",
    "addr:street":"Avda Victor Gallego",
    "iso:country":"ES",
    "sg:address":"Avda Victor Gallego, 19",
    "sg:city":"Zamora",
    "sg:orig_category":"Asesor\u00cda Fiscal Y Jur\u00cddica",
    "sg:phone":"+34 980 51 63 36",
    "sg:postcode":"49009",
    "sg:province":"Zamora",
    "wof:name":"Vidal Gutierrez Carlos",
    "wof:placetype":"venue"
},
  "geometry": {"coordinates":[-5.7428879738,41.5101051331],"type":"Point"}
}