{
  "type": "Feature",
  "properties": {
    "addr:full":"Rua Rio Vali\u00d1a, 3 Barcala La Coru\u00f1a 15660",
    "addr:housenumber":"3",
    "addr:postcode":"15660",
    "addr:street":"Rua;Valin\u0303A;Barcala La Corun\u0303A",
    "iso:country":"ES",
    "sg:address":"Rua Rio Vali\u00d1a, 3",
    "sg:city":"Barcala",
    "sg:orig_category":"Pescader\u00cdas (al Por Menor)",
    "sg:phone":"+34 981 65 13 20",
    "sg:postcode":"15660",
    "sg:province":"La Coru\u00f1a",
    "wof:name":"Garcia Martinez Enrique",
    "wof:placetype":"venue"
},
  "geometry": {"coordinates":[-8.3534107208,43.3052062988],"type":"Point"}
}