{
  "type": "Feature",
  "properties": {
    "iso:country":"ES",
    "sg:address":"Calle de Juan Ramon Jimenez, S/n",
    "sg:city":"Infante Juan Manuel",
    "sg:orig_category":"Caf\u00c9s, Bares, Cervecer\u00cdas",
    "sg:phone":"+34 968 26 81 52",
    "sg:postcode":"30011",
    "sg:province":"Murcia",
    "wof:name":"Inversiones Jb S.l.",
    "wof:placetype":"venue"
},
  "geometry": {"coordinates":[-1.1249890327,37.9780845642],"type":"Point"}
}