{
  "type": "Feature",
  "properties": {
    "iso:country":"ES",
    "sg:address":"Calle de Sextil (villafria), 6",
    "sg:city":"Villafria",
    "sg:orig_category":"Aluminio Y Aleaciones (producci\u00d3n, Transformaci\u00d3n, Negocio)",
    "sg:phone":"+34 947 47 50 67",
    "sg:postcode":"09192",
    "sg:province":"Burgos",
    "wof:name":"Ayuso Tres Burgos S.l.",
    "wof:placetype":"venue"
},
  "geometry": {"coordinates":[-3.5749700069,42.3601303101],"type":"Point"}
}