{
  "type": "Feature",
  "properties": {
    "addr:full":"Pol Ind Vado Hermoso, S/n Cabra C\u00f3rdoba 14940",
    "addr:housenumber":"s / n",
    "addr:postcode":"14940",
    "addr:street":"Co\u0301Rdoba",
    "iso:country":"ES",
    "sg:address":"Pol Ind Vado Hermoso, S/n",
    "sg:city":"Cabra",
    "sg:orig_category":"Venta, Instalaci\u00d3n De Cocinas",
    "sg:phone":"+34 957 52 40 13",
    "sg:postcode":"14940",
    "sg:province":"C\u00f3rdoba",
    "wof:name":"Gamiz Aguilera Francisco Jose",
    "wof:placetype":"venue"
},
  "geometry": {"coordinates":[-4.4614992142,37.473815918],"type":"Point"}
}