{
  "type": "Feature",
  "properties": {
    "addr:full":"Ctra. Punta Arabi, 5 Sta. Eularia Riu Islas Baleares 07840",
    "addr:housenumber":"5",
    "addr:postcode":"07840",
    "addr:street":"Ctra. Punta Arabi;Baleares",
    "iso:country":"ES",
    "sg:address":"Ctra. Punta Arabi, 5",
    "sg:city":"Sta. Eularia Riu",
    "sg:orig_category":"Laboratorios Y Trabajos De Fotograf\u00cda, V\u00cddeo Y Cine",
    "sg:phone":"+34 971 33 08 27",
    "sg:postcode":"07840",
    "sg:province":"Islas Baleares",
    "wof:name":"Rohra  Manoj Rajaldas",
    "wof:placetype":"venue"
},
  "geometry": {"coordinates":[1.5341850519,38.9850311279],"type":"Point"}
}