{
  "type": "Feature",
  "properties": {
    "iso:country":"ES",
    "sg:address":"A Reigosa, 52",
    "sg:city":"Touron",
    "sg:orig_category":"Edici\u00d3n De Diarios, Revistas, Boletines",
    "sg:phone":"+34 986 75 75 01",
    "sg:postcode":"36827",
    "sg:province":"Pontevedra",
    "wof:name":"Lerez Ediciones S.l.",
    "wof:placetype":"venue"
},
  "geometry": {"coordinates":[-8.5463991165,42.4074401855],"type":"Point"}
}