{
  "type": "Feature",
  "properties": {
    "iso:country":"ES",
    "sg:address":"Calle de San Antonio, 12",
    "sg:city":"Paiporta",
    "sg:orig_category":"Alquiler De V\u00cddeo",
    "sg:phone":"+34 963 97 15 57",
    "sg:postcode":"46200",
    "sg:province":"Valencia",
    "wof:name":"Broadway Imagen S.l.",
    "wof:placetype":"venue"
},
  "geometry": {"coordinates":[-0.4222899973,39.4288978577],"type":"Point"}
}