{
  "type": "Feature",
  "properties": {
    "addr:full":"Carrer de Marcelino Menendez Pelayo, 14 Granollers Barcelona 08401",
    "addr:housenumber":"14",
    "addr:postcode":"08401",
    "addr:street":"Carrer De Marcelino Menendez Pelayo",
    "iso:country":"ES",
    "sg:address":"Carrer de Marcelino Menendez Pelayo, 14",
    "sg:city":"Granollers",
    "sg:orig_category":"Cerrajer\u00cda, Ferrallista",
    "sg:phone":"+34 938 70 07 22",
    "sg:postcode":"08401",
    "sg:province":"Barcelona",
    "wof:name":"Barnils Garcia Jaime",
    "wof:placetype":"venue"
},
  "geometry": {"coordinates":[2.2837200165,41.606300354],"type":"Point"}
}