{
  "type": "Feature",
  "properties": {
    "iso:country":"ES",
    "sg:address":"Calle de Sacerdote Fernando Pastor, 15",
    "sg:city":"Motilla Palancar",
    "sg:orig_category":"Doctores En Medicina",
    "sg:phone":"+34 969 33 11 79",
    "sg:postcode":"16200",
    "sg:province":"Cuenca",
    "wof:name":"Cuellar Serrano Abel",
    "wof:placetype":"venue"
},
  "geometry": {"coordinates":[-1.9104419947,39.563079834],"type":"Point"}
}