{
  "type": "Feature",
  "properties": {
    "iso:country":"ES",
    "sg:address":"Calle de Canovas Del Castillo, 21",
    "sg:city":"Pinoso",
    "sg:orig_category":"Bancos",
    "sg:phone":"+34 965 47 72 24",
    "sg:postcode":"03650",
    "sg:province":"Alicante",
    "wof:name":"Banco Espa\u00f1ol De Credito S.a.",
    "wof:placetype":"venue"
},
  "geometry": {"coordinates":[-1.040948987,38.4019432068],"type":"Point"}
}