{
  "type": "Feature",
  "properties": {
    "iso:country":"ES",
    "sg:address":"Calle de Camarena, 148",
    "sg:city":"Madrid",
    "sg:orig_category":"Madera Para Construcci\u00d3n E Industria",
    "sg:phone":"+34 917 18 45 00",
    "sg:postcode":"28047",
    "sg:province":"Madrid",
    "wof:name":"Lavalle Leon Byron",
    "wof:placetype":"venue"
},
  "geometry": {"coordinates":[-3.75568223,40.3901786804],"type":"Point"}
}