{
  "type": "Feature",
  "properties": {
    "addr:full":"Calle de Union, 25 Leganes Madrid 28914",
    "addr:housenumber":"25",
    "addr:postcode":"28914",
    "addr:street":"Calle De",
    "iso:country":"ES",
    "sg:address":"Calle de Union, 25",
    "sg:city":"Leganes",
    "sg:orig_category":"Empresas De Carpinter\u00cda De Madera",
    "sg:phone":"+34 916 94 00 23",
    "sg:postcode":"28914",
    "sg:province":"Madrid",
    "wof:name":"Carpinteria-ebanisteria F.mu\u00f1oz S.l.",
    "wof:placetype":"venue"
},
  "geometry": {"coordinates":[-3.7710630894,40.3180046082],"type":"Point"}
}