{
  "type": "Feature",
  "properties": {
    "iso:country":"ES",
    "sg:address":"Teixeira, S/n",
    "sg:city":"Teixeira",
    "sg:orig_category":"Cooperativas Agr\u00cdcolas",
    "sg:phone":"+34 988 20 75 53",
    "sg:postcode":"32765",
    "sg:province":"Ourense",
    "wof:name":"A Carosa-teixeira Asociacion Agricultores",
    "wof:placetype":"venue"
},
  "geometry": {"coordinates":[-7.4872374535,42.385684967],"type":"Point"}
}