{
  "type": "Feature",
  "properties": {
    "addr:full":"Avda Alcalde Gregorio Espino, 50 Vigo Pontevedra 36205",
    "addr:housenumber":"50",
    "addr:postcode":"36205",
    "addr:street":"Avda Alcalde Gregorio Espino",
    "iso:country":"ES",
    "sg:address":"Avda Alcalde Gregorio Espino, 50",
    "sg:city":"Vigo",
    "sg:orig_category":"Promotores Constructores",
    "sg:phone":"+34 986 37 86 35",
    "sg:postcode":"36205",
    "sg:province":"Pontevedra",
    "wof:name":"Construcciones Sito Y Fernandez S.l.",
    "wof:placetype":"venue"
},
  "geometry": {"coordinates":[-8.7089738846,42.2271118164],"type":"Point"}
}