{
  "type": "Feature",
  "properties": {
    "iso:country":"ES",
    "sg:address":"Plaz Jardinillos (los), 10",
    "sg:city":"Jaen",
    "sg:orig_category":"Zapatos (al Por Menor)",
    "sg:phone":"+34 953 27 50 22",
    "sg:postcode":"23003",
    "sg:province":"Ja\u00e9n",
    "wof:name":"Jimenez Marin Dolores",
    "wof:placetype":"venue"
},
  "geometry": {"coordinates":[-3.7269899845,37.7898101807],"type":"Point"}
}