{
  "type": "Feature",
  "properties": {
    "iso:country":"ES",
    "sg:address":"Avda Gran Canaria (de), 13",
    "sg:city":"Playa Del Ingles",
    "sg:orig_category":"Abogados",
    "sg:phone":"+34 928 76 53 71",
    "sg:postcode":"35100",
    "sg:province":"Las Palmas",
    "wof:name":"Naranjo Viera Gustavo Adolfo",
    "wof:placetype":"venue"
},
  "geometry": {"coordinates":[-15.5695466995,27.7624073029],"type":"Point"}
}