{
  "type": "Feature",
  "properties": {
    "addr:full":"Carrer de Joan Lluis Vives, 16 Can Trias Industrial Barcelona 08232",
    "addr:housenumber":"16",
    "addr:postcode":"08232",
    "addr:street":"Carrer De Joan Lluis Vives",
    "iso:country":"ES",
    "sg:address":"Carrer de Joan Lluis Vives, 16",
    "sg:city":"Can Trias Industrial",
    "sg:orig_category":"Fabricaci\u00d3n Y Venta De Volquetes Y Remolques",
    "sg:phone":"+34 937 33 25 32",
    "sg:postcode":"08232",
    "sg:province":"Barcelona",
    "wof:name":"Montenegro Iberica",
    "wof:placetype":"venue"
},
  "geometry": {"coordinates":[1.9658440351,41.5599975586],"type":"Point"}
}