{
  "type": "Feature",
  "properties": {
    "addr:full":"Calle de Santa Angela De La Cruz, 14 Villacarrillo Ja\u00e9n 23300",
    "addr:housenumber":"14",
    "addr:postcode":"23300",
    "addr:street":"Calle De Santa Angela De La Cruz;Jae\u0301N",
    "iso:country":"ES",
    "sg:address":"Calle de Santa Angela De La Cruz, 14",
    "sg:city":"Villacarrillo",
    "sg:orig_category":"Telas Para Tapizar, Cortinas, Pasamaner\u00cda (fabricaci\u00d3n, Al Por Mayor)",
    "sg:phone":"+34 953 45 43 39",
    "sg:postcode":"23300",
    "sg:province":"Ja\u00e9n",
    "wof:name":"Pulido Marin Felisa",
    "wof:placetype":"venue"
},
  "geometry": {"coordinates":[-3.0831570625,38.1163215637],"type":"Point"}
}