{
  "type": "Feature",
  "properties": {
    "iso:country":"ES",
    "sg:address":"Calle de Infante Don Juan Manuel, 15",
    "sg:city":"Yecla",
    "sg:orig_category":"Electrodom\u00c9sticos (al Por Menor)",
    "sg:phone":"+34 968 71 87 21",
    "sg:postcode":"30510",
    "sg:province":"Murcia",
    "wof:name":"Javier Electro Hogar S.l.",
    "wof:placetype":"venue"
},
  "geometry": {"coordinates":[-1.1088399887,38.6055603027],"type":"Point"}
}