{
  "type": "Feature",
  "properties": {
    "addr:full":"Calle de Casta\u00d1os, 7 Bilbao Vizcaya 48007",
    "addr:housenumber":"7",
    "addr:postcode":"48007",
    "addr:street":"Calle De Castan\u0303Os",
    "iso:country":"ES",
    "sg:address":"Calle de Casta\u00d1os, 7",
    "sg:city":"Bilbao",
    "sg:orig_category":"Lateros",
    "sg:phone":"+34 944 45 34 96",
    "sg:postcode":"48007",
    "sg:province":"Vizcaya",
    "wof:name":"Perez Calvo Raul",
    "wof:placetype":"venue"
},
  "geometry": {"coordinates":[-2.9260094166,43.2679328918],"type":"Point"}
}