{
  "type": "Feature",
  "properties": {
    "iso:country":"ES",
    "sg:address":"Rond Sant Oleguer, 100",
    "sg:city":"Mataro",
    "sg:orig_category":"Confecciones De Art\u00cdculos De Punto",
    "sg:phone":"+34 937 55 03 03",
    "sg:postcode":"08304",
    "sg:province":"Barcelona",
    "wof:name":"Garcia Lasso Jose Santiago",
    "wof:placetype":"venue"
},
  "geometry": {"coordinates":[2.4471418858,41.5513801575],"type":"Point"}
}