{
  "type": "Feature",
  "properties": {
    "addr:full":"Calle de Picota, S/n Beade Ourense 32431",
    "addr:housenumber":"s / n",
    "addr:postcode":"32431",
    "addr:street":"Calle De Picota",
    "iso:country":"ES",
    "sg:address":"Calle de Picota, S/n",
    "sg:city":"Beade",
    "sg:orig_category":"Cerrajer\u00cda, Ferrallista",
    "sg:phone":"+34 988 48 00 21",
    "sg:postcode":"32431",
    "sg:province":"Ourense",
    "wof:name":"Cerrajeria Rodriguez Ferro S.l",
    "wof:placetype":"venue"
},
  "geometry": {"coordinates":[-8.1290893555,42.3304710388],"type":"Point"}
}