{
  "type": "Feature",
  "properties": {
    "addr:full":"Calle de Santa Lucia, 8 Puerto De Santa Maria C\u00e1diz 11500",
    "addr:housenumber":"8",
    "addr:postcode":"11500",
    "addr:street":"Calle De Santa Lucia;Ca\u0301Diz",
    "iso:country":"ES",
    "sg:address":"Calle de Santa Lucia, 8",
    "sg:city":"Puerto De Santa Maria",
    "sg:orig_category":"Venta, Instalaci\u00d3n, Reparaci\u00d3n De Antenas Para Televisi\u00d3n",
    "sg:phone":"+34 956 85 09 16",
    "sg:postcode":"11500",
    "sg:province":"C\u00e1diz",
    "wof:name":"Antenas Alcaraz S.l.",
    "wof:placetype":"venue"
},
  "geometry": {"coordinates":[-6.2293534279,36.5991516113],"type":"Point"}
}