{
  "type": "Feature",
  "properties": {
    "iso:country":"ES",
    "sg:address":"Carrer de Batlle Joan Deu, 13",
    "sg:city":"Sentmenat",
    "sg:orig_category":"Arquitectos",
    "sg:phone":"+34 937 15 12 42",
    "sg:postcode":"08181",
    "sg:province":"Barcelona",
    "wof:name":"Torre Sanahuja Jose Luis De La",
    "wof:placetype":"venue"
},
  "geometry": {"coordinates":[2.1359701157,41.6086997986],"type":"Point"}
}