{
  "type": "Feature",
  "properties": {
    "iso:country":"ES",
    "sg:address":"Av Gabriel Roca, 39",
    "sg:city":"Palma",
    "sg:orig_category":"Agencias Y Agentes Comerciales, Representantes",
    "sg:phone":"+34 971 45 59 95",
    "sg:postcode":"07014",
    "sg:province":"Islas Baleares",
    "wof:name":"Aguilo Pico Joan",
    "wof:placetype":"venue"
},
  "geometry": {"coordinates":[2.628020525,39.5635795593],"type":"Point"}
}