{
  "type": "Feature",
  "properties": {
    "addr:full":"G.v. Escultor Francisco Salzillo, 8 Santa Catalina Murcia 30004",
    "addr:housenumber":"8",
    "addr:postcode":"30004",
    "addr:street":"Escultor Francisco Salzillo",
    "iso:country":"ES",
    "sg:address":"G.v. Escultor Francisco Salzillo, 8",
    "sg:city":"Santa Catalina",
    "sg:orig_category":"Agentes Generales De Seguros",
    "sg:phone":"+34 968 21 39 51",
    "sg:postcode":"30004",
    "sg:province":"Murcia",
    "wof:name":"Seguros Enrique Martinez Vicente S.l.",
    "wof:placetype":"venue"
},
  "geometry": {"coordinates":[-1.1316239834,37.9846534729],"type":"Point"}
}