{
  "type": "Feature",
  "properties": {
    "iso:country":"ES",
    "sg:address":"Carrer de Albacete, 9",
    "sg:city":"Barcelona",
    "sg:orig_category":"Inform\u00c1tica: Consultores",
    "sg:phone":"+34 932 37 01 21",
    "sg:postcode":"08012",
    "sg:province":"Barcelona",
    "wof:name":"Do Business Designer S.l.",
    "wof:placetype":"venue"
},
  "geometry": {"coordinates":[2.151129961,41.4077835083],"type":"Point"}
}