{
  "type": "Feature",
  "properties": {
    "addr:full":"Calle de Molinillo, 24 Burgos Burgos 09002",
    "addr:housenumber":"24",
    "addr:postcode":"09002",
    "addr:street":"Calle De Molinillo",
    "iso:country":"ES",
    "sg:address":"Calle de Molinillo, 24",
    "sg:city":"Burgos",
    "sg:orig_category":"Estancos",
    "sg:phone":"+34 947 26 16 12",
    "sg:postcode":"09002",
    "sg:province":"Burgos",
    "wof:name":"Iglesia Mata Felicidad De",
    "wof:placetype":"venue"
},
  "geometry": {"coordinates":[-3.6926369667,42.338104248],"type":"Point"}
}