{
  "type": "Feature",
  "properties": {
    "iso:country":"ES",
    "sg:address":"Calle de Santa Maria Magdalena, 4",
    "sg:city":"Sevilla",
    "sg:orig_category":"Centros Empresariales",
    "sg:phone":"+34 954 36 71 38",
    "sg:postcode":"41008",
    "sg:province":"Sevilla",
    "wof:name":"Clesmill S.l.",
    "wof:placetype":"venue"
},
  "geometry": {"coordinates":[-5.9750552177,37.4038963318],"type":"Point"}
}