{
  "type": "Feature",
  "properties": {
    "iso:country":"ES",
    "sg:address":"Calle de Antonio Alcaide Sanchez, 27",
    "sg:city":"Torremolinos",
    "sg:orig_category":"Papeler\u00cdas, Librer\u00cdas",
    "sg:phone":"+34 952 05 10 27",
    "sg:postcode":"29620",
    "sg:province":"M\u00e1laga",
    "wof:name":"Govez S.a.",
    "wof:placetype":"venue"
},
  "geometry": {"coordinates":[-4.5166215897,36.6108779907],"type":"Point"}
}