{
  "type": "Feature",
  "properties": {
    "addr:full":"Afueras, S/n Alforque Zaragoza 50783",
    "addr:postcode":"50783",
    "addr:street":"Afueras S / N Alforque",
    "iso:country":"ES",
    "sg:address":"Afueras, S/n",
    "sg:city":"Alforque",
    "sg:orig_category":"Poller\u00cda Y Caza (al Por Menor)",
    "sg:phone":"+34 976 17 81 61",
    "sg:postcode":"50783",
    "sg:province":"Zaragoza",
    "wof:name":"Arias Utrilla David",
    "wof:placetype":"venue"
},
  "geometry": {"coordinates":[-0.3889622092,41.3454170227],"type":"Point"}
}