{
  "type": "Feature",
  "properties": {
    "addr:full":"Carrer de Cristofol Colom, 24 Granollers Barcelona 08402",
    "addr:housenumber":"24",
    "addr:postcode":"08402",
    "addr:street":"Carrer De Cristofol Colom",
    "iso:country":"ES",
    "sg:address":"Carrer de Cristofol Colom, 24",
    "sg:city":"Granollers",
    "sg:orig_category":"Florister\u00cdas",
    "sg:phone":"+34 938 79 43 13",
    "sg:postcode":"08402",
    "sg:province":"Barcelona",
    "wof:name":"Yuste Tirado Inmaculada",
    "wof:placetype":"venue"
},
  "geometry": {"coordinates":[2.2889099121,41.6079521179],"type":"Point"}
}