{
  "type": "Feature",
  "properties": {
    "addr:full":"Avda Virgen De Los Dolores, 1 Cordoba C\u00f3rdoba 14004",
    "addr:housenumber":"1",
    "addr:postcode":"14004",
    "addr:street":"Avda Virgen De Los Dolores;Co\u0301Rdoba",
    "iso:country":"ES",
    "sg:address":"Avda Virgen De Los Dolores, 1",
    "sg:city":"Cordoba",
    "sg:orig_category":"Inform\u00c1tica (estudios, Servicios, Asesor\u00cda, Formaci\u00d3n)",
    "sg:phone":"+34 957 45 41 70",
    "sg:postcode":"14004",
    "sg:province":"C\u00f3rdoba",
    "sg:website":"www.interbook/empresas/lamflo",
    "wof:name":"Lamflo S.l.",
    "wof:placetype":"venue"
},
  "geometry": {"coordinates":[-4.7970299721,37.8752708435],"type":"Point"}
}