{
  "type": "Feature",
  "properties": {
    "iso:country":"ES",
    "sg:address":"Calle de Pablo Iglesias, 48",
    "sg:city":"Zubia",
    "sg:orig_category":"Agencias De Viajes",
    "sg:phone":"+34 958 89 21 74",
    "sg:postcode":"18140",
    "sg:province":"Granada",
    "wof:name":"Margarita Tours S.l.",
    "wof:placetype":"venue"
},
  "geometry": {"coordinates":[-3.582723856,37.1211585999],"type":"Point"}
}