{
  "type": "Feature",
  "properties": {
    "iso:country":"ES",
    "sg:address":"Avda Marques De Valterra, 73",
    "sg:city":"Estribela",
    "sg:orig_category":"Fabricaci\u00d3n, Reparaci\u00d3n Y Mantenimiento De Construcciones Navales Y Fluviales",
    "sg:phone":"+34 986 88 15 00",
    "sg:postcode":"36910",
    "sg:province":"Pontevedra",
    "wof:name":"Efectos Navales Taracido S.l.",
    "wof:placetype":"venue"
},
  "geometry": {"coordinates":[-8.6895112991,42.3996200562],"type":"Point"}
}