{
  "type": "Feature",
  "properties": {
    "addr:full":"Ctra Chinchon (de), Km. 0002,5 Puente De Arganda Madrid 28500",
    "addr:postcode":"28500",
    "addr:street":"Ctra Chinchon De Km. 0002,5 Puente De Arganda",
    "iso:country":"ES",
    "sg:address":"Ctra Chinchon (de), Km. 0002,5",
    "sg:city":"Puente De Arganda",
    "sg:orig_category":"Agentes, Concesionarios Y Sucursales De Camiones Y Veh\u00cdculos Industriales",
    "sg:phone":"+34 918 72 96 27",
    "sg:postcode":"28500",
    "sg:province":"Madrid",
    "wof:name":"Auto Camion Ape S.l.",
    "wof:placetype":"venue"
},
  "geometry": {"coordinates":[-3.5113883018,40.3169517517],"type":"Point"}
}