{
  "type": "Feature",
  "properties": {
    "iso:country":"ES",
    "sg:address":"Pg Sant Joan, 162",
    "sg:city":"Barcelona",
    "sg:orig_category":"Agencias Y Asesores De Publicidad",
    "sg:phone":"+34 932 08 12 16",
    "sg:postcode":"08037",
    "sg:province":"Barcelona",
    "wof:name":"Compa\u00d1ia General De Ideas S.l.",
    "wof:placetype":"venue"
},
  "geometry": {"coordinates":[2.1656548977,41.402759552],"type":"Point"}
}