{
  "type": "Feature",
  "properties": {
    "addr:full":"Rond Carcaboso, 26 Tietar C\u00e1ceres 10319",
    "addr:housenumber":"26",
    "addr:postcode":"10319",
    "addr:street":"Carcaboso;Ca\u0301Ceres",
    "iso:country":"ES",
    "sg:address":"Rond Carcaboso, 26",
    "sg:city":"Tietar",
    "sg:orig_category":"Alquiler De Veh\u00cdculos: Turismos Y Utilitarios",
    "sg:phone":"+34 927 55 02 79",
    "sg:postcode":"10319",
    "sg:province":"C\u00e1ceres",
    "wof:name":"Mangas Iglesias Miguel Angel",
    "wof:placetype":"venue"
},
  "geometry": {"coordinates":[-5.4800000191,40.0293388367],"type":"Point"}
}