{
  "type": "Feature",
  "properties": {
    "addr:full":"Calle de San Bruno, 9 Burgos Burgos 09007",
    "addr:housenumber":"9",
    "addr:postcode":"09007",
    "addr:street":"Calle De San Bruno",
    "iso:country":"ES",
    "sg:address":"Calle de San Bruno, 9",
    "sg:city":"Burgos",
    "sg:orig_category":"Vinos Y Licores (venta Al Por Menor)",
    "sg:phone":"+34 947 21 77 86",
    "sg:postcode":"09007",
    "sg:province":"Burgos",
    "wof:name":"Fuente Garcia Marta",
    "wof:placetype":"venue"
},
  "geometry": {"coordinates":[-3.6728720665,42.3494377136],"type":"Point"}
}