{
  "type": "Feature",
  "properties": {
    "addr:full":"Calle de Tres De Noviembre, 13 Santander Cantabria 39010",
    "addr:housenumber":"13",
    "addr:postcode":"39010",
    "addr:street":"Calle De Tres De Noviembre",
    "iso:country":"ES",
    "sg:address":"Calle de Tres De Noviembre, 13",
    "sg:city":"Santander",
    "sg:classifiers":[
        {
            "category":"Professional",
            "subcategory":"Business Services",
            "type":"Services"
        }
    ],
    "sg:phone":"+34 942 37 22 00",
    "sg:postcode":"39010",
    "sg:province":"Cantabria",
    "sg:tags":[
        "control",
        "asesor\u00cda",
        "organizaci\u00d3n",
        "la",
        "de",
        "gesti\u00d3n",
        "y"
    ],
    "sg:website":"www.cacmalaga.org",
    "wof:name":"Gestion Cultural Y Comunicacion S.l.",
    "wof:placetype":"venue"
},
  "geometry": {"coordinates":[-3.8175079823,43.4599876404],"type":"Point"}
}