{
  "type": "Feature",
  "properties": {
    "addr:full":"Calle de Moises De Leon, 49 Le\u00f3n Le\u00f3n 24006",
    "addr:housenumber":"49",
    "addr:postcode":"24006",
    "addr:street":"Calle De Moises De Leon;Leo\u0301N",
    "iso:country":"ES",
    "sg:address":"Calle de Moises De Leon, 49",
    "sg:city":"Le\u00f3n",
    "sg:orig_category":"Edici\u00d3n De Diarios, Revistas, Boletines",
    "sg:phone":"+34 987 21 25 12",
    "sg:postcode":"24006",
    "sg:province":"Le\u00f3n",
    "wof:name":"Promociones Periodisticas Leonesas S. A.",
    "wof:placetype":"venue"
},
  "geometry": {"coordinates":[-5.5596170425,42.5898857117],"type":"Point"}
}