{
  "type": "Feature",
  "properties": {
    "iso:country":"ES",
    "sg:address":"Carrer de Proven\u00c7a, 304",
    "sg:city":"Barcelona",
    "sg:orig_category":"M\u00c9dicos: Medicina General Orientada A La Acupuntura",
    "sg:phone":"+34 934 87 36 56",
    "sg:postcode":"08008",
    "sg:province":"Barcelona",
    "wof:name":"Garcia Jeneras Albert",
    "wof:placetype":"venue"
},
  "geometry": {"coordinates":[2.1627650261,41.3956947327],"type":"Point"}
}