{
  "type": "Feature",
  "properties": {
    "iso:country":"ES",
    "sg:address":"Clna St\u00aa Quiteria, 28",
    "sg:city":"Tarancon",
    "sg:orig_category":"Empresas De Desmonte",
    "sg:phone":"+34 969 32 29 30",
    "sg:postcode":"16400",
    "sg:province":"Cuenca",
    "wof:name":"Excader Ca\u00f1ada S.l.l.",
    "wof:placetype":"venue"
},
  "geometry": {"coordinates":[-3.0001590252,40.0126686096],"type":"Point"}
}