{
  "type": "Feature",
  "properties": {
    "iso:country":"ES",
    "sg:address":"Carretera, Km. 0310,6",
    "sg:city":"Bugedo",
    "sg:orig_category":"Distribuci\u00d3n De Petr\u00d3leo Y Derivados",
    "sg:phone":"+34 947 33 24 51",
    "sg:postcode":"09293",
    "sg:province":"Burgos",
    "wof:name":"Estacion De Servicio Roa S.a.",
    "wof:placetype":"venue"
},
  "geometry": {"coordinates":[-3.0171239376,42.649230957],"type":"Point"}
}