{
  "type": "Feature",
  "properties": {
    "addr:full":"Calle de Juan Miro, 6 Caudete Albacete 02660",
    "addr:housenumber":"6",
    "addr:postcode":"02660",
    "addr:street":"Calle De Juan Miro",
    "iso:country":"ES",
    "sg:address":"Calle de Juan Miro, 6",
    "sg:city":"Caudete",
    "sg:orig_category":"Loter\u00cda Y T\u00d3mbola",
    "sg:phone":"+34 965 82 50 67",
    "sg:postcode":"02660",
    "sg:province":"Albacete",
    "wof:name":"Martinez Requena Magali Maria",
    "wof:placetype":"venue"
},
  "geometry": {"coordinates":[-0.9886760116,38.7040252686],"type":"Point"}
}