{
  "type": "Feature",
  "properties": {
    "addr:full":"Plaz Obispo, 3 Malaga M\u00e1laga 29015",
    "addr:housenumber":"3",
    "addr:postcode":"29015",
    "addr:street":"Obispo;Ma\u0301Laga",
    "iso:country":"ES",
    "sg:address":"Plaz Obispo, 3",
    "sg:city":"Malaga",
    "sg:orig_category":"Caf\u00c9s, Bares, Cervecer\u00cdas",
    "sg:phone":"+34 952 21 75 75",
    "sg:postcode":"29015",
    "sg:province":"M\u00e1laga",
    "wof:name":"Soto Romero Antonio",
    "wof:placetype":"venue"
},
  "geometry": {"coordinates":[-4.4203867912,36.7198219299],"type":"Point"}
}