{
  "type": "Feature",
  "properties": {
    "addr:full":"Avda Alcalde Jose Rodriguez, 16 Dolores Alicante 03150",
    "addr:housenumber":"16",
    "addr:postcode":"03150",
    "addr:street":"Avda Alcalde Jose Rodriguez",
    "iso:country":"ES",
    "sg:address":"Avda Alcalde Jose Rodriguez, 16",
    "sg:city":"Dolores",
    "sg:orig_category":"Promotores Constructores",
    "sg:phone":"+34 966 71 03 15",
    "sg:postcode":"03150",
    "sg:province":"Alicante",
    "wof:name":"Menditxu S.l.",
    "wof:placetype":"venue"
},
  "geometry": {"coordinates":[-0.7704229951,38.1398277283],"type":"Point"}
}