{
  "type": "Feature",
  "properties": {
    "iso:country":"ES",
    "sg:address":"Avda Ciudad De Barcelona, 105",
    "sg:city":"Madrid",
    "sg:orig_category":"Pod\u00d3logos: Pedicuros",
    "sg:phone":"+34 915 52 38 11",
    "sg:postcode":"28007",
    "sg:province":"Madrid",
    "wof:name":"Gago Pascual Carlos Benito",
    "wof:placetype":"venue"
},
  "geometry": {"coordinates":[-3.6711299419,40.3994636536],"type":"Point"}
}