{
  "type": "Feature",
  "properties": {
    "addr:full":"Ctra Benamaurel, Km. 0003,5 Baza Granada 18800",
    "addr:postcode":"18800",
    "addr:street":"Ctra Benamaurel Km. 0003,5",
    "iso:country":"ES",
    "sg:address":"Ctra Benamaurel, Km. 0003,5",
    "sg:city":"Baza",
    "sg:orig_category":"Charcuter\u00cdas (al Por Mayor)",
    "sg:phone":"+34 958 34 23 53",
    "sg:postcode":"18800",
    "sg:province":"Granada",
    "wof:name":"Embutidos Y Jamones Hermanos Guiron, Sl",
    "wof:placetype":"venue"
},
  "geometry": {"coordinates":[-2.7732260227,37.4938468933],"type":"Point"}
}