{
  "type": "Feature",
  "properties": {
    "addr:full":"Rua Recanto Do Forno, 11 Seixalbo Ourense 32970",
    "addr:housenumber":"11",
    "addr:postcode":"32970",
    "addr:street":"Rua Recanto;Forno",
    "iso:country":"ES",
    "sg:address":"Rua Recanto Do Forno, 11",
    "sg:city":"Seixalbo",
    "sg:orig_category":"Cajas Y Embalajes De Cart\u00d3n Y Papel",
    "sg:phone":"+34 988 39 14 92",
    "sg:postcode":"32970",
    "sg:province":"Ourense",
    "wof:name":"Jose Lantero E Hijos S.a.",
    "wof:placetype":"venue"
},
  "geometry": {"coordinates":[-7.8508682251,42.3009872437],"type":"Point"}
}