{
  "type": "Feature",
  "properties": {
    "addr:full":"Calle de Castello, 25 Madrid Madrid 28001",
    "addr:housenumber":"25",
    "addr:postcode":"madrid;28001",
    "addr:street":"Calle De Castello",
    "iso:country":"ES",
    "sg:address":"Calle de Castello, 25",
    "sg:city":"Madrid",
    "sg:orig_category":"Agentes, Concesionarios Y Sucursales De Veh\u00cdculos",
    "sg:phone":"+34 914 35 85 83",
    "sg:postcode":"28001",
    "sg:province":"Madrid",
    "sg:website":"www.bmw.es",
    "wof:name":"Moncloa Motor Concesionario S.a.",
    "wof:placetype":"venue"
},
  "geometry": {"coordinates":[-3.6815748215,40.4247169495],"type":"Point"}
}