{
  "type": "Feature",
  "properties": {
    "addr:full":"Calle de Covadonga, 7 Fuenlabrada Madrid 28944",
    "addr:housenumber":"7",
    "addr:postcode":"28944",
    "addr:street":"Calle De Covadonga",
    "iso:country":"ES",
    "sg:address":"Calle de Covadonga, 7",
    "sg:city":"Fuenlabrada",
    "sg:orig_category":"Frutas, Legumbres Frescas Y Tempranas (al Por Menor)",
    "sg:phone":"+34 916 90 19 22",
    "sg:postcode":"28944",
    "sg:province":"Madrid",
    "wof:name":"Perez Gaitan Jose Maria",
    "wof:placetype":"venue"
},
  "geometry": {"coordinates":[-3.7978589535,40.2809371948],"type":"Point"}
}