{
  "type": "Feature",
  "properties": {
    "addr:full":"Calle de Rio Bergantes, S/n Torremolinos M\u00e1laga 29620",
    "addr:housenumber":"s / n",
    "addr:postcode":"29620",
    "addr:street":"Calle De Rio Bergantes;Ma\u0301Laga",
    "iso:country":"ES",
    "sg:address":"Calle de Rio Bergantes, S/n",
    "sg:city":"Torremolinos",
    "sg:orig_category":"Cristaler\u00cdas",
    "sg:phone":"+34 952 38 97 96",
    "sg:postcode":"29620",
    "sg:province":"M\u00e1laga",
    "wof:name":"Navarro Rivas Antonio",
    "wof:placetype":"venue"
},
  "geometry": {"coordinates":[-4.5017290115,36.6284408569],"type":"Point"}
}