{
  "type": "Feature",
  "properties": {
    "iso:country":"ES",
    "sg:address":"Calle de Fernandez De Los Rios, 43",
    "sg:city":"Madrid",
    "sg:orig_category":"Perfumer\u00cda (al Por Menor)",
    "sg:phone":"+34 915 49 49 72",
    "sg:postcode":"28015",
    "sg:province":"Madrid",
    "wof:name":"Ester Lublan S.l.",
    "wof:placetype":"venue"
},
  "geometry": {"coordinates":[-3.7104260921,40.4350662231],"type":"Point"}
}