{
  "type": "Feature",
  "properties": {
    "iso:country":"ES",
    "sg:address":"Carrer de Fluvia, 261",
    "sg:city":"Barcelona",
    "sg:orig_category":"Maquinaria Para Industrias Diversas",
    "sg:phone":"+34 933 03 31 64",
    "sg:postcode":"08020",
    "sg:province":"Barcelona",
    "wof:name":"Pressing Plus S.l.",
    "wof:placetype":"venue"
},
  "geometry": {"coordinates":[2.1937479973,41.4167976379],"type":"Point"}
}