{
  "type": "Feature",
  "properties": {
    "addr:full":"Avgd Cami Nou, 144 Benetusser Valencia 46910",
    "addr:housenumber":"144",
    "addr:postcode":"46910",
    "addr:street":"Nou",
    "iso:country":"ES",
    "sg:address":"Avgd Cami Nou, 144",
    "sg:city":"Benetusser",
    "sg:orig_category":"Fabricaci\u00d3n De Muebles",
    "sg:phone":"+34 963 75 15 11",
    "sg:postcode":"46910",
    "sg:province":"Valencia",
    "wof:name":"Sebastia Vilar Luis",
    "wof:placetype":"venue"
},
  "geometry": {"coordinates":[-0.3971590102,39.4194908142],"type":"Point"}
}