{
  "type": "Feature",
  "properties": {
    "addr:full":"Calle de Casca, 3 Iscar Valladolid 47420",
    "addr:housenumber":"3",
    "addr:postcode":"47420",
    "addr:street":"Calle De Casca",
    "iso:country":"ES",
    "sg:address":"Calle de Casca, 3",
    "sg:city":"Iscar",
    "sg:orig_category":"Carnicer\u00cdas, Carnicer\u00cdas",
    "sg:phone":"+34 983 61 11 02",
    "sg:postcode":"47420",
    "sg:province":"Valladolid",
    "wof:name":"Caviedes Velasco Francisco Javier",
    "wof:placetype":"venue"
},
  "geometry": {"coordinates":[-4.5298967361,41.3638687134],"type":"Point"}
}