{
  "type": "Feature",
  "properties": {
    "addr:full":"Calle de Alcala, 363 Madrid Madrid 28027",
    "addr:housenumber":"363",
    "addr:postcode":"28027",
    "addr:street":"Calle De Alcala",
    "iso:country":"ES",
    "sg:address":"Calle de Alcala, 363",
    "sg:city":"Madrid",
    "sg:orig_category":"Farmacias",
    "sg:phone":"+34 913 67 36 13",
    "sg:postcode":"28027",
    "sg:province":"Madrid",
    "wof:name":"Bocanegra Grau Nuria",
    "wof:placetype":"venue"
},
  "geometry": {"coordinates":[-3.6448373795,40.4347038269],"type":"Point"}
}