{
  "type": "Feature",
  "properties": {
    "addr:full":"Luga Laba\u00d1ou, S/n Coru\u00d1a La Coru\u00f1a 15011",
    "addr:housenumber":"s",
    "addr:postcode":"15011",
    "addr:street":"/ N Corun\u0303A La Corun\u0303A",
    "iso:country":"ES",
    "sg:address":"Luga Laba\u00d1ou, S/n",
    "sg:city":"Coru\u00d1a",
    "sg:orig_category":"Carnicer\u00cdas, Carnicer\u00cdas",
    "sg:phone":"+34 981 26 02 89",
    "sg:postcode":"15011",
    "sg:province":"La Coru\u00f1a",
    "wof:name":"Fernandez Hermida Jose",
    "wof:placetype":"venue"
},
  "geometry": {"coordinates":[-8.4485845566,43.3661346436],"type":"Point"}
}