{
  "type": "Feature",
  "properties": {
    "iso:country":"ES",
    "sg:address":"Calle de Ramon Y Cajal, S/n",
    "sg:city":"Coru\u00d1a",
    "sg:orig_category":"Ropa Para Se\u00d1oras (al Por Menor)",
    "sg:phone":"+34 981 23 20 15",
    "sg:postcode":"15006",
    "sg:province":"A Coru\u00f1a",
    "sg:website":"www.zara.com",
    "wof:name":"Zara Espa\u00f1a S.a.",
    "wof:placetype":"venue"
},
  "geometry": {"coordinates":[-8.4019117355,43.3559761047],"type":"Point"}
}