{
  "type": "Feature",
  "properties": {
    "addr:full":"Plaz Jesus, 14 Utiel Valencia 46300",
    "addr:housenumber":"14",
    "addr:postcode":"46300",
    "addr:street":"Utiel",
    "iso:country":"ES",
    "sg:address":"Plaz Jesus, 14",
    "sg:city":"Utiel",
    "sg:orig_category":"Asociaciones Y Clubs Deportivos",
    "sg:phone":"+34 962 17 03 60",
    "sg:postcode":"46300",
    "sg:province":"Valencia",
    "wof:name":"Moya Martinez Angel",
    "wof:placetype":"venue"
},
  "geometry": {"coordinates":[-1.2038509846,39.5675544739],"type":"Point"}
}