{
  "type": "Feature",
  "properties": {
    "addr:full":"Calle de Matematico Pedrayes, 20 Oviedo Asturias 33004",
    "addr:housenumber":"20",
    "addr:postcode":"33004",
    "addr:street":"Calle De Matematico Pedrayes",
    "iso:country":"ES",
    "sg:address":"Calle de Matematico Pedrayes, 20",
    "sg:city":"Oviedo",
    "sg:orig_category":"Abogados",
    "sg:phone":"+34 985 23 55 80",
    "sg:postcode":"33004",
    "sg:province":"Asturias",
    "wof:name":"Rafael Bondi Cernuda",
    "wof:placetype":"venue"
},
  "geometry": {"coordinates":[-5.85587883,43.3628997803],"type":"Point"}
}