{
  "type": "Feature",
  "properties": {
    "addr:full":"Avda Constitucion (de La), 49 Mostoles Madrid 28931",
    "addr:housenumber":"49",
    "addr:postcode":"28931",
    "addr:street":"Avda Constitucion De La",
    "iso:country":"ES",
    "sg:address":"Avda Constitucion (de La), 49",
    "sg:city":"Mostoles",
    "sg:orig_category":"Frutas, Legumbres Frescas Y Tempranas (al Por Menor)",
    "sg:phone":"+34 916 17 75 27",
    "sg:postcode":"28931",
    "sg:province":"Madrid",
    "wof:name":"Cuenca Quiroga Felix",
    "wof:placetype":"venue"
},
  "geometry": {"coordinates":[-3.8609418869,40.3267745972],"type":"Point"}
}