{
  "type": "Feature",
  "properties": {
    "iso:country":"ES",
    "sg:address":"Carrer de Mallorca, 11",
    "sg:city":"Olesa Montserrat",
    "sg:orig_category":"Material Y Suministros Para Peluquer\u00cda",
    "sg:phone":"+34 937 75 94 48",
    "sg:postcode":"08640",
    "sg:province":"Barcelona",
    "wof:name":"Gonell Seguer Francisco Jose",
    "wof:placetype":"venue"
},
  "geometry": {"coordinates":[1.8919930458,41.543800354],"type":"Point"}
}