{
  "type": "Feature",
  "properties": {
    "addr:full":"Calle de Pedro Iv El Ceremonioso, 6 Zaragoza Zaragoza 50009",
    "addr:housenumber":"6",
    "addr:postcode":"50009",
    "addr:street":"Calle De Pedro Iv El Ceremonioso",
    "iso:country":"ES",
    "sg:address":"Calle de Pedro Iv El Ceremonioso, 6",
    "sg:city":"Zaragoza",
    "sg:orig_category":"Aceites Y Grasas Alimentarias (fabricaci\u00d3n, Al Por Mayor)",
    "sg:phone":"+34 976 35 33 98",
    "sg:postcode":"50009",
    "sg:province":"Zaragoza",
    "wof:name":"Aceites Ibericos Acisa S.a.",
    "wof:placetype":"venue"
},
  "geometry": {"coordinates":[-0.9051126242,41.6343002319],"type":"Point"}
}