{
  "type": "Feature",
  "properties": {
    "addr:full":"Avda Huelva De, 27 Lepe Huelva 21440",
    "addr:housenumber":"27",
    "addr:postcode":"21440",
    "addr:street":"Avda Huelva De",
    "iso:country":"ES",
    "sg:address":"Avda Huelva De, 27",
    "sg:city":"Lepe",
    "sg:classifiers":[
        {
            "category":"Casinos & Gambling",
            "type":"Entertainment"
        }
    ],
    "sg:phone":"+34 959 38 28 23",
    "sg:postcode":"21440",
    "sg:province":"Huelva",
    "sg:tags":[
        "locale",
        "de",
        "juego"
    ],
    "wof:name":"Sistelcom-telemensaje S.a.",
    "wof:placetype":"venue"
},
  "geometry": {"coordinates":[-7.1994271278,37.2599487305],"type":"Point"}
}