{
  "type": "Feature",
  "properties": {
    "addr:full":"Poligono Ventilla, S/n Sotillo Adrada \u00c1vila 05420",
    "addr:housenumber":"s / n",
    "addr:postcode":"05420",
    "addr:street":"Poligono Ventilla",
    "iso:country":"ES",
    "sg:address":"Poligono Ventilla, S/n",
    "sg:city":"Sotillo Adrada",
    "sg:orig_category":"Venta, Instalaci\u00d3n De Calefacci\u00d3n",
    "sg:phone":"+34 918 66 00 13",
    "sg:postcode":"05420",
    "sg:province":"\u00c1vila",
    "wof:name":"Suministros Candido Martin S.a.l.",
    "wof:placetype":"venue"
},
  "geometry": {"coordinates":[-4.5675840378,40.283164978],"type":"Point"}
}