{
  "type": "Feature",
  "properties": {
    "addr:full":"Carrer de Montmajor, 27 Barcelona Barcelona 08031",
    "addr:housenumber":"27",
    "addr:postcode":"08031",
    "addr:street":"Carrer De Montmajor",
    "iso:country":"ES",
    "sg:address":"Carrer de Montmajor, 27",
    "sg:city":"Barcelona",
    "sg:orig_category":"Organizaciones Internacionales",
    "sg:phone":"+34 934 07 01 85",
    "sg:postcode":"08031",
    "sg:province":"Barcelona",
    "wof:name":"Vida Y Libertad",
    "wof:placetype":"venue"
},
  "geometry": {"coordinates":[2.1707229614,41.4328727722],"type":"Point"}
}