{
  "type": "Feature",
  "properties": {
    "iso:country":"ES",
    "sg:address":"Plaz Mayor, 14",
    "sg:city":"Malpartida Plasencia",
    "sg:orig_category":"Cajas De Ahorro",
    "sg:phone":"+34 927 40 43 49",
    "sg:postcode":"10680",
    "sg:province":"C\u00e1ceres",
    "wof:name":"Caja De Ahorros Y Monte De Piedad De Extremadura",
    "wof:placetype":"venue"
},
  "geometry": {"coordinates":[-6.0462641716,39.9780693054],"type":"Point"}
}