{
  "type": "Feature",
  "properties": {
    "iso:country":"ES",
    "sg:address":"Pl Corona, 28",
    "sg:city":"Granollers",
    "sg:orig_category":"Ropa Para Ni\u00d1os (al Por Menor)",
    "sg:phone":"+34 938 70 70 64",
    "sg:postcode":"08402",
    "sg:province":"Barcelona",
    "wof:name":"Baby Blue S.l.",
    "wof:placetype":"venue"
},
  "geometry": {"coordinates":[2.2883458138,41.605594635],"type":"Point"}
}