{
  "type": "Feature",
  "properties": {
    "addr:full":"Calle de Navalcan, 11 Talavera Reina Toledo 45600",
    "addr:housenumber":"11",
    "addr:postcode":"45600",
    "addr:street":"Calle De Navalcan",
    "iso:country":"ES",
    "sg:address":"Calle de Navalcan, 11",
    "sg:city":"Talavera Reina",
    "sg:orig_category":"Confecci\u00d3n De Zapatos",
    "sg:phone":"+34 925 80 41 23",
    "sg:postcode":"45600",
    "sg:province":"Toledo",
    "wof:name":"Calzados De Talavera S.l.",
    "wof:placetype":"venue"
},
  "geometry": {"coordinates":[-4.8439798355,39.9592819214],"type":"Point"}
}