{
  "type": "Feature",
  "properties": {
    "iso:country":"ES",
    "sg:address":"Avda Luis Espada, 68",
    "sg:city":"Verin",
    "sg:orig_category":"Farmacias",
    "sg:phone":"+34 988 41 39 04",
    "sg:postcode":"32600",
    "sg:province":"Ourense",
    "wof:name":"Guillen Alonso Yolanda",
    "wof:placetype":"venue"
},
  "geometry": {"coordinates":[-7.437374115,41.9403381348],"type":"Point"}
}