{
  "type": "Feature",
  "properties": {
    "iso:country":"ES",
    "sg:address":"Guadalmina Plaza, 12",
    "sg:city":"San Pedro Alcantara",
    "sg:orig_category":"Inmobiliaria (agencias)",
    "sg:phone":"+34 952 88 21 62",
    "sg:postcode":"29670",
    "sg:province":"M\u00e1laga",
    "wof:name":"A Y R Arrendamientos S.l.",
    "wof:placetype":"venue"
},
  "geometry": {"coordinates":[-5.003718853,36.4735946655],"type":"Point"}
}