{
  "type": "Feature",
  "properties": {
    "addr:full":"Pl Gorriones, 2 Coria Rio Sevilla 41100",
    "addr:housenumber":"2",
    "addr:postcode":"41100",
    "addr:street":"Pl Gorriones;Rio Sevilla",
    "iso:country":"ES",
    "sg:address":"Pl Gorriones, 2",
    "sg:city":"Coria Rio",
    "sg:orig_category":"Transportes Internacionales",
    "sg:phone":"+34 954 77 45 13",
    "sg:postcode":"41100",
    "sg:province":"Sevilla",
    "wof:name":"Quivirtrans S.l.",
    "wof:placetype":"venue"
},
  "geometry": {"coordinates":[-6.0509738922,37.2873153687],"type":"Point"}
}