{
  "type": "Feature",
  "properties": {
    "addr:full":"Calle de Cap Ramonell Boix, 63 Palma Islas Baleares 07006",
    "addr:housenumber":"63",
    "addr:postcode":"07006",
    "addr:street":"Calle De Cap Ramonell Boix",
    "iso:country":"ES",
    "sg:address":"Calle de Cap Ramonell Boix, 63",
    "sg:city":"Palma",
    "sg:orig_category":"Cajas De Ahorro",
    "sg:phone":"+34 971 24 33 29",
    "sg:postcode":"07006",
    "sg:province":"Islas Baleares",
    "wof:name":"Savia Amadeus S.a.",
    "wof:placetype":"venue"
},
  "geometry": {"coordinates":[2.6756970882,39.559627533],"type":"Point"}
}