{
  "type": "Feature",
  "properties": {
    "iso:country":"ES",
    "sg:address":"Ctra Alharilla, Km. 0001,5",
    "sg:city":"Porcuna",
    "sg:orig_category":"Cooperativas Agr\u00cdcolas",
    "sg:phone":"+34 953 54 48 48",
    "sg:postcode":"23790",
    "sg:province":"Ja\u00e9n",
    "wof:name":"Sociedad Cooperativa Andaluza Agraria De Porcuna",
    "wof:placetype":"venue"
},
  "geometry": {"coordinates":[-4.1859688759,37.8754959106],"type":"Point"}
}