{
  "type": "Feature",
  "properties": {
    "iso:country":"ES",
    "sg:address":"Calle de Caballeros, 14",
    "sg:city":"Ciudad Real",
    "sg:orig_category":"Procuradores",
    "sg:phone":"+34 926 22 30 73",
    "sg:postcode":"13003",
    "sg:province":"Ciudad Real",
    "wof:name":"Baeza Diaz Portales Maria Del Carmen",
    "wof:placetype":"venue"
},
  "geometry": {"coordinates":[-3.9304189682,38.9883842468],"type":"Point"}
}