{
  "type": "Feature",
  "properties": {
    "iso:country":"ES",
    "sg:address":"Avda Manzanilla (la), S/n",
    "sg:city":"Jerez De La Frontera",
    "sg:orig_category":"Carnicer\u00cdas, Carnicer\u00cdas",
    "sg:phone":"+34 956 30 73 02",
    "sg:postcode":"11404",
    "sg:province":"C\u00e1diz",
    "wof:name":"Perez Guerrero Manuel",
    "wof:placetype":"venue"
},
  "geometry": {"coordinates":[-6.1462540627,36.6979141235],"type":"Point"}
}