{
  "type": "Feature",
  "properties": {
    "iso:country":"ES",
    "sg:address":"Calle de Doctor Juan Dominguez Perez, 10",
    "sg:city":"Palmas De Gran Canaria",
    "sg:orig_category":"Quincaller\u00cda (al Por Menor)",
    "sg:phone":"+34 928 47 53 84",
    "sg:postcode":"35008",
    "sg:province":"Las Palmas",
    "wof:name":"Anidia S.a.",
    "wof:placetype":"venue"
},
  "geometry": {"coordinates":[-15.4151639938,28.1567687988],"type":"Point"}
}