{
  "type": "Feature",
  "properties": {
    "iso:country":"ES",
    "sg:address":"Calle de Yeseros, 5",
    "sg:city":"Madrid",
    "sg:orig_category":"Mec\u00c1nico Del Autom\u00d3vil",
    "sg:phone":"+34 913 65 40 85",
    "sg:postcode":"28005",
    "sg:province":"Madrid",
    "wof:name":"Ortega Palao Juan Francisco",
    "wof:placetype":"venue"
},
  "geometry": {"coordinates":[-3.7143232822,40.4125785828],"type":"Point"}
}