{
  "type": "Feature",
  "properties": {
    "addr:full":"Ctra Guarnizo Villacarriedo, 12 Saron Cantabria 39620",
    "addr:housenumber":"12",
    "addr:postcode":"39620",
    "addr:street":"Ctra Guarnizo Villacarriedo",
    "iso:country":"ES",
    "sg:address":"Ctra Guarnizo Villacarriedo, 12",
    "sg:city":"Saron",
    "sg:orig_category":"Electricidad: Instaladores",
    "sg:phone":"+34 942 56 37 42",
    "sg:postcode":"39620",
    "sg:province":"Cantabria",
    "wof:name":"Electricidad Gutierrez S.l.",
    "wof:placetype":"venue"
},
  "geometry": {"coordinates":[-3.8524339199,43.3249206543],"type":"Point"}
}