{
  "type": "Feature",
  "properties": {
    "addr:full":"Avda Jose Maria Alcaraz Y Alenda, 3 Badajoz Badajoz 06011",
    "addr:housenumber":"3",
    "addr:postcode":"06011",
    "addr:street":"Avda Jose Maria Alcaraz Y Alenda",
    "iso:country":"ES",
    "sg:address":"Avda Jose Maria Alcaraz Y Alenda, 3",
    "sg:city":"Badajoz",
    "sg:orig_category":"Agencias De Viajes",
    "sg:phone":"+34 924 25 91 91",
    "sg:postcode":"06011",
    "sg:province":"Badajoz",
    "wof:name":"Douro Agencia De Viajes S.l.",
    "wof:placetype":"venue"
},
  "geometry": {"coordinates":[-6.9818410873,38.8714675903],"type":"Point"}
}