{
  "type": "Feature",
  "properties": {
    "addr:full":"Pg Tarongers, Dels, 7 Playa Valencia 46760",
    "addr:housenumber":"7",
    "addr:postcode":"46760",
    "addr:street":"Tarongers Dels;Valencia",
    "iso:country":"ES",
    "sg:address":"Pg Tarongers, Dels, 7",
    "sg:city":"Playa",
    "sg:orig_category":"Inmobiliaria (agencias)",
    "sg:phone":"+34 962 88 42 55",
    "sg:postcode":"46760",
    "sg:province":"Valencia",
    "wof:name":"Gonzalez Vercher Miguel",
    "wof:placetype":"venue"
},
  "geometry": {"coordinates":[-0.2594090104,39.0749702454],"type":"Point"}
}