{
  "type": "Feature",
  "properties": {
    "iso:country":"ES",
    "sg:address":"Calle de Villamanin, 52",
    "sg:city":"Madrid",
    "sg:classifiers":[
        {
            "category":"Banks & Credit Unions",
            "subcategory":"Bureau De Change",
            "type":"Services"
        }
    ],
    "sg:phone":"+34 914 63 28 26",
    "sg:postcode":"28011",
    "sg:province":"Madrid",
    "sg:tags":[
        "organismos",
        "control"
    ],
    "wof:name":"Peyco Proyectos Y Construcciones S.a.",
    "wof:placetype":"venue"
},
  "geometry": {"coordinates":[-3.753557682,40.4058609009],"type":"Point"}
}