{
  "type": "Feature",
  "properties": {
    "addr:full":"Francesc Crusats, 16 Selva Del Camp Tarragona 43470",
    "addr:housenumber":"16",
    "addr:postcode":"43470",
    "addr:street":"Crusats",
    "iso:country":"ES",
    "sg:address":"Francesc Crusats, 16",
    "sg:city":"Selva Del Camp",
    "sg:orig_category":"Centros De Educaci\u00d3n Especial",
    "sg:phone":"+34 977 84 40 42",
    "sg:postcode":"43470",
    "sg:province":"Tarragona",
    "wof:name":"Ajuntament De La Selva Del Camp",
    "wof:placetype":"venue"
},
  "geometry": {"coordinates":[1.1257082224,41.2050590515],"type":"Point"}
}