{
  "type": "Feature",
  "properties": {
    "addr:full":"Calle de Segunda Del Campo, 14 Felix Almer\u00eda 04739",
    "addr:housenumber":"14",
    "addr:postcode":"04739",
    "addr:street":"Calle De Segunda Del Campo;Felix Almeri\u0301A",
    "iso:country":"ES",
    "sg:address":"Calle de Segunda Del Campo, 14",
    "sg:city":"Felix",
    "sg:orig_category":"Aceites Y Grasas Alimentarias (fabricaci\u00d3n, Al Por Mayor)",
    "sg:phone":"+34 950 55 97 40",
    "sg:postcode":"04739",
    "sg:province":"Almer\u00eda",
    "wof:name":"Almazara De Felix S.c.a.",
    "wof:placetype":"venue"
},
  "geometry": {"coordinates":[-2.6598684788,36.8684883118],"type":"Point"}
}