{
  "type": "Feature",
  "properties": {
    "iso:country":"ES",
    "sg:address":"Carrer de Balletbo, S/n",
    "sg:city":"Viladecans",
    "sg:orig_category":"Electricidad: Instaladores",
    "sg:phone":"+34 936 58 28 88",
    "sg:postcode":"08840",
    "sg:province":"Barcelona",
    "wof:name":"Proyectos Y Montajes Nuri S.l.",
    "wof:placetype":"venue"
},
  "geometry": {"coordinates":[2.017179966,41.3163261414],"type":"Point"}
}