{
  "type": "Feature",
  "properties": {
    "iso:country":"ES",
    "sg:address":"Calle de Brasil, 22",
    "sg:city":"Gijon",
    "sg:orig_category":"Frutas, Legumbres Frescas Y Tempranas (al Por Menor)",
    "sg:phone":"+34 985 32 67 88",
    "sg:postcode":"33213",
    "sg:province":"Asturias",
    "wof:name":"Paniagua Garcia Albertoano",
    "wof:placetype":"venue"
},
  "geometry": {"coordinates":[-5.7001419067,43.5402755737],"type":"Point"}
}