{
  "type": "Feature",
  "properties": {
    "iso:country":"ES",
    "sg:address":"Avda Aurora, 18",
    "sg:city":"Malaga",
    "sg:orig_category":"Perfumer\u00cda (al Por Menor)",
    "sg:phone":"+34 952 32 55 03",
    "sg:postcode":"29002",
    "sg:province":"M\u00e1laga",
    "sg:website":"www.espejo-perfumerias.com",
    "wof:name":"Espejo Hermanos S. A.",
    "wof:placetype":"venue"
},
  "geometry": {"coordinates":[-4.4305100441,36.7161560059],"type":"Point"}
}