{
  "type": "Feature",
  "properties": {
    "addr:full":"Plaz San Juan De Los Lagos, 2 Burgos Burgos 09006",
    "addr:housenumber":"2",
    "addr:postcode":"09006",
    "addr:street":"Plaz San Juan De Los Lagos",
    "iso:country":"ES",
    "sg:address":"Plaz San Juan De Los Lagos, 2",
    "sg:city":"Burgos",
    "sg:orig_category":"Escayola Y Productos De Escayola (fabricaci\u00d3n, Al Por Mayor)",
    "sg:phone":"+34 947 23 99 62",
    "sg:postcode":"09006",
    "sg:province":"Burgos",
    "wof:name":"Garcia Salvador Santiago",
    "wof:placetype":"venue"
},
  "geometry": {"coordinates":[-3.6855568886,42.3546714783],"type":"Point"}
}