{
  "type": "Feature",
  "properties": {
    "iso:country":"ES",
    "sg:address":"Calle de San Francisco, S/n",
    "sg:city":"Le\u00f3n",
    "sg:orig_category":"Sindicatos De Trabajadores",
    "sg:phone":"+34 987 24 96 15",
    "sg:postcode":"24003",
    "sg:province":"Le\u00f3n",
    "wof:name":"Central Sindical Independiente Y De Funcionarios",
    "wof:placetype":"venue"
},
  "geometry": {"coordinates":[-5.5700387955,42.5943374634],"type":"Point"}
}