{
  "type": "Feature",
  "properties": {
    "addr:full":"Calle de Guillen De Castro, 9 Malaga M\u00e1laga 29005",
    "addr:housenumber":"9",
    "addr:postcode":"29005",
    "addr:street":"Calle De Guillen De Castro;Ma\u0301Laga",
    "iso:country":"ES",
    "sg:address":"Calle de Guillen De Castro, 9",
    "sg:city":"Malaga",
    "sg:orig_category":"Florister\u00cdas",
    "sg:phone":"+34 952 60 15 70",
    "sg:postcode":"29005",
    "sg:province":"M\u00e1laga",
    "wof:name":"Garcia Zayas Florymar S.l.",
    "wof:placetype":"venue"
},
  "geometry": {"coordinates":[-4.4235730171,36.7183303833],"type":"Point"}
}