{
  "type": "Feature",
  "properties": {
    "iso:country":"ES",
    "sg:address":"Calle de Fola, 9",
    "sg:city":"Castellon",
    "sg:orig_category":"Abogados",
    "sg:phone":"+34 964 23 67 08",
    "sg:postcode":"12002",
    "sg:province":"Castell\u00f3n",
    "wof:name":"Castellanos Martinez Luis",
    "wof:placetype":"venue"
},
  "geometry": {"coordinates":[-0.0382389985,39.9826202393],"type":"Point"}
}