{
  "type": "Feature",
  "properties": {
    "iso:country":"ES",
    "sg:address":"Avda Real Academia De Medicina, 1",
    "sg:city":"Ranero",
    "sg:orig_category":"Agencias De Viajes",
    "sg:phone":"+34 968 27 47 10",
    "sg:postcode":"30100",
    "sg:province":"Murcia",
    "wof:name":"Calipso Vacaciones S. A",
    "wof:placetype":"venue"
},
  "geometry": {"coordinates":[-1.153594017,38.0103034973],"type":"Point"}
}