{
  "type": "Feature",
  "properties": {
    "addr:full":"Av Mare Deu De Montserrat, 135 Barcelona Barcelona 08041",
    "addr:housenumber":"135",
    "addr:postcode":"08041",
    "addr:street":"Av Mare;De Montserrat",
    "iso:country":"ES",
    "sg:address":"Av Mare Deu De Montserrat, 135",
    "sg:city":"Barcelona",
    "sg:orig_category":"Quincaller\u00cda (al Por Menor)",
    "sg:phone":"+34 934 36 02 09",
    "sg:postcode":"08041",
    "sg:province":"Barcelona",
    "wof:name":"Fernandez Varela Lourdes",
    "wof:placetype":"venue"
},
  "geometry": {"coordinates":[2.1700189114,41.4164924622],"type":"Point"}
}