{
  "type": "Feature",
  "properties": {
    "iso:country":"ES",
    "sg:address":"Manuel W Guimbarda, 31",
    "sg:city":"Cartagena",
    "sg:orig_category":"Pescader\u00cdas (al Por Menor)",
    "sg:phone":"+34 968 50 62 55",
    "sg:postcode":"30204",
    "sg:province":"Murcia",
    "wof:name":"Sanchez Aguera Francisco",
    "wof:placetype":"venue"
},
  "geometry": {"coordinates":[-0.9865480065,37.6104850769],"type":"Point"}
}