{
  "type": "Feature",
  "properties": {
    "addr:full":"Plaz Matadero (del), 5 Estepa Sevilla 41560",
    "addr:postcode":"41560",
    "addr:street":"Plaz;Del;Estepa Sevilla",
    "iso:country":"ES",
    "sg:address":"Plaz Matadero (del), 5",
    "sg:city":"Estepa",
    "sg:orig_category":"Empresarios",
    "sg:phone":"+34 955 91 33 87",
    "sg:postcode":"41560",
    "sg:province":"Sevilla",
    "wof:name":"Fundacion Red Andalucia Emprende",
    "wof:placetype":"venue"
},
  "geometry": {"coordinates":[-4.8781452179,37.2889785767],"type":"Point"}
}