{
  "type": "Feature",
  "properties": {
    "addr:full":"Cmno Alcoraya, S/n Alacant Alicante 03006",
    "addr:housenumber":"s / n",
    "addr:postcode":"03006",
    "addr:street":"Cmno Alcoraya",
    "iso:country":"ES",
    "sg:address":"Cmno Alcoraya, S/n",
    "sg:city":"Alacant",
    "sg:orig_category":"Fabricaci\u00d3n De Productos Textiles Sin Tejer",
    "sg:phone":"+34 965 28 54 18",
    "sg:postcode":"03006",
    "sg:province":"Alicante",
    "wof:name":"Alicortex S.l.l.",
    "wof:placetype":"venue"
},
  "geometry": {"coordinates":[-0.529948175,38.3534584045],"type":"Point"}
}