{
  "type": "Feature",
  "properties": {
    "addr:full":"Calle de Marques De Jura Real, 34 Madrid Madrid 28019",
    "addr:housenumber":"34",
    "addr:postcode":"madrid;28019",
    "addr:street":"Calle De Marques De Jura Real",
    "iso:country":"ES",
    "sg:address":"Calle de Marques De Jura Real, 34",
    "sg:city":"Madrid",
    "sg:orig_category":"Centro De Estudios",
    "sg:phone":"+34 914 69 09 42",
    "sg:postcode":"28019",
    "sg:province":"Madrid",
    "wof:name":"Perez-chirinos Del Rio Sonia Maria",
    "wof:placetype":"venue"
},
  "geometry": {"coordinates":[-3.7122297287,40.3906517029],"type":"Point"}
}