{
  "type": "Feature",
  "properties": {
    "iso:country":"ES",
    "sg:address":"Carr Nou, 1",
    "sg:city":"Boadella D'emporda",
    "sg:orig_category":"Centros De Educaci\u00d3n Especial",
    "sg:phone":"+34 972 56 91 27",
    "sg:postcode":"17706",
    "sg:province":"Girona",
    "wof:name":"Generalitat De Catalunya",
    "wof:placetype":"venue"
},
  "geometry": {"coordinates":[2.8570103645,42.330821991],"type":"Point"}
}