{
  "type": "Feature",
  "properties": {
    "iso:country":"ES",
    "sg:address":"Calle de Arturo Soria, 105",
    "sg:city":"Madrid",
    "sg:orig_category":"Cl\u00cdnicas M\u00c9dicas",
    "sg:phone":"+34 915 10 06 03",
    "sg:postcode":"28043",
    "sg:province":"Madrid",
    "wof:name":"Merino Abad Y Asociados S.l.",
    "wof:placetype":"venue"
},
  "geometry": {"coordinates":[-3.6519436836,40.4502105713],"type":"Point"}
}