{
  "type": "Feature",
  "properties": {
    "addr:full":"Pla\u00c7 Pla\u00c7a Major, 50 Alzira Valencia 46600",
    "addr:housenumber":"50",
    "addr:postcode":"46600",
    "addr:street":"Major",
    "iso:country":"ES",
    "sg:address":"Pla\u00c7 Pla\u00c7a Major, 50",
    "sg:city":"Alzira",
    "sg:orig_category":"Agencias De Viajes",
    "sg:phone":"+34 962 40 34 18",
    "sg:postcode":"46600",
    "sg:province":"Valencia",
    "wof:name":"Viajes Agullo S.l.",
    "wof:placetype":"venue"
},
  "geometry": {"coordinates":[-0.4378489852,39.1517295837],"type":"Point"}
}