{
  "type": "Feature",
  "properties": {
    "iso:country":"ES",
    "sg:address":"Avda Regne De Valencia, 74",
    "sg:city":"Valencia",
    "sg:orig_category":"Peleter\u00cdas",
    "sg:phone":"+34 963 74 16 82",
    "sg:postcode":"46005",
    "sg:province":"Valencia",
    "wof:name":"Lopez Yuste Julia",
    "wof:placetype":"venue"
},
  "geometry": {"coordinates":[-0.3641749918,39.4627113342],"type":"Point"}
}