{
  "type": "Feature",
  "properties": {
    "addr:full":"Avda Bruselas, S/n Alacant Alicante 03540",
    "addr:housenumber":"s / n",
    "addr:postcode":"03540",
    "addr:street":"Avda Bruselas",
    "iso:country":"ES",
    "sg:address":"Avda Bruselas, S/n",
    "sg:city":"Alacant",
    "sg:orig_category":"Ropa Para Se\u00d1oras (al Por Menor)",
    "sg:phone":"+34 965 26 68 04",
    "sg:postcode":"03540",
    "sg:province":"Alicante",
    "wof:name":"Pleite Esteso Victoria",
    "wof:placetype":"venue"
},
  "geometry": {"coordinates":[-0.4135789871,38.3707199097],"type":"Point"}
}