{
  "type": "Feature",
  "properties": {
    "iso:country":"ES",
    "sg:address":"Calle de Doctor Sanchez Mariscal, 5",
    "sg:city":"Granada",
    "sg:orig_category":"Librer\u00cdas",
    "sg:phone":"+34 958 16 28 71",
    "sg:postcode":"18012",
    "sg:province":"Granada",
    "wof:name":"Bazan Arbol Maria Jose",
    "wof:placetype":"venue"
},
  "geometry": {"coordinates":[-3.6077139378,37.1912384033],"type":"Point"}
}