{
  "type": "Feature",
  "properties": {
    "iso:country":"ES",
    "sg:address":"Calle de Pedro Sarmiento De Gamboa, 1",
    "sg:city":"Alcala Henares",
    "sg:classifiers":[
        {
            "category":"Personal",
            "subcategory":"Barber",
            "type":"Services"
        }
    ],
    "sg:phone":"+34 918 82 67 98",
    "sg:postcode":"28805",
    "sg:province":"Madrid",
    "sg:tags":[
        "caballeros",
        "de",
        "peluqueros"
    ],
    "wof:name":"Ciruelos Gomez Tomas",
    "wof:placetype":"venue"
},
  "geometry": {"coordinates":[-3.3607649803,40.4897117615],"type":"Point"}
}