{
  "type": "Feature",
  "properties": {
    "iso:country":"ES",
    "sg:address":"Calle de Santa Engracia, 48",
    "sg:city":"Madrid",
    "sg:orig_category":"Aparcamientos (infraestructuras, Accesorios)",
    "sg:phone":"+34 915 93 18 65",
    "sg:postcode":"28010",
    "sg:province":"Madrid",
    "wof:name":"Galdos S. A.",
    "wof:placetype":"venue"
},
  "geometry": {"coordinates":[-3.6980569363,40.4338264465],"type":"Point"}
}