{
  "type": "Feature",
  "properties": {
    "iso:country":"ES",
    "sg:address":"Avda Golf (del), 168",
    "sg:city":"Altorreal",
    "sg:orig_category":"Agencias Y Agentes Comerciales, Representantes",
    "sg:phone":"+34 968 64 89 09",
    "sg:postcode":"30500",
    "sg:province":"Murcia",
    "wof:name":"Vidal Romero Juan",
    "wof:placetype":"venue"
},
  "geometry": {"coordinates":[-1.2119740248,38.0535736084],"type":"Point"}
}