{
  "type": "Feature",
  "properties": {
    "iso:country":"ES",
    "sg:address":"Calle de Cervantes, 9",
    "sg:city":"Villanueva De Los Infantes",
    "sg:orig_category":"Bancos",
    "sg:phone":"+34 926 36 13 37",
    "sg:postcode":"13320",
    "sg:province":"Ciudad Real",
    "wof:name":"Banco Espa\u00f1ol De Credito S.a.",
    "wof:placetype":"venue"
},
  "geometry": {"coordinates":[-3.0122520924,38.7345466614],"type":"Point"}
}