{
  "type": "Feature",
  "properties": {
    "addr:full":"Calle de Barranquilla De Colombia, S/n Nerja M\u00e1laga 29780",
    "addr:housenumber":"s / n",
    "addr:postcode":"29780",
    "addr:street":"Calle De Barranquilla De Colombia",
    "iso:country":"ES",
    "sg:address":"Calle de Barranquilla De Colombia, S/n",
    "sg:city":"Nerja",
    "sg:orig_category":"Iglesia Cat\u00d3lica",
    "sg:phone":"+34 952 52 19 95",
    "sg:postcode":"29780",
    "sg:province":"M\u00e1laga",
    "wof:name":"Obispado De Malaga",
    "wof:placetype":"venue"
},
  "geometry": {"coordinates":[-3.8747754097,36.750995636],"type":"Point"}
}