{
  "type": "Feature",
  "properties": {
    "addr:full":"Calle de Cuesta De Las Vi\u00d1as, 6 Santurtzi Vizcaya 48980",
    "addr:housenumber":"6",
    "addr:postcode":"48980",
    "addr:street":"Calle De Cuesta De Las Vin\u0303As",
    "iso:country":"ES",
    "sg:address":"Calle de Cuesta De Las Vi\u00d1as, 6",
    "sg:city":"Santurtzi",
    "sg:classifiers":[
        {
            "category":"Taxi",
            "type":"Transportation"
        }
    ],
    "sg:phone":"+34 944 83 79 07",
    "sg:postcode":"48980",
    "sg:province":"Vizcaya",
    "wof:name":"Campo Ruiz Fernando",
    "wof:placetype":"venue"
},
  "geometry": {"coordinates":[-3.037364006,43.3303527832],"type":"Point"}
}