{
  "type": "Feature",
  "properties": {
    "iso:country":"ES",
    "sg:address":"Calle de Tienda, 23",
    "sg:city":"Valdemorillo",
    "sg:orig_category":"Controles De Edificaci\u00d3n (construcci\u00d3n, Seguridad)",
    "sg:phone":"+34 918 97 87 08",
    "sg:postcode":"28210",
    "sg:province":"Madrid",
    "wof:name":"Gepical S.l",
    "wof:placetype":"venue"
},
  "geometry": {"coordinates":[-4.0722160339,40.501739502],"type":"Point"}
}