{
  "type": "Feature",
  "properties": {
    "addr:full":"Carr Impressors Oliva, 5 Girona Girona 17001",
    "addr:housenumber":"5",
    "addr:postcode":"17001",
    "addr:street":"Carr Impressors Oliva",
    "iso:country":"ES",
    "sg:address":"Carr Impressors Oliva, 5",
    "sg:city":"Girona",
    "sg:orig_category":"Fisioterapia",
    "sg:phone":"+34 972 21 03 03",
    "sg:postcode":"17001",
    "sg:province":"Girona",
    "wof:name":"Armengol Niell Carme",
    "wof:placetype":"venue"
},
  "geometry": {"coordinates":[2.8154735565,41.9829788208],"type":"Point"}
}