{
  "type": "Feature",
  "properties": {
    "addr:full":"Calle de Andalucia, 14 Durcal Granada 18650",
    "addr:housenumber":"14",
    "addr:postcode":"18650",
    "addr:street":"Calle De Andalucia",
    "iso:country":"ES",
    "sg:address":"Calle de Andalucia, 14",
    "sg:city":"Durcal",
    "sg:classifiers":[
        {
            "category":"Taxi",
            "type":"Transportation"
        }
    ],
    "sg:phone":"+34 958 78 08 80",
    "sg:postcode":"18650",
    "sg:province":"Granada",
    "wof:name":"Alarcon Melguizo Francisco",
    "wof:placetype":"venue"
},
  "geometry": {"coordinates":[-3.5689640045,36.9902839661],"type":"Point"}
}