{
  "type": "Feature",
  "properties": {
    "iso:country":"ES",
    "sg:address":"Ctra Valverde, Km. 0002,8",
    "sg:city":"Badajoz",
    "sg:orig_category":"Asesor\u00cda Sobre Comunicaci\u00d3n De Empresas",
    "sg:phone":"+34 924 26 75 41",
    "sg:postcode":"06010",
    "sg:province":"Badajoz",
    "wof:name":"Asesor.merc.fisc.y Financ.de Badajoz S.l",
    "wof:placetype":"venue"
},
  "geometry": {"coordinates":[-6.9605979919,38.7867279053],"type":"Point"}
}