{
  "type": "Feature",
  "properties": {
    "iso:country":"ES",
    "sg:address":"Av Verge Montserrat, 47",
    "sg:city":"Prat Llobregat",
    "sg:orig_category":"Agencias Y Asesores De Publicidad",
    "sg:phone":"+34 933 79 98 74",
    "sg:postcode":"08820",
    "sg:province":"Barcelona",
    "wof:name":"Lumps Of Sugart",
    "wof:placetype":"venue"
},
  "geometry": {"coordinates":[2.0987401009,41.3270645142],"type":"Point"}
}