{
  "type": "Feature",
  "properties": {
    "addr:full":"Calle de Gran Via, 5 Zaragoza Zaragoza 50006",
    "addr:housenumber":"5",
    "addr:postcode":"50006",
    "addr:street":"Calle De Gran Via",
    "iso:country":"ES",
    "sg:address":"Calle de Gran Via, 5",
    "sg:city":"Zaragoza",
    "sg:orig_category":"Centros Empresariales",
    "sg:phone":"+34 976 21 43 05",
    "sg:postcode":"50006",
    "sg:province":"Zaragoza",
    "wof:name":"Asociacion Provincial De Centros De Ense\u00f1anza",
    "wof:placetype":"venue"
},
  "geometry": {"coordinates":[-0.886141181,41.6467247009],"type":"Point"}
}