{
  "type": "Feature",
  "properties": {
    "iso:country":"ES",
    "sg:address":"Calle de Huesca, 74",
    "sg:city":"Logro\u00f1o",
    "sg:orig_category":"Muebles, Minoristas",
    "sg:phone":"+34 941 22 08 96",
    "sg:postcode":"26005",
    "sg:province":"La Rioja",
    "wof:name":"Balanza Mateo Jose Carlos",
    "wof:placetype":"venue"
},
  "geometry": {"coordinates":[-2.4572570324,42.4611663818],"type":"Point"}
}