{
  "type": "Feature",
  "properties": {
    "iso:country":"ES",
    "sg:address":"Carrer de Borriana, 15",
    "sg:city":"Barcelona",
    "sg:orig_category":"Abrasivos Y Superabrasivos (fabricaci\u00d3n, Al Por Mayor)",
    "sg:phone":"+34 933 00 89 55",
    "sg:postcode":"08030",
    "sg:province":"Barcelona",
    "wof:name":"Bma Aplicaciones De Abrasivos S.l.",
    "wof:placetype":"venue"
},
  "geometry": {"coordinates":[2.190737009,41.4304351807],"type":"Point"}
}