{
  "type": "Feature",
  "properties": {
    "addr:full":"Calle de Atalde, S/n Bermeo Vizcaya 48370",
    "addr:housenumber":"s / n",
    "addr:postcode":"48370",
    "addr:street":"Calle De Atalde",
    "iso:country":"ES",
    "sg:address":"Calle de Atalde, S/n",
    "sg:city":"Bermeo",
    "sg:orig_category":"Centros De Educaci\u00d3n Especial",
    "sg:phone":"+34 946 88 44 41",
    "sg:postcode":"48370",
    "sg:province":"Vizcaya",
    "wof:name":"Gobierno Vasco-eusko Jaurlaritza",
    "wof:placetype":"venue"
},
  "geometry": {"coordinates":[-2.7271285057,43.4212493896],"type":"Point"}
}