{
  "type": "Feature",
  "properties": {
    "addr:full":"Calle de Galileo, 94 Madrid Madrid 28015",
    "addr:housenumber":"94",
    "addr:postcode":"madrid;28015",
    "addr:street":"Calle De Galileo",
    "iso:country":"ES",
    "sg:address":"Calle de Galileo, 94",
    "sg:city":"Madrid",
    "sg:orig_category":"M\u00c1quinas De Escribir, M\u00c1quinas De Oficina (al Por Menor, Reparaci\u00d3n)",
    "sg:phone":"+34 915 34 49 35",
    "sg:postcode":"28015",
    "sg:province":"Madrid",
    "wof:name":"Rial Dominguez Alfonso",
    "wof:placetype":"venue"
},
  "geometry": {"coordinates":[-3.7098019123,40.4381866455],"type":"Point"}
}