{
  "type": "Feature",
  "properties": {
    "addr:full":"Calle de Victor Pradera, 4 Chipiona C\u00e1diz 11550",
    "addr:housenumber":"4",
    "addr:postcode":"11550",
    "addr:street":"Calle De Victor Pradera",
    "iso:country":"ES",
    "sg:address":"Calle de Victor Pradera, 4",
    "sg:city":"Chipiona",
    "sg:orig_category":"Cajas De Ahorro",
    "sg:phone":"+34 956 37 01 87",
    "sg:postcode":"11550",
    "sg:province":"C\u00e1diz",
    "sg:website":"www.unicaja.es",
    "wof:name":"Unicaja",
    "wof:placetype":"venue"
},
  "geometry": {"coordinates":[-6.4354429245,36.7374343872],"type":"Point"}
}