{
  "type": "Feature",
  "properties": {
    "addr:full":"Calle de Sacramento, 65 Cadiz C\u00e1diz 11003",
    "addr:housenumber":"65",
    "addr:postcode":"11003",
    "addr:street":"Calle De Sacramento",
    "iso:country":"ES",
    "sg:address":"Calle de Sacramento, 65",
    "sg:city":"Cadiz",
    "sg:orig_category":"Estancos",
    "sg:phone":"+34 956 22 15 24",
    "sg:postcode":"11003",
    "sg:province":"C\u00e1diz",
    "wof:name":"Fernandez Barbales Jose Luis",
    "wof:placetype":"venue"
},
  "geometry": {"coordinates":[-6.301194191,36.5331001282],"type":"Point"}
}