{
  "type": "Feature",
  "properties": {
    "iso:country":"ES",
    "sg:address":"Calle de Virgen De Fatima, 18",
    "sg:city":"Alacant",
    "sg:orig_category":"Empresas De Limpieza",
    "sg:phone":"+34 965 11 62 71",
    "sg:postcode":"03006",
    "sg:province":"Alicante",
    "wof:name":"Hydraldana Siglo Xxi S.l.",
    "wof:placetype":"venue"
},
  "geometry": {"coordinates":[-0.5153840184,38.3469924927],"type":"Point"}
}