{
  "type": "Feature",
  "properties": {
    "addr:full":"Calle de Estambul, 30 Alcorcon Madrid 28...",
    "addr:housenumber":"30;28 ...",
    "addr:street":"Calle De Estambul;Madrid",
    "iso:country":"ES",
    "sg:address":"Calle de Estambul, 30",
    "sg:city":"Alcorcon",
    "sg:orig_category":"Hospitales",
    "sg:phone":"+34 916 49 66 00",
    "sg:postcode":"28...",
    "sg:province":"Madrid",
    "wof:name":"Hospital Sur S.l.",
    "wof:placetype":"venue"
},
  "geometry": {"coordinates":[-3.8488481045,40.342628479],"type":"Point"}
}