{
  "type": "Feature",
  "properties": {
    "addr:full":"Calle de Zacarias Martinez, 13 Huesca Huesca 22006",
    "addr:housenumber":"13",
    "addr:postcode":"22006",
    "addr:street":"Calle De Zacarias Martinez",
    "iso:country":"ES",
    "sg:address":"Calle de Zacarias Martinez, 13",
    "sg:city":"Huesca",
    "sg:orig_category":"Promotores Constructores",
    "sg:phone":"+34 974 22 34 11",
    "sg:postcode":"22006",
    "sg:province":"Huesca",
    "wof:name":"Hermanos Zamora S.cv.",
    "wof:placetype":"venue"
},
  "geometry": {"coordinates":[-0.3940320015,42.141166687],"type":"Point"}
}