{
  "type": "Feature",
  "properties": {
    "addr:full":"Rbla Principal, 51 Vilanova I La Geltru Barcelona 08800",
    "addr:housenumber":"51",
    "addr:postcode":"08800",
    "addr:street":"Rbla Principal",
    "iso:country":"ES",
    "sg:address":"Rbla Principal, 51",
    "sg:city":"Vilanova I La Geltru",
    "sg:orig_category":"Asesor\u00cda Sobre Comunicaci\u00d3n De Empresas",
    "sg:phone":"+34 938 16 57 19",
    "sg:postcode":"08800",
    "sg:province":"Barcelona",
    "wof:name":"V.n. Grup S.a.",
    "wof:placetype":"venue"
},
  "geometry": {"coordinates":[1.7251261473,41.2235221863],"type":"Point"}
}