{
  "type": "Feature",
  "properties": {
    "addr:full":"Ctra Alicante, Km. 0002,0 Elche Alicante 03202",
    "addr:postcode":"03202",
    "addr:street":"Ctra Alicante Km. 0002,0",
    "iso:country":"ES",
    "sg:address":"Ctra Alicante, Km. 0002,0",
    "sg:city":"Elche",
    "sg:orig_category":"Negocio De Enlosados, Soler\u00cdas",
    "sg:phone":"+34 966 61 30 87",
    "sg:postcode":"03202",
    "sg:province":"Alicante",
    "sg:website":"www.keraben.com",
    "wof:name":"Keraben Tiendas S.l.",
    "wof:placetype":"venue"
},
  "geometry": {"coordinates":[-0.672706008,38.2721786499],"type":"Point"}
}