{
  "type": "Feature",
  "properties": {
    "addr:full":"Avda David Lario, 3 Calamocha Teruel 44200",
    "addr:housenumber":"3",
    "addr:postcode":"44200",
    "addr:street":"Avda David Lario",
    "iso:country":"ES",
    "sg:address":"Avda David Lario, 3",
    "sg:city":"Calamocha",
    "sg:orig_category":"Quincaller\u00cda (al Por Menor)",
    "sg:phone":"+34 978 73 04 85",
    "sg:postcode":"44200",
    "sg:province":"Teruel",
    "wof:name":"Sanchez Valero Antonio",
    "wof:placetype":"venue"
},
  "geometry": {"coordinates":[-1.2978429794,40.9190864563],"type":"Point"}
}