{
  "type": "Feature",
  "properties": {
    "iso:country":"ES",
    "sg:address":"Calle de Isaac Peral, 7",
    "sg:city":"Mazarron",
    "sg:orig_category":"Sociedades, Compa\u00d1\u00cdas Aseguradoras",
    "sg:phone":"+34 968 59 24 31",
    "sg:postcode":"30870",
    "sg:province":"Murcia",
    "wof:name":"Seguros Catalana Occidente S.a. De Seguros Y Reaseguros",
    "wof:placetype":"venue"
},
  "geometry": {"coordinates":[-1.3141189814,37.6004295349],"type":"Point"}
}