{
  "type": "Feature",
  "properties": {
    "addr:full":"Av. C. Sotelo, 50 Padron A Coru\u00f1a 15900",
    "addr:housenumber":"50",
    "addr:postcode":"15900",
    "addr:street":"Av. C. Sotelo;Padron A Corun\u0303A",
    "iso:country":"ES",
    "sg:address":"Av. C. Sotelo, 50",
    "sg:city":"Padron",
    "sg:orig_category":"Bazares, Art\u00cdculos De Limpieza Y De Cocina (al Por Menor)",
    "sg:phone":"+34 981 81 09 55",
    "sg:postcode":"15900",
    "sg:province":"A Coru\u00f1a",
    "wof:name":"Varela Seijo Enrique",
    "wof:placetype":"venue"
},
  "geometry": {"coordinates":[-8.6591444016,42.7387466431],"type":"Point"}
}