{
  "type": "Feature",
  "properties": {
    "iso:country":"ES",
    "sg:address":"Cust Santo Domingo, 20",
    "sg:city":"Madrid",
    "sg:orig_category":"Agencias Y Agentes Comerciales, Representantes",
    "sg:phone":"+34 915 41 85 42",
    "sg:postcode":"28013",
    "sg:province":"Madrid",
    "wof:name":"Ishizaki  Ryota",
    "wof:placetype":"venue"
},
  "geometry": {"coordinates":[-3.7084190845,40.4196357727],"type":"Point"}
}