{
  "type": "Feature",
  "properties": {
    "addr:full":"Calle de Molinos (los), 14 Herencia Ciudad Real 13640",
    "addr:housenumber":"14",
    "addr:postcode":"13640",
    "addr:street":"Calle De Molinos Los",
    "iso:country":"ES",
    "sg:address":"Calle de Molinos (los), 14",
    "sg:city":"Herencia",
    "sg:orig_category":"Empresas De Carpinter\u00cda De Madera",
    "sg:phone":"+34 926 57 24 47",
    "sg:postcode":"13640",
    "sg:province":"Ciudad Real",
    "wof:name":"Ubeda-contreras Fernandez Santiago",
    "wof:placetype":"venue"
},
  "geometry": {"coordinates":[-3.3489916325,39.3669509888],"type":"Point"}
}