{
  "type": "Feature",
  "properties": {
    "addr:full":"Avda Primo De Rivera, 1 Coru\u00d1a A Coru\u00f1a 15006",
    "addr:housenumber":"1",
    "addr:postcode":"15006",
    "addr:street":"Avda Primo De Rivera;Corun\u0303A",
    "iso:country":"ES",
    "sg:address":"Avda Primo De Rivera, 1",
    "sg:city":"Coru\u00d1a",
    "sg:classifiers":[
        {
            "category":"Manufacturing",
            "subcategory":"Building Materials",
            "type":"Manufacturing & Wholesale Goods"
        }
    ],
    "sg:phone":"+34 981 24 76 25",
    "sg:postcode":"15006",
    "sg:province":"A Coru\u00f1a",
    "sg:tags":[
        "cemento",
        "y",
        "de",
        "fabricaci\u00d3n",
        "cal"
    ],
    "wof:name":"Sociedad Anonima Tudela Veguin",
    "wof:placetype":"venue"
},
  "geometry": {"coordinates":[-8.405175209,43.3614501953],"type":"Point"}
}