{
  "type": "Feature",
  "properties": {
    "addr:full":"Calle de Villalba, 29 Poligono Industrial Los Villares Salamanca 37184",
    "addr:housenumber":"29",
    "addr:postcode":"37184",
    "addr:street":"Calle De Villalba;Industrial",
    "iso:country":"ES",
    "sg:address":"Calle de Villalba, 29",
    "sg:city":"Poligono Industrial Los Villares",
    "sg:orig_category":"Electrodom\u00c9sticos (al Por Menor)",
    "sg:phone":"+34 923 24 86 16",
    "sg:postcode":"37184",
    "sg:province":"Salamanca",
    "wof:name":"Representaciones Garrido S. L.",
    "wof:placetype":"venue"
},
  "geometry": {"coordinates":[-5.6396541595,40.9895515442],"type":"Point"}
}