{
  "type": "Feature",
  "properties": {
    "addr:full":"Huerta, 2 Rincon Victoria M\u00e1laga 29730",
    "addr:housenumber":"2",
    "addr:postcode":"29730",
    "addr:street":"Huerta;Ma\u0301Laga",
    "iso:country":"ES",
    "sg:address":"Huerta, 2",
    "sg:city":"Rincon Victoria",
    "sg:orig_category":"Pescader\u00cdas (al Por Menor)",
    "sg:phone":"+34 952 97 19 35",
    "sg:postcode":"29730",
    "sg:province":"M\u00e1laga",
    "wof:name":"Albarracin Caparros Jose Antonio",
    "wof:placetype":"venue"
},
  "geometry": {"coordinates":[-4.3113942146,36.7146759033],"type":"Point"}
}