{
  "type": "Feature",
  "properties": {
    "iso:country":"ES",
    "sg:address":"Agote, 9",
    "sg:city":"Arroa-bekoa",
    "sg:orig_category":"Empresas De Hormig\u00d3n, Hormig\u00d3n Armado Y Pretensado",
    "sg:phone":"+34 943 14 84 55",
    "sg:postcode":"20740",
    "sg:province":"Guip\u00f9zcoa",
    "sg:website":"www.etxebelez.com",
    "wof:name":"Prefabricados De Hormigon Etxeberria S. A.",
    "wof:placetype":"venue"
},
  "geometry": {"coordinates":[-2.2549140453,43.2378883362],"type":"Point"}
}