{
  "type": "Feature",
  "properties": {
    "addr:full":"Cjon Tramposos, 2 Ronda M\u00e1laga 29400",
    "addr:housenumber":"2",
    "addr:postcode":"29400",
    "addr:street":"Cjon Tramposos;Ronda Ma\u0301Laga",
    "iso:country":"ES",
    "sg:address":"Cjon Tramposos, 2",
    "sg:city":"Ronda",
    "sg:orig_category":"Administradores De Bienes Y Delegados De Comunidades De Propietarios",
    "sg:phone":"+34 952 87 97 41",
    "sg:postcode":"29400",
    "sg:province":"M\u00e1laga",
    "sg:website":"www.adfincas-ronda.com",
    "wof:name":"Perez Rojas Francisco Jose",
    "wof:placetype":"venue"
},
  "geometry": {"coordinates":[-5.1650438309,36.738193512],"type":"Point"}
}