{
  "type": "Feature",
  "properties": {
    "iso:country":"ES",
    "sg:address":"Avda Principe De Asturias, 86",
    "sg:city":"Badajoz",
    "sg:orig_category":"Agencias Y Agentes Comerciales, Representantes",
    "sg:phone":"+34 924 24 22 71",
    "sg:postcode":"06011",
    "sg:province":"Badajoz",
    "wof:name":"Diaz Martinez Juan Carlos",
    "wof:placetype":"venue"
},
  "geometry": {"coordinates":[-6.9916830063,38.8642234802],"type":"Point"}
}