{
  "type": "Feature",
  "properties": {
    "addr:full":"Av Logro\u00f1o, Km. 0043,9 Ba\u00f1ares La Rioja 26257",
    "addr:postcode":"26257",
    "addr:street":"Av Logron\u0303O Km. 0043,9 Ban\u0303Ares;Rioja",
    "iso:country":"ES",
    "sg:address":"Av Logro\u00f1o, Km. 0043,9",
    "sg:city":"Ba\u00f1ares",
    "sg:orig_category":"Patatas (al Por Mayor)",
    "sg:phone":"+34 941 34 09 21",
    "sg:postcode":"26257",
    "sg:province":"La Rioja",
    "wof:name":"Ecoagra S. A.",
    "wof:placetype":"venue"
},
  "geometry": {"coordinates":[-2.9351489544,42.4394187927],"type":"Point"}
}