{
  "type": "Feature",
  "properties": {
    "iso:country":"ES",
    "sg:address":"San Pedro, 12",
    "sg:city":"Benissa",
    "sg:orig_category":"Fotograf\u00cda Art\u00cdstica Y Retratos",
    "sg:phone":"+34 965 73 03 96",
    "sg:postcode":"03720",
    "sg:province":"Alicante",
    "wof:name":"Serra Cervera Juan Ignacio",
    "wof:placetype":"venue"
},
  "geometry": {"coordinates":[0.0501630008,38.7146530151],"type":"Point"}
}