{
  "type": "Feature",
  "properties": {
    "iso:country":"ES",
    "sg:address":"Calle de Donostia-san Sebastian, 10",
    "sg:city":"Errenteria",
    "sg:orig_category":"Estancos",
    "sg:phone":"+34 943 51 43 98",
    "sg:postcode":"20100",
    "sg:province":"Guip\u00f9zcoa",
    "wof:name":"Razquin Maiza Javier",
    "wof:placetype":"venue"
},
  "geometry": {"coordinates":[-1.9021762609,43.3154563904],"type":"Point"}
}