{
  "type": "Feature",
  "properties": {
    "iso:country":"ES",
    "sg:address":"Calle de Marques De Urquijo, 1",
    "sg:city":"Madrid",
    "sg:orig_category":"Molduras, Junquillos, Listones Y Molduras Perforadas",
    "sg:phone":"+34 915 48 20 45",
    "sg:postcode":"28008",
    "sg:province":"Madrid",
    "wof:name":"Fernandez Garcia Maria Del Carmen",
    "wof:placetype":"venue"
},
  "geometry": {"coordinates":[-3.7163779736,40.4304618835],"type":"Point"}
}