{
  "type": "Feature",
  "properties": {
    "addr:full":"Carrer de Sardenya, 516 Barcelona Barcelona 08024",
    "addr:housenumber":"516",
    "addr:postcode":"08024",
    "addr:street":"Carrer De Sardenya",
    "iso:country":"ES",
    "sg:address":"Carrer de Sardenya, 516",
    "sg:city":"Barcelona",
    "sg:orig_category":"Complementos De Vestir (al Por Menor)",
    "sg:phone":"+34 932 84 72 82",
    "sg:postcode":"08024",
    "sg:province":"Barcelona",
    "wof:name":"Fasorca S.l",
    "wof:placetype":"venue"
},
  "geometry": {"coordinates":[2.1630759239,41.4116210938],"type":"Point"}
}