{
  "type": "Feature",
  "properties": {
    "addr:full":"Ctra Juncal (el), S/n Ugarte Vizcaya 48510",
    "addr:postcode":"48510",
    "addr:street":"Ctra Juncal El S / N Ugarte",
    "iso:country":"ES",
    "sg:address":"Ctra Juncal (el), S/n",
    "sg:city":"Ugarte",
    "sg:orig_category":"Electrodom\u00c9sticos (al Por Menor)",
    "sg:phone":"+34 944 18 90 01",
    "sg:postcode":"48510",
    "sg:province":"Vizcaya",
    "wof:name":"E. G. O. Iberica I S. L.",
    "wof:placetype":"venue"
},
  "geometry": {"coordinates":[-3.0369338989,43.3047294617],"type":"Point"}
}