{
  "type": "Feature",
  "properties": {
    "iso:country":"ES",
    "sg:address":"Ctra Camos, 72",
    "sg:city":"Banyoles",
    "sg:orig_category":"Bazares, Art\u00cdculos De Limpieza Y De Cocina (al Por Menor)",
    "sg:phone":"+34 972 58 08 60",
    "sg:postcode":"17820",
    "sg:province":"Girona",
    "wof:name":"Pinatella Angel Fills Cdad",
    "wof:placetype":"venue"
},
  "geometry": {"coordinates":[2.7675700188,42.1119804382],"type":"Point"}
}