{
  "type": "Feature",
  "properties": {
    "addr:full":"Carrer de Tallers, 77 Barcelona Barcelona 08001",
    "addr:housenumber":"77",
    "addr:postcode":"08001",
    "addr:street":"Carrer De Tallers",
    "iso:country":"ES",
    "sg:address":"Carrer de Tallers, 77",
    "sg:city":"Barcelona",
    "sg:orig_category":"Alimentaci\u00d3n General (al Por Menor)",
    "sg:phone":"+34 933 17 61 70",
    "sg:postcode":"08001",
    "sg:province":"Barcelona",
    "wof:name":"Labugan Hidalgo S.l.",
    "wof:placetype":"venue"
},
  "geometry": {"coordinates":[2.1663489342,41.3848495483],"type":"Point"}
}