{
  "type": "Feature",
  "properties": {
    "addr:full":"Calle de Hermanos Pinzon, 5 Albacete Albacete 02006",
    "addr:housenumber":"5",
    "addr:postcode":"02006",
    "addr:street":"Calle De Hermanos Pinzon",
    "iso:country":"ES",
    "sg:address":"Calle de Hermanos Pinzon, 5",
    "sg:city":"Albacete",
    "sg:orig_category":"Chapa Y Pintura Veh\u00cdculos",
    "sg:phone":"+34 967 51 08 43",
    "sg:postcode":"02006",
    "sg:province":"Albacete",
    "wof:name":"Juype S.c.l",
    "wof:placetype":"venue"
},
  "geometry": {"coordinates":[-1.8723499775,38.9978141785],"type":"Point"}
}