{
  "type": "Feature",
  "properties": {
    "iso:country":"ES",
    "sg:address":"Avda Benicasim, 32",
    "sg:city":"Castellon",
    "sg:orig_category":"Empresas De Carpinter\u00cda De Madera",
    "sg:phone":"+34 964 20 62 49",
    "sg:postcode":"12004",
    "sg:province":"Castell\u00f3n",
    "wof:name":"Industrias De La Madera Avenida S.l.",
    "wof:placetype":"venue"
},
  "geometry": {"coordinates":[-0.0403059982,40.0001716614],"type":"Point"}
}