{
  "type": "Feature",
  "properties": {
    "iso:country":"ES",
    "sg:address":"Calle de Maria Cristina, 8",
    "sg:city":"Ciudad Real",
    "sg:orig_category":"Complementos De Vestir (al Por Menor)",
    "sg:phone":"+34 926 25 63 46",
    "sg:postcode":"13001",
    "sg:province":"Ciudad Real",
    "wof:name":"Cleopatra Modas S.l.",
    "wof:placetype":"venue"
},
  "geometry": {"coordinates":[-3.9284689426,38.9858398438],"type":"Point"}
}