{
  "type": "Feature",
  "properties": {
    "iso:country":"ES",
    "sg:address":"Calle de 21 B, 24",
    "sg:city":"Nueva Andalucia",
    "sg:orig_category":"Agencias Y Agentes Comerciales, Representantes",
    "sg:phone":"+34 952 81 29 06",
    "sg:postcode":"29660",
    "sg:province":"M\u00e1laga",
    "wof:name":"Martinez Torres Maria Victoria",
    "wof:placetype":"venue"
},
  "geometry": {"coordinates":[-4.9546365738,36.5083236694],"type":"Point"}
}