{
  "type": "Feature",
  "properties": {
    "iso:country":"ES",
    "sg:address":"Av Pere El Cerimonios, 14",
    "sg:city":"Reus",
    "sg:orig_category":"Peluqueros: De Se\u00d1oras",
    "sg:phone":"+34 977 75 05 09",
    "sg:postcode":"43205",
    "sg:province":"Tarragona",
    "wof:name":"Armesto Alba Marta",
    "wof:placetype":"venue"
},
  "geometry": {"coordinates":[1.1114370823,41.1506958008],"type":"Point"}
}