{
  "type": "Feature",
  "properties": {
    "addr:full":"Calle de Juan De Mena, 18 Estepona M\u00e1laga 29680",
    "addr:housenumber":"18",
    "addr:postcode":"29680",
    "addr:street":"Calle De Juan;Mena",
    "iso:country":"ES",
    "sg:address":"Calle de Juan De Mena, 18",
    "sg:city":"Estepona",
    "sg:orig_category":"Agentes, Concesionarios Y Sucursales De Veh\u00cdculos",
    "sg:phone":"+34 952 80 50 61",
    "sg:postcode":"29680",
    "sg:province":"M\u00e1laga",
    "wof:name":"Lopez Flores Manuel",
    "wof:placetype":"venue"
},
  "geometry": {"coordinates":[-5.1689519882,36.4313163757],"type":"Point"}
}