{
  "type": "Feature",
  "properties": {
    "addr:full":"Av Alfonso Puchades, 21 Benidorm Alicante 03500",
    "addr:housenumber":"21",
    "addr:postcode":"03500",
    "addr:street":"Av Alfonso Puchades",
    "iso:country":"ES",
    "sg:address":"Av Alfonso Puchades, 21",
    "sg:city":"Benidorm",
    "sg:orig_category":"Servicio De Salud",
    "sg:phone":"+34 966 83 00 80",
    "sg:postcode":"03500",
    "sg:province":"Alicante",
    "wof:name":"Crealux Design S.l.",
    "wof:placetype":"venue"
},
  "geometry": {"coordinates":[-0.1276639998,38.5431785583],"type":"Point"}
}