{
  "type": "Feature",
  "properties": {
    "addr:full":"A Riba, S/n Callobre Pontevedra 36688",
    "addr:postcode":"36688",
    "addr:street":"Riba S / N",
    "iso:country":"ES",
    "sg:address":"A Riba, S/n",
    "sg:city":"Callobre",
    "sg:orig_category":"Art\u00cdculos De Madera (fabricaci\u00d3n Y Al Por Mayor)",
    "sg:phone":"+34 986 57 23 60",
    "sg:postcode":"36688",
    "sg:province":"Pontevedra",
    "wof:name":"Muebles Fecama S.l.",
    "wof:placetype":"venue"
},
  "geometry": {"coordinates":[-8.4677591324,42.6931114197],"type":"Point"}
}