{
  "type": "Feature",
  "properties": {
    "iso:country":"ES",
    "sg:address":"Carrer de Font Honrada, 35",
    "sg:city":"Barcelona",
    "sg:orig_category":"Frutas, Legumbres Frescas Y Tempranas (al Por Menor)",
    "sg:phone":"+34 934 23 12 51",
    "sg:postcode":"08004",
    "sg:province":"Barcelona",
    "wof:name":"Castillo Arrieta Emiliano German",
    "wof:placetype":"venue"
},
  "geometry": {"coordinates":[2.1560690403,41.3728370667],"type":"Point"}
}