{
  "type": "Feature",
  "properties": {
    "iso:country":"ES",
    "sg:address":"Carrer de Llorenc Vicens, 1",
    "sg:city":"Palma",
    "sg:orig_category":"Psic\u00d3logos",
    "sg:phone":"+34 971 72 91 88",
    "sg:postcode":"07002",
    "sg:province":"Islas Baleares",
    "wof:name":"Carreras Orozco Catalina Maria",
    "wof:placetype":"venue"
},
  "geometry": {"coordinates":[2.655133009,39.5736351013],"type":"Point"}
}