{
  "type": "Feature",
  "properties": {
    "addr:full":"Calle de Monte Alberes, 2 Madrid Madrid 28038",
    "addr:housenumber":"2",
    "addr:postcode":"28038",
    "addr:street":"Calle De Monte Alberes",
    "iso:country":"ES",
    "sg:address":"Calle de Monte Alberes, 2",
    "sg:city":"Madrid",
    "sg:orig_category":"Tiendas De Grano, Frutas Y Legumbres Secas (al Por Menor)",
    "sg:phone":"+34 913 32 74 49",
    "sg:postcode":"28038",
    "sg:province":"Madrid",
    "wof:name":"Marquez Villarreal Cecilia",
    "wof:placetype":"venue"
},
  "geometry": {"coordinates":[-3.6448390484,40.3909721375],"type":"Point"}
}