{
  "type": "Feature",
  "properties": {
    "addr:full":"Calle de Posadas, 6 Huercal-overa Almer\u00eda 04600",
    "addr:housenumber":"6",
    "addr:postcode":"04600",
    "addr:street":"Calle De Posadas;Almeri\u0301A",
    "iso:country":"ES",
    "sg:address":"Calle de Posadas, 6",
    "sg:city":"Huercal-overa",
    "sg:orig_category":"Inform\u00c1tica: Material Y Suministros",
    "sg:phone":"+34 950 61 60 74",
    "sg:postcode":"04600",
    "sg:province":"Almer\u00eda",
    "wof:name":"Mena Molina Esther",
    "wof:placetype":"venue"
},
  "geometry": {"coordinates":[-1.9427750111,37.3894844055],"type":"Point"}
}