{
  "type": "Feature",
  "properties": {
    "iso:country":"ES",
    "sg:address":"Calle de Rio Eo, 72",
    "sg:city":"Gijon",
    "sg:orig_category":"Construcci\u00d3n De Edificios Residenciales Y No Residenciales",
    "sg:phone":"+34 985 16 47 99",
    "sg:postcode":"33210",
    "sg:province":"Asturias",
    "wof:name":"Armando Corripio S.l.",
    "wof:placetype":"venue"
},
  "geometry": {"coordinates":[-5.6720900536,43.5225028992],"type":"Point"}
}