{
  "type": "Feature",
  "properties": {
    "iso:country":"ES",
    "sg:address":"Calle de Cultura (la), 3",
    "sg:city":"Bara\u00f1ain",
    "sg:orig_category":"Prot\u00c9sicos Dentales",
    "sg:phone":"+34 948 18 33 20",
    "sg:postcode":"31010",
    "sg:province":"Navarra",
    "wof:name":"Araguas Bergua Carmen Y Garcia Mur Francisco",
    "wof:placetype":"venue"
},
  "geometry": {"coordinates":[-1.686019659,42.8043861389],"type":"Point"}
}