{
  "type": "Feature",
  "properties": {
    "iso:country":"ES",
    "sg:address":"Poli Las Capellanias, S/n",
    "sg:city":"Caceres",
    "sg:orig_category":"Servicios De Telecomunicaciones",
    "sg:phone":"+34 927 23 04 82",
    "sg:postcode":"10005",
    "sg:province":"C\u00e1ceres",
    "wof:name":"Avanzit Telecom S.l.",
    "wof:placetype":"venue"
},
  "geometry": {"coordinates":[-6.5341739655,39.4675254822],"type":"Point"}
}