{
  "type": "Feature",
  "properties": {
    "iso:country":"ES",
    "sg:address":"Calle de Telefonica, 3",
    "sg:city":"Olivos-la Postura",
    "sg:orig_category":"Farmacias",
    "sg:phone":"+34 922 71 06 98",
    "sg:postcode":"38670",
    "sg:province":"Santa Cruz De Tenerife",
    "wof:name":"Santana Perez Maria Del Mar",
    "wof:placetype":"venue"
},
  "geometry": {"coordinates":[-16.724899292,28.1215400696],"type":"Point"}
}