{
  "type": "Feature",
  "properties": {
    "addr:full":"El Tronquedal, S/n Carbayin Asturias 33936",
    "addr:housenumber":"s / n",
    "addr:postcode":"33936",
    "iso:country":"ES",
    "sg:address":"El Tronquedal, S/n",
    "sg:city":"Carbayin",
    "sg:orig_category":"Transportes Ferroviarios",
    "sg:phone":"+34 985 73 40 07",
    "sg:postcode":"33936",
    "sg:province":"Asturias",
    "wof:name":"Ferrocarriles De Via Estrecha",
    "wof:placetype":"venue"
},
  "geometry": {"coordinates":[-5.6397972107,43.3430328369],"type":"Point"}
}