{
  "type": "Feature",
  "properties": {
    "iso:country":"ES",
    "sg:address":"Calle de Pio Xii, 10",
    "sg:orig_category":"Relojer\u00cda (al Por Menor, Reparaci\u00d3n)",
    "sg:phone":"+34 944 03 60 52",
    "sg:postcode":"01400",
    "sg:province":"\u00c1lava",
    "wof:name":"Ana Isabel Ballesteros (joyeria)",
    "wof:placetype":"venue"
},
  "geometry": {"coordinates":[-2.9620895386,43.1430587769],"type":"Point"}
}