{
  "type": "Feature",
  "properties": {
    "addr:full":"Avda Corredera, 125 Hinojosa Del Duque C\u00f3rdoba 14270",
    "addr:housenumber":"125",
    "addr:postcode":"14270",
    "addr:street":"Avda Corredera;Co\u0301Rdoba",
    "iso:country":"ES",
    "sg:address":"Avda Corredera, 125",
    "sg:city":"Hinojosa Del Duque",
    "sg:orig_category":"Arreglo, Reparaci\u00d3n, Piezas Sueltas De Televisi\u00d3n, V\u00cddeo, Hi",
    "sg:phone":"+34 957 14 12 11",
    "sg:postcode":"14270",
    "sg:province":"C\u00f3rdoba",
    "wof:name":"Barbero Alcudia Rafael",
    "wof:placetype":"venue"
},
  "geometry": {"coordinates":[-5.1428489685,38.4971618652],"type":"Point"}
}