{
  "type": "Feature",
  "properties": {
    "addr:full":"Avda Mediterraneo, Km. 0009,5 Madrid Madrid 28031",
    "addr:postcode":"28031",
    "addr:street":"Avda Mediterraneo Km. 0009,5",
    "iso:country":"ES",
    "sg:address":"Avda Mediterraneo, Km. 0009,5",
    "sg:city":"Madrid",
    "sg:orig_category":"Promotores Constructores",
    "sg:phone":"+34 913 01 33 12",
    "sg:postcode":"28031",
    "sg:province":"Madrid",
    "wof:name":"Ortiz Construcciones Y Proyectos S.a.",
    "wof:placetype":"venue"
},
  "geometry": {"coordinates":[-3.6271688938,40.3911514282],"type":"Point"}
}