{
  "type": "Feature",
  "properties": {
    "iso:country":"ES",
    "sg:address":"Carrer de Pau (de La), 8",
    "sg:city":"Llagostera",
    "sg:orig_category":"Tapones Y Art\u00cdculos De Corcho",
    "sg:phone":"+34 972 83 03 80",
    "sg:postcode":"17240",
    "sg:province":"Girona",
    "wof:name":"Subirana Riera Josep",
    "wof:placetype":"venue"
},
  "geometry": {"coordinates":[2.8962700367,41.8287391663],"type":"Point"}
}