{
  "type": "Feature",
  "properties": {
    "addr:full":"Calle de Bolos, 7 San Andres Murcia 30005",
    "addr:housenumber":"7",
    "addr:postcode":"30005",
    "addr:street":"Calle De Bolos",
    "iso:country":"ES",
    "sg:address":"Calle de Bolos, 7",
    "sg:city":"San Andres",
    "sg:orig_category":"Telas Y Sedas (al Por Menor)",
    "sg:phone":"+34 968 29 57 29",
    "sg:postcode":"30005",
    "sg:province":"Murcia",
    "wof:name":"Vidal Perez Vicente",
    "wof:placetype":"venue"
},
  "geometry": {"coordinates":[-1.1387289762,37.9852600098],"type":"Point"}
}