{
  "type": "Feature",
  "properties": {
    "iso:country":"ES",
    "sg:address":"Carr Magistrat Saura, 19",
    "sg:city":"Tremp",
    "sg:orig_category":"Promotores Constructores",
    "sg:phone":"+34 973 65 02 96",
    "sg:postcode":"25620",
    "sg:province":"Lleida",
    "wof:name":"Parramon S.l. Construcciones",
    "wof:placetype":"venue"
},
  "geometry": {"coordinates":[0.8959850073,42.1640167236],"type":"Point"}
}