{
  "type": "Feature",
  "properties": {
    "iso:country":"ES",
    "sg:address":"Calle de Rio Genil, S/n",
    "sg:city":"Baeza",
    "sg:orig_category":"Fotograf\u00cda Publicitaria E Industrial",
    "sg:phone":"+34 953 74 00 59",
    "sg:postcode":"23440",
    "sg:province":"Ja\u00e9n",
    "wof:name":"Jose Y Jaime Fotografos S.l.l.",
    "wof:placetype":"venue"
},
  "geometry": {"coordinates":[-3.4837090969,37.9932098389],"type":"Point"}
}