{
  "type": "Feature",
  "properties": {
    "addr:full":"Pla De La Calma, 205 Viabrea Girona 17404",
    "addr:housenumber":"205",
    "addr:postcode":"17404",
    "addr:street":"Calma",
    "iso:country":"ES",
    "sg:address":"Pla De La Calma, 205",
    "sg:city":"Viabrea",
    "sg:orig_category":"Carb\u00d3n, Carb\u00d3n De Madera (al Por Mayor)",
    "sg:phone":"+34 938 47 23 02",
    "sg:postcode":"17404",
    "sg:province":"Girona",
    "wof:name":"Iglesias Cuadras Arturo",
    "wof:placetype":"venue"
},
  "geometry": {"coordinates":[2.5488100052,41.7241516113],"type":"Point"}
}