{
  "type": "Feature",
  "properties": {
    "iso:country":"ES",
    "sg:address":"Calle de Vicente Delgado Algaba, 86",
    "sg:city":"Badajoz",
    "sg:orig_category":"Muebles Y Accesorios Para Cocinas Y Cuartos De Ba\u00d1o (al Por Menor)",
    "sg:phone":"+34 924 24 24 06",
    "sg:postcode":"06010",
    "sg:province":"Badajoz",
    "wof:name":"Martinez-piron Rodriguez Maria Casilda",
    "wof:placetype":"venue"
},
  "geometry": {"coordinates":[-6.9751291275,38.8659515381],"type":"Point"}
}