{
  "type": "Feature",
  "properties": {
    "addr:full":"Calle de Jose Antonio, 28 Cantalejo Segovia 40320",
    "addr:housenumber":"28",
    "addr:postcode":"40320",
    "addr:street":"Calle De Jose Antonio",
    "iso:country":"ES",
    "sg:address":"Calle de Jose Antonio, 28",
    "sg:city":"Cantalejo",
    "sg:orig_category":"Comercio, Reparaci\u00d3n De Motocicletas, Bicicletas Y Piezas Sueltas",
    "sg:phone":"+34 921 52 03 98",
    "sg:postcode":"40320",
    "sg:province":"Segovia",
    "wof:name":"Pastor San Inocencio Juan Manuel",
    "wof:placetype":"venue"
},
  "geometry": {"coordinates":[-3.9296889305,41.2605514526],"type":"Point"}
}