{
  "type": "Feature",
  "properties": {
    "addr:full":"Calle de Ca\u00d1amo, 1 Cordoba C\u00f3rdoba 14010",
    "addr:housenumber":"1",
    "addr:postcode":"14010",
    "addr:street":"Calle De Can\u0303Amo;Co\u0301Rdoba",
    "iso:country":"ES",
    "sg:address":"Calle de Ca\u00d1amo, 1",
    "sg:city":"Cordoba",
    "sg:orig_category":"Empresas De Pintura Y Revestimientos",
    "sg:phone":"+34 957 26 55 28",
    "sg:postcode":"14010",
    "sg:province":"C\u00f3rdoba",
    "wof:name":"Martinez Flores Francisco",
    "wof:placetype":"venue"
},
  "geometry": {"coordinates":[-4.7664465904,37.8825912476],"type":"Point"}
}