{
  "type": "Feature",
  "properties": {
    "iso:country":"ES",
    "sg:address":"Carrer de Zorrilla, 4",
    "sg:city":"S. Feliu Guixols",
    "sg:orig_category":"Venta, Instalaci\u00d3n De Calefacci\u00d3n",
    "sg:phone":"+34 972 32 33 57",
    "sg:postcode":"17220",
    "sg:province":"Girona",
    "wof:name":"Borrego Padros Jaime",
    "wof:placetype":"venue"
},
  "geometry": {"coordinates":[3.0244259834,41.7853927612],"type":"Point"}
}