{
  "type": "Feature",
  "properties": {
    "addr:full":"Calle de Altube, 3 Bilbao Vizcaya 48002",
    "addr:housenumber":"3",
    "addr:postcode":"48002",
    "addr:street":"Calle De Altube",
    "iso:country":"ES",
    "sg:address":"Calle de Altube, 3",
    "sg:city":"Bilbao",
    "sg:orig_category":"Ropa Para Se\u00d1oras Y Caballeros (al Por Menor)",
    "sg:phone":"+34 944 44 37 35",
    "sg:postcode":"48002",
    "sg:province":"Vizcaya",
    "wof:name":"Monica Gomez Antonio (modas Monica)",
    "wof:placetype":"venue"
},
  "geometry": {"coordinates":[-2.9474952221,43.2514801025],"type":"Point"}
}