{
  "type": "Feature",
  "properties": {
    "iso:country":"ES",
    "sg:address":"Avda Hispano America (de), 18",
    "sg:city":"Petrer",
    "sg:classifiers":[
        {
            "category":"Banks & Credit Unions",
            "subcategory":"Bureau De Change",
            "type":"Services"
        }
    ],
    "sg:phone":"+34 965 37 21 94",
    "sg:postcode":"03610",
    "sg:province":"Alicante",
    "sg:tags":[
        "organismos",
        "control"
    ],
    "wof:name":"Francisco Mu\u00f1oz Irles Cdad",
    "wof:placetype":"venue"
},
  "geometry": {"coordinates":[-0.7676309943,38.4818153381],"type":"Point"}
}