{
  "type": "Feature",
  "properties": {
    "addr:full":"Pl Sant Jaume, 2 Barcelona Barcelona 08002",
    "addr:housenumber":"2",
    "addr:postcode":"08002",
    "addr:street":"Pl Sant Jaume",
    "iso:country":"ES",
    "sg:address":"Pl Sant Jaume, 2",
    "sg:city":"Barcelona",
    "sg:orig_category":"Arquitectos",
    "sg:phone":"+34 933 17 80 62",
    "sg:postcode":"08002",
    "sg:province":"Barcelona",
    "wof:name":"Correa Ruiz Federico",
    "wof:placetype":"venue"
},
  "geometry": {"coordinates":[2.1768369675,41.3823623657],"type":"Point"}
}