{
  "type": "Feature",
  "properties": {
    "iso:country":"ES",
    "sg:address":"Pl Imperial Tarraco, 1",
    "sg:city":"Tarragona",
    "sg:orig_category":"Librer\u00cdas",
    "sg:phone":"+34 977 24 87 03",
    "sg:postcode":"43005",
    "sg:province":"Tarragona",
    "wof:name":"Trinidad Carrillo Angeles",
    "wof:placetype":"venue"
},
  "geometry": {"coordinates":[1.2460039854,41.1191825867],"type":"Point"}
}