{
  "type": "Feature",
  "properties": {
    "addr:full":"Calle de Sevilla, 3 Pozuelo De Alarcon Madrid 28223",
    "addr:housenumber":"3",
    "addr:postcode":"28223",
    "addr:street":"Calle De Sevilla",
    "iso:country":"ES",
    "sg:address":"Calle de Sevilla, 3",
    "sg:city":"Pozuelo De Alarcon",
    "sg:orig_category":"M\u00c9dicos: Estomatolog\u00cda",
    "sg:phone":"+34 913 52 55 62",
    "sg:postcode":"28223",
    "sg:province":"Madrid",
    "wof:name":"Fernandez Martin Olga",
    "wof:placetype":"venue"
},
  "geometry": {"coordinates":[-3.8093950748,40.4356193542],"type":"Point"}
}