{
  "type": "Feature",
  "properties": {
    "iso:country":"ES",
    "sg:address":"Calle de Carmen, 32",
    "sg:city":"Fortuna",
    "sg:orig_category":"Bisuter\u00cda, Joyer\u00cda, Relojer\u00cda (al Por Menor)",
    "sg:phone":"+34 968 68 63 34",
    "sg:postcode":"30620",
    "sg:province":"Murcia",
    "wof:name":"Hupancu Group Hour S.l.",
    "wof:placetype":"venue"
},
  "geometry": {"coordinates":[-1.1236584187,38.1810913086],"type":"Point"}
}