{
  "type": "Feature",
  "properties": {
    "addr:full":"Avda Crevillente, 5 Dolores Alicante 03150",
    "addr:housenumber":"5",
    "addr:postcode":"03150",
    "addr:street":"Avda Crevillente",
    "iso:country":"ES",
    "sg:address":"Avda Crevillente, 5",
    "sg:city":"Dolores",
    "sg:orig_category":"Agentes Generales De Seguros",
    "sg:phone":"+34 966 71 13 75",
    "sg:postcode":"03150",
    "sg:province":"Alicante",
    "wof:name":"Hernandez Martinez Rafael",
    "wof:placetype":"venue"
},
  "geometry": {"coordinates":[-0.7716659904,38.1372375488],"type":"Point"}
}