{
  "type": "Feature",
  "properties": {
    "addr:full":"Plaz Artesania, S/n Guadalcacin Del Caudillo C\u00e1diz 11591",
    "addr:housenumber":"s / n",
    "addr:postcode":"11591",
    "iso:country":"ES",
    "sg:address":"Plaz Artesania, S/n",
    "sg:city":"Guadalcacin Del Caudillo",
    "sg:orig_category":"Iglesia Cat\u00d3lica",
    "sg:phone":"+34 956 15 73 35",
    "sg:postcode":"11591",
    "sg:province":"C\u00e1diz",
    "wof:name":"Parroquia San Enrique Y Santa Teresa",
    "wof:placetype":"venue"
},
  "geometry": {"coordinates":[-6.0885739326,36.7132606506],"type":"Point"}
}