{
  "type": "Feature",
  "properties": {
    "addr:full":"Calle de Jose Erbina, 11 Vitoria-gasteiz \u00c1lava 01005",
    "addr:housenumber":"11",
    "addr:postcode":"01005",
    "addr:street":"Calle De Jose Erbina",
    "iso:country":"ES",
    "sg:address":"Calle de Jose Erbina, 11",
    "sg:city":"Vitoria-gasteiz",
    "sg:orig_category":"Centros M\u00c9dicos Y Sociales, Dispensarios",
    "sg:phone":"+34 945 13 19 19",
    "sg:postcode":"01005",
    "sg:province":"\u00c1lava",
    "wof:name":"Garcia Montoya Amando",
    "wof:placetype":"venue"
},
  "geometry": {"coordinates":[-2.6692450047,42.8413200378],"type":"Point"}
}