{
  "type": "Feature",
  "properties": {
    "addr:full":"Calle de Casa\u00d1e, 9 Palencia Palencia 34002",
    "addr:housenumber":"9",
    "addr:postcode":"34002",
    "addr:street":"Calle De Casan\u0303E",
    "iso:country":"ES",
    "sg:address":"Calle de Casa\u00d1e, 9",
    "sg:city":"Palencia",
    "sg:orig_category":"Contenedores (mercanc\u00cdas)",
    "sg:phone":"+34 979 72 04 14",
    "sg:postcode":"34002",
    "sg:province":"Palencia",
    "wof:name":"Cipriano Herrero S.l.",
    "wof:placetype":"venue"
},
  "geometry": {"coordinates":[-4.5265488625,42.002571106],"type":"Point"}
}