{
  "type": "Feature",
  "properties": {
    "iso:country":"ES",
    "sg:address":"Pase De La Acacia, S/n",
    "sg:city":"Poligono Ind. La Mora",
    "sg:orig_category":"Transportes Por Carretera: Lotes Completos, Mercanc\u00cdas Diversas",
    "sg:phone":"+34 983 40 32 10",
    "sg:postcode":"47193",
    "sg:province":"Valladolid",
    "wof:name":"Gecarsa S.a.",
    "wof:placetype":"venue"
},
  "geometry": {"coordinates":[-4.6859240532,41.6106681824],"type":"Point"}
}