{
  "type": "Feature",
  "properties": {
    "iso:country":"ES",
    "sg:address":"Calle de Fuego (del), 32",
    "sg:city":"Alcobendas",
    "sg:orig_category":"Carnicer\u00cdas, Carnicer\u00cdas",
    "sg:phone":"+34 916 53 86 30",
    "sg:postcode":"28100",
    "sg:province":"Madrid",
    "wof:name":"Carnicas Los Segovianos S.l.",
    "wof:placetype":"venue"
},
  "geometry": {"coordinates":[-3.6350390911,40.5433273315],"type":"Point"}
}