{
  "type": "Feature",
  "properties": {
    "addr:full":"Peloteros, 20 Beznar Granada 18660",
    "addr:housenumber":"20",
    "addr:postcode":"18660",
    "addr:street":"Peloteros",
    "iso:country":"ES",
    "sg:address":"Peloteros, 20",
    "sg:city":"Beznar",
    "sg:orig_category":"Frutas Y Legumbres Frescas (al Por Mayor)",
    "sg:phone":"+34 958 78 80 92",
    "sg:postcode":"18660",
    "sg:province":"Granada",
    "wof:name":"Rios Rios Roberto",
    "wof:placetype":"venue"
},
  "geometry": {"coordinates":[-3.5423090458,36.9273834229],"type":"Point"}
}