{
  "type": "Feature",
  "properties": {
    "iso:country":"ES",
    "sg:address":"Calle de Rio Murela, S/n",
    "sg:city":"Cari\u00f1o",
    "sg:orig_category":"Distribuci\u00d3n De Petr\u00d3leo Y Derivados",
    "sg:phone":"+34 981 40 51 80",
    "sg:postcode":"15360",
    "sg:province":"La Coru\u00f1a",
    "wof:name":"Gonzalez Y Salgueiro S.l.",
    "wof:placetype":"venue"
},
  "geometry": {"coordinates":[-7.8727040291,43.7388954163],"type":"Point"}
}