{
  "type": "Feature",
  "properties": {
    "addr:full":"Carrer de Jaume Abril, 26 Viladecans Barcelona 08840",
    "addr:housenumber":"26",
    "addr:postcode":"08840",
    "addr:street":"Carrer De Jaume Abril",
    "iso:country":"ES",
    "sg:address":"Carrer de Jaume Abril, 26",
    "sg:city":"Viladecans",
    "sg:orig_category":"Distribuci\u00d3n De Petr\u00d3leo Y Derivados",
    "sg:phone":"+34 936 58 10 16",
    "sg:postcode":"08840",
    "sg:province":"Barcelona",
    "wof:name":"Pescados Y Mariscos Marcos I Rosa S.l.",
    "wof:placetype":"venue"
},
  "geometry": {"coordinates":[2.0176699162,41.3155212402],"type":"Point"}
}