{
  "type": "Feature",
  "properties": {
    "addr:full":"Calle de Sancho El Sabio, 19 Vitoria-gasteiz \u00c1lava 01008",
    "addr:housenumber":"19",
    "addr:postcode":"01008",
    "addr:street":"Calle De Sancho El Sabio",
    "iso:country":"ES",
    "sg:address":"Calle de Sancho El Sabio, 19",
    "sg:city":"Vitoria-gasteiz",
    "sg:orig_category":"Muebles Y Accesorios Para Cocinas Y Cuartos De Ba\u00d1o (al Por Menor)",
    "sg:phone":"+34 945 13 95 06",
    "sg:postcode":"01008",
    "sg:province":"\u00c1lava",
    "wof:name":"Muebles Navas S.l.",
    "wof:placetype":"venue"
},
  "geometry": {"coordinates":[-2.6802198887,42.8480911255],"type":"Point"}
}