{
  "type": "Feature",
  "properties": {
    "iso:country":"ES",
    "sg:address":"Calle de Rio Chanza, 3",
    "sg:city":"Atalayuela",
    "sg:orig_category":"Art\u00cdculos De Decoraci\u00d3n",
    "sg:phone":"+34 916 91 94 89",
    "sg:postcode":"28906",
    "sg:province":"Madrid",
    "wof:name":"Stock Bo S.l.",
    "wof:placetype":"venue"
},
  "geometry": {"coordinates":[-3.6963059902,40.2772979736],"type":"Point"}
}