{
  "type": "Feature",
  "properties": {
    "addr:full":"Calle de Garcia Gamero, S/n Cadiz C\u00e1diz 11012",
    "addr:housenumber":"s / n",
    "addr:postcode":"11012",
    "addr:street":"Calle De Garcia Gamero",
    "iso:country":"ES",
    "sg:address":"Calle de Garcia Gamero, S/n",
    "sg:city":"Cadiz",
    "sg:orig_category":"Asociaciones, Organismos Culturales Y Socioeducativos",
    "sg:phone":"+34 956 26 15 19",
    "sg:postcode":"11012",
    "sg:province":"C\u00e1diz",
    "wof:name":"Hermandad Del Rocio De Cadiz",
    "wof:placetype":"venue"
},
  "geometry": {"coordinates":[-6.2774815559,36.5162506104],"type":"Point"}
}