{
  "type": "Feature",
  "properties": {
    "iso:country":"ES",
    "sg:address":"Calle de Pablo Medina, 22",
    "sg:city":"Albacete",
    "sg:orig_category":"Aparcamientos (infraestructuras, Accesorios)",
    "sg:phone":"+34 967 52 23 53",
    "sg:postcode":"02005",
    "sg:province":"Albacete",
    "wof:name":"I Mas D. Parking S.l.",
    "wof:placetype":"venue"
},
  "geometry": {"coordinates":[-1.8561120033,38.9971847534],"type":"Point"}
}