{
  "type": "Feature",
  "properties": {
    "iso:country":"ES",
    "sg:address":"Plaz Pi\u00d1a (de La), 7",
    "sg:city":"Valdemoro",
    "sg:orig_category":"Poller\u00cda Y Caza (al Por Menor)",
    "sg:phone":"+34 918 95 02 42",
    "sg:postcode":"28340",
    "sg:province":"Madrid",
    "wof:name":"Garrido Torres Sebastiana",
    "wof:placetype":"venue"
},
  "geometry": {"coordinates":[-3.6738090515,40.1909751892],"type":"Point"}
}