{
  "type": "Feature",
  "properties": {
    "iso:country":"ES",
    "sg:address":"Rua San Pedro (de), 115",
    "sg:city":"Santiago De Compostela",
    "sg:classifiers":[
        {
            "category":"Personal",
            "subcategory":"Barber",
            "type":"Services"
        }
    ],
    "sg:phone":"+34 981 56 04 84",
    "sg:postcode":"15703",
    "sg:province":"A Coru\u00f1a",
    "sg:tags":[
        "caballeros",
        "de",
        "peluqueros"
    ],
    "wof:name":"Vidal Neira Jesus",
    "wof:placetype":"venue"
},
  "geometry": {"coordinates":[-8.535610199,42.8818626404],"type":"Point"}
}