{
  "type": "Feature",
  "properties": {
    "iso:country":"ES",
    "sg:address":"Calle de Escritora Josefina Rodriguez De Aldecoa, 1",
    "sg:city":"Robla",
    "sg:orig_category":"Bibliotecas, Mediatecas",
    "sg:phone":"+34 987 57 04 39",
    "sg:postcode":"24640",
    "sg:province":"Le\u00f3n",
    "wof:name":"Ayuntamiento De La Robla",
    "wof:placetype":"venue"
},
  "geometry": {"coordinates":[-5.6294178963,42.8025932312],"type":"Point"}
}