{
  "type": "Feature",
  "properties": {
    "iso:country":"ES",
    "sg:address":"Calle de Turis, 12",
    "sg:city":"Valencia",
    "sg:orig_category":"Promotores Constructores",
    "sg:phone":"+34 963 57 06 44",
    "sg:postcode":"46018",
    "sg:province":"Valencia",
    "wof:name":"Fontelman S.l.",
    "wof:placetype":"venue"
},
  "geometry": {"coordinates":[-0.3925690055,39.4635238647],"type":"Point"}
}