{
  "type": "Feature",
  "properties": {
    "addr:full":"Plaz San Felix, S/n Eriste Huesca 22468",
    "addr:housenumber":"s",
    "addr:postcode":"22468",
    "addr:street":"Plaz San Felix;/ N Eriste",
    "iso:country":"ES",
    "sg:address":"Plaz San Felix, S/n",
    "sg:city":"Eriste",
    "sg:orig_category":"Carnicer\u00cdas, Carnicer\u00cdas",
    "sg:phone":"+34 974 55 13 02",
    "sg:postcode":"22468",
    "sg:province":"Huesca",
    "wof:name":"Rufat More Felix",
    "wof:placetype":"venue"
},
  "geometry": {"coordinates":[0.466403991,42.5777740479],"type":"Point"}
}