{
  "type": "Feature",
  "properties": {
    "addr:full":"Calle de Lombilla, 27 Aldeanueva Ebro La Rioja 26559",
    "addr:housenumber":"27",
    "addr:postcode":"26559",
    "addr:street":"Calle De Lombilla;Ebro",
    "iso:country":"ES",
    "sg:address":"Calle de Lombilla, 27",
    "sg:city":"Aldeanueva Ebro",
    "sg:orig_category":"Electrodom\u00c9sticos (al Por Menor)",
    "sg:phone":"+34 941 16 31 61",
    "sg:postcode":"26559",
    "sg:province":"La Rioja",
    "wof:name":"Saenz Gutierrez Jose Maria",
    "wof:placetype":"venue"
},
  "geometry": {"coordinates":[-1.8868360519,42.2279510498],"type":"Point"}
}