{
  "type": "Feature",
  "properties": {
    "iso:country":"ES",
    "sg:address":"Ctra Sant Hipolit, 20",
    "sg:city":"Vic",
    "sg:orig_category":"M\u00c1rmoles, Granitos Y Piedras Naturales",
    "sg:phone":"+34 938 86 19 98",
    "sg:postcode":"08500",
    "sg:province":"Barcelona",
    "wof:name":"Granets Y Marbres Vic S.l.",
    "wof:placetype":"venue"
},
  "geometry": {"coordinates":[2.2532479763,41.9448928833],"type":"Point"}
}