{
  "type": "Feature",
  "properties": {
    "addr:full":"Carrer de Costa Brava, 11 Reus Tarragona 43205",
    "addr:housenumber":"11",
    "addr:postcode":"43205",
    "addr:street":"Carrer De Costa Brava",
    "iso:country":"ES",
    "sg:address":"Carrer de Costa Brava, 11",
    "sg:city":"Reus",
    "sg:orig_category":"Mec\u00c1nico Del Autom\u00d3vil",
    "sg:phone":"+34 977 77 26 43",
    "sg:postcode":"43205",
    "sg:province":"Tarragona",
    "wof:name":"Rosado Fernandez Hermenegildo",
    "wof:placetype":"venue"
},
  "geometry": {"coordinates":[1.1083569527,41.1462097168],"type":"Point"}
}