{
  "type": "Feature",
  "properties": {
    "addr:full":"Carrer de Joaquin Costa, 58 Barcelona Barcelona 08001",
    "addr:housenumber":"58",
    "addr:postcode":"08001",
    "addr:street":"Carrer De Joaquin Costa",
    "iso:country":"ES",
    "sg:address":"Carrer de Joaquin Costa, 58",
    "sg:city":"Barcelona",
    "sg:orig_category":"Tiendas De Grano, Frutas Y Legumbres Secas (al Por Menor)",
    "sg:phone":"+34 933 01 36 90",
    "sg:postcode":"08001",
    "sg:province":"Barcelona",
    "wof:name":"Fhashafiqur  Rahman",
    "wof:placetype":"venue"
},
  "geometry": {"coordinates":[2.1649389267,41.3835029602],"type":"Point"}
}