{
  "type": "Feature",
  "properties": {
    "iso:country":"ES",
    "sg:address":"Calle de Goya, 11",
    "sg:city":"Valladolid",
    "sg:orig_category":"Aluminio Y Aleaciones (producci\u00d3n, Transformaci\u00d3n, Negocio)",
    "sg:phone":"+34 983 23 44 76",
    "sg:postcode":"47007",
    "sg:province":"Valladolid",
    "wof:name":"Alvarez Aluminio Y Hierro S.l.",
    "wof:placetype":"venue"
},
  "geometry": {"coordinates":[-4.7384343147,41.632850647],"type":"Point"}
}