{
  "type": "Feature",
  "properties": {
    "iso:country":"ES",
    "sg:address":"Avda Celanova (de), 54",
    "sg:city":"Valenza",
    "sg:orig_category":"Peluquer\u00cdas, Peluquer\u00cda Mixta",
    "sg:phone":"+34 988 25 28 94",
    "sg:postcode":"32002",
    "sg:province":"Ourense",
    "wof:name":"Perez Dieguez Paula",
    "wof:placetype":"venue"
},
  "geometry": {"coordinates":[-7.8813490868,42.3190040588],"type":"Point"}
}