{
  "type": "Feature",
  "properties": {
    "iso:country":"ES",
    "sg:address":"Calle de San Miguel, 21",
    "sg:city":"Villanueva De Los Infantes",
    "sg:orig_category":"Empresas De Pintura Y Revestimientos",
    "sg:phone":"+34 926 36 05 91",
    "sg:postcode":"13320",
    "sg:province":"Ciudad Real",
    "wof:name":"Los Barreros Cdad",
    "wof:placetype":"venue"
},
  "geometry": {"coordinates":[-3.0082089901,38.7398300171],"type":"Point"}
}