{
  "type": "Feature",
  "properties": {
    "iso:country":"ES",
    "sg:address":"Calle de Corral Del Veleta, 7",
    "sg:city":"Granada",
    "sg:orig_category":"Promotores Constructores",
    "sg:phone":"+34 958 81 45 70",
    "sg:postcode":"18008",
    "sg:province":"Granada",
    "wof:name":"Meridional De Obras S.l.",
    "wof:placetype":"venue"
},
  "geometry": {"coordinates":[-3.5825982094,37.160785675],"type":"Point"}
}