{
  "type": "Feature",
  "properties": {
    "addr:full":"Calle de Santa Teresa, 5 Barco De Avila \u00c1vila 05600",
    "addr:housenumber":"5",
    "addr:postcode":"05600",
    "addr:street":"Calle De Santa Teresa;A\u0301Vila",
    "iso:country":"ES",
    "sg:address":"Calle de Santa Teresa, 5",
    "sg:city":"Barco De Avila",
    "sg:orig_category":"Cajas Para Embalar",
    "sg:phone":"+34 920 34 05 79",
    "sg:postcode":"05600",
    "sg:province":"\u00c1vila",
    "wof:name":"Caja Rural Provincial De Salamanca",
    "wof:placetype":"venue"
},
  "geometry": {"coordinates":[-5.5233011246,40.3575401306],"type":"Point"}
}