{
  "type": "Feature",
  "properties": {
    "addr:full":"Ptda Rebolledo, 37 Rebolledo Alicante 03113",
    "addr:housenumber":"37",
    "addr:postcode":"03113",
    "addr:street":"Ptda Rebolledo",
    "iso:country":"ES",
    "sg:address":"Ptda Rebolledo, 37",
    "sg:city":"Rebolledo",
    "sg:orig_category":"Negocio De Materiales De Construcci\u00d3n",
    "sg:phone":"+34 965 18 98 12",
    "sg:postcode":"03113",
    "sg:province":"Alicante",
    "wof:name":"Hijos De Vicente Quirant S.l.",
    "wof:placetype":"venue"
},
  "geometry": {"coordinates":[-0.590644002,38.3419342041],"type":"Point"}
}