{
  "type": "Feature",
  "properties": {
    "iso:country":"ES",
    "sg:address":"Av Francesc Macia, 60",
    "sg:city":"Sabadell",
    "sg:orig_category":"Inform\u00c1tica (estudios, Servicios, Asesor\u00cda, Formaci\u00d3n)",
    "sg:phone":"+34 937 23 65 45",
    "sg:postcode":"08206",
    "sg:province":"Barcelona",
    "wof:name":"Solunix S.a.",
    "wof:placetype":"venue"
},
  "geometry": {"coordinates":[2.0980739594,41.5547332764],"type":"Point"}
}