{
  "type": "Feature",
  "properties": {
    "addr:full":"Calle de Arquitecto Juan Jose Belmonte, Km. 0020,0 Balsicas Murcia 30591",
    "addr:postcode":"30591",
    "addr:street":"Calle De Arquitecto Juan Jose Belmonte Km. 0020,0",
    "iso:country":"ES",
    "sg:address":"Calle de Arquitecto Juan Jose Belmonte, Km. 0020,0",
    "sg:city":"Balsicas",
    "sg:orig_category":"Negocio De Materiales De Construcci\u00d3n",
    "sg:phone":"+34 968 58 08 09",
    "sg:postcode":"30591",
    "sg:province":"Murcia",
    "sg:website":"www.bigmat.es",
    "wof:name":"Materiales De Construccion Juan Garcia S.l.",
    "wof:placetype":"venue"
},
  "geometry": {"coordinates":[-0.9569808841,37.8168411255],"type":"Point"}
}