{
  "type": "Feature",
  "properties": {
    "addr:full":"Calle de Emilio Castelar, 14 Alcazar S. Juan Ciudad Real 13600",
    "addr:housenumber":"14",
    "addr:postcode":"13600",
    "addr:street":"Calle De Emilio Castelar;Alcazar S. Juan Ciudad Real",
    "iso:country":"ES",
    "sg:address":"Calle de Emilio Castelar, 14",
    "sg:city":"Alcazar S. Juan",
    "sg:orig_category":"Ropa Para Se\u00d1oras Y Caballeros (al Por Menor)",
    "sg:phone":"+34 926 54 14 84",
    "sg:postcode":"13600",
    "sg:province":"Ciudad Real",
    "wof:name":"Tiendas De Vestir Joven S.l.",
    "wof:placetype":"venue"
},
  "geometry": {"coordinates":[-3.2092280388,39.3905677795],"type":"Point"}
}