{
  "type": "Feature",
  "properties": {
    "addr:full":"Calle de Fuente Del Berro, 12 Madrid Madrid 28009",
    "addr:housenumber":"12",
    "addr:postcode":"madrid;28009",
    "addr:street":"Calle De Fuente Del Berro",
    "iso:country":"ES",
    "sg:address":"Calle de Fuente Del Berro, 12",
    "sg:city":"Madrid",
    "sg:orig_category":"Abogados",
    "sg:phone":"+34 914 01 65 82",
    "sg:postcode":"28009",
    "sg:province":"Madrid",
    "wof:name":"Jimenez Calzada Eduardo",
    "wof:placetype":"venue"
},
  "geometry": {"coordinates":[-3.6708254814,40.4259986877],"type":"Point"}
}