{
  "type": "Feature",
  "properties": {
    "iso:country":"ES",
    "sg:address":"N. San J. Palmete, Km. 0005,0",
    "sg:city":"Sevilla",
    "sg:orig_category":"Inmobiliaria (agencias)",
    "sg:phone":"+34 954 65 62 83",
    "sg:postcode":"41006",
    "sg:province":"Sevilla",
    "wof:name":"Cercado Del Pozo S.l.",
    "wof:placetype":"venue"
},
  "geometry": {"coordinates":[-5.9406838417,37.3823814392],"type":"Point"}
}