{
  "type": "Feature",
  "properties": {
    "addr:full":"Carrer de San Jose, 16 Guardamar Segura Alicante 03140",
    "addr:housenumber":"16",
    "addr:postcode":"03140",
    "addr:street":"Carrer De San",
    "iso:country":"ES",
    "sg:address":"Carrer de San Jose, 16",
    "sg:city":"Guardamar Segura",
    "sg:orig_category":"Carnicer\u00cdas, Carnicer\u00cdas",
    "sg:phone":"+34 965 72 86 89",
    "sg:postcode":"03140",
    "sg:province":"Alicante",
    "wof:name":"Saez Lopez Maria Carmen",
    "wof:placetype":"venue"
},
  "geometry": {"coordinates":[-0.6540849805,38.0909576416],"type":"Point"}
}