{
  "type": "Feature",
  "properties": {
    "iso:country":"ES",
    "sg:address":"Avda Cruz De Juarez, 24",
    "sg:city":"Cordoba",
    "sg:orig_category":"Comercio, Reparaci\u00d3n De Bicicletas, De Motocicletas, De Accesorios",
    "sg:phone":"+34 957 27 11 14",
    "sg:postcode":"14006",
    "sg:province":"C\u00f3rdoba",
    "wof:name":"Molina Jurado Milagros",
    "wof:placetype":"venue"
},
  "geometry": {"coordinates":[-4.7803621292,37.8984489441],"type":"Point"}
}