{
  "type": "Feature",
  "properties": {
    "addr:full":"Plaz San Antonio De Texas, 1 Santa Cruz De Tenerife Santa Cruz De Tenerife 38001",
    "addr:housenumber":"1",
    "addr:postcode":"38001",
    "addr:street":"Plaz;Texas",
    "iso:country":"ES",
    "sg:address":"Plaz San Antonio De Texas, 1",
    "sg:city":"Santa Cruz De Tenerife",
    "sg:orig_category":"M\u00c9dicos: Pediatr\u00cda. Enfermedades De Los Ni\u00d1os",
    "sg:phone":"+34 922 24 85 81",
    "sg:postcode":"38001",
    "sg:province":"Santa Cruz De Tenerife",
    "wof:name":"Ortigosa Del Castillo Luis",
    "wof:placetype":"venue"
},
  "geometry": {"coordinates":[-16.2538375854,28.4946174622],"type":"Point"}
}