{
  "type": "Feature",
  "properties": {
    "addr:full":"Calle de San Pablo, 6 Salamanca Salamanca 37001",
    "addr:housenumber":"6",
    "addr:postcode":"37001",
    "addr:street":"Calle De San Pablo",
    "iso:country":"ES",
    "sg:address":"Calle de San Pablo, 6",
    "sg:city":"Salamanca",
    "sg:orig_category":"Filatelia",
    "sg:phone":"+34 923 26 58 77",
    "sg:postcode":"37001",
    "sg:province":"Salamanca",
    "wof:name":"Hernandez Alvarez Angela",
    "wof:placetype":"venue"
},
  "geometry": {"coordinates":[-5.6642417908,40.9635047913],"type":"Point"}
}