{
  "type": "Feature",
  "properties": {
    "addr:full":"Plaz San Felipe Neri, S/n Valencia Valencia 46021",
    "addr:housenumber":"s / n",
    "addr:postcode":"46021",
    "addr:street":"Plaz",
    "iso:country":"ES",
    "sg:address":"Plaz San Felipe Neri, S/n",
    "sg:city":"Valencia",
    "sg:orig_category":"Carnicer\u00cdas, Carnicer\u00cdas",
    "sg:phone":"+34 963 69 48 62",
    "sg:postcode":"46021",
    "sg:province":"Valencia",
    "wof:name":"Gomez Gonzalez Pedro",
    "wof:placetype":"venue"
},
  "geometry": {"coordinates":[-0.3539189994,39.4699440002],"type":"Point"}
}