{
  "type": "Feature",
  "properties": {
    "iso:country":"ES",
    "sg:address":"Carr Josep Tarradellas, 66",
    "sg:city":"Blanes",
    "sg:orig_category":"Fabricaci\u00d3n De Juguetes Autom\u00c1ticos",
    "sg:phone":"+34 972 35 54 35",
    "sg:postcode":"17300",
    "sg:province":"Girona",
    "wof:name":"Blanes Slot S.l.",
    "wof:placetype":"venue"
},
  "geometry": {"coordinates":[2.7831120491,41.6678009033],"type":"Point"}
}