{
  "type": "Feature",
  "properties": {
    "iso:country":"ES",
    "sg:address":"Rua Domingo Antonio De Andrade, S/n",
    "sg:city":"Cee",
    "sg:orig_category":"Ense\u00d1anza, Formaci\u00d3n Profesional: Aprendizaje",
    "sg:phone":"+34 981 70 60 64",
    "sg:postcode":"15270",
    "sg:province":"A Coru\u00f1a",
    "wof:name":"Servicio Publico De Empleo Estatal-dron. Prov. La Coru\u00d1a",
    "wof:placetype":"venue"
},
  "geometry": {"coordinates":[-9.1897392273,42.9556236267],"type":"Point"}
}