{
  "type": "Feature",
  "properties": {
    "iso:country":"ES",
    "sg:address":"Calle de Andres Isasi, 4",
    "sg:city":"Algorta",
    "sg:orig_category":"Ense\u00d1anza: Idiomas",
    "sg:phone":"+34 944 60 81 65",
    "sg:postcode":"48992",
    "sg:province":"Vizcaya",
    "sg:website":"www.astex.es",
    "wof:name":"Astex Asesoramientos De Estudios En El Extranjero S.a.",
    "wof:placetype":"venue"
},
  "geometry": {"coordinates":[-3.0100162029,43.3435287476],"type":"Point"}
}