{
  "type": "Feature",
  "properties": {
    "addr:full":"Pase Marquesa Viuda De Aldama (de La), 31 Alcobendas Madrid 28109",
    "addr:housenumber":"31",
    "addr:postcode":"28109",
    "addr:street":"Aldama De La",
    "iso:country":"ES",
    "sg:address":"Pase Marquesa Viuda De Aldama (de La), 31",
    "sg:city":"Alcobendas",
    "sg:orig_category":"Promotores Constructores",
    "sg:phone":"+34 916 50 17 12",
    "sg:postcode":"28109",
    "sg:province":"Madrid",
    "wof:name":"Francap S.a.",
    "wof:placetype":"venue"
},
  "geometry": {"coordinates":[-3.6235330105,40.5168876648],"type":"Point"}
}