{
  "type": "Feature",
  "properties": {
    "addr:full":"Plaz Espa\u00d1a, 17 Badajoz Badajoz 06002",
    "addr:housenumber":"17",
    "addr:postcode":"06002",
    "addr:street":"Plaz Espan\u0303A",
    "iso:country":"ES",
    "sg:address":"Plaz Espa\u00d1a, 17",
    "sg:city":"Badajoz",
    "sg:orig_category":"Centros Empresariales",
    "sg:phone":"+34 924 22 00 02",
    "sg:postcode":"06002",
    "sg:province":"Badajoz",
    "wof:name":"Vaaf Auditores Consultores S.l.",
    "wof:placetype":"venue"
},
  "geometry": {"coordinates":[-6.97016716,38.8787002563],"type":"Point"}
}