{
  "type": "Feature",
  "properties": {
    "iso:country":"ES",
    "sg:address":"Calle de Torrijos, 10",
    "sg:city":"Cordoba",
    "sg:orig_category":"Organizaci\u00d3n De Actos, Seminarios Y Congresos",
    "sg:phone":"+34 902 12 34 12",
    "sg:postcode":"14003",
    "sg:province":"C\u00f3rdoba",
    "sg:website":"www.concordcongresos.com",
    "wof:name":"Concord Opc S.l.",
    "wof:placetype":"venue"
},
  "geometry": {"coordinates":[-4.7801961899,37.87840271],"type":"Point"}
}