{
  "type": "Feature",
  "properties": {
    "addr:full":"Plaz Maestro, S/n Le\u00f3n Le\u00f3n 24005",
    "addr:postcode":"24005",
    "addr:street":"Plaz Maestro S / N Leo\u0301N Leo\u0301N",
    "iso:country":"ES",
    "sg:address":"Plaz Maestro, S/n",
    "sg:city":"Le\u00f3n",
    "sg:orig_category":"Ense\u00d1anza, Formaci\u00d3n Profesional: Aprendizaje",
    "sg:phone":"+34 987 21 28 97",
    "sg:postcode":"24005",
    "sg:province":"Le\u00f3n",
    "wof:name":"Ayuntamiento De Leon",
    "wof:placetype":"venue"
},
  "geometry": {"coordinates":[-5.5459785461,42.5785369873],"type":"Point"}
}