{
  "type": "Feature",
  "properties": {
    "iso:country":"ES",
    "sg:address":"Carr Salmeron, 6",
    "sg:city":"Lleida",
    "sg:orig_category":"Confecci\u00d3n De Trajes Para Se\u00d1oras",
    "sg:phone":"+34 973 24 11 14",
    "sg:postcode":"25004",
    "sg:province":"Lleida",
    "wof:name":"Empretex S.a.l.",
    "wof:placetype":"venue"
},
  "geometry": {"coordinates":[0.6272400022,41.6208457947],"type":"Point"}
}