{
  "type": "Feature",
  "properties": {
    "addr:full":"Calle de Archiduque Carlos, 8 Valencia Valencia 46018",
    "addr:housenumber":"8",
    "addr:postcode":"46018",
    "addr:street":"Calle De Archiduque Carlos",
    "iso:country":"ES",
    "sg:address":"Calle de Archiduque Carlos, 8",
    "sg:city":"Valencia",
    "sg:orig_category":"Comercio Y Bancos",
    "sg:phone":"+34 963 85 18 14",
    "sg:postcode":"46018",
    "sg:province":"Valencia",
    "wof:name":"Volectric S.l.",
    "wof:placetype":"venue"
},
  "geometry": {"coordinates":[-0.3932797015,39.4665527344],"type":"Point"}
}