{
  "type": "Feature",
  "properties": {
    "addr:full":"Calle de Justiniano Lopez Brea, 21 Talavera Reina Toledo 45600",
    "addr:housenumber":"21",
    "addr:postcode":"45600",
    "addr:street":"Calle De Justiniano Lopez Brea",
    "iso:country":"ES",
    "sg:address":"Calle de Justiniano Lopez Brea, 21",
    "sg:city":"Talavera Reina",
    "sg:orig_category":"M\u00c1quinas Textiles, Accesorios Y Suministros (fabricaci\u00d3n)",
    "sg:phone":"+34 925 81 23 17",
    "sg:postcode":"45600",
    "sg:province":"Toledo",
    "wof:name":"Tecmatex Maquinaria S.l.",
    "wof:placetype":"venue"
},
  "geometry": {"coordinates":[-4.8155989647,39.9676704407],"type":"Point"}
}