{
  "type": "Feature",
  "properties": {
    "addr:full":"Calle de Calvario, 8 Burgos Burgos 09002",
    "addr:housenumber":"8",
    "addr:postcode":"09002",
    "addr:street":"Calle De Calvario",
    "iso:country":"ES",
    "sg:address":"Calle de Calvario, 8",
    "sg:city":"Burgos",
    "sg:orig_category":"Supermercados Y Hipermercados",
    "sg:phone":"+34 947 26 66 70",
    "sg:postcode":"09002",
    "sg:province":"Burgos",
    "sg:website":"www.mercadona.es",
    "wof:name":"Mercadona S.a.",
    "wof:placetype":"venue"
},
  "geometry": {"coordinates":[-3.6966094971,42.3348999023],"type":"Point"}
}