{
  "type": "Feature",
  "properties": {
    "iso:country":"ES",
    "sg:address":"Rua Carballo Calero, 6",
    "sg:city":"Ourense",
    "sg:orig_category":"Fabricaci\u00d3n De Jabones, Detergentes Y Lej\u00cdas",
    "sg:phone":"+34 988 22 79 42",
    "sg:postcode":"32005",
    "sg:province":"Ourense",
    "wof:name":"Fidalgo Joga S.l.",
    "wof:placetype":"venue"
},
  "geometry": {"coordinates":[-7.856716156,42.3298301697],"type":"Point"}
}