{
  "type": "Feature",
  "properties": {
    "addr:full":"Calle de Escorial, 5 Madrid Madrid 28004",
    "addr:housenumber":"5",
    "addr:postcode":"28004",
    "addr:street":"Calle De Escorial",
    "iso:country":"ES",
    "sg:address":"Calle de Escorial, 5",
    "sg:city":"Madrid",
    "sg:orig_category":"Promotores Constructores",
    "sg:phone":"+34 915 31 08 69",
    "sg:postcode":"28004",
    "sg:province":"Madrid",
    "wof:name":"Estudios Y Reformas S.l.",
    "wof:placetype":"venue"
},
  "geometry": {"coordinates":[-3.7028980255,40.4236335754],"type":"Point"}
}