{
  "type": "Feature",
  "properties": {
    "iso:country":"ES",
    "sg:address":"Calle de Granadilla, 12",
    "sg:city":"Majadahonda",
    "sg:orig_category":"Electrodom\u00c9sticos (fabricaci\u00d3n, Al Por Mayor)",
    "sg:phone":"+34 916 34 71 28",
    "sg:postcode":"28220",
    "sg:province":"Madrid",
    "sg:website":"www.vorwerk.es",
    "wof:name":"T-systems Itc Services Espa\u00d1a S.a.",
    "wof:placetype":"venue"
},
  "geometry": {"coordinates":[-3.8751242161,40.4705314636],"type":"Point"}
}