{
  "type": "Feature",
  "properties": {
    "addr:full":"Ctra Valdepe\u00d1as, S/n Ciudad Real Ciudad Real 13005",
    "addr:housenumber":"s",
    "addr:postcode":"13005",
    "addr:street":"Ctra Valdepen\u0303As;/ N",
    "iso:country":"ES",
    "sg:address":"Ctra Valdepe\u00d1as, S/n",
    "sg:city":"Ciudad Real",
    "sg:orig_category":"Pensiones Familiares",
    "sg:phone":"+34 926 25 23 09",
    "sg:postcode":"13005",
    "sg:province":"Ciudad Real",
    "wof:name":"Escudero Cencerrero Jose",
    "wof:placetype":"venue"
},
  "geometry": {"coordinates":[-3.9179279804,38.975063324],"type":"Point"}
}