{
  "type": "Feature",
  "properties": {
    "addr:full":"Calle de Martinez De Vega, 17 Mieres Asturias 33600",
    "addr:housenumber":"17",
    "addr:postcode":"33600",
    "addr:street":"Calle De Martinez De Vega",
    "iso:country":"ES",
    "sg:address":"Calle de Martinez De Vega, 17",
    "sg:city":"Mieres",
    "sg:orig_category":"Asesor\u00cda Sobre Comunicaci\u00d3n De Empresas",
    "sg:phone":"+34 985 45 09 16",
    "sg:postcode":"33600",
    "sg:province":"Asturias",
    "wof:name":"Suarez Rodriguez Maria Carmen",
    "wof:placetype":"venue"
},
  "geometry": {"coordinates":[-5.7750511169,43.2486038208],"type":"Point"}
}