{
  "type": "Feature",
  "properties": {
    "addr:full":"Av Paral.lel, 15 Barcelona Barcelona 08004",
    "addr:housenumber":"15",
    "addr:postcode":"08004",
    "addr:street":"Av Paral.Lel",
    "iso:country":"ES",
    "sg:address":"Av Paral.lel, 15",
    "sg:city":"Barcelona",
    "sg:orig_category":"Psicoterapeutas",
    "sg:phone":"+34 934 42 77 76",
    "sg:postcode":"08004",
    "sg:province":"Barcelona",
    "wof:name":"Preciado Iglesias Ignacio",
    "wof:placetype":"venue"
},
  "geometry": {"coordinates":[2.1748819351,41.3745498657],"type":"Point"}
}