{
  "type": "Feature",
  "properties": {
    "addr:full":"Calle de Doctor Manuel Candela, 53 Valencia Valencia 46021",
    "addr:housenumber":"53",
    "addr:postcode":"46021",
    "addr:street":"Calle De Doctor Manuel Candela",
    "iso:country":"ES",
    "sg:address":"Calle de Doctor Manuel Candela, 53",
    "sg:city":"Valencia",
    "sg:orig_category":"Inmobiliaria (agencias)",
    "sg:phone":"+34 963 39 46 10",
    "sg:postcode":"46021",
    "sg:province":"Valencia",
    "sg:website":"www.espofinques.es",
    "wof:name":"Oportunidad Levante, S.l",
    "wof:placetype":"venue"
},
  "geometry": {"coordinates":[-0.3496196866,39.4692420959],"type":"Point"}
}