{
  "type": "Feature",
  "properties": {
    "iso:country":"ES",
    "sg:address":"Merindad De Valdeporres, 9",
    "sg:city":"Villalonquejar",
    "sg:orig_category":"Fabricaci\u00d3n De Cajas De Cart\u00d3n",
    "sg:phone":"+34 947 29 70 30",
    "sg:postcode":"09001",
    "sg:province":"Burgos",
    "wof:name":"Embalajes Gosuma S.l.",
    "wof:placetype":"venue"
},
  "geometry": {"coordinates":[-3.7448339462,42.3662643433],"type":"Point"}
}