{
  "type": "Feature",
  "properties": {
    "iso:country":"ES",
    "sg:address":"Calle de Cea Bermudez, 4",
    "sg:city":"Madrid",
    "sg:orig_category":"Abogados",
    "sg:phone":"+34 915 53 39 97",
    "sg:postcode":"28003",
    "sg:province":"Madrid",
    "wof:name":"Bassols Coma Martin",
    "wof:placetype":"venue"
},
  "geometry": {"coordinates":[-3.706084013,40.4388771057],"type":"Point"}
}