{
  "type": "Feature",
  "properties": {
    "addr:full":"Calle de San Miguel, 21 Villanueva De Los Infantes Ciudad Real 13320",
    "addr:housenumber":"21",
    "addr:postcode":"13320",
    "addr:street":"Calle De San Miguel;Infantes",
    "iso:country":"ES",
    "sg:address":"Calle de San Miguel, 21",
    "sg:city":"Villanueva De Los Infantes",
    "sg:orig_category":"Frutas Y Legumbres Frescas (al Por Mayor)",
    "sg:phone":"+34 926 36 07 32",
    "sg:postcode":"13320",
    "sg:province":"Ciudad Real",
    "wof:name":"Riaza Solera Antonio",
    "wof:placetype":"venue"
},
  "geometry": {"coordinates":[-3.0082089901,38.7398300171],"type":"Point"}
}