{
  "type": "Feature",
  "properties": {
    "addr:full":"Pase San Gregorio, 70 Puertollano Ciudad Real 13500",
    "addr:housenumber":"70",
    "addr:postcode":"13500",
    "addr:street":"San Gregorio",
    "iso:country":"ES",
    "sg:address":"Pase San Gregorio, 70",
    "sg:city":"Puertollano",
    "sg:orig_category":"Mutuas De Seguros",
    "sg:phone":"+34 926 42 35 01",
    "sg:postcode":"13500",
    "sg:province":"Ciudad Real",
    "wof:name":"Fraternidad-muprespa Mutua De Accidentes De Trabajo Y Enfermedades Profesionales",
    "wof:placetype":"venue"
},
  "geometry": {"coordinates":[-4.1013522148,38.6896896362],"type":"Point"}
}