{
  "type": "Feature",
  "properties": {
    "iso:country":"ES",
    "sg:address":"A Fraga, S/n",
    "sg:city":"Fraga",
    "sg:orig_category":"Centros De Educaci\u00d3n Especial",
    "sg:phone":"+34 981 19 55 68",
    "sg:postcode":"15319",
    "sg:province":"La Coru\u00f1a",
    "wof:name":"Concello De Bergondo",
    "wof:placetype":"venue"
},
  "geometry": {"coordinates":[-8.0784473419,43.3035011292],"type":"Point"}
}