{
  "type": "Feature",
  "properties": {
    "addr:full":"Via Trajana, 47 Barcelona Barcelona 08020",
    "addr:housenumber":"47",
    "addr:postcode":"08020",
    "addr:street":"Via Trajana",
    "iso:country":"ES",
    "sg:address":"Via Trajana, 47",
    "sg:city":"Barcelona",
    "sg:orig_category":"Productos Qu\u00cdmicos (fabricaci\u00d3n, Al Por Mayor)",
    "sg:phone":"+34 933 14 29 09",
    "sg:postcode":"08020",
    "sg:province":"Barcelona",
    "wof:name":"Productos Quimicos Barcelona S. A.",
    "wof:placetype":"venue"
},
  "geometry": {"coordinates":[2.1996779442,41.4284248352],"type":"Point"}
}