{
  "type": "Feature",
  "properties": {
    "addr:full":"Calle de Pedro Monedero, 1 Astudillo Palencia 34450",
    "addr:housenumber":"1",
    "addr:postcode":"34450",
    "addr:street":"Calle De Pedro Monedero",
    "iso:country":"ES",
    "sg:address":"Calle de Pedro Monedero, 1",
    "sg:city":"Astudillo",
    "sg:orig_category":"Bancos",
    "sg:phone":"+34 979 82 21 96",
    "sg:postcode":"34450",
    "sg:province":"Palencia",
    "sg:website":"www.banesto.es",
    "wof:name":"Banco Espa\u00f1ol De Credito S.a.",
    "wof:placetype":"venue"
},
  "geometry": {"coordinates":[-4.2919120789,42.1925086975],"type":"Point"}
}