{
  "type": "Feature",
  "properties": {
    "iso:country":"ES",
    "sg:address":"Ctra Nac 152, Km. 0118,0",
    "sg:city":"Campelles",
    "sg:orig_category":"Distribuci\u00d3n De Petr\u00d3leo Y Derivados",
    "sg:phone":"+34 972 72 72 71",
    "sg:postcode":"17534",
    "sg:province":"Girona",
    "wof:name":"Movil S. A.",
    "wof:placetype":"venue"
},
  "geometry": {"coordinates":[-97.78224945069999,45.7040786743],"type":"Point"}
}