{
  "type": "Feature",
  "properties": {
    "iso:country":"ES",
    "sg:address":"Cmno Suarez, 12",
    "sg:city":"Malaga",
    "sg:orig_category":"Inmobiliaria (agencias)",
    "sg:phone":"+34 952 64 07 08",
    "sg:postcode":"29011",
    "sg:province":"M\u00e1laga",
    "wof:name":"Mas Que Casas S.l.",
    "wof:placetype":"venue"
},
  "geometry": {"coordinates":[-4.4369821548,36.7274284363],"type":"Point"}
}