{
  "type": "Feature",
  "properties": {
    "addr:full":"Calle de Mayor, 57 Bu\u00f1uel Navarra 31540",
    "addr:housenumber":"57",
    "addr:postcode":"31540",
    "addr:street":"Calle De Mayor",
    "iso:country":"ES",
    "sg:address":"Calle de Mayor, 57",
    "sg:city":"Bu\u00f1uel",
    "sg:orig_category":"Reposter\u00cdas",
    "sg:phone":"+34 948 83 30 50",
    "sg:postcode":"31540",
    "sg:province":"Navarra",
    "wof:name":"Arriazu Santos Maria Rosario Y Gracia Bozal Eduardo S.cv",
    "wof:placetype":"venue"
},
  "geometry": {"coordinates":[-1.4909447432,42.0218505859],"type":"Point"}
}