{
  "type": "Feature",
  "properties": {
    "addr:full":"Avda Agirre Lehendakaria, 58 Urbi Vizcaya 48970",
    "addr:housenumber":"58",
    "addr:postcode":"48970",
    "addr:street":"Avda Agirre Lehendakaria",
    "iso:country":"ES",
    "sg:address":"Avda Agirre Lehendakaria, 58",
    "sg:city":"Urbi",
    "sg:orig_category":"Higiene, Belleza: Art\u00cdculos (al Por Menor)",
    "sg:phone":"+34 944 40 46 58",
    "sg:postcode":"48970",
    "sg:province":"Vizcaya",
    "sg:website":"www.nectarcosmetics.com",
    "wof:name":"Yague Martin Maria Mar",
    "wof:placetype":"venue"
},
  "geometry": {"coordinates":[-2.8846490383,43.2368927002],"type":"Point"}
}