{
  "type": "Feature",
  "properties": {
    "addr:full":"Calle de Dolores Barranco, 33 Madrid Madrid 28026",
    "addr:housenumber":"33",
    "addr:postcode":"madrid;28026",
    "addr:street":"Calle De Dolores Barranco",
    "iso:country":"ES",
    "sg:address":"Calle de Dolores Barranco, 33",
    "sg:city":"Madrid",
    "sg:orig_category":"Agentes, Concesionarios Y Sucursales De Veh\u00cdculos",
    "sg:phone":"+34 914 76 06 51",
    "sg:postcode":"28026",
    "sg:province":"Madrid",
    "wof:name":"Bravosur Autos S.l.",
    "wof:placetype":"venue"
},
  "geometry": {"coordinates":[-3.7059340477,40.3831596375],"type":"Point"}
}