{
  "type": "Feature",
  "properties": {
    "addr:full":"Avda Aragon, 53 Alca\u00f1iz Teruel 44600",
    "addr:housenumber":"53",
    "addr:postcode":"44600",
    "addr:street":"Avda Aragon",
    "iso:country":"ES",
    "sg:address":"Avda Aragon, 53",
    "sg:city":"Alca\u00f1iz",
    "sg:orig_category":"\u00d3pticos Optometristas (al Por Menor)",
    "sg:phone":"+34 978 83 37 56",
    "sg:postcode":"44600",
    "sg:province":"Teruel",
    "wof:name":"Optica Y Audiologia Alca\u00f1iz S.l.",
    "wof:placetype":"venue"
},
  "geometry": {"coordinates":[-0.1296280026,41.0471458435],"type":"Point"}
}