{
  "type": "Feature",
  "properties": {
    "addr:full":"Calle de Los Lirios, 37 Almoradi Alicante 03160",
    "addr:housenumber":"37",
    "addr:postcode":"03160",
    "addr:street":"Calle De Los Lirios",
    "iso:country":"ES",
    "sg:address":"Calle de Los Lirios, 37",
    "sg:city":"Almoradi",
    "sg:orig_category":"Oficinas: Suministros Para (fabricaci\u00d3n, Al Por Mayor)",
    "sg:phone":"+34 965 70 12 50",
    "sg:postcode":"03160",
    "sg:province":"Alicante",
    "wof:name":"Ma\u00f1ogil Vegara Vicente",
    "wof:placetype":"venue"
},
  "geometry": {"coordinates":[-0.7928090096,38.1139984131],"type":"Point"}
}