{
  "type": "Feature",
  "properties": {
    "addr:full":"Oria Etorbidea-avenida De Oria, 8 Lasarte-oria Guip\u00f9zcoa 20160",
    "addr:housenumber":"8",
    "addr:postcode":"20160",
    "addr:street":"Oria;Guipu\u0300Zcoa",
    "iso:country":"ES",
    "sg:address":"Oria Etorbidea-avenida De Oria, 8",
    "sg:city":"Lasarte-oria",
    "sg:orig_category":"Fabricaci\u00d3n De Muebles",
    "sg:phone":"+34 943 36 04 96",
    "sg:postcode":"20160",
    "sg:province":"Guip\u00f9zcoa",
    "wof:name":"Izaribi, S.l.",
    "wof:placetype":"venue"
},
  "geometry": {"coordinates":[-2.020414114,43.2698173523],"type":"Point"}
}