{
  "type": "Feature",
  "properties": {
    "addr:full":"Avgd Alacant, 53 Pedreguer Alicante 03750",
    "addr:housenumber":"53",
    "addr:postcode":"03750",
    "addr:street":"Alacant",
    "iso:country":"ES",
    "sg:address":"Avgd Alacant, 53",
    "sg:city":"Pedreguer",
    "sg:orig_category":"Enfermeras: Consultas, Atenci\u00d3n A Domicilio",
    "sg:phone":"+34 965 76 13 71",
    "sg:postcode":"03750",
    "sg:province":"Alicante",
    "wof:name":"Salva Ballester Jose Pedro",
    "wof:placetype":"venue"
},
  "geometry": {"coordinates":[0.0378109999,38.792804718],"type":"Point"}
}