{
  "type": "Feature",
  "properties": {
    "iso:country":"ES",
    "sg:address":"Calle de Don Quijote, 70",
    "sg:city":"Novelda",
    "sg:orig_category":"Estancos",
    "sg:phone":"+34 965 60 02 89",
    "sg:postcode":"03660",
    "sg:province":"Alicante",
    "wof:name":"Garcia Caruana Arcadio",
    "wof:placetype":"venue"
},
  "geometry": {"coordinates":[-0.7581986189,38.3862571716],"type":"Point"}
}