{
  "type": "Feature",
  "properties": {
    "addr:full":"Calle de Cesar Elguezabal, 14 Alacant Alicante 03001",
    "addr:housenumber":"14",
    "addr:postcode":"03001",
    "addr:street":"Calle De Cesar Elguezabal",
    "iso:country":"ES",
    "sg:address":"Calle de Cesar Elguezabal, 14",
    "sg:city":"Alacant",
    "sg:orig_category":"Telas Y Sedas (al Por Menor)",
    "sg:phone":"+34 965 20 86 70",
    "sg:postcode":"03001",
    "sg:province":"Alicante",
    "wof:name":"Dise\u00f1o Alta Costura Diliana S.l",
    "wof:placetype":"venue"
},
  "geometry": {"coordinates":[-0.4861570895,38.3447647095],"type":"Point"}
}