{
  "type": "Feature",
  "properties": {
    "addr:full":"La Variante, 6 Lardero La Rioja 26140",
    "addr:housenumber":"6",
    "addr:postcode":"26140",
    "addr:street":"Variante;Rioja",
    "iso:country":"ES",
    "sg:address":"La Variante, 6",
    "sg:city":"Lardero",
    "sg:orig_category":"Cristaler\u00cdas",
    "sg:phone":"+34 941 45 20 82",
    "sg:postcode":"26140",
    "sg:province":"La Rioja",
    "wof:name":"Losantos Blanco David",
    "wof:placetype":"venue"
},
  "geometry": {"coordinates":[-2.4627640247,42.4269752502],"type":"Point"}
}