{
  "type": "Feature",
  "properties": {
    "iso:country":"ES",
    "sg:address":"Carrer de Santa Anna, 11",
    "sg:city":"Granollers",
    "sg:orig_category":"Peluqueros: De Se\u00d1oras",
    "sg:phone":"+34 938 70 79 50",
    "sg:postcode":"08401",
    "sg:province":"Barcelona",
    "wof:name":"Clavera Mirambell Maria Rosa",
    "wof:placetype":"venue"
},
  "geometry": {"coordinates":[2.2865879536,41.6088485718],"type":"Point"}
}