{
  "type": "Feature",
  "properties": {
    "addr:full":"Ctra Sant Mateu, S/n Benicarlo Castell\u00f3n 12580",
    "addr:housenumber":"s / n",
    "addr:postcode":"12580",
    "addr:street":"Ctra Sant Mateu",
    "iso:country":"ES",
    "sg:address":"Ctra Sant Mateu, S/n",
    "sg:city":"Benicarlo",
    "sg:orig_category":"Frutas Y Legumbres Frescas (al Por Mayor)",
    "sg:phone":"+34 964 47 30 39",
    "sg:postcode":"12580",
    "sg:province":"Castell\u00f3n",
    "wof:name":"Valles Marzal Francisco",
    "wof:placetype":"venue"
},
  "geometry": {"coordinates":[0.4157389998,40.4240646362],"type":"Point"}
}