{
  "type": "Feature",
  "properties": {
    "iso:country":"ES",
    "sg:address":"Calle de Pedrezuela, 38",
    "sg:city":"Madrid",
    "sg:orig_category":"Electricidad: Instaladores",
    "sg:phone":"+34 914 05 48 35",
    "sg:postcode":"28017",
    "sg:province":"Madrid",
    "wof:name":"Mu\u00f1oz Gallego Elias",
    "wof:placetype":"venue"
},
  "geometry": {"coordinates":[-3.6530740261,40.4280967712],"type":"Point"}
}