{
  "type": "Feature",
  "properties": {
    "iso:country":"ES",
    "sg:address":"Calle de San Prudencio, 13",
    "sg:city":"Vitoria-gasteiz",
    "sg:orig_category":"Cine (distribuci\u00d3n)",
    "sg:phone":"+34 945 14 01 26",
    "sg:postcode":"01005",
    "sg:province":"\u00c1lava",
    "wof:name":"Sociedad Kino Vision S.l.",
    "wof:placetype":"venue"
},
  "geometry": {"coordinates":[-2.6722779274,42.8441238403],"type":"Point"}
}