{
  "type": "Feature",
  "properties": {
    "addr:full":"Calle de Cromo, 167 Valladolid Valladolid 47012",
    "addr:housenumber":"167",
    "addr:postcode":"47012",
    "addr:street":"Calle De Cromo",
    "iso:country":"ES",
    "sg:address":"Calle de Cromo, 167",
    "sg:city":"Valladolid",
    "sg:orig_category":"Artes Gr\u00c1ficas, Artes Pl\u00c1sticas (curso)",
    "sg:phone":"+34 983 29 02 22",
    "sg:postcode":"47012",
    "sg:province":"Valladolid",
    "wof:name":"Valladolid Artes Graficas S.l.",
    "wof:placetype":"venue"
},
  "geometry": {"coordinates":[-4.7077889442,41.6255683899],"type":"Point"}
}