{
  "type": "Feature",
  "properties": {
    "iso:country":"ES",
    "sg:address":"Carrer de Lluis Jover (de), 57",
    "sg:city":"Vilassar De Mar",
    "sg:orig_category":"Caf\u00c9s, Bares, Cervecer\u00cdas",
    "sg:phone":"+34 937 50 02 58",
    "sg:postcode":"08340",
    "sg:province":"Barcelona",
    "wof:name":"Alegre Rubio Teresa",
    "wof:placetype":"venue"
},
  "geometry": {"coordinates":[2.38813591,41.5092124939],"type":"Point"}
}