{
  "type": "Feature",
  "properties": {
    "addr:full":"Carrer de Arquimedes, 33 Terrassa Barcelona 08224",
    "addr:housenumber":"33",
    "addr:postcode":"08224",
    "addr:street":"Carrer De Arquimedes",
    "iso:country":"ES",
    "sg:address":"Carrer de Arquimedes, 33",
    "sg:city":"Terrassa",
    "sg:orig_category":"Ingenier\u00cda, Centros De Estudios (diversos)",
    "sg:phone":"+34 937 89 38 10",
    "sg:postcode":"08224",
    "sg:province":"Barcelona",
    "wof:name":"Tormentila Sl",
    "wof:placetype":"venue"
},
  "geometry": {"coordinates":[2.0060760975,41.5575675964],"type":"Point"}
}