{
  "type": "Feature",
  "properties": {
    "iso:country":"ES",
    "sg:address":"Calle de Rafael Alberti, 6",
    "sg:city":"Coru\u00d1a",
    "sg:orig_category":"Inform\u00c1tica, Ofim\u00c1tica (estudios, Asesor\u00cda, Ingenier\u00cda, Formaci\u00d3n)",
    "sg:phone":"+34 981 28 35 11",
    "sg:postcode":"15008",
    "sg:province":"La Coru\u00f1a",
    "wof:name":"Confederacion De Empresarios De La Coru\u00d1a",
    "wof:placetype":"venue"
},
  "geometry": {"coordinates":[-8.4068670273,43.3494033813],"type":"Point"}
}