{
  "type": "Feature",
  "properties": {
    "addr:full":"Calle de Parroquia De Moruxo, S/n Poligono Industrial La Coru\u00f1a 15166",
    "addr:housenumber":"s / n",
    "addr:postcode":"15166",
    "addr:street":"Calle De Parroquia De Moruxo;Poligono Industrial;Corun\u0303A",
    "iso:country":"ES",
    "sg:address":"Calle de Parroquia De Moruxo, S/n",
    "sg:city":"Poligono Industrial",
    "sg:orig_category":"Bancos",
    "sg:phone":"+34 981 78 34 82",
    "sg:postcode":"15166",
    "sg:province":"La Coru\u00f1a",
    "sg:website":"www.bancogalicia.es",
    "wof:name":"Banco De Galicia",
    "wof:placetype":"venue"
},
  "geometry": {"coordinates":[-8.2616682053,43.3274726868],"type":"Point"}
}