{
  "type": "Feature",
  "properties": {
    "addr:full":"Calle de Euskalduna, 10 Bilbao Vizcaya 48008",
    "addr:housenumber":"10",
    "addr:postcode":"48008",
    "addr:street":"Calle De Euskalduna",
    "iso:country":"ES",
    "sg:address":"Calle de Euskalduna, 10",
    "sg:city":"Bilbao",
    "sg:orig_category":"Doctores En Medicina",
    "sg:phone":"+34 944 10 19 90",
    "sg:postcode":"48008",
    "sg:province":"Vizcaya",
    "wof:name":"Glamzagine S.l",
    "wof:placetype":"venue"
},
  "geometry": {"coordinates":[-2.9319870472,43.2597122192],"type":"Point"}
}