{
  "type": "Feature",
  "properties": {
    "iso:country":"ES",
    "sg:address":"El Palacio, 3",
    "sg:city":"Quintanadue\u00f1as",
    "sg:orig_category":"Sales (al Por Mayor)",
    "sg:phone":"+34 947 29 26 28",
    "sg:postcode":"09197",
    "sg:province":"Burgos",
    "wof:name":"Caldos Del Norte S. L.",
    "wof:placetype":"venue"
},
  "geometry": {"coordinates":[-3.7336161137,42.3859024048],"type":"Point"}
}