{
  "type": "Feature",
  "properties": {
    "iso:country":"ES",
    "sg:address":"Calle de Madrid, 12",
    "sg:city":"Getafe",
    "sg:orig_category":"Inmobiliaria (agencias)",
    "sg:phone":"+34 916 95 39 17",
    "sg:postcode":"28901",
    "sg:province":"Madrid",
    "wof:name":"Martin Durn Julio Jose",
    "wof:placetype":"venue"
},
  "geometry": {"coordinates":[-3.7312200069,40.3058204651],"type":"Point"}
}