{
  "type": "Feature",
  "properties": {
    "addr:full":"Avda Juan Carlos I, 9 Puebla Don Fadrique Granada 18820",
    "addr:housenumber":"9",
    "addr:postcode":"18820",
    "addr:street":"Avda Juan Carlos I",
    "iso:country":"ES",
    "sg:address":"Avda Juan Carlos I, 9",
    "sg:city":"Puebla Don Fadrique",
    "sg:orig_category":"Perfumer\u00cda (al Por Menor)",
    "sg:phone":"+34 958 72 16 39",
    "sg:postcode":"18820",
    "sg:province":"Granada",
    "wof:name":"Valcarcel Sanchez Ana",
    "wof:placetype":"venue"
},
  "geometry": {"coordinates":[-2.4366710186,37.9590187073],"type":"Point"}
}