{
  "type": "Feature",
  "properties": {
    "addr:full":"Calle de Agapito Marazuela, 22 Segovia Segovia 40005",
    "addr:housenumber":"22",
    "addr:postcode":"40005",
    "addr:street":"Calle De Agapito Marazuela",
    "iso:country":"ES",
    "sg:address":"Calle de Agapito Marazuela, 22",
    "sg:city":"Segovia",
    "sg:classifiers":[
        {
            "category":"Tea Room",
            "subcategory":"None",
            "type":"Food & Drink"
        }
    ],
    "sg:phone":"+34 921 43 64 93",
    "sg:postcode":"40005",
    "sg:province":"Segovia",
    "sg:tags":[
        "snack"
    ],
    "wof:name":"Burgos De Antonio Gema",
    "wof:placetype":"venue"
},
  "geometry": {"coordinates":[-4.1125769615,40.9379730225],"type":"Point"}
}