{
  "type": "Feature",
  "properties": {
    "addr:full":"Calle de Maria Magdalena, 27 Ibi Alicante 03440",
    "addr:housenumber":"27",
    "addr:postcode":"03440",
    "addr:street":"Calle De Maria Magdalena",
    "iso:country":"ES",
    "sg:address":"Calle de Maria Magdalena, 27",
    "sg:city":"Ibi",
    "sg:orig_category":"Fabricaci\u00d3n De Moldes Y Modelos",
    "sg:phone":"+34 966 55 33 80",
    "sg:postcode":"03440",
    "sg:province":"Alicante",
    "wof:name":"Grata Union Industrial S.l.",
    "wof:placetype":"venue"
},
  "geometry": {"coordinates":[-0.5821610093,38.6184539795],"type":"Point"}
}