{
  "type": "Feature",
  "properties": {
    "iso:country":"ES",
    "sg:address":"Calle de Alonso Cano, 8",
    "sg:city":"Madrid",
    "sg:orig_category":"Tintes (fabricaci\u00d3n, Al Por Mayor)",
    "sg:phone":"+34 914 48 66 59",
    "sg:postcode":"28010",
    "sg:province":"Madrid",
    "sg:website":"www.tintoreriaelytesec.com",
    "wof:name":"Pimafe S.l.",
    "wof:placetype":"venue"
},
  "geometry": {"coordinates":[-3.6979820728,40.4360351562],"type":"Point"}
}