{
  "type": "Feature",
  "properties": {
    "iso:country":"ES",
    "sg:address":"Calle de Juan Antonio Tercero, 19",
    "sg:city":"Malaga",
    "sg:orig_category":"Ropa Para Se\u00d1oras (al Por Menor)",
    "sg:phone":"+34 952 39 83 71",
    "sg:postcode":"29011",
    "sg:province":"M\u00e1laga",
    "wof:name":"Molia Garcia Gloria De Los Dolores",
    "wof:placetype":"venue"
},
  "geometry": {"coordinates":[-4.4418888092,36.7297515869],"type":"Point"}
}