{
  "type": "Feature",
  "properties": {
    "iso:country":"ES",
    "sg:address":"El Pozo, 1",
    "sg:city":"Mohedas",
    "sg:classifiers":[
        {
            "category":"Taxi",
            "type":"Transportation"
        }
    ],
    "sg:phone":"+34 927 67 35 90",
    "sg:postcode":"10664",
    "sg:province":"C\u00e1ceres",
    "wof:name":"Batuecas Franqueiro Francisco",
    "wof:placetype":"venue"
},
  "geometry": {"coordinates":[-6.2009358406,40.2672767639],"type":"Point"}
}