{
  "type": "Feature",
  "properties": {
    "addr:full":"Calle de Gonzalo Calamita, 4 Villaviciosa Odon Madrid 28670",
    "addr:housenumber":"4",
    "addr:postcode":"28670",
    "addr:street":"Calle De Gonzalo Calamita;Odon",
    "iso:country":"ES",
    "sg:address":"Calle de Gonzalo Calamita, 4",
    "sg:city":"Villaviciosa Odon",
    "sg:orig_category":"Arquitectos",
    "sg:phone":"+34 916 16 46 32",
    "sg:postcode":"28670",
    "sg:province":"Madrid",
    "wof:name":"Martin Martin Jose Antonio",
    "wof:placetype":"venue"
},
  "geometry": {"coordinates":[-3.9008491039,40.3587532043],"type":"Point"}
}