{
  "type": "Feature",
  "properties": {
    "iso:country":"ES",
    "sg:address":"Calle de Leizaran, 27",
    "sg:city":"Madrid",
    "sg:orig_category":"Ense\u00d1anza: Idiomas",
    "sg:phone":"+34 915 61 30 86",
    "sg:postcode":"28002",
    "sg:province":"Madrid",
    "wof:name":"Becherling De Pira Martina Christiane",
    "wof:placetype":"venue"
},
  "geometry": {"coordinates":[-3.6813969612,40.4480323792],"type":"Point"}
}