{
  "type": "Feature",
  "properties": {
    "addr:full":"Av Flors, 2 Sitges Barcelona 08870",
    "addr:housenumber":"2",
    "addr:postcode":"08870",
    "addr:street":"Av Flors",
    "iso:country":"ES",
    "sg:address":"Av Flors, 2",
    "sg:city":"Sitges",
    "sg:orig_category":"Cajas De Ahorro",
    "sg:phone":"+34 938 94 24 69",
    "sg:postcode":"08870",
    "sg:province":"Barcelona",
    "wof:name":"Caixa D'estalvis Del Penedes",
    "wof:placetype":"venue"
},
  "geometry": {"coordinates":[1.811193943,41.238986969],"type":"Point"}
}