{
  "type": "Feature",
  "properties": {
    "addr:full":"Calle de Cifuentes, 43 Guadalajara Guadalajara 19003",
    "addr:housenumber":"43",
    "addr:postcode":"19003",
    "addr:street":"Calle De Cifuentes",
    "iso:country":"ES",
    "sg:address":"Calle de Cifuentes, 43",
    "sg:city":"Guadalajara",
    "sg:orig_category":"Frutas, Legumbres Frescas Y Tempranas (al Por Menor)",
    "sg:phone":"+34 949 21 83 60",
    "sg:postcode":"19003",
    "sg:province":"Guadalajara",
    "wof:name":"Zorita Adan Jose Luis",
    "wof:placetype":"venue"
},
  "geometry": {"coordinates":[-3.1739890575,40.6319313049],"type":"Point"}
}