{
  "type": "Feature",
  "properties": {
    "iso:country":"ES",
    "sg:address":"Calle de Gutemberg, 14",
    "sg:city":"Getafe",
    "sg:orig_category":"Reparaciones Y Remolcado De Veh\u00cdculos",
    "sg:phone":"+34 916 81 36 48",
    "sg:postcode":"28906",
    "sg:province":"Madrid",
    "wof:name":"Gruas Peninsular S.l.",
    "wof:placetype":"venue"
},
  "geometry": {"coordinates":[-3.7001497746,40.2976074219],"type":"Point"}
}