{
  "type": "Feature",
  "properties": {
    "addr:full":"Calle de Santa Ana, 54 Villanueva Arzobispo Ja\u00e9n 23330",
    "addr:housenumber":"54",
    "addr:postcode":"23330",
    "addr:street":"Calle De Santa Ana",
    "iso:country":"ES",
    "sg:address":"Calle de Santa Ana, 54",
    "sg:city":"Villanueva Arzobispo",
    "sg:orig_category":"Empresas De Carpinter\u00cda Met\u00c1lica",
    "sg:phone":"+34 953 45 12 01",
    "sg:postcode":"23330",
    "sg:province":"Ja\u00e9n",
    "wof:name":"Fernandez Ballesteros Francisco",
    "wof:placetype":"venue"
},
  "geometry": {"coordinates":[-3.0133531094,38.16847229],"type":"Point"}
}