{
  "type": "Feature",
  "properties": {
    "addr:full":"Las Higueras, 21 Agua Garcia Santa Cruz De Tenerife 38355",
    "addr:housenumber":"21",
    "addr:postcode":"38355",
    "addr:street":"Las Higueras",
    "iso:country":"ES",
    "sg:address":"Las Higueras, 21",
    "sg:city":"Agua Garcia",
    "sg:orig_category":"Insecticidas, Fumigaci\u00d3n",
    "sg:phone":"+34 922 56 19 25",
    "sg:postcode":"38355",
    "sg:province":"Santa Cruz De Tenerife",
    "wof:name":"Delgado Guijarro Olegario",
    "wof:placetype":"venue"
},
  "geometry": {"coordinates":[-16.4078235626,28.4666137695],"type":"Point"}
}