{
  "type": "Feature",
  "properties": {
    "addr:full":"Carrer de Llum De La Selva, 2 Sabadell Barcelona 08208",
    "addr:housenumber":"2",
    "addr:postcode":"08208",
    "addr:street":"Carrer De Llum De La Selva",
    "iso:country":"ES",
    "sg:address":"Carrer de Llum De La Selva, 2",
    "sg:city":"Sabadell",
    "sg:orig_category":"Carnicer\u00cdas, Carnicer\u00cdas",
    "sg:phone":"+34 937 16 29 27",
    "sg:postcode":"08208",
    "sg:province":"Barcelona",
    "wof:name":"Embotits Medran S. L.",
    "wof:placetype":"venue"
},
  "geometry": {"coordinates":[2.1028680801,41.5613746643],"type":"Point"}
}