{
  "type": "Feature",
  "properties": {
    "iso:country":"ES",
    "sg:address":"Prado San Pedro, S/n",
    "sg:city":"Sig\u00fcenza",
    "sg:orig_category":"Maquinaria Para Industrias Diversas",
    "sg:phone":"+34 949 39 12 42",
    "sg:postcode":"19250",
    "sg:province":"Guadalajara",
    "wof:name":"Transportes Vibate S. L.",
    "wof:placetype":"venue"
},
  "geometry": {"coordinates":[-2.6444160938,41.0686836243],"type":"Point"}
}