{
  "type": "Feature",
  "properties": {
    "addr:full":"Avda Torre Pacheco (jimenado), S/n Jimenado Murcia 30708",
    "addr:housenumber":"s",
    "addr:postcode":"30708",
    "addr:street":"Avda Torre;Jimenado;/ N",
    "iso:country":"ES",
    "sg:address":"Avda Torre Pacheco (jimenado), S/n",
    "sg:city":"Jimenado",
    "sg:orig_category":"Alquiler De Gr\u00daas",
    "sg:phone":"+34 968 58 76 95",
    "sg:postcode":"30708",
    "sg:province":"Murcia",
    "wof:name":"Gruas Agumar S.l.",
    "wof:placetype":"venue"
},
  "geometry": {"coordinates":[-1.0358489752,37.7589912415],"type":"Point"}
}