{
  "type": "Feature",
  "properties": {
    "addr:full":"Avda Reyes Catolicos, S/n Zamora Zamora 49021",
    "addr:housenumber":"s",
    "addr:postcode":"49021",
    "addr:street":"Avda Reyes Catolicos;/ N",
    "iso:country":"ES",
    "sg:address":"Avda Reyes Catolicos, S/n",
    "sg:city":"Zamora",
    "sg:orig_category":"Asociaciones, Organismos Culturales Y Socioeducativos",
    "sg:phone":"+34 980 52 34 63",
    "sg:postcode":"49021",
    "sg:province":"Zamora",
    "wof:name":"Asociacion De Vecinos Y Cultural Los Bloques",
    "wof:placetype":"venue"
},
  "geometry": {"coordinates":[-5.7311382294,41.5120277405],"type":"Point"}
}