{
  "type": "Feature",
  "properties": {
    "iso:country":"ES",
    "sg:address":"Calle de Andalucia, S/n",
    "sg:city":"Cazalla Sierra",
    "sg:orig_category":"Internados & Ense\u00d1anza Privada",
    "sg:phone":"+34 954 88 41 35",
    "sg:postcode":"41370",
    "sg:province":"Sevilla",
    "wof:name":"Misioneras Doctrina Cristiana Curia Gener",
    "wof:placetype":"venue"
},
  "geometry": {"coordinates":[-5.760869503,37.9330787659],"type":"Point"}
}