{
  "type": "Feature",
  "properties": {
    "iso:country":"ES",
    "sg:address":"Calle de Milan, S/n",
    "sg:city":"Alcala Henares",
    "sg:orig_category":"Alquiler De Camiones Y Veh\u00cdculos Industriales",
    "sg:phone":"+34 918 82 98 88",
    "sg:postcode":"28805",
    "sg:province":"Madrid",
    "wof:name":"Benito Alonso Lorenzo",
    "wof:placetype":"venue"
},
  "geometry": {"coordinates":[-3.3372039795,40.4974555969],"type":"Point"}
}