{
  "type": "Feature",
  "properties": {
    "addr:full":"Calle de Pozuelo (de), 21 Fuenlabrada Madrid 28945",
    "addr:housenumber":"21",
    "addr:postcode":"28945",
    "addr:street":"Calle De Pozuelo De",
    "iso:country":"ES",
    "sg:address":"Calle de Pozuelo (de), 21",
    "sg:city":"Fuenlabrada",
    "sg:orig_category":"Hielo Artificial (fabricaci\u00d3n, Distribuci\u00d3n)",
    "sg:phone":"+34 916 15 21 10",
    "sg:postcode":"28945",
    "sg:province":"Madrid",
    "wof:name":"Espi Espi Miguel Angel",
    "wof:placetype":"venue"
},
  "geometry": {"coordinates":[-3.7956330776,40.2863540649],"type":"Point"}
}