{
  "type": "Feature",
  "properties": {
    "addr:full":"Rua Maria, 48 Ferrol La Coru\u00f1a 15402",
    "addr:housenumber":"48",
    "addr:postcode":"15402",
    "addr:street":"Rua Maria;La Corun\u0303A",
    "iso:country":"ES",
    "sg:address":"Rua Maria, 48",
    "sg:city":"Ferrol",
    "sg:orig_category":"M\u00c9dicos: Medicina General Orientada A La Homeopat\u00cda",
    "sg:phone":"+34 981 35 68 46",
    "sg:postcode":"15402",
    "sg:province":"La Coru\u00f1a",
    "wof:name":"Espi\u00f1eira Permuy Alberto",
    "wof:placetype":"venue"
},
  "geometry": {"coordinates":[-8.2320919037,43.4853744507],"type":"Point"}
}