{
  "type": "Feature",
  "properties": {
    "iso:country":"ES",
    "sg:address":"Calle de Francisco Aritio, 23",
    "sg:city":"Guadalajara",
    "sg:orig_category":"Mec\u00c1nico Del Autom\u00d3vil",
    "sg:phone":"+34 949 21 31 14",
    "sg:postcode":"19004",
    "sg:province":"Guadalajara",
    "wof:name":"Reparfast S.l.",
    "wof:placetype":"venue"
},
  "geometry": {"coordinates":[-3.1789183617,40.6437339783],"type":"Point"}
}