{
  "type": "Feature",
  "properties": {
    "addr:full":"Av Maresme (del), 383 Mataro Barcelona 08301",
    "addr:postcode":"08301",
    "addr:street":"Av;Del 383 Mataro Barcelona",
    "iso:country":"ES",
    "sg:address":"Av Maresme (del), 383",
    "sg:city":"Mataro",
    "sg:orig_category":"Laboratorios Y Trabajos De Fotograf\u00cda, V\u00cddeo Y Cine",
    "sg:phone":"+34 937 55 14 66",
    "sg:postcode":"08301",
    "sg:province":"Barcelona",
    "wof:name":"Martin Mas Asuncion",
    "wof:placetype":"venue"
},
  "geometry": {"coordinates":[2.4515299797,41.537979126],"type":"Point"}
}