{
  "type": "Feature",
  "properties": {
    "iso:country":"ES",
    "sg:address":"Calle de General Aranaz, 28",
    "sg:city":"Madrid",
    "sg:orig_category":"Promotores Constructores",
    "sg:phone":"+34 913 20 22 41",
    "sg:postcode":"28027",
    "sg:province":"Madrid",
    "wof:name":"Rodriguez Arenzana Rosa Maria",
    "wof:placetype":"venue"
},
  "geometry": {"coordinates":[-3.6370580196,40.4410667419],"type":"Point"}
}