{
  "type": "Feature",
  "properties": {
    "iso:country":"ES",
    "sg:address":"Carrer de Alts Forns, S/n",
    "sg:city":"Barcelona",
    "sg:orig_category":"Cristaler\u00cdas",
    "sg:phone":"+34 934 31 63 05",
    "sg:postcode":"08038",
    "sg:province":"Barcelona",
    "wof:name":"Cristaleria Rima S.l.",
    "wof:placetype":"venue"
},
  "geometry": {"coordinates":[2.1426401138,41.3600387573],"type":"Point"}
}