{
  "type": "Feature",
  "properties": {
    "addr:full":"Av Cortes Valencianas, 50 Albal Valencia 46470",
    "addr:housenumber":"50",
    "addr:postcode":"46470",
    "addr:street":"Av Cortes Valencianas",
    "iso:country":"ES",
    "sg:address":"Av Cortes Valencianas, 50",
    "sg:city":"Albal",
    "sg:orig_category":"Cajas De Ahorro",
    "sg:phone":"+34 961 26 02 94",
    "sg:postcode":"46470",
    "sg:province":"Valencia",
    "sg:website":"www.cam.es",
    "wof:name":"Caja De Ahorros Del Mediterraneo",
    "wof:placetype":"venue"
},
  "geometry": {"coordinates":[-0.4096949995,39.3967323303],"type":"Point"}
}