{
  "type": "Feature",
  "properties": {
    "iso:country":"ES",
    "sg:address":"Carrer de Major De Sarria, 75",
    "sg:city":"Barcelona",
    "sg:orig_category":"Arquitectos",
    "sg:phone":"+34 932 80 53 40",
    "sg:postcode":"08017",
    "sg:province":"Barcelona",
    "wof:name":"Font Ausio Jose Ignacio",
    "wof:placetype":"venue"
},
  "geometry": {"coordinates":[2.1222081184,41.398651123],"type":"Point"}
}