{
  "type": "Feature",
  "properties": {
    "addr:full":"Calle de Constitucion (de La), 14 Alcobendas Madrid 28100",
    "addr:housenumber":"14",
    "addr:postcode":"28100",
    "addr:street":"Calle De Constitucion De La",
    "iso:country":"ES",
    "sg:address":"Calle de Constitucion (de La), 14",
    "sg:city":"Alcobendas",
    "sg:orig_category":"Loter\u00cda Y T\u00d3mbola",
    "sg:phone":"+34 916 54 40 41",
    "sg:postcode":"28100",
    "sg:province":"Madrid",
    "wof:name":"Gomez Martin Jose Maria",
    "wof:placetype":"venue"
},
  "geometry": {"coordinates":[-3.6345255375,40.5416374207],"type":"Point"}
}