{
  "type": "Feature",
  "properties": {
    "iso:country":"ES",
    "sg:address":"Calle de Covarrubias, 6",
    "sg:city":"Toledo",
    "sg:orig_category":"Organizaciones Internacionales",
    "sg:phone":"+34 925 25 32 70",
    "sg:postcode":"45003",
    "sg:province":"Toledo",
    "wof:name":"Educacion Sin Fronteras",
    "wof:placetype":"venue"
},
  "geometry": {"coordinates":[-4.022149086,39.8677940369],"type":"Point"}
}