{
  "type": "Feature",
  "properties": {
    "iso:country":"ES",
    "sg:address":"Calle de Virgen De Criptana, 7",
    "sg:city":"Campo Criptana",
    "sg:orig_category":"Internados & Ense\u00d1anza Privada",
    "sg:phone":"+34 926 56 16 66",
    "sg:postcode":"13610",
    "sg:province":"Ciudad Real",
    "wof:name":"Monjas De La Orden De La Inmaculada Concepcion",
    "wof:placetype":"venue"
},
  "geometry": {"coordinates":[-3.1207270622,39.4054718018],"type":"Point"}
}