{
  "type": "Feature",
  "properties": {
    "addr:full":"C/ Hospital, 31 Elche Alicante 03203",
    "addr:housenumber":"31",
    "addr:postcode":"03203",
    "addr:street":"C / Hospital",
    "iso:country":"ES",
    "sg:address":"C/ Hospital, 31",
    "sg:city":"Elche",
    "sg:orig_category":"Fotocopias, Reprograf\u00cda",
    "sg:phone":"+34 965 42 36 51",
    "sg:postcode":"03203",
    "sg:province":"Alicante",
    "wof:name":"Plot-copy Elche S.l.",
    "wof:placetype":"venue"
},
  "geometry": {"coordinates":[-0.6955490112,38.2654800415],"type":"Point"}
}