{
  "type": "Feature",
  "properties": {
    "addr:full":"Pol Ind Hurpe, Km. 0432,0 Atarfe Granada 18230",
    "addr:postcode":"18230",
    "addr:street":"Hurpe Km. 0432,0",
    "iso:country":"ES",
    "sg:address":"Pol Ind Hurpe, Km. 0432,0",
    "sg:city":"Atarfe",
    "sg:orig_category":"Art\u00cdculos De Limpieza Y De Cocina (fabricaci\u00d3n, Al Por Mayor)",
    "sg:phone":"+34 958 43 79 23",
    "sg:postcode":"18230",
    "sg:province":"Granada",
    "wof:name":"Gonzalez Lopez Antonio",
    "wof:placetype":"venue"
},
  "geometry": {"coordinates":[-3.6903159618,37.2228775024],"type":"Point"}
}