{
  "type": "Feature",
  "properties": {
    "iso:country":"ES",
    "sg:address":"Calle de Salazar, 8",
    "sg:city":"Montoro",
    "sg:orig_category":"Asilos De Ancianos. Centros Privados",
    "sg:phone":"+34 957 16 22 47",
    "sg:postcode":"14600",
    "sg:province":"C\u00f3rdoba",
    "wof:name":"Hijas De La Caridad",
    "wof:placetype":"venue"
},
  "geometry": {"coordinates":[-4.3822999001,38.0250053406],"type":"Point"}
}