{
  "type": "Feature",
  "properties": {
    "addr:full":"Ctra. Jerez-los Barrios, S/n A. Gazules C\u00e1diz 11180",
    "addr:housenumber":"s / n",
    "addr:postcode":"11180",
    "addr:street":"Ctra. Jerez-Los Barrios;Ca\u0301Diz",
    "iso:country":"ES",
    "sg:address":"Ctra. Jerez-los Barrios, S/n",
    "sg:city":"A. Gazules",
    "sg:orig_category":"Cr\u00cda De Animales",
    "sg:phone":"+34 956 23 30 63",
    "sg:postcode":"11180",
    "sg:province":"C\u00e1diz",
    "wof:name":"Vallefor S.a.",
    "wof:placetype":"venue"
},
  "geometry": {"coordinates":[-5.7211689949,36.4625244141],"type":"Point"}
}