{
  "type": "Feature",
  "properties": {
    "iso:country":"ES",
    "sg:address":"Ctra Sant Hipolit, 16",
    "sg:city":"Vic",
    "sg:orig_category":"Alquiler De Gr\u00daas",
    "sg:phone":"+34 938 86 65 30",
    "sg:postcode":"08500",
    "sg:province":"Barcelona",
    "sg:website":"www.ausio.com",
    "wof:name":"Ausio-sistemas De Elevacion S.l.",
    "wof:placetype":"venue"
},
  "geometry": {"coordinates":[2.2532145977,41.9442863464],"type":"Point"}
}