{
  "type": "Feature",
  "properties": {
    "iso:country":"ES",
    "sg:address":"Calle de Italia, 27",
    "sg:city":"Alacant",
    "sg:orig_category":"Muebles, Minoristas",
    "sg:phone":"+34 965 22 88 71",
    "sg:postcode":"03003",
    "sg:province":"Alicante",
    "wof:name":"Almez S. A.",
    "wof:placetype":"venue"
},
  "geometry": {"coordinates":[-0.490974009,38.3404960632],"type":"Point"}
}