{
  "type": "Feature",
  "properties": {
    "addr:full":"Avgd Princep D'espanya, 10 Alcudia Islas Baleares 07400",
    "addr:housenumber":"10",
    "addr:postcode":"07400",
    "addr:street":"D'Espanya",
    "iso:country":"ES",
    "sg:address":"Avgd Princep D'espanya, 10",
    "sg:city":"Alcudia",
    "sg:orig_category":"Mec\u00c1nico Del Autom\u00d3vil",
    "sg:phone":"+34 971 54 58 45",
    "sg:postcode":"07400",
    "sg:province":"Islas Baleares",
    "wof:name":"Garcia Martinez Francisco",
    "wof:placetype":"venue"
},
  "geometry": {"coordinates":[3.1240999699,39.8519210815],"type":"Point"}
}