{
  "type": "Feature",
  "properties": {
    "addr:full":"Carrer de Joaquin Costa, 29 Barcelona Barcelona 08001",
    "addr:housenumber":"29",
    "addr:postcode":"08001",
    "addr:street":"Carrer De Joaquin Costa",
    "iso:country":"ES",
    "sg:address":"Carrer de Joaquin Costa, 29",
    "sg:city":"Barcelona",
    "sg:orig_category":"Farmacias",
    "sg:phone":"+34 934 42 49 45",
    "sg:postcode":"08001",
    "sg:province":"Barcelona",
    "wof:name":"Benavides Helbig Santiago",
    "wof:placetype":"venue"
},
  "geometry": {"coordinates":[2.1660439968,41.3820953369],"type":"Point"}
}