{
  "type": "Feature",
  "properties": {
    "iso:country":"ES",
    "sg:address":"Calle de Real, 9",
    "sg:city":"Valdemoro",
    "sg:orig_category":"Empresas De Carpinter\u00cda",
    "sg:phone":"+34 918 95 38 33",
    "sg:postcode":"28340",
    "sg:province":"Madrid",
    "wof:name":"Euro Alu-cris 2002 S.l",
    "wof:placetype":"venue"
},
  "geometry": {"coordinates":[-3.6784238815,40.1901855469],"type":"Point"}
}