{
  "type": "Feature",
  "properties": {
    "iso:country":"ES",
    "sg:address":"Carrer de Balmes, 30",
    "sg:city":"Barcelona",
    "sg:orig_category":"Abogados",
    "sg:phone":"+34 934 51 35 15",
    "sg:postcode":"08007",
    "sg:province":"Barcelona",
    "wof:name":"Gimenez Pita Emilio Antonio",
    "wof:placetype":"venue"
},
  "geometry": {"coordinates":[2.164331913,41.3881721497],"type":"Point"}
}