{
  "type": "Feature",
  "properties": {
    "addr:full":"Rond Alfons Xii, 3 Mataro Barcelona 08302",
    "addr:postcode":"08302",
    "iso:country":"ES",
    "sg:address":"Rond Alfons Xii, 3",
    "sg:city":"Mataro",
    "sg:orig_category":"Piedra, Vidrio, Cer\u00c1mica Y Porcelana",
    "sg:phone":"+34 937 99 48 59",
    "sg:postcode":"08302",
    "sg:province":"Barcelona",
    "wof:name":"Plana Abril Roser",
    "wof:placetype":"venue"
},
  "geometry": {"coordinates":[2.4398601055,41.5346183777],"type":"Point"}
}