{
  "type": "Feature",
  "properties": {
    "addr:full":"Calle de Baron De Santa Barbara, 68 Godella Valencia 46110",
    "addr:housenumber":"68",
    "addr:postcode":"46110",
    "addr:street":"Calle De Baron De Santa Barbara",
    "iso:country":"ES",
    "sg:address":"Calle de Baron De Santa Barbara, 68",
    "sg:city":"Godella",
    "sg:orig_category":"T\u00c9cnicos Veterinarios",
    "sg:phone":"+34 963 63 94 37",
    "sg:postcode":"46110",
    "sg:province":"Valencia",
    "wof:name":"Gallart Boix Rafael",
    "wof:placetype":"venue"
},
  "geometry": {"coordinates":[-0.4201470912,39.5230064392],"type":"Point"}
}