{
  "type": "Feature",
  "properties": {
    "iso:country":"ES",
    "sg:address":"Calle de Abajo, 4",
    "sg:city":"Guijuelo",
    "sg:orig_category":"Transportes De Animales Vivos",
    "sg:phone":"+34 923 58 08 07",
    "sg:postcode":"37770",
    "sg:province":"Salamanca",
    "sg:website":"www.psanchezmarcos.es",
    "wof:name":"Salchicheria Sanchez Marcos C.b.",
    "wof:placetype":"venue"
},
  "geometry": {"coordinates":[-5.671462059,40.5569610596],"type":"Point"}
}