{
  "type": "Feature",
  "properties": {
    "addr:full":"Pl Angel (de L'), 7 Tortosa Tarragona 43500",
    "addr:housenumber":"7",
    "addr:postcode":"43500",
    "addr:street":"Pl Angel De L '",
    "iso:country":"ES",
    "sg:address":"Pl Angel (de L'), 7",
    "sg:city":"Tortosa",
    "sg:orig_category":"\u00d3ptica: Instrumentos (fabricaci\u00d3n)",
    "sg:phone":"+34 977 44 51 24",
    "sg:postcode":"43500",
    "sg:province":"Tarragona",
    "wof:name":"Tot Per La Taula S.l.",
    "wof:placetype":"venue"
},
  "geometry": {"coordinates":[0.5217289925,40.812122345],"type":"Point"}
}