{
  "type": "Feature",
  "properties": {
    "addr:full":"Avda Mariano Andres, 58 Le\u00f3n Le\u00f3n 24008",
    "addr:housenumber":"58",
    "addr:postcode":"24008",
    "addr:street":"Avda Mariano Andres;Leo\u0301N",
    "iso:country":"ES",
    "sg:address":"Avda Mariano Andres, 58",
    "sg:city":"Le\u00f3n",
    "sg:orig_category":"Peluqueros: De Se\u00d1oras",
    "sg:phone":"+34 987 24 04 11",
    "sg:postcode":"24008",
    "sg:province":"Le\u00f3n",
    "wof:name":"Macias Martinez Maria De Las Mercedes",
    "wof:placetype":"venue"
},
  "geometry": {"coordinates":[-5.572347641,42.6085662842],"type":"Point"}
}