{
  "type": "Feature",
  "properties": {
    "addr:full":"Rua Nosa Sra. Do Viso, 2 Ourense Ourense 32005",
    "addr:housenumber":"2",
    "addr:postcode":"32005",
    "addr:street":"Rua Nosa Sra.;Viso",
    "iso:country":"ES",
    "sg:address":"Rua Nosa Sra. Do Viso, 2",
    "sg:city":"Ourense",
    "sg:orig_category":"Mec\u00c1nico Del Autom\u00d3vil",
    "sg:phone":"+34 988 22 77 36",
    "sg:postcode":"32005",
    "sg:province":"Ourense",
    "wof:name":"Soto Beneitez Luis",
    "wof:placetype":"venue"
},
  "geometry": {"coordinates":[-7.8635058403,42.3293037415],"type":"Point"}
}