{
  "type": "Feature",
  "properties": {
    "addr:full":"Carr Enginyer Balaguer, (de L'), 11 Carlet Valencia 46240",
    "addr:housenumber":"11",
    "addr:postcode":"46240",
    "addr:street":"Carr Enginyer;De L '",
    "iso:country":"ES",
    "sg:address":"Carr Enginyer Balaguer, (de L'), 11",
    "sg:city":"Carlet",
    "sg:orig_category":"Cajas De Ahorro",
    "sg:phone":"+34 962 53 80 29",
    "sg:postcode":"46240",
    "sg:province":"Valencia",
    "sg:website":"www.cam.es",
    "wof:name":"Caja De Ahorros Del Mediterraneo",
    "wof:placetype":"venue"
},
  "geometry": {"coordinates":[-0.5219320059,39.2265052795],"type":"Point"}
}