{
  "type": "Feature",
  "properties": {
    "addr:full":"Calle de Vizconde De Los Asilos, 7 Madrid Madrid 28027",
    "addr:housenumber":"7",
    "addr:postcode":"madrid;28027",
    "addr:street":"Calle De Vizconde De Los Asilos",
    "iso:country":"ES",
    "sg:address":"Calle de Vizconde De Los Asilos, 7",
    "sg:city":"Madrid",
    "sg:orig_category":"Droguer\u00cdas (al Por Menor)",
    "sg:phone":"+34 917 42 31 22",
    "sg:postcode":"28027",
    "sg:province":"Madrid",
    "wof:name":"Gonzalez Martinez Maximino",
    "wof:placetype":"venue"
},
  "geometry": {"coordinates":[-3.6384189129,40.4404907227],"type":"Point"}
}