{
  "type": "Feature",
  "properties": {
    "addr:full":"Carrer de Riera Ginjolers, 29 Roses Girona 17480",
    "addr:housenumber":"29",
    "addr:postcode":"17480",
    "addr:street":"Carrer De Riera Ginjolers",
    "iso:country":"ES",
    "sg:address":"Carrer de Riera Ginjolers, 29",
    "sg:city":"Roses",
    "sg:orig_category":"Bares, Piano",
    "sg:phone":"+34 972 25 42 20",
    "sg:postcode":"17480",
    "sg:province":"Girona",
    "wof:name":"Portales Rodriguez Veronica",
    "wof:placetype":"venue"
},
  "geometry": {"coordinates":[3.1767890453,42.2625465393],"type":"Point"}
}