{
  "type": "Feature",
  "properties": {
    "iso:country":"ES",
    "sg:address":"Avda Kilimon, 1",
    "sg:city":"Mendaro",
    "sg:orig_category":"Centros De Educaci\u00d3n Especial",
    "sg:phone":"+34 943 75 61 41",
    "sg:postcode":"20850",
    "sg:province":"Guip\u00f9zcoa",
    "wof:name":"Mendaroko Ikastola",
    "wof:placetype":"venue"
},
  "geometry": {"coordinates":[-2.3886470795,43.2516708374],"type":"Point"}
}