{
  "type": "Feature",
  "properties": {
    "addr:full":"Calle de Aranjuez, S/n Alcala Henares Madrid 28805",
    "addr:housenumber":"s",
    "addr:postcode":"28805",
    "addr:street":"Calle De Aranjuez;/ N",
    "iso:country":"ES",
    "sg:address":"Calle de Aranjuez, S/n",
    "sg:city":"Alcala Henares",
    "sg:orig_category":"Chapister\u00cda",
    "sg:phone":"+34 918 78 85 26",
    "sg:postcode":"28805",
    "sg:province":"Madrid",
    "wof:name":"Talleres Jumacar Alcala S.l.",
    "wof:placetype":"venue"
},
  "geometry": {"coordinates":[-3.350828886,40.4933052063],"type":"Point"}
}