{
  "type": "Feature",
  "properties": {
    "iso:country":"ES",
    "sg:address":"Calle de Sol, S/n",
    "sg:city":"Cogeces Monte",
    "sg:orig_category":"Cajas De Ahorro",
    "sg:phone":"+34 983 69 91 43",
    "sg:postcode":"47313",
    "sg:province":"Valladolid",
    "sg:website":"www.cajaespana.es",
    "wof:name":"Caja Espa\u00f1a De Inversiones Caja De Ahorros Y Monte De Piedad",
    "wof:placetype":"venue"
},
  "geometry": {"coordinates":[-4.3159470558,41.5097618103],"type":"Point"}
}