{
  "type": "Feature",
  "properties": {
    "addr:full":"Calle de Clara Del Rey, 14 Madrid Madrid 28002",
    "addr:housenumber":"14",
    "addr:postcode":"madrid;28002",
    "addr:street":"Calle De Clara Del Rey",
    "iso:country":"ES",
    "sg:address":"Calle de Clara Del Rey, 14",
    "sg:city":"Madrid",
    "sg:orig_category":"Bisuter\u00cda, Joyer\u00cda, Relojer\u00cda (al Por Menor)",
    "sg:phone":"+34 914 13 10 84",
    "sg:postcode":"28002",
    "sg:province":"Madrid",
    "wof:name":"Gomez Bada Mercedes",
    "wof:placetype":"venue"
},
  "geometry": {"coordinates":[-3.6713550091,40.4417533875],"type":"Point"}
}