{
  "type": "Feature",
  "properties": {
    "iso:country":"ES",
    "sg:address":"Calle de Americo Vespucio, S/n",
    "sg:city":"Sevilla",
    "sg:orig_category":"Aguas (distribuci\u00d3n, Servicios)",
    "sg:phone":"+34 954 46 02 51",
    "sg:postcode":"41092",
    "sg:province":"Sevilla",
    "sg:website":"www.centa-ue.com",
    "wof:name":"Centro De Las Nuevas Tecnologias Del Agua",
    "wof:placetype":"venue"
},
  "geometry": {"coordinates":[-6.0084457397,37.4042472839],"type":"Point"}
}