{
  "type": "Feature",
  "properties": {
    "iso:country":"ES",
    "sg:address":"Carr N'orlandis, De, 29",
    "sg:city":"Son Servera",
    "sg:orig_category":"Trabajos De Perforaciones, Sondeos, Construcci\u00d3n De Pozos",
    "sg:phone":"+34 971 56 70 12",
    "sg:postcode":"07550",
    "sg:province":"Islas Baleares",
    "wof:name":"Perello Calvo Lorenzo",
    "wof:placetype":"venue"
},
  "geometry": {"coordinates":[3.3564610481,39.6229934692],"type":"Point"}
}