{
  "type": "Feature",
  "properties": {
    "iso:country":"ES",
    "sg:address":"Rua Cruceiro, 7",
    "sg:city":"Cambre",
    "sg:orig_category":"Restaurantes",
    "sg:phone":"+34 981 67 45 00",
    "sg:postcode":"15660",
    "sg:province":"La Coru\u00f1a",
    "wof:name":"Miguez Losada Maria",
    "wof:placetype":"venue"
},
  "geometry": {"coordinates":[-8.3557987213,43.3154907227],"type":"Point"}
}