{
  "type": "Feature",
  "properties": {
    "addr:full":"Carrer de Industria, S/n Xiol Barcelona 08185",
    "addr:postcode":"08185",
    "addr:street":"Carrer De Industria S / N Xiol",
    "iso:country":"ES",
    "sg:address":"Carrer de Industria, S/n",
    "sg:city":"Xiol",
    "sg:orig_category":"Hilaturas, Hilos Y Actividades Relacionadas",
    "sg:phone":"+34 938 43 97 84",
    "sg:postcode":"08185",
    "sg:province":"Barcelona",
    "wof:name":"Kiianinks Iberica S.l.",
    "wof:placetype":"venue"
},
  "geometry": {"coordinates":[2.2325119972,41.5866622925],"type":"Point"}
}