{
  "type": "Feature",
  "properties": {
    "addr:full":"Carrer de L'estudiant, 52 Barcelona Barcelona 08016",
    "addr:housenumber":"52",
    "addr:postcode":"08016",
    "addr:street":"Carrer De L'Estudiant",
    "iso:country":"ES",
    "sg:address":"Carrer de L'estudiant, 52",
    "sg:city":"Barcelona",
    "sg:orig_category":"Transporte En General",
    "sg:phone":"+34 932 76 11 08",
    "sg:postcode":"08016",
    "sg:province":"Barcelona",
    "wof:name":"Vicente Vazquez David",
    "wof:placetype":"venue"
},
  "geometry": {"coordinates":[2.1785376072,41.435005188],"type":"Point"}
}