{
  "type": "Feature",
  "properties": {
    "addr:full":"Calle de San Gerardo, 59 Madrid Madrid 28035",
    "addr:housenumber":"59",
    "addr:postcode":"madrid;28035",
    "addr:street":"Calle De San Gerardo",
    "iso:country":"ES",
    "sg:address":"Calle de San Gerardo, 59",
    "sg:city":"Madrid",
    "sg:orig_category":"Abogados",
    "sg:phone":"+34 913 16 78 96",
    "sg:postcode":"28035",
    "sg:province":"Madrid",
    "wof:name":"Garcia Gomez Maria Elena",
    "wof:placetype":"venue"
},
  "geometry": {"coordinates":[-3.7246379852,40.4708518982],"type":"Point"}
}