{
  "type": "Feature",
  "properties": {
    "iso:country":"ES",
    "sg:address":"Avda Ifach, De, 18",
    "sg:city":"Calpe",
    "sg:orig_category":"Laboratorios Y Trabajos De Fotograf\u00cda, V\u00cddeo Y Cine",
    "sg:phone":"+34 965 83 14 16",
    "sg:postcode":"03710",
    "sg:province":"Alicante",
    "wof:name":"Borja Coello S.l.",
    "wof:placetype":"venue"
},
  "geometry": {"coordinates":[0.0455089994,38.6447715759],"type":"Point"}
}