{
  "type": "Feature",
  "properties": {
    "addr:full":"Cmno Pte Rey, S/n El Rocio Huelva 21750",
    "addr:housenumber":"s / n",
    "addr:postcode":"21750",
    "addr:street":"Cmno Pte Rey",
    "iso:country":"ES",
    "sg:address":"Cmno Pte Rey, S/n",
    "sg:city":"El Rocio",
    "sg:orig_category":"Centros De Educaci\u00d3n Especial",
    "sg:phone":"+34 959 44 22 27",
    "sg:postcode":"21750",
    "sg:province":"Huelva",
    "wof:name":"Junta De Andalucia",
    "wof:placetype":"venue"
},
  "geometry": {"coordinates":[-6.4842190742,37.1334342957],"type":"Point"}
}