{
  "type": "Feature",
  "properties": {
    "addr:full":"Carrer de Oms, 36 Palma Islas Baleares 07003",
    "addr:housenumber":"36",
    "addr:postcode":"07003",
    "addr:street":"Carrer De Oms",
    "iso:country":"ES",
    "sg:address":"Carrer de Oms, 36",
    "sg:city":"Palma",
    "sg:orig_category":"Fotocopias, Reprograf\u00cda",
    "sg:phone":"+34 971 72 43 32",
    "sg:postcode":"07003",
    "sg:province":"Islas Baleares",
    "sg:website":"www.scotibooks.com",
    "wof:name":"Salom Coli Serafin",
    "wof:placetype":"venue"
},
  "geometry": {"coordinates":[2.6495070457,39.5751228333],"type":"Point"}
}