{
  "type": "Feature",
  "properties": {
    "iso:country":"ES",
    "sg:address":"Ctra Malilla, 50",
    "sg:city":"Valencia",
    "sg:orig_category":"Peluqueros: De Se\u00d1oras",
    "sg:phone":"+34 963 33 94 25",
    "sg:postcode":"46026",
    "sg:province":"Valencia",
    "wof:name":"Garcia Alfaro Rosa",
    "wof:placetype":"venue"
},
  "geometry": {"coordinates":[-0.3789600134,39.4513397217],"type":"Point"}
}