{
  "type": "Feature",
  "properties": {
    "iso:country":"ES",
    "sg:address":"Avda Jablillo (el), S/n",
    "sg:city":"Costa Teguise",
    "sg:orig_category":"Dorados, Plater\u00cda (orfebrer\u00cda)",
    "sg:phone":"+34 928 34 60 42",
    "sg:postcode":"35509",
    "sg:province":"Las Palmas",
    "wof:name":"Lopez Masias Josefa",
    "wof:placetype":"venue"
},
  "geometry": {"coordinates":[-13.4973039627,28.9996700287],"type":"Point"}
}