{
  "type": "Feature",
  "properties": {
    "addr:full":"Calle de Lezeaga, 22 Bilbao Vizcaya 48002",
    "addr:housenumber":"22",
    "addr:postcode":"48002",
    "addr:street":"Calle De Lezeaga",
    "iso:country":"ES",
    "sg:address":"Calle de Lezeaga, 22",
    "sg:city":"Bilbao",
    "sg:orig_category":"Peluquer\u00cdas, Peluquer\u00cda Mixta",
    "sg:phone":"+34 944 42 27 95",
    "sg:postcode":"48002",
    "sg:province":"Vizcaya",
    "wof:name":"Torres Orois Ainoa",
    "wof:placetype":"venue"
},
  "geometry": {"coordinates":[-2.957003355,43.2585372925],"type":"Point"}
}