{
  "type": "Feature",
  "properties": {
    "iso:country":"ES",
    "sg:address":"Avda Zaragoza (de), S/n",
    "sg:city":"Albalate Arzobispo",
    "sg:orig_category":"Mec\u00c1nico Del Autom\u00d3vil",
    "sg:phone":"+34 978 81 23 61",
    "sg:postcode":"44540",
    "sg:province":"Teruel",
    "wof:name":"Quilez Aznar Joaquin",
    "wof:placetype":"venue"
},
  "geometry": {"coordinates":[-0.5104749799,41.1236877441],"type":"Point"}
}