{
  "type": "Feature",
  "properties": {
    "addr:full":"Calle de Cabru\u00d1ana, 52 Aviles Asturias 33402",
    "addr:housenumber":"52",
    "addr:postcode":"33402",
    "addr:street":"Calle De Cabrun\u0303Ana",
    "iso:country":"ES",
    "sg:address":"Calle de Cabru\u00d1ana, 52",
    "sg:city":"Aviles",
    "sg:orig_category":"Doctores En Medicina",
    "sg:phone":"+34 985 56 50 41",
    "sg:postcode":"33402",
    "sg:province":"Asturias",
    "wof:name":"Puertas Sanchez Cleto",
    "wof:placetype":"venue"
},
  "geometry": {"coordinates":[-5.9274358749,43.554271698],"type":"Point"}
}