{
  "type": "Feature",
  "properties": {
    "iso:country":"ES",
    "sg:address":"Calle de General Alvarez De Castro, 25",
    "sg:city":"Madrid",
    "sg:orig_category":"Institutos De Belleza",
    "sg:phone":"+34 914 48 53 25",
    "sg:postcode":"28010",
    "sg:province":"Madrid",
    "wof:name":"Nuevo Montero Consuelo",
    "wof:placetype":"venue"
},
  "geometry": {"coordinates":[-3.7027289867,40.4361953735],"type":"Point"}
}