{
  "type": "Feature",
  "properties": {
    "addr:full":"Avda Calvo Sotelo, 17 Huetor-tajar Granada 18360",
    "addr:housenumber":"17",
    "addr:postcode":"18360",
    "addr:street":"Avda Calvo Sotelo",
    "iso:country":"ES",
    "sg:address":"Avda Calvo Sotelo, 17",
    "sg:city":"Huetor-tajar",
    "sg:orig_category":"Orquestas Cl\u00c1sicas, Asociaciones De M\u00dasica, Coros Y Corales",
    "sg:phone":"+34 958 33 30 83",
    "sg:postcode":"18360",
    "sg:province":"Granada",
    "wof:name":"Crew Producciones S.l",
    "wof:placetype":"venue"
},
  "geometry": {"coordinates":[-4.0470910072,37.1975708008],"type":"Point"}
}