{
  "type": "Feature",
  "properties": {
    "addr:full":"Roquetes, 114 Sta. Eulalia Ron\u00e7ana Barcelona 08187",
    "addr:housenumber":"114",
    "addr:postcode":"08187",
    "addr:street":"Sta. Eulalia Ronc\u0327Ana",
    "iso:country":"ES",
    "sg:address":"Roquetes, 114",
    "sg:city":"Sta. Eulalia Ron\u00e7ana",
    "sg:orig_category":"Construcciones Met\u00c1licas",
    "sg:phone":"+34 938 44 96 66",
    "sg:postcode":"08187",
    "sg:province":"Barcelona",
    "wof:name":"Cercados Eurocasa S.l.",
    "wof:placetype":"venue"
},
  "geometry": {"coordinates":[2.2334620953,41.6613998413],"type":"Point"}
}