{
  "type": "Feature",
  "properties": {
    "iso:country":"ES",
    "sg:address":"Calle de Vicente Blasco Iba\u00d1ez, 23",
    "sg:city":"Rafal",
    "sg:orig_category":"Material Hidr\u00c1ulico",
    "sg:phone":"+34 966 75 22 37",
    "sg:postcode":"03369",
    "sg:province":"Alicante",
    "wof:name":"Construcciones Herrero Y Leal S.l.",
    "wof:placetype":"venue"
},
  "geometry": {"coordinates":[-0.8479530215,38.1050186157],"type":"Point"}
}