{
  "type": "Feature",
  "properties": {
    "addr:full":"Calle de A(campollano), 13 Albacete Albacete 02006",
    "addr:housenumber":"13",
    "addr:postcode":"02006",
    "addr:street":"Calle De A Campollano",
    "iso:country":"ES",
    "sg:address":"Calle de A(campollano), 13",
    "sg:city":"Albacete",
    "sg:orig_category":"Cuchiller\u00cda (al Por Menor)",
    "sg:phone":"+34 967 52 04 14",
    "sg:postcode":"02006",
    "sg:province":"Albacete",
    "wof:name":"Cuchilleria Ramirez S.l.",
    "wof:placetype":"venue"
},
  "geometry": {"coordinates":[-1.9490209818,39.013168335],"type":"Point"}
}