{
  "type": "Feature",
  "properties": {
    "iso:country":"ES",
    "sg:address":"Mogel Kalea, S/n",
    "sg:city":"Deba",
    "sg:orig_category":"Polideportivos",
    "sg:phone":"+34 943 19 22 62",
    "sg:postcode":"20820",
    "sg:province":"Guip\u00f9zcoa",
    "wof:name":"Kirolberri S.l.",
    "wof:placetype":"venue"
},
  "geometry": {"coordinates":[-2.3537769318,43.2924613953],"type":"Point"}
}