{
  "type": "Feature",
  "properties": {
    "iso:country":"ES",
    "sg:address":"Plaza Mayor, 4",
    "sg:city":"Albox",
    "sg:orig_category":"Hoteles",
    "sg:phone":"+34 950 43 00 24",
    "sg:postcode":"04800",
    "sg:province":"Almer\u00eda",
    "wof:name":"Hosteleria Albox S.l.",
    "wof:placetype":"venue"
},
  "geometry": {"coordinates":[-2.1415529251,37.4031028748],"type":"Point"}
}