{
  "type": "Feature",
  "properties": {
    "addr:full":"Calle de Ramon Y Cajal, 35 Coru\u00d1a La Coru\u00f1a 15006",
    "addr:housenumber":"35",
    "addr:postcode":"15006",
    "addr:street":"Calle De Ramon Y Cajal;Corun\u0303A",
    "iso:country":"ES",
    "sg:address":"Calle de Ramon Y Cajal, 35",
    "sg:city":"Coru\u00d1a",
    "sg:orig_category":"Restaurantes",
    "sg:phone":"+34 981 15 09 92",
    "sg:postcode":"15006",
    "sg:province":"La Coru\u00f1a",
    "wof:name":"Bonilla E Hijos S.l.",
    "wof:placetype":"venue"
},
  "geometry": {"coordinates":[-8.4016427994,43.3560562134],"type":"Point"}
}