{
  "type": "Feature",
  "properties": {
    "iso:country":"ES",
    "sg:address":"Rua A. R. Castelao, 28",
    "sg:city":"Bueu",
    "sg:orig_category":"Molduras, Junquillos, Listones Y Molduras Perforadas",
    "sg:phone":"+34 986 32 23 58",
    "sg:postcode":"36930",
    "sg:province":"Pontevedra",
    "wof:name":"Juncal Mari\u00f1o Serafin",
    "wof:placetype":"venue"
},
  "geometry": {"coordinates":[-8.7835893631,42.3273200989],"type":"Point"}
}