{
  "type": "Feature",
  "properties": {
    "iso:country":"ES",
    "sg:address":"Calle de Doctor Tolosa Latour, 37",
    "sg:city":"Chipiona",
    "sg:orig_category":"Molduras, Junquillos, Listones Y Molduras Perforadas",
    "sg:phone":"+34 956 37 18 49",
    "sg:postcode":"11550",
    "sg:province":"C\u00e1diz",
    "wof:name":"Garcia Mu\u00f1oz Jose",
    "wof:placetype":"venue"
},
  "geometry": {"coordinates":[-6.4383063316,36.7400817871],"type":"Point"}
}