{
  "type": "Feature",
  "properties": {
    "addr:full":"Calle de Mariano Ayala, 1 Bollullos Par Condado Huelva 21710",
    "addr:housenumber":"1",
    "addr:postcode":"21710",
    "addr:street":"Calle De Mariano Ayala",
    "iso:country":"ES",
    "sg:address":"Calle de Mariano Ayala, 1",
    "sg:city":"Bollullos Par Condado",
    "sg:orig_category":"Muebles, Minoristas",
    "sg:phone":"+34 959 41 06 15",
    "sg:postcode":"21710",
    "sg:province":"Huelva",
    "sg:website":"www.flandes.com",
    "wof:name":"Flandes Mobiliario S.l.",
    "wof:placetype":"venue"
},
  "geometry": {"coordinates":[-6.5344109535,37.3381958008],"type":"Point"}
}