{
  "type": "Feature",
  "properties": {
    "iso:country":"ES",
    "sg:address":"Calle de San Juan, 3",
    "sg:city":"Donostia-san Sebastian",
    "sg:orig_category":"Panader\u00cdas, Panader\u00cdas",
    "sg:phone":"+34 943 42 72 46",
    "sg:postcode":"20003",
    "sg:province":"Guip\u00f9zcoa",
    "wof:name":"Aristizadal Inziarte Maria Aranzazu",
    "wof:placetype":"venue"
},
  "geometry": {"coordinates":[-1.983053565,43.3232955933],"type":"Point"}
}