{
  "type": "Feature",
  "properties": {
    "iso:country":"ES",
    "sg:address":"Pla\u00c7 Llibertat, 16",
    "sg:city":"Centre Urba",
    "sg:orig_category":"Cajas De Ahorro",
    "sg:phone":"+34 972 70 01 53",
    "sg:postcode":"17500",
    "sg:province":"Girona",
    "wof:name":"Caixa De Girona",
    "wof:placetype":"venue"
},
  "geometry": {"coordinates":[2.1959049702,42.1965866089],"type":"Point"}
}