{
  "type": "Feature",
  "properties": {
    "addr:full":"Carr Binicanella, De, 7 Cala Millor Islas Baleares 07560",
    "addr:housenumber":"7",
    "addr:postcode":"07560",
    "addr:street":"Carr Binicanella De;Millor",
    "iso:country":"ES",
    "sg:address":"Carr Binicanella, De, 7",
    "sg:city":"Cala Millor",
    "sg:orig_category":"Zapatos (al Por Menor)",
    "sg:phone":"+34 971 58 73 23",
    "sg:postcode":"07560",
    "sg:province":"Islas Baleares",
    "wof:name":"Pallicer Morey Antonio",
    "wof:placetype":"venue"
},
  "geometry": {"coordinates":[3.3846700191,39.6020126343],"type":"Point"}
}