{
  "type": "Feature",
  "properties": {
    "addr:full":"Avda Lorca, 56 Sangonera Seca Murcia 30835",
    "addr:housenumber":"56",
    "addr:postcode":"30835",
    "addr:street":"Avda Lorca",
    "iso:country":"ES",
    "sg:address":"Avda Lorca, 56",
    "sg:city":"Sangonera Seca",
    "sg:orig_category":"Quincaller\u00cda (al Por Menor)",
    "sg:phone":"+34 968 80 08 97",
    "sg:postcode":"30835",
    "sg:province":"Murcia",
    "wof:name":"Bricogomez S.l.",
    "wof:placetype":"venue"
},
  "geometry": {"coordinates":[-1.2287689447,37.9602012634],"type":"Point"}
}