{
  "type": "Feature",
  "properties": {
    "iso:country":"ES",
    "sg:address":"Calle de Henao, 44",
    "sg:city":"Bilbao",
    "sg:orig_category":"Cajas De Ahorro",
    "sg:phone":"+34 944 24 67 14",
    "sg:postcode":"48009",
    "sg:province":"Vizcaya",
    "sg:website":"www.cajalaboral.com",
    "wof:name":"Caja Laboral Popular",
    "wof:placetype":"venue"
},
  "geometry": {"coordinates":[-2.935240984,43.2654876709],"type":"Point"}
}