{
  "type": "Feature",
  "properties": {
    "addr:full":"Calle de Folia (la), S/n Costa Teguise Las Palmas 35509",
    "addr:postcode":"35509",
    "addr:street":"Calle De Folia La S / N",
    "iso:country":"ES",
    "sg:address":"Calle de Folia (la), S/n",
    "sg:city":"Costa Teguise",
    "sg:orig_category":"Promotores Constructores",
    "sg:phone":"+34 928 34 65 11",
    "sg:postcode":"35509",
    "sg:province":"Las Palmas",
    "wof:name":"Hormiconsa Canarias S.a.",
    "wof:placetype":"venue"
},
  "geometry": {"coordinates":[-13.5136985779,28.98960495],"type":"Point"}
}