{
  "type": "Feature",
  "properties": {
    "iso:country":"ES",
    "sg:address":"Avda Teresa Pascual, 6",
    "sg:city":"Benasal",
    "sg:orig_category":"Mec\u00c1nico Del Autom\u00d3vil",
    "sg:phone":"+34 964 43 12 78",
    "sg:postcode":"12160",
    "sg:province":"Castell\u00f3n",
    "wof:name":"Talleres Pibel S.l.",
    "wof:placetype":"venue"
},
  "geometry": {"coordinates":[-0.1405189931,40.3801345825],"type":"Point"}
}