{
  "type": "Feature",
  "properties": {
    "addr:full":"Viso El, 13 Arahal Sevilla 41600",
    "addr:housenumber":"13",
    "addr:postcode":"41600",
    "addr:street":"Viso El",
    "iso:country":"ES",
    "sg:address":"Viso El, 13",
    "sg:city":"Arahal",
    "sg:orig_category":"Electricidad: Instaladores",
    "sg:phone":"+34 955 84 11 00",
    "sg:postcode":"41600",
    "sg:province":"Sevilla",
    "wof:name":"Lopez Segura Montajes Electricos S.l.",
    "wof:placetype":"venue"
},
  "geometry": {"coordinates":[-5.5427370071,37.2658920288],"type":"Point"}
}