{
  "type": "Feature",
  "properties": {
    "addr:full":"Carr Fassina, 9 Vilanova I La Geltru Barcelona 08800",
    "addr:housenumber":"9",
    "addr:postcode":"08800",
    "addr:street":"Carr Fassina",
    "iso:country":"ES",
    "sg:address":"Carr Fassina, 9",
    "sg:city":"Vilanova I La Geltru",
    "sg:orig_category":"Dibujantes (diversos)",
    "sg:phone":"+34 938 15 10 77",
    "sg:postcode":"08800",
    "sg:province":"Barcelona",
    "wof:name":"Andreu A\u00f1or Carlos",
    "wof:placetype":"venue"
},
  "geometry": {"coordinates":[1.7341939211,41.2175941467],"type":"Point"}
}