{
  "type": "Feature",
  "properties": {
    "addr:full":"Calle de A, S/n Pol. Plano-las Canales Zaragoza 50430",
    "addr:housenumber":"s / n",
    "addr:postcode":"50430",
    "addr:street":"Calle De A;Pol. Plano-Las Canales",
    "iso:country":"ES",
    "sg:address":"Calle de A, S/n",
    "sg:city":"Pol. Plano-las Canales",
    "sg:orig_category":"Construcciones Met\u00c1licas",
    "sg:phone":"+34 976 12 67 87",
    "sg:postcode":"50430",
    "sg:province":"Zaragoza",
    "sg:website":"www.wonder.es",
    "wof:name":"Transformaciones Agroganaderas S.l.",
    "wof:placetype":"venue"
},
  "geometry": {"coordinates":[-0.9965239763,41.5399703979],"type":"Point"}
}