{
  "type": "Feature",
  "properties": {
    "addr:full":"Carrer de Aspirantat Sant Jordi, 13 Alcanar Tarragona 43530",
    "addr:housenumber":"13",
    "addr:postcode":"43530",
    "addr:street":"Carrer De Aspirantat Sant Jordi",
    "iso:country":"ES",
    "sg:address":"Carrer de Aspirantat Sant Jordi, 13",
    "sg:city":"Alcanar",
    "sg:orig_category":"Forjas Y Altos Hornos",
    "sg:phone":"+34 977 73 10 49",
    "sg:postcode":"43530",
    "sg:province":"Tarragona",
    "wof:name":"Royo Fibla Manuel",
    "wof:placetype":"venue"
},
  "geometry": {"coordinates":[0.482558012,40.5414123535],"type":"Point"}
}