{
  "type": "Feature",
  "properties": {
    "iso:country":"ES",
    "sg:address":"Calle de Alameda Pint. Manuela Amo, 50",
    "sg:city":"Callosa Segura",
    "sg:orig_category":"Agentes, Concesionarios Y Sucursales De Veh\u00cdculos",
    "sg:phone":"+34 965 31 06 92",
    "sg:postcode":"03360",
    "sg:province":"Alicante",
    "wof:name":"Talleres Hipolito S.l.",
    "wof:placetype":"venue"
},
  "geometry": {"coordinates":[-0.8776689768,38.1256752014],"type":"Point"}
}