{
  "type": "Feature",
  "properties": {
    "iso:country":"ES",
    "sg:address":"Calle de Hernan Cortes, 4",
    "sg:city":"S. Clemente",
    "sg:orig_category":"Inform\u00c1tica, Ofim\u00c1tica (estudios, Asesor\u00cda, Ingenier\u00cda, Formaci\u00d3n)",
    "sg:phone":"+34 969 30 00 00",
    "sg:postcode":"16600",
    "sg:province":"Cuenca",
    "wof:name":"Pinedo Saiz Jesus",
    "wof:placetype":"venue"
},
  "geometry": {"coordinates":[-2.4239630699,39.4040718079],"type":"Point"}
}