{
  "type": "Feature",
  "properties": {
    "iso:country":"ES",
    "sg:address":"Avda Veinticinco De Julio, 57",
    "sg:city":"Santa Cruz De Tenerife",
    "sg:orig_category":"Abogados",
    "sg:phone":"+34 922 28 42 01",
    "sg:postcode":"38004",
    "sg:province":"Santa Cruz De Tenerife",
    "wof:name":"Matos Mascare\u00f1o Pablo",
    "wof:placetype":"venue"
},
  "geometry": {"coordinates":[-16.2564601898,28.4795894623],"type":"Point"}
}