{
  "type": "Feature",
  "properties": {
    "iso:country":"ES",
    "sg:address":"Calle de Lujan Perez, 8",
    "sg:city":"Villa De Moya",
    "sg:orig_category":"Ropa Y Accesorios",
    "sg:phone":"+34 928 61 21 90",
    "sg:postcode":"35420",
    "sg:province":"Las Palmas",
    "wof:name":"Marrero Batista Inmaculada",
    "wof:placetype":"venue"
},
  "geometry": {"coordinates":[-15.5831098557,28.1082134247],"type":"Point"}
}