{
  "type": "Feature",
  "properties": {
    "iso:country":"ES",
    "sg:address":"Pol Ind L'alter, S/n",
    "sg:city":"Alcacer",
    "sg:orig_category":"Contenedores (mercanc\u00cdas)",
    "sg:phone":"+34 961 24 20 77",
    "sg:postcode":"46290",
    "sg:province":"Valencia",
    "wof:name":"Transportes De Muebles Y Mudanzas Francisco M. S.l.",
    "wof:placetype":"venue"
},
  "geometry": {"coordinates":[-0.4493550062,39.3561897278],"type":"Point"}
}