{
  "type": "Feature",
  "properties": {
    "addr:full":"Avda Ricardo Carapeto Zambrano, 39 Badajoz Badajoz 06008",
    "addr:housenumber":"39",
    "addr:postcode":"06008",
    "addr:street":"Avda Ricardo Carapeto Zambrano",
    "iso:country":"ES",
    "sg:address":"Avda Ricardo Carapeto Zambrano, 39",
    "sg:city":"Badajoz",
    "sg:orig_category":"Controles De Edificaci\u00d3n (construcci\u00d3n, Seguridad)",
    "sg:phone":"+34 924 26 21 62",
    "sg:postcode":"06008",
    "sg:province":"Badajoz",
    "wof:name":"Floymal Promociones S.l",
    "wof:placetype":"venue"
},
  "geometry": {"coordinates":[-6.9527177811,38.8786239624],"type":"Point"}
}