{
  "type": "Feature",
  "properties": {
    "addr:full":"Cmno Planarresano, 60 Arnedo La Rioja 26580",
    "addr:housenumber":"60",
    "addr:postcode":"26580",
    "addr:street":"Cmno Planarresano;Rioja",
    "iso:country":"ES",
    "sg:address":"Cmno Planarresano, 60",
    "sg:city":"Arnedo",
    "sg:orig_category":"Motocicletas (agentes, Concesionarios)",
    "sg:phone":"+34 941 38 49 60",
    "sg:postcode":"26580",
    "sg:province":"La Rioja",
    "wof:name":"Martinez Martinez-burbana Javier",
    "wof:placetype":"venue"
},
  "geometry": {"coordinates":[-2.0999939442,42.2267951965],"type":"Point"}
}