{
  "type": "Feature",
  "properties": {
    "iso:country":"ES",
    "sg:address":"Avda Ciudad De Linares (de La), 22",
    "sg:city":"Ubeda",
    "sg:orig_category":"Carnicer\u00cdas, Carnicer\u00cdas",
    "sg:phone":"+34 953 79 28 56",
    "sg:postcode":"23400",
    "sg:province":"Ja\u00e9n",
    "wof:name":"Garcia Martinez Cristobal",
    "wof:placetype":"venue"
},
  "geometry": {"coordinates":[-3.3790938854,38.0151329041],"type":"Point"}
}