{
  "type": "Feature",
  "properties": {
    "iso:country":"ES",
    "sg:address":"Calle de Salvador, El, 65",
    "sg:city":"Torrent",
    "sg:orig_category":"Reposter\u00cdas",
    "sg:phone":"+34 961 55 00 94",
    "sg:postcode":"46900",
    "sg:province":"Valencia",
    "wof:name":"Canuto Perez Francisco",
    "wof:placetype":"venue"
},
  "geometry": {"coordinates":[-0.4725210071,39.4360198975],"type":"Point"}
}