{
  "type": "Feature",
  "properties": {
    "iso:country":"ES",
    "sg:address":"Calle de Xaheriz, 12",
    "sg:city":"Marchena",
    "sg:orig_category":"Reposter\u00cdas",
    "sg:phone":"+34 955 84 61 77",
    "sg:postcode":"41620",
    "sg:province":"Sevilla",
    "wof:name":"Panaderia Espiritu Santo S.l.",
    "wof:placetype":"venue"
},
  "geometry": {"coordinates":[-5.4220190048,37.3332481384],"type":"Point"}
}