{
  "type": "Feature",
  "properties": {
    "addr:full":"Calle de Menendez Y Pelayo, 40 Puerto Valencia 46520",
    "addr:housenumber":"40",
    "addr:postcode":"46520",
    "addr:street":"Calle De Menendez Y Pelayo",
    "iso:country":"ES",
    "sg:address":"Calle de Menendez Y Pelayo, 40",
    "sg:city":"Puerto",
    "sg:orig_category":"Cristaler\u00cdas",
    "sg:phone":"+34 962 67 13 07",
    "sg:postcode":"46520",
    "sg:province":"Valencia",
    "wof:name":"Cristaleria Felipe Belmonte Sl",
    "wof:placetype":"venue"
},
  "geometry": {"coordinates":[-0.218829006,39.6605949402],"type":"Point"}
}