{
  "type": "Feature",
  "properties": {
    "iso:country":"ES",
    "sg:address":"Calle de Arenal, 8",
    "sg:city":"Madrid",
    "sg:orig_category":"Relojer\u00cda (al Por Menor, Reparaci\u00d3n)",
    "sg:phone":"+34 915 21 33 42",
    "sg:postcode":"28013",
    "sg:province":"Madrid",
    "wof:name":"Taller Relojeria Maximo S.l.",
    "wof:placetype":"venue"
},
  "geometry": {"coordinates":[-3.7053759098,40.4169654846],"type":"Point"}
}