{
  "type": "Feature",
  "properties": {
    "addr:full":"Carrer de Pompeu Fabra, 8 Manresa Barcelona 08242",
    "addr:housenumber":"8",
    "addr:postcode":"08242",
    "addr:street":"Carrer De Pompeu Fabra",
    "iso:country":"ES",
    "sg:address":"Carrer de Pompeu Fabra, 8",
    "sg:city":"Manresa",
    "sg:orig_category":"Alumbrados",
    "sg:phone":"+34 938 72 17 32",
    "sg:postcode":"08242",
    "sg:province":"Barcelona",
    "sg:website":"www.bonetroca.com",
    "wof:name":"Bonet Roca S.a.",
    "wof:placetype":"venue"
},
  "geometry": {"coordinates":[1.8224289417,41.725933075],"type":"Point"}
}