{
  "type": "Feature",
  "properties": {
    "addr:full":"Carr Alberes, 37 Empuriabrava Girona 17487",
    "addr:housenumber":"37",
    "addr:postcode":"17487",
    "addr:street":"Carr Alberes",
    "iso:country":"ES",
    "sg:address":"Carr Alberes, 37",
    "sg:city":"Empuriabrava",
    "sg:orig_category":"Inmobiliaria (agencias)",
    "sg:phone":"+34 972 45 18 14",
    "sg:postcode":"17487",
    "sg:province":"Girona",
    "wof:name":"Coll Renart Jaume",
    "wof:placetype":"venue"
},
  "geometry": {"coordinates":[3.1146008968,42.2449607849],"type":"Point"}
}