{
  "type": "Feature",
  "properties": {
    "iso:country":"ES",
    "sg:address":"Calle de San Juan, 13",
    "sg:city":"Gernika-lumo",
    "sg:orig_category":"Psic\u00d3logos",
    "sg:phone":"+34 946 25 38 91",
    "sg:postcode":"48300",
    "sg:province":"Vizcaya",
    "wof:name":"Borda Elejabarrieta Juan Luis",
    "wof:placetype":"venue"
},
  "geometry": {"coordinates":[-2.6783380508,43.3161048889],"type":"Point"}
}