{
  "type": "Feature",
  "properties": {
    "addr:full":"Carrer de Foneria, 20 Barcelona Barcelona 08038",
    "addr:housenumber":"20",
    "addr:postcode":"08038",
    "addr:street":"Carrer De Foneria",
    "iso:country":"ES",
    "sg:address":"Carrer de Foneria, 20",
    "sg:city":"Barcelona",
    "sg:orig_category":"Alimentaci\u00d3n General (al Por Menor)",
    "sg:phone":"+34 932 96 86 30",
    "sg:postcode":"08038",
    "sg:province":"Barcelona",
    "wof:name":"Fernandez Bustos Pablo Manuel",
    "wof:placetype":"venue"
},
  "geometry": {"coordinates":[2.1376099586,41.3599624634],"type":"Point"}
}