{
  "type": "Feature",
  "properties": {
    "iso:country":"ES",
    "sg:address":"Calle de Fika, 63",
    "sg:city":"Bilbao",
    "sg:orig_category":"Frutas, Legumbres Frescas Y Tempranas (al Por Menor)",
    "sg:phone":"+34 944 33 05 98",
    "sg:postcode":"48006",
    "sg:province":"Vizcaya",
    "wof:name":"Diaz Jambrino Maria Rosana",
    "wof:placetype":"venue"
},
  "geometry": {"coordinates":[-2.917222023,43.2536392212],"type":"Point"}
}