{
  "type": "Feature",
  "properties": {
    "iso:country":"ES",
    "sg:address":"Calle de Gitana, 4",
    "sg:city":"Alameda",
    "sg:orig_category":"Zapatos (al Por Menor)",
    "sg:phone":"+34 952 71 12 67",
    "sg:postcode":"29530",
    "sg:province":"M\u00e1laga",
    "wof:name":"Ca\u00f1o Lanzas Mari Carmen",
    "wof:placetype":"venue"
},
  "geometry": {"coordinates":[-4.6586179733,37.2086715698],"type":"Point"}
}