{
  "type": "Feature",
  "properties": {
    "iso:country":"ES",
    "sg:address":"Calle de Velez De Guevara, 35",
    "sg:city":"Logro\u00f1o",
    "sg:orig_category":"Escayola Y Productos De Escayola (fabricaci\u00d3n, Al Por Mayor)",
    "sg:phone":"+34 941 22 87 90",
    "sg:postcode":"26005",
    "sg:province":"La Rioja",
    "wof:name":"Garcia De Pablo Jesus",
    "wof:placetype":"venue"
},
  "geometry": {"coordinates":[-2.4564549923,42.4616851807],"type":"Point"}
}