{
  "type": "Feature",
  "properties": {
    "addr:full":"Calle de Brujula, 6 Torrejon Ardoz Madrid 28850",
    "addr:housenumber":"6",
    "addr:postcode":"28850",
    "addr:street":"Calle De Brujula",
    "iso:country":"ES",
    "sg:address":"Calle de Brujula, 6",
    "sg:city":"Torrejon Ardoz",
    "sg:orig_category":"Guarder\u00cdas",
    "sg:phone":"+34 916 55 50 64",
    "sg:postcode":"28850",
    "sg:province":"Madrid",
    "wof:name":"Cenador Descosido Francisco",
    "wof:placetype":"venue"
},
  "geometry": {"coordinates":[-3.4598479271,40.4493484497],"type":"Point"}
}