{
  "type": "Feature",
  "properties": {
    "iso:country":"ES",
    "sg:address":"Calle de Informatica (la), 22",
    "sg:city":"Azuqueca Henares",
    "sg:orig_category":"Puertas Autom\u00c1ticas, Puertas De Garaje",
    "sg:phone":"+34 949 26 32 00",
    "sg:postcode":"19200",
    "sg:province":"Guadalajara",
    "wof:name":"Automatismos Bft Centro S.l.",
    "wof:placetype":"venue"
},
  "geometry": {"coordinates":[-3.2640228271,40.5587081909],"type":"Point"}
}