{
  "type": "Feature",
  "properties": {
    "addr:full":"Calle de Salinas, 21 Fuengirola M\u00e1laga 29640",
    "addr:housenumber":"21",
    "addr:postcode":"29640",
    "addr:street":"Calle De Salinas;Ma\u0301Laga",
    "iso:country":"ES",
    "sg:address":"Calle de Salinas, 21",
    "sg:city":"Fuengirola",
    "sg:orig_category":"Alquiler De Veh\u00cdculos: Turismos Y Utilitarios",
    "sg:phone":"+34 952 46 71 53",
    "sg:postcode":"29640",
    "sg:province":"M\u00e1laga",
    "wof:name":"Coots  David James",
    "wof:placetype":"venue"
},
  "geometry": {"coordinates":[-4.6222848892,36.559879303],"type":"Point"}
}