{
  "type": "Feature",
  "properties": {
    "addr:full":"Calle de Moreras (de Las), 39 Aranjuez Madrid 28300",
    "addr:housenumber":"39",
    "addr:postcode":"28300",
    "addr:street":"Calle De Moreras De Las",
    "iso:country":"ES",
    "sg:address":"Calle de Moreras (de Las), 39",
    "sg:city":"Aranjuez",
    "sg:orig_category":"Cl\u00cdnicas M\u00c9dicas",
    "sg:phone":"+34 918 92 10 71",
    "sg:postcode":"28300",
    "sg:province":"Madrid",
    "wof:name":"Moya Mu\u00f1oz Francisco Javier",
    "wof:placetype":"venue"
},
  "geometry": {"coordinates":[-3.5950820446,40.0355491638],"type":"Point"}
}