{
  "type": "Feature",
  "properties": {
    "iso:country":"ES",
    "sg:address":"Av. Petroleo, 10",
    "sg:city":"Leganes",
    "sg:orig_category":"Ebanister\u00cda",
    "sg:phone":"+34 916 11 52 57",
    "sg:postcode":"28918",
    "sg:province":"Madrid",
    "wof:name":"Hermadu S.l.",
    "wof:placetype":"venue"
},
  "geometry": {"coordinates":[-3.8017959595,40.3502426147],"type":"Point"}
}