{
  "type": "Feature",
  "properties": {
    "iso:country":"ES",
    "sg:address":"Cmno Socorro (del), 11",
    "sg:city":"G\u00fcimar",
    "sg:orig_category":"Teatro, Ballet, Danza (agrupaciones, Compa\u00d1\u00cdas)",
    "sg:phone":"+34 922 51 01 78",
    "sg:postcode":"38500",
    "sg:province":"Santa Cruz De Tenerife",
    "wof:name":"Lm Producciones Artisticas Canarias 2003 S.l.",
    "wof:placetype":"venue"
},
  "geometry": {"coordinates":[-16.4044284821,28.3154716492],"type":"Point"}
}