{
  "type": "Feature",
  "properties": {
    "addr:full":"Calle de Feria, 155 Sevilla Sevilla 41002",
    "addr:housenumber":"155",
    "addr:postcode":"41002",
    "addr:street":"Calle De Feria",
    "iso:country":"ES",
    "sg:address":"Calle de Feria, 155",
    "sg:city":"Sevilla",
    "sg:orig_category":"Molduras, Junquillos, Listones Y Molduras Perforadas",
    "sg:phone":"+34 954 37 88 57",
    "sg:postcode":"41002",
    "sg:province":"Sevilla",
    "wof:name":"Reyes Hurtado Genaro",
    "wof:placetype":"venue"
},
  "geometry": {"coordinates":[-5.9916419983,37.4020042419],"type":"Point"}
}