{
  "type": "Feature",
  "properties": {
    "addr:full":"Av Pau, 7 Platja D'aro Girona 17250",
    "addr:housenumber":"7",
    "addr:postcode":"17250",
    "addr:street":"Av Pau",
    "iso:country":"ES",
    "sg:address":"Av Pau, 7",
    "sg:city":"Platja D'aro",
    "sg:orig_category":"Discotecas Y Salas De Baile",
    "sg:phone":"+34 972 81 95 41",
    "sg:postcode":"17250",
    "sg:province":"Girona",
    "wof:name":"Roque Vilanova Ramon",
    "wof:placetype":"venue"
},
  "geometry": {"coordinates":[2.8254179955,41.9897994995],"type":"Point"}
}