{
  "type": "Feature",
  "properties": {
    "iso:country":"ES",
    "sg:address":"Plaz La Ciudadela, 1",
    "sg:city":"Vitoria-gasteiz",
    "sg:orig_category":"Agencias De Viajes",
    "sg:phone":"+34 945 14 59 59",
    "sg:postcode":"01012",
    "sg:province":"\u00c1lava",
    "wof:name":"Viajes Olarizu S.l.",
    "wof:placetype":"venue"
},
  "geometry": {"coordinates":[-2.6775500774,42.8551483154],"type":"Point"}
}