{
  "type": "Feature",
  "properties": {
    "addr:full":"Calle de Norte, 3 Villarquemado Teruel 44380",
    "addr:housenumber":"3",
    "addr:postcode":"44380",
    "addr:street":"Calle De Norte",
    "iso:country":"ES",
    "sg:address":"Calle de Norte, 3",
    "sg:city":"Villarquemado",
    "sg:orig_category":"Farmacias",
    "sg:phone":"+34 978 86 70 22",
    "sg:postcode":"44380",
    "sg:province":"Teruel",
    "wof:name":"Gil Hernandez Cayetano",
    "wof:placetype":"venue"
},
  "geometry": {"coordinates":[-1.2645030022,40.5180664062],"type":"Point"}
}