{
  "type": "Feature",
  "properties": {
    "addr:full":"Calle de Ensanche, 4 Sevilla Sevilla 41012",
    "addr:housenumber":"4",
    "addr:postcode":"41012",
    "addr:street":"Calle De Ensanche",
    "iso:country":"ES",
    "sg:address":"Calle de Ensanche, 4",
    "sg:city":"Sevilla",
    "sg:orig_category":"Energ\u00cda Solar Y Nuevas Energ\u00cdas (equipo, Estudios)",
    "sg:phone":"+34 954 62 04 70",
    "sg:postcode":"41012",
    "sg:province":"Sevilla",
    "wof:name":"Sol Xxi S.l.",
    "wof:placetype":"venue"
},
  "geometry": {"coordinates":[-5.9877109528,37.3560218811],"type":"Point"}
}