{
  "type": "Feature",
  "properties": {
    "addr:full":"Poli Industrial, S/n Guarnizo Cantabria 39611",
    "addr:housenumber":"/ n",
    "addr:postcode":"39611",
    "addr:street":"Industrial",
    "iso:country":"ES",
    "sg:address":"Poli Industrial, S/n",
    "sg:city":"Guarnizo",
    "sg:orig_category":"Mec\u00c1nico Del Autom\u00d3vil",
    "sg:phone":"+34 942 54 00 19",
    "sg:postcode":"39611",
    "sg:province":"Cantabria",
    "wof:name":"Talleres Marcelino Y Tomas S.l.",
    "wof:placetype":"venue"
},
  "geometry": {"coordinates":[-3.822521925,43.3990821838],"type":"Point"}
}