{
  "type": "Feature",
  "properties": {
    "addr:full":"Calle de Mercurio, 1 Alcorcon Madrid 28925",
    "addr:housenumber":"1",
    "addr:postcode":"28925",
    "addr:street":"Calle De Mercurio",
    "iso:country":"ES",
    "sg:address":"Calle de Mercurio, 1",
    "sg:city":"Alcorcon",
    "sg:orig_category":"Alimentaci\u00d3n General (al Por Menor)",
    "sg:phone":"+34 916 42 60 65",
    "sg:postcode":"28925",
    "sg:province":"Madrid",
    "wof:name":"Ye  Xianjuan",
    "wof:placetype":"venue"
},
  "geometry": {"coordinates":[-3.8077759743,40.3517723083],"type":"Point"}
}