{
  "type": "Feature",
  "properties": {
    "addr:full":"Calle de Santa Teresita, 42 Torrent Valencia 46900",
    "addr:housenumber":"42",
    "addr:postcode":"46900",
    "addr:street":"Calle De Santa Teresita;Valencia",
    "iso:country":"ES",
    "sg:address":"Calle de Santa Teresita, 42",
    "sg:city":"Torrent",
    "sg:orig_category":"Centros Empresariales",
    "sg:phone":"+34 961 56 56 37",
    "sg:postcode":"46900",
    "sg:province":"Valencia",
    "wof:name":"Garrido Blesa Nuria",
    "wof:placetype":"venue"
},
  "geometry": {"coordinates":[-0.4826120138,39.434211731],"type":"Point"}
}