{
  "type": "Feature",
  "properties": {
    "iso:country":"ES",
    "sg:address":"Pl Arago, 5",
    "sg:city":"Cambrils",
    "sg:orig_category":"Alimentaci\u00d3n General (al Por Menor)",
    "sg:phone":"+34 977 36 98 36",
    "sg:postcode":"43850",
    "sg:province":"Tarragona",
    "wof:name":"Corporacion Alimentaria Guissona S.a.",
    "wof:placetype":"venue"
},
  "geometry": {"coordinates":[1.0613429546,41.0674705505],"type":"Point"}
}