{
  "type": "Feature",
  "properties": {
    "iso:country":"ES",
    "sg:address":"Alfredo Alvarez Espina(prunadiella), 6",
    "sg:city":"Riosa",
    "sg:orig_category":"Sociedades, Compa\u00d1\u00cdas Aseguradoras",
    "sg:phone":"+34 985 76 70 96",
    "sg:postcode":"33160",
    "sg:province":"Asturias",
    "wof:name":"Mapfre Servicios De Informatica",
    "wof:placetype":"venue"
},
  "geometry": {"coordinates":[-5.8801760674,43.2323265076],"type":"Point"}
}