{
  "type": "Feature",
  "properties": {
    "addr:full":"Rond Nelle, 116 Coru\u00d1a La Coru\u00f1a 15010",
    "addr:housenumber":"116",
    "addr:postcode":"15010",
    "addr:street":"Rond Nelle;Corun\u0303A",
    "iso:country":"ES",
    "sg:address":"Rond Nelle, 116",
    "sg:city":"Coru\u00d1a",
    "sg:orig_category":"Farmacias",
    "sg:phone":"+34 981 25 71 00",
    "sg:postcode":"15010",
    "sg:province":"La Coru\u00f1a",
    "wof:name":"Farmacia Quintana Lacaci S.l.",
    "wof:placetype":"venue"
},
  "geometry": {"coordinates":[-8.4163150787,43.3621292114],"type":"Point"}
}