{
  "type": "Feature",
  "properties": {
    "addr:full":"Calle de Rio Valdecarza, 5 Poligono Sta M. De Benquerencia Toledo 45007",
    "addr:housenumber":"5 poligono",
    "addr:postcode":"45007",
    "addr:street":"Calle De Rio Valdecarza;Sta M. De Benquerencia",
    "iso:country":"ES",
    "sg:address":"Calle de Rio Valdecarza, 5",
    "sg:city":"Poligono Sta M. De Benquerencia",
    "sg:orig_category":"Cerrajer\u00cda, Ferrallista",
    "sg:phone":"+34 925 23 24 72",
    "sg:postcode":"45007",
    "sg:province":"Toledo",
    "wof:name":"Otero Dieguez Manuel",
    "wof:placetype":"venue"
},
  "geometry": {"coordinates":[-3.9523200989,39.8708992004],"type":"Point"}
}