{
  "type": "Feature",
  "properties": {
    "addr:full":"Pl Ajuntament, 1 Alcalali Alicante 03728",
    "addr:housenumber":"1",
    "addr:postcode":"03728",
    "addr:street":"Pl Ajuntament;Alicante",
    "iso:country":"ES",
    "sg:address":"Pl Ajuntament, 1",
    "sg:city":"Alcalali",
    "sg:orig_category":"Administraciones Regionales, Departamentales Y Locales",
    "sg:phone":"+34 966 48 20 24",
    "sg:postcode":"03728",
    "sg:province":"Alicante",
    "wof:name":"Ayuntamiento De Alcalali",
    "wof:placetype":"venue"
},
  "geometry": {"coordinates":[-0.0415849984,38.749710083],"type":"Point"}
}