{
  "type": "Feature",
  "properties": {
    "addr:full":"Calle de Valladolid, 7 Burgos Burgos 09002",
    "addr:housenumber":"7",
    "addr:postcode":"09002",
    "addr:street":"Calle De Valladolid",
    "iso:country":"ES",
    "sg:address":"Calle de Valladolid, 7",
    "sg:city":"Burgos",
    "sg:orig_category":"Procuradores",
    "sg:phone":"+34 947 26 72 65",
    "sg:postcode":"09002",
    "sg:province":"Burgos",
    "wof:name":"Santamaria Villorejo Jose Roberto",
    "wof:placetype":"venue"
},
  "geometry": {"coordinates":[-3.7005200386,42.3392829895],"type":"Point"}
}