{
  "type": "Feature",
  "properties": {
    "iso:country":"ES",
    "sg:address":"Calle de Hernan Cortes, S/n",
    "sg:city":"Andujar",
    "sg:orig_category":"Centros De Educaci\u00d3n Especial",
    "sg:phone":"+34 953 50 07 26",
    "sg:postcode":"23740",
    "sg:province":"Ja\u00e9n",
    "wof:name":"Junta De Andalucia.cp Jose Ruiz De Gordoa",
    "wof:placetype":"venue"
},
  "geometry": {"coordinates":[-4.0509538651,38.0446052551],"type":"Point"}
}