{
  "type": "Feature",
  "properties": {
    "iso:country":"ES",
    "sg:address":"Calle de Soto De Rojas, 82",
    "sg:city":"Granada",
    "sg:orig_category":"Molduras, Junquillos, Listones Y Molduras Perforadas",
    "sg:phone":"+34 958 15 35 16",
    "sg:postcode":"18011",
    "sg:province":"Granada",
    "wof:name":"Morales Moreno Manuel",
    "wof:placetype":"venue"
},
  "geometry": {"coordinates":[-3.6002442837,37.2067451477],"type":"Point"}
}