{
  "type": "Feature",
  "properties": {
    "iso:country":"ES",
    "sg:address":"Avda Castrelos, 20",
    "sg:city":"Vigo",
    "sg:orig_category":"Ense\u00d1anza Variada",
    "sg:phone":"+34 986 23 15 53",
    "sg:postcode":"36210",
    "sg:province":"Pontevedra",
    "sg:website":"www.come.to/estudios.mega",
    "wof:name":"Estudios Mega S.l.",
    "wof:placetype":"venue"
},
  "geometry": {"coordinates":[-8.7326183319,42.2193527222],"type":"Point"}
}