{
  "type": "Feature",
  "properties": {
    "iso:country":"ES",
    "sg:address":"Calle de Nieves (las), 21",
    "sg:city":"Segovia",
    "sg:orig_category":"Quincaller\u00cda (al Por Menor)",
    "sg:phone":"+34 921 44 11 48",
    "sg:postcode":"40003",
    "sg:province":"Segovia",
    "wof:name":"Gilsanz Arranz Mariano",
    "wof:placetype":"venue"
},
  "geometry": {"coordinates":[-4.1100668907,40.9552078247],"type":"Point"}
}