{
  "type": "Feature",
  "properties": {
    "iso:country":"ES",
    "sg:address":"Calle de Angel Torro, 18",
    "sg:city":"Banyeres Mariola",
    "sg:orig_category":"Peluquer\u00cdas, Peluquer\u00cda Mixta",
    "sg:phone":"+34 965 56 63 72",
    "sg:postcode":"03450",
    "sg:province":"Alicante",
    "wof:name":"Blasco Vicedo Miguel",
    "wof:placetype":"venue"
},
  "geometry": {"coordinates":[-0.6580539942,38.7164649963],"type":"Point"}
}