{
  "type": "Feature",
  "properties": {
    "iso:country":"ES",
    "sg:address":"Rua Condesa Pardo Bazan (la), 10",
    "sg:city":"Pontevedra",
    "sg:orig_category":"Albergues",
    "sg:phone":"+34 986 84 09 80",
    "sg:postcode":"36002",
    "sg:province":"Pontevedra",
    "wof:name":"Solla Barragans Jose Maria",
    "wof:placetype":"venue"
},
  "geometry": {"coordinates":[-8.649848938,42.4327888489],"type":"Point"}
}