{
  "type": "Feature",
  "properties": {
    "iso:country":"ES",
    "sg:address":"Pl Catalunya, 18",
    "sg:city":"Prat Llobregat",
    "sg:orig_category":"Mercer\u00cda, Lencer\u00cda (al Por Menor)",
    "sg:phone":"+34 934 78 51 04",
    "sg:postcode":"08820",
    "sg:province":"Barcelona",
    "wof:name":"Sanchez Sanclodio Encarnacion",
    "wof:placetype":"venue"
},
  "geometry": {"coordinates":[2.0921070576,41.3227767944],"type":"Point"}
}