{
  "type": "Feature",
  "properties": {
    "iso:country":"ES",
    "sg:address":"Pla\u00c7 Calvet I Rubalcaba, 7",
    "sg:city":"Girona",
    "sg:orig_category":"Papeler\u00cdas, Librer\u00cdas",
    "sg:phone":"+34 972 20 27 49",
    "sg:postcode":"17002",
    "sg:province":"Girona",
    "sg:website":"www.massegur.com",
    "wof:name":"Massegur S. A.",
    "wof:placetype":"venue"
},
  "geometry": {"coordinates":[2.822124958,41.9796485901],"type":"Point"}
}