{
  "type": "Feature",
  "properties": {
    "addr:full":"Calle de Lopez Landa, 4 Calatayud Zaragoza 50300",
    "addr:housenumber":"4",
    "addr:postcode":"50300",
    "addr:street":"Calle De Lopez Landa",
    "iso:country":"ES",
    "sg:address":"Calle de Lopez Landa, 4",
    "sg:city":"Calatayud",
    "sg:orig_category":"Molduras, Junquillos, Listones Y Molduras Perforadas",
    "sg:phone":"+34 976 88 25 24",
    "sg:postcode":"50300",
    "sg:province":"Zaragoza",
    "wof:name":"Argedas Bueno Manuel",
    "wof:placetype":"venue"
},
  "geometry": {"coordinates":[-1.6405930519,41.3526573181],"type":"Point"}
}