{
  "type": "Feature",
  "properties": {
    "iso:country":"ES",
    "sg:address":"Ctra Cartagena, S/n",
    "sg:city":"Valle Escombreras",
    "sg:orig_category":"Transportes Por V\u00cdas Navegables",
    "sg:phone":"+34 968 16 70 18",
    "sg:postcode":"30350",
    "sg:province":"Murcia",
    "wof:name":"Compa\u00d1ia Iberica De Transportes Especiales S.a.",
    "wof:placetype":"venue"
},
  "geometry": {"coordinates":[-0.9158269763,37.5820999146],"type":"Point"}
}