{
  "type": "Feature",
  "properties": {
    "addr:full":"Cmno Canal, 91 Valencia Valencia 46024",
    "addr:housenumber":"91",
    "addr:postcode":"46024",
    "addr:street":"Cmno Canal",
    "iso:country":"ES",
    "sg:address":"Cmno Canal, 91",
    "sg:city":"Valencia",
    "sg:orig_category":"Deportes N\u00c1uticos, Acu\u00c1ticos Y Subacu\u00c1ticos: Art\u00cdculos Y Equipo (al Por Menor)",
    "sg:phone":"+34 963 67 39 75",
    "sg:postcode":"46024",
    "sg:province":"Valencia",
    "sg:website":"www.miguelnavarro.com",
    "wof:name":"Carta Nautica S.l.",
    "wof:placetype":"venue"
},
  "geometry": {"coordinates":[-0.3359290063,39.4420890808],"type":"Point"}
}