{
  "type": "Feature",
  "properties": {
    "addr:full":"Calle de San Vicente, 3 Cadiz C\u00e1diz 11002",
    "addr:housenumber":"3",
    "addr:postcode":"11002",
    "addr:street":"Calle De San Vicente",
    "iso:country":"ES",
    "sg:address":"Calle de San Vicente, 3",
    "sg:city":"Cadiz",
    "sg:orig_category":"Carnicer\u00cdas, Carnicer\u00cdas",
    "sg:phone":"+34 956 22 59 33",
    "sg:postcode":"11002",
    "sg:province":"C\u00e1diz",
    "wof:name":"Rodriguez Herrera Manuel",
    "wof:placetype":"venue"
},
  "geometry": {"coordinates":[-6.299405098,36.5299835205],"type":"Point"}
}