{
  "type": "Feature",
  "properties": {
    "addr:full":"Arteaga Auzoa, 86 Arteaga Vizcaya 48170",
    "addr:housenumber":"86",
    "addr:postcode":"48170",
    "addr:street":"Arteaga Auzoa",
    "iso:country":"ES",
    "sg:address":"Arteaga Auzoa, 86",
    "sg:city":"Arteaga",
    "sg:orig_category":"Vulcanizado",
    "sg:phone":"+34 944 52 11 38",
    "sg:postcode":"48170",
    "sg:province":"Vizcaya",
    "wof:name":"Senarriaga Gutierrez Maria Julia",
    "wof:placetype":"venue"
},
  "geometry": {"coordinates":[-2.8546490669,43.2803573608],"type":"Point"}
}