{
  "type": "Feature",
  "properties": {
    "addr:full":"Calle de Jose Antonio, 39 Cuesta Santa Cruz De Tenerife 38320",
    "addr:housenumber":"39",
    "addr:postcode":"38320",
    "addr:street":"Calle De Jose Antonio;Cuesta Santa Cruz De",
    "iso:country":"ES",
    "sg:address":"Calle de Jose Antonio, 39",
    "sg:city":"Cuesta",
    "sg:orig_category":"Lavado, Limpieza De Veh\u00cdculos",
    "sg:phone":"+34 922 66 07 45",
    "sg:postcode":"38320",
    "sg:province":"Santa Cruz De Tenerife",
    "wof:name":"Autolavados Nonin S.l.",
    "wof:placetype":"venue"
},
  "geometry": {"coordinates":[-16.2905597687,28.4662284851],"type":"Point"}
}