{
  "type": "Feature",
  "properties": {
    "addr:full":"Avda Rio Nalon (del), S/n Alcazares Murcia 30710",
    "addr:postcode":"30710",
    "addr:street":"Avda Rio Nalon Del S / N",
    "iso:country":"ES",
    "sg:address":"Avda Rio Nalon (del), S/n",
    "sg:city":"Alcazares",
    "sg:orig_category":"Peluquer\u00cdas, Peluquer\u00cda Mixta",
    "sg:phone":"+34 968 58 22 83",
    "sg:postcode":"30710",
    "sg:province":"Murcia",
    "wof:name":"Moreno Soler Santiago",
    "wof:placetype":"venue"
},
  "geometry": {"coordinates":[-0.8425840139,37.7543411255],"type":"Point"}
}