{
  "type": "Feature",
  "properties": {
    "addr:full":"Calle de Colon, 13 Valencia Valencia 46004",
    "addr:housenumber":"13",
    "addr:postcode":"46004",
    "addr:street":"Calle De Colon",
    "iso:country":"ES",
    "sg:address":"Calle de Colon, 13",
    "sg:city":"Valencia",
    "sg:orig_category":"Ropa Para Se\u00d1oras (al Por Menor)",
    "sg:phone":"+34 963 94 25 90",
    "sg:postcode":"46004",
    "sg:province":"Valencia",
    "wof:name":"Perez Garcia-lajara Jose Luis",
    "wof:placetype":"venue"
},
  "geometry": {"coordinates":[-0.3733837008,39.4681777954],"type":"Point"}
}