{
  "type": "Feature",
  "properties": {
    "iso:country":"ES",
    "sg:address":"Calle de Rio Ventalama, 4",
    "sg:city":"Poligono Sta M. De Benquerencia",
    "sg:orig_category":"Empresas De Limpieza",
    "sg:phone":"+34 925 23 05 48",
    "sg:postcode":"45007",
    "sg:province":"Toledo",
    "wof:name":"Urbaser S.a.",
    "wof:placetype":"venue"
},
  "geometry": {"coordinates":[-3.944562912,39.8739242554],"type":"Point"}
}