{
  "type": "Feature",
  "properties": {
    "iso:country":"ES",
    "sg:address":"Carrer de Maria Vidal (de), 202",
    "sg:city":"Vilassar De Mar",
    "sg:orig_category":"Florister\u00cdas",
    "sg:phone":"+34 937 59 75 31",
    "sg:postcode":"08340",
    "sg:province":"Barcelona",
    "wof:name":"Gel Jorba Elena",
    "wof:placetype":"venue"
},
  "geometry": {"coordinates":[2.3879899979,41.5020217896],"type":"Point"}
}