{
  "type": "Feature",
  "properties": {
    "iso:country":"ES",
    "sg:address":"Pase Estacion, 91",
    "sg:city":"Salamanca",
    "sg:orig_category":"Zapater\u00cds Y Cordeler\u00cda",
    "sg:phone":"+34 923 22 02 98",
    "sg:postcode":"37004",
    "sg:province":"Salamanca",
    "wof:name":"Articulos De Fabricacion Natural S.l.",
    "wof:placetype":"venue"
},
  "geometry": {"coordinates":[-5.6507773399,40.9715957642],"type":"Point"}
}