{
  "type": "Feature",
  "properties": {
    "iso:country":"ES",
    "sg:address":"Calle de Inventor La Cierva, 26",
    "sg:city":"Langreo",
    "sg:orig_category":"Empresas De Desmonte",
    "sg:phone":"+34 985 69 54 33",
    "sg:postcode":"33930",
    "sg:province":"Asturias",
    "wof:name":"Valles Juez Jose Maria",
    "wof:placetype":"venue"
},
  "geometry": {"coordinates":[-5.6948680878,43.3066368103],"type":"Point"}
}