{
  "type": "Feature",
  "properties": {
    "iso:country":"ES",
    "sg:address":"Calle de Cruz, 14",
    "sg:city":"Madrid",
    "sg:orig_category":"Radiocomunicaciones, Telefon\u00cda M\u00d3vil, Radiomensajer\u00cda: Servicios, Comercializaci\u00d3n",
    "sg:phone":"+34 915 24 02 58",
    "sg:postcode":"28012",
    "sg:province":"Madrid",
    "wof:name":"Sion Telcom Dos",
    "wof:placetype":"venue"
},
  "geometry": {"coordinates":[-3.7019739151,40.4156074524],"type":"Point"}
}