{
  "type": "Feature",
  "properties": {
    "addr:full":"Aranerreka Kalea, 1 Bergara Guip\u00f9zcoa 20570",
    "addr:housenumber":"1",
    "addr:postcode":"20570",
    "addr:street":"Aranerreka Kalea;Guipu\u0300Zcoa",
    "iso:country":"ES",
    "sg:address":"Aranerreka Kalea, 1",
    "sg:city":"Bergara",
    "sg:orig_category":"Caf\u00c9s, Bares, Cervecer\u00cdas",
    "sg:phone":"+34 943 76 00 13",
    "sg:postcode":"20570",
    "sg:province":"Guip\u00f9zcoa",
    "wof:name":"Aranzabal Dorreonsoro Beatriz",
    "wof:placetype":"venue"
},
  "geometry": {"coordinates":[-2.4075059891,43.1199531555],"type":"Point"}
}