{
  "type": "Feature",
  "properties": {
    "addr:full":"Avda Teniente General Muslera, S/n Ceuta Ceuta 51002",
    "addr:housenumber":"s",
    "addr:postcode":"51002",
    "addr:street":"Avda Teniente General Muslera;/ N",
    "iso:country":"ES",
    "sg:address":"Avda Teniente General Muslera, S/n",
    "sg:city":"Ceuta",
    "sg:orig_category":"Ropa Para Ni\u00d1os (al Por Menor)",
    "sg:phone":"+34 956 50 17 13",
    "sg:postcode":"51002",
    "sg:province":"Ceuta",
    "sg:website":"www.bershka.com",
    "wof:name":"Bershka Bsr Espa\u00d1a S.a.",
    "wof:placetype":"venue"
},
  "geometry": {"coordinates":[-5.3299298286,35.8878097534],"type":"Point"}
}