{
  "type": "Feature",
  "properties": {
    "addr:full":"Calle de Mendizabala, 80 Vitoria-gasteiz \u00c1lava 01007",
    "addr:housenumber":"80",
    "addr:postcode":"01007",
    "addr:street":"Calle De Mendizabala",
    "iso:country":"ES",
    "sg:address":"Calle de Mendizabala, 80",
    "sg:city":"Vitoria-gasteiz",
    "sg:orig_category":"Empresas De Pintura Y Revestimientos",
    "sg:phone":"+34 945 23 28 55",
    "sg:postcode":"01007",
    "sg:province":"\u00c1lava",
    "wof:name":"Perez Mayo Isaac",
    "wof:placetype":"venue"
},
  "geometry": {"coordinates":[-2.6806030273,42.8364982605],"type":"Point"}
}