{
  "type": "Feature",
  "properties": {
    "addr:full":"Partida La Coma, S/n Fuentespalda Teruel 44587",
    "addr:housenumber":"s",
    "addr:postcode":"44587",
    "addr:street":"Partida La Coma;/ N",
    "iso:country":"ES",
    "sg:address":"Partida La Coma, S/n",
    "sg:city":"Fuentespalda",
    "sg:orig_category":"Cr\u00cda De Cerdos",
    "sg:phone":"+34 978 85 60 55",
    "sg:postcode":"44587",
    "sg:province":"Teruel",
    "wof:name":"Explotaciones Ganaderas La Coma",
    "wof:placetype":"venue"
},
  "geometry": {"coordinates":[0.0659089983,40.8055114746],"type":"Point"}
}