{
  "type": "Feature",
  "properties": {
    "iso:country":"ES",
    "sg:address":"Carrer de Doctor Pages, 39",
    "sg:city":"Santa Coloma De Gramenet",
    "sg:orig_category":"Radiocomunicaciones, Telefon\u00cda M\u00d3vil, Radiomensajer\u00cda: Servicios, Comercializaci\u00d3n",
    "sg:phone":"+34 934 68 51 65",
    "sg:postcode":"08922",
    "sg:province":"Barcelona",
    "wof:name":"Faruk  Ahamed",
    "wof:placetype":"venue"
},
  "geometry": {"coordinates":[2.2164950371,41.4486160278],"type":"Point"}
}