{
  "type": "Feature",
  "properties": {
    "addr:full":"Calle de Federico Martin Bahamonte, S/n Bollullos Par Condado Huelva 21710",
    "addr:housenumber":"s / n",
    "addr:postcode":"21710",
    "addr:street":"Calle De Federico Martin Bahamonte",
    "iso:country":"ES",
    "sg:address":"Calle de Federico Martin Bahamonte, S/n",
    "sg:city":"Bollullos Par Condado",
    "sg:orig_category":"Mec\u00c1nico Del Autom\u00d3vil",
    "sg:phone":"+34 959 41 15 03",
    "sg:postcode":"21710",
    "sg:province":"Huelva",
    "wof:name":"Suministros Y Talleres Del Condado S.c.a.",
    "wof:placetype":"venue"
},
  "geometry": {"coordinates":[-6.5249757767,37.3204689026],"type":"Point"}
}