{
  "type": "Feature",
  "properties": {
    "iso:country":"ES",
    "sg:address":"Estda. Viso A Vilanova, 65",
    "sg:city":"Hio",
    "sg:orig_category":"Librer\u00cdas",
    "sg:phone":"+34 986 32 87 15",
    "sg:postcode":"36948",
    "sg:province":"Pontevedra",
    "wof:name":"Cordeiro Coya Josefa",
    "wof:placetype":"venue"
},
  "geometry": {"coordinates":[-8.6428003311,42.4304618835],"type":"Point"}
}