{
  "type": "Feature",
  "properties": {
    "addr:full":"Carregal De Abaixo, 70 Amorin Pontevedra 36730",
    "addr:housenumber":"70",
    "addr:postcode":"36730",
    "addr:street":"Carregal De Abaixo",
    "iso:country":"ES",
    "sg:address":"Carregal De Abaixo, 70",
    "sg:city":"Amorin",
    "sg:orig_category":"Producci\u00d3n, Venta De Productos De Agricultura Biol\u00d3gica",
    "sg:phone":"+34 986 63 34 09",
    "sg:postcode":"36730",
    "sg:province":"Pontevedra",
    "wof:name":"Suministros Horticolas Bacelo S.l.",
    "wof:placetype":"venue"
},
  "geometry": {"coordinates":[-8.7277517319,41.9853744507],"type":"Point"}
}