{
  "type": "Feature",
  "properties": {
    "addr:full":"Calle de General Aznar, 43 Totana Murcia 30850",
    "addr:housenumber":"43",
    "addr:postcode":"30850",
    "addr:street":"Calle De General Aznar",
    "iso:country":"ES",
    "sg:address":"Calle de General Aznar, 43",
    "sg:city":"Totana",
    "sg:orig_category":"Electricidad: Instaladores",
    "sg:phone":"+34 968 42 42 67",
    "sg:postcode":"30850",
    "sg:province":"Murcia",
    "wof:name":"Instalaciones Y Montajes Rehelec S.l.",
    "wof:placetype":"venue"
},
  "geometry": {"coordinates":[-1.5001360178,37.7680282593],"type":"Point"}
}