{
  "type": "Feature",
  "properties": {
    "addr:full":"Pg Sunyer, 16 Reus Tarragona 43202",
    "addr:housenumber":"16",
    "addr:postcode":"43202",
    "addr:street":"Pg Sunyer",
    "iso:country":"ES",
    "sg:address":"Pg Sunyer, 16",
    "sg:city":"Reus",
    "sg:orig_category":"Cajas De Ahorro",
    "sg:phone":"+34 977 33 25 53",
    "sg:postcode":"43202",
    "sg:province":"Tarragona",
    "sg:website":"www.caixamanresa.es",
    "wof:name":"Caixa D'estalvis De Manresa",
    "wof:placetype":"venue"
},
  "geometry": {"coordinates":[1.1014260054,41.1567268372],"type":"Point"}
}