{
  "type": "Feature",
  "properties": {
    "addr:full":"Carrer de Torres (gracia), 48 Barcelona Barcelona 08042",
    "addr:housenumber":"48",
    "addr:postcode":"08042",
    "addr:street":"Carrer De Torres Gracia",
    "iso:country":"ES",
    "sg:address":"Carrer de Torres (gracia), 48",
    "sg:city":"Barcelona",
    "sg:orig_category":"Reposter\u00cdas",
    "sg:phone":"+34 932 76 25 75",
    "sg:postcode":"08042",
    "sg:province":"Barcelona",
    "wof:name":"Fruben S.a.",
    "wof:placetype":"venue"
},
  "geometry": {"coordinates":[2.1759700775,41.4470443726],"type":"Point"}
}