{
  "type": "Feature",
  "properties": {
    "addr:full":"Carr Paborde Marti, 33 Ciutadella Menorca Islas Baleares 07760",
    "addr:housenumber":"33",
    "addr:postcode":"07760",
    "addr:street":"Carr Paborde Marti",
    "iso:country":"ES",
    "sg:address":"Carr Paborde Marti, 33",
    "sg:city":"Ciutadella Menorca",
    "sg:orig_category":"Contenedores (mercanc\u00cdas)",
    "sg:phone":"+34 971 38 23 78",
    "sg:postcode":"07760",
    "sg:province":"Islas Baleares",
    "wof:name":"Alles Genestar Guillermo",
    "wof:placetype":"venue"
},
  "geometry": {"coordinates":[3.8431344032,40.0011672974],"type":"Point"}
}