{
  "type": "Feature",
  "properties": {
    "addr:full":"Calle de Isabel Serrano, 7 Madrid Madrid 28029",
    "addr:housenumber":"7",
    "addr:postcode":"madrid;28029",
    "addr:street":"Calle De Isabel Serrano",
    "iso:country":"ES",
    "sg:address":"Calle de Isabel Serrano, 7",
    "sg:city":"Madrid",
    "sg:orig_category":"Art\u00cdculos De Regalo (al Por Menor)",
    "sg:phone":"+34 913 14 32 94",
    "sg:postcode":"28029",
    "sg:province":"Madrid",
    "wof:name":"Blanco Fernandez Jose Ramon",
    "wof:placetype":"venue"
},
  "geometry": {"coordinates":[-3.7047870159,40.4685974121],"type":"Point"}
}