{
  "type": "Feature",
  "properties": {
    "addr:full":"Calle de Pio V, 12 Orihuela Alicante 03300",
    "addr:housenumber":"12",
    "addr:postcode":"03300",
    "addr:street":"Calle De Pio V",
    "iso:country":"ES",
    "sg:address":"Calle de Pio V, 12",
    "sg:city":"Orihuela",
    "sg:orig_category":"Pintura Y Barniz (al Por Menor)",
    "sg:phone":"+34 966 74 42 84",
    "sg:postcode":"03300",
    "sg:province":"Alicante",
    "wof:name":"Decoraciones Baspin S.l.",
    "wof:placetype":"venue"
},
  "geometry": {"coordinates":[-0.9395819902,38.0877685547],"type":"Point"}
}