{
  "type": "Feature",
  "properties": {
    "addr:full":"Avda Hontanilla, 8 Espinar Segovia 40400",
    "addr:housenumber":"8",
    "addr:postcode":"40400",
    "addr:street":"Avda Hontanilla",
    "iso:country":"ES",
    "sg:address":"Avda Hontanilla, 8",
    "sg:city":"Espinar",
    "sg:orig_category":"Carnicer\u00cdas, Carnicer\u00cdas",
    "sg:phone":"+34 921 18 24 75",
    "sg:postcode":"40400",
    "sg:province":"Segovia",
    "wof:name":"Garcia Martin Javier",
    "wof:placetype":"venue"
},
  "geometry": {"coordinates":[-4.2474741936,40.7178764343],"type":"Point"}
}