{
  "type": "Feature",
  "properties": {
    "iso:country":"ES",
    "sg:address":"Calle de Playa Frexeira, 6",
    "sg:city":"Estacion",
    "sg:orig_category":"Ense\u00d1anza: Idiomas",
    "sg:phone":"+34 918 51 68 20",
    "sg:postcode":"28400",
    "sg:province":"Madrid",
    "wof:name":"Made In English S.l.",
    "wof:placetype":"venue"
},
  "geometry": {"coordinates":[-4.0095911026,40.6211204529],"type":"Point"}
}