{
  "type": "Feature",
  "properties": {
    "addr:full":"Calle de Rafael Gil, 6 Huesca Huesca 22003",
    "addr:housenumber":"6",
    "addr:postcode":"22003",
    "addr:street":"Calle De Rafael Gil",
    "iso:country":"ES",
    "sg:address":"Calle de Rafael Gil, 6",
    "sg:city":"Huesca",
    "sg:orig_category":"Frutas, Legumbres Frescas Y Tempranas (al Por Menor)",
    "sg:phone":"+34 974 22 16 19",
    "sg:postcode":"22003",
    "sg:province":"Huesca",
    "wof:name":"Sauque Capablo Pedro",
    "wof:placetype":"venue"
},
  "geometry": {"coordinates":[-0.4156009853,42.1400527954],"type":"Point"}
}