{
  "type": "Feature",
  "properties": {
    "addr:full":"Poligono Industrial, S/n Guadix Granada 18500",
    "addr:postcode":"18500",
    "addr:street":"Industrial S / N",
    "iso:country":"ES",
    "sg:address":"Poligono Industrial, S/n",
    "sg:city":"Guadix",
    "sg:orig_category":"Mec\u00c1nico Del Autom\u00d3vil",
    "sg:phone":"+34 958 66 15 26",
    "sg:postcode":"18500",
    "sg:province":"Granada",
    "wof:name":"Talleres Martinez Y Lopez S.l.l.",
    "wof:placetype":"venue"
},
  "geometry": {"coordinates":[-3.1343688965,37.303894043],"type":"Point"}
}