{
  "type": "Feature",
  "properties": {
    "addr:full":"Calle de Carretera, S/n Villahibiera Le\u00f3n 24930",
    "addr:postcode":"24930",
    "addr:street":"Calle De Carretera S / N Villahibiera Leo\u0301N",
    "iso:country":"ES",
    "sg:address":"Calle de Carretera, S/n",
    "sg:city":"Villahibiera",
    "sg:orig_category":"Venta, Instalaci\u00d3n De Cocinas",
    "sg:phone":"+34 987 33 31 02",
    "sg:postcode":"24930",
    "sg:province":"Le\u00f3n",
    "wof:name":"Montero Martinez Santos",
    "wof:placetype":"venue"
},
  "geometry": {"coordinates":[-5.2270007133,42.6052856445],"type":"Point"}
}