{
  "type": "Feature",
  "properties": {
    "addr:full":"Calle de Oruro, 14 Madrid Madrid 28016",
    "addr:housenumber":"14",
    "addr:postcode":"madrid;28016",
    "addr:street":"Calle De Oruro",
    "iso:country":"ES",
    "sg:address":"Calle de Oruro, 14",
    "sg:city":"Madrid",
    "sg:orig_category":"Caf\u00c9s, Bares, Cervecer\u00cdas",
    "sg:phone":"+34 913 44 04 31",
    "sg:postcode":"28016",
    "sg:province":"Madrid",
    "wof:name":"Cuadrado Ramos Jose Antonio",
    "wof:placetype":"venue"
},
  "geometry": {"coordinates":[-3.678467989,40.4554595947],"type":"Point"}
}