{
  "type": "Feature",
  "properties": {
    "iso:country":"ES",
    "sg:address":"Calle de Conde De Barajas, 21",
    "sg:city":"Sevilla",
    "sg:classifiers":[
        {
            "category":"Arts & Performance",
            "subcategory":"Art Gallery",
            "type":"Entertainment"
        }
    ],
    "sg:phone":"+34 954 90 58 26",
    "sg:postcode":"41002",
    "sg:province":"Sevilla",
    "sg:tags":[
        "arte",
        "de",
        "galer\u00cdas"
    ],
    "wof:name":"Manuela Talaverano S.c",
    "wof:placetype":"venue"
},
  "geometry": {"coordinates":[-5.9956803322,37.3967247009],"type":"Point"}
}