{
  "type": "Feature",
  "properties": {
    "iso:country":"ES",
    "sg:address":"Calle de Via Carpetana, 342",
    "sg:city":"Madrid",
    "sg:orig_category":"Herboristas (al Por Menor)",
    "sg:phone":"+34 914 61 17 65",
    "sg:postcode":"28047",
    "sg:province":"Madrid",
    "wof:name":"Jimenez Andrino Teresa",
    "wof:placetype":"venue"
},
  "geometry": {"coordinates":[-3.743473053,40.3907165527],"type":"Point"}
}