{
  "type": "Feature",
  "properties": {
    "addr:full":"Calle de Alfonso El Sabio, 12 Ponferrada Le\u00f3n 24400",
    "addr:housenumber":"12",
    "addr:postcode":"24400",
    "addr:street":"Calle De Alfonso El Sabio",
    "iso:country":"ES",
    "sg:address":"Calle de Alfonso El Sabio, 12",
    "sg:city":"Ponferrada",
    "sg:orig_category":"Bazares, Art\u00cdculos De Limpieza Y De Cocina (al Por Menor)",
    "sg:phone":"+34 987 41 37 48",
    "sg:postcode":"24400",
    "sg:province":"Le\u00f3n",
    "wof:name":"Luna Luna Gaspar",
    "wof:placetype":"venue"
},
  "geometry": {"coordinates":[-6.5960760117,42.5452575684],"type":"Point"}
}