{
  "type": "Feature",
  "properties": {
    "iso:country":"ES",
    "sg:address":"Calle de Cerro Minguete, 14",
    "sg:city":"Madrid",
    "sg:orig_category":"Abogados",
    "sg:phone":"+34 913 76 71 05",
    "sg:postcode":"28035",
    "sg:province":"Madrid",
    "wof:name":"Valcarcel Fincas",
    "wof:placetype":"venue"
},
  "geometry": {"coordinates":[-3.7181789875,40.4869346619],"type":"Point"}
}