{
  "type": "Feature",
  "properties": {
    "iso:country":"ES",
    "sg:address":"Calle de Hortensia, 26",
    "sg:city":"Melilla",
    "sg:orig_category":"Agentes, Concesionarios Y Sucursales De Veh\u00cdculos",
    "sg:phone":"+34 952 67 08 55",
    "sg:postcode":"52006",
    "sg:province":"Melilla",
    "wof:name":"Parres Kia S.l.",
    "wof:placetype":"venue"
},
  "geometry": {"coordinates":[-2.9415540695,35.2709503174],"type":"Point"}
}