{
  "type": "Feature",
  "properties": {
    "iso:country":"ES",
    "sg:address":"Av Pas D'arro, 29",
    "sg:city":"Vielha",
    "sg:orig_category":"Peluquer\u00cdas, Peluquer\u00cda Mixta",
    "sg:phone":"+34 973 64 14 15",
    "sg:postcode":"25530",
    "sg:province":"Lleida",
    "wof:name":"Valle Blazquez Nieves Del",
    "wof:placetype":"venue"
},
  "geometry": {"coordinates":[0.7975779772,42.7008934021],"type":"Point"}
}