{
  "type": "Feature",
  "properties": {
    "iso:country":"ES",
    "sg:address":"Ctra Valladolid, 8",
    "sg:city":"Avila",
    "sg:orig_category":"Empresas De Carpinter\u00cda De Madera",
    "sg:phone":"+34 920 25 69 97",
    "sg:postcode":"05004",
    "sg:province":"\u00c1vila",
    "wof:name":"Jose Tomas Rodriguez S.l.",
    "wof:placetype":"venue"
},
  "geometry": {"coordinates":[-4.6882801056,40.6693992615],"type":"Point"}
}