{
  "type": "Feature",
  "properties": {
    "iso:country":"ES",
    "sg:address":"Plaz Adolfo Mu\u00d1oz Alonso, 9",
    "sg:city":"Pe\u00f1afiel",
    "sg:orig_category":"Bisuter\u00cda, Joyer\u00cda, Relojer\u00cda (al Por Menor)",
    "sg:phone":"+34 983 88 09 09",
    "sg:postcode":"47300",
    "sg:province":"Valladolid",
    "wof:name":"Gonzalez Redondo Teofilo",
    "wof:placetype":"venue"
},
  "geometry": {"coordinates":[-4.1223688126,41.5960998535],"type":"Point"}
}