{
  "type": "Feature",
  "properties": {
    "addr:full":"La Toba, S/n La Toba Ja\u00e9n 23297",
    "addr:housenumber":"s / n",
    "addr:postcode":"23297",
    "addr:street":"La Toba Jae\u0301N",
    "iso:country":"ES",
    "sg:address":"La Toba, S/n",
    "sg:city":"La Toba",
    "sg:orig_category":"Centros De Educaci\u00d3n Especial",
    "sg:phone":"+34 953 43 37 36",
    "sg:postcode":"23297",
    "sg:province":"Ja\u00e9n",
    "wof:name":"Junta De Andalucia",
    "wof:placetype":"venue"
},
  "geometry": {"coordinates":[-2.5608189106,38.1824684143],"type":"Point"}
}