{
  "type": "Feature",
  "properties": {
    "iso:country":"ES",
    "sg:address":"Ptda Salinetas, S/n",
    "sg:city":"Petrer",
    "sg:orig_category":"Fabricaci\u00d3n De Sobres, Bolsas Y Fundas",
    "sg:phone":"+34 965 37 74 10",
    "sg:postcode":"03610",
    "sg:province":"Alicante",
    "wof:name":"Bolsos Vermont S.l.",
    "wof:placetype":"venue"
},
  "geometry": {"coordinates":[-0.7714939713,38.480255127],"type":"Point"}
}