{
  "type": "Feature",
  "properties": {
    "addr:full":"Trva Inchostia / Intxostia, 8 Alsasua Navarra 31800",
    "addr:housenumber":"8",
    "addr:postcode":"31800",
    "addr:street":"Trva Inchostia / Intxostia",
    "iso:country":"ES",
    "sg:address":"Trva Inchostia / Intxostia, 8",
    "sg:city":"Alsasua",
    "sg:orig_category":"Zapatos (al Por Menor)",
    "sg:phone":"+34 948 46 79 08",
    "sg:postcode":"31800",
    "sg:province":"Navarra",
    "wof:name":"Bengoechea Lecea Concepcion",
    "wof:placetype":"venue"
},
  "geometry": {"coordinates":[-2.1706728935,42.894317627],"type":"Point"}
}