{
  "type": "Feature",
  "properties": {
    "addr:full":"Pg Torras I Bages, 83 Barcelona Barcelona 08030",
    "addr:housenumber":"83",
    "addr:postcode":"08030",
    "addr:street":"Pg Torras I Bages",
    "iso:country":"ES",
    "sg:address":"Pg Torras I Bages, 83",
    "sg:city":"Barcelona",
    "sg:orig_category":"Farmacias",
    "sg:phone":"+34 933 45 06 34",
    "sg:postcode":"08030",
    "sg:province":"Barcelona",
    "wof:name":"Planas Pascual Josep Maria",
    "wof:placetype":"venue"
},
  "geometry": {"coordinates":[2.1908180714,41.4397125244],"type":"Point"}
}