{
  "type": "Feature",
  "properties": {
    "addr:full":"Ctra Sarriguren, Km. 0003,0 Burlada Navarra 31600",
    "addr:postcode":"31600",
    "addr:street":"Ctra Sarriguren Km. 0003,0",
    "iso:country":"ES",
    "sg:address":"Ctra Sarriguren, Km. 0003,0",
    "sg:city":"Burlada",
    "sg:orig_category":"Mec\u00c1nico Del Autom\u00d3vil",
    "sg:phone":"+34 948 15 34 37",
    "sg:postcode":"31600",
    "sg:province":"Navarra",
    "wof:name":"Automocion Mendillorri S.a.l.",
    "wof:placetype":"venue"
},
  "geometry": {"coordinates":[-1.6244446039,42.8143692017],"type":"Point"}
}