{
  "type": "Feature",
  "properties": {
    "iso:country":"ES",
    "sg:address":"Calle de Ni\u00d1o Jesus, 13",
    "sg:city":"Yecla",
    "sg:orig_category":"Muebles, Minoristas",
    "sg:phone":"+34 968 75 20 22",
    "sg:postcode":"30510",
    "sg:province":"Murcia",
    "wof:name":"Perez Martinez Ascensio",
    "wof:placetype":"venue"
},
  "geometry": {"coordinates":[-1.1169199944,38.6131057739],"type":"Point"}
}