{
  "type": "Feature",
  "properties": {
    "addr:full":"Avda Libertad (de La), 52 Alcazares Murcia 30710",
    "addr:housenumber":"52",
    "addr:postcode":"30710",
    "addr:street":"Avda Libertad De La",
    "iso:country":"ES",
    "sg:address":"Avda Libertad (de La), 52",
    "sg:city":"Alcazares",
    "sg:orig_category":"Bisuter\u00cda, Joyer\u00cda, Relojer\u00cda (al Por Menor)",
    "sg:phone":"+34 968 17 14 93",
    "sg:postcode":"30710",
    "sg:province":"Murcia",
    "wof:name":"Aurum Union Joyeros S.l.",
    "wof:placetype":"venue"
},
  "geometry": {"coordinates":[-0.8520230055,37.7393798828],"type":"Point"}
}