{
  "type": "Feature",
  "properties": {
    "addr:full":"Pg Anselm Clave, 8 Sentmenat Barcelona 08181",
    "addr:housenumber":"8",
    "addr:postcode":"08181",
    "addr:street":"Anselm Clave",
    "iso:country":"ES",
    "sg:address":"Pg Anselm Clave, 8",
    "sg:city":"Sentmenat",
    "sg:orig_category":"Fotocopias, Reprograf\u00cda",
    "sg:phone":"+34 937 15 45 33",
    "sg:postcode":"08181",
    "sg:province":"Barcelona",
    "sg:website":"www.copydentic.com",
    "wof:name":"Identic Copisteria Scp",
    "wof:placetype":"venue"
},
  "geometry": {"coordinates":[2.1347260475,41.6113433838],"type":"Point"}
}