{
  "type": "Feature",
  "properties": {
    "iso:country":"ES",
    "sg:address":"Calle de Mayor, 21",
    "sg:city":"Burgo Osma",
    "sg:orig_category":"Carnicer\u00cdas, Carnicer\u00cdas",
    "sg:phone":"+34 975 34 08 68",
    "sg:postcode":"42300",
    "sg:province":"Soria",
    "wof:name":"Carniceria Lidia C.b.",
    "wof:placetype":"venue"
},
  "geometry": {"coordinates":[-3.068406105,41.5867080688],"type":"Point"}
}