{
  "type": "Feature",
  "properties": {
    "iso:country":"ES",
    "sg:address":"Calle de Juan Ramon Jimenez, 47",
    "sg:city":"Valencia",
    "sg:orig_category":"Bancos",
    "sg:phone":"+34 963 73 07 76",
    "sg:postcode":"46026",
    "sg:province":"Valencia",
    "wof:name":"Banco Espa\u00f1ol De Credito S.a.",
    "wof:placetype":"venue"
},
  "geometry": {"coordinates":[-0.3743740022,39.4528884888],"type":"Point"}
}