{
  "type": "Feature",
  "properties": {
    "addr:full":"Calle de Porto Colon, 6 Alcorcon Madrid 28924",
    "addr:housenumber":"6",
    "addr:postcode":"28924",
    "addr:street":"Calle De Porto Colon",
    "iso:country":"ES",
    "sg:address":"Calle de Porto Colon, 6",
    "sg:city":"Alcorcon",
    "sg:orig_category":"Inform\u00c1tica: Soportes De Informaci\u00d3n, Suministros & Accesorios",
    "sg:phone":"+34 916 21 02 59",
    "sg:postcode":"28924",
    "sg:province":"Madrid",
    "sg:website":"www.lasermant.com",
    "wof:name":"Suministros Informaticos Laser-mant S.l.",
    "wof:placetype":"venue"
},
  "geometry": {"coordinates":[-3.8209218979,40.3522758484],"type":"Point"}
}