{
  "type": "Feature",
  "properties": {
    "iso:country":"ES",
    "sg:address":"Carrer de Comte De Sicart (del), 14",
    "sg:city":"Vila-seca",
    "sg:orig_category":"Fabricaci\u00d3n De Sobres, Bolsas Y Fundas",
    "sg:phone":"+34 977 39 11 24",
    "sg:postcode":"43480",
    "sg:province":"Tarragona",
    "wof:name":"Guinjoan Gasellas Maria",
    "wof:placetype":"venue"
},
  "geometry": {"coordinates":[1.1466920376,41.1119346619],"type":"Point"}
}