{
  "type": "Feature",
  "properties": {
    "iso:country":"ES",
    "sg:address":"Pase Jose Fernandez Vega, 26",
    "sg:city":"Brenes",
    "sg:orig_category":"Quincaller\u00cda (al Por Menor)",
    "sg:phone":"+34 955 65 32 04",
    "sg:postcode":"41310",
    "sg:province":"Sevilla",
    "wof:name":"Algaba Lopez Rosa",
    "wof:placetype":"venue"
},
  "geometry": {"coordinates":[-5.8709373474,37.5472831726],"type":"Point"}
}