{
  "type": "Feature",
  "properties": {
    "iso:country":"ES",
    "sg:address":"Carr Santiago Rusi\u00d1ol, 94",
    "sg:city":"Santa Coloma De Farners",
    "sg:orig_category":"Empresas De Carpinter\u00cda",
    "sg:phone":"+34 972 84 36 06",
    "sg:postcode":"17430",
    "sg:province":"Girona",
    "wof:name":"Aluminis En General I Sistemas Electrics S.l.l.",
    "wof:placetype":"venue"
},
  "geometry": {"coordinates":[2.6546506882,41.868309021],"type":"Point"}
}