{
  "type": "Feature",
  "properties": {
    "addr:full":"Av Girona, S/n Santa Perpetua De Mogoda Barcelona 08130",
    "addr:housenumber":"s / n",
    "addr:postcode":"08130",
    "addr:street":"Av Girona",
    "iso:country":"ES",
    "sg:address":"Av Girona, S/n",
    "sg:city":"Santa Perpetua De Mogoda",
    "sg:orig_category":"Venta, Instalaci\u00d3n De Calefacci\u00d3n",
    "sg:phone":"+34 935 44 60 16",
    "sg:postcode":"08130",
    "sg:province":"Barcelona",
    "wof:name":"Gaservei 2002 S.l.",
    "wof:placetype":"venue"
},
  "geometry": {"coordinates":[2.1815900803,41.5288352966],"type":"Point"}
}