{
  "type": "Feature",
  "properties": {
    "addr:full":"Carrer de Muntaner, 443 Barcelona Barcelona 08021",
    "addr:housenumber":"443",
    "addr:postcode":"08021",
    "addr:street":"Carrer De Muntaner",
    "iso:country":"ES",
    "sg:address":"Carrer de Muntaner, 443",
    "sg:city":"Barcelona",
    "sg:orig_category":"Asesor\u00cda Sobre Comunicaci\u00d3n De Empresas",
    "sg:phone":"+34 932 09 07 14",
    "sg:postcode":"08021",
    "sg:province":"Barcelona",
    "wof:name":"Forn Argimon Ramon",
    "wof:placetype":"venue"
},
  "geometry": {"coordinates":[2.139854908,41.401184082],"type":"Point"}
}