{
  "type": "Feature",
  "properties": {
    "addr:full":"Avda Riato (del), 37 Motilla Palancar Cuenca 16200",
    "addr:housenumber":"37",
    "addr:postcode":"16200",
    "addr:street":"Avda Riato Del",
    "iso:country":"ES",
    "sg:address":"Avda Riato (del), 37",
    "sg:city":"Motilla Palancar",
    "sg:orig_category":"Bancos",
    "sg:phone":"+34 969 33 12 13",
    "sg:postcode":"16200",
    "sg:province":"Cuenca",
    "sg:website":"www.bancopopular.es",
    "wof:name":"Banco Popular Espa\u00d1ol S.a.",
    "wof:placetype":"venue"
},
  "geometry": {"coordinates":[-1.9118709564,39.5613594055],"type":"Point"}
}