{
  "type": "Feature",
  "properties": {
    "iso:country":"ES",
    "sg:address":"Calle de Marques De La Valdavia (del), 99",
    "sg:city":"Alcobendas",
    "sg:orig_category":"Electricidad, Electr\u00d3nica: Suministros (al Por Menor)",
    "sg:phone":"+34 916 63 80 80",
    "sg:postcode":"28100",
    "sg:province":"Madrid",
    "sg:website":"www.merchan.es",
    "wof:name":"Electronica Merchan S.l.",
    "wof:placetype":"venue"
},
  "geometry": {"coordinates":[-3.6518781185,40.5463218689],"type":"Point"}
}