{
  "type": "Feature",
  "properties": {
    "addr:full":"Pg Verdaguer, 135 Igualada Barcelona 08700",
    "addr:housenumber":"135",
    "addr:postcode":"08700",
    "addr:street":"Pg Verdaguer",
    "iso:country":"ES",
    "sg:address":"Pg Verdaguer, 135",
    "sg:city":"Igualada",
    "sg:orig_category":"Electrodom\u00c9sticos (al Por Menor)",
    "sg:phone":"+34 938 03 31 91",
    "sg:postcode":"08700",
    "sg:province":"Barcelona",
    "wof:name":"Electrodomesticos Martinez S.a.",
    "wof:placetype":"venue"
},
  "geometry": {"coordinates":[1.6270660162,41.5792312622],"type":"Point"}
}