{
  "type": "Feature",
  "properties": {
    "addr:full":"Calle de Meseguer, S/n Alcazares Murcia 30710",
    "addr:housenumber":"s",
    "addr:postcode":"30710",
    "addr:street":"Calle De Meseguer;/ N",
    "iso:country":"ES",
    "sg:address":"Calle de Meseguer, S/n",
    "sg:city":"Alcazares",
    "sg:orig_category":"Supermercados Y Hipermercados",
    "sg:phone":"+34 968 58 24 37",
    "sg:postcode":"30710",
    "sg:province":"Murcia",
    "wof:name":"Gracia Sanchez Fulgencio",
    "wof:placetype":"venue"
},
  "geometry": {"coordinates":[-0.8508290052,37.7425117493],"type":"Point"}
}