{
  "type": "Feature",
  "properties": {
    "addr:full":"Cra Carretera De Martorell, Km. 0592,4 S. Andreu Barca Barcelona 08740",
    "addr:postcode":"08740",
    "addr:street":"Carretera De Martorell Km. 0592,4 S. Andreu;Barcelona",
    "iso:country":"ES",
    "sg:address":"Cra Carretera De Martorell, Km. 0592,4",
    "sg:city":"S. Andreu Barca",
    "sg:orig_category":"Materias Pl\u00c1sticas: Art\u00cdculos Para La Industria",
    "sg:phone":"+34 936 53 09 99",
    "sg:postcode":"08740",
    "sg:province":"Barcelona",
    "sg:website":"www.clariant.es",
    "wof:name":"Clariant Masterbatch Iberica S.a.",
    "wof:placetype":"venue"
},
  "geometry": {"coordinates":[1.973369956,41.4486236572],"type":"Point"}
}