{
  "type": "Feature",
  "properties": {
    "iso:country":"ES",
    "sg:address":"Calle de Conde De Altea, 41",
    "sg:city":"Altea",
    "sg:orig_category":"Promotores Constructores",
    "sg:phone":"+34 966 88 10 22",
    "sg:postcode":"03590",
    "sg:province":"Alicante",
    "sg:website":"www.urban_info.com",
    "wof:name":"Consorcio Altea S.l.",
    "wof:placetype":"venue"
},
  "geometry": {"coordinates":[-0.0459594987,38.6020851135],"type":"Point"}
}