{
  "type": "Feature",
  "properties": {
    "addr:full":"Calle de Cautivo, 7 Alcazar S. Juan Ciudad Real 13600",
    "addr:housenumber":"7",
    "addr:postcode":"13600",
    "addr:street":"Calle De Cautivo;Alcazar S. Juan Ciudad Real",
    "iso:country":"ES",
    "sg:address":"Calle de Cautivo, 7",
    "sg:city":"Alcazar S. Juan",
    "sg:orig_category":"Delegados, Agentes De Tr\u00c1nsito, Auxiliares De Transporte Internacional",
    "sg:phone":"+34 926 54 09 30",
    "sg:postcode":"13600",
    "sg:province":"Ciudad Real",
    "wof:name":"Alaminos Campos Coralio",
    "wof:placetype":"venue"
},
  "geometry": {"coordinates":[-3.2084667683,39.388885498],"type":"Point"}
}