{
  "type": "Feature",
  "properties": {
    "addr:full":"Calle de De Los Escayolistas, 2 Velilla S.antonio Madrid 28891",
    "addr:housenumber":"2",
    "addr:postcode":"28891",
    "addr:street":"Calle De De Los Escayolistas",
    "iso:country":"ES",
    "sg:address":"Calle de De Los Escayolistas, 2",
    "sg:city":"Velilla S.antonio",
    "sg:orig_category":"Metacrilato: Art\u00cdculos (fabricaci\u00d3n Y Al Por Mayor)",
    "sg:phone":"+34 916 55 31 13",
    "sg:postcode":"28891",
    "sg:province":"Madrid",
    "wof:name":"Polimetacrilato Dise\u00f1o Y Fabricacion S.l.",
    "wof:placetype":"venue"
},
  "geometry": {"coordinates":[-3.4774355888,40.357334137],"type":"Point"}
}