{
  "type": "Feature",
  "properties": {
    "iso:country":"ES",
    "sg:address":"Calle de Alcalde Blazquez, S/n",
    "sg:city":"Cadiz",
    "sg:orig_category":"Farmacias",
    "sg:phone":"+34 956 20 08 00",
    "sg:postcode":"11012",
    "sg:province":"C\u00e1diz",
    "wof:name":"Farmacia Alba Comunidad De Bienes",
    "wof:placetype":"venue"
},
  "geometry": {"coordinates":[-6.2734174728,36.5102348328],"type":"Point"}
}