{
  "type": "Feature",
  "properties": {
    "iso:country":"ES",
    "sg:address":"Rua Vilarrodis, S/n",
    "sg:city":"Vilarrodis",
    "sg:orig_category":"M\u00c1rmoles, Granitos Y Piedras Naturales",
    "sg:phone":"+34 981 60 10 02",
    "sg:postcode":"15141",
    "sg:province":"La Coru\u00f1a",
    "wof:name":"Lista Granit S.a.",
    "wof:placetype":"venue"
},
  "geometry": {"coordinates":[-8.4733343124,43.3170700073],"type":"Point"}
}