{
  "type": "Feature",
  "properties": {
    "addr:full":"Carr Ramon Franco, 32 Cala Ratjada Islas Baleares 07590",
    "addr:housenumber":"32",
    "addr:postcode":"07590",
    "addr:street":"Carr Ramon Franco",
    "iso:country":"ES",
    "sg:address":"Carr Ramon Franco, 32",
    "sg:city":"Cala Ratjada",
    "sg:orig_category":"Agencias Y Agentes Comerciales, Representantes",
    "sg:phone":"+34 971 56 53 83",
    "sg:postcode":"07590",
    "sg:province":"Islas Baleares",
    "wof:name":"Soler Torrens E Hijos S.l",
    "wof:placetype":"venue"
},
  "geometry": {"coordinates":[3.4606449604,39.7145996094],"type":"Point"}
}