{
  "type": "Feature",
  "properties": {
    "iso:country":"ES",
    "sg:address":"Calle de Alcolea, 1",
    "sg:city":"Constantina",
    "sg:orig_category":"Cerrajer\u00cda, Ferrallista",
    "sg:phone":"+34 955 88 01 51",
    "sg:postcode":"41450",
    "sg:province":"Sevilla",
    "wof:name":"Cercados La Barrera S.l.",
    "wof:placetype":"venue"
},
  "geometry": {"coordinates":[-5.6180715561,37.8669586182],"type":"Point"}
}