{
  "type": "Feature",
  "properties": {
    "addr:full":"C/ Balmes, 27 Ripollet Barcelona 08291",
    "addr:housenumber":"27",
    "addr:postcode":"08291",
    "addr:street":"C / Balmes",
    "iso:country":"ES",
    "sg:address":"C/ Balmes, 27",
    "sg:city":"Ripollet",
    "sg:orig_category":"Molduras, Junquillos, Listones Y Molduras Perforadas",
    "sg:phone":"+34 935 80 21 67",
    "sg:postcode":"08291",
    "sg:province":"Barcelona",
    "wof:name":"Pink Panther S.cv.",
    "wof:placetype":"venue"
},
  "geometry": {"coordinates":[2.1591210365,41.4945068359],"type":"Point"}
}