{
  "type": "Feature",
  "properties": {
    "iso:country":"ES",
    "sg:address":"Rua Galicia (de), 35",
    "sg:city":"Ponte Dena",
    "sg:orig_category":"Abogados",
    "sg:phone":"+34 986 74 32 62",
    "sg:postcode":"36967",
    "sg:province":"Pontevedra",
    "wof:name":"Salgueiro Castro Maria Dolores",
    "wof:placetype":"venue"
},
  "geometry": {"coordinates":[-8.8113946915,42.454082489],"type":"Point"}
}