{
  "type": "Feature",
  "properties": {
    "addr:full":"Calle de Baja Iglesia, 5 Berchules Granada 18451",
    "addr:housenumber":"5",
    "addr:postcode":"18451",
    "addr:street":"Calle De Baja Iglesia",
    "iso:country":"ES",
    "sg:address":"Calle de Baja Iglesia, 5",
    "sg:city":"Berchules",
    "sg:orig_category":"Granos Y Semillas (producci\u00d3n, Al Por Mayor)",
    "sg:phone":"+34 958 85 25 37",
    "sg:postcode":"18451",
    "sg:province":"Granada",
    "wof:name":"Semillar La Alpujarra S.l.",
    "wof:placetype":"venue"
},
  "geometry": {"coordinates":[-3.1901130676,36.975276947],"type":"Point"}
}