{
  "type": "Feature",
  "properties": {
    "iso:country":"ES",
    "sg:address":"Carrer de Major, 2",
    "sg:city":"Masroig",
    "sg:orig_category":"Ingeniero",
    "sg:phone":"+34 977 82 52 57",
    "sg:postcode":"43736",
    "sg:province":"Tarragona",
    "wof:name":"Guerola Vernet Jaume",
    "wof:placetype":"venue"
},
  "geometry": {"coordinates":[0.7316190004,41.1264457703],"type":"Point"}
}