{
  "type": "Feature",
  "properties": {
    "addr:full":"Avda Primo De Rivera, 11 Coru\u00d1a La Coru\u00f1a 15006",
    "addr:housenumber":"11",
    "addr:postcode":"15006",
    "addr:street":"Avda Primo De Rivera;La Corun\u0303A",
    "iso:country":"ES",
    "sg:address":"Avda Primo De Rivera, 11",
    "sg:city":"Coru\u00d1a",
    "sg:orig_category":"Sociedades, Compa\u00d1\u00cdas Aseguradoras",
    "sg:phone":"+34 981 24 19 22",
    "sg:postcode":"15006",
    "sg:province":"La Coru\u00f1a",
    "wof:name":"Meridiano S.a.",
    "wof:placetype":"venue"
},
  "geometry": {"coordinates":[-8.4030342102,43.359210968],"type":"Point"}
}