{
  "type": "Feature",
  "properties": {
    "addr:full":"Calle de Mendez Alvaro, S/n Madrid Madrid 28053",
    "addr:housenumber":"s / n",
    "addr:postcode":"28053",
    "addr:street":"Calle De Mendez Alvaro",
    "iso:country":"ES",
    "sg:address":"Calle de Mendez Alvaro, S/n",
    "sg:city":"Madrid",
    "sg:orig_category":"Autob\u00das (explotaci\u00d3n Y Servicios De)",
    "sg:phone":"+34 915 30 53 09",
    "sg:postcode":"28053",
    "sg:province":"Madrid",
    "sg:website":"www.continental-auto.es",
    "wof:name":"Continental Auto S.l.",
    "wof:placetype":"venue"
},
  "geometry": {"coordinates":[-3.6741681099,40.391330719],"type":"Point"}
}