{
  "type": "Feature",
  "properties": {
    "iso:country":"ES",
    "sg:address":"Calle de Padres Dominicos, 6",
    "sg:city":"Almagro",
    "sg:orig_category":"Distribuci\u00d3n De Petr\u00d3leo Y Derivados",
    "sg:phone":"+34 926 86 02 16",
    "sg:postcode":"13270",
    "sg:province":"Ciudad Real",
    "wof:name":"Aranda Sobrino Jose Maria",
    "wof:placetype":"venue"
},
  "geometry": {"coordinates":[-3.7067995071,38.8915328979],"type":"Point"}
}