{
  "type": "Feature",
  "properties": {
    "addr:full":"Rua San Marti\u00d1o, 14 Pobra Trives Ourense 32780",
    "addr:housenumber":"14",
    "addr:postcode":"32780",
    "addr:street":"Rua San Martin\u0303O",
    "iso:country":"ES",
    "sg:address":"Rua San Marti\u00d1o, 14",
    "sg:city":"Pobra Trives",
    "sg:orig_category":"Librer\u00cdas",
    "sg:phone":"+34 988 33 24 13",
    "sg:postcode":"32780",
    "sg:province":"Ourense",
    "wof:name":"Alvarez Gonzalez Luisa",
    "wof:placetype":"venue"
},
  "geometry": {"coordinates":[-7.2530627251,42.3386917114],"type":"Point"}
}