{
  "type": "Feature",
  "properties": {
    "iso:country":"ES",
    "sg:address":"Carr Nou D'octubre, 2",
    "sg:city":"Gandia",
    "sg:orig_category":"M\u00c9dicos: Estomatolog\u00cda",
    "sg:phone":"+34 962 86 51 57",
    "sg:postcode":"46700",
    "sg:province":"Valencia",
    "wof:name":"Nu\u00f1ez Marti Juan Manuel",
    "wof:placetype":"venue"
},
  "geometry": {"coordinates":[-0.1934490055,38.9626426697],"type":"Point"}
}