{
  "type": "Feature",
  "properties": {
    "addr:full":"Carr Joan Baget, 1 Lleida Lleida 25003",
    "addr:housenumber":"1",
    "addr:postcode":"25003",
    "addr:street":"Carr Joan Baget",
    "iso:country":"ES",
    "sg:address":"Carr Joan Baget, 1",
    "sg:city":"Lleida",
    "sg:classifiers":[
        {
            "category":"Autos & Motor Vehicles",
            "subcategory":"Automobile Sales",
            "type":"Retail Goods"
        }
    ],
    "sg:phone":"+34 973 26 81 88",
    "sg:postcode":"25003",
    "sg:province":"Lleida",
    "wof:name":"Gonzalez Oliver Pedro Angel",
    "wof:placetype":"venue"
},
  "geometry": {"coordinates":[0.6205329895,41.6159057617],"type":"Point"}
}