{
  "type": "Feature",
  "properties": {
    "addr:full":"Calle de Virgen De Los Milagros, 29 Puerto De Santa Maria C\u00e1diz 11500",
    "addr:housenumber":"29",
    "addr:postcode":"11500",
    "addr:street":"Calle De Virgen De Los Milagros;Ca\u0301Diz",
    "iso:country":"ES",
    "sg:address":"Calle de Virgen De Los Milagros, 29",
    "sg:city":"Puerto De Santa Maria",
    "sg:orig_category":"Sociedades, Compa\u00d1\u00cdas Aseguradoras",
    "sg:phone":"+34 956 54 31 92",
    "sg:postcode":"11500",
    "sg:province":"C\u00e1diz",
    "wof:name":"Meridiano S.a.",
    "wof:placetype":"venue"
},
  "geometry": {"coordinates":[-6.2248878479,36.5975189209],"type":"Point"}
}