{
  "type": "Feature",
  "properties": {
    "iso:country":"ES",
    "sg:address":"Pg Fabra I Puig, 352",
    "sg:city":"Barcelona",
    "sg:classifiers":[
        {
            "category":"Autos & Motor Vehicles",
            "subcategory":"Automobile Sales",
            "type":"Retail Goods"
        }
    ],
    "sg:phone":"+34 933 57 93 48",
    "sg:postcode":"08031",
    "sg:province":"Barcelona",
    "wof:name":"J. Mendi V. S.l.",
    "wof:placetype":"venue"
},
  "geometry": {"coordinates":[2.1663351059,41.4306297302],"type":"Point"}
}