{
  "type": "Feature",
  "properties": {
    "iso:country":"ES",
    "sg:address":"Calle de Camino Del Campillo, S/n",
    "sg:city":"Ciudad Real",
    "sg:orig_category":"M\u00c9dicos: Medicina General",
    "sg:phone":"+34 926 21 06 57",
    "sg:postcode":"13002",
    "sg:province":"Ciudad Real",
    "wof:name":"Huertas Serna Francisco Javier",
    "wof:placetype":"venue"
},
  "geometry": {"coordinates":[-3.936570406,38.9861717224],"type":"Point"}
}