{
  "type": "Feature",
  "properties": {
    "iso:country":"ES",
    "sg:address":"Calle de Pizarro, 20",
    "sg:city":"Aranda Duero",
    "sg:orig_category":"Fabricaci\u00d3n De Postres Y Desayunos Preparados",
    "sg:phone":"+34 947 50 57 58",
    "sg:postcode":"09400",
    "sg:province":"Burgos",
    "wof:name":"Panaderia Reposteria La Espiga S.l.",
    "wof:placetype":"venue"
},
  "geometry": {"coordinates":[-3.6785778999,41.6702728271],"type":"Point"}
}