{
  "type": "Feature",
  "properties": {
    "addr:full":"Calle de Milan, 12 Alcorcon Madrid 28925",
    "addr:housenumber":"12",
    "addr:postcode":"28925",
    "addr:street":"Calle De Milan",
    "iso:country":"ES",
    "sg:address":"Calle de Milan, 12",
    "sg:city":"Alcorcon",
    "sg:orig_category":"T\u00c9cnicos Veterinarios",
    "sg:phone":"+34 916 89 18 83",
    "sg:postcode":"28925",
    "sg:province":"Madrid",
    "wof:name":"Centro Veterinario Parque Oeste S.l.",
    "wof:placetype":"venue"
},
  "geometry": {"coordinates":[-3.8353390694,40.3956756592],"type":"Point"}
}