{
  "type": "Feature",
  "properties": {
    "iso:country":"ES",
    "sg:address":"Avda Doutor Fleming, 81",
    "sg:city":"Ferrol",
    "sg:orig_category":"Promotores Constructores",
    "sg:phone":"+34 981 35 40 68",
    "sg:postcode":"15401",
    "sg:province":"La Coru\u00f1a",
    "wof:name":"Columa",
    "wof:placetype":"venue"
},
  "geometry": {"coordinates":[-8.2385969162,43.4844093323],"type":"Point"}
}