{
  "type": "Feature",
  "properties": {
    "iso:country":"ES",
    "sg:address":"Calle de Juan Xxiii, 15",
    "sg:city":"Chantada",
    "sg:classifiers":[
        {
            "category":"Autos & Motor Vehicles",
            "subcategory":"Automobile Sales",
            "type":"Retail Goods"
        }
    ],
    "sg:phone":"+34 982 46 23 00",
    "sg:postcode":"27500",
    "sg:province":"Lugo",
    "wof:name":"Gonzalez Ledo Andres",
    "wof:placetype":"venue"
},
  "geometry": {"coordinates":[-8.5196342468,42.7190093994],"type":"Point"}
}