{
  "type": "Feature",
  "properties": {
    "iso:country":"ES",
    "sg:address":"Calle de Karl Marx, 6",
    "sg:city":"Astrabudua",
    "sg:orig_category":"Mercer\u00cda, Lencer\u00cda (al Por Menor)",
    "sg:phone":"+34 944 67 03 26",
    "sg:postcode":"48950",
    "sg:province":"Vizcaya",
    "wof:name":"Gonzalez Asorey Pilar",
    "wof:placetype":"venue"
},
  "geometry": {"coordinates":[-2.9845299721,43.3162841797],"type":"Point"}
}