{
  "type": "Feature",
  "properties": {
    "iso:country":"ES",
    "sg:address":"Calle de Pintor Jover, 17",
    "sg:city":"Valencia",
    "sg:orig_category":"Electricidad: Instaladores",
    "sg:phone":"+34 963 33 33 90",
    "sg:postcode":"46013",
    "sg:province":"Valencia",
    "wof:name":"Valencia A Domicilio Dos S.l.",
    "wof:placetype":"venue"
},
  "geometry": {"coordinates":[-0.366858989,39.4423522949],"type":"Point"}
}