{
  "type": "Feature",
  "properties": {
    "iso:country":"ES",
    "sg:address":"Calle de Buigas, 33",
    "sg:city":"Estepona",
    "sg:orig_category":"Fabricaci\u00d3n, Venta, Instalaci\u00d3n De R\u00d3tulos, De R\u00d3tulos Luminosos",
    "sg:phone":"+34 952 80 79 84",
    "sg:postcode":"29680",
    "sg:province":"M\u00e1laga",
    "wof:name":"Rotumania Costa S.l.",
    "wof:placetype":"venue"
},
  "geometry": {"coordinates":[-5.1689977646,36.4288787842],"type":"Point"}
}