{
  "type": "Feature",
  "properties": {
    "addr:full":"Plaz Corrillo, 17 Salamanca Salamanca 37002",
    "addr:housenumber":"17",
    "addr:postcode":"37002",
    "addr:street":"Plaz Corrillo",
    "iso:country":"ES",
    "sg:address":"Plaz Corrillo, 17",
    "sg:city":"Salamanca",
    "sg:orig_category":"Molduras, Junquillos, Listones Y Molduras Perforadas",
    "sg:phone":"+34 923 21 93 99",
    "sg:postcode":"37002",
    "sg:province":"Salamanca",
    "wof:name":"Afiaca S.c.l.",
    "wof:placetype":"venue"
},
  "geometry": {"coordinates":[-5.664809227,40.9641723633],"type":"Point"}
}