{
  "type": "Feature",
  "properties": {
    "addr:full":"Rua Conde Torrecedeira, 32 Vigo Pontevedra 36202",
    "addr:housenumber":"32",
    "addr:postcode":"36202",
    "addr:street":"Rua Conde Torrecedeira",
    "iso:country":"ES",
    "sg:address":"Rua Conde Torrecedeira, 32",
    "sg:city":"Vigo",
    "sg:classifiers":[
        {
            "category":"Personal",
            "subcategory":"Barber",
            "type":"Services"
        }
    ],
    "sg:phone":"+34 986 20 95 53",
    "sg:postcode":"36202",
    "sg:province":"Pontevedra",
    "sg:tags":[
        "caballeros",
        "de",
        "peluqueros"
    ],
    "wof:name":"Alvarez Fernandez Jose Abilio",
    "wof:placetype":"venue"
},
  "geometry": {"coordinates":[-8.7331075668,42.2291297913],"type":"Point"}
}