{
  "type": "Feature",
  "properties": {
    "addr:full":"Carrer de Mossen Blancafort, S/n Nucli Urba Barcelona 08186",
    "addr:housenumber":"s / n",
    "addr:postcode":"08186",
    "addr:street":"Carrer De Mossen Blancafort",
    "iso:country":"ES",
    "sg:address":"Carrer de Mossen Blancafort, S/n",
    "sg:city":"Nucli Urba",
    "sg:orig_category":"Iglesia Cat\u00d3lica",
    "sg:phone":"+34 938 41 50 54",
    "sg:postcode":"08186",
    "sg:province":"Barcelona",
    "wof:name":"Parroquia De San Julian",
    "wof:placetype":"venue"
},
  "geometry": {"coordinates":[2.2382690907,41.612449646],"type":"Point"}
}