{
  "type": "Feature",
  "properties": {
    "iso:country":"ES",
    "sg:address":"Plaz Marques De Estella, 1",
    "sg:city":"Fuentes Nava",
    "sg:orig_category":"Bancos",
    "sg:phone":"+34 979 84 20 38",
    "sg:postcode":"34337",
    "sg:province":"Palencia",
    "wof:name":"Merino Lobato Juan Carlos",
    "wof:placetype":"venue"
},
  "geometry": {"coordinates":[-4.7798190117,42.081413269],"type":"Point"}
}