{
  "type": "Feature",
  "properties": {
    "addr:full":"Calle de Pedro Laborde, 56 Madrid Madrid 28018",
    "addr:housenumber":"56",
    "addr:postcode":"madrid;28018",
    "addr:street":"Calle De Pedro Laborde",
    "iso:country":"ES",
    "sg:address":"Calle de Pedro Laborde, 56",
    "sg:city":"Madrid",
    "sg:orig_category":"Estancos",
    "sg:phone":"+34 913 03 24 96",
    "sg:postcode":"28018",
    "sg:province":"Madrid",
    "wof:name":"Molina Gete Luis",
    "wof:placetype":"venue"
},
  "geometry": {"coordinates":[-3.6493549347,40.3871994019],"type":"Point"}
}