{
  "type": "Feature",
  "properties": {
    "addr:full":"Calle de Espinosa, 3 Alcala Real Ja\u00e9n 23680",
    "addr:housenumber":"3",
    "addr:postcode":"23680",
    "addr:street":"Calle De Espinosa;Jae\u0301N",
    "iso:country":"ES",
    "sg:address":"Calle de Espinosa, 3",
    "sg:city":"Alcala Real",
    "sg:orig_category":"Ebanister\u00cda",
    "sg:phone":"+34 953 58 11 22",
    "sg:postcode":"23680",
    "sg:province":"Ja\u00e9n",
    "wof:name":"Ebanisteria Hidalgo Rueda S.l.",
    "wof:placetype":"venue"
},
  "geometry": {"coordinates":[-3.923707962,37.4649047852],"type":"Point"}
}