{
  "type": "Feature",
  "properties": {
    "addr:full":"Calle de Arenal, 58 Chinchilla Monte-aragon Albacete 02520",
    "addr:housenumber":"58",
    "addr:postcode":"02520",
    "addr:street":"Calle De Arenal;Monte-Aragon",
    "iso:country":"ES",
    "sg:address":"Calle de Arenal, 58",
    "sg:city":"Chinchilla Monte-aragon",
    "sg:orig_category":"Plomeros",
    "sg:phone":"+34 967 26 05 75",
    "sg:postcode":"02520",
    "sg:province":"Albacete",
    "wof:name":"Martinez Royo Francisco",
    "wof:placetype":"venue"
},
  "geometry": {"coordinates":[-1.7220554352,38.9161567688],"type":"Point"}
}