{
  "type": "Feature",
  "properties": {
    "addr:full":"Calle de Alcala, 205 Madrid Madrid 28028",
    "addr:housenumber":"205",
    "addr:postcode":"28028",
    "addr:street":"Calle De Alcala",
    "iso:country":"ES",
    "sg:address":"Calle de Alcala, 205",
    "sg:city":"Madrid",
    "sg:orig_category":"Asesor\u00cda De Formaci\u00d3n Y Gesti\u00d3n De Personal",
    "sg:phone":"+34 913 61 09 63",
    "sg:postcode":"28028",
    "sg:province":"Madrid",
    "wof:name":"Ca\u00f1eque Lopez Maria Teresa",
    "wof:placetype":"venue"
},
  "geometry": {"coordinates":[-3.6670131683,40.428981781],"type":"Point"}
}