{
  "type": "Feature",
  "properties": {
    "iso:country":"ES",
    "sg:address":"Plaza De Ayuntamiento, S/n",
    "sg:city":"Pereiro De Aguiar",
    "sg:orig_category":"Ense\u00d1anza, Formaci\u00d3n Profesional: Aprendizaje",
    "sg:phone":"+34 988 25 93 85",
    "sg:postcode":"32710",
    "sg:province":"Ourense",
    "wof:name":"Concello Do Pereiro De Aguiar",
    "wof:placetype":"venue"
},
  "geometry": {"coordinates":[-7.8072919846,42.3483390808],"type":"Point"}
}