{
  "type": "Feature",
  "properties": {
    "iso:country":"ES",
    "sg:address":"Carr Sant Pere Martir, 26",
    "sg:city":"Blanes",
    "sg:orig_category":"Arquitectos",
    "sg:phone":"+34 972 35 74 06",
    "sg:postcode":"17300",
    "sg:province":"Girona",
    "wof:name":"Arq-tec Suris Associats S.l.",
    "wof:placetype":"venue"
},
  "geometry": {"coordinates":[2.7873382568,41.6737632751],"type":"Point"}
}