{
  "type": "Feature",
  "properties": {
    "iso:country":"ES",
    "sg:address":"Calle de Benito Guinea, 2",
    "sg:city":"Vitoria-gasteiz",
    "sg:orig_category":"Librer\u00cdas",
    "sg:phone":"+34 945 25 75 14",
    "sg:postcode":"01003",
    "sg:province":"\u00c1lava",
    "wof:name":"Izargi, Sl",
    "wof:placetype":"venue"
},
  "geometry": {"coordinates":[-2.6637938023,42.8463439941],"type":"Point"}
}