{
  "type": "Feature",
  "properties": {
    "iso:country":"ES",
    "sg:address":"Calle de Santo Tomas De Villanueva, 21",
    "sg:city":"Granada",
    "sg:orig_category":"Quiropr\u00c1cticos",
    "sg:phone":"+34 958 20 16 85",
    "sg:postcode":"18004",
    "sg:province":"Granada",
    "wof:name":"Valette  Bruno",
    "wof:placetype":"venue"
},
  "geometry": {"coordinates":[-3.616271019,37.1806030273],"type":"Point"}
}