{
  "type": "Feature",
  "properties": {
    "addr:full":"Calle de Alfonso X El Sabio, 3 Parla Madrid 28980",
    "addr:housenumber":"3",
    "addr:postcode":"28980",
    "addr:street":"Calle De Alfonso X El Sabio",
    "iso:country":"ES",
    "sg:address":"Calle de Alfonso X El Sabio, 3",
    "sg:city":"Parla",
    "sg:orig_category":"Bazares, Art\u00cdculos De Limpieza Y De Cocina (al Por Menor)",
    "sg:phone":"+34 916 99 87 69",
    "sg:postcode":"28980",
    "sg:province":"Madrid",
    "wof:name":"Bazar Amistad S.l.",
    "wof:placetype":"venue"
},
  "geometry": {"coordinates":[-3.7694284916,40.2360305786],"type":"Point"}
}