{
  "type": "Feature",
  "properties": {
    "addr:full":"Barr San Antonio, S/n Mosqueruela Teruel 44410",
    "addr:housenumber":"s / n",
    "addr:postcode":"44410",
    "addr:street":"Antonio",
    "iso:country":"ES",
    "sg:address":"Barr San Antonio, S/n",
    "sg:city":"Mosqueruela",
    "sg:orig_category":"Reposter\u00cdas",
    "sg:phone":"+34 978 80 51 59",
    "sg:postcode":"44410",
    "sg:province":"Teruel",
    "wof:name":"Horno Pilar Y Teresa S.l.",
    "wof:placetype":"venue"
},
  "geometry": {"coordinates":[-0.4460110068,40.3599777222],"type":"Point"}
}