{
  "type": "Feature",
  "properties": {
    "iso:country":"ES",
    "sg:address":"Avda Reyes Catolicos, 16",
    "sg:city":"Burgos",
    "sg:orig_category":"Doctores En Medicina",
    "sg:phone":"+34 947 23 03 31",
    "sg:postcode":"09005",
    "sg:province":"Burgos",
    "wof:name":"Herrero Roa Jose",
    "wof:placetype":"venue"
},
  "geometry": {"coordinates":[-3.6949019432,42.3458061218],"type":"Point"}
}