{
  "type": "Feature",
  "properties": {
    "addr:full":"Calle de Bilbao, 16 Leganes Madrid 28914",
    "addr:housenumber":"16",
    "addr:postcode":"28914",
    "addr:street":"Calle De Bilbao",
    "iso:country":"ES",
    "sg:address":"Calle de Bilbao, 16",
    "sg:city":"Leganes",
    "sg:orig_category":"Cerrajer\u00cda, Ferrallista",
    "sg:phone":"+34 916 94 15 88",
    "sg:postcode":"28914",
    "sg:province":"Madrid",
    "wof:name":"Cerrajeria Perluvan",
    "wof:placetype":"venue"
},
  "geometry": {"coordinates":[-3.7549123764,40.3213577271],"type":"Point"}
}