{
  "type": "Feature",
  "properties": {
    "addr:full":"Avda Reina Mercedes, 23 Sevilla Sevilla 41012",
    "addr:housenumber":"23",
    "addr:postcode":"41012",
    "addr:street":"Avda Reina Mercedes",
    "iso:country":"ES",
    "sg:address":"Avda Reina Mercedes, 23",
    "sg:city":"Sevilla",
    "sg:orig_category":"Agencias Y Agentes Comerciales, Representantes",
    "sg:phone":"+34 954 62 93 01",
    "sg:postcode":"41012",
    "sg:province":"Sevilla",
    "wof:name":"Areta Marigo Esteban",
    "wof:placetype":"venue"
},
  "geometry": {"coordinates":[-5.9862866402,37.360370636],"type":"Point"}
}