{
  "type": "Feature",
  "properties": {
    "iso:country":"ES",
    "sg:address":"Calle de Forja, 14",
    "sg:city":"Malaga",
    "sg:orig_category":"Transportes Por V\u00cdas Navegables",
    "sg:phone":"+34 952 43 24 19",
    "sg:postcode":"29190",
    "sg:province":"M\u00e1laga",
    "wof:name":"Estevanez Jimenez Francisco",
    "wof:placetype":"venue"
},
  "geometry": {"coordinates":[-4.4796190262,36.7349090576],"type":"Point"}
}