{
  "type": "Feature",
  "properties": {
    "iso:country":"ES",
    "sg:address":"Calle de Arzobispo Loaces, 29",
    "sg:city":"Alacant",
    "sg:orig_category":"Asesor\u00cdas Y Estudios Financieros",
    "sg:phone":"+34 965 12 02 20",
    "sg:postcode":"03003",
    "sg:province":"Alicante",
    "wof:name":"Asidif S.l.",
    "wof:placetype":"venue"
},
  "geometry": {"coordinates":[-0.4913707078,38.3397026062],"type":"Point"}
}