{
  "type": "Feature",
  "properties": {
    "addr:full":"Ctra Madrid (de), Km. 0037,8 Colmenar Viejo Madrid 28770",
    "addr:postcode":"28770",
    "addr:street":"Ctra Madrid De Km. 0037,8",
    "iso:country":"ES",
    "sg:address":"Ctra Madrid (de), Km. 0037,8",
    "sg:city":"Colmenar Viejo",
    "sg:orig_category":"Empresas De Impermeabilizaci\u00d3n",
    "sg:phone":"+34 918 44 11 12",
    "sg:postcode":"28770",
    "sg:province":"Madrid",
    "wof:name":"Uretain Spa S.l.",
    "wof:placetype":"venue"
},
  "geometry": {"coordinates":[-3.7699229717,40.6656646729],"type":"Point"}
}