{
  "type": "Feature",
  "properties": {
    "addr:full":"Calle de Madre Celeste, 3 Madrid Madrid 28044",
    "addr:housenumber":"3",
    "addr:postcode":"28044",
    "addr:street":"Calle De Madre Celeste",
    "iso:country":"ES",
    "sg:address":"Calle de Madre Celeste, 3",
    "sg:city":"Madrid",
    "sg:orig_category":"Plomeros",
    "sg:phone":"+34 915 08 51 58",
    "sg:postcode":"28044",
    "sg:province":"Madrid",
    "wof:name":"Escribano Jare\u00f1o Reyes",
    "wof:placetype":"venue"
},
  "geometry": {"coordinates":[-3.755286932,40.372756958],"type":"Point"}
}