{
  "type": "Feature",
  "properties": {
    "iso:country":"ES",
    "sg:address":"Calle de Benifairo, 5",
    "sg:city":"Valencia",
    "sg:orig_category":"Empresas De Vigilancia, Guardia Y Protecci\u00d3n",
    "sg:phone":"+34 963 55 01 21",
    "sg:postcode":"46015",
    "sg:province":"Valencia",
    "wof:name":"Protelcom Seguridad S.l.",
    "wof:placetype":"venue"
},
  "geometry": {"coordinates":[-0.4000056088,39.4884300232],"type":"Point"}
}