{
  "type": "Feature",
  "properties": {
    "addr:full":"Calle de Leon Y Castillo, 359 Palmas De Gran Canaria Las Palmas 35006",
    "addr:housenumber":"359",
    "addr:postcode":"35006",
    "addr:street":"Calle De Leon Y Castillo",
    "iso:country":"ES",
    "sg:address":"Calle de Leon Y Castillo, 359",
    "sg:city":"Palmas De Gran Canaria",
    "sg:orig_category":"Ense\u00d1anza Variada",
    "sg:phone":"+34 928 24 27 98",
    "sg:postcode":"35006",
    "sg:province":"Las Palmas",
    "wof:name":"Suarez Hernandez Agustin",
    "wof:placetype":"venue"
},
  "geometry": {"coordinates":[-15.4299974442,28.1326065063],"type":"Point"}
}