{
  "type": "Feature",
  "properties": {
    "addr:full":"Carrer de Foners, 36 Palma Islas Baleares 07006",
    "addr:housenumber":"36",
    "addr:postcode":"07006",
    "addr:street":"Carrer De Foners",
    "iso:country":"ES",
    "sg:address":"Carrer de Foners, 36",
    "sg:city":"Palma",
    "sg:orig_category":"Pescader\u00cdas (al Por Menor)",
    "sg:phone":"+34 971 46 80 17",
    "sg:postcode":"07006",
    "sg:province":"Islas Baleares",
    "wof:name":"Pescados Bauza Gimenez S.a.",
    "wof:placetype":"venue"
},
  "geometry": {"coordinates":[2.6611380577,39.5689163208],"type":"Point"}
}