{
  "type": "Feature",
  "properties": {
    "iso:country":"ES",
    "sg:address":"Calle de Plateria, 14",
    "sg:city":"San Bartolome",
    "sg:orig_category":"Notarios",
    "sg:phone":"+34 968 21 76 29",
    "sg:postcode":"30004",
    "sg:province":"Murcia",
    "wof:name":"Prieto Garcia Jose",
    "wof:placetype":"venue"
},
  "geometry": {"coordinates":[-1.1314200163,37.9855232239],"type":"Point"}
}