{
  "type": "Feature",
  "properties": {
    "iso:country":"ES",
    "sg:address":"Pla\u00c7 Gra, 11",
    "sg:city":"Figueres",
    "sg:orig_category":"Reposter\u00cdas",
    "sg:phone":"+34 972 50 58 13",
    "sg:postcode":"17600",
    "sg:province":"Girona",
    "wof:name":"Industries Costa Miquel S.l.",
    "wof:placetype":"venue"
},
  "geometry": {"coordinates":[2.9625587463,42.2720336914],"type":"Point"}
}