{
  "type": "Feature",
  "properties": {
    "iso:country":"ES",
    "sg:address":"Avda Juan Sebastian Elcano, 49",
    "sg:city":"Badajoz",
    "sg:orig_category":"Herboristas (al Por Menor)",
    "sg:phone":"+34 924 25 05 46",
    "sg:postcode":"06003",
    "sg:province":"Badajoz",
    "wof:name":"Gamero Sevillano Antonio",
    "wof:placetype":"venue"
},
  "geometry": {"coordinates":[-6.9658989906,38.8710517883],"type":"Point"}
}