{
  "type": "Feature",
  "properties": {
    "iso:country":"ES",
    "sg:address":"Calle de Tenesoya, 90",
    "sg:city":"Monta\u00e7eta Del Calero",
    "sg:orig_category":"Promotores Constructores",
    "sg:phone":"+34 928 68 52 60",
    "sg:postcode":"35200",
    "sg:province":"Las Palmas",
    "wof:name":"Prococal Canarias S.l.u.",
    "wof:placetype":"venue"
},
  "geometry": {"coordinates":[-15.4144220352,28.0029888153],"type":"Point"}
}