{
  "type": "Feature",
  "properties": {
    "addr:full":"Carrer de Sant Pere, 6 Manresa Barcelona 08241",
    "addr:housenumber":"6",
    "addr:postcode":"08241",
    "addr:street":"Carrer De Sant Pere",
    "iso:country":"ES",
    "sg:address":"Carrer de Sant Pere, 6",
    "sg:city":"Manresa",
    "sg:orig_category":"Ropa Para Se\u00d1oras (al Por Menor)",
    "sg:phone":"+34 938 72 07 61",
    "sg:postcode":"08241",
    "sg:province":"Barcelona",
    "wof:name":"Zanichelli Soler Luis",
    "wof:placetype":"venue"
},
  "geometry": {"coordinates":[1.825832963,41.7234039307],"type":"Point"}
}