{
  "type": "Feature",
  "properties": {
    "iso:country":"ES",
    "sg:address":"Calle de Nuncio (del), 12",
    "sg:city":"Alcorcon",
    "sg:orig_category":"Electrodom\u00c9sticos (al Por Menor)",
    "sg:phone":"+34 916 43 49 05",
    "sg:postcode":"28921",
    "sg:province":"Madrid",
    "wof:name":"Tv Casado S.l.",
    "wof:placetype":"venue"
},
  "geometry": {"coordinates":[-3.8292219639,40.3471908569],"type":"Point"}
}