{
  "type": "Feature",
  "properties": {
    "iso:country":"ES",
    "sg:address":"Psaj Gitanillas De Las, S/n",
    "sg:city":"Torremolinos",
    "sg:orig_category":"Carnicer\u00cdas, Carnicer\u00cdas",
    "sg:phone":"+34 952 38 15 15",
    "sg:postcode":"29620",
    "sg:province":"M\u00e1laga",
    "wof:name":"Moreno Merida Juan Antonio",
    "wof:placetype":"venue"
},
  "geometry": {"coordinates":[-4.4979090691,36.6246833801],"type":"Point"}
}