{
  "type": "Feature",
  "properties": {
    "addr:full":"Calle de Alamillos, 1 Valladolid Valladolid 47005",
    "addr:housenumber":"1",
    "addr:postcode":"47005",
    "addr:street":"Calle De Alamillos",
    "iso:country":"ES",
    "sg:address":"Calle de Alamillos, 1",
    "sg:city":"Valladolid",
    "sg:orig_category":"Peluquer\u00cdas, Peluquer\u00cda Mixta",
    "sg:phone":"+34 983 20 75 72",
    "sg:postcode":"47005",
    "sg:province":"Valladolid",
    "wof:name":"Comunidad De Bienes Carrasco Y Roman",
    "wof:placetype":"venue"
},
  "geometry": {"coordinates":[-4.7157454491,41.6539039612],"type":"Point"}
}