{
  "type": "Feature",
  "properties": {
    "addr:full":"Calle de Navas De Tolosa, 10 Castejon Navarra 31590",
    "addr:housenumber":"10",
    "addr:postcode":"31590",
    "addr:street":"Calle De Navas De Tolosa",
    "iso:country":"ES",
    "sg:address":"Calle de Navas De Tolosa, 10",
    "sg:city":"Castejon",
    "sg:orig_category":"Electrodom\u00c9sticos (fabricaci\u00d3n, Al Por Mayor)",
    "sg:phone":"+34 948 77 06 35",
    "sg:postcode":"31590",
    "sg:province":"Navarra",
    "wof:name":"Gonzalez Aragon Trinidad",
    "wof:placetype":"venue"
},
  "geometry": {"coordinates":[-1.6905599833,42.1707496643],"type":"Point"}
}