{
  "type": "Feature",
  "properties": {
    "iso:country":"ES",
    "sg:address":"Calle de San Millan, 11",
    "sg:city":"Malaga",
    "sg:orig_category":"Fabricaci\u00d3n, Importaci\u00d3n De Material Y Sistemas De Telecomunicaciones",
    "sg:phone":"+34 952 26 54 08",
    "sg:postcode":"29013",
    "sg:province":"M\u00e1laga",
    "wof:name":"Europhone 2000 S.a.",
    "wof:placetype":"venue"
},
  "geometry": {"coordinates":[-4.420293808,36.7278823853],"type":"Point"}
}