{
  "type": "Feature",
  "properties": {
    "iso:country":"ES",
    "sg:address":"Avda Portugal, 50",
    "sg:city":"Talavera Reina",
    "sg:orig_category":"Agentes, Concesionarios Y Sucursales De Veh\u00cdculos",
    "sg:phone":"+34 925 80 40 58",
    "sg:postcode":"45600",
    "sg:province":"Toledo",
    "wof:name":"Repuestos Lisboa S.l.",
    "wof:placetype":"venue"
},
  "geometry": {"coordinates":[-4.8471679688,39.9580383301],"type":"Point"}
}