{
  "type": "Feature",
  "properties": {
    "addr:full":"Carr Juneda, 34 Lleida Lleida 25001",
    "addr:housenumber":"34",
    "addr:postcode":"25001",
    "addr:street":"Carr Juneda",
    "iso:country":"ES",
    "sg:address":"Carr Juneda, 34",
    "sg:city":"Lleida",
    "sg:orig_category":"Art\u00cdculos De Limpieza Y De Cocina (fabricaci\u00d3n, Al Por Mayor)",
    "sg:phone":"+34 973 20 20 13",
    "sg:postcode":"25001",
    "sg:province":"Lleida",
    "wof:name":"Solans Roy Jose Maria",
    "wof:placetype":"venue"
},
  "geometry": {"coordinates":[0.6468390226,41.6037406921],"type":"Point"}
}