{
  "type": "Feature",
  "properties": {
    "addr:full":"Calle de Caceres, 48 Madrid Madrid 28045",
    "addr:housenumber":"48",
    "addr:postcode":"madrid;28045",
    "addr:street":"Calle De Caceres",
    "iso:country":"ES",
    "sg:address":"Calle de Caceres, 48",
    "sg:city":"Madrid",
    "sg:orig_category":"Sociedades, Compa\u00d1\u00cdas Aseguradoras",
    "sg:phone":"+34 914 73 02 43",
    "sg:postcode":"28045",
    "sg:province":"Madrid",
    "wof:name":"Alfaval S.l.",
    "wof:placetype":"venue"
},
  "geometry": {"coordinates":[-3.699701786,40.3989486694],"type":"Point"}
}