{
  "type": "Feature",
  "properties": {
    "iso:country":"ES",
    "sg:address":"Calle de Campoamor, 1",
    "sg:city":"Castellon",
    "sg:orig_category":"Ropa Para Se\u00d1oras (al Por Menor)",
    "sg:phone":"+34 964 22 27 93",
    "sg:postcode":"12001",
    "sg:province":"Castell\u00f3n",
    "wof:name":"El Postiguet 2007 C.b.",
    "wof:placetype":"venue"
},
  "geometry": {"coordinates":[-0.0360050015,39.984249115],"type":"Point"}
}