{
  "type": "Feature",
  "properties": {
    "addr:full":"Carrer de Piquer, 24 Barcelona Barcelona 08004",
    "addr:housenumber":"24",
    "addr:postcode":"08004",
    "addr:street":"Carrer De Piquer",
    "iso:country":"ES",
    "sg:address":"Carrer de Piquer, 24",
    "sg:city":"Barcelona",
    "sg:orig_category":"Supermercados Y Hipermercados",
    "sg:phone":"+34 934 41 55 42",
    "sg:postcode":"08004",
    "sg:province":"Barcelona",
    "wof:name":"Bharat Doaba S.l.",
    "wof:placetype":"venue"
},
  "geometry": {"coordinates":[2.1703128815,41.373046875],"type":"Point"}
}