{
  "type": "Feature",
  "properties": {
    "addr:full":"Carrer de Vergos, 12 Barcelona Barcelona 08017",
    "addr:housenumber":"12",
    "addr:postcode":"08017",
    "addr:street":"Carrer De Vergos",
    "iso:country":"ES",
    "sg:address":"Carrer de Vergos, 12",
    "sg:city":"Barcelona",
    "sg:orig_category":"Alimentaci\u00d3n General (al Por Menor)",
    "sg:phone":"+34 934 17 58 25",
    "sg:postcode":"08017",
    "sg:province":"Barcelona",
    "wof:name":"Zaera Nuez Clara",
    "wof:placetype":"venue"
},
  "geometry": {"coordinates":[2.1306881905,41.3994522095],"type":"Point"}
}