{
  "type": "Feature",
  "properties": {
    "addr:full":"Plaz Coimbra, 16 Madrid Madrid 28025",
    "addr:housenumber":"16",
    "addr:postcode":"madrid;28025",
    "addr:street":"Coimbra",
    "iso:country":"ES",
    "sg:address":"Plaz Coimbra, 16",
    "sg:city":"Madrid",
    "sg:orig_category":"Cobro De Pr\u00c9stamos",
    "sg:phone":"+34 915 60 72 60",
    "sg:postcode":"28025",
    "sg:province":"Madrid",
    "wof:name":"Hermanos Alonso Garran S.l.",
    "wof:placetype":"venue"
},
  "geometry": {"coordinates":[-3.7235450745,40.3834152222],"type":"Point"}
}