{
  "type": "Feature",
  "properties": {
    "addr:full":"Muronovo-s. Xian Lai\u00f1o, S/n Muronovo La Coru\u00f1a 15981",
    "addr:postcode":"15981",
    "addr:street":"Lain\u0303O S / N Muronovo La Corun\u0303A",
    "iso:country":"ES",
    "sg:address":"Muronovo-s. Xian Lai\u00f1o, S/n",
    "sg:city":"Muronovo",
    "sg:orig_category":"Materias Pl\u00c1sticas: Productos De Consumo Masivo (fabricaci\u00d3n, Al Por Mayor)",
    "sg:phone":"+34 981 80 25 23",
    "sg:postcode":"15981",
    "sg:province":"La Coru\u00f1a",
    "wof:name":"Induro S.l.",
    "wof:placetype":"venue"
},
  "geometry": {"coordinates":[-8.7148532867,42.7164039612],"type":"Point"}
}