{
  "type": "Feature",
  "properties": {
    "addr:full":"Avda Washington, 53 Malaga M\u00e1laga 29006",
    "addr:housenumber":"53",
    "addr:postcode":"29006",
    "addr:street":"Avda Washington;Ma\u0301Laga",
    "iso:country":"ES",
    "sg:address":"Avda Washington, 53",
    "sg:city":"Malaga",
    "sg:orig_category":"Torrefactado De Caf\u00c9",
    "sg:phone":"+34 952 34 08 58",
    "sg:postcode":"29006",
    "sg:province":"M\u00e1laga",
    "sg:website":"www.cafescastel.com",
    "wof:name":"Cafes Castel S. A.",
    "wof:placetype":"venue"
},
  "geometry": {"coordinates":[-4.4831271172,36.7125205994],"type":"Point"}
}