{
  "type": "Feature",
  "properties": {
    "iso:country":"ES",
    "sg:address":"C\u00aa Arguis, S/n",
    "sg:city":"Arascues",
    "sg:classifiers":[
        {
            "category":"Sports & Exercise",
            "subcategory":"Golf",
            "type":"Entertainment"
        }
    ],
    "sg:phone":"+34 974 34 01 65",
    "sg:postcode":"22193",
    "sg:province":"Huesca",
    "sg:tags":[
        "y",
        "de",
        "campos",
        "clases"
    ],
    "wof:name":"Golf De Guara S.a.",
    "wof:placetype":"venue"
},
  "geometry": {"coordinates":[-0.4381479919,42.2663497925],"type":"Point"}
}