{
  "type": "Feature",
  "properties": {
    "addr:full":"Carr Major, 30 Palamos Girona 17230",
    "addr:housenumber":"30",
    "addr:postcode":"17230",
    "addr:street":"Carr Major",
    "iso:country":"ES",
    "sg:address":"Carr Major, 30",
    "sg:city":"Palamos",
    "sg:orig_category":"Tintes (fabricaci\u00d3n, Al Por Mayor)",
    "sg:phone":"+34 972 31 43 82",
    "sg:postcode":"17230",
    "sg:province":"Girona",
    "wof:name":"Huestal S.l.",
    "wof:placetype":"venue"
},
  "geometry": {"coordinates":[3.1294770241,41.8474655151],"type":"Point"}
}