{
  "type": "Feature",
  "properties": {
    "iso:country":"ES",
    "sg:address":"Ctra. Soria-plasencia, Km. 0144,5",
    "sg:city":"Pradena",
    "sg:orig_category":"Distribuci\u00d3n De Petr\u00d3leo Y Derivados",
    "sg:phone":"+34 921 50 72 25",
    "sg:postcode":"40165",
    "sg:province":"Segovia",
    "wof:name":"Estacion De Servicio Lopez Hermanos S. A.",
    "wof:placetype":"venue"
},
  "geometry": {"coordinates":[-3.6885719299,41.1401100159],"type":"Point"}
}