{
  "type": "Feature",
  "properties": {
    "addr:full":"Carrer de Montornes, 17 Barcelona Barcelona 08023",
    "addr:housenumber":"17",
    "addr:postcode":"08023",
    "addr:street":"Carrer De Montornes",
    "iso:country":"ES",
    "sg:address":"Carrer de Montornes, 17",
    "sg:city":"Barcelona",
    "sg:orig_category":"Diplomas Diversos",
    "sg:phone":"+34 932 19 66 43",
    "sg:postcode":"08023",
    "sg:province":"Barcelona",
    "wof:name":"Horta Almaraz Federico",
    "wof:placetype":"venue"
},
  "geometry": {"coordinates":[2.1427690983,41.4172592163],"type":"Point"}
}