{
  "type": "Feature",
  "properties": {
    "iso:country":"ES",
    "sg:address":"Carrer de Sant Honorat, 39",
    "sg:city":"Sabadell",
    "sg:orig_category":"Telas Y Sedas (al Por Menor)",
    "sg:phone":"+34 937 25 15 20",
    "sg:postcode":"08202",
    "sg:province":"Barcelona",
    "wof:name":"Llar D\u00efnfants Casa Tereseta S.l.",
    "wof:placetype":"venue"
},
  "geometry": {"coordinates":[2.1094560623,41.5518112183],"type":"Point"}
}