{
  "type": "Feature",
  "properties": {
    "iso:country":"ES",
    "sg:address":"Calle de Plazuela, 45",
    "sg:city":"Huercanos",
    "sg:orig_category":"Tractores Agr\u00cdcolas Y Remolques",
    "sg:phone":"+34 941 37 14 36",
    "sg:postcode":"26314",
    "sg:province":"La Rioja",
    "wof:name":"Hurtado Iruzubieta Jose Antonio",
    "wof:placetype":"venue"
},
  "geometry": {"coordinates":[-2.6930088997,42.4273757935],"type":"Point"}
}