{
  "type": "Feature",
  "properties": {
    "iso:country":"ES",
    "sg:address":"Carrer de Muntaner, 259",
    "sg:city":"Barcelona",
    "sg:orig_category":"M\u00c9dicos: Neurolog\u00cda",
    "sg:phone":"+34 932 09 47 73",
    "sg:postcode":"08021",
    "sg:province":"Barcelona",
    "wof:name":"Acarin Tusell Pedro Nolasco",
    "wof:placetype":"venue"
},
  "geometry": {"coordinates":[2.1478447914,41.395362854],"type":"Point"}
}