{
  "type": "Feature",
  "properties": {
    "iso:country":"ES",
    "sg:address":"Carr Major, 61",
    "sg:city":"Sant Joan",
    "sg:orig_category":"Administraciones Regionales, Departamentales Y Locales",
    "sg:phone":"+34 971 52 60 03",
    "sg:postcode":"07240",
    "sg:province":"Islas Baleares",
    "wof:name":"Ayuntamiento De Sant Joan",
    "wof:placetype":"venue"
},
  "geometry": {"coordinates":[3.0392611027,39.5963249207],"type":"Point"}
}