{
  "type": "Feature",
  "properties": {
    "iso:country":"ES",
    "sg:address":"Calle de Ardisa, 8",
    "sg:city":"Ejea De Los Caballeros",
    "sg:orig_category":"Promotores Constructores",
    "sg:phone":"+34 976 66 35 66",
    "sg:postcode":"50600",
    "sg:province":"Zaragoza",
    "wof:name":"Construcciones Escario S.c.",
    "wof:placetype":"venue"
},
  "geometry": {"coordinates":[-1.1346937418,42.1300811768],"type":"Point"}
}