{
  "type": "Feature",
  "properties": {
    "addr:full":"Carrer de Salvador Barone, 119 Viladecans Barcelona 08840",
    "addr:housenumber":"119",
    "addr:postcode":"08840",
    "addr:street":"Carrer De Salvador Barone",
    "iso:country":"ES",
    "sg:address":"Carrer de Salvador Barone, 119",
    "sg:city":"Viladecans",
    "sg:orig_category":"Estudios, Instalaci\u00d3n De Climatizaci\u00d3n",
    "sg:phone":"+34 936 58 44 10",
    "sg:postcode":"08840",
    "sg:province":"Barcelona",
    "wof:name":"Envima S.l.",
    "wof:placetype":"venue"
},
  "geometry": {"coordinates":[2.0069921017,41.3162727356],"type":"Point"}
}