{
  "type": "Feature",
  "properties": {
    "addr:full":"Avda Doctor Sanchez Malo, 87 Ecija Sevilla 41400",
    "addr:housenumber":"87",
    "addr:postcode":"41400",
    "addr:street":"Avda Doctor Sanchez Malo",
    "iso:country":"ES",
    "sg:address":"Avda Doctor Sanchez Malo, 87",
    "sg:city":"Ecija",
    "sg:orig_category":"Internados & Ense\u00d1anza Privada",
    "sg:phone":"+34 955 90 13 38",
    "sg:postcode":"41400",
    "sg:province":"Sevilla",
    "wof:name":"Escuelas Profesionales Sagrada Familia",
    "wof:placetype":"venue"
},
  "geometry": {"coordinates":[-5.0873689651,37.5350799561],"type":"Point"}
}