{
  "type": "Feature",
  "properties": {
    "iso:country":"ES",
    "sg:address":"Autovia A-iii, Km. 0190,0",
    "sg:city":"Tebar",
    "sg:orig_category":"Distribuci\u00d3n De Petr\u00d3leo Y Derivados",
    "sg:phone":"+34 969 38 14 42",
    "sg:postcode":"16213",
    "sg:province":"Cuenca",
    "wof:name":"Herca S.l.",
    "wof:placetype":"venue"
},
  "geometry": {"coordinates":[-2.1630542278,39.4957695007],"type":"Point"}
}