{
  "type": "Feature",
  "properties": {
    "iso:country":"ES",
    "sg:address":"Carrer de Roger De Lluria, 5",
    "sg:city":"Barcelona",
    "sg:orig_category":"Edici\u00d3n De Diarios, Revistas, Boletines",
    "sg:phone":"+34 933 01 08 87",
    "sg:postcode":"08010",
    "sg:province":"Barcelona",
    "sg:website":"www.claret@claret.es",
    "wof:name":"Editorial Claret S.a.",
    "wof:placetype":"venue"
},
  "geometry": {"coordinates":[2.1727910042,41.389957428],"type":"Point"}
}