{
  "type": "Feature",
  "properties": {
    "addr:full":"Calle de Santa Maria, S/n Villazala Le\u00f3n 24763",
    "addr:postcode":"24763",
    "addr:street":"Calle De Santa;S / N Villazala Leo\u0301N",
    "iso:country":"ES",
    "sg:address":"Calle de Santa Maria, S/n",
    "sg:city":"Villazala",
    "sg:orig_category":"Asociaciones Ecologistas",
    "sg:phone":"+34 987 64 38 48",
    "sg:postcode":"24763",
    "sg:province":"Le\u00f3n",
    "wof:name":"Comunidad De Regantes",
    "wof:placetype":"venue"
},
  "geometry": {"coordinates":[-5.8551688194,42.3608093262],"type":"Point"}
}