{
  "type": "Feature",
  "properties": {
    "iso:country":"ES",
    "sg:address":"Carr Sor Angela De La Cruz, 4",
    "sg:city":"Aldaia",
    "sg:orig_category":"Asociaciones Humanitarias, De Cooperaci\u00d3n, De Acci\u00d3n Social",
    "sg:phone":"+34 961 51 70 29",
    "sg:postcode":"46960",
    "sg:province":"Valencia",
    "wof:name":"Asociacion De Padres Y Colaboradores De Minusvalidos",
    "wof:placetype":"venue"
},
  "geometry": {"coordinates":[-0.4569796026,39.4598083496],"type":"Point"}
}