{
  "type": "Feature",
  "properties": {
    "addr:full":"Pg Gracia, 66 Barcelona Barcelona 08007",
    "addr:housenumber":"66",
    "addr:postcode":"08007",
    "addr:street":"Pg Gracia",
    "iso:country":"ES",
    "sg:address":"Pg Gracia, 66",
    "sg:city":"Barcelona",
    "sg:orig_category":"Inmobiliaria (agencias)",
    "sg:phone":"+34 932 15 64 14",
    "sg:postcode":"08007",
    "sg:province":"Barcelona",
    "wof:name":"Morales Utiel Cesar",
    "wof:placetype":"venue"
},
  "geometry": {"coordinates":[2.1642599106,41.3931083679],"type":"Point"}
}