{
  "type": "Feature",
  "properties": {
    "addr:full":"Ctra. General, S/n Belmonte Asturias 33830",
    "addr:postcode":"33830",
    "addr:street":"Ctra. General S / N Belmonte Asturias",
    "iso:country":"ES",
    "sg:address":"Ctra. General, S/n",
    "sg:city":"Belmonte",
    "sg:orig_category":"Cajas De Ahorro",
    "sg:phone":"+34 985 76 20 50",
    "sg:postcode":"33830",
    "sg:province":"Asturias",
    "wof:name":"Cajastur",
    "wof:placetype":"venue"
},
  "geometry": {"coordinates":[-6.2189888954,43.2804718018],"type":"Point"}
}