{
  "type": "Feature",
  "properties": {
    "addr:full":"Alam Urquijo, 20 Bilbao Vizcaya 48008",
    "addr:housenumber":"20",
    "addr:postcode":"48008",
    "addr:street":"Alam Urquijo",
    "iso:country":"ES",
    "sg:address":"Alam Urquijo, 20",
    "sg:city":"Bilbao",
    "sg:orig_category":"Relojer\u00cda (al Por Menor, Reparaci\u00d3n)",
    "sg:phone":"+34 944 43 92 92",
    "sg:postcode":"48008",
    "sg:province":"Vizcaya",
    "wof:name":"Ribera Comercial De Relojeria S.l.",
    "wof:placetype":"venue"
},
  "geometry": {"coordinates":[-2.9337320328,43.2597770691],"type":"Point"}
}