{
  "type": "Feature",
  "properties": {
    "iso:country":"ES",
    "sg:address":"A Granxa, S/n",
    "sg:city":"Sela",
    "sg:classifiers":[
        {
            "category":"Manufacturing",
            "subcategory":"Building Materials",
            "type":"Manufacturing & Wholesale Goods"
        }
    ],
    "sg:phone":"+34 986 66 51 25",
    "sg:postcode":"36494",
    "sg:province":"Pontevedra",
    "sg:tags":[
        "bebidas",
        "para",
        "la",
        "de",
        "y",
        "equipo",
        "industria"
    ],
    "wof:name":"Freijanes Morales Jorge Valentin",
    "wof:placetype":"venue"
},
  "geometry": {"coordinates":[-8.3118143082,42.1128349304],"type":"Point"}
}