{
  "type": "Feature",
  "properties": {
    "iso:country":"ES",
    "sg:address":"Carrer de Rafael Llopart, S/n",
    "sg:city":"Sitges",
    "sg:orig_category":"Empresas De Carpinter\u00cda De Madera",
    "sg:phone":"+34 938 94 61 20",
    "sg:postcode":"08870",
    "sg:province":"Barcelona",
    "wof:name":"Vazquez Pinatar Pedro",
    "wof:placetype":"venue"
},
  "geometry": {"coordinates":[1.8130229712,41.2363815308],"type":"Point"}
}