{
  "type": "Feature",
  "properties": {
    "iso:country":"ES",
    "sg:address":"Carrer de Corominas, 5",
    "sg:city":"Hospitalet Llobregat",
    "sg:orig_category":"Cerrajer\u00cda, Ferrallista",
    "sg:phone":"+34 932 98 95 44",
    "sg:postcode":"08902",
    "sg:province":"Barcelona",
    "wof:name":"Cerrajeria Y -automatismos M.g. S.c.p.",
    "wof:placetype":"venue"
},
  "geometry": {"coordinates":[2.1209859848,41.3662948608],"type":"Point"}
}