{
  "type": "Feature",
  "properties": {
    "addr:full":"Avda Guardia Civil, 93 Tobarra Albacete 02500",
    "addr:housenumber":"93",
    "addr:postcode":"02500",
    "addr:street":"Avda Guardia Civil",
    "iso:country":"ES",
    "sg:address":"Avda Guardia Civil, 93",
    "sg:city":"Tobarra",
    "sg:orig_category":"Forjas Y Altos Hornos",
    "sg:phone":"+34 967 32 52 85",
    "sg:postcode":"02500",
    "sg:province":"Albacete",
    "wof:name":"Cotillas Lopez Joaquin",
    "wof:placetype":"venue"
},
  "geometry": {"coordinates":[-1.6869189739,38.5923881531],"type":"Point"}
}