{
  "type": "Feature",
  "properties": {
    "addr:full":"Calle de Vicente Aleixandre, 12 Vitoria-gasteiz \u00c1lava 01003",
    "addr:housenumber":"12",
    "addr:postcode":"01003",
    "addr:street":"Calle De Vicente Aleixandre",
    "iso:country":"ES",
    "sg:address":"Calle de Vicente Aleixandre, 12",
    "sg:city":"Vitoria-gasteiz",
    "sg:orig_category":"Afiladoras, Pulidoras Y Bru\u00d1idoras",
    "sg:phone":"+34 945 28 70 82",
    "sg:postcode":"01003",
    "sg:province":"\u00c1lava",
    "wof:name":"Lopez Sanchez Marcial",
    "wof:placetype":"venue"
},
  "geometry": {"coordinates":[-2.6568689346,42.844745636],"type":"Point"}
}