{
  "type": "Feature",
  "properties": {
    "iso:country":"ES",
    "sg:address":"Plaz Constitucion, 4",
    "sg:city":"S. Fulgencio",
    "sg:orig_category":"Museos",
    "sg:phone":"+34 966 79 40 20",
    "sg:postcode":"03177",
    "sg:province":"Alicante",
    "wof:name":"Ayuntamiento De San Fulgencio",
    "wof:placetype":"venue"
},
  "geometry": {"coordinates":[-0.7383440137,38.1049537659],"type":"Point"}
}