{
  "type": "Feature",
  "properties": {
    "iso:country":"ES",
    "sg:address":"Calle de Alta, 12",
    "sg:city":"S. Vicente Barquera",
    "sg:orig_category":"Ense\u00d1anza, Formaci\u00d3n Profesional: Aprendizaje",
    "sg:phone":"+34 942 71 25 21",
    "sg:postcode":"39540",
    "sg:province":"Cantabria",
    "wof:name":"Centro De Formacion Profesional Corazon De Maria",
    "wof:placetype":"venue"
},
  "geometry": {"coordinates":[-4.4030866623,43.3841018677],"type":"Point"}
}