{
  "type": "Feature",
  "properties": {
    "iso:country":"ES",
    "sg:address":"Plaz Obispo Alcolea, 3",
    "sg:city":"Astorga",
    "sg:orig_category":"M\u00c9dicos: Estomatolog\u00cda",
    "sg:phone":"+34 987 61 61 96",
    "sg:postcode":"24700",
    "sg:province":"Le\u00f3n",
    "wof:name":"Juan Benavides Tomas",
    "wof:placetype":"venue"
},
  "geometry": {"coordinates":[-6.0573301315,42.4597511292],"type":"Point"}
}