{
  "type": "Feature",
  "properties": {
    "iso:country":"ES",
    "sg:address":"Calle de Floridablanca, 3",
    "sg:city":"Almeria",
    "sg:orig_category":"Animales (al Por Menor)",
    "sg:phone":"+34 950 23 05 91",
    "sg:postcode":"04001",
    "sg:province":"Almer\u00eda",
    "wof:name":"Martin Camus Diego",
    "wof:placetype":"venue"
},
  "geometry": {"coordinates":[-2.4655280113,36.8396377563],"type":"Point"}
}