{
  "type": "Feature",
  "properties": {
    "addr:full":"Avda Ernestina Otero, 37 Redondela Pontevedra 36800",
    "addr:housenumber":"37",
    "addr:postcode":"36800",
    "addr:street":"Avda Ernestina Otero",
    "iso:country":"ES",
    "sg:address":"Avda Ernestina Otero, 37",
    "sg:city":"Redondela",
    "sg:orig_category":"Asociaciones, Organismos Culturales Y Socioeducativos",
    "sg:phone":"+34 986 40 02 56",
    "sg:postcode":"36800",
    "sg:province":"Pontevedra",
    "wof:name":"Centro Recreativo Cultural",
    "wof:placetype":"venue"
},
  "geometry": {"coordinates":[-8.6094665527,42.2842140198],"type":"Point"}
}