{
  "type": "Feature",
  "properties": {
    "iso:country":"ES",
    "sg:address":"Carr Caputxins, 30",
    "sg:city":"Vilanova I La Geltru",
    "sg:orig_category":"Bisuter\u00cda, Joyer\u00cda, Relojer\u00cda (al Por Menor)",
    "sg:phone":"+34 938 93 02 76",
    "sg:postcode":"08800",
    "sg:province":"Barcelona",
    "wof:name":"Sogu S.c.p.",
    "wof:placetype":"venue"
},
  "geometry": {"coordinates":[1.7257820368,41.2253417969],"type":"Point"}
}