{
  "type": "Feature",
  "properties": {
    "addr:full":"Avda Bidearte, 13 Arizgoiti Vizcaya 48970",
    "addr:housenumber":"13",
    "addr:postcode":"48970",
    "addr:street":"Avda Bidearte",
    "iso:country":"ES",
    "sg:address":"Avda Bidearte, 13",
    "sg:city":"Arizgoiti",
    "sg:orig_category":"Carnicer\u00cdas, Carnicer\u00cdas",
    "sg:phone":"+34 944 49 00 10",
    "sg:postcode":"48970",
    "sg:province":"Vizcaya",
    "wof:name":"Aresti Landeta Luis Maria",
    "wof:placetype":"venue"
},
  "geometry": {"coordinates":[-2.8907675743,43.2361373901],"type":"Point"}
}