{
  "type": "Feature",
  "properties": {
    "addr:full":"Calle de Varadero, 7 Almerimar Almer\u00eda 04711",
    "addr:housenumber":"7",
    "addr:postcode":"04711",
    "addr:street":"Calle De Varadero;Almeri\u0301A",
    "iso:country":"ES",
    "sg:address":"Calle de Varadero, 7",
    "sg:city":"Almerimar",
    "sg:orig_category":"Deportes N\u00c1uticos, Acu\u00c1ticos Y Subacu\u00c1ticos: Art\u00cdculos Y Equipo (al Por Menor)",
    "sg:phone":"+34 950 49 79 47",
    "sg:postcode":"04711",
    "sg:province":"Almer\u00eda",
    "wof:name":"Beacon  Spencer",
    "wof:placetype":"venue"
},
  "geometry": {"coordinates":[-2.7874190807,36.6967582703],"type":"Point"}
}