{
  "type": "Feature",
  "properties": {
    "addr:full":"Plaz Duque De Mandas, 30 Alhama Granada Granada 18120",
    "addr:housenumber":"30",
    "addr:postcode":"18120",
    "addr:street":"Mandas",
    "iso:country":"ES",
    "sg:address":"Plaz Duque De Mandas, 30",
    "sg:city":"Alhama Granada",
    "sg:orig_category":"Cl\u00cdnicas Dentales",
    "sg:phone":"+34 958 36 07 79",
    "sg:postcode":"18120",
    "sg:province":"Granada",
    "wof:name":"Grupo Dental Generalife S.l.",
    "wof:placetype":"venue"
},
  "geometry": {"coordinates":[-3.9909889698,37.0056495667],"type":"Point"}
}