{
  "type": "Feature",
  "properties": {
    "addr:full":"Calle de Nueva, 54 Motril Granada 18600",
    "addr:housenumber":"54",
    "addr:postcode":"18600",
    "addr:street":"Calle De Nueva",
    "iso:country":"ES",
    "sg:address":"Calle de Nueva, 54",
    "sg:city":"Motril",
    "sg:orig_category":"Tintorer\u00cdas, Limpieza En Seco",
    "sg:phone":"+34 958 60 85 28",
    "sg:postcode":"18600",
    "sg:province":"Granada",
    "sg:website":"www.pressto.com",
    "wof:name":"Luque Y Rosado C.b.",
    "wof:placetype":"venue"
},
  "geometry": {"coordinates":[-3.5183489323,36.7474784851],"type":"Point"}
}