{
  "type": "Feature",
  "properties": {
    "addr:full":"Calle de Valencia, 33 Salamanca Salamanca 37005",
    "addr:housenumber":"33",
    "addr:postcode":"37005",
    "addr:street":"Calle De Valencia",
    "iso:country":"ES",
    "sg:address":"Calle de Valencia, 33",
    "sg:city":"Salamanca",
    "sg:orig_category":"Peluquer\u00cdas, Peluquer\u00cda Mixta",
    "sg:phone":"+34 923 22 07 13",
    "sg:postcode":"37005",
    "sg:province":"Salamanca",
    "wof:name":"Peluqueria Tokes S.l.",
    "wof:placetype":"venue"
},
  "geometry": {"coordinates":[-5.6620440483,40.9715995789],"type":"Point"}
}