{
  "type": "Feature",
  "properties": {
    "iso:country":"ES",
    "sg:address":"Calle de Mateo Seoane Sobral, 26",
    "sg:city":"Valladolid",
    "sg:orig_category":"Papeler\u00cdas, Librer\u00cdas",
    "sg:phone":"+34 983 37 50 74",
    "sg:postcode":"47014",
    "sg:province":"Valladolid",
    "wof:name":"Andres Conde Daniel",
    "wof:placetype":"venue"
},
  "geometry": {"coordinates":[-4.7559103966,41.6357879639],"type":"Point"}
}