{
  "type": "Feature",
  "properties": {
    "addr:full":"Calle de La Florida, 16 Vitoria-gasteiz \u00c1lava 01005",
    "addr:housenumber":"16",
    "addr:postcode":"01005",
    "addr:street":"Calle De La Florida",
    "iso:country":"ES",
    "sg:address":"Calle de La Florida, 16",
    "sg:city":"Vitoria-gasteiz",
    "sg:orig_category":"M\u00c9dicos: Estomatolog\u00cda",
    "sg:phone":"+34 945 23 29 42",
    "sg:postcode":"01005",
    "sg:province":"\u00c1lava",
    "wof:name":"Zurdo Mu\u00f1iz Concepcion",
    "wof:placetype":"venue"
},
  "geometry": {"coordinates":[-2.673009634,42.8432006836],"type":"Point"}
}