{
  "type": "Feature",
  "properties": {
    "iso:country":"ES",
    "sg:address":"Calle de Islas Canarias, 138",
    "sg:city":"Valencia",
    "sg:orig_category":"Chapister\u00cda",
    "sg:phone":"+34 963 30 16 35",
    "sg:postcode":"46023",
    "sg:province":"Valencia",
    "wof:name":"Marques Leiva Antonio",
    "wof:placetype":"venue"
},
  "geometry": {"coordinates":[-0.3429585993,39.4622306824],"type":"Point"}
}