{
  "type": "Feature",
  "properties": {
    "addr:full":"Pase Pamplona, 4 Tudela Navarra 31500",
    "addr:housenumber":"4",
    "addr:postcode":"31500",
    "addr:street":"Pamplona",
    "iso:country":"ES",
    "sg:address":"Pase Pamplona, 4",
    "sg:city":"Tudela",
    "sg:orig_category":"Agentes Generales De Seguros",
    "sg:phone":"+34 948 82 22 65",
    "sg:postcode":"31500",
    "sg:province":"Navarra",
    "wof:name":"Goicoechea Subies Sandra",
    "wof:placetype":"venue"
},
  "geometry": {"coordinates":[-1.6023850441,42.0629959106],"type":"Point"}
}