{
  "type": "Feature",
  "properties": {
    "addr:full":"Carr Agustin Olivert, 5 Cullera Valencia 46400",
    "addr:housenumber":"5",
    "addr:postcode":"46400",
    "addr:street":"Carr Agustin Olivert",
    "iso:country":"ES",
    "sg:address":"Carr Agustin Olivert, 5",
    "sg:city":"Cullera",
    "sg:orig_category":"Agencias De Viajes",
    "sg:phone":"+34 961 72 06 53",
    "sg:postcode":"46400",
    "sg:province":"Valencia",
    "wof:name":"Kuzh Alacant, S.l.",
    "wof:placetype":"venue"
},
  "geometry": {"coordinates":[-0.2466640025,39.1641044617],"type":"Point"}
}