{
  "type": "Feature",
  "properties": {
    "addr:full":"Calle de Mayor, 32 Burgohondo \u00c1vila 05113",
    "addr:housenumber":"32",
    "addr:postcode":"05113",
    "addr:street":"Calle De Mayor;A\u0301Vila",
    "iso:country":"ES",
    "sg:address":"Calle de Mayor, 32",
    "sg:city":"Burgohondo",
    "sg:orig_category":"Electricidad, Electr\u00d3nica: Suministros (al Por Menor)",
    "sg:phone":"+34 920 28 30 00",
    "sg:postcode":"05113",
    "sg:province":"\u00c1vila",
    "wof:name":"Martin Mu\u00f1oz Roberto",
    "wof:placetype":"venue"
},
  "geometry": {"coordinates":[-4.7861628532,40.4130744934],"type":"Point"}
}