{
  "type": "Feature",
  "properties": {
    "addr:full":"Carr Magatzem, 73 Badalona Barcelona 08911",
    "addr:housenumber":"73",
    "addr:postcode":"08911",
    "addr:street":"Carr Magatzem",
    "iso:country":"ES",
    "sg:address":"Carr Magatzem, 73",
    "sg:city":"Badalona",
    "sg:orig_category":"Molduras, Junquillos, Listones Y Molduras Perforadas",
    "sg:phone":"+34 933 84 23 35",
    "sg:postcode":"08911",
    "sg:province":"Barcelona",
    "wof:name":"Morales Saladrigas Maria Esperanza",
    "wof:placetype":"venue"
},
  "geometry": {"coordinates":[2.2519180775,41.4492492676],"type":"Point"}
}