{
  "type": "Feature",
  "properties": {
    "addr:full":"Ctra Vall D'aran, S/n Almenar Lleida 25126",
    "addr:housenumber":"s / n",
    "addr:postcode":"25126",
    "addr:street":"Ctra Vall D'Aran",
    "iso:country":"ES",
    "sg:address":"Ctra Vall D'aran, S/n",
    "sg:city":"Almenar",
    "sg:orig_category":"Agentes, Concesionarios Y Sucursales De Camiones Y Veh\u00cdculos Industriales",
    "sg:phone":"+34 973 77 06 22",
    "sg:postcode":"25126",
    "sg:province":"Lleida",
    "wof:name":"Quads Ponent Sl",
    "wof:placetype":"venue"
},
  "geometry": {"coordinates":[0.5701000094,41.7965507507],"type":"Point"}
}