{
  "type": "Feature",
  "properties": {
    "iso:country":"ES",
    "sg:address":"Av Rey J Carlos I, 50",
    "sg:city":"Javea",
    "sg:orig_category":"Muebles Y Accesorios Para Cocinas Y Cuartos De Ba\u00d1o (al Por Menor)",
    "sg:phone":"+34 965 79 40 93",
    "sg:postcode":"03730",
    "sg:province":"Alicante",
    "wof:name":"Sede\u00f1o Morales Martin",
    "wof:placetype":"venue"
},
  "geometry": {"coordinates":[0.1570300013,38.7885093689],"type":"Point"}
}