{
  "type": "Feature",
  "properties": {
    "iso:country":"ES",
    "sg:address":"Calle de San Mariano, 100",
    "sg:city":"Madrid",
    "sg:orig_category":"Cerrajer\u00cda, Ferrallista",
    "sg:phone":"+34 917 41 60 30",
    "sg:postcode":"28022",
    "sg:province":"Madrid",
    "wof:name":"Mu\u00f1oz Sancho Pilar",
    "wof:placetype":"venue"
},
  "geometry": {"coordinates":[-3.6092910767,40.436504364],"type":"Point"}
}