{
  "type": "Feature",
  "properties": {
    "addr:full":"Calle de Corredera, 10 Llerena Badajoz 06900",
    "addr:housenumber":"10",
    "addr:postcode":"06900",
    "addr:street":"Calle De Corredera",
    "iso:country":"ES",
    "sg:address":"Calle de Corredera, 10",
    "sg:city":"Llerena",
    "sg:orig_category":"Material Y Herramientas Agr\u00cdcolas",
    "sg:phone":"+34 924 87 20 02",
    "sg:postcode":"06900",
    "sg:province":"Badajoz",
    "wof:name":"Talleres Marcelo S.a.",
    "wof:placetype":"venue"
},
  "geometry": {"coordinates":[-6.0142760277,38.2371253967],"type":"Point"}
}