{
  "type": "Feature",
  "properties": {
    "addr:full":"Carrer de Aribau, 250 Barcelona Barcelona 08006",
    "addr:housenumber":"250",
    "addr:postcode":"08006",
    "addr:street":"Carrer De Aribau",
    "iso:country":"ES",
    "sg:address":"Carrer de Aribau, 250",
    "sg:city":"Barcelona",
    "sg:orig_category":"Abogados",
    "sg:phone":"+34 932 01 16 67",
    "sg:postcode":"08006",
    "sg:province":"Barcelona",
    "wof:name":"Del Castillo Aragon Luis",
    "wof:placetype":"venue"
},
  "geometry": {"coordinates":[2.1492331028,41.3962516785],"type":"Point"}
}