{
  "type": "Feature",
  "properties": {
    "addr:full":"Calle de Prevision (la), 41 Cordoba C\u00f3rdoba 14004",
    "addr:housenumber":"41",
    "addr:postcode":"14004",
    "addr:street":"Calle De Prevision La;Co\u0301Rdoba",
    "iso:country":"ES",
    "sg:address":"Calle de Prevision (la), 41",
    "sg:city":"Cordoba",
    "sg:orig_category":"Bisuter\u00cda, Joyer\u00cda, Relojer\u00cda (al Por Menor)",
    "sg:phone":"+34 957 45 17 24",
    "sg:postcode":"14004",
    "sg:province":"C\u00f3rdoba",
    "wof:name":"Luque Vacas Julian",
    "wof:placetype":"venue"
},
  "geometry": {"coordinates":[-4.7920098305,37.8785858154],"type":"Point"}
}