{
  "type": "Feature",
  "properties": {
    "addr:full":"Calle de Bravo Murillo, 21 Madrid Madrid 28015",
    "addr:housenumber":"21",
    "addr:postcode":"madrid;28015",
    "addr:street":"Calle De Bravo Murillo",
    "iso:country":"ES",
    "sg:address":"Calle de Bravo Murillo, 21",
    "sg:city":"Madrid",
    "sg:orig_category":"Administradores De Bienes Y Delegados De Comunidades De Propietarios",
    "sg:phone":"+34 914 47 56 13",
    "sg:postcode":"28015",
    "sg:province":"Madrid",
    "wof:name":"Alser Administracion De Fincas S.l.",
    "wof:placetype":"venue"
},
  "geometry": {"coordinates":[-3.704349041,40.435546875],"type":"Point"}
}