{
  "type": "Feature",
  "properties": {
    "addr:full":"Calle de Elias Iglesias, 16 Cacabelos Le\u00f3n 24540",
    "addr:housenumber":"16",
    "addr:postcode":"24540",
    "addr:street":"Calle De Elias Iglesias",
    "iso:country":"ES",
    "sg:address":"Calle de Elias Iglesias, 16",
    "sg:city":"Cacabelos",
    "sg:orig_category":"Madera Para Construcci\u00d3n E Industria",
    "sg:phone":"+34 987 54 94 85",
    "sg:postcode":"24540",
    "sg:province":"Le\u00f3n",
    "wof:name":"Revestimiento Tarimas Y Parquets M.a.c S.l.",
    "wof:placetype":"venue"
},
  "geometry": {"coordinates":[-6.7258119583,42.5953445435],"type":"Point"}
}