{
  "type": "Feature",
  "properties": {
    "addr:full":"Calle de Rubio, 40 Cintruenigo Navarra 31592",
    "addr:housenumber":"40",
    "addr:postcode":"31592",
    "addr:street":"Calle De Rubio",
    "iso:country":"ES",
    "sg:address":"Calle de Rubio, 40",
    "sg:city":"Cintruenigo",
    "sg:orig_category":"Negocio De Materiales De Construcci\u00d3n",
    "sg:phone":"+34 948 81 52 49",
    "sg:postcode":"31592",
    "sg:province":"Navarra",
    "wof:name":"Ceramicas Cecilio Chivite S.l.",
    "wof:placetype":"venue"
},
  "geometry": {"coordinates":[-1.8106110096,42.08070755],"type":"Point"}
}