{
  "type": "Feature",
  "properties": {
    "iso:country":"ES",
    "sg:address":"Ctra Olivares-vva Del Ariscal, S/n",
    "sg:city":"Olivares",
    "sg:orig_category":"Reciclaje, Desguace De Veh\u00cdculos",
    "sg:phone":"+34 955 99 04 24",
    "sg:postcode":"41804",
    "sg:province":"Sevilla",
    "wof:name":"Desguaces Olivares S.l.",
    "wof:placetype":"venue"
},
  "geometry": {"coordinates":[-6.153439045,37.4184074402],"type":"Point"}
}