{
  "type": "Feature",
  "properties": {
    "iso:country":"ES",
    "sg:address":"Calle de O'daly, 5",
    "sg:city":"Santa Cruz Palma",
    "sg:orig_category":"Consultas M\u00c9dicas",
    "sg:phone":"+34 922 42 05 71",
    "sg:postcode":"38700",
    "sg:province":"Santa Cruz De Tenerife",
    "wof:name":"Elchofer S.l.",
    "wof:placetype":"venue"
},
  "geometry": {"coordinates":[-16.3033008575,28.4396839142],"type":"Point"}
}