{
  "type": "Feature",
  "properties": {
    "iso:country":"ES",
    "sg:address":"Calle de Via Ensanche, 23",
    "sg:city":"Merida",
    "sg:orig_category":"Congelados: Productos Alimentarios (al Por Menor)",
    "sg:phone":"+34 924 31 36 62",
    "sg:postcode":"06800",
    "sg:province":"Badajoz",
    "wof:name":"Acedo Penco Joaquin",
    "wof:placetype":"venue"
},
  "geometry": {"coordinates":[-6.3398060799,38.9125976562],"type":"Point"}
}