{
  "type": "Feature",
  "properties": {
    "iso:country":"ES",
    "sg:address":"Lg Vilar De Arriba (pereira), S/n",
    "sg:city":"Barbeira",
    "sg:orig_category":"Medias Y Calcetines (fabricaci\u00d3n, Al Por Mayor)",
    "sg:phone":"+34 981 89 65 65",
    "sg:postcode":"15837",
    "sg:province":"La Coru\u00f1a",
    "wof:name":"Frovima S.l.",
    "wof:placetype":"venue"
},
  "geometry": {"coordinates":[-8.8731641769,42.9889831543],"type":"Point"}
}