{
  "type": "Feature",
  "properties": {
    "iso:country":"ES",
    "sg:address":"Avda Mahia, S/n",
    "sg:city":"Bertamirans",
    "sg:orig_category":"Lencer\u00cda Femenina, Corseter\u00cda, Trajes De Ba\u00d1o (al Por Menor)",
    "sg:phone":"+34 981 89 14 00",
    "sg:postcode":"15220",
    "sg:province":"La Coru\u00f1a",
    "wof:name":"Bures Cores Mercedes",
    "wof:placetype":"venue"
},
  "geometry": {"coordinates":[-8.6555786133,42.8583068848],"type":"Point"}
}