{
  "type": "Feature",
  "properties": {
    "iso:country":"ES",
    "sg:address":"Avda Ordo\u00d1o Ii, 32",
    "sg:city":"Le\u00f3n",
    "sg:orig_category":"Promotores Constructores",
    "sg:phone":"+34 987 22 77 00",
    "sg:postcode":"24001",
    "sg:province":"Le\u00f3n",
    "wof:name":"Ayala Alvarez Pablo",
    "wof:placetype":"venue"
},
  "geometry": {"coordinates":[-5.5772600174,42.5965995789],"type":"Point"}
}