{
  "type": "Feature",
  "properties": {
    "addr:full":"Ptge Rector Marti I Pi\u00d1ol, 14 Prat Llobregat Barcelona 08820",
    "addr:housenumber":"14",
    "addr:postcode":"08820",
    "addr:street":"Ptge Rector Marti I Pin\u0303Ol;Llobregat",
    "iso:country":"ES",
    "sg:address":"Ptge Rector Marti I Pi\u00d1ol, 14",
    "sg:city":"Prat Llobregat",
    "sg:orig_category":"Molduras, Junquillos, Listones Y Molduras Perforadas",
    "sg:phone":"+34 933 79 41 52",
    "sg:postcode":"08820",
    "sg:province":"Barcelona",
    "wof:name":"Castellar Heredia Candido",
    "wof:placetype":"venue"
},
  "geometry": {"coordinates":[2.0945019722,41.3289718628],"type":"Point"}
}