{
  "type": "Feature",
  "properties": {
    "addr:full":"Avda Cardones Los, 46 Cardones Las Palmas 35470",
    "addr:housenumber":"46",
    "addr:postcode":"35470",
    "addr:street":"Avda Cardones Los",
    "iso:country":"ES",
    "sg:address":"Avda Cardones Los, 46",
    "sg:city":"Cardones",
    "sg:orig_category":"Reposter\u00cdas",
    "sg:phone":"+34 928 89 11 50",
    "sg:postcode":"35470",
    "sg:province":"Las Palmas",
    "wof:name":"Panaderia Artenara Hermanos Medina S.l.",
    "wof:placetype":"venue"
},
  "geometry": {"coordinates":[-15.7829742432,27.98595047],"type":"Point"}
}