{
  "type": "Feature",
  "properties": {
    "iso:country":"ES",
    "sg:address":"Carrer de Temple De Sant Telm, 17",
    "sg:city":"Denia",
    "sg:orig_category":"M\u00c9dicos: Neurolog\u00cda",
    "sg:phone":"+34 965 78 22 73",
    "sg:postcode":"03700",
    "sg:province":"Alicante",
    "wof:name":"Lopez Leon Carmen",
    "wof:placetype":"venue"
},
  "geometry": {"coordinates":[0.110694997,38.8420677185],"type":"Point"}
}