{
  "type": "Feature",
  "properties": {
    "iso:country":"ES",
    "sg:address":"Calle de Reyes Catolicos, 5",
    "sg:city":"Calera Leon",
    "sg:orig_category":"Doctores En Medicina",
    "sg:phone":"+34 924 58 40 88",
    "sg:postcode":"06292",
    "sg:province":"Badajoz",
    "wof:name":"Megias Diaz Jesus",
    "wof:placetype":"venue"
},
  "geometry": {"coordinates":[-6.3369731903,38.107509613],"type":"Point"}
}