{
  "type": "Feature",
  "properties": {
    "addr:full":"Zapateria, 13 Iru\u00f1a Navarra 31001",
    "addr:housenumber":"13",
    "addr:postcode":"31001",
    "addr:street":"Irun\u0303A Navarra",
    "iso:country":"ES",
    "sg:address":"Zapateria, 13",
    "sg:city":"Iru\u00f1a",
    "sg:orig_category":"Ropa Para Se\u00d1oras Y Caballeros (al Por Menor)",
    "sg:phone":"+34 948 22 11 73",
    "sg:postcode":"31001",
    "sg:province":"Navarra",
    "wof:name":"Gonzalez Morentin Francisco Javier",
    "wof:placetype":"venue"
},
  "geometry": {"coordinates":[-1.6438390017,42.8175239563],"type":"Point"}
}