{
  "type": "Feature",
  "properties": {
    "iso:country":"ES",
    "sg:address":"Poli Poligono Industrial Quemadas, S/n",
    "sg:city":"Quemadas",
    "sg:orig_category":"Construcciones Met\u00c1licas",
    "sg:phone":"+34 957 32 57 00",
    "sg:postcode":"14014",
    "sg:province":"C\u00f3rdoba",
    "wof:name":"Carpinteria Metalica Cabanillas S.l.",
    "wof:placetype":"venue"
},
  "geometry": {"coordinates":[-4.7624139786,37.9240608215],"type":"Point"}
}