{
  "type": "Feature",
  "properties": {
    "addr:full":"Av. B. Navarra, 38 Iru\u00f1a Navarra 31004",
    "addr:housenumber":"38",
    "addr:postcode":"31004",
    "addr:street":"Av. B. Navarra",
    "iso:country":"ES",
    "sg:address":"Av. B. Navarra, 38",
    "sg:city":"Iru\u00f1a",
    "sg:orig_category":"Agencias Y Asesores De Publicidad",
    "sg:phone":"+34 948 15 07 50",
    "sg:postcode":"31004",
    "sg:province":"Navarra",
    "sg:website":"www.irunako.com",
    "wof:name":"Publicidad Los Iru\u00f1ako S.l.",
    "wof:placetype":"venue"
},
  "geometry": {"coordinates":[-1.6437540054,42.81275177],"type":"Point"}
}