{
  "type": "Feature",
  "properties": {
    "addr:full":"Carrer de Balboa, 12 Barcelona Barcelona 08003",
    "addr:housenumber":"12",
    "addr:postcode":"08003",
    "addr:street":"Carrer De Balboa",
    "iso:country":"ES",
    "sg:address":"Carrer de Balboa, 12",
    "sg:city":"Barcelona",
    "sg:orig_category":"Reposter\u00cdas",
    "sg:phone":"+34 933 10 61 85",
    "sg:postcode":"08003",
    "sg:province":"Barcelona",
    "wof:name":"Safarina S.l.",
    "wof:placetype":"venue"
},
  "geometry": {"coordinates":[2.1880030632,41.3819923401],"type":"Point"}
}