{
  "type": "Feature",
  "properties": {
    "addr:full":"Carrer de Lluis Castells, 53 S. Boi Llobregat Barcelona 08830",
    "addr:housenumber":"53",
    "addr:postcode":"08830",
    "addr:street":"Carrer De Lluis Castells",
    "iso:country":"ES",
    "sg:address":"Carrer de Lluis Castells, 53",
    "sg:city":"S. Boi Llobregat",
    "sg:orig_category":"Decoradores",
    "sg:phone":"+34 936 30 21 35",
    "sg:postcode":"08830",
    "sg:province":"Barcelona",
    "wof:name":"Gracia Llurda Maria Luisa",
    "wof:placetype":"venue"
},
  "geometry": {"coordinates":[2.0365829468,41.3462257385],"type":"Point"}
}