{
  "type": "Feature",
  "properties": {
    "iso:country":"ES",
    "sg:address":"Calle de Ciudad De Fraga, 2",
    "sg:city":"Sabi\u00f1anigo",
    "sg:orig_category":"Clubes Y Asociaciones Deportivas Y De Actividades Invernales Y De Monta\u00d1a",
    "sg:phone":"+34 974 48 06 87",
    "sg:postcode":"22600",
    "sg:province":"Huesca",
    "wof:name":"Grupos De Monta\u00f1a Sabi\u00f1anigo",
    "wof:placetype":"venue"
},
  "geometry": {"coordinates":[-0.3689875901,42.5189704895],"type":"Point"}
}