{
  "type": "Feature",
  "properties": {
    "iso:country":"ES",
    "sg:address":"Carrer de Nu\u00d1ez De Balboa, 17",
    "sg:city":"Mataro",
    "sg:orig_category":"Inmobiliaria (agencias)",
    "sg:phone":"+34 937 41 40 27",
    "sg:postcode":"08302",
    "sg:province":"Barcelona",
    "wof:name":"Perez Garcia Joan",
    "wof:placetype":"venue"
},
  "geometry": {"coordinates":[2.4340848923,41.5362968445],"type":"Point"}
}