{
  "type": "Feature",
  "properties": {
    "iso:country":"ES",
    "sg:address":"Calle de Tinerfe, 1",
    "sg:city":"Longuera",
    "sg:orig_category":"Muebles, Minoristas",
    "sg:phone":"+34 922 36 24 94",
    "sg:postcode":"38418",
    "sg:province":"Santa Cruz De Tenerife",
    "wof:name":"Don Habit S.l.",
    "wof:placetype":"venue"
},
  "geometry": {"coordinates":[-16.5708580017,28.3957233429],"type":"Point"}
}