{
  "type": "Feature",
  "properties": {
    "addr:full":"Carrer de Joaquim Costa, 128 Terrassa Barcelona 08222",
    "addr:housenumber":"128",
    "addr:postcode":"08222",
    "addr:street":"Carrer De Joaquim Costa",
    "iso:country":"ES",
    "sg:address":"Carrer de Joaquim Costa, 128",
    "sg:city":"Terrassa",
    "sg:orig_category":"Centros Comerciales Y Grandes Tiendas",
    "sg:phone":"+34 937 31 90 66",
    "sg:postcode":"08222",
    "sg:province":"Barcelona",
    "wof:name":"Mostin S.l.",
    "wof:placetype":"venue"
},
  "geometry": {"coordinates":[2.0255990028,41.5612983704],"type":"Point"}
}