{
  "type": "Feature",
  "properties": {
    "iso:country":"ES",
    "sg:address":"Calle de Tormento, 41",
    "sg:city":"Palmas De Gran Canaria",
    "sg:orig_category":"Peluquer\u00cdas, Peluquer\u00cda Mixta",
    "sg:phone":"+34 928 20 65 44",
    "sg:postcode":"35012",
    "sg:province":"Las Palmas",
    "wof:name":"Valiente Perez Francisca Eugenia",
    "wof:placetype":"venue"
},
  "geometry": {"coordinates":[-15.435295105,28.1092281342],"type":"Point"}
}