{
  "type": "Feature",
  "properties": {
    "addr:full":"Avda Dilar (de), 63 Granada Granada 18007",
    "addr:housenumber":"63",
    "addr:postcode":"18007",
    "addr:street":"Avda Dilar De",
    "iso:country":"ES",
    "sg:address":"Avda Dilar (de), 63",
    "sg:city":"Granada",
    "sg:orig_category":"Confecci\u00d3n (fabricaci\u00d3n, Al Por Mayor)",
    "sg:phone":"+34 958 13 01 20",
    "sg:postcode":"18007",
    "sg:province":"Granada",
    "wof:name":"Modimpacto S.l.",
    "wof:placetype":"venue"
},
  "geometry": {"coordinates":[-3.600039959,37.1568145752],"type":"Point"}
}