{
  "type": "Feature",
  "properties": {
    "addr:full":"Av Sarria, 47 Barcelona Barcelona 08029",
    "addr:housenumber":"47",
    "addr:postcode":"08029",
    "addr:street":"Av Sarria",
    "iso:country":"ES",
    "sg:address":"Av Sarria, 47",
    "sg:city":"Barcelona",
    "sg:orig_category":"Arquitectos",
    "sg:phone":"+34 934 39 64 33",
    "sg:postcode":"08029",
    "sg:province":"Barcelona",
    "wof:name":"Herrera Sevilla Bernardino",
    "wof:placetype":"venue"
},
  "geometry": {"coordinates":[2.1431789398,41.3904266357],"type":"Point"}
}