{
  "type": "Feature",
  "properties": {
    "addr:full":"Calle de Bermudez De Castro, 44 Oviedo Asturias 33011",
    "addr:housenumber":"44",
    "addr:postcode":"33011",
    "addr:street":"Calle De Bermudez De Castro",
    "iso:country":"ES",
    "sg:address":"Calle de Bermudez De Castro, 44",
    "sg:city":"Oviedo",
    "sg:orig_category":"Droguer\u00cdas (al Por Menor)",
    "sg:phone":"+34 985 28 32 20",
    "sg:postcode":"33011",
    "sg:province":"Asturias",
    "wof:name":"Tamargo Ardura Enrique",
    "wof:placetype":"venue"
},
  "geometry": {"coordinates":[-5.836643219,43.3714523315],"type":"Point"}
}