{
  "type": "Feature",
  "properties": {
    "addr:full":"Plaz Constitucion (de La), 9 Cedrillas Teruel 44147",
    "addr:housenumber":"9",
    "addr:postcode":"44147",
    "iso:country":"ES",
    "sg:address":"Plaz Constitucion (de La), 9",
    "sg:city":"Cedrillas",
    "sg:orig_category":"Reposter\u00cdas",
    "sg:phone":"+34 978 77 40 03",
    "sg:postcode":"44147",
    "sg:province":"Teruel",
    "wof:name":"Abril Edo Jesus",
    "wof:placetype":"venue"
},
  "geometry": {"coordinates":[-0.85301,40.435795],"type":"Point"}
}