{
  "type": "Feature",
  "properties": {
    "addr:full":"Carrer de Sant Pere, 18 Hospitalet Llobregat Barcelona 08906",
    "addr:housenumber":"18",
    "addr:postcode":"08906",
    "addr:street":"Carrer De Sant Pere",
    "iso:country":"ES",
    "sg:address":"Carrer de Sant Pere, 18",
    "sg:city":"Hospitalet Llobregat",
    "sg:orig_category":"Peluquer\u00cdas, Peluquer\u00cda Mixta",
    "sg:phone":"+34 934 38 75 06",
    "sg:postcode":"08906",
    "sg:province":"Barcelona",
    "wof:name":"Vallejo Lopez Antonio",
    "wof:placetype":"venue"
},
  "geometry": {"coordinates":[2.0987129211,41.3672027588],"type":"Point"}
}