{
  "type": "Feature",
  "properties": {
    "iso:country":"ES",
    "sg:address":"Calle de Valenzuela, S/n",
    "sg:city":"Pozuelo Calatrava",
    "sg:orig_category":"Cerrajer\u00cda, Ferrallista",
    "sg:phone":"+34 926 84 05 57",
    "sg:postcode":"13179",
    "sg:province":"Ciudad Real",
    "wof:name":"Lopez Sanchez Gregorio",
    "wof:placetype":"venue"
},
  "geometry": {"coordinates":[-3.8325922489,38.9081802368],"type":"Point"}
}