{
  "type": "Feature",
  "properties": {
    "iso:country":"ES",
    "sg:address":"Calle de Veracruz, 86",
    "sg:city":"Valdepe\u00f1as",
    "sg:orig_category":"Agentes, Concesionarios Y Sucursales De Camiones Y Veh\u00cdculos Industriales",
    "sg:phone":"+34 926 31 16 90",
    "sg:postcode":"13300",
    "sg:province":"Ciudad Real",
    "wof:name":"Garcia Cabezuelo Miguel Angel",
    "wof:placetype":"venue"
},
  "geometry": {"coordinates":[-3.3756089211,38.7609214783],"type":"Point"}
}