{
  "type": "Feature",
  "properties": {
    "addr:full":"Avda Canarias De, 22 Palmas De Gran Canaria Las Palmas 35002",
    "addr:postcode":"35002",
    "addr:street":"Avda Canarias De 22",
    "iso:country":"ES",
    "sg:address":"Avda Canarias De, 22",
    "sg:city":"Palmas De Gran Canaria",
    "sg:orig_category":"Centros Empresariales",
    "sg:phone":"+34 928 36 57 09",
    "sg:postcode":"35002",
    "sg:province":"Las Palmas",
    "sg:website":"www.consultoriadenegociosmba.com",
    "wof:name":"Escuela De Negocios Mba S.l.",
    "wof:placetype":"venue"
},
  "geometry": {"coordinates":[-15.4137544632,28.1060218811],"type":"Point"}
}