{
  "type": "Feature",
  "properties": {
    "iso:country":"ES",
    "sg:address":"Urba Arenals De Mar, 2",
    "sg:city":"Arenals De Mar",
    "sg:orig_category":"Inmobiliaria (agencias)",
    "sg:phone":"+34 972 66 79 58",
    "sg:postcode":"17256",
    "sg:province":"Girona",
    "wof:name":"Proaltur S.a.",
    "wof:placetype":"venue"
},
  "geometry": {"coordinates":[3.1482629776,41.9678573608],"type":"Point"}
}