{
  "type": "Feature",
  "properties": {
    "iso:country":"ES",
    "sg:address":"Calle de Plomo, 36",
    "sg:city":"Aimayr",
    "sg:orig_category":"Distribuci\u00d3n De Petr\u00d3leo Y Derivados",
    "sg:phone":"+34 916 92 28 74",
    "sg:postcode":"28320",
    "sg:province":"Madrid",
    "wof:name":"Combustibles Aranjuez S.l.",
    "wof:placetype":"venue"
},
  "geometry": {"coordinates":[-3.6336250305,40.2364997864],"type":"Point"}
}