{
  "type": "Feature",
  "properties": {
    "addr:full":"Avda Ciudades (de Las), 1 Getafe Madrid 28903",
    "addr:housenumber":"1",
    "addr:postcode":"28903",
    "addr:street":"Avda Ciudades De Las",
    "iso:country":"ES",
    "sg:address":"Avda Ciudades (de Las), 1",
    "sg:city":"Getafe",
    "sg:orig_category":"Fotocopias, Reprograf\u00cda",
    "sg:phone":"+34 916 84 05 27",
    "sg:postcode":"28903",
    "sg:province":"Madrid",
    "wof:name":"Pe\u00f1a Mendoza Candida",
    "wof:placetype":"venue"
},
  "geometry": {"coordinates":[-3.7261309624,40.3197174072],"type":"Point"}
}