{
  "type": "Feature",
  "properties": {
    "addr:full":"Carrer de Creu Coberta, 93 Barcelona Barcelona 08014",
    "addr:housenumber":"93",
    "addr:postcode":"08014",
    "addr:street":"Carrer De Creu Coberta",
    "iso:country":"ES",
    "sg:address":"Carrer de Creu Coberta, 93",
    "sg:city":"Barcelona",
    "sg:orig_category":"Bancos",
    "sg:phone":"+34 933 32 94 80",
    "sg:postcode":"08014",
    "sg:province":"Barcelona",
    "wof:name":"Banco Espa\u00d1ol De Credito S.a.",
    "wof:placetype":"venue"
},
  "geometry": {"coordinates":[2.1436810493,41.3751106262],"type":"Point"}
}