{
  "type": "Feature",
  "properties": {
    "addr:full":"Calle de Tarrago Y Mateos, 1 Guadix Granada 18500",
    "addr:postcode":"18500",
    "addr:street":"Calle De Tarrago Y Mateos 1",
    "iso:country":"ES",
    "sg:address":"Calle de Tarrago Y Mateos, 1",
    "sg:city":"Guadix",
    "sg:orig_category":"Alimentaci\u00d3n General (al Por Menor)",
    "sg:phone":"+34 958 66 06 64",
    "sg:postcode":"18500",
    "sg:province":"Granada",
    "wof:name":"Valverde Sierra Antonio Francisco",
    "wof:placetype":"venue"
},
  "geometry": {"coordinates":[-3.1338639259,37.3004837036],"type":"Point"}
}