{
  "type": "Feature",
  "properties": {
    "addr:full":"Vila Carlet, 1 Borges Blanques Lleida 25400",
    "addr:housenumber":"1",
    "addr:postcode":"25400",
    "iso:country":"ES",
    "sg:address":"Vila Carlet, 1",
    "sg:city":"Borges Blanques",
    "sg:orig_category":"Agencias Y Agentes Comerciales, Representantes",
    "sg:phone":"+34 973 14 28 74",
    "sg:postcode":"25400",
    "sg:province":"Lleida",
    "wof:name":"Codextra S.l.",
    "wof:placetype":"venue"
},
  "geometry": {"coordinates":[0.8711360097,41.5198669434],"type":"Point"}
}