{
  "type": "Feature",
  "properties": {
    "addr:full":"Calle de Doctor Fleming, 32 Valencina Concepcion Sevilla 41907",
    "addr:housenumber":"32",
    "addr:postcode":"41907",
    "addr:street":"Calle De Doctor Fleming",
    "iso:country":"ES",
    "sg:address":"Calle de Doctor Fleming, 32",
    "sg:city":"Valencina Concepcion",
    "sg:orig_category":"Peluqueros: De Se\u00d1oras",
    "sg:phone":"+34 955 72 92 05",
    "sg:postcode":"41907",
    "sg:province":"Sevilla",
    "wof:name":"De Paz Pavon Rocio",
    "wof:placetype":"venue"
},
  "geometry": {"coordinates":[-6.0776147842,37.4170455933],"type":"Point"}
}