{
  "type": "Feature",
  "properties": {
    "addr:full":"Carr Doctor Robert, 39 Albatarrec Lleida 25171",
    "addr:housenumber":"39",
    "addr:postcode":"25171",
    "addr:street":"Carr Doctor Robert",
    "iso:country":"ES",
    "sg:address":"Carr Doctor Robert, 39",
    "sg:city":"Albatarrec",
    "sg:orig_category":"Agencias Y Agentes Comerciales, Representantes",
    "sg:phone":"+34 973 72 00 40",
    "sg:postcode":"25171",
    "sg:province":"Lleida",
    "wof:name":"Pascual Carabasa Ramon",
    "wof:placetype":"venue"
},
  "geometry": {"coordinates":[0.605790019,41.5727729797],"type":"Point"}
}