{
  "type": "Feature",
  "properties": {
    "addr:full":"Hierro, 7 Loeches Madrid 28890",
    "addr:housenumber":"7",
    "addr:postcode":"28890",
    "addr:street":"Hierro",
    "iso:country":"ES",
    "sg:address":"Hierro, 7",
    "sg:city":"Loeches",
    "sg:orig_category":"Embalajes",
    "sg:phone":"+34 918 86 22 40",
    "sg:postcode":"28890",
    "sg:province":"Madrid",
    "wof:name":"Exclusivas Martinsa S.l.",
    "wof:placetype":"venue"
},
  "geometry": {"coordinates":[-3.4083790779,40.4027328491],"type":"Point"}
}