{
  "type": "Feature",
  "properties": {
    "addr:full":"Avda Buenos Aires, 14 Madrid Madrid 28038",
    "addr:housenumber":"14",
    "addr:postcode":"madrid;28038",
    "addr:street":"Avda Buenos Aires",
    "iso:country":"ES",
    "sg:address":"Avda Buenos Aires, 14",
    "sg:city":"Madrid",
    "sg:orig_category":"Molduras, Junquillos, Listones Y Molduras Perforadas",
    "sg:phone":"+34 917 78 54 15",
    "sg:postcode":"28038",
    "sg:province":"Madrid",
    "wof:name":"Meneses Esteban Julian",
    "wof:placetype":"venue"
},
  "geometry": {"coordinates":[-3.6535360813,40.3902664185],"type":"Point"}
}