{
  "type": "Feature",
  "properties": {
    "iso:country":"ES",
    "sg:address":"Calle de San Isidro, S/n",
    "sg:city":"Tarancon",
    "sg:orig_category":"Material Y Herramientas Agr\u00cdcolas",
    "sg:phone":"+34 969 32 14 43",
    "sg:postcode":"16400",
    "sg:province":"Cuenca",
    "wof:name":"Hermanos Lopez Cb.",
    "wof:placetype":"venue"
},
  "geometry": {"coordinates":[-3.0129139423,40.007484436],"type":"Point"}
}