{
  "type": "Feature",
  "properties": {
    "iso:country":"ES",
    "sg:address":"Carrer de Nord, 48",
    "sg:city":"Sabadell",
    "sg:orig_category":"Molduras, Junquillos, Listones Y Molduras Perforadas",
    "sg:phone":"+34 937 16 11 62",
    "sg:postcode":"08207",
    "sg:province":"Barcelona",
    "wof:name":"Gil Ruiz Jose",
    "wof:placetype":"venue"
},
  "geometry": {"coordinates":[2.0895659924,41.562877655],"type":"Point"}
}