{
  "type": "Feature",
  "properties": {
    "iso:country":"ES",
    "sg:address":"Calle de Literato Azorin, 29",
    "sg:city":"Valencia",
    "sg:orig_category":"Inversiones",
    "sg:phone":"+34 963 41 87 55",
    "sg:postcode":"46006",
    "sg:province":"Valencia",
    "wof:name":"Manussio Inversiones S.l.",
    "wof:placetype":"venue"
},
  "geometry": {"coordinates":[-0.3756949902,39.4596214294],"type":"Point"}
}