{
  "type": "Feature",
  "properties": {
    "iso:country":"ES",
    "sg:address":"Calle de Caracol, 27",
    "sg:city":"Marin",
    "sg:orig_category":"Molduras, Junquillos, Listones Y Molduras Perforadas",
    "sg:phone":"+34 986 88 37 01",
    "sg:postcode":"36900",
    "sg:province":"Pontevedra",
    "wof:name":"Lourido Amoedo Jose",
    "wof:placetype":"venue"
},
  "geometry": {"coordinates":[-8.7023582458,42.3928146362],"type":"Point"}
}