{
  "type": "Feature",
  "properties": {
    "addr:full":"Calle de Santa Ana, 1 Zamora Zamora 49006",
    "addr:housenumber":"1",
    "addr:postcode":"49006",
    "addr:street":"Calle De Santa Ana",
    "iso:country":"ES",
    "sg:address":"Calle de Santa Ana, 1",
    "sg:city":"Zamora",
    "sg:orig_category":"Electrodom\u00c9sticos (al Por Menor)",
    "sg:phone":"+34 980 53 02 73",
    "sg:postcode":"49006",
    "sg:province":"Zamora",
    "wof:name":"Ugidos Alvarez Emilia",
    "wof:placetype":"venue"
},
  "geometry": {"coordinates":[-5.7458190918,41.5076255798],"type":"Point"}
}