{
  "type": "Feature",
  "properties": {
    "iso:country":"ES",
    "sg:address":"Rua Bolivia, 3",
    "sg:city":"Vigo",
    "sg:orig_category":"Inform\u00c1tica, Ofim\u00c1tica (estudios, Asesor\u00cda, Ingenier\u00cda, Formaci\u00d3n)",
    "sg:phone":"+34 986 41 11 72",
    "sg:postcode":"36203",
    "sg:province":"Pontevedra",
    "wof:name":"Sistac-ils.s.l.",
    "wof:placetype":"venue"
},
  "geometry": {"coordinates":[-8.7207460403,42.2322845459],"type":"Point"}
}