{
  "type": "Feature",
  "properties": {
    "addr:full":"Avda Rodriguez Acosta, 1 Motril Granada 18600",
    "addr:housenumber":"1",
    "addr:postcode":"18600",
    "addr:street":"Avda Rodriguez Acosta",
    "iso:country":"ES",
    "sg:address":"Avda Rodriguez Acosta, 1",
    "sg:city":"Motril",
    "sg:orig_category":"Ingeniero",
    "sg:phone":"+34 958 82 15 84",
    "sg:postcode":"18600",
    "sg:province":"Granada",
    "wof:name":"Folk Madrid Francisco",
    "wof:placetype":"venue"
},
  "geometry": {"coordinates":[-3.5155479908,36.7438163757],"type":"Point"}
}