{
  "type": "Feature",
  "properties": {
    "iso:country":"ES",
    "sg:address":"Calle de Oto\u00d1o, 71",
    "sg:city":"Hoya Andrea",
    "sg:orig_category":"Chapa Y Pintura Veh\u00cdculos",
    "sg:phone":"+34 928 67 41 79",
    "sg:postcode":"35018",
    "sg:province":"Las Palmas",
    "wof:name":"Bruno Quintana Alfonso",
    "wof:placetype":"venue"
},
  "geometry": {"coordinates":[-15.4607715607,28.0883998871],"type":"Point"}
}