{
  "type": "Feature",
  "properties": {
    "iso:country":"ES",
    "sg:address":"Carrer de Beat Oriol, 1",
    "sg:city":"Mas Rampinyo",
    "sg:orig_category":"Fabricaci\u00d3n De Bibliotecas Y Estanter\u00cdas",
    "sg:phone":"+34 935 65 18 00",
    "sg:postcode":"08110",
    "sg:province":"Barcelona",
    "wof:name":"Sidac Iberia S. A.",
    "wof:placetype":"venue"
},
  "geometry": {"coordinates":[2.1811699867,41.491191864],"type":"Point"}
}