{
  "type": "Feature",
  "properties": {
    "iso:country":"ES",
    "sg:address":"Carr Riu Vinalopo, 36",
    "sg:city":"Pai I Capellans",
    "sg:orig_category":"Albergues",
    "sg:phone":"+34 961 92 05 35",
    "sg:postcode":"46930",
    "sg:province":"Valencia",
    "wof:name":"Contreras Sanchez Manuel",
    "wof:placetype":"venue"
},
  "geometry": {"coordinates":[-0.4419890046,39.482711792],"type":"Point"}
}