{
  "type": "Feature",
  "properties": {
    "addr:full":"Calle de Utrera, 62 Moron Frontera Sevilla 41530",
    "addr:housenumber":"62",
    "addr:postcode":"41530",
    "addr:street":"Calle De Utrera",
    "iso:country":"ES",
    "sg:address":"Calle de Utrera, 62",
    "sg:city":"Moron Frontera",
    "sg:orig_category":"Enfermeras: Consultas, Atenci\u00d3n A Domicilio",
    "sg:phone":"+34 954 85 04 79",
    "sg:postcode":"41530",
    "sg:province":"Sevilla",
    "wof:name":"Martinez Guzman Isidro",
    "wof:placetype":"venue"
},
  "geometry": {"coordinates":[-5.4586210251,37.1211776733],"type":"Point"}
}