{
  "type": "Feature",
  "properties": {
    "iso:country":"ES",
    "sg:address":"Rua Garrucha, 5",
    "sg:city":"Porto De Santa Cruz",
    "sg:orig_category":"Peluquer\u00cdas, Peluquer\u00cda Mixta",
    "sg:phone":"+34 981 61 47 86",
    "sg:postcode":"15179",
    "sg:province":"La Coru\u00f1a",
    "wof:name":"Barreiro Trillo Manuela",
    "wof:placetype":"venue"
},
  "geometry": {"coordinates":[-8.3427381516,43.3501701355],"type":"Point"}
}