{
  "type": "Feature",
  "properties": {
    "iso:country":"ES",
    "sg:address":"Ptda Cotes Baixes, 10",
    "sg:city":"Alcoi",
    "sg:orig_category":"Fabricaci\u00d3n De Telas Y Sedas",
    "sg:phone":"+34 965 52 40 61",
    "sg:postcode":"03804",
    "sg:province":"Alicante",
    "wof:name":"Olcina Borrell Jose",
    "wof:placetype":"venue"
},
  "geometry": {"coordinates":[-0.4650489986,38.712688446],"type":"Point"}
}