{
  "type": "Feature",
  "properties": {
    "iso:country":"ES",
    "sg:address":"Carr Constitucion, 1",
    "sg:city":"Manises",
    "sg:orig_category":"Cajas De Ahorro",
    "sg:phone":"+34 961 52 10 12",
    "sg:postcode":"46940",
    "sg:province":"Valencia",
    "wof:name":"Caja De Ahorros De Valencia Castellon Y Alicante",
    "wof:placetype":"venue"
},
  "geometry": {"coordinates":[-0.4521690011,39.4894752502],"type":"Point"}
}