{
  "type": "Feature",
  "properties": {
    "addr:full":"Avda Asturias De, 6 Longara Asturias 33750",
    "addr:postcode":"33750",
    "addr:street":"Avda Asturias De 6 Longara Asturias",
    "iso:country":"ES",
    "sg:address":"Avda Asturias De, 6",
    "sg:city":"Longara",
    "sg:orig_category":"Ingeniero",
    "sg:phone":"+34 985 63 77 84",
    "sg:postcode":"33750",
    "sg:province":"Asturias",
    "wof:name":"Medicion E Instrumentacion Solar S.l.",
    "wof:placetype":"venue"
},
  "geometry": {"coordinates":[-6.8270339966,43.5506744385],"type":"Point"}
}