{
  "type": "Feature",
  "properties": {
    "iso:country":"ES",
    "sg:address":"Av Diagonal, 536",
    "sg:city":"Barcelona",
    "sg:orig_category":"Abogados",
    "sg:phone":"+34 932 00 63 55",
    "sg:postcode":"08006",
    "sg:province":"Barcelona",
    "wof:name":"Llopis De Aysa Modesto",
    "wof:placetype":"venue"
},
  "geometry": {"coordinates":[2.1518990993,41.3949317932],"type":"Point"}
}