{
  "type": "Feature",
  "properties": {
    "addr:full":"Avgd Ausias March, 21 Burjassot Valencia 46100",
    "addr:housenumber":"21",
    "addr:postcode":"46100",
    "addr:street":"March",
    "iso:country":"ES",
    "sg:address":"Avgd Ausias March, 21",
    "sg:city":"Burjassot",
    "sg:orig_category":"Mercer\u00cda, Lencer\u00cda (al Por Menor)",
    "sg:phone":"+34 963 63 86 14",
    "sg:postcode":"46100",
    "sg:province":"Valencia",
    "wof:name":"Garcia Aguilar Emilio Andres",
    "wof:placetype":"venue"
},
  "geometry": {"coordinates":[-0.4113810956,39.5115318298],"type":"Point"}
}