{
  "type": "Feature",
  "properties": {
    "iso:country":"ES",
    "sg:address":"Pase Bertsol. Txirrita, 30",
    "sg:city":"Donostia-san Sebastian",
    "sg:orig_category":"Carnicer\u00cdas, Carnicer\u00cdas",
    "sg:phone":"+34 943 39 38 36",
    "sg:postcode":"20017",
    "sg:province":"Guip\u00f9zcoa",
    "wof:name":"Alastuey Mangas Jose Ignacio",
    "wof:placetype":"venue"
},
  "geometry": {"coordinates":[-1.9390360117,43.3156661987],"type":"Point"}
}