{
  "type": "Feature",
  "properties": {
    "iso:country":"ES",
    "sg:address":"Ctra San Martin De Valdeiglesias, Km. 0000,1",
    "sg:city":"Carretera De San Martin",
    "sg:orig_category":"Papel (al Por Mayor)",
    "sg:phone":"+34 916 12 69 01",
    "sg:postcode":"28925",
    "sg:province":"Madrid",
    "wof:name":"Marepa S.a.",
    "wof:placetype":"venue"
},
  "geometry": {"coordinates":[-3.8353390694,40.3956756592],"type":"Point"}
}