{
  "type": "Feature",
  "properties": {
    "iso:country":"ES",
    "sg:address":"Calle de Ermita, S/n",
    "sg:city":"Cretas",
    "sg:orig_category":"Molduras, Junquillos, Listones Y Molduras Perforadas",
    "sg:phone":"+34 978 89 02 57",
    "sg:postcode":"44623",
    "sg:province":"Teruel",
    "wof:name":"Lombarte Pique Jose",
    "wof:placetype":"venue"
},
  "geometry": {"coordinates":[0.2130679041,40.9291992188],"type":"Point"}
}