{
  "type": "Feature",
  "properties": {
    "addr:full":"Calle de Vazquez De Mella, 17 Oviedo Asturias 33012",
    "addr:housenumber":"17",
    "addr:postcode":"33012",
    "addr:street":"Calle De Vazquez De Mella",
    "iso:country":"ES",
    "sg:address":"Calle de Vazquez De Mella, 17",
    "sg:city":"Oviedo",
    "sg:orig_category":"Lencer\u00cda Femenina, Corseter\u00cda, Trajes De Ba\u00d1o (al Por Menor)",
    "sg:phone":"+34 985 24 32 99",
    "sg:postcode":"33012",
    "sg:province":"Asturias",
    "wof:name":"Suarez Garcia Rosa Maria",
    "wof:placetype":"venue"
},
  "geometry": {"coordinates":[-5.8621678352,43.3647003174],"type":"Point"}
}