{
  "type": "Feature",
  "properties": {
    "addr:full":"Calle de Tarragona, 3 Zaragoza Zaragoza 50005",
    "addr:housenumber":"3",
    "addr:postcode":"50005",
    "addr:street":"Calle De Tarragona",
    "iso:country":"ES",
    "sg:address":"Calle de Tarragona, 3",
    "sg:city":"Zaragoza",
    "sg:orig_category":"Agencias Y Agentes Comerciales, Representantes",
    "sg:phone":"+34 976 55 98 85",
    "sg:postcode":"50005",
    "sg:province":"Zaragoza",
    "wof:name":"Comercial Pedro Gabaldon S.l.",
    "wof:placetype":"venue"
},
  "geometry": {"coordinates":[-0.8957409859,41.6484146118],"type":"Point"}
}