{
  "type": "Feature",
  "properties": {
    "iso:country":"ES",
    "sg:address":"Ctra Sierra (de La), 2",
    "sg:city":"Granada",
    "sg:orig_category":"Venta, Instalaci\u00d3n De Calefacci\u00d3n",
    "sg:phone":"+34 958 22 34 43",
    "sg:postcode":"18008",
    "sg:province":"Granada",
    "wof:name":"Garcia Jimenez Antonio",
    "wof:placetype":"venue"
},
  "geometry": {"coordinates":[-3.5885810852,37.1674232483],"type":"Point"}
}