{
  "type": "Feature",
  "properties": {
    "addr:full":"Calle de Nuestra Se\u00d1ora De La Luz, 34 Madrid Madrid 28025",
    "addr:housenumber":"34",
    "addr:postcode":"madrid;28025",
    "addr:street":"Calle De Nuestra Sen\u0303Ora De La Luz",
    "iso:country":"ES",
    "sg:address":"Calle de Nuestra Se\u00d1ora De La Luz, 34",
    "sg:city":"Madrid",
    "sg:orig_category":"Molduras, Junquillos, Listones Y Molduras Perforadas",
    "sg:phone":"+34 914 61 42 85",
    "sg:postcode":"28025",
    "sg:province":"Madrid",
    "wof:name":"Valverde Gutierrez Norma",
    "wof:placetype":"venue"
},
  "geometry": {"coordinates":[-3.7443900108,40.3835716248],"type":"Point"}
}