{
  "type": "Feature",
  "properties": {
    "iso:country":"ES",
    "sg:address":"Calle de Araba Kalea, 1",
    "sg:city":"Amurrio",
    "sg:classifiers":[
        {
            "category":"Autos & Motor Vehicles",
            "subcategory":"Automobile Sales",
            "type":"Retail Goods"
        }
    ],
    "sg:phone":"+34 945 89 19 70",
    "sg:postcode":"01470",
    "sg:province":"\u00c1lava",
    "wof:name":"Auto Escuela Latatu Sl",
    "wof:placetype":"venue"
},
  "geometry": {"coordinates":[-2.999409914,43.0538520813],"type":"Point"}
}