{
  "type": "Feature",
  "properties": {
    "iso:country":"ES",
    "sg:address":"Avda. Finisterre, 18",
    "sg:city":"A Coru\u00f1a",
    "sg:orig_category":"Institutos De Belleza",
    "sg:phone":"+34 981 27 65 41",
    "sg:postcode":"15004",
    "sg:province":"La Coru\u00f1a",
    "wof:name":"Body Hair Total S.l.",
    "wof:placetype":"venue"
},
  "geometry": {"coordinates":[-8.4098453522,43.366733551],"type":"Point"}
}