{
  "type": "Feature",
  "properties": {
    "iso:country":"ES",
    "sg:address":"Calle de Formentera, 23",
    "sg:city":"Gelves",
    "sg:orig_category":"Industrias Aeron\u00c1uticas Y Espaciales",
    "sg:phone":"+34 955 76 20 40",
    "sg:postcode":"41120",
    "sg:province":"Sevilla",
    "wof:name":"Repaso Aeronautico S.l.",
    "wof:placetype":"venue"
},
  "geometry": {"coordinates":[-6.0286512375,37.3293037415],"type":"Point"}
}