{
  "type": "Feature",
  "properties": {
    "addr:full":"Ctra. De Chimeneas, S/n Lachar Granada 18327",
    "addr:housenumber":"s / n",
    "addr:postcode":"18327",
    "addr:street":"Ctra. De Chimeneas",
    "iso:country":"ES",
    "sg:address":"Ctra. De Chimeneas, S/n",
    "sg:city":"Lachar",
    "sg:orig_category":"Cooperativas Agr\u00cdcolas",
    "sg:phone":"+34 958 45 74 32",
    "sg:postcode":"18327",
    "sg:province":"Granada",
    "wof:name":"Agrolachar Sociedad Cooperativa Andaluza",
    "wof:placetype":"venue"
},
  "geometry": {"coordinates":[-3.8300068378,37.1827735901],"type":"Point"}
}