{
  "type": "Feature",
  "properties": {
    "addr:full":"Calle de Obispo Pozuelo, 35 Pozoblanco C\u00f3rdoba 14400",
    "addr:housenumber":"35",
    "addr:postcode":"14400",
    "addr:street":"Calle De Obispo Pozuelo",
    "iso:country":"ES",
    "sg:address":"Calle de Obispo Pozuelo, 35",
    "sg:city":"Pozoblanco",
    "sg:orig_category":"Empresas De Pintura Y Revestimientos",
    "sg:phone":"+34 957 13 14 29",
    "sg:postcode":"14400",
    "sg:province":"C\u00f3rdoba",
    "wof:name":"Espejo Fernandez Juan",
    "wof:placetype":"venue"
},
  "geometry": {"coordinates":[-4.8432002068,38.3807067871],"type":"Point"}
}