{
  "type": "Feature",
  "properties": {
    "iso:country":"ES",
    "sg:address":"Calle de Rafael Finat, 40",
    "sg:city":"Madrid",
    "sg:classifiers":[
        {
            "category":"Autos & Motor Vehicles",
            "subcategory":"Automobile Sales",
            "type":"Retail Goods"
        }
    ],
    "sg:phone":"+34 917 06 63 04",
    "sg:postcode":"28044",
    "sg:province":"Madrid",
    "wof:name":"Yin  Biping",
    "wof:placetype":"venue"
},
  "geometry": {"coordinates":[-3.7682843208,40.3807220459],"type":"Point"}
}