{
  "type": "Feature",
  "properties": {
    "iso:country":"ES",
    "sg:address":"Pg Maritim, 10",
    "sg:city":"Castelldefels",
    "sg:orig_category":"Asesor\u00cda Sobre Comunicaci\u00d3n De Empresas",
    "sg:phone":"+34 936 65 70 97",
    "sg:postcode":"08860",
    "sg:province":"Barcelona",
    "sg:website":"www.asesoriagarcialopez.es",
    "wof:name":"Asesoria Garcia Lopez S L..",
    "wof:placetype":"venue"
},
  "geometry": {"coordinates":[1.9991849661,41.2655067444],"type":"Point"}
}