{
  "type": "Feature",
  "properties": {
    "iso:country":"ES",
    "sg:address":"Plaz Canovas Del Castillo, 9",
    "sg:city":"Valdemoro",
    "sg:orig_category":"Agencias De Viajes",
    "sg:phone":"+34 918 95 50 12",
    "sg:postcode":"28340",
    "sg:province":"Madrid",
    "wof:name":"Viajes B.t.c. S.l.",
    "wof:placetype":"venue"
},
  "geometry": {"coordinates":[-3.6796400547,40.1906929016],"type":"Point"}
}