{
  "type": "Feature",
  "properties": {
    "iso:country":"ES",
    "sg:address":"Carrer de Trafalgar, 53",
    "sg:city":"Barcelona",
    "sg:orig_category":"Ropa Para Se\u00d1oras Y Caballeros (al Por Menor)",
    "sg:phone":"+34 932 68 41 93",
    "sg:postcode":"08010",
    "sg:province":"Barcelona",
    "wof:name":"Lisa's Clothes S.l.",
    "wof:placetype":"venue"
},
  "geometry": {"coordinates":[2.178716898,41.3907661438],"type":"Point"}
}