{
  "type": "Feature",
  "properties": {
    "iso:country":"ES",
    "sg:address":"Carrer de Gran, 52",
    "sg:city":"Esparreguera",
    "sg:orig_category":"Panader\u00cdas, Panader\u00cdas",
    "sg:phone":"+34 937 77 29 52",
    "sg:postcode":"08292",
    "sg:province":"Barcelona",
    "wof:name":"Mach Castells Fernando",
    "wof:placetype":"venue"
},
  "geometry": {"coordinates":[1.8689899445,41.5402984619],"type":"Point"}
}