{
  "type": "Feature",
  "properties": {
    "iso:country":"ES",
    "sg:address":"Rua Cami\u00d1o Real (do), 64",
    "sg:city":"Lugo",
    "sg:orig_category":"Peluqueros: De Se\u00d1oras",
    "sg:phone":"+34 982 25 05 45",
    "sg:postcode":"27004",
    "sg:province":"Lugo",
    "wof:name":"Vazquez Perez Maria Del Carmen",
    "wof:placetype":"venue"
},
  "geometry": {"coordinates":[-7.5625591278,43.0165786743],"type":"Point"}
}