{
  "type": "Feature",
  "properties": {
    "iso:country":"ES",
    "sg:address":"Calle de General Sanz Pastor, 7",
    "sg:city":"Burgos",
    "sg:orig_category":"Retoques De Vestidos",
    "sg:phone":"+34 947 20 78 82",
    "sg:postcode":"09003",
    "sg:province":"Burgos",
    "sg:website":"www.retoucherie.com",
    "wof:name":"La Retoucherie De Burgos Sc",
    "wof:placetype":"venue"
},
  "geometry": {"coordinates":[-3.6994450092,42.3441886902],"type":"Point"}
}