{
  "type": "Feature",
  "properties": {
    "addr:full":"Calle de Arroyo Del Olivar, 99 Madrid Madrid 28018",
    "addr:housenumber":"99",
    "addr:postcode":"madrid;28018",
    "addr:street":"Calle De Arroyo Del Olivar",
    "iso:country":"ES",
    "sg:address":"Calle de Arroyo Del Olivar, 99",
    "sg:city":"Madrid",
    "sg:orig_category":"Inmobiliaria (agencias)",
    "sg:phone":"+34 913 80 43 00",
    "sg:postcode":"28018",
    "sg:province":"Madrid",
    "wof:name":"Agencia De Servicios Inmobiliarios Y Juridicos Vallecas S.l.",
    "wof:placetype":"venue"
},
  "geometry": {"coordinates":[-3.6490147114,40.3877868652],"type":"Point"}
}