{
  "type": "Feature",
  "properties": {
    "iso:country":"ES",
    "sg:address":"Carrer de Industria, 98",
    "sg:city":"Barcelona",
    "sg:orig_category":"Mec\u00c1nico Del Autom\u00d3vil",
    "sg:phone":"+34 934 55 46 24",
    "sg:postcode":"08025",
    "sg:province":"Barcelona",
    "wof:name":"Rodes Sanchez Pedro",
    "wof:placetype":"venue"
},
  "geometry": {"coordinates":[2.170924902,41.4067420959],"type":"Point"}
}