{
  "type": "Feature",
  "properties": {
    "addr:full":"Calle de Cueva De Montesinos, 3 Madrid Madrid 28034",
    "addr:housenumber":"3",
    "addr:postcode":"28034",
    "addr:street":"Calle De Cueva De Montesinos",
    "iso:country":"ES",
    "sg:address":"Calle de Cueva De Montesinos, 3",
    "sg:city":"Madrid",
    "sg:orig_category":"Inmobiliaria (agencias)",
    "sg:phone":"+34 917 35 37 11",
    "sg:postcode":"28034",
    "sg:province":"Madrid",
    "wof:name":"Gallego Alonso Emilio",
    "wof:placetype":"venue"
},
  "geometry": {"coordinates":[-3.688149929,40.5005302429],"type":"Point"}
}