{
  "type": "Feature",
  "properties": {
    "iso:country":"ES",
    "sg:address":"Calle de Alzina, 15",
    "sg:city":"Madrid",
    "sg:orig_category":"Empresas De Carpinter\u00cda Met\u00c1lica",
    "sg:phone":"+34 915 08 63 86",
    "sg:postcode":"28044",
    "sg:province":"Madrid",
    "wof:name":"Cornejo Blazquez Felix",
    "wof:placetype":"venue"
},
  "geometry": {"coordinates":[-3.7564973831,40.3678016663],"type":"Point"}
}