{
  "type": "Feature",
  "properties": {
    "addr:full":"Calle de Juan Rico, 2 Lucena C\u00f3rdoba 14900",
    "addr:housenumber":"2",
    "addr:postcode":"14900",
    "addr:street":"Calle De Juan Rico",
    "iso:country":"ES",
    "sg:address":"Calle de Juan Rico, 2",
    "sg:city":"Lucena",
    "sg:orig_category":"Colchones (fabricaci\u00d3n, Al Por Mayor, Al Por Menor)",
    "sg:phone":"+34 957 50 15 38",
    "sg:postcode":"14900",
    "sg:province":"C\u00f3rdoba",
    "wof:name":"Arcos Onieva Carmen",
    "wof:placetype":"venue"
},
  "geometry": {"coordinates":[-4.4832134247,37.4084854126],"type":"Point"}
}