{
  "type": "Feature",
  "properties": {
    "iso:country":"ES",
    "sg:address":"Pl Olimpia, 16",
    "sg:city":"Sabadell",
    "sg:orig_category":"Peluquer\u00cdas, Peluquer\u00cda Mixta",
    "sg:phone":"+34 937 23 46 15",
    "sg:postcode":"08206",
    "sg:province":"Barcelona",
    "wof:name":"Torvisco Larios Maite",
    "wof:placetype":"venue"
},
  "geometry": {"coordinates":[2.0908548832,41.5547523499],"type":"Point"}
}