{
  "type": "Feature",
  "properties": {
    "iso:country":"ES",
    "sg:address":"Calle de Camara La, 26",
    "sg:city":"Aviles",
    "sg:orig_category":"Abogados",
    "sg:phone":"+34 985 56 66 47",
    "sg:postcode":"33402",
    "sg:province":"Asturias",
    "wof:name":"Fernandez Suarez Manuel David",
    "wof:placetype":"venue"
},
  "geometry": {"coordinates":[-5.9235191345,43.5565185547],"type":"Point"}
}