{
  "type": "Feature",
  "properties": {
    "iso:country":"ES",
    "sg:address":"Carr Peix, S/n",
    "sg:city":"Muro",
    "sg:orig_category":"Cobro De Pr\u00c9stamos",
    "sg:phone":"+34 971 86 05 19",
    "sg:postcode":"07440",
    "sg:province":"Islas Baleares",
    "wof:name":"Alzamora Torres Gabriel Maria",
    "wof:placetype":"venue"
},
  "geometry": {"coordinates":[3.0527818203,39.730670929],"type":"Point"}
}