{
  "type": "Feature",
  "properties": {
    "iso:country":"ES",
    "sg:address":"Avda Pries, 7",
    "sg:city":"Malaga",
    "sg:orig_category":"Bisuter\u00cda, Joyer\u00cda, Relojer\u00cda (al Por Menor)",
    "sg:phone":"+34 952 22 72 41",
    "sg:postcode":"29016",
    "sg:province":"M\u00e1laga",
    "wof:name":"Joyeria Hago Sl",
    "wof:placetype":"venue"
},
  "geometry": {"coordinates":[-4.4066362381,36.7213058472],"type":"Point"}
}