{
  "type": "Feature",
  "properties": {
    "iso:country":"ES",
    "sg:address":"Calle de Mesones, 16",
    "sg:city":"Herencia",
    "sg:orig_category":"Muebles, Minoristas",
    "sg:phone":"+34 926 57 36 65",
    "sg:postcode":"13640",
    "sg:province":"Ciudad Real",
    "wof:name":"Portillo Villarreal Yolanda",
    "wof:placetype":"venue"
},
  "geometry": {"coordinates":[-3.3539299965,39.3672790527],"type":"Point"}
}