{
  "type": "Feature",
  "properties": {
    "addr:full":"Calle de Torre De Don Miguel, 29 Madrid Madrid 28031",
    "addr:housenumber":"29",
    "addr:postcode":"madrid;28031",
    "addr:street":"Calle De Torre;Miguel",
    "iso:country":"ES",
    "sg:address":"Calle de Torre De Don Miguel, 29",
    "sg:city":"Madrid",
    "sg:orig_category":"Charcuter\u00cdas (al Por Mayor)",
    "sg:phone":"+34 913 80 42 96",
    "sg:postcode":"28031",
    "sg:province":"Madrid",
    "wof:name":"Presa Y Calvete S. A.",
    "wof:placetype":"venue"
},
  "geometry": {"coordinates":[-3.7057740688,40.42029953],"type":"Point"}
}