{
  "type": "Feature",
  "properties": {
    "iso:country":"ES",
    "sg:address":"Calle de Alazan, 36",
    "sg:city":"Badajoz",
    "sg:orig_category":"Electricidad: Instaladores",
    "sg:phone":"+34 924 25 58 85",
    "sg:postcode":"06008",
    "sg:province":"Badajoz",
    "wof:name":"Incoex S.l.",
    "wof:placetype":"venue"
},
  "geometry": {"coordinates":[-6.9536647797,38.8796730042],"type":"Point"}
}