{
  "type": "Feature",
  "properties": {
    "addr:full":"Calle de Sopranis, 21 Cadiz C\u00e1diz 11006",
    "addr:housenumber":"21",
    "addr:postcode":"11006",
    "addr:street":"Calle De Sopranis",
    "iso:country":"ES",
    "sg:address":"Calle de Sopranis, 21",
    "sg:city":"Cadiz",
    "sg:orig_category":"Moda",
    "sg:phone":"+34 956 25 83 98",
    "sg:postcode":"11006",
    "sg:province":"C\u00e1diz",
    "wof:name":"Perez Andria Amalia",
    "wof:placetype":"venue"
},
  "geometry": {"coordinates":[-6.2909841537,36.5288696289],"type":"Point"}
}