{
  "type": "Feature",
  "properties": {
    "iso:country":"ES",
    "sg:address":"Calle de Mayor, 60",
    "sg:city":"Alca\u00f1iz",
    "sg:orig_category":"Carnicer\u00cdas, Carnicer\u00cdas",
    "sg:phone":"+34 978 83 08 03",
    "sg:postcode":"44600",
    "sg:province":"Teruel",
    "wof:name":"Casanova Pastor Jaime",
    "wof:placetype":"venue"
},
  "geometry": {"coordinates":[-0.135134995,41.0515403748],"type":"Point"}
}