{
  "type": "Feature",
  "properties": {
    "iso:country":"ES",
    "sg:address":"Calle de Hercules, 26",
    "sg:city":"Alacant",
    "sg:orig_category":"Mec\u00c1nico Del Autom\u00d3vil",
    "sg:phone":"+34 965 28 19 13",
    "sg:postcode":"03006",
    "sg:province":"Alicante",
    "wof:name":"Gimenez \u00d1iguez Angel",
    "wof:placetype":"venue"
},
  "geometry": {"coordinates":[-0.5113959908,38.347114563],"type":"Point"}
}