{
  "type": "Feature",
  "properties": {
    "addr:full":"Calle de Antonia Maria De Oviedo, 12 Alaquas Valencia 46970",
    "addr:housenumber":"12",
    "addr:postcode":"46970",
    "addr:street":"Calle De Antonia Maria De Oviedo",
    "iso:country":"ES",
    "sg:address":"Calle de Antonia Maria De Oviedo, 12",
    "sg:city":"Alaquas",
    "sg:orig_category":"Administradores De Bienes Y Delegados De Comunidades De Propietarios",
    "sg:phone":"+34 961 51 72 40",
    "sg:postcode":"46970",
    "sg:province":"Valencia",
    "wof:name":"Beta Aparicio Ana Maria",
    "wof:placetype":"venue"
},
  "geometry": {"coordinates":[-0.4617840052,39.4563064575],"type":"Point"}
}