{
  "type": "Feature",
  "properties": {
    "iso:country":"ES",
    "sg:address":"Centro Comercial Orotava, 10",
    "sg:city":"La Orotava",
    "sg:orig_category":"Comercio De Piezas De Recambio Y De Accesorios De Veh\u00cdculos, Veh\u00cdculos Industriales",
    "sg:phone":"+34 922 32 80 70",
    "sg:postcode":"38312",
    "sg:province":"Santa Cruz De Tenerife",
    "wof:name":"Neumaticos El Val S.l.",
    "wof:placetype":"venue"
},
  "geometry": {"coordinates":[-16.5512580872,28.3783855438],"type":"Point"}
}