{
  "type": "Feature",
  "properties": {
    "addr:full":"Carrer de Antoni De Bofarull, S/n Reus Tarragona 43243",
    "addr:housenumber":"s / n",
    "addr:postcode":"43243",
    "addr:street":"Carrer De Antoni De Bofarull",
    "iso:country":"ES",
    "sg:address":"Carrer de Antoni De Bofarull, S/n",
    "sg:city":"Reus",
    "sg:orig_category":"Molduras, Junquillos, Listones Y Molduras Perforadas",
    "sg:phone":"+34 977 31 51 67",
    "sg:postcode":"43243",
    "sg:province":"Tarragona",
    "wof:name":"Redondo Gil Antonio",
    "wof:placetype":"venue"
},
  "geometry": {"coordinates":[1.1019300222,41.1497840881],"type":"Point"}
}