{
  "type": "Feature",
  "properties": {
    "iso:country":"ES",
    "sg:address":"Carrer de Font De L'avellaner, S/n",
    "sg:city":"Vilafranca Penedes",
    "sg:orig_category":"Torrefactado De Caf\u00c9",
    "sg:phone":"+34 938 90 12 11",
    "sg:postcode":"08720",
    "sg:province":"Barcelona",
    "sg:website":"www.cafesnovell.es",
    "wof:name":"Cafes Novell S.a.",
    "wof:placetype":"venue"
},
  "geometry": {"coordinates":[1.6817899942,41.3305664062],"type":"Point"}
}