{
  "type": "Feature",
  "properties": {
    "iso:country":"ES",
    "sg:address":"Calle de Santa Maria De La Cabeza, 5",
    "sg:city":"Majadahonda",
    "sg:orig_category":"Carnicer\u00cdas, Carnicer\u00cdas",
    "sg:phone":"+34 916 38 65 46",
    "sg:postcode":"28220",
    "sg:province":"Madrid",
    "wof:name":"Martin Aller Santiago",
    "wof:placetype":"venue"
},
  "geometry": {"coordinates":[-3.870898962,40.4732933044],"type":"Point"}
}