{
  "type": "Feature",
  "properties": {
    "addr:full":"Calle de Sorbas, 14 Carboneras Almer\u00eda 04140",
    "addr:housenumber":"14",
    "addr:postcode":"04140",
    "addr:street":"Calle De Sorbas",
    "iso:country":"ES",
    "sg:address":"Calle de Sorbas, 14",
    "sg:city":"Carboneras",
    "sg:orig_category":"Cajas De Ahorro",
    "sg:phone":"+34 950 45 48 77",
    "sg:postcode":"04140",
    "sg:province":"Almer\u00eda",
    "sg:website":"www.lacaixa.es",
    "wof:name":"Caixa D'estalvis I Pensions De Barcelona",
    "wof:placetype":"venue"
},
  "geometry": {"coordinates":[-1.8937710524,36.9974975586],"type":"Point"}
}