{
  "type": "Feature",
  "properties": {
    "iso:country":"ES",
    "sg:address":"Calle de Virgen De Las Angustias, 18",
    "sg:city":"Avila",
    "sg:orig_category":"Carnicer\u00cdas, Carnicer\u00cdas",
    "sg:phone":"+34 920 22 13 39",
    "sg:postcode":"05005",
    "sg:province":"\u00c1vila",
    "wof:name":"Blazquez Perez Jose Luis",
    "wof:placetype":"venue"
},
  "geometry": {"coordinates":[-4.6906890869,40.6604690552],"type":"Point"}
}