{
  "type": "Feature",
  "properties": {
    "addr:full":"Cno La Granja, S/n Xativa Valencia 46800",
    "addr:housenumber":"s",
    "addr:postcode":"46800",
    "addr:street":"Cno La Granja;/ N",
    "iso:country":"ES",
    "sg:address":"Cno La Granja, S/n",
    "sg:city":"Xativa",
    "sg:orig_category":"Ferreter\u00cda (diversos)",
    "sg:phone":"+34 962 27 06 11",
    "sg:postcode":"46800",
    "sg:province":"Valencia",
    "sg:website":"www.horprese.com",
    "wof:name":"Horprese S. L.",
    "wof:placetype":"venue"
},
  "geometry": {"coordinates":[-0.5285540223,38.9876708984],"type":"Point"}
}