{
  "type": "Feature",
  "properties": {
    "addr:full":"Avda Tunte (de), 35 San Fernando Las Palmas 35100",
    "addr:housenumber":"35",
    "addr:postcode":"35100",
    "addr:street":"Avda Tunte De",
    "iso:country":"ES",
    "sg:address":"Avda Tunte (de), 35",
    "sg:city":"San Fernando",
    "sg:orig_category":"Electricidad, Electr\u00d3nica: Suministros (al Por Menor)",
    "sg:phone":"+34 928 76 26 37",
    "sg:postcode":"35100",
    "sg:province":"Las Palmas",
    "wof:name":"Gurnani  Manoj",
    "wof:placetype":"venue"
},
  "geometry": {"coordinates":[-15.5837392807,28.090631485],"type":"Point"}
}