{
  "type": "Feature",
  "properties": {
    "addr:full":"Carrer de Olivera, 42 Barcelona Barcelona 08004",
    "addr:housenumber":"42",
    "addr:postcode":"08004",
    "addr:street":"Carrer De Olivera",
    "iso:country":"ES",
    "sg:address":"Carrer de Olivera, 42",
    "sg:city":"Barcelona",
    "sg:orig_category":"Papeler\u00cdas, Librer\u00cdas",
    "sg:phone":"+34 934 26 37 18",
    "sg:postcode":"08004",
    "sg:province":"Barcelona",
    "wof:name":"Perez Galdon Rosa",
    "wof:placetype":"venue"
},
  "geometry": {"coordinates":[2.1573410034,41.3737831116],"type":"Point"}
}