{
  "type": "Feature",
  "properties": {
    "addr:full":"Carrer de Major (sant Celoni), 119 S. Celoni Barcelona 08470",
    "addr:housenumber":"119",
    "addr:postcode":"08470",
    "addr:street":"Carrer De Major Sant Celoni;S. Celoni Barcelona",
    "iso:country":"ES",
    "sg:address":"Carrer de Major (sant Celoni), 119",
    "sg:city":"S. Celoni",
    "sg:orig_category":"Lencer\u00cda Femenina, Corseter\u00cda, Trajes De Ba\u00d1o (al Por Menor)",
    "sg:phone":"+34 938 67 00 42",
    "sg:postcode":"08470",
    "sg:province":"Barcelona",
    "wof:name":"Renau Bruguera Josefa",
    "wof:placetype":"venue"
},
  "geometry": {"coordinates":[2.4913659096,41.6899414062],"type":"Point"}
}