{
  "type": "Feature",
  "properties": {
    "addr:full":"Calle de Francisco Javier De Moya, 6 Albacete Albacete 02006",
    "addr:housenumber":"6",
    "addr:postcode":"02006",
    "addr:street":"Calle De Francisco Javier De Moya",
    "iso:country":"ES",
    "sg:address":"Calle de Francisco Javier De Moya, 6",
    "sg:city":"Albacete",
    "sg:orig_category":"Fabrica De Cer\u00c1micas",
    "sg:phone":"+34 967 19 30 06",
    "sg:postcode":"02006",
    "sg:province":"Albacete",
    "wof:name":"Cooperativa Nuestra Se\u00f1ora De Las Nieves",
    "wof:placetype":"venue"
},
  "geometry": {"coordinates":[-1.8444540501,38.9866027832],"type":"Point"}
}