{
  "type": "Feature",
  "properties": {
    "iso:country":"ES",
    "sg:address":"Calle de Villalba Hervas, 6",
    "sg:city":"Santa Cruz De Tenerife",
    "sg:orig_category":"Abogados",
    "sg:phone":"+34 922 24 22 76",
    "sg:postcode":"38002",
    "sg:province":"Santa Cruz De Tenerife",
    "wof:name":"Medina Hernandez Orlando",
    "wof:placetype":"venue"
},
  "geometry": {"coordinates":[-16.2485923767,28.4676647186],"type":"Point"}
}