{
  "type": "Feature",
  "properties": {
    "addr:full":"Calle de Iglesia, S/n Benameji C\u00f3rdoba 14910",
    "addr:housenumber":"s / n",
    "addr:postcode":"14910",
    "addr:street":"Calle De Iglesia;Co\u0301Rdoba",
    "iso:country":"ES",
    "sg:address":"Calle de Iglesia, S/n",
    "sg:city":"Benameji",
    "sg:orig_category":"Caf\u00c9s, Bares, Cervecer\u00cdas",
    "sg:phone":"+34 957 53 04 07",
    "sg:postcode":"14910",
    "sg:province":"C\u00f3rdoba",
    "wof:name":"Macrotelefonia Division Andalucia S.l.",
    "wof:placetype":"venue"
},
  "geometry": {"coordinates":[-4.5409641266,37.2671546936],"type":"Point"}
}