{
  "type": "Feature",
  "properties": {
    "addr:full":"Avda Barcelona (de), 22 Granada Granada 18006",
    "addr:housenumber":"22",
    "addr:postcode":"18006",
    "addr:street":"Avda Barcelona De",
    "iso:country":"ES",
    "sg:address":"Avda Barcelona (de), 22",
    "sg:city":"Granada",
    "sg:orig_category":"Cl\u00cdnicas Dentales",
    "sg:phone":"+34 958 13 35 92",
    "sg:postcode":"18006",
    "sg:province":"Granada",
    "wof:name":"Montes Lopez Pablo David",
    "wof:placetype":"venue"
},
  "geometry": {"coordinates":[-3.6005549431,37.1604270935],"type":"Point"}
}