{
  "type": "Feature",
  "properties": {
    "addr:full":"Jose Hernandez, 27 Espinardo Murcia 30100",
    "addr:housenumber":"27",
    "addr:postcode":"30100",
    "addr:street":"Jose Hernandez",
    "iso:country":"ES",
    "sg:address":"Jose Hernandez, 27",
    "sg:city":"Espinardo",
    "sg:orig_category":"Empresas De Empaquetado, Embalajes Por Encargo",
    "sg:phone":"+34 968 30 72 64",
    "sg:postcode":"30100",
    "sg:province":"Murcia",
    "wof:name":"Gaspar Y Nortes S.l.",
    "wof:placetype":"venue"
},
  "geometry": {"coordinates":[-1.1514359713,38.0098342896],"type":"Point"}
}