{
  "type": "Feature",
  "properties": {
    "iso:country":"ES",
    "sg:address":"Ptda Calvet, 49",
    "sg:city":"Alboraya",
    "sg:orig_category":"Clubes, Asociaciones De Ocio",
    "sg:phone":"+34 961 85 04 64",
    "sg:postcode":"46120",
    "sg:province":"Valencia",
    "wof:name":"Perez Richart Juan Carlos",
    "wof:placetype":"venue"
},
  "geometry": {"coordinates":[-0.3405140042,39.4990692139],"type":"Point"}
}