{
  "type": "Feature",
  "properties": {
    "iso:country":"ES",
    "sg:address":"Calle de Canalejas, S/n",
    "sg:city":"Santa Cruz De Mudela",
    "sg:orig_category":"F\u00c1bricas De Ladrillo Y Tejas",
    "sg:phone":"+34 926 34 21 66",
    "sg:postcode":"13730",
    "sg:province":"Ciudad Real",
    "wof:name":"Ceramicas Valera S.a.",
    "wof:placetype":"venue"
},
  "geometry": {"coordinates":[-3.4577264786,38.6422119141],"type":"Point"}
}