{
  "type": "Feature",
  "properties": {
    "addr:full":"Calle de Severo Ochoa, 7 Arrigorriaga Vizcaya 48480",
    "addr:housenumber":"7",
    "addr:postcode":"48480",
    "addr:street":"Calle De Severo Ochoa",
    "iso:country":"ES",
    "sg:address":"Calle de Severo Ochoa, 7",
    "sg:city":"Arrigorriaga",
    "sg:orig_category":"Panader\u00cdas, Panader\u00cdas",
    "sg:phone":"+34 946 71 31 67",
    "sg:postcode":"48480",
    "sg:province":"Vizcaya",
    "wof:name":"Rey Santamaria Marimar",
    "wof:placetype":"venue"
},
  "geometry": {"coordinates":[-2.8863019943,43.2090911865],"type":"Point"}
}