{
  "type": "Feature",
  "properties": {
    "addr:full":"Carrer de Sant Antoni De Padua, 13 Pego Alicante 03780",
    "addr:housenumber":"13",
    "addr:postcode":"03780",
    "addr:street":"Carrer De Sant",
    "iso:country":"ES",
    "sg:address":"Carrer de Sant Antoni De Padua, 13",
    "sg:city":"Pego",
    "sg:orig_category":"Quincaller\u00cda (al Por Menor)",
    "sg:phone":"+34 965 57 27 93",
    "sg:postcode":"03780",
    "sg:province":"Alicante",
    "wof:name":"Ferreteria Bolufer S.l.",
    "wof:placetype":"venue"
},
  "geometry": {"coordinates":[-0.1174530014,38.8411102295],"type":"Point"}
}