{
  "type": "Feature",
  "properties": {
    "addr:full":"Carrer de Verge De Montserrat, 8 Cornella Llobregat Barcelona 08940",
    "addr:housenumber":"8",
    "addr:postcode":"08940",
    "addr:street":"Carrer De Verge De Montserrat",
    "iso:country":"ES",
    "sg:address":"Carrer de Verge De Montserrat, 8",
    "sg:city":"Cornella Llobregat",
    "sg:orig_category":"Caf\u00c9s, Bares, Cervecer\u00cdas",
    "sg:phone":"+34 933 77 42 05",
    "sg:postcode":"08940",
    "sg:province":"Barcelona",
    "wof:name":"D&l Coffee S.c.p.",
    "wof:placetype":"venue"
},
  "geometry": {"coordinates":[2.0706520081,41.3523254395],"type":"Point"}
}