{
  "type": "Feature",
  "properties": {
    "addr:full":"Calle de General Mola, 17 Carmena Toledo 45531",
    "addr:housenumber":"17",
    "addr:postcode":"45531",
    "addr:street":"Calle De General Mola",
    "iso:country":"ES",
    "sg:address":"Calle de General Mola, 17",
    "sg:city":"Carmena",
    "sg:orig_category":"Cajas Para Embalar",
    "sg:phone":"+34 925 74 21 88",
    "sg:postcode":"45531",
    "sg:province":"Toledo",
    "wof:name":"Caja Rural Provincial De Toledo",
    "wof:placetype":"venue"
},
  "geometry": {"coordinates":[-4.4035830498,39.9570198059],"type":"Point"}
}