{
  "type": "Feature",
  "properties": {
    "addr:full":"Calle de Cefiro, 21 Antilla Huelva 21449",
    "addr:housenumber":"21",
    "addr:postcode":"21449",
    "addr:street":"Calle De Cefiro",
    "iso:country":"ES",
    "sg:address":"Calle de Cefiro, 21",
    "sg:city":"Antilla",
    "sg:orig_category":"Centros De Educaci\u00d3n Especial",
    "sg:phone":"+34 959 48 14 58",
    "sg:postcode":"21449",
    "sg:province":"Huelva",
    "wof:name":"Ayuntamiento De Lepe",
    "wof:placetype":"venue"
},
  "geometry": {"coordinates":[-7.2231168747,37.2050170898],"type":"Point"}
}