{
  "type": "Feature",
  "properties": {
    "iso:country":"ES",
    "sg:address":"Avda Hispanidad, S/n",
    "sg:city":"Santa Fe",
    "sg:orig_category":"\u00d3ptica: Instrumentos (fabricaci\u00d3n)",
    "sg:phone":"+34 958 44 11 01",
    "sg:postcode":"18320",
    "sg:province":"Granada",
    "wof:name":"Cabrera Aguilera Maria Luisa",
    "wof:placetype":"venue"
},
  "geometry": {"coordinates":[-3.7110390663,37.1915512085],"type":"Point"}
}