{
  "type": "Feature",
  "properties": {
    "iso:country":"ES",
    "sg:address":"Calle de Sierra De Cadi, 10",
    "sg:city":"Madrid",
    "sg:orig_category":"Cervecer\u00cdas",
    "sg:phone":"+34 914 77 21 95",
    "sg:postcode":"28018",
    "sg:province":"Madrid",
    "wof:name":"Tejados Javier Deyanira Del Carmen 000785393x S.l.n.e.",
    "wof:placetype":"venue"
},
  "geometry": {"coordinates":[-3.6609649658,40.3926010132],"type":"Point"}
}