{
  "type": "Feature",
  "properties": {
    "iso:country":"ES",
    "sg:address":"Carrer de Sant Pere, 59",
    "sg:city":"Terrassa",
    "sg:orig_category":"Librer\u00cdas",
    "sg:phone":"+34 937 88 53 23",
    "sg:postcode":"08221",
    "sg:province":"Barcelona",
    "wof:name":"Gorina Casas Luis",
    "wof:placetype":"venue"
},
  "geometry": {"coordinates":[2.0120000839,41.5643386841],"type":"Point"}
}