{
  "type": "Feature",
  "properties": {
    "addr:full":"Carr Coll I Pujol, 90 Badalona Barcelona 08912",
    "addr:housenumber":"90",
    "addr:postcode":"08912",
    "addr:street":"Carr Coll I Pujol",
    "iso:country":"ES",
    "sg:address":"Carr Coll I Pujol, 90",
    "sg:city":"Badalona",
    "sg:orig_category":"Cajas Y Embalajes Met\u00c1licos",
    "sg:phone":"+34 902 40 05 38",
    "sg:postcode":"08912",
    "sg:province":"Barcelona",
    "sg:website":"www.llamas.big",
    "wof:name":"Llamas S.l.",
    "wof:placetype":"venue"
},
  "geometry": {"coordinates":[2.2450649738,41.4503440857],"type":"Point"}
}