{
  "type": "Feature",
  "properties": {
    "addr:full":"Avda Juan Carlos I, Rey, 20 Melilla Melilla 52001",
    "addr:housenumber":"20",
    "addr:postcode":"52001",
    "addr:street":"Avda Juan Carlos I Rey",
    "iso:country":"ES",
    "sg:address":"Avda Juan Carlos I, Rey, 20",
    "sg:city":"Melilla",
    "sg:orig_category":"Ropa Para Se\u00d1oras (al Por Menor)",
    "sg:phone":"+34 952 68 03 02",
    "sg:postcode":"52001",
    "sg:province":"Melilla",
    "wof:name":"Benhamu Benguigui Leon",
    "wof:placetype":"venue"
},
  "geometry": {"coordinates":[-2.9404931068,35.2937316895],"type":"Point"}
}