{
  "type": "Feature",
  "properties": {
    "iso:country":"ES",
    "sg:address":"Carrer de Roger De Belfort, 7",
    "sg:city":"Reus",
    "sg:orig_category":"Cr\u00cda De Animales",
    "sg:phone":"+34 977 31 20 81",
    "sg:postcode":"43202",
    "sg:province":"Tarragona",
    "wof:name":"Moliner Arbos Jaime",
    "wof:placetype":"venue"
},
  "geometry": {"coordinates":[1.100118041,41.1529502869],"type":"Point"}
}