{
  "type": "Feature",
  "properties": {
    "addr:full":"C/ Santa Anna, 103 Cerdanyola Valles Barcelona 08290",
    "addr:housenumber":"103",
    "addr:postcode":"08290",
    "addr:street":"C / Santa Anna;Valles Barcelona",
    "iso:country":"ES",
    "sg:address":"C/ Santa Anna, 103",
    "sg:city":"Cerdanyola Valles",
    "sg:orig_category":"Artes Gr\u00c1ficas, Artes Pl\u00c1sticas (curso)",
    "sg:phone":"+34 935 94 47 77",
    "sg:postcode":"08290",
    "sg:province":"Barcelona",
    "wof:name":"Tecnograf S. A.",
    "wof:placetype":"venue"
},
  "geometry": {"coordinates":[2.1470150948,41.4924812317],"type":"Point"}
}