{
  "type": "Feature",
  "properties": {
    "addr:full":"Calle de Escuelas, 5 Barrio Roca Valencia 46133",
    "addr:housenumber":"5",
    "addr:postcode":"46133",
    "addr:street":"Calle De Escuelas;Roca",
    "iso:country":"ES",
    "sg:address":"Calle de Escuelas, 5",
    "sg:city":"Barrio Roca",
    "sg:orig_category":"Iglesia Cat\u00d3lica",
    "sg:phone":"+34 961 49 06 16",
    "sg:postcode":"46133",
    "sg:province":"Valencia",
    "wof:name":"Parroquia Nuestra Se\u00f1ora De La Misericordia",
    "wof:placetype":"venue"
},
  "geometry": {"coordinates":[-0.3230139911,39.5274848938],"type":"Point"}
}