{
  "type": "Feature",
  "properties": {
    "addr:full":"Nogueira, S/n Nogueira Ourense 32765",
    "addr:housenumber":"s / n",
    "addr:postcode":"32765",
    "addr:street":"Nogueira",
    "iso:country":"ES",
    "sg:address":"Nogueira, S/n",
    "sg:city":"Nogueira",
    "sg:orig_category":"Supermercados Y Hipermercados",
    "sg:phone":"+34 988 20 74 01",
    "sg:postcode":"32765",
    "sg:province":"Ourense",
    "wof:name":"Prieto Alvarez Jose Antonio",
    "wof:placetype":"venue"
},
  "geometry": {"coordinates":[-7.4741168022,42.3902511597],"type":"Point"}
}