{
  "type": "Feature",
  "properties": {
    "addr:full":"Ctra Malagon-el Cristo, Km. 0001,6 Daimiel Ciudad Real 13250",
    "addr:postcode":"13250",
    "addr:street":"Ctra Malagon-El Cristo Km. 0001,6",
    "iso:country":"ES",
    "sg:address":"Ctra Malagon-el Cristo, Km. 0001,6",
    "sg:city":"Daimiel",
    "sg:orig_category":"Mec\u00c1nico Del Autom\u00d3vil",
    "sg:phone":"+34 926 85 46 21",
    "sg:postcode":"13250",
    "sg:province":"Ciudad Real",
    "wof:name":"Tubos Arelag S.l.",
    "wof:placetype":"venue"
},
  "geometry": {"coordinates":[-3.617358923,39.0695037842],"type":"Point"}
}