{
  "type": "Feature",
  "properties": {
    "addr:full":"Sanguesa, 19 Iru\u00f1a Navarra 31003",
    "addr:housenumber":"19",
    "addr:postcode":"31003",
    "addr:street":"Sanguesa",
    "iso:country":"ES",
    "sg:address":"Sanguesa, 19",
    "sg:city":"Iru\u00f1a",
    "sg:orig_category":"Pescader\u00cdas (al Por Menor)",
    "sg:phone":"+34 948 24 64 65",
    "sg:postcode":"31003",
    "sg:province":"Navarra",
    "wof:name":"Comercial Bacaladera S.a.",
    "wof:placetype":"venue"
},
  "geometry": {"coordinates":[-1.6392970085,42.8097648621],"type":"Point"}
}