{
  "type": "Feature",
  "properties": {
    "iso:country":"ES",
    "sg:address":"Joaquin Velasco, S/n",
    "sg:city":"Arnedillo",
    "sg:orig_category":"Hoteles",
    "sg:phone":"+34 901 22 29 02",
    "sg:postcode":"26589",
    "sg:province":"La Rioja",
    "wof:name":"Terma Europa S.a.",
    "wof:placetype":"venue"
},
  "geometry": {"coordinates":[-2.2408549786,42.2088737488],"type":"Point"}
}