{
  "type": "Feature",
  "properties": {
    "iso:country":"ES",
    "sg:address":"Malleza, 77",
    "sg:city":"Malleza",
    "sg:orig_category":"Charcuter\u00cdas (al Por Mayor)",
    "sg:phone":"+34 985 83 59 35",
    "sg:postcode":"33866",
    "sg:province":"Asturias",
    "wof:name":"Embutidos La Union S.l.",
    "wof:placetype":"venue"
},
  "geometry": {"coordinates":[-6.2530331612,43.455532074],"type":"Point"}
}