{
  "type": "Feature",
  "properties": {
    "addr:full":"Carrer de Major (sant Celoni), 136 S. Celoni Barcelona 08470",
    "addr:housenumber":"136",
    "addr:postcode":"08470",
    "addr:street":"Carrer De Major Sant Celoni;S. Celoni Barcelona",
    "iso:country":"ES",
    "sg:address":"Carrer de Major (sant Celoni), 136",
    "sg:city":"S. Celoni",
    "sg:orig_category":"Panader\u00cdas, Panader\u00cdas",
    "sg:phone":"+34 938 67 02 40",
    "sg:postcode":"08470",
    "sg:province":"Barcelona",
    "wof:name":"Lleonart Vila Amadeo",
    "wof:placetype":"venue"
},
  "geometry": {"coordinates":[2.4912290573,41.6895713806],"type":"Point"}
}