{
  "type": "Feature",
  "properties": {
    "addr:full":"Calle de Gustavo Adolfo Becquer, 4 Santa Fe Granada 18320",
    "addr:housenumber":"4",
    "addr:postcode":"18320",
    "addr:street":"Calle De Gustavo Adolfo Becquer;Fe",
    "iso:country":"ES",
    "sg:address":"Calle de Gustavo Adolfo Becquer, 4",
    "sg:city":"Santa Fe",
    "sg:orig_category":"Plomeros",
    "sg:phone":"+34 958 44 00 68",
    "sg:postcode":"18320",
    "sg:province":"Granada",
    "wof:name":"Castro Fernandez Jose",
    "wof:placetype":"venue"
},
  "geometry": {"coordinates":[-3.7171089649,37.1911964417],"type":"Point"}
}