{
  "type": "Feature",
  "properties": {
    "addr:full":"San Andres, 2 Villota Paramo Palencia 34112",
    "addr:housenumber":"2",
    "addr:postcode":"34112",
    "addr:street":"San Andres",
    "iso:country":"ES",
    "sg:address":"San Andres, 2",
    "sg:city":"Villota Paramo",
    "sg:orig_category":"Plomeros",
    "sg:phone":"+34 979 89 45 14",
    "sg:postcode":"34112",
    "sg:province":"Palencia",
    "wof:name":"Lozano Maeso Pedro",
    "wof:placetype":"venue"
},
  "geometry": {"coordinates":[-4.7961888313,42.5063285828],"type":"Point"}
}