{
  "type": "Feature",
  "properties": {
    "addr:full":"Canal De Rosarito, S/n Villanueva Vera C\u00e1ceres 10470",
    "addr:postcode":"10470",
    "addr:street":"S / N;Ca\u0301Ceres",
    "iso:country":"ES",
    "sg:address":"Canal De Rosarito, S/n",
    "sg:city":"Villanueva Vera",
    "sg:orig_category":"Sales (al Por Mayor)",
    "sg:phone":"+34 927 19 80 45",
    "sg:postcode":"10470",
    "sg:province":"C\u00e1ceres",
    "sg:website":"www.serpienteverde.com",
    "wof:name":"La Serpiente Verde Sl",
    "wof:placetype":"venue"
},
  "geometry": {"coordinates":[-5.4627428055,40.1311225891],"type":"Point"}
}