{
  "type": "Feature",
  "properties": {
    "iso:country":"ES",
    "sg:address":"Calle de Almacellas, 44",
    "sg:city":"Binefar",
    "sg:orig_category":"Material Y Suministros Para Veterinarios",
    "sg:phone":"+34 974 43 12 65",
    "sg:postcode":"22500",
    "sg:province":"Huesca",
    "wof:name":"Veterinaria Ganavic S.l.",
    "wof:placetype":"venue"
},
  "geometry": {"coordinates":[0.2960340083,41.8459320068],"type":"Point"}
}