{
  "type": "Feature",
  "properties": {
    "iso:country":"ES",
    "sg:address":"Avda Portugal, 8",
    "sg:city":"Zamora",
    "sg:orig_category":"Psic\u00d3logos",
    "sg:phone":"+34 980 53 64 29",
    "sg:postcode":"49015",
    "sg:province":"Zamora",
    "wof:name":"Mayado Carbajo Veronica",
    "wof:placetype":"venue"
},
  "geometry": {"coordinates":[-5.7405948639,41.5066146851],"type":"Point"}
}