{
  "type": "Feature",
  "properties": {
    "addr:full":"Calle de Tortola, 10 Valladolid Valladolid 47012",
    "addr:housenumber":"10",
    "addr:postcode":"47012",
    "addr:street":"Calle De Tortola",
    "iso:country":"ES",
    "sg:address":"Calle de Tortola, 10",
    "sg:city":"Valladolid",
    "sg:orig_category":"Industria Qu\u00cdmica",
    "sg:phone":"+34 983 30 11 16",
    "sg:postcode":"47012",
    "sg:province":"Valladolid",
    "wof:name":"Cohal S.a.",
    "wof:placetype":"venue"
},
  "geometry": {"coordinates":[-4.71270895,41.6463851929],"type":"Point"}
}