{
  "type": "Feature",
  "properties": {
    "iso:country":"ES",
    "sg:address":"Pase Santo Tomas (de), 2",
    "sg:city":"Avila",
    "sg:orig_category":"Abogados",
    "sg:phone":"+34 920 22 88 24",
    "sg:postcode":"05003",
    "sg:province":"\u00c1vila",
    "wof:name":"Sanchez Estebez Raquel",
    "wof:placetype":"venue"
},
  "geometry": {"coordinates":[-4.6912212372,40.6491508484],"type":"Point"}
}