{
  "type": "Feature",
  "properties": {
    "addr:full":"Calle de Santisima Trinidad, 5 Fuengirola M\u00e1laga 29640",
    "addr:housenumber":"5",
    "addr:postcode":"29640",
    "addr:street":"Calle De Santisima Trinidad;Ma\u0301Laga",
    "iso:country":"ES",
    "sg:address":"Calle de Santisima Trinidad, 5",
    "sg:city":"Fuengirola",
    "sg:orig_category":"Peluquer\u00cdas",
    "sg:phone":"+34 952 46 52 08",
    "sg:postcode":"29640",
    "sg:province":"M\u00e1laga",
    "wof:name":"Jimenez Morillo Francisco Javier",
    "wof:placetype":"venue"
},
  "geometry": {"coordinates":[-4.615375042,36.552570343],"type":"Point"}
}