{
  "type": "Feature",
  "properties": {
    "addr:full":"Calle de Cervantes, 29 Segovia Segovia 40001",
    "addr:housenumber":"29",
    "addr:postcode":"40001",
    "addr:street":"Calle De Cervantes",
    "iso:country":"ES",
    "sg:address":"Calle de Cervantes, 29",
    "sg:city":"Segovia",
    "sg:orig_category":"Arquitectos",
    "sg:phone":"+34 921 46 27 88",
    "sg:postcode":"40001",
    "sg:province":"Segovia",
    "wof:name":"Moreno Yuste Adolfo",
    "wof:placetype":"venue"
},
  "geometry": {"coordinates":[-4.1185588837,40.9478569031],"type":"Point"}
}