{
  "type": "Feature",
  "properties": {
    "addr:full":"Carrer de Major, 27 Morell Tarragona 43760",
    "addr:housenumber":"27",
    "addr:postcode":"43760",
    "addr:street":"Carrer De Major",
    "iso:country":"ES",
    "sg:address":"Carrer de Major, 27",
    "sg:city":"Morell",
    "sg:orig_category":"Empresarios",
    "sg:phone":"+34 977 84 29 23",
    "sg:postcode":"43760",
    "sg:province":"Tarragona",
    "wof:name":"Guiluz 98, S.c.",
    "wof:placetype":"venue"
},
  "geometry": {"coordinates":[1.2101839781,41.1929931641],"type":"Point"}
}