{
  "type": "Feature",
  "properties": {
    "iso:country":"ES",
    "sg:address":"Calle de Navarra, 40",
    "sg:city":"Sevilla",
    "sg:orig_category":"Reposter\u00cdas",
    "sg:phone":"+34 954 90 15 06",
    "sg:postcode":"41015",
    "sg:province":"Sevilla",
    "wof:name":"Gonzalez Prieto Julian",
    "wof:placetype":"venue"
},
  "geometry": {"coordinates":[-5.9840388298,37.4234390259],"type":"Point"}
}