{
  "type": "Feature",
  "properties": {
    "addr:full":"Avda El Ferial, 71 Benavente Zamora 49600",
    "addr:housenumber":"71",
    "addr:postcode":"49600",
    "addr:street":"Avda El Ferial",
    "iso:country":"ES",
    "sg:address":"Avda El Ferial, 71",
    "sg:city":"Benavente",
    "sg:orig_category":"Asesor\u00cda Fiscal Y Jur\u00cddica",
    "sg:phone":"+34 980 63 05 27",
    "sg:postcode":"49600",
    "sg:province":"Zamora",
    "wof:name":"Gutierrez Colinas C.b.",
    "wof:placetype":"venue"
},
  "geometry": {"coordinates":[-5.6773190498,41.9971694946],"type":"Point"}
}