{
  "type": "Feature",
  "properties": {
    "addr:full":"Calle de Oiartzun, 13 Errenteria Guip\u00f9zcoa 20100",
    "addr:housenumber":"13",
    "addr:postcode":"20100",
    "addr:street":"Calle De Oiartzun;Guipu\u0300Zcoa",
    "iso:country":"ES",
    "sg:address":"Calle de Oiartzun, 13",
    "sg:city":"Errenteria",
    "sg:orig_category":"Mec\u00c1nico Del Autom\u00d3vil",
    "sg:phone":"+34 943 01 96 67",
    "sg:postcode":"20100",
    "sg:province":"Guip\u00f9zcoa",
    "wof:name":"Juan Luis Babon Escudero (taller)",
    "wof:placetype":"venue"
},
  "geometry": {"coordinates":[-1.903709054,43.3161506653],"type":"Point"}
}