{
  "type": "Feature",
  "properties": {
    "addr:full":"Calle de Intxaurrondo, 52 Donostia-san Sebastian Guip\u00f9zcoa 20015",
    "addr:housenumber":"52",
    "addr:postcode":"20015",
    "addr:street":"Calle De Intxaurrondo",
    "iso:country":"ES",
    "sg:address":"Calle de Intxaurrondo, 52",
    "sg:city":"Donostia-san Sebastian",
    "sg:orig_category":"Vinos Y Licores (venta Al Por Menor)",
    "sg:phone":"+34 943 28 53 93",
    "sg:postcode":"20015",
    "sg:province":"Guip\u00f9zcoa",
    "wof:name":"Arribas Bahillo Melchor",
    "wof:placetype":"venue"
},
  "geometry": {"coordinates":[-1.9534788132,43.3205032349],"type":"Point"}
}