{
  "type": "Feature",
  "properties": {
    "addr:full":"Calle de Aliatar, 18 Loja Granada 18300",
    "addr:housenumber":"18 loja",
    "addr:postcode":"18300",
    "addr:street":"Calle De Aliatar",
    "iso:country":"ES",
    "sg:address":"Calle de Aliatar, 18",
    "sg:city":"Loja",
    "sg:orig_category":"Transportes De Animales Vivos",
    "sg:phone":"+34 958 32 10 44",
    "sg:postcode":"18300",
    "sg:province":"Granada",
    "wof:name":"Perez Ramos Niceto",
    "wof:placetype":"venue"
},
  "geometry": {"coordinates":[-4.1497797966,37.1683959961],"type":"Point"}
}