{
  "type": "Feature",
  "properties": {
    "addr:full":"Avda Cruz De Mayo, 47 Lebrija Sevilla 41740",
    "addr:housenumber":"47",
    "addr:postcode":"41740",
    "addr:street":"Avda Cruz De Mayo",
    "iso:country":"ES",
    "sg:address":"Avda Cruz De Mayo, 47",
    "sg:city":"Lebrija",
    "sg:orig_category":"Art\u00cdculos Funerarios (al Por Menor)",
    "sg:phone":"+34 955 97 25 19",
    "sg:postcode":"41740",
    "sg:province":"Sevilla",
    "wof:name":"Dans Zapata Jose Antonio",
    "wof:placetype":"venue"
},
  "geometry": {"coordinates":[-6.0764517784,36.9232673645],"type":"Point"}
}