{
  "type": "Feature",
  "properties": {
    "iso:country":"ES",
    "sg:address":"Carrer de Calvet D'estrella, 46",
    "sg:city":"Sabadell",
    "sg:orig_category":"Empresas De Portes Y Mensajer\u00cda",
    "sg:phone":"+34 937 10 11 22",
    "sg:postcode":"08203",
    "sg:province":"Barcelona",
    "wof:name":"Valles Expres S.l.",
    "wof:placetype":"venue"
},
  "geometry": {"coordinates":[2.1164739132,41.5361251831],"type":"Point"}
}