{
  "type": "Feature",
  "properties": {
    "addr:full":"Posadas, 18 Zahinos Badajoz 06129",
    "addr:housenumber":"18",
    "addr:postcode":"06129",
    "addr:street":"Posadas",
    "iso:country":"ES",
    "sg:address":"Posadas, 18",
    "sg:city":"Zahinos",
    "sg:orig_category":"Bisuter\u00cda, Joyer\u00cda, Relojer\u00cda (al Por Menor)",
    "sg:phone":"+34 924 73 84 64",
    "sg:postcode":"06129",
    "sg:province":"Badajoz",
    "wof:name":"Vila Ramos Jose Angel",
    "wof:placetype":"venue"
},
  "geometry": {"coordinates":[-6.9537529945,38.3291893005],"type":"Point"}
}