{
  "type": "Feature",
  "properties": {
    "iso:country":"ES",
    "sg:address":"Calle de Molino, 21",
    "sg:city":"Villanueva De Los Castillejos",
    "sg:orig_category":"Electrodom\u00c9sticos (al Por Menor)",
    "sg:phone":"+34 959 38 53 11",
    "sg:postcode":"21540",
    "sg:province":"Huelva",
    "wof:name":"Joaquin Diaz Alvaro De La Cruz",
    "wof:placetype":"venue"
},
  "geometry": {"coordinates":[-7.2675490379,37.5029296875],"type":"Point"}
}