{
  "type": "Feature",
  "properties": {
    "iso:country":"ES",
    "sg:address":"Carr Villamarchante, 8",
    "sg:city":"Eliana",
    "sg:orig_category":"Comercio, Reparaci\u00d3n De Bicicletas, De Motocicletas, De Accesorios",
    "sg:phone":"+34 962 74 26 24",
    "sg:postcode":"46183",
    "sg:province":"Valencia",
    "wof:name":"Bici Velo Vike S.l.",
    "wof:placetype":"venue"
},
  "geometry": {"coordinates":[-0.5277870297,39.5659942627],"type":"Point"}
}