{
  "type": "Feature",
  "properties": {
    "addr:full":"Calle de Gil De Jaz, 4 Oviedo Asturias 33004",
    "addr:housenumber":"4",
    "addr:postcode":"33004",
    "addr:street":"Calle De Gil De Jaz",
    "iso:country":"ES",
    "sg:address":"Calle de Gil De Jaz, 4",
    "sg:city":"Oviedo",
    "sg:orig_category":"Bancos",
    "sg:phone":"+34 985 24 00 00",
    "sg:postcode":"33004",
    "sg:province":"Asturias",
    "wof:name":"Banc Sabadell S.a.",
    "wof:placetype":"venue"
},
  "geometry": {"coordinates":[-5.8523888588,43.3638763428],"type":"Point"}
}