{
  "type": "Feature",
  "properties": {
    "iso:country":"ES",
    "sg:address":"Avda Constitucion (de La), 39",
    "sg:city":"Candelaria",
    "sg:orig_category":"Carnicer\u00cdas, Carnicer\u00cdas",
    "sg:phone":"+34 922 50 29 67",
    "sg:postcode":"38530",
    "sg:province":"Santa Cruz De Tenerife",
    "wof:name":"Garcia Reyes Cristobal",
    "wof:placetype":"venue"
},
  "geometry": {"coordinates":[-16.3693599701,28.3571128845],"type":"Point"}
}