{
  "type": "Feature",
  "properties": {
    "addr:full":"Trav De Gracia, 205 Barcelona Barcelona 08012",
    "addr:housenumber":"205",
    "addr:postcode":"08012",
    "addr:street":"Trav De Gracia",
    "iso:country":"ES",
    "sg:address":"Trav De Gracia, 205",
    "sg:city":"Barcelona",
    "sg:orig_category":"Bisuter\u00cda, Joyer\u00cda, Relojer\u00cda (al Por Menor)",
    "sg:phone":"+34 932 13 56 86",
    "sg:postcode":"08012",
    "sg:province":"Barcelona",
    "wof:name":"Oca\u00f1a Moratalla Manuel",
    "wof:placetype":"venue"
},
  "geometry": {"coordinates":[2.1601579189,41.4028739929],"type":"Point"}
}