{
  "type": "Feature",
  "properties": {
    "iso:country":"ES",
    "sg:address":"Plaz Jose Antonio, 24",
    "sg:city":"Colunga",
    "sg:orig_category":"Panader\u00cdas, Panader\u00cdas",
    "sg:phone":"+34 985 85 21 56",
    "sg:postcode":"33320",
    "sg:province":"Asturias",
    "wof:name":"Suarez Martinez Daniel",
    "wof:placetype":"venue"
},
  "geometry": {"coordinates":[-5.2751731873,43.485458374],"type":"Point"}
}