{
  "type": "Feature",
  "properties": {
    "iso:country":"ES",
    "sg:address":"Calle de Portales De Cami\u00d1as, 7",
    "sg:city":"Salamanca",
    "sg:orig_category":"Servidores Y Editores De Bases De Datos",
    "sg:phone":"+34 923 21 15 77",
    "sg:postcode":"37001",
    "sg:province":"Salamanca",
    "sg:website":"www.miweb.es",
    "wof:name":"Mi Web Internet S.l.",
    "wof:placetype":"venue"
},
  "geometry": {"coordinates":[-5.6613988876,40.9651756287],"type":"Point"}
}