{
  "type": "Feature",
  "properties": {
    "addr:full":"Pl. Abastos, S/n Noia La Coru\u00f1a 15200",
    "addr:housenumber":"s / n",
    "addr:postcode":"15200",
    "addr:street":"Abastos;La Corun\u0303A",
    "iso:country":"ES",
    "sg:address":"Pl. Abastos, S/n",
    "sg:city":"Noia",
    "sg:orig_category":"Carnicer\u00cdas, Carnicer\u00cdas",
    "sg:phone":"+34 981 82 36 08",
    "sg:postcode":"15200",
    "sg:province":"La Coru\u00f1a",
    "wof:name":"Barreiro Romero Maria Purificacion",
    "wof:placetype":"venue"
},
  "geometry": {"coordinates":[-8.8883037567,42.788608551],"type":"Point"}
}