{
  "type": "Feature",
  "properties": {
    "iso:country":"ES",
    "sg:address":"Calle de Arquillo Del Reloj, 4",
    "sg:city":"Chiclana De La Frontera",
    "sg:orig_category":"Molduras, Junquillos, Listones Y Molduras Perforadas",
    "sg:phone":"+34 956 40 03 16",
    "sg:postcode":"11130",
    "sg:province":"C\u00e1diz",
    "wof:name":"Benitez Salado Francisco",
    "wof:placetype":"venue"
},
  "geometry": {"coordinates":[-6.1456580162,36.4187736511],"type":"Point"}
}