{
  "type": "Feature",
  "properties": {
    "iso:country":"ES",
    "sg:address":"Calle de Reyes Leoneses, 46",
    "sg:city":"Le\u00f3n",
    "sg:orig_category":"Supermercados Y Hipermercados",
    "sg:phone":"+34 987 87 53 18",
    "sg:postcode":"24008",
    "sg:province":"Le\u00f3n",
    "wof:name":"Merkaprecio S.a.",
    "wof:placetype":"venue"
},
  "geometry": {"coordinates":[-5.587744236,42.612663269],"type":"Point"}
}