{
  "type": "Feature",
  "properties": {
    "iso:country":"ES",
    "sg:address":"Calle de Moral, 2",
    "sg:city":"Sisante",
    "sg:classifiers":[
        {
            "category":"Taxi",
            "type":"Transportation"
        }
    ],
    "sg:phone":"+34 969 38 72 21",
    "sg:postcode":"16700",
    "sg:province":"Cuenca",
    "wof:name":"Jimenez Santiago Sebastian",
    "wof:placetype":"venue"
},
  "geometry": {"coordinates":[-2.2019250393,39.4058990479],"type":"Point"}
}