{
  "type": "Feature",
  "properties": {
    "iso:country":"ES",
    "sg:address":"Poseidon, 7",
    "sg:city":"Ejido",
    "sg:orig_category":"Psic\u00d3logos",
    "sg:phone":"+34 950 48 93 43",
    "sg:postcode":"04700",
    "sg:province":"Almer\u00eda",
    "wof:name":"Maldonado Martin Victor Manuel",
    "wof:placetype":"venue"
},
  "geometry": {"coordinates":[-2.7580699921,36.7285690308],"type":"Point"}
}