{
  "type": "Feature",
  "properties": {
    "addr:full":"Calle de Cobre, 3 Campo Nuevo Madrid 28863",
    "addr:housenumber":"3",
    "addr:postcode":"28863",
    "addr:street":"Calle De Cobre",
    "iso:country":"ES",
    "sg:address":"Calle de Cobre, 3",
    "sg:city":"Campo Nuevo",
    "sg:orig_category":"Publicidad (soportes Y Gesti\u00d3n)",
    "sg:phone":"+34 916 20 84 17",
    "sg:postcode":"28863",
    "sg:province":"Madrid",
    "wof:name":"Macope Comunicacion S.l.",
    "wof:placetype":"venue"
},
  "geometry": {"coordinates":[-3.7003455162,40.4166908264],"type":"Point"}
}