{
  "type": "Feature",
  "properties": {
    "iso:country":"ES",
    "sg:address":"Avda Nuestra Se\u00d1ora De Estibaliz, 3",
    "sg:city":"Vitoria-gasteiz",
    "sg:orig_category":"Agentes Generales De Seguros",
    "sg:phone":"+34 945 12 86 88",
    "sg:postcode":"01003",
    "sg:province":"\u00c1lava",
    "wof:name":"Berganza Irastorza Bego\u00f1a",
    "wof:placetype":"venue"
},
  "geometry": {"coordinates":[-2.6636619568,42.8453559875],"type":"Point"}
}