{
  "type": "Feature",
  "properties": {
    "addr:full":"Calle de Federico Velez, 4 Burgos Burgos 09001",
    "addr:housenumber":"4",
    "addr:postcode":"09001",
    "addr:street":"Calle De Federico Velez",
    "iso:country":"ES",
    "sg:address":"Calle de Federico Velez, 4",
    "sg:city":"Burgos",
    "sg:orig_category":"Asociaciones Humanitarias, De Cooperaci\u00d3n, De Acci\u00d3n Social",
    "sg:phone":"+34 947 24 02 77",
    "sg:postcode":"09001",
    "sg:province":"Burgos",
    "sg:website":"www.antisidaburgos.org",
    "wof:name":"Comite Ciudadano Anti-sida De Burgos",
    "wof:placetype":"venue"
},
  "geometry": {"coordinates":[-3.7166740894,42.3456268311],"type":"Point"}
}