{
  "type": "Feature",
  "properties": {
    "iso:country":"ES",
    "sg:address":"Calle de Grandeza Espa\u00d1ola, 36",
    "sg:city":"Madrid",
    "sg:orig_category":"Mec\u00c1nico Del Autom\u00d3vil",
    "sg:phone":"+34 914 64 93 00",
    "sg:postcode":"28011",
    "sg:province":"Madrid",
    "wof:name":"Portillo Montes Manuel",
    "wof:placetype":"venue"
},
  "geometry": {"coordinates":[-3.7322740555,40.4116096497],"type":"Point"}
}