{
  "type": "Feature",
  "properties": {
    "iso:country":"ES",
    "sg:address":"Calle de Doctor Pulido, 6",
    "sg:city":"Guadix",
    "sg:orig_category":"Confecci\u00d3n (fabricaci\u00d3n, Al Por Mayor)",
    "sg:phone":"+34 958 66 50 20",
    "sg:postcode":"18500",
    "sg:province":"Granada",
    "wof:name":"Onieva Martinez Antonio",
    "wof:placetype":"venue"
},
  "geometry": {"coordinates":[-3.1317679882,37.3009872437],"type":"Point"}
}