{
  "type": "Feature",
  "properties": {
    "addr:full":"Calle de Escuelas Pias, 17 Tafalla Navarra 31300",
    "addr:housenumber":"17",
    "addr:postcode":"31300",
    "addr:street":"Calle De Escuelas Pias",
    "iso:country":"ES",
    "sg:address":"Calle de Escuelas Pias, 17",
    "sg:city":"Tafalla",
    "sg:orig_category":"Librer\u00cdas",
    "sg:phone":"+34 948 70 02 27",
    "sg:postcode":"31300",
    "sg:province":"Navarra",
    "wof:name":"Ojer Go\u00f1i Francisco Javier",
    "wof:placetype":"venue"
},
  "geometry": {"coordinates":[-1.674628973,42.5283813477],"type":"Point"}
}