{
  "type": "Feature",
  "properties": {
    "addr:full":"G.v. Corts Catalanes, 493 Barcelona Barcelona 08015",
    "addr:housenumber":"493",
    "addr:postcode":"08015",
    "addr:street":"Catalanes",
    "iso:country":"ES",
    "sg:address":"G.v. Corts Catalanes, 493",
    "sg:city":"Barcelona",
    "sg:orig_category":"Venta, Instalaci\u00d3n De Sistemas De Alarmas Y Vigilancia",
    "sg:phone":"+34 934 51 75 00",
    "sg:postcode":"08015",
    "sg:province":"Barcelona",
    "wof:name":"Alarmas Spitz S.a.",
    "wof:placetype":"venue"
},
  "geometry": {"coordinates":[2.1563301086,41.3807258606],"type":"Point"}
}