{
  "type": "Feature",
  "properties": {
    "addr:full":"Carrer de Doctor Letamendi, 63 Barcelona Barcelona 08031",
    "addr:housenumber":"63",
    "addr:postcode":"08031",
    "addr:street":"Carrer De Doctor Letamendi",
    "iso:country":"ES",
    "sg:address":"Carrer de Doctor Letamendi, 63",
    "sg:city":"Barcelona",
    "sg:orig_category":"Internados & Ense\u00d1anza Privada",
    "sg:phone":"+34 934 27 15 00",
    "sg:postcode":"08031",
    "sg:province":"Barcelona",
    "wof:name":"Hermanos De Las Escuelas Cristianas",
    "wof:placetype":"venue"
},
  "geometry": {"coordinates":[2.1610169411,41.4367141724],"type":"Point"}
}