{
  "type": "Feature",
  "properties": {
    "addr:full":"Fuero Del Trabajo, 37 Burgos Burgos 09007",
    "addr:housenumber":"37",
    "addr:postcode":"09007",
    "iso:country":"ES",
    "sg:address":"Fuero Del Trabajo, 37",
    "sg:city":"Burgos",
    "sg:orig_category":"Asesor\u00cda Para La Organizaci\u00d3n Y Gesti\u00d3n Del Transporte",
    "sg:phone":"+34 947 48 65 22",
    "sg:postcode":"09007",
    "sg:province":"Burgos",
    "wof:name":"Miguel Servicios Logisticos S.l.",
    "wof:placetype":"venue"
},
  "geometry": {"coordinates":[-3.6424589157,42.3604316711],"type":"Point"}
}