{
  "type": "Feature",
  "properties": {
    "iso:country":"ES",
    "sg:address":"Calle de Jesus Nazareno, 2",
    "sg:city":"Huelva",
    "sg:orig_category":"Inmobiliaria (agencias)",
    "sg:phone":"+34 959 25 11 59",
    "sg:postcode":"21001",
    "sg:province":"Huelva",
    "wof:name":"Jimenez Leon Maria Del Carmen",
    "wof:placetype":"venue"
},
  "geometry": {"coordinates":[-6.9544591904,37.2573013306],"type":"Point"}
}