{
  "type": "Feature",
  "properties": {
    "iso:country":"ES",
    "sg:address":"Calle de Molino, 13",
    "sg:city":"Viver",
    "sg:orig_category":"Empresas De Electricidad En General",
    "sg:phone":"+34 964 14 17 71",
    "sg:postcode":"12460",
    "sg:province":"Castell\u00f3n",
    "wof:name":"Ma\u00f1es Molina Jesus Manuel",
    "wof:placetype":"venue"
},
  "geometry": {"coordinates":[-0.5953660011,39.9220123291],"type":"Point"}
}