{
  "type": "Feature",
  "properties": {
    "addr:full":"Rua Montevideo, 33 Lugo Lugo 27001",
    "addr:housenumber":"33",
    "addr:postcode":"27001",
    "addr:street":"Rua Montevideo",
    "iso:country":"ES",
    "sg:address":"Rua Montevideo, 33",
    "sg:city":"Lugo",
    "sg:orig_category":"Peluquer\u00cdas, Peluquer\u00cda Mixta",
    "sg:phone":"+34 982 24 20 14",
    "sg:postcode":"27001",
    "sg:province":"Lugo",
    "wof:name":"Perez Arias Edita",
    "wof:placetype":"venue"
},
  "geometry": {"coordinates":[-7.5609688759,43.0121803284],"type":"Point"}
}