{
  "type": "Feature",
  "properties": {
    "iso:country":"ES",
    "sg:address":"Avda Galan Bergua, 13",
    "sg:city":"Alca\u00f1iz",
    "sg:orig_category":"Muebles, Minoristas",
    "sg:phone":"+34 978 83 03 17",
    "sg:postcode":"44600",
    "sg:province":"Teruel",
    "wof:name":"Garcia Montala Eusebio",
    "wof:placetype":"venue"
},
  "geometry": {"coordinates":[-0.1300317049,41.0513153076],"type":"Point"}
}