{
  "type": "Feature",
  "properties": {
    "addr:full":"Av Europa, 189 Hospitalet Llobregat Barcelona 08907",
    "addr:housenumber":"189",
    "addr:postcode":"08907",
    "addr:street":"Av Europa",
    "iso:country":"ES",
    "sg:address":"Av Europa, 189",
    "sg:city":"Hospitalet Llobregat",
    "sg:orig_category":"Molduras, Junquillos, Listones Y Molduras Perforadas",
    "sg:phone":"+34 933 35 15 24",
    "sg:postcode":"08907",
    "sg:province":"Barcelona",
    "wof:name":"Carrasco Corral Manuel",
    "wof:placetype":"venue"
},
  "geometry": {"coordinates":[2.1127500534,41.356628418],"type":"Point"}
}