{
  "type": "Feature",
  "properties": {
    "addr:full":"Rua Portelo, 16 Allariz Ourense 32660",
    "addr:housenumber":"16",
    "addr:postcode":"32660",
    "addr:street":"Rua Portelo",
    "iso:country":"ES",
    "sg:address":"Rua Portelo, 16",
    "sg:city":"Allariz",
    "sg:orig_category":"Molduras, Junquillos, Listones Y Molduras Perforadas",
    "sg:phone":"+34 988 44 20 52",
    "sg:postcode":"32660",
    "sg:province":"Ourense",
    "wof:name":"Perez Cid Elena",
    "wof:placetype":"venue"
},
  "geometry": {"coordinates":[-7.8007731438,42.1893539429],"type":"Point"}
}