{
  "type": "Feature",
  "properties": {
    "iso:country":"ES",
    "sg:address":"Calle de Atindana, 3",
    "sg:city":"Cruce I",
    "sg:orig_category":"Inform\u00c1tica, Ofim\u00c1tica (estudios, Asesor\u00cda, Ingenier\u00cda, Formaci\u00d3n)",
    "sg:phone":"+34 928 75 73 29",
    "sg:postcode":"35110",
    "sg:province":"Las Palmas",
    "wof:name":"O.k.informatica Canaria S.l.l.",
    "wof:placetype":"venue"
},
  "geometry": {"coordinates":[-15.4392213821,27.85455513],"type":"Point"}
}