{
  "type": "Feature",
  "properties": {
    "iso:country":"ES",
    "sg:address":"Carrer de Talamanca, 15",
    "sg:city":"Manresa",
    "sg:orig_category":"Asociaciones, Organismos Culturales Y Socioeducativos",
    "sg:phone":"+34 938 72 49 26",
    "sg:postcode":"08241",
    "sg:province":"Barcelona",
    "wof:name":"Agrupacio Cultural Del Bages",
    "wof:placetype":"venue"
},
  "geometry": {"coordinates":[1.823558569,41.7229919434],"type":"Point"}
}