{
  "type": "Feature",
  "properties": {
    "iso:country":"ES",
    "sg:address":"Calle de Alcoraz, 6",
    "sg:city":"Huesca",
    "sg:orig_category":"Ropa Para Se\u00d1oras (al Por Menor)",
    "sg:phone":"+34 974 21 14 64",
    "sg:postcode":"22002",
    "sg:province":"Huesca",
    "wof:name":"Varona Sotes Maria Angeles",
    "wof:placetype":"venue"
},
  "geometry": {"coordinates":[-0.4101833105,42.1355056763],"type":"Point"}
}