{
  "type": "Feature",
  "properties": {
    "iso:country":"ES",
    "sg:address":"Avda Beiramar, 211",
    "sg:city":"Vigo",
    "sg:orig_category":"Fabricaci\u00d3n, Reparaci\u00d3n Y Mantenimiento De Construcciones Navales Y Fluviales",
    "sg:phone":"+34 986 23 22 02",
    "sg:postcode":"36208",
    "sg:province":"Pontevedra",
    "wof:name":"Innovaciones Navales S.l.",
    "wof:placetype":"venue"
},
  "geometry": {"coordinates":[-8.7484636307,42.2247848511],"type":"Point"}
}