{
  "type": "Feature",
  "properties": {
    "addr:full":"Calle de Manuel Aza\u00d1a, 11 Coru\u00d1a La Coru\u00f1a 15011",
    "addr:housenumber":"11",
    "addr:postcode":"15011",
    "addr:street":"Calle De Manuel Azan\u0303A;La Corun\u0303A",
    "iso:country":"ES",
    "sg:address":"Calle de Manuel Aza\u00d1a, 11",
    "sg:city":"Coru\u00d1a",
    "sg:orig_category":"Asilos De Ancianos. Centros Privados",
    "sg:phone":"+34 981 64 77 14",
    "sg:postcode":"15011",
    "sg:province":"La Coru\u00f1a",
    "wof:name":"Gabinete Tecnico De Trabajo Social S.l.",
    "wof:placetype":"venue"
},
  "geometry": {"coordinates":[-8.427321434,43.3748893738],"type":"Point"}
}