{
  "type": "Feature",
  "properties": {
    "iso:country":"ES",
    "sg:address":"Calle de Zarza, 11",
    "sg:city":"Ciudad Real",
    "sg:orig_category":"Plomeros",
    "sg:phone":"+34 926 22 82 19",
    "sg:postcode":"13002",
    "sg:province":"Ciudad Real",
    "wof:name":"Fernandez Pelaez Patrocinio",
    "wof:placetype":"venue"
},
  "geometry": {"coordinates":[-3.9315290451,38.9872817993],"type":"Point"}
}