{
  "type": "Feature",
  "properties": {
    "addr:full":"Av Espanya, 120 Eivissa Islas Baleares 07800",
    "addr:housenumber":"120",
    "addr:postcode":"07800",
    "addr:street":"Av Espanya",
    "iso:country":"ES",
    "sg:address":"Av Espanya, 120",
    "sg:city":"Eivissa",
    "sg:orig_category":"Alimentaci\u00d3n General (al Por Menor)",
    "sg:phone":"+34 971 30 03 63",
    "sg:postcode":"07800",
    "sg:province":"Islas Baleares",
    "wof:name":"Escandell Juan Antonio",
    "wof:placetype":"venue"
},
  "geometry": {"coordinates":[1.4210300446,38.906539917],"type":"Point"}
}