{
  "type": "Feature",
  "properties": {
    "iso:country":"ES",
    "sg:address":"Ctra Bao, 130",
    "sg:city":"Combro",
    "sg:orig_category":"Molduras, Junquillos, Listones Y Molduras Perforadas",
    "sg:phone":"+34 986 49 04 16",
    "sg:postcode":"36330",
    "sg:province":"Pontevedra",
    "wof:name":"Comesa\u00f1a Alvarez Manuel",
    "wof:placetype":"venue"
},
  "geometry": {"coordinates":[-8.694773674,42.6678962708],"type":"Point"}
}