{
  "type": "Feature",
  "properties": {
    "addr:full":"Avda Fundador Gonzalo Gonzalez, Km. 0000,3 Granadilla Abona Santa Cruz De Tenerife 38600",
    "addr:postcode":"38600",
    "addr:street":"Avda Fundador Gonzalo Gonzalez Km. 0000,3",
    "iso:country":"ES",
    "sg:address":"Avda Fundador Gonzalo Gonzalez, Km. 0000,3",
    "sg:city":"Granadilla Abona",
    "sg:orig_category":"Lubrificantes (fabricaci\u00d3n, Al Por Mayor)",
    "sg:phone":"+34 922 77 12 27",
    "sg:postcode":"38600",
    "sg:province":"Santa Cruz De Tenerife",
    "wof:name":"Garcia Martin Juan Jose",
    "wof:placetype":"venue"
},
  "geometry": {"coordinates":[-16.5768527985,28.1200637817],"type":"Point"}
}