{
  "type": "Feature",
  "properties": {
    "iso:country":"ES",
    "sg:address":"Carrer de Gracia, 2",
    "sg:city":"Sabadell",
    "sg:orig_category":"Promotores Constructores",
    "sg:phone":"+34 937 27 04 57",
    "sg:postcode":"08201",
    "sg:province":"Barcelona",
    "wof:name":"Solisol, S.a.",
    "wof:placetype":"venue"
},
  "geometry": {"coordinates":[2.107790947,41.5466766357],"type":"Point"}
}