{
  "type": "Feature",
  "properties": {
    "iso:country":"ES",
    "sg:address":"Calle de Estartetxe, 5",
    "sg:city":"Leioa",
    "sg:orig_category":"Ingenier\u00cda, Centros De Estudios (industria)",
    "sg:phone":"+34 944 02 23 53",
    "sg:postcode":"48940",
    "sg:province":"Vizcaya",
    "wof:name":"Jose Ignacio Ojinaga Azcorra",
    "wof:placetype":"venue"
},
  "geometry": {"coordinates":[-2.987901926,43.3265800476],"type":"Point"}
}