{
  "type": "Feature",
  "properties": {
    "iso:country":"ES",
    "sg:address":"Bxda. Bourg-madame, 7",
    "sg:city":"Puigcerda",
    "sg:orig_category":"Lencer\u00cda Femenina, Corseter\u00cda, Trajes De Ba\u00d1o (al Por Menor)",
    "sg:phone":"+34 972 88 15 48",
    "sg:postcode":"17520",
    "sg:province":"Girona",
    "wof:name":"Moda Intima Merce S.l.",
    "wof:placetype":"venue"
},
  "geometry": {"coordinates":[1.9321850538,42.432258606],"type":"Point"}
}