{
  "type": "Feature",
  "properties": {
    "iso:country":"ES",
    "sg:address":"Avda Marques De Los Velez, 2",
    "sg:city":"Vista Alegre",
    "sg:orig_category":"M\u00c9dicos: An\u00c1lisis Cl\u00cdnicos",
    "sg:phone":"+34 968 24 98 70",
    "sg:postcode":"30008",
    "sg:province":"Murcia",
    "wof:name":"Laboratorios Munuera S. L.",
    "wof:placetype":"venue"
},
  "geometry": {"coordinates":[-1.1281670332,37.9922676086],"type":"Point"}
}