{
  "type": "Feature",
  "properties": {
    "addr:full":"Calle de Nueva Del Carmen, 39 Valladolid Valladolid 47011",
    "addr:housenumber":"39",
    "addr:postcode":"47011",
    "addr:street":"Calle De Nueva Del Carmen",
    "iso:country":"ES",
    "sg:address":"Calle de Nueva Del Carmen, 39",
    "sg:city":"Valladolid",
    "sg:orig_category":"Empresas De Desmonte",
    "sg:phone":"+34 983 20 92 25",
    "sg:postcode":"47011",
    "sg:province":"Valladolid",
    "wof:name":"Estudio De Arqueologia Foramen S.l.",
    "wof:placetype":"venue"
},
  "geometry": {"coordinates":[-4.7076311111,41.6563606262],"type":"Point"}
}