{
  "type": "Feature",
  "properties": {
    "addr:full":"Carrer de Mesquita De Cordova, 9 Castelldefels Barcelona 08860",
    "addr:housenumber":"9",
    "addr:postcode":"08860",
    "addr:street":"Carrer De Mesquita De Cordova",
    "iso:country":"ES",
    "sg:address":"Carrer de Mesquita De Cordova, 9",
    "sg:city":"Castelldefels",
    "sg:orig_category":"Escayola Y Productos De Escayola (fabricaci\u00d3n, Al Por Mayor)",
    "sg:phone":"+34 936 65 79 18",
    "sg:postcode":"08860",
    "sg:province":"Barcelona",
    "wof:name":"Gonzalez Vega Manuel",
    "wof:placetype":"venue"
},
  "geometry": {"coordinates":[1.9772859812,41.2901153564],"type":"Point"}
}