{
  "type": "Feature",
  "properties": {
    "iso:country":"ES",
    "sg:address":"Calle de Fuente De Piedra, 18",
    "sg:city":"Madrid",
    "sg:orig_category":"Molduras, Junquillos, Listones Y Molduras Perforadas",
    "sg:phone":"+34 917 77 52 59",
    "sg:postcode":"28018",
    "sg:province":"Madrid",
    "wof:name":"Iglesias Portillo Angel",
    "wof:placetype":"venue"
},
  "geometry": {"coordinates":[-3.6401979923,40.3828163147],"type":"Point"}
}