{
  "type": "Feature",
  "properties": {
    "iso:country":"ES",
    "sg:address":"Av Rei En Jaume, 112",
    "sg:city":"Cardedeu",
    "sg:orig_category":"Panader\u00cdas, Panader\u00cdas",
    "sg:phone":"+34 938 46 10 68",
    "sg:postcode":"08440",
    "sg:province":"Barcelona",
    "wof:name":"Ricos Marti Maria Dolors",
    "wof:placetype":"venue"
},
  "geometry": {"coordinates":[2.3608601093,41.6370773315],"type":"Point"}
}