{
  "type": "Feature",
  "properties": {
    "iso:country":"ES",
    "sg:address":"Avda Europa, 12",
    "sg:city":"Pozuelo De Alarcon",
    "sg:orig_category":"Caf\u00c9s, Bares, Cervecer\u00cdas",
    "sg:phone":"+34 913 51 36 70",
    "sg:postcode":"28224",
    "sg:province":"Madrid",
    "sg:website":"www.viena-capellanes.com",
    "wof:name":"Viena Capellanes",
    "wof:placetype":"venue"
},
  "geometry": {"coordinates":[-3.7969949245,40.4361038208],"type":"Point"}
}