{
  "type": "Feature",
  "properties": {
    "addr:full":"Carrer de Juan De Mena, 5 Barcelona Barcelona 08035",
    "addr:housenumber":"5",
    "addr:postcode":"08035",
    "addr:street":"Carrer De Juan De Mena",
    "iso:country":"ES",
    "sg:address":"Carrer de Juan De Mena, 5",
    "sg:city":"Barcelona",
    "sg:orig_category":"Alimentaci\u00d3n General (al Por Menor)",
    "sg:phone":"+34 934 28 05 94",
    "sg:postcode":"08035",
    "sg:province":"Barcelona",
    "wof:name":"Ruiz Pintor Jose",
    "wof:placetype":"venue"
},
  "geometry": {"coordinates":[2.1477360725,41.4308395386],"type":"Point"}
}