{
  "type": "Feature",
  "properties": {
    "iso:country":"ES",
    "sg:address":"Carrer de Napols, 19",
    "sg:city":"Sabadell",
    "sg:orig_category":"Lencer\u00cda Femenina, Corseter\u00cda, Trajes De Ba\u00d1o (al Por Menor)",
    "sg:phone":"+34 937 23 46 93",
    "sg:postcode":"08207",
    "sg:province":"Barcelona",
    "wof:name":"Intima 2000 S.l.",
    "wof:placetype":"venue"
},
  "geometry": {"coordinates":[2.0878150463,41.5653381348],"type":"Point"}
}