{
  "type": "Feature",
  "properties": {
    "iso:country":"ES",
    "sg:address":"C/ Sants Metges, S/n",
    "sg:city":"Elche",
    "sg:orig_category":"Orquestas De Variedades",
    "sg:phone":"+34 965 42 79 16",
    "sg:postcode":"03203",
    "sg:province":"Alicante",
    "wof:name":"Orquesta De Camara Ciudad De Elche",
    "wof:placetype":"venue"
},
  "geometry": {"coordinates":[-0.696344018,38.2647399902],"type":"Point"}
}