{
  "type": "Feature",
  "properties": {
    "addr:full":"Calle de Pio Baroja, 22 Playa Del Hombre Las Palmas 35214",
    "addr:housenumber":"22",
    "addr:postcode":"35214",
    "addr:street":"Calle De Pio Baroja;Del Hombre Las",
    "iso:country":"ES",
    "sg:address":"Calle de Pio Baroja, 22",
    "sg:city":"Playa Del Hombre",
    "sg:orig_category":"Inmobiliaria (agencias)",
    "sg:phone":"+34 928 70 74 87",
    "sg:postcode":"35214",
    "sg:province":"Las Palmas",
    "wof:name":"Protufia Canarias S.l.",
    "wof:placetype":"venue"
},
  "geometry": {"coordinates":[-15.3771085739,27.9981651306],"type":"Point"}
}