{
  "type": "Feature",
  "properties": {
    "iso:country":"ES",
    "sg:address":"Calle de Arrasate, 24",
    "sg:city":"Donostia-san Sebastian",
    "sg:orig_category":"Instalaci\u00d3n, Reparaci\u00d3n De Calefacci\u00d3n El\u00c9ctrica",
    "sg:phone":"+34 943 42 93 80",
    "sg:postcode":"20005",
    "sg:province":"Guip\u00f9zcoa",
    "wof:name":"Tecnotrac Tecnologias Tecnicas S.l",
    "wof:placetype":"venue"
},
  "geometry": {"coordinates":[-1.9820890427,43.3182106018],"type":"Point"}
}