{
  "type": "Feature",
  "properties": {
    "addr:full":"Ctra Losas (de Las), 108 Parador Hortichuelas Almer\u00eda 04720",
    "addr:housenumber":"108",
    "addr:postcode":"04720",
    "addr:street":"Ctra Losas De Las;Almeri\u0301A",
    "iso:country":"ES",
    "sg:address":"Ctra Losas (de Las), 108",
    "sg:city":"Parador Hortichuelas",
    "sg:orig_category":"Promotores Constructores",
    "sg:phone":"+34 950 34 40 57",
    "sg:postcode":"04720",
    "sg:province":"Almer\u00eda",
    "wof:name":"Promociones Archirub S.l.",
    "wof:placetype":"venue"
},
  "geometry": {"coordinates":[-2.6007230282,36.8032073975],"type":"Point"}
}