{
  "type": "Feature",
  "properties": {
    "iso:country":"ES",
    "sg:address":"Av Jocs Olimpics (dels), 10",
    "sg:city":"Reus",
    "sg:orig_category":"Equipo De Refrigeraci\u00d3n Industrial",
    "sg:phone":"+34 977 31 10 10",
    "sg:postcode":"43202",
    "sg:province":"Tarragona",
    "wof:name":"Mu\u00f1oz Gasca Antonio",
    "wof:placetype":"venue"
},
  "geometry": {"coordinates":[1.0986130238,41.1589431763],"type":"Point"}
}