{
  "type": "Feature",
  "properties": {
    "addr:full":"Carrer de Sant Joaquim, 133 Santa Coloma De Gramenet Barcelona 08922",
    "addr:housenumber":"133",
    "addr:postcode":"08922",
    "addr:street":"Carrer De Sant Joaquim",
    "iso:country":"ES",
    "sg:address":"Carrer de Sant Joaquim, 133",
    "sg:city":"Santa Coloma De Gramenet",
    "sg:orig_category":"Materiales De Aislamiento T\u00c9rmico Y Ac\u00dastico",
    "sg:phone":"+34 934 66 33 95",
    "sg:postcode":"08922",
    "sg:province":"Barcelona",
    "wof:name":"Lambda 91 S.l.",
    "wof:placetype":"venue"
},
  "geometry": {"coordinates":[2.2079110146,41.4457969666],"type":"Point"}
}