{
  "type": "Feature",
  "properties": {
    "iso:country":"ES",
    "sg:address":"Calle de Pintor Cabrera, 26",
    "sg:city":"Alacant",
    "sg:orig_category":"Psic\u00d3logos",
    "sg:phone":"+34 965 12 29 37",
    "sg:postcode":"03003",
    "sg:province":"Alicante",
    "wof:name":"Ortu\u00f1o Iba\u00f1ez Vicente",
    "wof:placetype":"venue"
},
  "geometry": {"coordinates":[-0.4927339852,38.3442420959],"type":"Point"}
}