{
  "type": "Feature",
  "properties": {
    "iso:country":"ES",
    "sg:address":"Carrer de Santjoanistes, 17",
    "sg:city":"Barcelona",
    "sg:orig_category":"Bares, Piano",
    "sg:phone":"+34 932 17 19 29",
    "sg:postcode":"08006",
    "sg:province":"Barcelona",
    "wof:name":"Banzais Informatica S.r.l.",
    "wof:placetype":"venue"
},
  "geometry": {"coordinates":[2.1475260258,41.4028968811],"type":"Point"}
}