{
  "type": "Feature",
  "properties": {
    "addr:full":"Calle de General Palafox, S/n Alfajarin Zaragoza 50172",
    "addr:housenumber":"s",
    "addr:postcode":"50172",
    "addr:street":"Calle De General Palafox;/ N Alfajarin",
    "iso:country":"ES",
    "sg:address":"Calle de General Palafox, S/n",
    "sg:city":"Alfajarin",
    "sg:orig_category":"Polideportivos",
    "sg:phone":"+34 976 10 03 86",
    "sg:postcode":"50172",
    "sg:province":"Zaragoza",
    "wof:name":"Patronato Muncipal De Deportes De Alfajarin",
    "wof:placetype":"venue"
},
  "geometry": {"coordinates":[-0.7022070289,41.6124420166],"type":"Point"}
}