{
  "type": "Feature",
  "properties": {
    "addr:full":"Calle de Monzon, 12 Sevilla Sevilla 41012",
    "addr:housenumber":"12",
    "addr:postcode":"41012",
    "addr:street":"Calle De Monzon",
    "iso:country":"ES",
    "sg:address":"Calle de Monzon, 12",
    "sg:city":"Sevilla",
    "sg:orig_category":"Universidades",
    "sg:phone":"+34 954 23 80 49",
    "sg:postcode":"41012",
    "sg:province":"Sevilla",
    "wof:name":"Academia Monzon 12 S.l.",
    "wof:placetype":"venue"
},
  "geometry": {"coordinates":[-5.9857378006,37.3603096008],"type":"Point"}
}