{
  "type": "Feature",
  "properties": {
    "addr:full":"Urb Picos Nagueles, 3 Marbella M\u00e1laga 29600",
    "addr:housenumber":"3",
    "addr:postcode":"29600",
    "addr:street":"Urb Picos Nagueles;Ma\u0301Laga",
    "iso:country":"ES",
    "sg:address":"Urb Picos Nagueles, 3",
    "sg:city":"Marbella",
    "sg:orig_category":"Agencias Y Agentes Comerciales, Representantes",
    "sg:phone":"+34 952 86 59 74",
    "sg:postcode":"29600",
    "sg:province":"M\u00e1laga",
    "wof:name":"Itjeshorst Geert Jan",
    "wof:placetype":"venue"
},
  "geometry": {"coordinates":[-4.8833007812,36.5079956055],"type":"Point"}
}