{
  "type": "Feature",
  "properties": {
    "addr:full":"Calle de Monasterio De Siresa, 1 Zaragoza Zaragoza 50002",
    "addr:housenumber":"1",
    "addr:postcode":"50002",
    "addr:street":"Calle De Monasterio De Siresa",
    "iso:country":"ES",
    "sg:address":"Calle de Monasterio De Siresa, 1",
    "sg:city":"Zaragoza",
    "sg:orig_category":"Pescader\u00cdas (al Por Menor)",
    "sg:phone":"+34 976 49 28 07",
    "sg:postcode":"50002",
    "sg:province":"Zaragoza",
    "wof:name":"Torrejon Garzon Joaquin",
    "wof:placetype":"venue"
},
  "geometry": {"coordinates":[-0.8619859815,41.6471748352],"type":"Point"}
}