{
  "type": "Feature",
  "properties": {
    "iso:country":"ES",
    "sg:address":"Calle de Sanclemente, 15",
    "sg:city":"Zaragoza",
    "sg:orig_category":"Asociaciones Y Clubs Deportivos",
    "sg:phone":"+34 976 22 64 70",
    "sg:postcode":"50001",
    "sg:province":"Zaragoza",
    "wof:name":"Laborda Ferruz Maria Gloria",
    "wof:placetype":"venue"
},
  "geometry": {"coordinates":[-0.8811647296,41.6495399475],"type":"Point"}
}