{
  "type": "Feature",
  "properties": {
    "addr:full":"Barreiro(vilaza), 4 Barreiro Pontevedra 36380",
    "addr:housenumber":"4",
    "addr:postcode":"36380",
    "addr:street":"Vilaza",
    "iso:country":"ES",
    "sg:address":"Barreiro(vilaza), 4",
    "sg:city":"Barreiro",
    "sg:orig_category":"Construcciones Met\u00c1licas",
    "sg:phone":"+34 986 36 39 12",
    "sg:postcode":"36380",
    "sg:province":"Pontevedra",
    "wof:name":"Kial Mi\u00f1or Sl",
    "wof:placetype":"venue"
},
  "geometry": {"coordinates":[-8.7611093521,42.1116867065],"type":"Point"}
}