{
  "type": "Feature",
  "properties": {
    "addr:full":"Calle de Mayor, 9 Cabezo Torres Murcia 30110",
    "addr:housenumber":"9",
    "addr:postcode":"30110",
    "addr:street":"Calle De Mayor",
    "iso:country":"ES",
    "sg:address":"Calle de Mayor, 9",
    "sg:city":"Cabezo Torres",
    "sg:orig_category":"Librer\u00cdas",
    "sg:phone":"+34 968 30 57 16",
    "sg:postcode":"30110",
    "sg:province":"Murcia",
    "wof:name":"Lopez Perez Amparo",
    "wof:placetype":"venue"
},
  "geometry": {"coordinates":[-1.1357469559,38.0178451538],"type":"Point"}
}