{
  "type": "Feature",
  "properties": {
    "iso:country":"ES",
    "sg:address":"Carrer de Bonifas, 2",
    "sg:city":"Valls",
    "sg:orig_category":"Arquitectos",
    "sg:phone":"+34 977 61 49 29",
    "sg:postcode":"43800",
    "sg:province":"Tarragona",
    "wof:name":"Mellado Gilabert Ana Maria",
    "wof:placetype":"venue"
},
  "geometry": {"coordinates":[1.2532900572,41.287021637],"type":"Point"}
}