{
  "type": "Feature",
  "properties": {
    "addr:full":"Calle de Algeciras, 21 Carmona Sevilla 41410",
    "addr:housenumber":"21",
    "addr:postcode":"41410",
    "addr:street":"Calle De Algeciras",
    "iso:country":"ES",
    "sg:address":"Calle de Algeciras, 21",
    "sg:city":"Carmona",
    "sg:orig_category":"Tapicer\u00cdas",
    "sg:phone":"+34 954 14 14 61",
    "sg:postcode":"41410",
    "sg:province":"Sevilla",
    "wof:name":"Tapizados La Rosa S.l.",
    "wof:placetype":"venue"
},
  "geometry": {"coordinates":[-5.6452870369,37.4735565186],"type":"Point"}
}