{
  "type": "Feature",
  "properties": {
    "iso:country":"ES",
    "sg:address":"Calle de Santa Alicia, 18",
    "sg:city":"Madrid",
    "sg:orig_category":"Reposter\u00cdas",
    "sg:phone":"+34 914 78 50 03",
    "sg:postcode":"28053",
    "sg:province":"Madrid",
    "wof:name":"Alcolea Esteban Jose Luis",
    "wof:placetype":"venue"
},
  "geometry": {"coordinates":[-3.6665644646,40.3870925903],"type":"Point"}
}