{
  "type": "Feature",
  "properties": {
    "addr:full":"Calle de Travessia, 2 Novelda Alicante 03660",
    "addr:housenumber":"2",
    "addr:postcode":"03660",
    "addr:street":"Calle De Travessia",
    "iso:country":"ES",
    "sg:address":"Calle de Travessia, 2",
    "sg:city":"Novelda",
    "sg:orig_category":"Cajas De Ahorro",
    "sg:phone":"+34 965 60 39 05",
    "sg:postcode":"03660",
    "sg:province":"Alicante",
    "sg:website":"www.cajamurcia.es",
    "wof:name":"Caja De Ahorros De Murcia",
    "wof:placetype":"venue"
},
  "geometry": {"coordinates":[-0.7646890283,38.385471344],"type":"Point"}
}