{
  "type": "Feature",
  "properties": {
    "iso:country":"ES",
    "sg:address":"Carrer de Cami Vell De Canovelles, 32",
    "sg:city":"Granollers",
    "sg:orig_category":"Cr\u00cda De Animales",
    "sg:phone":"+34 938 49 15 61",
    "sg:postcode":"08403",
    "sg:province":"Barcelona",
    "wof:name":"Font Viroles Jose",
    "wof:placetype":"venue"
},
  "geometry": {"coordinates":[2.2823870182,41.6124534607],"type":"Point"}
}