{
  "type": "Feature",
  "properties": {
    "addr:full":"Avda Ribera-puerto Banus, 9 Nueva Andalucia M\u00e1laga 29660",
    "addr:housenumber":"9",
    "addr:postcode":"29660",
    "addr:street":"Avda Ribera-Puerto Banus;Ma\u0301Laga",
    "iso:country":"ES",
    "sg:address":"Avda Ribera-puerto Banus, 9",
    "sg:city":"Nueva Andalucia",
    "sg:orig_category":"Promotores Constructores",
    "sg:phone":"+34 952 90 81 17",
    "sg:postcode":"29660",
    "sg:province":"M\u00e1laga",
    "wof:name":"Ondobide S. A.",
    "wof:placetype":"venue"
},
  "geometry": {"coordinates":[-4.9540901184,36.4891586304],"type":"Point"}
}