{
  "type": "Feature",
  "properties": {
    "iso:country":"ES",
    "sg:address":"Carretera De Sevilla, Km. 0116,0",
    "sg:city":"Ronda",
    "sg:orig_category":"Restaurantes",
    "sg:phone":"+34 952 87 95 30",
    "sg:postcode":"29400",
    "sg:province":"M\u00e1laga",
    "wof:name":"Ute Restauracion Sur",
    "wof:placetype":"venue"
},
  "geometry": {"coordinates":[-5.1662788391,36.7417945862],"type":"Point"}
}