{
  "type": "Feature",
  "properties": {
    "addr:full":"Pase Cristobal Colon, S/n Sevilla Sevilla 41001",
    "addr:postcode":"41001",
    "addr:street":"Cristobal Colon S / N",
    "iso:country":"ES",
    "sg:address":"Pase Cristobal Colon, S/n",
    "sg:city":"Sevilla",
    "sg:orig_category":"Museos",
    "sg:phone":"+34 954 22 24 19",
    "sg:postcode":"41001",
    "sg:province":"Sevilla",
    "wof:name":"Torre Del Oro",
    "wof:placetype":"venue"
},
  "geometry": {"coordinates":[-6.0010838509,37.3871307373],"type":"Point"}
}