{
  "type": "Feature",
  "properties": {
    "iso:country":"ES",
    "sg:address":"Plaz Campas Las, 7",
    "sg:city":"Tineo",
    "sg:orig_category":"Ense\u00d1anza: Idiomas",
    "sg:phone":"+34 985 80 00 77",
    "sg:postcode":"33870",
    "sg:province":"Asturias",
    "wof:name":"Fernandez Alvarez Francisco Manuel",
    "wof:placetype":"venue"
},
  "geometry": {"coordinates":[-6.4165468216,43.3338775635],"type":"Point"}
}