{
  "type": "Feature",
  "properties": {
    "iso:country":"ES",
    "sg:address":"Calle de Factoria Matagorda, 32",
    "sg:city":"Pto Real",
    "sg:orig_category":"Limpieza Industrial",
    "sg:phone":"+34 956 47 24 68",
    "sg:postcode":"11510",
    "sg:province":"C\u00e1diz",
    "wof:name":"Prolimin S.l.",
    "wof:placetype":"venue"
},
  "geometry": {"coordinates":[-6.1948108673,36.5288658142],"type":"Point"}
}