{
  "type": "Feature",
  "properties": {
    "iso:country":"ES",
    "sg:address":"Calle de Lope De Rueda, 278",
    "sg:city":"Malaga",
    "sg:orig_category":"Inform\u00c1tica (estudios, Servicios, Asesor\u00cda, Formaci\u00d3n)",
    "sg:phone":"+34 952 10 05 84",
    "sg:postcode":"29190",
    "sg:province":"M\u00e1laga",
    "wof:name":"Sistemas Informaticos Malaga S.l.",
    "wof:placetype":"venue"
},
  "geometry": {"coordinates":[-4.4911370277,36.7448501587],"type":"Point"}
}