{
  "type": "Feature",
  "properties": {
    "iso:country":"ES",
    "sg:address":"Pase Maria Agustin, 13",
    "sg:city":"Zaragoza",
    "sg:orig_category":"M\u00c9dicos: Psiquiatr\u00cda",
    "sg:phone":"+34 976 23 86 63",
    "sg:postcode":"50004",
    "sg:province":"Zaragoza",
    "wof:name":"Porcel Berdala Miguel Angel",
    "wof:placetype":"venue"
},
  "geometry": {"coordinates":[-0.8890910149,41.6504325867],"type":"Point"}
}