{
  "type": "Feature",
  "properties": {
    "addr:full":"Rua Greco (el), 8 Ourense Ourense 32002",
    "addr:postcode":"32002",
    "addr:street":"Rua Greco El",
    "iso:country":"ES",
    "sg:address":"Rua Greco (el), 8",
    "sg:city":"Ourense",
    "sg:orig_category":"Frutas, Legumbres Frescas Y Tempranas (al Por Menor)",
    "sg:phone":"+34 988 23 38 33",
    "sg:postcode":"32002",
    "sg:province":"Ourense",
    "wof:name":"Alvarez Perez Maria Luisa",
    "wof:placetype":"venue"
},
  "geometry": {"coordinates":[-7.8728399277,42.341594696],"type":"Point"}
}