{
  "type": "Feature",
  "properties": {
    "addr:full":"Calle de Marques De Nervion, 104 Sevilla Sevilla 41005",
    "addr:housenumber":"104",
    "addr:postcode":"41005",
    "addr:street":"Calle De Marques De Nervion",
    "iso:country":"ES",
    "sg:address":"Calle de Marques De Nervion, 104",
    "sg:city":"Sevilla",
    "sg:orig_category":"Asilos De Ancianos. Centros Privados",
    "sg:phone":"+34 954 92 30 80",
    "sg:postcode":"41005",
    "sg:province":"Sevilla",
    "wof:name":"Residencia Geriatrica Virgen Del Carmen S.l.",
    "wof:placetype":"venue"
},
  "geometry": {"coordinates":[-5.9687991142,37.3791885376],"type":"Point"}
}