{
  "type": "Feature",
  "properties": {
    "iso:country":"ES",
    "sg:address":"Calle de Rio, 3",
    "sg:city":"Guadalajara",
    "sg:orig_category":"Arquitectos",
    "sg:phone":"+34 949 21 91 04",
    "sg:postcode":"19004",
    "sg:province":"Guadalajara",
    "wof:name":"Estudio 2 Arquitectura Jak S.l.",
    "wof:placetype":"venue"
},
  "geometry": {"coordinates":[-3.1719069481,40.6389427185],"type":"Point"}
}