{
  "type": "Feature",
  "properties": {
    "iso:country":"ES",
    "sg:address":"Avda Navarra, 77",
    "sg:city":"Errenteria",
    "sg:orig_category":"Farmacias",
    "sg:phone":"+34 943 34 45 49",
    "sg:postcode":"20100",
    "sg:province":"Guip\u00f9zcoa",
    "wof:name":"Aragon Garbizu Itziar",
    "wof:placetype":"venue"
},
  "geometry": {"coordinates":[-1.903383255,43.3149414062],"type":"Point"}
}