{
  "type": "Feature",
  "properties": {
    "iso:country":"ES",
    "sg:address":"Carr Onyar, 6",
    "sg:city":"Quart",
    "sg:orig_category":"Bosques (trabajos, Asesor\u00cda, Gesti\u00d3n)",
    "sg:phone":"+34 972 46 92 74",
    "sg:postcode":"17242",
    "sg:province":"Girona",
    "wof:name":"Valenti Ferran Desbrossments S.l.",
    "wof:placetype":"venue"
},
  "geometry": {"coordinates":[2.8420550823,41.9365539551],"type":"Point"}
}