{
  "type": "Feature",
  "properties": {
    "addr:full":"Calle de Carril Del Conde, 106 Madrid Madrid 28043",
    "addr:housenumber":"106",
    "addr:postcode":"28043",
    "addr:street":"Calle De Carril Del Conde",
    "iso:country":"ES",
    "sg:address":"Calle de Carril Del Conde, 106",
    "sg:city":"Madrid",
    "sg:orig_category":"Administradores De Bienes Y Delegados De Comunidades De Propietarios",
    "sg:phone":"+34 913 00 33 02",
    "sg:postcode":"28043",
    "sg:province":"Madrid",
    "wof:name":"Administracion De Fincas Y Servicios A Comunidades S.l.",
    "wof:placetype":"venue"
},
  "geometry": {"coordinates":[-3.6530482769,40.4629936218],"type":"Point"}
}