{
  "type": "Feature",
  "properties": {
    "addr:full":"Calle de Orense, 5 Tui Pontevedra 36700",
    "addr:housenumber":"5",
    "addr:postcode":"36700",
    "addr:street":"Calle De Orense",
    "iso:country":"ES",
    "sg:address":"Calle de Orense, 5",
    "sg:city":"Tui",
    "sg:orig_category":"Tintes (fabricaci\u00d3n, Al Por Mayor)",
    "sg:phone":"+34 986 60 16 10",
    "sg:postcode":"36700",
    "sg:province":"Pontevedra",
    "wof:name":"Tintoreria Galicia S.l.",
    "wof:placetype":"venue"
},
  "geometry": {"coordinates":[-8.6464118958,42.0497283936],"type":"Point"}
}