{
  "type": "Feature",
  "properties": {
    "addr:full":"Carrer de Eduard Tubau, 20 Barcelona Barcelona 08016",
    "addr:housenumber":"20",
    "addr:postcode":"08016",
    "addr:street":"Carrer De Eduard Tubau",
    "iso:country":"ES",
    "sg:address":"Carrer de Eduard Tubau, 20",
    "sg:city":"Barcelona",
    "sg:orig_category":"Instalaci\u00d3n, Mantenimiento De Porteros Electr\u00d3nicos Y Controles De Acceso",
    "sg:phone":"+34 933 50 33 66",
    "sg:postcode":"08016",
    "sg:province":"Barcelona",
    "wof:name":"Sevsat 2000 S.l.",
    "wof:placetype":"venue"
},
  "geometry": {"coordinates":[2.1760818958,41.437828064],"type":"Point"}
}