{
  "type": "Feature",
  "properties": {
    "iso:country":"ES",
    "sg:address":"Calle de Almirante, 6",
    "sg:city":"Madrid",
    "sg:orig_category":"Ropa Para Caballeros (al Por Menor)",
    "sg:phone":"+34 915 21 81 83",
    "sg:postcode":"28004",
    "sg:province":"Madrid",
    "wof:name":"Almirante Seis S.l.",
    "wof:placetype":"venue"
},
  "geometry": {"coordinates":[-3.6950194836,40.4224967957],"type":"Point"}
}