{
  "type": "Feature",
  "properties": {
    "iso:country":"ES",
    "sg:address":"Calle de Sevilla, 27",
    "sg:city":"Malaga",
    "sg:orig_category":"Carnicer\u00cdas, Carnicer\u00cdas",
    "sg:phone":"+34 952 39 39 16",
    "sg:postcode":"29009",
    "sg:province":"M\u00e1laga",
    "wof:name":"Artesacarne S.l.",
    "wof:placetype":"venue"
},
  "geometry": {"coordinates":[-4.4294900894,36.72605896],"type":"Point"}
}