{
  "type": "Feature",
  "properties": {
    "iso:country":"ES",
    "sg:address":"Calle de Castilla (de), 6",
    "sg:city":"Mejorada Campo",
    "sg:orig_category":"Metacrilato: Art\u00cdculos (fabricaci\u00d3n Y Al Por Mayor)",
    "sg:phone":"+34 916 79 12 50",
    "sg:postcode":"28840",
    "sg:province":"Madrid",
    "wof:name":"Lc Se\u00f1alizacion Sociedad Cooperativa Madrile\u00f1a",
    "wof:placetype":"venue"
},
  "geometry": {"coordinates":[-3.4837865829,40.3889160156],"type":"Point"}
}