{
  "type": "Feature",
  "properties": {
    "addr:full":"Calle de Recoletos, 19 Madrid Madrid 28001",
    "addr:housenumber":"19",
    "addr:postcode":"madrid;28001",
    "addr:street":"Calle De Recoletos",
    "iso:country":"ES",
    "sg:address":"Calle de Recoletos, 19",
    "sg:city":"Madrid",
    "sg:orig_category":"Bisuter\u00cda, Joyer\u00cda, Relojer\u00cda (al Por Menor)",
    "sg:phone":"+34 914 26 22 51",
    "sg:postcode":"28001",
    "sg:province":"Madrid",
    "wof:name":"Cruz Ansoain S.l.",
    "wof:placetype":"venue"
},
  "geometry": {"coordinates":[-3.6891169548,40.4215774536],"type":"Point"}
}