{
  "type": "Feature",
  "properties": {
    "iso:country":"ES",
    "sg:address":"Calle de Juan Jose Ruano, 1",
    "sg:city":"Santo\u00f1a",
    "sg:orig_category":"Ropa Para Ni\u00d1os (al Por Menor)",
    "sg:phone":"+34 942 67 10 26",
    "sg:postcode":"39740",
    "sg:province":"Cantabria",
    "wof:name":"Garay Herreria Maria Asuncion",
    "wof:placetype":"venue"
},
  "geometry": {"coordinates":[-3.4562718868,43.4415626526],"type":"Point"}
}