{
  "type": "Feature",
  "properties": {
    "addr:full":"Calle de Bilbao, 7 San Sebastian De Los Reyes Madrid 28700",
    "addr:housenumber":"7",
    "addr:postcode":"28700",
    "addr:street":"Calle De Bilbao",
    "iso:country":"ES",
    "sg:address":"Calle de Bilbao, 7",
    "sg:city":"San Sebastian De Los Reyes",
    "sg:orig_category":"Caf\u00c9s, Bares, Cervecer\u00cdas",
    "sg:phone":"+34 916 51 87 29",
    "sg:postcode":"28700",
    "sg:province":"Madrid",
    "wof:name":"Mu\u00f1oz Lara Cayetano",
    "wof:placetype":"venue"
},
  "geometry": {"coordinates":[-3.6257526875,40.5488815308],"type":"Point"}
}