{
  "type": "Feature",
  "properties": {
    "addr:full":"Alfageme, 52 Trobajo Camino Le\u00f3n 24010",
    "addr:housenumber":"52",
    "addr:postcode":"24010",
    "addr:street":"Alfageme;Camino Leo\u0301N",
    "iso:country":"ES",
    "sg:address":"Alfageme, 52",
    "sg:city":"Trobajo Camino",
    "sg:orig_category":"Contenedores (mercanc\u00cdas)",
    "sg:phone":"+34 987 80 29 10",
    "sg:postcode":"24010",
    "sg:province":"Le\u00f3n",
    "wof:name":"Hermanos Garcia Blanco S. L.",
    "wof:placetype":"venue"
},
  "geometry": {"coordinates":[-5.6055607796,42.5929374695],"type":"Point"}
}