{
  "type": "Feature",
  "properties": {
    "iso:country":"ES",
    "sg:address":"Carrer de Carrio, 20",
    "sg:city":"Manresa",
    "sg:orig_category":"Iglesia Cat\u00d3lica",
    "sg:phone":"+34 938 72 53 33",
    "sg:postcode":"08242",
    "sg:province":"Barcelona",
    "wof:name":"Bisbat De Vic",
    "wof:placetype":"venue"
},
  "geometry": {"coordinates":[1.8230210543,41.7285652161],"type":"Point"}
}