{
  "type": "Feature",
  "properties": {
    "addr:full":"Calle de Mayor, 176 Alcantarilla Murcia 30820",
    "addr:housenumber":"176",
    "addr:postcode":"30820",
    "addr:street":"Calle De Mayor",
    "iso:country":"ES",
    "sg:address":"Calle de Mayor, 176",
    "sg:city":"Alcantarilla",
    "sg:orig_category":"Cl\u00cdnicas Dentales",
    "sg:phone":"+34 968 80 77 95",
    "sg:postcode":"30820",
    "sg:province":"Murcia",
    "wof:name":"Clinica Dental Doctores Tomas Tapia Y Ortiz Ortiz C.b.",
    "wof:placetype":"venue"
},
  "geometry": {"coordinates":[-1.2185180187,37.9670524597],"type":"Point"}
}