{
  "type": "Feature",
  "properties": {
    "addr:full":"Carrer de Arago, 277 Barcelona Barcelona 08007",
    "addr:housenumber":"277",
    "addr:postcode":"08007",
    "addr:street":"Carrer De Arago",
    "iso:country":"ES",
    "sg:address":"Carrer de Arago, 277",
    "sg:city":"Barcelona",
    "sg:orig_category":"Inmobiliaria (agencias)",
    "sg:phone":"+34 932 15 68 13",
    "sg:postcode":"08007",
    "sg:province":"Barcelona",
    "wof:name":"Stilcasa S. A.",
    "wof:placetype":"venue"
},
  "geometry": {"coordinates":[2.1658089161,41.3930625916],"type":"Point"}
}