{
  "type": "Feature",
  "properties": {
    "iso:country":"ES",
    "sg:address":"Calle de Sanchez Madrigal, 11",
    "sg:city":"San Bartolome",
    "sg:orig_category":"Arquitectos",
    "sg:phone":"+34 968 21 88 49",
    "sg:postcode":"30004",
    "sg:province":"Murcia",
    "wof:name":"Ortu\u00f1o Ya\u00f1ez Demetrio",
    "wof:placetype":"venue"
},
  "geometry": {"coordinates":[-1.1303009987,37.9854354858],"type":"Point"}
}