{
  "type": "Feature",
  "properties": {
    "iso:country":"ES",
    "sg:address":"Calle de Cava Baja, 31",
    "sg:city":"Madrid",
    "sg:orig_category":"Molduras, Junquillos, Listones Y Molduras Perforadas",
    "sg:phone":"+34 913 66 31 10",
    "sg:postcode":"28005",
    "sg:province":"Madrid",
    "wof:name":"Izquierdo Sanchez Maria Carmen",
    "wof:placetype":"venue"
},
  "geometry": {"coordinates":[-3.7098908424,40.4120330811],"type":"Point"}
}