{
  "type": "Feature",
  "properties": {
    "iso:country":"ES",
    "sg:address":"Calle de Viera Y Clavijo, 28",
    "sg:city":"Cerruda",
    "sg:orig_category":"Aparcamientos (infraestructuras, Accesorios)",
    "sg:phone":"+34 928 79 13 57",
    "sg:postcode":"35110",
    "sg:province":"Las Palmas",
    "wof:name":"Sanchez Medina Leonardo",
    "wof:placetype":"venue"
},
  "geometry": {"coordinates":[-15.4485340118,27.8392906189],"type":"Point"}
}