{
  "type": "Feature",
  "properties": {
    "addr:full":"Carrer de Motors, 324 Hospitalet Llobregat Barcelona 08908",
    "addr:housenumber":"324",
    "addr:postcode":"08908",
    "addr:street":"Carrer",
    "iso:country":"ES",
    "sg:address":"Carrer de Motors, 324",
    "sg:city":"Hospitalet Llobregat",
    "sg:orig_category":"Contenedores (mercanc\u00cdas)",
    "sg:phone":"+34 933 36 26 97",
    "sg:postcode":"08908",
    "sg:province":"Barcelona",
    "wof:name":"Transfont S.l.",
    "wof:placetype":"venue"
},
  "geometry": {"coordinates":[2.1213600636,41.3452911377],"type":"Point"}
}