{
  "type": "Feature",
  "properties": {
    "iso:country":"ES",
    "sg:address":"Calle de Cuartel Del Este, 8",
    "sg:city":"Miranda Ebro",
    "sg:orig_category":"Empresarios",
    "sg:phone":"+34 947 33 63 19",
    "sg:postcode":"09200",
    "sg:province":"Burgos",
    "wof:name":"Comunidad Propietarios Cuartel Del Este,n\u00ba8",
    "wof:placetype":"venue"
},
  "geometry": {"coordinates":[-2.93947649,42.689655304],"type":"Point"}
}