{
  "type": "Feature",
  "properties": {
    "addr:full":"Avda Portugal, 6 Jerez De Los Caballeros Badajoz 06380",
    "addr:housenumber":"6",
    "addr:postcode":"06380",
    "addr:street":"Avda Portugal",
    "iso:country":"ES",
    "sg:address":"Avda Portugal, 6",
    "sg:city":"Jerez De Los Caballeros",
    "sg:orig_category":"Escotaduras, Torneados",
    "sg:phone":"+34 924 73 17 63",
    "sg:postcode":"06380",
    "sg:province":"Badajoz",
    "wof:name":"Mecanizados David Granado S.l",
    "wof:placetype":"venue"
},
  "geometry": {"coordinates":[-6.7678670883,38.3229064941],"type":"Point"}
}