{
  "type": "Feature",
  "properties": {
    "addr:full":"Rua Varsovia (de), 4 Santiago De Compostela La Coru\u00f1a 15707",
    "addr:housenumber":"4",
    "addr:postcode":"15707",
    "addr:street":"Rua Varsovia De;Corun\u0303A",
    "iso:country":"ES",
    "sg:address":"Rua Varsovia (de), 4",
    "sg:city":"Santiago De Compostela",
    "sg:orig_category":"Abogados",
    "sg:phone":"+34 981 56 34 26",
    "sg:postcode":"15707",
    "sg:province":"La Coru\u00f1a",
    "wof:name":"Ber Y Mor Abogados S.l.",
    "wof:placetype":"venue"
},
  "geometry": {"coordinates":[-8.5274839401,42.8833847046],"type":"Point"}
}