{
  "type": "Feature",
  "properties": {
    "iso:country":"ES",
    "sg:address":"Calle de Nicanor Guerrero, 9",
    "sg:city":"Monterrubio Serena",
    "sg:orig_category":"Farmacias",
    "sg:phone":"+34 924 61 01 82",
    "sg:postcode":"06427",
    "sg:province":"Badajoz",
    "wof:name":"Garcia Rejon Eloisa",
    "wof:placetype":"venue"
},
  "geometry": {"coordinates":[-5.4440069199,38.5882225037],"type":"Point"}
}