{
  "type": "Feature",
  "properties": {
    "addr:full":"Carr Major, 20 Alpicat Lleida 25110",
    "addr:housenumber":"20",
    "addr:postcode":"25110",
    "addr:street":"Carr Major",
    "iso:country":"ES",
    "sg:address":"Carr Major, 20",
    "sg:city":"Alpicat",
    "sg:orig_category":"Promotores Constructores",
    "sg:phone":"+34 973 73 68 32",
    "sg:postcode":"25110",
    "sg:province":"Lleida",
    "wof:name":"Felip Roure Promocions I Construccions S.l.",
    "wof:placetype":"venue"
},
  "geometry": {"coordinates":[0.5297340155,41.6597290039],"type":"Point"}
}