{
  "type": "Feature",
  "properties": {
    "iso:country":"ES",
    "sg:address":"Calle de Hinojosas, 9",
    "sg:city":"Puertollano",
    "sg:orig_category":"Asesor\u00cda De Formaci\u00d3n Y Gesti\u00d3n De Personal",
    "sg:phone":"+34 926 44 15 58",
    "sg:postcode":"13500",
    "sg:province":"Ciudad Real",
    "wof:name":"Fundacion Fislem",
    "wof:placetype":"venue"
},
  "geometry": {"coordinates":[-4.1116762161,38.7037239075],"type":"Point"}
}