{
  "type": "Feature",
  "properties": {
    "addr:full":"Calle de Briviesca, 21 Burgos Burgos 09004",
    "addr:housenumber":"21",
    "addr:postcode":"09004",
    "addr:street":"Calle De Briviesca",
    "iso:country":"ES",
    "sg:address":"Calle de Briviesca, 21",
    "sg:city":"Burgos",
    "sg:orig_category":"Molduras, Junquillos, Listones Y Molduras Perforadas",
    "sg:phone":"+34 947 27 00 20",
    "sg:postcode":"09004",
    "sg:province":"Burgos",
    "wof:name":"Iba\u00f1ez Vicario David",
    "wof:placetype":"venue"
},
  "geometry": {"coordinates":[-3.6905186176,42.3448257446],"type":"Point"}
}