{
  "type": "Feature",
  "properties": {
    "iso:country":"ES",
    "sg:address":"Pl Bages, 9",
    "sg:city":"Manresa",
    "sg:orig_category":"Molduras, Junquillos, Listones Y Molduras Perforadas",
    "sg:phone":"+34 938 73 10 69",
    "sg:postcode":"08242",
    "sg:province":"Barcelona",
    "wof:name":"Soler I Soler S.c.p",
    "wof:placetype":"venue"
},
  "geometry": {"coordinates":[1.8233749866,41.735534668],"type":"Point"}
}