{
  "type": "Feature",
  "properties": {
    "iso:country":"ES",
    "sg:address":"Alqueria Dolores, S/n",
    "sg:city":"Aldaia",
    "sg:orig_category":"Maquinaria Para Industrias Diversas",
    "sg:phone":"+34 961 51 98 10",
    "sg:postcode":"46960",
    "sg:province":"Valencia",
    "sg:website":"www.netocasion.com",
    "wof:name":"Red-net Maquinaria De Ocasion S.l.",
    "wof:placetype":"venue"
},
  "geometry": {"coordinates":[-0.4401170015,39.4649925232],"type":"Point"}
}