{
  "type": "Feature",
  "properties": {
    "iso:country":"ES",
    "sg:address":"Calle de Martinez De La Riva, 44",
    "sg:city":"Madrid",
    "sg:orig_category":"Inmobiliaria (agencias)",
    "sg:phone":"+34 914 77 02 30",
    "sg:postcode":"28053",
    "sg:province":"Madrid",
    "wof:name":"Sanchez Canalo Encarnacion",
    "wof:placetype":"venue"
},
  "geometry": {"coordinates":[-3.6658570766,40.3920021057],"type":"Point"}
}