{
  "type": "Feature",
  "properties": {
    "iso:country":"ES",
    "sg:address":"Calle de San Jose, 8",
    "sg:city":"Yecla",
    "sg:orig_category":"Ense\u00d1anza, Formaci\u00d3n Profesional: Aprendizaje",
    "sg:phone":"+34 968 75 00 00",
    "sg:postcode":"30510",
    "sg:province":"Murcia",
    "wof:name":"Ayuntamiento De Yecla",
    "wof:placetype":"venue"
},
  "geometry": {"coordinates":[-1.1148879528,38.6140403748],"type":"Point"}
}