{
  "type": "Feature",
  "properties": {
    "iso:country":"ES",
    "sg:address":"Avda Galicia, 56",
    "sg:city":"Ponferrada",
    "sg:orig_category":"Ingenier\u00cda, Centros De Estudios (diversos)",
    "sg:phone":"+34 987 40 98 38",
    "sg:postcode":"24400",
    "sg:province":"Le\u00f3n",
    "wof:name":"Joisto Sl",
    "wof:placetype":"venue"
},
  "geometry": {"coordinates":[-6.6120591164,42.554649353],"type":"Point"}
}