{
  "type": "Feature",
  "properties": {
    "iso:country":"ES",
    "sg:address":"Calle de Pescadores, 3",
    "sg:city":"Logro\u00f1o",
    "sg:orig_category":"Cristaler\u00cdas",
    "sg:phone":"+34 941 25 01 23",
    "sg:postcode":"26006",
    "sg:province":"La Rioja",
    "wof:name":"Hernandez Vinuesa Antonio",
    "wof:placetype":"venue"
},
  "geometry": {"coordinates":[-2.4036989212,42.46043396],"type":"Point"}
}