{
  "type": "Feature",
  "properties": {
    "iso:country":"ES",
    "sg:address":"Avda Reyes Catolicos, 4",
    "sg:city":"Alcantarilla",
    "sg:orig_category":"Herboristas (al Por Menor)",
    "sg:phone":"+34 968 89 19 83",
    "sg:postcode":"30820",
    "sg:province":"Murcia",
    "wof:name":"Martinez Fenoll Maria Dolores",
    "wof:placetype":"venue"
},
  "geometry": {"coordinates":[-1.2177419662,37.9698486328],"type":"Point"}
}