{
  "type": "Feature",
  "properties": {
    "iso:country":"ES",
    "sg:address":"Plaz Asuncion, 8",
    "sg:city":"Puertollano",
    "sg:orig_category":"Administradores De Bienes Y Delegados De Comunidades De Propietarios",
    "sg:phone":"+34 926 42 91 67",
    "sg:postcode":"13500",
    "sg:province":"Ciudad Real",
    "wof:name":"Comunidad De Propietarios Plaza De La Asuncion 8",
    "wof:placetype":"venue"
},
  "geometry": {"coordinates":[-4.1113371849,38.6864242554],"type":"Point"}
}