{
  "type": "Feature",
  "properties": {
    "iso:country":"ES",
    "sg:address":"Calle de Angel Matos, 15",
    "sg:city":"Oliva Frontera",
    "sg:orig_category":"Ropa Para Se\u00d1oras Y Caballeros (al Por Menor)",
    "sg:phone":"+34 924 75 44 90",
    "sg:postcode":"06120",
    "sg:province":"Badajoz",
    "wof:name":"Tienda 1",
    "wof:placetype":"venue"
},
  "geometry": {"coordinates":[-6.9201908112,38.2762908936],"type":"Point"}
}