{
  "type": "Feature",
  "properties": {
    "addr:full":"Calle de Hercules, 27 Alacant Alicante 03006",
    "addr:housenumber":"27",
    "addr:postcode":"03006",
    "addr:street":"Calle De Hercules",
    "iso:country":"ES",
    "sg:address":"Calle de Hercules, 27",
    "sg:city":"Alacant",
    "sg:orig_category":"Centros Empresariales",
    "sg:phone":"+34 965 11 73 14",
    "sg:postcode":"03006",
    "sg:province":"Alicante",
    "wof:name":"Mar 6 Consultora S.l.",
    "wof:placetype":"venue"
},
  "geometry": {"coordinates":[-0.511811018,38.346698761],"type":"Point"}
}