{
  "type": "Feature",
  "properties": {
    "addr:full":"Calle de Secundino Esnaola, 48 Donostia-san Sebastian Guip\u00f9zcoa 20001",
    "addr:housenumber":"48",
    "addr:postcode":"20001",
    "addr:street":"Calle De Secundino Esnaola",
    "iso:country":"ES",
    "sg:address":"Calle de Secundino Esnaola, 48",
    "sg:city":"Donostia-san Sebastian",
    "sg:orig_category":"Molduras, Junquillos, Listones Y Molduras Perforadas",
    "sg:phone":"+34 943 27 71 86",
    "sg:postcode":"20001",
    "sg:province":"Guip\u00f9zcoa",
    "wof:name":"Maria Luisa Lago Sanches Y Otro C.b",
    "wof:placetype":"venue"
},
  "geometry": {"coordinates":[-1.9704899788,43.3250427246],"type":"Point"}
}