{
  "type": "Feature",
  "properties": {
    "addr:full":"Calle de Santa Teresa, 5 Madrid Madrid 28004",
    "addr:housenumber":"5",
    "addr:postcode":"28004",
    "addr:street":"Calle De Santa Teresa",
    "iso:country":"ES",
    "sg:address":"Calle de Santa Teresa, 5",
    "sg:city":"Madrid",
    "sg:orig_category":"Centros Empresariales",
    "sg:phone":"+34 913 19 16 02",
    "sg:postcode":"28004",
    "sg:province":"Madrid",
    "wof:name":"Lopez Garrido Maria Jesus",
    "wof:placetype":"venue"
},
  "geometry": {"coordinates":[-3.6956670284,40.4258728027],"type":"Point"}
}