{
  "type": "Feature",
  "properties": {
    "addr:full":"Calle de Pozo De La Nieve, 3 Consuegra Toledo 45700",
    "addr:housenumber":"3",
    "addr:postcode":"45700",
    "addr:street":"Calle De Pozo De La Nieve",
    "iso:country":"ES",
    "sg:address":"Calle de Pozo De La Nieve, 3",
    "sg:city":"Consuegra",
    "sg:orig_category":"Imprenta",
    "sg:phone":"+34 925 48 02 11",
    "sg:postcode":"45700",
    "sg:province":"Toledo",
    "wof:name":"Imprenta Rodriguez S.l.",
    "wof:placetype":"venue"
},
  "geometry": {"coordinates":[-3.6057100296,39.4587516785],"type":"Point"}
}