{
  "type": "Feature",
  "properties": {
    "addr:full":"Pedro Malon De Chaide, 37 Iru\u00f1a Navarra 31008",
    "addr:housenumber":"37",
    "addr:postcode":"31008",
    "addr:street":"Pedro Malon De Chaide",
    "iso:country":"ES",
    "sg:address":"Pedro Malon De Chaide, 37",
    "sg:city":"Iru\u00f1a",
    "sg:orig_category":"Asesor\u00cda Sobre Comunicaci\u00d3n De Empresas",
    "sg:phone":"+34 948 17 51 83",
    "sg:postcode":"31008",
    "sg:province":"Navarra",
    "wof:name":"Quijera Asesores S.l.",
    "wof:placetype":"venue"
},
  "geometry": {"coordinates":[-1.6674469709,42.8099021912],"type":"Point"}
}