{
  "type": "Feature",
  "properties": {
    "iso:country":"ES",
    "sg:address":"Calle de General Bravo, S/n",
    "sg:city":"Jinamar",
    "sg:orig_category":"Bares, Piano",
    "sg:phone":"+34 928 71 14 58",
    "sg:postcode":"35220",
    "sg:province":"Las Palmas",
    "sg:website":"www.eiarchipielago.es",
    "wof:name":"Establecimientos Industriales Archipielago S. A.",
    "wof:placetype":"venue"
},
  "geometry": {"coordinates":[-15.4175510406,28.0331096649],"type":"Point"}
}