{
  "type": "Feature",
  "properties": {
    "iso:country":"ES",
    "sg:address":"Pl Castellers, 3",
    "sg:city":"Sitges",
    "sg:orig_category":"Ingeniero",
    "sg:phone":"+34 938 14 65 68",
    "sg:postcode":"08870",
    "sg:province":"Barcelona",
    "wof:name":"Waters  Ziggy",
    "wof:placetype":"venue"
},
  "geometry": {"coordinates":[1.8611011505,41.2558288574],"type":"Point"}
}