{
  "type": "Feature",
  "properties": {
    "iso:country":"ES",
    "sg:address":"Calle de Valdemorillo, 87",
    "sg:city":"Ventorro Del Cano",
    "sg:orig_category":"Promotores Constructores",
    "sg:phone":"+34 916 32 64 80",
    "sg:postcode":"28925",
    "sg:province":"Madrid",
    "wof:name":"Andobras S.a.",
    "wof:placetype":"venue"
},
  "geometry": {"coordinates":[-3.8418269157,40.3900642395],"type":"Point"}
}