{
  "type": "Feature",
  "properties": {
    "addr:full":"Calle de San Sebastian, 7 Benabarre Huesca 22580",
    "addr:housenumber":"7",
    "addr:postcode":"22580",
    "addr:street":"Calle De San Sebastian",
    "iso:country":"ES",
    "sg:address":"Calle de San Sebastian, 7",
    "sg:city":"Benabarre",
    "sg:orig_category":"Electricidad: Instaladores",
    "sg:phone":"+34 974 54 31 90",
    "sg:postcode":"22580",
    "sg:province":"Huesca",
    "wof:name":"Pociello Palau Luis",
    "wof:placetype":"venue"
},
  "geometry": {"coordinates":[0.4789099991,42.1083183289],"type":"Point"}
}