{
  "type": "Feature",
  "properties": {
    "iso:country":"ES",
    "sg:address":"Carrer de Vinyeta, 17",
    "sg:city":"Hospitalet Llobregat",
    "sg:orig_category":"Carnicer\u00cdas, Carnicer\u00cdas",
    "sg:phone":"+34 933 34 90 93",
    "sg:postcode":"08904",
    "sg:province":"Barcelona",
    "wof:name":"Casanovas Arnavat Antonio",
    "wof:placetype":"venue"
},
  "geometry": {"coordinates":[2.1159470081,41.3712234497],"type":"Point"}
}