{
  "type": "Feature",
  "properties": {
    "addr:full":"Calle de Eraso, 20 Madrid Madrid 28028",
    "addr:housenumber":"20",
    "addr:postcode":"madrid;28028",
    "addr:street":"Calle De Eraso",
    "iso:country":"ES",
    "sg:address":"Calle de Eraso, 20",
    "sg:city":"Madrid",
    "sg:orig_category":"Inform\u00c1tica, Ofim\u00c1tica (estudios, Asesor\u00cda, Ingenier\u00cda, Formaci\u00d3n)",
    "sg:phone":"+34 917 26 51 97",
    "sg:postcode":"28028",
    "sg:province":"Madrid",
    "wof:name":"Marcos Gilaranz Carlos",
    "wof:placetype":"venue"
},
  "geometry": {"coordinates":[-3.6702420712,40.4345588684],"type":"Point"}
}