{
  "type": "Feature",
  "properties": {
    "iso:country":"ES",
    "sg:address":"Calle de Maria Auxiliadora, 35",
    "sg:city":"Villatuerta",
    "sg:orig_category":"Reposter\u00cdas",
    "sg:phone":"+34 948 54 13 48",
    "sg:postcode":"31132",
    "sg:province":"Navarra",
    "wof:name":"Horno Cooperativo San Jose De Villatuerta",
    "wof:placetype":"venue"
},
  "geometry": {"coordinates":[-1.9955869913,42.6611480713],"type":"Point"}
}