{
  "type": "Feature",
  "properties": {
    "iso:country":"ES",
    "sg:address":"Calle de Francisco Martinez Soria, 24",
    "sg:city":"Tarazona",
    "sg:orig_category":"Ropa Para Ni\u00d1os (al Por Menor)",
    "sg:phone":"+34 976 64 12 40",
    "sg:postcode":"50500",
    "sg:province":"Zaragoza",
    "wof:name":"Artanga Burgos Laura",
    "wof:placetype":"venue"
},
  "geometry": {"coordinates":[-1.7251933813,41.9037742615],"type":"Point"}
}