{
  "type": "Feature",
  "properties": {
    "addr:full":"Carr Pere Escanellas, 32 Sant Josep De Sa Talaia Islas Baleares 07830",
    "addr:housenumber":"32",
    "addr:postcode":"07830",
    "addr:street":"Carr Pere Escanellas",
    "iso:country":"ES",
    "sg:address":"Carr Pere Escanellas, 32",
    "sg:city":"Sant Josep De Sa Talaia",
    "sg:orig_category":"Art\u00cdculos De Decoraci\u00d3n",
    "sg:phone":"+34 971 80 00 47",
    "sg:postcode":"07830",
    "sg:province":"Islas Baleares",
    "wof:name":"Mari Tur Jose",
    "wof:placetype":"venue"
},
  "geometry": {"coordinates":[1.2925050259,38.9218063354],"type":"Point"}
}