{
  "type": "Feature",
  "properties": {
    "iso:country":"ES",
    "sg:address":"Estafeta, 16",
    "sg:city":"Iru\u00f1a",
    "sg:orig_category":"Material De Ocasi\u00d3n (compra, Reventa)",
    "sg:phone":"+34 948 22 79 18",
    "sg:postcode":"31001",
    "sg:province":"Navarra",
    "wof:name":"Munarriz Moreno Maria Teresa",
    "wof:placetype":"venue"
},
  "geometry": {"coordinates":[-1.642565012,42.8177108765],"type":"Point"}
}