{
  "type": "Feature",
  "properties": {
    "addr:full":"Plaz San Cosme Y San Damian, 1 Andosilla Navarra 31261",
    "addr:housenumber":"1",
    "addr:postcode":"31261",
    "addr:street":"Plaz;Damian",
    "iso:country":"ES",
    "sg:address":"Plaz San Cosme Y San Damian, 1",
    "sg:city":"Andosilla",
    "sg:orig_category":"Ense\u00d1anza, Formaci\u00d3n Profesional: Aprendizaje",
    "sg:phone":"+34 948 67 48 53",
    "sg:postcode":"31261",
    "sg:province":"Navarra",
    "wof:name":"Ayuntamiento De Andosilla",
    "wof:placetype":"venue"
},
  "geometry": {"coordinates":[-1.9447740316,42.3778915405],"type":"Point"}
}