{
  "type": "Feature",
  "properties": {
    "iso:country":"ES",
    "sg:address":"Calle de Antonio Machado, S/n",
    "sg:city":"Lugones",
    "sg:orig_category":"Perfumer\u00cda (al Por Menor)",
    "sg:phone":"+34 985 98 70 96",
    "sg:postcode":"33420",
    "sg:province":"Asturias",
    "wof:name":"Perfumeria Cleopatra",
    "wof:placetype":"venue"
},
  "geometry": {"coordinates":[-5.8076791763,43.4024848938],"type":"Point"}
}