{
  "type": "Feature",
  "properties": {
    "iso:country":"ES",
    "sg:address":"Pg Saladar, 75",
    "sg:city":"Denia",
    "sg:orig_category":"Perfumer\u00cda, Art\u00cdculos De Ba\u00d1o (fabricaci\u00d3n, Al Por Mayor)",
    "sg:phone":"+34 965 78 70 51",
    "sg:postcode":"03700",
    "sg:province":"Alicante",
    "wof:name":"Perfumeria Caselles C.b.",
    "wof:placetype":"venue"
},
  "geometry": {"coordinates":[0.1098840013,38.8391075134],"type":"Point"}
}