{
  "type": "Feature",
  "properties": {
    "addr:full":"Pase Moreras, 19 Madrid Madrid 28021",
    "addr:housenumber":"19",
    "addr:postcode":"madrid;28021",
    "addr:street":"Moreras",
    "iso:country":"ES",
    "sg:address":"Pase Moreras, 19",
    "sg:city":"Madrid",
    "sg:orig_category":"Peluqueros: De Se\u00d1oras",
    "sg:phone":"+34 915 05 03 99",
    "sg:postcode":"28021",
    "sg:province":"Madrid",
    "wof:name":"Higuera Garcia Felipe",
    "wof:placetype":"venue"
},
  "geometry": {"coordinates":[-3.7101550102,40.3454208374],"type":"Point"}
}