{
  "type": "Feature",
  "properties": {
    "addr:full":"Calle de Bodegueros, 18 Malaga M\u00e1laga 29006",
    "addr:housenumber":"18",
    "addr:postcode":"29006",
    "addr:street":"Calle De Bodegueros;Ma\u0301Laga",
    "iso:country":"ES",
    "sg:address":"Calle de Bodegueros, 18",
    "sg:city":"Malaga",
    "sg:orig_category":"Estudios, Instalaci\u00d3n De Climatizaci\u00d3n",
    "sg:phone":"+34 952 04 02 98",
    "sg:postcode":"29006",
    "sg:province":"M\u00e1laga",
    "sg:website":"www.ingadia.com",
    "wof:name":"Ingadia S.a.",
    "wof:placetype":"venue"
},
  "geometry": {"coordinates":[-4.4455485344,36.7068138123],"type":"Point"}
}