{
  "type": "Feature",
  "properties": {
    "iso:country":"ES",
    "sg:address":"Calle de Prensa (la), 2",
    "sg:city":"San Sebastian De Los Reyes",
    "sg:orig_category":"Fisioterapia",
    "sg:phone":"+34 916 52 12 09",
    "sg:postcode":"28700",
    "sg:province":"Madrid",
    "wof:name":"Suarez Sanchez Diego Luis",
    "wof:placetype":"venue"
},
  "geometry": {"coordinates":[-3.6281151772,40.5443840027],"type":"Point"}
}