{
  "type": "Feature",
  "properties": {
    "iso:country":"ES",
    "sg:address":"Calle de Ondara, 1",
    "sg:city":"Denia",
    "sg:orig_category":"Chapister\u00cda",
    "sg:phone":"+34 965 78 76 49",
    "sg:postcode":"03700",
    "sg:province":"Alicante",
    "wof:name":"Vicmon S.l.",
    "wof:placetype":"venue"
},
  "geometry": {"coordinates":[0.0970750004,38.8400611877],"type":"Point"}
}