{
  "type": "Feature",
  "properties": {
    "addr:full":"Calle de Aguera, S/n Algar Murcia 30366",
    "addr:housenumber":"s / n",
    "addr:postcode":"30366",
    "addr:street":"Calle De Aguera",
    "iso:country":"ES",
    "sg:address":"Calle de Aguera, S/n",
    "sg:city":"Algar",
    "sg:orig_category":"Comercio, Reparaci\u00d3n De Motocicletas, Bicicletas Y Piezas Sueltas",
    "sg:phone":"+34 968 13 60 37",
    "sg:postcode":"30366",
    "sg:province":"Murcia",
    "wof:name":"Urrea Martinez Juan",
    "wof:placetype":"venue"
},
  "geometry": {"coordinates":[-0.868614018,37.6490783691],"type":"Point"}
}