{
  "type": "Feature",
  "properties": {
    "iso:country":"ES",
    "sg:address":"Carrer de Comte D'urgell, 288",
    "sg:city":"Barcelona",
    "sg:orig_category":"M\u00c9dicos: An\u00c1lisis Cl\u00cdnicos",
    "sg:phone":"+34 933 21 98 70",
    "sg:postcode":"08036",
    "sg:province":"Barcelona",
    "wof:name":"Laboratorios Fornells Olo Crespo S A",
    "wof:placetype":"venue"
},
  "geometry": {"coordinates":[2.1459755898,41.3916511536],"type":"Point"}
}