{
  "type": "Feature",
  "properties": {
    "iso:country":"ES",
    "sg:address":"Avgd Joan Servera Camps, Den, 23",
    "sg:city":"Cala Millor",
    "sg:orig_category":"Tintes (fabricaci\u00d3n, Al Por Mayor)",
    "sg:phone":"+34 971 58 69 21",
    "sg:postcode":"07560",
    "sg:province":"Islas Baleares",
    "wof:name":"Artigues Catala Barbara",
    "wof:placetype":"venue"
},
  "geometry": {"coordinates":[3.382986784,39.6040153503],"type":"Point"}
}