{
  "type": "Feature",
  "properties": {
    "addr:full":"Calle de Gardenias (las), S/n Envia Almer\u00eda 04738",
    "addr:postcode":"04738",
    "addr:street":"Calle De Gardenias Las S / N Envia Almeri\u0301A",
    "iso:country":"ES",
    "sg:address":"Calle de Gardenias (las), S/n",
    "sg:city":"Envia",
    "sg:orig_category":"Agentes Generales De Seguros",
    "sg:phone":"+34 950 55 98 41",
    "sg:postcode":"04738",
    "sg:province":"Almer\u00eda",
    "wof:name":"Cruz Zamora Maria Dolores",
    "wof:placetype":"venue"
},
  "geometry": {"coordinates":[-2.6420009136,36.8316612244],"type":"Point"}
}