{
  "type": "Feature",
  "properties": {
    "addr:full":"Parque S. Fernando, S/n Cuenca Cuenca 16004",
    "addr:housenumber":"s / n",
    "addr:postcode":"16004",
    "iso:country":"ES",
    "sg:address":"Parque S. Fernando, S/n",
    "sg:city":"Cuenca",
    "sg:orig_category":"Sindicatos De Trabajadores",
    "sg:phone":"+34 969 24 00 34",
    "sg:postcode":"16004",
    "sg:province":"Cuenca",
    "wof:name":"Sindicato De Enfermeria (satse",
    "wof:placetype":"venue"
},
  "geometry": {"coordinates":[-2.1362390518,40.0720710754],"type":"Point"}
}