{
  "type": "Feature",
  "properties": {
    "iso:country":"ES",
    "sg:address":"Calle de Maria Auxiliadora, 11",
    "sg:city":"Gines",
    "sg:orig_category":"Ingeniero",
    "sg:phone":"+34 954 71 91 92",
    "sg:postcode":"41960",
    "sg:province":"Sevilla",
    "wof:name":"Ingecon Ingenieria De La Construccion S.l.",
    "wof:placetype":"venue"
},
  "geometry": {"coordinates":[-6.0810670853,37.3817367554],"type":"Point"}
}