{
  "type": "Feature",
  "properties": {
    "iso:country":"ES",
    "sg:address":"Pg Callao, S/n",
    "sg:city":"Mataro",
    "sg:orig_category":"Deportes N\u00c1uticos, Acu\u00c1ticos Y Subacu\u00c1ticos: Art\u00cdculos Y Equipo (al Por Menor)",
    "sg:phone":"+34 937 96 18 60",
    "sg:postcode":"08301",
    "sg:province":"Barcelona",
    "sg:website":"www.doriavidal.com",
    "wof:name":"Vidal Ricart Carmen",
    "wof:placetype":"venue"
},
  "geometry": {"coordinates":[2.4549300671,41.539604187],"type":"Point"}
}