{
  "type": "Feature",
  "properties": {
    "iso:country":"ES",
    "sg:address":"Calle de Amapola, 6",
    "sg:city":"Morales Vino",
    "sg:orig_category":"Arquitectos",
    "sg:phone":"+34 980 57 02 38",
    "sg:postcode":"49190",
    "sg:province":"Zamora",
    "wof:name":"Bueno Crespo Juan Jose",
    "wof:placetype":"venue"
},
  "geometry": {"coordinates":[-5.73462677,41.4416236877],"type":"Point"}
}