{
  "type": "Feature",
  "properties": {
    "addr:full":"Trss Francesc Moli, 16 Lleida Lleida 25005",
    "addr:housenumber":"16",
    "addr:postcode":"25005",
    "addr:street":"Moli",
    "iso:country":"ES",
    "sg:address":"Trss Francesc Moli, 16",
    "sg:city":"Lleida",
    "sg:orig_category":"Construcciones Met\u00c1licas",
    "sg:phone":"+34 973 22 91 86",
    "sg:postcode":"25005",
    "sg:province":"Lleida",
    "wof:name":"Montvafer S.l.",
    "wof:placetype":"venue"
},
  "geometry": {"coordinates":[0.6276429892,41.6253700256],"type":"Point"}
}