{
  "type": "Feature",
  "properties": {
    "iso:country":"ES",
    "sg:address":"Calle de Cuadrilla De Vitoria-gasteiz, 4",
    "sg:city":"Vitoria-gasteiz",
    "sg:orig_category":"Molduras, Junquillos, Listones Y Molduras Perforadas",
    "sg:phone":"+34 945 27 88 54",
    "sg:postcode":"01013",
    "sg:province":"\u00c1lava",
    "wof:name":"Martinez Arrabal Luis Miguel",
    "wof:placetype":"venue"
},
  "geometry": {"coordinates":[-2.6727826595,42.856880188],"type":"Point"}
}