{
  "type": "Feature",
  "properties": {
    "iso:country":"ES",
    "sg:address":"Rua Bilbao, 6",
    "sg:city":"Meicende",
    "sg:orig_category":"Molduras, Junquillos, Listones Y Molduras Perforadas",
    "sg:phone":"+34 981 26 00 89",
    "sg:postcode":"15140",
    "sg:province":"La Coru\u00f1a",
    "wof:name":"Abellon Carro Arturo",
    "wof:placetype":"venue"
},
  "geometry": {"coordinates":[-8.444372,43.345085],"type":"Point"}
}