{
  "type": "Feature",
  "properties": {
    "addr:full":"Calle de Montoro, 8 Alcorcon Madrid 28922",
    "addr:housenumber":"8",
    "addr:postcode":"28922",
    "addr:street":"Calle De Montoro",
    "iso:country":"ES",
    "sg:address":"Calle de Montoro, 8",
    "sg:city":"Alcorcon",
    "sg:orig_category":"Molduras, Junquillos, Listones Y Molduras Perforadas",
    "sg:phone":"+34 916 44 08 56",
    "sg:postcode":"28922",
    "sg:province":"Madrid",
    "wof:name":"Salvador Garcia Aurelia",
    "wof:placetype":"venue"
},
  "geometry": {"coordinates":[-3.8337359428,40.3455734253],"type":"Point"}
}