{
  "type": "Feature",
  "properties": {
    "addr:full":"Rua Cano (o), 4 Francelos Ourense 32418",
    "addr:housenumber":"4",
    "addr:postcode":"32418",
    "addr:street":"Rua Cano O",
    "iso:country":"ES",
    "sg:address":"Rua Cano (o), 4",
    "sg:city":"Francelos",
    "sg:orig_category":"Carnicer\u00cdas, Carnicer\u00cdas",
    "sg:phone":"+34 988 47 10 38",
    "sg:postcode":"32418",
    "sg:province":"Ourense",
    "wof:name":"Alvarez Montero Jose",
    "wof:placetype":"venue"
},
  "geometry": {"coordinates":[-8.1583662033,42.2768821716],"type":"Point"}
}