{
  "type": "Feature",
  "properties": {
    "addr:full":"Calle de Mantulene, 1 Donostia-san Sebastian Guip\u00f9zcoa 20009",
    "addr:housenumber":"1",
    "addr:postcode":"20009",
    "addr:street":"Calle De Mantulene",
    "iso:country":"ES",
    "sg:address":"Calle de Mantulene, 1",
    "sg:city":"Donostia-san Sebastian",
    "sg:orig_category":"Marketing Telef\u00d3nico",
    "sg:phone":"+34 943 31 46 22",
    "sg:postcode":"20009",
    "sg:province":"Guip\u00f9zcoa",
    "sg:website":"www.gctelemarketing.com",
    "wof:name":"Gc Asesoramiento En Telemarketing S.l.",
    "wof:placetype":"venue"
},
  "geometry": {"coordinates":[-1.989997983,43.2991676331],"type":"Point"}
}