{
  "type": "Feature",
  "properties": {
    "addr:full":"Pg Francesc Macia, 1 Cambrils Tarragona 43850",
    "addr:housenumber":"1",
    "addr:postcode":"43850",
    "addr:street":"Pg Francesc Macia",
    "iso:country":"ES",
    "sg:address":"Pg Francesc Macia, 1",
    "sg:city":"Cambrils",
    "sg:orig_category":"Cajas De Ahorro",
    "sg:phone":"+34 977 36 61 87",
    "sg:postcode":"43850",
    "sg:province":"Tarragona",
    "sg:website":"www.caixatarragona.es",
    "wof:name":"Caixa D'estalvis De Tarragona",
    "wof:placetype":"venue"
},
  "geometry": {"coordinates":[1.0611100197,41.0672683716],"type":"Point"}
}