{
  "type": "Feature",
  "properties": {
    "addr:full":"Carr Sant Pere, 36 Algemesi Valencia 46680",
    "addr:housenumber":"36",
    "addr:postcode":"46680",
    "addr:street":"Carr Sant Pere",
    "iso:country":"ES",
    "sg:address":"Carr Sant Pere, 36",
    "sg:city":"Algemesi",
    "sg:orig_category":"Plomeros",
    "sg:phone":"+34 962 42 00 40",
    "sg:postcode":"46680",
    "sg:province":"Valencia",
    "wof:name":"Forner Jumilla Juan",
    "wof:placetype":"venue"
},
  "geometry": {"coordinates":[-0.4332920015,39.194896698],"type":"Point"}
}