{
  "type": "Feature",
  "properties": {
    "iso:country":"ES",
    "sg:address":"Calle de General Pintos, 27",
    "sg:city":"Alacant",
    "sg:orig_category":"Automatizaci\u00d3n De Procesos Industriales Y De Edificaci\u00d3n (estudios, Instalaci\u00d3n)",
    "sg:phone":"+34 965 25 32 90",
    "sg:postcode":"03010",
    "sg:province":"Alicante",
    "wof:name":"Alisisten S.l.",
    "wof:placetype":"venue"
},
  "geometry": {"coordinates":[-0.4877260923,38.359954834],"type":"Point"}
}