{
  "type": "Feature",
  "properties": {
    "iso:country":"ES",
    "sg:address":"Plaz San Esteban, 4",
    "sg:city":"Guadalajara",
    "sg:orig_category":"Semiller\u00cdas",
    "sg:phone":"+34 949 22 12 99",
    "sg:postcode":"19001",
    "sg:province":"Guadalajara",
    "wof:name":"Santos Sanz Faustino Ildefonso",
    "wof:placetype":"venue"
},
  "geometry": {"coordinates":[-3.1645519733,40.6334533691],"type":"Point"}
}