{
  "type": "Feature",
  "properties": {
    "addr:full":"Calle de Puerta De La Villa, 15 Roa Burgos 09300",
    "addr:housenumber":"15",
    "addr:postcode":"09300",
    "addr:street":"Calle De Puerta De La Villa",
    "iso:country":"ES",
    "sg:address":"Calle de Puerta De La Villa, 15",
    "sg:city":"Roa",
    "sg:orig_category":"Cristaler\u00cdas",
    "sg:phone":"+34 947 54 04 91",
    "sg:postcode":"09300",
    "sg:province":"Burgos",
    "wof:name":"Casado Hervas Jose Luis",
    "wof:placetype":"venue"
},
  "geometry": {"coordinates":[-3.9305949211,41.6977806091],"type":"Point"}
}