{
  "type": "Feature",
  "properties": {
    "iso:country":"ES",
    "sg:address":"Calle de Antonia Diaz, 27",
    "sg:city":"Sevilla",
    "sg:orig_category":"Arquitectos",
    "sg:phone":"+34 954 21 69 79",
    "sg:postcode":"41001",
    "sg:province":"Sevilla",
    "wof:name":"Chaparro Narbona Mario",
    "wof:placetype":"venue"
},
  "geometry": {"coordinates":[-5.9977564812,37.3854866028],"type":"Point"}
}