{
  "type": "Feature",
  "properties": {
    "iso:country":"ES",
    "sg:address":"Ere\u00d1otzu Auzoa, 94",
    "sg:city":"Ere\u00d1otzu",
    "sg:orig_category":"Metalizados",
    "sg:phone":"+34 943 55 21 86",
    "sg:postcode":"20120",
    "sg:province":"Guip\u00f9zcoa",
    "wof:name":"Urumea Tailerrak S.l.",
    "wof:placetype":"venue"
},
  "geometry": {"coordinates":[-1.9798289537,43.2647514343],"type":"Point"}
}