{
  "type": "Feature",
  "properties": {
    "addr:full":"La Ribera, 9 Priego Cordoba C\u00f3rdoba 14800",
    "addr:housenumber":"9",
    "addr:postcode":"14800",
    "addr:street":"La Ribera;Cordoba Co\u0301Rdoba",
    "iso:country":"ES",
    "sg:address":"La Ribera, 9",
    "sg:city":"Priego Cordoba",
    "sg:orig_category":"Telas Y Sedas (al Por Menor)",
    "sg:phone":"+34 957 54 03 17",
    "sg:postcode":"14800",
    "sg:province":"C\u00f3rdoba",
    "wof:name":"Alcala Perez Jose Joaquin",
    "wof:placetype":"venue"
},
  "geometry": {"coordinates":[-4.1938462257,37.438533783],"type":"Point"}
}