{
  "type": "Feature",
  "properties": {
    "addr:full":"Calle de Francisco Vitoria, 1 Zaragoza Zaragoza 50008",
    "addr:housenumber":"1",
    "addr:postcode":"50008",
    "addr:street":"Calle De Francisco Vitoria",
    "iso:country":"ES",
    "sg:address":"Calle de Francisco Vitoria, 1",
    "sg:city":"Zaragoza",
    "sg:orig_category":"Confecci\u00d3n De Trajes Para Se\u00d1oras",
    "sg:phone":"+34 976 30 25 86",
    "sg:postcode":"50008",
    "sg:province":"Zaragoza",
    "sg:website":"www.formes.com",
    "wof:name":"Formes Iberia S.l.",
    "wof:placetype":"venue"
},
  "geometry": {"coordinates":[-0.8802531958,41.6461601257],"type":"Point"}
}