{
  "type": "Feature",
  "properties": {
    "addr:full":"Calle de Ecuador, 1 Alacant Alicante 03008",
    "addr:housenumber":"1",
    "addr:postcode":"03008",
    "addr:street":"Calle De Ecuador",
    "iso:country":"ES",
    "sg:address":"Calle de Ecuador, 1",
    "sg:city":"Alacant",
    "sg:orig_category":"Papeler\u00cdas: Art\u00cdculos (al Por Mayor)",
    "sg:phone":"+34 965 11 53 95",
    "sg:postcode":"03008",
    "sg:province":"Alicante",
    "wof:name":"Comercial Del Sur De Papeleria S.a.",
    "wof:placetype":"venue"
},
  "geometry": {"coordinates":[-0.5081204176,38.3312530518],"type":"Point"}
}