{
  "type": "Feature",
  "properties": {
    "addr:full":"Calle de Peru, 4 Matas-pinar-monte Rozas Madrid 28290",
    "addr:housenumber":"4",
    "addr:postcode":"28290",
    "addr:street":"Calle De Peru",
    "iso:country":"ES",
    "sg:address":"Calle de Peru, 4",
    "sg:city":"Matas-pinar-monte Rozas",
    "sg:orig_category":"Embalajes",
    "sg:phone":"+34 917 99 04 33",
    "sg:postcode":"28290",
    "sg:province":"Madrid",
    "wof:name":"Web Embalaje S.a.",
    "wof:placetype":"venue"
},
  "geometry": {"coordinates":[-3.8965079784,40.5449905396],"type":"Point"}
}