{
  "type": "Feature",
  "properties": {
    "iso:country":"ES",
    "sg:address":"Chancela(logrosa), 27",
    "sg:city":"Chancela",
    "sg:orig_category":"Art\u00cdculos Funerarios (al Por Menor)",
    "sg:phone":"+34 981 88 52 83",
    "sg:postcode":"15830",
    "sg:province":"La Coru\u00f1a",
    "wof:name":"Furelos Bahamonde Manuel Vicente",
    "wof:placetype":"venue"
},
  "geometry": {"coordinates":[-8.7368841171,42.9089660645],"type":"Point"}
}