{
  "type": "Feature",
  "properties": {
    "iso:country":"ES",
    "sg:address":"Calle de Santiago Ramon Y Cajal, 30",
    "sg:city":"Cartagena",
    "sg:orig_category":"Peluquer\u00cdas, Peluquer\u00cda Mixta",
    "sg:phone":"+34 968 12 30 17",
    "sg:postcode":"30204",
    "sg:province":"Murcia",
    "wof:name":"Martinez Perez Carmen",
    "wof:placetype":"venue"
},
  "geometry": {"coordinates":[-0.9916880131,37.6110877991],"type":"Point"}
}