{
  "type": "Feature",
  "properties": {
    "addr:full":"Av Reis Catolics, 25 Olot Girona 17800",
    "addr:housenumber":"25",
    "addr:postcode":"17800",
    "addr:street":"Av Reis Catolics",
    "iso:country":"ES",
    "sg:address":"Av Reis Catolics, 25",
    "sg:city":"Olot",
    "sg:orig_category":"Venta, Colocaci\u00d3n, Reparaci\u00d3n De Parabrisas, Techos Descapotables",
    "sg:phone":"+34 972 27 34 11",
    "sg:postcode":"17800",
    "sg:province":"Girona",
    "wof:name":"Vidre Eris S.l.",
    "wof:placetype":"venue"
},
  "geometry": {"coordinates":[2.4815580845,42.1829566956],"type":"Point"}
}