{
  "type": "Feature",
  "properties": {
    "iso:country":"ES",
    "sg:address":"Avda Paisos Catalans, S/n",
    "sg:city":"Monjos",
    "sg:orig_category":"Mataderos Y Talleres De Despiezado",
    "sg:phone":"+34 938 98 11 86",
    "sg:postcode":"08730",
    "sg:province":"Barcelona",
    "wof:name":"Sole Santacana Joana",
    "wof:placetype":"venue"
},
  "geometry": {"coordinates":[1.6636550426,41.3288345337],"type":"Point"}
}