{
  "type": "Feature",
  "properties": {
    "addr:full":"Carrer de Ample, 13 Torredembarra Tarragona 43830",
    "addr:housenumber":"13",
    "addr:postcode":"43830",
    "addr:street":"Carrer De Ample",
    "iso:country":"ES",
    "sg:address":"Carrer de Ample, 13",
    "sg:city":"Torredembarra",
    "sg:orig_category":"Peluquer\u00cdas, Peluquer\u00cda Mixta",
    "sg:phone":"+34 977 64 52 07",
    "sg:postcode":"43830",
    "sg:province":"Tarragona",
    "wof:name":"Sole Cascon Olga",
    "wof:placetype":"venue"
},
  "geometry": {"coordinates":[1.3943799734,41.1447639465],"type":"Point"}
}