{
  "type": "Feature",
  "properties": {
    "addr:full":"Cra Sant Boi, 63 Sant Vicen\u00c7 Dels Horts Barcelona 08620",
    "addr:housenumber":"63",
    "addr:postcode":"08620",
    "iso:country":"ES",
    "sg:address":"Cra Sant Boi, 63",
    "sg:city":"Sant Vicen\u00c7 Dels Horts",
    "sg:classifiers":[
        {
            "category":"Cinema",
            "subcategory":"Movie Theater",
            "type":"Entertainment"
        }
    ],
    "sg:phone":"+34 936 56 80 87",
    "sg:postcode":"08620",
    "sg:province":"Barcelona",
    "sg:tags":[
        "salas",
        "de",
        "cine"
    ],
    "wof:name":"Multicines La Vailet S.l.",
    "wof:placetype":"venue"
},
  "geometry": {"coordinates":[2.0100400448,41.3932189941],"type":"Point"}
}