{
  "type": "Feature",
  "properties": {
    "iso:country":"ES",
    "sg:address":"Calle de Santa Ana, 72",
    "sg:city":"Gineta",
    "sg:orig_category":"Art\u00cdculos De Madera (fabricaci\u00d3n Y Al Por Mayor)",
    "sg:phone":"+34 967 27 50 25",
    "sg:postcode":"02110",
    "sg:province":"Albacete",
    "wof:name":"Inpamar S.l.",
    "wof:placetype":"venue"
},
  "geometry": {"coordinates":[-2.0002090931,39.1132087708],"type":"Point"}
}