{
  "type": "Feature",
  "properties": {
    "iso:country":"ES",
    "sg:address":"Calle de Arenas, 22",
    "sg:city":"Madrid",
    "sg:orig_category":"Ropa Para Se\u00d1oras Y Caballeros (al Por Menor)",
    "sg:phone":"+34 917 97 17 96",
    "sg:postcode":"28021",
    "sg:province":"Madrid",
    "wof:name":"Yuste Recio Francisco",
    "wof:placetype":"venue"
},
  "geometry": {"coordinates":[-3.7126543522,40.3449020386],"type":"Point"}
}