{
  "type": "Feature",
  "properties": {
    "addr:full":"Carr Sant Joan, 32 Vilanova I La Geltru Barcelona 08800",
    "addr:housenumber":"32",
    "addr:postcode":"08800",
    "addr:street":"Carr Sant Joan",
    "iso:country":"ES",
    "sg:address":"Carr Sant Joan, 32",
    "sg:city":"Vilanova I La Geltru",
    "sg:orig_category":"Peluquer\u00cdas, Peluquer\u00cda Mixta",
    "sg:phone":"+34 938 93 41 88",
    "sg:postcode":"08800",
    "sg:province":"Barcelona",
    "wof:name":"Raventos Poveda Elisabeth",
    "wof:placetype":"venue"
},
  "geometry": {"coordinates":[1.7250130177,41.2256851196],"type":"Point"}
}