{
  "type": "Feature",
  "properties": {
    "addr:full":"Plaz Mayor, 10 S. Esteban Gormaz Soria 42330",
    "addr:housenumber":"10",
    "addr:postcode":"42330",
    "addr:street":"Plaz Mayor",
    "iso:country":"ES",
    "sg:address":"Plaz Mayor, 10",
    "sg:city":"S. Esteban Gormaz",
    "sg:orig_category":"Supermercados Y Hipermercados",
    "sg:phone":"+34 975 35 12 51",
    "sg:postcode":"42330",
    "sg:province":"Soria",
    "wof:name":"Cerrada Madrid Pedro",
    "wof:placetype":"venue"
},
  "geometry": {"coordinates":[-3.1995689869,41.5723457336],"type":"Point"}
}