{
  "type": "Feature",
  "properties": {
    "iso:country":"ES",
    "sg:address":"Calle de Santa Cruz, 7",
    "sg:city":"Burgos",
    "sg:orig_category":"Grafistas",
    "sg:phone":"+34 947 26 90 80",
    "sg:postcode":"09002",
    "sg:province":"Burgos",
    "wof:name":"Portilla De La Concha Luis Alberto",
    "wof:placetype":"venue"
},
  "geometry": {"coordinates":[-3.6967830658,42.3380393982],"type":"Point"}
}