{
  "type": "Feature",
  "properties": {
    "addr:full":"Cami Sta. Llogaia, S/n Figueres Girona 17600",
    "addr:housenumber":"s",
    "addr:postcode":"17600",
    "addr:street":"/ N",
    "iso:country":"ES",
    "sg:address":"Cami Sta. Llogaia, S/n",
    "sg:city":"Figueres",
    "sg:classifiers":[
        {
            "category":"Utilities",
            "subcategory":"Natural Gas",
            "type":"Services"
        }
    ],
    "sg:phone":"+34 972 50 39 02",
    "sg:postcode":"17600",
    "sg:province":"Girona",
    "wof:name":"Naturcorp Redes S.a.",
    "wof:placetype":"venue"
},
  "geometry": {"coordinates":[2.9599349499,42.2640762329],"type":"Point"}
}