{
  "type": "Feature",
  "properties": {
    "addr:full":"Calle de Manuel Franco Cubeiro, 31 Torremolinos M\u00e1laga 29620",
    "addr:housenumber":"31",
    "addr:postcode":"29620",
    "addr:street":"Calle De Manuel Franco Cubeiro;Ma\u0301Laga",
    "iso:country":"ES",
    "sg:address":"Calle de Manuel Franco Cubeiro, 31",
    "sg:city":"Torremolinos",
    "sg:orig_category":"Tratamiento De Metales",
    "sg:phone":"+34 952 05 31 76",
    "sg:postcode":"29620",
    "sg:province":"M\u00e1laga",
    "wof:name":"Transformados Masur S.l.",
    "wof:placetype":"venue"
},
  "geometry": {"coordinates":[-4.5181751251,36.6132087708],"type":"Point"}
}