{
  "type": "Feature",
  "properties": {
    "addr:full":"Cmno Villalba (de), S/n Hoyo Manzanares Madrid 28240",
    "addr:postcode":"28240",
    "addr:street":"Cmno Villalba De S / N Hoyo",
    "iso:country":"ES",
    "sg:address":"Cmno Villalba (de), S/n",
    "sg:city":"Hoyo Manzanares",
    "sg:orig_category":"M\u00c1quinas Textiles, Accesorios Y Suministros (fabricaci\u00d3n)",
    "sg:phone":"+34 918 56 65 52",
    "sg:postcode":"28240",
    "sg:province":"Madrid",
    "sg:website":"www.tecramsl.com",
    "wof:name":"Tecram,artesania Textil S.l.",
    "wof:placetype":"venue"
},
  "geometry": {"coordinates":[-3.9074640274,40.6213912964],"type":"Point"}
}