{
  "type": "Feature",
  "properties": {
    "iso:country":"ES",
    "sg:address":"Calle de San Francisco, 22",
    "sg:city":"Vitoria-gasteiz",
    "sg:orig_category":"Florister\u00cdas",
    "sg:phone":"+34 945 26 36 18",
    "sg:postcode":"01001",
    "sg:province":"\u00c1lava",
    "wof:name":"Fernandez De Arroyabe Paunero Josu",
    "wof:placetype":"venue"
},
  "geometry": {"coordinates":[-2.6693470478,42.8470573425],"type":"Point"}
}