{
  "type": "Feature",
  "properties": {
    "addr:full":"Calle de Arenal, 16 Carcabuey C\u00f3rdoba 14810",
    "addr:housenumber":"16",
    "addr:postcode":"14810",
    "addr:street":"Calle De Arenal",
    "iso:country":"ES",
    "sg:address":"Calle de Arenal, 16",
    "sg:city":"Carcabuey",
    "sg:orig_category":"Producci\u00d3n, Venta De Productos De Agricultura Biol\u00d3gica",
    "sg:phone":"+34 957 55 32 26",
    "sg:postcode":"14810",
    "sg:province":"C\u00f3rdoba",
    "wof:name":"Perez Cobo Carmen",
    "wof:placetype":"venue"
},
  "geometry": {"coordinates":[-4.2733778954,37.4456443787],"type":"Point"}
}