{
  "type": "Feature",
  "properties": {
    "iso:country":"ES",
    "sg:address":"Calle de Priego De Cordoba, 7",
    "sg:city":"Cordoba",
    "sg:orig_category":"Florister\u00cdas",
    "sg:phone":"+34 957 29 52 20",
    "sg:postcode":"14013",
    "sg:province":"C\u00f3rdoba",
    "wof:name":"Risquez Pantoja Rosa Maria",
    "wof:placetype":"venue"
},
  "geometry": {"coordinates":[-4.7759928703,37.8664627075],"type":"Point"}
}