{
  "type": "Feature",
  "properties": {
    "iso:country":"ES",
    "sg:address":"Avda Marques De Ombreiro, 4",
    "sg:city":"Lugo",
    "sg:orig_category":"Peluqueros: De Se\u00d1oras",
    "sg:phone":"+34 982 21 73 69",
    "sg:postcode":"27004",
    "sg:province":"Lugo",
    "wof:name":"Graga Grandio Cristina",
    "wof:placetype":"venue"
},
  "geometry": {"coordinates":[-7.5778231621,43.0072402954],"type":"Point"}
}