{
  "type": "Feature",
  "properties": {
    "iso:country":"ES",
    "sg:address":"Calle de Serrano, 143",
    "sg:city":"Madrid",
    "sg:orig_category":"Centros Empresariales",
    "sg:phone":"+34 915 61 30 50",
    "sg:postcode":"28006",
    "sg:province":"Madrid",
    "sg:website":"www.gmcconsultores.es",
    "wof:name":"Gmc Consultores S.l.",
    "wof:placetype":"venue"
},
  "geometry": {"coordinates":[-3.6859090328,40.4443511963],"type":"Point"}
}