{
  "type": "Feature",
  "properties": {
    "iso:country":"ES",
    "sg:address":"Calle de Jose Ortega Y Gasset, 70",
    "sg:city":"Madrid",
    "sg:orig_category":"Organismos De Reclutamiento",
    "sg:phone":"+34 913 09 50 96",
    "sg:postcode":"28006",
    "sg:province":"Madrid",
    "wof:name":"Forper Tecnicas S.l.",
    "wof:placetype":"venue"
},
  "geometry": {"coordinates":[-3.6745870113,40.4297294617],"type":"Point"}
}