{
  "type": "Feature",
  "properties": {
    "addr:full":"Calle de Isaac Peral, 15 Linares Ja\u00e9n 23700",
    "addr:housenumber":"15",
    "addr:postcode":"23700",
    "addr:street":"Calle De Isaac Peral;Jae\u0301N",
    "iso:country":"ES",
    "sg:address":"Calle de Isaac Peral, 15",
    "sg:city":"Linares",
    "sg:orig_category":"Cajas De Ahorro",
    "sg:phone":"+34 953 69 97 59",
    "sg:postcode":"23700",
    "sg:province":"Ja\u00e9n",
    "wof:name":"Caixa D'estalvis I Pensions De Barcelona",
    "wof:placetype":"venue"
},
  "geometry": {"coordinates":[-3.6332149506,38.0960273743],"type":"Point"}
}