{
  "type": "Feature",
  "properties": {
    "addr:full":"Avda Cambados, 2 Mosteiro Pontevedra 36637",
    "addr:housenumber":"2",
    "addr:postcode":"36637",
    "addr:street":"Avda Cambados",
    "iso:country":"ES",
    "sg:address":"Avda Cambados, 2",
    "sg:city":"Mosteiro",
    "sg:orig_category":"Caf\u00c9s, Bares, Cervecer\u00cdas",
    "sg:phone":"+34 986 71 21 85",
    "sg:postcode":"36637",
    "sg:province":"Pontevedra",
    "wof:name":"Cafeteria Ansede S.l.",
    "wof:placetype":"venue"
},
  "geometry": {"coordinates":[-8.696688652,42.5155601501],"type":"Point"}
}