{
  "type": "Feature",
  "properties": {
    "iso:country":"ES",
    "sg:address":"Carr Hannover, 16",
    "sg:city":"Mao",
    "sg:orig_category":"\u00d3ptica: Instrumentos (fabricaci\u00d3n)",
    "sg:phone":"+34 971 36 35 60",
    "sg:postcode":"07703",
    "sg:province":"Islas Baleares",
    "wof:name":"Carreras Tuduri Benjamin",
    "wof:placetype":"venue"
},
  "geometry": {"coordinates":[4.265625,39.8903694153],"type":"Point"}
}