{
  "type": "Feature",
  "properties": {
    "iso:country":"ES",
    "sg:address":"Avda Letxumborro, 72",
    "sg:city":"Irun",
    "sg:orig_category":"Sales (al Por Mayor)",
    "sg:phone":"+34 943 66 70 83",
    "sg:postcode":"20303",
    "sg:province":"Guip\u00f9zcoa",
    "wof:name":"Distribuciones Zamora S. L.",
    "wof:placetype":"venue"
},
  "geometry": {"coordinates":[-1.81556499,43.3351707458],"type":"Point"}
}