{
  "type": "Feature",
  "properties": {
    "addr:full":"Ctra Haro, Km. 0003,0 Anguciana La Rioja 26210",
    "addr:postcode":"26210",
    "addr:street":"Ctra Haro Km. 0003,0 Anguciana;Rioja",
    "iso:country":"ES",
    "sg:address":"Ctra Haro, Km. 0003,0",
    "sg:city":"Anguciana",
    "sg:orig_category":"Empresas De Carpinter\u00cda Met\u00c1lica",
    "sg:phone":"+34 941 30 26 41",
    "sg:postcode":"26210",
    "sg:province":"La Rioja",
    "wof:name":"Ivan Ruiz Martinez Y Uno",
    "wof:placetype":"venue"
},
  "geometry": {"coordinates":[-2.9017310143,42.5744590759],"type":"Point"}
}