{
  "type": "Feature",
  "properties": {
    "iso:country":"ES",
    "sg:address":"Pla\u00c7 Onze De Setembre, 24",
    "sg:city":"Blanes",
    "sg:orig_category":"Prendas Deportivas (fabricaci\u00d3n)",
    "sg:phone":"+34 972 35 04 63",
    "sg:postcode":"17300",
    "sg:province":"Girona",
    "wof:name":"Creaciones Yo. Graddual S.l.",
    "wof:placetype":"venue"
},
  "geometry": {"coordinates":[2.7894790173,41.6780548096],"type":"Point"}
}