{
  "type": "Feature",
  "properties": {
    "addr:full":"Leon-astorga, Km. 0019,0 Villadangos Paramo Le\u00f3n 24392",
    "addr:postcode":"24392",
    "addr:street":"Leon-Astorga Km. 0019,0;Leo\u0301N",
    "iso:country":"ES",
    "sg:address":"Leon-astorga, Km. 0019,0",
    "sg:city":"Villadangos Paramo",
    "sg:orig_category":"Empresarios",
    "sg:phone":"+34 987 39 05 26",
    "sg:postcode":"24392",
    "sg:province":"Le\u00f3n",
    "wof:name":"Fernandez Garcia Vicente",
    "wof:placetype":"venue"
},
  "geometry": {"coordinates":[-5.7662639618,42.5171508789],"type":"Point"}
}