{
  "type": "Feature",
  "properties": {
    "iso:country":"ES",
    "sg:address":"Carrer de Ciutadans, 7",
    "sg:city":"Pineda Mar",
    "sg:orig_category":"Cajas De Ahorro",
    "sg:phone":"+34 937 67 04 51",
    "sg:postcode":"08397",
    "sg:province":"Barcelona",
    "sg:website":"www.lacaixa.es",
    "wof:name":"Caixa D'estalvis I Pensions De Barcelona",
    "wof:placetype":"venue"
},
  "geometry": {"coordinates":[2.6894290447,41.627948761],"type":"Point"}
}