{
  "type": "Feature",
  "properties": {
    "addr:full":"Avda Agustin De Foxa, 8 Ciudad Rodrigo Salamanca 37500",
    "addr:housenumber":"8",
    "addr:postcode":"37500",
    "addr:street":"Avda Agustin De Foxa",
    "iso:country":"ES",
    "sg:address":"Avda Agustin De Foxa, 8",
    "sg:city":"Ciudad Rodrigo",
    "sg:orig_category":"Centros P\u00dablicos De Formaci\u00d3n Profesional Y T\u00c9cnica",
    "sg:phone":"+34 923 46 05 51",
    "sg:postcode":"37500",
    "sg:province":"Salamanca",
    "wof:name":"Misioneras De La Providencia",
    "wof:placetype":"venue"
},
  "geometry": {"coordinates":[-6.5307440758,40.5990982056],"type":"Point"}
}