{
  "type": "Feature",
  "properties": {
    "addr:full":"Carrer de Sant Pere Mes Baix, 38 Barcelona Barcelona 08003",
    "addr:housenumber":"38",
    "addr:postcode":"08003",
    "addr:street":"Carrer De Sant",
    "iso:country":"ES",
    "sg:address":"Carrer de Sant Pere Mes Baix, 38",
    "sg:city":"Barcelona",
    "sg:orig_category":"Ropa Para Ni\u00d1os (al Por Menor)",
    "sg:phone":"+34 933 10 41 99",
    "sg:postcode":"08003",
    "sg:province":"Barcelona",
    "wof:name":"Articulos Infantiles Alicia S.a.",
    "wof:placetype":"venue"
},
  "geometry": {"coordinates":[2.1775906086,41.3873443604],"type":"Point"}
}