{
  "type": "Feature",
  "properties": {
    "addr:full":"Calle de San Antonio, 26 Vitoria-gasteiz \u00c1lava 01005",
    "addr:housenumber":"26",
    "addr:postcode":"01005",
    "addr:street":"Calle De San Antonio",
    "iso:country":"ES",
    "sg:address":"Calle de San Antonio, 26",
    "sg:city":"Vitoria-gasteiz",
    "sg:orig_category":"Psic\u00d3logos",
    "sg:phone":"+34 945 13 15 38",
    "sg:postcode":"01005",
    "sg:province":"\u00c1lava",
    "wof:name":"Guisasola Jauregui Arrate",
    "wof:placetype":"venue"
},
  "geometry": {"coordinates":[-2.6746079922,42.8426589966],"type":"Point"}
}