{
  "type": "Feature",
  "properties": {
    "addr:full":"Carrer de Rubio I Ors, 35 Cornella Llobregat Barcelona 08940",
    "addr:housenumber":"35",
    "addr:postcode":"08940",
    "addr:street":"Carrer De Rubio;Ors",
    "iso:country":"ES",
    "sg:address":"Carrer de Rubio I Ors, 35",
    "sg:city":"Cornella Llobregat",
    "sg:orig_category":"Molduras, Junquillos, Listones Y Molduras Perforadas",
    "sg:phone":"+34 933 77 99 25",
    "sg:postcode":"08940",
    "sg:province":"Barcelona",
    "wof:name":"Anido Rivas Narciso",
    "wof:placetype":"venue"
},
  "geometry": {"coordinates":[2.0675299168,41.3547325134],"type":"Point"}
}