{
  "type": "Feature",
  "properties": {
    "addr:full":"Avda Isabel De Moctezuma, 5 Caceres C\u00e1ceres 10005",
    "addr:housenumber":"5",
    "addr:postcode":"10005",
    "addr:street":"Avda Isabel De Moctezuma;Ca\u0301Ceres",
    "iso:country":"ES",
    "sg:address":"Avda Isabel De Moctezuma, 5",
    "sg:city":"Caceres",
    "sg:orig_category":"Herboristas (al Por Menor)",
    "sg:phone":"+34 927 21 44 21",
    "sg:postcode":"10005",
    "sg:province":"C\u00e1ceres",
    "wof:name":"Tejada Dominguez Teresa",
    "wof:placetype":"venue"
},
  "geometry": {"coordinates":[-6.3787560463,39.4649848938],"type":"Point"}
}