{
  "type": "Feature",
  "properties": {
    "iso:country":"ES",
    "sg:address":"Calle de Doctor Severo Ochoa Del, 2",
    "sg:city":"Aviles",
    "sg:orig_category":"Empresas De Pintura Y Revestimientos",
    "sg:phone":"+34 985 52 02 97",
    "sg:postcode":"33402",
    "sg:province":"Asturias",
    "wof:name":"Garcia Cernuda Francisco",
    "wof:placetype":"venue"
},
  "geometry": {"coordinates":[-5.9282765388,43.5539360046],"type":"Point"}
}