{
  "type": "Feature",
  "properties": {
    "iso:country":"ES",
    "sg:address":"Calle de San Hilarion, 4",
    "sg:city":"Puertollano",
    "sg:orig_category":"Cristaler\u00cdas",
    "sg:phone":"+34 926 69 82 44",
    "sg:postcode":"13500",
    "sg:province":"Ciudad Real",
    "wof:name":"Gallardo Olmo Antonio",
    "wof:placetype":"venue"
},
  "geometry": {"coordinates":[-4.1143021584,38.6895523071],"type":"Point"}
}