{
  "type": "Feature",
  "properties": {
    "addr:full":"Tor. Tortuguer (els Pinetons), 9 Ripollet Barcelona 08291",
    "addr:housenumber":"9",
    "addr:postcode":"08291",
    "addr:street":"Pinetons",
    "iso:country":"ES",
    "sg:address":"Tor. Tortuguer (els Pinetons), 9",
    "sg:city":"Ripollet",
    "sg:orig_category":"Electricidad: Instaladores",
    "sg:phone":"+34 935 80 38 45",
    "sg:postcode":"08291",
    "sg:province":"Barcelona",
    "wof:name":"Ecoelectric Instalaciones S.l.",
    "wof:placetype":"venue"
},
  "geometry": {"coordinates":[2.1489770412,41.5094833374],"type":"Point"}
}