{
  "type": "Feature",
  "properties": {
    "iso:country":"ES",
    "sg:address":"Carrer de Lleida, 31",
    "sg:city":"Barcelona",
    "sg:orig_category":"Asesor\u00cda Fiscal Y Jur\u00cddica",
    "sg:phone":"+34 934 25 24 60",
    "sg:postcode":"08004",
    "sg:province":"Barcelona",
    "wof:name":"Millans Capo David",
    "wof:placetype":"venue"
},
  "geometry": {"coordinates":[2.1555149555,41.3726234436],"type":"Point"}
}