{
  "type": "Feature",
  "properties": {
    "iso:country":"ES",
    "sg:address":"Calle de Chaves Nogales, 15",
    "sg:city":"Sevilla",
    "sg:orig_category":"Inform\u00c1tica, Ofim\u00c1tica (estudios, Asesor\u00cda, Ingenier\u00cda, Formaci\u00d3n)",
    "sg:phone":"+34 954 98 91 36",
    "sg:postcode":"41018",
    "sg:province":"Sevilla",
    "sg:website":"www.eurotronic.es",
    "wof:name":"Eurotronic Ingenieros S. A. L.",
    "wof:placetype":"venue"
},
  "geometry": {"coordinates":[-5.9800944328,37.3850860596],"type":"Point"}
}