{
  "type": "Feature",
  "properties": {
    "iso:country":"ES",
    "sg:address":"Avda Barcelona, 29",
    "sg:city":"Jaen",
    "sg:orig_category":"Electrodom\u00c9sticos (al Por Menor)",
    "sg:phone":"+34 953 29 59 79",
    "sg:postcode":"23006",
    "sg:province":"Ja\u00e9n",
    "wof:name":"Ruiz Marchal Francisco",
    "wof:placetype":"venue"
},
  "geometry": {"coordinates":[-3.7995829582,37.7804298401],"type":"Point"}
}