{
  "type": "Feature",
  "properties": {
    "addr:full":"Calle de Jose Del Pino, 60 Madrid Madrid 28021",
    "addr:housenumber":"60",
    "addr:postcode":"madrid;28021",
    "addr:street":"Calle De Jose Del Pino",
    "iso:country":"ES",
    "sg:address":"Calle de Jose Del Pino, 60",
    "sg:city":"Madrid",
    "sg:orig_category":"Delegados, Agentes De Tr\u00c1nsito, Auxiliares De Transporte Internacional",
    "sg:phone":"+34 915 05 20 87",
    "sg:postcode":"28021",
    "sg:province":"Madrid",
    "wof:name":"Prieto Trimi\u00f1o Rafael",
    "wof:placetype":"venue"
},
  "geometry": {"coordinates":[-3.689109087,40.3507614136],"type":"Point"}
}