{
  "type": "Feature",
  "properties": {
    "addr:full":"Calle de Escuelas, S/n Cabeza Del Caballo Salamanca 37214",
    "addr:housenumber":"s / n",
    "addr:postcode":"37214",
    "addr:street":"Calle De Escuelas",
    "iso:country":"ES",
    "sg:address":"Calle de Escuelas, S/n",
    "sg:city":"Cabeza Del Caballo",
    "sg:orig_category":"Centros De Educaci\u00d3n Especial",
    "sg:phone":"+34 923 52 26 65",
    "sg:postcode":"37214",
    "sg:province":"Salamanca",
    "wof:name":"Ministerio De Educacion Y Ciencia Centro Docente Publico De Cabeza De Caballo",
    "wof:placetype":"venue"
},
  "geometry": {"coordinates":[-6.5563750267,41.13123703],"type":"Point"}
}