{
  "type": "Feature",
  "properties": {
    "addr:full":"Calle de Viana Principe De, 5 Bilbao Vizcaya 48007",
    "addr:housenumber":"5",
    "addr:postcode":"48007",
    "addr:street":"Calle De Viana Principe De",
    "iso:country":"ES",
    "sg:address":"Calle de Viana Principe De, 5",
    "sg:city":"Bilbao",
    "sg:orig_category":"Traductores",
    "sg:phone":"+34 944 46 05 86",
    "sg:postcode":"48007",
    "sg:province":"Vizcaya",
    "sg:website":"www.igela.net",
    "wof:name":"Igela Traducciones Sl",
    "wof:placetype":"venue"
},
  "geometry": {"coordinates":[-2.923732996,43.2661628723],"type":"Point"}
}