{
  "type": "Feature",
  "properties": {
    "iso:country":"ES",
    "sg:address":"Rua Rosalia De Castro, 15",
    "sg:city":"Vimianzo",
    "sg:orig_category":"Peluquer\u00cdas, Peluquer\u00cda Mixta",
    "sg:phone":"+34 981 71 63 97",
    "sg:postcode":"15120",
    "sg:province":"La Coru\u00f1a",
    "wof:name":"Pose Cancela Maria Isabel",
    "wof:placetype":"venue"
},
  "geometry": {"coordinates":[-9.0335187912,43.1113777161],"type":"Point"}
}