{
  "type": "Feature",
  "properties": {
    "addr:full":"Calle de Illeta, 10 Algorta Vizcaya 48991",
    "addr:housenumber":"10",
    "addr:postcode":"48991",
    "addr:street":"Calle De Illeta",
    "iso:country":"ES",
    "sg:address":"Calle de Illeta, 10",
    "sg:city":"Algorta",
    "sg:orig_category":"Peluqueros: De Se\u00d1oras",
    "sg:phone":"+34 944 30 02 28",
    "sg:postcode":"48991",
    "sg:province":"Vizcaya",
    "wof:name":"Ramirez Uribarri Itziar",
    "wof:placetype":"venue"
},
  "geometry": {"coordinates":[-3.0089840889,43.3535690308],"type":"Point"}
}