{
  "type": "Feature",
  "properties": {
    "addr:full":"Avda Madrid, 142 Zaragoza Zaragoza 50017",
    "addr:housenumber":"142",
    "addr:postcode":"50017",
    "addr:street":"Avda Madrid",
    "iso:country":"ES",
    "sg:address":"Avda Madrid, 142",
    "sg:city":"Zaragoza",
    "sg:orig_category":"Pescader\u00cdas (al Por Menor)",
    "sg:phone":"+34 976 33 22 10",
    "sg:postcode":"50017",
    "sg:province":"Zaragoza",
    "wof:name":"Toral Alejandre Leopoldo Javier",
    "wof:placetype":"venue"
},
  "geometry": {"coordinates":[-0.910589993,41.6521720886],"type":"Point"}
}