{
  "type": "Feature",
  "properties": {
    "addr:full":"Calle de Doctor Mendizabal, 4 Villarcayo Burgos 09550",
    "addr:housenumber":"4",
    "addr:postcode":"09550",
    "addr:street":"Calle De Doctor Mendizabal",
    "iso:country":"ES",
    "sg:address":"Calle de Doctor Mendizabal, 4",
    "sg:city":"Villarcayo",
    "sg:orig_category":"Carnicer\u00cdas, Carnicer\u00cdas",
    "sg:phone":"+34 947 13 21 73",
    "sg:postcode":"09550",
    "sg:province":"Burgos",
    "wof:name":"Gonzalez Rueda Jose Arturo",
    "wof:placetype":"venue"
},
  "geometry": {"coordinates":[-3.5726900101,42.9378967285],"type":"Point"}
}