{
  "type": "Feature",
  "properties": {
    "iso:country":"ES",
    "sg:address":"Ctra. General, S/n",
    "sg:city":"Trevias",
    "sg:orig_category":"Imprenta",
    "sg:phone":"+34 985 64 70 22",
    "sg:postcode":"33780",
    "sg:province":"Asturias",
    "wof:name":"Graficas Trevias S.l.",
    "wof:placetype":"venue"
},
  "geometry": {"coordinates":[-6.4858551025,43.4557800293],"type":"Point"}
}