{
  "type": "Feature",
  "properties": {
    "iso:country":"ES",
    "sg:address":"Ligallo Del Roig, S/n",
    "sg:city":"Ligallo Del Roig",
    "sg:orig_category":"Material Y Herramientas Agr\u00cdcolas",
    "sg:phone":"+34 977 47 01 11",
    "sg:postcode":"43894",
    "sg:province":"Tarragona",
    "wof:name":"Valls Bertomeu Francisco",
    "wof:placetype":"venue"
},
  "geometry": {"coordinates":[0.6723750234,40.7711791992],"type":"Point"}
}