{
  "type": "Feature",
  "properties": {
    "addr:full":"Calle de Valle Inclan, 70 Madrid Madrid 28044",
    "addr:housenumber":"70",
    "addr:postcode":"madrid;28044",
    "addr:street":"Calle De Valle Inclan",
    "iso:country":"ES",
    "sg:address":"Calle de Valle Inclan, 70",
    "sg:city":"Madrid",
    "sg:orig_category":"Inmobiliaria (agencias)",
    "sg:phone":"+34 917 05 63 98",
    "sg:postcode":"28044",
    "sg:province":"Madrid",
    "wof:name":"Estudio San Ignacio Xxi S.l.",
    "wof:placetype":"venue"
},
  "geometry": {"coordinates":[-3.775083065,40.3758010864],"type":"Point"}
}