{
  "type": "Feature",
  "properties": {
    "addr:full":"Calle de Puente (el), S/n Isso Albacete 02420",
    "addr:housenumber":"/ n",
    "addr:postcode":"02420",
    "addr:street":"Calle De Puente El S",
    "iso:country":"ES",
    "sg:address":"Calle de Puente (el), S/n",
    "sg:city":"Isso",
    "sg:orig_category":"Producci\u00d3n De Abonos Y De Fertilizantes",
    "sg:phone":"+34 967 30 87 83",
    "sg:postcode":"02420",
    "sg:province":"Albacete",
    "wof:name":"Agriisso S.l.",
    "wof:placetype":"venue"
},
  "geometry": {"coordinates":[-1.7404977083,38.4918212891],"type":"Point"}
}