{
  "type": "Feature",
  "properties": {
    "addr:full":"Avda Madridejos, 30 Villaca\u00f1as Toledo 45860",
    "addr:housenumber":"30",
    "addr:postcode":"45860",
    "addr:street":"Avda Madridejos",
    "iso:country":"ES",
    "sg:address":"Avda Madridejos, 30",
    "sg:city":"Villaca\u00f1as",
    "sg:orig_category":"Zapatos (al Por Menor)",
    "sg:phone":"+34 925 20 03 14",
    "sg:postcode":"45860",
    "sg:province":"Toledo",
    "wof:name":"Torres Cordoba Maria De Los Angeles",
    "wof:placetype":"venue"
},
  "geometry": {"coordinates":[-3.3327970505,39.6216392517],"type":"Point"}
}