{
  "type": "Feature",
  "properties": {
    "addr:full":"Calle de Recaredo Baillo, 36 Belmonte Cuenca 16640",
    "addr:housenumber":"36",
    "addr:postcode":"16640",
    "addr:street":"Calle De Recaredo Baillo",
    "iso:country":"ES",
    "sg:address":"Calle de Recaredo Baillo, 36",
    "sg:city":"Belmonte",
    "sg:classifiers":[
        {
            "category":"Autos & Motor Vehicles",
            "subcategory":"Automobile Sales",
            "type":"Retail Goods"
        }
    ],
    "sg:phone":"+34 967 17 02 52",
    "sg:postcode":"16640",
    "sg:province":"Cuenca",
    "wof:name":"Auto Escuela Belmonte S.l.",
    "wof:placetype":"venue"
},
  "geometry": {"coordinates":[-2.705094099,39.5604362488],"type":"Point"}
}