{
  "type": "Feature",
  "properties": {
    "iso:country":"ES",
    "sg:address":"Calle de San Francisco, 36",
    "sg:city":"Talavera Reina",
    "sg:orig_category":"Bazares, Art\u00cdculos De Limpieza Y De Cocina (al Por Menor)",
    "sg:phone":"+34 925 80 01 40",
    "sg:postcode":"45600",
    "sg:province":"Toledo",
    "wof:name":"Rodriguez Sanchez Castro Francisco",
    "wof:placetype":"venue"
},
  "geometry": {"coordinates":[-4.8292651176,39.9615364075],"type":"Point"}
}