{
  "type": "Feature",
  "properties": {
    "addr:full":"Calle de Perez Galdos, 1 Tomelloso Ciudad Real 13700",
    "addr:housenumber":"1",
    "addr:postcode":"13700",
    "addr:street":"Calle De Perez Galdos",
    "iso:country":"ES",
    "sg:address":"Calle de Perez Galdos, 1",
    "sg:city":"Tomelloso",
    "sg:orig_category":"Empresas De Carpinter\u00cda Met\u00c1lica",
    "sg:phone":"+34 926 50 58 30",
    "sg:postcode":"13700",
    "sg:province":"Ciudad Real",
    "wof:name":"Gomez Paulet Antonio",
    "wof:placetype":"venue"
},
  "geometry": {"coordinates":[-3.0307929516,39.157623291],"type":"Point"}
}