{
  "type": "Feature",
  "properties": {
    "iso:country":"ES",
    "sg:address":"Calle de Santa Rosa De Lima, 3",
    "sg:city":"Santa Cruz De Tenerife",
    "sg:orig_category":"Doctores En Medicina",
    "sg:phone":"+34 922 28 76 57",
    "sg:postcode":"38002",
    "sg:province":"Santa Cruz De Tenerife",
    "wof:name":"Saavedra Martinez Jose Antonio",
    "wof:placetype":"venue"
},
  "geometry": {"coordinates":[-16.2501983643,28.4694137573],"type":"Point"}
}