{
  "type": "Feature",
  "properties": {
    "addr:full":"Carrer de Rosales, 3 Sabadell Barcelona 08205",
    "addr:housenumber":"3",
    "addr:postcode":"08205",
    "addr:street":"Carrer De Rosales",
    "iso:country":"ES",
    "sg:address":"Carrer de Rosales, 3",
    "sg:city":"Sabadell",
    "sg:orig_category":"Bisuteros (fabricaci\u00d3n, Al Por Mayor)",
    "sg:phone":"+34 937 27 92 46",
    "sg:postcode":"08205",
    "sg:province":"Barcelona",
    "wof:name":"Artesa De Joies Del Valles",
    "wof:placetype":"venue"
},
  "geometry": {"coordinates":[2.1037478447,41.5420455933],"type":"Point"}
}