{
  "type": "Feature",
  "properties": {
    "addr:full":"Calle de Amargura, 3 Jerez De Los Caballeros Badajoz 06380",
    "addr:housenumber":"3",
    "addr:postcode":"06380",
    "addr:street":"Calle De Amargura",
    "iso:country":"ES",
    "sg:address":"Calle de Amargura, 3",
    "sg:city":"Jerez De Los Caballeros",
    "sg:orig_category":"Florister\u00cdas",
    "sg:phone":"+34 924 75 06 90",
    "sg:postcode":"06380",
    "sg:province":"Badajoz",
    "wof:name":"Garcia Pastelero Carmen Consuelo",
    "wof:placetype":"venue"
},
  "geometry": {"coordinates":[-6.7709307671,38.3201446533],"type":"Point"}
}