{
  "type": "Feature",
  "properties": {
    "addr:full":"Calle de Rosario, 15 S. Fernando C\u00e1diz 11100",
    "addr:housenumber":"15",
    "addr:postcode":"11100",
    "addr:street":"Calle De Rosario;S. Fernando Ca\u0301Diz",
    "iso:country":"ES",
    "sg:address":"Calle de Rosario, 15",
    "sg:city":"S. Fernando",
    "sg:orig_category":"Bisuter\u00cda, Joyer\u00cda, Relojer\u00cda (al Por Menor)",
    "sg:phone":"+34 956 88 21 33",
    "sg:postcode":"11100",
    "sg:province":"C\u00e1diz",
    "wof:name":"Servan Armario Cristobal",
    "wof:placetype":"venue"
},
  "geometry": {"coordinates":[-6.1960668564,36.4676246643],"type":"Point"}
}