{
  "type": "Feature",
  "properties": {
    "iso:country":"ES",
    "sg:address":"Rua Gandaron, 69",
    "sg:city":"Vilar",
    "sg:orig_category":"Artes Gr\u00c1ficas, Artes Pl\u00c1sticas: Material Y Suministros (al Por Menor)",
    "sg:phone":"+34 986 25 22 85",
    "sg:postcode":"36214",
    "sg:province":"Pontevedra",
    "wof:name":"Perez Bedea Enrique",
    "wof:placetype":"venue"
},
  "geometry": {"coordinates":[-8.7059106827,42.2124443054],"type":"Point"}
}