{
  "type": "Feature",
  "properties": {
    "addr:full":"Calle de Ramon Y Cajal, 113 Granja Torrehermosa Badajoz 06910",
    "addr:housenumber":"113",
    "addr:postcode":"06910",
    "addr:street":"Calle De Ramon Y Cajal",
    "iso:country":"ES",
    "sg:address":"Calle de Ramon Y Cajal, 113",
    "sg:city":"Granja Torrehermosa",
    "sg:orig_category":"Electrodom\u00c9sticos (al Por Menor)",
    "sg:phone":"+34 924 89 51 07",
    "sg:postcode":"06910",
    "sg:province":"Badajoz",
    "wof:name":"Alcolea Serrano Carlos",
    "wof:placetype":"venue"
},
  "geometry": {"coordinates":[-5.599609375,38.3090438843],"type":"Point"}
}