{
  "type": "Feature",
  "properties": {
    "iso:country":"ES",
    "sg:address":"Barr Martillo, S/n",
    "sg:city":"Villaverde Pontones",
    "sg:orig_category":"Animales (al Por Menor)",
    "sg:phone":"+34 942 50 82 20",
    "sg:postcode":"39793",
    "sg:province":"Cantabria",
    "wof:name":"Comercial Ganadera Malla",
    "wof:placetype":"venue"
},
  "geometry": {"coordinates":[-3.6987690926,43.4123954773],"type":"Point"}
}