{
  "type": "Feature",
  "properties": {
    "iso:country":"ES",
    "sg:address":"Carr Central, S/n",
    "sg:city":"Alp",
    "sg:orig_category":"Asesor\u00cda Fiscal Y Jur\u00cddica",
    "sg:phone":"+34 972 89 00 19",
    "sg:postcode":"17538",
    "sg:province":"Girona",
    "wof:name":"Consultors Financers Catalunya Central S.l.",
    "wof:placetype":"venue"
},
  "geometry": {"coordinates":[1.88458395,42.3719100952],"type":"Point"}
}