{
  "type": "Feature",
  "properties": {
    "iso:country":"ES",
    "sg:address":"Calle de Manuel Alfaro Pereira, 2",
    "sg:city":"Badajoz",
    "sg:orig_category":"Loter\u00cda Y T\u00d3mbola",
    "sg:phone":"+34 924 23 37 31",
    "sg:postcode":"06004",
    "sg:province":"Badajoz",
    "wof:name":"Crespo Dias Jacinta De Jesus",
    "wof:placetype":"venue"
},
  "geometry": {"coordinates":[-6.972413063,38.8736381531],"type":"Point"}
}