{
  "type": "Feature",
  "properties": {
    "iso:country":"ES",
    "sg:address":"Avgd Catalunya, 8",
    "sg:city":"Lleida",
    "sg:orig_category":"Peluqueros: De Se\u00d1oras",
    "sg:phone":"+34 973 27 06 39",
    "sg:postcode":"25002",
    "sg:province":"Lleida",
    "wof:name":"Surroca Esteve Josefa",
    "wof:placetype":"venue"
},
  "geometry": {"coordinates":[0.621291995,41.6112594604],"type":"Point"}
}