{
  "type": "Feature",
  "properties": {
    "addr:full":"Calle de Salvador Giner, 2 Meliana Valencia 46133",
    "addr:housenumber":"2",
    "addr:postcode":"46133",
    "addr:street":"Calle De Salvador Giner",
    "iso:country":"ES",
    "sg:address":"Calle de Salvador Giner, 2",
    "sg:city":"Meliana",
    "sg:orig_category":"Plomeros",
    "sg:phone":"+34 961 49 63 81",
    "sg:postcode":"46133",
    "sg:province":"Valencia",
    "wof:name":"Lynsmar Instalaciones S.l",
    "wof:placetype":"venue"
},
  "geometry": {"coordinates":[-0.3516710103,39.5252685547],"type":"Point"}
}