{
  "type": "Feature",
  "properties": {
    "iso:country":"ES",
    "sg:address":"Ermita, 110",
    "sg:city":"Vila Joiosa",
    "sg:orig_category":"Agencias Y Agentes Comerciales, Representantes",
    "sg:phone":"+34 965 89 56 57",
    "sg:postcode":"03570",
    "sg:province":"Alicante",
    "wof:name":"Nudarsis S.l.",
    "wof:placetype":"venue"
},
  "geometry": {"coordinates":[-0.2375639975,38.5228233337],"type":"Point"}
}