{
  "type": "Feature",
  "properties": {
    "iso:country":"ES",
    "sg:address":"Ctra Artxanda-santo Domingo, 27",
    "sg:city":"Bilbao",
    "sg:orig_category":"Clubes, Asociaciones De Ocio",
    "sg:phone":"+34 944 00 37 01",
    "sg:postcode":"48015",
    "sg:province":"Vizcaya",
    "wof:name":"Funicular De Artxanda S.a.",
    "wof:placetype":"venue"
},
  "geometry": {"coordinates":[-2.9101190567,43.270652771],"type":"Point"}
}