{
  "type": "Feature",
  "properties": {
    "addr:full":"Calle de Fortaleza Y Plaza, 2 Alaejos Valladolid 47510",
    "addr:housenumber":"2",
    "addr:postcode":"47510",
    "addr:street":"Calle De Fortaleza Y Plaza",
    "iso:country":"ES",
    "sg:address":"Calle de Fortaleza Y Plaza, 2",
    "sg:city":"Alaejos",
    "sg:orig_category":"Asociaciones, Organismos Culturales Y Socioeducativos",
    "sg:phone":"+34 983 81 75 60",
    "sg:postcode":"47510",
    "sg:province":"Valladolid",
    "wof:name":"Asociacion Tercera Edad De Alaejos",
    "wof:placetype":"venue"
},
  "geometry": {"coordinates":[-5.2173027992,41.3067550659],"type":"Point"}
}