{
  "type": "Feature",
  "properties": {
    "iso:country":"ES",
    "sg:address":"Plaz Reina, 19",
    "sg:city":"Valencia",
    "sg:orig_category":"M\u00c9dicos: Pediatr\u00cda. Enfermedades De Los Ni\u00d1os",
    "sg:phone":"+34 963 92 57 40",
    "sg:postcode":"46003",
    "sg:province":"Valencia",
    "wof:name":"Calabuig Sanchez Miguel",
    "wof:placetype":"venue"
},
  "geometry": {"coordinates":[-0.3750460148,39.4746208191],"type":"Point"}
}