{
  "type": "Feature",
  "properties": {
    "iso:country":"ES",
    "sg:address":"Calle de Puente Y Pellon, 9",
    "sg:city":"Sevilla",
    "sg:orig_category":"Telas Y Sedas (al Por Menor)",
    "sg:phone":"+34 954 22 37 36",
    "sg:postcode":"41004",
    "sg:province":"Sevilla",
    "wof:name":"Almacenes Arias S.l.",
    "wof:placetype":"venue"
},
  "geometry": {"coordinates":[-5.9922218323,37.3911094666],"type":"Point"}
}