{
  "type": "Feature",
  "properties": {
    "addr:full":"Carrer de Varsovia, 46 Barcelona Barcelona 08041",
    "addr:housenumber":"46",
    "addr:postcode":"08041",
    "addr:street":"Carrer De Varsovia",
    "iso:country":"ES",
    "sg:address":"Carrer de Varsovia, 46",
    "sg:city":"Barcelona",
    "sg:orig_category":"Peluqueros: De Se\u00d1oras",
    "sg:phone":"+34 934 35 20 88",
    "sg:postcode":"08041",
    "sg:province":"Barcelona",
    "wof:name":"Gallardo Garcia Gemma",
    "wof:placetype":"venue"
},
  "geometry": {"coordinates":[2.1755750179,41.4228363037],"type":"Point"}
}