{
  "type": "Feature",
  "properties": {
    "addr:full":"Calle de Gloria, S/n Valdepe\u00f1as Ciudad Real 13300",
    "addr:housenumber":"s / n",
    "addr:postcode":"13300",
    "addr:street":"Calle De Gloria",
    "iso:country":"ES",
    "sg:address":"Calle de Gloria, S/n",
    "sg:city":"Valdepe\u00f1as",
    "sg:orig_category":"Vidrio, Fabricaci\u00d3n Y Comercio",
    "sg:phone":"+34 926 32 45 90",
    "sg:postcode":"13300",
    "sg:province":"Ciudad Real",
    "wof:name":"Saint Gobain Vicasa S.a.",
    "wof:placetype":"venue"
},
  "geometry": {"coordinates":[-3.3965339661,38.7602806091],"type":"Point"}
}