{
  "type": "Feature",
  "properties": {
    "addr:full":"Calle de Flor, 42 Mora Toledo 45400",
    "addr:housenumber":"42",
    "addr:postcode":"45400",
    "addr:street":"Calle De Flor",
    "iso:country":"ES",
    "sg:address":"Calle de Flor, 42",
    "sg:city":"Mora",
    "sg:orig_category":"Impuestos, Tesoro P\u00dablico",
    "sg:phone":"+34 925 34 15 51",
    "sg:postcode":"45400",
    "sg:province":"Toledo",
    "wof:name":"Colado Ramirez Julian Rafael",
    "wof:placetype":"venue"
},
  "geometry": {"coordinates":[-3.777089119,39.6836013794],"type":"Point"}
}