{
  "type": "Feature",
  "properties": {
    "addr:full":"Carrer de Felip Ii, 236 Barcelona Barcelona 08016",
    "addr:housenumber":"236",
    "addr:postcode":"08016",
    "addr:street":"Carrer De Felip Ii",
    "iso:country":"ES",
    "sg:address":"Carrer de Felip Ii, 236",
    "sg:city":"Barcelona",
    "sg:orig_category":"Molduras, Junquillos, Listones Y Molduras Perforadas",
    "sg:phone":"+34 934 08 24 00",
    "sg:postcode":"08016",
    "sg:province":"Barcelona",
    "wof:name":"Vazquez Rey Juan Antonio",
    "wof:placetype":"venue"
},
  "geometry": {"coordinates":[2.177200079,41.4279670715],"type":"Point"}
}