{
  "type": "Feature",
  "properties": {
    "iso:country":"ES",
    "sg:address":"Calle de Rio Taibilla, S/n",
    "sg:city":"Ceuti",
    "sg:orig_category":"Gr\u00daas, Montacargas Y Elevadores Para Astilleros",
    "sg:phone":"+34 902 15 48 91",
    "sg:postcode":"30562",
    "sg:province":"Murcia",
    "wof:name":"Talleres Y Gruas Belen S.l.",
    "wof:placetype":"venue"
},
  "geometry": {"coordinates":[-1.2709289789,38.0850753784],"type":"Point"}
}