{
  "type": "Feature",
  "properties": {
    "addr:full":"Rua Paraguay, 5 Vigo Pontevedra 36204",
    "addr:housenumber":"5",
    "addr:postcode":"36204",
    "addr:street":"Rua Paraguay",
    "iso:country":"ES",
    "sg:address":"Rua Paraguay, 5",
    "sg:city":"Vigo",
    "sg:orig_category":"Edici\u00d3n De Diarios, Revistas, Boletines",
    "sg:phone":"+34 986 48 25 43",
    "sg:postcode":"36204",
    "sg:province":"Pontevedra",
    "wof:name":"Ediciones Lenda S.l.",
    "wof:placetype":"venue"
},
  "geometry": {"coordinates":[-8.7161207199,42.2330169678],"type":"Point"}
}