{
  "type": "Feature",
  "properties": {
    "addr:full":"Calle de Doctor Luis Prieto, 16 Aguilas Murcia 30880",
    "addr:housenumber":"16",
    "addr:postcode":"30880",
    "addr:street":"Calle De Doctor Luis Prieto",
    "iso:country":"ES",
    "sg:address":"Calle de Doctor Luis Prieto, 16",
    "sg:city":"Aguilas",
    "sg:orig_category":"Electrodom\u00c9sticos (al Por Menor)",
    "sg:phone":"+34 968 41 49 57",
    "sg:postcode":"30880",
    "sg:province":"Murcia",
    "wof:name":"Valera Hernandez Cesar",
    "wof:placetype":"venue"
},
  "geometry": {"coordinates":[-1.5827620029,37.4075737],"type":"Point"}
}