{
  "type": "Feature",
  "properties": {
    "addr:full":"Ctra. Linares, 36 Ubeda Ja\u00e9n 23400",
    "addr:housenumber":"36",
    "addr:postcode":"23400",
    "addr:street":"Ctra. Linares;Jae\u0301N",
    "iso:country":"ES",
    "sg:address":"Ctra. Linares, 36",
    "sg:city":"Ubeda",
    "sg:orig_category":"Ortopedia General",
    "sg:phone":"+34 953 75 12 37",
    "sg:postcode":"23400",
    "sg:province":"Ja\u00e9n",
    "wof:name":"Alvarez Parrilla Domingo",
    "wof:placetype":"venue"
},
  "geometry": {"coordinates":[-3.3829391003,38.0188140869],"type":"Point"}
}