{
  "type": "Feature",
  "properties": {
    "addr:full":"Barr Ventas, S/n Pekotxeta Navarra 31669",
    "addr:housenumber":"s",
    "addr:postcode":"31669",
    "addr:street":"/ N Pekotxeta Navarra",
    "iso:country":"ES",
    "sg:address":"Barr Ventas, S/n",
    "sg:city":"Pekotxeta",
    "sg:orig_category":"Bazares, Art\u00cdculos De Limpieza Y De Cocina (al Por Menor)",
    "sg:phone":"+34 948 79 00 21",
    "sg:postcode":"31669",
    "sg:province":"Navarra",
    "wof:name":"Jose Bazo S.a.",
    "wof:placetype":"venue"
},
  "geometry": {"coordinates":[-1.3061690331,43.096408844],"type":"Point"}
}