{
  "type": "Feature",
  "properties": {
    "iso:country":"ES",
    "sg:address":"Calle de Fundicion, 1",
    "sg:city":"Motril",
    "sg:orig_category":"\u00d3ptica: Instrumentos (fabricaci\u00d3n)",
    "sg:phone":"+34 958 60 90 88",
    "sg:postcode":"18600",
    "sg:province":"Granada",
    "wof:name":"Gafas Granada S.l.",
    "wof:placetype":"venue"
},
  "geometry": {"coordinates":[-3.5178580284,36.7473258972],"type":"Point"}
}