{
  "type": "Feature",
  "properties": {
    "iso:country":"ES",
    "sg:address":"Ctra Monte (del), S/n",
    "sg:city":"Palencia",
    "sg:orig_category":"Discapacitados",
    "sg:phone":"+34 979 74 16 22",
    "sg:postcode":"34005",
    "sg:province":"Palencia",
    "wof:name":"Servicios Sociales De La Junta De Castilla Y Leon",
    "wof:placetype":"venue"
},
  "geometry": {"coordinates":[-4.5382080078,42.0074653625],"type":"Point"}
}