{
  "type": "Feature",
  "properties": {
    "iso:country":"ES",
    "sg:address":"Calle de Vista Nevada, 7",
    "sg:city":"Barrio De La Vega",
    "sg:orig_category":"Agencias Y Agentes Comerciales, Representantes",
    "sg:phone":"+34 958 30 40 89",
    "sg:postcode":"18193",
    "sg:province":"Granada",
    "wof:name":"Mu\u00f1oz Rodriguez Francisco Ramon",
    "wof:placetype":"venue"
},
  "geometry": {"coordinates":[-3.5619580746,37.1308326721],"type":"Point"}
}