{
  "type": "Feature",
  "properties": {
    "iso:country":"ES",
    "sg:address":"Carr Virtut, 22",
    "sg:city":"Igualada",
    "sg:orig_category":"Frutas Y Legumbres Frescas (al Por Mayor)",
    "sg:phone":"+34 938 04 03 03",
    "sg:postcode":"08700",
    "sg:province":"Barcelona",
    "wof:name":"Fruites Doroteo S.l.",
    "wof:placetype":"venue"
},
  "geometry": {"coordinates":[1.6232110262,41.5783348083],"type":"Point"}
}