{
  "type": "Feature",
  "properties": {
    "addr:full":"Rond Sant Antoni, 46 Barcelona Barcelona 08001",
    "addr:housenumber":"46",
    "addr:postcode":"08001",
    "addr:street":"Sant Antoni",
    "iso:country":"ES",
    "sg:address":"Rond Sant Antoni, 46",
    "sg:city":"Barcelona",
    "sg:orig_category":"Electrodom\u00c9sticos (al Por Menor)",
    "sg:phone":"+34 933 29 70 00",
    "sg:postcode":"08001",
    "sg:province":"Barcelona",
    "wof:name":"Cooperativa Perez Nebot Sccl.",
    "wof:placetype":"venue"
},
  "geometry": {"coordinates":[2.1639449596,41.379032135],"type":"Point"}
}