{
  "type": "Feature",
  "properties": {
    "iso:country":"ES",
    "sg:address":"Pase San Antonio, 17",
    "sg:city":"Salamanca",
    "sg:orig_category":"Quincaller\u00cda (al Por Menor)",
    "sg:phone":"+34 923 23 00 53",
    "sg:postcode":"37003",
    "sg:province":"Salamanca",
    "wof:name":"Sogo Gomez Jose",
    "wof:placetype":"venue"
},
  "geometry": {"coordinates":[-5.6562981606,40.9648170471],"type":"Point"}
}