{
  "type": "Feature",
  "properties": {
    "iso:country":"ES",
    "sg:address":"Urb Cales Piques, 353",
    "sg:city":"Cales Piques",
    "sg:orig_category":"Supermercados Y Hipermercados",
    "sg:phone":"+34 971 38 80 66",
    "sg:postcode":"07760",
    "sg:province":"Islas Baleares",
    "wof:name":"Super Beta S.l.",
    "wof:placetype":"venue"
},
  "geometry": {"coordinates":[3.8078680038,40.0073127747],"type":"Point"}
}