{
  "type": "Feature",
  "properties": {
    "iso:country":"ES",
    "sg:address":"Calle de Frailes, 27",
    "sg:city":"Cortegana",
    "sg:classifiers":[
        {
            "category":"Taxi",
            "type":"Transportation"
        }
    ],
    "sg:phone":"+34 959 13 18 57",
    "sg:postcode":"21230",
    "sg:province":"Huelva",
    "wof:name":"Borrallo Flores Carmen",
    "wof:placetype":"venue"
},
  "geometry": {"coordinates":[-6.8190741539,37.9098167419],"type":"Point"}
}