{
  "type": "Feature",
  "properties": {
    "addr:full":"Calle de Martires, 2 Villanueva Del Duque C\u00f3rdoba 14250",
    "addr:housenumber":"2",
    "addr:postcode":"14250",
    "addr:street":"Calle De Martires;Co\u0301Rdoba",
    "iso:country":"ES",
    "sg:address":"Calle de Martires, 2",
    "sg:city":"Villanueva Del Duque",
    "sg:orig_category":"Empresas De Electricidad En General",
    "sg:phone":"+34 957 12 61 74",
    "sg:postcode":"14250",
    "sg:province":"C\u00f3rdoba",
    "wof:name":"Central Electrica San Francisco S.l.",
    "wof:placetype":"venue"
},
  "geometry": {"coordinates":[-4.9980359077,38.3927383423],"type":"Point"}
}