{
  "type": "Feature",
  "properties": {
    "addr:full":"Arretxe Kalea, 15 Azpeitia Guip\u00f9zcoa 20730",
    "addr:housenumber":"15",
    "addr:postcode":"20730",
    "addr:street":"Arretxe Kalea;Guipu\u0300Zcoa",
    "iso:country":"ES",
    "sg:address":"Arretxe Kalea, 15",
    "sg:city":"Azpeitia",
    "sg:orig_category":"Empresas De Carpinter\u00cda De Madera",
    "sg:phone":"+34 943 81 01 65",
    "sg:postcode":"20730",
    "sg:province":"Guip\u00f9zcoa",
    "wof:name":"Mitxel Aroztegia S.l.",
    "wof:placetype":"venue"
},
  "geometry": {"coordinates":[-2.2582550049,43.1797370911],"type":"Point"}
}