{
  "type": "Feature",
  "properties": {
    "addr:full":"Calle de Francos Rodriguez, 24 Madrid Madrid 28039",
    "addr:housenumber":"24",
    "addr:postcode":"madrid;28039",
    "addr:street":"Calle De Francos Rodriguez",
    "iso:country":"ES",
    "sg:address":"Calle de Francos Rodriguez, 24",
    "sg:city":"Madrid",
    "sg:orig_category":"Perfumer\u00cda (al Por Menor)",
    "sg:phone":"+34 913 11 52 15",
    "sg:postcode":"28039",
    "sg:province":"Madrid",
    "sg:website":"www.marionnaud.es",
    "wof:name":"Marionnaud Perfumeries Iberica S.l.",
    "wof:placetype":"venue"
},
  "geometry": {"coordinates":[-3.7040998936,40.4556121826],"type":"Point"}
}