{
  "type": "Feature",
  "properties": {
    "addr:full":"Calle de Antonio Ponz, 41 Valencia Valencia 46011",
    "addr:housenumber":"41",
    "addr:postcode":"46011",
    "addr:street":"Calle De Antonio Ponz",
    "iso:country":"ES",
    "sg:address":"Calle de Antonio Ponz, 41",
    "sg:city":"Valencia",
    "sg:orig_category":"Empresas De Carpinter\u00cda De Madera",
    "sg:phone":"+34 963 56 30 48",
    "sg:postcode":"46011",
    "sg:province":"Valencia",
    "wof:name":"Fernandez Martinez Francisco Javier",
    "wof:placetype":"venue"
},
  "geometry": {"coordinates":[-0.3273578882,39.481212616],"type":"Point"}
}