{
  "type": "Feature",
  "properties": {
    "addr:full":"Calle de Comercio, 2 Coru\u00d1a La Coru\u00f1a 15010",
    "addr:housenumber":"2",
    "addr:postcode":"15010",
    "addr:street":"Calle De Comercio;La Corun\u0303A",
    "iso:country":"ES",
    "sg:address":"Calle de Comercio, 2",
    "sg:city":"Coru\u00d1a",
    "sg:orig_category":"Caf\u00c9s, Bares, Cervecer\u00cdas",
    "sg:phone":"+34 981 26 27 99",
    "sg:postcode":"15010",
    "sg:province":"La Coru\u00f1a",
    "wof:name":"Mesias Sanjurjo Antonio",
    "wof:placetype":"venue"
},
  "geometry": {"coordinates":[-8.417301178,43.3617706299],"type":"Point"}
}