{
  "type": "Feature",
  "properties": {
    "iso:country":"ES",
    "sg:address":"Calle de Ramon Gomez De La Serna, 22",
    "sg:city":"Marbella",
    "sg:orig_category":"Centros De Coordinaci\u00d3n",
    "sg:phone":"+34 952 85 70 97",
    "sg:postcode":"29600",
    "sg:province":"M\u00e1laga",
    "wof:name":"Gestoria Marbella Internacional 98 S.l.",
    "wof:placetype":"venue"
},
  "geometry": {"coordinates":[-4.9014258385,36.5095901489],"type":"Point"}
}