{
  "type": "Feature",
  "properties": {
    "addr:full":"Calle de Virgen De Fatima, 6 Motril Granada 18600",
    "addr:housenumber":"6",
    "addr:postcode":"18600",
    "addr:street":"Calle De Virgen De Fatima",
    "iso:country":"ES",
    "sg:address":"Calle de Virgen De Fatima, 6",
    "sg:city":"Motril",
    "sg:orig_category":"Cristaler\u00cdas",
    "sg:phone":"+34 958 82 00 63",
    "sg:postcode":"18600",
    "sg:province":"Granada",
    "wof:name":"Perez Jimenez Ignacio",
    "wof:placetype":"venue"
},
  "geometry": {"coordinates":[-3.5144228935,36.7451286316],"type":"Point"}
}