{
  "type": "Feature",
  "properties": {
    "addr:full":"Calle de Lopez De Ayala, 41 Villanueva Serena Badajoz 06700",
    "addr:housenumber":"41",
    "addr:postcode":"06700",
    "addr:street":"Calle De Lopez De Ayala",
    "iso:country":"ES",
    "sg:address":"Calle de Lopez De Ayala, 41",
    "sg:city":"Villanueva Serena",
    "sg:orig_category":"Empresarios Y Productoras De Espect\u00c1culos",
    "sg:phone":"+34 924 84 90 78",
    "sg:postcode":"06700",
    "sg:province":"Badajoz",
    "wof:name":"Lobo Records",
    "wof:placetype":"venue"
},
  "geometry": {"coordinates":[-5.797118187,38.9745407104],"type":"Point"}
}