{
  "type": "Feature",
  "properties": {
    "iso:country":"ES",
    "sg:address":"Calle de Condes De Montijo, 10",
    "sg:city":"Montijo",
    "sg:orig_category":"Tintorer\u00cdas, Limpieza En Seco",
    "sg:phone":"+34 924 45 20 01",
    "sg:postcode":"06480",
    "sg:province":"Badajoz",
    "wof:name":"Nu\u00f1ez Sanchez Antonio",
    "wof:placetype":"venue"
},
  "geometry": {"coordinates":[-6.6194067001,38.9090461731],"type":"Point"}
}