{
  "type": "Feature",
  "properties": {
    "addr:full":"Carrer de Valles I Ribot, 8 Barcelona Barcelona 08027",
    "addr:housenumber":"8",
    "addr:postcode":"08027",
    "addr:street":"Carrer De Valles I Ribot",
    "iso:country":"ES",
    "sg:address":"Carrer de Valles I Ribot, 8",
    "sg:city":"Barcelona",
    "sg:orig_category":"Farmacias",
    "sg:phone":"+34 933 52 24 07",
    "sg:postcode":"08027",
    "sg:province":"Barcelona",
    "wof:name":"Sanz Suay Nestor",
    "wof:placetype":"venue"
},
  "geometry": {"coordinates":[2.1889719963,41.4230918884],"type":"Point"}
}