{
  "type": "Feature",
  "properties": {
    "addr:full":"Rua Poeta Lois Pereiro, 8 Monforte De Lemos Lugo 27400",
    "addr:housenumber":"8",
    "addr:postcode":"27400",
    "addr:street":"Rua Poeta Lois Pereiro",
    "iso:country":"ES",
    "sg:address":"Rua Poeta Lois Pereiro, 8",
    "sg:city":"Monforte De Lemos",
    "sg:orig_category":"Agencias Y Agentes Comerciales, Representantes",
    "sg:phone":"+34 982 40 33 25",
    "sg:postcode":"27400",
    "sg:province":"Lugo",
    "wof:name":"Promociones Y Construcciones Sarria S.a.",
    "wof:placetype":"venue"
},
  "geometry": {"coordinates":[-7.5172939301,42.5221710205],"type":"Point"}
}