{
  "type": "Feature",
  "properties": {
    "addr:full":"Bacelo, 2 Bacelo Ourense 32417",
    "addr:housenumber":"2",
    "addr:postcode":"32417",
    "addr:street":"Bacelo Ourense",
    "iso:country":"ES",
    "sg:address":"Bacelo, 2",
    "sg:city":"Bacelo",
    "sg:orig_category":"Contenedores (mercanc\u00cdas)",
    "sg:phone":"+34 988 49 29 20",
    "sg:postcode":"32417",
    "sg:province":"Ourense",
    "wof:name":"Pivida Vazquez Dolores",
    "wof:placetype":"venue"
},
  "geometry": {"coordinates":[-8.1362161636,42.2448577881],"type":"Point"}
}