{
  "type": "Feature",
  "properties": {
    "addr:full":"Czad Castellanos, 41 Poligono Industrial Los Villares Salamanca 37184",
    "addr:housenumber":"41",
    "addr:postcode":"37184",
    "addr:street":"Czad;Poligono Industrial",
    "iso:country":"ES",
    "sg:address":"Czad Castellanos, 41",
    "sg:city":"Poligono Industrial Los Villares",
    "sg:orig_category":"Quincaller\u00cda (al Por Menor)",
    "sg:phone":"+34 923 25 30 31",
    "sg:postcode":"37184",
    "sg:province":"Salamanca",
    "wof:name":"L.j.m Suministros Industriales S.l",
    "wof:placetype":"venue"
},
  "geometry": {"coordinates":[-5.630669117,40.9951896667],"type":"Point"}
}