{
  "type": "Feature",
  "properties": {
    "addr:full":"Calle de Hermana Brigida, 4 Moguer Huelva 21800",
    "addr:housenumber":"4",
    "addr:postcode":"21800",
    "addr:street":"Calle De Hermana Brigida",
    "iso:country":"ES",
    "sg:address":"Calle de Hermana Brigida, 4",
    "sg:city":"Moguer",
    "sg:orig_category":"Ingenier\u00cda, Centros De Estudios (diversos)",
    "sg:phone":"+34 959 37 13 35",
    "sg:postcode":"21800",
    "sg:province":"Huelva",
    "wof:name":"Prorreding Ii S.l.",
    "wof:placetype":"venue"
},
  "geometry": {"coordinates":[-6.8342490196,37.2783584595],"type":"Point"}
}