{
  "type": "Feature",
  "properties": {
    "addr:full":"Calle de Jorge Juan, 84 Castellon Castell\u00f3n 12006",
    "addr:housenumber":"84",
    "addr:postcode":"12006",
    "addr:street":"Calle De Jorge Juan",
    "iso:country":"ES",
    "sg:address":"Calle de Jorge Juan, 84",
    "sg:city":"Castellon",
    "sg:orig_category":"Fabricaci\u00d3n De Su\u00c9ters Y Chalecos De Punto",
    "sg:phone":"+34 964 20 12 91",
    "sg:postcode":"12006",
    "sg:province":"Castell\u00f3n",
    "wof:name":"Salvador Vicente Francisco",
    "wof:placetype":"venue"
},
  "geometry": {"coordinates":[-0.1292939931,40.0168533325],"type":"Point"}
}