{
  "type": "Feature",
  "properties": {
    "addr:full":"Avda Albufera, 7 Alfafar Valencia 46910",
    "addr:housenumber":"7",
    "addr:postcode":"46910",
    "addr:street":"Avda Albufera",
    "iso:country":"ES",
    "sg:address":"Avda Albufera, 7",
    "sg:city":"Alfafar",
    "sg:orig_category":"Cajas De Ahorro",
    "sg:phone":"+34 963 75 87 03",
    "sg:postcode":"46910",
    "sg:province":"Valencia",
    "sg:website":"www.lacaixa.es",
    "wof:name":"Caixa D'estalvis I Pensions De Barcelona",
    "wof:placetype":"venue"
},
  "geometry": {"coordinates":[-0.3778989911,39.4160575867],"type":"Point"}
}