{
  "type": "Feature",
  "properties": {
    "addr:full":"Cami. Vell Rubi-s. Cugat, S/n Rubi Barcelona 08...",
    "addr:housenumber":"s;08 ...",
    "addr:street":"Cami. Vell Rubi-S. Cugat;/ N;Barcelona",
    "iso:country":"ES",
    "sg:address":"Cami. Vell Rubi-s. Cugat, S/n",
    "sg:city":"Rubi",
    "sg:orig_category":"Cables Y Hilos El\u00c9ctricos (fabricaci\u00d3n, Al Por Mayor)",
    "sg:phone":"+34 935 61 49 00",
    "sg:postcode":"08...",
    "sg:province":"Barcelona",
    "wof:name":"Alcabe S.a.",
    "wof:placetype":"venue"
},
  "geometry": {"coordinates":[2.0312616825,41.4923324585],"type":"Point"}
}