{
  "type": "Feature",
  "properties": {
    "iso:country":"ES",
    "sg:address":"Avda Ramon Y Cajal, 50",
    "sg:city":"Almaden",
    "sg:orig_category":"Reposter\u00cdas",
    "sg:phone":"+34 926 71 01 78",
    "sg:postcode":"13400",
    "sg:province":"Ciudad Real",
    "wof:name":"Dorado Viso Braulio",
    "wof:placetype":"venue"
},
  "geometry": {"coordinates":[-4.8295559883,38.7821083069],"type":"Point"}
}