{
  "type": "Feature",
  "properties": {
    "addr:full":"Pg Estacio, 1 Pobla De Montornes Tarragona 43761",
    "addr:housenumber":"1",
    "addr:postcode":"43761",
    "addr:street":"Pg Estacio",
    "iso:country":"ES",
    "sg:address":"Pg Estacio, 1",
    "sg:city":"Pobla De Montornes",
    "sg:orig_category":"Fabricaci\u00d3n De Telas Y Sedas",
    "sg:phone":"+34 977 64 81 14",
    "sg:postcode":"43761",
    "sg:province":"Tarragona",
    "sg:website":"www.recasens.com",
    "wof:name":"S.a. Recasens",
    "wof:placetype":"venue"
},
  "geometry": {"coordinates":[1.4161599874,41.1763839722],"type":"Point"}
}