{
  "type": "Feature",
  "properties": {
    "iso:country":"ES",
    "sg:address":"Calle de Joaquin Costa, 39",
    "sg:city":"Teruel",
    "sg:orig_category":"Deportes Y Ocio: Art\u00cdculos Y Ropas (al Por Menor Y Accesorios)",
    "sg:phone":"+34 978 60 77 76",
    "sg:postcode":"44001",
    "sg:province":"Teruel",
    "wof:name":"Deportes El Tozal C. B.",
    "wof:placetype":"venue"
},
  "geometry": {"coordinates":[-1.105891943,40.3438873291],"type":"Point"}
}