{
  "type": "Feature",
  "properties": {
    "iso:country":"ES",
    "sg:address":"Calle de I\u00d1igo Lopez De Haro Kalea, 15",
    "sg:city":"Gernika-lumo",
    "sg:orig_category":"Venta, Instalaci\u00d3n De Calefacci\u00d3n",
    "sg:phone":"+34 946 25 55 11",
    "sg:postcode":"48300",
    "sg:province":"Vizcaya",
    "wof:name":"Urarin, S.l.",
    "wof:placetype":"venue"
},
  "geometry": {"coordinates":[-2.6801118851,43.317401886],"type":"Point"}
}