{
  "type": "Feature",
  "properties": {
    "iso:country":"ES",
    "sg:address":"Carrer de Goleta, 3",
    "sg:city":"Terrassa",
    "sg:orig_category":"Ropa Para Se\u00d1oras Y Caballeros (al Por Menor)",
    "sg:phone":"+34 937 33 29 28",
    "sg:postcode":"08221",
    "sg:province":"Barcelona",
    "sg:website":"www.lacoste.es",
    "wof:name":"Tauros 85 Sll",
    "wof:placetype":"venue"
},
  "geometry": {"coordinates":[2.0091600418,41.5631103516],"type":"Point"}
}