{
  "type": "Feature",
  "properties": {
    "addr:full":"Carrer de Montserrat, 17 Sentmenat Barcelona 08181",
    "addr:housenumber":"17",
    "addr:postcode":"08181",
    "addr:street":"Carrer De Montserrat",
    "iso:country":"ES",
    "sg:address":"Carrer de Montserrat, 17",
    "sg:city":"Sentmenat",
    "sg:orig_category":"Empresas De Carpinter\u00cda",
    "sg:phone":"+34 937 15 14 06",
    "sg:postcode":"08181",
    "sg:province":"Barcelona",
    "wof:name":"Furete Carmona David 000909776n S.l.",
    "wof:placetype":"venue"
},
  "geometry": {"coordinates":[2.1351981163,41.6102180481],"type":"Point"}
}