{
  "type": "Feature",
  "properties": {
    "addr:full":"Urb C.r. La Soledad, S/n Chiclana De La Frontera C\u00e1diz 11130",
    "addr:housenumber":"s",
    "addr:postcode":"11130",
    "addr:street":"Urb C.R. La Soledad;/ N",
    "iso:country":"ES",
    "sg:address":"Urb C.r. La Soledad, S/n",
    "sg:city":"Chiclana De La Frontera",
    "sg:orig_category":"Aguas (distribuci\u00d3n, Servicios)",
    "sg:phone":"+34 956 53 22 00",
    "sg:postcode":"11130",
    "sg:province":"C\u00e1diz",
    "sg:website":"www.chiclananatural.com",
    "wof:name":"Chiclana Natural S.a.",
    "wof:placetype":"venue"
},
  "geometry": {"coordinates":[-6.157763958,36.4190406799],"type":"Point"}
}