{
  "type": "Feature",
  "properties": {
    "addr:full":"Bazkardo Plaza, 3 Andoain Guip\u00f9zcoa 20140",
    "addr:housenumber":"3",
    "addr:postcode":"20140",
    "addr:street":"Bazkardo Plaza;Guipu\u0300Zcoa",
    "iso:country":"ES",
    "sg:address":"Bazkardo Plaza, 3",
    "sg:city":"Andoain",
    "sg:orig_category":"Molduras, Junquillos, Listones Y Molduras Perforadas",
    "sg:phone":"+34 943 59 28 05",
    "sg:postcode":"20140",
    "sg:province":"Guip\u00f9zcoa",
    "wof:name":"Maria Angeles Segurola Embil",
    "wof:placetype":"venue"
},
  "geometry": {"coordinates":[-2.0260670185,43.2224006653],"type":"Point"}
}