{
  "type": "Feature",
  "properties": {
    "addr:full":"Calle de Jacinto Benavente, 8 Fuengirola M\u00e1laga 29640",
    "addr:housenumber":"8",
    "addr:postcode":"29640",
    "addr:street":"Calle De Jacinto Benavente;Ma\u0301Laga",
    "iso:country":"ES",
    "sg:address":"Calle de Jacinto Benavente, 8",
    "sg:city":"Fuengirola",
    "sg:orig_category":"Bazares, Art\u00cdculos De Limpieza Y De Cocina (al Por Menor)",
    "sg:phone":"+34 952 47 87 42",
    "sg:postcode":"29640",
    "sg:province":"M\u00e1laga",
    "wof:name":"Lahyani Mohamed Mimoun",
    "wof:placetype":"venue"
},
  "geometry": {"coordinates":[-4.6206698418,36.5404281616],"type":"Point"}
}