{
  "type": "Feature",
  "properties": {
    "addr:full":"Calle de Groizard, 5 Don Benito Badajoz 06400",
    "addr:housenumber":"5",
    "addr:postcode":"06400",
    "addr:street":"Calle De Groizard",
    "iso:country":"ES",
    "sg:address":"Calle de Groizard, 5",
    "sg:city":"Don Benito",
    "sg:orig_category":"Institutos De Belleza",
    "sg:phone":"+34 924 80 17 90",
    "sg:postcode":"06400",
    "sg:province":"Badajoz",
    "wof:name":"Cerrato Gonzalez Rocio",
    "wof:placetype":"venue"
},
  "geometry": {"coordinates":[-5.861618042,38.9553489685],"type":"Point"}
}