{
  "type": "Feature",
  "properties": {
    "addr:full":"Barr Riegos (los), 9 Arce Cantabria 39478",
    "addr:postcode":"39478",
    "iso:country":"ES",
    "sg:address":"Barr Riegos (los), 9",
    "sg:city":"Arce",
    "sg:orig_category":"Comisarios",
    "sg:phone":"+34 942 57 53 05",
    "sg:postcode":"39478",
    "sg:province":"Cantabria",
    "wof:name":"Velarde Perez Emiliano",
    "wof:placetype":"venue"
},
  "geometry": {"coordinates":[-3.9400789738,43.4105300903],"type":"Point"}
}