{
  "type": "Feature",
  "properties": {
    "addr:full":"Calle de Glorieta, 3 Ca\u00e7ete De Las Torres C\u00f3rdoba 14660",
    "addr:housenumber":"3",
    "addr:postcode":"14660",
    "addr:street":"Calle De Glorieta;Co\u0301Rdoba",
    "iso:country":"ES",
    "sg:address":"Calle de Glorieta, 3",
    "sg:city":"Ca\u00e7ete De Las Torres",
    "sg:orig_category":"Material Y Herramientas Agr\u00cdcolas",
    "sg:phone":"+34 957 18 31 58",
    "sg:postcode":"14660",
    "sg:province":"C\u00f3rdoba",
    "wof:name":"J. Rosa S.l.",
    "wof:placetype":"venue"
},
  "geometry": {"coordinates":[-4.7791519165,37.884727478],"type":"Point"}
}