{
  "type": "Feature",
  "properties": {
    "iso:country":"ES",
    "sg:address":"Avda Francisco Montenegro, 1",
    "sg:city":"Huelva",
    "sg:orig_category":"Electricidad: Equipos Industriales, Componentes (fabricaci\u00d3n)",
    "sg:phone":"+34 959 25 02 95",
    "sg:postcode":"21001",
    "sg:province":"Huelva",
    "wof:name":"Ramos Sierra Sa",
    "wof:placetype":"venue"
},
  "geometry": {"coordinates":[-6.9519839287,37.2283668518],"type":"Point"}
}