{
  "type": "Feature",
  "properties": {
    "iso:country":"ES",
    "sg:address":"Carr Enric Arderiu, 1",
    "sg:city":"Lleida",
    "sg:orig_category":"Administradores De Bienes Y Delegados De Comunidades De Propietarios",
    "sg:phone":"+34 973 22 83 02",
    "sg:postcode":"25005",
    "sg:province":"Lleida",
    "wof:name":"Gestio De Finques Rive S.l.",
    "wof:placetype":"venue"
},
  "geometry": {"coordinates":[0.632001996,41.6284217834],"type":"Point"}
}