{
  "type": "Feature",
  "properties": {
    "addr:full":"Calle de Mercado, 6 Navalmoral Mata C\u00e1ceres 10300",
    "addr:housenumber":"6",
    "addr:postcode":"10300",
    "addr:street":"Calle De Mercado;Ca\u0301Ceres",
    "iso:country":"ES",
    "sg:address":"Calle de Mercado, 6",
    "sg:city":"Navalmoral Mata",
    "sg:orig_category":"Ropa Para Caballeros (al Por Menor)",
    "sg:phone":"+34 927 53 25 93",
    "sg:postcode":"10300",
    "sg:province":"C\u00e1ceres",
    "wof:name":"Paz Moyano Agustin De",
    "wof:placetype":"venue"
},
  "geometry": {"coordinates":[-5.5387191772,39.8892631531],"type":"Point"}
}