{
  "type": "Feature",
  "properties": {
    "iso:country":"ES",
    "sg:address":"Calle de San Francisco, 70",
    "sg:city":"Burgos",
    "sg:orig_category":"Confecci\u00d3n De Trajes De Ba\u00d1o Y De Ropa De Playa",
    "sg:phone":"+34 947 21 57 49",
    "sg:postcode":"09005",
    "sg:province":"Burgos",
    "wof:name":"Artifex Herica S. A",
    "wof:placetype":"venue"
},
  "geometry": {"coordinates":[-3.6968173981,42.3506507874],"type":"Point"}
}