{
  "type": "Feature",
  "properties": {
    "iso:country":"ES",
    "sg:address":"Avda Daganzo, 4",
    "sg:city":"Alcala Henares",
    "sg:classifiers":[
        {
            "category":"Autos & Motor Vehicles",
            "subcategory":"Automobile Sales",
            "type":"Retail Goods"
        }
    ],
    "sg:phone":"+34 918 88 08 93",
    "sg:postcode":"28806",
    "sg:province":"Madrid",
    "wof:name":"Autoescuelas Oromar-ta S.l.",
    "wof:placetype":"venue"
},
  "geometry": {"coordinates":[-3.3815360069,40.4936027527],"type":"Point"}
}