{
  "type": "Feature",
  "properties": {
    "addr:full":"Ctra Nacional V, Km. 0292,0 Miajadas C\u00e1ceres 10100",
    "addr:postcode":"10100",
    "addr:street":"Ctra Nacional V Km. 0292,0;Ca\u0301Ceres",
    "iso:country":"ES",
    "sg:address":"Ctra Nacional V, Km. 0292,0",
    "sg:city":"Miajadas",
    "sg:orig_category":"Ense\u00d1anza, Formaci\u00d3n Profesional: Aprendizaje",
    "sg:phone":"+34 927 34 50 80",
    "sg:postcode":"10100",
    "sg:province":"C\u00e1ceres",
    "wof:name":"Servicio Publico De Empleo Estatal-dron. Prov. Caceres",
    "wof:placetype":"venue"
},
  "geometry": {"coordinates":[-5.9082989693,39.1555213928],"type":"Point"}
}