{
  "type": "Feature",
  "properties": {
    "iso:country":"ES",
    "sg:address":"Calle de Fuentona, S/n",
    "sg:city":"Fuente S. Esteban",
    "sg:orig_category":"Pensiones Familiares",
    "sg:phone":"+34 923 44 00 31",
    "sg:postcode":"37200",
    "sg:province":"Salamanca",
    "wof:name":"Cuadrado Iglesias Maria Teresa",
    "wof:placetype":"venue"
},
  "geometry": {"coordinates":[-6.1650328636,40.826171875],"type":"Point"}
}