{
  "type": "Feature",
  "properties": {
    "iso:country":"ES",
    "sg:address":"Calle de Madre Puy, 8",
    "sg:city":"Calatayud",
    "sg:orig_category":"Comercio, Reparaci\u00d3n De Motocicletas, Bicicletas Y Piezas Sueltas",
    "sg:phone":"+34 976 88 46 00",
    "sg:postcode":"50300",
    "sg:province":"Zaragoza",
    "wof:name":"R P M Moreno S.l.",
    "wof:placetype":"venue"
},
  "geometry": {"coordinates":[-1.6386870146,41.3509254456],"type":"Point"}
}