{
  "type": "Feature",
  "properties": {
    "iso:country":"ES",
    "sg:address":"Calle de Heraclio Fournier, 19",
    "sg:city":"Vitoria-gasteiz",
    "sg:orig_category":"Caf\u00c9s, Bares, Cervecer\u00cdas",
    "sg:phone":"+34 945 14 42 25",
    "sg:postcode":"01006",
    "sg:province":"\u00c1lava",
    "wof:name":"Ladritel Gasteiz S.l.",
    "wof:placetype":"venue"
},
  "geometry": {"coordinates":[-2.6650211811,42.8381652832],"type":"Point"}
}