{
  "type": "Feature",
  "properties": {
    "addr:full":"Avda Primero De Mayo, 1 Valencia Valencia 46017",
    "addr:housenumber":"1",
    "addr:postcode":"46017",
    "addr:street":"Avda Primero De Mayo",
    "iso:country":"ES",
    "sg:address":"Avda Primero De Mayo, 1",
    "sg:city":"Valencia",
    "sg:orig_category":"Molduras, Junquillos, Listones Y Molduras Perforadas",
    "sg:phone":"+34 963 78 69 29",
    "sg:postcode":"46017",
    "sg:province":"Valencia",
    "wof:name":"Romo Barahona Mari Cruz",
    "wof:placetype":"venue"
},
  "geometry": {"coordinates":[-0.3857699931,39.4484863281],"type":"Point"}
}