{
  "type": "Feature",
  "properties": {
    "iso:country":"ES",
    "sg:address":"Avda Reina Victoria, 54",
    "sg:city":"Madrid",
    "sg:orig_category":"Publicidad (soportes Y Gesti\u00d3n)",
    "sg:phone":"+34 915 33 66 39",
    "sg:postcode":"28003",
    "sg:province":"Madrid",
    "wof:name":"Gallego Blanco Benigno",
    "wof:placetype":"venue"
},
  "geometry": {"coordinates":[-3.7121119499,40.4466705322],"type":"Point"}
}