{
  "type": "Feature",
  "properties": {
    "addr:full":"Avgd De Iecla, 28 Benicarlo Castell\u00f3n 12580",
    "addr:housenumber":"28",
    "addr:postcode":"12580",
    "iso:country":"ES",
    "sg:address":"Avgd De Iecla, 28",
    "sg:city":"Benicarlo",
    "sg:orig_category":"Inform\u00c1tica (estudios, Servicios, Asesor\u00cda, Formaci\u00d3n)",
    "sg:phone":"+34 964 47 47 70",
    "sg:postcode":"12580",
    "sg:province":"Castell\u00f3n",
    "wof:name":"Winstation S.l.",
    "wof:placetype":"venue"
},
  "geometry": {"coordinates":[0.4030939937,40.4407463074],"type":"Point"}
}