{
  "type": "Feature",
  "properties": {
    "iso:country":"ES",
    "sg:address":"Calle de Moros, 12",
    "sg:city":"Gijon",
    "sg:orig_category":"Asesor\u00cda Fiscal Y Jur\u00cddica",
    "sg:phone":"+34 985 17 51 42",
    "sg:postcode":"33206",
    "sg:province":"Asturias",
    "wof:name":"Union Asturiana De Asesores",
    "wof:placetype":"venue"
},
  "geometry": {"coordinates":[-5.6633992195,43.5416717529],"type":"Point"}
}