{
  "type": "Feature",
  "properties": {
    "iso:country":"ES",
    "sg:address":"Calle de Iglesia, 20",
    "sg:city":"Aliseda",
    "sg:orig_category":"Iglesia Cat\u00d3lica",
    "sg:phone":"+34 927 27 71 21",
    "sg:postcode":"10550",
    "sg:province":"C\u00e1ceres",
    "wof:name":"Parroquia Nuestra Se\u00f1ora De La Asuncion",
    "wof:placetype":"venue"
},
  "geometry": {"coordinates":[-6.6906900406,39.4207000732],"type":"Point"}
}