{
  "type": "Feature",
  "properties": {
    "addr:full":"Avda Eduardo Dato, 45 Sevilla Sevilla 41018",
    "addr:housenumber":"45",
    "addr:postcode":"41018",
    "addr:street":"Avda Eduardo Dato",
    "iso:country":"ES",
    "sg:address":"Avda Eduardo Dato, 45",
    "sg:city":"Sevilla",
    "sg:orig_category":"Abogados",
    "sg:phone":"+34 954 53 16 20",
    "sg:postcode":"41018",
    "sg:province":"Sevilla",
    "wof:name":"Areal Tavora Joaquin",
    "wof:placetype":"venue"
},
  "geometry": {"coordinates":[-5.9762558937,37.3834495544],"type":"Point"}
}