{
  "type": "Feature",
  "properties": {
    "iso:country":"ES",
    "sg:address":"Calle de Palmera, 14",
    "sg:city":"Puebla Alfinden",
    "sg:orig_category":"Perfumer\u00cda, Art\u00cdculos De Ba\u00d1o (fabricaci\u00d3n, Al Por Mayor)",
    "sg:phone":"+34 976 10 85 00",
    "sg:postcode":"50171",
    "sg:province":"Zaragoza",
    "wof:name":"Creative Perfums S.l.",
    "wof:placetype":"venue"
},
  "geometry": {"coordinates":[-0.7614790201,41.6412010193],"type":"Point"}
}