{
  "type": "Feature",
  "properties": {
    "iso:country":"ES",
    "sg:address":"Carrer de Passeig, 24",
    "sg:city":"Castellar Valles",
    "sg:orig_category":"Importaci\u00d3n",
    "sg:phone":"+34 937 15 87 36",
    "sg:postcode":"08211",
    "sg:province":"Barcelona",
    "sg:website":"www.donpiso.com",
    "wof:name":"Ferrovial Servicios Inmobiliarios S.l.",
    "wof:placetype":"venue"
},
  "geometry": {"coordinates":[2.0856060982,41.6146125793],"type":"Point"}
}