{
  "type": "Feature",
  "properties": {
    "addr:full":"Carrer de Alcoi, 9 Terrassa Barcelona 08225",
    "addr:housenumber":"9",
    "addr:postcode":"08225",
    "addr:street":"Carrer De Alcoi",
    "iso:country":"ES",
    "sg:address":"Carrer de Alcoi, 9",
    "sg:city":"Terrassa",
    "sg:orig_category":"Peluqueros: De Se\u00d1oras",
    "sg:phone":"+34 937 35 77 80",
    "sg:postcode":"08225",
    "sg:province":"Barcelona",
    "wof:name":"Romero Montoro Ricardo",
    "wof:placetype":"venue"
},
  "geometry": {"coordinates":[2.0075309277,41.5790290833],"type":"Point"}
}