{
  "type": "Feature",
  "properties": {
    "iso:country":"ES",
    "sg:address":"Calle de Embajadores, 62",
    "sg:city":"Valladolid",
    "sg:orig_category":"Negocio De Enlosados, Soler\u00cdas",
    "sg:phone":"+34 983 23 08 91",
    "sg:postcode":"47013",
    "sg:province":"Valladolid",
    "wof:name":"Pavimentos Sanchez Pascual S.r.l",
    "wof:placetype":"venue"
},
  "geometry": {"coordinates":[-4.7224988937,41.6349563599],"type":"Point"}
}