{
  "type": "Feature",
  "properties": {
    "addr:full":"Calle de Monasterio De Caaveiro, 4 Coru\u00d1a A Coru\u00f1a 15010",
    "addr:housenumber":"4",
    "addr:postcode":"15010",
    "addr:street":"Calle De Monasterio De Caaveiro;Corun\u0303A",
    "iso:country":"ES",
    "sg:address":"Calle de Monasterio De Caaveiro, 4",
    "sg:city":"Coru\u00d1a",
    "sg:orig_category":"Librer\u00cdas",
    "sg:phone":"+34 981 14 05 39",
    "sg:postcode":"15010",
    "sg:province":"A Coru\u00f1a",
    "wof:name":"Tecnicas De Eficacia Social S.l. (ites",
    "wof:placetype":"venue"
},
  "geometry": {"coordinates":[-8.4256467819,43.3620185852],"type":"Point"}
}