{
  "type": "Feature",
  "properties": {
    "iso:country":"ES",
    "sg:address":"Cami Antic A Vilablareix, S/n",
    "sg:city":"Salt",
    "sg:orig_category":"Aislamiento El\u00c9ctrico",
    "sg:phone":"+34 972 23 54 10",
    "sg:postcode":"17190",
    "sg:province":"Girona",
    "wof:name":"Aislamientos Luis S.l.",
    "wof:placetype":"venue"
},
  "geometry": {"coordinates":[2.8220713139,41.9737968445],"type":"Point"}
}