{
  "type": "Feature",
  "properties": {
    "iso:country":"ES",
    "sg:address":"G.v. Lopez De Haro D. Diego, 61",
    "sg:city":"Bilbao",
    "sg:orig_category":"Bancos",
    "sg:phone":"+34 944 42 40 93",
    "sg:postcode":"48011",
    "sg:province":"Vizcaya",
    "sg:website":"www.bancosimeon.es",
    "wof:name":"Banco Caixa Geral S.a.",
    "wof:placetype":"venue"
},
  "geometry": {"coordinates":[-2.9400260448,43.2639732361],"type":"Point"}
}