{
  "type": "Feature",
  "properties": {
    "addr:full":"Calle de Cardenal Cisneros, 4 Santander Cantabria 39007",
    "addr:housenumber":"4",
    "addr:postcode":"39007",
    "addr:street":"Calle De Cardenal Cisneros",
    "iso:country":"ES",
    "sg:address":"Calle de Cardenal Cisneros, 4",
    "sg:city":"Santander",
    "sg:orig_category":"Cine: Pel\u00cdculas Educativas, Industriales Y Publicitarias (producci\u00d3n)",
    "sg:phone":"+34 942 21 17 08",
    "sg:postcode":"39007",
    "sg:province":"Cantabria",
    "wof:name":"Pinar Fernandez Jose 000436803k Slne",
    "wof:placetype":"venue"
},
  "geometry": {"coordinates":[-3.8234865665,43.4620361328],"type":"Point"}
}