{
  "type": "Feature",
  "properties": {
    "addr:full":"Avda Guadalquivir (del), 5 Cazorla Ja\u00e9n 23470",
    "addr:housenumber":"5",
    "addr:postcode":"23470",
    "addr:street":"Avda Guadalquivir Del",
    "iso:country":"ES",
    "sg:address":"Avda Guadalquivir (del), 5",
    "sg:city":"Cazorla",
    "sg:orig_category":"Venta, Montaje De Neum\u00c1ticos",
    "sg:phone":"+34 953 71 01 22",
    "sg:postcode":"23470",
    "sg:province":"Ja\u00e9n",
    "wof:name":"Garcia Pe\u00f1a Francisco",
    "wof:placetype":"venue"
},
  "geometry": {"coordinates":[-2.9951012135,37.9200897217],"type":"Point"}
}