{
  "type": "Feature",
  "properties": {
    "iso:country":"ES",
    "sg:address":"Trav De Gracia, 15",
    "sg:city":"Barcelona",
    "sg:orig_category":"Organismos De Reclutamiento",
    "sg:phone":"+34 934 59 30 67",
    "sg:postcode":"08021",
    "sg:province":"Barcelona",
    "wof:name":"Suri\u00f1a Assesors En Formacio Sl",
    "wof:placetype":"venue"
},
  "geometry": {"coordinates":[2.1462740898,41.3942298889],"type":"Point"}
}