{
  "type": "Feature",
  "properties": {
    "iso:country":"ES",
    "sg:address":"Calle de Fontanares, 24",
    "sg:city":"Valencia",
    "sg:orig_category":"Farmacias",
    "sg:phone":"+34 963 77 29 71",
    "sg:postcode":"46007",
    "sg:province":"Valencia",
    "wof:name":"Folgado Bisbal Juan Miguel",
    "wof:placetype":"venue"
},
  "geometry": {"coordinates":[-0.3924992979,39.4582176208],"type":"Point"}
}