{
  "type": "Feature",
  "properties": {
    "iso:country":"ES",
    "sg:address":"Rua Cervantes, 41",
    "sg:city":"Foz",
    "sg:orig_category":"Asilos De Ancianos. Centros Privados",
    "sg:phone":"+34 982 14 00 22",
    "sg:postcode":"27780",
    "sg:province":"Lugo",
    "wof:name":"Edad Dorada",
    "wof:placetype":"venue"
},
  "geometry": {"coordinates":[-7.2613739967,43.5743751526],"type":"Point"}
}