{
  "type": "Feature",
  "properties": {
    "iso:country":"ES",
    "sg:address":"Calle de Paris, 2",
    "sg:city":"Toledo",
    "sg:orig_category":"Cajas De Ahorro",
    "sg:phone":"+34 925 28 33 26",
    "sg:postcode":"45005",
    "sg:province":"Toledo",
    "wof:name":"Caja De Ahorros De Castilla La Mancha",
    "wof:placetype":"venue"
},
  "geometry": {"coordinates":[-4.0265231133,39.8737220764],"type":"Point"}
}