{
  "type": "Feature",
  "properties": {
    "iso:country":"ES",
    "sg:address":"Rua Angustia (da), 17",
    "sg:city":"Santiago De Compostela",
    "sg:orig_category":"Electrodom\u00c9sticos (al Por Menor)",
    "sg:phone":"+34 981 56 32 98",
    "sg:postcode":"15703",
    "sg:province":"La Coru\u00f1a",
    "wof:name":"Electrodomesticos Garcia Compostela S.l.",
    "wof:placetype":"venue"
},
  "geometry": {"coordinates":[-8.5354270935,42.882396698],"type":"Point"}
}