{
  "type": "Feature",
  "properties": {
    "addr:full":"A Ramallosa, S/n Luci A Coru\u00f1a 15883",
    "addr:housenumber":"/ n",
    "addr:postcode":"15883",
    "addr:street":"Ramallosa S;Luci A Corun\u0303A",
    "iso:country":"ES",
    "sg:address":"A Ramallosa, S/n",
    "sg:city":"Luci",
    "sg:orig_category":"Caf\u00c9s, Bares, Cervecer\u00cdas",
    "sg:phone":"+34 981 80 97 38",
    "sg:postcode":"15883",
    "sg:province":"A Coru\u00f1a",
    "wof:name":"Sieira Lai\u00f1o Lucia",
    "wof:placetype":"venue"
},
  "geometry": {"coordinates":[-8.5444011688,42.8382263184],"type":"Point"}
}