{
  "type": "Feature",
  "properties": {
    "addr:full":"Calle de Hierro (el), 4 Flores Del Sil Le\u00f3n 24400",
    "addr:housenumber":"4",
    "addr:postcode":"24400",
    "addr:street":"Calle De Hierro El",
    "iso:country":"ES",
    "sg:address":"Calle de Hierro (el), 4",
    "sg:city":"Flores Del Sil",
    "sg:orig_category":"Bisuter\u00cda, Joyer\u00cda, Relojer\u00cda (al Por Menor)",
    "sg:phone":"+34 987 40 46 04",
    "sg:postcode":"24400",
    "sg:province":"Le\u00f3n",
    "wof:name":"Merayo Ja\u00f1ez Jose Manuel",
    "wof:placetype":"venue"
},
  "geometry": {"coordinates":[-6.5983390808,42.5483360291],"type":"Point"}
}