{
  "type": "Feature",
  "properties": {
    "addr:full":"Cust Morana La, 9 Zamora Zamora 49025",
    "addr:postcode":"49025",
    "iso:country":"ES",
    "sg:address":"Cust Morana La, 9",
    "sg:city":"Zamora",
    "sg:orig_category":"Veh\u00cdculos De Ocasi\u00d3n",
    "sg:phone":"+34 980 51 00 06",
    "sg:postcode":"49025",
    "sg:province":"Zamora",
    "wof:name":"Movilla Gangoso Eufrasio",
    "wof:placetype":"venue"
},
  "geometry": {"coordinates":[-5.7457342148,41.5033302307],"type":"Point"}
}