{
  "type": "Feature",
  "properties": {
    "addr:full":"Avda Libertad De La, 9 Donostia-san Sebastian Guip\u00f9zcoa 20004",
    "addr:housenumber":"9",
    "addr:postcode":"20004",
    "addr:street":"Avda Libertad De La",
    "iso:country":"ES",
    "sg:address":"Avda Libertad De La, 9",
    "sg:city":"Donostia-san Sebastian",
    "sg:orig_category":"M\u00c9dicos: Cirug\u00cda General",
    "sg:phone":"+34 943 42 15 79",
    "sg:postcode":"20004",
    "sg:province":"Guip\u00f9zcoa",
    "wof:name":"Betran Visus Andres",
    "wof:placetype":"venue"
},
  "geometry": {"coordinates":[-1.9804439545,43.3200111389],"type":"Point"}
}