{
  "type": "Feature",
  "properties": {
    "iso:country":"ES",
    "sg:address":"Av Meridiana, 354",
    "sg:city":"Barcelona",
    "sg:orig_category":"Trabajos De Fotocomposici\u00d3n",
    "sg:phone":"+34 933 12 08 07",
    "sg:postcode":"08027",
    "sg:province":"Barcelona",
    "wof:name":"Fotocomposicion Marques S.l.",
    "wof:placetype":"venue"
},
  "geometry": {"coordinates":[2.1855049133,41.4271316528],"type":"Point"}
}