{
  "type": "Feature",
  "properties": {
    "iso:country":"ES",
    "sg:address":"Calle de Camilo Jose Cela, S/n",
    "sg:city":"Brihuega",
    "sg:orig_category":"Reposter\u00cdas",
    "sg:phone":"+34 949 28 02 24",
    "sg:postcode":"19400",
    "sg:province":"Guadalajara",
    "wof:name":"Aguilera Corral Alfonso Carlos",
    "wof:placetype":"venue"
},
  "geometry": {"coordinates":[-2.8776638508,40.7409095764],"type":"Point"}
}