{
  "type": "Feature",
  "properties": {
    "iso:country":"ES",
    "sg:address":"Plaz Constitucion, 1",
    "sg:city":"Espeluy",
    "sg:orig_category":"Administraciones Regionales, Departamentales Y Locales",
    "sg:phone":"+34 953 53 71 61",
    "sg:postcode":"23628",
    "sg:province":"Ja\u00e9n",
    "wof:name":"Ayuntamiento De Espeluy",
    "wof:placetype":"venue"
},
  "geometry": {"coordinates":[-3.8618021011,38.0330810547],"type":"Point"}
}