{
  "type": "Feature",
  "properties": {
    "addr:full":"Presa Del Rumblar, S/n Bailen Ja\u00e9n 23710",
    "addr:housenumber":"s",
    "addr:postcode":"23710",
    "addr:street":"/ N;Jae\u0301N",
    "iso:country":"ES",
    "sg:address":"Presa Del Rumblar, S/n",
    "sg:city":"Bailen",
    "sg:orig_category":"Asociaciones Ecologistas",
    "sg:phone":"+34 953 67 65 14",
    "sg:postcode":"23710",
    "sg:province":"Ja\u00e9n",
    "wof:name":"Comunidad De Regantes Del Pantano Del Rumblar",
    "wof:placetype":"venue"
},
  "geometry": {"coordinates":[-3.7710540295,38.0965309143],"type":"Point"}
}