{
  "type": "Feature",
  "properties": {
    "addr:full":"Calle de Salvador La Casta, S/n Alzira Valencia 46600",
    "addr:housenumber":"s",
    "addr:postcode":"46600",
    "addr:street":"Calle De Salvador La Casta;/ N;Valencia",
    "iso:country":"ES",
    "sg:address":"Calle de Salvador La Casta, S/n",
    "sg:city":"Alzira",
    "sg:orig_category":"Servicio De Salud",
    "sg:phone":"+34 962 41 76 35",
    "sg:postcode":"46600",
    "sg:province":"Valencia",
    "wof:name":"Huguet Terol Y Ribes S. L.",
    "wof:placetype":"venue"
},
  "geometry": {"coordinates":[-0.4407019913,39.1440353394],"type":"Point"}
}