{
  "type": "Feature",
  "properties": {
    "iso:country":"ES",
    "sg:address":"Calle de Ramiro Valbuena, 4",
    "sg:city":"Le\u00f3n",
    "sg:orig_category":"Abogados",
    "sg:phone":"+34 987 22 31 92",
    "sg:postcode":"24002",
    "sg:province":"Le\u00f3n",
    "wof:name":"Guisasola Mu\u00f1iz Alvaro",
    "wof:placetype":"venue"
},
  "geometry": {"coordinates":[-5.5750222206,42.6008605957],"type":"Point"}
}