{
  "type": "Feature",
  "properties": {
    "addr:full":"Calle de Olvido, 60 Madrid Madrid 28026",
    "addr:housenumber":"60",
    "addr:postcode":"madrid;28026",
    "addr:street":"Calle De Olvido",
    "iso:country":"ES",
    "sg:address":"Calle de Olvido, 60",
    "sg:city":"Madrid",
    "sg:orig_category":"Estudios, Instalaci\u00d3n De Climatizaci\u00d3n",
    "sg:phone":"+34 914 44 61 48",
    "sg:postcode":"28026",
    "sg:province":"Madrid",
    "wof:name":"Ateclima S.l.",
    "wof:placetype":"venue"
},
  "geometry": {"coordinates":[-3.7025487423,40.3846969604],"type":"Point"}
}