{
  "type": "Feature",
  "properties": {
    "iso:country":"ES",
    "sg:address":"Pase Doctor Torres Villarroel, 56",
    "sg:city":"Salamanca",
    "sg:orig_category":"Iglesia Cat\u00d3lica",
    "sg:phone":"+34 923 12 09 09",
    "sg:postcode":"37005",
    "sg:province":"Salamanca",
    "wof:name":"Obispado De Salamanca",
    "wof:placetype":"venue"
},
  "geometry": {"coordinates":[-5.6628789902,40.9743499756],"type":"Point"}
}