{
  "type": "Feature",
  "properties": {
    "iso:country":"ES",
    "sg:address":"Virgen De Los Desamparados, 14",
    "sg:city":"Oliva",
    "sg:orig_category":"Confecci\u00d3n (fabricaci\u00d3n, Al Por Mayor)",
    "sg:phone":"+34 962 83 90 25",
    "sg:postcode":"46780",
    "sg:province":"Valencia",
    "wof:name":"Moncho Sanchis Jose Enrique",
    "wof:placetype":"venue"
},
  "geometry": {"coordinates":[-0.1249869987,38.9209365845],"type":"Point"}
}