{
  "type": "Feature",
  "properties": {
    "iso:country":"ES",
    "sg:address":"Carrer de Transversal, 239",
    "sg:city":"Terrassa",
    "sg:orig_category":"M\u00c1quinas De Coser Y De Hacer Punto (al Por Mayor)",
    "sg:phone":"+34 937 35 85 42",
    "sg:postcode":"08225",
    "sg:province":"Barcelona",
    "wof:name":"Pons Pladellorens Mireia",
    "wof:placetype":"venue"
},
  "geometry": {"coordinates":[2.0117220879,41.5729446411],"type":"Point"}
}