{
  "type": "Feature",
  "properties": {
    "addr:full":"Calle de Castelar, 7 Santander Cantabria 39004",
    "addr:housenumber":"7",
    "addr:postcode":"39004",
    "addr:street":"Calle De Castelar",
    "iso:country":"ES",
    "sg:address":"Calle de Castelar, 7",
    "sg:city":"Santander",
    "sg:orig_category":"M\u00c9dicos: Pediatr\u00cda. Enfermedades De Los Ni\u00d1os",
    "sg:phone":"+34 942 22 15 55",
    "sg:postcode":"39004",
    "sg:province":"Cantabria",
    "wof:name":"Lastra Olano Juan Jose De La",
    "wof:placetype":"venue"
},
  "geometry": {"coordinates":[-3.7950172424,43.4629020691],"type":"Point"}
}