{
  "type": "Feature",
  "properties": {
    "addr:full":"Calle de Puente Colgante, 2 Valladolid Valladolid 47007",
    "addr:housenumber":"2",
    "addr:postcode":"47007",
    "addr:street":"Calle De Puente Colgante",
    "iso:country":"ES",
    "sg:address":"Calle de Puente Colgante, 2",
    "sg:city":"Valladolid",
    "sg:orig_category":"Carnicer\u00cdas, Carnicer\u00cdas",
    "sg:phone":"+34 983 23 25 30",
    "sg:postcode":"47007",
    "sg:province":"Valladolid",
    "wof:name":"Ballesteros Barba Elier",
    "wof:placetype":"venue"
},
  "geometry": {"coordinates":[-4.7316918373,41.641254425],"type":"Point"}
}