{
  "type": "Feature",
  "properties": {
    "addr:full":"Avda Gregorio Ruiz, 4 Talavera Reina Toledo 45600",
    "addr:housenumber":"4",
    "addr:postcode":"45600",
    "addr:street":"Avda Gregorio Ruiz",
    "iso:country":"ES",
    "sg:address":"Avda Gregorio Ruiz, 4",
    "sg:city":"Talavera Reina",
    "sg:orig_category":"Arquitectos",
    "sg:phone":"+34 925 81 30 47",
    "sg:postcode":"45600",
    "sg:province":"Toledo",
    "wof:name":"Ortega Alcaraz Ernesto",
    "wof:placetype":"venue"
},
  "geometry": {"coordinates":[-4.8272309303,39.9614868164],"type":"Point"}
}