{
  "type": "Feature",
  "properties": {
    "iso:country":"ES",
    "sg:address":"Calle de Santa Amalia, S/n",
    "sg:city":"Don Benito",
    "sg:orig_category":"Conservas De Legumbres (fabricaci\u00d3n, Al Por Mayor)",
    "sg:phone":"+34 924 14 72 53",
    "sg:postcode":"06400",
    "sg:province":"Badajoz",
    "wof:name":"Sat Gourmet",
    "wof:placetype":"venue"
},
  "geometry": {"coordinates":[-5.8650240898,38.9595947266],"type":"Point"}
}