{
  "type": "Feature",
  "properties": {
    "iso:country":"ES",
    "sg:address":"Calle de Llama (la), 16",
    "sg:city":"Torrelavega",
    "sg:orig_category":"Mec\u00c1nico Del Autom\u00d3vil",
    "sg:phone":"+34 942 88 11 42",
    "sg:postcode":"39300",
    "sg:province":"Cantabria",
    "wof:name":"Tallcom S.cv.",
    "wof:placetype":"venue"
},
  "geometry": {"coordinates":[-4.0447010994,43.3486747742],"type":"Point"}
}