{
  "type": "Feature",
  "properties": {
    "addr:full":"Avda Constitucion, 3 Torrejon Ardoz Madrid 28850",
    "addr:housenumber":"3",
    "addr:postcode":"28850",
    "addr:street":"Avda Constitucion",
    "iso:country":"ES",
    "sg:address":"Avda Constitucion, 3",
    "sg:city":"Torrejon Ardoz",
    "sg:orig_category":"Perfumer\u00cda Y Cosm\u00c9tica (fabricaci\u00d3n, Al Por Mayor)",
    "sg:phone":"+34 916 56 76 95",
    "sg:postcode":"28850",
    "sg:province":"Madrid",
    "wof:name":"Cosmenatura S.a.",
    "wof:placetype":"venue"
},
  "geometry": {"coordinates":[-3.4877450466,40.4550933838],"type":"Point"}
}