{
  "type": "Feature",
  "properties": {
    "iso:country":"ES",
    "sg:address":"Cacharoza, S/n",
    "sg:city":"Cacharosa",
    "sg:orig_category":"Electricidad (montaje, Ensamblaje De Componentes)",
    "sg:phone":"+34 981 71 83 01",
    "sg:postcode":"15150",
    "sg:province":"La Coru\u00f1a",
    "wof:name":"Espasandin Ferreiro Manuel",
    "wof:placetype":"venue"
},
  "geometry": {"coordinates":[-8.9681482315,43.147567749],"type":"Point"}
}