{
  "type": "Feature",
  "properties": {
    "iso:country":"ES",
    "sg:address":"Avda Francisco Lopez Real, S/n",
    "sg:city":"Nerva",
    "sg:orig_category":"Sanatorios M\u00c9dico",
    "sg:phone":"+34 959 58 03 33",
    "sg:postcode":"21670",
    "sg:province":"Huelva",
    "wof:name":"Servicio Andaluz De Salud",
    "wof:placetype":"venue"
},
  "geometry": {"coordinates":[-6.5401940346,37.6921310425],"type":"Point"}
}