{
  "type": "Feature",
  "properties": {
    "addr:full":"Calle de Goienkalea, 12 Gernika-lumo Vizcaya 48300",
    "addr:housenumber":"12",
    "addr:postcode":"48300",
    "addr:street":"Calle De Goienkalea",
    "iso:country":"ES",
    "sg:address":"Calle de Goienkalea, 12",
    "sg:city":"Gernika-lumo",
    "sg:orig_category":"Asociaciones Y Clubs Deportivos",
    "sg:phone":"+34 946 25 04 12",
    "sg:postcode":"48300",
    "sg:province":"Vizcaya",
    "wof:name":"Roberto Baraiazarra Ocerin",
    "wof:placetype":"venue"
},
  "geometry": {"coordinates":[-2.6791601181,43.314540863],"type":"Point"}
}