{
  "type": "Feature",
  "properties": {
    "addr:full":"Avda Constitucion (de La), 47 Fuente De Pedro Naharro Cuenca 16411",
    "addr:housenumber":"47",
    "addr:postcode":"16411",
    "addr:street":"Avda Constitucion De La",
    "iso:country":"ES",
    "sg:address":"Avda Constitucion (de La), 47",
    "sg:city":"Fuente De Pedro Naharro",
    "sg:orig_category":"Alimentaci\u00d3n General (al Por Menor)",
    "sg:phone":"+34 969 12 50 55",
    "sg:postcode":"16411",
    "sg:province":"Cuenca",
    "wof:name":"Morales Sanchez Emiliano",
    "wof:placetype":"venue"
},
  "geometry": {"coordinates":[-3.008343935,39.9259567261],"type":"Point"}
}