{
  "type": "Feature",
  "properties": {
    "addr:full":"Av Llibertat, 3 Mollet Valles Barcelona 08100",
    "addr:housenumber":"3",
    "addr:postcode":"08100",
    "addr:street":"Av Llibertat",
    "iso:country":"ES",
    "sg:address":"Av Llibertat, 3",
    "sg:city":"Mollet Valles",
    "sg:orig_category":"Molduras, Junquillos, Listones Y Molduras Perforadas",
    "sg:phone":"+34 935 70 68 15",
    "sg:postcode":"08100",
    "sg:province":"Barcelona",
    "wof:name":"Gutierrez Fuentes Alsira",
    "wof:placetype":"venue"
},
  "geometry": {"coordinates":[2.2127490044,41.5372123718],"type":"Point"}
}