{
  "type": "Feature",
  "properties": {
    "addr:full":"Plaz Los Fueros, 1 Balmaseda Vizcaya 48800",
    "addr:housenumber":"1",
    "addr:postcode":"48800",
    "addr:street":"Los Fueros",
    "iso:country":"ES",
    "sg:address":"Plaz Los Fueros, 1",
    "sg:city":"Balmaseda",
    "sg:orig_category":"Estancos",
    "sg:phone":"+34 946 80 06 62",
    "sg:postcode":"48800",
    "sg:province":"Vizcaya",
    "wof:name":"Ibarretxe Larrea Gartzen",
    "wof:placetype":"venue"
},
  "geometry": {"coordinates":[-3.196199894,43.1932907104],"type":"Point"}
}