{
  "type": "Feature",
  "properties": {
    "addr:full":"Calle de Recogidas, 62 Granada Granada 18002",
    "addr:housenumber":"62",
    "addr:postcode":"18002",
    "addr:street":"Calle De Recogidas",
    "iso:country":"ES",
    "sg:address":"Calle de Recogidas, 62",
    "sg:city":"Granada",
    "sg:orig_category":"Abogados",
    "sg:phone":"+34 958 25 25 47",
    "sg:postcode":"18002",
    "sg:province":"Granada",
    "wof:name":"Rull Serrano Emilio",
    "wof:placetype":"venue"
},
  "geometry": {"coordinates":[-3.6058490276,37.1701583862],"type":"Point"}
}