{
  "type": "Feature",
  "properties": {
    "iso:country":"ES",
    "sg:address":"Calle de Lopez De Hoyos, 5",
    "sg:city":"Madrid",
    "sg:orig_category":"Compraventa De Antig\u00dcedades",
    "sg:phone":"+34 915 62 30 70",
    "sg:postcode":"28006",
    "sg:province":"Madrid",
    "wof:name":"Iglesias Cubria Julio",
    "wof:placetype":"venue"
},
  "geometry": {"coordinates":[-3.6875920296,40.4370040894],"type":"Point"}
}