{
  "type": "Feature",
  "properties": {
    "addr:full":"Carr Jaume I, 35 Girona Girona 17001",
    "addr:housenumber":"35",
    "addr:postcode":"17001",
    "addr:street":"Carr Jaume I",
    "iso:country":"ES",
    "sg:address":"Carr Jaume I, 35",
    "sg:city":"Girona",
    "sg:orig_category":"Papeler\u00cdas, Librer\u00cdas",
    "sg:phone":"+34 972 20 16 02",
    "sg:postcode":"17001",
    "sg:province":"Girona",
    "wof:name":"Callico Culubret Maria Angeles",
    "wof:placetype":"venue"
},
  "geometry": {"coordinates":[2.8187448978,41.9808616638],"type":"Point"}
}