{
  "type": "Feature",
  "properties": {
    "iso:country":"ES",
    "sg:address":"Calle de Gremios Del Cuero (los), S/n",
    "sg:city":"Hontoria",
    "sg:orig_category":"Tintorer\u00cdas, Limpieza En Seco",
    "sg:phone":"+34 921 42 57 17",
    "sg:postcode":"40195",
    "sg:province":"Segovia",
    "wof:name":"Laguna Garcia Francisco Javier",
    "wof:placetype":"venue"
},
  "geometry": {"coordinates":[-4.1221280098,40.9089508057],"type":"Point"}
}