{
  "type": "Feature",
  "properties": {
    "addr:full":"Calle de Ramon Y Cajal, 35 Gijon Asturias 33204",
    "addr:housenumber":"35",
    "addr:postcode":"33204",
    "addr:street":"Calle De Ramon Y Cajal",
    "iso:country":"ES",
    "sg:address":"Calle de Ramon Y Cajal, 35",
    "sg:city":"Gijon",
    "sg:orig_category":"Carnicer\u00cdas, Carnicer\u00cdas",
    "sg:phone":"+34 985 36 91 33",
    "sg:postcode":"33204",
    "sg:province":"Asturias",
    "wof:name":"Alonso Suarez Jose Antonio",
    "wof:placetype":"venue"
},
  "geometry": {"coordinates":[-5.6538596153,43.5332679749],"type":"Point"}
}