{
  "type": "Feature",
  "properties": {
    "iso:country":"ES",
    "sg:address":"Co. Viejo De Vicolozano, S/n",
    "sg:city":"Vicolozano",
    "sg:orig_category":"Panader\u00cdas, Panader\u00cdas",
    "sg:phone":"+34 920 22 28 70",
    "sg:postcode":"05194",
    "sg:province":"\u00c1vila",
    "wof:name":"San Roque Fabrica De Pan Y Bolleria S.l.",
    "wof:placetype":"venue"
},
  "geometry": {"coordinates":[-4.5642142296,40.700920105],"type":"Point"}
}