{
  "type": "Feature",
  "properties": {
    "iso:country":"ES",
    "sg:address":"Calle de Gonzalez De Aguilar, 4",
    "sg:city":"Ayamonte",
    "sg:orig_category":"Caf\u00c9s, Bares, Cervecer\u00cdas",
    "sg:phone":"+34 959 47 07 46",
    "sg:postcode":"21400",
    "sg:province":"Huelva",
    "wof:name":"Perez Lorenzo Juan",
    "wof:placetype":"venue"
},
  "geometry": {"coordinates":[-7.4084692001,37.2134933472],"type":"Point"}
}