{
  "type": "Feature",
  "properties": {
    "iso:country":"ES",
    "sg:address":"Calle de Virgen De Lujan, 39",
    "sg:city":"Sevilla",
    "sg:orig_category":"Importaci\u00d3n",
    "sg:phone":"+34 954 45 11 95",
    "sg:postcode":"41011",
    "sg:province":"Sevilla",
    "wof:name":"Centro Financiero Comercial Y De Servicios S. A.",
    "wof:placetype":"venue"
},
  "geometry": {"coordinates":[-6.001185894,37.3744926453],"type":"Point"}
}