{
  "type": "Feature",
  "properties": {
    "addr:full":"El Espada\u00f1al, 1 Huerga Garavalles Le\u00f3n 24768",
    "addr:housenumber":"1",
    "addr:postcode":"24768",
    "addr:street":"Huerga Garavalles Leo\u0301N",
    "iso:country":"ES",
    "sg:address":"El Espada\u00f1al, 1",
    "sg:city":"Huerga Garavalles",
    "sg:orig_category":"Transportes Por V\u00cdas Navegables",
    "sg:phone":"+34 987 65 53 60",
    "sg:postcode":"24768",
    "sg:province":"Le\u00f3n",
    "wof:name":"Gonzalez Franco Angel",
    "wof:placetype":"venue"
},
  "geometry": {"coordinates":[-5.5717520714,42.5998764038],"type":"Point"}
}