{
  "type": "Feature",
  "properties": {
    "addr:full":"Calle de Buendia, 2 Alcala Henares Madrid 28803",
    "addr:housenumber":"2",
    "addr:postcode":"28803",
    "addr:street":"Calle De Buendia",
    "iso:country":"ES",
    "sg:address":"Calle de Buendia, 2",
    "sg:city":"Alcala Henares",
    "sg:orig_category":"Asesor\u00cda Sobre Comunicaci\u00d3n De Empresas",
    "sg:phone":"+34 918 83 44 91",
    "sg:postcode":"28803",
    "sg:province":"Madrid",
    "wof:name":"Maestre Lopez Francisca",
    "wof:placetype":"venue"
},
  "geometry": {"coordinates":[-3.3657531738,40.4716758728],"type":"Point"}
}