{
  "type": "Feature",
  "properties": {
    "iso:country":"ES",
    "sg:address":"Avda Andalucia, S/n",
    "sg:city":"Peal Becerro",
    "sg:orig_category":"Cooperativas Agr\u00cdcolas",
    "sg:phone":"+34 953 73 07 08",
    "sg:postcode":"23460",
    "sg:province":"Ja\u00e9n",
    "wof:name":"Union De Peque\u00f1os Agricultores De Jaen",
    "wof:placetype":"venue"
},
  "geometry": {"coordinates":[-3.1102941036,37.9139595032],"type":"Point"}
}