{
  "type": "Feature",
  "properties": {
    "addr:full":"Calle de Cantarranas, 15 Cantimpalos Segovia 40360",
    "addr:housenumber":"15",
    "addr:postcode":"40360",
    "addr:street":"Calle De Cantarranas;Segovia",
    "iso:country":"ES",
    "sg:address":"Calle de Cantarranas, 15",
    "sg:city":"Cantimpalos",
    "sg:orig_category":"Electricidad: Instaladores",
    "sg:phone":"+34 921 49 63 36",
    "sg:postcode":"40360",
    "sg:province":"Segovia",
    "wof:name":"Arribas Ceballos Josefa",
    "wof:placetype":"venue"
},
  "geometry": {"coordinates":[-4.1577262878,41.0755157471],"type":"Point"}
}