{
  "type": "Feature",
  "properties": {
    "addr:full":"Plaz Constitucion, S/n Santiz Salamanca 37110",
    "addr:housenumber":"/ n",
    "addr:postcode":"37110",
    "addr:street":"Constitucion S",
    "iso:country":"ES",
    "sg:address":"Plaz Constitucion, S/n",
    "sg:city":"Santiz",
    "sg:orig_category":"Centros De Educaci\u00d3n Especial",
    "sg:phone":"+34 923 32 08 08",
    "sg:postcode":"37110",
    "sg:province":"Salamanca",
    "wof:name":"Ayuntamiento",
    "wof:placetype":"venue"
},
  "geometry": {"coordinates":[-5.8944535255,41.205997467],"type":"Point"}
}