{
  "type": "Feature",
  "properties": {
    "addr:full":"Urb Guadalpark, 15 Marbella M\u00e1laga 29600",
    "addr:housenumber":"15",
    "addr:postcode":"29600",
    "addr:street":"Urb Guadalpark;Ma\u0301Laga",
    "iso:country":"ES",
    "sg:address":"Urb Guadalpark, 15",
    "sg:city":"Marbella",
    "sg:orig_category":"Importaci\u00d3n",
    "sg:phone":"+34 952 82 80 10",
    "sg:postcode":"29600",
    "sg:province":"M\u00e1laga",
    "wof:name":"Solum Import S.l.",
    "wof:placetype":"venue"
},
  "geometry": {"coordinates":[-4.8833007812,36.5079956055],"type":"Point"}
}