{
  "type": "Feature",
  "properties": {
    "addr:full":"Carrer de Numero 43 De La Zona Franca, S/n Barcelona Barcelona 08040",
    "addr:postcode":"08040",
    "addr:street":"Carrer De Numero 43 De La;Franca S / N",
    "iso:country":"ES",
    "sg:address":"Carrer de Numero 43 De La Zona Franca, S/n",
    "sg:city":"Barcelona",
    "sg:orig_category":"Transportes Mar\u00cdtimos",
    "sg:phone":"+34 932 64 93 93",
    "sg:postcode":"08040",
    "sg:province":"Barcelona",
    "sg:website":"www.tasmar.es",
    "wof:name":"Tasmar Logistica S.a.",
    "wof:placetype":"venue"
},
  "geometry": {"coordinates":[2.1029939651,41.3365631104],"type":"Point"}
}