{
  "type": "Feature",
  "properties": {
    "iso:country":"ES",
    "sg:address":"Calle de Huerta Del Marques, 1",
    "sg:city":"Arevalo",
    "sg:orig_category":"Inform\u00c1tica, Ofim\u00c1tica (estudios, Asesor\u00cda, Ingenier\u00cda, Formaci\u00d3n)",
    "sg:phone":"+34 920 30 36 94",
    "sg:postcode":"05200",
    "sg:province":"\u00c1vila",
    "wof:name":"Digital 2000 Cb",
    "wof:placetype":"venue"
},
  "geometry": {"coordinates":[-4.7219891548,41.0565795898],"type":"Point"}
}