{
  "type": "Feature",
  "properties": {
    "iso:country":"ES",
    "sg:address":"Plaz Espa\u00d1a, 11",
    "sg:city":"Valladolid",
    "sg:orig_category":"Zapatos (al Por Menor)",
    "sg:phone":"+34 983 30 86 72",
    "sg:postcode":"47001",
    "sg:province":"Valladolid",
    "wof:name":"Escudero Oviedo Esperanza",
    "wof:placetype":"venue"
},
  "geometry": {"coordinates":[-4.7245001793,41.648651123],"type":"Point"}
}