{
  "type": "Feature",
  "properties": {
    "addr:full":"Calle de Coso, 87 Zaragoza Zaragoza 50001",
    "addr:housenumber":"87",
    "addr:postcode":"50001",
    "addr:street":"Calle De Coso",
    "iso:country":"ES",
    "sg:address":"Calle de Coso, 87",
    "sg:city":"Zaragoza",
    "sg:orig_category":"Partidos Pol\u00cdticos",
    "sg:phone":"+34 976 20 06 16",
    "sg:postcode":"50001",
    "sg:province":"Zaragoza",
    "wof:name":"Partido Aragones",
    "wof:placetype":"venue"
},
  "geometry": {"coordinates":[-0.8775395751,41.6511459351],"type":"Point"}
}