{
  "type": "Feature",
  "properties": {
    "iso:country":"ES",
    "sg:address":"Avda Puente De Carlos Iii, 44",
    "sg:city":"Reinosa",
    "sg:orig_category":"\u00d3ptica: Instrumentos (fabricaci\u00d3n)",
    "sg:phone":"+34 942 75 49 90",
    "sg:postcode":"39200",
    "sg:province":"Cantabria",
    "wof:name":"Rodriguez Suarez Emilio",
    "wof:placetype":"venue"
},
  "geometry": {"coordinates":[-4.1397218704,42.9973220825],"type":"Point"}
}