{
  "type": "Feature",
  "properties": {
    "addr:full":"Av Sant Julia, 50 Granollers Barcelona 08403",
    "addr:housenumber":"50",
    "addr:postcode":"08403",
    "addr:street":"Av Sant Julia",
    "iso:country":"ES",
    "sg:address":"Av Sant Julia, 50",
    "sg:city":"Granollers",
    "sg:orig_category":"Cajas Y Embalajes De Pl\u00c1stico",
    "sg:phone":"+34 938 46 70 14",
    "sg:postcode":"08403",
    "sg:province":"Barcelona",
    "wof:name":"Valles Pack S.a.",
    "wof:placetype":"venue"
},
  "geometry": {"coordinates":[2.2748429775,41.595790863],"type":"Point"}
}