{
  "type": "Feature",
  "properties": {
    "addr:full":"Calle de Corredera, 2 San Mateo Murcia 30800",
    "addr:housenumber":"2",
    "addr:postcode":"30800",
    "addr:street":"Calle De Corredera",
    "iso:country":"ES",
    "sg:address":"Calle de Corredera, 2",
    "sg:city":"San Mateo",
    "sg:orig_category":"Cajas De Ahorro",
    "sg:phone":"+34 968 46 74 15",
    "sg:postcode":"30800",
    "sg:province":"Murcia",
    "wof:name":"Caixa D'estalvis De Catalunya",
    "wof:placetype":"venue"
},
  "geometry": {"coordinates":[-1.1298867464,37.9834747314],"type":"Point"}
}