{
  "type": "Feature",
  "properties": {
    "iso:country":"ES",
    "sg:address":"Ctra Madrid (de), S/n",
    "sg:city":"Manzanares",
    "sg:orig_category":"Gastronom\u00cda: Especialidades Regionales (al Por Menor)",
    "sg:phone":"+34 926 61 19 00",
    "sg:postcode":"13200",
    "sg:province":"Ciudad Real",
    "wof:name":"Seven S.a.",
    "wof:placetype":"venue"
},
  "geometry": {"coordinates":[-3.3627939224,38.9942054749],"type":"Point"}
}