{
  "type": "Feature",
  "properties": {
    "iso:country":"ES",
    "sg:address":"Calle de Vega (la), 11",
    "sg:city":"Hellin",
    "sg:orig_category":"Escotaduras, Torneados",
    "sg:phone":"+34 967 30 61 92",
    "sg:postcode":"02400",
    "sg:province":"Albacete",
    "wof:name":"Rios Martinez Jose Antonio",
    "wof:placetype":"venue"
},
  "geometry": {"coordinates":[-1.7095689774,38.5045318604],"type":"Point"}
}