{
  "type": "Feature",
  "properties": {
    "addr:full":"Calle de Arrospide Jon, 17 Bilbao Vizcaya 48014",
    "addr:housenumber":"17",
    "addr:postcode":"48014",
    "addr:street":"Calle De Arrospide Jon",
    "iso:country":"ES",
    "sg:address":"Calle de Arrospide Jon, 17",
    "sg:city":"Bilbao",
    "sg:orig_category":"Metalurgia",
    "sg:phone":"+34 944 75 35 39",
    "sg:postcode":"48014",
    "sg:province":"Vizcaya",
    "wof:name":"Industrias Echeiri S.l.",
    "wof:placetype":"venue"
},
  "geometry": {"coordinates":[-2.9533326626,43.2688369751],"type":"Point"}
}