{
  "type": "Feature",
  "properties": {
    "addr:full":"Carrer de Parellada (la), 21 Vilafranca Penedes Barcelona 08720",
    "addr:housenumber":"21",
    "addr:postcode":"08720",
    "addr:street":"Carrer De Parellada La;Penedes Barcelona",
    "iso:country":"ES",
    "sg:address":"Carrer de Parellada (la), 21",
    "sg:city":"Vilafranca Penedes",
    "sg:orig_category":"Confiter\u00cdas, Chocolater\u00cdas (al Por Menor)",
    "sg:phone":"+34 938 92 01 08",
    "sg:postcode":"08720",
    "sg:province":"Barcelona",
    "wof:name":"Colet Massana Gerard",
    "wof:placetype":"venue"
},
  "geometry": {"coordinates":[1.6993039846,41.3467140198],"type":"Point"}
}