{
  "type": "Feature",
  "properties": {
    "iso:country":"ES",
    "sg:address":"Avda Barcelona, 32",
    "sg:city":"Malaga",
    "sg:orig_category":"Trajes Y Adornos De Boda (confecci\u00d3n, Al Por Menor)",
    "sg:phone":"+34 952 39 66 43",
    "sg:postcode":"29009",
    "sg:province":"M\u00e1laga",
    "wof:name":"Flores De Liania Sl",
    "wof:placetype":"venue"
},
  "geometry": {"coordinates":[-4.4311790466,36.7248497009],"type":"Point"}
}