{
  "type": "Feature",
  "properties": {
    "addr:full":"Carrer de Major, 58 Cervello Barcelona 08758",
    "addr:housenumber":"58",
    "addr:postcode":"08758",
    "addr:street":"Carrer De Major;Barcelona",
    "iso:country":"ES",
    "sg:address":"Carrer de Major, 58",
    "sg:city":"Cervello",
    "sg:orig_category":"Sociedades, Compa\u00d1\u00cdas Aseguradoras",
    "sg:phone":"+34 936 84 13 57",
    "sg:postcode":"08758",
    "sg:province":"Barcelona",
    "wof:name":"Mapfre Servicios De Informatica",
    "wof:placetype":"venue"
},
  "geometry": {"coordinates":[1.9553040266,41.3958587646],"type":"Point"}
}