{
  "type": "Feature",
  "properties": {
    "addr:full":"El Hoyo, 1 Teror Las Palmas 35330",
    "addr:housenumber":"1",
    "addr:postcode":"35330",
    "addr:street":"El Hoyo",
    "iso:country":"ES",
    "sg:address":"El Hoyo, 1",
    "sg:city":"Teror",
    "sg:orig_category":"Distribuci\u00d3n De Petr\u00d3leo Y Derivados",
    "sg:phone":"+34 928 61 35 45",
    "sg:postcode":"35330",
    "sg:province":"Las Palmas",
    "wof:name":"Sanchez Sanchez Juan",
    "wof:placetype":"venue"
},
  "geometry": {"coordinates":[-15.5451288223,28.0638542175],"type":"Point"}
}