{
  "type": "Feature",
  "properties": {
    "iso:country":"ES",
    "sg:address":"Ctra. Santiago, S/n",
    "sg:city":"Negreira",
    "sg:orig_category":"Distribuci\u00d3n De Petr\u00d3leo Y Derivados",
    "sg:phone":"+34 981 88 50 82",
    "sg:postcode":"15830",
    "sg:province":"A Coru\u00f1a",
    "wof:name":"Sune S. A.",
    "wof:placetype":"venue"
},
  "geometry": {"coordinates":[-8.7368841171,42.9089660645],"type":"Point"}
}