{
  "type": "Feature",
  "properties": {
    "addr:full":"Calle de Berlin, 11 Arenal Islas Baleares 07600",
    "addr:housenumber":"11",
    "addr:postcode":"07600",
    "addr:street":"Calle De Berlin",
    "iso:country":"ES",
    "sg:address":"Calle de Berlin, 11",
    "sg:city":"Arenal",
    "sg:orig_category":"\u00d3ptica: Instrumentos (fabricaci\u00d3n)",
    "sg:phone":"+34 971 74 35 91",
    "sg:postcode":"07600",
    "sg:province":"Islas Baleares",
    "wof:name":"Amengual Aguilo Jose Juan",
    "wof:placetype":"venue"
},
  "geometry": {"coordinates":[2.7526257038,39.5052490234],"type":"Point"}
}