{
  "type": "Feature",
  "properties": {
    "iso:country":"ES",
    "sg:address":"Calle de Zaragoza, 3",
    "sg:city":"Getafe",
    "sg:orig_category":"Ropa Para Se\u00d1oras (al Por Menor)",
    "sg:phone":"+34 916 83 41 37",
    "sg:postcode":"28903",
    "sg:province":"Madrid",
    "wof:name":"Gremoba S.l.",
    "wof:placetype":"venue"
},
  "geometry": {"coordinates":[-3.7167840004,40.3115577698],"type":"Point"}
}