{
  "type": "Feature",
  "properties": {
    "addr:full":"Ctra Jabalquinto, Km. 0005,0 Linares Ja\u00e9n 23700",
    "addr:postcode":"23700",
    "addr:street":"Ctra Jabalquinto Km. 0005,0;Jae\u0301N",
    "iso:country":"ES",
    "sg:address":"Ctra Jabalquinto, Km. 0005,0",
    "sg:city":"Linares",
    "sg:orig_category":"Producci\u00d3n, Venta De Productos De Agricultura Biol\u00d3gica",
    "sg:phone":"+34 953 12 50 68",
    "sg:postcode":"23700",
    "sg:province":"Ja\u00e9n",
    "wof:name":"Cortijo Fuencaliente C.b.",
    "wof:placetype":"venue"
},
  "geometry": {"coordinates":[-3.6403288841,38.084903717],"type":"Point"}
}