{
  "type": "Feature",
  "properties": {
    "iso:country":"ES",
    "sg:address":"Pase Chopera (de La), 28",
    "sg:city":"Alcobendas",
    "sg:orig_category":"Farmacias",
    "sg:phone":"+34 916 61 14 25",
    "sg:postcode":"28100",
    "sg:province":"Madrid",
    "wof:name":"Rodero Torres Elena",
    "wof:placetype":"venue"
},
  "geometry": {"coordinates":[-3.6380419731,40.5385704041],"type":"Point"}
}