{
  "type": "Feature",
  "properties": {
    "iso:country":"ES",
    "sg:address":"Calle de Virgen De Lourdes, 1",
    "sg:city":"Pozoblanco",
    "sg:orig_category":"Flores Y Plantas Naturales (al Por Mayor)",
    "sg:phone":"+34 957 77 06 59",
    "sg:postcode":"14400",
    "sg:province":"C\u00f3rdoba",
    "wof:name":"Recio Pobo Pablo",
    "wof:placetype":"venue"
},
  "geometry": {"coordinates":[-4.8458089828,38.3772735596],"type":"Point"}
}