{
  "type": "Feature",
  "properties": {
    "addr:full":"Calle de Ab-el-hamet, 4 Alacant Alicante 03003",
    "addr:housenumber":"4",
    "addr:postcode":"03003",
    "addr:street":"Calle De Ab-El-Hamet",
    "iso:country":"ES",
    "sg:address":"Calle de Ab-el-hamet, 4",
    "sg:city":"Alacant",
    "sg:orig_category":"M\u00c9dicos: Neurocirug\u00cda",
    "sg:phone":"+34 965 12 02 57",
    "sg:postcode":"03003",
    "sg:province":"Alicante",
    "wof:name":"Moreno Lopez Pedro",
    "wof:placetype":"venue"
},
  "geometry": {"coordinates":[-0.4890637994,38.3400497437],"type":"Point"}
}