{
  "type": "Feature",
  "properties": {
    "addr:full":"Calle de Alfonso Iii, 3 Piedras Blancas Asturias 33450",
    "addr:housenumber":"3",
    "addr:postcode":"33450",
    "addr:street":"Calle De Alfonso Iii",
    "iso:country":"ES",
    "sg:address":"Calle de Alfonso Iii, 3",
    "sg:city":"Piedras Blancas",
    "sg:orig_category":"Centros De Coordinaci\u00d3n",
    "sg:phone":"+34 985 50 78 27",
    "sg:postcode":"33450",
    "sg:province":"Asturias",
    "wof:name":"Frank Asesores S.l.",
    "wof:placetype":"venue"
},
  "geometry": {"coordinates":[-5.9734067917,43.5603294373],"type":"Point"}
}