{
  "type": "Feature",
  "properties": {
    "addr:full":"Bo Pe\u00f1ascal Auzoa, S/n Bilbao Vizcaya 48002",
    "addr:housenumber":"s / n",
    "addr:postcode":"48002",
    "addr:street":"Pen\u0303Ascal Auzoa",
    "iso:country":"ES",
    "sg:address":"Bo Pe\u00f1ascal Auzoa, S/n",
    "sg:city":"Bilbao",
    "sg:orig_category":"Hormigonados",
    "sg:phone":"+34 944 43 23 49",
    "sg:postcode":"48002",
    "sg:province":"Vizcaya",
    "wof:name":"Hormigones Vascos S. A.",
    "wof:placetype":"venue"
},
  "geometry": {"coordinates":[-2.9434030056,43.2355995178],"type":"Point"}
}