{
  "type": "Feature",
  "properties": {
    "iso:country":"ES",
    "sg:address":"Ctra. Caceres, S/n",
    "sg:city":"Casillas De Coria",
    "sg:orig_category":"Cerrajer\u00cda, Ferrallista",
    "sg:phone":"+34 927 14 61 55",
    "sg:postcode":"10818",
    "sg:province":"C\u00e1ceres",
    "wof:name":"Cruz Rodriguez Emeterio Maria",
    "wof:placetype":"venue"
},
  "geometry": {"coordinates":[-6.6341629028,39.9637413025],"type":"Point"}
}