{
  "type": "Feature",
  "properties": {
    "iso:country":"ES",
    "sg:address":"Calle de C(campollano), 4",
    "sg:city":"Albacete",
    "sg:orig_category":"Empresas De Carpinter\u00cda Met\u00c1lica",
    "sg:phone":"+34 967 52 40 62",
    "sg:postcode":"02006",
    "sg:province":"Albacete",
    "wof:name":"Lopez Parra Manuela",
    "wof:placetype":"venue"
},
  "geometry": {"coordinates":[-1.9490209818,39.013168335],"type":"Point"}
}