{
  "type": "Feature",
  "properties": {
    "iso:country":"ES",
    "sg:address":"Rua Algalia De Arriba (da), 16",
    "sg:city":"Santiago De Compostela",
    "sg:orig_category":"Asociaciones Y Clubs Deportivos",
    "sg:phone":"+34 981 57 31 04",
    "sg:postcode":"15704",
    "sg:province":"La Coru\u00f1a",
    "wof:name":"Centro Deportivo S.l.",
    "wof:placetype":"venue"
},
  "geometry": {"coordinates":[-8.5422992706,42.8819122314],"type":"Point"}
}