{
  "type": "Feature",
  "properties": {
    "iso:country":"ES",
    "sg:address":"Avda Diputacion (de La), 25",
    "sg:city":"Castro Rio",
    "sg:orig_category":"Comercio De Piezas De Recambio Y De Accesorios De Veh\u00cdculos, Veh\u00cdculos Industriales",
    "sg:phone":"+34 957 37 02 96",
    "sg:postcode":"14840",
    "sg:province":"C\u00f3rdoba",
    "wof:name":"Criado Moreno Maria De La Paz",
    "wof:placetype":"venue"
},
  "geometry": {"coordinates":[-4.4860157967,37.6916618347],"type":"Point"}
}