{
  "type": "Feature",
  "properties": {
    "addr:full":"Calle de Duquesa, 9 Rute C\u00f3rdoba 14960",
    "addr:housenumber":"9",
    "addr:postcode":"14960",
    "addr:street":"Calle De Duquesa;Co\u0301Rdoba",
    "iso:country":"ES",
    "sg:address":"Calle de Duquesa, 9",
    "sg:city":"Rute",
    "sg:orig_category":"Alquiler De V\u00cddeo",
    "sg:phone":"+34 957 53 30 08",
    "sg:postcode":"14960",
    "sg:province":"C\u00f3rdoba",
    "wof:name":"Diaz Caballero Eva",
    "wof:placetype":"venue"
},
  "geometry": {"coordinates":[-4.3720488548,37.3263282776],"type":"Point"}
}