{
  "type": "Feature",
  "properties": {
    "iso:country":"ES",
    "sg:address":"Calle de Maestro Palau, 8",
    "sg:city":"Paiporta",
    "sg:orig_category":"Venta, Montaje De Neum\u00c1ticos",
    "sg:phone":"+34 963 97 90 26",
    "sg:postcode":"46200",
    "sg:province":"Valencia",
    "wof:name":"Jorge Juan",
    "wof:placetype":"venue"
},
  "geometry": {"coordinates":[-0.4196290076,39.4254455566],"type":"Point"}
}