{
  "type": "Feature",
  "properties": {
    "addr:full":"Rbla S Ferran, 51 Igualada Barcelona 08700",
    "addr:housenumber":"51",
    "addr:postcode":"08700",
    "addr:street":"Rbla S Ferran",
    "iso:country":"ES",
    "sg:address":"Rbla S Ferran, 51",
    "sg:city":"Igualada",
    "sg:orig_category":"Electrodom\u00c9sticos (al Por Menor)",
    "sg:phone":"+34 938 05 25 34",
    "sg:postcode":"08700",
    "sg:province":"Barcelona",
    "sg:website":"www.miro.es",
    "wof:name":"Establecimientos Miro S.l.",
    "wof:placetype":"venue"
},
  "geometry": {"coordinates":[1.6170699596,41.5795402527],"type":"Point"}
}