{
  "type": "Feature",
  "properties": {
    "iso:country":"ES",
    "sg:address":"Carrer de Mossen Cinto Verdaguer, 17",
    "sg:city":"Riudecols",
    "sg:orig_category":"Empresarios",
    "sg:phone":"+34 977 81 73 10",
    "sg:postcode":"43390",
    "sg:province":"Tarragona",
    "wof:name":"Aragones Camarasa Antonio",
    "wof:placetype":"venue"
},
  "geometry": {"coordinates":[0.9778231978,41.1677017212],"type":"Point"}
}