{
  "type": "Feature",
  "properties": {
    "addr:full":"Rbla Nova, 67 Mollet Valles Barcelona 08100",
    "addr:housenumber":"67",
    "addr:postcode":"08100",
    "addr:street":"Rbla Nova",
    "iso:country":"ES",
    "sg:address":"Rbla Nova, 67",
    "sg:city":"Mollet Valles",
    "sg:orig_category":"Reciclaje, Tratamiento De Tejidos",
    "sg:phone":"+34 935 93 89 50",
    "sg:postcode":"08100",
    "sg:province":"Barcelona",
    "wof:name":"Gonzalez Ruiz Encarnacion",
    "wof:placetype":"venue"
},
  "geometry": {"coordinates":[2.2095301151,41.5402107239],"type":"Point"}
}