{
  "type": "Feature",
  "properties": {
    "iso:country":"ES",
    "sg:address":"Rua Olas, 2",
    "sg:city":"Oleiros",
    "sg:orig_category":"Granos Y Semillas (producci\u00d3n, Al Por Mayor)",
    "sg:phone":"+34 981 63 11 61",
    "sg:postcode":"15173",
    "sg:province":"A Coru\u00f1a",
    "sg:website":"www.zulueta.com",
    "wof:name":"Zulueta Corporacion Para La Naturaleza S.a.",
    "wof:placetype":"venue"
},
  "geometry": {"coordinates":[-8.3184213638,43.3336296082],"type":"Point"}
}