{
  "type": "Feature",
  "properties": {
    "addr:full":"Calle de Rosario, 20 Gijon Asturias 33201",
    "addr:housenumber":"20",
    "addr:postcode":"33201",
    "addr:street":"Calle De Rosario",
    "iso:country":"ES",
    "sg:address":"Calle de Rosario, 20",
    "sg:city":"Gijon",
    "sg:orig_category":"Carnicer\u00cdas, Carnicer\u00cdas",
    "sg:phone":"+34 985 35 13 65",
    "sg:postcode":"33201",
    "sg:province":"Asturias",
    "wof:name":"Mones Sanchez Maria",
    "wof:placetype":"venue"
},
  "geometry": {"coordinates":[-5.6634979248,43.5461769104],"type":"Point"}
}