{
  "type": "Feature",
  "properties": {
    "iso:country":"ES",
    "sg:address":"Avda Moratalaz, 195",
    "sg:city":"Madrid",
    "sg:orig_category":"Tintes (fabricaci\u00d3n, Al Por Mayor)",
    "sg:phone":"+34 914 30 08 95",
    "sg:postcode":"28030",
    "sg:province":"Madrid",
    "wof:name":"Tintorerias Limi S.l.",
    "wof:placetype":"venue"
},
  "geometry": {"coordinates":[-3.6424760818,40.4093933105],"type":"Point"}
}