{
  "type": "Feature",
  "properties": {
    "addr:full":"Avda Manuel Torres, 21 Malaga M\u00e1laga 29003",
    "addr:housenumber":"21",
    "addr:postcode":"29003",
    "addr:street":"Avda Manuel Torres;Ma\u0301Laga",
    "iso:country":"ES",
    "sg:address":"Avda Manuel Torres, 21",
    "sg:city":"Malaga",
    "sg:orig_category":"Asociaciones Y Clubs Deportivos",
    "sg:phone":"+34 952 34 79 18",
    "sg:postcode":"29003",
    "sg:province":"M\u00e1laga",
    "wof:name":"Montiel Gutierrez Miguel Angel",
    "wof:placetype":"venue"
},
  "geometry": {"coordinates":[-4.4482188225,36.7004699707],"type":"Point"}
}