{
  "type": "Feature",
  "properties": {
    "iso:country":"ES",
    "sg:address":"Cami Cementeri, S/n",
    "sg:city":"Monovar",
    "sg:orig_category":"Discapacitados",
    "sg:phone":"+34 965 47 13 58",
    "sg:postcode":"03640",
    "sg:province":"Alicante",
    "wof:name":"Asociacion De Minusvalidos Com Tu",
    "wof:placetype":"venue"
},
  "geometry": {"coordinates":[-0.8310387731,38.4391174316],"type":"Point"}
}