{
  "type": "Feature",
  "properties": {
    "iso:country":"ES",
    "sg:address":"C/ Sant Antoni, 54",
    "sg:city":"Cerdanyola Valles",
    "sg:orig_category":"Centros De Coordinaci\u00d3n",
    "sg:phone":"+34 935 80 70 73",
    "sg:postcode":"08290",
    "sg:province":"Barcelona",
    "wof:name":"Eurogestiones 1990 S.l.",
    "wof:placetype":"venue"
},
  "geometry": {"coordinates":[2.1356670856,41.4935874939],"type":"Point"}
}