{
  "type": "Feature",
  "properties": {
    "iso:country":"ES",
    "sg:address":"Carrer de Joaquim Molins, 5",
    "sg:city":"Barcelona",
    "sg:orig_category":"Hormigonados",
    "sg:phone":"+34 934 90 06 36",
    "sg:postcode":"08028",
    "sg:province":"Barcelona",
    "wof:name":"Beton Catalan S.a.",
    "wof:placetype":"venue"
},
  "geometry": {"coordinates":[2.129034996,41.385925293],"type":"Point"}
}