{
  "type": "Feature",
  "properties": {
    "iso:country":"ES",
    "sg:address":"Carr Miranda (de La), 3",
    "sg:city":"Agramunt",
    "sg:orig_category":"Transportes Por V\u00cdas Navegables",
    "sg:phone":"+34 973 39 02 43",
    "sg:postcode":"25310",
    "sg:province":"Lleida",
    "wof:name":"Coma Naves Ramon",
    "wof:placetype":"venue"
},
  "geometry": {"coordinates":[1.0938349962,41.7863693237],"type":"Point"}
}