{
  "type": "Feature",
  "properties": {
    "addr:full":"Calle de Ignacio Serrano, 83 Valladolid Valladolid 47008",
    "addr:housenumber":"83",
    "addr:postcode":"47008",
    "addr:street":"Calle De Ignacio Serrano",
    "iso:country":"ES",
    "sg:address":"Calle de Ignacio Serrano, 83",
    "sg:city":"Valladolid",
    "sg:orig_category":"Agencias Y Agentes Comerciales, Representantes",
    "sg:phone":"+34 983 24 59 94",
    "sg:postcode":"47008",
    "sg:province":"Valladolid",
    "wof:name":"Jimenez Villanueva Jorge",
    "wof:placetype":"venue"
},
  "geometry": {"coordinates":[-4.7545580864,41.6095352173],"type":"Point"}
}