{
  "type": "Feature",
  "properties": {
    "iso:country":"ES",
    "sg:address":"Calle de Calderon De La Barca, 10",
    "sg:city":"S. Fernando",
    "sg:orig_category":"Abogados",
    "sg:phone":"+34 956 59 34 40",
    "sg:postcode":"11100",
    "sg:province":"C\u00e1diz",
    "wof:name":"De Querol Y Balen Abogados S.l.",
    "wof:placetype":"venue"
},
  "geometry": {"coordinates":[-6.1991691589,36.4646110535],"type":"Point"}
}