{
  "type": "Feature",
  "properties": {
    "addr:full":"D Juan Austria, 12 Guadix Granada 18500",
    "addr:housenumber":"12",
    "addr:postcode":"18500",
    "addr:street":"D Juan Austria",
    "iso:country":"ES",
    "sg:address":"D Juan Austria, 12",
    "sg:city":"Guadix",
    "sg:orig_category":"Electricidad (montaje, Ensamblaje De Componentes)",
    "sg:phone":"+34 958 66 01 39",
    "sg:postcode":"18500",
    "sg:province":"Granada",
    "wof:name":"Martinez Lopez Francisco",
    "wof:placetype":"venue"
},
  "geometry": {"coordinates":[-3.131834507,37.3015937805],"type":"Point"}
}