{
  "type": "Feature",
  "properties": {
    "addr:full":"Carr Espero, De S', 13 Poima Islas Baleares 07714",
    "addr:housenumber":"13",
    "addr:postcode":"07714",
    "addr:street":"Carr Espero De S ';Islas",
    "iso:country":"ES",
    "sg:address":"Carr Espero, De S', 13",
    "sg:city":"Poima",
    "sg:orig_category":"Empresas De Carpinter\u00cda",
    "sg:phone":"+34 971 36 16 59",
    "sg:postcode":"07714",
    "sg:province":"Islas Baleares",
    "wof:name":"Francisco Pons Truyol S.l.",
    "wof:placetype":"venue"
},
  "geometry": {"coordinates":[2.9117100239,39.6136398315],"type":"Point"}
}