{
  "type": "Feature",
  "properties": {
    "addr:full":"Carr Rei En Jaume, 58 Villarreal Castell\u00f3n 12540",
    "addr:housenumber":"58",
    "addr:postcode":"12540",
    "addr:street":"Carr Rei En Jaume",
    "iso:country":"ES",
    "sg:address":"Carr Rei En Jaume, 58",
    "sg:city":"Villarreal",
    "sg:orig_category":"Psic\u00d3logos",
    "sg:phone":"+34 964 53 33 88",
    "sg:postcode":"12540",
    "sg:province":"Castell\u00f3n",
    "wof:name":"Catalan Bou Consuelo",
    "wof:placetype":"venue"
},
  "geometry": {"coordinates":[-0.0952939987,39.9453048706],"type":"Point"}
}