{
  "type": "Feature",
  "properties": {
    "iso:country":"ES",
    "sg:address":"Calle de Remanso, 7",
    "sg:city":"Fuenlabrada",
    "sg:orig_category":"Construcciones Prefabricadas Y Desmontables",
    "sg:phone":"+34 916 07 13 50",
    "sg:postcode":"28942",
    "sg:province":"Madrid",
    "sg:website":"www.tabicota.com",
    "wof:name":"Contratas Y Tabiques S.l.",
    "wof:placetype":"venue"
},
  "geometry": {"coordinates":[-3.813035965,40.2920036316],"type":"Point"}
}