{
  "type": "Feature",
  "properties": {
    "addr:full":"Calle de Valmojado, 179 Madrid Madrid 28047",
    "addr:housenumber":"179",
    "addr:postcode":"28047",
    "addr:street":"Calle De Valmojado",
    "iso:country":"ES",
    "sg:address":"Calle de Valmojado, 179",
    "sg:city":"Madrid",
    "sg:orig_category":"Peluqueros: De Se\u00d1oras",
    "sg:phone":"+34 917 19 43 00",
    "sg:postcode":"28047",
    "sg:province":"Madrid",
    "wof:name":"Peluqueria Rossy S.l",
    "wof:placetype":"venue"
},
  "geometry": {"coordinates":[-3.7573502064,40.3899803162],"type":"Point"}
}