{
  "type": "Feature",
  "properties": {
    "iso:country":"ES",
    "sg:address":"Plaz Mayor, S/n",
    "sg:city":"Burgos",
    "sg:orig_category":"Aparcamientos (infraestructuras, Accesorios)",
    "sg:phone":"+34 947 25 75 64",
    "sg:postcode":"09003",
    "sg:province":"Burgos",
    "wof:name":"Aparcamientos Y Finanzas",
    "wof:placetype":"venue"
},
  "geometry": {"coordinates":[-3.7012963295,42.341632843],"type":"Point"}
}