{
  "type": "Feature",
  "properties": {
    "iso:country":"ES",
    "sg:address":"Calle de Mendez Alvaro, 4",
    "sg:city":"Madrid",
    "sg:orig_category":"Contenedores (mercanc\u00cdas)",
    "sg:phone":"+34 915 06 09 65",
    "sg:postcode":"28045",
    "sg:province":"Madrid",
    "wof:name":"Mist Madrid S.l.",
    "wof:placetype":"venue"
},
  "geometry": {"coordinates":[-3.6927399635,40.4067726135],"type":"Point"}
}