{
  "type": "Feature",
  "properties": {
    "addr:full":"Rua Francisco Llorens Diaz, 13 Ourense Ourense 32002",
    "addr:housenumber":"13",
    "addr:postcode":"32002",
    "addr:street":"Rua Francisco Llorens Diaz",
    "iso:country":"ES",
    "sg:address":"Rua Francisco Llorens Diaz, 13",
    "sg:city":"Ourense",
    "sg:orig_category":"Elementos Para Suelos Prefabricados",
    "sg:phone":"+34 988 23 10 20",
    "sg:postcode":"32002",
    "sg:province":"Ourense",
    "wof:name":"Gonzalez Fernandez Antonio",
    "wof:placetype":"venue"
},
  "geometry": {"coordinates":[-7.8707818985,42.3429298401],"type":"Point"}
}