{
  "type": "Feature",
  "properties": {
    "addr:full":"Calle de Maiquez, 12 Madrid Madrid 28009",
    "addr:housenumber":"12",
    "addr:postcode":"madrid;28009",
    "addr:street":"Calle De Maiquez",
    "iso:country":"ES",
    "sg:address":"Calle de Maiquez, 12",
    "sg:city":"Madrid",
    "sg:orig_category":"Juegos Y Juguetes (al Por Menor)",
    "sg:phone":"+34 915 04 11 95",
    "sg:postcode":"28009",
    "sg:province":"Madrid",
    "sg:website":"www.dismodel.com",
    "wof:name":"Madrid Pasamontes Alfredo",
    "wof:placetype":"venue"
},
  "geometry": {"coordinates":[-3.6728556156,40.4214439392],"type":"Point"}
}