{
  "type": "Feature",
  "properties": {
    "addr:full":"Calle de Brasa, 7 Zamora Zamora 49003",
    "addr:housenumber":"7",
    "addr:postcode":"49003",
    "addr:street":"Calle De Brasa",
    "iso:country":"ES",
    "sg:address":"Calle de Brasa, 7",
    "sg:city":"Zamora",
    "sg:orig_category":"Abogados",
    "sg:phone":"+34 980 53 38 55",
    "sg:postcode":"49003",
    "sg:province":"Zamora",
    "wof:name":"Martinez Toribio Zacarias",
    "wof:placetype":"venue"
},
  "geometry": {"coordinates":[-5.7423772812,41.5049438477],"type":"Point"}
}