{
  "type": "Feature",
  "properties": {
    "iso:country":"ES",
    "sg:address":"Carr Lleida (de), 22",
    "sg:city":"Guissona",
    "sg:orig_category":"Promotores Constructores",
    "sg:phone":"+34 973 55 21 08",
    "sg:postcode":"25210",
    "sg:province":"Lleida",
    "wof:name":"Promocions Esteve Olle S.l.",
    "wof:placetype":"venue"
},
  "geometry": {"coordinates":[1.2887649536,41.7873535156],"type":"Point"}
}