{
  "type": "Feature",
  "properties": {
    "iso:country":"ES",
    "sg:address":"Calle de Salpa (la), 1",
    "sg:city":"Alacant",
    "sg:orig_category":"Abogados",
    "sg:phone":"+34 965 16 38 01",
    "sg:postcode":"03540",
    "sg:province":"Alicante",
    "wof:name":"Martinez Navarro Paya Paya Abogados Asociados S.l.",
    "wof:placetype":"venue"
},
  "geometry": {"coordinates":[-0.410638988,38.3581085205],"type":"Point"}
}