{
  "type": "Feature",
  "properties": {
    "addr:full":"Calle de Maria Auxiliadora, 19 Puertollano Ciudad Real 13500",
    "addr:housenumber":"19",
    "addr:postcode":"13500",
    "addr:street":"Calle De Maria Auxiliadora",
    "iso:country":"ES",
    "sg:address":"Calle de Maria Auxiliadora, 19",
    "sg:city":"Puertollano",
    "sg:orig_category":"Peluquer\u00cdas, Peluquer\u00cda Mixta",
    "sg:phone":"+34 926 41 50 02",
    "sg:postcode":"13500",
    "sg:province":"Ciudad Real",
    "wof:name":"Fernandez Zamora Sarai",
    "wof:placetype":"venue"
},
  "geometry": {"coordinates":[-4.0993380547,38.6871070862],"type":"Point"}
}