{
  "type": "Feature",
  "properties": {
    "iso:country":"ES",
    "sg:address":"Poli Vernicha (la), S/n",
    "sg:city":"Vall D'uixo",
    "sg:orig_category":"Transportes Por Carretera: Lotes Completos, Mercanc\u00cdas Diversas",
    "sg:phone":"+34 964 66 08 97",
    "sg:postcode":"12600",
    "sg:province":"Castell\u00f3n",
    "wof:name":"Coloniales Nebot S.l.",
    "wof:placetype":"venue"
},
  "geometry": {"coordinates":[-0.0482099988,39.992477417],"type":"Point"}
}