{
  "type": "Feature",
  "properties": {
    "addr:full":"Carrer de Lloma (la), 80 Agost Alicante 03698",
    "addr:housenumber":"80",
    "addr:postcode":"03698",
    "addr:street":"Carrer De Lloma La",
    "iso:country":"ES",
    "sg:address":"Carrer de Lloma (la), 80",
    "sg:city":"Agost",
    "sg:orig_category":"Contenedores (mercanc\u00cdas)",
    "sg:phone":"+34 965 69 15 49",
    "sg:postcode":"03698",
    "sg:province":"Alicante",
    "wof:name":"Vicedo Ivorra Juan Jose",
    "wof:placetype":"venue"
},
  "geometry": {"coordinates":[-0.6360780001,38.4367408752],"type":"Point"}
}