{
  "type": "Feature",
  "properties": {
    "iso:country":"ES",
    "sg:address":"Avda Cuenca, 5",
    "sg:city":"Benidorm",
    "sg:orig_category":"Servicios De Telecomunicaciones",
    "sg:phone":"+34 965 86 66 78",
    "sg:postcode":"03500",
    "sg:province":"Alicante",
    "wof:name":"Coroas Callejas Alberto",
    "wof:placetype":"venue"
},
  "geometry": {"coordinates":[-0.1173449978,38.536895752],"type":"Point"}
}