{
  "type": "Feature",
  "properties": {
    "addr:full":"Av Vila De Blanes, 117 Lloret Mar Girona 17310",
    "addr:housenumber":"117",
    "addr:postcode":"17310",
    "addr:street":"Av Vila De Blanes",
    "iso:country":"ES",
    "sg:address":"Av Vila De Blanes, 117",
    "sg:city":"Lloret Mar",
    "sg:orig_category":"Molduras, Junquillos, Listones Y Molduras Perforadas",
    "sg:phone":"+34 972 36 78 64",
    "sg:postcode":"17310",
    "sg:province":"Girona",
    "wof:name":"Delgado Barral Antonio",
    "wof:placetype":"venue"
},
  "geometry": {"coordinates":[2.8320589066,41.6996994019],"type":"Point"}
}