{
  "type": "Feature",
  "properties": {
    "addr:full":"Calle de Juan Calzada Kalea, 87 Gernika-lumo Vizcaya 48300",
    "addr:housenumber":"87",
    "addr:postcode":"48300",
    "addr:street":"Calle De Juan Calzada Kalea",
    "iso:country":"ES",
    "sg:address":"Calle de Juan Calzada Kalea, 87",
    "sg:city":"Gernika-lumo",
    "sg:orig_category":"Institutos De Belleza",
    "sg:phone":"+34 946 25 29 09",
    "sg:postcode":"48300",
    "sg:province":"Vizcaya",
    "wof:name":"Martin Oteo Ainara",
    "wof:placetype":"venue"
},
  "geometry": {"coordinates":[-2.6803450584,43.3077507019],"type":"Point"}
}