{
  "type": "Feature",
  "properties": {
    "addr:full":"Pda. Bufarrat, S/n Soses Lleida 25181",
    "addr:housenumber":"s / n",
    "addr:postcode":"25181",
    "iso:country":"ES",
    "sg:address":"Pda. Bufarrat, S/n",
    "sg:city":"Soses",
    "sg:orig_category":"Poller\u00cda Y Caza (al Por Menor)",
    "sg:phone":"+34 973 79 70 94",
    "sg:postcode":"25181",
    "sg:province":"Lleida",
    "wof:name":"Tresanchez S.c.",
    "wof:placetype":"venue"
},
  "geometry": {"coordinates":[0.4859260023,41.5447273254],"type":"Point"}
}