{
  "type": "Feature",
  "properties": {
    "iso:country":"ES",
    "sg:address":"Trva Araquil, 1",
    "sg:city":"Peralta",
    "sg:orig_category":"Electromec\u00c1nica",
    "sg:phone":"+34 948 71 30 29",
    "sg:postcode":"31350",
    "sg:province":"Navarra",
    "wof:name":"Electromecanica Araquil S.l.",
    "wof:placetype":"venue"
},
  "geometry": {"coordinates":[-1.8035570383,42.3392906189],"type":"Point"}
}