{
  "type": "Feature",
  "properties": {
    "iso:country":"ES",
    "sg:address":"Calle de Do\u00d1a Perfecta, 210",
    "sg:city":"Palmas De Gran Canaria",
    "sg:orig_category":"Serigraf\u00cda (material Y Suministros)",
    "sg:phone":"+34 928 28 11 28",
    "sg:postcode":"35012",
    "sg:province":"Las Palmas",
    "sg:website":"www.agcanarias.com",
    "wof:name":"Artes Graficas Canarias S.l.",
    "wof:placetype":"venue"
},
  "geometry": {"coordinates":[-15.4382743835,28.1075649261],"type":"Point"}
}