{
  "type": "Feature",
  "properties": {
    "addr:full":"Urb Tomillar (el), 4 Tomillar M\u00e1laga 29740",
    "addr:postcode":"29740",
    "addr:street":"Urb;El;Ma\u0301Laga",
    "iso:country":"ES",
    "sg:address":"Urb Tomillar (el), 4",
    "sg:city":"Tomillar",
    "sg:orig_category":"Granos Y Semillas (producci\u00d3n, Al Por Mayor)",
    "sg:phone":"+34 952 54 43 48",
    "sg:postcode":"29740",
    "sg:province":"M\u00e1laga",
    "wof:name":"Calle Fuentes Jose",
    "wof:placetype":"venue"
},
  "geometry": {"coordinates":[-4.0894589424,36.7442398071],"type":"Point"}
}