{
  "type": "Feature",
  "properties": {
    "addr:full":"Calle de Bilbao, 12 Valencia Valencia 46009",
    "addr:housenumber":"12",
    "addr:postcode":"46009",
    "addr:street":"Calle De Bilbao",
    "iso:country":"ES",
    "sg:address":"Calle de Bilbao, 12",
    "sg:city":"Valencia",
    "sg:orig_category":"Inmobiliaria (agencias)",
    "sg:phone":"+34 963 68 83 38",
    "sg:postcode":"46009",
    "sg:province":"Valencia",
    "wof:name":"Garcia Valero Felix",
    "wof:placetype":"venue"
},
  "geometry": {"coordinates":[-0.3728317916,39.48645401],"type":"Point"}
}