{
  "type": "Feature",
  "properties": {
    "addr:full":"Calle de Navarrosa, 7 Azuqueca Henares Guadalajara 19200",
    "addr:housenumber":"7",
    "addr:postcode":"19200",
    "addr:street":"Calle De Navarrosa",
    "iso:country":"ES",
    "sg:address":"Calle de Navarrosa, 7",
    "sg:city":"Azuqueca Henares",
    "sg:orig_category":"Pescader\u00cdas (al Por Menor)",
    "sg:phone":"+34 949 26 01 54",
    "sg:postcode":"19200",
    "sg:province":"Guadalajara",
    "wof:name":"Aldulce C.b.",
    "wof:placetype":"venue"
},
  "geometry": {"coordinates":[-3.2545859814,40.5733833313],"type":"Point"}
}