{
  "type": "Feature",
  "properties": {
    "iso:country":"ES",
    "sg:address":"La Fuente, S/n",
    "sg:city":"Villabalter",
    "sg:orig_category":"Carnicer\u00cdas, Carnicer\u00cdas",
    "sg:phone":"+34 987 84 64 70",
    "sg:postcode":"24010",
    "sg:province":"Le\u00f3n",
    "wof:name":"Castro Alvarez Jose Manuel",
    "wof:placetype":"venue"
},
  "geometry": {"coordinates":[-5.6193161011,42.6222076416],"type":"Point"}
}