{
  "type": "Feature",
  "properties": {
    "iso:country":"ES",
    "sg:address":"Pg Vint-i-dos De Juliol, 508",
    "sg:city":"Terrassa",
    "sg:orig_category":"Promotores Constructores",
    "sg:phone":"+34 937 83 30 42",
    "sg:postcode":"08222",
    "sg:province":"Barcelona",
    "wof:name":"Construcciones Sabert S.a.",
    "wof:placetype":"venue"
},
  "geometry": {"coordinates":[2.0202050209,41.5693283081],"type":"Point"}
}