{
  "type": "Feature",
  "properties": {
    "iso:country":"ES",
    "sg:address":"Carrer de Diputacio, 233",
    "sg:city":"Barcelona",
    "sg:orig_category":"Cervecer\u00cdas",
    "sg:phone":"+34 934 87 60 34",
    "sg:postcode":"08007",
    "sg:province":"Barcelona",
    "wof:name":"Viguin Restauracion S.l",
    "wof:placetype":"venue"
},
  "geometry": {"coordinates":[2.164192915,41.3884429932],"type":"Point"}
}