{
  "type": "Feature",
  "properties": {
    "addr:full":"Calle de Mari Monreal, 18 Alcazar S. Juan Ciudad Real 13600",
    "addr:housenumber":"18",
    "addr:postcode":"13600",
    "addr:street":"Calle De Mari Monreal;Alcazar S. Juan Ciudad Real",
    "iso:country":"ES",
    "sg:address":"Calle de Mari Monreal, 18",
    "sg:city":"Alcazar S. Juan",
    "sg:orig_category":"Centros De Educaci\u00d3n Especial",
    "sg:phone":"+34 926 54 62 83",
    "sg:postcode":"13600",
    "sg:province":"Ciudad Real",
    "wof:name":"Colegio Publico Juan De Austria",
    "wof:placetype":"venue"
},
  "geometry": {"coordinates":[-3.210203886,39.3900718689],"type":"Point"}
}