{
  "type": "Feature",
  "properties": {
    "iso:country":"ES",
    "sg:address":"Carrer de Eduardo Conde, 50",
    "sg:city":"Barcelona",
    "sg:orig_category":"Peluquer\u00cdas, Peluquer\u00cda Mixta",
    "sg:phone":"+34 932 05 16 93",
    "sg:postcode":"08034",
    "sg:province":"Barcelona",
    "wof:name":"Martinez Alcazar Maria Eugenia",
    "wof:placetype":"venue"
},
  "geometry": {"coordinates":[2.1210699081,41.393989563],"type":"Point"}
}