{
  "type": "Feature",
  "properties": {
    "addr:full":"Carr General Pastor, 31 Eliana Valencia 46183",
    "addr:housenumber":"31",
    "addr:postcode":"46183",
    "addr:street":"Carr General Pastor",
    "iso:country":"ES",
    "sg:address":"Carr General Pastor, 31",
    "sg:city":"Eliana",
    "sg:orig_category":"Papeler\u00cdas, Librer\u00cdas",
    "sg:phone":"+34 961 65 50 06",
    "sg:postcode":"46183",
    "sg:province":"Valencia",
    "wof:name":"Sanchez Sanchez Maria Teresa",
    "wof:placetype":"venue"
},
  "geometry": {"coordinates":[-0.5312190056,39.5645904541],"type":"Point"}
}