{
  "type": "Feature",
  "properties": {
    "addr:full":"Carrer de Santa M. De Mazzarello, 72 Terrassa Barcelona 08224",
    "addr:housenumber":"72",
    "addr:postcode":"08224",
    "addr:street":"Carrer De Santa M. De Mazzarello",
    "iso:country":"ES",
    "sg:address":"Carrer de Santa M. De Mazzarello, 72",
    "sg:city":"Terrassa",
    "sg:orig_category":"Peluquer\u00cdas, Peluquer\u00cda Mixta",
    "sg:phone":"+34 937 88 66 49",
    "sg:postcode":"08224",
    "sg:province":"Barcelona",
    "wof:name":"Quesada Mu\u00f1oz Maria",
    "wof:placetype":"venue"
},
  "geometry": {"coordinates":[1.9906500578,41.5405235291],"type":"Point"}
}