{
  "type": "Feature",
  "properties": {
    "addr:full":"Calle de Ense\u00d1anza, 1 Chiva Valencia 46370",
    "addr:housenumber":"1",
    "addr:postcode":"46370",
    "addr:street":"Calle De Ensen\u0303Anza",
    "iso:country":"ES",
    "sg:address":"Calle de Ense\u00d1anza, 1",
    "sg:city":"Chiva",
    "sg:orig_category":"Molduras, Junquillos, Listones Y Molduras Perforadas",
    "sg:phone":"+34 962 52 04 09",
    "sg:postcode":"46370",
    "sg:province":"Valencia",
    "wof:name":"Castellote Verdejo Belinda",
    "wof:placetype":"venue"
},
  "geometry": {"coordinates":[-0.7168319821,39.4718780518],"type":"Point"}
}