{
  "type": "Feature",
  "properties": {
    "addr:full":"Carrer de Catalunya, 21 Secuita Tarragona 43765",
    "addr:housenumber":"21",
    "addr:postcode":"43765",
    "addr:street":"Carrer De Catalunya",
    "iso:country":"ES",
    "sg:address":"Carrer de Catalunya, 21",
    "sg:city":"Secuita",
    "sg:orig_category":"Ingeniero",
    "sg:phone":"+34 977 61 13 63",
    "sg:postcode":"43765",
    "sg:province":"Tarragona",
    "wof:name":"Herrera Figuera Roger",
    "wof:placetype":"venue"
},
  "geometry": {"coordinates":[1.2802950144,41.2049217224],"type":"Point"}
}