{
  "type": "Feature",
  "properties": {
    "addr:full":"Carrer de Francesc Tarafa, 22 Granollers Barcelona 08402",
    "addr:housenumber":"22",
    "addr:postcode":"08402",
    "addr:street":"Carrer De Francesc Tarafa",
    "iso:country":"ES",
    "sg:address":"Carrer de Francesc Tarafa, 22",
    "sg:city":"Granollers",
    "sg:orig_category":"Farmacias (repartici\u00d3n Y Al Por Mayor)",
    "sg:phone":"+34 938 70 62 54",
    "sg:postcode":"08402",
    "sg:province":"Barcelona",
    "wof:name":"Valles-farma S. A.",
    "wof:placetype":"venue"
},
  "geometry": {"coordinates":[2.2904040813,41.6109428406],"type":"Point"}
}