{
  "type": "Feature",
  "properties": {
    "iso:country":"ES",
    "sg:address":"Calle de Se\u00d1or De La Expiracion, S/n",
    "sg:city":"Lanjaron",
    "sg:orig_category":"Delegados, Agentes De Tr\u00c1nsito, Auxiliares De Transporte Internacional",
    "sg:phone":"+34 958 77 08 35",
    "sg:postcode":"18420",
    "sg:province":"Granada",
    "wof:name":"Gonzalez Fernandez Juan",
    "wof:placetype":"venue"
},
  "geometry": {"coordinates":[-3.4785439968,36.9183692932],"type":"Point"}
}