{
  "type": "Feature",
  "properties": {
    "addr:full":"Carretera Galera, 5 Sta. Barbara Tarragona 43570",
    "addr:housenumber":"5 sta.",
    "addr:postcode":"43570",
    "addr:street":"Carretera Galera;Barbara Tarragona",
    "iso:country":"ES",
    "sg:address":"Carretera Galera, 5",
    "sg:city":"Sta. Barbara",
    "sg:orig_category":"Bosques (trabajos, Asesor\u00cda, Gesti\u00d3n)",
    "sg:phone":"+34 977 71 84 90",
    "sg:postcode":"43570",
    "sg:province":"Tarragona",
    "wof:name":"Ger' S-mar S.c.p.",
    "wof:placetype":"venue"
},
  "geometry": {"coordinates":[0.4884600043,40.7129096985],"type":"Point"}
}