{
  "type": "Feature",
  "properties": {
    "iso:country":"ES",
    "sg:address":"Rua Real, 53",
    "sg:city":"Ferrol",
    "sg:classifiers":[
        {
            "category":"Autos & Motor Vehicles",
            "subcategory":"Automobile Sales",
            "type":"Retail Goods"
        }
    ],
    "sg:phone":"+34 981 35 52 01",
    "sg:postcode":"15402",
    "sg:province":"A Coru\u00f1a",
    "wof:name":"Torremar Sociedad Cooperativa Limitada Auto Escuela",
    "wof:placetype":"venue"
},
  "geometry": {"coordinates":[-8.2311382294,43.48462677],"type":"Point"}
}