{
  "type": "Feature",
  "properties": {
    "addr:full":"Calle de Jose Antonio (garrapinillos), 15 Garrapinillos Zaragoza 50190",
    "addr:housenumber":"15",
    "addr:postcode":"50190",
    "addr:street":"Calle De Jose Antonio Garrapinillos",
    "iso:country":"ES",
    "sg:address":"Calle de Jose Antonio (garrapinillos), 15",
    "sg:city":"Garrapinillos",
    "sg:orig_category":"Plomeros",
    "sg:phone":"+34 976 78 05 36",
    "sg:postcode":"50190",
    "sg:province":"Zaragoza",
    "wof:name":"Andia Arjol Jose Miguel",
    "wof:placetype":"venue"
},
  "geometry": {"coordinates":[-1.0273573399,41.6837768555],"type":"Point"}
}