{
  "type": "Feature",
  "properties": {
    "iso:country":"ES",
    "sg:address":"Calle de Santiago, 20",
    "sg:city":"Valladolid",
    "sg:orig_category":"Moda",
    "sg:phone":"+34 983 35 46 73",
    "sg:postcode":"47001",
    "sg:province":"Valladolid",
    "wof:name":"Guante Varade S. A.",
    "wof:placetype":"venue"
},
  "geometry": {"coordinates":[-4.7291789055,41.6496047974],"type":"Point"}
}