{
  "type": "Feature",
  "properties": {
    "addr:full":"Pla\u00c7 De Sant Domingo, S/n Ontinyent Valencia 46870",
    "addr:housenumber":"s / n",
    "addr:postcode":"46870",
    "iso:country":"ES",
    "sg:address":"Pla\u00c7 De Sant Domingo, S/n",
    "sg:city":"Ontinyent",
    "sg:orig_category":"Loter\u00cda Y T\u00d3mbola",
    "sg:phone":"+34 962 38 58 91",
    "sg:postcode":"46870",
    "sg:province":"Valencia",
    "wof:name":"Climent Domenech Alejandro",
    "wof:placetype":"venue"
},
  "geometry": {"coordinates":[-0.606629014,38.8222808838],"type":"Point"}
}