{
  "type": "Feature",
  "properties": {
    "addr:full":"Carrer de Sindicat, 70 Palma Islas Baleares 07002",
    "addr:housenumber":"70",
    "addr:postcode":"07002",
    "addr:street":"Carrer De Sindicat",
    "iso:country":"ES",
    "sg:address":"Carrer de Sindicat, 70",
    "sg:city":"Palma",
    "sg:orig_category":"Tiendas De Grano, Frutas Y Legumbres Secas (al Por Menor)",
    "sg:phone":"+34 971 71 63 36",
    "sg:postcode":"07002",
    "sg:province":"Islas Baleares",
    "wof:name":"Margarita Juan Blanch Francisca Juan Blanch Y Francisco Juan Obrador Cdad.",
    "wof:placetype":"venue"
},
  "geometry": {"coordinates":[2.656443119,39.5723953247],"type":"Point"}
}