{
  "type": "Feature",
  "properties": {
    "iso:country":"ES",
    "sg:address":"Avda Principe De Asturias, 44",
    "sg:city":"Villaviciosa Odon",
    "sg:orig_category":"Cajas De Ahorro",
    "sg:phone":"+34 916 16 95 40",
    "sg:postcode":"28670",
    "sg:province":"Madrid",
    "sg:website":"www.bbk.es",
    "wof:name":"Bilbao Bizkaia Kutxa",
    "wof:placetype":"venue"
},
  "geometry": {"coordinates":[-3.9028429985,40.3568763733],"type":"Point"}
}