{
  "type": "Feature",
  "properties": {
    "iso:country":"ES",
    "sg:address":"Calle de Abastos (de), 130",
    "sg:city":"Aranjuez",
    "sg:orig_category":"Farmacias",
    "sg:phone":"+34 918 91 42 17",
    "sg:postcode":"28300",
    "sg:province":"Madrid",
    "wof:name":"Novofarma 2000 S.l.",
    "wof:placetype":"venue"
},
  "geometry": {"coordinates":[-3.598852396,40.0317115784],"type":"Point"}
}