{
  "type": "Feature",
  "properties": {
    "addr:full":"Ctra Santa Coloma, 10 Girona Girona 17005",
    "addr:housenumber":"10",
    "addr:postcode":"17005",
    "addr:street":"Ctra Santa Coloma",
    "iso:country":"ES",
    "sg:address":"Ctra Santa Coloma, 10",
    "sg:city":"Girona",
    "sg:orig_category":"Ingenier\u00cda, Centros De Estudios (diversos)",
    "sg:phone":"+34 972 23 80 00",
    "sg:postcode":"17005",
    "sg:province":"Girona",
    "wof:name":"Desenvolupament De Projectes Girona S.l.",
    "wof:placetype":"venue"
},
  "geometry": {"coordinates":[2.811909914,41.9689788818],"type":"Point"}
}