{
  "type": "Feature",
  "properties": {
    "iso:country":"ES",
    "sg:address":"Carrer de Nou, 44",
    "sg:city":"S. Pere Ribes",
    "sg:orig_category":"Inmobiliaria (agencias)",
    "sg:phone":"+34 938 96 33 66",
    "sg:postcode":"08810",
    "sg:province":"Barcelona",
    "wof:name":"Eastward Construmax S.l.",
    "wof:placetype":"venue"
},
  "geometry": {"coordinates":[1.7697329521,41.2609176636],"type":"Point"}
}