{
  "type": "Feature",
  "properties": {
    "iso:country":"ES",
    "sg:address":"Ctra Gojar-dilar, Km. 0002,0",
    "sg:city":"Gojar",
    "sg:orig_category":"Producci\u00d3n De Abonos Y De Fertilizantes",
    "sg:phone":"+34 958 59 76 11",
    "sg:postcode":"18150",
    "sg:province":"Granada",
    "wof:name":"Agroorganicos Mediterraneo S.l.",
    "wof:placetype":"venue"
},
  "geometry": {"coordinates":[-3.595654,37.113304],"type":"Point"}
}