{
  "type": "Feature",
  "properties": {
    "addr:full":"Carrer de Cartagena, 302 Barcelona Barcelona 08025",
    "addr:housenumber":"302",
    "addr:postcode":"08025",
    "addr:street":"Carrer De Cartagena",
    "iso:country":"ES",
    "sg:address":"Carrer de Cartagena, 302",
    "sg:city":"Barcelona",
    "sg:orig_category":"Frutas, Legumbres Frescas Y Tempranas (al Por Menor)",
    "sg:phone":"+34 934 55 08 55",
    "sg:postcode":"08025",
    "sg:province":"Barcelona",
    "wof:name":"Villanova Adan Pablo",
    "wof:placetype":"venue"
},
  "geometry": {"coordinates":[2.1758439541,41.4102058411],"type":"Point"}
}