{
  "type": "Feature",
  "properties": {
    "iso:country":"ES",
    "sg:address":"Pol Barrios, 11",
    "sg:city":"Rojales",
    "sg:orig_category":"Transportes Internacionales",
    "sg:phone":"+34 966 79 24 04",
    "sg:postcode":"03170",
    "sg:province":"Alicante",
    "wof:name":"Almofresh S.a.",
    "wof:placetype":"venue"
},
  "geometry": {"coordinates":[-0.705779016,38.0716133118],"type":"Point"}
}