{
  "type": "Feature",
  "properties": {
    "iso:country":"ES",
    "sg:address":"Carrer de Verge Del Remei, 3",
    "sg:city":"Rieral",
    "sg:orig_category":"Cuchiller\u00cda (al Por Menor)",
    "sg:phone":"+34 938 44 69 36",
    "sg:postcode":"08187",
    "sg:province":"Barcelona",
    "wof:name":"Margigar S.l.",
    "wof:placetype":"venue"
},
  "geometry": {"coordinates":[2.2261309624,41.6427230835],"type":"Point"}
}