{
  "type": "Feature",
  "properties": {
    "addr:full":"Carrer de Arxiprest Borras, 23 Coll De'n Rabassa Islas Baleares 07007",
    "addr:housenumber":"23",
    "addr:postcode":"07007",
    "addr:street":"Carrer De Arxiprest Borras",
    "iso:country":"ES",
    "sg:address":"Carrer de Arxiprest Borras, 23",
    "sg:city":"Coll De'n Rabassa",
    "sg:orig_category":"Iglesia Cat\u00d3lica",
    "sg:phone":"+34 971 26 09 68",
    "sg:postcode":"07007",
    "sg:province":"Islas Baleares",
    "wof:name":"Obispado De Mallorca",
    "wof:placetype":"venue"
},
  "geometry": {"coordinates":[2.9117100239,39.6136398315],"type":"Point"}
}