{
  "type": "Feature",
  "properties": {
    "iso:country":"ES",
    "sg:address":"Calle de Fernando El Catolico, S/n",
    "sg:city":"Torredelcampo",
    "sg:orig_category":"Contenedores (mercanc\u00cdas)",
    "sg:phone":"+34 953 56 71 42",
    "sg:postcode":"23640",
    "sg:province":"Ja\u00e9n",
    "wof:name":"Exposito Aguayo Jose",
    "wof:placetype":"venue"
},
  "geometry": {"coordinates":[-3.9001119137,37.7719154358],"type":"Point"}
}