{
  "type": "Feature",
  "properties": {
    "addr:full":"Ptge Pau Casals, 2 Valls Tarragona 43800",
    "addr:housenumber":"2",
    "addr:postcode":"43800",
    "addr:street":"Ptge Pau Casals",
    "iso:country":"ES",
    "sg:address":"Ptge Pau Casals, 2",
    "sg:city":"Valls",
    "sg:orig_category":"Transportes De Autom\u00d3viles Y Otros Veh\u00cdculos",
    "sg:phone":"+34 977 60 14 50",
    "sg:postcode":"43800",
    "sg:province":"Tarragona",
    "wof:name":"Grues I Transports Arseni Sanz Sl",
    "wof:placetype":"venue"
},
  "geometry": {"coordinates":[1.2565976381,41.2897644043],"type":"Point"}
}