{
  "type": "Feature",
  "properties": {
    "addr:full":"Rua Coru\u00d1a, 26 Vigo Pontevedra 36211",
    "addr:housenumber":"26",
    "addr:postcode":"36211",
    "addr:street":"Rua Corun\u0303A",
    "iso:country":"ES",
    "sg:address":"Rua Coru\u00d1a, 26",
    "sg:city":"Vigo",
    "sg:orig_category":"M\u00c9dicos: Cardiolog\u00cda Y Afecciones Cardiovasculares",
    "sg:phone":"+34 986 29 42 68",
    "sg:postcode":"36211",
    "sg:province":"Pontevedra",
    "wof:name":"Fundacion Medica Para La Investigacion Y",
    "wof:placetype":"venue"
},
  "geometry": {"coordinates":[-8.734249115,42.2223892212],"type":"Point"}
}