{
  "type": "Feature",
  "properties": {
    "iso:country":"ES",
    "sg:address":"Av Mosquera, 1",
    "sg:city":"Alcalali",
    "sg:orig_category":"M\u00c9dicos: Estomatolog\u00cda",
    "sg:phone":"+34 966 48 24 33",
    "sg:postcode":"03728",
    "sg:province":"Alicante",
    "wof:name":"Gregoret  Enso Jose",
    "wof:placetype":"venue"
},
  "geometry": {"coordinates":[-0.0420310013,38.7513961792],"type":"Point"}
}