{
  "type": "Feature",
  "properties": {
    "iso:country":"ES",
    "sg:address":"Pol Atalayas, S/n",
    "sg:city":"Alacant",
    "sg:orig_category":"Papel, Reciclaje",
    "sg:phone":"+34 965 10 80 18",
    "sg:postcode":"03006",
    "sg:province":"Alicante",
    "sg:website":"www.martinezcano-sa.es",
    "wof:name":"Pedro Martinez Cano S.l.",
    "wof:placetype":"venue"
},
  "geometry": {"coordinates":[-0.4804739952,38.3440856934],"type":"Point"}
}