{
  "type": "Feature",
  "properties": {
    "iso:country":"ES",
    "sg:address":"Castillejo, 12",
    "sg:city":"Estepa",
    "sg:orig_category":"Asilos De Ancianos. Centros Privados",
    "sg:phone":"+34 955 91 32 54",
    "sg:postcode":"41560",
    "sg:province":"Sevilla",
    "wof:name":"Residencia De Ancianos Nuestra Se\u00f1ora De La Asuncion",
    "wof:placetype":"venue"
},
  "geometry": {"coordinates":[-4.8826031685,37.2892189026],"type":"Point"}
}