{
  "type": "Feature",
  "properties": {
    "iso:country":"ES",
    "sg:address":"Calle de Doctor Luis Nistal, 1",
    "sg:city":"Ba\u00d1eza",
    "sg:orig_category":"Empresarios",
    "sg:phone":"+34 987 64 35 07",
    "sg:postcode":"24750",
    "sg:province":"Le\u00f3n",
    "wof:name":"Lobato Sanjuan Miguel Prudencio",
    "wof:placetype":"venue"
},
  "geometry": {"coordinates":[-5.5717520714,42.5998764038],"type":"Point"}
}