{
  "type": "Feature",
  "properties": {
    "addr:full":"Calle de Stuart (de), 106 Aranjuez Madrid 28300",
    "addr:housenumber":"106",
    "addr:postcode":"28300",
    "addr:street":"Calle De Stuart De",
    "iso:country":"ES",
    "sg:address":"Calle de Stuart (de), 106",
    "sg:city":"Aranjuez",
    "sg:orig_category":"Confecci\u00d3n De Trajes Para Se\u00d1oras",
    "sg:phone":"+34 918 91 09 57",
    "sg:postcode":"28300",
    "sg:province":"Madrid",
    "wof:name":"Gimeno Gimenez Juan Antonio",
    "wof:placetype":"venue"
},
  "geometry": {"coordinates":[-3.6038639545,40.031703949],"type":"Point"}
}