{
  "type": "Feature",
  "properties": {
    "iso:country":"ES",
    "sg:address":"Afueras, S/n",
    "sg:city":"Valdivia",
    "sg:orig_category":"Cooperativas Agr\u00cdcolas",
    "sg:phone":"+34 924 83 20 61",
    "sg:postcode":"06720",
    "sg:province":"Badajoz",
    "wof:name":"Cooperativa De Regantes De Extremadura",
    "wof:placetype":"venue"
},
  "geometry": {"coordinates":[-5.7112240791,39.0330505371],"type":"Point"}
}