{
  "type": "Feature",
  "properties": {
    "iso:country":"ES",
    "sg:address":"Carr Josep Coroleu, 76",
    "sg:city":"Vilanova I La Geltru",
    "sg:orig_category":"Empresas De Limpieza",
    "sg:phone":"+34 938 15 77 92",
    "sg:postcode":"08800",
    "sg:province":"Barcelona",
    "wof:name":"Crista-rapid S.c.p.",
    "wof:placetype":"venue"
},
  "geometry": {"coordinates":[1.7190840244,41.2221488953],"type":"Point"}
}