{
  "type": "Feature",
  "properties": {
    "addr:full":"Calle de Lora Del Rio, 9 Fuentes De Andalucia Sevilla 41420",
    "addr:housenumber":"9",
    "addr:postcode":"41420",
    "addr:street":"Calle De Lora Del Rio",
    "iso:country":"ES",
    "sg:address":"Calle de Lora Del Rio, 9",
    "sg:city":"Fuentes De Andalucia",
    "sg:orig_category":"Fotograf\u00cda Art\u00cdstica Y Retratos",
    "sg:phone":"+34 954 83 72 24",
    "sg:postcode":"41420",
    "sg:province":"Sevilla",
    "wof:name":"Talavera Caro Juan",
    "wof:placetype":"venue"
},
  "geometry": {"coordinates":[-5.3458151817,37.4633216858],"type":"Point"}
}