{
  "type": "Feature",
  "properties": {
    "addr:full":"Calle de Maestro Millan Picazo, 17 Algeciras C\u00e1diz 11204",
    "addr:housenumber":"17;ca\u0301diz",
    "addr:postcode":"11204",
    "addr:street":"Calle De Maestro Millan Picazo",
    "iso:country":"ES",
    "sg:address":"Calle de Maestro Millan Picazo, 17",
    "sg:city":"Algeciras",
    "sg:orig_category":"Lavado, Limpieza De Veh\u00cdculos",
    "sg:phone":"+34 956 65 11 51",
    "sg:postcode":"11204",
    "sg:province":"C\u00e1diz",
    "wof:name":"Fernandez Vargas Salvador",
    "wof:placetype":"venue"
},
  "geometry": {"coordinates":[-5.4497599602,36.1404151917],"type":"Point"}
}