{
  "type": "Feature",
  "properties": {
    "addr:full":"Calle de Silvina, 1 Malaga M\u00e1laga 29190",
    "addr:housenumber":"1",
    "addr:postcode":"29190",
    "addr:street":"Calle De Silvina;Ma\u0301Laga",
    "iso:country":"ES",
    "sg:address":"Calle de Silvina, 1",
    "sg:city":"Malaga",
    "sg:orig_category":"Reposter\u00cdas",
    "sg:phone":"+34 952 43 24 67",
    "sg:postcode":"29190",
    "sg:province":"M\u00e1laga",
    "wof:name":"Paconlo S.l.",
    "wof:placetype":"venue"
},
  "geometry": {"coordinates":[-4.492181778,36.7469863892],"type":"Point"}
}