{
  "type": "Feature",
  "properties": {
    "iso:country":"ES",
    "sg:address":"Calle de Fernandez Ladreda, 10",
    "sg:city":"Oviedo",
    "sg:orig_category":"Institutos De Belleza",
    "sg:phone":"+34 985 11 42 03",
    "sg:postcode":"33011",
    "sg:province":"Asturias",
    "wof:name":"Corral Vega Marta Maria",
    "wof:placetype":"venue"
},
  "geometry": {"coordinates":[-5.8361310959,43.3705482483],"type":"Point"}
}