{
  "type": "Feature",
  "properties": {
    "addr:full":"Pantano De Arlanzon, S/n Villasur Herreros Burgos 09199",
    "addr:housenumber":"s / n",
    "addr:postcode":"09199",
    "iso:country":"ES",
    "sg:address":"Pantano De Arlanzon, S/n",
    "sg:city":"Villasur Herreros",
    "sg:orig_category":"Empresas De Electricidad En General",
    "sg:phone":"+34 947 42 40 05",
    "sg:postcode":"09199",
    "sg:province":"Burgos",
    "wof:name":"Redondo Hermanos S. L.",
    "wof:placetype":"venue"
},
  "geometry": {"coordinates":[-3.4606389999,42.3377113342],"type":"Point"}
}