{
  "type": "Feature",
  "properties": {
    "iso:country":"ES",
    "sg:address":"Avda Rosalia De Castro (de), 56",
    "sg:city":"Santiago De Compostela",
    "sg:orig_category":"Asociaciones Y Clubs Deportivos",
    "sg:phone":"+34 981 59 61 88",
    "sg:postcode":"15706",
    "sg:province":"La Coru\u00f1a",
    "wof:name":"Filloy Rial Juan Benito",
    "wof:placetype":"venue"
},
  "geometry": {"coordinates":[-8.5517940521,42.8746910095],"type":"Point"}
}