{
  "type": "Feature",
  "properties": {
    "addr:full":"Calle de Placentines, 41 Sevilla Sevilla 41004",
    "addr:housenumber":"41",
    "addr:postcode":"41004",
    "addr:street":"Calle De Placentines",
    "iso:country":"ES",
    "sg:address":"Calle de Placentines, 41",
    "sg:city":"Sevilla",
    "sg:orig_category":"Compraventa De Antig\u00dcedades",
    "sg:phone":"+34 954 22 76 17",
    "sg:postcode":"41004",
    "sg:province":"Sevilla",
    "wof:name":"Plata Del Pino Antonio",
    "wof:placetype":"venue"
},
  "geometry": {"coordinates":[-5.9922790527,37.3872451782],"type":"Point"}
}