{
  "type": "Feature",
  "properties": {
    "addr:full":"Calle de Nuestra Se\u00d1ora Del Aguila, 9 Alcala Guadaira Sevilla 41500",
    "addr:housenumber":"9",
    "addr:postcode":"41500",
    "addr:street":"Calle De Nuestra;Del Aguila",
    "iso:country":"ES",
    "sg:address":"Calle de Nuestra Se\u00d1ora Del Aguila, 9",
    "sg:city":"Alcala Guadaira",
    "sg:orig_category":"Mercer\u00cda, Lencer\u00cda (al Por Menor)",
    "sg:phone":"+34 955 68 22 08",
    "sg:postcode":"41500",
    "sg:province":"Sevilla",
    "wof:name":"Antonio Mancha S. L.",
    "wof:placetype":"venue"
},
  "geometry": {"coordinates":[-5.8459062576,37.3364067078],"type":"Point"}
}