{
  "type": "Feature",
  "properties": {
    "iso:country":"ES",
    "sg:address":"Carr Onofre Cervero, 4",
    "sg:city":"Lleida",
    "sg:orig_category":"Arquitectos",
    "sg:phone":"+34 973 23 21 95",
    "sg:postcode":"25004",
    "sg:province":"Lleida",
    "wof:name":"Villacampa Blasi Miguel",
    "wof:placetype":"venue"
},
  "geometry": {"coordinates":[0.6219940186,41.6197433472],"type":"Point"}
}