{
  "type": "Feature",
  "properties": {
    "iso:country":"ES",
    "sg:address":"Ctra. Andratx, 66",
    "sg:city":"Peguera",
    "sg:classifiers":[
        {
            "category":"Arts & Performance",
            "subcategory":"Art Gallery",
            "type":"Entertainment"
        }
    ],
    "sg:phone":"+34 971 68 78 14",
    "sg:postcode":"07160",
    "sg:province":"Islas Baleares",
    "sg:tags":[
        "arte",
        "de",
        "galer\u00cdas"
    ],
    "wof:name":"Casta\u00f1o Fondon Pedro",
    "wof:placetype":"venue"
},
  "geometry": {"coordinates":[2.4631509781,39.5322647095],"type":"Point"}
}