{
  "type": "Feature",
  "properties": {
    "iso:country":"ES",
    "sg:address":"Carr Puig, 9",
    "sg:city":"Xativa",
    "sg:orig_category":"Reposter\u00cdas",
    "sg:phone":"+34 962 27 62 91",
    "sg:postcode":"46800",
    "sg:province":"Valencia",
    "wof:name":"Sanvictorino Perez Wenceslao",
    "wof:placetype":"venue"
},
  "geometry": {"coordinates":[-0.5200830102,38.9934272766],"type":"Point"}
}