{
  "type": "Feature",
  "properties": {
    "iso:country":"ES",
    "sg:address":"Calle de Jose Perez Jimenez, 1",
    "sg:city":"Segura Leon",
    "sg:orig_category":"Parafarmacias",
    "sg:phone":"+34 924 70 31 05",
    "sg:postcode":"06270",
    "sg:province":"Badajoz",
    "wof:name":"Rodriguez Armijo Carrera Obdulio",
    "wof:placetype":"venue"
},
  "geometry": {"coordinates":[-6.5279622078,38.1202087402],"type":"Point"}
}