{
  "type": "Feature",
  "properties": {
    "addr:full":"Plaz Cebada, 15 Madrid Madrid 28005",
    "addr:housenumber":"15",
    "addr:postcode":"madrid;28005",
    "addr:street":"Cebada",
    "iso:country":"ES",
    "sg:address":"Plaz Cebada, 15",
    "sg:city":"Madrid",
    "sg:orig_category":"Complementos De Vestir (al Por Menor)",
    "sg:phone":"+34 913 65 60 09",
    "sg:postcode":"28005",
    "sg:province":"Madrid",
    "wof:name":"Garcia Gonzalez Luisa",
    "wof:placetype":"venue"
},
  "geometry": {"coordinates":[-3.7094779015,40.4105453491],"type":"Point"}
}