{
  "type": "Feature",
  "properties": {
    "iso:country":"ES",
    "sg:address":"Pl Clave, 6",
    "sg:city":"Terrassa",
    "sg:orig_category":"Molduras, Junquillos, Listones Y Molduras Perforadas",
    "sg:phone":"+34 937 88 70 54",
    "sg:postcode":"08224",
    "sg:province":"Barcelona",
    "wof:name":"Baumatel S.l.",
    "wof:placetype":"venue"
},
  "geometry": {"coordinates":[1.9906500578,41.5405235291],"type":"Point"}
}