{
  "type": "Feature",
  "properties": {
    "iso:country":"ES",
    "sg:address":"Avda Menendez Pelayo, 75",
    "sg:city":"Madrid",
    "sg:orig_category":"Agentes, Concesionarios Y Sucursales De Veh\u00cdculos",
    "sg:phone":"+34 915 01 68 44",
    "sg:postcode":"28007",
    "sg:province":"Madrid",
    "sg:website":"www.listamotor.com",
    "wof:name":"Lista Motor S.a.",
    "wof:placetype":"venue"
},
  "geometry": {"coordinates":[-3.6765930653,40.4104537964],"type":"Point"}
}