{
  "type": "Feature",
  "properties": {
    "addr:full":"Carrer de Elies Rogent, S/n S. Cugat Valles Barcelona 08172",
    "addr:housenumber":"s",
    "addr:postcode":"08172",
    "addr:street":"Carrer De Elies Rogent;/ N S. Cugat Valles Barcelona",
    "iso:country":"ES",
    "sg:address":"Carrer de Elies Rogent, S/n",
    "sg:city":"S. Cugat Valles",
    "sg:orig_category":"Multimedia: Servicios En L\u00cdnea, Acceso En L\u00cdnea, Cd",
    "sg:phone":"+34 935 90 11 59",
    "sg:postcode":"08172",
    "sg:province":"Barcelona",
    "wof:name":"Iniciativas Terfa S.l",
    "wof:placetype":"venue"
},
  "geometry": {"coordinates":[2.0892550945,41.4712142944],"type":"Point"}
}