{
  "type": "Feature",
  "properties": {
    "iso:country":"ES",
    "sg:address":"G.v. Corts Catalanes, 1176",
    "sg:city":"Barcelona",
    "sg:orig_category":"Transporte En General",
    "sg:phone":"+34 932 78 80 32",
    "sg:postcode":"08020",
    "sg:province":"Barcelona",
    "wof:name":"Logistic Control Management S.l.",
    "wof:placetype":"venue"
},
  "geometry": {"coordinates":[2.2094969749,41.4196624756],"type":"Point"}
}