{
  "type": "Feature",
  "properties": {
    "addr:full":"Carrer de Alcudia, 96 Barcelona Barcelona 08016",
    "addr:housenumber":"96",
    "addr:postcode":"08016",
    "addr:street":"Carrer De Alcudia",
    "iso:country":"ES",
    "sg:address":"Carrer de Alcudia, 96",
    "sg:city":"Barcelona",
    "sg:orig_category":"Ingenier\u00cda, Centros De Estudios (diversos)",
    "sg:phone":"+34 933 59 82 09",
    "sg:postcode":"08016",
    "sg:province":"Barcelona",
    "wof:name":"Tecnologia Ingenieria Y Sistemas S.l.",
    "wof:placetype":"venue"
},
  "geometry": {"coordinates":[2.1758189201,41.4376716614],"type":"Point"}
}