{
  "type": "Feature",
  "properties": {
    "addr:full":"Av Ronda Norte, 23 Picassent Valencia 46220",
    "addr:housenumber":"23",
    "addr:postcode":"46220",
    "addr:street":"Av Ronda Norte",
    "iso:country":"ES",
    "sg:address":"Av Ronda Norte, 23",
    "sg:city":"Picassent",
    "sg:orig_category":"Promotores Constructores",
    "sg:phone":"+34 961 23 52 93",
    "sg:postcode":"46220",
    "sg:province":"Valencia",
    "sg:website":"www.roan.es",
    "wof:name":"Asesoramiento Inmobiliario Roan S.a.",
    "wof:placetype":"venue"
},
  "geometry": {"coordinates":[-0.4974358976,39.3506889343],"type":"Point"}
}