{
  "type": "Feature",
  "properties": {
    "iso:country":"ES",
    "sg:address":"Carr Pare Lluis Rodes, 34",
    "sg:city":"Santa Coloma De Farners",
    "sg:orig_category":"Supermercados Y Hipermercados",
    "sg:phone":"+34 972 84 21 20",
    "sg:postcode":"17430",
    "sg:province":"Girona",
    "wof:name":"Autoservicio Turon Tarres S.l.",
    "wof:placetype":"venue"
},
  "geometry": {"coordinates":[2.6090042591,41.8603363037],"type":"Point"}
}