{
  "type": "Feature",
  "properties": {
    "iso:country":"ES",
    "sg:address":"Calle de Bobuta, 33",
    "sg:city":"Abanilla",
    "sg:orig_category":"Peluqueros: De Se\u00d1oras",
    "sg:phone":"+34 968 68 03 28",
    "sg:postcode":"30640",
    "sg:province":"Murcia",
    "wof:name":"Ramirez Perez Carmelo",
    "wof:placetype":"venue"
},
  "geometry": {"coordinates":[-1.0397150517,38.2063446045],"type":"Point"}
}