{
  "type": "Feature",
  "properties": {
    "iso:country":"ES",
    "sg:address":"Carr Josep Coll, 51",
    "sg:city":"Lloseta",
    "sg:orig_category":"Maquinaria Para Industrias Diversas",
    "sg:phone":"+34 971 87 33 55",
    "sg:postcode":"07360",
    "sg:province":"Islas Baleares",
    "wof:name":"Celaya Prades Vicente",
    "wof:placetype":"venue"
},
  "geometry": {"coordinates":[2.8714189529,39.7208061218],"type":"Point"}
}