{
  "type": "Feature",
  "properties": {
    "iso:country":"ES",
    "sg:address":"Calle de Puerto Oncala, 3",
    "sg:city":"Malaga",
    "sg:orig_category":"Art\u00cdculos De Decoraci\u00d3n",
    "sg:phone":"+34 952 31 06 87",
    "sg:postcode":"29003",
    "sg:province":"M\u00e1laga",
    "wof:name":"Ruiz Ruiz Jose Antonio",
    "wof:placetype":"venue"
},
  "geometry": {"coordinates":[-4.4518370628,36.7009086609],"type":"Point"}
}