{
  "type": "Feature",
  "properties": {
    "iso:country":"ES",
    "sg:address":"Pol Ind Riu Clar, 18",
    "sg:city":"Tarragona",
    "sg:orig_category":"Automatizaci\u00d3n De Procesos Industriales Y De Edificaci\u00d3n (estudios, Instalaci\u00d3n)",
    "sg:phone":"+34 977 20 63 17",
    "sg:postcode":"43006",
    "sg:province":"Tarragona",
    "sg:website":"www.sistec-aut.com",
    "wof:name":"Sistemes Tecnics D Automatitzacio Sociedad Limitada",
    "wof:placetype":"venue"
},
  "geometry": {"coordinates":[1.2209249735,41.1154441833],"type":"Point"}
}