{
  "type": "Feature",
  "properties": {
    "addr:full":"Carrer de Foc Follet, 68 Barcelona Barcelona 08030",
    "addr:housenumber":"68",
    "addr:postcode":"08030",
    "addr:street":"Carrer De Foc Follet",
    "iso:country":"ES",
    "sg:address":"Carrer de Foc Follet, 68",
    "sg:city":"Barcelona",
    "sg:orig_category":"M\u00c1quinas, Material Y Suministros Para Cajas Y Embalajes",
    "sg:phone":"+34 933 13 84 96",
    "sg:postcode":"08030",
    "sg:province":"Barcelona",
    "wof:name":"Serrano Sanchez Jose Antonio",
    "wof:placetype":"venue"
},
  "geometry": {"coordinates":[2.2049179077,41.4344100952],"type":"Point"}
}