{
  "type": "Feature",
  "properties": {
    "addr:full":"Calle de Jose Antonio Noguera Gil, 14 Aguilas Murcia 30880",
    "addr:housenumber":"14",
    "addr:postcode":"30880",
    "addr:street":"Calle De Jose Antonio Noguera Gil",
    "iso:country":"ES",
    "sg:address":"Calle de Jose Antonio Noguera Gil, 14",
    "sg:city":"Aguilas",
    "sg:orig_category":"Fabricaci\u00d3n, Reparaci\u00d3n Y Mantenimiento De Construcciones Navales Y Fluviales",
    "sg:phone":"+34 968 44 78 10",
    "sg:postcode":"30880",
    "sg:province":"Murcia",
    "wof:name":"Talleres Sofer S.l.",
    "wof:placetype":"venue"
},
  "geometry": {"coordinates":[-1.5846780539,37.407119751],"type":"Point"}
}