{
  "type": "Feature",
  "properties": {
    "addr:full":"Calle de Gran Canaria, 54 Pto. Rosario Las Palmas 35600",
    "addr:housenumber":"54",
    "addr:postcode":"35600",
    "addr:street":"Calle De Gran Canaria;Pto. Rosario Las",
    "iso:country":"ES",
    "sg:address":"Calle de Gran Canaria, 54",
    "sg:city":"Pto. Rosario",
    "sg:orig_category":"Ense\u00d1anza Variada",
    "sg:phone":"+34 928 86 10 48",
    "sg:postcode":"35600",
    "sg:province":"Las Palmas",
    "wof:name":"Fuerteventura 2000 S.l.",
    "wof:placetype":"venue"
},
  "geometry": {"coordinates":[-13.8665103912,28.5029182434],"type":"Point"}
}