{
  "type": "Feature",
  "properties": {
    "iso:country":"ES",
    "sg:address":"Luga Ponton De Vaqueros, S/n",
    "sg:city":"Cerde\u00d1o",
    "sg:orig_category":"Empresas De Pintura Y Revestimientos",
    "sg:phone":"+34 985 29 37 40",
    "sg:postcode":"33011",
    "sg:province":"Asturias",
    "wof:name":"Martin Suarez Jose",
    "wof:placetype":"venue"
},
  "geometry": {"coordinates":[-5.8241991997,43.3843231201],"type":"Point"}
}