{
  "type": "Feature",
  "properties": {
    "iso:country":"ES",
    "sg:address":"Generalisimo, 7",
    "sg:city":"Segura Sierra",
    "sg:orig_category":"Supermercados Y Hipermercados",
    "sg:phone":"+34 953 48 03 30",
    "sg:postcode":"23391",
    "sg:province":"Ja\u00e9n",
    "wof:name":"Galiano Peralta Valeriano",
    "wof:placetype":"venue"
},
  "geometry": {"coordinates":[-2.6828589439,38.4163322449],"type":"Point"}
}