{
  "type": "Feature",
  "properties": {
    "iso:country":"ES",
    "sg:address":"Calle de Concepcion Arenal, 25",
    "sg:city":"Guarda",
    "sg:orig_category":"M\u00c9dicos: Estomatolog\u00cda",
    "sg:phone":"+34 986 61 06 43",
    "sg:postcode":"36780",
    "sg:province":"Pontevedra",
    "wof:name":"Coedo Pacheco Rosa Maria",
    "wof:placetype":"venue"
},
  "geometry": {"coordinates":[-8.8712062836,41.9012413025],"type":"Point"}
}