{
  "type": "Feature",
  "properties": {
    "addr:full":"Praz Ferrol (de), 12 Lugo Lugo 27001",
    "addr:housenumber":"12",
    "addr:postcode":"27001",
    "addr:street":"Praz;De",
    "iso:country":"ES",
    "sg:address":"Praz Ferrol (de), 12",
    "sg:city":"Lugo",
    "sg:orig_category":"Carnicer\u00cdas, Carnicer\u00cdas",
    "sg:phone":"+34 982 25 25 44",
    "sg:postcode":"27001",
    "sg:province":"Lugo",
    "wof:name":"Jose Isidro Gancedo Cruz Y Otros Cdad",
    "wof:placetype":"venue"
},
  "geometry": {"coordinates":[-7.5574932098,43.0142555237],"type":"Point"}
}