{
  "type": "Feature",
  "properties": {
    "addr:full":"Avda La Libertad, 12 San Vicente De Barakaldo Vizcaya 48901",
    "addr:housenumber":"12",
    "addr:postcode":"48901",
    "addr:street":"Avda La Libertad",
    "iso:country":"ES",
    "sg:address":"Avda La Libertad, 12",
    "sg:city":"San Vicente De Barakaldo",
    "sg:orig_category":"Colchones (fabricaci\u00d3n, Al Por Mayor, Al Por Menor)",
    "sg:phone":"+34 944 78 16 83",
    "sg:postcode":"48901",
    "sg:province":"Vizcaya",
    "wof:name":"Colchonerias Artea Textil S.l.",
    "wof:placetype":"venue"
},
  "geometry": {"coordinates":[-2.9896540642,43.296131134],"type":"Point"}
}