{
  "type": "Feature",
  "properties": {
    "addr:full":"Plaz Onesimo Redondo, S/n Ramales Victoria Cantabria 39800",
    "addr:housenumber":"/ n",
    "addr:postcode":"39800",
    "addr:street":"Plaz;Redondo S",
    "iso:country":"ES",
    "sg:address":"Plaz Onesimo Redondo, S/n",
    "sg:city":"Ramales Victoria",
    "sg:orig_category":"Mercer\u00cda, Lencer\u00cda (al Por Menor)",
    "sg:phone":"+34 942 64 60 72",
    "sg:postcode":"39800",
    "sg:province":"Cantabria",
    "wof:name":"Gonzalez Borrajo Maria Angeles",
    "wof:placetype":"venue"
},
  "geometry": {"coordinates":[-3.4654049873,43.2575874329],"type":"Point"}
}