{
  "type": "Feature",
  "properties": {
    "addr:full":"Calle de Toledo, 44 Guadalajara Guadalajara 19002",
    "addr:housenumber":"44",
    "addr:postcode":"19002",
    "addr:street":"Calle De Toledo",
    "iso:country":"ES",
    "sg:address":"Calle de Toledo, 44",
    "sg:city":"Guadalajara",
    "sg:orig_category":"Aparcamientos (infraestructuras, Accesorios)",
    "sg:phone":"+34 949 21 79 46",
    "sg:postcode":"19002",
    "sg:province":"Guadalajara",
    "wof:name":"Servicios Sanitarios De Guadalajara S.l.",
    "wof:placetype":"venue"
},
  "geometry": {"coordinates":[-3.159318924,40.6233940125],"type":"Point"}
}