{
  "type": "Feature",
  "properties": {
    "addr:full":"Carrer de Sant Oleguer, 1 Mollet Valles Barcelona 08100",
    "addr:housenumber":"1",
    "addr:postcode":"08100",
    "addr:street":"Carrer De Sant Oleguer",
    "iso:country":"ES",
    "sg:address":"Carrer de Sant Oleguer, 1",
    "sg:city":"Mollet Valles",
    "sg:orig_category":"Silicatos Y Caol\u00cdn",
    "sg:phone":"+34 935 93 00 97",
    "sg:postcode":"08100",
    "sg:province":"Barcelona",
    "wof:name":"Mayol Pi Maria Dolors",
    "wof:placetype":"venue"
},
  "geometry": {"coordinates":[2.2138359547,41.5394325256],"type":"Point"}
}