{
  "type": "Feature",
  "properties": {
    "iso:country":"ES",
    "sg:address":"Calle de Pava, 1",
    "sg:city":"Sevilla",
    "sg:orig_category":"Zapatos (al Por Menor)",
    "sg:phone":"+34 954 61 03 47",
    "sg:postcode":"41012",
    "sg:province":"Sevilla",
    "wof:name":"Fernandez Sanchez Manuel",
    "wof:placetype":"venue"
},
  "geometry": {"coordinates":[-5.9878468513,37.3553504944],"type":"Point"}
}