{
  "type": "Feature",
  "properties": {
    "addr:full":"Avda Miguel Cano, 14 Marbella M\u00e1laga 29600",
    "addr:housenumber":"14",
    "addr:postcode":"29600",
    "addr:street":"Avda Miguel Cano;Ma\u0301Laga",
    "iso:country":"ES",
    "sg:address":"Avda Miguel Cano, 14",
    "sg:city":"Marbella",
    "sg:orig_category":"Oficinas De Cambio",
    "sg:phone":"+34 952 77 51 47",
    "sg:postcode":"29600",
    "sg:province":"M\u00e1laga",
    "wof:name":"Merino Moreno Maria Sonia",
    "wof:placetype":"venue"
},
  "geometry": {"coordinates":[-4.8869380951,36.5082473755],"type":"Point"}
}