{
  "type": "Feature",
  "properties": {
    "iso:country":"ES",
    "sg:address":"Calle de Calvario, 49",
    "sg:city":"Vilalba",
    "sg:orig_category":"Artes Gr\u00c1ficas, Artes Pl\u00c1sticas (curso)",
    "sg:phone":"+34 982 51 19 09",
    "sg:postcode":"27800",
    "sg:province":"Lugo",
    "wof:name":"Artes Graficas Sera S.l.",
    "wof:placetype":"venue"
},
  "geometry": {"coordinates":[-7.6779990196,43.2951469421],"type":"Point"}
}