{
  "type": "Feature",
  "properties": {
    "iso:country":"ES",
    "sg:address":"Calle de Republica Argentina, 56",
    "sg:city":"Jaen",
    "sg:orig_category":"Chapister\u00cda",
    "sg:phone":"+34 953 22 04 32",
    "sg:postcode":"23001",
    "sg:province":"Ja\u00e9n",
    "wof:name":"Lopez Carrascosa Asuncion",
    "wof:placetype":"venue"
},
  "geometry": {"coordinates":[-3.7835988998,37.7741203308],"type":"Point"}
}