{
  "type": "Feature",
  "properties": {
    "addr:full":"Calle de Rioja, 122 Leganes Madrid 28915",
    "addr:housenumber":"122",
    "addr:postcode":"28915",
    "addr:street":"Calle De Rioja",
    "iso:country":"ES",
    "sg:address":"Calle de Rioja, 122",
    "sg:city":"Leganes",
    "sg:classifiers":[
        {
            "category":"Personal",
            "subcategory":"Barber",
            "type":"Services"
        }
    ],
    "sg:phone":"+34 916 86 27 65",
    "sg:postcode":"28915",
    "sg:province":"Madrid",
    "sg:tags":[
        "caballeros",
        "de",
        "peluqueros"
    ],
    "wof:name":"Marco Cabrera Manuel",
    "wof:placetype":"venue"
},
  "geometry": {"coordinates":[-3.7485909462,40.3340606689],"type":"Point"}
}