{
  "type": "Feature",
  "properties": {
    "addr:full":"Calle de Leganes, 1 Navarrevisca \u00c1vila 05115",
    "addr:housenumber":"1",
    "addr:postcode":"05115",
    "addr:street":"Calle De Leganes",
    "iso:country":"ES",
    "sg:address":"Calle de Leganes, 1",
    "sg:city":"Navarrevisca",
    "sg:orig_category":"Centros De Educaci\u00d3n Especial",
    "sg:phone":"+34 920 28 90 13",
    "sg:postcode":"05115",
    "sg:province":"\u00c1vila",
    "wof:name":"Centro Rural Agrupado Alto Alberche",
    "wof:placetype":"venue"
},
  "geometry": {"coordinates":[-4.8939480782,40.3641471863],"type":"Point"}
}