{
  "type": "Feature",
  "properties": {
    "iso:country":"ES",
    "sg:address":"Carrer de Avel.li Xalabarder, 35",
    "sg:city":"Caldes Montbui",
    "sg:orig_category":"Electrodom\u00c9sticos (al Por Menor)",
    "sg:phone":"+34 938 65 37 46",
    "sg:postcode":"08140",
    "sg:province":"Barcelona",
    "sg:website":"www.jbc-disdr.com",
    "wof:name":"Baque Camps S.l.",
    "wof:placetype":"venue"
},
  "geometry": {"coordinates":[2.1688559055,41.6297912598],"type":"Point"}
}