{
  "type": "Feature",
  "properties": {
    "addr:full":"Av Valencia, 6 Molins Rei Barcelona 08750",
    "addr:housenumber":"6",
    "addr:postcode":"08750",
    "addr:street":"Av Valencia;Barcelona",
    "iso:country":"ES",
    "sg:address":"Av Valencia, 6",
    "sg:city":"Molins Rei",
    "sg:orig_category":"M\u00c9dicos: Ginecolog\u00cda Y Obstetricia",
    "sg:phone":"+34 936 68 50 53",
    "sg:postcode":"08750",
    "sg:province":"Barcelona",
    "wof:name":"Mercade Socoro Dionisia",
    "wof:placetype":"venue"
},
  "geometry": {"coordinates":[2.0189290047,41.409954071],"type":"Point"}
}