{
  "type": "Feature",
  "properties": {
    "iso:country":"ES",
    "sg:address":"Avgd Alcalde Recasens, 80",
    "sg:city":"Lleida",
    "sg:orig_category":"Molduras, Junquillos, Listones Y Molduras Perforadas",
    "sg:phone":"+34 973 22 45 98",
    "sg:postcode":"25005",
    "sg:province":"Lleida",
    "wof:name":"Bar Jaif Sl",
    "wof:placetype":"venue"
},
  "geometry": {"coordinates":[0.6326299906,41.6292304993],"type":"Point"}
}