{
  "type": "Feature",
  "properties": {
    "addr:full":"Calle de Doreste Y Molina, S/n Puerto Rico Las Palmas 35130",
    "addr:housenumber":"s / n",
    "addr:postcode":"35130",
    "addr:street":"Calle De Doreste Y Molina;Rico",
    "iso:country":"ES",
    "sg:address":"Calle de Doreste Y Molina, S/n",
    "sg:city":"Puerto Rico",
    "sg:orig_category":"Publicidad (edici\u00d3n)",
    "sg:phone":"+34 928 15 31 58",
    "sg:postcode":"35130",
    "sg:province":"Las Palmas",
    "wof:name":"Kumar  Kamal",
    "wof:placetype":"venue"
},
  "geometry": {"coordinates":[-15.7118616104,27.7871952057],"type":"Point"}
}