{
  "type": "Feature",
  "properties": {
    "iso:country":"ES",
    "sg:address":"Avda Amaia, 2",
    "sg:city":"Leioa",
    "sg:orig_category":"Inform\u00c1tica (estudios, Servicios, Asesor\u00cda, Formaci\u00d3n)",
    "sg:phone":"+34 944 03 89 07",
    "sg:postcode":"48940",
    "sg:province":"Vizcaya",
    "wof:name":"Easo Informatica Soluciones Graficas, S.l.",
    "wof:placetype":"venue"
},
  "geometry": {"coordinates":[-3.0069890022,43.3251419067],"type":"Point"}
}