{
  "type": "Feature",
  "properties": {
    "addr:full":"Calle de Curtidores, 20 Utrera Sevilla 41710",
    "addr:housenumber":"20",
    "addr:postcode":"41710",
    "addr:street":"Calle De Curtidores",
    "iso:country":"ES",
    "sg:address":"Calle de Curtidores, 20",
    "sg:city":"Utrera",
    "sg:orig_category":"Forjas Y Altos Hornos",
    "sg:phone":"+34 954 86 31 09",
    "sg:postcode":"41710",
    "sg:province":"Sevilla",
    "wof:name":"Sanchez Macias Francisco",
    "wof:placetype":"venue"
},
  "geometry": {"coordinates":[-5.7932009697,37.0917663574],"type":"Point"}
}