{
  "type": "Feature",
  "properties": {
    "addr:full":"Calle de Enmedio, 31 Costur Castell\u00f3n 12119",
    "addr:housenumber":"31",
    "addr:postcode":"12119",
    "addr:street":"Calle De Enmedio;Castello\u0301N",
    "iso:country":"ES",
    "sg:address":"Calle de Enmedio, 31",
    "sg:city":"Costur",
    "sg:orig_category":"Cajas Para Embalar",
    "sg:phone":"+34 964 38 80 73",
    "sg:postcode":"12119",
    "sg:province":"Castell\u00f3n",
    "wof:name":"Caja Rural Del Mediterraneo Ruralcaja S Coop De Credito",
    "wof:placetype":"venue"
},
  "geometry": {"coordinates":[-0.1735350043,40.1200408936],"type":"Point"}
}