{
  "type": "Feature",
  "properties": {
    "addr:full":"Trva Norias, 4 Navalcan Toledo 45610",
    "addr:housenumber":"4",
    "addr:postcode":"45610",
    "addr:street":"Trva Norias",
    "iso:country":"ES",
    "sg:address":"Trva Norias, 4",
    "sg:city":"Navalcan",
    "sg:orig_category":"Supermercados Y Hipermercados",
    "sg:phone":"+34 925 84 46 16",
    "sg:postcode":"45610",
    "sg:province":"Toledo",
    "wof:name":"Iglesias Garcia Jose Manuel",
    "wof:placetype":"venue"
},
  "geometry": {"coordinates":[-5.0958828926,40.0696640015],"type":"Point"}
}