{
  "type": "Feature",
  "properties": {
    "addr:full":"Calle de Rudiana, 28 Tarazona Zaragoza 50500",
    "addr:housenumber":"28",
    "addr:postcode":"50500",
    "addr:street":"Calle De Rudiana",
    "iso:country":"ES",
    "sg:address":"Calle de Rudiana, 28",
    "sg:city":"Tarazona",
    "sg:orig_category":"Electrodom\u00c9sticos (al Por Menor)",
    "sg:phone":"+34 976 64 13 41",
    "sg:postcode":"50500",
    "sg:province":"Zaragoza",
    "wof:name":"Electrodomesticos Yecora S.l.",
    "wof:placetype":"venue"
},
  "geometry": {"coordinates":[-1.7244240046,41.909450531],"type":"Point"}
}