{
  "type": "Feature",
  "properties": {
    "addr:full":"Doctor Fleming, S/n Campillo Salvatierra Salamanca 37778",
    "addr:housenumber":"s / n",
    "addr:postcode":"37778",
    "addr:street":"Doctor Fleming",
    "iso:country":"ES",
    "sg:address":"Doctor Fleming, S/n",
    "sg:city":"Campillo Salvatierra",
    "sg:orig_category":"Mataderos Y Talleres De Despiezado",
    "sg:phone":"+34 923 58 01 41",
    "sg:postcode":"37778",
    "sg:province":"Salamanca",
    "sg:website":"www.paginasamarillas.es/on/line/isaiashvaras",
    "wof:name":"Isaias Hernandez Varas S.l.",
    "wof:placetype":"venue"
},
  "geometry": {"coordinates":[-5.676940918,40.5710067749],"type":"Point"}
}