{
  "type": "Feature",
  "properties": {
    "addr:full":"Calle de General Vives Camino, S/n Guadalajara Guadalajara 19003",
    "addr:postcode":"19003",
    "addr:street":"Calle De General Vives Camino S / N",
    "iso:country":"ES",
    "sg:address":"Calle de General Vives Camino, S/n",
    "sg:city":"Guadalajara",
    "sg:orig_category":"Caf\u00c9s, Bares, Cervecer\u00cdas",
    "sg:phone":"+34 949 23 09 77",
    "sg:postcode":"19003",
    "sg:province":"Guadalajara",
    "wof:name":"Perez Duarte Jesus",
    "wof:placetype":"venue"
},
  "geometry": {"coordinates":[-3.1792631149,40.6286430359],"type":"Point"}
}