{
  "type": "Feature",
  "properties": {
    "iso:country":"ES",
    "sg:address":"Avda Castilla (de), 2",
    "sg:city":"Poligono De San Fernando De Henares",
    "sg:orig_category":"Filtros Y Elementos Filtradores",
    "sg:phone":"+34 916 76 86 68",
    "sg:postcode":"28830",
    "sg:province":"Madrid",
    "wof:name":"Donaldson Iberica Soluciones En Filtracion, S.l.",
    "wof:placetype":"venue"
},
  "geometry": {"coordinates":[-3.5104780197,40.4524345398],"type":"Point"}
}