{
  "type": "Feature",
  "properties": {
    "iso:country":"ES",
    "sg:address":"Calle de Sevilla, 10",
    "sg:city":"Santos De Maimona",
    "sg:orig_category":"Bisuter\u00cda, Joyer\u00cda, Relojer\u00cda (al Por Menor)",
    "sg:phone":"+34 924 57 12 84",
    "sg:postcode":"06230",
    "sg:province":"Badajoz",
    "wof:name":"Barros Gonzalez Dolores",
    "wof:placetype":"venue"
},
  "geometry": {"coordinates":[-6.3826389313,38.4493484497],"type":"Point"}
}