{
  "type": "Feature",
  "properties": {
    "addr:full":"Mlle Poniente, S/n Alacant Alicante 03001",
    "addr:housenumber":"s / n",
    "addr:postcode":"03001",
    "addr:street":"Mlle Poniente",
    "iso:country":"ES",
    "sg:address":"Mlle Poniente, S/n",
    "sg:city":"Alacant",
    "sg:orig_category":"Delegados, Agentes De Tr\u00c1nsito, Auxiliares De Transporte Internacional",
    "sg:phone":"+34 965 13 12 46",
    "sg:postcode":"03001",
    "sg:province":"Alicante",
    "wof:name":"Navitrans S.coop.v.",
    "wof:placetype":"venue"
},
  "geometry": {"coordinates":[-0.4804739952,38.3440856934],"type":"Point"}
}