{
  "type": "Feature",
  "properties": {
    "iso:country":"ES",
    "sg:address":"Calle de Gordoniz, 74",
    "sg:city":"Bilbao",
    "sg:orig_category":"Inmobiliaria (agencias)",
    "sg:phone":"+34 944 10 60 54",
    "sg:postcode":"48002",
    "sg:province":"Vizcaya",
    "sg:website":"www.vascasa.com",
    "wof:name":"Gestion Inmobiliaria Gordoniz S.l.",
    "wof:placetype":"venue"
},
  "geometry": {"coordinates":[-2.9466638565,43.2511138916],"type":"Point"}
}