{
  "type": "Feature",
  "properties": {
    "addr:full":"Calle de Adora, 9 Madrid Madrid 28041",
    "addr:housenumber":"9",
    "addr:postcode":"madrid;28041",
    "addr:street":"Calle De Adora",
    "iso:country":"ES",
    "sg:address":"Calle de Adora, 9",
    "sg:city":"Madrid",
    "sg:orig_category":"Asociaciones Humanitarias, De Cooperaci\u00d3n, De Acci\u00d3n Social",
    "sg:phone":"+34 917 92 15 62",
    "sg:postcode":"28041",
    "sg:province":"Madrid",
    "wof:name":"Asociacion Fantid San Fermin",
    "wof:placetype":"venue"
},
  "geometry": {"coordinates":[-3.6889815331,40.3692092896],"type":"Point"}
}