{
  "type": "Feature",
  "properties": {
    "iso:country":"ES",
    "sg:address":"Av Terra Alta (de La), 36",
    "sg:city":"Batea",
    "sg:orig_category":"Arquitectos",
    "sg:phone":"+34 977 43 05 43",
    "sg:postcode":"43786",
    "sg:province":"Tarragona",
    "wof:name":"Ferrus Ferre Joaquim",
    "wof:placetype":"venue"
},
  "geometry": {"coordinates":[0.3128690124,41.0936012268],"type":"Point"}
}