{
  "type": "Feature",
  "properties": {
    "iso:country":"ES",
    "sg:address":"Carrer de Santa Teresa, 48",
    "sg:city":"Mataro",
    "sg:orig_category":"Panader\u00cdas, Panader\u00cdas",
    "sg:phone":"+34 937 90 17 26",
    "sg:postcode":"08302",
    "sg:province":"Barcelona",
    "wof:name":"Oms Fontanals Carlos",
    "wof:placetype":"venue"
},
  "geometry": {"coordinates":[2.444396019,41.5378227234],"type":"Point"}
}