{
  "type": "Feature",
  "properties": {
    "addr:full":"Avda Juan Pablo Ii, 25 Pozuelo De Alarcon Madrid 28224",
    "addr:housenumber":"25",
    "addr:postcode":"28224",
    "addr:street":"Avda Juan Pablo Ii",
    "iso:country":"ES",
    "sg:address":"Avda Juan Pablo Ii, 25",
    "sg:city":"Pozuelo De Alarcon",
    "sg:orig_category":"M\u00c9dicos: Estomatolog\u00cda",
    "sg:phone":"+34 913 52 61 26",
    "sg:postcode":"28224",
    "sg:province":"Madrid",
    "wof:name":"Fernandez Ateca Bego\u00f1a",
    "wof:placetype":"venue"
},
  "geometry": {"coordinates":[-3.8036990166,40.4464416504],"type":"Point"}
}