{
  "type": "Feature",
  "properties": {
    "addr:full":"G.v. Fernando El Catolico, 12 Valencia Valencia 46008",
    "addr:housenumber":"12",
    "addr:postcode":"46008",
    "addr:street":"Fernando El Catolico",
    "iso:country":"ES",
    "sg:address":"G.v. Fernando El Catolico, 12",
    "sg:city":"Valencia",
    "sg:orig_category":"Librer\u00cdas",
    "sg:phone":"+34 963 91 14 94",
    "sg:postcode":"46008",
    "sg:province":"Valencia",
    "wof:name":"Izquierdo Izquierdo Florentino",
    "wof:placetype":"venue"
},
  "geometry": {"coordinates":[-0.3848040104,39.4705886841],"type":"Point"}
}