{
  "type": "Feature",
  "properties": {
    "iso:country":"ES",
    "sg:address":"Calle de Moratin, 14",
    "sg:city":"Valencia",
    "sg:classifiers":[
        {
            "category":"Manufacturing",
            "subcategory":"Building Materials",
            "type":"Manufacturing & Wholesale Goods"
        }
    ],
    "sg:phone":"+34 963 53 06 64",
    "sg:postcode":"46002",
    "sg:province":"Valencia",
    "sg:tags":[
        "cemento",
        "y",
        "de",
        "fabricaci\u00d3n",
        "cal"
    ],
    "wof:name":"Rodio Cimentaciones Especiales S.a.",
    "wof:placetype":"venue"
},
  "geometry": {"coordinates":[-0.3757539988,39.4704627991],"type":"Point"}
}