{
  "type": "Feature",
  "properties": {
    "iso:country":"ES",
    "sg:address":"Calle de Blas Infante, S/n",
    "sg:city":"Alameda",
    "sg:orig_category":"Negocio De Materiales De Construcci\u00d3n",
    "sg:phone":"+34 952 71 10 65",
    "sg:postcode":"29530",
    "sg:province":"M\u00e1laga",
    "wof:name":"Varo Y Pozo 1991 Sl",
    "wof:placetype":"venue"
},
  "geometry": {"coordinates":[-4.6526989937,37.2073135376],"type":"Point"}
}