{
  "type": "Feature",
  "properties": {
    "iso:country":"ES",
    "sg:address":"Ctra Malaga, 19",
    "sg:city":"Algeciras",
    "sg:orig_category":"Ense\u00d1anza Variada",
    "sg:phone":"+34 956 65 01 00",
    "sg:postcode":"11203",
    "sg:province":"C\u00e1diz",
    "wof:name":"Junta De Andalucia",
    "wof:placetype":"venue"
},
  "geometry": {"coordinates":[-5.4526491165,36.1276016235],"type":"Point"}
}