{
  "type": "Feature",
  "properties": {
    "addr:full":"Avda Antonio Trueba, 1 San Juan De Muskiz Vizcaya 48550",
    "addr:housenumber":"1",
    "addr:postcode":"48550",
    "addr:street":"Avda Antonio Trueba",
    "iso:country":"ES",
    "sg:address":"Avda Antonio Trueba, 1",
    "sg:city":"San Juan De Muskiz",
    "sg:orig_category":"M\u00c9dicos: Estomatolog\u00cda",
    "sg:phone":"+34 946 70 76 00",
    "sg:postcode":"48550",
    "sg:province":"Vizcaya",
    "wof:name":"Diez Rojo Eduardo",
    "wof:placetype":"venue"
},
  "geometry": {"coordinates":[-3.1139039993,43.3222846985],"type":"Point"}
}