{
  "type": "Feature",
  "properties": {
    "addr:full":"Poligono Industrial, S/n Ribaforada Navarra 31550",
    "addr:postcode":"31550",
    "addr:street":"Industrial S / N",
    "iso:country":"ES",
    "sg:address":"Poligono Industrial, S/n",
    "sg:city":"Ribaforada",
    "sg:orig_category":"Frutas Y Legumbres Frescas (al Por Mayor)",
    "sg:phone":"+34 948 86 45 01",
    "sg:postcode":"31550",
    "sg:province":"Navarra",
    "wof:name":"Jacinto Rosario Y Maria Pilar Huguet Perez S.cv.",
    "wof:placetype":"venue"
},
  "geometry": {"coordinates":[-1.5151189566,41.9949760437],"type":"Point"}
}