{
  "type": "Feature",
  "properties": {
    "addr:full":"Rua Fonte (da), 27 Becerrea Lugo 27640",
    "addr:housenumber":"27",
    "addr:postcode":"27640",
    "addr:street":"Rua Fonte Da",
    "iso:country":"ES",
    "sg:address":"Rua Fonte (da), 27",
    "sg:city":"Becerrea",
    "sg:orig_category":"Carnicer\u00cdas, Carnicer\u00cdas",
    "sg:phone":"+34 982 36 01 06",
    "sg:postcode":"27640",
    "sg:province":"Lugo",
    "wof:name":"Arias Vilares Jesus",
    "wof:placetype":"venue"
},
  "geometry": {"coordinates":[-7.1653113365,42.8559989929],"type":"Point"}
}