{
  "type": "Feature",
  "properties": {
    "addr:full":"Calle de San Francisco, 23 Burlada Navarra 31600",
    "addr:housenumber":"23",
    "addr:postcode":"31600",
    "addr:street":"Calle De San Francisco",
    "iso:country":"ES",
    "sg:address":"Calle de San Francisco, 23",
    "sg:city":"Burlada",
    "sg:orig_category":"Molduras, Junquillos, Listones Y Molduras Perforadas",
    "sg:phone":"+34 948 24 33 99",
    "sg:postcode":"31600",
    "sg:province":"Navarra",
    "wof:name":"Martinez Arias Nicomedes",
    "wof:placetype":"venue"
},
  "geometry": {"coordinates":[-1.6148190498,42.82289505],"type":"Point"}
}