{
  "type": "Feature",
  "properties": {
    "iso:country":"ES",
    "sg:address":"Rua Falperra, 37",
    "sg:city":"Vigo",
    "sg:orig_category":"Imprenta",
    "sg:phone":"+34 986 43 89 41",
    "sg:postcode":"36202",
    "sg:province":"Pontevedra",
    "wof:name":"Diaz Martinez Herminio",
    "wof:placetype":"venue"
},
  "geometry": {"coordinates":[-8.7283935547,42.2347450256],"type":"Point"}
}