{
  "type": "Feature",
  "properties": {
    "iso:country":"ES",
    "sg:address":"Carr Raiers, 15",
    "sg:city":"Pobla Segur",
    "sg:orig_category":"Cr\u00cda De Animales",
    "sg:phone":"+34 973 68 02 19",
    "sg:postcode":"25500",
    "sg:province":"Lleida",
    "wof:name":"Gordo S.a.t.",
    "wof:placetype":"venue"
},
  "geometry": {"coordinates":[0.9664350152,42.2486915588],"type":"Point"}
}