{
  "type": "Feature",
  "properties": {
    "addr:full":"Carr Masarrochos, 2 Moncada Valencia 46113",
    "addr:housenumber":"2",
    "addr:postcode":"46113",
    "addr:street":"Carr Masarrochos",
    "iso:country":"ES",
    "sg:address":"Carr Masarrochos, 2",
    "sg:city":"Moncada",
    "sg:orig_category":"Ferreter\u00cda (diversos)",
    "sg:phone":"+34 961 39 16 45",
    "sg:postcode":"46113",
    "sg:province":"Valencia",
    "wof:name":"Morello Martinez Vicente",
    "wof:placetype":"venue"
},
  "geometry": {"coordinates":[-0.3987019956,39.5433235168],"type":"Point"}
}