{
  "type": "Feature",
  "properties": {
    "addr:full":"Rbla Volart, 68 Barcelona Barcelona 08041",
    "addr:housenumber":"68",
    "addr:postcode":"08041",
    "addr:street":"Rbla Volart",
    "iso:country":"ES",
    "sg:address":"Rbla Volart, 68",
    "sg:city":"Barcelona",
    "sg:orig_category":"Pintores",
    "sg:phone":"+34 934 55 08 62",
    "sg:postcode":"08041",
    "sg:province":"Barcelona",
    "wof:name":"Lleo Sanchez Juan",
    "wof:placetype":"venue"
},
  "geometry": {"coordinates":[2.1760869026,41.4171943665],"type":"Point"}
}