{
  "type": "Feature",
  "properties": {
    "iso:country":"ES",
    "sg:address":"Urpal, S/n",
    "sg:city":"Bre\u00f1a Alta",
    "sg:orig_category":"Electricidad: Equipos Industriales, Componentes (fabricaci\u00d3n)",
    "sg:phone":"+34 922 41 24 83",
    "sg:postcode":"38710",
    "sg:province":"Santa Cruz De Tenerife",
    "wof:name":"Comercial Electrica Canarias S. A.",
    "wof:placetype":"venue"
},
  "geometry": {"coordinates":[-17.7874984741,28.6631908417],"type":"Point"}
}