{
  "type": "Feature",
  "properties": {
    "addr:full":"Carr Pare Coll, 9 Girona Girona 17005",
    "addr:housenumber":"9",
    "addr:postcode":"17005",
    "addr:street":"Carr Pare Coll",
    "iso:country":"ES",
    "sg:address":"Carr Pare Coll, 9",
    "sg:city":"Girona",
    "sg:orig_category":"Asesor\u00cda Sobre Comunicaci\u00d3n De Empresas",
    "sg:phone":"+34 972 24 41 26",
    "sg:postcode":"17005",
    "sg:province":"Girona",
    "wof:name":"Seitem S.l.",
    "wof:placetype":"venue"
},
  "geometry": {"coordinates":[2.8123979568,41.9778671265],"type":"Point"}
}