{
  "type": "Feature",
  "properties": {
    "iso:country":"ES",
    "sg:address":"Carr Estany Petit, 26",
    "sg:city":"Platja D'alcudia",
    "sg:orig_category":"Parques De Atracciones Y Centros De Esparcimiento",
    "sg:phone":"+34 971 89 28 12",
    "sg:postcode":"07408",
    "sg:province":"Islas Baleares",
    "wof:name":"Recreativos Domenech S.l.",
    "wof:placetype":"venue"
},
  "geometry": {"coordinates":[3.1100409031,39.8356018066],"type":"Point"}
}