{
  "type": "Feature",
  "properties": {
    "iso:country":"ES",
    "sg:address":"Polig. Pocomaco, S/n",
    "sg:city":"A Coru\u00f1a",
    "sg:orig_category":"Negocio De Materiales De Construcci\u00d3n",
    "sg:phone":"+34 981 17 09 83",
    "sg:postcode":"15190",
    "sg:province":"La Coru\u00f1a",
    "sg:website":"www.ariasnadela.com",
    "wof:name":"Arias Nadela S. L.",
    "wof:placetype":"venue"
},
  "geometry": {"coordinates":[-8.4335021973,43.3301010132],"type":"Point"}
}