{
  "type": "Feature",
  "properties": {
    "addr:full":"Pl. Ayuntamiento, S/n Laracha La Coru\u00f1a 15145",
    "addr:housenumber":"/ n",
    "addr:postcode":"15145",
    "addr:street":"Ayuntamiento S;La Corun\u0303A",
    "iso:country":"ES",
    "sg:address":"Pl. Ayuntamiento, S/n",
    "sg:city":"Laracha",
    "sg:classifiers":[
        {
            "category":"Taxi",
            "type":"Transportation"
        }
    ],
    "sg:phone":"+34 981 60 50 84",
    "sg:postcode":"15145",
    "sg:province":"La Coru\u00f1a",
    "wof:name":"Asociacion De Auto-turismo",
    "wof:placetype":"venue"
},
  "geometry": {"coordinates":[-8.5844688416,43.2523193359],"type":"Point"}
}