{
  "type": "Feature",
  "properties": {
    "addr:full":"Calle de Pesquero Joven Alonso, S/n Barbate C\u00e1diz 11160",
    "addr:housenumber":"s / n",
    "addr:postcode":"11160",
    "addr:street":"Calle De",
    "iso:country":"ES",
    "sg:address":"Calle de Pesquero Joven Alonso, S/n",
    "sg:city":"Barbate",
    "sg:orig_category":"Guarder\u00cdas",
    "sg:phone":"+34 956 43 23 01",
    "sg:postcode":"11160",
    "sg:province":"C\u00e1diz",
    "wof:name":"Instituto Social De La Marina-guarderia Infantil",
    "wof:placetype":"venue"
},
  "geometry": {"coordinates":[-5.9146790504,36.195110321],"type":"Point"}
}