{
  "type": "Feature",
  "properties": {
    "iso:country":"ES",
    "sg:address":"Urb Pe\u00f1ismar, 3",
    "sg:city":"Pe\u00f1iscola",
    "sg:orig_category":"Bisuter\u00cda, Joyer\u00cda, Relojer\u00cda (al Por Menor)",
    "sg:phone":"+34 964 48 16 48",
    "sg:postcode":"12598",
    "sg:province":"Castell\u00f3n",
    "wof:name":"Garcia Prat Jose Vicente",
    "wof:placetype":"venue"
},
  "geometry": {"coordinates":[-0.0360242017,39.9860687256],"type":"Point"}
}