{
  "type": "Feature",
  "properties": {
    "iso:country":"ES",
    "sg:address":"Calle de Camino Del Norte, S/n",
    "sg:city":"Alcora",
    "sg:orig_category":"Cerrajer\u00cda, Ferrallista",
    "sg:phone":"+34 964 36 04 53",
    "sg:postcode":"12110",
    "sg:province":"Castell\u00f3n",
    "wof:name":"Aparici Puerto Juan Antonio",
    "wof:placetype":"venue"
},
  "geometry": {"coordinates":[-0.215545997,40.0709190369],"type":"Point"}
}