{
  "type": "Feature",
  "properties": {
    "addr:full":"Calle de Rodolfo Gil, 96 Puente-genil C\u00f3rdoba 14500",
    "addr:housenumber":"96",
    "addr:postcode":"14500",
    "addr:street":"Calle De Rodolfo Gil;Co\u0301Rdoba",
    "iso:country":"ES",
    "sg:address":"Calle de Rodolfo Gil, 96",
    "sg:city":"Puente-genil",
    "sg:orig_category":"Reposter\u00cdas",
    "sg:phone":"+34 957 60 71 98",
    "sg:postcode":"14500",
    "sg:province":"C\u00f3rdoba",
    "wof:name":"Aguilar Bernabe Manuel Jose",
    "wof:placetype":"venue"
},
  "geometry": {"coordinates":[-4.7655301094,37.3867912292],"type":"Point"}
}