{
  "type": "Feature",
  "properties": {
    "addr:full":"Ctra Rodilana, 10 Medina Campo Valladolid 47400",
    "addr:housenumber":"10",
    "addr:postcode":"47400",
    "addr:street":"Ctra Rodilana",
    "iso:country":"ES",
    "sg:address":"Ctra Rodilana, 10",
    "sg:city":"Medina Campo",
    "sg:orig_category":"Electricidad: Instaladores",
    "sg:phone":"+34 983 80 28 02",
    "sg:postcode":"47400",
    "sg:province":"Valladolid",
    "wof:name":"Electro Castilla 2000 S.l.",
    "wof:placetype":"venue"
},
  "geometry": {"coordinates":[-4.9011888504,41.3371200562],"type":"Point"}
}