{
  "type": "Feature",
  "properties": {
    "addr:full":"Avenida De Pio Xii, 20 Albox Almer\u00eda 04800",
    "addr:housenumber":"20",
    "addr:postcode":"04800",
    "addr:street":"Avenida De Pio Xii",
    "iso:country":"ES",
    "sg:address":"Avenida De Pio Xii, 20",
    "sg:city":"Albox",
    "sg:orig_category":"Mec\u00c1nico Del Autom\u00d3vil",
    "sg:phone":"+34 950 43 02 37",
    "sg:postcode":"04800",
    "sg:province":"Almer\u00eda",
    "wof:name":"Gimenez Sanz Juan",
    "wof:placetype":"venue"
},
  "geometry": {"coordinates":[-2.1477179527,37.3870925903],"type":"Point"}
}