{
  "type": "Feature",
  "properties": {
    "iso:country":"ES",
    "sg:address":"Calle de Pizarro, 8",
    "sg:city":"Poligono Industrial Los Villares",
    "sg:orig_category":"Mudanzas",
    "sg:phone":"+34 923 12 39 59",
    "sg:postcode":"37184",
    "sg:province":"Salamanca",
    "wof:name":"Mudanzas Tormes S.l.",
    "wof:placetype":"venue"
},
  "geometry": {"coordinates":[-5.6336789131,40.9948005676],"type":"Point"}
}