{
  "type": "Feature",
  "properties": {
    "iso:country":"ES",
    "sg:address":"Av Coronel Molera, 7",
    "sg:city":"Puigcerda",
    "sg:orig_category":"Publicidad (soportes Y Gesti\u00d3n)",
    "sg:phone":"+34 972 88 24 72",
    "sg:postcode":"17520",
    "sg:province":"Girona",
    "wof:name":"Flaujat Vianya Margarita",
    "wof:placetype":"venue"
},
  "geometry": {"coordinates":[1.9282900095,42.4334907532],"type":"Point"}
}