{
  "type": "Feature",
  "properties": {
    "iso:country":"ES",
    "sg:address":"Santa Mar\u00eda De Mellid, S/n",
    "sg:city":"Melide",
    "sg:orig_category":"Molduras, Junquillos, Listones Y Molduras Perforadas",
    "sg:phone":"+34 981 50 75 43",
    "sg:postcode":"15800",
    "sg:province":"La Coru\u00f1a",
    "wof:name":"Garcia Sanchez Manuel",
    "wof:placetype":"venue"
},
  "geometry": {"coordinates":[-8.0165987015,42.9150886536],"type":"Point"}
}