{
  "type": "Feature",
  "properties": {
    "addr:full":"Ctra Coin, 36 Cortijo De Maza-el Olivar M\u00e1laga 29140",
    "addr:housenumber":"36",
    "addr:postcode":"29140",
    "addr:street":"Ctra Coin;Ma\u0301Laga",
    "iso:country":"ES",
    "sg:address":"Ctra Coin, 36",
    "sg:city":"Cortijo De Maza-el Olivar",
    "sg:orig_category":"Venta De Caravanas, Casas M\u00d3viles, Camping",
    "sg:phone":"+34 952 62 15 72",
    "sg:postcode":"29140",
    "sg:province":"M\u00e1laga",
    "wof:name":"Caravanas Y Remolques Cardona S.l.",
    "wof:placetype":"venue"
},
  "geometry": {"coordinates":[-4.4937429428,36.6597900391],"type":"Point"}
}