{
  "type": "Feature",
  "properties": {
    "addr:full":"Calle de Baratzategi, 29 Donostia-san Sebastian Guip\u00f9zcoa 20015",
    "addr:housenumber":"29",
    "addr:postcode":"20015",
    "addr:street":"Calle De Baratzategi",
    "iso:country":"ES",
    "sg:address":"Calle de Baratzategi, 29",
    "sg:city":"Donostia-san Sebastian",
    "sg:orig_category":"Molduras, Junquillos, Listones Y Molduras Perforadas",
    "sg:phone":"+34 943 29 23 59",
    "sg:postcode":"20015",
    "sg:province":"Guip\u00f9zcoa",
    "wof:name":"Arturo Manchado Lozano",
    "wof:placetype":"venue"
},
  "geometry": {"coordinates":[-1.9513748884,43.3128166199],"type":"Point"}
}