{
  "type": "Feature",
  "properties": {
    "iso:country":"ES",
    "sg:address":"Calle de Sierra Toledana, 25",
    "sg:city":"Madrid",
    "sg:classifiers":[
        {
            "category":"Autos & Motor Vehicles",
            "subcategory":"Automobile Sales",
            "type":"Retail Goods"
        }
    ],
    "sg:phone":"+34 914 37 60 84",
    "sg:postcode":"28038",
    "sg:province":"Madrid",
    "wof:name":"Autoescuelas Hermanos Justo S.l.",
    "wof:placetype":"venue"
},
  "geometry": {"coordinates":[-3.6602692604,40.4018821716],"type":"Point"}
}