{
  "type": "Feature",
  "properties": {
    "iso:country":"ES",
    "sg:address":"Ctra. La Pobla-vilallonga, S/n",
    "sg:city":"El Morell",
    "sg:orig_category":"Delegados, Agentes De Tr\u00c1nsito, Auxiliares De Transporte Internacional",
    "sg:phone":"+34 977 84 29 34",
    "sg:postcode":"43760",
    "sg:province":"Tarragona",
    "wof:name":"Camiones Grua Simon S.l.",
    "wof:placetype":"venue"
},
  "geometry": {"coordinates":[1.2065999508,41.1918067932],"type":"Point"}
}