{
  "type": "Feature",
  "properties": {
    "iso:country":"ES",
    "sg:address":"Rua Colon, 10",
    "sg:city":"Vigo",
    "sg:orig_category":"Abogados",
    "sg:phone":"+34 986 44 93 00",
    "sg:postcode":"36201",
    "sg:province":"Pontevedra",
    "wof:name":"Cuatrecasas Abogados Srl",
    "wof:placetype":"venue"
},
  "geometry": {"coordinates":[-8.7204866409,42.2381057739],"type":"Point"}
}