{
  "type": "Feature",
  "properties": {
    "addr:full":"Calle de Antonio Machado, 9 Albacete Albacete 02003",
    "addr:housenumber":"9",
    "addr:postcode":"02003",
    "addr:street":"Calle De Antonio Machado",
    "iso:country":"ES",
    "sg:address":"Calle de Antonio Machado, 9",
    "sg:city":"Albacete",
    "sg:orig_category":"Ingenier\u00cda, Centros De Estudios (diversos)",
    "sg:phone":"+34 967 23 82 67",
    "sg:postcode":"02003",
    "sg:province":"Albacete",
    "wof:name":"Artigao Ramirez Alfonso",
    "wof:placetype":"venue"
},
  "geometry": {"coordinates":[-1.8591175079,38.9888687134],"type":"Point"}
}