{
  "type": "Feature",
  "properties": {
    "addr:full":"Calle de Marques De Murrieta, 24 Logro\u00f1o La Rioja 26005",
    "addr:housenumber":"24",
    "addr:postcode":"26005",
    "addr:street":"Calle De Marques De Murrieta;Rioja",
    "iso:country":"ES",
    "sg:address":"Calle de Marques De Murrieta, 24",
    "sg:city":"Logro\u00f1o",
    "sg:orig_category":"Inmobiliaria (agencias)",
    "sg:phone":"+34 941 20 81 59",
    "sg:postcode":"26005",
    "sg:province":"La Rioja",
    "wof:name":"Fincas Corral S.l.",
    "wof:placetype":"venue"
},
  "geometry": {"coordinates":[-2.4543159008,42.4654426575],"type":"Point"}
}