{
  "type": "Feature",
  "properties": {
    "iso:country":"ES",
    "sg:address":"Calle de Augusto Figueroa, 13",
    "sg:city":"Madrid",
    "sg:orig_category":"Alimentaci\u00d3n General (al Por Menor)",
    "sg:phone":"+34 915 31 69 21",
    "sg:postcode":"28004",
    "sg:province":"Madrid",
    "wof:name":"Jin  Cheng Qui",
    "wof:placetype":"venue"
},
  "geometry": {"coordinates":[-3.6996924877,40.4228286743],"type":"Point"}
}