{
  "type": "Feature",
  "properties": {
    "addr:full":"Calle de Juan De Castilla, 4 Palencia Palencia 34001",
    "addr:housenumber":"4",
    "addr:postcode":"34001",
    "addr:street":"Calle De Juan De Castilla",
    "iso:country":"ES",
    "sg:address":"Calle de Juan De Castilla, 4",
    "sg:city":"Palencia",
    "sg:orig_category":"Promotores Constructores",
    "sg:phone":"+34 979 70 65 91",
    "sg:postcode":"34001",
    "sg:province":"Palencia",
    "wof:name":"Construcciones Cisneros Castilla 2000 S.l.",
    "wof:placetype":"venue"
},
  "geometry": {"coordinates":[-4.5351581573,42.0116043091],"type":"Point"}
}