{
  "type": "Feature",
  "properties": {
    "iso:country":"ES",
    "sg:address":"Carrer de Bertran I Musitu, 40",
    "sg:city":"Viladecans",
    "sg:orig_category":"Loter\u00cda Y T\u00d3mbola",
    "sg:phone":"+34 936 37 53 39",
    "sg:postcode":"08840",
    "sg:province":"Barcelona",
    "wof:name":"Campama Tugas Montserrat",
    "wof:placetype":"venue"
},
  "geometry": {"coordinates":[2.024586916,41.3164367676],"type":"Point"}
}