{
  "type": "Feature",
  "properties": {
    "iso:country":"ES",
    "sg:address":"Avda Oviedo, 70",
    "sg:city":"Lugones",
    "sg:orig_category":"Asesor\u00cda Sobre Comunicaci\u00d3n De Empresas",
    "sg:phone":"+34 985 26 63 28",
    "sg:postcode":"33420",
    "sg:province":"Asturias",
    "wof:name":"Asociacion Euroforo De Emprendedores Empresariales Asturias 2000",
    "wof:placetype":"venue"
},
  "geometry": {"coordinates":[-5.8102478981,43.4013710022],"type":"Point"}
}