{
  "type": "Feature",
  "properties": {
    "addr:full":"Calle de L'horteta, 7 Rafelbunyol Valencia 46138",
    "addr:housenumber":"7",
    "addr:postcode":"46138",
    "addr:street":"Calle De L'Horteta",
    "iso:country":"ES",
    "sg:address":"Calle de L'horteta, 7",
    "sg:city":"Rafelbunyol",
    "sg:orig_category":"Diarios, Revistas Y Boletines (suscripciones)",
    "sg:phone":"+34 961 41 22 89",
    "sg:postcode":"46138",
    "sg:province":"Valencia",
    "wof:name":"Comercial Distribuidora Magazine S. A.",
    "wof:placetype":"venue"
},
  "geometry": {"coordinates":[-0.3235799968,39.5853652954],"type":"Point"}
}