{
  "type": "Feature",
  "properties": {
    "iso:country":"ES",
    "sg:address":"Calle de Poeta Miguel Hernandez, S/n",
    "sg:city":"Cordoba",
    "sg:orig_category":"Panader\u00cdas, Panader\u00cdas",
    "sg:phone":"+34 957 27 66 14",
    "sg:postcode":"14012",
    "sg:province":"C\u00f3rdoba",
    "wof:name":"Confiteria Panaderia Salazar S.l.",
    "wof:placetype":"venue"
},
  "geometry": {"coordinates":[-4.7924132347,37.9003334045],"type":"Point"}
}