{
  "type": "Feature",
  "properties": {
    "addr:full":"D, 87 Golmayo Soria 42190",
    "addr:housenumber":"87",
    "addr:postcode":"42190",
    "addr:street":"D",
    "iso:country":"ES",
    "sg:address":"D, 87",
    "sg:city":"Golmayo",
    "sg:orig_category":"Cooperativas Agr\u00cdcolas",
    "sg:phone":"+34 975 24 90 44",
    "sg:postcode":"42190",
    "sg:province":"Soria",
    "wof:name":"Rubio De La Iglesia Maria Estrella",
    "wof:placetype":"venue"
},
  "geometry": {"coordinates":[-2.5046589375,41.7767601013],"type":"Point"}
}