{
  "type": "Feature",
  "properties": {
    "iso:country":"ES",
    "sg:address":"Pase Isabel La Catolica, 7",
    "sg:city":"Valladolid",
    "sg:orig_category":"Arquitectos",
    "sg:phone":"+34 983 37 44 44",
    "sg:postcode":"47001",
    "sg:province":"Valladolid",
    "wof:name":"B3b C.b.",
    "wof:placetype":"venue"
},
  "geometry": {"coordinates":[-4.7324223518,41.6516075134],"type":"Point"}
}