{
  "type": "Feature",
  "properties": {
    "iso:country":"ES",
    "sg:address":"Calle de Pedreras, 66",
    "sg:city":"Linea De La Concepcion",
    "sg:orig_category":"Bazares, Art\u00cdculos De Limpieza Y De Cocina (al Por Menor)",
    "sg:phone":"+34 956 76 45 45",
    "sg:postcode":"11300",
    "sg:province":"C\u00e1diz",
    "wof:name":"Ye  Xiqiang",
    "wof:placetype":"venue"
},
  "geometry": {"coordinates":[-5.3555436134,36.1655464172],"type":"Point"}
}