{
  "type": "Feature",
  "properties": {
    "iso:country":"ES",
    "sg:address":"Ctra. Palamos, Km. 0007,2",
    "sg:city":"Juia",
    "sg:orig_category":"Carros Elevadores, Carros De Operaciones Portuarias",
    "sg:phone":"+34 972 49 10 06",
    "sg:postcode":"17462",
    "sg:province":"Girona",
    "wof:name":"Comas Pujol Jorge",
    "wof:placetype":"venue"
},
  "geometry": {"coordinates":[2.9117949009,42.0443763733],"type":"Point"}
}