{
  "type": "Feature",
  "properties": {
    "addr:full":"Carrer de Penedes, 28 Castell -tenda Nova Barcelona 08184",
    "addr:housenumber":"28",
    "addr:postcode":"08184",
    "addr:street":"Carrer De Penedes",
    "iso:country":"ES",
    "sg:address":"Carrer de Penedes, 28",
    "sg:city":"Castell -tenda Nova",
    "sg:orig_category":"Alimentaci\u00d3n General (al Por Menor)",
    "sg:phone":"+34 938 64 38 02",
    "sg:postcode":"08184",
    "sg:province":"Barcelona",
    "wof:name":"E.s. Marti 2003 S.l.",
    "wof:placetype":"venue"
},
  "geometry": {"coordinates":[2.181032896,41.5802307129],"type":"Point"}
}