{
  "type": "Feature",
  "properties": {
    "addr:full":"Pla\u00c7 Firal, 27 Santa Coloma De Farners Girona 17430",
    "addr:housenumber":"27",
    "addr:postcode":"17430",
    "addr:street":"Firal",
    "iso:country":"ES",
    "sg:address":"Pla\u00c7 Firal, 27",
    "sg:city":"Santa Coloma De Farners",
    "sg:orig_category":"Arquitectos",
    "sg:phone":"+34 972 84 29 50",
    "sg:postcode":"17430",
    "sg:province":"Girona",
    "wof:name":"Estudi 9 S.a.",
    "wof:placetype":"venue"
},
  "geometry": {"coordinates":[2.6672530174,41.861579895],"type":"Point"}
}