{
  "type": "Feature",
  "properties": {
    "iso:country":"ES",
    "sg:address":"Carrer de Bellavista, 16",
    "sg:city":"Hospitalet Llobregat",
    "sg:orig_category":"Fabricaci\u00d3n, Importaci\u00d3n, Venta De Material De Telefon\u00cda, Peritelefon\u00cda",
    "sg:phone":"+34 933 38 23 89",
    "sg:postcode":"08901",
    "sg:province":"Barcelona",
    "wof:name":"Grupo Royal Telecom S.l.",
    "wof:placetype":"venue"
},
  "geometry": {"coordinates":[2.0949749947,41.3616256714],"type":"Point"}
}