{
  "type": "Feature",
  "properties": {
    "iso:country":"ES",
    "sg:address":"Carrer de Comte D'urgell, 67",
    "sg:city":"Barcelona",
    "sg:orig_category":"Abogados",
    "sg:phone":"+34 933 23 61 82",
    "sg:postcode":"08011",
    "sg:province":"Barcelona",
    "wof:name":"Gimenez Badell Santiago",
    "wof:placetype":"venue"
},
  "geometry": {"coordinates":[2.1577806473,41.3827171326],"type":"Point"}
}