{
  "type": "Feature",
  "properties": {
    "addr:full":"Calle de Marques De Santillana, S/n Osorno Palencia 34460",
    "addr:housenumber":"/ n",
    "addr:postcode":"34460",
    "addr:street":"Calle De Marques De Santillana S",
    "iso:country":"ES",
    "sg:address":"Calle de Marques De Santillana, S/n",
    "sg:city":"Osorno",
    "sg:orig_category":"Hoteles",
    "sg:phone":"+34 979 81 72 16",
    "sg:postcode":"34460",
    "sg:province":"Palencia",
    "wof:name":"Hotel Tierra De Campos S.l.u.",
    "wof:placetype":"venue"
},
  "geometry": {"coordinates":[-4.3620858192,42.4097862244],"type":"Point"}
}