{
  "type": "Feature",
  "properties": {
    "iso:country":"ES",
    "sg:address":"Calle de Sevilla, 4",
    "sg:city":"Granada",
    "sg:orig_category":"Bazares, Art\u00cdculos De Limpieza Y De Cocina (al Por Menor)",
    "sg:phone":"+34 958 20 29 62",
    "sg:postcode":"18003",
    "sg:province":"Granada",
    "wof:name":"Iberinox S. A.",
    "wof:placetype":"venue"
},
  "geometry": {"coordinates":[-3.6110620499,37.1768913269],"type":"Point"}
}