{
  "type": "Feature",
  "properties": {
    "addr:full":"Pg Rubio I Ors, 34 Sabadell Barcelona 08204",
    "addr:housenumber":"34",
    "addr:postcode":"08204",
    "addr:street":"Ors",
    "iso:country":"ES",
    "sg:address":"Pg Rubio I Ors, 34",
    "sg:city":"Sabadell",
    "sg:orig_category":"Veh\u00cdculos De Ocasi\u00d3n",
    "sg:phone":"+34 937 11 95 51",
    "sg:postcode":"08204",
    "sg:province":"Barcelona",
    "wof:name":"Delcor Antonietti Jose Maria",
    "wof:placetype":"venue"
},
  "geometry": {"coordinates":[2.1192901134,41.5325012207],"type":"Point"}
}