{
  "type": "Feature",
  "properties": {
    "iso:country":"ES",
    "sg:address":"Barr Peruri, S/n",
    "sg:city":"Peruri",
    "sg:orig_category":"Fabricaci\u00d3n De Art\u00cdculos Y Equipos Deportivos Y De Ocio",
    "sg:phone":"+34 944 91 17 15",
    "sg:postcode":"48940",
    "sg:province":"Vizcaya",
    "sg:website":"www.footlocker.com",
    "wof:name":"Foot Locker Spain S.l.",
    "wof:placetype":"venue"
},
  "geometry": {"coordinates":[-2.9860789776,43.3275489807],"type":"Point"}
}