{
  "type": "Feature",
  "properties": {
    "iso:country":"ES",
    "sg:address":"Avda Austria, S/n",
    "sg:city":"San Eugenio Alto",
    "sg:orig_category":"Inmobiliaria (agencias)",
    "sg:phone":"+34 922 79 35 84",
    "sg:postcode":"38660",
    "sg:province":"Santa Cruz De Tenerife",
    "wof:name":"Freedom Retiremants S.l.",
    "wof:placetype":"venue"
},
  "geometry": {"coordinates":[-16.7264919281,28.0804977417],"type":"Point"}
}