{
  "type": "Feature",
  "properties": {
    "iso:country":"ES",
    "sg:address":"Avda Constitucion De (la), S/n",
    "sg:city":"Alhaurin El Grande",
    "sg:orig_category":"Ense\u00d1anza: Comercio, Gesti\u00d3n, Inform\u00c1tica",
    "sg:phone":"+34 952 49 90 48",
    "sg:postcode":"29120",
    "sg:province":"M\u00e1laga",
    "wof:name":"Itdsystem",
    "wof:placetype":"venue"
},
  "geometry": {"coordinates":[-4.6831912994,36.6414299011],"type":"Point"}
}