{
  "type": "Feature",
  "properties": {
    "addr:full":"Avda Carlos Pelaez, 13 Navia Asturias 33710",
    "addr:housenumber":"13",
    "addr:postcode":"33710",
    "addr:street":"Avda Carlos Pelaez",
    "iso:country":"ES",
    "sg:address":"Avda Carlos Pelaez, 13",
    "sg:city":"Navia",
    "sg:orig_category":"Peluqueros: De Se\u00d1oras",
    "sg:phone":"+34 985 47 35 89",
    "sg:postcode":"33710",
    "sg:province":"Asturias",
    "wof:name":"Alvarez Iglesias Javier",
    "wof:placetype":"venue"
},
  "geometry": {"coordinates":[-6.7196879387,43.5426368713],"type":"Point"}
}