{
  "type": "Feature",
  "properties": {
    "addr:full":"Calle de Pintor Agrasot, 4 Alacant Alicante 03001",
    "addr:housenumber":"4",
    "addr:postcode":"03001",
    "addr:street":"Calle De Pintor Agrasot",
    "iso:country":"ES",
    "sg:address":"Calle de Pintor Agrasot, 4",
    "sg:city":"Alacant",
    "sg:orig_category":"Ropa Para Se\u00d1oras (al Por Menor)",
    "sg:phone":"+34 965 14 08 37",
    "sg:postcode":"03001",
    "sg:province":"Alicante",
    "wof:name":"Bonmati Sempere Maria Asuncion",
    "wof:placetype":"venue"
},
  "geometry": {"coordinates":[-0.4880689979,38.3441390991],"type":"Point"}
}