{
  "type": "Feature",
  "properties": {
    "iso:country":"ES",
    "sg:address":"Pol Ind Zabal Bajo, 85",
    "sg:city":"La Linea",
    "sg:orig_category":"Fabricaci\u00d3n, Importaci\u00d3n, Venta De Material De Telefon\u00cda, Peritelefon\u00cda",
    "sg:phone":"+34 956 64 51 57",
    "sg:postcode":"11300",
    "sg:province":"C\u00e1diz",
    "wof:name":"Alberto Macias Angeles",
    "wof:placetype":"venue"
},
  "geometry": {"coordinates":[-5.3468561172,36.1927337646],"type":"Point"}
}