{
  "type": "Feature",
  "properties": {
    "iso:country":"ES",
    "sg:address":"Calle de Aben Cuzman, 59",
    "sg:city":"Cordoba",
    "sg:orig_category":"Bisuteros (fabricaci\u00d3n, Al Por Mayor)",
    "sg:phone":"+34 957 43 06 77",
    "sg:postcode":"14014",
    "sg:province":"C\u00f3rdoba",
    "wof:name":"Rafael Gomez Marin S.l.",
    "wof:placetype":"venue"
},
  "geometry": {"coordinates":[-4.6243748665,37.9513511658],"type":"Point"}
}