{
  "type": "Feature",
  "properties": {
    "iso:country":"ES",
    "sg:address":"Calle de Lersundi, 9",
    "sg:city":"Bilbao",
    "sg:orig_category":"Sociedades, Compa\u00d1\u00cdas Aseguradoras",
    "sg:phone":"+34 944 35 46 00",
    "sg:postcode":"48009",
    "sg:province":"Vizcaya",
    "wof:name":"Segurmec Correduria De Seguros S.l.",
    "wof:placetype":"venue"
},
  "geometry": {"coordinates":[-2.9329409599,43.266746521],"type":"Point"}
}