{
  "type": "Feature",
  "properties": {
    "addr:full":"Calle de Guzman, 1 Almeria Almer\u00eda 04001",
    "addr:housenumber":"1",
    "addr:postcode":"04001",
    "addr:street":"Calle De Guzman",
    "iso:country":"ES",
    "sg:address":"Calle de Guzman, 1",
    "sg:city":"Almeria",
    "sg:orig_category":"Promotores Constructores",
    "sg:phone":"+34 950 25 11 34",
    "sg:postcode":"04001",
    "sg:province":"Almer\u00eda",
    "wof:name":"Tecovial S.l.",
    "wof:placetype":"venue"
},
  "geometry": {"coordinates":[-2.4643139839,36.8384590149],"type":"Point"}
}