{
  "type": "Feature",
  "properties": {
    "iso:country":"ES",
    "sg:address":"Calle de Iglesia, 1",
    "sg:city":"Camarillas",
    "sg:orig_category":"Empresas De Carpinter\u00cda De Madera",
    "sg:phone":"+34 978 77 10 12",
    "sg:postcode":"44155",
    "sg:province":"Teruel",
    "wof:name":"Lleo Lloret Daniel",
    "wof:placetype":"venue"
},
  "geometry": {"coordinates":[-0.8590040207,40.5082740784],"type":"Point"}
}