{
  "type": "Feature",
  "properties": {
    "iso:country":"ES",
    "sg:address":"Calle de Padre Francisco Suarez, 2",
    "sg:city":"Valladolid",
    "sg:orig_category":"Agencias Y Agentes Comerciales, Representantes",
    "sg:phone":"+34 983 37 96 03",
    "sg:postcode":"47006",
    "sg:province":"Valladolid",
    "wof:name":"Martin Carpintero Jose Maria",
    "wof:placetype":"venue"
},
  "geometry": {"coordinates":[-4.7356281281,41.6453094482],"type":"Point"}
}