{
  "type": "Feature",
  "properties": {
    "addr:full":"Calle de San Roke Kalea, 1 Gernika-lumo Vizcaya 48300",
    "addr:housenumber":"1",
    "addr:postcode":"48300",
    "addr:street":"Calle De San Roke Kalea",
    "iso:country":"ES",
    "sg:address":"Calle de San Roke Kalea, 1",
    "sg:city":"Gernika-lumo",
    "sg:orig_category":"Carnicer\u00cdas, Carnicer\u00cdas",
    "sg:phone":"+34 946 25 06 90",
    "sg:postcode":"48300",
    "sg:province":"Vizcaya",
    "wof:name":"Javier Aurre Mandaluniz",
    "wof:placetype":"venue"
},
  "geometry": {"coordinates":[-2.5366230011,43.3311347961],"type":"Point"}
}