{
  "type": "Feature",
  "properties": {
    "iso:country":"ES",
    "sg:address":"Calle de Pinto, 17",
    "sg:city":"Salamanca",
    "sg:orig_category":"Asociaciones Y Clubs Deportivos",
    "sg:phone":"+34 923 27 09 75",
    "sg:postcode":"37001",
    "sg:province":"Salamanca",
    "wof:name":"Gracia Galache Miguel Angel",
    "wof:placetype":"venue"
},
  "geometry": {"coordinates":[-5.663848877,40.964225769],"type":"Point"}
}