{
  "type": "Feature",
  "properties": {
    "iso:country":"ES",
    "sg:address":"Avda De La Mediterranea, 8",
    "sg:city":"Moncada",
    "sg:orig_category":"Sanatorios M\u00c9dico",
    "sg:phone":"+34 961 30 00 68",
    "sg:postcode":"46113",
    "sg:province":"Valencia",
    "wof:name":"Generalitat Valenciana",
    "wof:placetype":"venue"
},
  "geometry": {"coordinates":[-0.3955839872,39.5440063477],"type":"Point"}
}