{
  "type": "Feature",
  "properties": {
    "addr:full":"Cra. Reial, Km. 0614,0 S. Just Desvern Barcelona 08960",
    "addr:postcode":"08960",
    "addr:street":"Reial Km. 0614,0 S. Just Desvern Barcelona",
    "iso:country":"ES",
    "sg:address":"Cra. Reial, Km. 0614,0",
    "sg:city":"S. Just Desvern",
    "sg:orig_category":"Ingenier\u00cda, Centros De Estudios (diversos)",
    "sg:phone":"+34 934 70 51 73",
    "sg:postcode":"08960",
    "sg:province":"Barcelona",
    "wof:name":"Pabestructures S.l.",
    "wof:placetype":"venue"
},
  "geometry": {"coordinates":[2.0782721043,41.3850669861],"type":"Point"}
}