{
  "type": "Feature",
  "properties": {
    "iso:country":"ES",
    "sg:address":"Calle de Hernan Cortes, 109",
    "sg:city":"Villanueva Serena",
    "sg:orig_category":"Caf\u00c9s, Bares, Cervecer\u00cdas",
    "sg:phone":"+34 924 84 02 50",
    "sg:postcode":"06700",
    "sg:province":"Badajoz",
    "wof:name":"Borrallo Martin S.l.",
    "wof:placetype":"venue"
},
  "geometry": {"coordinates":[-5.7930588722,38.974609375],"type":"Point"}
}