{
  "type": "Feature",
  "properties": {
    "iso:country":"ES",
    "sg:address":"Picadue\u00f1a Alta, 7",
    "sg:city":"Jerez",
    "sg:classifiers":[
        {
            "category":"Professional",
            "subcategory":"Management & Consulting",
            "type":"Services"
        }
    ],
    "sg:phone":"+34 956 34 89 08",
    "sg:postcode":"11408",
    "sg:province":"C\u00e1diz",
    "sg:tags":[
        "asesor\u00cda",
        "en",
        "marketing"
    ],
    "wof:name":"Gonzalez Corrales Guillermo",
    "wof:placetype":"venue"
},
  "geometry": {"coordinates":[-6.1486229897,36.6821327209],"type":"Point"}
}