{
  "type": "Feature",
  "properties": {
    "iso:country":"ES",
    "sg:address":"Calle de San Cesareo, 22",
    "sg:city":"Madrid",
    "sg:orig_category":"Centros Empresariales",
    "sg:phone":"+34 917 10 98 07",
    "sg:postcode":"28021",
    "sg:province":"Madrid",
    "wof:name":"Mimx Zeus Spain S.a.",
    "wof:placetype":"venue"
},
  "geometry": {"coordinates":[-3.7077989578,40.3377418518],"type":"Point"}
}