{
  "type": "Feature",
  "properties": {
    "iso:country":"ES",
    "sg:address":"Calle de Maestro Chapi, 56",
    "sg:city":"Castellon",
    "sg:orig_category":"Agencias Y Agentes Comerciales, Representantes",
    "sg:phone":"+34 964 20 22 14",
    "sg:postcode":"12001",
    "sg:province":"Castell\u00f3n",
    "wof:name":"Mir Ramada Pilar",
    "wof:placetype":"venue"
},
  "geometry": {"coordinates":[-0.0386799984,39.9865379333],"type":"Point"}
}