{
  "type": "Feature",
  "properties": {
    "addr:full":"Calle de San Lamberto, 11 Madrid Madrid 28017",
    "addr:housenumber":"11",
    "addr:postcode":"madrid;28017",
    "addr:street":"Calle De San Lamberto",
    "iso:country":"ES",
    "sg:address":"Calle de San Lamberto, 11",
    "sg:city":"Madrid",
    "sg:orig_category":"Postigos, Persianas Y Celos\u00cdas",
    "sg:phone":"+34 914 05 49 03",
    "sg:postcode":"28017",
    "sg:province":"Madrid",
    "wof:name":"Sanz Sanz Francisco",
    "wof:placetype":"venue"
},
  "geometry": {"coordinates":[-3.6518259048,40.42029953],"type":"Point"}
}