{
  "type": "Feature",
  "properties": {
    "iso:country":"ES",
    "sg:address":"Avda Ramon Nieto, 485",
    "sg:city":"Penis",
    "sg:orig_category":"Zapatos (al Por Mayor)",
    "sg:phone":"+34 986 27 38 14",
    "sg:postcode":"36205",
    "sg:province":"Pontevedra",
    "wof:name":"Lamas Dominguez Ramon",
    "wof:placetype":"venue"
},
  "geometry": {"coordinates":[-8.70246315,42.2290763855],"type":"Point"}
}