{
  "type": "Feature",
  "properties": {
    "addr:full":"Carrer de Miguel Hernandez, 14 Guardamar Segura Alicante 03140",
    "addr:housenumber":"14",
    "addr:postcode":"03140",
    "addr:street":"Carrer De Miguel Hernandez",
    "iso:country":"ES",
    "sg:address":"Carrer de Miguel Hernandez, 14",
    "sg:city":"Guardamar Segura",
    "sg:orig_category":"Molduras, Junquillos, Listones Y Molduras Perforadas",
    "sg:phone":"+34 965 72 89 21",
    "sg:postcode":"03140",
    "sg:province":"Alicante",
    "wof:name":"Perez Garcia Marcos",
    "wof:placetype":"venue"
},
  "geometry": {"coordinates":[-0.6540349722,38.0892333984],"type":"Point"}
}