{
  "type": "Feature",
  "properties": {
    "addr:full":"Carr Industria, 44 Angles Girona 17160",
    "addr:housenumber":"44",
    "addr:postcode":"17160",
    "addr:street":"Carr Industria",
    "iso:country":"ES",
    "sg:address":"Carr Industria, 44",
    "sg:city":"Angles",
    "sg:orig_category":"Electrodom\u00c9sticos (al Por Menor)",
    "sg:phone":"+34 972 42 00 53",
    "sg:postcode":"17160",
    "sg:province":"Girona",
    "wof:name":"Tenllado Rodriguez Francisca",
    "wof:placetype":"venue"
},
  "geometry": {"coordinates":[2.6366140842,41.9568328857],"type":"Point"}
}