{
  "type": "Feature",
  "properties": {
    "addr:full":"Carrer de Llobateres, 20 Barbera Valles Barcelona 08210",
    "addr:housenumber":"20",
    "addr:postcode":"08210",
    "addr:street":"Carrer De Llobateres",
    "iso:country":"ES",
    "sg:address":"Carrer de Llobateres, 20",
    "sg:city":"Barbera Valles",
    "sg:orig_category":"Venta, Alquiler, Mantenimiento De Calderas",
    "sg:phone":"+34 937 29 47 53",
    "sg:postcode":"08210",
    "sg:province":"Barcelona",
    "wof:name":"Argerinox S.l.",
    "wof:placetype":"venue"
},
  "geometry": {"coordinates":[2.1444265842,41.5258979797],"type":"Point"}
}