{
  "type": "Feature",
  "properties": {
    "addr:full":"Calle de Cobalto, 35 Valladolid Valladolid 47012",
    "addr:housenumber":"35",
    "addr:postcode":"47012",
    "addr:street":"Calle De Cobalto",
    "iso:country":"ES",
    "sg:address":"Calle de Cobalto, 35",
    "sg:city":"Valladolid",
    "sg:orig_category":"Pintura Y Barniz (al Por Menor)",
    "sg:phone":"+34 983 39 28 39",
    "sg:postcode":"47012",
    "sg:province":"Valladolid",
    "wof:name":"Librea 10 S.l.",
    "wof:placetype":"venue"
},
  "geometry": {"coordinates":[-4.7064275742,41.6202087402],"type":"Point"}
}