{
  "type": "Feature",
  "properties": {
    "addr:full":"Carrer de Sant Josep, 7 Manresa Barcelona 08242",
    "addr:housenumber":"7",
    "addr:postcode":"08242",
    "addr:street":"Carrer De Sant Josep",
    "iso:country":"ES",
    "sg:address":"Carrer de Sant Josep, 7",
    "sg:city":"Manresa",
    "sg:orig_category":"Centros M\u00c9dicos Y Sociales, Dispensarios",
    "sg:phone":"+34 938 73 45 94",
    "sg:postcode":"08242",
    "sg:province":"Barcelona",
    "wof:name":"Rafat Selga Juan Salvador",
    "wof:placetype":"venue"
},
  "geometry": {"coordinates":[1.8268419504,41.7320671082],"type":"Point"}
}