{
  "type": "Feature",
  "properties": {
    "addr:full":"Avda Conde Vallellano, S/n Ayllon Segovia 40520",
    "addr:housenumber":"s / n",
    "addr:postcode":"40520",
    "addr:street":"Avda Conde Vallellano",
    "iso:country":"ES",
    "sg:address":"Avda Conde Vallellano, S/n",
    "sg:city":"Ayllon",
    "sg:orig_category":"Barbacoas Y Accesorios",
    "sg:phone":"+34 921 55 31 22",
    "sg:postcode":"40520",
    "sg:province":"Segovia",
    "wof:name":"Sanz Mu\u00f1oz Fortunato",
    "wof:placetype":"venue"
},
  "geometry": {"coordinates":[-3.3829190731,41.4201087952],"type":"Point"}
}