{
  "type": "Feature",
  "properties": {
    "iso:country":"ES",
    "sg:address":"Avda Descubrimientos (de Los), 22",
    "sg:city":"Chiclana De La Frontera",
    "sg:orig_category":"Comercio De Muebles De Estilo Y Contempor\u00c1neos",
    "sg:phone":"+34 956 40 67 71",
    "sg:postcode":"11130",
    "sg:province":"C\u00e1diz",
    "wof:name":"Artefor Asencio Merino E Hijos",
    "wof:placetype":"venue"
},
  "geometry": {"coordinates":[-6.1526126862,36.4260597229],"type":"Point"}
}