{
  "type": "Feature",
  "properties": {
    "addr:full":"Avda Burjasot, 275 Valencia Valencia 46015",
    "addr:housenumber":"275",
    "addr:postcode":"46015",
    "addr:street":"Avda Burjasot",
    "iso:country":"ES",
    "sg:address":"Avda Burjasot, 275",
    "sg:city":"Valencia",
    "sg:orig_category":"Carnicer\u00cdas, Carnicer\u00cdas",
    "sg:phone":"+34 963 48 04 38",
    "sg:postcode":"46015",
    "sg:province":"Valencia",
    "wof:name":"Berlanga Lopez Maria Isabel",
    "wof:placetype":"venue"
},
  "geometry": {"coordinates":[-0.3976280093,39.4963645935],"type":"Point"}
}