{
  "type": "Feature",
  "properties": {
    "addr:full":"Bda. Palmeras, 4 Cordoba C\u00f3rdoba 14005",
    "addr:housenumber":"bda.;4",
    "addr:postcode":"14005",
    "addr:street":"Palmeras;Co\u0301Rdoba",
    "iso:country":"ES",
    "sg:address":"Bda. Palmeras, 4",
    "sg:city":"Cordoba",
    "sg:orig_category":"Alimentaci\u00d3n General (al Por Menor)",
    "sg:phone":"+34 957 46 09 11",
    "sg:postcode":"14005",
    "sg:province":"C\u00f3rdoba",
    "wof:name":"Alimentacion Esquina S.a.",
    "wof:placetype":"venue"
},
  "geometry": {"coordinates":[-4.8831849098,37.866859436],"type":"Point"}
}