{
  "type": "Feature",
  "properties": {
    "iso:country":"ES",
    "sg:address":"Calle de Rosa De Silva, 11",
    "sg:city":"Madrid",
    "sg:orig_category":"Cerrajer\u00cda, Ferrallista",
    "sg:phone":"+34 915 79 16 26",
    "sg:postcode":"28020",
    "sg:province":"Madrid",
    "wof:name":"Sanchez Molina Carlos",
    "wof:placetype":"venue"
},
  "geometry": {"coordinates":[-3.6952049732,40.4632301331],"type":"Point"}
}