{
  "type": "Feature",
  "properties": {
    "addr:full":"Carrer de Alcalde Armengou, 16 Manresa Barcelona 08242",
    "addr:housenumber":"16",
    "addr:postcode":"08242",
    "addr:street":"Carrer De Alcalde Armengou",
    "iso:country":"ES",
    "sg:address":"Carrer de Alcalde Armengou, 16",
    "sg:city":"Manresa",
    "sg:orig_category":"Frutas, Legumbres Frescas Y Tempranas (al Por Menor)",
    "sg:phone":"+34 938 74 42 10",
    "sg:postcode":"08242",
    "sg:province":"Barcelona",
    "sg:website":"www.lafruitaacasa.com",
    "wof:name":"Fruites I Verdures Del Bages S.l.",
    "wof:placetype":"venue"
},
  "geometry": {"coordinates":[1.8219009638,41.7308540344],"type":"Point"}
}