{
  "type": "Feature",
  "properties": {
    "iso:country":"ES",
    "sg:address":"Carrer de Ramon Berenguer Iv (de), 35",
    "sg:city":"Tortosa",
    "sg:orig_category":"Asesor\u00cda Fiscal Y Jur\u00cddica",
    "sg:phone":"+34 977 44 57 33",
    "sg:postcode":"43500",
    "sg:province":"Tarragona",
    "wof:name":"Llorca Marti Alfonso",
    "wof:placetype":"venue"
},
  "geometry": {"coordinates":[0.5237550139,40.8097953796],"type":"Point"}
}