{
  "type": "Feature",
  "properties": {
    "addr:full":"Avda Coru\u00d1a (da), 281 Lugo Lugo 27003",
    "addr:housenumber":"281",
    "addr:postcode":"27003",
    "addr:street":"Avda Corun\u0303A Da",
    "iso:country":"ES",
    "sg:address":"Avda Coru\u00d1a (da), 281",
    "sg:city":"Lugo",
    "sg:orig_category":"Ropa Para Se\u00d1oras Y Caballeros (al Por Menor)",
    "sg:phone":"+34 982 20 33 72",
    "sg:postcode":"27003",
    "sg:province":"Lugo",
    "wof:name":"Veiga Vilari\u00f1o S.l.",
    "wof:placetype":"venue"
},
  "geometry": {"coordinates":[-7.565600872,43.0232810974],"type":"Point"}
}