{
  "type": "Feature",
  "properties": {
    "addr:full":"Calle de Portuetxe, 83 Donostia-san Sebastian Guip\u00f9zcoa 20018",
    "addr:housenumber":"83",
    "addr:postcode":"20018",
    "addr:street":"Calle De Portuetxe",
    "iso:country":"ES",
    "sg:address":"Calle de Portuetxe, 83",
    "sg:city":"Donostia-san Sebastian",
    "sg:classifiers":[
        {
            "category":"Banks & Credit Unions",
            "subcategory":"Bureau De Change",
            "type":"Services"
        }
    ],
    "sg:phone":"+34 943 01 11 64",
    "sg:postcode":"20018",
    "sg:province":"Guip\u00f9zcoa",
    "sg:tags":[
        "organismos",
        "control"
    ],
    "sg:website":"www.s-medion.es",
    "wof:name":"Ecoiso Consultores,s.l.",
    "wof:placetype":"venue"
},
  "geometry": {"coordinates":[-2.020704031,43.3011016846],"type":"Point"}
}