{
  "type": "Feature",
  "properties": {
    "iso:country":"ES",
    "sg:address":"Avda Artesanos (de Los), 6",
    "sg:city":"Ingenio",
    "sg:orig_category":"Farmacias",
    "sg:phone":"+34 928 78 06 95",
    "sg:postcode":"35250",
    "sg:province":"Las Palmas",
    "wof:name":"Artiles Artiles Fernando",
    "wof:placetype":"venue"
},
  "geometry": {"coordinates":[-15.4209213257,27.9162330627],"type":"Point"}
}