{
  "type": "Feature",
  "properties": {
    "addr:full":"Calle de Dunas, 1 Donostia-san Sebastian Guip\u00f9zcoa 20002",
    "addr:housenumber":"1",
    "addr:postcode":"20002",
    "addr:street":"Calle De Dunas",
    "iso:country":"ES",
    "sg:address":"Calle de Dunas, 1",
    "sg:city":"Donostia-san Sebastian",
    "sg:orig_category":"Perfumer\u00cda (al Por Menor)",
    "sg:phone":"+34 943 28 65 94",
    "sg:postcode":"20002",
    "sg:province":"Guip\u00f9zcoa",
    "wof:name":"Gonzalez Gil Arantza",
    "wof:placetype":"venue"
},
  "geometry": {"coordinates":[-1.9765863419,43.3231544495],"type":"Point"}
}