{
  "type": "Feature",
  "properties": {
    "addr:full":"Marjalillo, 12 Motril Granada 18600",
    "addr:housenumber":"12",
    "addr:postcode":"18600",
    "addr:street":"Marjalillo",
    "iso:country":"ES",
    "sg:address":"Marjalillo, 12",
    "sg:city":"Motril",
    "sg:orig_category":"\u00d3ptica: Instrumentos (fabricaci\u00d3n)",
    "sg:phone":"+34 958 60 36 56",
    "sg:postcode":"18600",
    "sg:province":"Granada",
    "wof:name":"Lopez Salido Pedro",
    "wof:placetype":"venue"
},
  "geometry": {"coordinates":[-3.5152790546,36.7456130981],"type":"Point"}
}