{
  "type": "Feature",
  "properties": {
    "iso:country":"ES",
    "sg:address":"Calle de Nuestra Se\u00d1ora, S/n",
    "sg:city":"Barroman",
    "sg:orig_category":"Insecticidas, Fumigaci\u00d3n",
    "sg:phone":"+34 920 32 30 45",
    "sg:postcode":"05229",
    "sg:province":"\u00c1vila",
    "wof:name":"Sesmero Agroquimica C.b.",
    "wof:placetype":"venue"
},
  "geometry": {"coordinates":[-4.9307889938,41.0660705566],"type":"Point"}
}