{
  "type": "Feature",
  "properties": {
    "iso:country":"ES",
    "sg:address":"Avda Blasco Iba\u00d1ez, 33",
    "sg:city":"Valencia",
    "sg:orig_category":"Estancos",
    "sg:phone":"+34 963 69 92 65",
    "sg:postcode":"46010",
    "sg:province":"Valencia",
    "wof:name":"Simo Dionis Gonzalo",
    "wof:placetype":"venue"
},
  "geometry": {"coordinates":[-0.3560740054,39.4768562317],"type":"Point"}
}