{
  "type": "Feature",
  "properties": {
    "addr:full":"Carrer de Sant Jaume, 4 Vic Barcelona 08500",
    "addr:housenumber":"4",
    "addr:postcode":"08500",
    "addr:street":"Carrer De Sant Jaume",
    "iso:country":"ES",
    "sg:address":"Carrer de Sant Jaume, 4",
    "sg:city":"Vic",
    "sg:orig_category":"Empresas De Carpinter\u00cda",
    "sg:phone":"+34 938 85 26 64",
    "sg:postcode":"08500",
    "sg:province":"Barcelona",
    "wof:name":"Jimenez Mu\u00f1oz Gregorio",
    "wof:placetype":"venue"
},
  "geometry": {"coordinates":[2.2578790188,41.9228591919],"type":"Point"}
}