{
  "type": "Feature",
  "properties": {
    "addr:full":"Rua Nicaragua, 50 Vigo Pontevedra 36204",
    "addr:housenumber":"50",
    "addr:postcode":"36204",
    "addr:street":"Rua Nicaragua",
    "iso:country":"ES",
    "sg:address":"Rua Nicaragua, 50",
    "sg:city":"Vigo",
    "sg:orig_category":"Guarder\u00cdas",
    "sg:phone":"+34 986 41 22 58",
    "sg:postcode":"36204",
    "sg:province":"Pontevedra",
    "wof:name":"Escuela Infantil Apa Alve",
    "wof:placetype":"venue"
},
  "geometry": {"coordinates":[-8.7176599503,42.2301177979],"type":"Point"}
}