{
  "type": "Feature",
  "properties": {
    "addr:full":"Avgd De L'almaig, 63 Ontinyent Valencia 46870",
    "addr:housenumber":"63",
    "addr:postcode":"46870",
    "iso:country":"ES",
    "sg:address":"Avgd De L'almaig, 63",
    "sg:city":"Ontinyent",
    "sg:orig_category":"Empresas De Carpinter\u00cda De Madera",
    "sg:phone":"+34 962 91 00 37",
    "sg:postcode":"46870",
    "sg:province":"Valencia",
    "wof:name":"La Finestra Md S.l",
    "wof:placetype":"venue"
},
  "geometry": {"coordinates":[-0.6036059856,38.8186798096],"type":"Point"}
}