{
  "type": "Feature",
  "properties": {
    "addr:full":"Trujillo, 1 Las Galletas Santa Cruz De Tenerife 38631",
    "addr:housenumber":"1",
    "addr:postcode":"38631",
    "addr:street":"Trujillo",
    "iso:country":"ES",
    "sg:address":"Trujillo, 1",
    "sg:city":"Las Galletas",
    "sg:orig_category":"Alimentaci\u00d3n General (al Por Menor)",
    "sg:phone":"+34 922 73 20 71",
    "sg:postcode":"38631",
    "sg:province":"Santa Cruz De Tenerife",
    "wof:name":"Trujillo Rodriguez Gumersindo",
    "wof:placetype":"venue"
},
  "geometry": {"coordinates":[-16.670463562,28.0141906738],"type":"Point"}
}