{
  "type": "Feature",
  "properties": {
    "addr:full":"Plaz Aurora, 5 San Miguel Murcia 30001",
    "addr:housenumber":"5",
    "addr:postcode":"30001",
    "addr:street":"Aurora",
    "iso:country":"ES",
    "sg:address":"Plaz Aurora, 5",
    "sg:city":"San Miguel",
    "sg:orig_category":"Muebles, Minoristas",
    "sg:phone":"+34 968 24 92 59",
    "sg:postcode":"30001",
    "sg:province":"Murcia",
    "sg:website":"www.ka-international.com",
    "wof:name":"Garcia Bernal Maria Dolores",
    "wof:placetype":"venue"
},
  "geometry": {"coordinates":[-1.1298867464,37.9834747314],"type":"Point"}
}