{
  "type": "Feature",
  "properties": {
    "addr:full":"G.v. Lopez De Haro D. Diego, 8 Bilbao Vizcaya 48001",
    "addr:housenumber":"8",
    "addr:postcode":"48001",
    "addr:street":"Lopez De Haro D. Diego",
    "iso:country":"ES",
    "sg:address":"G.v. Lopez De Haro D. Diego, 8",
    "sg:city":"Bilbao",
    "sg:orig_category":"Abogados",
    "sg:phone":"+34 944 24 99 54",
    "sg:postcode":"48001",
    "sg:province":"Vizcaya",
    "wof:name":"Gomeza Eleizalde Iciar",
    "wof:placetype":"venue"
},
  "geometry": {"coordinates":[-2.9288609028,43.2618026733],"type":"Point"}
}