{
  "type": "Feature",
  "properties": {
    "addr:full":"Calle de Cielos, 87 Puerto De Santa Maria C\u00e1diz 11500",
    "addr:housenumber":"87",
    "addr:postcode":"11500",
    "addr:street":"Calle De Cielos;Ca\u0301Diz",
    "iso:country":"ES",
    "sg:address":"Calle de Cielos, 87",
    "sg:city":"Puerto De Santa Maria",
    "sg:orig_category":"Bisuteros (fabricaci\u00d3n, Al Por Mayor)",
    "sg:phone":"+34 956 54 06 99",
    "sg:postcode":"11500",
    "sg:province":"C\u00e1diz",
    "wof:name":"Alvarez Gatica Jose",
    "wof:placetype":"venue"
},
  "geometry": {"coordinates":[-6.2260575294,36.6009902954],"type":"Point"}
}