{
  "type": "Feature",
  "properties": {
    "iso:country":"ES",
    "sg:address":"Carrer de Corsega, 276",
    "sg:city":"Barcelona",
    "sg:orig_category":"Ense\u00d1anza: Social, Param\u00c9dica",
    "sg:phone":"+34 932 37 71 07",
    "sg:postcode":"08008",
    "sg:province":"Barcelona",
    "wof:name":"Sagrera Ferrandiz Jorge",
    "wof:placetype":"venue"
},
  "geometry": {"coordinates":[2.156826973,41.3944511414],"type":"Point"}
}