{
  "type": "Feature",
  "properties": {
    "addr:full":"Calle de Ordo\u00d1ez, 13 Leganes Madrid 28911",
    "addr:housenumber":"13",
    "addr:postcode":"28911",
    "addr:street":"Calle De Ordon\u0303Ez",
    "iso:country":"ES",
    "sg:address":"Calle de Ordo\u00d1ez, 13",
    "sg:city":"Leganes",
    "sg:orig_category":"Telas Y Sedas (al Por Menor)",
    "sg:phone":"+34 916 94 59 00",
    "sg:postcode":"28911",
    "sg:province":"Madrid",
    "wof:name":"Diaz Garcia Jose",
    "wof:placetype":"venue"
},
  "geometry": {"coordinates":[-3.7678411007,40.3294677734],"type":"Point"}
}