{
  "type": "Feature",
  "properties": {
    "addr:full":"Avda Salas Pombo, 5 Calvarrasa Abajo Salamanca 37181",
    "addr:housenumber":"5",
    "addr:postcode":"37181",
    "addr:street":"Avda Salas Pombo",
    "iso:country":"ES",
    "sg:address":"Avda Salas Pombo, 5",
    "sg:city":"Calvarrasa Abajo",
    "sg:orig_category":"Molduras, Junquillos, Listones Y Molduras Perforadas",
    "sg:phone":"+34 923 30 60 04",
    "sg:postcode":"37181",
    "sg:province":"Salamanca",
    "wof:name":"Santos Diego Angel Domingo",
    "wof:placetype":"venue"
},
  "geometry": {"coordinates":[-5.5544691086,40.9459648132],"type":"Point"}
}