{
  "type": "Feature",
  "properties": {
    "iso:country":"ES",
    "sg:address":"Calle de Alcalde Marchesi, 20",
    "sg:city":"Coru\u00d1a",
    "sg:orig_category":"Papeler\u00cdas, Librer\u00cdas",
    "sg:phone":"+34 981 29 15 17",
    "sg:postcode":"15006",
    "sg:province":"La Coru\u00f1a",
    "wof:name":"Garcia Cajal S.c.",
    "wof:placetype":"venue"
},
  "geometry": {"coordinates":[-8.4036140442,43.3560066223],"type":"Point"}
}