{
  "type": "Feature",
  "properties": {
    "iso:country":"ES",
    "sg:address":"Calle de Profesor Lucena Conde, 10",
    "sg:city":"Cordoba",
    "sg:orig_category":"M\u00c9dicos: Estomatolog\u00cda",
    "sg:phone":"+34 957 40 09 09",
    "sg:postcode":"14012",
    "sg:province":"C\u00f3rdoba",
    "wof:name":"Fernandez Malpica Teodomiro",
    "wof:placetype":"venue"
},
  "geometry": {"coordinates":[-4.7836737633,37.8997764587],"type":"Point"}
}