{
  "type": "Feature",
  "properties": {
    "addr:full":"Carrer de Pasteur, 21 Barcelona Barcelona 08024",
    "addr:housenumber":"21",
    "addr:postcode":"08024",
    "addr:street":"Carrer De Pasteur",
    "iso:country":"ES",
    "sg:address":"Carrer de Pasteur, 21",
    "sg:city":"Barcelona",
    "sg:orig_category":"Electricidad: Instaladores",
    "sg:phone":"+34 934 29 09 14",
    "sg:postcode":"08024",
    "sg:province":"Barcelona",
    "wof:name":"Belmonte Tapias Jose",
    "wof:placetype":"venue"
},
  "geometry": {"coordinates":[2.159250021,41.4176292419],"type":"Point"}
}