{
  "type": "Feature",
  "properties": {
    "addr:full":"Rua Dr. Carracido, 39 Vigo Pontevedra 36205",
    "addr:housenumber":"39",
    "addr:postcode":"36205",
    "addr:street":"Rua Dr. Carracido",
    "iso:country":"ES",
    "sg:address":"Rua Dr. Carracido, 39",
    "sg:city":"Vigo",
    "sg:orig_category":"Negocio De Madera",
    "sg:phone":"+34 986 26 39 17",
    "sg:postcode":"36205",
    "sg:province":"Pontevedra",
    "wof:name":"Pi\u00f1eiro Fernandez Pedro",
    "wof:placetype":"venue"
},
  "geometry": {"coordinates":[-8.7045383453,42.2295341492],"type":"Point"}
}