{
  "type": "Feature",
  "properties": {
    "addr:full":"Pl Joan Alsina, 16 Cardedeu Barcelona 08440",
    "addr:housenumber":"16",
    "addr:postcode":"08440",
    "addr:street":"Pl Joan Alsina",
    "iso:country":"ES",
    "sg:address":"Pl Joan Alsina, 16",
    "sg:city":"Cardedeu",
    "sg:orig_category":"Peluqueros: De Se\u00d1oras",
    "sg:phone":"+34 938 46 20 05",
    "sg:postcode":"08440",
    "sg:province":"Barcelona",
    "wof:name":"Erquicia Ledesma Ana",
    "wof:placetype":"venue"
},
  "geometry": {"coordinates":[2.3616108894,41.6418075562],"type":"Point"}
}