{
  "type": "Feature",
  "properties": {
    "iso:country":"ES",
    "sg:address":"M Hernandez, 28",
    "sg:city":"Estella",
    "sg:orig_category":"Escayola Y Productos De Escayola (fabricaci\u00d3n, Al Por Mayor)",
    "sg:phone":"+34 948 55 39 07",
    "sg:postcode":"31200",
    "sg:province":"Navarra",
    "wof:name":"Martinez Carnicero Pedro",
    "wof:placetype":"venue"
},
  "geometry": {"coordinates":[-2.0353488922,42.6726417542],"type":"Point"}
}