{
  "type": "Feature",
  "properties": {
    "addr:full":"Ctra De Los Villares, Km. 0003,0 Jabalcuz Ja\u00e9n 23194",
    "addr:postcode":"23194",
    "addr:street":"Ctra De Los Villares Km. 0003,0 Jabalcuz Jae\u0301N",
    "iso:country":"ES",
    "sg:address":"Ctra De Los Villares, Km. 0003,0",
    "sg:city":"Jabalcuz",
    "sg:orig_category":"Instalaci\u00d3n, Reparaci\u00d3n De Ascensores Y Montacargas",
    "sg:phone":"+34 953 31 50 56",
    "sg:postcode":"23194",
    "sg:province":"Ja\u00e9n",
    "wof:name":"Ascensores Jaen S.l.",
    "wof:placetype":"venue"
},
  "geometry": {"coordinates":[-3.8145108223,37.7447128296],"type":"Point"}
}