{
  "type": "Feature",
  "properties": {
    "iso:country":"ES",
    "sg:address":"Calle de Escudial, 1",
    "sg:city":"Biescas",
    "sg:orig_category":"Reposter\u00cdas",
    "sg:phone":"+34 974 48 53 01",
    "sg:postcode":"22630",
    "sg:province":"Huesca",
    "wof:name":"Hernando Gracia Maria Angeles",
    "wof:placetype":"venue"
},
  "geometry": {"coordinates":[-0.3265120983,42.6249275208],"type":"Point"}
}