{
  "type": "Feature",
  "properties": {
    "iso:country":"ES",
    "sg:address":"Avda Monforte De Lemos, S/n",
    "sg:city":"Madrid",
    "sg:orig_category":"Ropa Para Se\u00d1oras (al Por Menor)",
    "sg:phone":"+34 917 30 26 63",
    "sg:postcode":"28029",
    "sg:province":"Madrid",
    "sg:website":"www.trucco.es",
    "wof:name":"Tell Training S.a.",
    "wof:placetype":"venue"
},
  "geometry": {"coordinates":[-3.7155539989,40.4773712158],"type":"Point"}
}