{
  "type": "Feature",
  "properties": {
    "addr:full":"Carrer de Perez Moya, 16 Sabadell Barcelona 08204",
    "addr:housenumber":"16",
    "addr:postcode":"08204",
    "addr:street":"Carrer De Perez Moya",
    "iso:country":"ES",
    "sg:address":"Carrer de Perez Moya, 16",
    "sg:city":"Sabadell",
    "sg:orig_category":"Abogados",
    "sg:phone":"+34 937 11 45 32",
    "sg:postcode":"08204",
    "sg:province":"Barcelona",
    "wof:name":"Serrano Martinez Antonia",
    "wof:placetype":"venue"
},
  "geometry": {"coordinates":[2.1192278862,41.528793335],"type":"Point"}
}