{
  "type": "Feature",
  "properties": {
    "addr:full":"Calle de Santa Engracia, 5 Madrid Madrid 28010",
    "addr:housenumber":"5",
    "addr:postcode":"28010",
    "addr:street":"Calle De Santa Engracia",
    "iso:country":"ES",
    "sg:address":"Calle de Santa Engracia, 5",
    "sg:city":"Madrid",
    "sg:orig_category":"Inmobiliaria (agencias)",
    "sg:phone":"+34 914 46 24 84",
    "sg:postcode":"28010",
    "sg:province":"Madrid",
    "wof:name":"Millas Y Chuman S.a.",
    "wof:placetype":"venue"
},
  "geometry": {"coordinates":[-3.696160078,40.4286842346],"type":"Point"}
}