{
  "type": "Feature",
  "properties": {
    "addr:full":"Calle de Carboneria, 1 San Ildefonso O La Granja Segovia 40100",
    "addr:housenumber":"1",
    "addr:postcode":"40100",
    "addr:street":"Calle De Carboneria;O",
    "iso:country":"ES",
    "sg:address":"Calle de Carboneria, 1",
    "sg:city":"San Ildefonso O La Granja",
    "sg:orig_category":"Asesor\u00cda Fiscal Y Jur\u00cddica",
    "sg:phone":"+34 921 47 18 35",
    "sg:postcode":"40100",
    "sg:province":"Segovia",
    "wof:name":"Perez Alonso Miguel",
    "wof:placetype":"venue"
},
  "geometry": {"coordinates":[-4.0055809021,40.9015808105],"type":"Point"}
}