{
  "type": "Feature",
  "properties": {
    "addr:full":"Calle de General Prim, 29 Alcala Guadaira Sevilla 41500",
    "addr:housenumber":"29",
    "addr:postcode":"41500",
    "addr:street":"Calle De General Prim",
    "iso:country":"ES",
    "sg:address":"Calle de General Prim, 29",
    "sg:city":"Alcala Guadaira",
    "sg:orig_category":"Venta, Instalaci\u00d3n, Reparaci\u00d3n De Antenas Para Televisi\u00d3n",
    "sg:phone":"+34 955 61 05 11",
    "sg:postcode":"41500",
    "sg:province":"Sevilla",
    "wof:name":"Electro Alcala S.l.",
    "wof:placetype":"venue"
},
  "geometry": {"coordinates":[-5.8379068375,37.3433876038],"type":"Point"}
}