{
  "type": "Feature",
  "properties": {
    "addr:full":"Calle de Poeta Salvador Ibarra Espa\u00d1a, 8 Malaga M\u00e1laga 29011",
    "addr:housenumber":"8",
    "addr:postcode":"29011",
    "addr:street":"Calle De Poeta Salvador;Espan\u0303A;Ma\u0301Laga",
    "iso:country":"ES",
    "sg:address":"Calle de Poeta Salvador Ibarra Espa\u00d1a, 8",
    "sg:city":"Malaga",
    "sg:orig_category":"Enfermeras: Consultas, Atenci\u00d3n A Domicilio",
    "sg:phone":"+34 952 61 01 98",
    "sg:postcode":"29011",
    "sg:province":"M\u00e1laga",
    "wof:name":"Tellez Burgos Francisco",
    "wof:placetype":"venue"
},
  "geometry": {"coordinates":[-4.4311590195,36.7328147888],"type":"Point"}
}