{
  "type": "Feature",
  "properties": {
    "addr:full":"Carrer de Biscaia, 25 Rubi Barcelona 08191",
    "addr:housenumber":"25",
    "addr:postcode":"08191",
    "addr:street":"Carrer De Biscaia",
    "iso:country":"ES",
    "sg:address":"Carrer de Biscaia, 25",
    "sg:city":"Rubi",
    "sg:orig_category":"Agencias Y Asesores De Publicidad",
    "sg:phone":"+34 936 97 94 57",
    "sg:postcode":"08191",
    "sg:province":"Barcelona",
    "wof:name":"Rubiroda Promociones S.l.",
    "wof:placetype":"venue"
},
  "geometry": {"coordinates":[2.0468559265,41.5035133362],"type":"Point"}
}