{
  "type": "Feature",
  "properties": {
    "iso:country":"ES",
    "sg:address":"Calle de E, 84",
    "sg:city":"Pol. Malpica",
    "sg:orig_category":"Fabricaci\u00d3n Y Venta De Volquetes Y Remolques",
    "sg:phone":"+34 976 57 35 17",
    "sg:postcode":"50057",
    "sg:province":"Zaragoza",
    "sg:website":"www.basculantespepin.es",
    "wof:name":"Basculantes Pepin S. A.",
    "wof:placetype":"venue"
},
  "geometry": {"coordinates":[-0.7917029858,41.6579627991],"type":"Point"}
}