{
  "type": "Feature",
  "properties": {
    "addr:full":"Calle de San Ignacio, 25 San Vicente De Barakaldo Vizcaya 48903",
    "addr:housenumber":"25",
    "addr:postcode":"48903",
    "addr:street":"Calle De San Ignacio",
    "iso:country":"ES",
    "sg:address":"Calle de San Ignacio, 25",
    "sg:city":"San Vicente De Barakaldo",
    "sg:orig_category":"Asesor\u00cda De Formaci\u00d3n Y Gesti\u00d3n De Personal",
    "sg:phone":"+34 944 82 07 44",
    "sg:postcode":"48903",
    "sg:province":"Vizcaya",
    "wof:name":"Tekfor Taldea S. L.",
    "wof:placetype":"venue"
},
  "geometry": {"coordinates":[-2.9902749062,43.2841110229],"type":"Point"}
}