{
  "type": "Feature",
  "properties": {
    "addr:full":"Carril De Carretas, 17 S. Clemente Cuenca 16600",
    "addr:housenumber":"17",
    "addr:postcode":"16600",
    "addr:street":"Carril De Carretas;S. Clemente Cuenca",
    "iso:country":"ES",
    "sg:address":"Carril De Carretas, 17",
    "sg:city":"S. Clemente",
    "sg:orig_category":"Autob\u00das (explotaci\u00d3n Y Servicios De)",
    "sg:phone":"+34 969 30 04 67",
    "sg:postcode":"16600",
    "sg:province":"Cuenca",
    "wof:name":"Autocares J.y C.navarro S.l.",
    "wof:placetype":"venue"
},
  "geometry": {"coordinates":[-2.4270188808,39.3993186951],"type":"Point"}
}