{
  "type": "Feature",
  "properties": {
    "iso:country":"ES",
    "sg:address":"Carrer de Castelao, 103",
    "sg:city":"Hospitalet Llobregat",
    "sg:orig_category":"Venta, Colocaci\u00d3n, Reparaci\u00d3n De Radiadores Para Veh\u00cdculos",
    "sg:phone":"+34 932 98 16 26",
    "sg:postcode":"08902",
    "sg:province":"Barcelona",
    "wof:name":"Radiatruck S.l.",
    "wof:placetype":"venue"
},
  "geometry": {"coordinates":[2.1253530979,41.3625106812],"type":"Point"}
}