{
  "type": "Feature",
  "properties": {
    "iso:country":"ES",
    "sg:address":"Calle de Prim, 31",
    "sg:city":"Donostia-san Sebastian",
    "sg:orig_category":"Pantallas, Mamparas Y Accesorios (fabricaci\u00d3n)",
    "sg:phone":"+34 943 46 41 34",
    "sg:postcode":"20006",
    "sg:province":"Guip\u00f9zcoa",
    "wof:name":"Arbide Camps Maria Eugenia",
    "wof:placetype":"venue"
},
  "geometry": {"coordinates":[-1.9799846411,43.3158912659],"type":"Point"}
}