{
  "type": "Feature",
  "properties": {
    "addr:full":"Calle de Yebenes, 88 Madrid Madrid 28047",
    "addr:housenumber":"88",
    "addr:postcode":"madrid;28047",
    "addr:street":"Calle De Yebenes",
    "iso:country":"ES",
    "sg:address":"Calle de Yebenes, 88",
    "sg:city":"Madrid",
    "sg:orig_category":"Inmobiliaria (agencias)",
    "sg:phone":"+34 917 10 10 83",
    "sg:postcode":"28047",
    "sg:province":"Madrid",
    "wof:name":"Qui.mad Asesores Sl",
    "wof:placetype":"venue"
},
  "geometry": {"coordinates":[-3.7535068989,40.3926963806],"type":"Point"}
}