{
  "type": "Feature",
  "properties": {
    "addr:full":"Ctra Moraira-calpe, 120 Teulada Alicante 03725",
    "addr:housenumber":"120",
    "addr:postcode":"03725",
    "addr:street":"Ctra Moraira-Calpe",
    "iso:country":"ES",
    "sg:address":"Ctra Moraira-calpe, 120",
    "sg:city":"Teulada",
    "sg:orig_category":"Inform\u00c1tica, Ofim\u00c1tica (estudios, Asesor\u00cda, Ingenier\u00cda, Formaci\u00d3n)",
    "sg:phone":"+34 966 49 15 21",
    "sg:postcode":"03725",
    "sg:province":"Alicante",
    "wof:name":"Speedcom Europa S.l.",
    "wof:placetype":"venue"
},
  "geometry": {"coordinates":[0.1247060001,38.6862411499],"type":"Point"}
}