{
  "type": "Feature",
  "properties": {
    "iso:country":"ES",
    "sg:address":"Calle de Empedrada, 16",
    "sg:city":"Manzanares",
    "sg:orig_category":"Ropa Para Se\u00d1oras Y Caballeros (al Por Menor)",
    "sg:phone":"+34 926 61 20 92",
    "sg:postcode":"13200",
    "sg:province":"Ciudad Real",
    "wof:name":"Comercial Roman C.b.",
    "wof:placetype":"venue"
},
  "geometry": {"coordinates":[-3.3720190525,38.9964790344],"type":"Point"}
}