{
  "type": "Feature",
  "properties": {
    "iso:country":"ES",
    "sg:address":"Calle de Garachico, 19",
    "sg:city":"Santa Cruz Palma",
    "sg:orig_category":"Peluquer\u00cdas, Peluquer\u00cda Mixta",
    "sg:phone":"+34 922 41 62 23",
    "sg:postcode":"38700",
    "sg:province":"Santa Cruz De Tenerife",
    "wof:name":"Concepcion Perez Lucia",
    "wof:placetype":"venue"
},
  "geometry": {"coordinates":[-17.7634906769,28.6847877502],"type":"Point"}
}