{
  "type": "Feature",
  "properties": {
    "addr:full":"Avda Reino De Espa\u00d1a, 186 Roquetas Mar Almer\u00eda 04740",
    "addr:housenumber":"186",
    "addr:postcode":"04740",
    "addr:street":"Avda Reino De Espan\u0303A;Mar Almeri\u0301A",
    "iso:country":"ES",
    "sg:address":"Avda Reino De Espa\u00d1a, 186",
    "sg:city":"Roquetas Mar",
    "sg:orig_category":"Inmobiliaria (agencias)",
    "sg:phone":"+34 950 32 97 58",
    "sg:postcode":"04740",
    "sg:province":"Almer\u00eda",
    "wof:name":"Macdonald G.m.d.c. S.l.",
    "wof:placetype":"venue"
},
  "geometry": {"coordinates":[-2.6084189415,36.7703056335],"type":"Point"}
}