{
  "type": "Feature",
  "properties": {
    "iso:country":"ES",
    "sg:address":"Calle de Moreras, 2",
    "sg:city":"Oropesa",
    "sg:orig_category":"Centros De Educaci\u00d3n Especial",
    "sg:phone":"+34 925 43 03 30",
    "sg:postcode":"45560",
    "sg:province":"Toledo",
    "wof:name":"Carmelitas Misioneras",
    "wof:placetype":"venue"
},
  "geometry": {"coordinates":[-5.1713690758,39.9169616699],"type":"Point"}
}