{
  "type": "Feature",
  "properties": {
    "addr:full":"Paseo De San Antonio, S/n Santiago Espada Ja\u00e9n 23290",
    "addr:housenumber":"s / n",
    "addr:postcode":"23290",
    "addr:street":"Paseo De San Antonio;Jae\u0301N",
    "iso:country":"ES",
    "sg:address":"Paseo De San Antonio, S/n",
    "sg:city":"Santiago Espada",
    "sg:orig_category":"Centros De Educaci\u00d3n Especial",
    "sg:phone":"+34 953 43 81 61",
    "sg:postcode":"23290",
    "sg:province":"Ja\u00e9n",
    "wof:name":"Junta De Andalucia",
    "wof:placetype":"venue"
},
  "geometry": {"coordinates":[-2.8128240108,38.0918540955],"type":"Point"}
}