{
  "type": "Feature",
  "properties": {
    "addr:full":"Avda Benito Perez Armas, 6 Santa Cruz De Tenerife Santa Cruz De Tenerife 38007",
    "addr:housenumber":"6",
    "addr:postcode":"38007",
    "addr:street":"Avda Benito Perez Armas",
    "iso:country":"ES",
    "sg:address":"Avda Benito Perez Armas, 6",
    "sg:city":"Santa Cruz De Tenerife",
    "sg:orig_category":"Supermercados Y Hipermercados",
    "sg:phone":"+34 922 21 71 02",
    "sg:postcode":"38007",
    "sg:province":"Santa Cruz De Tenerife",
    "wof:name":"Comercial Jesuman",
    "wof:placetype":"venue"
},
  "geometry": {"coordinates":[-16.2653560638,28.4600486755],"type":"Point"}
}