{
  "type": "Feature",
  "properties": {
    "iso:country":"ES",
    "sg:address":"Carr Madre Juana Maria Condesa Lluch, 6",
    "sg:city":"Valencia",
    "sg:orig_category":"Ingenier\u00cda, Centros De Estudios (industria)",
    "sg:phone":"+34 963 83 66 99",
    "sg:postcode":"46014",
    "sg:province":"Valencia",
    "wof:name":"Insegma S.l.",
    "wof:placetype":"venue"
},
  "geometry": {"coordinates":[-0.4113740027,39.4659805298],"type":"Point"}
}