{
  "type": "Feature",
  "properties": {
    "addr:full":"Carrer de Parellades, 68 Sitges Barcelona 08870",
    "addr:housenumber":"68",
    "addr:postcode":"08870",
    "addr:street":"Carrer De Parellades",
    "iso:country":"ES",
    "sg:address":"Carrer de Parellades, 68",
    "sg:city":"Sitges",
    "sg:orig_category":"Muebles, Minoristas",
    "sg:phone":"+34 938 10 24 10",
    "sg:postcode":"08870",
    "sg:province":"Barcelona",
    "wof:name":"Telesofa S.l.",
    "wof:placetype":"venue"
},
  "geometry": {"coordinates":[1.8068619967,41.2366065979],"type":"Point"}
}