{
  "type": "Feature",
  "properties": {
    "iso:country":"ES",
    "sg:address":"Calle de Axular, 8",
    "sg:city":"Basauri",
    "sg:orig_category":"Carnicer\u00cdas, Carnicer\u00cdas",
    "sg:phone":"+34 944 05 82 04",
    "sg:postcode":"48970",
    "sg:province":"Vizcaya",
    "wof:name":"Maria Luisa Nu\u00f1ez Fonce",
    "wof:placetype":"venue"
},
  "geometry": {"coordinates":[-2.8929209709,43.2366333008],"type":"Point"}
}