{
  "type": "Feature",
  "properties": {
    "addr:full":"Calle de Toledo, 32 Torres Cotillas Murcia 30565",
    "addr:housenumber":"32",
    "addr:postcode":"30565",
    "addr:street":"Calle De Toledo",
    "iso:country":"ES",
    "sg:address":"Calle de Toledo, 32",
    "sg:city":"Torres Cotillas",
    "sg:orig_category":"Transportes Por V\u00cdas Navegables",
    "sg:phone":"+34 968 62 61 93",
    "sg:postcode":"30565",
    "sg:province":"Murcia",
    "wof:name":"Lopez Illan Pedro",
    "wof:placetype":"venue"
},
  "geometry": {"coordinates":[-1.2395490408,38.0263290405],"type":"Point"}
}