{
  "type": "Feature",
  "properties": {
    "addr:full":"Calle de Castelar, 13 Sevilla Sevilla 41001",
    "addr:housenumber":"13",
    "addr:postcode":"41001",
    "addr:street":"Calle De Castelar",
    "iso:country":"ES",
    "sg:address":"Calle de Castelar, 13",
    "sg:city":"Sevilla",
    "sg:orig_category":"Seguridad Social",
    "sg:phone":"+34 954 50 25 16",
    "sg:postcode":"41001",
    "sg:province":"Sevilla",
    "sg:website":"www.seg-social.es",
    "wof:name":"Tesoreria General De La Seguridad Social-direccion Provincial De Sevilla",
    "wof:placetype":"venue"
},
  "geometry": {"coordinates":[-5.9972100258,37.3869781494],"type":"Point"}
}