{
  "type": "Feature",
  "properties": {
    "addr:full":"Cmno Ortigas, 16 Medellin Badajoz 06411",
    "addr:housenumber":"16",
    "addr:postcode":"06411",
    "addr:street":"Cmno Ortigas",
    "iso:country":"ES",
    "sg:address":"Cmno Ortigas, 16",
    "sg:city":"Medellin",
    "sg:orig_category":"Maquinaria Para Industrias Diversas",
    "sg:phone":"+34 924 82 24 54",
    "sg:postcode":"06411",
    "sg:province":"Badajoz",
    "wof:name":"Talleres Barragan E Hijos C.b.",
    "wof:placetype":"venue"
},
  "geometry": {"coordinates":[-5.9577040672,38.9618453979],"type":"Point"}
}