{
  "type": "Feature",
  "properties": {
    "iso:country":"ES",
    "sg:address":"Calle de Bailen, 5",
    "sg:city":"Puertollano",
    "sg:orig_category":"Peluquer\u00cdas, Peluquer\u00cda Mixta",
    "sg:phone":"+34 926 42 61 08",
    "sg:postcode":"13500",
    "sg:province":"Ciudad Real",
    "wof:name":"Romero Romero Maria Del Mar",
    "wof:placetype":"venue"
},
  "geometry": {"coordinates":[-4.1044597626,38.6843757629],"type":"Point"}
}