{
  "type": "Feature",
  "properties": {
    "iso:country":"ES",
    "sg:address":"Calle de Mayor, 24",
    "sg:city":"Guadalajara",
    "sg:orig_category":"Bisuter\u00cda, Joyer\u00cda, Relojer\u00cda (al Por Menor)",
    "sg:phone":"+34 949 22 61 65",
    "sg:postcode":"19001",
    "sg:province":"Guadalajara",
    "wof:name":"Sanchez Gutierrez Jose Maria",
    "wof:placetype":"venue"
},
  "geometry": {"coordinates":[-3.1655459404,40.631980896],"type":"Point"}
}