{
  "type": "Feature",
  "properties": {
    "addr:full":"Urb Dehesa Ganaderos (garrapinillos), S/n Garrapinillos Zaragoza 50190",
    "addr:housenumber":"s / n",
    "addr:postcode":"50190",
    "addr:street":"Garrapinillos",
    "iso:country":"ES",
    "sg:address":"Urb Dehesa Ganaderos (garrapinillos), S/n",
    "sg:city":"Garrapinillos",
    "sg:orig_category":"Promotores Constructores",
    "sg:phone":"+34 976 13 12 67",
    "sg:postcode":"50190",
    "sg:province":"Zaragoza",
    "wof:name":"Aragonesa De Asfaltos Y Construcciones S.a.",
    "wof:placetype":"venue"
},
  "geometry": {"coordinates":[-1.0273573399,41.6837768555],"type":"Point"}
}