{
  "type": "Feature",
  "properties": {
    "addr:full":"Plaz Espa\u00d1a, S/n Aguilar Campoo Palencia 34800",
    "addr:housenumber":"s",
    "addr:postcode":"34800",
    "addr:street":"Plaz Espan\u0303A;/ N",
    "iso:country":"ES",
    "sg:address":"Plaz Espa\u00d1a, S/n",
    "sg:city":"Aguilar Campoo",
    "sg:classifiers":[
        {
            "category":"Taxi",
            "type":"Transportation"
        }
    ],
    "sg:phone":"+34 979 12 26 69",
    "sg:postcode":"34800",
    "sg:province":"Palencia",
    "wof:name":"Ayuntamiento De Aguilar De Campoo",
    "wof:placetype":"venue"
},
  "geometry": {"coordinates":[-4.3009209633,42.6296615601],"type":"Point"}
}