{
  "type": "Feature",
  "properties": {
    "iso:country":"ES",
    "sg:address":"Pase Delicias, 130",
    "sg:city":"Madrid",
    "sg:orig_category":"Caf\u00c9s, Bares, Cervecer\u00cdas",
    "sg:phone":"+34 914 74 69 39",
    "sg:postcode":"28045",
    "sg:province":"Madrid",
    "wof:name":"Ortego Vicente Francisco",
    "wof:placetype":"venue"
},
  "geometry": {"coordinates":[-3.6949670315,40.3933601379],"type":"Point"}
}