{
  "type": "Feature",
  "properties": {
    "addr:full":"Calle de Reyes Catolicos, 22 Elda Alicante 03600",
    "addr:housenumber":"22",
    "addr:postcode":"03600",
    "addr:street":"Calle De Reyes Catolicos",
    "iso:country":"ES",
    "sg:address":"Calle de Reyes Catolicos, 22",
    "sg:city":"Elda",
    "sg:orig_category":"Dietistas",
    "sg:phone":"+34 965 39 12 60",
    "sg:postcode":"03600",
    "sg:province":"Alicante",
    "wof:name":"Housediet S.l Sociedad Unipersonal",
    "wof:placetype":"venue"
},
  "geometry": {"coordinates":[-0.7910630107,38.4790763855],"type":"Point"}
}