{
  "type": "Feature",
  "properties": {
    "addr:full":"Calle de Carreteria, 15 Sanlucar De Barrameda C\u00e1diz 11540",
    "addr:housenumber":"15",
    "addr:postcode":"11540",
    "addr:street":"Calle De Carreteria;Ca\u0301Diz",
    "iso:country":"ES",
    "sg:address":"Calle de Carreteria, 15",
    "sg:city":"Sanlucar De Barrameda",
    "sg:orig_category":"Promotores Constructores",
    "sg:phone":"+34 956 36 93 52",
    "sg:postcode":"11540",
    "sg:province":"C\u00e1diz",
    "wof:name":"Hernandez Moreno Jose Antonio",
    "wof:placetype":"venue"
},
  "geometry": {"coordinates":[-6.3529644012,36.7716560364],"type":"Point"}
}