{
  "type": "Feature",
  "properties": {
    "iso:country":"ES",
    "sg:address":"Calle de Garcia Gutierrez, 1",
    "sg:city":"Linea De La Concepcion",
    "sg:orig_category":"Supermercados Y Hipermercados",
    "sg:phone":"+34 956 76 37 27",
    "sg:postcode":"11300",
    "sg:province":"C\u00e1diz",
    "wof:name":"Sanchez Rusis Francisco",
    "wof:placetype":"venue"
},
  "geometry": {"coordinates":[-5.3463559151,36.1692886353],"type":"Point"}
}