{
  "type": "Feature",
  "properties": {
    "iso:country":"ES",
    "sg:address":"Calle de Juan Xxiii, 15",
    "sg:city":"Santurtzi",
    "sg:orig_category":"Caf\u00c9s, Bares, Cervecer\u00cdas",
    "sg:phone":"+34 944 62 79 69",
    "sg:postcode":"48980",
    "sg:province":"Vizcaya",
    "wof:name":"Martinez Ruiz Luis",
    "wof:placetype":"venue"
},
  "geometry": {"coordinates":[-3.034569025,43.331199646],"type":"Point"}
}