{
  "type": "Feature",
  "properties": {
    "addr:full":"Praz Corgo (do), S/n Grove Pontevedra 36980",
    "addr:housenumber":"s",
    "addr:postcode":"36980",
    "addr:street":"Praz;/ N Grove",
    "iso:country":"ES",
    "sg:address":"Praz Corgo (do), S/n",
    "sg:city":"Grove",
    "sg:orig_category":"Carnicer\u00cdas, Carnicer\u00cdas",
    "sg:phone":"+34 986 73 08 48",
    "sg:postcode":"36980",
    "sg:province":"Pontevedra",
    "wof:name":"Dominguez Fernandez Manuel",
    "wof:placetype":"venue"
},
  "geometry": {"coordinates":[-8.86282444,42.4956588745],"type":"Point"}
}