{
  "type": "Feature",
  "properties": {
    "iso:country":"ES",
    "sg:address":"Cmno Ayudante, S/n",
    "sg:city":"Pampanico",
    "sg:orig_category":"Cooperativas Agr\u00cdcolas",
    "sg:phone":"+34 950 48 06 65",
    "sg:postcode":"04700",
    "sg:province":"Almer\u00eda",
    "wof:name":"Camposol Sociedad Cooperativa Andaluza",
    "wof:placetype":"venue"
},
  "geometry": {"coordinates":[-2.8176040649,36.7727012634],"type":"Point"}
}