{
  "type": "Feature",
  "properties": {
    "iso:country":"ES",
    "sg:address":"Calle de Fernando Vi, 2",
    "sg:city":"Madrid",
    "sg:orig_category":"Aparatos De Iluminaci\u00d3n (al Por Menor)",
    "sg:phone":"+34 917 02 00 78",
    "sg:postcode":"28004",
    "sg:province":"Madrid",
    "wof:name":"Tenorio Garcia Juan Luis",
    "wof:placetype":"venue"
},
  "geometry": {"coordinates":[-3.6971580982,40.4257583618],"type":"Point"}
}