{
  "type": "Feature",
  "properties": {
    "addr:full":"Carrer de Victor Pradera, 124 Almeda Mercader Barcelona 08940",
    "addr:housenumber":"124",
    "addr:postcode":"08940",
    "addr:street":"Carrer De Victor Pradera;Mercader Barcelona",
    "iso:country":"ES",
    "sg:address":"Carrer de Victor Pradera, 124",
    "sg:city":"Almeda Mercader",
    "sg:orig_category":"Contenedores (mercanc\u00cdas)",
    "sg:phone":"+34 933 77 61 33",
    "sg:postcode":"08940",
    "sg:province":"Barcelona",
    "wof:name":"Trans G.m. S.l.",
    "wof:placetype":"venue"
},
  "geometry": {"coordinates":[2.0708940029,41.3559417725],"type":"Point"}
}