{
  "type": "Feature",
  "properties": {
    "iso:country":"ES",
    "sg:address":"Carrer de Sol, 110",
    "sg:city":"Sabadell",
    "sg:orig_category":"Arquitectos",
    "sg:phone":"+34 937 25 89 06",
    "sg:postcode":"08201",
    "sg:province":"Barcelona",
    "wof:name":"Ral Arquitectura E Interiorisme Scp",
    "wof:placetype":"venue"
},
  "geometry": {"coordinates":[2.1095209122,41.5429534912],"type":"Point"}
}