{
  "type": "Feature",
  "properties": {
    "iso:country":"ES",
    "sg:address":"El Porvenir, 30",
    "sg:city":"Pedreguer",
    "sg:orig_category":"Carnicer\u00cdas, Carnicer\u00cdas",
    "sg:phone":"+34 966 45 64 76",
    "sg:postcode":"03750",
    "sg:province":"Alicante",
    "wof:name":"Costa Carrio Pedro Vicente",
    "wof:placetype":"venue"
},
  "geometry": {"coordinates":[0.0296519995,38.7918777466],"type":"Point"}
}