{
  "type": "Feature",
  "properties": {
    "addr:full":"Calle de General Franco, 21 Santa Brigida Las Palmas 35300",
    "addr:housenumber":"21",
    "addr:postcode":"35300",
    "addr:street":"Calle De General Franco",
    "iso:country":"ES",
    "sg:address":"Calle de General Franco, 21",
    "sg:city":"Santa Brigida",
    "sg:orig_category":"Empresarios",
    "sg:phone":"+34 928 64 00 87",
    "sg:postcode":"35300",
    "sg:province":"Las Palmas",
    "wof:name":"Fulcauto Opea 2002",
    "wof:placetype":"venue"
},
  "geometry": {"coordinates":[-15.4995641708,28.0333786011],"type":"Point"}
}