{
  "type": "Feature",
  "properties": {
    "addr:full":"Calle de Santa Ana, 33 Montejicar Granada 18561",
    "addr:housenumber":"33",
    "addr:postcode":"18561",
    "addr:street":"Calle De Santa Ana",
    "iso:country":"ES",
    "sg:address":"Calle de Santa Ana, 33",
    "sg:city":"Montejicar",
    "sg:orig_category":"Asociaciones, Organismos Culturales Y Socioeducativos",
    "sg:phone":"+34 958 39 33 39",
    "sg:postcode":"18561",
    "sg:province":"Granada",
    "wof:name":"Circulo La Amistad",
    "wof:placetype":"venue"
},
  "geometry": {"coordinates":[-3.5032858849,37.5702896118],"type":"Point"}
}