{
  "type": "Feature",
  "properties": {
    "addr:full":"Calle de Hernando Del Pulgar, 31 Sevilla Sevilla 41007",
    "addr:housenumber":"31",
    "addr:postcode":"41007",
    "addr:street":"Calle De Hernando Del Pulgar",
    "iso:country":"ES",
    "sg:address":"Calle de Hernando Del Pulgar, 31",
    "sg:city":"Sevilla",
    "sg:orig_category":"Contenedores (mercanc\u00cdas)",
    "sg:phone":"+34 954 98 00 39",
    "sg:postcode":"41007",
    "sg:province":"Sevilla",
    "wof:name":"Sistemas De Envios Internacionales S.l.",
    "wof:placetype":"venue"
},
  "geometry": {"coordinates":[-5.9709467888,37.3894309998],"type":"Point"}
}