{
  "type": "Feature",
  "properties": {
    "addr:full":"Nullan, S/n Nullan Lugo 27677",
    "addr:postcode":"27677",
    "addr:street":"S / N",
    "iso:country":"ES",
    "sg:address":"Nullan, S/n",
    "sg:city":"Nullan",
    "sg:orig_category":"Empresas De Carpinter\u00cda",
    "sg:phone":"+34 982 16 12 10",
    "sg:postcode":"27677",
    "sg:province":"Lugo",
    "wof:name":"Muebles Freixo S.a.",
    "wof:placetype":"venue"
},
  "geometry": {"coordinates":[-7.1095547676,42.8088111877],"type":"Point"}
}