{
  "type": "Feature",
  "properties": {
    "addr:full":"Carrer de Renaixement, 21 Terrassa Barcelona 08226",
    "addr:housenumber":"21",
    "addr:postcode":"08226",
    "addr:street":"Carrer De Renaixement",
    "iso:country":"ES",
    "sg:address":"Carrer de Renaixement, 21",
    "sg:city":"Terrassa",
    "sg:orig_category":"Agencias Y Agentes Comerciales, Representantes",
    "sg:phone":"+34 937 85 13 62",
    "sg:postcode":"08226",
    "sg:province":"Barcelona",
    "wof:name":"Alfaro Peropadre Ricardo",
    "wof:placetype":"venue"
},
  "geometry": {"coordinates":[2.0286242962,41.5741996765],"type":"Point"}
}