{
  "type": "Feature",
  "properties": {
    "addr:full":"Calle de Perez Soto, 21 Santa Cruz De Tenerife Santa Cruz De Tenerife 38009",
    "addr:housenumber":"21",
    "addr:postcode":"38009",
    "addr:street":"Calle De Perez Soto",
    "iso:country":"ES",
    "sg:address":"Calle de Perez Soto, 21",
    "sg:city":"Santa Cruz De Tenerife",
    "sg:orig_category":"Masajistas Kinesiterapeutas",
    "sg:phone":"+34 922 64 10 86",
    "sg:postcode":"38009",
    "sg:province":"Santa Cruz De Tenerife",
    "wof:name":"Andreu Requena Luis",
    "wof:placetype":"venue"
},
  "geometry": {"coordinates":[-16.2783546448,28.4629478455],"type":"Point"}
}