{
  "type": "Feature",
  "properties": {
    "addr:full":"Pl Pau (de La), 1 Vilallonga Camp Tarragona 43141",
    "addr:housenumber":"1",
    "addr:postcode":"43141",
    "addr:street":"Pl Pau De La",
    "iso:country":"ES",
    "sg:address":"Pl Pau (de La), 1",
    "sg:city":"Vilallonga Camp",
    "sg:orig_category":"Construcciones Met\u00c1licas",
    "sg:phone":"+34 977 84 00 87",
    "sg:postcode":"43141",
    "sg:province":"Tarragona",
    "wof:name":"Talleres J. Gomis S.l.",
    "wof:placetype":"venue"
},
  "geometry": {"coordinates":[1.206684947,41.2080802917],"type":"Point"}
}