{
  "type": "Feature",
  "properties": {
    "iso:country":"ES",
    "sg:address":"Plaza De La Iglesia, 1",
    "sg:city":"Cuevas Ca\u00f1art",
    "sg:orig_category":"Centros De Educaci\u00d3n Especial",
    "sg:phone":"+34 978 88 74 23",
    "sg:postcode":"44562",
    "sg:province":"Teruel",
    "wof:name":"C. R. A. De Castellote D. G. A. Cuevas De Ca\u00f1art",
    "wof:placetype":"venue"
},
  "geometry": {"coordinates":[-0.4289390147,40.7623214722],"type":"Point"}
}