{
  "type": "Feature",
  "properties": {
    "iso:country":"ES",
    "sg:address":"Calle de San Patricio, 12",
    "sg:city":"Madrid",
    "sg:orig_category":"\u00d3ptica: Instrumentos (fabricaci\u00d3n)",
    "sg:phone":"+34 914 72 23 33",
    "sg:postcode":"28019",
    "sg:province":"Madrid",
    "wof:name":"Gonzalez Martinez Ricardo",
    "wof:placetype":"venue"
},
  "geometry": {"coordinates":[-3.7251799107,40.3910903931],"type":"Point"}
}