{
  "type": "Feature",
  "properties": {
    "iso:country":"ES",
    "sg:address":"Calle de Salvador Alonso, 11",
    "sg:city":"Madrid",
    "sg:orig_category":"Fabricaci\u00d3n, Venta De Cuadros, Accesorios Para Enmarcar",
    "sg:phone":"+34 915 25 80 11",
    "sg:postcode":"28019",
    "sg:province":"Madrid",
    "wof:name":"Cobas Cabrera Jose Antonio",
    "wof:placetype":"venue"
},
  "geometry": {"coordinates":[-3.7375249863,40.3952674866],"type":"Point"}
}