{
  "type": "Feature",
  "properties": {
    "iso:country":"ES",
    "sg:address":"Avda Estella, 5",
    "sg:city":"Tafalla",
    "sg:orig_category":"Plomeros",
    "sg:phone":"+34 948 75 50 20",
    "sg:postcode":"31300",
    "sg:province":"Navarra",
    "wof:name":"Sakalta Rubio Y Olalla S.l",
    "wof:placetype":"venue"
},
  "geometry": {"coordinates":[-1.6781760454,42.5263748169],"type":"Point"}
}