{
  "type": "Feature",
  "properties": {
    "iso:country":"ES",
    "sg:address":"Carrer de Sant Vicent Ferrer, 41",
    "sg:city":"Crevillent",
    "sg:orig_category":"Masajes",
    "sg:phone":"+34 966 68 07 88",
    "sg:postcode":"03330",
    "sg:province":"Alicante",
    "wof:name":"Macia Dura Teresa Eulalia",
    "wof:placetype":"venue"
},
  "geometry": {"coordinates":[-0.8039150238,38.2469711304],"type":"Point"}
}