{
  "type": "Feature",
  "properties": {
    "iso:country":"ES",
    "sg:address":"Av Republica Argentina, 248",
    "sg:city":"Barcelona",
    "sg:orig_category":"Inmobiliaria (agencias)",
    "sg:phone":"+34 932 12 05 38",
    "sg:postcode":"08023",
    "sg:province":"Barcelona",
    "wof:name":"Fincas Lau S.l.",
    "wof:placetype":"venue"
},
  "geometry": {"coordinates":[2.1394538879,41.4130058289],"type":"Point"}
}