{
  "type": "Feature",
  "properties": {
    "iso:country":"ES",
    "sg:address":"Calle de Eguia General, 36",
    "sg:city":"Bilbao",
    "sg:orig_category":"Molduras, Junquillos, Listones Y Molduras Perforadas",
    "sg:phone":"+34 944 41 08 12",
    "sg:postcode":"48010",
    "sg:province":"Vizcaya",
    "wof:name":"Sancho Borrallo Rafael",
    "wof:placetype":"venue"
},
  "geometry": {"coordinates":[-2.9457719326,43.2592391968],"type":"Point"}
}