{
  "type": "Feature",
  "properties": {
    "addr:full":"Calle de Priorato, 37 Leganes Madrid 28915",
    "addr:housenumber":"37",
    "addr:postcode":"28915",
    "addr:street":"Calle De Priorato",
    "iso:country":"ES",
    "sg:address":"Calle de Priorato, 37",
    "sg:city":"Leganes",
    "sg:orig_category":"Loter\u00cda Y T\u00d3mbola",
    "sg:phone":"+34 916 86 61 08",
    "sg:postcode":"28915",
    "sg:province":"Madrid",
    "sg:website":"www.haciendomillonarios",
    "wof:name":"Rodriguez Molero Maria De Las Mercedes",
    "wof:placetype":"venue"
},
  "geometry": {"coordinates":[-3.7509241104,40.3397216797],"type":"Point"}
}