{
  "type": "Feature",
  "properties": {
    "iso:country":"ES",
    "sg:address":"Calle de Amapola, 3",
    "sg:city":"Zubia",
    "sg:orig_category":"Empresas De Carpinter\u00cda De Madera",
    "sg:phone":"+34 958 59 07 13",
    "sg:postcode":"18140",
    "sg:province":"Granada",
    "wof:name":"Romero Duran Carmelo",
    "wof:placetype":"venue"
},
  "geometry": {"coordinates":[-3.5736031532,37.1501464844],"type":"Point"}
}