{
  "type": "Feature",
  "properties": {
    "iso:country":"ES",
    "sg:address":"Calle de Prol Santa Barbara, 5",
    "sg:city":"Olias Rey",
    "sg:orig_category":"Promotores Constructores",
    "sg:phone":"+34 925 49 07 06",
    "sg:postcode":"45280",
    "sg:province":"Toledo",
    "wof:name":"Zarco Y Asociados Excavaciones Y Obras S.l.",
    "wof:placetype":"venue"
},
  "geometry": {"coordinates":[-3.9889214039,39.9427871704],"type":"Point"}
}