{
  "type": "Feature",
  "properties": {
    "iso:country":"ES",
    "sg:address":"Calle de Alvarez Quintero, 12",
    "sg:city":"Carmen",
    "sg:orig_category":"Psic\u00d3logos",
    "sg:phone":"+34 968 34 11 27",
    "sg:postcode":"30002",
    "sg:province":"Murcia",
    "wof:name":"Hilario Meca Pascual Salvador",
    "wof:placetype":"venue"
},
  "geometry": {"coordinates":[-1.1311708689,37.9773674011],"type":"Point"}
}