{
  "type": "Feature",
  "properties": {
    "addr:full":"Carr Roger De Flor, 154 Badalona Barcelona 08912",
    "addr:housenumber":"154",
    "addr:postcode":"08912",
    "addr:street":"Carr Roger De Flor",
    "iso:country":"ES",
    "sg:address":"Carr Roger De Flor, 154",
    "sg:city":"Badalona",
    "sg:orig_category":"Papeler\u00cdas, Librer\u00cdas",
    "sg:phone":"+34 933 87 98 45",
    "sg:postcode":"08912",
    "sg:province":"Barcelona",
    "wof:name":"Arajol S. A.",
    "wof:placetype":"venue"
},
  "geometry": {"coordinates":[2.2395348549,41.4450721741],"type":"Point"}
}