{
  "type": "Feature",
  "properties": {
    "iso:country":"ES",
    "sg:address":"Avda Alcalde De Lavadores, 122",
    "sg:city":"Bagunda",
    "sg:orig_category":"Electricidad, Electr\u00d3nica: Material Y Suministros (al Por Mayor)",
    "sg:phone":"+34 986 26 60 83",
    "sg:postcode":"36214",
    "sg:province":"Pontevedra",
    "sg:website":"www.maresa.net",
    "wof:name":"Maresa Electricidad S.l.",
    "wof:placetype":"venue"
},
  "geometry": {"coordinates":[-8.7059106827,42.2124443054],"type":"Point"}
}