{
  "type": "Feature",
  "properties": {
    "iso:country":"ES",
    "sg:address":"Calle de Doctor Gonzalez Serrano (del), 15",
    "sg:city":"Colmenar Viejo",
    "sg:orig_category":"Agencias De Viajes",
    "sg:phone":"+34 918 48 63 52",
    "sg:postcode":"28770",
    "sg:province":"Madrid",
    "wof:name":"Viajes Ananta S.l.l.",
    "wof:placetype":"venue"
},
  "geometry": {"coordinates":[-3.7670350075,40.6598739624],"type":"Point"}
}