{
  "type": "Feature",
  "properties": {
    "addr:full":"G. Brenan, 3 Alhaurin Grande M\u00e1laga 29120",
    "addr:housenumber":"3",
    "addr:postcode":"29120",
    "addr:street":"G. Brenan",
    "iso:country":"ES",
    "sg:address":"G. Brenan, 3",
    "sg:city":"Alhaurin Grande",
    "sg:orig_category":"Panader\u00cdas, Panader\u00cdas",
    "sg:phone":"+34 952 49 14 65",
    "sg:postcode":"29120",
    "sg:province":"M\u00e1laga",
    "wof:name":"El Rubio Comercial De Alimentacion S.l.",
    "wof:placetype":"venue"
},
  "geometry": {"coordinates":[-4.6911292076,36.6420783997],"type":"Point"}
}