{
  "type": "Feature",
  "properties": {
    "addr:full":"Carrer de Hurtado, 12 Barcelona Barcelona 08023",
    "addr:housenumber":"12",
    "addr:postcode":"08023",
    "addr:street":"Carrer De Hurtado",
    "iso:country":"ES",
    "sg:address":"Carrer de Hurtado, 12",
    "sg:city":"Barcelona",
    "sg:orig_category":"Edici\u00d3n De Diarios, Revistas, Boletines",
    "sg:phone":"+34 932 53 02 26",
    "sg:postcode":"08023",
    "sg:province":"Barcelona",
    "wof:name":"Nu\u00f1o Lopez Ana",
    "wof:placetype":"venue"
},
  "geometry": {"coordinates":[2.1407010555,41.4109458923],"type":"Point"}
}