{
  "type": "Feature",
  "properties": {
    "iso:country":"ES",
    "sg:address":"Av. Colon, 13",
    "sg:city":"S. Sebastian Gomera",
    "sg:orig_category":"\u00d3ptica: Instrumentos (fabricaci\u00d3n)",
    "sg:phone":"+34 922 87 06 26",
    "sg:postcode":"38800",
    "sg:province":"Santa Cruz De Tenerife",
    "wof:name":"Centro Optico Garajonay S.l.",
    "wof:placetype":"venue"
},
  "geometry": {"coordinates":[-17.1121845245,28.0919456482],"type":"Point"}
}