{
  "type": "Feature",
  "properties": {
    "addr:full":"Calle de Cristo Rey, 13 Andujar Ja\u00e9n 23740",
    "addr:housenumber":"13",
    "addr:postcode":"23740",
    "addr:street":"Calle De Cristo Rey",
    "iso:country":"ES",
    "sg:address":"Calle de Cristo Rey, 13",
    "sg:city":"Andujar",
    "sg:orig_category":"Arreglo, Reparaci\u00d3n, Piezas Sueltas De Televisi\u00d3n, V\u00cddeo, Hi",
    "sg:phone":"+34 953 51 36 09",
    "sg:postcode":"23740",
    "sg:province":"Ja\u00e9n",
    "wof:name":"Garcia Pe\u00f1alver Manuel Angel",
    "wof:placetype":"venue"
},
  "geometry": {"coordinates":[-4.0488200188,38.0412902832],"type":"Point"}
}