{
  "type": "Feature",
  "properties": {
    "iso:country":"ES",
    "sg:address":"Carrer de Santjoanistes, 28",
    "sg:city":"Barcelona",
    "sg:orig_category":"Restaurantes",
    "sg:phone":"+34 932 00 55 41",
    "sg:postcode":"08006",
    "sg:province":"Barcelona",
    "wof:name":"Vall Barella Ramon",
    "wof:placetype":"venue"
},
  "geometry": {"coordinates":[2.1463649273,41.4022941589],"type":"Point"}
}