{
  "type": "Feature",
  "properties": {
    "iso:country":"ES",
    "sg:address":"Calle de Rio Pliego, 2",
    "sg:city":"San Pio X",
    "sg:orig_category":"Comercio De Piezas De Recambio Y De Accesorios De Veh\u00cdculos, Veh\u00cdculos Industriales",
    "sg:phone":"+34 968 35 00 40",
    "sg:postcode":"30010",
    "sg:province":"Murcia",
    "sg:website":"www.rectisa.",
    "wof:name":"Rectificados S. A. L.",
    "wof:placetype":"venue"
},
  "geometry": {"coordinates":[-1.1358590126,37.9719581604],"type":"Point"}
}