{
  "type": "Feature",
  "properties": {
    "iso:country":"ES",
    "sg:address":"Av Gabriel Roca, 16",
    "sg:city":"Palma",
    "sg:orig_category":"Seguridad Social",
    "sg:phone":"+34 971 22 03 22",
    "sg:postcode":"07014",
    "sg:province":"Islas Baleares",
    "sg:website":"www.fimac.net",
    "wof:name":"Fimac Mutua De Accidentes De Trabajo",
    "wof:placetype":"venue"
},
  "geometry": {"coordinates":[2.6290299892,39.5657081604],"type":"Point"}
}