{
  "type": "Feature",
  "properties": {
    "addr:full":"Calle de Mayor, 1 Arenas -areeta Vizcaya 48930",
    "addr:housenumber":"1;areeta",
    "addr:postcode":"48930",
    "addr:street":"Calle De Mayor",
    "iso:country":"ES",
    "sg:address":"Calle de Mayor, 1",
    "sg:city":"Arenas -areeta",
    "sg:orig_category":"Colchones (fabricaci\u00d3n, Al Por Mayor, Al Por Menor)",
    "sg:phone":"+34 944 63 44 95",
    "sg:postcode":"48930",
    "sg:province":"Vizcaya",
    "wof:name":"El Siglo Modas S. A.",
    "wof:placetype":"venue"
},
  "geometry": {"coordinates":[-3.0157690048,43.3244285583],"type":"Point"}
}