{
  "type": "Feature",
  "properties": {
    "addr:full":"Pg Francesc Macia, 10 Rubi Barcelona 08191",
    "addr:housenumber":"10",
    "addr:postcode":"08191",
    "addr:street":"Pg Francesc Macia",
    "iso:country":"ES",
    "sg:address":"Pg Francesc Macia, 10",
    "sg:city":"Rubi",
    "sg:orig_category":"Fabricaci\u00d3n De Art\u00cdculos Y Equipos Deportivos Y De Ocio",
    "sg:phone":"+34 935 88 01 73",
    "sg:postcode":"08191",
    "sg:province":"Barcelona",
    "wof:name":"Esports Edelweiss S.l",
    "wof:placetype":"venue"
},
  "geometry": {"coordinates":[2.0315020084,41.4897880554],"type":"Point"}
}