{
  "type": "Feature",
  "properties": {
    "addr:full":"Ctra. Salamanca, Km. 0630,0 Jarilla C\u00e1ceres 10728",
    "addr:housenumber":"km.",
    "addr:postcode":"10728",
    "addr:street":"Ctra. Salamanca;0630,0 Jarilla Ca\u0301Ceres",
    "iso:country":"ES",
    "sg:address":"Ctra. Salamanca, Km. 0630,0",
    "sg:city":"Jarilla",
    "sg:orig_category":"Albergues",
    "sg:phone":"+34 927 47 70 57",
    "sg:postcode":"10728",
    "sg:province":"C\u00e1ceres",
    "wof:name":"Hostal Asturias S.l.",
    "wof:placetype":"venue"
},
  "geometry": {"coordinates":[-6.0025019646,40.172958374],"type":"Point"}
}