{
  "type": "Feature",
  "properties": {
    "iso:country":"ES",
    "sg:address":"Aginaga Auzoa, 63",
    "sg:city":"Aginaga",
    "sg:orig_category":"Producci\u00d3n De Sidra",
    "sg:phone":"+34 943 37 26 91",
    "sg:postcode":"20170",
    "sg:province":"Guip\u00f9zcoa",
    "wof:name":"Urdaira Sagardotegia",
    "wof:placetype":"venue"
},
  "geometry": {"coordinates":[-2.0539140701,43.2733459473],"type":"Point"}
}