{
  "type": "Feature",
  "properties": {
    "iso:country":"ES",
    "sg:address":"Avda Primero De Julio, 47",
    "sg:city":"Valdepe\u00f1as",
    "sg:orig_category":"Abogados",
    "sg:phone":"+34 926 31 02 37",
    "sg:postcode":"13300",
    "sg:province":"Ciudad Real",
    "wof:name":"Carceller Ruiz Maria Luisa",
    "wof:placetype":"venue"
},
  "geometry": {"coordinates":[-3.391283989,38.7575492859],"type":"Point"}
}