{
  "type": "Feature",
  "properties": {
    "addr:full":"Camino De Segovia, S/n Cantimpalos Segovia 40360",
    "addr:postcode":"40360",
    "addr:street":"Camino De Segovia S / N Cantimpalos Segovia",
    "iso:country":"ES",
    "sg:address":"Camino De Segovia, S/n",
    "sg:city":"Cantimpalos",
    "sg:orig_category":"Fabrica De Charcuter\u00cda",
    "sg:phone":"+34 921 49 63 14",
    "sg:postcode":"40360",
    "sg:province":"Segovia",
    "wof:name":"Mendoza Lopez Bego\u00f1a",
    "wof:placetype":"venue"
},
  "geometry": {"coordinates":[-4.1557478905,41.073299408],"type":"Point"}
}