{
  "type": "Feature",
  "properties": {
    "addr:full":"Calle de Valdes, 2 Oviedo Asturias 33012",
    "addr:housenumber":"2",
    "addr:postcode":"33012",
    "addr:street":"Calle De Valdes",
    "iso:country":"ES",
    "sg:address":"Calle de Valdes, 2",
    "sg:city":"Oviedo",
    "sg:orig_category":"Promotores Constructores",
    "sg:phone":"+34 985 25 06 66",
    "sg:postcode":"33012",
    "sg:province":"Asturias",
    "wof:name":"Comunidad De Propietarios Edificio Verdel",
    "wof:placetype":"venue"
},
  "geometry": {"coordinates":[-5.8747692108,43.3663101196],"type":"Point"}
}