{
  "type": "Feature",
  "properties": {
    "addr:full":"Plaz Iglesia (la), S/n Olvera C\u00e1diz 11690",
    "addr:housenumber":"s / n",
    "addr:postcode":"11690",
    "addr:street":"Ca\u0301Diz",
    "iso:country":"ES",
    "sg:address":"Plaz Iglesia (la), S/n",
    "sg:city":"Olvera",
    "sg:orig_category":"Museos",
    "sg:phone":"+34 956 12 08 16",
    "sg:postcode":"11690",
    "sg:province":"C\u00e1diz",
    "wof:name":"Carre\u00f1o Villalba Francisca",
    "wof:placetype":"venue"
},
  "geometry": {"coordinates":[-5.2676668167,36.9362831116],"type":"Point"}
}