{
  "type": "Feature",
  "properties": {
    "iso:country":"ES",
    "sg:address":"Carr Baldomer Sola, 6",
    "sg:city":"Badalona",
    "sg:orig_category":"Molduras, Junquillos, Listones Y Molduras Perforadas",
    "sg:phone":"+34 933 87 37 97",
    "sg:postcode":"08912",
    "sg:province":"Barcelona",
    "wof:name":"Monterde Sanchez Angeles Noelia",
    "wof:placetype":"venue"
},
  "geometry": {"coordinates":[2.2400250435,41.4476852417],"type":"Point"}
}