{
  "type": "Feature",
  "properties": {
    "iso:country":"ES",
    "sg:address":"Pol. Veintiseis, S/n",
    "sg:city":"Vallelado",
    "sg:orig_category":"Muebles Y Accesorios Para Cocinas Y Cuartos De Ba\u00d1o (al Por Menor)",
    "sg:phone":"+34 921 15 03 34",
    "sg:postcode":"40213",
    "sg:province":"Segovia",
    "wof:name":"Angel Cuellar E Hijos Sl",
    "wof:placetype":"venue"
},
  "geometry": {"coordinates":[-4.4259529114,41.4042625427],"type":"Point"}
}