{
  "type": "Feature",
  "properties": {
    "addr:full":"Calle de O'daly, 3 Santa Cruz Palma Santa Cruz De Tenerife 38700",
    "addr:housenumber":"3",
    "addr:postcode":"38700",
    "addr:street":"Calle De O'Daly",
    "iso:country":"ES",
    "sg:address":"Calle de O'daly, 3",
    "sg:city":"Santa Cruz Palma",
    "sg:orig_category":"Bazares, Art\u00cdculos De Limpieza Y De Cocina (al Por Menor)",
    "sg:phone":"+34 922 41 20 90",
    "sg:postcode":"38700",
    "sg:province":"Santa Cruz De Tenerife",
    "wof:name":"Tarachand Dadlani Jethanand",
    "wof:placetype":"venue"
},
  "geometry": {"coordinates":[-17.7659053802,28.6819610596],"type":"Point"}
}