{
  "type": "Feature",
  "properties": {
    "iso:country":"ES",
    "sg:address":"Idiazabal Kalea, 7",
    "sg:city":"Urnieta",
    "sg:orig_category":"Motocicletas (agentes, Concesionarios)",
    "sg:phone":"+34 943 55 10 04",
    "sg:postcode":"20130",
    "sg:province":"Guip\u00f9zcoa",
    "wof:name":"Bruna Sanchez Ramon",
    "wof:placetype":"venue"
},
  "geometry": {"coordinates":[-1.99198699,43.248790741],"type":"Point"}
}