{
  "type": "Feature",
  "properties": {
    "iso:country":"ES",
    "sg:address":"Avgd Generalitat Valenciana, 21",
    "sg:city":"Picanya",
    "sg:orig_category":"Empresas De Pintura Y Revestimientos",
    "sg:phone":"+34 961 59 18 91",
    "sg:postcode":"46210",
    "sg:province":"Valencia",
    "wof:name":"Pinturas Jusepe S.l.",
    "wof:placetype":"venue"
},
  "geometry": {"coordinates":[-0.4319069982,39.4325408936],"type":"Point"}
}