{
  "type": "Feature",
  "properties": {
    "iso:country":"ES",
    "sg:address":"Av Meridiana, 180",
    "sg:city":"Barcelona",
    "sg:classifiers":[
        {
            "category":"Autos & Motor Vehicles",
            "subcategory":"Automobile Sales",
            "type":"Retail Goods"
        }
    ],
    "sg:phone":"+34 933 49 55 24",
    "sg:postcode":"08026",
    "sg:province":"Barcelona",
    "wof:name":"J. Mendi V. S.l.",
    "wof:placetype":"venue"
},
  "geometry": {"coordinates":[2.1870319843,41.4121017456],"type":"Point"}
}