{
  "type": "Feature",
  "properties": {
    "iso:country":"ES",
    "sg:address":"C. Maya, 44",
    "sg:city":"Iru\u00f1a",
    "sg:orig_category":"Sales (al Por Mayor)",
    "sg:phone":"+34 948 15 07 43",
    "sg:postcode":"31003",
    "sg:province":"Navarra",
    "wof:name":"Alfamil S.a.",
    "wof:placetype":"venue"
},
  "geometry": {"coordinates":[-1.6369539499,42.8103904724],"type":"Point"}
}