{
  "type": "Feature",
  "properties": {
    "iso:country":"ES",
    "sg:address":"Rua Paseo (do), 22",
    "sg:city":"Ourense",
    "sg:orig_category":"Mutuas De Seguros",
    "sg:phone":"+34 988 24 02 56",
    "sg:postcode":"32003",
    "sg:province":"Ourense",
    "sg:website":"www.fraternidad.es",
    "wof:name":"Fraternidad-muprespa Mutua De Accidentes De Trabajo Y Enfermedades Profesionales",
    "wof:placetype":"venue"
},
  "geometry": {"coordinates":[-7.8643817902,42.3397369385],"type":"Point"}
}