{
  "type": "Feature",
  "properties": {
    "addr:full":"Calle de Diego De Siloe, 4 Burgos Burgos 09002",
    "addr:housenumber":"4",
    "addr:postcode":"09002",
    "addr:street":"Calle De Diego De Siloe",
    "iso:country":"ES",
    "sg:address":"Calle de Diego De Siloe, 4",
    "sg:city":"Burgos",
    "sg:orig_category":"Guarder\u00cdas",
    "sg:phone":"+34 947 26 00 61",
    "sg:postcode":"09002",
    "sg:province":"Burgos",
    "wof:name":"Religiosas Del Santisimo Sacramento",
    "wof:placetype":"venue"
},
  "geometry": {"coordinates":[-3.6724648476,42.3253631592],"type":"Point"}
}