{
  "type": "Feature",
  "properties": {
    "iso:country":"ES",
    "sg:address":"Calle de Adolfo Aznar, 33",
    "sg:city":"Zaragoza",
    "sg:orig_category":"Inmobiliaria (agencias)",
    "sg:phone":"+34 976 52 38 19",
    "sg:postcode":"50018",
    "sg:province":"Zaragoza",
    "wof:name":"Martin Jimenez Maria Angeles",
    "wof:placetype":"venue"
},
  "geometry": {"coordinates":[-0.8843560815,41.6760025024],"type":"Point"}
}