{
  "type": "Feature",
  "properties": {
    "addr:full":"Carrer de Navarra, 62 Granollers Barcelona 08401",
    "addr:housenumber":"62",
    "addr:postcode":"08401",
    "addr:street":"Carrer De Navarra",
    "iso:country":"ES",
    "sg:address":"Carrer de Navarra, 62",
    "sg:city":"Granollers",
    "sg:orig_category":"Asesor\u00cda Fiscal Y Jur\u00cddica",
    "sg:phone":"+34 938 70 71 02",
    "sg:postcode":"08401",
    "sg:province":"Barcelona",
    "wof:name":"Pelegrin Abas Nuria",
    "wof:placetype":"venue"
},
  "geometry": {"coordinates":[2.284003973,41.6041984558],"type":"Point"}
}