{
  "type": "Feature",
  "properties": {
    "addr:full":"Avda Carlos Pinilla, 41 Toro Zamora 49800",
    "addr:housenumber":"41",
    "addr:postcode":"49800",
    "addr:street":"Avda Carlos Pinilla",
    "iso:country":"ES",
    "sg:address":"Avda Carlos Pinilla, 41",
    "sg:city":"Toro",
    "sg:orig_category":"Carnicer\u00cdas, Carnicer\u00cdas",
    "sg:phone":"+34 980 69 29 32",
    "sg:postcode":"49800",
    "sg:province":"Zamora",
    "wof:name":"Castro Fernandez Enrique De",
    "wof:placetype":"venue"
},
  "geometry": {"coordinates":[-5.3973989487,41.5269813538],"type":"Point"}
}