{
  "type": "Feature",
  "properties": {
    "iso:country":"ES",
    "sg:address":"Carrer de Sant Lloren\u00c7, 27",
    "sg:city":"Rosales",
    "sg:orig_category":"Productos Qu\u00cdmicos (fabricaci\u00d3n, Al Por Mayor)",
    "sg:phone":"+34 937 21 13 25",
    "sg:postcode":"08192",
    "sg:province":"Barcelona",
    "wof:name":"Lluis Jane Busquets Laboratorio De Analisis S.l.",
    "wof:placetype":"venue"
},
  "geometry": {"coordinates":[2.0748400688,41.5303916931],"type":"Point"}
}