{
  "type": "Feature",
  "properties": {
    "iso:country":"ES",
    "sg:address":"Avda Alemania (de), 39",
    "sg:city":"Caceres",
    "sg:orig_category":"Venta, Alquiler, Mantenimiento De Telex, Teleimpresi\u00d3n",
    "sg:phone":"+34 927 62 93 14",
    "sg:postcode":"10005",
    "sg:province":"C\u00e1ceres",
    "wof:name":"Sistemas De Oficina De Caceres S.a.",
    "wof:placetype":"venue"
},
  "geometry": {"coordinates":[-6.3818092346,39.4484481812],"type":"Point"}
}