{
  "type": "Feature",
  "properties": {
    "addr:full":"Carrer de Pou, 61 Calafell Tarragona 43820",
    "addr:housenumber":"61",
    "addr:postcode":"43820",
    "addr:street":"Carrer De Pou",
    "iso:country":"ES",
    "sg:address":"Carrer de Pou, 61",
    "sg:city":"Calafell",
    "sg:orig_category":"Artes Gr\u00c1ficas, Artes Pl\u00c1sticas (curso)",
    "sg:phone":"+34 977 69 54 62",
    "sg:postcode":"43820",
    "sg:province":"Tarragona",
    "wof:name":"Industries Del Vidre Lasa S.l",
    "wof:placetype":"venue"
},
  "geometry": {"coordinates":[1.5719300508,41.1980018616],"type":"Point"}
}