{
  "type": "Feature",
  "properties": {
    "addr:full":"Calle de Padura Batalla De, 2 Bis Bilbao Vizcaya 48012",
    "addr:postcode":"48012",
    "addr:street":"Calle De Padura Batalla De 2 Bis",
    "iso:country":"ES",
    "sg:address":"Calle de Padura Batalla De, 2 Bis",
    "sg:city":"Bilbao",
    "sg:orig_category":"Agencias Y Asesores De Publicidad",
    "sg:phone":"+34 944 10 66 69",
    "sg:postcode":"48012",
    "sg:province":"Vizcaya",
    "sg:website":"www.ascan.es",
    "wof:name":"Servicios Multimedia Askan, S.l.",
    "wof:placetype":"venue"
},
  "geometry": {"coordinates":[-2.9461190701,43.2686500549],"type":"Point"}
}