{
  "type": "Feature",
  "properties": {
    "addr:full":"Calle de Eugenio Gross, 2 Malaga M\u00e1laga 29009",
    "addr:housenumber":"2",
    "addr:postcode":"29009",
    "addr:street":"Calle De Eugenio Gross;Ma\u0301Laga",
    "iso:country":"ES",
    "sg:address":"Calle de Eugenio Gross, 2",
    "sg:city":"Malaga",
    "sg:orig_category":"Inform\u00c1tica Equipo Y Programas (al Por Mayor)",
    "sg:phone":"+34 952 28 22 80",
    "sg:postcode":"29009",
    "sg:province":"M\u00e1laga",
    "wof:name":"Espa\u00f1a Aguera Juan",
    "wof:placetype":"venue"
},
  "geometry": {"coordinates":[-4.4356088638,36.7216720581],"type":"Point"}
}