{
  "type": "Feature",
  "properties": {
    "iso:country":"ES",
    "sg:address":"Trva Cascajo Segunda, 104",
    "sg:city":"Fuentespina",
    "sg:orig_category":"Grafistas",
    "sg:phone":"+34 947 51 33 44",
    "sg:postcode":"09470",
    "sg:province":"Burgos",
    "wof:name":"Gonzalez Esteban Carlos",
    "wof:placetype":"venue"
},
  "geometry": {"coordinates":[-3.6870539188,41.6330718994],"type":"Point"}
}