{
  "type": "Feature",
  "properties": {
    "addr:full":"Calle de San Rafael, 23 Zaragoza Zaragoza 50017",
    "addr:housenumber":"23",
    "addr:postcode":"50017",
    "addr:street":"Calle De San Rafael",
    "iso:country":"ES",
    "sg:address":"Calle de San Rafael, 23",
    "sg:city":"Zaragoza",
    "sg:orig_category":"Frutas Y Legumbres Frescas (al Por Mayor)",
    "sg:phone":"+34 976 32 39 63",
    "sg:postcode":"50017",
    "sg:province":"Zaragoza",
    "wof:name":"Frutas Mimadas S.l.",
    "wof:placetype":"venue"
},
  "geometry": {"coordinates":[-0.910458982,41.6513214111],"type":"Point"}
}