{
  "type": "Feature",
  "properties": {
    "addr:full":"Calle de Ribera (la), 19 Maracena Granada 18200",
    "addr:housenumber":"19",
    "addr:postcode":"18200",
    "addr:street":"Calle De Ribera La",
    "iso:country":"ES",
    "sg:address":"Calle de Ribera (la), 19",
    "sg:city":"Maracena",
    "sg:orig_category":"Fabricaci\u00d3n De Juguetes Autom\u00c1ticos",
    "sg:phone":"+34 958 42 01 13",
    "sg:postcode":"18200",
    "sg:province":"Granada",
    "wof:name":"Unibox Sur S.l.",
    "wof:placetype":"venue"
},
  "geometry": {"coordinates":[-3.6383140087,37.2062301636],"type":"Point"}
}