{
  "type": "Feature",
  "properties": {
    "iso:country":"ES",
    "sg:address":"Carrer de Planes, 25",
    "sg:city":"Sabadell",
    "sg:orig_category":"Asilos De Ancianos. Centros Privados",
    "sg:phone":"+34 937 26 52 40",
    "sg:postcode":"08201",
    "sg:province":"Barcelona",
    "wof:name":"Asistential Cresgra Services S.l.",
    "wof:placetype":"venue"
},
  "geometry": {"coordinates":[2.108591795,41.5437660217],"type":"Point"}
}