{
  "type": "Feature",
  "properties": {
    "addr:full":"Negro, S/n Galisteo C\u00e1ceres 10691",
    "addr:housenumber":"/ n",
    "addr:postcode":"10691",
    "addr:street":"S;Ca\u0301Ceres",
    "iso:country":"ES",
    "sg:address":"Negro, S/n",
    "sg:city":"Galisteo",
    "sg:orig_category":"Bebidas",
    "sg:phone":"+34 927 45 20 19",
    "sg:postcode":"10691",
    "sg:province":"C\u00e1ceres",
    "wof:name":"Toscano Martin Ciriaco",
    "wof:placetype":"venue"
},
  "geometry": {"coordinates":[-6.2683730125,39.9757537842],"type":"Point"}
}