{
  "type": "Feature",
  "properties": {
    "addr:full":"Calle de Matahacas, 8 Sevilla Sevilla 41003",
    "addr:housenumber":"8",
    "addr:postcode":"41003",
    "addr:street":"Calle De Matahacas",
    "iso:country":"ES",
    "sg:address":"Calle de Matahacas, 8",
    "sg:city":"Sevilla",
    "sg:classifiers":[
        {
            "category":"Government",
            "subcategory":"Post Office",
            "type":"Public Place"
        }
    ],
    "sg:phone":"+34 954 22 96 42",
    "sg:postcode":"41003",
    "sg:province":"Sevilla",
    "sg:tags":[
        "de",
        "yoga",
        "clases"
    ],
    "sg:website":"www.sevilla.sadhana.es",
    "wof:name":"Marquez Romero Juan Carlos",
    "wof:placetype":"venue"
},
  "geometry": {"coordinates":[-5.9856638908,37.3942222595],"type":"Point"}
}