{
  "type": "Feature",
  "properties": {
    "iso:country":"ES",
    "sg:address":"Pol Ind Jaraiz Vera, Km. 0016,2",
    "sg:city":"Jaraiz Vera",
    "sg:orig_category":"Distribuci\u00d3n De Petr\u00d3leo Y Derivados",
    "sg:phone":"+34 927 17 01 27",
    "sg:postcode":"10400",
    "sg:province":"C\u00e1ceres",
    "sg:website":"www.cepsa.es",
    "wof:name":"Carburantes Los Olivos S.l.",
    "wof:placetype":"venue"
},
  "geometry": {"coordinates":[-5.7516927719,40.0606231689],"type":"Point"}
}