{
  "type": "Feature",
  "properties": {
    "addr:full":"Carrer de Sant Magi, 9 Manresa Barcelona 08241",
    "addr:housenumber":"9",
    "addr:postcode":"08241",
    "addr:street":"Carrer De Sant Magi",
    "iso:country":"ES",
    "sg:address":"Carrer de Sant Magi, 9",
    "sg:city":"Manresa",
    "sg:orig_category":"Tapicer\u00cdas",
    "sg:phone":"+34 938 73 17 73",
    "sg:postcode":"08241",
    "sg:province":"Barcelona",
    "wof:name":"Romera Venteo Francesc",
    "wof:placetype":"venue"
},
  "geometry": {"coordinates":[1.8357950449,41.7247161865],"type":"Point"}
}