{
  "type": "Feature",
  "properties": {
    "iso:country":"ES",
    "sg:address":"Cementerio, 13",
    "sg:city":"Sevilleja De La Jara",
    "sg:orig_category":"Asilos De Ancianos. Centros Privados",
    "sg:phone":"+34 925 45 51 52",
    "sg:postcode":"45671",
    "sg:province":"Toledo",
    "wof:name":"Ayuntamiento De Sevilleja",
    "wof:placetype":"venue"
},
  "geometry": {"coordinates":[-4.9648489952,39.5768585205],"type":"Point"}
}