{
  "type": "Feature",
  "properties": {
    "iso:country":"ES",
    "sg:address":"Calle de Carretas, 43",
    "sg:city":"Herrera",
    "sg:orig_category":"Alimentaci\u00d3n General (al Por Menor)",
    "sg:phone":"+34 954 01 36 26",
    "sg:postcode":"41567",
    "sg:province":"Sevilla",
    "wof:name":"Monta\u00f1o Campos Juan",
    "wof:placetype":"venue"
},
  "geometry": {"coordinates":[-4.8487730026,37.366985321],"type":"Point"}
}