{
  "type": "Feature",
  "properties": {
    "addr:full":"Calle de Real, 7 Burgos Burgos 09007",
    "addr:housenumber":"7",
    "addr:postcode":"09007",
    "addr:street":"Calle De Real",
    "iso:country":"ES",
    "sg:address":"Calle de Real, 7",
    "sg:city":"Burgos",
    "sg:orig_category":"Droguer\u00cdas (al Por Menor)",
    "sg:phone":"+34 947 23 33 93",
    "sg:postcode":"09007",
    "sg:province":"Burgos",
    "wof:name":"Arnaiz Urrez Venancio",
    "wof:placetype":"venue"
},
  "geometry": {"coordinates":[-3.6691801548,42.3469047546],"type":"Point"}
}