{
  "type": "Feature",
  "properties": {
    "iso:country":"ES",
    "sg:address":"Carrer de Josep Irla, 16",
    "sg:city":"Masnou",
    "sg:orig_category":"Deportes Y Programas De Aventura",
    "sg:phone":"+34 935 55 53 75",
    "sg:postcode":"08320",
    "sg:province":"Barcelona",
    "wof:name":"Canalda Porcar Lourdes",
    "wof:placetype":"venue"
},
  "geometry": {"coordinates":[2.3217699528,41.4827346802],"type":"Point"}
}