{
  "type": "Feature",
  "properties": {
    "iso:country":"ES",
    "sg:address":"Carrer de Torras I Bages, 2",
    "sg:city":"Sabadell",
    "sg:orig_category":"Asesor\u00cda Fiscal Y Jur\u00cddica",
    "sg:phone":"+34 937 27 00 97",
    "sg:postcode":"08201",
    "sg:province":"Barcelona",
    "wof:name":"Ortomesa S.a.",
    "wof:placetype":"venue"
},
  "geometry": {"coordinates":[2.1057620049,41.5453834534],"type":"Point"}
}