{
  "type": "Feature",
  "properties": {
    "iso:country":"ES",
    "sg:address":"Ctra Sta Catalina, 70",
    "sg:city":"Murcia",
    "sg:orig_category":"Chapister\u00cda",
    "sg:phone":"+34 968 34 26 72",
    "sg:postcode":"30012",
    "sg:province":"Murcia",
    "wof:name":"Talleres Costa Calida S.l.",
    "wof:placetype":"venue"
},
  "geometry": {"coordinates":[-1.1373859644,37.9611701965],"type":"Point"}
}