{
  "type": "Feature",
  "properties": {
    "iso:country":"ES",
    "sg:address":"Avda Rioja (la), 10",
    "sg:city":"Najera",
    "sg:orig_category":"Fisioterapia",
    "sg:phone":"+34 941 36 17 40",
    "sg:postcode":"26300",
    "sg:province":"La Rioja",
    "wof:name":"Allcoz Alsasua Juan Jose",
    "wof:placetype":"venue"
},
  "geometry": {"coordinates":[-2.7317967415,42.4179534912],"type":"Point"}
}