{
  "type": "Feature",
  "properties": {
    "addr:full":"Calle de Josefa Segovia, 10 Jaen Ja\u00e9n 23001",
    "addr:housenumber":"10;jae\u0301n",
    "addr:postcode":"23001",
    "addr:street":"Calle De Josefa Segovia",
    "iso:country":"ES",
    "sg:address":"Calle de Josefa Segovia, 10",
    "sg:city":"Jaen",
    "sg:orig_category":"Internados & Ense\u00d1anza Privada",
    "sg:phone":"+34 953 23 84 20",
    "sg:postcode":"23001",
    "sg:province":"Ja\u00e9n",
    "wof:name":"Colegio Pedro Poveda De Itac",
    "wof:placetype":"venue"
},
  "geometry": {"coordinates":[-3.7877869606,37.764125824],"type":"Point"}
}