{
  "type": "Feature",
  "properties": {
    "addr:full":"Calle de Emilio Castelar, 3 Novelda Alicante 03660",
    "addr:housenumber":"3",
    "addr:postcode":"03660",
    "addr:street":"Calle De Emilio Castelar",
    "iso:country":"ES",
    "sg:address":"Calle de Emilio Castelar, 3",
    "sg:city":"Novelda",
    "sg:orig_category":"Ropa Para Se\u00d1oras Y Caballeros (al Por Menor)",
    "sg:phone":"+34 965 60 06 78",
    "sg:postcode":"03660",
    "sg:province":"Alicante",
    "wof:name":"Jover Mira Amparo",
    "wof:placetype":"venue"
},
  "geometry": {"coordinates":[-0.765632987,38.3851394653],"type":"Point"}
}