{
  "type": "Feature",
  "properties": {
    "addr:full":"Calle de Pedrote, 7 Aranda Duero Burgos 09400",
    "addr:housenumber":"7",
    "addr:postcode":"09400",
    "addr:street":"Calle De Pedrote",
    "iso:country":"ES",
    "sg:address":"Calle de Pedrote, 7",
    "sg:city":"Aranda Duero",
    "sg:orig_category":"Ense\u00d1anza: Idiomas",
    "sg:phone":"+34 947 50 48 67",
    "sg:postcode":"09400",
    "sg:province":"Burgos",
    "wof:name":"Liceo De Idiomas Modernos S.l.",
    "wof:placetype":"venue"
},
  "geometry": {"coordinates":[-3.6840689182,41.6711082458],"type":"Point"}
}