{
  "type": "Feature",
  "properties": {
    "iso:country":"ES",
    "sg:address":"Calle de Canalejas, 2",
    "sg:city":"Lucena",
    "sg:orig_category":"Estilistas Y Estudios De Estilo De Corte Y Confecci\u00d3n",
    "sg:phone":"+34 957 51 31 49",
    "sg:postcode":"14900",
    "sg:province":"C\u00f3rdoba",
    "wof:name":"Deluce S.l.",
    "wof:placetype":"venue"
},
  "geometry": {"coordinates":[-4.4856190681,37.4096107483],"type":"Point"}
}