{
  "type": "Feature",
  "properties": {
    "addr:full":"Pe\u00f1a Salon, S/n Lugo Asturias 33192",
    "addr:housenumber":"s / n",
    "addr:postcode":"33192",
    "iso:country":"ES",
    "sg:address":"Pe\u00f1a Salon, S/n",
    "sg:city":"Lugo",
    "sg:orig_category":"Congelados: Productos Alimentarios (fabricaci\u00d3n, Al Por Mayor)",
    "sg:phone":"+34 985 26 36 62",
    "sg:postcode":"33192",
    "sg:province":"Asturias",
    "wof:name":"Frionorte S. A.",
    "wof:placetype":"venue"
},
  "geometry": {"coordinates":[-5.7745718956,43.4596939087],"type":"Point"}
}