{
  "type": "Feature",
  "properties": {
    "addr:full":"Calle de Eusebio Gonzalez Suarez, 1 Valladolid Valladolid 47014",
    "addr:housenumber":"1",
    "addr:postcode":"47014",
    "addr:street":"Calle De Eusebio Gonzalez Suarez",
    "iso:country":"ES",
    "sg:address":"Calle de Eusebio Gonzalez Suarez, 1",
    "sg:city":"Valladolid",
    "sg:orig_category":"Alimentaci\u00d3n General (al Por Menor)",
    "sg:phone":"+34 983 37 07 14",
    "sg:postcode":"47014",
    "sg:province":"Valladolid",
    "wof:name":"Duque Martin Maria Isabel",
    "wof:placetype":"venue"
},
  "geometry": {"coordinates":[-4.7555289268,41.6341552734],"type":"Point"}
}