{
  "type": "Feature",
  "properties": {
    "iso:country":"ES",
    "sg:address":"Plaz Arrabal (del), 18",
    "sg:city":"Arevalo",
    "sg:orig_category":"Confecci\u00d3n (fabricaci\u00d3n, Al Por Mayor)",
    "sg:phone":"+34 920 30 01 77",
    "sg:postcode":"05200",
    "sg:province":"\u00c1vila",
    "wof:name":"Lermo Hernandez Laura",
    "wof:placetype":"venue"
},
  "geometry": {"coordinates":[-4.7200651169,41.0629768372],"type":"Point"}
}