{
  "type": "Feature",
  "properties": {
    "addr:full":"Calle de Montichelvo, 22 Valencia Valencia 46006",
    "addr:housenumber":"22",
    "addr:postcode":"46006",
    "addr:street":"Calle De Montichelvo",
    "iso:country":"ES",
    "sg:address":"Calle de Montichelvo, 22",
    "sg:city":"Valencia",
    "sg:orig_category":"Electricidad: Instaladores",
    "sg:phone":"+34 963 73 57 06",
    "sg:postcode":"46006",
    "sg:province":"Valencia",
    "wof:name":"Saiz Villanueva Jose Luis",
    "wof:placetype":"venue"
},
  "geometry": {"coordinates":[-0.3665269911,39.4569473267],"type":"Point"}
}