{
  "type": "Feature",
  "properties": {
    "addr:full":"Gazanda Bidea, 1 Mungia Vizcaya 48100",
    "addr:housenumber":"1",
    "addr:postcode":"48100",
    "addr:street":"Gazanda Bidea",
    "iso:country":"ES",
    "sg:address":"Gazanda Bidea, 1",
    "sg:city":"Mungia",
    "sg:orig_category":"Empresas De Portes Y Mensajer\u00cda",
    "sg:phone":"+34 946 74 21 13",
    "sg:postcode":"48100",
    "sg:province":"Vizcaya",
    "sg:website":"www.bcc.es",
    "wof:name":"Intxa Hermanos(bcc",
    "wof:placetype":"venue"
},
  "geometry": {"coordinates":[-2.8228890896,43.3520736694],"type":"Point"}
}