{
  "type": "Feature",
  "properties": {
    "addr:full":"Cra. Nacional Ii, Km. 0635,0 El Masnou Barcelona 08320",
    "addr:postcode":"08320",
    "addr:street":"Km. 0635,0",
    "iso:country":"ES",
    "sg:address":"Cra. Nacional Ii, Km. 0635,0",
    "sg:city":"El Masnou",
    "sg:orig_category":"Inmobiliaria (agencias)",
    "sg:phone":"+34 935 40 90 90",
    "sg:postcode":"08320",
    "sg:province":"Barcelona",
    "wof:name":"Assessors Immobiliaris Set Claus S.l.",
    "wof:placetype":"venue"
},
  "geometry": {"coordinates":[2.3147675991,41.4805679321],"type":"Point"}
}