{
  "type": "Feature",
  "properties": {
    "addr:full":"Ptge Forns, 22 Tarragona Tarragona 43001",
    "addr:housenumber":"22",
    "addr:postcode":"43001",
    "addr:street":"Ptge Forns",
    "iso:country":"ES",
    "sg:address":"Ptge Forns, 22",
    "sg:city":"Tarragona",
    "sg:orig_category":"Droguer\u00cdas (al Por Menor)",
    "sg:phone":"+34 977 23 49 28",
    "sg:postcode":"43001",
    "sg:province":"Tarragona",
    "wof:name":"Sanroman Fortuny Jose Maria",
    "wof:placetype":"venue"
},
  "geometry": {"coordinates":[1.247220993,41.1138916016],"type":"Point"}
}