{
  "type": "Feature",
  "properties": {
    "addr:full":"Calle de Argantonio, 18 Sevilla Sevilla 41008",
    "addr:housenumber":"18",
    "addr:postcode":"41008",
    "addr:street":"Calle De Argantonio",
    "iso:country":"ES",
    "sg:address":"Calle de Argantonio, 18",
    "sg:city":"Sevilla",
    "sg:orig_category":"Molduras, Junquillos, Listones Y Molduras Perforadas",
    "sg:phone":"+34 954 42 61 69",
    "sg:postcode":"41008",
    "sg:province":"Sevilla",
    "wof:name":"Ruiz Gil Francisco",
    "wof:placetype":"venue"
},
  "geometry": {"coordinates":[-5.9714865685,37.3989753723],"type":"Point"}
}