{
  "type": "Feature",
  "properties": {
    "iso:country":"ES",
    "sg:address":"Calle de Oro, 34",
    "sg:city":"Valladolid",
    "sg:orig_category":"Fabricaci\u00d3n De Material Y Sistemas De Se\u00d1alizaci\u00d3n De Carreteras, Urbanos Y De Obras",
    "sg:phone":"+34 983 21 22 56",
    "sg:postcode":"47012",
    "sg:province":"Valladolid",
    "wof:name":"Globalec Mantenimiento Vial",
    "wof:placetype":"venue"
},
  "geometry": {"coordinates":[-4.7037158012,41.6171302795],"type":"Point"}
}