{
  "type": "Feature",
  "properties": {
    "iso:country":"ES",
    "sg:address":"Pg Sant Joan, 146",
    "sg:city":"Barcelona",
    "sg:orig_category":"Molduras, Junquillos, Listones Y Molduras Perforadas",
    "sg:phone":"+34 934 57 81 59",
    "sg:postcode":"08037",
    "sg:province":"Barcelona",
    "wof:name":"Algides Pimentel Paulino",
    "wof:placetype":"venue"
},
  "geometry": {"coordinates":[2.1667530537,41.4018058777],"type":"Point"}
}