{
  "type": "Feature",
  "properties": {
    "iso:country":"ES",
    "sg:address":"Rua Colexio (do), 9",
    "sg:city":"Burela",
    "sg:orig_category":"Empresas De Carpinter\u00cda Met\u00c1lica",
    "sg:phone":"+34 982 58 60 69",
    "sg:postcode":"27880",
    "sg:province":"Lugo",
    "wof:name":"Aluminios Os Castros S.l.",
    "wof:placetype":"venue"
},
  "geometry": {"coordinates":[-7.3633384705,43.6673431396],"type":"Point"}
}