{
  "type": "Feature",
  "properties": {
    "iso:country":"ES",
    "sg:address":"Avda Doctores Terron, 16",
    "sg:city":"Vega Espinareda",
    "sg:orig_category":"Frutas, Legumbres Frescas Y Tempranas (al Por Menor)",
    "sg:phone":"+34 987 56 89 87",
    "sg:postcode":"24430",
    "sg:province":"Le\u00f3n",
    "wof:name":"Carro Fernandez Maria Angela",
    "wof:placetype":"venue"
},
  "geometry": {"coordinates":[-6.6570549011,42.7280273438],"type":"Point"}
}