{
  "type": "Feature",
  "properties": {
    "iso:country":"ES",
    "sg:address":"Avda Ermita (de La), 14",
    "sg:city":"Rinconada",
    "sg:orig_category":"Maquinaria Para Industrias Diversas",
    "sg:phone":"+34 955 79 84 48",
    "sg:postcode":"41309",
    "sg:province":"Sevilla",
    "wof:name":"Parque Guerra Carmen",
    "wof:placetype":"venue"
},
  "geometry": {"coordinates":[-5.9824738503,37.4847488403],"type":"Point"}
}