{
  "type": "Feature",
  "properties": {
    "iso:country":"ES",
    "sg:address":"Calle de Zaragoza, 1",
    "sg:city":"Angeles",
    "sg:classifiers":[
        {
            "category":"Community Center",
            "subcategory":"Youth",
            "type":"Public Place"
        }
    ],
    "sg:phone":"+34 915 31 35 56",
    "sg:postcode":"28223",
    "sg:province":"Madrid",
    "sg:tags":[
        "juventud",
        "administraci\u00d3n",
        "la",
        "en",
        "deporte",
        "el",
        "y"
    ],
    "wof:name":"Consulting Planesa S.l.",
    "wof:placetype":"venue"
},
  "geometry": {"coordinates":[-3.7794499397,40.4057426453],"type":"Point"}
}