{
  "type": "Feature",
  "properties": {
    "iso:country":"ES",
    "sg:address":"Calle de Cardenal Cisneros, 71",
    "sg:city":"Santander",
    "sg:orig_category":"Centros De Educaci\u00d3n Especial",
    "sg:phone":"+34 942 23 59 84",
    "sg:postcode":"39007",
    "sg:province":"Cantabria",
    "wof:name":"Colegio Antonio Mendoza",
    "wof:placetype":"venue"
},
  "geometry": {"coordinates":[-3.8178603649,43.4624595642],"type":"Point"}
}