{
  "type": "Feature",
  "properties": {
    "addr:full":"Plaz Paula, 10 Durcal Granada 18650",
    "addr:housenumber":"10",
    "addr:postcode":"18650",
    "addr:street":"Durcal Granada",
    "iso:country":"ES",
    "sg:address":"Plaz Paula, 10",
    "sg:city":"Durcal",
    "sg:orig_category":"Ropa Para Ni\u00d1os (al Por Menor)",
    "sg:phone":"+34 958 78 09 37",
    "sg:postcode":"18650",
    "sg:province":"Granada",
    "wof:name":"Morales Melguizo Rosa Maria",
    "wof:placetype":"venue"
},
  "geometry": {"coordinates":[-3.5704190731,36.9924316406],"type":"Point"}
}