{
  "type": "Feature",
  "properties": {
    "iso:country":"ES",
    "sg:address":"Calle de Villalon, 3",
    "sg:city":"Burgos",
    "sg:orig_category":"Reposter\u00cdas",
    "sg:phone":"+34 947 46 15 29",
    "sg:postcode":"09003",
    "sg:province":"Burgos",
    "wof:name":"Quintana Gimenez Ignacio",
    "wof:placetype":"venue"
},
  "geometry": {"coordinates":[-3.716105938,42.3413276672],"type":"Point"}
}