{
  "type": "Feature",
  "properties": {
    "addr:full":"Calle de Pintor Maella, 30 Valencia Valencia 46023",
    "addr:housenumber":"30",
    "addr:postcode":"46023",
    "addr:street":"Calle De Pintor Maella",
    "iso:country":"ES",
    "sg:address":"Calle de Pintor Maella, 30",
    "sg:city":"Valencia",
    "sg:orig_category":"Inmobiliaria (agencias)",
    "sg:phone":"+34 963 31 82 22",
    "sg:postcode":"46023",
    "sg:province":"Valencia",
    "wof:name":"Soler Pla Bartolome",
    "wof:placetype":"venue"
},
  "geometry": {"coordinates":[-0.3484990895,39.4590759277],"type":"Point"}
}