{
  "type": "Feature",
  "properties": {
    "addr:full":"Calle de Gabriel Gomez, 6 Madrid Madrid 28044",
    "addr:housenumber":"6",
    "addr:postcode":"28044",
    "addr:street":"Calle De Gabriel Gomez",
    "iso:country":"ES",
    "sg:address":"Calle de Gabriel Gomez, 6",
    "sg:city":"Madrid",
    "sg:orig_category":"Fabricaci\u00d3n, Venta, Instalaci\u00d3n De R\u00d3tulos, De R\u00d3tulos Luminosos",
    "sg:phone":"+34 915 08 01 37",
    "sg:postcode":"28044",
    "sg:province":"Madrid",
    "wof:name":"Giflo S.l.",
    "wof:placetype":"venue"
},
  "geometry": {"coordinates":[-3.7608428001,40.3679733276],"type":"Point"}
}