{
  "type": "Feature",
  "properties": {
    "iso:country":"ES",
    "sg:address":"Calle de San Isidro, 20",
    "sg:city":"Villacedre",
    "sg:orig_category":"Abogados",
    "sg:phone":"+34 987 21 32 69",
    "sg:postcode":"24194",
    "sg:province":"Le\u00f3n",
    "wof:name":"Rodriguez Fernandez Luis",
    "wof:placetype":"venue"
},
  "geometry": {"coordinates":[-5.5860338211,42.5638847351],"type":"Point"}
}