{
  "type": "Feature",
  "properties": {
    "addr:full":"Calle de Virgen De La Vega, 23 Haro La Rioja 26200",
    "addr:housenumber":"23",
    "addr:postcode":"26200",
    "addr:street":"Calle De Virgen De La Vega",
    "iso:country":"ES",
    "sg:address":"Calle de Virgen De La Vega, 23",
    "sg:city":"Haro",
    "sg:orig_category":"Peleter\u00cdas",
    "sg:phone":"+34 941 31 22 13",
    "sg:postcode":"26200",
    "sg:province":"La Rioja",
    "wof:name":"Haro Piel S. A.",
    "wof:placetype":"venue"
},
  "geometry": {"coordinates":[-2.8491139412,42.5769996643],"type":"Point"}
}