{
  "type": "Feature",
  "properties": {
    "addr:full":"Calle de Cuerda, S/n Corral Almaguer Toledo 45880",
    "addr:housenumber":"s / n",
    "addr:postcode":"45880",
    "addr:street":"Calle De Cuerda",
    "iso:country":"ES",
    "sg:address":"Calle de Cuerda, S/n",
    "sg:city":"Corral Almaguer",
    "sg:orig_category":"Cajas Para Embalar",
    "sg:phone":"+34 925 19 01 83",
    "sg:postcode":"45880",
    "sg:province":"Toledo",
    "wof:name":"Caja Rural Provincial De Toledo",
    "wof:placetype":"venue"
},
  "geometry": {"coordinates":[-3.1670365334,39.7587890625],"type":"Point"}
}