{
  "type": "Feature",
  "properties": {
    "iso:country":"ES",
    "sg:address":"Calle de Ponferrada, 21",
    "sg:city":"Madrid",
    "sg:orig_category":"Talleres: Ropa A Medida",
    "sg:phone":"+34 917 30 85 95",
    "sg:postcode":"28029",
    "sg:province":"Madrid",
    "wof:name":"Maldonado Serrano Santiago",
    "wof:placetype":"venue"
},
  "geometry": {"coordinates":[-3.7132968903,40.4748878479],"type":"Point"}
}