{
  "type": "Feature",
  "properties": {
    "iso:country":"ES",
    "sg:address":"Calle de Simon Hernandez (de), 60",
    "sg:city":"Mostoles",
    "sg:orig_category":"Peluquer\u00cdas, Peluquer\u00cda Mixta",
    "sg:phone":"+34 916 47 19 43",
    "sg:postcode":"28937",
    "sg:province":"Madrid",
    "wof:name":"Luna Estilistas S.l. Unipersonal",
    "wof:placetype":"venue"
},
  "geometry": {"coordinates":[-3.8565049171,40.3200187683],"type":"Point"}
}