{
  "type": "Feature",
  "properties": {
    "iso:country":"ES",
    "sg:address":"Calle de Virgen De Las Angustias, 15",
    "sg:city":"Palmas De Gran Canaria",
    "sg:orig_category":"Peluquer\u00cdas, Peluquer\u00cda Mixta",
    "sg:phone":"+34 928 36 93 82",
    "sg:postcode":"35013",
    "sg:province":"Las Palmas",
    "wof:name":"Medina Gonzalez Gonzalo",
    "wof:placetype":"venue"
},
  "geometry": {"coordinates":[-15.4318666458,28.1064910889],"type":"Point"}
}