{
  "type": "Feature",
  "properties": {
    "addr:full":"Avda Hytasa, 15 Sevilla Sevilla 41006",
    "addr:housenumber":"15",
    "addr:postcode":"41006",
    "addr:street":"Avda Hytasa",
    "iso:country":"ES",
    "sg:address":"Avda Hytasa, 15",
    "sg:city":"Sevilla",
    "sg:orig_category":"Servicios De Telecomunicaciones",
    "sg:phone":"+34 954 66 39 02",
    "sg:postcode":"41006",
    "sg:province":"Sevilla",
    "sg:website":"www.ofitel.es",
    "wof:name":"Ofitel Ofimatica Y Telecomunicaciones S.l.",
    "wof:placetype":"venue"
},
  "geometry": {"coordinates":[-5.9630298615,37.3725738525],"type":"Point"}
}