{
  "type": "Feature",
  "properties": {
    "iso:country":"ES",
    "sg:address":"Calle de Rio Jarama, S/n",
    "sg:city":"Poligono Sta M. De Benquerencia",
    "sg:orig_category":"Electricidad: Equipos Industriales, Componentes (fabricaci\u00d3n)",
    "sg:phone":"+34 925 24 08 01",
    "sg:postcode":"45007",
    "sg:province":"Toledo",
    "wof:name":"Suministros Electricos Morales S.a.",
    "wof:placetype":"venue"
},
  "geometry": {"coordinates":[-4.0244760513,39.8567771912],"type":"Point"}
}