{
  "type": "Feature",
  "properties": {
    "iso:country":"ES",
    "sg:address":"Pg Gracia, 55",
    "sg:city":"Barcelona",
    "sg:orig_category":"Compraventa De Antig\u00dcedades",
    "sg:phone":"+34 932 15 76 22",
    "sg:postcode":"08007",
    "sg:province":"Barcelona",
    "wof:name":"Vives De La Cortada Sole Sara",
    "wof:placetype":"venue"
},
  "geometry": {"coordinates":[2.164087534,41.3926239014],"type":"Point"}
}