{
  "type": "Feature",
  "properties": {
    "iso:country":"ES",
    "sg:address":"Av Pi I Margall, 55",
    "sg:city":"Caldes Montbui",
    "sg:orig_category":"Molduras, Junquillos, Listones Y Molduras Perforadas",
    "sg:phone":"+34 938 65 02 21",
    "sg:postcode":"08140",
    "sg:province":"Barcelona",
    "wof:name":"Membrado Conesa Luis",
    "wof:placetype":"venue"
},
  "geometry": {"coordinates":[2.1648209095,41.6307525635],"type":"Point"}
}