{
  "type": "Feature",
  "properties": {
    "iso:country":"ES",
    "sg:address":"Rua Pura Y Dora Vazquez, 2",
    "sg:city":"Ourense",
    "sg:orig_category":"Caf\u00c9s, Bares, Cervecer\u00cdas",
    "sg:phone":"+34 988 36 62 57",
    "sg:postcode":"32002",
    "sg:province":"Ourense",
    "sg:website":"www.cgamallo.com",
    "wof:name":"Antasonia S.l.",
    "wof:placetype":"venue"
},
  "geometry": {"coordinates":[-7.8776021004,42.3342933655],"type":"Point"}
}