{
  "type": "Feature",
  "properties": {
    "addr:full":"Calle de Ruise\u00d1or (el), 57 Huercal Almeria Almer\u00eda 04230",
    "addr:postcode":"04230",
    "addr:street":"Calle De Ruisen\u0303Or El;Huercal;Almeri\u0301A",
    "iso:country":"ES",
    "sg:address":"Calle de Ruise\u00d1or (el), 57",
    "sg:city":"Huercal Almeria",
    "sg:orig_category":"Mec\u00c1nico Del Autom\u00d3vil",
    "sg:phone":"+34 950 30 13 30",
    "sg:postcode":"04230",
    "sg:province":"Almer\u00eda",
    "wof:name":"Castillo Salas Gregorio",
    "wof:placetype":"venue"
},
  "geometry": {"coordinates":[-2.442109108,36.8873100281],"type":"Point"}
}