{
  "type": "Feature",
  "properties": {
    "addr:full":"Carr Venus, 6 Lleida Lleida 25003",
    "addr:housenumber":"6",
    "addr:postcode":"25003",
    "addr:street":"Carr Venus",
    "iso:country":"ES",
    "sg:address":"Carr Venus, 6",
    "sg:city":"Lleida",
    "sg:orig_category":"Papeler\u00cdas: Art\u00cdculos (al Por Mayor)",
    "sg:phone":"+34 973 26 21 57",
    "sg:postcode":"25003",
    "sg:province":"Lleida",
    "wof:name":"Carrera Farra Jaime",
    "wof:placetype":"venue"
},
  "geometry": {"coordinates":[0.6125699878,41.6117973328],"type":"Point"}
}