{
  "type": "Feature",
  "properties": {
    "iso:country":"ES",
    "sg:address":"Calle de Torno (del), 12",
    "sg:city":"Partija-santa Monica",
    "sg:orig_category":"Fabricaci\u00d3n De Muebles",
    "sg:phone":"+34 916 66 60 54",
    "sg:postcode":"28529",
    "sg:province":"Madrid",
    "wof:name":"Grancasa S.l.",
    "wof:placetype":"venue"
},
  "geometry": {"coordinates":[-3.5102670193,40.314289093],"type":"Point"}
}