{
  "type": "Feature",
  "properties": {
    "iso:country":"ES",
    "sg:address":"Ctra Valencia-alicante, Km. 0088,5",
    "sg:city":"S. Juan Alicante",
    "sg:orig_category":"Agentes, Concesionarios Y Sucursales De Veh\u00cdculos",
    "sg:phone":"+34 965 93 90 40",
    "sg:postcode":"03550",
    "sg:province":"Alicante",
    "sg:website":"www.gruposala.com",
    "wof:name":"Sala Hermanos Import S.l.",
    "wof:placetype":"venue"
},
  "geometry": {"coordinates":[-0.4289290011,38.400390625],"type":"Point"}
}