{
  "type": "Feature",
  "properties": {
    "iso:country":"ES",
    "sg:address":"Calle de Sofia, 64",
    "sg:city":"Madrid",
    "sg:orig_category":"Confiter\u00cdas, Chocolater\u00cdas (al Por Menor)",
    "sg:phone":"+34 917 75 95 03",
    "sg:postcode":"28022",
    "sg:province":"Madrid",
    "wof:name":"Chuping  Li",
    "wof:placetype":"venue"
},
  "geometry": {"coordinates":[-3.6014499664,40.4294776917],"type":"Point"}
}