{
  "type": "Feature",
  "properties": {
    "iso:country":"ES",
    "sg:address":"Calle de Barrio Gimeno, 11",
    "sg:city":"Burgos",
    "sg:orig_category":"Agencias Y Agentes Comerciales, Representantes",
    "sg:phone":"+34 947 20 67 70",
    "sg:postcode":"09001",
    "sg:province":"Burgos",
    "wof:name":"Herrera Ballesteros Fernando",
    "wof:placetype":"venue"
},
  "geometry": {"coordinates":[-3.7028458118,42.3360481262],"type":"Point"}
}