{
  "type": "Feature",
  "properties": {
    "addr:full":"Avda Puerta Del Sur, 4 Jerez De La Frontera C\u00e1diz 11408",
    "addr:housenumber":"4",
    "addr:postcode":"11408",
    "addr:street":"Avda Puerta Del Sur",
    "iso:country":"ES",
    "sg:address":"Avda Puerta Del Sur, 4",
    "sg:city":"Jerez De La Frontera",
    "sg:orig_category":"Aceros Inoxidables",
    "sg:phone":"+34 956 14 01 93",
    "sg:postcode":"11408",
    "sg:province":"C\u00e1diz",
    "wof:name":"Cordobesa De Fluidos S.l.",
    "wof:placetype":"venue"
},
  "geometry": {"coordinates":[-6.1482620239,36.6722297668],"type":"Point"}
}