{
  "type": "Feature",
  "properties": {
    "iso:country":"ES",
    "sg:address":"Calle de Gran Via, 47",
    "sg:city":"Salamanca",
    "sg:orig_category":"Caf\u00c9s, Bares, Cervecer\u00cdas",
    "sg:phone":"+34 923 26 35 18",
    "sg:postcode":"37001",
    "sg:province":"Salamanca",
    "wof:name":"Cafeteria Marfil",
    "wof:placetype":"venue"
},
  "geometry": {"coordinates":[-5.6605191231,40.9651031494],"type":"Point"}
}