{
  "type": "Feature",
  "properties": {
    "addr:full":"Calle de Duque De Calabria, 6 Valencia Valencia 46005",
    "addr:housenumber":"6",
    "addr:postcode":"46005",
    "addr:street":"Calle De Duque De Calabria",
    "iso:country":"ES",
    "sg:address":"Calle de Duque De Calabria, 6",
    "sg:city":"Valencia",
    "sg:orig_category":"Muebles",
    "sg:phone":"+34 963 33 58 31",
    "sg:postcode":"46005",
    "sg:province":"Valencia",
    "sg:website":"www.esquitino.com",
    "wof:name":"Esquitino Martinez S.a.",
    "wof:placetype":"venue"
},
  "geometry": {"coordinates":[-0.3664591014,39.4630432129],"type":"Point"}
}