{
  "type": "Feature",
  "properties": {
    "iso:country":"ES",
    "sg:address":"Carrer de Arimon, 8",
    "sg:city":"Barcelona",
    "sg:orig_category":"Arquitectos",
    "sg:phone":"+34 932 11 41 29",
    "sg:postcode":"08022",
    "sg:province":"Barcelona",
    "wof:name":"Zaragoza De Pedro Isabel",
    "wof:placetype":"venue"
},
  "geometry": {"coordinates":[2.1374418736,41.4049377441],"type":"Point"}
}