{
  "type": "Feature",
  "properties": {
    "iso:country":"ES",
    "sg:address":"Avda Abaro, 6",
    "sg:city":"Portugalete",
    "sg:orig_category":"Cajas De Ahorro",
    "sg:phone":"+34 946 02 61 28",
    "sg:postcode":"48920",
    "sg:province":"Vizcaya",
    "sg:website":"www.bbk.es",
    "wof:name":"Bilbao Bizkaia Kutxa",
    "wof:placetype":"venue"
},
  "geometry": {"coordinates":[-3.0202429295,43.3211250305],"type":"Point"}
}