{
  "type": "Feature",
  "properties": {
    "addr:full":"Poli Industrial Alesves/villafranca, S/n Villafranca Navarra 31330",
    "addr:housenumber":"s / n",
    "addr:postcode":"31330",
    "iso:country":"ES",
    "sg:address":"Poli Industrial Alesves/villafranca, S/n",
    "sg:city":"Villafranca",
    "sg:orig_category":"Conservas De Legumbres (fabricaci\u00d3n, Al Por Mayor)",
    "sg:phone":"+34 948 84 58 35",
    "sg:postcode":"31330",
    "sg:province":"Navarra",
    "sg:website":"www.gutarra.com",
    "wof:name":"Conservas Hijos De Manuel Sanchez Basarte S.a.",
    "wof:placetype":"venue"
},
  "geometry": {"coordinates":[-1.7458839417,42.2780952454],"type":"Point"}
}