{
  "type": "Feature",
  "properties": {
    "iso:country":"ES",
    "sg:address":"Calle de San Francisco De Asis, 1",
    "sg:city":"Totana",
    "sg:orig_category":"Peluqueros: De Se\u00d1oras",
    "sg:phone":"+34 968 42 29 02",
    "sg:postcode":"30850",
    "sg:province":"Murcia",
    "wof:name":"Ruiz Peran Ana Rosa",
    "wof:placetype":"venue"
},
  "geometry": {"coordinates":[-1.4989290237,37.7752990723],"type":"Point"}
}