{
  "type": "Feature",
  "properties": {
    "addr:full":"Calle de Puerta Del Mar, 1 Almeria Almer\u00eda 04002",
    "addr:housenumber":"1",
    "addr:postcode":"04002",
    "addr:street":"Calle De Puerta Del Mar",
    "iso:country":"ES",
    "sg:address":"Calle de Puerta Del Mar, 1",
    "sg:city":"Almeria",
    "sg:orig_category":"Agencias De Viajes",
    "sg:phone":"+34 950 62 05 75",
    "sg:postcode":"04002",
    "sg:province":"Almer\u00eda",
    "wof:name":"Viajes Paris S.a.",
    "wof:placetype":"venue"
},
  "geometry": {"coordinates":[-2.467674017,36.8364486694],"type":"Point"}
}