{
  "type": "Feature",
  "properties": {
    "addr:full":"Carrer de Josep Anselm Clave, 8 Palma Islas Baleares 07002",
    "addr:housenumber":"8",
    "addr:postcode":"07002",
    "addr:street":"Carrer De Josep Anselm Clave",
    "iso:country":"ES",
    "sg:address":"Carrer de Josep Anselm Clave, 8",
    "sg:city":"Palma",
    "sg:orig_category":"Autob\u00das (explotaci\u00d3n Y Servicios De)",
    "sg:phone":"+34 971 72 32 39",
    "sg:postcode":"07002",
    "sg:province":"Islas Baleares",
    "wof:name":"Aplicaciones Y Sistemas Integrales Para El Transporte",
    "wof:placetype":"venue"
},
  "geometry": {"coordinates":[2.6550564766,39.5732841492],"type":"Point"}
}