{
  "type": "Feature",
  "properties": {
    "iso:country":"ES",
    "sg:address":"Avda Pio Xii, 23",
    "sg:city":"Logro\u00f1o",
    "sg:orig_category":"Librer\u00cdas",
    "sg:phone":"+34 941 25 92 44",
    "sg:postcode":"26003",
    "sg:province":"La Rioja",
    "wof:name":"Enriquez Sanchez Fernando",
    "wof:placetype":"venue"
},
  "geometry": {"coordinates":[-2.4423179626,42.4601173401],"type":"Point"}
}