{
  "type": "Feature",
  "properties": {
    "addr:full":"Calle de Pilar (el), 3 Aldeanueva Ebro La Rioja 26559",
    "addr:housenumber":"3",
    "addr:postcode":"26559",
    "addr:street":"Calle De Pilar El;Ebro",
    "iso:country":"ES",
    "sg:address":"Calle de Pilar (el), 3",
    "sg:city":"Aldeanueva Ebro",
    "sg:orig_category":"Empresas De Desmonte",
    "sg:phone":"+34 941 16 34 06",
    "sg:postcode":"26559",
    "sg:province":"La Rioja",
    "wof:name":"Arpon Calonge Tomas",
    "wof:placetype":"venue"
},
  "geometry": {"coordinates":[-1.8902709484,42.2290916443],"type":"Point"}
}