{
  "type": "Feature",
  "properties": {
    "iso:country":"ES",
    "sg:address":"Avda Mariano Andres, 120",
    "sg:city":"Le\u00f3n",
    "sg:orig_category":"Peluquer\u00cdas, Peluquer\u00cda Mixta",
    "sg:phone":"+34 987 24 29 90",
    "sg:postcode":"24008",
    "sg:province":"Le\u00f3n",
    "wof:name":"Franco Bernardo Maria Esther",
    "wof:placetype":"venue"
},
  "geometry": {"coordinates":[-5.5700221062,42.6124420166],"type":"Point"}
}