{
  "type": "Feature",
  "properties": {
    "iso:country":"ES",
    "sg:address":"Pg Del Penyal D'ifach, 38",
    "sg:city":"Coma",
    "sg:orig_category":"Agencias Y Agentes Comerciales, Representantes",
    "sg:phone":"+34 963 63 83 51",
    "sg:postcode":"46980",
    "sg:province":"Valencia",
    "wof:name":"Olmos Tarazona Alberto",
    "wof:placetype":"venue"
},
  "geometry": {"coordinates":[-0.4247039855,39.5201950073],"type":"Point"}
}