{
  "type": "Feature",
  "properties": {
    "iso:country":"ES",
    "sg:address":"Calle de Farmaceutico Obdulio Fernandez, 36",
    "sg:city":"Burgos",
    "sg:orig_category":"Caf\u00c9s, Bares, Cervecer\u00cdas",
    "sg:phone":"+34 947 22 75 58",
    "sg:postcode":"09006",
    "sg:province":"Burgos",
    "wof:name":"Bueno Diez Soluciones S.l.",
    "wof:placetype":"venue"
},
  "geometry": {"coordinates":[-3.682156086,42.3469657898],"type":"Point"}
}