{
  "type": "Feature",
  "properties": {
    "addr:full":"Alemani-p I Prado De Feria, 22 Medina-sidonia C\u00e1diz 11170",
    "addr:housenumber":"22",
    "addr:postcode":"11170",
    "addr:street":"Feria;Ca\u0301Diz",
    "iso:country":"ES",
    "sg:address":"Alemani-p I Prado De Feria, 22",
    "sg:city":"Medina-sidonia",
    "sg:orig_category":"Escayola Y Productos De Escayola (fabricaci\u00d3n, Al Por Mayor)",
    "sg:phone":"+34 956 41 23 82",
    "sg:postcode":"11170",
    "sg:province":"C\u00e1diz",
    "wof:name":"Escayolas Gomez C.b.",
    "wof:placetype":"venue"
},
  "geometry": {"coordinates":[-5.9282741547,36.463180542],"type":"Point"}
}