{
  "type": "Feature",
  "properties": {
    "addr:full":"Calle de En Sanz, 6 Valencia Valencia 46001",
    "addr:housenumber":"6",
    "addr:postcode":"46001",
    "addr:street":"Calle De En Sanz",
    "iso:country":"ES",
    "sg:address":"Calle de En Sanz, 6",
    "sg:city":"Valencia",
    "sg:orig_category":"Ingenier\u00cda, Centros De Estudios (diversos)",
    "sg:phone":"+34 963 51 57 60",
    "sg:postcode":"46001",
    "sg:province":"Valencia",
    "wof:name":"Ival Ingenieros S.l.u",
    "wof:placetype":"venue"
},
  "geometry": {"coordinates":[-0.3769130111,39.4687919617],"type":"Point"}
}