{
  "type": "Feature",
  "properties": {
    "iso:country":"ES",
    "sg:address":"Calle de Sevilla, 8",
    "sg:city":"Malaga",
    "sg:orig_category":"Asociaciones Humanitarias, De Cooperaci\u00d3n, De Acci\u00d3n Social",
    "sg:phone":"+34 952 10 41 29",
    "sg:postcode":"29009",
    "sg:province":"M\u00e1laga",
    "wof:name":"Ara\u00f1a Tejido De Asociaciones Por El Empleo Juvenil",
    "wof:placetype":"venue"
},
  "geometry": {"coordinates":[-4.4296159744,36.7241821289],"type":"Point"}
}