{
  "type": "Feature",
  "properties": {
    "addr:full":"Calle de Txurruka, 5 Donostia-san Sebastian Guip\u00f9zcoa 20004",
    "addr:housenumber":"5",
    "addr:postcode":"20004",
    "addr:street":"Calle De Txurruka",
    "iso:country":"ES",
    "sg:address":"Calle de Txurruka, 5",
    "sg:city":"Donostia-san Sebastian",
    "sg:orig_category":"Farmacias",
    "sg:phone":"+34 943 42 62 24",
    "sg:postcode":"20004",
    "sg:province":"Guip\u00f9zcoa",
    "wof:name":"Echeverria Lecuona Maria Luisa",
    "wof:placetype":"venue"
},
  "geometry": {"coordinates":[-1.9819250107,43.3202934265],"type":"Point"}
}