{
  "type": "Feature",
  "properties": {
    "addr:full":"Calle de Zarauz, 6 Madrid Madrid 28023",
    "addr:housenumber":"6",
    "addr:postcode":"28023",
    "addr:street":"Calle De Zarauz",
    "iso:country":"ES",
    "sg:address":"Calle de Zarauz, 6",
    "sg:city":"Madrid",
    "sg:orig_category":"Asilos De Ancianos. Centros Privados",
    "sg:phone":"+34 913 72 94 98",
    "sg:postcode":"28023",
    "sg:province":"Madrid",
    "wof:name":"Florida 95s.l.",
    "wof:placetype":"venue"
},
  "geometry": {"coordinates":[-3.8136310577,40.4704551697],"type":"Point"}
}