{
  "type": "Feature",
  "properties": {
    "addr:full":"Calle de Molinos De Abajo, 3 Alhaurin El Grande M\u00e1laga 29120",
    "addr:housenumber":"3",
    "addr:postcode":"29120",
    "addr:street":"Calle De Molinos De Abajo",
    "iso:country":"ES",
    "sg:address":"Calle de Molinos De Abajo, 3",
    "sg:city":"Alhaurin El Grande",
    "sg:orig_category":"Alimentaci\u00d3n General (al Por Menor)",
    "sg:phone":"+34 952 49 09 66",
    "sg:postcode":"29120",
    "sg:province":"M\u00e1laga",
    "wof:name":"Bravo Fernandez Jose",
    "wof:placetype":"venue"
},
  "geometry": {"coordinates":[-4.6891307831,36.6445236206],"type":"Point"}
}