{
  "type": "Feature",
  "properties": {
    "iso:country":"ES",
    "sg:address":"Avda Cruz Roja Espa\u00d1ola (de La), S/n",
    "sg:city":"Cuenca",
    "sg:orig_category":"Soportes L\u00d3gicos, Programas Integradores De Aplicaciones (progiciels)",
    "sg:phone":"+34 969 23 48 75",
    "sg:postcode":"16002",
    "sg:province":"Cuenca",
    "sg:website":"www.solucionesip.com",
    "wof:name":"Soluciones Hispanas",
    "wof:placetype":"venue"
},
  "geometry": {"coordinates":[-2.1614289284,40.0741081238],"type":"Point"}
}