{
  "type": "Feature",
  "properties": {
    "addr:full":"Calle de Vergara, 33 Salamanca Salamanca 37003",
    "addr:housenumber":"33",
    "addr:postcode":"37003",
    "addr:street":"Calle De Vergara",
    "iso:country":"ES",
    "sg:address":"Calle de Vergara, 33",
    "sg:city":"Salamanca",
    "sg:orig_category":"Promotores Constructores",
    "sg:phone":"+34 923 18 16 78",
    "sg:postcode":"37003",
    "sg:province":"Salamanca",
    "wof:name":"Nueva Aldealengua S.l.",
    "wof:placetype":"venue"
},
  "geometry": {"coordinates":[-5.6537599564,40.9628753662],"type":"Point"}
}