{
  "type": "Feature",
  "properties": {
    "iso:country":"ES",
    "sg:address":"Calle de Cantarranas, S/n",
    "sg:city":"Casar Caceres",
    "sg:orig_category":"Discapacitados",
    "sg:phone":"+34 927 29 02 65",
    "sg:postcode":"10190",
    "sg:province":"C\u00e1ceres",
    "wof:name":"Patronato Centro Especial De Empleo Tajosalor",
    "wof:placetype":"venue"
},
  "geometry": {"coordinates":[-6.4186291695,39.5573730469],"type":"Point"}
}