{
  "type": "Feature",
  "properties": {
    "addr:full":"Carr Pau, 41 Cassa Selva Girona 17244",
    "addr:housenumber":"41",
    "addr:postcode":"17244",
    "addr:street":"Carr Pau",
    "iso:country":"ES",
    "sg:address":"Carr Pau, 41",
    "sg:city":"Cassa Selva",
    "sg:orig_category":"Promotores Constructores",
    "sg:phone":"+34 972 46 17 72",
    "sg:postcode":"17244",
    "sg:province":"Girona",
    "wof:name":"Bosch Carreras Josep",
    "wof:placetype":"venue"
},
  "geometry": {"coordinates":[2.8780760765,41.8896598816],"type":"Point"}
}