{
  "type": "Feature",
  "properties": {
    "addr:full":"Avda Mimosas, 15 Bormujos Sevilla 41930",
    "addr:housenumber":"15",
    "addr:postcode":"41930",
    "addr:street":"Avda Mimosas",
    "iso:country":"ES",
    "sg:address":"Avda Mimosas, 15",
    "sg:city":"Bormujos",
    "sg:orig_category":"Notarios",
    "sg:phone":"+34 955 72 21 85",
    "sg:postcode":"41930",
    "sg:province":"Sevilla",
    "wof:name":"Ballester Vazquez Eduardo",
    "wof:placetype":"venue"
},
  "geometry": {"coordinates":[-6.0656042099,37.3624382019],"type":"Point"}
}