{
  "type": "Feature",
  "properties": {
    "addr:full":"Calle de Jesus Del Valle, 16 Madrid Madrid 28004",
    "addr:housenumber":"16",
    "addr:postcode":"madrid;28004",
    "addr:street":"Calle De Jesus Del Valle",
    "iso:country":"ES",
    "sg:address":"Calle de Jesus Del Valle, 16",
    "sg:city":"Madrid",
    "sg:orig_category":"Periodistas Profesionales",
    "sg:phone":"+34 915 22 45 05",
    "sg:postcode":"28004",
    "sg:province":"Madrid",
    "wof:name":"Barroso Lopez Julio Miguel",
    "wof:placetype":"venue"
},
  "geometry": {"coordinates":[-3.7040970325,40.4243621826],"type":"Point"}
}