{
  "type": "Feature",
  "properties": {
    "iso:country":"ES",
    "sg:address":"Ctra. Alba, 15",
    "sg:city":"Navales",
    "sg:orig_category":"Transportes Por Carretera: Lotes Completos, Mercanc\u00cdas Diversas",
    "sg:phone":"+34 923 30 03 08",
    "sg:postcode":"37880",
    "sg:province":"Salamanca",
    "wof:name":"Perez Arroyo Juan",
    "wof:placetype":"venue"
},
  "geometry": {"coordinates":[-5.4800801277,40.7890586853],"type":"Point"}
}