{
  "type": "Feature",
  "properties": {
    "addr:full":"Serra Perenxisa, S/n Aldaia Valencia 46960",
    "addr:housenumber":"s / n",
    "addr:postcode":"46960",
    "iso:country":"ES",
    "sg:address":"Serra Perenxisa, S/n",
    "sg:city":"Aldaia",
    "sg:orig_category":"Vidrio, Fabricaci\u00d3n Y Comercio",
    "sg:phone":"+34 963 83 30 40",
    "sg:postcode":"46960",
    "sg:province":"Valencia",
    "wof:name":"Imeca De Valencia S.a.",
    "wof:placetype":"venue"
},
  "geometry": {"coordinates":[-0.4663490057,39.4723091125],"type":"Point"}
}