{
  "type": "Feature",
  "properties": {
    "addr:full":"Los Baldios, S/n Corrales Sevilla 41657",
    "addr:housenumber":"s / n",
    "addr:postcode":"41657",
    "iso:country":"ES",
    "sg:address":"Los Baldios, S/n",
    "sg:city":"Corrales",
    "sg:orig_category":"Paletas",
    "sg:phone":"+34 955 91 81 12",
    "sg:postcode":"41657",
    "sg:province":"Sevilla",
    "wof:name":"Pefaja Sociedad Cooperativa Andaluza",
    "wof:placetype":"venue"
},
  "geometry": {"coordinates":[-4.9846491814,37.101146698],"type":"Point"}
}