{
  "type": "Feature",
  "properties": {
    "addr:full":"Calle de Maestros Alpargateros, 4 Fuente Alamo Murcia 30320",
    "addr:housenumber":"4",
    "addr:postcode":"30320",
    "addr:street":"Calle De Maestros Alpargateros",
    "iso:country":"ES",
    "sg:address":"Calle de Maestros Alpargateros, 4",
    "sg:city":"Fuente Alamo",
    "sg:orig_category":"Agricultura: Abastecimiento Y Cosechado (negocio)",
    "sg:phone":"+34 968 59 79 50",
    "sg:postcode":"30320",
    "sg:province":"Murcia",
    "wof:name":"Organizacion De Agricultores De Fuente Alamo",
    "wof:placetype":"venue"
},
  "geometry": {"coordinates":[-1.1703629494,37.7203063965],"type":"Point"}
}