{
  "type": "Feature",
  "properties": {
    "iso:country":"ES",
    "sg:address":"Plaza De Los Marineros, S/n",
    "sg:city":"Punta Umbria",
    "sg:orig_category":"T\u00c9cnicos Veterinarios",
    "sg:phone":"+34 959 31 59 38",
    "sg:postcode":"21100",
    "sg:province":"Huelva",
    "wof:name":"Vethome S.l.",
    "wof:placetype":"venue"
},
  "geometry": {"coordinates":[-6.9646840096,37.1852798462],"type":"Point"}
}