{
  "type": "Feature",
  "properties": {
    "iso:country":"ES",
    "sg:address":"Calle de Luis Montoto, 112",
    "sg:city":"Sevilla",
    "sg:orig_category":"Promotores Constructores",
    "sg:phone":"+34 954 57 45 00",
    "sg:postcode":"41018",
    "sg:province":"Sevilla",
    "wof:name":"Constructora San Jose S. A.",
    "wof:placetype":"venue"
},
  "geometry": {"coordinates":[-5.9733948708,37.3871994019],"type":"Point"}
}