{
  "type": "Feature",
  "properties": {
    "addr:full":"Carrer de Consell De Cent, 383 Barcelona Barcelona 08009",
    "addr:housenumber":"383",
    "addr:postcode":"08009",
    "addr:street":"Carrer De Consell De Cent",
    "iso:country":"ES",
    "sg:address":"Carrer de Consell De Cent, 383",
    "sg:city":"Barcelona",
    "sg:orig_category":"Arquitectos",
    "sg:phone":"+34 934 88 14 96",
    "sg:postcode":"08009",
    "sg:province":"Barcelona",
    "wof:name":"Asmarats Mercadal Evaristo",
    "wof:placetype":"venue"
},
  "geometry": {"coordinates":[2.1695449352,41.3940124512],"type":"Point"}
}