{
  "type": "Feature",
  "properties": {
    "iso:country":"ES",
    "sg:address":"C/ Abat Oliba, 14",
    "sg:city":"Salt",
    "sg:orig_category":"Empresas De Carpinter\u00cda De Madera",
    "sg:phone":"+34 972 23 77 65",
    "sg:postcode":"17190",
    "sg:province":"Girona",
    "wof:name":"Roura Serra Jordi",
    "wof:placetype":"venue"
},
  "geometry": {"coordinates":[2.7980749607,41.9752845764],"type":"Point"}
}