{
  "type": "Feature",
  "properties": {
    "iso:country":"ES",
    "sg:address":"Plaz Ayuntamiento (el), 3",
    "sg:city":"Pizarra",
    "sg:orig_category":"Bancos",
    "sg:phone":"+34 952 48 30 42",
    "sg:postcode":"29560",
    "sg:province":"M\u00e1laga",
    "wof:name":"Banco Espa\u00f1ol De Credito S.a.",
    "wof:placetype":"venue"
},
  "geometry": {"coordinates":[-4.707526207,36.7672538757],"type":"Point"}
}