{
  "type": "Feature",
  "properties": {
    "addr:full":"Calle de Villamediana, 35 Logro\u00f1o La Rioja 26003",
    "addr:housenumber":"35",
    "addr:postcode":"26003",
    "addr:street":"Calle De Villamediana;Rioja",
    "iso:country":"ES",
    "sg:address":"Calle de Villamediana, 35",
    "sg:city":"Logro\u00f1o",
    "sg:orig_category":"Asociaciones, Organismos Culturales Y Socioeducativos",
    "sg:phone":"+34 941 24 23 94",
    "sg:postcode":"26003",
    "sg:province":"La Rioja",
    "wof:name":"Sociedad Recreativa Cultural Gastronomica 25",
    "wof:placetype":"venue"
},
  "geometry": {"coordinates":[-2.4379870892,42.4598503113],"type":"Point"}
}