{
  "type": "Feature",
  "properties": {
    "iso:country":"ES",
    "sg:address":"Gta Pintor Sorolla, 4",
    "sg:city":"Madrid",
    "sg:orig_category":"Empresarios",
    "sg:phone":"+34 914 48 39 40",
    "sg:postcode":"28010",
    "sg:province":"Madrid",
    "sg:website":"www.fundacionbelen.org",
    "wof:name":"Fundacion Belen",
    "wof:placetype":"venue"
},
  "geometry": {"coordinates":[-3.6987259388,40.4351577759],"type":"Point"}
}