{
  "type": "Feature",
  "properties": {
    "iso:country":"ES",
    "sg:address":"Calle de Juan De Toledo, 7",
    "sg:city":"Albacete",
    "sg:orig_category":"Negocio De Materiales De Construcci\u00d3n",
    "sg:phone":"+34 967 21 35 97",
    "sg:postcode":"02005",
    "sg:province":"Albacete",
    "wof:name":"Alba Robledillo C.b.",
    "wof:placetype":"venue"
},
  "geometry": {"coordinates":[-1.8604955673,39.0008773804],"type":"Point"}
}