{
  "type": "Feature",
  "properties": {
    "addr:full":"Calle de Santiago Alio, 25 Madrid Madrid 28038",
    "addr:housenumber":"25",
    "addr:postcode":"madrid;28038",
    "addr:street":"Calle De Santiago Alio",
    "iso:country":"ES",
    "sg:address":"Calle de Santiago Alio, 25",
    "sg:city":"Madrid",
    "sg:orig_category":"Molduras, Junquillos, Listones Y Molduras Perforadas",
    "sg:phone":"+34 913 03 52 32",
    "sg:postcode":"28038",
    "sg:province":"Madrid",
    "wof:name":"Feo Camacho Francisco",
    "wof:placetype":"venue"
},
  "geometry": {"coordinates":[-3.6464691162,40.3876457214],"type":"Point"}
}