{
  "type": "Feature",
  "properties": {
    "iso:country":"ES",
    "sg:address":"Calle de Francisco Aritio, 111",
    "sg:city":"Guadalajara",
    "sg:orig_category":"Asilos De Ancianos. Centros Privados",
    "sg:phone":"+34 949 20 31 58",
    "sg:postcode":"19004",
    "sg:province":"Guadalajara",
    "wof:name":"Centro Geriatrico Manantial S.a.",
    "wof:placetype":"venue"
},
  "geometry": {"coordinates":[-3.1887381077,40.6363716125],"type":"Point"}
}