{
  "type": "Feature",
  "properties": {
    "iso:country":"ES",
    "sg:address":"Calle de Mayor, 3",
    "sg:city":"Alcala Henares",
    "sg:orig_category":"Panader\u00cdas, Panader\u00cdas",
    "sg:phone":"+34 918 88 20 24",
    "sg:postcode":"28801",
    "sg:province":"Madrid",
    "wof:name":"Montes Andres Julia",
    "wof:placetype":"venue"
},
  "geometry": {"coordinates":[-3.365167141,40.4830551147],"type":"Point"}
}