{
  "type": "Feature",
  "properties": {
    "addr:full":"Calle de Juan De Tapia, 9 Astudillo Palencia 34450",
    "addr:housenumber":"9",
    "addr:postcode":"34450",
    "addr:street":"Calle De Juan De Tapia",
    "iso:country":"ES",
    "sg:address":"Calle de Juan De Tapia, 9",
    "sg:city":"Astudillo",
    "sg:orig_category":"Cooperativas Agr\u00cdcolas",
    "sg:phone":"+34 979 82 20 95",
    "sg:postcode":"34450",
    "sg:province":"Palencia",
    "wof:name":"Cooperativa Agricola Del Campo",
    "wof:placetype":"venue"
},
  "geometry": {"coordinates":[-4.2960028648,42.1935920715],"type":"Point"}
}