{
  "type": "Feature",
  "properties": {
    "iso:country":"ES",
    "sg:address":"Calle de Carretera General, S/n",
    "sg:city":"Unquera",
    "sg:orig_category":"Loter\u00cda Y T\u00d3mbola",
    "sg:phone":"+34 942 71 71 33",
    "sg:postcode":"39560",
    "sg:province":"Cantabria",
    "wof:name":"Sanchez Floranes Juan Carlos",
    "wof:placetype":"venue"
},
  "geometry": {"coordinates":[-4.5087156296,43.3750686646],"type":"Point"}
}