{
  "type": "Feature",
  "properties": {
    "iso:country":"ES",
    "sg:address":"Rua Sanjurjo Badia, 128",
    "sg:city":"Vigo",
    "sg:orig_category":"\u00d3ptica: Instrumentos (fabricaci\u00d3n)",
    "sg:phone":"+34 986 37 81 05",
    "sg:postcode":"36207",
    "sg:province":"Pontevedra",
    "wof:name":"Optica Alemana S. A.",
    "wof:placetype":"venue"
},
  "geometry": {"coordinates":[-8.7019891739,42.2456703186],"type":"Point"}
}