{
  "type": "Feature",
  "properties": {
    "addr:full":"Avda Doctor Sanchez Malo, S/n Ecija Sevilla 41400",
    "addr:housenumber":"s",
    "addr:postcode":"41400",
    "addr:street":"Avda Doctor Sanchez Malo;/ N",
    "iso:country":"ES",
    "sg:address":"Avda Doctor Sanchez Malo, S/n",
    "sg:city":"Ecija",
    "sg:orig_category":"Agentes, Concesionarios Y Sucursales De Veh\u00cdculos",
    "sg:phone":"+34 954 83 47 17",
    "sg:postcode":"41400",
    "sg:province":"Sevilla",
    "wof:name":"Carvalme Sll",
    "wof:placetype":"venue"
},
  "geometry": {"coordinates":[-5.0934081078,37.5324058533],"type":"Point"}
}