{
  "type": "Feature",
  "properties": {
    "iso:country":"ES",
    "sg:address":"Calle de General Serrano, 88",
    "sg:city":"Santa Cruz De Tenerife",
    "sg:orig_category":"Ense\u00d1anza: Comercio, Gesti\u00d3n, Inform\u00c1tica",
    "sg:phone":"+34 922 27 76 24",
    "sg:postcode":"38006",
    "sg:province":"Santa Cruz De Tenerife",
    "wof:name":"Luis Gutierrez Carmen Gregoria",
    "wof:placetype":"venue"
},
  "geometry": {"coordinates":[-16.2655067444,28.4712772369],"type":"Point"}
}