{
  "type": "Feature",
  "properties": {
    "addr:full":"Avda Galicia (de), 33 Monforte De Lemos Lugo 27400",
    "addr:housenumber":"33",
    "addr:postcode":"27400",
    "addr:street":"Avda Galicia De",
    "iso:country":"ES",
    "sg:address":"Avda Galicia (de), 33",
    "sg:city":"Monforte De Lemos",
    "sg:orig_category":"Arquitectos",
    "sg:phone":"+34 982 40 22 10",
    "sg:postcode":"27400",
    "sg:province":"Lugo",
    "wof:name":"Mclf Arquitecta S.l.",
    "wof:placetype":"venue"
},
  "geometry": {"coordinates":[-7.5101761818,42.5177383423],"type":"Point"}
}