{
  "type": "Feature",
  "properties": {
    "iso:country":"ES",
    "sg:address":"Calle de Rio Segura, 15",
    "sg:city":"Ceuti",
    "sg:orig_category":"Fabricaci\u00d3n De Material Y Sistemas De Se\u00d1alizaci\u00d3n De Carreteras, Urbanos Y De Obras",
    "sg:phone":"+34 968 69 38 00",
    "sg:postcode":"30562",
    "sg:province":"Murcia",
    "sg:website":"www.aliminter.com",
    "wof:name":"Aliminter S.a.",
    "wof:placetype":"venue"
},
  "geometry": {"coordinates":[-1.2684687376,38.0834960938],"type":"Point"}
}