{
  "type": "Feature",
  "properties": {
    "addr:full":"Calle de Marquesa Viuda De Aldama (de La), 27 Alcobendas Madrid 28100",
    "addr:housenumber":"27",
    "addr:postcode":"28100",
    "addr:street":"Calle De Marquesa Viuda De Aldama De La",
    "iso:country":"ES",
    "sg:address":"Calle de Marquesa Viuda De Aldama (de La), 27",
    "sg:city":"Alcobendas",
    "sg:orig_category":"Cervecer\u00cdas",
    "sg:phone":"+34 916 51 71 08",
    "sg:postcode":"28100",
    "sg:province":"Madrid",
    "wof:name":"Lolupe S.a.",
    "wof:placetype":"venue"
},
  "geometry": {"coordinates":[-3.6313195229,40.541847229],"type":"Point"}
}