{
  "type": "Feature",
  "properties": {
    "iso:country":"ES",
    "sg:address":"Carrer de Nou, 19",
    "sg:city":"S. Pere Ribes",
    "sg:orig_category":"Arreglo, Reparaci\u00d3n, Piezas Sueltas De Televisi\u00d3n, V\u00cddeo, Hi",
    "sg:phone":"+34 938 96 19 04",
    "sg:postcode":"08810",
    "sg:province":"Barcelona",
    "wof:name":"Tecninova Instalaciones S.l.",
    "wof:placetype":"venue"
},
  "geometry": {"coordinates":[1.7710440159,41.2611122131],"type":"Point"}
}