{
  "type": "Feature",
  "properties": {
    "addr:full":"Calle de Torreon, 10 Guijuelo Salamanca 37770",
    "addr:housenumber":"10",
    "addr:postcode":"37770",
    "addr:street":"Calle De Torreon",
    "iso:country":"ES",
    "sg:address":"Calle de Torreon, 10",
    "sg:city":"Guijuelo",
    "sg:orig_category":"Carnicer\u00cdas, Carnicer\u00cdas",
    "sg:phone":"+34 923 58 15 47",
    "sg:postcode":"37770",
    "sg:province":"Salamanca",
    "wof:name":"Carnicas Rodriguez G. Del Aguila S.l",
    "wof:placetype":"venue"
},
  "geometry": {"coordinates":[-5.6728820801,40.5542221069],"type":"Point"}
}