{
  "type": "Feature",
  "properties": {
    "iso:country":"ES",
    "sg:address":"Calle de Panaderos, 18",
    "sg:city":"Malaga",
    "sg:orig_category":"M\u00c9dicos: Ginecolog\u00cda Y Obstetricia",
    "sg:phone":"+34 952 22 21 23",
    "sg:postcode":"29005",
    "sg:province":"M\u00e1laga",
    "wof:name":"Garcia Fernandez Laureano",
    "wof:placetype":"venue"
},
  "geometry": {"coordinates":[-4.4245610237,36.7177658081],"type":"Point"}
}