{
  "type": "Feature",
  "properties": {
    "addr:full":"Pase Doctor Vallejo Nagera, 38 Madrid Madrid 28005",
    "addr:housenumber":"38",
    "addr:postcode":"madrid;28005",
    "addr:street":"Nagera",
    "iso:country":"ES",
    "sg:address":"Pase Doctor Vallejo Nagera, 38",
    "sg:city":"Madrid",
    "sg:orig_category":"Veh\u00cdculos De Ocasi\u00d3n",
    "sg:phone":"+34 915 30 76 57",
    "sg:postcode":"28005",
    "sg:province":"Madrid",
    "sg:website":"www.motormontecarlo.com",
    "wof:name":"Motor Montecarlo S.a.",
    "wof:placetype":"venue"
},
  "geometry": {"coordinates":[-3.7126390934,40.4032897949],"type":"Point"}
}