{
  "type": "Feature",
  "properties": {
    "iso:country":"ES",
    "sg:address":"Carlos Ii El Malo, 9",
    "sg:city":"Estella",
    "sg:orig_category":"Institutos De Belleza",
    "sg:phone":"+34 948 55 15 14",
    "sg:postcode":"31200",
    "sg:province":"Navarra",
    "wof:name":"Ajona Pinillos Cristina",
    "wof:placetype":"venue"
},
  "geometry": {"coordinates":[-2.0320057869,42.6705703735],"type":"Point"}
}