{
  "type": "Feature",
  "properties": {
    "iso:country":"ES",
    "sg:address":"Avda Portugal, 107",
    "sg:city":"Salamanca",
    "sg:orig_category":"\u00d3ptica: Instrumentos (fabricaci\u00d3n)",
    "sg:phone":"+34 923 12 10 42",
    "sg:postcode":"37005",
    "sg:province":"Salamanca",
    "wof:name":"Bustos Caballero Jacinto",
    "wof:placetype":"venue"
},
  "geometry": {"coordinates":[-5.6625151634,40.972202301],"type":"Point"}
}