{
  "type": "Feature",
  "properties": {
    "addr:full":"Nord, 2 Vilablareix Girona 17180",
    "addr:housenumber":"2",
    "addr:postcode":"17180",
    "addr:street":"Nord",
    "iso:country":"ES",
    "sg:address":"Nord, 2",
    "sg:city":"Vilablareix",
    "sg:orig_category":"Artes Gr\u00c1ficas, Artes Pl\u00c1sticas (curso)",
    "sg:phone":"+34 972 40 02 90",
    "sg:postcode":"17180",
    "sg:province":"Girona",
    "wof:name":"Plastigraf S.c.",
    "wof:placetype":"venue"
},
  "geometry": {"coordinates":[2.7975449562,41.9574546814],"type":"Point"}
}