{
  "type": "Feature",
  "properties": {
    "addr:full":"Calle de Andorra, S/n Alcala Henares Madrid 28802",
    "addr:housenumber":"s / n",
    "addr:postcode":"28802",
    "addr:street":"Calle De Andorra",
    "iso:country":"ES",
    "sg:address":"Calle de Andorra, S/n",
    "sg:city":"Alcala Henares",
    "sg:orig_category":"Rectificaci\u00d3n, Mecanizado, Fresado",
    "sg:phone":"+34 918 82 43 45",
    "sg:postcode":"28802",
    "sg:province":"Madrid",
    "wof:name":"Mecanizados Alcala S.l.",
    "wof:placetype":"venue"
},
  "geometry": {"coordinates":[-3.3887217045,40.4815330505],"type":"Point"}
}