{
  "type": "Feature",
  "properties": {
    "iso:country":"ES",
    "sg:address":"Carrer de L'escultor Canet, 6",
    "sg:city":"Barcelona",
    "sg:orig_category":"Agencias Y Agentes Comerciales, Representantes",
    "sg:phone":"+34 934 31 87 23",
    "sg:postcode":"08028",
    "sg:province":"Barcelona",
    "wof:name":"Turmo Gabarros Javier",
    "wof:placetype":"venue"
},
  "geometry": {"coordinates":[2.1279056072,41.3741264343],"type":"Point"}
}