{
  "type": "Feature",
  "properties": {
    "iso:country":"ES",
    "sg:address":"Calle de Argentina, S/n",
    "sg:city":"Ceuta",
    "sg:orig_category":"Mec\u00c1nico Del Autom\u00d3vil",
    "sg:phone":"+34 956 50 83 93",
    "sg:postcode":"51002",
    "sg:province":"Ceuta",
    "wof:name":"Mohamed Mohamed Mustafa",
    "wof:placetype":"venue"
},
  "geometry": {"coordinates":[-5.3337006569,35.8819580078],"type":"Point"}
}