{
  "type": "Feature",
  "properties": {
    "iso:country":"ES",
    "sg:address":"Ba. Sauleda, S/n",
    "sg:city":"Mont-ras",
    "sg:orig_category":"Maquinaria Para Industrias Diversas",
    "sg:phone":"+34 972 61 22 65",
    "sg:postcode":"17253",
    "sg:province":"Girona",
    "wof:name":"Gonzalez Plana David",
    "wof:placetype":"venue"
},
  "geometry": {"coordinates":[3.1503999233,41.9084014893],"type":"Point"}
}