{
  "type": "Feature",
  "properties": {
    "iso:country":"ES",
    "sg:address":"Praz Cervantes, 6",
    "sg:city":"Celanova",
    "sg:orig_category":"Carnicer\u00cdas, Carnicer\u00cdas",
    "sg:phone":"+34 988 43 14 71",
    "sg:postcode":"32800",
    "sg:province":"Ourense",
    "wof:name":"Cid Calvi\u00f1o Angel",
    "wof:placetype":"venue"
},
  "geometry": {"coordinates":[-7.9583959579,42.1532974243],"type":"Point"}
}