{
  "type": "Feature",
  "properties": {
    "addr:full":"Rua Areal, 18 Vigo Pontevedra 36201",
    "addr:housenumber":"18",
    "addr:postcode":"36201",
    "addr:street":"Rua Areal",
    "iso:country":"ES",
    "sg:address":"Rua Areal, 18",
    "sg:city":"Vigo",
    "sg:classifiers":[
        {
            "category":"Banks & Credit Unions",
            "subcategory":"Bureau De Change",
            "type":"Services"
        }
    ],
    "sg:phone":"+34 986 43 40 88",
    "sg:postcode":"36201",
    "sg:province":"Pontevedra",
    "sg:tags":[
        "organismos",
        "control"
    ],
    "sg:website":"www.atisae.com",
    "wof:name":"Asistencia Tecnica Industrial S.a.e.",
    "wof:placetype":"venue"
},
  "geometry": {"coordinates":[-8.7154521942,42.2389793396],"type":"Point"}
}