{
  "type": "Feature",
  "properties": {
    "addr:full":"Carr Montgo, 4 Figueres Girona 17600",
    "addr:housenumber":"4",
    "addr:postcode":"17600",
    "addr:street":"Carr Montgo",
    "iso:country":"ES",
    "sg:address":"Carr Montgo, 4",
    "sg:city":"Figueres",
    "sg:orig_category":"Sociedades, Compa\u00d1\u00cdas Aseguradoras",
    "sg:phone":"+34 972 50 93 13",
    "sg:postcode":"17600",
    "sg:province":"Girona",
    "wof:name":"Gabinet Tecnic D'assegurances S.a.",
    "wof:placetype":"venue"
},
  "geometry": {"coordinates":[2.9581100941,42.2656898499],"type":"Point"}
}