{
  "type": "Feature",
  "properties": {
    "iso:country":"ES",
    "sg:address":"Ctra Pont De Molins, S/n",
    "sg:city":"Masies De Dalt",
    "sg:orig_category":"Cr\u00cda De Animales",
    "sg:phone":"+34 972 50 73 99",
    "sg:postcode":"17761",
    "sg:province":"Girona",
    "wof:name":"Pujolar Casta\u00f1e Agusti",
    "wof:placetype":"venue"
},
  "geometry": {"coordinates":[2.9780449867,42.3078231812],"type":"Point"}
}