{
  "type": "Feature",
  "properties": {
    "iso:country":"ES",
    "sg:address":"Calle de Carniceria Vieja, 10",
    "sg:city":"Bilbao",
    "sg:orig_category":"Fabricaci\u00d3n, Venta De Cuadros, Accesorios Para Enmarcar",
    "sg:phone":"+34 944 15 51 37",
    "sg:postcode":"48005",
    "sg:province":"Vizcaya",
    "sg:website":"www.billbaoguia.com/f3",
    "wof:name":"Fuente Herrera Felix Fernando De La",
    "wof:placetype":"venue"
},
  "geometry": {"coordinates":[-2.9238379002,43.2571983337],"type":"Point"}
}