{
  "type": "Feature",
  "properties": {
    "addr:full":"Carrer de Serra D'or, S/n Mas Rampinyo Barcelona 08110",
    "addr:housenumber":"s",
    "addr:postcode":"08110",
    "addr:street":"Carrer De Serra D'Or;/ N Mas Rampinyo",
    "iso:country":"ES",
    "sg:address":"Carrer de Serra D'or, S/n",
    "sg:city":"Mas Rampinyo",
    "sg:orig_category":"Prendas Y Chalecos De Punto (al Por Menor)",
    "sg:phone":"+34 935 64 51 03",
    "sg:postcode":"08110",
    "sg:province":"Barcelona",
    "wof:name":"Barea Barea Adela",
    "wof:placetype":"venue"
},
  "geometry": {"coordinates":[2.1819396019,41.4933700562],"type":"Point"}
}