{
  "type": "Feature",
  "properties": {
    "iso:country":"ES",
    "sg:address":"Rua Mayor, 11",
    "sg:city":"Olite",
    "sg:orig_category":"Ropa De Hogar (al Por Menor)",
    "sg:phone":"+34 948 74 07 44",
    "sg:postcode":"31390",
    "sg:province":"Navarra",
    "wof:name":"Alicia Blasco Llorente",
    "wof:placetype":"venue"
},
  "geometry": {"coordinates":[-1.6502213478,42.4808158875],"type":"Point"}
}