{
  "type": "Feature",
  "properties": {
    "addr:full":"Grup Jose Antonio, 10 Badajoz Badajoz 06005",
    "addr:housenumber":"10",
    "addr:postcode":"06005",
    "addr:street":"Jose Antonio",
    "iso:country":"ES",
    "sg:address":"Grup Jose Antonio, 10",
    "sg:city":"Badajoz",
    "sg:orig_category":"Inmobiliaria (agencias)",
    "sg:phone":"+34 924 24 98 48",
    "sg:postcode":"06005",
    "sg:province":"Badajoz",
    "wof:name":"Oreja Ruiz Maria Angeles",
    "wof:placetype":"venue"
},
  "geometry": {"coordinates":[-6.9790248871,38.8761444092],"type":"Point"}
}