{
  "type": "Feature",
  "properties": {
    "iso:country":"ES",
    "sg:address":"Carrer de Arago, 184",
    "sg:city":"Palma",
    "sg:orig_category":"Inmobiliaria (agencias)",
    "sg:phone":"+34 971 47 76 23",
    "sg:postcode":"07008",
    "sg:province":"Islas Baleares",
    "wof:name":"Martinez Y Menor Asociados S.l.",
    "wof:placetype":"venue"
},
  "geometry": {"coordinates":[2.6722888947,39.5850334167],"type":"Point"}
}