{
  "type": "Feature",
  "properties": {
    "addr:full":"Calle de Juan De Austria, 2 Rota C\u00e1diz 11520",
    "addr:housenumber":"2",
    "addr:postcode":"11520",
    "addr:street":"Calle De Juan De Austria;Ca\u0301Diz",
    "iso:country":"ES",
    "sg:address":"Calle de Juan De Austria, 2",
    "sg:city":"Rota",
    "sg:orig_category":"Deportes Diversos",
    "sg:phone":"+34 956 84 12 52",
    "sg:postcode":"11520",
    "sg:province":"C\u00e1diz",
    "wof:name":"Federacion Andaluza De Futbol",
    "wof:placetype":"venue"
},
  "geometry": {"coordinates":[-6.3602619171,36.6279373169],"type":"Point"}
}