{
  "type": "Feature",
  "properties": {
    "iso:country":"ES",
    "sg:address":"Calle de Cuarteles, 5",
    "sg:city":"Malaga",
    "sg:orig_category":"Fabricaci\u00d3n, Venta De Productos Base Farmac\u00c9uticos",
    "sg:phone":"+34 952 31 59 41",
    "sg:postcode":"29002",
    "sg:province":"M\u00e1laga",
    "wof:name":"Nieto Sanchez Viciente Miguel",
    "wof:placetype":"venue"
},
  "geometry": {"coordinates":[-4.426846981,36.7150535583],"type":"Point"}
}