{
  "type": "Feature",
  "properties": {
    "addr:full":"Urb Nuevo Versalles, S/n Loranca Madrid 28942",
    "addr:housenumber":"s / n",
    "addr:postcode":"28942",
    "addr:street":"Urb Nuevo Versalles",
    "iso:country":"ES",
    "sg:address":"Urb Nuevo Versalles, S/n",
    "sg:city":"Loranca",
    "sg:orig_category":"Laboratorios Y Cl\u00cdnicas Veterinarias",
    "sg:phone":"+34 914 86 85 63",
    "sg:postcode":"28942",
    "sg:province":"Madrid",
    "wof:name":"Rodriguez Lopez Rosalia",
    "wof:placetype":"venue"
},
  "geometry": {"coordinates":[-3.8304479122,40.2969512939],"type":"Point"}
}