{
  "type": "Feature",
  "properties": {
    "iso:country":"ES",
    "sg:address":"Calle de Pintor Almela Costa, 21",
    "sg:city":"Nuestra Se\u00e7ora De La Fuensanta",
    "sg:orig_category":"Pintura Y Barniz (al Por Menor)",
    "sg:phone":"+34 968 25 79 72",
    "sg:postcode":"30011",
    "sg:province":"Murcia",
    "wof:name":"Mengual Y Garcia S.l.",
    "wof:placetype":"venue"
},
  "geometry": {"coordinates":[-1.1195590496,37.975730896],"type":"Point"}
}