{
  "type": "Feature",
  "properties": {
    "iso:country":"ES",
    "sg:address":"Calle de Cirilo Amoros, 30",
    "sg:city":"Valencia",
    "sg:orig_category":"Ropa Para Ni\u00d1os (al Por Menor)",
    "sg:phone":"+34 963 51 30 84",
    "sg:postcode":"46004",
    "sg:province":"Valencia",
    "wof:name":"Navarro Guarner Maria Luisa",
    "wof:placetype":"venue"
},
  "geometry": {"coordinates":[-0.372032702,39.4670791626],"type":"Point"}
}