{
  "type": "Feature",
  "properties": {
    "addr:full":"Calle de Onda, 2 Alzira Valencia 46600",
    "addr:housenumber":"2",
    "addr:postcode":"46600",
    "addr:street":"Calle De Onda",
    "iso:country":"ES",
    "sg:address":"Calle de Onda, 2",
    "sg:city":"Alzira",
    "sg:orig_category":"Iglesia Cat\u00d3lica",
    "sg:phone":"+34 962 40 46 09",
    "sg:postcode":"46600",
    "sg:province":"Valencia",
    "wof:name":"Parroquia De La Encarnacion",
    "wof:placetype":"venue"
},
  "geometry": {"coordinates":[-0.4388509989,39.1466751099],"type":"Point"}
}