{
  "type": "Feature",
  "properties": {
    "iso:country":"ES",
    "sg:address":"Pol Ind El Cordovi, S/n",
    "sg:city":"Benalua Guadix",
    "sg:orig_category":"Mec\u00c1nico Del Autom\u00d3vil",
    "sg:phone":"+34 958 69 62 53",
    "sg:postcode":"18510",
    "sg:province":"Granada",
    "wof:name":"Gonzalez Castillo Jose Miguel",
    "wof:placetype":"venue"
},
  "geometry": {"coordinates":[-3.1669239998,37.3522415161],"type":"Point"}
}