{
  "type": "Feature",
  "properties": {
    "addr:full":"Calle de Generalisimo, 13 Blanca Murcia 30540",
    "addr:housenumber":"13",
    "addr:postcode":"30540",
    "addr:street":"Calle De Generalisimo",
    "iso:country":"ES",
    "sg:address":"Calle de Generalisimo, 13",
    "sg:city":"Blanca",
    "sg:orig_category":"Carnicer\u00cdas, Carnicer\u00cdas",
    "sg:phone":"+34 968 45 90 78",
    "sg:postcode":"30540",
    "sg:province":"Murcia",
    "wof:name":"Sanchez Sanchez Jose",
    "wof:placetype":"venue"
},
  "geometry": {"coordinates":[-1.3762789965,38.180431366],"type":"Point"}
}