{
  "type": "Feature",
  "properties": {
    "iso:country":"ES",
    "sg:address":"Vilardevesa, S/n",
    "sg:city":"Vilardevesa",
    "sg:orig_category":"Agricultores, Agricultores",
    "sg:phone":"+34 981 19 85 12",
    "sg:postcode":"15685",
    "sg:province":"A Coru\u00f1a",
    "wof:name":"Vilardevesa Sociedad Cooperativa Galega",
    "wof:placetype":"venue"
},
  "geometry": {"coordinates":[-8.2391490936,43.0809135437],"type":"Point"}
}