{
  "type": "Feature",
  "properties": {
    "addr:full":"Calle de Marques De Vallejo, 1 Logro\u00f1o La Rioja 26001",
    "addr:housenumber":"1",
    "addr:postcode":"26001",
    "addr:street":"Calle De Marques De Vallejo;Rioja",
    "iso:country":"ES",
    "sg:address":"Calle de Marques De Vallejo, 1",
    "sg:city":"Logro\u00f1o",
    "sg:orig_category":"Florister\u00cdas",
    "sg:phone":"+34 941 23 11 71",
    "sg:postcode":"26001",
    "sg:province":"La Rioja",
    "wof:name":"Bueno Perez Manuela",
    "wof:placetype":"venue"
},
  "geometry": {"coordinates":[-2.445720911,42.4659805298],"type":"Point"}
}