{
  "type": "Feature",
  "properties": {
    "addr:full":"Carrer de Rossello, 6 Mataro Barcelona 08303",
    "addr:housenumber":"6",
    "addr:postcode":"08303",
    "addr:street":"Carrer De Rossello",
    "iso:country":"ES",
    "sg:address":"Carrer de Rossello, 6",
    "sg:city":"Mataro",
    "sg:orig_category":"Panader\u00cdas, Panader\u00cdas",
    "sg:phone":"+34 937 98 44 92",
    "sg:postcode":"08303",
    "sg:province":"Barcelona",
    "wof:name":"Morell Barjoan Jose",
    "wof:placetype":"venue"
},
  "geometry": {"coordinates":[2.4244310856,41.5394592285],"type":"Point"}
}