{
  "type": "Feature",
  "properties": {
    "addr:full":"Calle de Maestro Estremiana, 44 Zaragoza Zaragoza 50006",
    "addr:housenumber":"44",
    "addr:postcode":"50006",
    "addr:street":"Calle De Maestro Estremiana",
    "iso:country":"ES",
    "sg:address":"Calle de Maestro Estremiana, 44",
    "sg:city":"Zaragoza",
    "sg:classifiers":[
        {
            "category":"Professional",
            "subcategory":"Management & Consulting",
            "type":"Services"
        }
    ],
    "sg:phone":"+34 976 25 20 15",
    "sg:postcode":"50006",
    "sg:province":"Zaragoza",
    "sg:tags":[
        "asesor\u00cda",
        "en",
        "marketing"
    ],
    "sg:website":"www.mkgabinet.com",
    "wof:name":"Casado Roman Luis Francisco",
    "wof:placetype":"venue"
},
  "geometry": {"coordinates":[-0.8886989951,41.6357803345],"type":"Point"}
}