{
  "type": "Feature",
  "properties": {
    "iso:country":"ES",
    "sg:address":"Uribarri Etorbidea, 37",
    "sg:city":"Arrasate",
    "sg:orig_category":"Platos Preparados Refrigerados (fabricaci\u00d3n, Al Por Mayor)",
    "sg:phone":"+34 943 71 19 60",
    "sg:postcode":"20500",
    "sg:province":"Guip\u00f9zcoa",
    "wof:name":"Multifood Scp",
    "wof:placetype":"venue"
},
  "geometry": {"coordinates":[-2.5009589195,43.0621109009],"type":"Point"}
}