{
  "type": "Feature",
  "properties": {
    "iso:country":"ES",
    "sg:address":"Calle de Historiador Jaen Morente, 4",
    "sg:city":"Cordoba",
    "sg:orig_category":"Farmacias",
    "sg:phone":"+34 957 26 42 42",
    "sg:postcode":"14014",
    "sg:province":"C\u00f3rdoba",
    "wof:name":"Marine Casana Maria Angeles",
    "wof:placetype":"venue"
},
  "geometry": {"coordinates":[-4.7581520081,37.8994102478],"type":"Point"}
}