{
  "type": "Feature",
  "properties": {
    "addr:full":"Avda Valencina, 124 Bollullos Mitacion Sevilla 41110",
    "addr:housenumber":"124",
    "addr:postcode":"41110",
    "addr:street":"Avda Valencina",
    "iso:country":"ES",
    "sg:address":"Avda Valencina, 124",
    "sg:city":"Bollullos Mitacion",
    "sg:orig_category":"Estudios, Instalaci\u00d3n De Climatizaci\u00d3n",
    "sg:phone":"+34 955 77 69 33",
    "sg:postcode":"41110",
    "sg:province":"Sevilla",
    "sg:website":"www.salvadorescoda.com",
    "wof:name":"Salvador Escoda S.a.",
    "wof:placetype":"venue"
},
  "geometry": {"coordinates":[-6.1479330063,37.3583869934],"type":"Point"}
}