{
  "type": "Feature",
  "properties": {
    "iso:country":"ES",
    "sg:address":"Calle de Suero De Qui\u00d1ones, 34",
    "sg:city":"Madrid",
    "sg:orig_category":"Inmobiliaria (agencias)",
    "sg:phone":"+34 915 63 07 00",
    "sg:postcode":"28002",
    "sg:province":"Madrid",
    "wof:name":"Inmobiliaria Chamartin, S.a.",
    "wof:placetype":"venue"
},
  "geometry": {"coordinates":[-3.6771640778,40.4470252991],"type":"Point"}
}