{
  "type": "Feature",
  "properties": {
    "addr:full":"Calle de Marques De Villores, 48 Albacete Albacete 02003",
    "addr:housenumber":"48",
    "addr:postcode":"02003",
    "addr:street":"Calle De Marques De Villores",
    "iso:country":"ES",
    "sg:address":"Calle de Marques De Villores, 48",
    "sg:city":"Albacete",
    "sg:orig_category":"Doctores En Medicina",
    "sg:phone":"+34 967 22 28 11",
    "sg:postcode":"02003",
    "sg:province":"Albacete",
    "wof:name":"Lopez-torres Hidalgo Jesus",
    "wof:placetype":"venue"
},
  "geometry": {"coordinates":[-1.8583048582,38.9896697998],"type":"Point"}
}