{
  "type": "Feature",
  "properties": {
    "iso:country":"ES",
    "sg:address":"Carrer de Nuria, 74",
    "sg:city":"Premia Mar",
    "sg:orig_category":"Agencias Y Agentes Comerciales, Representantes",
    "sg:phone":"+34 937 51 25 22",
    "sg:postcode":"08330",
    "sg:province":"Barcelona",
    "wof:name":"Ca\u00f1ada Moral Manuel",
    "wof:placetype":"venue"
},
  "geometry": {"coordinates":[2.3584480286,41.4972648621],"type":"Point"}
}