{
  "type": "Feature",
  "properties": {
    "iso:country":"ES",
    "sg:address":"Madre Teresa De Calcuta, 2",
    "sg:city":"Villa Rio",
    "sg:orig_category":"Agencias De Viajes",
    "sg:phone":"+34 957 17 69 08",
    "sg:postcode":"14640",
    "sg:province":"C\u00f3rdoba",
    "wof:name":"Navarro Rodriguez Bartolome",
    "wof:placetype":"venue"
},
  "geometry": {"coordinates":[-4.2819290161,37.983997345],"type":"Point"}
}