{
  "type": "Feature",
  "properties": {
    "addr:full":"Calle de Falla, 1 B Barakaldo Vizcaya 48902",
    "addr:housenumber":"1 b",
    "addr:postcode":"48902",
    "addr:street":"Calle De Falla",
    "iso:country":"ES",
    "sg:address":"Calle de Falla, 1 B",
    "sg:city":"Barakaldo",
    "sg:orig_category":"Peluquer\u00cdas, Peluquer\u00cda Mixta",
    "sg:phone":"+34 944 90 20 65",
    "sg:postcode":"48902",
    "sg:province":"Vizcaya",
    "wof:name":"Cesar Del Ca\u00f1o Flores",
    "wof:placetype":"venue"
},
  "geometry": {"coordinates":[-2.9858388901,43.2973098755],"type":"Point"}
}