{
  "type": "Feature",
  "properties": {
    "addr:full":"Rua Amador Rodriguez, 1 Melide A Coru\u00f1a 15800",
    "addr:housenumber":"1",
    "addr:postcode":"15800",
    "addr:street":"Rua Amador Rodriguez;Corun\u0303A",
    "iso:country":"ES",
    "sg:address":"Rua Amador Rodriguez, 1",
    "sg:city":"Melide",
    "sg:orig_category":"Supermercados Y Hipermercados",
    "sg:phone":"+34 981 50 70 27",
    "sg:postcode":"15800",
    "sg:province":"A Coru\u00f1a",
    "wof:name":"Supermercados Gomez",
    "wof:placetype":"venue"
},
  "geometry": {"coordinates":[-8.0150671005,42.9154129028],"type":"Point"}
}