{
  "type": "Feature",
  "properties": {
    "iso:country":"ES",
    "sg:address":"Calle de Escribano, 48",
    "sg:city":"Almendralejo",
    "sg:orig_category":"Bisuter\u00cda, Joyer\u00cda, Relojer\u00cda (al Por Menor)",
    "sg:phone":"+34 924 66 16 78",
    "sg:postcode":"06200",
    "sg:province":"Badajoz",
    "wof:name":"Paredes Paredes Diego",
    "wof:placetype":"venue"
},
  "geometry": {"coordinates":[-6.4080090523,38.6820602417],"type":"Point"}
}