{
  "type": "Feature",
  "properties": {
    "addr:full":"Av Pedra Del Diable, 1 Eixample Barcelona 08150",
    "addr:housenumber":"1",
    "addr:postcode":"08150",
    "addr:street":"Av Pedra Del Diable",
    "iso:country":"ES",
    "sg:address":"Av Pedra Del Diable, 1",
    "sg:city":"Eixample",
    "sg:orig_category":"Estudios De Grabaci\u00d3n Sonora",
    "sg:phone":"+34 935 62 60 85",
    "sg:postcode":"08150",
    "sg:province":"Barcelona",
    "wof:name":"Moreno Abanades Ruben",
    "wof:placetype":"venue"
},
  "geometry": {"coordinates":[2.2319469452,41.5694198608],"type":"Point"}
}