{
  "type": "Feature",
  "properties": {
    "addr:full":"Calle de Jueves, 54 Armilla Granada 18100",
    "addr:housenumber":"54",
    "addr:postcode":"18100",
    "addr:street":"Calle De Jueves",
    "iso:country":"ES",
    "sg:address":"Calle de Jueves, 54",
    "sg:city":"Armilla",
    "sg:orig_category":"Molduras, Junquillos, Listones Y Molduras Perforadas",
    "sg:phone":"+34 958 55 09 60",
    "sg:postcode":"18100",
    "sg:province":"Granada",
    "wof:name":"Luzon Lopez Maria Ascension",
    "wof:placetype":"venue"
},
  "geometry": {"coordinates":[-3.6221110821,37.1417808533],"type":"Point"}
}