{
  "type": "Feature",
  "properties": {
    "iso:country":"ES",
    "sg:address":"Avda Doctor Waksman, 15",
    "sg:city":"Valencia",
    "sg:orig_category":"Agencias Y Agentes Comerciales, Representantes",
    "sg:phone":"+34 963 74 87 43",
    "sg:postcode":"46006",
    "sg:province":"Valencia",
    "wof:name":"Doen Valencianos S.l.",
    "wof:placetype":"venue"
},
  "geometry": {"coordinates":[-0.3736259937,39.4566459656],"type":"Point"}
}