{
  "type": "Feature",
  "properties": {
    "addr:full":"Avda Madrid De, 8 Donostia-san Sebastian Guip\u00f9zcoa 20011",
    "addr:housenumber":"8",
    "addr:postcode":"20011",
    "addr:street":"Avda Madrid De",
    "iso:country":"ES",
    "sg:address":"Avda Madrid De, 8",
    "sg:city":"Donostia-san Sebastian",
    "sg:orig_category":"Arquitectos",
    "sg:phone":"+34 943 45 28 57",
    "sg:postcode":"20011",
    "sg:province":"Guip\u00f9zcoa",
    "wof:name":"Iboleon Adarraga Rafael",
    "wof:placetype":"venue"
},
  "geometry": {"coordinates":[-1.9772880077,43.304813385],"type":"Point"}
}