{
  "type": "Feature",
  "properties": {
    "addr:full":"Calle de Fuentespina, 19 Madrid Madrid 28031",
    "addr:housenumber":"19",
    "addr:postcode":"madrid;28031",
    "addr:street":"Calle De Fuentespina",
    "iso:country":"ES",
    "sg:address":"Calle de Fuentespina, 19",
    "sg:city":"Madrid",
    "sg:classifiers":[
        {
            "category":"Professional",
            "subcategory":"Business Services",
            "type":"Services"
        }
    ],
    "sg:phone":"+34 913 31 74 27",
    "sg:postcode":"28031",
    "sg:province":"Madrid",
    "sg:tags":[
        "control",
        "asesor\u00cda",
        "organizaci\u00d3n",
        "la",
        "de",
        "gesti\u00d3n",
        "y"
    ],
    "wof:name":"Karlra Gestion S.l.",
    "wof:placetype":"venue"
},
  "geometry": {"coordinates":[-3.6052000523,40.3797683716],"type":"Point"}
}