{
  "type": "Feature",
  "properties": {
    "addr:full":"Praz Mosteiro, 213 Mosteiro Pontevedra 36313",
    "addr:housenumber":"213",
    "addr:postcode":"36313",
    "addr:street":"Praz Mosteiro",
    "iso:country":"ES",
    "sg:address":"Praz Mosteiro, 213",
    "sg:city":"Mosteiro",
    "sg:orig_category":"Ambulancias",
    "sg:phone":"+34 986 42 00 15",
    "sg:postcode":"36313",
    "sg:province":"Pontevedra",
    "wof:name":"Ambulancias Orvi S.l.",
    "wof:placetype":"venue"
},
  "geometry": {"coordinates":[-8.7467193604,41.9883499146],"type":"Point"}
}