{
  "type": "Feature",
  "properties": {
    "addr:full":"Calle de Castillo, 23 Moclinejo M\u00e1laga 29738",
    "addr:housenumber":"23",
    "addr:postcode":"29738",
    "addr:street":"Calle De Castillo;Ma\u0301Laga",
    "iso:country":"ES",
    "sg:address":"Calle de Castillo, 23",
    "sg:city":"Moclinejo",
    "sg:orig_category":"Empresas De Carpinter\u00cda",
    "sg:phone":"+34 952 40 06 88",
    "sg:postcode":"29738",
    "sg:province":"M\u00e1laga",
    "wof:name":"Fernandez Gonzalez Jose Miguel",
    "wof:placetype":"venue"
},
  "geometry": {"coordinates":[-4.253018856,36.7710533142],"type":"Point"}
}