{
  "type": "Feature",
  "properties": {
    "iso:country":"ES",
    "sg:address":"Calle de Islas Canarias, 251",
    "sg:city":"Valencia",
    "sg:orig_category":"Instalaci\u00d3n, Reparaci\u00d3n De Ascensores Y Montacargas",
    "sg:phone":"+34 963 30 14 21",
    "sg:postcode":"46023",
    "sg:province":"Valencia",
    "wof:name":"Ascensores Carbonell S. A.",
    "wof:placetype":"venue"
},
  "geometry": {"coordinates":[-0.3394738138,39.4614181519],"type":"Point"}
}