{
  "type": "Feature",
  "properties": {
    "iso:country":"ES",
    "sg:address":"Calle de Bethencourt Alfonso, 34",
    "sg:city":"Santa Cruz De Tenerife",
    "sg:orig_category":"\u00d3ptica: Instrumentos (fabricaci\u00d3n)",
    "sg:phone":"+34 922 28 71 73",
    "sg:postcode":"38002",
    "sg:province":"Santa Cruz De Tenerife",
    "wof:name":"Matilla Perez Maria Jesus",
    "wof:placetype":"venue"
},
  "geometry": {"coordinates":[-16.2505531311,28.4675483704],"type":"Point"}
}