{
  "type": "Feature",
  "properties": {
    "iso:country":"ES",
    "sg:address":"Calle de Comunidad De Madrid (de La), 1",
    "sg:city":"Fuenlabrada",
    "sg:orig_category":"Carnicer\u00cdas, Carnicer\u00cdas",
    "sg:phone":"+34 916 90 28 25",
    "sg:postcode":"28944",
    "sg:province":"Madrid",
    "wof:name":"Trijueque Monge Gabriel",
    "wof:placetype":"venue"
},
  "geometry": {"coordinates":[-3.8015139103,40.2770271301],"type":"Point"}
}