{
  "type": "Feature",
  "properties": {
    "iso:country":"ES",
    "sg:address":"Calle de Corregidor Se\u00d1or De La Elipa, 16",
    "sg:city":"Madrid",
    "sg:orig_category":"Electricidad, Electr\u00d3nica: Material Y Suministros (al Por Mayor)",
    "sg:phone":"+34 914 30 30 67",
    "sg:postcode":"28030",
    "sg:province":"Madrid",
    "wof:name":"Harkishin Mirpuri  Ashok",
    "wof:placetype":"venue"
},
  "geometry": {"coordinates":[-3.650888443,40.4112472534],"type":"Point"}
}