{
  "type": "Feature",
  "properties": {
    "iso:country":"ES",
    "sg:address":"El Pozo, 25",
    "sg:city":"Los Portales",
    "sg:orig_category":"Reparaciones Y Remolcado De Veh\u00cdculos",
    "sg:phone":"+34 928 60 20 54",
    "sg:postcode":"35400",
    "sg:province":"Las Palmas",
    "wof:name":"Acosta Alvarez Fermin Pedro",
    "wof:placetype":"venue"
},
  "geometry": {"coordinates":[-15.5116319656,28.1014461517],"type":"Point"}
}