{
  "type": "Feature",
  "properties": {
    "addr:full":"Carrer de Enginyer Moncunill, 24 Hospitalet Llobregat Barcelona 08905",
    "addr:housenumber":"24",
    "addr:postcode":"08905",
    "addr:street":"Carrer De Enginyer Moncunill",
    "iso:country":"ES",
    "sg:address":"Carrer de Enginyer Moncunill, 24",
    "sg:city":"Hospitalet Llobregat",
    "sg:orig_category":"Aparatos, Sistemas De Tele",
    "sg:phone":"+34 933 33 40 81",
    "sg:postcode":"08905",
    "sg:province":"Barcelona",
    "wof:name":"Ilersegur S.l.",
    "wof:placetype":"venue"
},
  "geometry": {"coordinates":[2.1110548973,41.3720664978],"type":"Point"}
}