{
  "type": "Feature",
  "properties": {
    "addr:full":"Calle de Delicias, 2 Zaragoza Zaragoza 50017",
    "addr:housenumber":"2",
    "addr:postcode":"50017",
    "addr:street":"Calle De Delicias",
    "iso:country":"ES",
    "sg:address":"Calle de Delicias, 2",
    "sg:city":"Zaragoza",
    "sg:orig_category":"Cl\u00cdnicas Dentales",
    "sg:phone":"+34 976 32 81 11",
    "sg:postcode":"50017",
    "sg:province":"Zaragoza",
    "wof:name":"Toledo Calvo Marcelo",
    "wof:placetype":"venue"
},
  "geometry": {"coordinates":[-0.9061440229,41.652885437],"type":"Point"}
}