{
  "type": "Feature",
  "properties": {
    "iso:country":"ES",
    "sg:address":"Plaz Fresco El, S/n",
    "sg:city":"Zamora",
    "sg:orig_category":"Prendas Y Chalecos De Punto (al Por Menor)",
    "sg:phone":"+34 980 53 04 14",
    "sg:postcode":"49004",
    "sg:province":"Zamora",
    "wof:name":"Matanzas Vidales Elisa",
    "wof:placetype":"venue"
},
  "geometry": {"coordinates":[-5.7457342148,41.5033302307],"type":"Point"}
}