{
  "type": "Feature",
  "properties": {
    "addr:full":"Calle de Juan Perez De Viedma, 9 Malaga M\u00e1laga 29190",
    "addr:housenumber":"9",
    "addr:postcode":"29190",
    "addr:street":"Calle De Juan Perez De Viedma;Ma\u0301Laga",
    "iso:country":"ES",
    "sg:address":"Calle de Juan Perez De Viedma, 9",
    "sg:city":"Malaga",
    "sg:orig_category":"Mec\u00c1nico Del Autom\u00d3vil",
    "sg:phone":"+34 952 43 20 88",
    "sg:postcode":"29190",
    "sg:province":"M\u00e1laga",
    "wof:name":"Navarrete Padilla Joaquin",
    "wof:placetype":"venue"
},
  "geometry": {"coordinates":[-4.4876151085,36.7423973083],"type":"Point"}
}