{
  "type": "Feature",
  "properties": {
    "addr:full":"Geltoki Kalea-calle Estacion, 16 Lasarte-oria Guip\u00f9zcoa 20160",
    "addr:housenumber":"16",
    "addr:postcode":"20160",
    "addr:street":"Estacion;Guipu\u0300Zcoa",
    "iso:country":"ES",
    "sg:address":"Geltoki Kalea-calle Estacion, 16",
    "sg:city":"Lasarte-oria",
    "sg:orig_category":"Inmobiliaria (agencias)",
    "sg:phone":"+34 943 24 71 86",
    "sg:postcode":"20160",
    "sg:province":"Guip\u00f9zcoa",
    "sg:website":"www.inmounanue.com",
    "wof:name":"Jon Iraola Goya Y Otro C.b.",
    "wof:placetype":"venue"
},
  "geometry": {"coordinates":[-2.020414114,43.2698173523],"type":"Point"}
}