{
  "type": "Feature",
  "properties": {
    "iso:country":"ES",
    "sg:address":"Calle de Sahagun, 14",
    "sg:city":"Alcorcon",
    "sg:orig_category":"Perfumer\u00cda Y Cosm\u00c9tica (fabricaci\u00d3n, Al Por Mayor)",
    "sg:phone":"+34 914 88 00 10",
    "sg:postcode":"28925",
    "sg:province":"Madrid",
    "wof:name":"Kosmospain S.l.",
    "wof:placetype":"venue"
},
  "geometry": {"coordinates":[-3.8207700253,40.3546524048],"type":"Point"}
}