{
  "type": "Feature",
  "properties": {
    "addr:full":"Carr Vilafant, 9 Figueres Girona 17600",
    "addr:housenumber":"9",
    "addr:postcode":"17600",
    "addr:street":"Carr Vilafant",
    "iso:country":"ES",
    "sg:address":"Carr Vilafant, 9",
    "sg:city":"Figueres",
    "sg:orig_category":"Abogados",
    "sg:phone":"+34 972 50 03 45",
    "sg:postcode":"17600",
    "sg:province":"Girona",
    "sg:website":"www.bufetsis.com",
    "wof:name":"Serra & Simon Advocats S.c.p.",
    "wof:placetype":"venue"
},
  "geometry": {"coordinates":[2.9698579311,42.2675743103],"type":"Point"}
}