{
  "type": "Feature",
  "properties": {
    "iso:country":"ES",
    "sg:address":"Plaz Pilar, S/n",
    "sg:city":"Sisante",
    "sg:orig_category":"Supermercados Y Hipermercados",
    "sg:phone":"+34 969 38 74 08",
    "sg:postcode":"16700",
    "sg:province":"Cuenca",
    "wof:name":"Autoservicio Entredos S.l.",
    "wof:placetype":"venue"
},
  "geometry": {"coordinates":[-2.2007682323,39.407989502],"type":"Point"}
}