{
  "type": "Feature",
  "properties": {
    "iso:country":"ES",
    "sg:address":"C/ Argenters, S/n",
    "sg:city":"Manacor",
    "sg:orig_category":"Comercio De Perlas",
    "sg:phone":"+34 971 55 29 48",
    "sg:postcode":"07500",
    "sg:province":"Islas Baleares",
    "wof:name":"Dumafe C.b.",
    "wof:placetype":"venue"
},
  "geometry": {"coordinates":[3.1867630482,39.5719223022],"type":"Point"}
}