{
  "type": "Feature",
  "properties": {
    "addr:full":"Plaz Espa\u00d1a, 1 Binaced Huesca 22510",
    "addr:housenumber":"1",
    "addr:postcode":"22510",
    "addr:street":"Plaz Espan\u0303A",
    "iso:country":"ES",
    "sg:address":"Plaz Espa\u00d1a, 1",
    "sg:city":"Binaced",
    "sg:orig_category":"Cajas De Ahorro",
    "sg:phone":"+34 974 42 73 82",
    "sg:postcode":"22510",
    "sg:province":"Huesca",
    "sg:website":"www.lacaixa.es",
    "wof:name":"Caixa D'estalvis I Pensions De Barcelona",
    "wof:placetype":"venue"
},
  "geometry": {"coordinates":[0.2003239989,41.8264541626],"type":"Point"}
}