{
  "type": "Feature",
  "properties": {
    "addr:full":"Avda Republica Argentina, 73 Miranda Ebro Burgos 09200",
    "addr:housenumber":"73",
    "addr:postcode":"09200",
    "addr:street":"Avda Republica Argentina",
    "iso:country":"ES",
    "sg:address":"Avda Republica Argentina, 73",
    "sg:city":"Miranda Ebro",
    "sg:orig_category":"Confecci\u00d3n (fabricaci\u00d3n, Al Por Mayor)",
    "sg:phone":"+34 947 33 54 99",
    "sg:postcode":"09200",
    "sg:province":"Burgos",
    "wof:name":"Gomez Lama Elvira",
    "wof:placetype":"venue"
},
  "geometry": {"coordinates":[-2.9373600483,42.6876335144],"type":"Point"}
}