{
  "type": "Feature",
  "properties": {
    "iso:country":"ES",
    "sg:address":"Avda Constitucion (de La), 2",
    "sg:city":"Montilla",
    "sg:orig_category":"Molduras, Junquillos, Listones Y Molduras Perforadas",
    "sg:phone":"+34 957 65 34 52",
    "sg:postcode":"14550",
    "sg:province":"C\u00f3rdoba",
    "wof:name":"Lopez Amaro Angel",
    "wof:placetype":"venue"
},
  "geometry": {"coordinates":[-4.645804882,37.5788040161],"type":"Point"}
}