{
  "type": "Feature",
  "properties": {
    "iso:country":"ES",
    "sg:address":"Calle de Mayor, 36",
    "sg:city":"Lumbier",
    "sg:orig_category":"Pescader\u00cdas (al Por Menor)",
    "sg:phone":"+34 948 88 00 82",
    "sg:postcode":"31440",
    "sg:province":"Navarra",
    "wof:name":"Vicente Torres Felisa",
    "wof:placetype":"venue"
},
  "geometry": {"coordinates":[-1.3071609735,42.6529083252],"type":"Point"}
}