{
  "type": "Feature",
  "properties": {
    "iso:country":"ES",
    "sg:address":"Carrer de Corsega, 163",
    "sg:city":"Barcelona",
    "sg:orig_category":"Maquinaria Para Industrias Diversas",
    "sg:phone":"+34 934 19 26 79",
    "sg:postcode":"08036",
    "sg:province":"Barcelona",
    "sg:website":"www.iberseles.com",
    "wof:name":"Iberselex S.a.",
    "wof:placetype":"venue"
},
  "geometry": {"coordinates":[2.1494650841,41.3891448975],"type":"Point"}
}