{
  "type": "Feature",
  "properties": {
    "addr:full":"Calle de Juan De Herrera, 32 Entrepinos Valladolid 47130",
    "addr:housenumber":"32",
    "addr:postcode":"47130",
    "addr:street":"Calle De Juan De Herrera",
    "iso:country":"ES",
    "sg:address":"Calle de Juan De Herrera, 32",
    "sg:city":"Entrepinos",
    "sg:orig_category":"Abogados",
    "sg:phone":"+34 983 59 12 96",
    "sg:postcode":"47130",
    "sg:province":"Valladolid",
    "wof:name":"Vilches Zapata Ana Maria",
    "wof:placetype":"venue"
},
  "geometry": {"coordinates":[-4.8235812187,41.5907974243],"type":"Point"}
}