{
  "type": "Feature",
  "properties": {
    "iso:country":"ES",
    "sg:address":"Avia Puente Colgante, S/n",
    "sg:city":"Valladolid",
    "sg:orig_category":"Parafarmacias",
    "sg:phone":"+34 983 37 81 97",
    "sg:postcode":"47014",
    "sg:province":"Valladolid",
    "wof:name":"Andres Camino S.l.",
    "wof:placetype":"venue"
},
  "geometry": {"coordinates":[-4.7536277771,41.6377105713],"type":"Point"}
}