{
  "type": "Feature",
  "properties": {
    "addr:full":"Carrer de Claramunt, 23 Barcelona Barcelona 08030",
    "addr:housenumber":"23",
    "addr:postcode":"08030",
    "addr:street":"Carrer De Claramunt",
    "iso:country":"ES",
    "sg:address":"Carrer de Claramunt, 23",
    "sg:city":"Barcelona",
    "sg:orig_category":"Chapister\u00cda",
    "sg:phone":"+34 933 46 22 20",
    "sg:postcode":"08030",
    "sg:province":"Barcelona",
    "wof:name":"Sanchez Portero Francisco",
    "wof:placetype":"venue"
},
  "geometry": {"coordinates":[2.2047550678,41.43699646],"type":"Point"}
}