{
  "type": "Feature",
  "properties": {
    "addr:full":"Avda Mediterraneo, 33 Madrid Madrid 28007",
    "addr:housenumber":"33",
    "addr:postcode":"madrid;28007",
    "addr:street":"Avda Mediterraneo",
    "iso:country":"ES",
    "sg:address":"Avda Mediterraneo, 33",
    "sg:city":"Madrid",
    "sg:orig_category":"Supermercados Y Hipermercados",
    "sg:phone":"+34 914 33 22 00",
    "sg:postcode":"28007",
    "sg:province":"Madrid",
    "sg:website":"www.capraboacasa.com",
    "wof:name":"Caprabo S.a.",
    "wof:placetype":"venue"
},
  "geometry": {"coordinates":[-3.6723430157,40.4070091248],"type":"Point"}
}