{
  "type": "Feature",
  "properties": {
    "iso:country":"ES",
    "sg:address":"Av San Jorge, 69",
    "sg:city":"Iru\u00f1a",
    "sg:orig_category":"Supermercados Y Hipermercados",
    "sg:phone":"+34 948 14 17 94",
    "sg:postcode":"31012",
    "sg:province":"Navarra",
    "wof:name":"Gorriz Ardaiz Maria Teresa",
    "wof:placetype":"venue"
},
  "geometry": {"coordinates":[-1.6675269604,42.8210754395],"type":"Point"}
}