{
  "type": "Feature",
  "properties": {
    "addr:full":"Calle de Carcel De La Corona, 5 Valladolid Valladolid 47005",
    "addr:housenumber":"5",
    "addr:postcode":"47005",
    "addr:street":"Calle De Carcel De La Corona",
    "iso:country":"ES",
    "sg:address":"Calle de Carcel De La Corona, 5",
    "sg:city":"Valladolid",
    "sg:orig_category":"Peluquer\u00cdas, Peluquer\u00cda Mixta",
    "sg:phone":"+34 983 29 79 53",
    "sg:postcode":"47005",
    "sg:province":"Valladolid",
    "wof:name":"Martin Mu\u00f1oz Claudia",
    "wof:placetype":"venue"
},
  "geometry": {"coordinates":[-4.7171134949,41.6522293091],"type":"Point"}
}