{
  "type": "Feature",
  "properties": {
    "addr:full":"Calle de Tableron, 9 Jaen Ja\u00e9n 23001",
    "addr:housenumber":"9;jae\u0301n",
    "addr:postcode":"23001",
    "addr:street":"Calle De Tableron",
    "iso:country":"ES",
    "sg:address":"Calle de Tableron, 9",
    "sg:city":"Jaen",
    "sg:orig_category":"M\u00c1quinas De Escribir, M\u00c1quinas De Oficina (al Por Menor, Reparaci\u00d3n)",
    "sg:phone":"+34 953 24 10 39",
    "sg:postcode":"23001",
    "sg:province":"Ja\u00e9n",
    "wof:name":"Moreno Lanzas Francisco",
    "wof:placetype":"venue"
},
  "geometry": {"coordinates":[-3.7906870842,37.7650947571],"type":"Point"}
}