{
  "type": "Feature",
  "properties": {
    "addr:full":"Carretera, S/n Valderrobres Teruel 44580",
    "addr:postcode":"44580",
    "addr:street":"Carretera S / N",
    "iso:country":"ES",
    "sg:address":"Carretera, S/n",
    "sg:city":"Valderrobres",
    "sg:orig_category":"Alimentaci\u00d3n General (al Por Mayor)",
    "sg:phone":"+34 978 85 06 82",
    "sg:postcode":"44580",
    "sg:province":"Teruel",
    "wof:name":"Esypu S.l",
    "wof:placetype":"venue"
},
  "geometry": {"coordinates":[0.1538449973,40.8726615906],"type":"Point"}
}