{
  "type": "Feature",
  "properties": {
    "addr:full":"Calle de Gabriel Lobo, 10 Madrid Madrid 28002",
    "addr:housenumber":"10",
    "addr:postcode":"madrid;28002",
    "addr:street":"Calle De Gabriel Lobo",
    "iso:country":"ES",
    "sg:address":"Calle de Gabriel Lobo, 10",
    "sg:city":"Madrid",
    "sg:orig_category":"Molduras, Junquillos, Listones Y Molduras Perforadas",
    "sg:phone":"+34 915 64 37 65",
    "sg:postcode":"28002",
    "sg:province":"Madrid",
    "wof:name":"Lagaron Fernandez Juan Carlos",
    "wof:placetype":"venue"
},
  "geometry": {"coordinates":[-3.6810235977,40.4426345825],"type":"Point"}
}