{
  "type": "Feature",
  "properties": {
    "iso:country":"ES",
    "sg:address":"El Soto, S/n",
    "sg:city":"Quintana Pidio",
    "sg:orig_category":"Productores Recolectores, Venta Directa De Vinos",
    "sg:phone":"+34 947 54 56 99",
    "sg:postcode":"09443",
    "sg:province":"Burgos",
    "wof:name":"Bodegas J.a.calvo Casajus S.l.",
    "wof:placetype":"venue"
},
  "geometry": {"coordinates":[-3.7958199978,41.7082672119],"type":"Point"}
}