{
  "type": "Feature",
  "properties": {
    "addr:full":"Avda Vicente Medina, 2 Fortuna Murcia 30620",
    "addr:housenumber":"2",
    "addr:postcode":"30620",
    "addr:street":"Avda Vicente Medina",
    "iso:country":"ES",
    "sg:address":"Avda Vicente Medina, 2",
    "sg:city":"Fortuna",
    "sg:orig_category":"Mec\u00c1nico Del Autom\u00d3vil",
    "sg:phone":"+34 968 68 51 26",
    "sg:postcode":"30620",
    "sg:province":"Murcia",
    "wof:name":"Ruiz Marco Antonio",
    "wof:placetype":"venue"
},
  "geometry": {"coordinates":[-1.1288340092,38.1811676025],"type":"Point"}
}