{
  "type": "Feature",
  "properties": {
    "addr:full":"Calle de Bami, 27 Sevilla Sevilla 41013",
    "addr:housenumber":"27",
    "addr:postcode":"41013",
    "addr:street":"Calle De Bami",
    "iso:country":"ES",
    "sg:address":"Calle de Bami, 27",
    "sg:city":"Sevilla",
    "sg:orig_category":"Financiaci\u00d3n Y Cr\u00c9ditos",
    "sg:phone":"+34 954 23 99 20",
    "sg:postcode":"41013",
    "sg:province":"Sevilla",
    "wof:name":"Trevalher Y Asociados S.l.",
    "wof:placetype":"venue"
},
  "geometry": {"coordinates":[-5.9784693718,37.3589630127],"type":"Point"}
}