{
  "type": "Feature",
  "properties": {
    "addr:full":"Carrer de Lleo Xiii, 25 Barcelona Barcelona 08022",
    "addr:housenumber":"25",
    "addr:postcode":"08022",
    "addr:street":"Carrer De Lleo Xiii",
    "iso:country":"ES",
    "sg:address":"Carrer de Lleo Xiii, 25",
    "sg:city":"Barcelona",
    "sg:orig_category":"Abogados",
    "sg:phone":"+34 932 53 01 34",
    "sg:postcode":"08022",
    "sg:province":"Barcelona",
    "sg:website":"www.fabregat-perulles-sales.com",
    "wof:name":"Fabregat Perulles Sales Abogados S.c.p.",
    "wof:placetype":"venue"
},
  "geometry": {"coordinates":[2.1366899014,41.4128036499],"type":"Point"}
}