{
  "type": "Feature",
  "properties": {
    "addr:full":"Avda Asturias, 10 Boal Asturias 33720",
    "addr:housenumber":"10",
    "addr:postcode":"33720",
    "addr:street":"Avda Asturias",
    "iso:country":"ES",
    "sg:address":"Avda Asturias, 10",
    "sg:city":"Boal",
    "sg:orig_category":"Agentes Generales De Seguros",
    "sg:phone":"+34 985 62 06 18",
    "sg:postcode":"33720",
    "sg:province":"Asturias",
    "sg:website":"www.winterthur.es",
    "wof:name":"Martinez Fernandez Jose Ramon",
    "wof:placetype":"venue"
},
  "geometry": {"coordinates":[-6.81873703,43.4276847839],"type":"Point"}
}