{
  "type": "Feature",
  "properties": {
    "iso:country":"ES",
    "sg:address":"Carrer de Sepulveda, 136",
    "sg:city":"Barcelona",
    "sg:orig_category":"Peluquer\u00cdas, Peluquer\u00cda Mixta",
    "sg:phone":"+34 934 23 60 75",
    "sg:postcode":"08015",
    "sg:province":"Barcelona",
    "wof:name":"Diaz Soro Zulima Salome",
    "wof:placetype":"venue"
},
  "geometry": {"coordinates":[2.1596829891,41.3808860779],"type":"Point"}
}