{
  "type": "Feature",
  "properties": {
    "addr:full":"Calle de Leganes, 8 Parla Madrid 28980",
    "addr:housenumber":"8",
    "addr:postcode":"28980",
    "addr:street":"Calle De Leganes",
    "iso:country":"ES",
    "sg:address":"Calle de Leganes, 8",
    "sg:city":"Parla",
    "sg:orig_category":"Panader\u00cdas, Panader\u00cdas",
    "sg:phone":"+34 916 98 50 58",
    "sg:postcode":"28980",
    "sg:province":"Madrid",
    "wof:name":"Zou  Xiuming",
    "wof:placetype":"venue"
},
  "geometry": {"coordinates":[-3.7706487179,40.2417984009],"type":"Point"}
}