{
  "type": "Feature",
  "properties": {
    "iso:country":"ES",
    "sg:address":"Dieciocho Julio, 30",
    "sg:city":"Galvez",
    "sg:orig_category":"Reposter\u00cdas",
    "sg:phone":"+34 925 40 09 44",
    "sg:postcode":"45164",
    "sg:province":"Toledo",
    "wof:name":"Manrique Linares Jesus",
    "wof:placetype":"venue"
},
  "geometry": {"coordinates":[-4.2710590363,39.7023506165],"type":"Point"}
}