{
  "type": "Feature",
  "properties": {
    "addr:full":"Calle de Isaac Albeniz, 75 Majadahonda Madrid 28220",
    "addr:housenumber":"75",
    "addr:postcode":"28220",
    "addr:street":"Calle De Isaac Albeniz",
    "iso:country":"ES",
    "sg:address":"Calle de Isaac Albeniz, 75",
    "sg:city":"Majadahonda",
    "sg:orig_category":"Inmobiliaria (agencias)",
    "sg:phone":"+34 916 02 88 10",
    "sg:postcode":"28220",
    "sg:province":"Madrid",
    "wof:name":"Novoline Majadahonda Inmuebles S.l.",
    "wof:placetype":"venue"
},
  "geometry": {"coordinates":[-3.8682870865,40.4452667236],"type":"Point"}
}