{
  "type": "Feature",
  "properties": {
    "addr:full":"Calle de Serrota (la), 3 Avila \u00c1vila 05002",
    "addr:housenumber":"3",
    "addr:postcode":"05002",
    "addr:street":"Calle De Serrota La;A\u0301Vila",
    "iso:country":"ES",
    "sg:address":"Calle de Serrota (la), 3",
    "sg:city":"Avila",
    "sg:orig_category":"Electricidad, Electr\u00d3nica: Suministros (al Por Menor)",
    "sg:phone":"+34 920 25 49 16",
    "sg:postcode":"05002",
    "sg:province":"\u00c1vila",
    "wof:name":"Decoba\u00f1o Ajates S.l.",
    "wof:placetype":"venue"
},
  "geometry": {"coordinates":[-4.7004818916,40.6487426758],"type":"Point"}
}