{
  "type": "Feature",
  "properties": {
    "iso:country":"ES",
    "sg:address":"Plaz Constitucion, S/n",
    "sg:city":"Navia",
    "sg:orig_category":"Frutas, Legumbres Frescas Y Tempranas (al Por Menor)",
    "sg:phone":"+34 985 63 17 66",
    "sg:postcode":"33710",
    "sg:province":"Asturias",
    "wof:name":"Baniela Perez Marisol",
    "wof:placetype":"venue"
},
  "geometry": {"coordinates":[-6.7236289978,43.5388832092],"type":"Point"}
}