{
  "type": "Feature",
  "properties": {
    "iso:country":"ES",
    "sg:address":"Calle de Chile, 2",
    "sg:city":"Herrera Pisuerga",
    "sg:orig_category":"Ense\u00d1anza Secundaria: Colegios Y Escuelas Privadas",
    "sg:phone":"+34 979 13 07 32",
    "sg:postcode":"34400",
    "sg:province":"Palencia",
    "wof:name":"I.e.s.herrera De Pisuerga",
    "wof:placetype":"venue"
},
  "geometry": {"coordinates":[-4.3337192535,42.5951156616],"type":"Point"}
}