{
  "type": "Feature",
  "properties": {
    "iso:country":"ES",
    "sg:address":"Carrer de Lusitania, 75",
    "sg:city":"Sabadell",
    "sg:orig_category":"Cristaler\u00cdas",
    "sg:phone":"+34 937 17 33 99",
    "sg:postcode":"08206",
    "sg:province":"Barcelona",
    "wof:name":"Arisa Filella Juan",
    "wof:placetype":"venue"
},
  "geometry": {"coordinates":[2.0919601917,41.5596885681],"type":"Point"}
}