{
  "type": "Feature",
  "properties": {
    "iso:country":"ES",
    "sg:address":"Calle de Federico Garcia Lorca (de), 3",
    "sg:city":"Mejorada Campo",
    "sg:orig_category":"Reposter\u00cdas",
    "sg:phone":"+34 916 79 24 95",
    "sg:postcode":"28840",
    "sg:province":"Madrid",
    "wof:name":"Espinosa Garrido Antonio",
    "wof:placetype":"venue"
},
  "geometry": {"coordinates":[-3.487678051,40.3975753784],"type":"Point"}
}