{
  "type": "Feature",
  "properties": {
    "iso:country":"ES",
    "sg:address":"Avda Celanova (de), 126",
    "sg:city":"Valenza",
    "sg:orig_category":"Electricidad Veh\u00cdculo",
    "sg:phone":"+34 988 22 96 43",
    "sg:postcode":"32002",
    "sg:province":"Ourense",
    "wof:name":"Juan Cruz Cruz Y Francisco Manso Quintas C. B.",
    "wof:placetype":"venue"
},
  "geometry": {"coordinates":[-7.8807220459,42.3224868774],"type":"Point"}
}