{
  "type": "Feature",
  "properties": {
    "iso:country":"ES",
    "sg:address":"Carrer de Torrent De L'alba, 4",
    "sg:city":"Rubi",
    "sg:orig_category":"Abogados",
    "sg:phone":"+34 935 88 42 71",
    "sg:postcode":"08191",
    "sg:province":"Barcelona",
    "wof:name":"Cortes Palenciano Antonio",
    "wof:placetype":"venue"
},
  "geometry": {"coordinates":[2.0342447758,41.4899673462],"type":"Point"}
}