{
  "type": "Feature",
  "properties": {
    "iso:country":"ES",
    "sg:address":"Calle de Francisco Hurtado Izquierdo, 10",
    "sg:city":"Granada",
    "sg:orig_category":"Farmacias",
    "sg:phone":"+34 958 15 25 78",
    "sg:postcode":"18011",
    "sg:province":"Granada",
    "wof:name":"Suazo Garcia Sebastiana Orencia",
    "wof:placetype":"venue"
},
  "geometry": {"coordinates":[-3.6046628952,37.2051315308],"type":"Point"}
}