{
  "type": "Feature",
  "properties": {
    "addr:full":"Alam Principal, 11 Malaga M\u00e1laga 29001",
    "addr:housenumber":"11",
    "addr:postcode":"29001",
    "addr:street":"Alam Principal;Ma\u0301Laga",
    "iso:country":"ES",
    "sg:address":"Alam Principal, 11",
    "sg:city":"Malaga",
    "sg:orig_category":"Promotores Constructores",
    "sg:phone":"+34 952 22 20 96",
    "sg:postcode":"29001",
    "sg:province":"M\u00e1laga",
    "wof:name":"Gestion Siglo Xxi S.l.",
    "wof:placetype":"venue"
},
  "geometry": {"coordinates":[-4.4219222069,36.7174606323],"type":"Point"}
}