{
  "type": "Feature",
  "properties": {
    "iso:country":"ES",
    "sg:address":"Calle de Isandro, 25",
    "sg:city":"Madrid",
    "sg:orig_category":"Molduras, Junquillos, Listones Y Molduras Perforadas",
    "sg:phone":"+34 913 27 50 38",
    "sg:postcode":"28037",
    "sg:province":"Madrid",
    "wof:name":"Isla Prieto Rafael",
    "wof:placetype":"venue"
},
  "geometry": {"coordinates":[-3.6272559166,40.4261360168],"type":"Point"}
}