{
  "type": "Feature",
  "properties": {
    "iso:country":"ES",
    "sg:address":"Calle de Campoamor, 6",
    "sg:city":"Castellon",
    "sg:orig_category":"Mercer\u00cda, Lencer\u00cda (al Por Menor)",
    "sg:phone":"+34 964 23 99 04",
    "sg:postcode":"12001",
    "sg:province":"Castell\u00f3n",
    "wof:name":"Blonda Merceria S.l.",
    "wof:placetype":"venue"
},
  "geometry": {"coordinates":[-0.0360100009,39.984500885],"type":"Point"}
}