{
  "type": "Feature",
  "properties": {
    "iso:country":"ES",
    "sg:address":"Calle de Reina, 65",
    "sg:city":"Valencia",
    "sg:orig_category":"Art\u00cdculos De Regalo (al Por Menor)",
    "sg:phone":"+34 963 72 09 02",
    "sg:postcode":"46011",
    "sg:province":"Valencia",
    "wof:name":"Peiro Buch Consuelo Josefa",
    "wof:placetype":"venue"
},
  "geometry": {"coordinates":[-0.3291620016,39.4666023254],"type":"Point"}
}