{
  "type": "Feature",
  "properties": {
    "addr:full":"Polig. Industrial, S/n Vilalba Lugo 27800",
    "addr:housenumber":"/ n",
    "addr:postcode":"27800",
    "addr:street":"Industrial",
    "iso:country":"ES",
    "sg:address":"Polig. Industrial, S/n",
    "sg:city":"Vilalba",
    "sg:orig_category":"Mec\u00c1nico Del Autom\u00d3vil",
    "sg:phone":"+34 982 52 30 05",
    "sg:postcode":"27800",
    "sg:province":"Lugo",
    "wof:name":"Paco Mendez S.l.",
    "wof:placetype":"venue"
},
  "geometry": {"coordinates":[-7.6795740128,43.2989387512],"type":"Point"}
}