{
  "type": "Feature",
  "properties": {
    "iso:country":"ES",
    "sg:address":"Calle de Laguna, 9",
    "sg:city":"Sada",
    "sg:orig_category":"Servicio De Salud",
    "sg:phone":"+34 981 62 06 73",
    "sg:postcode":"15160",
    "sg:province":"La Coru\u00f1a",
    "wof:name":"Calefaccion Y Saneamientos Sada S.l.",
    "wof:placetype":"venue"
},
  "geometry": {"coordinates":[-8.2548141479,43.3510665894],"type":"Point"}
}