{
  "type": "Feature",
  "properties": {
    "addr:full":"Calle de Gutierre De Cetina, 71 Madrid Madrid 28017",
    "addr:housenumber":"71",
    "addr:postcode":"madrid;28017",
    "addr:street":"Calle De Gutierre De Cetina",
    "iso:country":"ES",
    "sg:address":"Calle de Gutierre De Cetina, 71",
    "sg:city":"Madrid",
    "sg:orig_category":"Frutas, Legumbres Frescas Y Tempranas (al Por Menor)",
    "sg:phone":"+34 913 67 68 60",
    "sg:postcode":"28017",
    "sg:province":"Madrid",
    "wof:name":"Hermanos Mu\u00f1oz Diaz S.c.",
    "wof:placetype":"venue"
},
  "geometry": {"coordinates":[-3.6415836811,40.4304275513],"type":"Point"}
}