{
  "type": "Feature",
  "properties": {
    "addr:full":"Eugenio Lopez Lopez, S/n Ortigueira La Coru\u00f1a 15330",
    "addr:housenumber":"s / n",
    "addr:postcode":"15330",
    "addr:street":"Eugenio Lopez Lopez;La Corun\u0303A",
    "iso:country":"ES",
    "sg:address":"Eugenio Lopez Lopez, S/n",
    "sg:city":"Ortigueira",
    "sg:orig_category":"Peluquer\u00cdas, Peluquer\u00cda Mixta",
    "sg:phone":"+34 981 40 03 03",
    "sg:postcode":"15330",
    "sg:province":"La Coru\u00f1a",
    "wof:name":"Salon Geminis S.l.",
    "wof:placetype":"venue"
},
  "geometry": {"coordinates":[-7.8515739441,43.6848068237],"type":"Point"}
}