{
  "type": "Feature",
  "properties": {
    "addr:full":"Pl Doctor Fleming, 8 Badalona Barcelona 08917",
    "addr:housenumber":"8",
    "addr:postcode":"08917",
    "addr:street":"Pl Doctor Fleming",
    "iso:country":"ES",
    "sg:address":"Pl Doctor Fleming, 8",
    "sg:city":"Badalona",
    "sg:orig_category":"Molduras, Junquillos, Listones Y Molduras Perforadas",
    "sg:phone":"+34 933 87 26 61",
    "sg:postcode":"08917",
    "sg:province":"Barcelona",
    "wof:name":"Boada Guaita Narciso",
    "wof:placetype":"venue"
},
  "geometry": {"coordinates":[2.2254400253,41.4526062012],"type":"Point"}
}