{
  "type": "Feature",
  "properties": {
    "addr:full":"Avda Constitucion, 204 Torrejon Ardoz Madrid 28850",
    "addr:housenumber":"204",
    "addr:postcode":"28850",
    "addr:street":"Avda Constitucion",
    "iso:country":"ES",
    "sg:address":"Avda Constitucion, 204",
    "sg:city":"Torrejon Ardoz",
    "sg:orig_category":"Metalurgia",
    "sg:phone":"+34 916 56 85 85",
    "sg:postcode":"28850",
    "sg:province":"Madrid",
    "wof:name":"Manufacturados Ardoz S.l.",
    "wof:placetype":"venue"
},
  "geometry": {"coordinates":[-3.4472110271,40.4630508423],"type":"Point"}
}