{
  "type": "Feature",
  "properties": {
    "iso:country":"ES",
    "sg:address":"Pg Colom, 3",
    "sg:city":"Barcelona",
    "sg:orig_category":"Ingenier\u00cda, Centros De Estudios (diversos)",
    "sg:phone":"+34 933 10 78 28",
    "sg:postcode":"08002",
    "sg:province":"Barcelona",
    "wof:name":"Ramugosa Garrido Jose",
    "wof:placetype":"venue"
},
  "geometry": {"coordinates":[2.1814661026,41.3808441162],"type":"Point"}
}