{
  "type": "Feature",
  "properties": {
    "addr:full":"Carr Girona, S/n Arbeca Lleida 25140",
    "addr:housenumber":"s / n",
    "addr:postcode":"25140",
    "addr:street":"Carr Girona",
    "iso:country":"ES",
    "sg:address":"Carr Girona, S/n",
    "sg:city":"Arbeca",
    "sg:orig_category":"Electricidad: Instaladores",
    "sg:phone":"+34 973 16 03 22",
    "sg:postcode":"25140",
    "sg:province":"Lleida",
    "wof:name":"Pernau S.l.",
    "wof:placetype":"venue"
},
  "geometry": {"coordinates":[0.9238830209,41.5452575684],"type":"Point"}
}