{
  "type": "Feature",
  "properties": {
    "iso:country":"ES",
    "sg:address":"Electronica (pol Guixeres), S/n",
    "sg:city":"Badalona",
    "sg:orig_category":"Tapiceros Y Tapiceros",
    "sg:phone":"+34 933 95 36 35",
    "sg:postcode":"08915",
    "sg:province":"Barcelona",
    "wof:name":"Arquitectura Interior Actualia S.l.",
    "wof:placetype":"venue"
},
  "geometry": {"coordinates":[2.2507317066,41.466835022],"type":"Point"}
}