{
  "type": "Feature",
  "properties": {
    "addr:full":"Carr Pi I Margall, 35 Lleida Lleida 25004",
    "addr:housenumber":"35",
    "addr:postcode":"25004",
    "addr:street":"Carr Pi I Margall",
    "iso:country":"ES",
    "sg:address":"Carr Pi I Margall, 35",
    "sg:city":"Lleida",
    "sg:orig_category":"Mercer\u00cda, Lencer\u00cda (al Por Menor)",
    "sg:phone":"+34 973 23 37 31",
    "sg:postcode":"25004",
    "sg:province":"Lleida",
    "wof:name":"Alba Barri Elias",
    "wof:placetype":"venue"
},
  "geometry": {"coordinates":[0.626893878,41.6221351624],"type":"Point"}
}