{
  "type": "Feature",
  "properties": {
    "iso:country":"ES",
    "sg:address":"Calle de La Florida, 8",
    "sg:city":"Vitoria-gasteiz",
    "sg:orig_category":"Ense\u00d1anza: Idiomas",
    "sg:phone":"+34 945 15 01 55",
    "sg:postcode":"01005",
    "sg:province":"\u00c1lava",
    "sg:website":"www.cim-idiomas.com",
    "wof:name":"Ikasondo S.l. Unipersonal",
    "wof:placetype":"venue"
},
  "geometry": {"coordinates":[-2.6739690304,42.8433609009],"type":"Point"}
}