{
  "type": "Feature",
  "properties": {
    "iso:country":"ES",
    "sg:address":"Ctra. Tous, Km. 0001,6",
    "sg:city":"Alberic",
    "sg:orig_category":"Reposter\u00cdas",
    "sg:phone":"+34 962 44 29 16",
    "sg:postcode":"46260",
    "sg:province":"Valencia",
    "wof:name":"Worldpan S.l.",
    "wof:placetype":"venue"
},
  "geometry": {"coordinates":[-0.5238810182,39.1189575195],"type":"Point"}
}