{
  "type": "Feature",
  "properties": {
    "addr:full":"Ctra Suspiro Moro, Km. 0001,0 Almu\u00f1ecar Granada 18690",
    "addr:postcode":"18690",
    "addr:street":"Ctra Suspiro Moro Km. 0001,0",
    "iso:country":"ES",
    "sg:address":"Ctra Suspiro Moro, Km. 0001,0",
    "sg:city":"Almu\u00f1ecar",
    "sg:orig_category":"Promotores Constructores",
    "sg:phone":"+34 958 63 44 77",
    "sg:postcode":"18690",
    "sg:province":"Granada",
    "sg:website":"www.cortijosantacruz.info",
    "wof:name":"Promotora Social Del Cercado De Santa Cruz S.l.",
    "wof:placetype":"venue"
},
  "geometry": {"coordinates":[-3.6897239685,36.737651825],"type":"Point"}
}