{
  "type": "Feature",
  "properties": {
    "addr:full":"Crri Garre, 23 Santiago El Mayor Murcia 30012",
    "addr:housenumber":"23",
    "addr:postcode":"30012",
    "addr:street":"Garre",
    "iso:country":"ES",
    "sg:address":"Crri Garre, 23",
    "sg:city":"Santiago El Mayor",
    "sg:orig_category":"Empresarios",
    "sg:phone":"+34 968 25 04 21",
    "sg:postcode":"30012",
    "sg:province":"Murcia",
    "wof:name":"Martinez Pineda Maria Jose",
    "wof:placetype":"venue"
},
  "geometry": {"coordinates":[-1.1206640005,37.9650650024],"type":"Point"}
}