{
  "type": "Feature",
  "properties": {
    "iso:country":"ES",
    "sg:address":"Carrer de Muntaner, 248",
    "sg:city":"Barcelona",
    "sg:orig_category":"M\u00c9dicos: Pediatr\u00cda. Enfermedades De Los Ni\u00d1os",
    "sg:phone":"+34 932 00 55 40",
    "sg:postcode":"08021",
    "sg:province":"Barcelona",
    "wof:name":"Trias Ba\u00f1eres Alfonso",
    "wof:placetype":"venue"
},
  "geometry": {"coordinates":[2.1486949921,41.3949394226],"type":"Point"}
}