{
  "type": "Feature",
  "properties": {
    "addr:full":"Urb Camino De Orconera, 2 Astillero Cantabria 39610",
    "addr:housenumber":"2",
    "addr:postcode":"39610",
    "addr:street":"Urb Camino De Orconera",
    "iso:country":"ES",
    "sg:address":"Urb Camino De Orconera, 2",
    "sg:city":"Astillero",
    "sg:orig_category":"Librer\u00cdas",
    "sg:phone":"+34 942 54 35 93",
    "sg:postcode":"39610",
    "sg:province":"Cantabria",
    "wof:name":"Pacheco Palencia Bego\u00f1a",
    "wof:placetype":"venue"
},
  "geometry": {"coordinates":[-3.821928978,43.4001655579],"type":"Point"}
}