{
  "type": "Feature",
  "properties": {
    "addr:full":"Ptda La Hoya, S/n La Hoya Alicante 03294",
    "addr:housenumber":"s / n",
    "addr:postcode":"03294",
    "addr:street":"Ptda La Hoya",
    "iso:country":"ES",
    "sg:address":"Ptda La Hoya, S/n",
    "sg:city":"La Hoya",
    "sg:orig_category":"Cooperativas Agr\u00cdcolas",
    "sg:phone":"+34 965 45 01 71",
    "sg:postcode":"03294",
    "sg:province":"Alicante",
    "wof:name":"Cooperativa Del Campo De Elche Coop.v",
    "wof:placetype":"venue"
},
  "geometry": {"coordinates":[-0.6838840246,38.2138900757],"type":"Point"}
}