{
  "type": "Feature",
  "properties": {
    "iso:country":"ES",
    "sg:address":"Avda Constitucion, 40",
    "sg:city":"Callosa Segura",
    "sg:orig_category":"Moquetas, Alfombras (al Por Menor)",
    "sg:phone":"+34 966 75 60 38",
    "sg:postcode":"03360",
    "sg:province":"Alicante",
    "wof:name":"Francisco Manuel Latorre Coves Y Otros C.b.",
    "wof:placetype":"venue"
},
  "geometry": {"coordinates":[-0.8777260184,38.1288642883],"type":"Point"}
}