{
  "type": "Feature",
  "properties": {
    "iso:country":"ES",
    "sg:address":"Calle de Coronel Beorlegui, 62",
    "sg:city":"Secar De La Real",
    "sg:orig_category":"Peluquer\u00cdas, Peluquer\u00cda Mixta",
    "sg:phone":"+34 971 76 07 36",
    "sg:postcode":"07010",
    "sg:province":"Islas Baleares",
    "wof:name":"Arjona Royo Antonia",
    "wof:placetype":"venue"
},
  "geometry": {"coordinates":[2.6355280876,39.6037330627],"type":"Point"}
}