{
  "type": "Feature",
  "properties": {
    "iso:country":"ES",
    "sg:address":"Carrer de Puigmal, S/n",
    "sg:city":"Cantallops",
    "sg:orig_category":"Diplomas Diversos",
    "sg:phone":"+34 938 43 65 17",
    "sg:postcode":"08185",
    "sg:province":"Barcelona",
    "sg:website":"www.biocop.es",
    "wof:name":"Biocop Productos Biologicos S.a.",
    "wof:placetype":"venue"
},
  "geometry": {"coordinates":[2.2333259583,41.580696106],"type":"Point"}
}