{
  "type": "Feature",
  "properties": {
    "iso:country":"ES",
    "sg:address":"Calle de Norte, 19",
    "sg:city":"Valencia",
    "sg:orig_category":"Electricidad, Electr\u00d3nica: Suministros (al Por Menor)",
    "sg:phone":"+34 963 82 45 78",
    "sg:postcode":"46008",
    "sg:province":"Valencia",
    "wof:name":"Componentes Electronicos Valencia S.l.",
    "wof:placetype":"venue"
},
  "geometry": {"coordinates":[-0.3913019896,39.4758415222],"type":"Point"}
}