{
  "type": "Feature",
  "properties": {
    "iso:country":"ES",
    "sg:address":"Pase Santa Maria De La Cabeza, 12",
    "sg:city":"Madrid",
    "sg:orig_category":"Oficinas De Cambio",
    "sg:phone":"+34 915 39 98 08",
    "sg:postcode":"28045",
    "sg:province":"Madrid",
    "sg:website":"www.moneyspain.com",
    "wof:name":"Money Exchange S.a.",
    "wof:placetype":"venue"
},
  "geometry": {"coordinates":[-3.6987500191,40.4011230469],"type":"Point"}
}