{
  "type": "Feature",
  "properties": {
    "iso:country":"ES",
    "sg:address":"Carrer de Lepant, 374",
    "sg:city":"Barcelona",
    "sg:orig_category":"Comercio De Piezas De Recambio Y De Accesorios De Veh\u00cdculos, Veh\u00cdculos Industriales",
    "sg:phone":"+34 934 35 09 00",
    "sg:postcode":"08025",
    "sg:province":"Barcelona",
    "wof:name":"Comercial Del Motor S. A.",
    "wof:placetype":"venue"
},
  "geometry": {"coordinates":[2.1708049774,41.4091033936],"type":"Point"}
}