{
  "type": "Feature",
  "properties": {
    "addr:full":"Carrer de Ricardo De La Cierva, 9 S. Esteve Sesrovires Barcelona 08635",
    "addr:housenumber":"9",
    "addr:postcode":"08635",
    "addr:street":"Carrer De Ricardo De La Cierva",
    "iso:country":"ES",
    "sg:address":"Carrer de Ricardo De La Cierva, 9",
    "sg:city":"S. Esteve Sesrovires",
    "sg:orig_category":"Embalajes",
    "sg:phone":"+34 937 71 59 90",
    "sg:postcode":"08635",
    "sg:province":"Barcelona",
    "wof:name":"Proersa Cosmetics S.a.",
    "wof:placetype":"venue"
},
  "geometry": {"coordinates":[1.8773399591,41.4805717468],"type":"Point"}
}