{
  "type": "Feature",
  "properties": {
    "addr:full":"Calle de Virgen (la), 32 Barraco \u00c1vila 05110",
    "addr:housenumber":"32",
    "addr:postcode":"05110",
    "addr:street":"Calle De Virgen La",
    "iso:country":"ES",
    "sg:address":"Calle de Virgen (la), 32",
    "sg:city":"Barraco",
    "sg:orig_category":"Marmolistas Funerarios",
    "sg:phone":"+34 920 28 12 78",
    "sg:postcode":"05110",
    "sg:province":"\u00c1vila",
    "wof:name":"Gonzalez Rodriguez Jose Maria",
    "wof:placetype":"venue"
},
  "geometry": {"coordinates":[-4.6373920441,40.4738235474],"type":"Point"}
}