{
  "type": "Feature",
  "properties": {
    "iso:country":"ES",
    "sg:address":"Plaz Constitucion (la), 18",
    "sg:city":"Bailen",
    "sg:orig_category":"Inform\u00c1tica, Ofim\u00c1tica (estudios, Asesor\u00cda, Ingenier\u00cda, Formaci\u00d3n)",
    "sg:phone":"+34 953 67 61 20",
    "sg:postcode":"23710",
    "sg:province":"Ja\u00e9n",
    "wof:name":"Pc-bailen S.l.",
    "wof:placetype":"venue"
},
  "geometry": {"coordinates":[-3.7710540295,38.0965309143],"type":"Point"}
}