{
  "type": "Feature",
  "properties": {
    "iso:country":"ES",
    "sg:address":"Carrer de Travessera, 5",
    "sg:city":"S. Quirze Valles",
    "sg:orig_category":"Papeler\u00cdas, Librer\u00cdas",
    "sg:phone":"+34 937 21 34 78",
    "sg:postcode":"08192",
    "sg:province":"Barcelona",
    "wof:name":"Ortega Robles Francisco Javier",
    "wof:placetype":"venue"
},
  "geometry": {"coordinates":[2.0762341022,41.534954071],"type":"Point"}
}