{
  "type": "Feature",
  "properties": {
    "iso:country":"ES",
    "sg:address":"Carr De Fontanars Dels Alforins, 5",
    "sg:city":"Ontinyent",
    "sg:orig_category":"\u00d3ptica: Instrumentos (fabricaci\u00d3n)",
    "sg:phone":"+34 962 91 07 44",
    "sg:postcode":"46870",
    "sg:province":"Valencia",
    "wof:name":"Optinova Ontinyent De Serveis Optics S.l",
    "wof:placetype":"venue"
},
  "geometry": {"coordinates":[-0.6030989885,38.8258895874],"type":"Point"}
}