{
  "type": "Feature",
  "properties": {
    "iso:country":"ES",
    "sg:address":"Calle de Francisco Fernandez Ordo\u00d1ez, S/n",
    "sg:city":"Miguelturra",
    "sg:orig_category":"Peluquer\u00cdas",
    "sg:phone":"+34 926 24 23 02",
    "sg:postcode":"13170",
    "sg:province":"Ciudad Real",
    "wof:name":"Martinez Villalvilla Maria De Los Angeles",
    "wof:placetype":"venue"
},
  "geometry": {"coordinates":[-3.8865740299,38.9593544006],"type":"Point"}
}