{
  "type": "Feature",
  "properties": {
    "addr:full":"Calle de Medico Rodriguez, 5 Coru\u00d1a La Coru\u00f1a 15004",
    "addr:housenumber":"5",
    "addr:postcode":"15004",
    "addr:street":"Calle De Medico Rodriguez;La Corun\u0303A",
    "iso:country":"ES",
    "sg:address":"Calle de Medico Rodriguez, 5",
    "sg:city":"Coru\u00d1a",
    "sg:orig_category":"M\u00c9dicos: Pediatr\u00cda. Enfermedades De Los Ni\u00d1os",
    "sg:phone":"+34 981 27 73 93",
    "sg:postcode":"15004",
    "sg:province":"La Coru\u00f1a",
    "wof:name":"Gallego Pastoriza Manuel",
    "wof:placetype":"venue"
},
  "geometry": {"coordinates":[-8.4090862274,43.3660163879],"type":"Point"}
}