{
  "type": "Feature",
  "properties": {
    "iso:country":"ES",
    "sg:address":"Av Comarques Catalanes, 26",
    "sg:city":"Mora D'ebre",
    "sg:orig_category":"Mec\u00c1nico Del Autom\u00d3vil",
    "sg:phone":"+34 977 40 16 36",
    "sg:postcode":"43740",
    "sg:province":"Tarragona",
    "wof:name":"Sarroca Florensa Antonio",
    "wof:placetype":"venue"
},
  "geometry": {"coordinates":[1.2540999651,41.1169281006],"type":"Point"}
}