{
  "type": "Feature",
  "properties": {
    "addr:full":"Calle de San Claudio, 55 Madrid Madrid 28038",
    "addr:housenumber":"55",
    "addr:postcode":"madrid;28038",
    "addr:street":"Calle De San",
    "iso:country":"ES",
    "sg:address":"Calle de San Claudio, 55",
    "sg:city":"Madrid",
    "sg:orig_category":"Centros Empresariales",
    "sg:phone":"+34 917 77 66 03",
    "sg:postcode":"28038",
    "sg:province":"Madrid",
    "wof:name":"Garcia Maiz Ivan",
    "wof:placetype":"venue"
},
  "geometry": {"coordinates":[-3.6380560398,40.3886756897],"type":"Point"}
}