{
  "type": "Feature",
  "properties": {
    "iso:country":"ES",
    "sg:address":"Ctra Zaragoza Castellon, Km. 0039,0",
    "sg:city":"Quinto",
    "sg:orig_category":"Granos Y Forrajes",
    "sg:phone":"+34 976 17 60 54",
    "sg:postcode":"50770",
    "sg:province":"Zaragoza",
    "wof:name":"La Pastora Quinto S.l.",
    "wof:placetype":"venue"
},
  "geometry": {"coordinates":[-0.5005689859,41.429561615],"type":"Point"}
}