{
  "type": "Feature",
  "properties": {
    "addr:full":"Carr Nord, 4 Mao Islas Baleares 07702",
    "addr:housenumber":"4",
    "addr:postcode":"07702",
    "addr:street":"Carr Nord",
    "iso:country":"ES",
    "sg:address":"Carr Nord, 4",
    "sg:city":"Mao",
    "sg:orig_category":"Oficinas De Turismo, Asociaciones De Iniciativa",
    "sg:phone":"+34 971 36 23 77",
    "sg:postcode":"07702",
    "sg:province":"Islas Baleares",
    "wof:name":"Fomento Del Turismo De Menorca",
    "wof:placetype":"venue"
},
  "geometry": {"coordinates":[4.265625,39.8903694153],"type":"Point"}
}