{
  "type": "Feature",
  "properties": {
    "addr:full":"Avda Ricardo Carapeto Zambrano, 50 Badajoz Badajoz 06008",
    "addr:housenumber":"50",
    "addr:postcode":"06008",
    "addr:street":"Avda Ricardo Carapeto Zambrano",
    "iso:country":"ES",
    "sg:address":"Avda Ricardo Carapeto Zambrano, 50",
    "sg:city":"Badajoz",
    "sg:orig_category":"Empresarios",
    "sg:phone":"+34 924 25 54 06",
    "sg:postcode":"06008",
    "sg:province":"Badajoz",
    "wof:name":"Garcia Vazquez Benito",
    "wof:placetype":"venue"
},
  "geometry": {"coordinates":[-6.9514760971,38.878288269],"type":"Point"}
}