{
  "type": "Feature",
  "properties": {
    "addr:full":"Avda Gernikako Arbola, 58 San Vicente De Barakaldo Vizcaya 48902",
    "addr:housenumber":"58",
    "addr:postcode":"48902",
    "addr:street":"Avda Gernikako Arbola",
    "iso:country":"ES",
    "sg:address":"Avda Gernikako Arbola, 58",
    "sg:city":"San Vicente De Barakaldo",
    "sg:orig_category":"Electrodom\u00c9sticos (al Por Menor)",
    "sg:phone":"+34 944 38 63 71",
    "sg:postcode":"48902",
    "sg:province":"Vizcaya",
    "wof:name":"Izquierdo Hierro Felix",
    "wof:placetype":"venue"
},
  "geometry": {"coordinates":[-2.9981529713,43.2942657471],"type":"Point"}
}