{
  "type": "Feature",
  "properties": {
    "iso:country":"ES",
    "sg:address":"Calle de Ciempozuelos, 13",
    "sg:city":"Getafe",
    "sg:orig_category":"Peluqueros: De Se\u00d1oras",
    "sg:phone":"+34 916 82 37 03",
    "sg:postcode":"28904",
    "sg:province":"Madrid",
    "wof:name":"Nieva Arroyo Aurora",
    "wof:placetype":"venue"
},
  "geometry": {"coordinates":[-3.7346785069,40.3035011292],"type":"Point"}
}