{
  "type": "Feature",
  "properties": {
    "iso:country":"ES",
    "sg:address":"Calle de Gonzalez Alonso, S/n",
    "sg:city":"Serradilla",
    "sg:orig_category":"Electricidad: Instalaciones Industriales",
    "sg:phone":"+34 927 40 73 40",
    "sg:postcode":"10530",
    "sg:province":"C\u00e1ceres",
    "wof:name":"Fernandez Montero Agustin",
    "wof:placetype":"venue"
},
  "geometry": {"coordinates":[-6.1410937309,39.8290901184],"type":"Point"}
}