{
  "type": "Feature",
  "properties": {
    "addr:full":"Ctra Errekalde-larraskitu, 33 Bilbao Vizcaya 48002",
    "addr:housenumber":"33",
    "addr:postcode":"48002",
    "addr:street":"Ctra Errekalde-Larraskitu",
    "iso:country":"ES",
    "sg:address":"Ctra Errekalde-larraskitu, 33",
    "sg:city":"Bilbao",
    "sg:orig_category":"Empresas De Carpinter\u00cda De Madera",
    "sg:phone":"+34 944 21 59 07",
    "sg:postcode":"48002",
    "sg:province":"Vizcaya",
    "wof:name":"Aniceto Marcos Arribas Y Juan Antonio Iglesias Sanguiao Cdad.",
    "wof:placetype":"venue"
},
  "geometry": {"coordinates":[-2.9409096241,43.2503623962],"type":"Point"}
}