{
  "type": "Feature",
  "properties": {
    "addr:full":"Rua San Marcos, 3 Lugo Lugo 27001",
    "addr:housenumber":"3",
    "addr:postcode":"27001",
    "addr:street":"Rua San Marcos",
    "iso:country":"ES",
    "sg:address":"Rua San Marcos, 3",
    "sg:city":"Lugo",
    "sg:orig_category":"Asesor\u00cda Fiscal Y Jur\u00cddica",
    "sg:phone":"+34 982 24 21 63",
    "sg:postcode":"27001",
    "sg:province":"Lugo",
    "wof:name":"Gonzalez Arias Luis Pablo",
    "wof:placetype":"venue"
},
  "geometry": {"coordinates":[-7.5566759109,43.0123710632],"type":"Point"}
}