{
  "type": "Feature",
  "properties": {
    "addr:full":"Plaz Tremedal, 4 Teruel Teruel 44001",
    "addr:housenumber":"4",
    "addr:postcode":"44001",
    "addr:street":"Tremedal",
    "iso:country":"ES",
    "sg:address":"Plaz Tremedal, 4",
    "sg:city":"Teruel",
    "sg:orig_category":"Carnicer\u00cdas, Carnicer\u00cdas",
    "sg:phone":"+34 978 60 26 84",
    "sg:postcode":"44001",
    "sg:province":"Teruel",
    "wof:name":"Aspas Martin Salvador",
    "wof:placetype":"venue"
},
  "geometry": {"coordinates":[-1.1065238714,40.3405189514],"type":"Point"}
}