{
  "type": "Feature",
  "properties": {
    "iso:country":"ES",
    "sg:address":"Pol Ind Martiartu I, S/n",
    "sg:city":"Arrigorriaga",
    "sg:orig_category":"Empresas De Carpinter\u00cda De Madera",
    "sg:phone":"+34 946 71 33 66",
    "sg:postcode":"48480",
    "sg:province":"Vizcaya",
    "wof:name":"Espino Eguren Vicente",
    "wof:placetype":"venue"
},
  "geometry": {"coordinates":[-2.8893239498,43.2034988403],"type":"Point"}
}