{
  "type": "Feature",
  "properties": {
    "iso:country":"ES",
    "sg:address":"Carr Enginyer Cellers, 19",
    "sg:city":"Lleida",
    "sg:orig_category":"Empresarios",
    "sg:phone":"+34 973 23 02 50",
    "sg:postcode":"25005",
    "sg:province":"Lleida",
    "wof:name":"Acabat 10 S.l.",
    "wof:placetype":"venue"
},
  "geometry": {"coordinates":[0.639133,41.625355],"type":"Point"}
}