{
  "type": "Feature",
  "properties": {
    "addr:full":"Calle de Goiri Erdikoa, 6 Basozabal Vizcaya 48150",
    "addr:housenumber":"6",
    "addr:postcode":"48150",
    "addr:street":"Calle De Goiri Erdikoa",
    "iso:country":"ES",
    "sg:address":"Calle de Goiri Erdikoa, 6",
    "sg:city":"Basozabal",
    "sg:orig_category":"Mec\u00c1nico Del Autom\u00d3vil",
    "sg:phone":"+34 944 53 18 78",
    "sg:postcode":"48150",
    "sg:province":"Vizcaya",
    "wof:name":"Azcorra Artieagoitia Juan Antonio",
    "wof:placetype":"venue"
},
  "geometry": {"coordinates":[-2.9285750389,43.3000564575],"type":"Point"}
}