{
  "type": "Feature",
  "properties": {
    "iso:country":"ES",
    "sg:address":"Carr Pare Vives, 46",
    "sg:city":"Pollen\u00e7a",
    "sg:orig_category":"Alquiler De V\u00cddeo",
    "sg:phone":"+34 971 53 15 61",
    "sg:postcode":"07460",
    "sg:province":"Islas Baleares",
    "wof:name":"Perez Palma Juan",
    "wof:placetype":"venue"
},
  "geometry": {"coordinates":[3.0177309513,39.8810806274],"type":"Point"}
}