{
  "type": "Feature",
  "properties": {
    "addr:full":"Av Jaume Iii, 23 Palma Islas Baleares 07012",
    "addr:housenumber":"23",
    "addr:postcode":"07012",
    "addr:street":"Av Jaume Iii",
    "iso:country":"ES",
    "sg:address":"Av Jaume Iii, 23",
    "sg:city":"Palma",
    "sg:orig_category":"Centros Empresariales",
    "sg:phone":"+34 971 71 71 96",
    "sg:postcode":"07012",
    "sg:province":"Islas Baleares",
    "wof:name":"Gestalt Mediterraneo",
    "wof:placetype":"venue"
},
  "geometry": {"coordinates":[2.6431109905,39.5723342896],"type":"Point"}
}