{
  "type": "Feature",
  "properties": {
    "iso:country":"ES",
    "sg:address":"Vred Macanas, 10",
    "sg:city":"Huerta Del Raal",
    "sg:orig_category":"Congelados: Productos Alimentarios (fabricaci\u00d3n, Al Por Mayor)",
    "sg:phone":"+34 968 37 90 00",
    "sg:postcode":"30139",
    "sg:province":"Murcia",
    "wof:name":"Fruveco S.a.",
    "wof:placetype":"venue"
},
  "geometry": {"coordinates":[-1.0326590538,38.0375366211],"type":"Point"}
}