{
  "type": "Feature",
  "properties": {
    "addr:full":"Calle de Rosario, S/n Riopar Albacete 02450",
    "addr:housenumber":"/ n",
    "addr:postcode":"02450",
    "addr:street":"Calle De Rosario S",
    "iso:country":"ES",
    "sg:address":"Calle de Rosario, S/n",
    "sg:city":"Riopar",
    "sg:orig_category":"Centros De Educaci\u00d3n Especial",
    "sg:phone":"+34 967 43 50 55",
    "sg:postcode":"02450",
    "sg:province":"Albacete",
    "wof:name":"Colegio Publico E. G. B.",
    "wof:placetype":"venue"
},
  "geometry": {"coordinates":[-2.4209189415,38.4977531433],"type":"Point"}
}