{
  "type": "Feature",
  "properties": {
    "iso:country":"ES",
    "sg:address":"Avda Iparraguirre, 1",
    "sg:city":"Zumarraga",
    "sg:orig_category":"Cl\u00cdnicas Dentales",
    "sg:phone":"+34 943 72 19 63",
    "sg:postcode":"20700",
    "sg:province":"Guip\u00f9zcoa",
    "wof:name":"Mendia Ibaceta Javier",
    "wof:placetype":"venue"
},
  "geometry": {"coordinates":[-2.314054966,43.0891876221],"type":"Point"}
}