{
  "type": "Feature",
  "properties": {
    "addr:full":"Calle de Alcora, 29 Almazora Castell\u00f3n 12550",
    "addr:housenumber":"29",
    "addr:postcode":"12550",
    "addr:street":"Calle De Alcora",
    "iso:country":"ES",
    "sg:address":"Calle de Alcora, 29",
    "sg:city":"Almazora",
    "sg:orig_category":"Estancos",
    "sg:phone":"+34 964 56 16 35",
    "sg:postcode":"12550",
    "sg:province":"Castell\u00f3n",
    "wof:name":"Canos Serrano Manuel",
    "wof:placetype":"venue"
},
  "geometry": {"coordinates":[-0.0643355995,39.9437332153],"type":"Point"}
}