{
  "type": "Feature",
  "properties": {
    "addr:full":"Calle de Belgica, 16 Galletas Santa Cruz De Tenerife 38631",
    "addr:housenumber":"16",
    "addr:postcode":"38631",
    "addr:street":"Calle De Belgica",
    "iso:country":"ES",
    "sg:address":"Calle de Belgica, 16",
    "sg:city":"Galletas",
    "sg:orig_category":"Inmobiliaria (agencias)",
    "sg:phone":"+34 922 78 54 52",
    "sg:postcode":"38631",
    "sg:province":"Santa Cruz De Tenerife",
    "wof:name":"Moreno Diaz Antonia",
    "wof:placetype":"venue"
},
  "geometry": {"coordinates":[-16.6547279358,28.0075073242],"type":"Point"}
}