{
  "type": "Feature",
  "properties": {
    "iso:country":"ES",
    "sg:address":"Carrer de Valencia, 621",
    "sg:city":"Barcelona",
    "sg:orig_category":"Farmacias",
    "sg:phone":"+34 932 31 06 08",
    "sg:postcode":"08026",
    "sg:province":"Barcelona",
    "wof:name":"Santigosa Bosch Nuria",
    "wof:placetype":"venue"
},
  "geometry": {"coordinates":[2.1873569489,41.4109458923],"type":"Point"}
}