{
  "type": "Feature",
  "properties": {
    "addr:full":"Calle de Rastro, 12 Ubeda Ja\u00e9n 23400",
    "addr:housenumber":"12",
    "addr:postcode":"23400",
    "addr:street":"Calle De Rastro;Jae\u0301N",
    "iso:country":"ES",
    "sg:address":"Calle de Rastro, 12",
    "sg:city":"Ubeda",
    "sg:orig_category":"Producci\u00d3n, Venta De Productos De Agricultura Biol\u00d3gica",
    "sg:phone":"+34 953 75 00 50",
    "sg:postcode":"23400",
    "sg:province":"Ja\u00e9n",
    "wof:name":"Cortijo La Catolica S.a.",
    "wof:placetype":"venue"
},
  "geometry": {"coordinates":[-3.3716480732,38.0106124878],"type":"Point"}
}