{
  "type": "Feature",
  "properties": {
    "iso:country":"ES",
    "sg:address":"Carrer de Rosella, 16",
    "sg:city":"Santa Perpetua De Mogoda",
    "sg:orig_category":"Contenedores (mercanc\u00cdas)",
    "sg:phone":"+34 935 74 40 34",
    "sg:postcode":"08130",
    "sg:province":"Barcelona",
    "wof:name":"Gestio Transport I Transit Barcelona S.l.",
    "wof:placetype":"venue"
},
  "geometry": {"coordinates":[2.1800150871,41.5258674622],"type":"Point"}
}