{
  "type": "Feature",
  "properties": {
    "iso:country":"ES",
    "sg:address":"Calle de Rufino, 3",
    "sg:city":"Cuesta",
    "sg:orig_category":"Muebles",
    "sg:phone":"+34 922 66 22 87",
    "sg:postcode":"38320",
    "sg:province":"Santa Cruz De Tenerife",
    "wof:name":"Comercial Toledo S. L.",
    "wof:placetype":"venue"
},
  "geometry": {"coordinates":[-16.2880134583,28.468454361],"type":"Point"}
}