{
  "type": "Feature",
  "properties": {
    "iso:country":"ES",
    "sg:address":"Av Baix Penedes, 57",
    "sg:city":"Vendrell",
    "sg:orig_category":"Empresas De Pintura Y Revestimientos",
    "sg:phone":"+34 977 66 67 25",
    "sg:postcode":"43700",
    "sg:province":"Tarragona",
    "wof:name":"Proicom Mercade S.l. Unip",
    "wof:placetype":"venue"
},
  "geometry": {"coordinates":[1.5278340578,41.2190704346],"type":"Point"}
}