{
  "type": "Feature",
  "properties": {
    "addr:full":"Calle de Narvaez, 23 Madrid Madrid 28009",
    "addr:housenumber":"23",
    "addr:postcode":"madrid;28009",
    "addr:street":"Calle De Narvaez",
    "iso:country":"ES",
    "sg:address":"Calle de Narvaez, 23",
    "sg:city":"Madrid",
    "sg:orig_category":"Bisuter\u00cda, Joyer\u00cda, Relojer\u00cda (al Por Menor)",
    "sg:phone":"+34 914 31 19 77",
    "sg:postcode":"28009",
    "sg:province":"Madrid",
    "wof:name":"Jimenez Juanes Jose",
    "wof:placetype":"venue"
},
  "geometry": {"coordinates":[-3.6759340763,40.4219360352],"type":"Point"}
}