{
  "type": "Feature",
  "properties": {
    "addr:full":"Carrer de Venecia, 25 Lloret Mar Girona 17310",
    "addr:housenumber":"25",
    "addr:postcode":"17310",
    "addr:street":"Carrer De Venecia",
    "iso:country":"ES",
    "sg:address":"Carrer de Venecia, 25",
    "sg:city":"Lloret Mar",
    "sg:orig_category":"Asociaciones Y Clubs Deportivos",
    "sg:phone":"+34 972 36 56 63",
    "sg:postcode":"17310",
    "sg:province":"Girona",
    "wof:name":"Uncle Sam S.l.",
    "wof:placetype":"venue"
},
  "geometry": {"coordinates":[2.851749897,41.7003517151],"type":"Point"}
}