{
  "type": "Feature",
  "properties": {
    "iso:country":"ES",
    "sg:address":"Calle de Lope De Vega, 6",
    "sg:city":"Santander",
    "sg:orig_category":"Abogados",
    "sg:phone":"+34 942 31 07 11",
    "sg:postcode":"39003",
    "sg:province":"Cantabria",
    "wof:name":"Suarez De Puga Fontes Enrique",
    "wof:placetype":"venue"
},
  "geometry": {"coordinates":[-3.7995812893,43.4631652832],"type":"Point"}
}