{
  "type": "Feature",
  "properties": {
    "iso:country":"ES",
    "sg:address":"Avda Miranda Do Douro, 13",
    "sg:city":"Aranda Duero",
    "sg:orig_category":"Estaciones De Servicio",
    "sg:phone":"+34 947 51 17 17",
    "sg:postcode":"09400",
    "sg:province":"Burgos",
    "wof:name":"Domingo Bravo S.l.",
    "wof:placetype":"venue"
},
  "geometry": {"coordinates":[-3.6883990765,41.6686592102],"type":"Point"}
}