{
  "type": "Feature",
  "properties": {
    "addr:full":"Calle de Canalejas, 36 Velez-malaga M\u00e1laga 29700",
    "addr:housenumber":"36",
    "addr:postcode":"29700",
    "addr:street":"Calle De Canalejas",
    "iso:country":"ES",
    "sg:address":"Calle de Canalejas, 36",
    "sg:city":"Velez-malaga",
    "sg:orig_category":"Farmacias",
    "sg:phone":"+34 952 50 16 47",
    "sg:postcode":"29700",
    "sg:province":"M\u00e1laga",
    "wof:name":"Luque Diaz Cristina",
    "wof:placetype":"venue"
},
  "geometry": {"coordinates":[-4.105547905,36.7818222046],"type":"Point"}
}