{
  "type": "Feature",
  "properties": {
    "addr:full":"Calle de Fernandez De Los Rios, 71 Madrid Madrid 28015",
    "addr:housenumber":"71",
    "addr:postcode":"madrid;28015",
    "addr:street":"Calle De Fernandez De Los Rios",
    "iso:country":"ES",
    "sg:address":"Calle de Fernandez De Los Rios, 71",
    "sg:city":"Madrid",
    "sg:orig_category":"Caf\u00c9s, Bares, Cervecer\u00cdas",
    "sg:phone":"+34 915 44 16 17",
    "sg:postcode":"28015",
    "sg:province":"Madrid",
    "wof:name":"Pebbleson S.l.",
    "wof:placetype":"venue"
},
  "geometry": {"coordinates":[-3.7135620117,40.4351921082],"type":"Point"}
}