{
  "type": "Feature",
  "properties": {
    "addr:full":"Calle de Costa Rica, 4 Moguer Huelva 21800",
    "addr:housenumber":"4",
    "addr:postcode":"21800",
    "addr:street":"Calle De Costa Rica",
    "iso:country":"ES",
    "sg:address":"Calle de Costa Rica, 4",
    "sg:city":"Moguer",
    "sg:classifiers":[
        {
            "category":"Autos & Motor Vehicles",
            "subcategory":"Automobile Sales",
            "type":"Retail Goods"
        }
    ],
    "sg:phone":"+34 959 37 25 03",
    "sg:postcode":"21800",
    "sg:province":"Huelva",
    "wof:name":"Auto Escuela Rabida Sdad.coop.andaluza",
    "wof:placetype":"venue"
},
  "geometry": {"coordinates":[-6.8373179436,37.2788925171],"type":"Point"}
}