{
  "type": "Feature",
  "properties": {
    "iso:country":"ES",
    "sg:address":"Avda Garcia Barbon, 116",
    "sg:city":"Vigo",
    "sg:orig_category":"Electrodom\u00c9sticos (al Por Menor)",
    "sg:phone":"+34 986 22 52 22",
    "sg:postcode":"36201",
    "sg:province":"Pontevedra",
    "wof:name":"Villar Ferreira Luis",
    "wof:placetype":"venue"
},
  "geometry": {"coordinates":[-8.7089090347,42.2389717102],"type":"Point"}
}