{
  "type": "Feature",
  "properties": {
    "addr:full":"Avda San Antonio Abad, 8 Zaidin Huesca 22530",
    "addr:housenumber":"8",
    "addr:postcode":"22530",
    "addr:street":"Avda San Antonio Abad",
    "iso:country":"ES",
    "sg:address":"Avda San Antonio Abad, 8",
    "sg:city":"Zaidin",
    "sg:orig_category":"Cajas De Ahorro",
    "sg:phone":"+34 974 47 82 18",
    "sg:postcode":"22530",
    "sg:province":"Huesca",
    "wof:name":"Caja De Ahorros Y Monte De Piedad De Zaragoza Aragon Y Rioja",
    "wof:placetype":"venue"
},
  "geometry": {"coordinates":[0.2686800063,41.6075401306],"type":"Point"}
}