{
  "type": "Feature",
  "properties": {
    "iso:country":"ES",
    "sg:address":"Calle de San Miguel (casetas), 5",
    "sg:city":"Casetas",
    "sg:orig_category":"Papeler\u00cdas, Librer\u00cdas",
    "sg:phone":"+34 976 77 14 40",
    "sg:postcode":"50620",
    "sg:province":"Zaragoza",
    "wof:name":"Gracia Camin Gregorio",
    "wof:placetype":"venue"
},
  "geometry": {"coordinates":[-1.0261600018,41.7186927795],"type":"Point"}
}