{
  "type": "Feature",
  "properties": {
    "addr:full":"Ptda La Pe\u00f1a, 275 Elche Alicante 03296",
    "addr:housenumber":"275",
    "addr:postcode":"03296",
    "addr:street":"Ptda La Pen\u0303A",
    "iso:country":"ES",
    "sg:address":"Ptda La Pe\u00f1a, 275",
    "sg:city":"Elche",
    "sg:orig_category":"Restaurantes",
    "sg:phone":"+34 965 43 47 98",
    "sg:postcode":"03296",
    "sg:province":"Alicante",
    "wof:name":"Palazon Palazon Antonio",
    "wof:placetype":"venue"
},
  "geometry": {"coordinates":[-0.7447530031,38.227268219],"type":"Point"}
}