{
  "type": "Feature",
  "properties": {
    "addr:full":"Avda Madrid, 108 Zaragoza Zaragoza 50010",
    "addr:housenumber":"108",
    "addr:postcode":"50010",
    "addr:street":"Avda Madrid",
    "iso:country":"ES",
    "sg:address":"Avda Madrid, 108",
    "sg:city":"Zaragoza",
    "sg:orig_category":"Frutas, Legumbres Frescas Y Tempranas (al Por Menor)",
    "sg:phone":"+34 976 33 01 77",
    "sg:postcode":"50010",
    "sg:province":"Zaragoza",
    "wof:name":"Contamina Ramiro Cipriano",
    "wof:placetype":"venue"
},
  "geometry": {"coordinates":[-0.9079639912,41.652759552],"type":"Point"}
}