{
  "type": "Feature",
  "properties": {
    "iso:country":"ES",
    "sg:address":"Calle de Carcagente, 6",
    "sg:city":"Valencia",
    "sg:orig_category":"Arquitectos",
    "sg:phone":"+34 963 80 63 55",
    "sg:postcode":"46007",
    "sg:province":"Valencia",
    "wof:name":"Hernandez Benhamou Jorge",
    "wof:placetype":"venue"
},
  "geometry": {"coordinates":[-0.3864248991,39.4603309631],"type":"Point"}
}