{
  "type": "Feature",
  "properties": {
    "iso:country":"ES",
    "sg:address":"Marruecos(trema\u00f1es), S/n",
    "sg:city":"Gijon",
    "sg:orig_category":"Institutos De Belleza",
    "sg:phone":"+34 985 31 15 59",
    "sg:postcode":"33211",
    "sg:province":"Asturias",
    "wof:name":"Salon De Belleza Noelia",
    "wof:placetype":"venue"
},
  "geometry": {"coordinates":[-5.7091789246,43.5269012451],"type":"Point"}
}