{
  "type": "Feature",
  "properties": {
    "addr:full":"Roncesvalles, 18 Estella Navarra 31200",
    "addr:housenumber":"18",
    "addr:postcode":"31200",
    "addr:street":"Roncesvalles",
    "iso:country":"ES",
    "sg:address":"Roncesvalles, 18",
    "sg:city":"Estella",
    "sg:orig_category":"Contenedores (mercanc\u00cdas)",
    "sg:phone":"+34 948 55 04 58",
    "sg:postcode":"31200",
    "sg:province":"Navarra",
    "wof:name":"Murguialday Martinez Rafael",
    "wof:placetype":"venue"
},
  "geometry": {"coordinates":[-2.0353488922,42.6726417542],"type":"Point"}
}