{
  "type": "Feature",
  "properties": {
    "iso:country":"ES",
    "sg:address":"Calle de Francisco Gomez, 15",
    "sg:city":"Barakaldo",
    "sg:orig_category":"Peluquer\u00cdas, Peluquer\u00cda Mixta",
    "sg:phone":"+34 944 78 05 23",
    "sg:postcode":"48902",
    "sg:province":"Vizcaya",
    "wof:name":"Iratxe Sanchez Aybar",
    "wof:placetype":"venue"
},
  "geometry": {"coordinates":[-2.9923269749,43.2958297729],"type":"Point"}
}