{
  "type": "Feature",
  "properties": {
    "addr:full":"Av Josep Anselm Clave, 31 Prat Llobregat Barcelona 08820",
    "addr:housenumber":"31",
    "addr:postcode":"08820",
    "addr:street":"Av Josep Anselm Clave;Llobregat",
    "iso:country":"ES",
    "sg:address":"Av Josep Anselm Clave, 31",
    "sg:city":"Prat Llobregat",
    "sg:orig_category":"Cristaler\u00cdas",
    "sg:phone":"+34 933 79 82 03",
    "sg:postcode":"08820",
    "sg:province":"Barcelona",
    "wof:name":"Sarabia Cortes Juan Bautista",
    "wof:placetype":"venue"
},
  "geometry": {"coordinates":[2.0961489677,41.3324127197],"type":"Point"}
}