{
  "type": "Feature",
  "properties": {
    "iso:country":"ES",
    "sg:address":"Plaz Iglesia (la), 1",
    "sg:city":"Corera",
    "sg:orig_category":"Ense\u00d1anza, Formaci\u00d3n Profesional: Aprendizaje",
    "sg:phone":"+34 941 43 83 04",
    "sg:postcode":"26144",
    "sg:province":"La Rioja",
    "wof:name":"Ayuntamiento De Corera",
    "wof:placetype":"venue"
},
  "geometry": {"coordinates":[-2.2189249992,42.3427734375],"type":"Point"}
}