{
  "type": "Feature",
  "properties": {
    "iso:country":"ES",
    "sg:address":"Plaz Grano, 1",
    "sg:city":"Quintanar Orden",
    "sg:orig_category":"Productores Recolectores, Venta Directa De Vinos",
    "sg:phone":"+34 925 18 09 30",
    "sg:postcode":"45800",
    "sg:province":"Toledo",
    "wof:name":"Sociedad Cooperativa Agricola Nuestra Se\u00f1ora De La Piedad",
    "wof:placetype":"venue"
},
  "geometry": {"coordinates":[-3.047492981,39.5965499878],"type":"Point"}
}