{
  "type": "Feature",
  "properties": {
    "iso:country":"ES",
    "sg:address":"Calle de Suarez Somonte, 66",
    "sg:city":"Merida",
    "sg:orig_category":"Organizaciones Internacionales",
    "sg:phone":"+34 924 31 63 55",
    "sg:postcode":"06800",
    "sg:province":"Badajoz",
    "wof:name":"Comision Espa\u00d1ola De Ayuda Al Refugiado",
    "wof:placetype":"venue"
},
  "geometry": {"coordinates":[-6.3409581184,38.9156265259],"type":"Point"}
}