{
  "type": "Feature",
  "properties": {
    "addr:full":"Carrer de Celia Vi\u00d1as, 3 Palma Islas Baleares 07008",
    "addr:housenumber":"3",
    "addr:postcode":"07008",
    "addr:street":"Carrer De Celia Vin\u0303As",
    "iso:country":"ES",
    "sg:address":"Carrer de Celia Vi\u00d1as, 3",
    "sg:city":"Palma",
    "sg:orig_category":"Molduras, Junquillos, Listones Y Molduras Perforadas",
    "sg:phone":"+34 971 24 46 99",
    "sg:postcode":"07008",
    "sg:province":"Islas Baleares",
    "wof:name":"Sistelcom-telemensaje S.a.",
    "wof:placetype":"venue"
},
  "geometry": {"coordinates":[2.6726720333,39.5802574158],"type":"Point"}
}