{
  "type": "Feature",
  "properties": {
    "iso:country":"ES",
    "sg:address":"Calle de Jesus Alonso Braga, 4",
    "sg:city":"Langreo",
    "sg:orig_category":"Abogados",
    "sg:phone":"+34 985 67 87 67",
    "sg:postcode":"33930",
    "sg:province":"Asturias",
    "wof:name":"Fernandez Noval Fernando Ramon",
    "wof:placetype":"venue"
},
  "geometry": {"coordinates":[-5.6922698021,43.3069343567],"type":"Point"}
}