{
  "type": "Feature",
  "properties": {
    "addr:full":"Calle de Diego Manchado, 72 Madrid Madrid 28038",
    "addr:housenumber":"72",
    "addr:postcode":"madrid;28038",
    "addr:street":"Calle De Diego Manchado",
    "iso:country":"ES",
    "sg:address":"Calle de Diego Manchado, 72",
    "sg:city":"Madrid",
    "sg:orig_category":"Empresas De Limpieza",
    "sg:phone":"+34 913 03 04 01",
    "sg:postcode":"28038",
    "sg:province":"Madrid",
    "wof:name":"Taestal Iberica S.l.",
    "wof:placetype":"venue"
},
  "geometry": {"coordinates":[-3.6462430954,40.3891716003],"type":"Point"}
}