{
  "type": "Feature",
  "properties": {
    "iso:country":"ES",
    "sg:address":"Arriba-san Paio, 35",
    "sg:city":"Ribadavia",
    "sg:orig_category":"Productores Recolectores, Venta Directa De Vinos",
    "sg:phone":"+34 988 47 20 69",
    "sg:postcode":"32414",
    "sg:province":"Ourense",
    "sg:website":"www.castrorei.com",
    "wof:name":"Bodega Castro Rei S.l.",
    "wof:placetype":"venue"
},
  "geometry": {"coordinates":[-8.1434307098,42.2893867493],"type":"Point"}
}