{
  "type": "Feature",
  "properties": {
    "addr:full":"Crt. Villanueva, Km. 0009,0 La Solana Ciudad Real 13240",
    "addr:postcode":"13240",
    "addr:street":"Villanueva Km. 0009,0 La",
    "iso:country":"ES",
    "sg:address":"Crt. Villanueva, Km. 0009,0",
    "sg:city":"La Solana",
    "sg:orig_category":"Cr\u00cda De Animales",
    "sg:phone":"+34 926 69 60 56",
    "sg:postcode":"13240",
    "sg:province":"Ciudad Real",
    "wof:name":"La Marina S.l.",
    "wof:placetype":"venue"
},
  "geometry": {"coordinates":[-3.2367699146,38.9386825562],"type":"Point"}
}