{
  "type": "Feature",
  "properties": {
    "iso:country":"ES",
    "sg:address":"Calle de Virgen De Gracia, 38",
    "sg:city":"Toro",
    "sg:orig_category":"Empresas De Desmonte",
    "sg:phone":"+34 980 69 26 10",
    "sg:postcode":"49800",
    "sg:province":"Zamora",
    "wof:name":"Martin Andres Vicente",
    "wof:placetype":"venue"
},
  "geometry": {"coordinates":[-5.3919878006,41.5290718079],"type":"Point"}
}