{
  "type": "Feature",
  "properties": {
    "addr:full":"Carrer de Rosa, 3 Sabadell Barcelona 08201",
    "addr:housenumber":"3",
    "addr:postcode":"08201",
    "addr:street":"Carrer De Rosa",
    "iso:country":"ES",
    "sg:address":"Carrer de Rosa, 3",
    "sg:city":"Sabadell",
    "sg:orig_category":"Inmobiliaria (agencias)",
    "sg:phone":"+34 937 27 60 56",
    "sg:postcode":"08201",
    "sg:province":"Barcelona",
    "wof:name":"Ferran Sampere Xavier",
    "wof:placetype":"venue"
},
  "geometry": {"coordinates":[2.1086161137,41.547504425],"type":"Point"}
}