{
  "type": "Feature",
  "properties": {
    "iso:country":"ES",
    "sg:address":"Carr Muralla, 44",
    "sg:city":"Blanes",
    "sg:orig_category":"Marroquiner\u00cda (confecci\u00d3n)",
    "sg:phone":"+34 972 33 10 28",
    "sg:postcode":"17300",
    "sg:province":"Girona",
    "wof:name":"Burcet Pages Montserrat",
    "wof:placetype":"venue"
},
  "geometry": {"coordinates":[2.7902669907,41.6741638184],"type":"Point"}
}