{
  "type": "Feature",
  "properties": {
    "addr:full":"Calle de Principe De Asturias, 44 Cartagena Murcia 30204",
    "addr:housenumber":"44",
    "addr:postcode":"30204",
    "addr:street":"Calle De Principe De Asturias",
    "iso:country":"ES",
    "sg:address":"Calle de Principe De Asturias, 44",
    "sg:city":"Cartagena",
    "sg:orig_category":"Asociaciones Y Clubs Deportivos",
    "sg:phone":"+34 968 50 85 27",
    "sg:postcode":"30204",
    "sg:province":"Murcia",
    "wof:name":"Collados Sports S.l.",
    "wof:placetype":"venue"
},
  "geometry": {"coordinates":[-0.9893959761,37.6096611023],"type":"Point"}
}