{
  "type": "Feature",
  "properties": {
    "addr:full":"Calle de Gustavo Adolfo Becquer, S/n Chiclana De La Frontera C\u00e1diz 11130",
    "addr:housenumber":"s / n",
    "addr:postcode":"11130",
    "addr:street":"Calle De Gustavo Adolfo Becquer",
    "iso:country":"ES",
    "sg:address":"Calle de Gustavo Adolfo Becquer, S/n",
    "sg:city":"Chiclana De La Frontera",
    "sg:orig_category":"Psic\u00d3logos",
    "sg:phone":"+34 956 40 51 19",
    "sg:postcode":"11130",
    "sg:province":"C\u00e1diz",
    "wof:name":"Sanchez Ariza Dolores",
    "wof:placetype":"venue"
},
  "geometry": {"coordinates":[-6.1518092155,36.4177360535],"type":"Point"}
}