{
  "type": "Feature",
  "properties": {
    "iso:country":"ES",
    "sg:address":"Avda Navarra, 17",
    "sg:city":"Tarazona",
    "sg:orig_category":"Producci\u00d3n, Distribuci\u00d3n De Gas Butano Y Propano",
    "sg:phone":"+34 976 19 10 05",
    "sg:postcode":"50500",
    "sg:province":"Zaragoza",
    "wof:name":"Disarbutan 2006 S.l.",
    "wof:placetype":"venue"
},
  "geometry": {"coordinates":[-1.7246769667,41.9085273743],"type":"Point"}
}