{
  "type": "Feature",
  "properties": {
    "iso:country":"ES",
    "sg:address":"Calle de San Blas, 26",
    "sg:city":"Castellon",
    "sg:orig_category":"Servicio De Salud",
    "sg:phone":"+34 964 25 71 81",
    "sg:postcode":"12002",
    "sg:province":"Castell\u00f3n",
    "wof:name":"Ayuda Familiar Castellon S.l.",
    "wof:placetype":"venue"
},
  "geometry": {"coordinates":[-0.0417400002,39.9835395813],"type":"Point"}
}