{
  "type": "Feature",
  "properties": {
    "iso:country":"ES",
    "sg:address":"Carrer de Valles, 34",
    "sg:city":"Mataro",
    "sg:orig_category":"Mec\u00c1nico Del Autom\u00d3vil",
    "sg:phone":"+34 937 99 72 56",
    "sg:postcode":"08303",
    "sg:province":"Barcelona",
    "wof:name":"Ramirez De Maya Jesus",
    "wof:placetype":"venue"
},
  "geometry": {"coordinates":[2.424093008,41.5435028076],"type":"Point"}
}