{
  "type": "Feature",
  "properties": {
    "addr:full":"Avda Lepanto, 20 Albox Almer\u00eda 04800",
    "addr:housenumber":"20",
    "addr:postcode":"04800",
    "addr:street":"Avda Lepanto",
    "iso:country":"ES",
    "sg:address":"Avda Lepanto, 20",
    "sg:city":"Albox",
    "sg:orig_category":"Veh\u00cdculos De Ocasi\u00d3n",
    "sg:phone":"+34 950 43 09 99",
    "sg:postcode":"04800",
    "sg:province":"Almer\u00eda",
    "wof:name":"Automoviles Jimenez Y Garcia S.l.",
    "wof:placetype":"venue"
},
  "geometry": {"coordinates":[-2.1372396946,37.3823318481],"type":"Point"}
}