{
  "type": "Feature",
  "properties": {
    "addr:full":"Avda Andalucia, S/n Algodonales C\u00e1diz 11680",
    "addr:postcode":"11680",
    "addr:street":"Avda Andalucia S / N;Ca\u0301Diz",
    "iso:country":"ES",
    "sg:address":"Avda Andalucia, S/n",
    "sg:city":"Algodonales",
    "sg:orig_category":"Supermercados Y Hipermercados",
    "sg:phone":"+34 956 13 77 28",
    "sg:postcode":"11680",
    "sg:province":"C\u00e1diz",
    "wof:name":"Benitez Luna Rafael",
    "wof:placetype":"venue"
},
  "geometry": {"coordinates":[-5.4036049843,36.8808403015],"type":"Point"}
}