{
  "type": "Feature",
  "properties": {
    "addr:full":"Avda Jose Antonio, 18 Plasencia C\u00e1ceres 10600",
    "addr:housenumber":"18",
    "addr:postcode":"10600",
    "addr:street":"Avda Jose Antonio;Ca\u0301Ceres",
    "iso:country":"ES",
    "sg:address":"Avda Jose Antonio, 18",
    "sg:city":"Plasencia",
    "sg:orig_category":"Sierras (fabricaci\u00d3n, Al Por Mayor)",
    "sg:phone":"+34 927 41 60 65",
    "sg:postcode":"10600",
    "sg:province":"C\u00e1ceres",
    "wof:name":"Motosierras Delgado E Hijos C.b.",
    "wof:placetype":"venue"
},
  "geometry": {"coordinates":[-6.0853486061,40.0316314697],"type":"Point"}
}