{
  "type": "Feature",
  "properties": {
    "iso:country":"ES",
    "sg:address":"Calle de Cubas, S/n",
    "sg:city":"Illescas",
    "sg:orig_category":"Alumbrados",
    "sg:phone":"+34 925 51 23 58",
    "sg:postcode":"45200",
    "sg:province":"Toledo",
    "wof:name":"Toledo Iluminacion S.l.",
    "wof:placetype":"venue"
},
  "geometry": {"coordinates":[-3.8455300331,40.1285591125],"type":"Point"}
}