{
  "type": "Feature",
  "properties": {
    "iso:country":"ES",
    "sg:address":"Calle de Tinte, S/n",
    "sg:city":"Cordoba",
    "sg:orig_category":"Peluquer\u00cdas, Peluquer\u00cda Mixta",
    "sg:phone":"+34 957 26 34 05",
    "sg:postcode":"14002",
    "sg:province":"C\u00f3rdoba",
    "wof:name":"Aljivanez S.l.",
    "wof:placetype":"venue"
},
  "geometry": {"coordinates":[-4.768122673,37.8812332153],"type":"Point"}
}