{
  "type": "Feature",
  "properties": {
    "addr:full":"Mallutz Kalea, 5 Ordizia Guip\u00f9zcoa 20240",
    "addr:housenumber":"5",
    "addr:postcode":"20240",
    "addr:street":"Mallutz Kalea;Guipu\u0300Zcoa",
    "iso:country":"ES",
    "sg:address":"Mallutz Kalea, 5",
    "sg:city":"Ordizia",
    "sg:orig_category":"Agencias Y Asesores De Publicidad",
    "sg:phone":"+34 943 16 30 10",
    "sg:postcode":"20240",
    "sg:province":"Guip\u00f9zcoa",
    "wof:name":"Arizmendi Berakoetxea Rafael",
    "wof:placetype":"venue"
},
  "geometry": {"coordinates":[-2.1756503582,43.0519523621],"type":"Point"}
}