{
  "type": "Feature",
  "properties": {
    "addr:full":"Calle de Merced, 6 Valladolid Valladolid 47002",
    "addr:housenumber":"6",
    "addr:postcode":"47002",
    "addr:street":"Calle De Merced",
    "iso:country":"ES",
    "sg:address":"Calle de Merced, 6",
    "sg:city":"Valladolid",
    "sg:orig_category":"Industria Qu\u00cdmica",
    "sg:phone":"+34 983 29 26 05",
    "sg:postcode":"47002",
    "sg:province":"Valladolid",
    "wof:name":"Burgoa Sanz Teresa",
    "wof:placetype":"venue"
},
  "geometry": {"coordinates":[-4.7196741104,41.6499023438],"type":"Point"}
}