{
  "type": "Feature",
  "properties": {
    "iso:country":"ES",
    "sg:address":"Calle de Alvaro De Bazan, 34",
    "sg:city":"Torredonjimeno",
    "sg:orig_category":"Agencias Y Agentes Comerciales, Representantes",
    "sg:phone":"+34 953 57 29 02",
    "sg:postcode":"23650",
    "sg:province":"Ja\u00e9n",
    "wof:name":"Martos Marmol Francisco",
    "wof:placetype":"venue"
},
  "geometry": {"coordinates":[-3.9543514252,37.767829895],"type":"Point"}
}