{
  "type": "Feature",
  "properties": {
    "addr:full":"Carrer de Licoristes, 28 Valls Tarragona 43800",
    "addr:housenumber":"28",
    "addr:postcode":"43800",
    "addr:street":"Carrer De Licoristes",
    "iso:country":"ES",
    "sg:address":"Carrer de Licoristes, 28",
    "sg:city":"Valls",
    "sg:orig_category":"Empresas De Operaciones Portuarias Y Elevaci\u00d3n De Mercanc\u00cdas",
    "sg:phone":"+34 977 60 70 50",
    "sg:postcode":"43800",
    "sg:province":"Tarragona",
    "wof:name":"Manipulats I Retractivas Valls S.l.",
    "wof:placetype":"venue"
},
  "geometry": {"coordinates":[1.2717380524,41.3125610352],"type":"Point"}
}