{
  "type": "Feature",
  "properties": {
    "iso:country":"ES",
    "sg:address":"Carrer de Reina M Cristina, 4",
    "sg:city":"Palma",
    "sg:orig_category":"Cl\u00cdnicas Dentales",
    "sg:phone":"+34 971 49 87 45",
    "sg:postcode":"07004",
    "sg:province":"Islas Baleares",
    "wof:name":"Dentapnea S.l.",
    "wof:placetype":"venue"
},
  "geometry": {"coordinates":[2.6536231041,39.5770606995],"type":"Point"}
}