{
  "type": "Feature",
  "properties": {
    "addr:full":"Calle de Virreina Alta, S/n Malaga M\u00e1laga 29011",
    "addr:housenumber":"s / n",
    "addr:postcode":"29011",
    "addr:street":"Calle De Virreina Alta;Ma\u0301Laga",
    "iso:country":"ES",
    "sg:address":"Calle de Virreina Alta, S/n",
    "sg:city":"Malaga",
    "sg:orig_category":"Iglesias Cristianas Diversas",
    "sg:phone":"+34 952 30 86 92",
    "sg:postcode":"29011",
    "sg:province":"M\u00e1laga",
    "wof:name":"Misioneras Cruzadas De La Iglesia",
    "wof:placetype":"venue"
},
  "geometry": {"coordinates":[-4.4325661659,36.7424621582],"type":"Point"}
}