{
  "type": "Feature",
  "properties": {
    "addr:full":"Cmno San Sebastian (de), 1 Boadilla Del Monte Madrid 28660",
    "addr:housenumber":"1",
    "addr:postcode":"28660",
    "addr:street":"Cmno San Sebastian De",
    "iso:country":"ES",
    "sg:address":"Cmno San Sebastian (de), 1",
    "sg:city":"Boadilla Del Monte",
    "sg:orig_category":"Fisioterapia",
    "sg:phone":"+34 916 33 38 25",
    "sg:postcode":"28660",
    "sg:province":"Madrid",
    "wof:name":"Sanz Orozco Ana Elena",
    "wof:placetype":"venue"
},
  "geometry": {"coordinates":[-3.8771870136,40.4057006836],"type":"Point"}
}