{
  "type": "Feature",
  "properties": {
    "addr:full":"Els Palmiters, 10 P.i. Masia Del Juez Valencia 46900",
    "addr:housenumber":"10",
    "addr:postcode":"46900",
    "addr:street":"Palmiters;P.I. Masia Del Juez",
    "iso:country":"ES",
    "sg:address":"Els Palmiters, 10",
    "sg:city":"P.i. Masia Del Juez",
    "sg:orig_category":"Cogeneraci\u00d3n: Equipo Y Servicios",
    "sg:phone":"+34 961 58 96 03",
    "sg:postcode":"46900",
    "sg:province":"Valencia",
    "wof:name":"Fiv Ondulados S.l.",
    "wof:placetype":"venue"
},
  "geometry": {"coordinates":[-0.4623290002,39.441619873],"type":"Point"}
}