{
  "type": "Feature",
  "properties": {
    "iso:country":"ES",
    "sg:address":"Trva Extremadura (de), 5",
    "sg:city":"Fuenlabrada",
    "sg:orig_category":"Radiocomunicaciones, Telefon\u00cda M\u00d3vil, Radiomensajer\u00cda: Servicios, Comercializaci\u00d3n",
    "sg:phone":"+34 916 15 46 18",
    "sg:postcode":"28944",
    "sg:province":"Madrid",
    "wof:name":"Espa\u00f1a Os Saluda S.l.",
    "wof:placetype":"venue"
},
  "geometry": {"coordinates":[-3.7960650921,40.2802352905],"type":"Point"}
}