{
  "type": "Feature",
  "properties": {
    "addr:full":"Muel San Diego, S/n Coru\u00d1a La Coru\u00f1a 15006",
    "addr:postcode":"15006",
    "addr:street":"San Diego S / N Corun\u0303A La Corun\u0303A",
    "iso:country":"ES",
    "sg:address":"Muel San Diego, S/n",
    "sg:city":"Coru\u00d1a",
    "sg:orig_category":"Importaci\u00d3n",
    "sg:phone":"+34 981 17 41 79",
    "sg:postcode":"15006",
    "sg:province":"La Coru\u00f1a",
    "wof:name":"Linectach S.l",
    "wof:placetype":"venue"
},
  "geometry": {"coordinates":[-8.395524025,43.3576431274],"type":"Point"}
}