{
  "type": "Feature",
  "properties": {
    "addr:full":"Calle de Carmen, 6 Zaragoza Zaragoza 50005",
    "addr:housenumber":"6",
    "addr:postcode":"50005",
    "addr:street":"Calle De Carmen",
    "iso:country":"ES",
    "sg:address":"Calle de Carmen, 6",
    "sg:city":"Zaragoza",
    "sg:orig_category":"Filatelia",
    "sg:phone":"+34 976 22 76 71",
    "sg:postcode":"50005",
    "sg:province":"Zaragoza",
    "wof:name":"Palomar Arribas Claudio",
    "wof:placetype":"venue"
},
  "geometry": {"coordinates":[-0.8915644288,41.6472091675],"type":"Point"}
}