{
  "type": "Feature",
  "properties": {
    "iso:country":"ES",
    "sg:address":"Rececinde(san Xusto), 36",
    "sg:city":"Coristanco",
    "sg:orig_category":"Empresas De Carpinter\u00cda De Madera",
    "sg:phone":"+34 981 73 32 15",
    "sg:postcode":"15147",
    "sg:province":"La Coru\u00f1a",
    "wof:name":"Fernandez Pose Manuel",
    "wof:placetype":"venue"
},
  "geometry": {"coordinates":[-8.7788820267,43.2015914917],"type":"Point"}
}