{
  "type": "Feature",
  "properties": {
    "iso:country":"ES",
    "sg:address":"Calle de San Matias, 25",
    "sg:city":"Malaha",
    "sg:classifiers":[
        {
            "category":"Taxi",
            "type":"Transportation"
        }
    ],
    "sg:phone":"+34 958 58 71 95",
    "sg:postcode":"18130",
    "sg:province":"Granada",
    "wof:name":"Perez Martin Salvador",
    "wof:placetype":"venue"
},
  "geometry": {"coordinates":[-3.7212929726,37.0974998474],"type":"Point"}
}