{
  "type": "Feature",
  "properties": {
    "addr:full":"Ctra Constanti, 181 Reus Tarragona 43206",
    "addr:housenumber":"181",
    "addr:postcode":"43206",
    "addr:street":"Ctra Constanti",
    "iso:country":"ES",
    "sg:address":"Ctra Constanti, 181",
    "sg:city":"Reus",
    "sg:orig_category":"Organizaciones Profesionales",
    "sg:phone":"+34 977 77 03 16",
    "sg:postcode":"43206",
    "sg:province":"Tarragona",
    "wof:name":"Roig Catala Juan",
    "wof:placetype":"venue"
},
  "geometry": {"coordinates":[1.1247279644,41.1590538025],"type":"Point"}
}