{
  "type": "Feature",
  "properties": {
    "addr:full":"La Caldereta, 3 Santa Cruz Palma Santa Cruz De Tenerife 38700",
    "addr:housenumber":"3",
    "addr:postcode":"38700",
    "iso:country":"ES",
    "sg:address":"La Caldereta, 3",
    "sg:city":"Santa Cruz Palma",
    "sg:orig_category":"Ense\u00d1anza: Profesiones Art\u00cdsticas",
    "sg:phone":"+34 922 41 17 91",
    "sg:postcode":"38700",
    "sg:province":"Santa Cruz De Tenerife",
    "wof:name":"Gobierno De Canarias",
    "wof:placetype":"venue"
},
  "geometry": {"coordinates":[-17.7677326202,28.6805782318],"type":"Point"}
}