{
  "type": "Feature",
  "properties": {
    "addr:full":"Carr Joan Maragall, 25 Figueres Girona 17600",
    "addr:housenumber":"25",
    "addr:postcode":"17600",
    "addr:street":"Carr Joan Maragall",
    "iso:country":"ES",
    "sg:address":"Carr Joan Maragall, 25",
    "sg:city":"Figueres",
    "sg:orig_category":"Ropa Para Se\u00d1oras Y Caballeros (al Por Menor)",
    "sg:phone":"+34 972 50 65 48",
    "sg:postcode":"17600",
    "sg:province":"Girona",
    "sg:website":"www.adolfo-dominguez.com",
    "wof:name":"Vivas Valiente Veronica",
    "wof:placetype":"venue"
},
  "geometry": {"coordinates":[2.9627885818,42.267578125],"type":"Point"}
}