{
  "type": "Feature",
  "properties": {
    "addr:full":"Plaz Angel De La Bodega, 6 Cabez\u00f3n Sal Cantabria 39500",
    "addr:housenumber":"6",
    "addr:postcode":"39500",
    "addr:street":"Bodega",
    "iso:country":"ES",
    "sg:address":"Plaz Angel De La Bodega, 6",
    "sg:city":"Cabez\u00f3n Sal",
    "sg:orig_category":"Restaurantes",
    "sg:phone":"+34 942 70 17 04",
    "sg:postcode":"39500",
    "sg:province":"Cantabria",
    "wof:name":"Teran Gonzalez Jose Maria",
    "wof:placetype":"venue"
},
  "geometry": {"coordinates":[-4.2374691963,43.3085784912],"type":"Point"}
}