{
  "type": "Feature",
  "properties": {
    "addr:full":"Avda Europa, 1 Pozuelo De Alarcon Madrid 28224",
    "addr:housenumber":"1",
    "addr:postcode":"28224",
    "addr:street":"Avda Europa",
    "iso:country":"ES",
    "sg:address":"Avda Europa, 1",
    "sg:city":"Pozuelo De Alarcon",
    "sg:orig_category":"Papeler\u00cdas, Librer\u00cdas",
    "sg:phone":"+34 917 15 85 32",
    "sg:postcode":"28224",
    "sg:province":"Madrid",
    "wof:name":"Ramos Rollon Olga",
    "wof:placetype":"venue"
},
  "geometry": {"coordinates":[-3.8027560711,40.4347038269],"type":"Point"}
}