{
  "type": "Feature",
  "properties": {
    "iso:country":"ES",
    "sg:address":"Pque Santurtzi, 7",
    "sg:city":"Santurtzi",
    "sg:orig_category":"Internados & Ense\u00d1anza Privada",
    "sg:phone":"+34 944 61 23 69",
    "sg:postcode":"48980",
    "sg:province":"Vizcaya",
    "wof:name":"Hermanas Carmelitas Teresa De San Jose",
    "wof:placetype":"venue"
},
  "geometry": {"coordinates":[-3.0297560692,43.3281364441],"type":"Point"}
}