{
  "type": "Feature",
  "properties": {
    "iso:country":"ES",
    "sg:address":"Carrer de Pons D'icart, 41",
    "sg:city":"Tarragona",
    "sg:orig_category":"Seguridad En El Trabajo Y Prevenci\u00d3n De Riesgos Laborales",
    "sg:phone":"+34 977 23 06 54",
    "sg:postcode":"43004",
    "sg:province":"Tarragona",
    "wof:name":"Grupo Mgo S.a.",
    "wof:placetype":"venue"
},
  "geometry": {"coordinates":[1.2536439896,41.1213378906],"type":"Point"}
}