{
  "type": "Feature",
  "properties": {
    "addr:full":"Avda Juan De Austria, 16 Alcala Henares Madrid 28804",
    "addr:housenumber":"16",
    "addr:postcode":"28804",
    "addr:street":"Avda Juan De Austria",
    "iso:country":"ES",
    "sg:address":"Avda Juan De Austria, 16",
    "sg:city":"Alcala Henares",
    "sg:orig_category":"Frutas Y Legumbres Frescas (al Por Mayor)",
    "sg:phone":"+34 918 88 34 10",
    "sg:postcode":"28804",
    "sg:province":"Madrid",
    "wof:name":"Lopez Fernandez Antonia",
    "wof:placetype":"venue"
},
  "geometry": {"coordinates":[-3.3550829887,40.4863624573],"type":"Point"}
}