{
  "type": "Feature",
  "properties": {
    "iso:country":"ES",
    "sg:address":"Calle de Rio Alhama, 15",
    "sg:city":"Corella",
    "sg:orig_category":"Empresas De Limpieza",
    "sg:phone":"+34 948 40 10 40",
    "sg:postcode":"31591",
    "sg:province":"Navarra",
    "wof:name":"Servicor Limpiezas Y Conservacion S.l.",
    "wof:placetype":"venue"
},
  "geometry": {"coordinates":[-1.7908300161,42.1151390076],"type":"Point"}
}