{
  "type": "Feature",
  "properties": {
    "iso:country":"ES",
    "sg:address":"Calle de Francisco De Icaza, 7",
    "sg:city":"Madrid",
    "sg:orig_category":"Aparcamientos (infraestructuras, Accesorios)",
    "sg:phone":"+34 915 69 09 60",
    "sg:postcode":"28025",
    "sg:province":"Madrid",
    "wof:name":"Arozamena S.l",
    "wof:placetype":"venue"
},
  "geometry": {"coordinates":[-3.7272946835,40.3854293823],"type":"Point"}
}