{
  "type": "Feature",
  "properties": {
    "iso:country":"ES",
    "sg:address":"Calle de Tridente, 10",
    "sg:city":"Alacant",
    "sg:orig_category":"Pescader\u00cdas (al Por Menor)",
    "sg:phone":"+34 965 15 05 62",
    "sg:postcode":"03540",
    "sg:province":"Alicante",
    "wof:name":"Cruz Perez Pablo Antonio De La",
    "wof:placetype":"venue"
},
  "geometry": {"coordinates":[-0.4232330024,38.3583869934],"type":"Point"}
}