{
  "type": "Feature",
  "properties": {
    "addr:full":"Avda Monterreal, 2 Loureiral Pontevedra 36300",
    "addr:housenumber":"2",
    "addr:postcode":"36300",
    "addr:street":"Avda Monterreal",
    "iso:country":"ES",
    "sg:address":"Avda Monterreal, 2",
    "sg:city":"Loureiral",
    "sg:orig_category":"Estilistas Y Estudios De Estilo De Corte Y Confecci\u00d3n",
    "sg:phone":"+34 986 35 82 06",
    "sg:postcode":"36300",
    "sg:province":"Pontevedra",
    "wof:name":"Galimoda S. L.",
    "wof:placetype":"venue"
},
  "geometry": {"coordinates":[-8.8501644135,42.1211166382],"type":"Point"}
}