{
  "type": "Feature",
  "properties": {
    "iso:country":"ES",
    "sg:address":"Avda Torneo, 35",
    "sg:city":"Sevilla",
    "sg:orig_category":"Muebles Y Accesorios Para Cocinas Y Cuartos De Ba\u00d1o (al Por Menor)",
    "sg:phone":"+34 954 38 83 20",
    "sg:postcode":"41002",
    "sg:province":"Sevilla",
    "wof:name":"Unikas Cocinas S.l",
    "wof:placetype":"venue"
},
  "geometry": {"coordinates":[-5.9996490479,37.3992385864],"type":"Point"}
}