{
  "type": "Feature",
  "properties": {
    "addr:full":"Rua Estrada, 7 Vigo Pontevedra 36209",
    "addr:housenumber":"7",
    "addr:postcode":"36209",
    "addr:street":"Rua Estrada",
    "iso:country":"ES",
    "sg:address":"Rua Estrada, 7",
    "sg:city":"Vigo",
    "sg:orig_category":"Iglesias Cristianas Diversas",
    "sg:phone":"+34 986 20 60 22",
    "sg:postcode":"36209",
    "sg:province":"Pontevedra",
    "wof:name":"Testigos Cristianos De Jehova",
    "wof:placetype":"venue"
},
  "geometry": {"coordinates":[-8.7429351807,42.2200469971],"type":"Point"}
}