{
  "type": "Feature",
  "properties": {
    "addr:full":"Calle de Duque De Sesto, 48 Madrid Madrid 28009",
    "addr:housenumber":"48",
    "addr:postcode":"madrid;28009",
    "addr:street":"Calle De Duque De Sesto",
    "iso:country":"ES",
    "sg:address":"Calle de Duque De Sesto, 48",
    "sg:city":"Madrid",
    "sg:orig_category":"Librer\u00cdas",
    "sg:phone":"+34 915 73 50 80",
    "sg:postcode":"28009",
    "sg:province":"Madrid",
    "sg:website":"www.romo.es",
    "wof:name":"Libreria Internacional De Romo S. L.",
    "wof:placetype":"venue"
},
  "geometry": {"coordinates":[-3.6737668514,40.4223594666],"type":"Point"}
}