{
  "type": "Feature",
  "properties": {
    "addr:full":"Estd Braganza (de), 79 Abedes Ourense 32615",
    "addr:postcode":"32615",
    "iso:country":"ES",
    "sg:address":"Estd Braganza (de), 79",
    "sg:city":"Abedes",
    "sg:orig_category":"Iglesia Cat\u00d3lica",
    "sg:phone":"+34 988 41 02 46",
    "sg:postcode":"32615",
    "sg:province":"Ourense",
    "wof:name":"Afonso Dominguez Nicolas",
    "wof:placetype":"venue"
},
  "geometry": {"coordinates":[-7.4089488983,41.9375076294],"type":"Point"}
}