{
  "type": "Feature",
  "properties": {
    "iso:country":"ES",
    "sg:address":"Carr Majoral De Quart, 13",
    "sg:city":"Quart Poblet",
    "sg:classifiers":[
        {
            "category":"Taxi",
            "type":"Transportation"
        }
    ],
    "sg:phone":"+34 961 54 47 25",
    "sg:postcode":"46930",
    "sg:province":"Valencia",
    "wof:name":"Martinez Cervera Vicente",
    "wof:placetype":"venue"
},
  "geometry": {"coordinates":[-0.4386099875,39.4822425842],"type":"Point"}
}