{
  "type": "Feature",
  "properties": {
    "addr:full":"Calle de Cristiandad, 5 S. Jordi Islas Baleares 07199",
    "addr:housenumber":"5",
    "addr:postcode":"07199",
    "addr:street":"Calle De Cristiandad;Jordi",
    "iso:country":"ES",
    "sg:address":"Calle de Cristiandad, 5",
    "sg:city":"S. Jordi",
    "sg:orig_category":"Panader\u00cdas, Panader\u00cdas",
    "sg:phone":"+34 971 74 22 37",
    "sg:postcode":"07199",
    "sg:province":"Islas Baleares",
    "wof:name":"Panaderia Y Pasteleria Col S.l.",
    "wof:placetype":"venue"
},
  "geometry": {"coordinates":[2.7764921188,39.5536727905],"type":"Point"}
}