{
  "type": "Feature",
  "properties": {
    "addr:full":"Carrer de Joan Prim, 297 Granollers Barcelona 08401",
    "addr:housenumber":"297",
    "addr:postcode":"08401",
    "addr:street":"Carrer De Joan Prim",
    "iso:country":"ES",
    "sg:address":"Carrer de Joan Prim, 297",
    "sg:city":"Granollers",
    "sg:orig_category":"Venta, Colocaci\u00d3n, Reparaci\u00d3n De Parabrisas, Techos Descapotables",
    "sg:phone":"+34 938 40 27 27",
    "sg:postcode":"08401",
    "sg:province":"Barcelona",
    "wof:name":"Servil-oil S.a.",
    "wof:placetype":"venue"
},
  "geometry": {"coordinates":[2.2913858891,41.6173095703],"type":"Point"}
}