{
  "type": "Feature",
  "properties": {
    "addr:full":"Calle de General Gallarza, 12 Calahorra La Rioja 26500",
    "addr:housenumber":"12",
    "addr:postcode":"26500",
    "addr:street":"Calle De General Gallarza",
    "iso:country":"ES",
    "sg:address":"Calle de General Gallarza, 12",
    "sg:city":"Calahorra",
    "sg:orig_category":"Electrodom\u00c9sticos (al Por Menor)",
    "sg:phone":"+34 941 13 28 94",
    "sg:postcode":"26500",
    "sg:province":"La Rioja",
    "wof:name":"Comerol S.l.",
    "wof:placetype":"venue"
},
  "geometry": {"coordinates":[-1.9655970335,42.3041152954],"type":"Point"}
}