{
  "type": "Feature",
  "properties": {
    "addr:full":"Calle de Hilados, 19 Torrejon Ardoz Madrid 28850",
    "addr:housenumber":"19",
    "addr:postcode":"28850",
    "addr:street":"Calle De Hilados",
    "iso:country":"ES",
    "sg:address":"Calle de Hilados, 19",
    "sg:city":"Torrejon Ardoz",
    "sg:orig_category":"Camiser\u00cda Y Ropa Interior Masculina (al Por Menor)",
    "sg:phone":"+34 916 77 76 44",
    "sg:postcode":"28850",
    "sg:province":"Madrid",
    "wof:name":"Tradicion Y Futuro S.l.",
    "wof:placetype":"venue"
},
  "geometry": {"coordinates":[-3.4597439766,40.446269989],"type":"Point"}
}