{
  "type": "Feature",
  "properties": {
    "addr:full":"Calle de Rosalia De Castro, S/n Vicedo Lugo 27860",
    "addr:housenumber":"s / n",
    "addr:postcode":"27860",
    "addr:street":"Calle De Rosalia De Castro",
    "iso:country":"ES",
    "sg:address":"Calle de Rosalia De Castro, S/n",
    "sg:city":"Vicedo",
    "sg:orig_category":"M\u00c1rmoles, Granitos Y Piedras Naturales",
    "sg:phone":"+34 982 57 26 68",
    "sg:postcode":"27860",
    "sg:province":"Lugo",
    "wof:name":"Marmoles Y Granitos Trayfer S. L.",
    "wof:placetype":"venue"
},
  "geometry": {"coordinates":[-7.6612930298,43.7364616394],"type":"Point"}
}