{
  "type": "Feature",
  "properties": {
    "addr:full":"Carrer de Planes (les), 21 S. Pere Ribes Barcelona 08810",
    "addr:housenumber":"21",
    "addr:postcode":"08810",
    "addr:street":"Carrer De Planes Les;S. Pere Ribes Barcelona",
    "iso:country":"ES",
    "sg:address":"Carrer de Planes (les), 21",
    "sg:city":"S. Pere Ribes",
    "sg:orig_category":"Agencias Y Agentes Comerciales, Representantes",
    "sg:phone":"+34 938 96 28 90",
    "sg:postcode":"08810",
    "sg:province":"Barcelona",
    "wof:name":"Ferreteria Aleix S.l.",
    "wof:placetype":"venue"
},
  "geometry": {"coordinates":[1.7712459564,41.2626304626],"type":"Point"}
}