{
  "type": "Feature",
  "properties": {
    "iso:country":"ES",
    "sg:address":"Silleros (pol Torobizco), S/n",
    "sg:city":"La Gineta",
    "sg:orig_category":"Fabricaci\u00d3n De Muebles",
    "sg:phone":"+34 967 27 54 40",
    "sg:postcode":"02110",
    "sg:province":"Albacete",
    "wof:name":"Toner Pintiras S.l.",
    "wof:placetype":"venue"
},
  "geometry": {"coordinates":[-1.9724440575,39.0904045105],"type":"Point"}
}