{
  "type": "Feature",
  "properties": {
    "iso:country":"ES",
    "sg:address":"Ronda De Pontevedra, 34",
    "sg:city":"Melide",
    "sg:orig_category":"Asesor\u00cdas Y Estudios Financieros",
    "sg:phone":"+34 981 50 75 02",
    "sg:postcode":"15800",
    "sg:province":"A Coru\u00f1a",
    "wof:name":"Villamor Alvarez Marcos",
    "wof:placetype":"venue"
},
  "geometry": {"coordinates":[-8.0150871277,42.9110641479],"type":"Point"}
}