{
  "type": "Feature",
  "properties": {
    "iso:country":"ES",
    "sg:address":"Calle de Luis Nu\u00d1ez, 24",
    "sg:city":"Villardeciervos",
    "sg:orig_category":"Pensiones Familiares",
    "sg:phone":"+34 980 65 49 01",
    "sg:postcode":"49562",
    "sg:province":"Zamora",
    "wof:name":"Herrero Gallego Angel",
    "wof:placetype":"venue"
},
  "geometry": {"coordinates":[-6.2849988937,41.9403991699],"type":"Point"}
}