{
  "type": "Feature",
  "properties": {
    "addr:full":"Calle de Juan Ramon Jimenez, 15 Almodovar Campo Ciudad Real 13580",
    "addr:housenumber":"15",
    "addr:postcode":"13580",
    "addr:street":"Calle De Juan Ramon Jimenez",
    "iso:country":"ES",
    "sg:address":"Calle de Juan Ramon Jimenez, 15",
    "sg:city":"Almodovar Campo",
    "sg:orig_category":"Abogados",
    "sg:phone":"+34 926 48 33 04",
    "sg:postcode":"13580",
    "sg:province":"Ciudad Real",
    "wof:name":"Fernandez Millan Sanchez Isidro",
    "wof:placetype":"venue"
},
  "geometry": {"coordinates":[-4.1787037849,38.7015380859],"type":"Point"}
}