{
  "type": "Feature",
  "properties": {
    "addr:full":"Calle de Marques De Vallejo, 14 Logro\u00f1o La Rioja 26001",
    "addr:housenumber":"14",
    "addr:postcode":"26001",
    "addr:street":"Calle De Marques De Vallejo;Rioja",
    "iso:country":"ES",
    "sg:address":"Calle de Marques De Vallejo, 14",
    "sg:city":"Logro\u00f1o",
    "sg:orig_category":"Peluqueros: De Se\u00d1oras",
    "sg:phone":"+34 941 24 50 90",
    "sg:postcode":"26001",
    "sg:province":"La Rioja",
    "wof:name":"Velilla De Pedro Maria Esther",
    "wof:placetype":"venue"
},
  "geometry": {"coordinates":[-2.4454450607,42.4661941528],"type":"Point"}
}