{
  "type": "Feature",
  "properties": {
    "iso:country":"ES",
    "sg:address":"Cmno Cabeza La Vaca, S/n",
    "sg:city":"Jara",
    "sg:orig_category":"Negocio De Materiales De Construcci\u00d3n",
    "sg:phone":"+34 956 38 95 16",
    "sg:postcode":"11540",
    "sg:province":"C\u00e1diz",
    "wof:name":"Ricardo Enriquez S.l.",
    "wof:placetype":"venue"
},
  "geometry": {"coordinates":[-6.3575987816,36.777721405],"type":"Point"}
}