{
  "type": "Feature",
  "properties": {
    "iso:country":"ES",
    "sg:address":"Anta (areas), S/n",
    "sg:city":"Anta",
    "sg:orig_category":"Goma: Productos De Uso Industrial (fabricaci\u00d3n, Al Por Mayor)",
    "sg:phone":"+34 986 60 37 64",
    "sg:postcode":"36711",
    "sg:province":"Pontevedra",
    "sg:website":"www.norrubber.telefonica.net",
    "wof:name":"Norrubber S.a.l.",
    "wof:placetype":"venue"
},
  "geometry": {"coordinates":[-8.6667318344,42.034992218],"type":"Point"}
}