{
  "type": "Feature",
  "properties": {
    "iso:country":"ES",
    "sg:address":"Calle de Cid Campeador, 7",
    "sg:city":"Mostoles",
    "sg:orig_category":"Librer\u00cdas",
    "sg:phone":"+34 916 13 03 36",
    "sg:postcode":"28935",
    "sg:province":"Madrid",
    "wof:name":"Disgarvi Distribuidora De Textos Medicos S.l.",
    "wof:placetype":"venue"
},
  "geometry": {"coordinates":[-3.8725745678,40.3270950317],"type":"Point"}
}