{
  "type": "Feature",
  "properties": {
    "iso:country":"ES",
    "sg:address":"Cno. Brandis, S/n",
    "sg:city":"Manacor",
    "sg:orig_category":"Pintura, Barniz, Productos Asimilables (fabricaci\u00d3n, Al Por Mayor)",
    "sg:phone":"+34 971 55 39 52",
    "sg:postcode":"07500",
    "sg:province":"Islas Baleares",
    "wof:name":"Gomila Alos Jaime",
    "wof:placetype":"venue"
},
  "geometry": {"coordinates":[3.2435810566,39.4760704041],"type":"Point"}
}