{
  "type": "Feature",
  "properties": {
    "iso:country":"ES",
    "sg:address":"Carrer de Frederic Prats, 12",
    "sg:city":"Hospitalet Llobregat",
    "sg:orig_category":"Peluqueros: De Se\u00d1oras",
    "sg:phone":"+34 933 38 74 37",
    "sg:postcode":"08901",
    "sg:province":"Barcelona",
    "wof:name":"Jordan Rodriguez Ana",
    "wof:placetype":"venue"
},
  "geometry": {"coordinates":[2.095760107,41.3599128723],"type":"Point"}
}