{
  "type": "Feature",
  "properties": {
    "addr:full":"Calle de Cabrales, 23 Gijon Asturias 33201",
    "addr:housenumber":"23",
    "addr:postcode":"33201",
    "addr:street":"Calle De Cabrales",
    "iso:country":"ES",
    "sg:address":"Calle de Cabrales, 23",
    "sg:city":"Gijon",
    "sg:orig_category":"Promotores Constructores",
    "sg:phone":"+34 985 34 36 90",
    "sg:postcode":"33201",
    "sg:province":"Asturias",
    "wof:name":"Ancizu Irure Alberto",
    "wof:placetype":"venue"
},
  "geometry": {"coordinates":[-5.6602835655,43.54063797],"type":"Point"}
}