{
  "type": "Feature",
  "properties": {
    "addr:full":"Calle de Miguel De Unamuno, 15 Valladolid Valladolid 47008",
    "addr:housenumber":"15",
    "addr:postcode":"47008",
    "addr:street":"Calle De Miguel De Unamuno",
    "iso:country":"ES",
    "sg:address":"Calle de Miguel De Unamuno, 15",
    "sg:city":"Valladolid",
    "sg:orig_category":"Caf\u00c9s, Bares, Cervecer\u00cdas",
    "sg:phone":"+34 983 24 84 72",
    "sg:postcode":"47008",
    "sg:province":"Valladolid",
    "wof:name":"Jose Antonio Perez Montero Y Otro Cdad",
    "wof:placetype":"venue"
},
  "geometry": {"coordinates":[-4.7525601387,41.6106414795],"type":"Point"}
}