{
  "type": "Feature",
  "properties": {
    "addr:full":"Calle de Francisco De Rojas, 5 Madrid Madrid 28010",
    "addr:housenumber":"5",
    "addr:postcode":"28010",
    "addr:street":"Calle De Francisco De Rojas",
    "iso:country":"ES",
    "sg:address":"Calle de Francisco De Rojas, 5",
    "sg:city":"Madrid",
    "sg:orig_category":"Abogados",
    "sg:phone":"+34 914 45 28 17",
    "sg:postcode":"28010",
    "sg:province":"Madrid",
    "wof:name":"Echarri Gutierrez Miguel",
    "wof:placetype":"venue"
},
  "geometry": {"coordinates":[-3.6997880936,40.4291725159],"type":"Point"}
}