{
  "type": "Feature",
  "properties": {
    "iso:country":"ES",
    "sg:address":"Carrer de Pare Bartomeu Pou, 34",
    "sg:city":"Palma",
    "sg:orig_category":"Asesor\u00cda De Formaci\u00d3n Y Gesti\u00d3n De Personal",
    "sg:phone":"+34 971 76 35 48",
    "sg:postcode":"07003",
    "sg:province":"Islas Baleares",
    "sg:website":"www.pentaasesores.com",
    "wof:name":"Penta Asesores Laborales S.l.",
    "wof:placetype":"venue"
},
  "geometry": {"coordinates":[2.6495079994,39.5810661316],"type":"Point"}
}