{
  "type": "Feature",
  "properties": {
    "iso:country":"ES",
    "sg:address":"Pg Carretera, 32",
    "sg:city":"Benidorm",
    "sg:orig_category":"Asesor\u00cdas Y Estudios Financieros",
    "sg:phone":"+34 966 80 29 15",
    "sg:postcode":"03500",
    "sg:province":"Alicante",
    "wof:name":"Gr Y Asociados Asesores Legales Y Tribut",
    "wof:placetype":"venue"
},
  "geometry": {"coordinates":[-0.130952999,38.5363006592],"type":"Point"}
}