{
  "type": "Feature",
  "properties": {
    "addr:full":"Avda Tren Expreso, 111 Venta De Ba\u00e7os Palencia 34200",
    "addr:housenumber":"111",
    "addr:postcode":"34200",
    "addr:street":"Avda Tren Expreso",
    "iso:country":"ES",
    "sg:address":"Avda Tren Expreso, 111",
    "sg:city":"Venta De Ba\u00e7os",
    "sg:orig_category":"Restaurantes",
    "sg:phone":"+34 979 77 22 74",
    "sg:postcode":"34200",
    "sg:province":"Palencia",
    "wof:name":"Hermanos Villacorta C.b.",
    "wof:placetype":"venue"
},
  "geometry": {"coordinates":[-4.4883089066,41.9319190979],"type":"Point"}
}