{
  "type": "Feature",
  "properties": {
    "addr:full":"C/ Sant Jaume, 2 Estanyol De Migjorn Islas Baleares 07639",
    "addr:housenumber":"2",
    "addr:postcode":"07639",
    "addr:street":"C / Sant Jaume",
    "iso:country":"ES",
    "sg:address":"C/ Sant Jaume, 2",
    "sg:city":"Estanyol De Migjorn",
    "sg:orig_category":"Electrodom\u00c9sticos (al Por Menor)",
    "sg:phone":"+34 971 64 06 62",
    "sg:postcode":"07639",
    "sg:province":"Islas Baleares",
    "wof:name":"Moll Pons Micaela",
    "wof:placetype":"venue"
},
  "geometry": {"coordinates":[2.8558709621,39.3647956848],"type":"Point"}
}