{
  "type": "Feature",
  "properties": {
    "addr:full":"Av Rei Jaume I, 1 Benidorm Alicante 03500",
    "addr:housenumber":"1",
    "addr:postcode":"03500",
    "addr:street":"Av Rei Jaume I",
    "iso:country":"ES",
    "sg:address":"Av Rei Jaume I, 1",
    "sg:city":"Benidorm",
    "sg:orig_category":"Ropa Para Se\u00d1oras Y Caballeros (al Por Menor)",
    "sg:phone":"+34 966 80 64 18",
    "sg:postcode":"03500",
    "sg:province":"Alicante",
    "wof:name":"Gestion Inmobiliaria Belenguer S.l.",
    "wof:placetype":"venue"
},
  "geometry": {"coordinates":[-0.137511,38.5375747681],"type":"Point"}
}