{
  "type": "Feature",
  "properties": {
    "iso:country":"ES",
    "sg:address":"Av Juan Gil - Albert, 22",
    "sg:city":"Alcoi",
    "sg:orig_category":"Psic\u00d3logos",
    "sg:phone":"+34 966 54 02 44",
    "sg:postcode":"03804",
    "sg:province":"Alicante",
    "sg:website":"www.proseleccion.es",
    "wof:name":"Proseleccion S.l.",
    "wof:placetype":"venue"
},
  "geometry": {"coordinates":[-0.47172001,38.7070426941],"type":"Point"}
}