{
  "type": "Feature",
  "properties": {
    "addr:full":"Calle de Manteria, 3 Valladolid Valladolid 47004",
    "addr:housenumber":"3",
    "addr:postcode":"47004",
    "addr:street":"Calle De Manteria",
    "iso:country":"ES",
    "sg:address":"Calle de Manteria, 3",
    "sg:city":"Valladolid",
    "sg:orig_category":"Perfumer\u00cda (al Por Menor)",
    "sg:phone":"+34 983 29 28 07",
    "sg:postcode":"47004",
    "sg:province":"Valladolid",
    "wof:name":"Mi Perfumeria S.a.",
    "wof:placetype":"venue"
},
  "geometry": {"coordinates":[-4.7239952087,41.6488647461],"type":"Point"}
}