{
  "type": "Feature",
  "properties": {
    "iso:country":"ES",
    "sg:address":"Calle de Padre Espla, 21",
    "sg:city":"Alacant",
    "sg:orig_category":"Fabricaci\u00d3n De Muebles",
    "sg:phone":"+34 965 21 63 39",
    "sg:postcode":"03013",
    "sg:province":"Alicante",
    "wof:name":"Muebles La Factoria S.a.",
    "wof:placetype":"venue"
},
  "geometry": {"coordinates":[-0.4777255058,38.3566246033],"type":"Point"}
}