{
  "type": "Feature",
  "properties": {
    "addr:full":"Calle de Fuente Del Real, 19 Gijon Asturias 33209",
    "addr:housenumber":"19",
    "addr:postcode":"33209",
    "addr:street":"Calle De Fuente Del Real",
    "iso:country":"ES",
    "sg:address":"Calle de Fuente Del Real, 19",
    "sg:city":"Gijon",
    "sg:orig_category":"Molduras, Junquillos, Listones Y Molduras Perforadas",
    "sg:phone":"+34 985 38 00 73",
    "sg:postcode":"33209",
    "sg:province":"Asturias",
    "wof:name":"Victor Y Loli C.b.",
    "wof:placetype":"venue"
},
  "geometry": {"coordinates":[-5.6570739746,43.5316047668],"type":"Point"}
}