{
  "type": "Feature",
  "properties": {
    "addr:full":"Rbla Guipuscoa, 19 Barcelona Barcelona 08018",
    "addr:housenumber":"19",
    "addr:postcode":"08018",
    "addr:street":"Rbla Guipuscoa",
    "iso:country":"ES",
    "sg:address":"Rbla Guipuscoa, 19",
    "sg:city":"Barcelona",
    "sg:orig_category":"Internados & Ense\u00d1anza Privada",
    "sg:phone":"+34 933 07 20 66",
    "sg:postcode":"08018",
    "sg:province":"Barcelona",
    "wof:name":"Roca Fernandez Juan Jose",
    "wof:placetype":"venue"
},
  "geometry": {"coordinates":[2.1936979294,41.4141235352],"type":"Point"}
}