{
  "type": "Feature",
  "properties": {
    "addr:full":"Calle de Ferrocarril, 20 Madrid Madrid 28045",
    "addr:housenumber":"20",
    "addr:postcode":"madrid;28045",
    "addr:street":"Calle De Ferrocarril",
    "iso:country":"ES",
    "sg:address":"Calle de Ferrocarril, 20",
    "sg:city":"Madrid",
    "sg:orig_category":"Centros De Coordinaci\u00d3n",
    "sg:phone":"+34 915 41 79 68",
    "sg:postcode":"28045",
    "sg:province":"Madrid",
    "wof:name":"Serprogesa",
    "wof:placetype":"venue"
},
  "geometry": {"coordinates":[-3.6958210468,40.4009895325],"type":"Point"}
}