{
  "type": "Feature",
  "properties": {
    "addr:full":"Avda Ca\u00d1ada (de La), S/n Coslada Madrid 28820",
    "addr:postcode":"28820",
    "addr:street":"Avda Can\u0303Ada De La S / N",
    "iso:country":"ES",
    "sg:address":"Avda Ca\u00d1ada (de La), S/n",
    "sg:city":"Coslada",
    "sg:orig_category":"Centros De Educaci\u00d3n Especial",
    "sg:phone":"+34 916 74 04 59",
    "sg:postcode":"28820",
    "sg:province":"Madrid",
    "wof:name":"Colegio Publico Agapito Marazuela",
    "wof:placetype":"venue"
},
  "geometry": {"coordinates":[-3.5391139984,40.4319610596],"type":"Point"}
}