{
  "type": "Feature",
  "properties": {
    "iso:country":"ES",
    "sg:address":"Calle de Rafael Finat, 7",
    "sg:city":"Madrid",
    "sg:orig_category":"Molduras, Junquillos, Listones Y Molduras Perforadas",
    "sg:phone":"+34 917 06 12 74",
    "sg:postcode":"28044",
    "sg:province":"Madrid",
    "wof:name":"Moran Serrano Daniel",
    "wof:placetype":"venue"
},
  "geometry": {"coordinates":[-3.7649359703,40.3834457397],"type":"Point"}
}