{
  "type": "Feature",
  "properties": {
    "iso:country":"ES",
    "sg:address":"Pase Yeserias, 3",
    "sg:city":"Madrid",
    "sg:orig_category":"Veh\u00cdculos De Ocasi\u00d3n",
    "sg:phone":"+34 915 17 81 60",
    "sg:postcode":"28005",
    "sg:province":"Madrid",
    "sg:website":"www.toleauto.es",
    "wof:name":"Toleauto S.a.",
    "wof:placetype":"venue"
},
  "geometry": {"coordinates":[-3.7133049965,40.4007034302],"type":"Point"}
}