{
  "type": "Feature",
  "properties": {
    "addr:full":"Calle de Violante De Hungria, 5 Zaragoza Zaragoza 50009",
    "addr:housenumber":"5",
    "addr:postcode":"50009",
    "addr:street":"Calle De Violante De Hungria",
    "iso:country":"ES",
    "sg:address":"Calle de Violante De Hungria, 5",
    "sg:city":"Zaragoza",
    "sg:orig_category":"Arquitectos",
    "sg:phone":"+34 976 55 98 13",
    "sg:postcode":"50009",
    "sg:province":"Zaragoza",
    "wof:name":"Ramos Martos Manuel",
    "wof:placetype":"venue"
},
  "geometry": {"coordinates":[-0.9015190005,41.6390075684],"type":"Point"}
}