{
  "type": "Feature",
  "properties": {
    "iso:country":"ES",
    "sg:address":"Avda Espa\u00d1a (de), 14",
    "sg:city":"Pinto",
    "sg:orig_category":"M\u00c9dicos: Ginecolog\u00cda Y Obstetricia",
    "sg:phone":"+34 916 92 27 66",
    "sg:postcode":"28320",
    "sg:province":"Madrid",
    "wof:name":"Rodriguez-mata Vargas Angel",
    "wof:placetype":"venue"
},
  "geometry": {"coordinates":[-3.6981630325,40.2398872375],"type":"Point"}
}