{
  "type": "Feature",
  "properties": {
    "addr:full":"Calle de Galicia, 3 Madrid Madrid 28024",
    "addr:housenumber":"3",
    "addr:postcode":"28024",
    "addr:street":"Calle De Galicia",
    "iso:country":"ES",
    "sg:address":"Calle de Galicia, 3",
    "sg:city":"Madrid",
    "sg:orig_category":"Carnicer\u00cdas, Carnicer\u00cdas",
    "sg:phone":"+34 917 11 03 87",
    "sg:postcode":"28024",
    "sg:province":"Madrid",
    "wof:name":"Bote Iglesias Ernesto",
    "wof:placetype":"venue"
},
  "geometry": {"coordinates":[-3.7711219788,40.3974113464],"type":"Point"}
}