{
  "type": "Feature",
  "properties": {
    "iso:country":"ES",
    "sg:address":"Calle de Juan Carlos I, 20",
    "sg:city":"Casar",
    "sg:orig_category":"Supermercados Y Hipermercados",
    "sg:phone":"+34 949 33 63 67",
    "sg:postcode":"19170",
    "sg:province":"Guadalajara",
    "wof:name":"La Tienda De Rodelas S .",
    "wof:placetype":"venue"
},
  "geometry": {"coordinates":[-3.4270989895,40.7050857544],"type":"Point"}
}