{
  "type": "Feature",
  "properties": {
    "addr:full":"Calle de Librero Esclapes, S/n Valencia Valencia 46019",
    "addr:housenumber":"s / n",
    "addr:postcode":"46019",
    "addr:street":"Calle De Librero Esclapes",
    "iso:country":"ES",
    "sg:address":"Calle de Librero Esclapes, S/n",
    "sg:city":"Valencia",
    "sg:orig_category":"Peluquer\u00cdas, Peluquer\u00cda Mixta",
    "sg:phone":"+34 963 66 54 53",
    "sg:postcode":"46019",
    "sg:province":"Valencia",
    "wof:name":"Mafer Valencia S.l.",
    "wof:placetype":"venue"
},
  "geometry": {"coordinates":[-0.3677740097,39.4987983704],"type":"Point"}
}