{
  "type": "Feature",
  "properties": {
    "addr:full":"Ctra Murcia, Km. 0054,0 Elche Alicante 03205",
    "addr:postcode":"03205",
    "addr:street":"Ctra Murcia Km. 0054,0",
    "iso:country":"ES",
    "sg:address":"Ctra Murcia, Km. 0054,0",
    "sg:city":"Elche",
    "sg:orig_category":"Confecci\u00d3n De Zapatos",
    "sg:phone":"+34 965 44 72 33",
    "sg:postcode":"03205",
    "sg:province":"Alicante",
    "wof:name":"Soler Mora Carlos",
    "wof:placetype":"venue"
},
  "geometry": {"coordinates":[-0.6995239854,38.2634811401],"type":"Point"}
}