{
  "type": "Feature",
  "properties": {
    "iso:country":"ES",
    "sg:address":"Avda Lugo, 107",
    "sg:city":"Pontevedra",
    "sg:orig_category":"Molduras, Junquillos, Listones Y Molduras Perforadas",
    "sg:phone":"+34 986 84 47 20",
    "sg:postcode":"36004",
    "sg:province":"Pontevedra",
    "wof:name":"Ventin Portasany Benito Manuel",
    "wof:placetype":"venue"
},
  "geometry": {"coordinates":[-8.621090889,42.4359550476],"type":"Point"}
}