{
  "type": "Feature",
  "properties": {
    "iso:country":"ES",
    "sg:address":"Calle de Caveda, 11",
    "sg:city":"Oviedo",
    "sg:orig_category":"Bisuter\u00cda, Joyer\u00cda, Relojer\u00cda (al Por Menor)",
    "sg:phone":"+34 985 22 09 08",
    "sg:postcode":"33002",
    "sg:province":"Asturias",
    "wof:name":"Garcia Osorio S.l.",
    "wof:placetype":"venue"
},
  "geometry": {"coordinates":[-5.8480181694,43.3647613525],"type":"Point"}
}