{
  "type": "Feature",
  "properties": {
    "iso:country":"ES",
    "sg:address":"Rua Calvo Sotelo, 126",
    "sg:city":"Sarria",
    "sg:orig_category":"Asociaciones Y Clubs Deportivos",
    "sg:phone":"+34 982 53 37 23",
    "sg:postcode":"27600",
    "sg:province":"Lugo",
    "wof:name":"Diaz Lopez Juan Jose",
    "wof:placetype":"venue"
},
  "geometry": {"coordinates":[-7.4101309776,42.7781600952],"type":"Point"}
}