{
  "type": "Feature",
  "properties": {
    "addr:full":"Calle de Extremadura, 21 Vitoria-gasteiz \u00c1lava 01003",
    "addr:housenumber":"21",
    "addr:postcode":"01003",
    "addr:street":"Calle De Extremadura",
    "iso:country":"ES",
    "sg:address":"Calle de Extremadura, 21",
    "sg:city":"Vitoria-gasteiz",
    "sg:orig_category":"Delineantes",
    "sg:phone":"+34 945 12 27 53",
    "sg:postcode":"01003",
    "sg:province":"\u00c1lava",
    "wof:name":"Garcia De Vicu\u00f1a Ortueta Jose",
    "wof:placetype":"venue"
},
  "geometry": {"coordinates":[-2.6601395607,42.8502464294],"type":"Point"}
}