{
  "type": "Feature",
  "properties": {
    "iso:country":"ES",
    "sg:address":"Calle de Alemania, 8",
    "sg:city":"Valencia",
    "sg:orig_category":"Ingeniero",
    "sg:phone":"+34 963 41 20 00",
    "sg:postcode":"46010",
    "sg:province":"Valencia",
    "wof:name":"Ba\u00f1on Martinez Francisco",
    "wof:placetype":"venue"
},
  "geometry": {"coordinates":[-0.3616231978,39.4816055298],"type":"Point"}
}