{
  "type": "Feature",
  "properties": {
    "iso:country":"ES",
    "sg:address":"Calle de Villadecanes, 1",
    "sg:city":"Fuenlabrada",
    "sg:orig_category":"Piedra, Vidrio, Cer\u00c1mica Y Porcelana",
    "sg:phone":"+34 916 42 29 52",
    "sg:postcode":"28947",
    "sg:province":"Madrid",
    "sg:website":"www.azulejosvalcarcel.com",
    "wof:name":"Valcarcel S.a.",
    "wof:placetype":"venue"
},
  "geometry": {"coordinates":[-3.747410059,40.2698898315],"type":"Point"}
}