{
  "type": "Feature",
  "properties": {
    "addr:full":"Calle de Virgen Del Rosario, 8 Armu\u00e7a De Almanzora Almer\u00eda 04888",
    "addr:housenumber":"8",
    "addr:postcode":"04888",
    "addr:street":"Calle De Virgen Del Rosario;Almeri\u0301A",
    "iso:country":"ES",
    "sg:address":"Calle de Virgen Del Rosario, 8",
    "sg:city":"Armu\u00e7a De Almanzora",
    "sg:orig_category":"Producci\u00d3n, Distribuci\u00d3n De Electricidad",
    "sg:phone":"+34 950 42 04 80",
    "sg:postcode":"04888",
    "sg:province":"Almer\u00eda",
    "wof:name":"Dielec Guerrero Lorente S.l.",
    "wof:placetype":"venue"
},
  "geometry": {"coordinates":[-2.4352989197,37.3336105347],"type":"Point"}
}