{
  "type": "Feature",
  "properties": {
    "iso:country":"ES",
    "sg:address":"Carrer de Torrent (portals Nous), 6",
    "sg:city":"Portals Nous",
    "sg:orig_category":"Organizaci\u00d3n De Seminarios, Congresos",
    "sg:phone":"+34 971 67 69 15",
    "sg:postcode":"07181",
    "sg:province":"Islas Baleares",
    "wof:name":"Abc Knowledge Company Sl",
    "wof:placetype":"venue"
},
  "geometry": {"coordinates":[2.570272,39.533974],"type":"Point"}
}