{
  "type": "Feature",
  "properties": {
    "iso:country":"ES",
    "sg:address":"Ptda Mola, S/n",
    "sg:city":"El Perello",
    "sg:orig_category":"Semiller\u00cdas",
    "sg:phone":"+34 977 26 78 26",
    "sg:postcode":"43519",
    "sg:province":"Tarragona",
    "wof:name":"El Mola Vivers S.l.",
    "wof:placetype":"venue"
},
  "geometry": {"coordinates":[0.7132700086,40.8763809204],"type":"Point"}
}