{
  "type": "Feature",
  "properties": {
    "addr:full":"Calle de Malasma\u00d1anas, 59 Alcala Guadaira Sevilla 41500",
    "addr:housenumber":"59",
    "addr:postcode":"41500",
    "addr:street":"Calle De Malasman\u0303Anas",
    "iso:country":"ES",
    "sg:address":"Calle de Malasma\u00d1anas, 59",
    "sg:city":"Alcala Guadaira",
    "sg:orig_category":"Panader\u00cdas, Panader\u00cdas",
    "sg:phone":"+34 954 10 25 17",
    "sg:postcode":"41500",
    "sg:province":"Sevilla",
    "wof:name":"Hornos Lorena, S.l.",
    "wof:placetype":"venue"
},
  "geometry": {"coordinates":[-5.839925766,37.3462982178],"type":"Point"}
}