{
  "type": "Feature",
  "properties": {
    "addr:full":"Carrer de Ataulf, 18 Barcelona Barcelona 08002",
    "addr:housenumber":"18",
    "addr:postcode":"08002",
    "addr:street":"Carrer De Ataulf",
    "iso:country":"ES",
    "sg:address":"Carrer de Ataulf, 18",
    "sg:city":"Barcelona",
    "sg:orig_category":"Comerciantes Al Por Mayor De Vinos, Licores Y Alcoholes",
    "sg:phone":"+34 933 15 11 59",
    "sg:postcode":"08002",
    "sg:province":"Barcelona",
    "wof:name":"Neotrinos S.l.",
    "wof:placetype":"venue"
},
  "geometry": {"coordinates":[2.1792430878,41.3808135986],"type":"Point"}
}