{
  "type": "Feature",
  "properties": {
    "addr:full":"Calle de Carmen, 5 Requena Valencia 46340",
    "addr:housenumber":"5",
    "addr:postcode":"46340",
    "addr:street":"Calle De Carmen",
    "iso:country":"ES",
    "sg:address":"Calle de Carmen, 5",
    "sg:city":"Requena",
    "sg:orig_category":"Estancos",
    "sg:phone":"+34 962 30 05 01",
    "sg:postcode":"46340",
    "sg:province":"Valencia",
    "wof:name":"Gil-orozco Limorte Maria Del Carmen",
    "wof:placetype":"venue"
},
  "geometry": {"coordinates":[-1.0987659693,39.4869041443],"type":"Point"}
}