{
  "type": "Feature",
  "properties": {
    "addr:full":"Luga Poligono Industrial Del Bierzo, S/n Toral De Los Vados Le\u00f3n 24560",
    "addr:postcode":"24560",
    "addr:street":"Poligono Industrial Del Bierzo S / N",
    "iso:country":"ES",
    "sg:address":"Luga Poligono Industrial Del Bierzo, S/n",
    "sg:city":"Toral De Los Vados",
    "sg:orig_category":"Papel (al Por Mayor)",
    "sg:phone":"+34 987 54 54 50",
    "sg:postcode":"24560",
    "sg:province":"Le\u00f3n",
    "wof:name":"Industrias Arias Gonzalez S.l.",
    "wof:placetype":"venue"
},
  "geometry": {"coordinates":[-6.7822341919,42.5436286926],"type":"Point"}
}