{
  "type": "Feature",
  "properties": {
    "addr:full":"Venta Del Alamo, S/n Durcal Granada 18650",
    "addr:postcode":"18650",
    "addr:street":"Alamo S / N",
    "iso:country":"ES",
    "sg:address":"Venta Del Alamo, S/n",
    "sg:city":"Durcal",
    "sg:orig_category":"Autob\u00das (explotaci\u00d3n Y Servicios De)",
    "sg:phone":"+34 958 78 13 90",
    "sg:postcode":"18650",
    "sg:province":"Granada",
    "wof:name":"Ruiz Bus S.l.",
    "wof:placetype":"venue"
},
  "geometry": {"coordinates":[-3.5767889023,36.9980545044],"type":"Point"}
}