{
  "type": "Feature",
  "properties": {
    "addr:full":"Carrer de Arago, 182 Barcelona Barcelona 08011",
    "addr:housenumber":"182",
    "addr:postcode":"08011",
    "addr:street":"Carrer De Arago",
    "iso:country":"ES",
    "sg:address":"Carrer de Arago, 182",
    "sg:city":"Barcelona",
    "sg:orig_category":"Centros Empresariales",
    "sg:phone":"+34 932 01 57 11",
    "sg:postcode":"08011",
    "sg:province":"Barcelona",
    "sg:website":"www.humangroup.es",
    "wof:name":"Eurocen Europea De Contratas S.a.",
    "wof:placetype":"venue"
},
  "geometry": {"coordinates":[2.1579890251,41.3867988586],"type":"Point"}
}