{
  "type": "Feature",
  "properties": {
    "addr:full":"Rua Ervedelo, 4 Ourense Ourense 32003",
    "addr:housenumber":"4",
    "addr:postcode":"32003",
    "addr:street":"Rua Ervedelo",
    "iso:country":"ES",
    "sg:address":"Rua Ervedelo, 4",
    "sg:city":"Ourense",
    "sg:orig_category":"Peritos En Seguros",
    "sg:phone":"+34 988 37 15 65",
    "sg:postcode":"32003",
    "sg:province":"Ourense",
    "wof:name":"Garcia & Bermello Correduria De Seguros S.l.",
    "wof:placetype":"venue"
},
  "geometry": {"coordinates":[-7.8670840263,42.3400001526],"type":"Point"}
}