{
  "type": "Feature",
  "properties": {
    "addr:full":"Calle de Luruaco, 11 Madrid Madrid 28033",
    "addr:housenumber":"11",
    "addr:postcode":"madrid;28033",
    "addr:street":"Calle De Luruaco",
    "iso:country":"ES",
    "sg:address":"Calle de Luruaco, 11",
    "sg:city":"Madrid",
    "sg:orig_category":"Molduras, Junquillos, Listones Y Molduras Perforadas",
    "sg:phone":"+34 917 63 00 93",
    "sg:postcode":"28033",
    "sg:province":"Madrid",
    "wof:name":"Martin Hernandez Faustino",
    "wof:placetype":"venue"
},
  "geometry": {"coordinates":[-3.6351621151,40.4731407166],"type":"Point"}
}