{
  "type": "Feature",
  "properties": {
    "iso:country":"ES",
    "sg:address":"Av Valencia, 66",
    "sg:city":"Molins Rei",
    "sg:orig_category":"Agencias Y Asesores De Publicidad",
    "sg:phone":"+34 936 80 36 07",
    "sg:postcode":"08750",
    "sg:province":"Barcelona",
    "wof:name":"Activacion De Ventas Y Consulting El Jardin De Apicuro S.l.",
    "wof:placetype":"venue"
},
  "geometry": {"coordinates":[2.0166869164,41.4097709656],"type":"Point"}
}