{
  "type": "Feature",
  "properties": {
    "iso:country":"ES",
    "sg:address":"Ma\u00f1ueta, 11",
    "sg:city":"Iru\u00f1a",
    "sg:orig_category":"Zapatos (al Por Menor)",
    "sg:phone":"+34 948 22 12 83",
    "sg:postcode":"31001",
    "sg:province":"Navarra",
    "wof:name":"Almacenes San Fernando S. A.",
    "wof:placetype":"venue"
},
  "geometry": {"coordinates":[-1.6434644461,42.8189659119],"type":"Point"}
}