{
  "type": "Feature",
  "properties": {
    "addr:full":"Calle de Juan Antonio Samaranch, 7 Roquetas Mar Almer\u00eda 04740",
    "addr:housenumber":"7",
    "addr:postcode":"04740",
    "addr:street":"Calle De Juan Antonio Samaranch",
    "iso:country":"ES",
    "sg:address":"Calle de Juan Antonio Samaranch, 7",
    "sg:city":"Roquetas Mar",
    "sg:orig_category":"Inmobiliaria (agencias)",
    "sg:phone":"+34 950 32 31 53",
    "sg:postcode":"04740",
    "sg:province":"Almer\u00eda",
    "wof:name":"Laurel De Aguadulce S.l.",
    "wof:placetype":"venue"
},
  "geometry": {"coordinates":[-2.6124989986,36.7638435364],"type":"Point"}
}