{
  "type": "Feature",
  "properties": {
    "addr:full":"Calle de Marineras, 2 Ajalvir Madrid 28864",
    "addr:housenumber":"2",
    "addr:postcode":"28864",
    "addr:street":"Calle De Marineras",
    "iso:country":"ES",
    "sg:address":"Calle de Marineras, 2",
    "sg:city":"Ajalvir",
    "sg:orig_category":"Cerrajer\u00cda, Ferrallista",
    "sg:phone":"+34 918 84 32 00",
    "sg:postcode":"28864",
    "sg:province":"Madrid",
    "sg:website":"www.iseoiberica.es",
    "wof:name":"Cerraduras Iseo Iberica S.l.",
    "wof:placetype":"venue"
},
  "geometry": {"coordinates":[-3.4797050953,40.5151519775],"type":"Point"}
}