{
  "type": "Feature",
  "properties": {
    "iso:country":"ES",
    "sg:address":"Plaz Ortega Y Gasset (de), 2",
    "sg:city":"Coslada",
    "sg:orig_category":"Electricidad: Equipos Industriales, Componentes (fabricaci\u00d3n)",
    "sg:phone":"+34 916 71 04 17",
    "sg:postcode":"28820",
    "sg:province":"Madrid",
    "sg:website":"www.belcrilux.net",
    "wof:name":"Castro Rodriguez Francisco Javier De",
    "wof:placetype":"venue"
},
  "geometry": {"coordinates":[-3.5652830601,40.424282074],"type":"Point"}
}