{
  "type": "Feature",
  "properties": {
    "iso:country":"ES",
    "sg:address":"Calle de Concordia, 60",
    "sg:city":"Torrevieja",
    "sg:orig_category":"Empresas De Limpieza",
    "sg:phone":"+34 965 71 05 05",
    "sg:postcode":"03180",
    "sg:province":"Alicante",
    "wof:name":"Pamies Berenguer Trinidad",
    "wof:placetype":"venue"
},
  "geometry": {"coordinates":[-0.6768159866,37.9785766602],"type":"Point"}
}