{
  "type": "Feature",
  "properties": {
    "addr:full":"Del Mar, 55 Torre Mar M\u00e1laga 29740",
    "addr:housenumber":"55",
    "addr:postcode":"29740",
    "addr:street":"Del Mar;Ma\u0301Laga",
    "iso:country":"ES",
    "sg:address":"Del Mar, 55",
    "sg:city":"Torre Mar",
    "sg:orig_category":"Agencias De Viajes",
    "sg:phone":"+34 952 54 79 79",
    "sg:postcode":"29740",
    "sg:province":"M\u00e1laga",
    "sg:website":"www.barceloviajes.com",
    "wof:name":"Conte Travel S.l.",
    "wof:placetype":"venue"
},
  "geometry": {"coordinates":[-4.3590788841,36.7187805176],"type":"Point"}
}