{
  "type": "Feature",
  "properties": {
    "iso:country":"ES",
    "sg:address":"Calle de Temprado, 9",
    "sg:city":"Teruel",
    "sg:orig_category":"Fotograf\u00cda Y Cine: Aparatos, Pel\u00cdculas Y Accesorios (al Por Menor)",
    "sg:phone":"+34 978 60 91 90",
    "sg:postcode":"44001",
    "sg:province":"Teruel",
    "wof:name":"Prisma Imagen Fotografia Sl",
    "wof:placetype":"venue"
},
  "geometry": {"coordinates":[-1.1084120274,40.3438835144],"type":"Point"}
}