{
  "type": "Feature",
  "properties": {
    "iso:country":"ES",
    "sg:address":"Avda Alcalde Miguel Casta\u00d1o, 69",
    "sg:city":"Le\u00f3n",
    "sg:orig_category":"Tapicer\u00cdas",
    "sg:phone":"+34 987 25 83 95",
    "sg:postcode":"24005",
    "sg:province":"Le\u00f3n",
    "wof:name":"Tapiceria Alpe S.l.",
    "wof:placetype":"venue"
},
  "geometry": {"coordinates":[-5.5613031387,42.5884628296],"type":"Point"}
}