{
  "type": "Feature",
  "properties": {
    "addr:full":"Calle de Sierra Carbonera, 57 Madrid Madrid 28053",
    "addr:housenumber":"57",
    "addr:postcode":"madrid;28053",
    "addr:street":"Calle De Sierra Carbonera",
    "iso:country":"ES",
    "sg:address":"Calle de Sierra Carbonera, 57",
    "sg:city":"Madrid",
    "sg:orig_category":"Comercio De Piezas De Recambio Y De Accesorios De Veh\u00cdculos, Veh\u00cdculos Industriales",
    "sg:phone":"+34 914 77 00 54",
    "sg:postcode":"28053",
    "sg:province":"Madrid",
    "wof:name":"Recambios Vallecas S.l.",
    "wof:placetype":"venue"
},
  "geometry": {"coordinates":[-3.6647279263,40.3905944824],"type":"Point"}
}