{
  "type": "Feature",
  "properties": {
    "iso:country":"ES",
    "sg:address":"Carr Pintor Sorolla, 57",
    "sg:city":"Moncada",
    "sg:orig_category":"Promotores Constructores",
    "sg:phone":"+34 961 30 03 24",
    "sg:postcode":"46113",
    "sg:province":"Valencia",
    "wof:name":"Naves Y Pavimentos S.l.",
    "wof:placetype":"venue"
},
  "geometry": {"coordinates":[-0.3887380064,39.5449295044],"type":"Point"}
}