{
  "type": "Feature",
  "properties": {
    "addr:full":"Calle de Juan Martinez Villergas, 11 Valladolid Valladolid 47014",
    "addr:housenumber":"11",
    "addr:postcode":"47014",
    "addr:street":"Calle De Juan Martinez Villergas",
    "iso:country":"ES",
    "sg:address":"Calle de Juan Martinez Villergas, 11",
    "sg:city":"Valladolid",
    "sg:orig_category":"Agencias De Viajes",
    "sg:phone":"+34 983 37 15 12",
    "sg:postcode":"47014",
    "sg:province":"Valladolid",
    "wof:name":"Alonso Arrabal Carlos Raul",
    "wof:placetype":"venue"
},
  "geometry": {"coordinates":[-4.7536277771,41.6377105713],"type":"Point"}
}