{
  "type": "Feature",
  "properties": {
    "addr:full":"Carr Emili Grahit, 5 Girona Girona 17002",
    "addr:housenumber":"5",
    "addr:postcode":"17002",
    "addr:street":"Carr Emili Grahit",
    "iso:country":"ES",
    "sg:address":"Carr Emili Grahit, 5",
    "sg:city":"Girona",
    "sg:orig_category":"Bancos",
    "sg:phone":"+34 872 08 02 80",
    "sg:postcode":"17002",
    "sg:province":"Girona",
    "sg:website":"www.bancodevalencia.es",
    "wof:name":"Banco De Valencia S A",
    "wof:placetype":"venue"
},
  "geometry": {"coordinates":[2.8172221184,41.9756774902],"type":"Point"}
}