{
  "type": "Feature",
  "properties": {
    "iso:country":"ES",
    "sg:address":"Calle de Ruiz Pons, 3",
    "sg:city":"Bu\u00f1ol",
    "sg:orig_category":"Distribuci\u00d3n De Petr\u00d3leo Y Derivados",
    "sg:phone":"+34 962 50 07 85",
    "sg:postcode":"46360",
    "sg:province":"Valencia",
    "wof:name":"Estacion De Servicio Pe\u00f1alver S. L.",
    "wof:placetype":"venue"
},
  "geometry": {"coordinates":[-0.7883089781,39.417930603],"type":"Point"}
}