{
  "type": "Feature",
  "properties": {
    "iso:country":"ES",
    "sg:address":"Crri Manolito, 11",
    "sg:city":"Dolores",
    "sg:orig_category":"Fabricaci\u00d3n, Importaci\u00d3n De L\u00c1mparas Y Bombillas",
    "sg:phone":"+34 968 25 76 11",
    "sg:postcode":"30011",
    "sg:province":"Murcia",
    "sg:website":"www.manasa.es",
    "wof:name":"Martinez Y Navarro S.a.",
    "wof:placetype":"venue"
},
  "geometry": {"coordinates":[-1.1055790186,37.9783668518],"type":"Point"}
}