{
  "type": "Feature",
  "properties": {
    "iso:country":"ES",
    "sg:address":"Calle de Quevedo, 13",
    "sg:city":"Puebla Cazalla",
    "sg:orig_category":"Negocio De Materiales De Construcci\u00d3n",
    "sg:phone":"+34 955 84 31 39",
    "sg:postcode":"41540",
    "sg:province":"Sevilla",
    "wof:name":"Amacenes Infagu S.l.",
    "wof:placetype":"venue"
},
  "geometry": {"coordinates":[-5.3179550171,37.2224159241],"type":"Point"}
}