{
  "type": "Feature",
  "properties": {
    "iso:country":"ES",
    "sg:address":"Av Baix Camp, S/n",
    "sg:city":"Cambrils",
    "sg:orig_category":"Cerrajer\u00cda, Ferrallista",
    "sg:phone":"+34 977 79 43 70",
    "sg:postcode":"43850",
    "sg:province":"Tarragona",
    "wof:name":"Abad Cerrajeros S.l.",
    "wof:placetype":"venue"
},
  "geometry": {"coordinates":[1.05517,41.072605],"type":"Point"}
}