{
  "type": "Feature",
  "properties": {
    "addr:full":"Carr De La Mare De Deu Del Pilar, 2 Benicarlo Castell\u00f3n 12580",
    "addr:housenumber":"2",
    "addr:postcode":"12580",
    "addr:street":"Carr De La Mare De Deu Del Pilar",
    "iso:country":"ES",
    "sg:address":"Carr De La Mare De Deu Del Pilar, 2",
    "sg:city":"Benicarlo",
    "sg:orig_category":"Ropa Para Ni\u00d1os (al Por Menor)",
    "sg:phone":"+34 964 46 18 20",
    "sg:postcode":"12580",
    "sg:province":"Castell\u00f3n",
    "wof:name":"Masip Moros Ana Maria",
    "wof:placetype":"venue"
},
  "geometry": {"coordinates":[0.4251340032,40.419631958],"type":"Point"}
}