{
  "type": "Feature",
  "properties": {
    "addr:full":"Ctra Bruc-manresa, Km. 0014,0 Salelles Barcelona 08253",
    "addr:postcode":"08253",
    "addr:street":"Ctra Bruc-Manresa Km. 0014,0 Salelles Barcelona",
    "iso:country":"ES",
    "sg:address":"Ctra Bruc-manresa, Km. 0014,0",
    "sg:city":"Salelles",
    "sg:orig_category":"Higiene, Belleza: Art\u00cdculos (al Por Menor)",
    "sg:phone":"+34 938 35 81 61",
    "sg:postcode":"08253",
    "sg:province":"Barcelona",
    "wof:name":"Ortepedia Y Cirugia S.l.",
    "wof:placetype":"venue"
},
  "geometry": {"coordinates":[1.7656999826,41.6832809448],"type":"Point"}
}