{
  "type": "Feature",
  "properties": {
    "addr:full":"Calle de Barco, 23 Madrid Madrid 28004",
    "addr:housenumber":"23",
    "addr:postcode":"madrid;28004",
    "addr:street":"Calle De Barco",
    "iso:country":"ES",
    "sg:address":"Calle de Barco, 23",
    "sg:city":"Madrid",
    "sg:orig_category":"Fabricaci\u00d3n, Importaci\u00d3n De L\u00c1mparas Y Bombillas",
    "sg:phone":"+34 915 22 50 77",
    "sg:postcode":"28004",
    "sg:province":"Madrid",
    "wof:name":"Cespedes Alvarez Jose",
    "wof:placetype":"venue"
},
  "geometry": {"coordinates":[-3.7026512623,40.4220199585],"type":"Point"}
}