{
  "type": "Feature",
  "properties": {
    "iso:country":"ES",
    "sg:address":"Calle de Fernan Caballero, 3",
    "sg:city":"Mairena Alcor",
    "sg:orig_category":"Mec\u00c1nico Del Autom\u00d3vil",
    "sg:phone":"+34 955 74 61 85",
    "sg:postcode":"41510",
    "sg:province":"Sevilla",
    "wof:name":"Galocha Dominguez Antonio",
    "wof:placetype":"venue"
},
  "geometry": {"coordinates":[-5.7494239807,37.3754272461],"type":"Point"}
}