{
  "type": "Feature",
  "properties": {
    "iso:country":"ES",
    "sg:address":"Poli Mugitegi-e, 16",
    "sg:city":"Urretxu",
    "sg:orig_category":"Empresas De Carpinter\u00cda Met\u00c1lica",
    "sg:phone":"+34 943 72 53 15",
    "sg:postcode":"20700",
    "sg:province":"Guip\u00f9zcoa",
    "sg:website":"www.aluminiosgoierri.com",
    "wof:name":"Aluminios Goierri S.l.",
    "wof:placetype":"venue"
},
  "geometry": {"coordinates":[-2.3134770393,43.086730957],"type":"Point"}
}