{
  "type": "Feature",
  "properties": {
    "iso:country":"ES",
    "sg:address":"Calle de Federico Ozanan, 79",
    "sg:city":"Zaragoza",
    "sg:orig_category":"M\u00c9dicos: Estomatolog\u00cda",
    "sg:phone":"+34 976 75 56 22",
    "sg:postcode":"50012",
    "sg:province":"Zaragoza",
    "wof:name":"Cardenas Quiroz Margarita",
    "wof:placetype":"venue"
},
  "geometry": {"coordinates":[-0.9347609878,41.6404953003],"type":"Point"}
}