{
  "type": "Feature",
  "properties": {
    "iso:country":"ES",
    "sg:address":"Rua Balorca (a), 3",
    "sg:city":"Barco",
    "sg:orig_category":"Alquiler De V\u00cddeo",
    "sg:phone":"+34 988 34 70 34",
    "sg:postcode":"32300",
    "sg:province":"Ourense",
    "wof:name":"Mesa Delgado Milagros",
    "wof:placetype":"venue"
},
  "geometry": {"coordinates":[-6.9839119911,42.4167251587],"type":"Point"}
}