{
  "type": "Feature",
  "properties": {
    "iso:country":"ES",
    "sg:address":"Calle de Velazquez, 5",
    "sg:city":"Madrid",
    "sg:orig_category":"Agencias Y Agentes Comerciales, Representantes",
    "sg:phone":"+34 915 75 94 00",
    "sg:postcode":"28001",
    "sg:province":"Madrid",
    "wof:name":"Hernandez Gonzalez Carolina Francisca",
    "wof:placetype":"venue"
},
  "geometry": {"coordinates":[-3.6845788956,40.4215240479],"type":"Point"}
}