{
  "type": "Feature",
  "properties": {
    "addr:full":"Pl Manuel Montanya, 2 Granollers Barcelona 08401",
    "addr:housenumber":"2",
    "addr:postcode":"08401",
    "addr:street":"Pl Manuel Montanya",
    "iso:country":"ES",
    "sg:address":"Pl Manuel Montanya, 2",
    "sg:city":"Granollers",
    "sg:orig_category":"Sindicatos Y Colegios Profesionales",
    "sg:phone":"+34 938 79 31 47",
    "sg:postcode":"08401",
    "sg:province":"Barcelona",
    "wof:name":"Bisu-art Granollers S.c.p.",
    "wof:placetype":"venue"
},
  "geometry": {"coordinates":[2.2872099876,41.6078491211],"type":"Point"}
}