{
  "type": "Feature",
  "properties": {
    "addr:full":"Calle de San Millan, 7 Malaga M\u00e1laga 29013",
    "addr:housenumber":"7",
    "addr:postcode":"29013",
    "addr:street":"Calle De San Millan;Ma\u0301Laga",
    "iso:country":"ES",
    "sg:address":"Calle de San Millan, 7",
    "sg:city":"Malaga",
    "sg:orig_category":"Agencias Y Asesores De Publicidad",
    "sg:phone":"+34 952 21 51 81",
    "sg:postcode":"29013",
    "sg:province":"M\u00e1laga",
    "wof:name":"Eventos J.b. Costa S.l.",
    "wof:placetype":"venue"
},
  "geometry": {"coordinates":[-4.4203090668,36.727355957],"type":"Point"}
}