{
  "type": "Feature",
  "properties": {
    "addr:full":"Calle de General Vives, 2 Palmas De Gran Canaria Las Palmas 35006",
    "addr:housenumber":"2",
    "addr:postcode":"35006",
    "addr:street":"Calle De General Vives",
    "iso:country":"ES",
    "sg:address":"Calle de General Vives, 2",
    "sg:city":"Palmas De Gran Canaria",
    "sg:orig_category":"Abogados",
    "sg:phone":"+34 928 29 54 04",
    "sg:postcode":"35006",
    "sg:province":"Las Palmas",
    "wof:name":"Bra\u00f1a Nogueira Julia",
    "wof:placetype":"venue"
},
  "geometry": {"coordinates":[-15.431552887,28.1403751373],"type":"Point"}
}