{
  "type": "Feature",
  "properties": {
    "iso:country":"ES",
    "sg:address":"Avda Compostela, 53",
    "sg:city":"Palas Rei",
    "sg:orig_category":"Empresarios",
    "sg:phone":"+34 982 37 41 31",
    "sg:postcode":"27200",
    "sg:province":"Lugo",
    "wof:name":"Fundacion Para O Desenvolvemento Da Comarca De A Ulloa",
    "wof:placetype":"venue"
},
  "geometry": {"coordinates":[-7.8687338829,42.8742141724],"type":"Point"}
}