{
  "type": "Feature",
  "properties": {
    "addr:full":"Carrer de Fra Juniper Serra, 77 Barcelona Barcelona 08030",
    "addr:housenumber":"77",
    "addr:postcode":"08030",
    "addr:street":"Carrer De Fra Juniper Serra",
    "iso:country":"ES",
    "sg:address":"Carrer de Fra Juniper Serra, 77",
    "sg:city":"Barcelona",
    "sg:orig_category":"Calderer\u00cda",
    "sg:phone":"+34 933 05 41 54",
    "sg:postcode":"08030",
    "sg:province":"Barcelona",
    "wof:name":"Pramar S.c.p.",
    "wof:placetype":"venue"
},
  "geometry": {"coordinates":[2.203099966,41.4334602356],"type":"Point"}
}