{
  "type": "Feature",
  "properties": {
    "iso:country":"ES",
    "sg:address":"Calle de Condes De Gomara, 8",
    "sg:city":"Soria",
    "sg:orig_category":"Carnicer\u00cdas, Carnicer\u00cdas",
    "sg:phone":"+34 975 22 48 70",
    "sg:postcode":"42004",
    "sg:province":"Soria",
    "wof:name":"Chico Lopez Alejandro",
    "wof:placetype":"venue"
},
  "geometry": {"coordinates":[-2.4633786678,41.7658462524],"type":"Point"}
}