{
  "type": "Feature",
  "properties": {
    "iso:country":"ES",
    "sg:address":"Vid, 3",
    "sg:city":"Rivas Vaciamadrid",
    "sg:orig_category":"Fisioterapia",
    "sg:phone":"+34 914 99 28 84",
    "sg:postcode":"28529",
    "sg:province":"Madrid",
    "wof:name":"Abulaji Toledano Watan",
    "wof:placetype":"venue"
},
  "geometry": {"coordinates":[-3.529789,40.353405],"type":"Point"}
}