{
  "type": "Feature",
  "properties": {
    "addr:full":"Calle de Maestro Mandos, 4 Novelda Alicante 03660",
    "addr:housenumber":"4",
    "addr:postcode":"03660",
    "addr:street":"Calle De Maestro Mandos",
    "iso:country":"ES",
    "sg:address":"Calle de Maestro Mandos, 4",
    "sg:city":"Novelda",
    "sg:orig_category":"Servicios De Higiene Y Peluquer\u00cda Para Perros Y Gatos",
    "sg:phone":"+34 965 60 24 19",
    "sg:postcode":"03660",
    "sg:province":"Alicante",
    "wof:name":"Martinez Navarro Remedios",
    "wof:placetype":"venue"
},
  "geometry": {"coordinates":[-0.7688689828,38.3906745911],"type":"Point"}
}