{
  "type": "Feature",
  "properties": {
    "addr:full":"Calle de Ramon Franco, 31 Arzua La Coru\u00f1a 15810",
    "addr:housenumber":"31",
    "addr:postcode":"15810",
    "addr:street":"Calle De Ramon Franco;La Corun\u0303A",
    "iso:country":"ES",
    "sg:address":"Calle de Ramon Franco, 31",
    "sg:city":"Arzua",
    "sg:orig_category":"Farmacias",
    "sg:phone":"+34 981 50 00 58",
    "sg:postcode":"15810",
    "sg:province":"La Coru\u00f1a",
    "wof:name":"Saavedra Pereira Manuel Angel",
    "wof:placetype":"venue"
},
  "geometry": {"coordinates":[-8.1639232635,42.9282455444],"type":"Point"}
}