{
  "type": "Feature",
  "properties": {
    "iso:country":"ES",
    "sg:address":"Plce Cruz De Piedra (de La), 2",
    "sg:city":"Granada",
    "sg:orig_category":"Internados & Ense\u00d1anza Privada",
    "sg:phone":"+34 958 29 14 09",
    "sg:postcode":"18010",
    "sg:province":"Granada",
    "wof:name":"Colegio En Granada Misioneras Del Divino Maestro",
    "wof:placetype":"venue"
},
  "geometry": {"coordinates":[-3.5915300846,37.1868934631],"type":"Point"}
}