{
  "type": "Feature",
  "properties": {
    "iso:country":"ES",
    "sg:address":"C/ Hermanos Navarro Caracena, 109",
    "sg:city":"Elche",
    "sg:orig_category":"Molduras, Junquillos, Listones Y Molduras Perforadas",
    "sg:phone":"+34 965 44 81 62",
    "sg:postcode":"03206",
    "sg:province":"Alicante",
    "wof:name":"Marin Garcia Fernando",
    "wof:placetype":"venue"
},
  "geometry": {"coordinates":[-0.7117189765,38.2765541077],"type":"Point"}
}