{
  "type": "Feature",
  "properties": {
    "addr:full":"Carrer de Ramon De Terrades, 2 Vic Barcelona 08500",
    "addr:housenumber":"2",
    "addr:postcode":"08500",
    "addr:street":"Carrer De Ramon De Terrades",
    "iso:country":"ES",
    "sg:address":"Carrer de Ramon De Terrades, 2",
    "sg:city":"Vic",
    "sg:orig_category":"Abogados",
    "sg:phone":"+34 938 85 41 59",
    "sg:postcode":"08500",
    "sg:province":"Barcelona",
    "wof:name":"Orozco Pardo Emilio",
    "wof:placetype":"venue"
},
  "geometry": {"coordinates":[2.250041008,41.9280776978],"type":"Point"}
}