{
  "type": "Feature",
  "properties": {
    "iso:country":"ES",
    "sg:address":"Calle de Batalla Arapiles, 30",
    "sg:city":"Arapiles",
    "sg:orig_category":"Reposter\u00cdas",
    "sg:phone":"+34 923 28 87 81",
    "sg:postcode":"37796",
    "sg:province":"Salamanca",
    "wof:name":"Marcos Hernandez Nemesio",
    "wof:placetype":"venue"
},
  "geometry": {"coordinates":[-5.6454930305,40.8936538696],"type":"Point"}
}