{
  "type": "Feature",
  "properties": {
    "addr:full":"Cno Catral, S/n Granja Rocamora Alicante 03348",
    "addr:housenumber":"s / n",
    "addr:postcode":"03348",
    "addr:street":"Cno Catral",
    "iso:country":"ES",
    "sg:address":"Cno Catral, S/n",
    "sg:city":"Granja Rocamora",
    "sg:orig_category":"Confecci\u00d3n De Zapatos",
    "sg:phone":"+34 965 36 04 05",
    "sg:postcode":"03348",
    "sg:province":"Alicante",
    "wof:name":"Vuldani S.l.",
    "wof:placetype":"venue"
},
  "geometry": {"coordinates":[-0.8836004138,38.1414222717],"type":"Point"}
}