{
  "type": "Feature",
  "properties": {
    "iso:country":"ES",
    "sg:address":"Calle de Astorga, 18",
    "sg:city":"Fuenlabrada",
    "sg:orig_category":"Fabricaci\u00d3n De Moldes Y Modelos",
    "sg:phone":"+34 916 42 00 03",
    "sg:postcode":"28947",
    "sg:province":"Madrid",
    "wof:name":"Jimenez Gonzalez Isidro",
    "wof:placetype":"venue"
},
  "geometry": {"coordinates":[-3.747150898,40.2624931335],"type":"Point"}
}