{
  "type": "Feature",
  "properties": {
    "addr:full":"Calle de Doctor Bonardell, 30 Alcazar S. Juan Ciudad Real 13600",
    "addr:housenumber":"30",
    "addr:postcode":"13600",
    "addr:street":"Calle De Doctor Bonardell;Alcazar S. Juan Ciudad Real",
    "iso:country":"ES",
    "sg:address":"Calle de Doctor Bonardell, 30",
    "sg:city":"Alcazar S. Juan",
    "sg:orig_category":"Restaurantes",
    "sg:phone":"+34 926 54 10 19",
    "sg:postcode":"13600",
    "sg:province":"Ciudad Real",
    "wof:name":"Fercotel Explotacion De Telefonos Publicos S.l.",
    "wof:placetype":"venue"
},
  "geometry": {"coordinates":[-3.2123727798,39.3892631531],"type":"Point"}
}