{
  "type": "Feature",
  "properties": {
    "addr:full":"Rua Ramon Cabanillas, 18 Acea De Ama La Coru\u00f1a 15670",
    "addr:housenumber":"18",
    "addr:postcode":"15670",
    "addr:street":"Rua Ramon Cabanillas;Corun\u0303A",
    "iso:country":"ES",
    "sg:address":"Rua Ramon Cabanillas, 18",
    "sg:city":"Acea De Ama",
    "sg:orig_category":"Delegados, Agentes De Tr\u00c1nsito, Auxiliares De Transporte Internacional",
    "sg:phone":"+34 981 66 22 52",
    "sg:postcode":"15670",
    "sg:province":"La Coru\u00f1a",
    "wof:name":"Cantabrica Ugente S.l.",
    "wof:placetype":"venue"
},
  "geometry": {"coordinates":[-8.3809137344,43.32447052],"type":"Point"}
}