{
  "type": "Feature",
  "properties": {
    "iso:country":"ES",
    "sg:address":"Pg. E. Prat Riba, 57",
    "sg:city":"El Masnou",
    "sg:orig_category":"Empresarios Y Productoras De Espect\u00c1culos",
    "sg:phone":"+34 935 40 39 90",
    "sg:postcode":"08320",
    "sg:province":"Barcelona",
    "wof:name":"Eina D'escola S.l.",
    "wof:placetype":"venue"
},
  "geometry": {"coordinates":[2.3180449009,41.4787750244],"type":"Point"}
}