{
  "type": "Feature",
  "properties": {
    "addr:full":"Calle de Maria Paya, 14 Biar Alicante 03410",
    "addr:housenumber":"14",
    "addr:postcode":"03410",
    "addr:street":"Calle De Maria Paya",
    "iso:country":"ES",
    "sg:address":"Calle de Maria Paya, 14",
    "sg:city":"Biar",
    "sg:orig_category":"Panader\u00cdas, Panader\u00cdas",
    "sg:phone":"+34 965 81 13 84",
    "sg:postcode":"03410",
    "sg:province":"Alicante",
    "wof:name":"D'erfon Cb",
    "wof:placetype":"venue"
},
  "geometry": {"coordinates":[-0.7647950053,38.628704071],"type":"Point"}
}