{
  "type": "Feature",
  "properties": {
    "addr:full":"Pase Barquera, S/n S. Vicente Barquera Cantabria 39540",
    "addr:housenumber":"s",
    "addr:postcode":"39540",
    "addr:street":"Barquera;/ N S. Vicente",
    "iso:country":"ES",
    "sg:address":"Pase Barquera, S/n",
    "sg:city":"S. Vicente Barquera",
    "sg:classifiers":[
        {
            "category":"Recreation",
            "type":"Entertainment"
        }
    ],
    "sg:phone":"+34 942 71 02 36",
    "sg:postcode":"39540",
    "sg:province":"Cantabria",
    "sg:tags":[
        "caza",
        "pr\u00c1ctica",
        "la",
        "de",
        "pesca",
        "y"
    ],
    "wof:name":"Cofradia De Pescadores",
    "wof:placetype":"venue"
},
  "geometry": {"coordinates":[-4.3995471001,43.3842964172],"type":"Point"}
}