{
  "type": "Feature",
  "properties": {
    "iso:country":"ES",
    "sg:address":"Avda Antonio Correa, 9",
    "sg:city":"Badajoz",
    "sg:orig_category":"Producci\u00d3n, Venta De Productos De Agricultura Biol\u00d3gica",
    "sg:phone":"+34 924 27 05 00",
    "sg:postcode":"06006",
    "sg:province":"Badajoz",
    "wof:name":"Extreme\u00f1o Aragonesa Agricola S. A.",
    "wof:placetype":"venue"
},
  "geometry": {"coordinates":[-6.9891691208,38.8922080994],"type":"Point"}
}