{
  "type": "Feature",
  "properties": {
    "iso:country":"ES",
    "sg:address":"Avda Playas (las), 37",
    "sg:city":"Puerto Del Carmen",
    "sg:orig_category":"Bazares, Art\u00cdculos De Limpieza Y De Cocina (al Por Menor)",
    "sg:phone":"+34 928 51 04 73",
    "sg:postcode":"35510",
    "sg:province":"Las Palmas",
    "wof:name":"Xueping  Xiao",
    "wof:placetype":"venue"
},
  "geometry": {"coordinates":[-13.6397809982,28.9244537354],"type":"Point"}
}