{
  "type": "Feature",
  "properties": {
    "iso:country":"ES",
    "sg:address":"Calle de Pe\u00d1a Bejo, 8",
    "sg:city":"Santander",
    "sg:orig_category":"Electricidad: Equipos Industriales, Componentes (fabricaci\u00d3n)",
    "sg:phone":"+34 942 35 50 07",
    "sg:postcode":"39011",
    "sg:province":"Cantabria",
    "wof:name":"Comercial Hispanofil S.a.",
    "wof:placetype":"venue"
},
  "geometry": {"coordinates":[-3.8342409134,43.4463844299],"type":"Point"}
}