{
  "type": "Feature",
  "properties": {
    "addr:full":"Avda Monteazahar, 3 Beniajan Murcia 30570",
    "addr:housenumber":"3",
    "addr:postcode":"30570",
    "addr:street":"Avda Monteazahar",
    "iso:country":"ES",
    "sg:address":"Avda Monteazahar, 3",
    "sg:city":"Beniajan",
    "sg:orig_category":"Zapatos (al Por Menor)",
    "sg:phone":"+34 968 83 72 15",
    "sg:postcode":"30570",
    "sg:province":"Murcia",
    "wof:name":"Navarro Andreu Maria Isabel",
    "wof:placetype":"venue"
},
  "geometry": {"coordinates":[-1.0705649853,37.9736289978],"type":"Point"}
}