{
  "type": "Feature",
  "properties": {
    "iso:country":"ES",
    "sg:address":"Carr Prat De La Riba, 126",
    "sg:city":"Juneda",
    "sg:orig_category":"Material Y Herramientas Agr\u00cdcolas",
    "sg:phone":"+34 973 15 01 47",
    "sg:postcode":"25430",
    "sg:province":"Lleida",
    "wof:name":"Serveis I Anivellacions Germans Gelonch S.l.",
    "wof:placetype":"venue"
},
  "geometry": {"coordinates":[0.8235899806,41.548084259],"type":"Point"}
}