{
  "type": "Feature",
  "properties": {
    "iso:country":"ES",
    "sg:address":"Calle de Cobos De Segovia, 5",
    "sg:city":"Madrid",
    "sg:orig_category":"Agencias Y Asesores De Publicidad",
    "sg:phone":"+34 913 65 11 10",
    "sg:postcode":"28005",
    "sg:province":"Madrid",
    "wof:name":"Pintado Perez Daniel",
    "wof:placetype":"venue"
},
  "geometry": {"coordinates":[-3.7191874981,40.4062156677],"type":"Point"}
}