{
  "type": "Feature",
  "properties": {
    "addr:full":"Calle de Donoso Cortes, 68 Madrid Madrid 28015",
    "addr:housenumber":"68",
    "addr:postcode":"madrid;28015",
    "addr:street":"Calle De Donoso Cortes",
    "iso:country":"ES",
    "sg:address":"Calle de Donoso Cortes, 68",
    "sg:city":"Madrid",
    "sg:orig_category":"Urbanistas",
    "sg:phone":"+34 915 44 44 42",
    "sg:postcode":"28015",
    "sg:province":"Madrid",
    "wof:name":"Ruiz Albusac Isicio",
    "wof:placetype":"venue"
},
  "geometry": {"coordinates":[-3.7133851051,40.4365386963],"type":"Point"}
}