{
  "type": "Feature",
  "properties": {
    "addr:full":"Calle de Juan De Austria (don), 11 Socuellamos Ciudad Real 13630",
    "addr:housenumber":"11",
    "addr:postcode":"13630",
    "addr:street":"Calle De Juan De Austria Don",
    "iso:country":"ES",
    "sg:address":"Calle de Juan De Austria (don), 11",
    "sg:city":"Socuellamos",
    "sg:orig_category":"Bares, Piano",
    "sg:phone":"+34 926 53 09 89",
    "sg:postcode":"13630",
    "sg:province":"Ciudad Real",
    "wof:name":"Toribio Alcolea Emilia",
    "wof:placetype":"venue"
},
  "geometry": {"coordinates":[-2.7944865227,39.2857666016],"type":"Point"}
}