{
  "type": "Feature",
  "properties": {
    "iso:country":"ES",
    "sg:address":"Calle de Nueva, 47",
    "sg:city":"Motril",
    "sg:orig_category":"Florister\u00cdas",
    "sg:phone":"+34 958 60 82 48",
    "sg:postcode":"18600",
    "sg:province":"Granada",
    "wof:name":"Ruiz Lopez Manuel",
    "wof:placetype":"venue"
},
  "geometry": {"coordinates":[-3.5181660652,36.7475662231],"type":"Point"}
}