{
  "type": "Feature",
  "properties": {
    "addr:full":"Calle de Granja (de La), 17 Arganda Madrid 28500",
    "addr:housenumber":"17",
    "addr:postcode":"28500",
    "addr:street":"Calle De Granja De La",
    "iso:country":"ES",
    "sg:address":"Calle de Granja (de La), 17",
    "sg:city":"Arganda",
    "sg:orig_category":"Embalajes",
    "sg:phone":"+34 918 71 65 13",
    "sg:postcode":"28500",
    "sg:province":"Madrid",
    "wof:name":"Embalajes Cui S.l.",
    "wof:placetype":"venue"
},
  "geometry": {"coordinates":[-3.4406979084,40.2999954224],"type":"Point"}
}