{
  "type": "Feature",
  "properties": {
    "iso:country":"ES",
    "sg:address":"Ptge Llobateras, 12",
    "sg:city":"Rubi",
    "sg:orig_category":"Telas Y Sedas (al Por Menor)",
    "sg:phone":"+34 935 88 61 80",
    "sg:postcode":"08191",
    "sg:province":"Barcelona",
    "wof:name":"Martinez Soler Remedios",
    "wof:placetype":"venue"
},
  "geometry": {"coordinates":[2.035736084,41.4895591736],"type":"Point"}
}