{
  "type": "Feature",
  "properties": {
    "iso:country":"ES",
    "sg:address":"Calle de Manuel De Falla, 22",
    "sg:city":"Motril",
    "sg:orig_category":"Librer\u00cdas",
    "sg:phone":"+34 958 60 59 98",
    "sg:postcode":"18600",
    "sg:province":"Granada",
    "wof:name":"Rubia Caparros Rosario",
    "wof:placetype":"venue"
},
  "geometry": {"coordinates":[-3.5137360096,36.7456321716],"type":"Point"}
}