{
  "type": "Feature",
  "properties": {
    "iso:country":"ES",
    "sg:address":"Calle de Argentina, 4",
    "sg:city":"Bailen",
    "sg:orig_category":"Mec\u00c1nico Del Autom\u00d3vil",
    "sg:phone":"+34 953 67 15 56",
    "sg:postcode":"23710",
    "sg:province":"Ja\u00e9n",
    "wof:name":"Roque Carmona Francisco",
    "wof:placetype":"venue"
},
  "geometry": {"coordinates":[-3.7701978683,38.097114563],"type":"Point"}
}