{
  "type": "Feature",
  "properties": {
    "iso:country":"ES",
    "sg:address":"Av Moli, 52",
    "sg:city":"Viladecans",
    "sg:orig_category":"Empresas De Carpinter\u00cda",
    "sg:phone":"+34 936 59 14 63",
    "sg:postcode":"08840",
    "sg:province":"Barcelona",
    "wof:name":"Gonzalez Martin Sebastian",
    "wof:placetype":"venue"
},
  "geometry": {"coordinates":[2.0101220608,41.3219642639],"type":"Point"}
}