{
  "type": "Feature",
  "properties": {
    "addr:full":"Calle de Santa Rita, 21 San Jose Rinconada Sevilla 41300",
    "addr:housenumber":"21",
    "addr:postcode":"41300",
    "addr:street":"Calle De Santa Rita",
    "iso:country":"ES",
    "sg:address":"Calle de Santa Rita, 21",
    "sg:city":"San Jose Rinconada",
    "sg:orig_category":"Mercer\u00cda, Lencer\u00cda (al Por Menor)",
    "sg:phone":"+34 954 79 28 13",
    "sg:postcode":"41300",
    "sg:province":"Sevilla",
    "wof:name":"Herrero Herrero Manuel",
    "wof:placetype":"venue"
},
  "geometry": {"coordinates":[-5.9417738914,37.4849281311],"type":"Point"}
}