{
  "type": "Feature",
  "properties": {
    "addr:full":"Carrer de Segle Xx, 16 Barcelona Barcelona 08041",
    "addr:housenumber":"16",
    "addr:postcode":"08041",
    "addr:street":"Carrer De Segle Xx",
    "iso:country":"ES",
    "sg:address":"Carrer de Segle Xx, 16",
    "sg:city":"Barcelona",
    "sg:orig_category":"Agentes, Concesionarios Y Sucursales De Veh\u00cdculos",
    "sg:phone":"+34 902 19 91 98",
    "sg:postcode":"08041",
    "sg:province":"Barcelona",
    "wof:name":"Lema Cars S.l.",
    "wof:placetype":"venue"
},
  "geometry": {"coordinates":[2.1780180931,41.422744751],"type":"Point"}
}