{
  "type": "Feature",
  "properties": {
    "addr:full":"Carrer de Carretera Marina, 11 Prat Llobregat Barcelona 08820",
    "addr:housenumber":"11",
    "addr:postcode":"08820",
    "addr:street":"Carrer De Carretera Marina;Llobregat",
    "iso:country":"ES",
    "sg:address":"Carrer de Carretera Marina, 11",
    "sg:city":"Prat Llobregat",
    "sg:orig_category":"Bazares, Art\u00cdculos De Limpieza Y De Cocina (al Por Menor)",
    "sg:phone":"+34 933 74 16 40",
    "sg:postcode":"08820",
    "sg:province":"Barcelona",
    "wof:name":"Alba Calera Francisco Javier",
    "wof:placetype":"venue"
},
  "geometry": {"coordinates":[2.101755619,41.3247947693],"type":"Point"}
}