{
  "type": "Feature",
  "properties": {
    "addr:full":"Calle de Iglesia, 4 Berge Teruel 44556",
    "addr:housenumber":"4",
    "addr:postcode":"44556",
    "addr:street":"Calle De Iglesia",
    "iso:country":"ES",
    "sg:address":"Calle de Iglesia, 4",
    "sg:city":"Berge",
    "sg:orig_category":"Frutas, Legumbres Frescas Y Tempranas (al Por Menor)",
    "sg:phone":"+34 978 84 90 68",
    "sg:postcode":"44556",
    "sg:province":"Teruel",
    "wof:name":"Orta Balaguer Josefina",
    "wof:placetype":"venue"
},
  "geometry": {"coordinates":[-0.4273990095,40.8571205139],"type":"Point"}
}