{
  "type": "Feature",
  "properties": {
    "iso:country":"ES",
    "sg:address":"Calle de Burgos, 2",
    "sg:city":"Valverde Camino",
    "sg:orig_category":"Reposter\u00cdas",
    "sg:phone":"+34 959 55 08 96",
    "sg:postcode":"21600",
    "sg:province":"Huelva",
    "wof:name":"Panaderia Perez Prados",
    "wof:placetype":"venue"
},
  "geometry": {"coordinates":[-6.7611160278,37.5769844055],"type":"Point"}
}