{
  "type": "Feature",
  "properties": {
    "iso:country":"ES",
    "sg:address":"Pol Ind Polysol, S/n",
    "sg:city":"Alcala Guadaira",
    "sg:orig_category":"Agencias De Relaciones P\u00dablicas",
    "sg:phone":"+34 955 62 03 90",
    "sg:postcode":"41500",
    "sg:province":"Sevilla",
    "sg:website":"www.edgdc.com",
    "wof:name":"Empresa Publica De Gestion De Programas Y Actividades",
    "wof:placetype":"venue"
},
  "geometry": {"coordinates":[-5.8398590088,37.3383140564],"type":"Point"}
}