{
  "type": "Feature",
  "properties": {
    "iso:country":"ES",
    "sg:address":"Plaz Constitucion, 2",
    "sg:city":"Berja",
    "sg:orig_category":"Bancos",
    "sg:phone":"+34 950 49 00 11",
    "sg:postcode":"04760",
    "sg:province":"Almer\u00eda",
    "sg:website":"wwww.banesto.es",
    "wof:name":"Banco Espa\u00f1ol De Credito S.a.",
    "wof:placetype":"venue"
},
  "geometry": {"coordinates":[-2.9501290321,36.8471107483],"type":"Point"}
}