{
  "type": "Feature",
  "properties": {
    "iso:country":"ES",
    "sg:address":"Carrer de Ferlandina, 53",
    "sg:city":"Barcelona",
    "sg:orig_category":"Arquitectos",
    "sg:phone":"+34 933 24 96 10",
    "sg:postcode":"08001",
    "sg:province":"Barcelona",
    "wof:name":"Distrito V S.c.p.",
    "wof:placetype":"venue"
},
  "geometry": {"coordinates":[2.165115118,41.3816223145],"type":"Point"}
}