{
  "type": "Feature",
  "properties": {
    "addr:full":"Calle de Juan Bravo, 55 Madrid Madrid 28006",
    "addr:housenumber":"55",
    "addr:postcode":"madrid;28006",
    "addr:street":"Calle De Juan Bravo",
    "iso:country":"ES",
    "sg:address":"Calle de Juan Bravo, 55",
    "sg:city":"Madrid",
    "sg:orig_category":"Mercer\u00cda, Lencer\u00cda (al Por Menor)",
    "sg:phone":"+34 913 09 38 33",
    "sg:postcode":"28006",
    "sg:province":"Madrid",
    "wof:name":"Vega Benitez Diego Francisco",
    "wof:placetype":"venue"
},
  "geometry": {"coordinates":[-3.6748149395,40.4326095581],"type":"Point"}
}