{
  "type": "Feature",
  "properties": {
    "addr:full":"Calle de Ignacio Martinez De Azcoitia, 21 Palencia Palencia 34001",
    "addr:housenumber":"21",
    "addr:postcode":"34001",
    "addr:street":"Calle De Ignacio Martinez De Azcoitia",
    "iso:country":"ES",
    "sg:address":"Calle de Ignacio Martinez De Azcoitia, 21",
    "sg:city":"Palencia",
    "sg:orig_category":"Abogados",
    "sg:phone":"+34 979 74 23 33",
    "sg:postcode":"34001",
    "sg:province":"Palencia",
    "sg:website":"www.paginasamarillas.es",
    "wof:name":"Marcos Marina Leopoldo",
    "wof:placetype":"venue"
},
  "geometry": {"coordinates":[-4.5309858322,42.0120620728],"type":"Point"}
}