{
  "type": "Feature",
  "properties": {
    "addr:full":"Ctra. Portugal, S/n Badajoz Badajoz 06006",
    "addr:housenumber":"s / n",
    "addr:postcode":"06006",
    "addr:street":"Ctra. Portugal",
    "iso:country":"ES",
    "sg:address":"Ctra. Portugal, S/n",
    "sg:city":"Badajoz",
    "sg:orig_category":"Electricidad, Electr\u00d3nica: Suministros (al Por Menor)",
    "sg:phone":"+34 924 27 51 18",
    "sg:postcode":"06006",
    "sg:province":"Badajoz",
    "sg:website":"www.philips.es",
    "wof:name":"Philips Iberica S.a.",
    "wof:placetype":"venue"
},
  "geometry": {"coordinates":[-7.038225174,38.9151191711],"type":"Point"}
}