{
  "type": "Feature",
  "properties": {
    "addr:full":"Carr Princep De Bergara, 40 Badalona Barcelona 08912",
    "addr:housenumber":"40",
    "addr:postcode":"08912",
    "addr:street":"Carr Princep De Bergara",
    "iso:country":"ES",
    "sg:address":"Carr Princep De Bergara, 40",
    "sg:city":"Badalona",
    "sg:orig_category":"Cristaler\u00cdas",
    "sg:phone":"+34 934 64 09 47",
    "sg:postcode":"08912",
    "sg:province":"Barcelona",
    "wof:name":"Crisba S. L.",
    "wof:placetype":"venue"
},
  "geometry": {"coordinates":[2.2420349121,41.4453277588],"type":"Point"}
}