{
  "type": "Feature",
  "properties": {
    "iso:country":"ES",
    "sg:address":"Trav De Gracia, 251",
    "sg:city":"Barcelona",
    "sg:orig_category":"M\u00c9dicos: Naturistas",
    "sg:phone":"+34 932 13 64 64",
    "sg:postcode":"08024",
    "sg:province":"Barcelona",
    "wof:name":"Jimenez Carrasco Maria Elena",
    "wof:placetype":"venue"
},
  "geometry": {"coordinates":[2.1624100208,41.4044113159],"type":"Point"}
}