{
  "type": "Feature",
  "properties": {
    "addr:full":"Avda San Juan El Real, 22 Calatayud Zaragoza 50300",
    "addr:housenumber":"22",
    "addr:postcode":"50300",
    "addr:street":"Avda San Juan El Real",
    "iso:country":"ES",
    "sg:address":"Avda San Juan El Real, 22",
    "sg:city":"Calatayud",
    "sg:orig_category":"Librer\u00cdas",
    "sg:phone":"+34 976 89 72 80",
    "sg:postcode":"50300",
    "sg:province":"Zaragoza",
    "wof:name":"Kai Futuro S.l.l.",
    "wof:placetype":"venue"
},
  "geometry": {"coordinates":[-1.6435890198,41.3526916504],"type":"Point"}
}