{
  "type": "Feature",
  "properties": {
    "addr:full":"Carr Forn De La Cal\u00c7, 13 Blanes Girona 17300",
    "addr:housenumber":"13",
    "addr:postcode":"17300",
    "addr:street":"Carr Forn De La Calc\u0327",
    "iso:country":"ES",
    "sg:address":"Carr Forn De La Cal\u00c7, 13",
    "sg:city":"Blanes",
    "sg:orig_category":"Institutos De Belleza",
    "sg:phone":"+34 972 33 35 18",
    "sg:postcode":"17300",
    "sg:province":"Girona",
    "wof:name":"Salvador Nicart Montserrat",
    "wof:placetype":"venue"
},
  "geometry": {"coordinates":[2.7906849384,41.6724243164],"type":"Point"}
}