{
  "type": "Feature",
  "properties": {
    "iso:country":"ES",
    "sg:address":"Calle de Castillo, 25",
    "sg:city":"Campo Criptana",
    "sg:orig_category":"Ropa Para Se\u00d1oras (al Por Menor)",
    "sg:phone":"+34 926 56 11 63",
    "sg:postcode":"13610",
    "sg:province":"Ciudad Real",
    "wof:name":"Vela Diaz-ropero Pilar",
    "wof:placetype":"venue"
},
  "geometry": {"coordinates":[-3.1226489544,39.4021492004],"type":"Point"}
}