{
  "type": "Feature",
  "properties": {
    "addr:full":"Luga Cruz De La Cebolla, 29 Orotava Santa Cruz De Tenerife 38300",
    "addr:housenumber":"29",
    "addr:postcode":"38300",
    "addr:street":"Cebolla",
    "iso:country":"ES",
    "sg:address":"Luga Cruz De La Cebolla, 29",
    "sg:city":"Orotava",
    "sg:orig_category":"Empresas De Pintura Y Revestimientos",
    "sg:phone":"+34 922 33 26 68",
    "sg:postcode":"38300",
    "sg:province":"Santa Cruz De Tenerife",
    "wof:name":"Garcia Machado Juan",
    "wof:placetype":"venue"
},
  "geometry": {"coordinates":[-16.5167045593,28.3957061768],"type":"Point"}
}