{
  "type": "Feature",
  "properties": {
    "iso:country":"ES",
    "sg:address":"Cmno Moreras (de Las), 165",
    "sg:city":"Garrapinillos",
    "sg:orig_category":"Tapiceros Y Tapiceros",
    "sg:phone":"+34 976 78 06 16",
    "sg:postcode":"50190",
    "sg:province":"Zaragoza",
    "wof:name":"Gimenez Perez Julio",
    "wof:placetype":"venue"
},
  "geometry": {"coordinates":[-1.0242235661,41.6838378906],"type":"Point"}
}