{
  "type": "Feature",
  "properties": {
    "addr:full":"Carr Segadors Gabellins, 2 Capdepera Islas Baleares 07580",
    "addr:housenumber":"2",
    "addr:postcode":"07580",
    "addr:street":"Carr Segadors Gabellins",
    "iso:country":"ES",
    "sg:address":"Carr Segadors Gabellins, 2",
    "sg:city":"Capdepera",
    "sg:orig_category":"Telas Y Sedas (al Por Menor)",
    "sg:phone":"+34 971 56 30 57",
    "sg:postcode":"07580",
    "sg:province":"Islas Baleares",
    "wof:name":"Tejidos Flaquer S. A.",
    "wof:placetype":"venue"
},
  "geometry": {"coordinates":[3.4309799671,39.6956367493],"type":"Point"}
}