{
  "type": "Feature",
  "properties": {
    "iso:country":"ES",
    "sg:address":"Calle de Joaquin Maria Lopez, 8",
    "sg:city":"Villena",
    "sg:orig_category":"Zapatos (al Por Menor)",
    "sg:phone":"+34 965 34 85 14",
    "sg:postcode":"03400",
    "sg:province":"Alicante",
    "wof:name":"Francisco Javier Sanz Marco S.l.",
    "wof:placetype":"venue"
},
  "geometry": {"coordinates":[-0.8642039895,38.63230896],"type":"Point"}
}