{
  "type": "Feature",
  "properties": {
    "iso:country":"ES",
    "sg:address":"Plaz Aragon De, 1",
    "sg:city":"Fraga",
    "sg:orig_category":"Bibliotecas, Mediatecas",
    "sg:phone":"+34 974 47 04 36",
    "sg:postcode":"22520",
    "sg:province":"Huesca",
    "wof:name":"Ayuntamiento De Fraga",
    "wof:placetype":"venue"
},
  "geometry": {"coordinates":[0.3438299894,41.5223045349],"type":"Point"}
}