{
  "type": "Feature",
  "properties": {
    "iso:country":"ES",
    "sg:address":"Calle de Oviedo, 82",
    "sg:city":"Zaragoza",
    "sg:orig_category":"Droguer\u00cdas (al Por Menor)",
    "sg:phone":"+34 976 27 51 68",
    "sg:postcode":"50007",
    "sg:province":"Zaragoza",
    "wof:name":"Lozano Aguilar Juan",
    "wof:placetype":"venue"
},
  "geometry": {"coordinates":[-0.878181994,41.625629425],"type":"Point"}
}