{
  "type": "Feature",
  "properties": {
    "iso:country":"ES",
    "sg:address":"Calle de Esgueva, 10",
    "sg:city":"Valladolid",
    "sg:orig_category":"Molduras, Junquillos, Listones Y Molduras Perforadas",
    "sg:phone":"+34 983 21 05 13",
    "sg:postcode":"47003",
    "sg:province":"Valladolid",
    "wof:name":"Gonzalez Sanpedro Jose",
    "wof:placetype":"venue"
},
  "geometry": {"coordinates":[-4.722630024,41.6544761658],"type":"Point"}
}