{
  "type": "Feature",
  "properties": {
    "addr:full":"Carrer de Holanda, 35 Hospitalet Llobregat Barcelona 08903",
    "addr:housenumber":"35",
    "addr:postcode":"08903",
    "addr:street":"Carrer De Holanda",
    "iso:country":"ES",
    "sg:address":"Carrer de Holanda, 35",
    "sg:city":"Hospitalet Llobregat",
    "sg:orig_category":"Radiocomunicaciones, Telefon\u00cda M\u00d3vil, Radiomensajer\u00cda: Servicios, Comercializaci\u00d3n",
    "sg:phone":"+34 933 31 58 20",
    "sg:postcode":"08903",
    "sg:province":"Barcelona",
    "wof:name":"Chouhan Saqlan Comunicaciones S.l.",
    "wof:placetype":"venue"
},
  "geometry": {"coordinates":[2.1266388893,41.3701019287],"type":"Point"}
}