{
  "type": "Feature",
  "properties": {
    "addr:full":"Carr Arbeca, 22 Mollerussa Lleida 25230",
    "addr:housenumber":"22",
    "addr:postcode":"25230",
    "addr:street":"Carr Arbeca",
    "iso:country":"ES",
    "sg:address":"Carr Arbeca, 22",
    "sg:city":"Mollerussa",
    "sg:orig_category":"Inmobiliaria (agencias)",
    "sg:phone":"+34 973 60 26 00",
    "sg:postcode":"25230",
    "sg:province":"Lleida",
    "wof:name":"Baro Vilalta S.l.",
    "wof:placetype":"venue"
},
  "geometry": {"coordinates":[0.8955060244,41.6241874695],"type":"Point"}
}