{
  "type": "Feature",
  "properties": {
    "iso:country":"ES",
    "sg:address":"Gandario(ouces), 24",
    "sg:city":"Gandario",
    "sg:orig_category":"Bisuter\u00cda, Joyer\u00cda, Relojer\u00cda (al Por Menor)",
    "sg:phone":"+34 981 79 17 12",
    "sg:postcode":"15167",
    "sg:province":"A Coru\u00f1a",
    "wof:name":"Tamiz Joyeros S.l.",
    "wof:placetype":"venue"
},
  "geometry": {"coordinates":[-8.244187355,43.3430557251],"type":"Point"}
}