{
  "type": "Feature",
  "properties": {
    "iso:country":"ES",
    "sg:address":"Pase Menendez Pelayo, 47",
    "sg:city":"Santander",
    "sg:orig_category":"Farmacias",
    "sg:phone":"+34 942 36 01 00",
    "sg:postcode":"39006",
    "sg:province":"Cantabria",
    "wof:name":"Iraola Lopez Maria Del Mar",
    "wof:placetype":"venue"
},
  "geometry": {"coordinates":[-3.7967441082,43.4664611816],"type":"Point"}
}