{
  "type": "Feature",
  "properties": {
    "iso:country":"ES",
    "sg:address":"Avda San Marcial, 5",
    "sg:city":"Lardero",
    "sg:orig_category":"Fisioterapia",
    "sg:phone":"+34 941 44 78 59",
    "sg:postcode":"26140",
    "sg:province":"La Rioja",
    "wof:name":"Monreal Gainza Gonzalo",
    "wof:placetype":"venue"
},
  "geometry": {"coordinates":[-2.4589669704,42.4282226562],"type":"Point"}
}