{
  "type": "Feature",
  "properties": {
    "iso:country":"ES",
    "sg:address":"Carrer de Jovara, 167",
    "sg:city":"Calella",
    "sg:orig_category":"Publicidad (soportes Y Gesti\u00d3n)",
    "sg:phone":"+34 937 66 25 62",
    "sg:postcode":"08370",
    "sg:province":"Barcelona",
    "wof:name":"Caletour Sport & Cultura S.l.",
    "wof:placetype":"venue"
},
  "geometry": {"coordinates":[2.6608719826,41.6136245728],"type":"Point"}
}