{
  "type": "Feature",
  "properties": {
    "iso:country":"ES",
    "sg:address":"Ctra Monroy, S/n",
    "sg:city":"Caceres",
    "sg:orig_category":"Comercio De Hierro",
    "sg:phone":"+34 927 62 80 40",
    "sg:postcode":"10004",
    "sg:province":"C\u00e1ceres",
    "sg:website":"www.grugasa.com",
    "wof:name":"Hierros Garcia Sanchez S.l.",
    "wof:placetype":"venue"
},
  "geometry": {"coordinates":[-6.3583831787,39.5027656555],"type":"Point"}
}