{
  "type": "Feature",
  "properties": {
    "iso:country":"ES",
    "sg:address":"Calle de Antonio Machado, 26",
    "sg:city":"Cuenca",
    "sg:classifiers":[
        {
            "category":"Taxi",
            "type":"Transportation"
        }
    ],
    "sg:phone":"+34 969 22 03 21",
    "sg:postcode":"16004",
    "sg:province":"Cuenca",
    "wof:name":"Hernandez Caballero Julio",
    "wof:placetype":"venue"
},
  "geometry": {"coordinates":[-2.1366927624,40.0579986572],"type":"Point"}
}