{
  "type": "Feature",
  "properties": {
    "addr:full":"Calle de Mistral, 6 Valencia Valencia 46020",
    "addr:housenumber":"6",
    "addr:postcode":"46020",
    "addr:street":"Calle De Mistral",
    "iso:country":"ES",
    "sg:address":"Calle de Mistral, 6",
    "sg:city":"Valencia",
    "sg:orig_category":"Guarder\u00cdas",
    "sg:phone":"+34 963 61 12 92",
    "sg:postcode":"46020",
    "sg:province":"Valencia",
    "wof:name":"Betel Infant School S.l.",
    "wof:placetype":"venue"
},
  "geometry": {"coordinates":[-0.3581269979,39.4841804504],"type":"Point"}
}