{
  "type": "Feature",
  "properties": {
    "addr:full":"Carrer de Sant Agusti (de), 19 Tarragona Tarragona 43003",
    "addr:housenumber":"19",
    "addr:postcode":"43003",
    "addr:street":"Carrer De Sant Agusti De",
    "iso:country":"ES",
    "sg:address":"Carrer de Sant Agusti (de), 19",
    "sg:city":"Tarragona",
    "sg:orig_category":"Zapatos (al Por Menor)",
    "sg:phone":"+34 977 22 32 62",
    "sg:postcode":"43003",
    "sg:province":"Tarragona",
    "wof:name":"Calcats Les Ameriques Sociedad Limitada",
    "wof:placetype":"venue"
},
  "geometry": {"coordinates":[1.2545930147,41.1153678894],"type":"Point"}
}