{
  "type": "Feature",
  "properties": {
    "iso:country":"ES",
    "sg:address":"Carrer de Julia Alvarez, 11",
    "sg:city":"Palma",
    "sg:orig_category":"Asesor\u00cda Fiscal Y Jur\u00cddica",
    "sg:phone":"+34 971 20 54 36",
    "sg:postcode":"07004",
    "sg:province":"Islas Baleares",
    "wof:name":"Fernandez Canosa Jose Luis",
    "wof:placetype":"venue"
},
  "geometry": {"coordinates":[2.652602911,39.5798835754],"type":"Point"}
}