{
  "type": "Feature",
  "properties": {
    "addr:full":"Cabezo Beaza, 1 Cartagena Murcia 30395",
    "addr:housenumber":"1",
    "addr:postcode":"30395",
    "addr:street":"Beaza",
    "iso:country":"ES",
    "sg:address":"Cabezo Beaza, 1",
    "sg:city":"Cartagena",
    "sg:orig_category":"Cajas Para Embalar",
    "sg:phone":"+34 968 12 14 48",
    "sg:postcode":"30395",
    "sg:province":"Murcia",
    "wof:name":"Cajamar",
    "wof:placetype":"venue"
},
  "geometry": {"coordinates":[-0.9203090072,37.717918396],"type":"Point"}
}