{
  "type": "Feature",
  "properties": {
    "addr:full":"Calle de Plata (la), 40 Barrios C\u00e1diz 11370",
    "addr:housenumber":"40",
    "addr:postcode":"11370",
    "addr:street":"Calle De Plata La;Ca\u0301Diz",
    "iso:country":"ES",
    "sg:address":"Calle de Plata (la), 40",
    "sg:city":"Barrios",
    "sg:orig_category":"M\u00c9dicos: Estomatolog\u00cda",
    "sg:phone":"+34 956 62 02 75",
    "sg:postcode":"11370",
    "sg:province":"C\u00e1diz",
    "wof:name":"Colomer Fari\u00f1a Vicente",
    "wof:placetype":"venue"
},
  "geometry": {"coordinates":[-5.4927020073,36.1840934753],"type":"Point"}
}