{
  "type": "Feature",
  "properties": {
    "addr:full":"Calle de Luis Braille, 10 Zaragoza Zaragoza 50013",
    "addr:housenumber":"10",
    "addr:postcode":"50013",
    "addr:street":"Calle De Luis Braille",
    "iso:country":"ES",
    "sg:address":"Calle de Luis Braille, 10",
    "sg:city":"Zaragoza",
    "sg:orig_category":"Carnicer\u00cdas, Carnicer\u00cdas",
    "sg:phone":"+34 976 41 99 18",
    "sg:postcode":"50013",
    "sg:province":"Zaragoza",
    "wof:name":"Monzaragon S.cv.",
    "wof:placetype":"venue"
},
  "geometry": {"coordinates":[-0.8716019988,41.6409378052],"type":"Point"}
}