{
  "type": "Feature",
  "properties": {
    "iso:country":"ES",
    "sg:address":"Forxan, 61",
    "sg:city":"Forxan",
    "sg:orig_category":"Molduras, Junquillos, Listones Y Molduras Perforadas",
    "sg:phone":"+34 986 69 15 71",
    "sg:postcode":"36979",
    "sg:province":"Pontevedra",
    "wof:name":"Basdedios Vazquez Jose",
    "wof:placetype":"venue"
},
  "geometry": {"coordinates":[-8.8151941299,42.4157600403],"type":"Point"}
}