{
  "type": "Feature",
  "properties": {
    "addr:full":"Plaz Santa Ana De, 9 Palmas De Gran Canaria Las Palmas 35001",
    "addr:postcode":"35001",
    "iso:country":"ES",
    "sg:address":"Plaz Santa Ana De, 9",
    "sg:city":"Palmas De Gran Canaria",
    "sg:orig_category":"Promotores Constructores",
    "sg:phone":"+34 928 31 01 26",
    "sg:postcode":"35001",
    "sg:province":"Las Palmas",
    "wof:name":"Fcc Construccion S.a.",
    "wof:placetype":"venue"
},
  "geometry": {"coordinates":[-15.4160404205,28.0998096466],"type":"Point"}
}