{
  "type": "Feature",
  "properties": {
    "addr:full":"Calle de Juan Xxiii (de), 17 Totana Murcia 30850",
    "addr:housenumber":"17",
    "addr:postcode":"30850",
    "addr:street":"Calle De Juan Xxiii De",
    "iso:country":"ES",
    "sg:address":"Calle de Juan Xxiii (de), 17",
    "sg:city":"Totana",
    "sg:orig_category":"Bazares, Art\u00cdculos De Limpieza Y De Cocina (al Por Menor)",
    "sg:phone":"+34 968 42 29 11",
    "sg:postcode":"30850",
    "sg:province":"Murcia",
    "wof:name":"Molino Victoria Vicente",
    "wof:placetype":"venue"
},
  "geometry": {"coordinates":[-1.5001709461,37.7715454102],"type":"Point"}
}