{
  "type": "Feature",
  "properties": {
    "iso:country":"ES",
    "sg:address":"Carr Caama\u00d1o, 3",
    "sg:city":"Figueres",
    "sg:orig_category":"M\u00c9dicos: Ginecolog\u00cda Y Obstetricia",
    "sg:phone":"+34 972 50 98 54",
    "sg:postcode":"17600",
    "sg:province":"Girona",
    "wof:name":"Garcia Turon Enrique",
    "wof:placetype":"venue"
},
  "geometry": {"coordinates":[2.9632599354,42.2667655945],"type":"Point"}
}