{
  "type": "Feature",
  "properties": {
    "addr:full":"Avda Aragon, 398 Madrid Madrid 28022",
    "addr:housenumber":"398",
    "addr:postcode":"28022",
    "addr:street":"Avda Aragon",
    "iso:country":"ES",
    "sg:address":"Avda Aragon, 398",
    "sg:city":"Madrid",
    "sg:orig_category":"Distribuci\u00d3n De Petr\u00d3leo Y Derivados",
    "sg:phone":"+34 913 29 14 93",
    "sg:postcode":"28022",
    "sg:province":"Madrid",
    "wof:name":"Anrimar S.a.",
    "wof:placetype":"venue"
},
  "geometry": {"coordinates":[-3.5590434074,40.4492759705],"type":"Point"}
}