{
  "type": "Feature",
  "properties": {
    "iso:country":"ES",
    "sg:address":"Avda Fernandez Balsera De, 12",
    "sg:city":"Aviles",
    "sg:orig_category":"Perfumer\u00cda (al Por Menor)",
    "sg:phone":"+34 985 56 69 69",
    "sg:postcode":"33402",
    "sg:province":"Asturias",
    "wof:name":"Dapargel S.l.",
    "wof:placetype":"venue"
},
  "geometry": {"coordinates":[-5.9270591736,43.5558166504],"type":"Point"}
}