{
  "type": "Feature",
  "properties": {
    "iso:country":"ES",
    "sg:address":"Calle de Gallo, 5",
    "sg:city":"Puerto Mazarron",
    "sg:orig_category":"Contenedores (mercanc\u00cdas)",
    "sg:phone":"+34 968 15 36 84",
    "sg:postcode":"30860",
    "sg:province":"Murcia",
    "wof:name":"Vivancos Mendez Andres",
    "wof:placetype":"venue"
},
  "geometry": {"coordinates":[-1.2578469515,37.5685806274],"type":"Point"}
}