{
  "type": "Feature",
  "properties": {
    "addr:full":"Carrer de Torrassa, 48 S. Adria Besos Barcelona 08930",
    "addr:housenumber":"48",
    "addr:postcode":"08930",
    "addr:street":"Carrer De Torrassa;S. Adria Besos Barcelona",
    "iso:country":"ES",
    "sg:address":"Carrer de Torrassa, 48",
    "sg:city":"S. Adria Besos",
    "sg:orig_category":"Peluqueros: De Se\u00d1oras",
    "sg:phone":"+34 934 62 03 07",
    "sg:postcode":"08930",
    "sg:province":"Barcelona",
    "wof:name":"Morenilla Escamez Encarnacion",
    "wof:placetype":"venue"
},
  "geometry": {"coordinates":[2.2261300087,41.426990509],"type":"Point"}
}