{
  "type": "Feature",
  "properties": {
    "addr:full":"Ctra Mas Del Jutge, 20 P.i. Masia Del Juez Valencia 46900",
    "addr:housenumber":"20",
    "addr:postcode":"46900",
    "addr:street":"Ctra Mas Del Jutge;P.I. Masia Del Juez",
    "iso:country":"ES",
    "sg:address":"Ctra Mas Del Jutge, 20",
    "sg:city":"P.i. Masia Del Juez",
    "sg:orig_category":"Maquinaria Para Industrias Diversas",
    "sg:phone":"+34 961 55 02 89",
    "sg:postcode":"46900",
    "sg:province":"Valencia",
    "wof:name":"Jamones Peiro S.l.",
    "wof:placetype":"venue"
},
  "geometry": {"coordinates":[-0.4623290002,39.441619873],"type":"Point"}
}