{
  "type": "Feature",
  "properties": {
    "iso:country":"ES",
    "sg:address":"Calle de Alcalde Sanz Noguer, 3",
    "sg:city":"Cordoba",
    "sg:orig_category":"Institutos De Belleza",
    "sg:phone":"+34 957 23 07 79",
    "sg:postcode":"14005",
    "sg:province":"C\u00f3rdoba",
    "wof:name":"Jimenez Olmo Gema",
    "wof:placetype":"venue"
},
  "geometry": {"coordinates":[-4.7910785675,37.8842391968],"type":"Point"}
}