{
  "type": "Feature",
  "properties": {
    "iso:country":"ES",
    "sg:address":"Carrer de Lepant, 196",
    "sg:city":"Terrassa",
    "sg:orig_category":"Grafistas",
    "sg:phone":"+34 937 86 26 24",
    "sg:postcode":"08223",
    "sg:province":"Barcelona",
    "sg:website":"www.ativegroup.es",
    "wof:name":"Active Group Networking & Services S L U P",
    "wof:placetype":"venue"
},
  "geometry": {"coordinates":[2.0094432831,41.5540122986],"type":"Point"}
}