{
  "type": "Feature",
  "properties": {
    "addr:full":"Calle de Obispo Segura Saez, 15 Caceres C\u00e1ceres 10001",
    "addr:housenumber":"15",
    "addr:postcode":"10001",
    "addr:street":"Calle De Obispo Segura Saez;Ca\u0301Ceres",
    "iso:country":"ES",
    "sg:address":"Calle de Obispo Segura Saez, 15",
    "sg:city":"Caceres",
    "sg:orig_category":"Ingenier\u00cda, Centros De Estudios (diversos)",
    "sg:phone":"+34 927 22 25 89",
    "sg:postcode":"10001",
    "sg:province":"C\u00e1ceres",
    "wof:name":"Casado Y Rubio Felipe",
    "wof:placetype":"venue"
},
  "geometry": {"coordinates":[-6.3792109489,39.4719009399],"type":"Point"}
}