{
  "type": "Feature",
  "properties": {
    "iso:country":"ES",
    "sg:address":"Calle de Caravaca, 12",
    "sg:city":"Madrid",
    "sg:orig_category":"Empresarios Y Productoras De Espect\u00c1culos",
    "sg:phone":"+34 915 06 11 01",
    "sg:postcode":"28012",
    "sg:province":"Madrid",
    "wof:name":"Gimenez Caminero Oscar",
    "wof:placetype":"venue"
},
  "geometry": {"coordinates":[-3.7030014992,40.4088668823],"type":"Point"}
}