{
  "type": "Feature",
  "properties": {
    "addr:full":"Ctra Estacion, 23 Lorqui Murcia 30564",
    "addr:housenumber":"23",
    "addr:postcode":"30564",
    "addr:street":"Ctra Estacion",
    "iso:country":"ES",
    "sg:address":"Ctra Estacion, 23",
    "sg:city":"Lorqui",
    "sg:orig_category":"Supermercados Y Hipermercados",
    "sg:phone":"+34 968 69 02 01",
    "sg:postcode":"30564",
    "sg:province":"Murcia",
    "wof:name":"Bermejo Cifuentes Jose Antonio",
    "wof:placetype":"venue"
},
  "geometry": {"coordinates":[-1.2511130571,38.0860137939],"type":"Point"}
}