{
  "type": "Feature",
  "properties": {
    "iso:country":"ES",
    "sg:address":"Calle de Alfonso Xi, 25",
    "sg:city":"Alcala Real",
    "sg:orig_category":"Agencias Y Agentes Comerciales, Representantes",
    "sg:phone":"+34 953 58 10 80",
    "sg:postcode":"23680",
    "sg:province":"Ja\u00e9n",
    "wof:name":"Perez Cobo Pedro",
    "wof:placetype":"venue"
},
  "geometry": {"coordinates":[-3.9239823818,37.4591064453],"type":"Point"}
}