{
  "type": "Feature",
  "properties": {
    "addr:full":"Avda Toledo, De, 31 Talavera Reina Toledo 45600",
    "addr:housenumber":"31",
    "addr:postcode":"45600",
    "addr:street":"Avda Toledo De",
    "iso:country":"ES",
    "sg:address":"Avda Toledo, De, 31",
    "sg:city":"Talavera Reina",
    "sg:orig_category":"Ense\u00d1anza: Comercio, Gesti\u00d3n, Inform\u00c1tica",
    "sg:phone":"+34 925 81 24 16",
    "sg:postcode":"45600",
    "sg:province":"Toledo",
    "wof:name":"Delta 3 Informatica S.l.",
    "wof:placetype":"venue"
},
  "geometry": {"coordinates":[-4.8326292038,39.9584884644],"type":"Point"}
}