{
  "type": "Feature",
  "properties": {
    "addr:full":"Ctra Borja-el Buste, 3 Borja Zaragoza 50540",
    "addr:housenumber":"3",
    "addr:postcode":"50540",
    "addr:street":"Ctra Borja-El Buste",
    "iso:country":"ES",
    "sg:address":"Ctra Borja-el Buste, 3",
    "sg:city":"Borja",
    "sg:orig_category":"Mantenimiento Y Reparaci\u00d3n De Motores Industriales",
    "sg:phone":"+34 976 85 29 21",
    "sg:postcode":"50540",
    "sg:province":"Zaragoza",
    "wof:name":"Agoiz Duarte Jose",
    "wof:placetype":"venue"
},
  "geometry": {"coordinates":[-1.5780334473,41.8533325195],"type":"Point"}
}