{
  "type": "Feature",
  "properties": {
    "addr:full":"Calle de Francisco De Orellana, 4 Santiago El Mayor Murcia 30012",
    "addr:housenumber":"4",
    "addr:postcode":"30012",
    "addr:street":"Calle De Francisco De Orellana",
    "iso:country":"ES",
    "sg:address":"Calle de Francisco De Orellana, 4",
    "sg:city":"Santiago El Mayor",
    "sg:orig_category":"Agencias Y Asesores De Publicidad",
    "sg:phone":"+34 968 35 02 88",
    "sg:postcode":"30012",
    "sg:province":"Murcia",
    "sg:website":"www.publisurbelando.com",
    "wof:name":"Publisur Marketing Y Publicidad S.a.",
    "wof:placetype":"venue"
},
  "geometry": {"coordinates":[-1.1206640005,37.9650650024],"type":"Point"}
}