{
  "type": "Feature",
  "properties": {
    "addr:full":"Calle de Txiki Otaegi, 10 Amorebieta Vizcaya 48340",
    "addr:housenumber":"10",
    "addr:postcode":"48340",
    "addr:street":"Calle De Txiki Otaegi",
    "iso:country":"ES",
    "sg:address":"Calle de Txiki Otaegi, 10",
    "sg:city":"Amorebieta",
    "sg:orig_category":"Contenedores (mercanc\u00cdas)",
    "sg:phone":"+34 946 73 24 23",
    "sg:postcode":"48340",
    "sg:province":"Vizcaya",
    "wof:name":"Joven Aval Manuel",
    "wof:placetype":"venue"
},
  "geometry": {"coordinates":[-2.7360429764,43.2210464478],"type":"Point"}
}