{
  "type": "Feature",
  "properties": {
    "iso:country":"ES",
    "sg:address":"Calle de Doctor Gonzalo Sierra (del), 18",
    "sg:city":"Mejorada Campo",
    "sg:orig_category":"Servicio De Salud",
    "sg:phone":"+34 916 79 08 61",
    "sg:postcode":"28840",
    "sg:province":"Madrid",
    "wof:name":"Foregas S.l.",
    "wof:placetype":"venue"
},
  "geometry": {"coordinates":[-3.4850587845,40.396697998],"type":"Point"}
}