{
  "type": "Feature",
  "properties": {
    "addr:full":"Calle de Martires, 18 Zafra Badajoz 06300",
    "addr:housenumber":"18",
    "addr:postcode":"06300",
    "addr:street":"Calle De Martires",
    "iso:country":"ES",
    "sg:address":"Calle de Martires, 18",
    "sg:city":"Zafra",
    "sg:orig_category":"Reposter\u00cdas",
    "sg:phone":"+34 924 55 00 28",
    "sg:postcode":"06300",
    "sg:province":"Badajoz",
    "wof:name":"Damaso Gomez E Hijos S.l.",
    "wof:placetype":"venue"
},
  "geometry": {"coordinates":[-6.4184188843,38.4186935425],"type":"Point"}
}