{
  "type": "Feature",
  "properties": {
    "addr:full":"Pase Pintor Rosales, 64 Madrid Madrid 28008",
    "addr:housenumber":"64",
    "addr:postcode":"madrid;28008",
    "addr:street":"Pintor Rosales",
    "iso:country":"ES",
    "sg:address":"Pase Pintor Rosales, 64",
    "sg:city":"Madrid",
    "sg:orig_category":"Abogados",
    "sg:phone":"+34 915 44 18 64",
    "sg:postcode":"28008",
    "sg:province":"Madrid",
    "wof:name":"Sierra Rouanet Y Corral Asesores S.l.",
    "wof:placetype":"venue"
},
  "geometry": {"coordinates":[-3.7234749794,40.4308547974],"type":"Point"}
}