{
  "type": "Feature",
  "properties": {
    "iso:country":"ES",
    "sg:address":"Carrer de Brutau, 113",
    "sg:city":"Sabadell",
    "sg:orig_category":"Venta, Localizaci\u00d3n, Reparaci\u00d3n De Material E Instrumental M\u00c9dico",
    "sg:phone":"+34 937 11 97 74",
    "sg:postcode":"08203",
    "sg:province":"Barcelona",
    "wof:name":"Blakufar S.l.",
    "wof:placetype":"venue"
},
  "geometry": {"coordinates":[2.1136898994,41.5370903015],"type":"Point"}
}