{
  "type": "Feature",
  "properties": {
    "addr:full":"Cmno Ca\u00d1averal, 20 Puente Botero Murcia 30813",
    "addr:housenumber":"20",
    "addr:postcode":"30813",
    "addr:street":"Cmno Can\u0303Averal",
    "iso:country":"ES",
    "sg:address":"Cmno Ca\u00d1averal, 20",
    "sg:city":"Puente Botero",
    "sg:orig_category":"Cooperativas Agr\u00cdcolas",
    "sg:phone":"+34 968 47 11 84",
    "sg:postcode":"30813",
    "sg:province":"Murcia",
    "wof:name":"Priser S.c.o.o.p.",
    "wof:placetype":"venue"
},
  "geometry": {"coordinates":[-1.7215889692,37.491394043],"type":"Point"}
}