{
  "type": "Feature",
  "properties": {
    "iso:country":"ES",
    "sg:address":"Pase Farnesio, 23",
    "sg:city":"Valladolid",
    "sg:orig_category":"Molduras, Junquillos, Listones Y Molduras Perforadas",
    "sg:phone":"+34 983 22 63 14",
    "sg:postcode":"47013",
    "sg:province":"Valladolid",
    "wof:name":"Carpanel Bar S.l.",
    "wof:placetype":"venue"
},
  "geometry": {"coordinates":[-4.7228679657,41.6396026611],"type":"Point"}
}