{
  "type": "Feature",
  "properties": {
    "addr:full":"Calle de Burgo De Osma, 2 Madrid Madrid 28033",
    "addr:housenumber":"2",
    "addr:postcode":"28033",
    "addr:street":"Calle De Burgo De Osma",
    "iso:country":"ES",
    "sg:address":"Calle de Burgo De Osma, 2",
    "sg:city":"Madrid",
    "sg:orig_category":"Seguridad En El Trabajo Y Prevenci\u00d3n De Riesgos Laborales",
    "sg:phone":"+34 913 83 88 42",
    "sg:postcode":"28033",
    "sg:province":"Madrid",
    "wof:name":"Quid Marketing S.l.",
    "wof:placetype":"venue"
},
  "geometry": {"coordinates":[-3.6615605354,40.4689178467],"type":"Point"}
}