{
  "type": "Feature",
  "properties": {
    "iso:country":"ES",
    "sg:address":"Calle de Julian Gayarre, 9",
    "sg:city":"Sestao",
    "sg:orig_category":"Empresas De Portes Y Mensajer\u00cda",
    "sg:phone":"+34 944 72 21 90",
    "sg:postcode":"48910",
    "sg:province":"Vizcaya",
    "wof:name":"Sanchez Andres Jesus Angel",
    "wof:placetype":"venue"
},
  "geometry": {"coordinates":[-3.0004680157,43.3088912964],"type":"Point"}
}