{
  "type": "Feature",
  "properties": {
    "iso:country":"ES",
    "sg:address":"Avda Ruperta Baraya, 9",
    "sg:city":"Aranda Duero",
    "sg:orig_category":"Suministros Para Carrocer\u00cdas",
    "sg:phone":"+34 947 50 05 71",
    "sg:postcode":"09400",
    "sg:province":"Burgos",
    "wof:name":"Rojas Alonso Tomas",
    "wof:placetype":"venue"
},
  "geometry": {"coordinates":[-3.6948869228,41.6685829163],"type":"Point"}
}