{
  "type": "Feature",
  "properties": {
    "addr:full":"Carrer de Major, 140 Mora Nova Tarragona 43770",
    "addr:housenumber":"140",
    "addr:postcode":"43770",
    "addr:street":"Carrer De Major",
    "iso:country":"ES",
    "sg:address":"Carrer de Major, 140",
    "sg:city":"Mora Nova",
    "sg:orig_category":"Estancos",
    "sg:phone":"+34 977 40 07 43",
    "sg:postcode":"43770",
    "sg:province":"Tarragona",
    "wof:name":"Giralt Llop Juan",
    "wof:placetype":"venue"
},
  "geometry": {"coordinates":[0.6522349715,41.1021003723],"type":"Point"}
}