{
  "type": "Feature",
  "properties": {
    "addr:full":"Avda Francisco Gonzalez Rey, 55 Celanova Ourense 32800",
    "addr:housenumber":"55",
    "addr:postcode":"32800",
    "addr:street":"Avda Francisco Gonzalez Rey",
    "iso:country":"ES",
    "sg:address":"Avda Francisco Gonzalez Rey, 55",
    "sg:city":"Celanova",
    "sg:classifiers":[
        {
            "category":"Autos & Motor Vehicles",
            "subcategory":"Automobile Sales",
            "type":"Retail Goods"
        }
    ],
    "sg:phone":"+34 988 43 20 87",
    "sg:postcode":"32800",
    "sg:province":"Ourense",
    "wof:name":"Autoescuela San Francisco S. L.",
    "wof:placetype":"venue"
},
  "geometry": {"coordinates":[-7.9865350723,42.1502799988],"type":"Point"}
}