{
  "type": "Feature",
  "properties": {
    "iso:country":"ES",
    "sg:address":"Metalurgia(pol. Bankunion Ii), 4",
    "sg:city":"Gijon",
    "sg:orig_category":"Negocio De Materiales De Construcci\u00d3n",
    "sg:phone":"+34 985 30 91 17",
    "sg:postcode":"33211",
    "sg:province":"Asturias",
    "wof:name":"Decoraciones Materiales Y Plasticos S.l.l.",
    "wof:placetype":"venue"
},
  "geometry": {"coordinates":[-5.7118520737,43.5255088806],"type":"Point"}
}