{
  "type": "Feature",
  "properties": {
    "iso:country":"ES",
    "sg:address":"Calle de Constantino, 51",
    "sg:city":"Ejido",
    "sg:orig_category":"Ropa Para Se\u00d1oras (al Por Menor)",
    "sg:phone":"+34 950 48 79 83",
    "sg:postcode":"04700",
    "sg:province":"Almer\u00eda",
    "wof:name":"Piedad Martin Lopez-carmen Martin Lopez Cdad.",
    "wof:placetype":"venue"
},
  "geometry": {"coordinates":[-2.8121666908,36.7751655579],"type":"Point"}
}