{
  "type": "Feature",
  "properties": {
    "iso:country":"ES",
    "sg:address":"Avda De La Constitucion, 11",
    "sg:city":"Cuacos Yuste",
    "sg:classifiers":[
        {
            "category":"Taxi",
            "type":"Transportation"
        }
    ],
    "sg:phone":"+34 927 17 21 10",
    "sg:postcode":"10430",
    "sg:province":"C\u00e1ceres",
    "wof:name":"Hernandez Rodriguez Victoria",
    "wof:placetype":"venue"
},
  "geometry": {"coordinates":[-5.7258291245,40.1029891968],"type":"Point"}
}