{
  "type": "Feature",
  "properties": {
    "addr:full":"Badia Polesine, 17 Estepa Sevilla 41560",
    "addr:housenumber":"17",
    "addr:postcode":"41560",
    "addr:street":"Badia Polesine;Sevilla",
    "iso:country":"ES",
    "sg:address":"Badia Polesine, 17",
    "sg:city":"Estepa",
    "sg:orig_category":"Agricultores, Agricultores",
    "sg:phone":"+34 954 82 08 05",
    "sg:postcode":"41560",
    "sg:province":"Sevilla",
    "wof:name":"Agroservicios Juarez Ortiz S.l.",
    "wof:placetype":"venue"
},
  "geometry": {"coordinates":[-4.8822855949,37.2962303162],"type":"Point"}
}