{
  "type": "Feature",
  "properties": {
    "iso:country":"ES",
    "sg:address":"Calle de Masquefa, 40",
    "sg:city":"Valencia",
    "sg:orig_category":"Art\u00cdculos De Regalo (al Por Menor)",
    "sg:phone":"+34 963 89 05 29",
    "sg:postcode":"46020",
    "sg:province":"Valencia",
    "wof:name":"Ramesh  Balani Balani",
    "wof:placetype":"venue"
},
  "geometry": {"coordinates":[-0.3586620092,39.4893417358],"type":"Point"}
}