{
  "type": "Feature",
  "properties": {
    "iso:country":"ES",
    "sg:address":"Calle de Ancha, 52",
    "sg:city":"Ponferrada",
    "sg:orig_category":"Mercer\u00cda, Lencer\u00cda (al Por Menor)",
    "sg:phone":"+34 987 40 12 25",
    "sg:postcode":"24400",
    "sg:province":"Le\u00f3n",
    "wof:name":"Gonzalez Blanco Maria Rosario",
    "wof:placetype":"venue"
},
  "geometry": {"coordinates":[-6.5864882469,42.5482254028],"type":"Point"}
}