{
  "type": "Feature",
  "properties": {
    "addr:full":"Carrer de Serrano, 14 Terrassa Barcelona 08222",
    "addr:housenumber":"14",
    "addr:postcode":"08222",
    "addr:street":"Carrer De Serrano",
    "iso:country":"ES",
    "sg:address":"Carrer de Serrano, 14",
    "sg:city":"Terrassa",
    "sg:orig_category":"Equipo De Refrigeraci\u00d3n Industrial",
    "sg:phone":"+34 937 86 24 80",
    "sg:postcode":"08222",
    "sg:province":"Barcelona",
    "wof:name":"Primo Arauzo Ignacio",
    "wof:placetype":"venue"
},
  "geometry": {"coordinates":[2.0181860924,41.559753418],"type":"Point"}
}