{
  "type": "Feature",
  "properties": {
    "iso:country":"ES",
    "sg:address":"Carrer de Torrent De L'olla, 202",
    "sg:city":"Barcelona",
    "sg:orig_category":"Bibliotecas, Mediatecas",
    "sg:phone":"+34 932 17 41 34",
    "sg:postcode":"08012",
    "sg:province":"Barcelona",
    "wof:name":"Istituto Europeo Di Design S.l.",
    "wof:placetype":"venue"
},
  "geometry": {"coordinates":[2.1536211967,41.4053688049],"type":"Point"}
}