{
  "type": "Feature",
  "properties": {
    "addr:full":"Carrer de Duc De Lerma, 19 Verger Alicante 03770",
    "addr:postcode":"03770",
    "addr:street":"Carrer De Duc;Lerma 19 Verger",
    "iso:country":"ES",
    "sg:address":"Carrer de Duc De Lerma, 19",
    "sg:city":"Verger",
    "sg:orig_category":"Arboricultura Y Producci\u00d3n De Frutas",
    "sg:phone":"+34 965 75 01 37",
    "sg:postcode":"03770",
    "sg:province":"Alicante",
    "wof:name":"Martinez Saiz Elviro",
    "wof:placetype":"venue"
},
  "geometry": {"coordinates":[0.008626,38.8471221924],"type":"Point"}
}