{
  "type": "Feature",
  "properties": {
    "iso:country":"ES",
    "sg:address":"Calle de Alamo, 3",
    "sg:city":"Torrejon Ardoz",
    "sg:orig_category":"Electromec\u00c1nica",
    "sg:phone":"+34 916 56 66 12",
    "sg:postcode":"28850",
    "sg:province":"Madrid",
    "wof:name":"Serine S.l.",
    "wof:placetype":"venue"
},
  "geometry": {"coordinates":[-3.4577360153,40.4452972412],"type":"Point"}
}