{
  "type": "Feature",
  "properties": {
    "iso:country":"ES",
    "sg:address":"Calle de Vivero, 6",
    "sg:city":"Trillo",
    "sg:orig_category":"Guarder\u00cdas",
    "sg:phone":"+34 949 81 52 38",
    "sg:postcode":"19450",
    "sg:province":"Guadalajara",
    "wof:name":"Ayuntamiento De Trillo",
    "wof:placetype":"venue"
},
  "geometry": {"coordinates":[-2.5929670334,40.69947052],"type":"Point"}
}