{
  "type": "Feature",
  "properties": {
    "addr:full":"Rua Regueiro, 6 Vigo Pontevedra 36211",
    "addr:housenumber":"6",
    "addr:postcode":"36211",
    "addr:street":"Rua Regueiro",
    "iso:country":"ES",
    "sg:address":"Rua Regueiro, 6",
    "sg:city":"Vigo",
    "sg:orig_category":"Electricidad: Instaladores",
    "sg:phone":"+34 986 29 96 45",
    "sg:postcode":"36211",
    "sg:province":"Pontevedra",
    "wof:name":"Alonso Riveiro Jose Carlos",
    "wof:placetype":"venue"
},
  "geometry": {"coordinates":[-8.729516983,42.2230072021],"type":"Point"}
}