{
  "type": "Feature",
  "properties": {
    "iso:country":"ES",
    "sg:address":"Carrer de Rossello (de), 4",
    "sg:city":"Tortosa",
    "sg:orig_category":"Bebidas",
    "sg:phone":"+34 977 44 13 87",
    "sg:postcode":"43500",
    "sg:province":"Tarragona",
    "wof:name":"Bertomeu Gas Jose Juan",
    "wof:placetype":"venue"
},
  "geometry": {"coordinates":[0.5217660069,40.8069038391],"type":"Point"}
}