{
  "type": "Feature",
  "properties": {
    "addr:full":"Carrer de Ruiz De Padron, 92 Barcelona Barcelona 08026",
    "addr:housenumber":"92",
    "addr:postcode":"08026",
    "addr:street":"Carrer De Ruiz De Padron",
    "iso:country":"ES",
    "sg:address":"Carrer de Ruiz De Padron, 92",
    "sg:city":"Barcelona",
    "sg:orig_category":"Agencias Y Agentes Comerciales, Representantes",
    "sg:phone":"+34 933 52 12 65",
    "sg:postcode":"08026",
    "sg:province":"Barcelona",
    "wof:name":"Pardo Escuder Jorge",
    "wof:placetype":"venue"
},
  "geometry": {"coordinates":[2.1848990917,41.4159317017],"type":"Point"}
}