{
  "type": "Feature",
  "properties": {
    "addr:full":"Calle de Caballerizas Del Conde, 7 Toro Zamora 49800",
    "addr:housenumber":"7",
    "addr:postcode":"49800",
    "addr:street":"Calle De Caballerizas Del Conde",
    "iso:country":"ES",
    "sg:address":"Calle de Caballerizas Del Conde, 7",
    "sg:city":"Toro",
    "sg:orig_category":"Arquitectos",
    "sg:phone":"+34 980 69 29 27",
    "sg:postcode":"49800",
    "sg:province":"Zamora",
    "wof:name":"Remis Fernandez Jesus",
    "wof:placetype":"venue"
},
  "geometry": {"coordinates":[-5.3949117661,41.5205535889],"type":"Point"}
}