{
  "type": "Feature",
  "properties": {
    "iso:country":"ES",
    "sg:address":"Calle de Alameda, S/n",
    "sg:city":"Marbella",
    "sg:orig_category":"Electrodom\u00c9sticos (al Por Menor)",
    "sg:phone":"+34 952 77 24 90",
    "sg:postcode":"29600",
    "sg:province":"M\u00e1laga",
    "wof:name":"Perez Y Perez Abascal Mario",
    "wof:placetype":"venue"
},
  "geometry": {"coordinates":[-4.8851232529,36.5092658997],"type":"Point"}
}