{
  "type": "Feature",
  "properties": {
    "iso:country":"ES",
    "sg:address":"Carrer de Moli Del Llobet, 10",
    "sg:city":"Vic",
    "sg:orig_category":"Cueros Y Pieles (al Por Mayor)",
    "sg:phone":"+34 938 86 14 29",
    "sg:postcode":"08500",
    "sg:province":"Barcelona",
    "wof:name":"Iterduc S.l",
    "wof:placetype":"venue"
},
  "geometry": {"coordinates":[2.2841339111,41.9462394714],"type":"Point"}
}