{
  "type": "Feature",
  "properties": {
    "addr:full":"Carr Vall, 16 Sueca Valencia 46410",
    "addr:housenumber":"16",
    "addr:postcode":"46410",
    "addr:street":"Carr Vall",
    "iso:country":"ES",
    "sg:address":"Carr Vall, 16",
    "sg:city":"Sueca",
    "sg:orig_category":"Reposter\u00cdas",
    "sg:phone":"+34 961 70 03 67",
    "sg:postcode":"46410",
    "sg:province":"Valencia",
    "wof:name":"Beltran Cuevas Maria Javiera",
    "wof:placetype":"venue"
},
  "geometry": {"coordinates":[-0.3076440096,39.2027435303],"type":"Point"}
}