{
  "type": "Feature",
  "properties": {
    "addr:full":"Carr Moli, 40 Alboraya Valencia 46120",
    "addr:housenumber":"40",
    "addr:postcode":"46120",
    "addr:street":"Carr Moli",
    "iso:country":"ES",
    "sg:address":"Carr Moli, 40",
    "sg:city":"Alboraya",
    "sg:orig_category":"Laboratorios",
    "sg:phone":"+34 961 85 75 11",
    "sg:postcode":"46120",
    "sg:province":"Valencia",
    "wof:name":"Lab Laboratoris S.l.",
    "wof:placetype":"venue"
},
  "geometry": {"coordinates":[-0.3405140042,39.4990692139],"type":"Point"}
}