{
  "type": "Feature",
  "properties": {
    "addr:full":"Av Rei En Jaume, 52 Cardedeu Barcelona 08440",
    "addr:housenumber":"52",
    "addr:postcode":"08440",
    "addr:street":"Av Rei En Jaume",
    "iso:country":"ES",
    "sg:address":"Av Rei En Jaume, 52",
    "sg:city":"Cardedeu",
    "sg:classifiers":[
        {
            "category":"Taxi",
            "type":"Transportation"
        }
    ],
    "sg:phone":"+34 938 46 13 45",
    "sg:postcode":"08440",
    "sg:province":"Barcelona",
    "wof:name":"Jubany Viade Juan",
    "wof:placetype":"venue"
},
  "geometry": {"coordinates":[2.3579499722,41.6369781494],"type":"Point"}
}