{
  "type": "Feature",
  "properties": {
    "addr:full":"Avda Egues, 16 Gorraitz-artzibar Navarra 31620",
    "addr:housenumber":"16",
    "addr:postcode":"31620",
    "addr:street":"Avda Egues",
    "iso:country":"ES",
    "sg:address":"Avda Egues, 16",
    "sg:city":"Gorraitz-artzibar",
    "sg:orig_category":"Arquitectos",
    "sg:phone":"+34 948 35 76 30",
    "sg:postcode":"31620",
    "sg:province":"Navarra",
    "wof:name":"Rosino Rosino Miguel Angel",
    "wof:placetype":"venue"
},
  "geometry": {"coordinates":[-1.5902739763,42.83177948],"type":"Point"}
}