{
  "type": "Feature",
  "properties": {
    "addr:full":"Carrer de Carretes, 31 Barcelona Barcelona 08001",
    "addr:housenumber":"31",
    "addr:postcode":"08001",
    "addr:street":"Carrer De Carretes",
    "iso:country":"ES",
    "sg:address":"Carrer de Carretes, 31",
    "sg:city":"Barcelona",
    "sg:orig_category":"Ingeniero",
    "sg:phone":"+34 934 41 21 24",
    "sg:postcode":"08001",
    "sg:province":"Barcelona",
    "wof:name":"Pesqueira De Schnorr  Maria Antoniela",
    "wof:placetype":"venue"
},
  "geometry": {"coordinates":[2.1672790051,41.3777122498],"type":"Point"}
}