{
  "type": "Feature",
  "properties": {
    "addr:full":"Carrer de Pi I Margall, 32 Barcelona Barcelona 08025",
    "addr:housenumber":"32",
    "addr:postcode":"08025",
    "addr:street":"Carrer De Pi I Margall",
    "iso:country":"ES",
    "sg:address":"Carrer de Pi I Margall, 32",
    "sg:city":"Barcelona",
    "sg:orig_category":"M\u00c1rmoles, Granitos Y Piedras Naturales",
    "sg:phone":"+34 932 84 03 09",
    "sg:postcode":"08025",
    "sg:province":"Barcelona",
    "wof:name":"Pelegri Oliva Victoria",
    "wof:placetype":"venue"
},
  "geometry": {"coordinates":[2.1636199951,41.4070777893],"type":"Point"}
}