{
  "type": "Feature",
  "properties": {
    "iso:country":"ES",
    "sg:address":"Carrer de Santiago, 2",
    "sg:city":"Montcada Centre",
    "sg:orig_category":"Molduras, Junquillos, Listones Y Molduras Perforadas",
    "sg:phone":"+34 935 64 82 08",
    "sg:postcode":"08110",
    "sg:province":"Barcelona",
    "wof:name":"Garcia Cuervo Mariano",
    "wof:placetype":"venue"
},
  "geometry": {"coordinates":[2.1817660332,41.4890899658],"type":"Point"}
}