{
  "type": "Feature",
  "properties": {
    "addr:full":"Pujol, 11 Montu\u00efri Islas Baleares 07230",
    "addr:housenumber":"11",
    "addr:postcode":"07230",
    "addr:street":"Pujol;Islas",
    "iso:country":"ES",
    "sg:address":"Pujol, 11",
    "sg:city":"Montu\u00efri",
    "sg:orig_category":"Inversiones",
    "sg:phone":"+34 971 64 66 81",
    "sg:postcode":"07230",
    "sg:province":"Islas Baleares",
    "wof:name":"Inversions I Assegurances Es Pujol S.l.",
    "wof:placetype":"venue"
},
  "geometry": {"coordinates":[2.9814040661,39.5666007996],"type":"Point"}
}