{
  "type": "Feature",
  "properties": {
    "iso:country":"ES",
    "sg:address":"Carrer de L'agregacio, 5",
    "sg:city":"Barcelona",
    "sg:orig_category":"Droguer\u00cdas (al Por Menor)",
    "sg:phone":"+34 933 51 86 65",
    "sg:postcode":"08041",
    "sg:province":"Barcelona",
    "wof:name":"Casajuana Morant Juan",
    "wof:placetype":"venue"
},
  "geometry": {"coordinates":[2.1770582199,41.4235610962],"type":"Point"}
}