{
  "type": "Feature",
  "properties": {
    "iso:country":"ES",
    "sg:address":"Calle de Sol, 8",
    "sg:city":"Arenas San Pedro",
    "sg:orig_category":"Frutas Y Legumbres Frescas (al Por Mayor)",
    "sg:phone":"+34 920 37 24 60",
    "sg:postcode":"05400",
    "sg:province":"\u00c1vila",
    "wof:name":"Collado Cuenca Francisco",
    "wof:placetype":"venue"
},
  "geometry": {"coordinates":[-5.0832519531,40.2119636536],"type":"Point"}
}