{
  "type": "Feature",
  "properties": {
    "addr:full":"Calle de Juan Hurtado De Mendoza, 3 Madrid Madrid 28036",
    "addr:housenumber":"3",
    "addr:postcode":"28036",
    "addr:street":"Calle De Juan Hurtado De Mendoza",
    "iso:country":"ES",
    "sg:address":"Calle de Juan Hurtado De Mendoza, 3",
    "sg:city":"Madrid",
    "sg:orig_category":"Sociedades, Compa\u00d1\u00cdas Aseguradoras",
    "sg:phone":"+34 913 59 74 88",
    "sg:postcode":"28036",
    "sg:province":"Madrid",
    "wof:name":"Reale Seguros Generales",
    "wof:placetype":"venue"
},
  "geometry": {"coordinates":[-3.6887760162,40.4606361389],"type":"Point"}
}