{
  "type": "Feature",
  "properties": {
    "addr:full":"Afueras, S/n Azuaga Badajoz 06920",
    "addr:postcode":"06920",
    "addr:street":"Afueras S / N",
    "iso:country":"ES",
    "sg:address":"Afueras, S/n",
    "sg:city":"Azuaga",
    "sg:orig_category":"Cooperativas Agr\u00cdcolas",
    "sg:phone":"+34 924 14 40 35",
    "sg:postcode":"06920",
    "sg:province":"Badajoz",
    "wof:name":"Cooperativa Olivarera San Antonio De Padua",
    "wof:placetype":"venue"
},
  "geometry": {"coordinates":[-5.6754541397,38.2559814453],"type":"Point"}
}