{
  "type": "Feature",
  "properties": {
    "iso:country":"ES",
    "sg:address":"Carrer de Mossen Jacint Verdaguer, 228",
    "sg:city":"Sant Vicen\u00c7 Dels Horts",
    "sg:orig_category":"Congelados: Productos Alimentarios (al Por Menor)",
    "sg:phone":"+34 936 56 55 58",
    "sg:postcode":"08620",
    "sg:province":"Barcelona",
    "wof:name":"Meral Valero Concepcion",
    "wof:placetype":"venue"
},
  "geometry": {"coordinates":[2.0063800812,41.3997039795],"type":"Point"}
}