{
  "type": "Feature",
  "properties": {
    "addr:full":"Crri Cebadero, 9 Ermita De Pati\u00e7o Murcia 30012",
    "addr:housenumber":"9",
    "addr:postcode":"30012",
    "addr:street":"Cebadero",
    "iso:country":"ES",
    "sg:address":"Crri Cebadero, 9",
    "sg:city":"Ermita De Pati\u00e7o",
    "sg:orig_category":"Empresas De Carpinter\u00cda Met\u00c1lica",
    "sg:phone":"+34 968 35 10 46",
    "sg:postcode":"30012",
    "sg:province":"Murcia",
    "wof:name":"Carpinteria Metalica Marsan S.l.l.",
    "wof:placetype":"venue"
},
  "geometry": {"coordinates":[-1.1206640005,37.9650650024],"type":"Point"}
}