{
  "type": "Feature",
  "properties": {
    "iso:country":"ES",
    "sg:address":"Carr Gerreria (de La), 10",
    "sg:city":"Castello Rugat",
    "sg:orig_category":"Ingeniero",
    "sg:phone":"+34 962 81 43 64",
    "sg:postcode":"46841",
    "sg:province":"Valencia",
    "wof:name":"Boronat Segui Joaquin",
    "wof:placetype":"venue"
},
  "geometry": {"coordinates":[-0.3831990063,38.8734703064],"type":"Point"}
}