{
  "type": "Feature",
  "properties": {
    "addr:full":"A Casilla, S/n Casilla Pontevedra 36418",
    "addr:housenumber":"s / n",
    "addr:postcode":"36418",
    "iso:country":"ES",
    "sg:address":"A Casilla, S/n",
    "sg:city":"Casilla",
    "sg:orig_category":"Materiales De Construcci\u00d3n (en General)",
    "sg:phone":"+34 986 33 76 89",
    "sg:postcode":"36418",
    "sg:province":"Pontevedra",
    "wof:name":"Casabano S.l.",
    "wof:placetype":"venue"
},
  "geometry": {"coordinates":[-8.617515564,42.1448669434],"type":"Point"}
}