{
  "type": "Feature",
  "properties": {
    "addr:full":"Av Xativa (de), 42 Cocentaina Alicante 03820",
    "addr:postcode":"03820",
    "addr:street":"Av",
    "iso:country":"ES",
    "sg:address":"Av Xativa (de), 42",
    "sg:city":"Cocentaina",
    "sg:orig_category":"Hilaturas (fibras Naturales Diversas)",
    "sg:phone":"+34 965 59 33 52",
    "sg:postcode":"03820",
    "sg:province":"Alicante",
    "sg:website":"www.hilex.es",
    "wof:name":"Hilados Exteriores S.l.",
    "wof:placetype":"venue"
},
  "geometry": {"coordinates":[-0.4393289983,38.748298645],"type":"Point"}
}