{
  "type": "Feature",
  "properties": {
    "iso:country":"ES",
    "sg:address":"Ctra Litos, Km. 0024,5",
    "sg:city":"Mozar",
    "sg:orig_category":"Molduras, Junquillos, Listones Y Molduras Perforadas",
    "sg:phone":"+34 980 64 05 40",
    "sg:postcode":"49698",
    "sg:province":"Zamora",
    "wof:name":"Fernandez Rodriguez Jesus",
    "wof:placetype":"venue"
},
  "geometry": {"coordinates":[-5.7810750008,41.9211845398],"type":"Point"}
}