{
  "type": "Feature",
  "properties": {
    "addr:full":"Calle de San Jaime, 8 Banyeres Mariola Alicante 03450",
    "addr:housenumber":"8",
    "addr:postcode":"03450",
    "addr:street":"Calle De San Jaime",
    "iso:country":"ES",
    "sg:address":"Calle de San Jaime, 8",
    "sg:city":"Banyeres Mariola",
    "sg:orig_category":"Ropa Para Se\u00d1oras Y Caballeros (al Por Menor)",
    "sg:phone":"+34 965 56 64 30",
    "sg:postcode":"03450",
    "sg:province":"Alicante",
    "wof:name":"Albero Frances Cristobal",
    "wof:placetype":"venue"
},
  "geometry": {"coordinates":[-0.6727505922,38.6310997009],"type":"Point"}
}