{
  "type": "Feature",
  "properties": {
    "addr:full":"Calle de Mayor, 3 Izarra \u00c1lava 01440",
    "addr:housenumber":"3",
    "addr:postcode":"01440",
    "addr:street":"Calle De Mayor;A\u0301Lava",
    "iso:country":"ES",
    "sg:address":"Calle de Mayor, 3",
    "sg:city":"Izarra",
    "sg:orig_category":"Empresas De Carpinter\u00cda De Madera",
    "sg:phone":"+34 945 43 72 59",
    "sg:postcode":"01440",
    "sg:province":"\u00c1lava",
    "wof:name":"Izar Velasco S.l.",
    "wof:placetype":"venue"
},
  "geometry": {"coordinates":[-2.9044690132,42.9536170959],"type":"Point"}
}