{
  "type": "Feature",
  "properties": {
    "addr:full":"Pla\u00c7 Fabrica Nova, 12 Vilanova I La Geltru Barcelona 08800",
    "addr:housenumber":"12",
    "addr:postcode":"08800",
    "iso:country":"ES",
    "sg:address":"Pla\u00c7 Fabrica Nova, 12",
    "sg:city":"Vilanova I La Geltru",
    "sg:orig_category":"Sociedades, Compa\u00d1\u00cdas Aseguradoras",
    "sg:phone":"+34 938 14 45 38",
    "sg:postcode":"08800",
    "sg:province":"Barcelona",
    "wof:name":"Ruiz Mestres Abigail",
    "wof:placetype":"venue"
},
  "geometry": {"coordinates":[1.7170779705,41.2255363464],"type":"Point"}
}