{
  "type": "Feature",
  "properties": {
    "iso:country":"ES",
    "sg:address":"Plaz Mayor, 6",
    "sg:city":"Villanueva Jara",
    "sg:orig_category":"Producci\u00d3n De Champi\u00d1ones",
    "sg:phone":"+34 967 49 85 20",
    "sg:postcode":"16230",
    "sg:province":"Cuenca",
    "wof:name":"Conservas La Jara S.l.",
    "wof:placetype":"venue"
},
  "geometry": {"coordinates":[-1.9583890438,39.4429244995],"type":"Point"}
}