{
  "type": "Feature",
  "properties": {
    "addr:full":"Calle de Rosario, 36 Fompedraza Valladolid 47311",
    "addr:housenumber":"36",
    "addr:postcode":"47311",
    "addr:street":"Calle De Rosario",
    "iso:country":"ES",
    "sg:address":"Calle de Rosario, 36",
    "sg:city":"Fompedraza",
    "sg:orig_category":"Cr\u00cda De Animales",
    "sg:phone":"+34 983 89 20 43",
    "sg:postcode":"47311",
    "sg:province":"Valladolid",
    "wof:name":"Ganados Fompedraza S.l.",
    "wof:placetype":"venue"
},
  "geometry": {"coordinates":[-4.1440029144,41.5355453491],"type":"Point"}
}