{
  "type": "Feature",
  "properties": {
    "iso:country":"ES",
    "sg:address":"Ctra Campo Lopez, Km. 0009,4",
    "sg:city":"Orilla Y Pi\u00e7ero",
    "sg:orig_category":"Arquitectos",
    "sg:phone":"+34 968 44 35 89",
    "sg:postcode":"30800",
    "sg:province":"Murcia",
    "wof:name":"Arquitectos Ingenieros Asociados S.c.",
    "wof:placetype":"venue"
},
  "geometry": {"coordinates":[-1.1298867464,37.9834747314],"type":"Point"}
}