{
  "type": "Feature",
  "properties": {
    "iso:country":"ES",
    "sg:address":"Carrer de Manlleu, 18",
    "sg:city":"Vic",
    "sg:orig_category":"Peluqueros: De Se\u00d1oras",
    "sg:phone":"+34 938 86 18 23",
    "sg:postcode":"08500",
    "sg:province":"Barcelona",
    "wof:name":"Domenech Campas Montserrat",
    "wof:placetype":"venue"
},
  "geometry": {"coordinates":[2.2555100918,41.9317321777],"type":"Point"}
}