{
  "type": "Feature",
  "properties": {
    "addr:full":"Calle de Ponzano, 5 Zaragoza Zaragoza 50004",
    "addr:housenumber":"5",
    "addr:postcode":"50004",
    "addr:street":"Calle De Ponzano",
    "iso:country":"ES",
    "sg:address":"Calle de Ponzano, 5",
    "sg:city":"Zaragoza",
    "sg:orig_category":"Abogados",
    "sg:phone":"+34 976 23 67 84",
    "sg:postcode":"50004",
    "sg:province":"Zaragoza",
    "wof:name":"Rubio Perez Pedro Luis",
    "wof:placetype":"venue"
},
  "geometry": {"coordinates":[-0.8849020004,41.6490898132],"type":"Point"}
}