{
  "type": "Feature",
  "properties": {
    "addr:full":"Avda Madrid, 166 Zaragoza Zaragoza 50017",
    "addr:housenumber":"166",
    "addr:postcode":"50017",
    "addr:street":"Avda Madrid",
    "iso:country":"ES",
    "sg:address":"Avda Madrid, 166",
    "sg:city":"Zaragoza",
    "sg:orig_category":"Zapatos (al Por Menor)",
    "sg:phone":"+34 976 34 43 40",
    "sg:postcode":"50017",
    "sg:province":"Zaragoza",
    "wof:name":"Merkal Calzados S.l.",
    "wof:placetype":"venue"
},
  "geometry": {"coordinates":[-0.9136319757,41.6514701843],"type":"Point"}
}