{
  "type": "Feature",
  "properties": {
    "addr:full":"Rua Frei Rosendo Salvado (de), 21 Santiago De Compostela La Coru\u00f1a 15701",
    "addr:housenumber":"21",
    "addr:postcode":"15701",
    "addr:street":"Rua Frei Rosendo Salvado De;Corun\u0303A",
    "iso:country":"ES",
    "sg:address":"Rua Frei Rosendo Salvado (de), 21",
    "sg:city":"Santiago De Compostela",
    "sg:orig_category":"Quincaller\u00cda (al Por Menor)",
    "sg:phone":"+34 981 59 60 06",
    "sg:postcode":"15701",
    "sg:province":"La Coru\u00f1a",
    "wof:name":"Franqueira Banzas Jesus",
    "wof:placetype":"venue"
},
  "geometry": {"coordinates":[-8.5515966415,42.8721389771],"type":"Point"}
}