{
  "type": "Feature",
  "properties": {
    "iso:country":"ES",
    "sg:address":"Avda Arana Sabino, 38",
    "sg:city":"Bilbao",
    "sg:orig_category":"Farmacias",
    "sg:phone":"+34 944 41 01 82",
    "sg:postcode":"48013",
    "sg:province":"Vizcaya",
    "wof:name":"Garcia Gomez Maria De Los Angeles",
    "wof:placetype":"venue"
},
  "geometry": {"coordinates":[-2.947906971,43.2597312927],"type":"Point"}
}