{
  "type": "Feature",
  "properties": {
    "addr:full":"Calle de Juan Xxiii (de), 2 Mostoles Madrid 28932",
    "addr:postcode":"28932",
    "addr:street":"Calle De Juan Xxiii De 2 Mostoles",
    "iso:country":"ES",
    "sg:address":"Calle de Juan Xxiii (de), 2",
    "sg:city":"Mostoles",
    "sg:orig_category":"Cajas De Ahorro",
    "sg:phone":"+34 916 65 51 32",
    "sg:postcode":"28932",
    "sg:province":"Madrid",
    "wof:name":"Caixa D'estalvis Laietana",
    "wof:placetype":"venue"
},
  "geometry": {"coordinates":[-3.8661930561,40.3205223083],"type":"Point"}
}