{
  "type": "Feature",
  "properties": {
    "addr:full":"Plaz Mayor, 27 Belorado Burgos 09250",
    "addr:housenumber":"27",
    "addr:postcode":"09250",
    "addr:street":"Plaz Mayor",
    "iso:country":"ES",
    "sg:address":"Plaz Mayor, 27",
    "sg:city":"Belorado",
    "sg:orig_category":"Muebles",
    "sg:phone":"+34 947 58 02 69",
    "sg:postcode":"09250",
    "sg:province":"Burgos",
    "wof:name":"Villar Espinosa Marcelo",
    "wof:placetype":"venue"
},
  "geometry": {"coordinates":[-3.1889169216,42.421962738],"type":"Point"}
}