{
  "type": "Feature",
  "properties": {
    "iso:country":"ES",
    "sg:address":"Calle de Santa Maria, 14",
    "sg:city":"Torreperogil",
    "sg:orig_category":"Imprenta",
    "sg:phone":"+34 953 77 70 10",
    "sg:postcode":"23320",
    "sg:province":"Ja\u00e9n",
    "wof:name":"Imprenta La Misericordia S.l.",
    "wof:placetype":"venue"
},
  "geometry": {"coordinates":[-3.2863230705,38.0351867676],"type":"Point"}
}