{
  "type": "Feature",
  "properties": {
    "iso:country":"ES",
    "sg:address":"Calle de General Mina, 15",
    "sg:city":"Mazarambroz",
    "sg:orig_category":"Supermercados Y Hipermercados",
    "sg:phone":"+34 925 39 74 04",
    "sg:postcode":"45114",
    "sg:province":"Toledo",
    "wof:name":"Dorado Sancho Jose Luis",
    "wof:placetype":"venue"
},
  "geometry": {"coordinates":[-4.0194830894,39.6975631714],"type":"Point"}
}