{
  "type": "Feature",
  "properties": {
    "addr:full":"Carrer de Murcia, 28 S. Boi Llobregat Barcelona 08830",
    "addr:housenumber":"28",
    "addr:postcode":"08830",
    "addr:street":"Carrer De Murcia",
    "iso:country":"ES",
    "sg:address":"Carrer de Murcia, 28",
    "sg:city":"S. Boi Llobregat",
    "sg:orig_category":"Electrodom\u00c9sticos (fabricaci\u00d3n, Al Por Mayor)",
    "sg:phone":"+34 936 30 81 80",
    "sg:postcode":"08830",
    "sg:province":"Barcelona",
    "sg:website":"www.dosefes.com",
    "wof:name":"Dos Efes S.a.",
    "wof:placetype":"venue"
},
  "geometry": {"coordinates":[2.0420799255,41.3285903931],"type":"Point"}
}