{
  "type": "Feature",
  "properties": {
    "addr:full":"Calle de San Jose, 8 Valladolid Valladolid 47007",
    "addr:housenumber":"8",
    "addr:postcode":"47007",
    "addr:street":"Calle De San Jose",
    "iso:country":"ES",
    "sg:address":"Calle de San Jose, 8",
    "sg:city":"Valladolid",
    "sg:orig_category":"Juristas",
    "sg:phone":"+34 983 47 03 06",
    "sg:postcode":"47007",
    "sg:province":"Valladolid",
    "wof:name":"Agroin Certificaciones S.l",
    "wof:placetype":"venue"
},
  "geometry": {"coordinates":[-4.7328782082,41.6420669556],"type":"Point"}
}