{
  "type": "Feature",
  "properties": {
    "iso:country":"ES",
    "sg:address":"Calle de Tejeras, 4",
    "sg:city":"Logro\u00f1o",
    "sg:orig_category":"Ropa Para Ni\u00d1os (al Por Menor)",
    "sg:phone":"+34 941 50 50 00",
    "sg:postcode":"26007",
    "sg:province":"La Rioja",
    "sg:website":"www.e-stradivarius.com",
    "wof:name":"Stradivarius Espa\u00d1a S.a.",
    "wof:placetype":"venue"
},
  "geometry": {"coordinates":[-2.5187389851,42.4914894104],"type":"Point"}
}