{
  "type": "Feature",
  "properties": {
    "addr:full":"Avda Miguel De Cervantes-campoamor, 37 Dehesa Campoamor Alicante 03189",
    "addr:housenumber":"37",
    "addr:postcode":"03189",
    "addr:street":"Avda Miguel De Cervantes-Campoamor",
    "iso:country":"ES",
    "sg:address":"Avda Miguel De Cervantes-campoamor, 37",
    "sg:city":"Dehesa Campoamor",
    "sg:orig_category":"Administradores De Bienes Y Delegados De Comunidades De Propietarios",
    "sg:phone":"+34 965 32 30 95",
    "sg:postcode":"03189",
    "sg:province":"Alicante",
    "wof:name":"Perez Lidon Ramona",
    "wof:placetype":"venue"
},
  "geometry": {"coordinates":[-0.7550780177,37.8987541199],"type":"Point"}
}