{
  "type": "Feature",
  "properties": {
    "addr:full":"Ctra Cardona, 37 Manresa Barcelona 08241",
    "addr:housenumber":"37",
    "addr:postcode":"08241",
    "addr:street":"Ctra Cardona",
    "iso:country":"ES",
    "sg:address":"Ctra Cardona, 37",
    "sg:city":"Manresa",
    "sg:orig_category":"Reposter\u00cdas",
    "sg:phone":"+34 938 72 09 53",
    "sg:postcode":"08241",
    "sg:province":"Barcelona",
    "wof:name":"Costa Esquius Juan",
    "wof:placetype":"venue"
},
  "geometry": {"coordinates":[1.8332829475,41.714176178],"type":"Point"}
}