{
  "type": "Feature",
  "properties": {
    "addr:full":"Pg Valldigna (de), 37 Monasterios Valencia 46530",
    "addr:housenumber":"37",
    "addr:postcode":"46530",
    "addr:street":"Pg Valldigna De",
    "iso:country":"ES",
    "sg:address":"Pg Valldigna (de), 37",
    "sg:city":"Monasterios",
    "sg:orig_category":"Pintores",
    "sg:phone":"+34 961 40 61 31",
    "sg:postcode":"46530",
    "sg:province":"Valencia",
    "sg:website":"www.periscarbonell.com",
    "wof:name":"Peris Carbonell Antonio",
    "wof:placetype":"venue"
},
  "geometry": {"coordinates":[-0.3008790016,39.6156044006],"type":"Point"}
}