{
  "type": "Feature",
  "properties": {
    "iso:country":"ES",
    "sg:address":"Av Andalucia(p I Chorrillo-el Prado), 34",
    "sg:city":"Lepe",
    "sg:orig_category":"Inform\u00c1tica, Ofim\u00c1tica (estudios, Asesor\u00cda, Ingenier\u00cda, Formaci\u00d3n)",
    "sg:phone":"+34 959 38 41 91",
    "sg:postcode":"21440",
    "sg:province":"Huelva",
    "wof:name":"Adder Componentes Digitales S.l.",
    "wof:placetype":"venue"
},
  "geometry": {"coordinates":[-7.232925415,37.279296875],"type":"Point"}
}