{
  "type": "Feature",
  "properties": {
    "addr:full":"Avgd Blondel, 31 Lleida Lleida 25002",
    "addr:housenumber":"31",
    "addr:postcode":"25002",
    "addr:street":"Blondel",
    "iso:country":"ES",
    "sg:address":"Avgd Blondel, 31",
    "sg:city":"Lleida",
    "sg:orig_category":"Camiser\u00cda Y Ropa Interior Masculina (al Por Menor)",
    "sg:phone":"+34 973 26 66 65",
    "sg:postcode":"25002",
    "sg:province":"Lleida",
    "wof:name":"Peralta Jovell Maite",
    "wof:placetype":"venue"
},
  "geometry": {"coordinates":[0.6224060059,41.6114425659],"type":"Point"}
}