{
  "type": "Feature",
  "properties": {
    "addr:full":"Ctra. Cabo Blanco, S/n Bahia Grande Islas Baleares 07609",
    "addr:housenumber":"s / n",
    "addr:postcode":"07609",
    "addr:street":"Ctra. Cabo Blanco",
    "iso:country":"ES",
    "sg:address":"Ctra. Cabo Blanco, S/n",
    "sg:city":"Bahia Grande",
    "sg:orig_category":"Arquitectos",
    "sg:phone":"+34 971 74 91 63",
    "sg:postcode":"07609",
    "sg:province":"Islas Baleares",
    "wof:name":"Estudio Arquitectura Tecnica Y Coordinacion S.l.",
    "wof:placetype":"venue"
},
  "geometry": {"coordinates":[2.7507419586,39.4544181824],"type":"Point"}
}