{
  "type": "Feature",
  "properties": {
    "iso:country":"ES",
    "sg:address":"Calle de Juela, 25",
    "sg:city":"Arriate",
    "sg:orig_category":"Charcuter\u00cdas (al Por Mayor)",
    "sg:phone":"+34 952 16 50 72",
    "sg:postcode":"29350",
    "sg:province":"M\u00e1laga",
    "wof:name":"Garcia Orozco Francisco",
    "wof:placetype":"venue"
},
  "geometry": {"coordinates":[-5.141523838,36.7980041504],"type":"Point"}
}