{
  "type": "Feature",
  "properties": {
    "addr:full":"Calle de Santa Rosa, 8 Santiago El Mayor Murcia 30012",
    "addr:housenumber":"8",
    "addr:postcode":"30012",
    "addr:street":"Calle De Santa Rosa",
    "iso:country":"ES",
    "sg:address":"Calle de Santa Rosa, 8",
    "sg:city":"Santiago El Mayor",
    "sg:orig_category":"Supermercados Y Hipermercados",
    "sg:phone":"+34 968 25 14 88",
    "sg:postcode":"30012",
    "sg:province":"Murcia",
    "wof:name":"Garcia Castillo Julian",
    "wof:placetype":"venue"
},
  "geometry": {"coordinates":[-1.1236809492,37.9721260071],"type":"Point"}
}