{
  "type": "Feature",
  "properties": {
    "addr:full":"Mercado Caba\u00f1al, 17 Valencia Valencia 46011",
    "addr:housenumber":"17",
    "addr:postcode":"46011",
    "addr:street":"Valencia",
    "iso:country":"ES",
    "sg:address":"Mercado Caba\u00f1al, 17",
    "sg:city":"Valencia",
    "sg:orig_category":"Carnicer\u00cdas, Carnicer\u00cdas",
    "sg:phone":"+34 963 72 07 46",
    "sg:postcode":"46011",
    "sg:province":"Valencia",
    "wof:name":"Salavert Casas Amparo",
    "wof:placetype":"venue"
},
  "geometry": {"coordinates":[-0.326315999,39.4735183716],"type":"Point"}
}