{
  "type": "Feature",
  "properties": {
    "addr:full":"Quintanes, 1 Parcent Alicante 03792",
    "addr:housenumber":"1",
    "addr:postcode":"03792",
    "addr:street":"Quintanes",
    "iso:country":"ES",
    "sg:address":"Quintanes, 1",
    "sg:city":"Parcent",
    "sg:orig_category":"Bares, Piano",
    "sg:phone":"+34 966 40 52 57",
    "sg:postcode":"03792",
    "sg:province":"Alicante",
    "sg:website":"www.arrakis.es/gutivega",
    "wof:name":"Bodegas Gutierrez De La Vega S.l.",
    "wof:placetype":"venue"
},
  "geometry": {"coordinates":[-0.0638789982,38.7439689636],"type":"Point"}
}