{
  "type": "Feature",
  "properties": {
    "iso:country":"ES",
    "sg:address":"Ctra. Alcantarilla, 78",
    "sg:city":"Puebla De Soto",
    "sg:orig_category":"Torrefactado De Caf\u00c9",
    "sg:phone":"+34 968 83 63 30",
    "sg:postcode":"30836",
    "sg:province":"Murcia",
    "wof:name":"El Taller Del Espresso Capuchino, S. L.",
    "wof:placetype":"venue"
},
  "geometry": {"coordinates":[-1.1857659817,37.9729804993],"type":"Point"}
}