{
  "type": "Feature",
  "properties": {
    "iso:country":"ES",
    "sg:address":"Calle de Lago Van, 17",
    "sg:city":"Madrid",
    "sg:orig_category":"Muebles, Minoristas",
    "sg:phone":"+34 917 76 40 11",
    "sg:postcode":"28032",
    "sg:province":"Madrid",
    "wof:name":"Sacristan Rivas Julio",
    "wof:placetype":"venue"
},
  "geometry": {"coordinates":[-3.6064550877,40.4048957825],"type":"Point"}
}