{
  "type": "Feature",
  "properties": {
    "addr:full":"Calle de Marques De Larios, 4 Malaga M\u00e1laga 29005",
    "addr:housenumber":"4",
    "addr:postcode":"29005",
    "addr:street":"Calle De Marques De Larios;Ma\u0301Laga",
    "iso:country":"ES",
    "sg:address":"Calle de Marques De Larios, 4",
    "sg:city":"Malaga",
    "sg:orig_category":"Impuestos, Tesoro P\u00dablico",
    "sg:phone":"+34 952 06 19 00",
    "sg:postcode":"29005",
    "sg:province":"M\u00e1laga",
    "wof:name":"Sociedad De Tasacion S.a.",
    "wof:placetype":"venue"
},
  "geometry": {"coordinates":[-4.4218211174,36.7201690674],"type":"Point"}
}