{
  "type": "Feature",
  "properties": {
    "addr:full":"G.v. Corts Catalanes, 236 Barcelona Barcelona 08004",
    "addr:housenumber":"236",
    "addr:postcode":"08004",
    "addr:street":"Catalanes",
    "iso:country":"ES",
    "sg:address":"G.v. Corts Catalanes, 236",
    "sg:city":"Barcelona",
    "sg:orig_category":"Comercios E Industrias (cesi\u00d3n Y Reactivaci\u00d3n)",
    "sg:phone":"+34 934 31 13 90",
    "sg:postcode":"08004",
    "sg:province":"Barcelona",
    "wof:name":"Torrent Boladeras Alberto",
    "wof:placetype":"venue"
},
  "geometry": {"coordinates":[2.1429610252,41.3700294495],"type":"Point"}
}