{
  "type": "Feature",
  "properties": {
    "addr:full":"Calle de Alcala De Xivert, 8 Castellon De La Plana Castell\u00f3n 12006",
    "addr:housenumber":"8",
    "addr:postcode":"12006",
    "addr:street":"Calle De Alcala De Xivert",
    "iso:country":"ES",
    "sg:address":"Calle de Alcala De Xivert, 8",
    "sg:city":"Castellon De La Plana",
    "sg:orig_category":"Empresas De Vigilancia, Guardia Y Protecci\u00d3n",
    "sg:phone":"+34 964 25 45 85",
    "sg:postcode":"12006",
    "sg:province":"Castell\u00f3n",
    "wof:name":"Extintores Cano Lopera S.r.l.",
    "wof:placetype":"venue"
},
  "geometry": {"coordinates":[-0.0523625016,39.9720458984],"type":"Point"}
}