{
  "type": "Feature",
  "properties": {
    "addr:full":"Pase Miraconcha De, 6 Donostia-san Sebastian Guip\u00f9zcoa 20007",
    "addr:postcode":"20007",
    "iso:country":"ES",
    "sg:address":"Pase Miraconcha De, 6",
    "sg:city":"Donostia-san Sebastian",
    "sg:classifiers":[
        {
            "category":"Professional",
            "subcategory":"Management & Consulting",
            "type":"Services"
        }
    ],
    "sg:phone":"+34 943 46 28 63",
    "sg:postcode":"20007",
    "sg:province":"Guip\u00f9zcoa",
    "sg:tags":[
        "asesor\u00cda",
        "en",
        "marketing"
    ],
    "wof:name":"Verami S.l.",
    "wof:placetype":"venue"
},
  "geometry": {"coordinates":[-2.0346250534,43.2695808411],"type":"Point"}
}