{
  "type": "Feature",
  "properties": {
    "iso:country":"ES",
    "sg:address":"Rua Estrada, 1",
    "sg:city":"Vigo",
    "sg:orig_category":"Agencias Y Agentes Comerciales, Representantes",
    "sg:phone":"+34 986 21 06 76",
    "sg:postcode":"36209",
    "sg:province":"Pontevedra",
    "wof:name":"Rodriguez Palacio Jose Antonio",
    "wof:placetype":"venue"
},
  "geometry": {"coordinates":[-8.7391691208,42.2205314636],"type":"Point"}
}