{
  "type": "Feature",
  "properties": {
    "addr:full":"Carrer de Ramon Llull, 103 Terrassa Barcelona 08224",
    "addr:housenumber":"103",
    "addr:postcode":"08224",
    "addr:street":"Carrer De Ramon Llull",
    "iso:country":"ES",
    "sg:address":"Carrer de Ramon Llull, 103",
    "sg:city":"Terrassa",
    "sg:orig_category":"Equipos De Marcado, Etiquetado",
    "sg:phone":"+34 937 88 23 49",
    "sg:postcode":"08224",
    "sg:province":"Barcelona",
    "wof:name":"Crimar Retolacio S.l.",
    "wof:placetype":"venue"
},
  "geometry": {"coordinates":[2.0017380714,41.5582962036],"type":"Point"}
}