{
  "type": "Feature",
  "properties": {
    "iso:country":"ES",
    "sg:address":"Crta Isla Menor (p I Fuente Del Rey), 111",
    "sg:city":"Dos Hermanas",
    "sg:orig_category":"Producci\u00d3n De Abonos Y De Fertilizantes",
    "sg:phone":"+34 954 68 05 61",
    "sg:postcode":"41700",
    "sg:province":"Sevilla",
    "wof:name":"Abonos Jimenez S.l.",
    "wof:placetype":"venue"
},
  "geometry": {"coordinates":[-5.922242,37.283176],"type":"Point"}
}