{
  "type": "Feature",
  "properties": {
    "iso:country":"ES",
    "sg:address":"Calle de Cid (el), 13",
    "sg:city":"Roda",
    "sg:orig_category":"Distribuci\u00d3n De Petr\u00d3leo Y Derivados",
    "sg:phone":"+34 967 44 28 12",
    "sg:postcode":"02630",
    "sg:province":"Albacete",
    "wof:name":"Pescaroda S.l.",
    "wof:placetype":"venue"
},
  "geometry": {"coordinates":[-2.1623296738,39.2054672241],"type":"Point"}
}