{
  "type": "Feature",
  "properties": {
    "iso:country":"ES",
    "sg:address":"Calle de Conde De Xiquena, 8",
    "sg:city":"Madrid",
    "sg:orig_category":"Restaurantes",
    "sg:phone":"+34 915 31 31 49",
    "sg:postcode":"28004",
    "sg:province":"Madrid",
    "wof:name":"Analisis Investigacion E Implantacion",
    "wof:placetype":"venue"
},
  "geometry": {"coordinates":[-3.6941246986,40.422908783],"type":"Point"}
}