{
  "type": "Feature",
  "properties": {
    "iso:country":"ES",
    "sg:address":"Calle de Escultor Laviada, 10",
    "sg:city":"Oviedo",
    "sg:orig_category":"Agencias Y Agentes Comerciales, Representantes",
    "sg:phone":"+34 985 96 59 08",
    "sg:postcode":"33012",
    "sg:province":"Asturias",
    "wof:name":"Herranz Peredo Aurelio",
    "wof:placetype":"venue"
},
  "geometry": {"coordinates":[-5.864423275,43.3679771423],"type":"Point"}
}