{
  "type": "Feature",
  "properties": {
    "iso:country":"ES",
    "sg:address":"Carr Glosador Vivo, 54",
    "sg:city":"Ciutadella Menorca",
    "sg:orig_category":"Animales (al Por Menor)",
    "sg:phone":"+34 971 48 19 18",
    "sg:postcode":"07760",
    "sg:province":"Islas Baleares",
    "wof:name":"Club Colombofilo Ciutadella",
    "wof:placetype":"venue"
},
  "geometry": {"coordinates":[3.8445661068,39.999584198],"type":"Point"}
}