{
  "type": "Feature",
  "properties": {
    "iso:country":"ES",
    "sg:address":"Calle de Alejandro Casona, 19",
    "sg:city":"Oviedo",
    "sg:orig_category":"Peluquer\u00cdas",
    "sg:phone":"+34 985 24 02 54",
    "sg:postcode":"33013",
    "sg:province":"Asturias",
    "wof:name":"Gonzalez Zapico Samuel",
    "wof:placetype":"venue"
},
  "geometry": {"coordinates":[-5.8663287163,43.3622932434],"type":"Point"}
}