{
  "type": "Feature",
  "properties": {
    "addr:full":"Calle de Sertorio, 2 Aduanas Alicante 03730",
    "addr:housenumber":"2",
    "addr:postcode":"03730",
    "addr:street":"Calle De Sertorio",
    "iso:country":"ES",
    "sg:address":"Calle de Sertorio, 2",
    "sg:city":"Aduanas",
    "sg:orig_category":"Deportes Diversos",
    "sg:phone":"+34 965 79 26 32",
    "sg:postcode":"03730",
    "sg:province":"Alicante",
    "wof:name":"Fenech Goicoa Vicente",
    "wof:placetype":"venue"
},
  "geometry": {"coordinates":[0.1798650026,38.7943344116],"type":"Point"}
}