{
  "type": "Feature",
  "properties": {
    "addr:full":"Calle de Pablo Iglesias, 3 Langreo Asturias 33900",
    "addr:housenumber":"3",
    "addr:postcode":"33900",
    "addr:street":"Calle De Pablo Iglesias",
    "iso:country":"ES",
    "sg:address":"Calle de Pablo Iglesias, 3",
    "sg:city":"Langreo",
    "sg:orig_category":"Molduras, Junquillos, Listones Y Molduras Perforadas",
    "sg:phone":"+34 985 68 11 36",
    "sg:postcode":"33900",
    "sg:province":"Asturias",
    "wof:name":"Nava Canteli Concepcion",
    "wof:placetype":"venue"
},
  "geometry": {"coordinates":[-5.6828846931,43.2964744568],"type":"Point"}
}