{
  "type": "Feature",
  "properties": {
    "iso:country":"ES",
    "sg:address":"Calle de Concepcion, 6",
    "sg:city":"Velez-blanco",
    "sg:orig_category":"Artesan\u00cda",
    "sg:phone":"+34 950 41 51 95",
    "sg:postcode":"04830",
    "sg:province":"Almer\u00eda",
    "wof:name":"Ceramica Los Velez",
    "wof:placetype":"venue"
},
  "geometry": {"coordinates":[-2.0947840214,37.6937789917],"type":"Point"}
}