{
  "type": "Feature",
  "properties": {
    "addr:full":"Calle de Gaztambide, 46 Madrid Madrid 28015",
    "addr:housenumber":"46",
    "addr:postcode":"madrid;28015",
    "addr:street":"Calle De Gaztambide",
    "iso:country":"ES",
    "sg:address":"Calle de Gaztambide, 46",
    "sg:city":"Madrid",
    "sg:orig_category":"Ingeniero",
    "sg:phone":"+34 915 49 41 07",
    "sg:postcode":"28015",
    "sg:province":"Madrid",
    "wof:name":"Cuartero Cuesta Julian",
    "wof:placetype":"venue"
},
  "geometry": {"coordinates":[-3.7152531147,40.4361724854],"type":"Point"}
}