{
  "type": "Feature",
  "properties": {
    "addr:full":"Carrer de Proven\u00c7a, 16 Barcelona Barcelona 08029",
    "addr:housenumber":"16",
    "addr:postcode":"08029",
    "addr:street":"Carrer De Provenc\u0327A",
    "iso:country":"ES",
    "sg:address":"Carrer de Proven\u00c7a, 16",
    "sg:city":"Barcelona",
    "sg:orig_category":"Pescader\u00cdas (al Por Menor)",
    "sg:phone":"+34 934 19 18 46",
    "sg:postcode":"08029",
    "sg:province":"Barcelona",
    "wof:name":"Calzado Ortega Jose Antonio",
    "wof:placetype":"venue"
},
  "geometry": {"coordinates":[2.1443068981,41.3816108704],"type":"Point"}
}