{
  "type": "Feature",
  "properties": {
    "addr:full":"Calle de Pontevedra, 4 Roquetas Mar Almer\u00eda 04740",
    "addr:housenumber":"4",
    "addr:postcode":"04740",
    "addr:street":"Calle De Pontevedra",
    "iso:country":"ES",
    "sg:address":"Calle de Pontevedra, 4",
    "sg:city":"Roquetas Mar",
    "sg:orig_category":"Organismos De Turismo",
    "sg:phone":"+34 950 32 50 35",
    "sg:postcode":"04740",
    "sg:province":"Almer\u00eda",
    "sg:website":"www.atlassieb.ro",
    "wof:name":"Atlassieb S.l.",
    "wof:placetype":"venue"
},
  "geometry": {"coordinates":[-2.6095075607,36.7773857117],"type":"Point"}
}