{
  "type": "Feature",
  "properties": {
    "addr:full":"Calle de Francisco Sarmiento, 4 Burgos Burgos 09005",
    "addr:housenumber":"4",
    "addr:postcode":"09005",
    "addr:street":"Calle De Francisco Sarmiento",
    "iso:country":"ES",
    "sg:address":"Calle de Francisco Sarmiento, 4",
    "sg:city":"Burgos",
    "sg:orig_category":"Carnicer\u00cdas, Carnicer\u00cdas",
    "sg:phone":"+34 947 22 40 21",
    "sg:postcode":"09005",
    "sg:province":"Burgos",
    "wof:name":"Tajadura Arnaiz Maximo Porfirio",
    "wof:placetype":"venue"
},
  "geometry": {"coordinates":[-3.6956202984,42.3495254517],"type":"Point"}
}