{
  "type": "Feature",
  "properties": {
    "addr:full":"Disseminat, S/n Polinya Barcelona 08213",
    "addr:postcode":"08213",
    "addr:street":"Disseminat S / N Polinya",
    "iso:country":"ES",
    "sg:address":"Disseminat, S/n",
    "sg:city":"Polinya",
    "sg:orig_category":"Barbacoas Y Accesorios",
    "sg:phone":"+34 937 13 36 09",
    "sg:postcode":"08213",
    "sg:province":"Barcelona",
    "wof:name":"Elias Vinardell Quirze",
    "wof:placetype":"venue"
},
  "geometry": {"coordinates":[2.157804966,41.5574531555],"type":"Point"}
}