{
  "type": "Feature",
  "properties": {
    "iso:country":"ES",
    "sg:address":"Calle de Doctor Domingo Deniz, 3",
    "sg:city":"Palmas De Gran Canaria",
    "sg:orig_category":"M\u00c9dicos: Medicina General",
    "sg:phone":"+34 928 36 13 58",
    "sg:postcode":"35002",
    "sg:province":"Las Palmas",
    "wof:name":"Rocafort Lorenzo Salvador",
    "wof:placetype":"venue"
},
  "geometry": {"coordinates":[-15.4169454575,28.1026916504],"type":"Point"}
}