{
  "type": "Feature",
  "properties": {
    "iso:country":"ES",
    "sg:address":"Calle de Gran Via, 64",
    "sg:city":"Madrid",
    "sg:orig_category":"Procuradores",
    "sg:phone":"+34 915 48 72 12",
    "sg:postcode":"28013",
    "sg:province":"Madrid",
    "wof:name":"Martin Moreno Sara",
    "wof:placetype":"venue"
},
  "geometry": {"coordinates":[-3.7088663578,40.4221153259],"type":"Point"}
}