{
  "type": "Feature",
  "properties": {
    "iso:country":"ES",
    "sg:address":"Avda Salobre\u00d1a, 24",
    "sg:city":"Motril",
    "sg:orig_category":"Agencias De Trabajo Temporal",
    "sg:phone":"+34 958 60 89 18",
    "sg:postcode":"18600",
    "sg:province":"Granada",
    "sg:website":"www.vedior.com",
    "wof:name":"Laborman Trabajo Temporal Ett S.a.",
    "wof:placetype":"venue"
},
  "geometry": {"coordinates":[-3.5188140869,36.7434043884],"type":"Point"}
}