{
  "type": "Feature",
  "properties": {
    "addr:full":"Calle de Virgen De La Fuencisla, 17 Madrid Madrid 28027",
    "addr:housenumber":"17",
    "addr:postcode":"madrid;28027",
    "addr:street":"Calle De Virgen De La Fuencisla",
    "iso:country":"ES",
    "sg:address":"Calle de Virgen De La Fuencisla, 17",
    "sg:city":"Madrid",
    "sg:orig_category":"Inform\u00c1tica, Ofim\u00c1tica (estudios, Asesor\u00cda, Ingenier\u00cda, Formaci\u00d3n)",
    "sg:phone":"+34 914 05 46 43",
    "sg:postcode":"28027",
    "sg:province":"Madrid",
    "wof:name":"Tqm Investigacion Y Formacion S.l.",
    "wof:placetype":"venue"
},
  "geometry": {"coordinates":[-3.6512539387,40.4379310608],"type":"Point"}
}