{
  "type": "Feature",
  "properties": {
    "iso:country":"ES",
    "sg:address":"Pase Parque Del, S/n",
    "sg:city":"Sotogrande",
    "sg:orig_category":"Importaci\u00d3n",
    "sg:phone":"+34 956 69 58 80",
    "sg:postcode":"11310",
    "sg:province":"C\u00e1diz",
    "wof:name":"Vazquez Almagro Francisca",
    "wof:placetype":"venue"
},
  "geometry": {"coordinates":[-5.2829370499,36.2767448425],"type":"Point"}
}