{
  "type": "Feature",
  "properties": {
    "addr:full":"Calle de San Antonio, 11 Totana Murcia 30850",
    "addr:housenumber":"11",
    "addr:postcode":"30850",
    "addr:street":"Calle De San Antonio",
    "iso:country":"ES",
    "sg:address":"Calle de San Antonio, 11",
    "sg:city":"Totana",
    "sg:orig_category":"Ropa Para Ni\u00d1os (al Por Menor)",
    "sg:phone":"+34 968 42 77 17",
    "sg:postcode":"30850",
    "sg:province":"Murcia",
    "wof:name":"Veseni Marial S.l.",
    "wof:placetype":"venue"
},
  "geometry": {"coordinates":[-1.5009717941,37.7712936401],"type":"Point"}
}