{
  "type": "Feature",
  "properties": {
    "iso:country":"ES",
    "sg:address":"Urb Vallserrat, 31",
    "sg:city":"S. Esteve Sesrovires",
    "sg:orig_category":"Empresarios",
    "sg:phone":"+34 937 71 33 66",
    "sg:postcode":"08635",
    "sg:province":"Barcelona",
    "wof:name":"Mu\u00f1oz Moreno Juan",
    "wof:placetype":"venue"
},
  "geometry": {"coordinates":[1.8731199503,41.4965515137],"type":"Point"}
}