{
  "type": "Feature",
  "properties": {
    "addr:full":"Calle de Pendon De Baeza, 21 Le\u00f3n Le\u00f3n 24006",
    "addr:housenumber":"21",
    "addr:postcode":"24006",
    "addr:street":"Calle De Pendon;Baeza;Leo\u0301N",
    "iso:country":"ES",
    "sg:address":"Calle de Pendon De Baeza, 21",
    "sg:city":"Le\u00f3n",
    "sg:orig_category":"Asociaciones Y Clubs Deportivos",
    "sg:phone":"+34 987 25 92 62",
    "sg:postcode":"24006",
    "sg:province":"Le\u00f3n",
    "wof:name":"Kumitel Eva Sll",
    "wof:placetype":"venue"
},
  "geometry": {"coordinates":[-5.5616998672,42.5920715332],"type":"Point"}
}