{
  "type": "Feature",
  "properties": {
    "iso:country":"ES",
    "sg:address":"Av Santiga, 3",
    "sg:city":"Santa Perpetua De Mogoda",
    "sg:orig_category":"Agentes, Concesionarios Y Sucursales De Veh\u00cdculos",
    "sg:phone":"+34 935 60 20 64",
    "sg:postcode":"08130",
    "sg:province":"Barcelona",
    "wof:name":"Automoviles Santa Perpetua S.a.",
    "wof:placetype":"venue"
},
  "geometry": {"coordinates":[2.1813876629,41.5371932983],"type":"Point"}
}