{
  "type": "Feature",
  "properties": {
    "addr:full":"Calle de Rio Jucar, S/n Mostoles Madrid 28...",
    "addr:housenumber":"s;28 ...",
    "addr:street":"Calle De Rio Jucar;/ N Mostoles Madrid",
    "iso:country":"ES",
    "sg:address":"Calle de Rio Jucar, S/n",
    "sg:city":"Mostoles",
    "sg:orig_category":"Hospitales",
    "sg:phone":"+34 916 48 98 00",
    "sg:postcode":"28...",
    "sg:province":"Madrid",
    "wof:name":"Tanaki Espa\u00d1a S.a.",
    "wof:placetype":"venue"
},
  "geometry": {"coordinates":[-3.8780677319,40.3154830933],"type":"Point"}
}