{
  "type": "Feature",
  "properties": {
    "iso:country":"ES",
    "sg:address":"Avda Escultora Miss Whitney, 39",
    "sg:city":"Huelva",
    "sg:orig_category":"Instalaci\u00d3n, Reparaci\u00d3n De Ascensores Y Montacargas",
    "sg:phone":"+34 959 23 76 44",
    "sg:postcode":"21003",
    "sg:province":"Huelva",
    "wof:name":"Conservacion Y Montaje De Ascensores Del Sur S.l.",
    "wof:placetype":"venue"
},
  "geometry": {"coordinates":[-6.9403829575,37.2530136108],"type":"Point"}
}