{
  "type": "Feature",
  "properties": {
    "addr:full":"Calle de Jose Oto, 53 Zaragoza Zaragoza 50014",
    "addr:housenumber":"53",
    "addr:postcode":"50014",
    "addr:street":"Calle De Jose Oto",
    "iso:country":"ES",
    "sg:address":"Calle de Jose Oto, 53",
    "sg:city":"Zaragoza",
    "sg:orig_category":"Agua",
    "sg:phone":"+34 976 44 49 82",
    "sg:postcode":"50014",
    "sg:province":"Zaragoza",
    "wof:name":"Calefacciones Mim S.l.",
    "wof:placetype":"venue"
},
  "geometry": {"coordinates":[-0.8651580215,41.6609458923],"type":"Point"}
}