{
  "type": "Feature",
  "properties": {
    "iso:country":"ES",
    "sg:address":"Calle de Torres, 4",
    "sg:city":"Almeria",
    "sg:orig_category":"Peluquer\u00cdas, Peluquer\u00cda Mixta",
    "sg:phone":"+34 950 24 35 80",
    "sg:postcode":"04001",
    "sg:province":"Almer\u00eda",
    "wof:name":"Sanchez Pinte\u00f1o Francisco",
    "wof:placetype":"venue"
},
  "geometry": {"coordinates":[-2.4652810097,36.8403968811],"type":"Point"}
}