{
  "type": "Feature",
  "properties": {
    "addr:full":"Carrer de Amadeu Torner, 70 Hospitalet Llobregat Barcelona 08902",
    "addr:housenumber":"70",
    "addr:postcode":"08902",
    "addr:street":"Carrer De Amadeu Torner",
    "iso:country":"ES",
    "sg:address":"Carrer de Amadeu Torner, 70",
    "sg:city":"Hospitalet Llobregat",
    "sg:orig_category":"Aparatos, Sistemas De Tele",
    "sg:phone":"+34 932 96 66 35",
    "sg:postcode":"08902",
    "sg:province":"Barcelona",
    "wof:name":"Sistemas Y Elementos De Seguridad S.l.",
    "wof:placetype":"venue"
},
  "geometry": {"coordinates":[2.1223640442,41.3623847961],"type":"Point"}
}