{
  "type": "Feature",
  "properties": {
    "iso:country":"ES",
    "sg:address":"Avda Doctor Garcia Tapia, 114",
    "sg:city":"Madrid",
    "sg:orig_category":"Autob\u00das (explotaci\u00d3n Y Servicios De)",
    "sg:phone":"+34 914 37 34 64",
    "sg:postcode":"28030",
    "sg:province":"Madrid",
    "wof:name":"Garcia Mateos Ramon",
    "wof:placetype":"venue"
},
  "geometry": {"coordinates":[-3.6488614082,40.4123077393],"type":"Point"}
}