{
  "type": "Feature",
  "properties": {
    "addr:full":"Carr Magdalena, 32 Lleida Lleida 25007",
    "addr:housenumber":"32",
    "addr:postcode":"25007",
    "addr:street":"Carr Magdalena",
    "iso:country":"ES",
    "sg:address":"Carr Magdalena, 32",
    "sg:city":"Lleida",
    "sg:orig_category":"Telas Y Sedas (al Por Menor)",
    "sg:phone":"+34 973 24 00 92",
    "sg:postcode":"25007",
    "sg:province":"Lleida",
    "wof:name":"Ambients De Casa Enriqueta Olives S.l.",
    "wof:placetype":"venue"
},
  "geometry": {"coordinates":[0.6291286945,41.6190414429],"type":"Point"}
}