{
  "type": "Feature",
  "properties": {
    "addr:full":"Avda Valencia, 51 Zaragoza Zaragoza 50005",
    "addr:housenumber":"51",
    "addr:postcode":"50005",
    "addr:street":"Avda Valencia",
    "iso:country":"ES",
    "sg:address":"Avda Valencia, 51",
    "sg:city":"Zaragoza",
    "sg:orig_category":"Agencias Y Agentes Comerciales, Representantes",
    "sg:phone":"+34 976 35 26 45",
    "sg:postcode":"50005",
    "sg:province":"Zaragoza",
    "wof:name":"Gonzalez Millan Juan",
    "wof:placetype":"venue"
},
  "geometry": {"coordinates":[-0.8986849785,41.6457748413],"type":"Point"}
}