{
  "type": "Feature",
  "properties": {
    "addr:full":"Carrer de Rullan, 15 Palma Islas Baleares 07005",
    "addr:housenumber":"15",
    "addr:postcode":"07005",
    "addr:street":"Carrer De Rullan",
    "iso:country":"ES",
    "sg:address":"Carrer de Rullan, 15",
    "sg:city":"Palma",
    "sg:orig_category":"Panader\u00cdas, Panader\u00cdas",
    "sg:phone":"+34 971 27 85 51",
    "sg:postcode":"07005",
    "sg:province":"Islas Baleares",
    "wof:name":"Mu\u00f1oz Rodriguez Luis",
    "wof:placetype":"venue"
},
  "geometry": {"coordinates":[2.6621000767,39.5812530518],"type":"Point"}
}