{
  "type": "Feature",
  "properties": {
    "addr:full":"Cami Can Frontera, 1 Pla De Na Tesa Islas Baleares 07009",
    "addr:housenumber":"1",
    "addr:postcode":"07009",
    "addr:street":"Islas",
    "iso:country":"ES",
    "sg:address":"Cami Can Frontera, 1",
    "sg:city":"Pla De Na Tesa",
    "sg:orig_category":"Supermercados Y Hipermercados",
    "sg:phone":"+34 971 79 48 01",
    "sg:postcode":"07009",
    "sg:province":"Islas Baleares",
    "wof:name":"Jimenez Calvo Maria Del Carmen",
    "wof:placetype":"venue"
},
  "geometry": {"coordinates":[2.6741399765,39.6011390686],"type":"Point"}
}