{
  "type": "Feature",
  "properties": {
    "iso:country":"ES",
    "sg:address":"Carretera, S/n",
    "sg:city":"Villarquemado",
    "sg:orig_category":"Fabricaci\u00d3n, Instalaci\u00d3n De Escaleras",
    "sg:phone":"+34 978 86 70 96",
    "sg:postcode":"44380",
    "sg:province":"Teruel",
    "wof:name":"Carpinteria Amable S.l.",
    "wof:placetype":"venue"
},
  "geometry": {"coordinates":[-1.2639280558,40.5184440613],"type":"Point"}
}