{
  "type": "Feature",
  "properties": {
    "iso:country":"ES",
    "sg:address":"Calle de Quevedo, 18",
    "sg:city":"Moraleja",
    "sg:orig_category":"Cueros Y Pieles (al Por Mayor)",
    "sg:phone":"+34 927 14 77 66",
    "sg:postcode":"10840",
    "sg:province":"C\u00e1ceres",
    "wof:name":"Garcia Martin Cesareo",
    "wof:placetype":"venue"
},
  "geometry": {"coordinates":[-6.6572589874,40.0722808838],"type":"Point"}
}