{
  "type": "Feature",
  "properties": {
    "addr:full":"Calle de Mayor, 148 Daroca Zaragoza 50360",
    "addr:housenumber":"148",
    "addr:postcode":"50360",
    "addr:street":"Calle De Mayor",
    "iso:country":"ES",
    "sg:address":"Calle de Mayor, 148",
    "sg:city":"Daroca",
    "sg:orig_category":"Estancos",
    "sg:phone":"+34 976 80 01 02",
    "sg:postcode":"50360",
    "sg:province":"Zaragoza",
    "wof:name":"Bello Lopez Maria Paz",
    "wof:placetype":"venue"
},
  "geometry": {"coordinates":[-1.4159929752,41.1137275696],"type":"Point"}
}