{
  "type": "Feature",
  "properties": {
    "iso:country":"ES",
    "sg:address":"Calle de Magallanes, 2",
    "sg:city":"Madrid",
    "sg:orig_category":"Estilistas Y Estudios De Estilo De Corte Y Confecci\u00d3n",
    "sg:phone":"+34 914 48 21 61",
    "sg:postcode":"28015",
    "sg:province":"Madrid",
    "wof:name":"Jaen Pardo Martin",
    "wof:placetype":"venue"
},
  "geometry": {"coordinates":[-3.7049810886,40.4322547913],"type":"Point"}
}