{
  "type": "Feature",
  "properties": {
    "addr:full":"Calle de Santa Barbara, 19 Totana Murcia 30850",
    "addr:housenumber":"19",
    "addr:postcode":"30850",
    "addr:street":"Calle De Santa Barbara",
    "iso:country":"ES",
    "sg:address":"Calle de Santa Barbara, 19",
    "sg:city":"Totana",
    "sg:orig_category":"Asesor\u00cda Sobre Comunicaci\u00d3n De Empresas",
    "sg:phone":"+34 968 42 09 86",
    "sg:postcode":"30850",
    "sg:province":"Murcia",
    "wof:name":"Carchespu\u00f1a S.l.",
    "wof:placetype":"venue"
},
  "geometry": {"coordinates":[-1.4982249737,37.7701721191],"type":"Point"}
}