{
  "type": "Feature",
  "properties": {
    "addr:full":"Calle de Doctor Antonio Cortes Llado, 9 Sevilla Sevilla 41004",
    "addr:housenumber":"9",
    "addr:postcode":"41004",
    "addr:street":"Calle De Doctor Antonio Cortes Llado",
    "iso:country":"ES",
    "sg:address":"Calle de Doctor Antonio Cortes Llado, 9",
    "sg:city":"Sevilla",
    "sg:orig_category":"Peluquer\u00cdas, Peluquer\u00cda Mixta",
    "sg:phone":"+34 954 53 07 99",
    "sg:postcode":"41004",
    "sg:province":"Sevilla",
    "wof:name":"Duomo Serviciosde Peluqueria Y Estetica S.l.",
    "wof:placetype":"venue"
},
  "geometry": {"coordinates":[-5.9810938835,37.3785896301],"type":"Point"}
}