{
  "type": "Feature",
  "properties": {
    "addr:full":"Portela, S/n Portela Ourense 32358",
    "addr:housenumber":"s / n",
    "addr:postcode":"32358",
    "addr:street":"Portela",
    "iso:country":"ES",
    "sg:address":"Portela, S/n",
    "sg:city":"Portela",
    "sg:orig_category":"Negocio De Madera",
    "sg:phone":"+34 988 34 80 20",
    "sg:postcode":"32358",
    "sg:province":"Ourense",
    "wof:name":"Transportes Canda S.l.",
    "wof:placetype":"venue"
},
  "geometry": {"coordinates":[-7.1602640152,42.3461837769],"type":"Point"}
}