{
  "type": "Feature",
  "properties": {
    "addr:full":"Calle de Bolivar, 7 Madrid Madrid 28045",
    "addr:housenumber":"7",
    "addr:postcode":"madrid;28045",
    "addr:street":"Calle De Bolivar",
    "iso:country":"ES",
    "sg:address":"Calle de Bolivar, 7",
    "sg:city":"Madrid",
    "sg:orig_category":"Papeler\u00cdas, Librer\u00cdas",
    "sg:phone":"+34 915 39 57 86",
    "sg:postcode":"28045",
    "sg:province":"Madrid",
    "wof:name":"Pamain S.l.",
    "wof:placetype":"venue"
},
  "geometry": {"coordinates":[-3.6935245991,40.3915901184],"type":"Point"}
}