{
  "type": "Feature",
  "properties": {
    "addr:full":"Calle de Na Jordana, 37 Valencia Valencia 46003",
    "addr:housenumber":"37",
    "addr:postcode":"46003",
    "addr:street":"Calle De Na Jordana",
    "iso:country":"ES",
    "sg:address":"Calle de Na Jordana, 37",
    "sg:city":"Valencia",
    "sg:orig_category":"Comit\u00c9s De Organizaci\u00d3n De Exposiciones, Ferias, Salones",
    "sg:phone":"+34 963 91 71 66",
    "sg:postcode":"46003",
    "sg:province":"Valencia",
    "wof:name":"Bengoechea Carriedo Elena",
    "wof:placetype":"venue"
},
  "geometry": {"coordinates":[-0.3825829923,39.4800491333],"type":"Point"}
}