{
  "type": "Feature",
  "properties": {
    "addr:full":"Calle de Montalban, 13 Granada Granada 18002",
    "addr:housenumber":"13",
    "addr:postcode":"18002",
    "addr:street":"Calle De Montalban",
    "iso:country":"ES",
    "sg:address":"Calle de Montalban, 13",
    "sg:city":"Granada",
    "sg:orig_category":"Asesor\u00cda Fiscal Y Jur\u00cddica",
    "sg:phone":"+34 958 28 92 93",
    "sg:postcode":"18002",
    "sg:province":"Granada",
    "wof:name":"Asesoria Perez Herrera S.l.",
    "wof:placetype":"venue"
},
  "geometry": {"coordinates":[-3.6043393612,37.1768035889],"type":"Point"}
}