{
  "type": "Feature",
  "properties": {
    "addr:full":"Calle de Dos Torres, 56 Pozoblanco C\u00f3rdoba 14400",
    "addr:housenumber":"56",
    "addr:postcode":"14400",
    "addr:street":"Calle De Dos Torres",
    "iso:country":"ES",
    "sg:address":"Calle de Dos Torres, 56",
    "sg:city":"Pozoblanco",
    "sg:orig_category":"Arquitectos",
    "sg:phone":"+34 957 13 16 23",
    "sg:postcode":"14400",
    "sg:province":"C\u00f3rdoba",
    "wof:name":"Olmo Escribano Rafael",
    "wof:placetype":"venue"
},
  "geometry": {"coordinates":[-4.8565607071,38.3817939758],"type":"Point"}
}