{
  "type": "Feature",
  "properties": {
    "iso:country":"ES",
    "sg:address":"Calle de Ribadumia, 3",
    "sg:city":"Madrid",
    "sg:orig_category":"Estancos",
    "sg:phone":"+34 913 20 19 01",
    "sg:postcode":"28022",
    "sg:province":"Madrid",
    "wof:name":"Garcia-moreno Cebeira Carmen",
    "wof:placetype":"venue"
},
  "geometry": {"coordinates":[-3.6107039452,40.4416885376],"type":"Point"}
}