{
  "type": "Feature",
  "properties": {
    "addr:full":"Av Generalitat (la), 45 S. Joan Despi Barcelona 08970",
    "addr:housenumber":"45",
    "addr:postcode":"08970",
    "addr:street":"Av Generalitat La;S. Joan Despi",
    "iso:country":"ES",
    "sg:address":"Av Generalitat (la), 45",
    "sg:city":"S. Joan Despi",
    "sg:orig_category":"Comercio De Piezas De Recambio Y De Accesorios De Veh\u00cdculos, Veh\u00cdculos Industriales",
    "sg:phone":"+34 934 77 06 88",
    "sg:postcode":"08970",
    "sg:province":"Barcelona",
    "wof:name":"Accesorios Nabet S.a.",
    "wof:placetype":"venue"
},
  "geometry": {"coordinates":[2.0651772022,41.3687782288],"type":"Point"}
}