{
  "type": "Feature",
  "properties": {
    "iso:country":"ES",
    "sg:address":"Avda Tres Cruces, 5",
    "sg:city":"Zamora",
    "sg:orig_category":"Ropa Para Se\u00d1oras (al Por Menor)",
    "sg:phone":"+34 980 51 81 45",
    "sg:postcode":"49008",
    "sg:province":"Zamora",
    "wof:name":"Calvo Gutierrez Maria Del Carmen",
    "wof:placetype":"venue"
},
  "geometry": {"coordinates":[-5.7421660423,41.5094680786],"type":"Point"}
}