{
  "type": "Feature",
  "properties": {
    "iso:country":"ES",
    "sg:address":"Calle de Portal De Arriaga, 62",
    "sg:city":"Vitoria-gasteiz",
    "sg:orig_category":"Rectificaci\u00d3n, Mecanizado, Fresado",
    "sg:phone":"+34 945 27 35 55",
    "sg:postcode":"01013",
    "sg:province":"\u00c1lava",
    "wof:name":"Mecanizados Mefer S.l.",
    "wof:placetype":"venue"
},
  "geometry": {"coordinates":[-2.6732010841,42.8563194275],"type":"Point"}
}