{
  "type": "Feature",
  "properties": {
    "iso:country":"ES",
    "sg:address":"Calle de San Miguel, 62",
    "sg:city":"Sang\u00fcesa",
    "sg:orig_category":"Ense\u00d1anza, Formaci\u00d3n Profesional: Aprendizaje",
    "sg:phone":"+34 948 87 14 17",
    "sg:postcode":"31400",
    "sg:province":"Navarra",
    "wof:name":"Ayuntamiento De Sanguesa",
    "wof:placetype":"venue"
},
  "geometry": {"coordinates":[-1.2818390131,42.5760688782],"type":"Point"}
}