{
  "type": "Feature",
  "properties": {
    "addr:full":"Calle de Madrid, 37 Alacant Alicante 03002",
    "addr:housenumber":"37",
    "addr:postcode":"03002",
    "addr:street":"Calle De Madrid",
    "iso:country":"ES",
    "sg:address":"Calle de Madrid, 37",
    "sg:city":"Alacant",
    "sg:orig_category":"Grafistas",
    "sg:phone":"+34 965 16 14 13",
    "sg:postcode":"03002",
    "sg:province":"Alicante",
    "sg:website":"www.capicor.com",
    "wof:name":"Dise\u00f1o Integral Capicor S.l.",
    "wof:placetype":"venue"
},
  "geometry": {"coordinates":[-0.473793,38.3493118286],"type":"Point"}
}