{
  "type": "Feature",
  "properties": {
    "iso:country":"ES",
    "sg:address":"Carrer de Mallorca, 277",
    "sg:city":"Barcelona",
    "sg:orig_category":"Agentes Generales De Seguros",
    "sg:phone":"+34 932 15 39 12",
    "sg:postcode":"08037",
    "sg:province":"Barcelona",
    "wof:name":"Albiol Biosca Enrique",
    "wof:placetype":"venue"
},
  "geometry": {"coordinates":[2.1640486717,41.3949966431],"type":"Point"}
}