{
  "type": "Feature",
  "properties": {
    "iso:country":"ES",
    "sg:address":"Calle de Trapero (el), 32",
    "sg:city":"Baeza",
    "sg:orig_category":"M\u00c1quinas De Coser Y De Hacer Punto (al Por Mayor)",
    "sg:phone":"+34 953 74 11 19",
    "sg:postcode":"23440",
    "sg:province":"Ja\u00e9n",
    "wof:name":"Jimenez Garcia Mariano",
    "wof:placetype":"venue"
},
  "geometry": {"coordinates":[-3.4734530449,37.9970779419],"type":"Point"}
}