{
  "type": "Feature",
  "properties": {
    "iso:country":"ES",
    "sg:address":"Plaz Salvador El, 8",
    "sg:city":"Sari\u00f1ena",
    "sg:orig_category":"Producci\u00d3n, Venta De Productos De Agricultura Biol\u00d3gica",
    "sg:phone":"+34 974 57 02 36",
    "sg:postcode":"22200",
    "sg:province":"Huesca",
    "wof:name":"Rega\u00f1o Blasco C.b.",
    "wof:placetype":"venue"
},
  "geometry": {"coordinates":[-0.157468006,41.7911071777],"type":"Point"}
}