{
  "type": "Feature",
  "properties": {
    "addr:full":"Calle de Antonio De Leyva, 61 Zaragoza Zaragoza 50011",
    "addr:housenumber":"61",
    "addr:postcode":"50011",
    "addr:street":"Calle De Antonio De Leyva",
    "iso:country":"ES",
    "sg:address":"Calle de Antonio De Leyva, 61",
    "sg:city":"Zaragoza",
    "sg:orig_category":"Estancos",
    "sg:phone":"+34 976 34 04 73",
    "sg:postcode":"50011",
    "sg:province":"Zaragoza",
    "wof:name":"Rubio Melendo Maria Ascension",
    "wof:placetype":"venue"
},
  "geometry": {"coordinates":[-0.9259461761,41.6515769958],"type":"Point"}
}