{
  "type": "Feature",
  "properties": {
    "addr:full":"Calle de Padre Pandelo, 40 Linea De La Concepcion C\u00e1diz 11300",
    "addr:housenumber":"40",
    "addr:postcode":"11300",
    "addr:street":"Calle De Padre Pandelo;Ca\u0301Diz",
    "iso:country":"ES",
    "sg:address":"Calle de Padre Pandelo, 40",
    "sg:city":"Linea De La Concepcion",
    "sg:orig_category":"Iglesia Cat\u00d3lica",
    "sg:phone":"+34 956 76 20 38",
    "sg:postcode":"11300",
    "sg:province":"C\u00e1diz",
    "wof:name":"Parroquia San Jose",
    "wof:placetype":"venue"
},
  "geometry": {"coordinates":[-5.3454289436,36.170009613],"type":"Point"}
}