{
  "type": "Feature",
  "properties": {
    "iso:country":"ES",
    "sg:address":"Seg. Estacion, S/n",
    "sg:city":"Gomecello",
    "sg:orig_category":"Frutas Y Legumbres Frescas (al Por Mayor)",
    "sg:phone":"+34 923 35 00 63",
    "sg:postcode":"37420",
    "sg:province":"Salamanca",
    "wof:name":"Garcia Almaraz Manuel",
    "wof:placetype":"venue"
},
  "geometry": {"coordinates":[-5.5381441116,41.0441207886],"type":"Point"}
}