{
  "type": "Feature",
  "properties": {
    "addr:full":"Carrer de Septimania, 46 Barcelona Barcelona 08006",
    "addr:housenumber":"46",
    "addr:postcode":"08006",
    "addr:street":"Carrer De Septimania",
    "iso:country":"ES",
    "sg:address":"Carrer de Septimania, 46",
    "sg:city":"Barcelona",
    "sg:orig_category":"Artes Gr\u00c1ficas, Artes Pl\u00c1sticas (curso)",
    "sg:phone":"+34 932 11 24 57",
    "sg:postcode":"08006",
    "sg:province":"Barcelona",
    "wof:name":"Marti Galbis Esteban",
    "wof:placetype":"venue"
},
  "geometry": {"coordinates":[2.1459391117,41.4048423767],"type":"Point"}
}