{
  "type": "Feature",
  "properties": {
    "iso:country":"ES",
    "sg:address":"Calle de Berlin, 71",
    "sg:city":"Parla",
    "sg:orig_category":"Puertas Y Portales",
    "sg:phone":"+34 916 98 27 43",
    "sg:postcode":"28980",
    "sg:province":"Madrid",
    "wof:name":"Nilsson Motor S.l.",
    "wof:placetype":"venue"
},
  "geometry": {"coordinates":[-3.7492494583,40.2389335632],"type":"Point"}
}