{
  "type": "Feature",
  "properties": {
    "iso:country":"ES",
    "sg:address":"Pl Divina Pastora, 10",
    "sg:city":"Vic",
    "sg:orig_category":"Electrodom\u00c9sticos (al Por Menor)",
    "sg:phone":"+34 938 86 42 38",
    "sg:postcode":"08500",
    "sg:province":"Barcelona",
    "sg:website":"www.electroahorro.com",
    "wof:name":"Ejja Ahrorro Y Garnatia",
    "wof:placetype":"venue"
},
  "geometry": {"coordinates":[2.26029706,41.930644989],"type":"Point"}
}