{
  "type": "Feature",
  "properties": {
    "iso:country":"ES",
    "sg:address":"Avda Regne De Valencia, 70",
    "sg:city":"Valencia",
    "sg:orig_category":"Asesor\u00cda Sobre Comunicaci\u00d3n De Empresas",
    "sg:phone":"+34 963 16 15 34",
    "sg:postcode":"46005",
    "sg:province":"Valencia",
    "wof:name":"Fos Bernabeu Juan Vicente",
    "wof:placetype":"venue"
},
  "geometry": {"coordinates":[-0.3652879894,39.4629592896],"type":"Point"}
}