{
  "type": "Feature",
  "properties": {
    "iso:country":"ES",
    "sg:address":"Cmno Cartagena, 760",
    "sg:city":"San Cristobal",
    "sg:orig_category":"Producci\u00d3n, Venta De Productos De Agricultura Biol\u00d3gica",
    "sg:phone":"+34 968 46 18 90",
    "sg:postcode":"30815",
    "sg:province":"Murcia",
    "wof:name":"Reverte Diaz Antonio",
    "wof:placetype":"venue"
},
  "geometry": {"coordinates":[-1.5774840117,37.5886192322],"type":"Point"}
}