{
  "type": "Feature",
  "properties": {
    "iso:country":"ES",
    "sg:address":"Ctra Marzagan De, 52",
    "sg:city":"Marzagan",
    "sg:orig_category":"Empresas De Carpinter\u00cda",
    "sg:phone":"+34 928 71 15 97",
    "sg:postcode":"35017",
    "sg:province":"Las Palmas",
    "wof:name":"Aluter San Roque S.l.",
    "wof:placetype":"venue"
},
  "geometry": {"coordinates":[-15.420627594,28.0409412384],"type":"Point"}
}