{
  "type": "Feature",
  "properties": {
    "iso:country":"ES",
    "sg:address":"Avda Gaiarre Julian, 32",
    "sg:city":"Bilbao",
    "sg:orig_category":"Carnicer\u00cdas, Carnicer\u00cdas",
    "sg:phone":"+34 944 12 65 68",
    "sg:postcode":"48004",
    "sg:province":"Vizcaya",
    "wof:name":"Pallares Marquez Maria Pilar",
    "wof:placetype":"venue"
},
  "geometry": {"coordinates":[-2.9009590149,43.2552680969],"type":"Point"}
}