{
  "type": "Feature",
  "properties": {
    "iso:country":"ES",
    "sg:address":"Calle de Arrabal, 44",
    "sg:city":"Laguna Duero",
    "sg:orig_category":"Empresas De Carpinter\u00cda",
    "sg:phone":"+34 983 54 17 83",
    "sg:postcode":"47140",
    "sg:province":"Valladolid",
    "wof:name":"Alba De Vega Jose Luis",
    "wof:placetype":"venue"
},
  "geometry": {"coordinates":[-4.7236909866,41.5813369751],"type":"Point"}
}