{
  "type": "Feature",
  "properties": {
    "addr:full":"Calle de Uruguay, 6 Navahermosa Toledo 45150",
    "addr:housenumber":"6",
    "addr:postcode":"45150",
    "addr:street":"Calle De Uruguay",
    "iso:country":"ES",
    "sg:address":"Calle de Uruguay, 6",
    "sg:city":"Navahermosa",
    "sg:orig_category":"T\u00c9cnicos Veterinarios",
    "sg:phone":"+34 925 42 83 03",
    "sg:postcode":"45150",
    "sg:province":"Toledo",
    "wof:name":"Perez De Vargas Cabrero Juan Ramon",
    "wof:placetype":"venue"
},
  "geometry": {"coordinates":[-4.4626131058,39.6326217651],"type":"Point"}
}