{
  "type": "Feature",
  "properties": {
    "addr:full":"Calle de Algemesi, 52 Madrid Madrid 28042",
    "addr:housenumber":"52",
    "addr:postcode":"madrid;28042",
    "addr:street":"Calle De Algemesi",
    "iso:country":"ES",
    "sg:address":"Calle de Algemesi, 52",
    "sg:city":"Madrid",
    "sg:orig_category":"Empresarios",
    "sg:phone":"+34 913 29 43 87",
    "sg:postcode":"28042",
    "sg:province":"Madrid",
    "wof:name":"Reparaciones Ramos S.l",
    "wof:placetype":"venue"
},
  "geometry": {"coordinates":[-3.5813047886,40.4726257324],"type":"Point"}
}