{
  "type": "Feature",
  "properties": {
    "iso:country":"ES",
    "sg:address":"Puerta De Granada, S/n",
    "sg:city":"Velez-rubio",
    "sg:orig_category":"Pescader\u00cdas (al Por Menor)",
    "sg:phone":"+34 950 41 00 32",
    "sg:postcode":"04820",
    "sg:province":"Almer\u00eda",
    "wof:name":"Perez Moreno Antonio",
    "wof:placetype":"venue"
},
  "geometry": {"coordinates":[-2.0764939785,37.6506996155],"type":"Point"}
}