{
  "type": "Feature",
  "properties": {
    "iso:country":"ES",
    "sg:address":"Calle de Jose San Martin, 1",
    "sg:city":"Vitoria-gasteiz",
    "sg:orig_category":"Peluqueros: De Se\u00d1oras",
    "sg:phone":"+34 945 27 93 46",
    "sg:postcode":"01003",
    "sg:province":"\u00c1lava",
    "wof:name":"M\u00aa Asun Contrasta",
    "wof:placetype":"venue"
},
  "geometry": {"coordinates":[-2.6619939804,42.8491859436],"type":"Point"}
}