{
  "type": "Feature",
  "properties": {
    "addr:full":"Calle de Sargento Mena, 8 Ceuta Ceuta 51001",
    "addr:housenumber":"8",
    "addr:postcode":"51001",
    "addr:street":"Calle De Sargento Mena",
    "iso:country":"ES",
    "sg:address":"Calle de Sargento Mena, 8",
    "sg:city":"Ceuta",
    "sg:orig_category":"Edici\u00d3n De Diarios, Revistas, Boletines",
    "sg:phone":"+34 956 52 40 35",
    "sg:postcode":"51001",
    "sg:province":"Ceuta",
    "wof:name":"Joaquin Ferrer Y Cia.s.a.",
    "wof:placetype":"venue"
},
  "geometry": {"coordinates":[-5.3087749481,35.8887519836],"type":"Point"}
}