{
  "type": "Feature",
  "properties": {
    "iso:country":"ES",
    "sg:address":"Cmno Villa Santa (de), 1",
    "sg:city":"Chiclana De La Frontera",
    "sg:orig_category":"Guarda",
    "sg:phone":"+34 956 40 84 26",
    "sg:postcode":"11130",
    "sg:province":"C\u00e1diz",
    "wof:name":"Mudanzas Bernabe S.l",
    "wof:placetype":"venue"
},
  "geometry": {"coordinates":[-6.1326007843,36.4381752014],"type":"Point"}
}