{
  "type": "Feature",
  "properties": {
    "addr:full":"Calle de Paz La, 5 Huelva Huelva 21003",
    "addr:housenumber":"5",
    "addr:postcode":"21003",
    "addr:street":"Calle De Paz La",
    "iso:country":"ES",
    "sg:address":"Calle de Paz La, 5",
    "sg:city":"Huelva",
    "sg:orig_category":"Informaci\u00d3n Financiera Y Comercial",
    "sg:phone":"+34 959 25 19 56",
    "sg:postcode":"21003",
    "sg:province":"Huelva",
    "wof:name":"Nu\u00f1ez Yanes Maria Angeles",
    "wof:placetype":"venue"
},
  "geometry": {"coordinates":[-6.9495940208,37.256313324],"type":"Point"}
}