{
  "type": "Feature",
  "properties": {
    "iso:country":"ES",
    "sg:address":"Ctra. Sabadell-granollers, Km. 0013,5",
    "sg:city":"Lli\u00e7a Vall",
    "sg:orig_category":"Cerrajer\u00cda, Ferrallista",
    "sg:phone":"+34 938 43 74 49",
    "sg:postcode":"08185",
    "sg:province":"Barcelona",
    "sg:website":"www.arcasrg.com",
    "wof:name":"Talleres Rodriguez Gil S.l.",
    "wof:placetype":"venue"
},
  "geometry": {"coordinates":[2.2324490547,41.5865364075],"type":"Point"}
}