{
  "type": "Feature",
  "properties": {
    "iso:country":"ES",
    "sg:address":"Afores, S/n",
    "sg:city":"Ogassa",
    "sg:orig_category":"Cr\u00cda De Animales",
    "sg:phone":"+34 972 72 02 83",
    "sg:postcode":"17861",
    "sg:province":"Girona",
    "wof:name":"Vila Puigcorbe Lluis",
    "wof:placetype":"venue"
},
  "geometry": {"coordinates":[2.2777171135,42.2658004761],"type":"Point"}
}