{
  "type": "Feature",
  "properties": {
    "addr:full":"Pase Marques De Corvera, 28 Carmen Murcia 30002",
    "addr:housenumber":"28",
    "addr:postcode":"30002",
    "addr:street":"Marques;Corvera",
    "iso:country":"ES",
    "sg:address":"Pase Marques De Corvera, 28",
    "sg:city":"Carmen",
    "sg:orig_category":"Cajas Para Embalar",
    "sg:phone":"+34 968 34 02 20",
    "sg:postcode":"30002",
    "sg:province":"Murcia",
    "sg:website":"www.cajamar.es",
    "wof:name":"Cajamar",
    "wof:placetype":"venue"
},
  "geometry": {"coordinates":[-1.1302499771,37.9829597473],"type":"Point"}
}