{
  "type": "Feature",
  "properties": {
    "addr:full":"Carrer de Sant Damia, 172 Terrassa Barcelona 08222",
    "addr:housenumber":"172",
    "addr:postcode":"08222",
    "addr:street":"Carrer De Sant Damia",
    "iso:country":"ES",
    "sg:address":"Carrer de Sant Damia, 172",
    "sg:city":"Terrassa",
    "sg:orig_category":"Molduras, Junquillos, Listones Y Molduras Perforadas",
    "sg:phone":"+34 937 83 62 33",
    "sg:postcode":"08222",
    "sg:province":"Barcelona",
    "wof:name":"Frances Simon Juan Antonio",
    "wof:placetype":"venue"
},
  "geometry": {"coordinates":[2.0309898853,41.5631408691],"type":"Point"}
}