{
  "type": "Feature",
  "properties": {
    "addr:full":"Calle de Barrio Seco, S/n Trefacio Zamora 49359",
    "addr:housenumber":"s / n",
    "addr:postcode":"49359",
    "addr:street":"Calle De Barrio Seco",
    "iso:country":"ES",
    "sg:address":"Calle de Barrio Seco, S/n",
    "sg:city":"Trefacio",
    "sg:orig_category":"Iglesia Cat\u00d3lica",
    "sg:phone":"+34 980 62 83 42",
    "sg:postcode":"49359",
    "sg:province":"Zamora",
    "wof:name":"Diocesis Astorga Administracion",
    "wof:placetype":"venue"
},
  "geometry": {"coordinates":[-6.6524267197,42.1228294373],"type":"Point"}
}