{
  "type": "Feature",
  "properties": {
    "iso:country":"ES",
    "sg:address":"Calle de Telde, 44",
    "sg:city":"S. Pedro Martir I",
    "sg:orig_category":"Promotores Constructores",
    "sg:phone":"+34 928 75 65 54",
    "sg:postcode":"35110",
    "sg:province":"Las Palmas",
    "wof:name":"Proyescan S.l.",
    "wof:placetype":"venue"
},
  "geometry": {"coordinates":[-15.4485340118,27.8392906189],"type":"Point"}
}