{
  "type": "Feature",
  "properties": {
    "iso:country":"ES",
    "sg:address":"Calle de Longuera (la), 31",
    "sg:city":"Longuera",
    "sg:orig_category":"Quincaller\u00cda (al Por Menor)",
    "sg:phone":"+34 922 36 20 02",
    "sg:postcode":"38418",
    "sg:province":"Santa Cruz De Tenerife",
    "wof:name":"Martin Sanchez Hernandez Calle S. L.",
    "wof:placetype":"venue"
},
  "geometry": {"coordinates":[-16.5776081085,28.3974990845],"type":"Point"}
}