{
  "type": "Feature",
  "properties": {
    "addr:full":"Calle de Alcala De Henares, 10 Granada Granada 18008",
    "addr:housenumber":"10",
    "addr:postcode":"18008",
    "addr:street":"Calle De Alcala De Henares",
    "iso:country":"ES",
    "sg:address":"Calle de Alcala De Henares, 10",
    "sg:city":"Granada",
    "sg:orig_category":"Asesor\u00cda Sobre Comunicaci\u00d3n De Empresas",
    "sg:phone":"+34 958 81 44 66",
    "sg:postcode":"18008",
    "sg:province":"Granada",
    "wof:name":"Ideas Contables S.l.",
    "wof:placetype":"venue"
},
  "geometry": {"coordinates":[-3.5896646976,37.1640357971],"type":"Point"}
}