{
  "type": "Feature",
  "properties": {
    "iso:country":"ES",
    "sg:address":"Calle de Estacion, S/n",
    "sg:city":"Xeraco",
    "sg:orig_category":"Fabricaci\u00d3n De Motores El\u00c9ctricos",
    "sg:phone":"+34 962 89 24 10",
    "sg:postcode":"46770",
    "sg:province":"Valencia",
    "sg:website":"www.ifimoto.com",
    "wof:name":"Industrias Francisco Ivars S.l.",
    "wof:placetype":"venue"
},
  "geometry": {"coordinates":[-0.218403995,39.0325698853],"type":"Point"}
}