{
  "type": "Feature",
  "properties": {
    "addr:full":"Rua Almirante Matos, 25 Pontevedra Pontevedra 36002",
    "addr:housenumber":"25",
    "addr:postcode":"36002",
    "addr:street":"Rua Almirante Matos",
    "iso:country":"ES",
    "sg:address":"Rua Almirante Matos, 25",
    "sg:city":"Pontevedra",
    "sg:orig_category":"Pintura, Barniz, Productos Asimilables (fabricaci\u00d3n, Al Por Mayor)",
    "sg:phone":"+34 986 85 95 00",
    "sg:postcode":"36002",
    "sg:province":"Pontevedra",
    "wof:name":"Almacenes Celso Miguez S. A.",
    "wof:placetype":"venue"
},
  "geometry": {"coordinates":[-8.6523475647,42.431350708],"type":"Point"}
}