{
  "type": "Feature",
  "properties": {
    "addr:full":"Calle de Doctor Jimenez Diaz Del, 4 Aviles Asturias 33402",
    "addr:housenumber":"4",
    "addr:postcode":"33402",
    "addr:street":"Calle De Doctor Jimenez Diaz Del",
    "iso:country":"ES",
    "sg:address":"Calle de Doctor Jimenez Diaz Del, 4",
    "sg:city":"Aviles",
    "sg:orig_category":"Empresas De Desmonte",
    "sg:phone":"+34 985 54 14 02",
    "sg:postcode":"33402",
    "sg:province":"Asturias",
    "wof:name":"G.ovies S.a.",
    "wof:placetype":"venue"
},
  "geometry": {"coordinates":[-5.9287648201,43.5531539917],"type":"Point"}
}