{
  "type": "Feature",
  "properties": {
    "addr:full":"Calle de Maria Auxiliadora, 1 Huesca Huesca 22003",
    "addr:housenumber":"1",
    "addr:postcode":"22003",
    "addr:street":"Calle De Maria Auxiliadora",
    "iso:country":"ES",
    "sg:address":"Calle de Maria Auxiliadora, 1",
    "sg:city":"Huesca",
    "sg:orig_category":"Cr\u00cda De Animales",
    "sg:phone":"+34 974 22 45 49",
    "sg:postcode":"22003",
    "sg:province":"Huesca",
    "wof:name":"Martinez Abadia Agustin",
    "wof:placetype":"venue"
},
  "geometry": {"coordinates":[-0.4119631052,42.1402854919],"type":"Point"}
}