{
  "type": "Feature",
  "properties": {
    "iso:country":"ES",
    "sg:address":"Rubi, 4",
    "sg:city":"Mijas Costa",
    "sg:orig_category":"Suministros Y Materiales Industriales",
    "sg:phone":"+34 952 93 42 97",
    "sg:postcode":"29649",
    "sg:province":"M\u00e1laga",
    "wof:name":"Comercial Sistemas Lineales S.l.",
    "wof:placetype":"venue"
},
  "geometry": {"coordinates":[-4.707034111,36.5010719299],"type":"Point"}
}