{
  "type": "Feature",
  "properties": {
    "addr:full":"Plaz Duque De Mandas, 26 Alhama Granada Granada 18120",
    "addr:housenumber":"26",
    "addr:postcode":"18120",
    "addr:street":"Mandas",
    "iso:country":"ES",
    "sg:address":"Plaz Duque De Mandas, 26",
    "sg:city":"Alhama Granada",
    "sg:orig_category":"Mec\u00c1nico Del Autom\u00d3vil",
    "sg:phone":"+34 958 35 05 92",
    "sg:postcode":"18120",
    "sg:province":"Granada",
    "wof:name":"Antonio Calderon C.b.",
    "wof:placetype":"venue"
},
  "geometry": {"coordinates":[-3.9913249016,37.0036354065],"type":"Point"}
}