{
  "type": "Feature",
  "properties": {
    "addr:full":"Pg Verdum, 2 Barcelona Barcelona 08016",
    "addr:housenumber":"2",
    "addr:postcode":"08016",
    "addr:street":"Pg Verdum",
    "iso:country":"ES",
    "sg:address":"Pg Verdum, 2",
    "sg:city":"Barcelona",
    "sg:orig_category":"Farmacias",
    "sg:phone":"+34 933 54 57 04",
    "sg:postcode":"08016",
    "sg:province":"Barcelona",
    "wof:name":"Andres Carbo Luz",
    "wof:placetype":"venue"
},
  "geometry": {"coordinates":[2.1723175049,41.4356765747],"type":"Point"}
}