{
  "type": "Feature",
  "properties": {
    "addr:full":"Avda Primero De Mayo, S/n Puertollano Ciudad Real 13500",
    "addr:housenumber":"s / n",
    "addr:postcode":"13500",
    "addr:street":"Avda Primero De Mayo",
    "iso:country":"ES",
    "sg:address":"Avda Primero De Mayo, S/n",
    "sg:city":"Puertollano",
    "sg:orig_category":"Art\u00cdculos De Regalo (al Por Menor)",
    "sg:phone":"+34 926 43 05 07",
    "sg:postcode":"13500",
    "sg:province":"Ciudad Real",
    "wof:name":"Ruben Y Ricardo Asociados",
    "wof:placetype":"venue"
},
  "geometry": {"coordinates":[-4.1051487923,38.6864356995],"type":"Point"}
}