{
  "type": "Feature",
  "properties": {
    "iso:country":"ES",
    "sg:address":"Calle de Doctor Eduardo Evangelista, 12",
    "sg:city":"San Pedro Alcantara",
    "sg:orig_category":"Farmacias",
    "sg:phone":"+34 952 78 92 79",
    "sg:postcode":"29670",
    "sg:province":"M\u00e1laga",
    "wof:name":"Nieto Palacios Remedio",
    "wof:placetype":"venue"
},
  "geometry": {"coordinates":[-4.9960479736,36.4857177734],"type":"Point"}
}