{
  "type": "Feature",
  "properties": {
    "addr:full":"Bo Providencia, S/n Archena Murcia 30600",
    "addr:housenumber":"s / n",
    "addr:postcode":"30600",
    "iso:country":"ES",
    "sg:address":"Bo Providencia, S/n",
    "sg:city":"Archena",
    "sg:orig_category":"Comercio, Reparaci\u00d3n De Motocicletas, Bicicletas Y Piezas Sueltas",
    "sg:phone":"+34 968 67 09 22",
    "sg:postcode":"30600",
    "sg:province":"Murcia",
    "wof:name":"Marin Quesada Jose",
    "wof:placetype":"venue"
},
  "geometry": {"coordinates":[-1.2987289429,38.117401123],"type":"Point"}
}