{
  "type": "Feature",
  "properties": {
    "addr:full":"Ctra General Santa Cruz Laguna, 116 Gracia Santa Cruz De Tenerife 38205",
    "addr:housenumber":"116",
    "addr:postcode":"38205",
    "addr:street":"Ctra General;Gracia",
    "iso:country":"ES",
    "sg:address":"Ctra General Santa Cruz Laguna, 116",
    "sg:city":"Gracia",
    "sg:orig_category":"Chapister\u00cda",
    "sg:phone":"+34 922 25 08 42",
    "sg:postcode":"38205",
    "sg:province":"Santa Cruz De Tenerife",
    "wof:name":"Alvarez Exposito Julio",
    "wof:placetype":"venue"
},
  "geometry": {"coordinates":[-16.2548561096,28.4698104858],"type":"Point"}
}