{
  "type": "Feature",
  "properties": {
    "addr:full":"Calle de Navalaosa (de La), 20 Colmenar Viejo Madrid 28770",
    "addr:postcode":"28770",
    "addr:street":"Calle De Navalaosa De La",
    "iso:country":"ES",
    "sg:address":"Calle de Navalaosa (de La), 20",
    "sg:city":"Colmenar Viejo",
    "sg:orig_category":"Peleter\u00cdas",
    "sg:phone":"+34 918 45 26 06",
    "sg:postcode":"28770",
    "sg:province":"Madrid",
    "wof:name":"Concepiel S.l.",
    "wof:placetype":"venue"
},
  "geometry": {"coordinates":[-3.7629590034,40.6607131958],"type":"Point"}
}