{
  "type": "Feature",
  "properties": {
    "addr:full":"Avda Burgos, 20 Aranda Duero Burgos 09400",
    "addr:housenumber":"20",
    "addr:postcode":"09400",
    "addr:street":"Avda Burgos",
    "iso:country":"ES",
    "sg:address":"Avda Burgos, 20",
    "sg:city":"Aranda Duero",
    "sg:orig_category":"Venta, Colocaci\u00d3n, Reparaci\u00d3n De Parabrisas, Techos Descapotables",
    "sg:phone":"+34 947 51 01 52",
    "sg:postcode":"09400",
    "sg:province":"Burgos",
    "wof:name":"Cristal Del Automovil De La Rivera S.l.",
    "wof:placetype":"venue"
},
  "geometry": {"coordinates":[-3.6791660786,41.66954422],"type":"Point"}
}