{
  "type": "Feature",
  "properties": {
    "addr:full":"Calle de Guindos (de Los), 31 San Sebastian De Los Reyes Madrid 28700",
    "addr:housenumber":"31",
    "addr:postcode":"28700",
    "addr:street":"Calle De Guindos De Los",
    "iso:country":"ES",
    "sg:address":"Calle de Guindos (de Los), 31",
    "sg:city":"San Sebastian De Los Reyes",
    "sg:orig_category":"Flores Y Plantas Naturales (al Por Mayor)",
    "sg:phone":"+34 916 51 94 71",
    "sg:postcode":"28700",
    "sg:province":"Madrid",
    "wof:name":"Sanseflor S.a.l.",
    "wof:placetype":"venue"
},
  "geometry": {"coordinates":[-3.6182079315,40.5450325012],"type":"Point"}
}