{
  "type": "Feature",
  "properties": {
    "iso:country":"ES",
    "sg:address":"Carrer de Baro De Coubertin, 8",
    "sg:city":"Olot",
    "sg:orig_category":"Cuchiller\u00cda (al Por Menor)",
    "sg:phone":"+34 972 26 45 56",
    "sg:postcode":"17800",
    "sg:province":"Girona",
    "wof:name":"Cuinsa S. A.",
    "wof:placetype":"venue"
},
  "geometry": {"coordinates":[2.47438097,42.1900138855],"type":"Point"}
}