{
  "type": "Feature",
  "properties": {
    "iso:country":"ES",
    "sg:address":"Avenida Toques, 57",
    "sg:city":"Melide",
    "sg:orig_category":"Flores Y Plantas Naturales (al Por Mayor)",
    "sg:phone":"+34 981 50 53 35",
    "sg:postcode":"15800",
    "sg:province":"La Coru\u00f1a",
    "wof:name":"Jose Xaneiro S.l.",
    "wof:placetype":"venue"
},
  "geometry": {"coordinates":[-8.0142192841,42.9189109802],"type":"Point"}
}