{
  "type": "Feature",
  "properties": {
    "addr:full":"Avda Castilla La Mancha, 7 Villahermosa Ciudad Real 13332",
    "addr:housenumber":"7",
    "addr:postcode":"13332",
    "addr:street":"Avda Castilla La Mancha",
    "iso:country":"ES",
    "sg:address":"Avda Castilla La Mancha, 7",
    "sg:city":"Villahermosa",
    "sg:orig_category":"Florister\u00cdas",
    "sg:phone":"+34 926 36 60 12",
    "sg:postcode":"13332",
    "sg:province":"Ciudad Real",
    "wof:name":"Moya Sanchez Alicia",
    "wof:placetype":"venue"
},
  "geometry": {"coordinates":[-2.8752229214,38.7509384155],"type":"Point"}
}