{
  "type": "Feature",
  "properties": {
    "iso:country":"ES",
    "sg:address":"Calle de Azkuene, 9",
    "sg:city":"Donostia-san Sebastian",
    "sg:orig_category":"Frutas, Legumbres Frescas Y Tempranas (al Por Menor)",
    "sg:phone":"+34 943 39 72 19",
    "sg:postcode":"20017",
    "sg:province":"Guip\u00f9zcoa",
    "wof:name":"Antonio Carrasco Su Fruteria S.l.",
    "wof:placetype":"venue"
},
  "geometry": {"coordinates":[-1.9379184246,43.3249549866],"type":"Point"}
}