{
  "type": "Feature",
  "properties": {
    "iso:country":"ES",
    "sg:address":"Rua Santa Uxia, 10",
    "sg:city":"Santa Uxia De Ribeira",
    "sg:orig_category":"Platos Preparados Refrigerados (fabricaci\u00d3n, Al Por Mayor)",
    "sg:phone":"+34 981 87 44 65",
    "sg:postcode":"15960",
    "sg:province":"La Coru\u00f1a",
    "wof:name":"A Patela Sl Unipersonal",
    "wof:placetype":"venue"
},
  "geometry": {"coordinates":[-8.992307663,42.5555114746],"type":"Point"}
}