{
  "type": "Feature",
  "properties": {
    "addr:full":"Ibarra Kalea, 19 Bergara Guip\u00f9zcoa 20570",
    "addr:housenumber":"19",
    "addr:postcode":"20570",
    "addr:street":"Ibarra Kalea;Guipu\u0300Zcoa",
    "iso:country":"ES",
    "sg:address":"Ibarra Kalea, 19",
    "sg:city":"Bergara",
    "sg:orig_category":"Aceros Inoxidables",
    "sg:phone":"+34 943 76 48 77",
    "sg:postcode":"20570",
    "sg:province":"Guip\u00f9zcoa",
    "wof:name":"Tornilleria Argi S.a.",
    "wof:placetype":"venue"
},
  "geometry": {"coordinates":[-2.4240260124,43.1048088074],"type":"Point"}
}