{
  "type": "Feature",
  "properties": {
    "addr:full":"Av Cami Dels Capellans, 24 Sitges Barcelona 08870",
    "addr:housenumber":"24",
    "addr:postcode":"08870",
    "addr:street":"Av Cami Dels Capellans",
    "iso:country":"ES",
    "sg:address":"Av Cami Dels Capellans, 24",
    "sg:city":"Sitges",
    "sg:orig_category":"Reposter\u00cdas",
    "sg:phone":"+34 938 11 11 39",
    "sg:postcode":"08870",
    "sg:province":"Barcelona",
    "wof:name":"Ortega Novella Maria",
    "wof:placetype":"venue"
},
  "geometry": {"coordinates":[1.8099000454,41.2404212952],"type":"Point"}
}