{
  "type": "Feature",
  "properties": {
    "iso:country":"ES",
    "sg:address":"Pg Generalitat, 17",
    "sg:city":"Vic",
    "sg:orig_category":"Reposter\u00cdas",
    "sg:phone":"+34 938 85 04 95",
    "sg:postcode":"08500",
    "sg:province":"Barcelona",
    "wof:name":"Forn De Pa I Bolleria Riera S.l.",
    "wof:placetype":"venue"
},
  "geometry": {"coordinates":[2.2535328865,41.9235801697],"type":"Point"}
}