{
  "type": "Feature",
  "properties": {
    "addr:full":"Calle de San Juan Bosco, 38 Almeria Almer\u00eda 04005",
    "addr:housenumber":"38",
    "addr:postcode":"04005",
    "addr:street":"Calle De San Juan Bosco",
    "iso:country":"ES",
    "sg:address":"Calle de San Juan Bosco, 38",
    "sg:city":"Almeria",
    "sg:orig_category":"Lencer\u00cda Femenina, Corseter\u00cda, Trajes De Ba\u00d1o (al Por Menor)",
    "sg:phone":"+34 950 26 07 49",
    "sg:postcode":"04005",
    "sg:province":"Almer\u00eda",
    "wof:name":"Maevas C.b.",
    "wof:placetype":"venue"
},
  "geometry": {"coordinates":[-2.4535360336,36.8426780701],"type":"Point"}
}