{
  "type": "Feature",
  "properties": {
    "iso:country":"ES",
    "sg:address":"Avda Chiprana, 12",
    "sg:city":"Caspe",
    "sg:classifiers":[
        {
            "category":"Autos & Motor Vehicles",
            "subcategory":"Automobile Sales",
            "type":"Retail Goods"
        }
    ],
    "sg:phone":"+34 976 63 03 73",
    "sg:postcode":"50700",
    "sg:province":"Zaragoza",
    "wof:name":"Perdiguero Ballester Manuel",
    "wof:placetype":"venue"
},
  "geometry": {"coordinates":[-0.047313001,41.2358970642],"type":"Point"}
}