{
  "type": "Feature",
  "properties": {
    "iso:country":"ES",
    "sg:address":"Calle de Guare\u00d1a, 6",
    "sg:city":"Don Benito",
    "sg:orig_category":"Grafistas",
    "sg:phone":"+34 924 81 34 19",
    "sg:postcode":"06400",
    "sg:province":"Badajoz",
    "wof:name":"Lasser Cat",
    "wof:placetype":"venue"
},
  "geometry": {"coordinates":[-5.8669290543,38.960018158],"type":"Point"}
}