{
  "type": "Feature",
  "properties": {
    "iso:country":"ES",
    "sg:address":"Carrer de Juan Ramon Jimenez, 30",
    "sg:city":"Rubi",
    "sg:orig_category":"Molduras, Junquillos, Listones Y Molduras Perforadas",
    "sg:phone":"+34 936 97 16 61",
    "sg:postcode":"08191",
    "sg:province":"Barcelona",
    "wof:name":"Escolano Espinosa Jorge",
    "wof:placetype":"venue"
},
  "geometry": {"coordinates":[2.0393950939,41.4879798889],"type":"Point"}
}