{
  "type": "Feature",
  "properties": {
    "iso:country":"ES",
    "sg:address":"Plaz Santa Cecilia, S/n",
    "sg:city":"Salamanca",
    "sg:orig_category":"Asistencia Social",
    "sg:phone":"+34 923 27 02 93",
    "sg:postcode":"37008",
    "sg:province":"Salamanca",
    "wof:name":"Ayuntamiento De Salamanca-centro Polivalente San Jose",
    "wof:placetype":"venue"
},
  "geometry": {"coordinates":[-5.6624660492,40.9508781433],"type":"Point"}
}