{
  "type": "Feature",
  "properties": {
    "addr:full":"Calle de Celestino Junquera, 2 Gijon Asturias 33202",
    "addr:housenumber":"2",
    "addr:postcode":"33202",
    "addr:street":"Calle De Celestino Junquera",
    "iso:country":"ES",
    "sg:address":"Calle de Celestino Junquera, 2",
    "sg:city":"Gijon",
    "sg:orig_category":"Marroquiner\u00cda (confecci\u00d3n)",
    "sg:phone":"+34 985 34 33 78",
    "sg:postcode":"33202",
    "sg:province":"Asturias",
    "wof:name":"Ramon Alvarez Representaciones S.l.",
    "wof:placetype":"venue"
},
  "geometry": {"coordinates":[-5.6580257416,43.5392112732],"type":"Point"}
}