{
  "type": "Feature",
  "properties": {
    "iso:country":"ES",
    "sg:address":"Plaz Porfirio Lopez, 13",
    "sg:city":"Astorga",
    "sg:orig_category":"Caf\u00c9s, Bares, Cervecer\u00cdas",
    "sg:phone":"+34 987 60 26 20",
    "sg:postcode":"24700",
    "sg:province":"Le\u00f3n",
    "wof:name":"El Inmigrante Luso S.l.",
    "wof:placetype":"venue"
},
  "geometry": {"coordinates":[-6.0519490242,42.4572181702],"type":"Point"}
}