{
  "type": "Feature",
  "properties": {
    "iso:country":"ES",
    "sg:address":"Carrer de Corsega, 230",
    "sg:city":"Barcelona",
    "sg:orig_category":"Textil",
    "sg:phone":"+34 932 18 91 42",
    "sg:postcode":"08036",
    "sg:province":"Barcelona",
    "wof:name":"Ruiz Martinez Maria Antonia",
    "wof:placetype":"venue"
},
  "geometry": {"coordinates":[2.1542420387,41.3925056458],"type":"Point"}
}