{
  "type": "Feature",
  "properties": {
    "iso:country":"ES",
    "sg:address":"Av Costa Brava, 86",
    "sg:city":"Malgrat Mar",
    "sg:orig_category":"Muebles Y Accesorios Para Cocinas Y Cuartos De Ba\u00d1o (al Por Menor)",
    "sg:phone":"+34 937 61 42 52",
    "sg:postcode":"08380",
    "sg:province":"Barcelona",
    "wof:name":"Aluminis Escudeo S.l.",
    "wof:placetype":"venue"
},
  "geometry": {"coordinates":[2.7347033024,41.6448898315],"type":"Point"}
}