{
  "type": "Feature",
  "properties": {
    "iso:country":"ES",
    "sg:address":"Calle de Nava, 8",
    "sg:city":"Gijon",
    "sg:orig_category":"Electricidad, Electr\u00d3nica: Material Y Suministros (al Por Mayor)",
    "sg:phone":"+34 985 17 50 82",
    "sg:postcode":"33207",
    "sg:province":"Asturias",
    "wof:name":"Empresa Comercial De Recreativos S.a.",
    "wof:placetype":"venue"
},
  "geometry": {"coordinates":[-5.6707000732,43.5386047363],"type":"Point"}
}