{
  "type": "Feature",
  "properties": {
    "addr:full":"Carrer de Salvador Olivella, 9 Sitges Barcelona 08870",
    "addr:housenumber":"9",
    "addr:postcode":"08870",
    "addr:street":"Carrer De Salvador Olivella",
    "iso:country":"ES",
    "sg:address":"Carrer de Salvador Olivella, 9",
    "sg:city":"Sitges",
    "sg:orig_category":"Agencias Y Agentes Comerciales, Representantes",
    "sg:phone":"+34 938 11 02 58",
    "sg:postcode":"08870",
    "sg:province":"Barcelona",
    "wof:name":"Capo Antich Maria Juana",
    "wof:placetype":"venue"
},
  "geometry": {"coordinates":[1.8053380251,41.2383537292],"type":"Point"}
}