{
  "type": "Feature",
  "properties": {
    "iso:country":"ES",
    "sg:address":"Ctra Roca (la) Km 10,3-12,2, Km. 0012,7",
    "sg:city":"S. Fost Campsentelles",
    "sg:orig_category":"Cajas Y Embalajes Met\u00c1licos",
    "sg:phone":"+34 935 70 47 12",
    "sg:postcode":"08105",
    "sg:province":"Barcelona",
    "wof:name":"Witte Y Sola S.a.",
    "wof:placetype":"venue"
},
  "geometry": {"coordinates":[2.2226347923,41.5208930969],"type":"Point"}
}