{
  "type": "Feature",
  "properties": {
    "addr:full":"Calle de Porto Cristo, 9 Alcorcon Madrid 28924",
    "addr:housenumber":"9",
    "addr:postcode":"28924",
    "addr:street":"Calle De Porto Cristo",
    "iso:country":"ES",
    "sg:address":"Calle de Porto Cristo, 9",
    "sg:city":"Alcorcon",
    "sg:orig_category":"M\u00c9dicos: Estomatolog\u00cda",
    "sg:phone":"+34 916 19 59 97",
    "sg:postcode":"28924",
    "sg:province":"Madrid",
    "wof:name":"Rodriguez Marquez Francisco",
    "wof:placetype":"venue"
},
  "geometry": {"coordinates":[-3.8173799515,40.3513870239],"type":"Point"}
}