{
  "type": "Feature",
  "properties": {
    "iso:country":"ES",
    "sg:address":"Los Caidos-la Vega, S/n",
    "sg:city":"Santiago",
    "sg:orig_category":"Fabricaci\u00d3n De Muebles",
    "sg:phone":"+34 985 74 85 61",
    "sg:postcode":"33518",
    "sg:province":"Asturias",
    "wof:name":"Martinez Naves Marta Maria",
    "wof:placetype":"venue"
},
  "geometry": {"coordinates":[-5.5597882271,43.4101409912],"type":"Point"}
}