{
  "type": "Feature",
  "properties": {
    "iso:country":"ES",
    "sg:address":"Calle de Santisima Trinidad, 30",
    "sg:city":"Madrid",
    "sg:orig_category":"Asesor\u00cda Fiscal Y Jur\u00cddica",
    "sg:phone":"+34 914 47 57 76",
    "sg:postcode":"28010",
    "sg:province":"Madrid",
    "wof:name":"Alvarez Guerrero Jose Ramon",
    "wof:placetype":"venue"
},
  "geometry": {"coordinates":[-3.7010524273,40.4380302429],"type":"Point"}
}