{
  "type": "Feature",
  "properties": {
    "iso:country":"ES",
    "sg:address":"Calle de Real, 25",
    "sg:city":"Huercal Almeria",
    "sg:classifiers":[
        {
            "category":"Autos & Motor Vehicles",
            "subcategory":"Automobile Sales",
            "type":"Retail Goods"
        }
    ],
    "sg:phone":"+34 950 60 08 65",
    "sg:postcode":"04230",
    "sg:province":"Almer\u00eda",
    "wof:name":"Autoescuela Bajo Andarax S.l",
    "wof:placetype":"venue"
},
  "geometry": {"coordinates":[-2.4357953072,36.8825149536],"type":"Point"}
}