{
  "type": "Feature",
  "properties": {
    "iso:country":"ES",
    "sg:address":"Rua Sampaio, 12",
    "sg:city":"Ourense",
    "sg:orig_category":"Cajas De Ahorro",
    "sg:phone":"+34 988 37 37 31",
    "sg:postcode":"32001",
    "sg:province":"Ourense",
    "wof:name":"Caixa De Aforros De Vigo Ourense E Pontevedra",
    "wof:placetype":"venue"
},
  "geometry": {"coordinates":[-7.8745570183,42.3494644165],"type":"Point"}
}