{
  "type": "Feature",
  "properties": {
    "iso:country":"ES",
    "sg:address":"Avda Constitucion, 30",
    "sg:city":"Novelda",
    "sg:orig_category":"Florister\u00cdas",
    "sg:phone":"+34 965 60 41 38",
    "sg:postcode":"03660",
    "sg:province":"Alicante",
    "wof:name":"Abadia Sempere Teresa",
    "wof:placetype":"venue"
},
  "geometry": {"coordinates":[-0.762392,38.382961],"type":"Point"}
}