{
  "type": "Feature",
  "properties": {
    "addr:full":"Carr Girona, 7 Campdevanol Girona 17530",
    "addr:housenumber":"7",
    "addr:postcode":"17530",
    "addr:street":"Carr Girona",
    "iso:country":"ES",
    "sg:address":"Carr Girona, 7",
    "sg:city":"Campdevanol",
    "sg:classifiers":[
        {
            "category":"Manufacturing",
            "subcategory":"Building Materials",
            "type":"Manufacturing & Wholesale Goods"
        }
    ],
    "sg:phone":"+34 972 73 00 43",
    "sg:postcode":"17530",
    "sg:province":"Girona",
    "sg:tags":[
        "cemento",
        "y",
        "de",
        "fabricaci\u00d3n",
        "cal"
    ],
    "wof:name":"Villaro Orriols Juan",
    "wof:placetype":"venue"
},
  "geometry": {"coordinates":[2.1704668999,42.2252960205],"type":"Point"}
}