{
  "type": "Feature",
  "properties": {
    "iso:country":"ES",
    "sg:address":"Centro Comercial Valterna, S/n",
    "sg:city":"Paterna",
    "sg:orig_category":"Armaduras De Hormig\u00d3n",
    "sg:phone":"+34 961 36 52 14",
    "sg:postcode":"46980",
    "sg:province":"Valencia",
    "wof:name":"Estructuras Terramar S.l.",
    "wof:placetype":"venue"
},
  "geometry": {"coordinates":[-0.4395389855,39.500629425],"type":"Point"}
}