{
  "type": "Feature",
  "properties": {
    "iso:country":"ES",
    "sg:address":"Calle de Emilia Pardo Bazan, 4",
    "sg:city":"Zubia",
    "sg:orig_category":"Negocio De Materiales De Construcci\u00d3n",
    "sg:phone":"+34 958 59 27 67",
    "sg:postcode":"18140",
    "sg:province":"Granada",
    "wof:name":"Impermeabilizaciones Y Aislamientos Coca S.l.",
    "wof:placetype":"venue"
},
  "geometry": {"coordinates":[-3.578938961,37.1264343262],"type":"Point"}
}