{
  "type": "Feature",
  "properties": {
    "addr:full":"Calle de Secundino Esnaola, 39 Donostia-san Sebastian Guip\u00f9zcoa 20001",
    "addr:housenumber":"39",
    "addr:postcode":"20001",
    "addr:street":"Calle De Secundino Esnaola",
    "iso:country":"ES",
    "sg:address":"Calle de Secundino Esnaola, 39",
    "sg:city":"Donostia-san Sebastian",
    "sg:orig_category":"Ense\u00d1anza: Idiomas",
    "sg:phone":"+34 943 29 24 74",
    "sg:postcode":"20001",
    "sg:province":"Guip\u00f9zcoa",
    "sg:website":"www.lacunza.es",
    "wof:name":"Academia Lacunza S.a.",
    "wof:placetype":"venue"
},
  "geometry": {"coordinates":[-1.9718714952,43.3244018555],"type":"Point"}
}