{
  "type": "Feature",
  "properties": {
    "addr:full":"Calle de Fray Juan Regla, 22 Zaragoza Zaragoza 50017",
    "addr:housenumber":"22",
    "addr:postcode":"50017",
    "addr:street":"Calle De Fray Juan Regla",
    "iso:country":"ES",
    "sg:address":"Calle de Fray Juan Regla, 22",
    "sg:city":"Zaragoza",
    "sg:orig_category":"Poller\u00cda Y Caza (al Por Menor)",
    "sg:phone":"+34 976 31 20 48",
    "sg:postcode":"50017",
    "sg:province":"Zaragoza",
    "wof:name":"Rojas Rodrigo Angeles",
    "wof:placetype":"venue"
},
  "geometry": {"coordinates":[-0.9141259789,41.6506233215],"type":"Point"}
}