{
  "type": "Feature",
  "properties": {
    "iso:country":"ES",
    "sg:address":"Prj. La Cumbre, S/n",
    "sg:city":"Ejido",
    "sg:orig_category":"Alquiler De Gr\u00daas",
    "sg:phone":"+34 950 16 22 73",
    "sg:postcode":"04700",
    "sg:province":"Almer\u00eda",
    "sg:website":"www.gruascanton.com",
    "wof:name":"Gruas Canton S.l.",
    "wof:placetype":"venue"
},
  "geometry": {"coordinates":[-2.7580699921,36.7285690308],"type":"Point"}
}