{
  "type": "Feature",
  "properties": {
    "iso:country":"ES",
    "sg:address":"Olivo, 29",
    "sg:city":"Lloret Mar",
    "sg:orig_category":"Comerciantes Al Por Mayor De Vinos, Licores Y Alcoholes",
    "sg:phone":"+34 972 37 08 74",
    "sg:postcode":"17310",
    "sg:province":"Girona",
    "wof:name":"Campos Iba\u00f1ez Juan",
    "wof:placetype":"venue"
},
  "geometry": {"coordinates":[2.8461010456,41.7021484375],"type":"Point"}
}