{
  "type": "Feature",
  "properties": {
    "iso:country":"ES",
    "sg:address":"Rua Carlos Iii, 38",
    "sg:city":"Becerrea",
    "sg:orig_category":"Bancos",
    "sg:phone":"+34 982 36 01 99",
    "sg:postcode":"27640",
    "sg:province":"Lugo",
    "wof:name":"Banco Pastor",
    "wof:placetype":"venue"
},
  "geometry": {"coordinates":[-7.1613059044,42.8526229858],"type":"Point"}
}