{
  "type": "Feature",
  "properties": {
    "iso:country":"ES",
    "sg:address":"Calle de Convento Santa Clara, 11",
    "sg:city":"Valencia",
    "sg:orig_category":"Parques De Atracciones Y Centros De Esparcimiento",
    "sg:phone":"+34 963 57 03 06",
    "sg:postcode":"46002",
    "sg:province":"Valencia",
    "wof:name":"Billares Valencia S.l.",
    "wof:placetype":"venue"
},
  "geometry": {"coordinates":[-0.3765319884,39.4681167603],"type":"Point"}
}