{
  "type": "Feature",
  "properties": {
    "addr:full":"Carrer de Quintana, 19 Sabadell Barcelona 08205",
    "addr:housenumber":"19",
    "addr:postcode":"08205",
    "addr:street":"Carrer De Quintana",
    "iso:country":"ES",
    "sg:address":"Carrer de Quintana, 19",
    "sg:city":"Sabadell",
    "sg:orig_category":"Rectificaci\u00d3n, Mecanizado, Fresado",
    "sg:phone":"+34 937 27 60 00",
    "sg:postcode":"08205",
    "sg:province":"Barcelona",
    "wof:name":"Rectificados Tecles S.l.",
    "wof:placetype":"venue"
},
  "geometry": {"coordinates":[2.0979950428,41.5397529602],"type":"Point"}
}