{
  "type": "Feature",
  "properties": {
    "iso:country":"ES",
    "sg:address":"Plaza De La Filarmonica, 2",
    "sg:city":"Olivenza",
    "sg:orig_category":"Agencias De Viajes",
    "sg:phone":"+34 924 49 06 93",
    "sg:postcode":"06100",
    "sg:province":"Badajoz",
    "wof:name":"Villoslada Garcia Maria Dolores",
    "wof:placetype":"venue"
},
  "geometry": {"coordinates":[-7.1010890007,38.6827507019],"type":"Point"}
}