{
  "type": "Feature",
  "properties": {
    "addr:full":"Calle de Santa Ana, 72 Madridejos Toledo 45710",
    "addr:housenumber":"72",
    "addr:postcode":"45710",
    "addr:street":"Calle De Santa Ana",
    "iso:country":"ES",
    "sg:address":"Calle de Santa Ana, 72",
    "sg:city":"Madridejos",
    "sg:orig_category":"Venta, Montaje De Neum\u00c1ticos",
    "sg:phone":"+34 925 46 08 77",
    "sg:postcode":"45710",
    "sg:province":"Toledo",
    "wof:name":"Abajo Recalde Juan De",
    "wof:placetype":"venue"
},
  "geometry": {"coordinates":[-3.527184,39.467319],"type":"Point"}
}