{
  "type": "Feature",
  "properties": {
    "iso:country":"ES",
    "sg:address":"Calle de Laguna Del Marquesado, 19",
    "sg:city":"Madrid",
    "sg:orig_category":"Material Y Suministros Para Fotocopiadoras, Reprograf\u00cda",
    "sg:phone":"+34 917 98 58 87",
    "sg:postcode":"28021",
    "sg:province":"Madrid",
    "wof:name":"Gr Digital S.l.",
    "wof:placetype":"venue"
},
  "geometry": {"coordinates":[-3.7056839466,40.333568573],"type":"Point"}
}