{
  "type": "Feature",
  "properties": {
    "iso:country":"ES",
    "sg:address":"Calle de Cuevas De Almanzora, 40",
    "sg:city":"Madrid",
    "sg:orig_category":"Peluquer\u00cdas, Peluquer\u00cda Mixta",
    "sg:phone":"+34 917 66 99 87",
    "sg:postcode":"28033",
    "sg:province":"Madrid",
    "wof:name":"Velarde Gonzalez Julia",
    "wof:placetype":"venue"
},
  "geometry": {"coordinates":[-3.6575100422,40.4776725769],"type":"Point"}
}