{
  "type": "Feature",
  "properties": {
    "addr:full":"Calle de Garcia Sanchez, 28 Zaragoza Zaragoza 50005",
    "addr:housenumber":"28",
    "addr:postcode":"50005",
    "addr:street":"Calle De Garcia Sanchez",
    "iso:country":"ES",
    "sg:address":"Calle de Garcia Sanchez, 28",
    "sg:city":"Zaragoza",
    "sg:orig_category":"Cajas De Ahorro",
    "sg:phone":"+34 976 55 16 06",
    "sg:postcode":"50005",
    "sg:province":"Zaragoza",
    "wof:name":"Caja De Ahorros Y Monte De Piedad De Zaragoza Aragon Y Rioja",
    "wof:placetype":"venue"
},
  "geometry": {"coordinates":[-0.8995950222,41.6478652954],"type":"Point"}
}