{
  "type": "Feature",
  "properties": {
    "iso:country":"ES",
    "sg:address":"Calle de San Isidro (de), 1",
    "sg:city":"Rivas Vaciamadrid",
    "sg:orig_category":"Molduras, Junquillos, Listones Y Molduras Perforadas",
    "sg:phone":"+34 916 70 45 80",
    "sg:postcode":"28529",
    "sg:province":"Madrid",
    "wof:name":"Rodriguez Arencon Maria Rosa",
    "wof:placetype":"venue"
},
  "geometry": {"coordinates":[-3.5182828903,40.3265838623],"type":"Point"}
}