{
  "type": "Feature",
  "properties": {
    "iso:country":"ES",
    "sg:address":"Carrer de Francesc Marti I M, 12",
    "sg:city":"Palma",
    "sg:orig_category":"M\u00c9dicos: Estomatolog\u00cda",
    "sg:phone":"+34 971 73 18 43",
    "sg:postcode":"07011",
    "sg:province":"Islas Baleares",
    "wof:name":"Amoros Cerda Enrique",
    "wof:placetype":"venue"
},
  "geometry": {"coordinates":[2.6400418282,39.5788040161],"type":"Point"}
}