{
  "type": "Feature",
  "properties": {
    "iso:country":"ES",
    "sg:address":"Calle de Corredera, 25",
    "sg:city":"Lebrija",
    "sg:orig_category":"Ropa Para Ni\u00d1os (al Por Menor)",
    "sg:phone":"+34 955 97 03 30",
    "sg:postcode":"41740",
    "sg:province":"Sevilla",
    "wof:name":"Guerrero Silva Juan Benito",
    "wof:placetype":"venue"
},
  "geometry": {"coordinates":[-6.0762104988,36.9195518494],"type":"Point"}
}