{
  "type": "Feature",
  "properties": {
    "iso:country":"ES",
    "sg:address":"Calle de Juan De La Cierva, 18",
    "sg:city":"Villaviciosa Odon",
    "sg:orig_category":"V\u00c1lvulas",
    "sg:phone":"+34 916 16 37 31",
    "sg:postcode":"28670",
    "sg:province":"Madrid",
    "wof:name":"Angodos Sl",
    "wof:placetype":"venue"
},
  "geometry": {"coordinates":[-3.9149792194,40.3618850708],"type":"Point"}
}