{
  "type": "Feature",
  "properties": {
    "addr:full":"Calle de Dos De Mayo, 12 Valladolid Valladolid 47004",
    "addr:housenumber":"12",
    "addr:postcode":"47004",
    "addr:street":"Calle De Dos;Mayo",
    "iso:country":"ES",
    "sg:address":"Calle de Dos De Mayo, 12",
    "sg:city":"Valladolid",
    "sg:orig_category":"Arquitectos",
    "sg:phone":"+34 983 30 93 79",
    "sg:postcode":"47004",
    "sg:province":"Valladolid",
    "wof:name":"Marcos Arroyo Angel Jose",
    "wof:placetype":"venue"
},
  "geometry": {"coordinates":[-4.7236862183,41.6464958191],"type":"Point"}
}