{
  "type": "Feature",
  "properties": {
    "iso:country":"ES",
    "sg:address":"Calle de San Francisco, 1",
    "sg:city":"Bilbao",
    "sg:orig_category":"Molduras, Junquillos, Listones Y Molduras Perforadas",
    "sg:phone":"+34 944 15 06 15",
    "sg:postcode":"48003",
    "sg:province":"Vizcaya",
    "wof:name":"Martin Moliner Fernando",
    "wof:placetype":"venue"
},
  "geometry": {"coordinates":[-2.9250991344,43.254901886],"type":"Point"}
}