{
  "type": "Feature",
  "properties": {
    "iso:country":"ES",
    "sg:address":"Plaz Panticosa (de), 9",
    "sg:city":"Fuenlabrada",
    "sg:orig_category":"Electricidad, Electr\u00d3nica: Material Y Suministros (al Por Mayor)",
    "sg:phone":"+34 916 06 96 47",
    "sg:postcode":"28941",
    "sg:province":"Madrid",
    "wof:name":"Mendia Amores Luis Fernando",
    "wof:placetype":"venue"
},
  "geometry": {"coordinates":[-3.7954320908,40.2963409424],"type":"Point"}
}