{
  "type": "Feature",
  "properties": {
    "addr:full":"Avda Sierra Nevada, 46 Cenes Vega Granada 18190",
    "addr:housenumber":"46",
    "addr:postcode":"18190",
    "addr:street":"Avda Sierra Nevada",
    "iso:country":"ES",
    "sg:address":"Avda Sierra Nevada, 46",
    "sg:city":"Cenes Vega",
    "sg:orig_category":"Agencias Y Agentes Comerciales, Representantes",
    "sg:phone":"+34 958 48 95 75",
    "sg:postcode":"18190",
    "sg:province":"Granada",
    "wof:name":"Hucoa Erloss S.a.",
    "wof:placetype":"venue"
},
  "geometry": {"coordinates":[-3.540168047,37.159702301],"type":"Point"}
}