{
  "type": "Feature",
  "properties": {
    "addr:full":"Avda Justina Y Berdia, 45 Saron Cantabria 39620",
    "addr:housenumber":"45",
    "addr:postcode":"39620",
    "addr:street":"Avda Justina Y Berdia",
    "iso:country":"ES",
    "sg:address":"Avda Justina Y Berdia, 45",
    "sg:city":"Saron",
    "sg:orig_category":"Reposter\u00cdas",
    "sg:phone":"+34 942 56 36 48",
    "sg:postcode":"39620",
    "sg:province":"Cantabria",
    "wof:name":"Viuda De Acebo E Hijos S.l.",
    "wof:placetype":"venue"
},
  "geometry": {"coordinates":[-3.8540782928,43.3238258362],"type":"Point"}
}