{
  "type": "Feature",
  "properties": {
    "iso:country":"ES",
    "sg:address":"Trubia, S/n",
    "sg:city":"Cenero",
    "sg:orig_category":"Distribuci\u00d3n De Petr\u00d3leo Y Derivados",
    "sg:phone":"+34 985 16 79 68",
    "sg:postcode":"33393",
    "sg:province":"Asturias",
    "wof:name":"Pesca San Pedro Ii S.l.",
    "wof:placetype":"venue"
},
  "geometry": {"coordinates":[-5.7263522148,43.507850647],"type":"Point"}
}