{
  "type": "Feature",
  "properties": {
    "addr:full":"Avda Miguel De Cervantes, 52 Tarancon Cuenca 16400",
    "addr:housenumber":"52",
    "addr:postcode":"16400",
    "addr:street":"Avda Miguel De Cervantes",
    "iso:country":"ES",
    "sg:address":"Avda Miguel De Cervantes, 52",
    "sg:city":"Tarancon",
    "sg:orig_category":"Pescader\u00cdas (al Por Menor)",
    "sg:phone":"+34 969 32 23 21",
    "sg:postcode":"16400",
    "sg:province":"Cuenca",
    "wof:name":"Llavepesca S.l.",
    "wof:placetype":"venue"
},
  "geometry": {"coordinates":[-3.0117089748,40.0100479126],"type":"Point"}
}