{
  "type": "Feature",
  "properties": {
    "addr:full":"Av Carles Buigas (de), 11 Salou Tarragona 43840",
    "addr:housenumber":"11",
    "addr:postcode":"43840",
    "addr:street":"Av Carles Buigas De",
    "iso:country":"ES",
    "sg:address":"Av Carles Buigas (de), 11",
    "sg:city":"Salou",
    "sg:orig_category":"Art\u00cdculos De Regalo (al Por Menor)",
    "sg:phone":"+34 977 38 43 17",
    "sg:postcode":"43840",
    "sg:province":"Tarragona",
    "wof:name":"Aysa Lopez Yolanda",
    "wof:placetype":"venue"
},
  "geometry": {"coordinates":[1.1457500458,41.0726928711],"type":"Point"}
}