{
  "type": "Feature",
  "properties": {
    "addr:full":"C/ Figueres, 5 Vilafant Girona 17740",
    "addr:housenumber":"5",
    "addr:postcode":"17740",
    "addr:street":"C / Figueres",
    "iso:country":"ES",
    "sg:address":"C/ Figueres, 5",
    "sg:city":"Vilafant",
    "sg:classifiers":[
        {
            "category":"Communications",
            "type":"Services"
        }
    ],
    "sg:phone":"+34 972 54 63 02",
    "sg:postcode":"17740",
    "sg:province":"Girona",
    "sg:tags":[
        "televisiones",
        "y",
        "radio"
    ],
    "wof:name":"Ajuntament De Vilafant-radio Vilafant",
    "wof:placetype":"venue"
},
  "geometry": {"coordinates":[2.9380328655,42.246711731],"type":"Point"}
}