{
  "type": "Feature",
  "properties": {
    "addr:full":"Calle de Munich, 3 Alcorcon Madrid 28923",
    "addr:housenumber":"3",
    "addr:postcode":"28923",
    "addr:street":"Calle De Munich",
    "iso:country":"ES",
    "sg:address":"Calle de Munich, 3",
    "sg:city":"Alcorcon",
    "sg:orig_category":"Supermercados Y Hipermercados",
    "sg:phone":"+34 916 11 32 31",
    "sg:postcode":"28923",
    "sg:province":"Madrid",
    "wof:name":"Caprabo S.a.",
    "wof:placetype":"venue"
},
  "geometry": {"coordinates":[-3.8153231144,40.3446578979],"type":"Point"}
}