{
  "type": "Feature",
  "properties": {
    "addr:full":"Calle de Abderraman Iii, 3 Cordoba C\u00f3rdoba 14006",
    "addr:housenumber":"3",
    "addr:postcode":"14006",
    "addr:street":"Calle De Abderraman Iii;Co\u0301Rdoba",
    "iso:country":"ES",
    "sg:address":"Calle de Abderraman Iii, 3",
    "sg:city":"Cordoba",
    "sg:orig_category":"Muebles, Minoristas",
    "sg:phone":"+34 957 27 24 88",
    "sg:postcode":"14006",
    "sg:province":"C\u00f3rdoba",
    "wof:name":"Muebles Martinez De Cordoba S.a.",
    "wof:placetype":"venue"
},
  "geometry": {"coordinates":[-4.7833042145,37.8940505981],"type":"Point"}
}