{
  "type": "Feature",
  "properties": {
    "iso:country":"ES",
    "sg:address":"Calle de Carmen, 25",
    "sg:city":"Isla Cristina",
    "sg:orig_category":"Zapatos (al Por Menor)",
    "sg:phone":"+34 959 33 07 70",
    "sg:postcode":"21410",
    "sg:province":"Huelva",
    "wof:name":"Zamora Rodriguez Cayetano",
    "wof:placetype":"venue"
},
  "geometry": {"coordinates":[-7.3246421814,37.2024688721],"type":"Point"}
}