{
  "type": "Feature",
  "properties": {
    "addr:full":"Carrer de Torre, 24 Barcelona Barcelona 08006",
    "addr:housenumber":"24",
    "addr:postcode":"08006",
    "addr:street":"Carrer De Torre",
    "iso:country":"ES",
    "sg:address":"Carrer de Torre, 24",
    "sg:city":"Barcelona",
    "sg:orig_category":"Promotores Constructores",
    "sg:phone":"+34 932 18 28 01",
    "sg:postcode":"08006",
    "sg:province":"Barcelona",
    "wof:name":"Jove Rifa Ramon",
    "wof:placetype":"venue"
},
  "geometry": {"coordinates":[2.1687450409,41.3855895996],"type":"Point"}
}