{
  "type": "Feature",
  "properties": {
    "addr:full":"Pase Delicias, 115 Madrid Madrid 28045",
    "addr:housenumber":"115",
    "addr:postcode":"madrid;28045",
    "iso:country":"ES",
    "sg:address":"Pase Delicias, 115",
    "sg:city":"Madrid",
    "sg:orig_category":"Molduras, Junquillos, Listones Y Molduras Perforadas",
    "sg:phone":"+34 915 28 06 27",
    "sg:postcode":"28045",
    "sg:province":"Madrid",
    "wof:name":"Blanco Martin Esteban",
    "wof:placetype":"venue"
},
  "geometry": {"coordinates":[-3.694619894,40.3932991028],"type":"Point"}
}