{
  "type": "Feature",
  "properties": {
    "iso:country":"ES",
    "sg:address":"Calle de Padre Bover, 3",
    "sg:city":"Vinaros",
    "sg:orig_category":"Electricidad (montaje, Ensamblaje De Componentes)",
    "sg:phone":"+34 964 45 32 15",
    "sg:postcode":"12500",
    "sg:province":"Castell\u00f3n",
    "wof:name":"Arag\u00fcete Cardona Ramon",
    "wof:placetype":"venue"
},
  "geometry": {"coordinates":[0.4745250046,40.4727783203],"type":"Point"}
}