{
  "type": "Feature",
  "properties": {
    "iso:country":"ES",
    "sg:address":"Rua Juan Bautista Andrade, 111",
    "sg:city":"Pontevedra",
    "sg:orig_category":"Supermercados Y Hipermercados",
    "sg:phone":"+34 986 87 11 14",
    "sg:postcode":"36005",
    "sg:province":"Pontevedra",
    "wof:name":"Supermercado Hnos Veiga S.l.",
    "wof:placetype":"venue"
},
  "geometry": {"coordinates":[-8.6383152008,42.4445457458],"type":"Point"}
}