{
  "type": "Feature",
  "properties": {
    "addr:full":"Carr Ferreria (la), 20 Alfas Pi Alicante 03580",
    "addr:housenumber":"20",
    "addr:postcode":"03580",
    "addr:street":"Carr Ferreria La",
    "iso:country":"ES",
    "sg:address":"Carr Ferreria (la), 20",
    "sg:city":"Alfas Pi",
    "sg:orig_category":"Asesor\u00cda Fiscal Y Jur\u00cddica",
    "sg:phone":"+34 965 88 73 60",
    "sg:postcode":"03580",
    "sg:province":"Alicante",
    "wof:name":"Asesoria Gonzalo Sanchez S.l",
    "wof:placetype":"venue"
},
  "geometry": {"coordinates":[-0.1005768031,38.5761947632],"type":"Point"}
}