{
  "type": "Feature",
  "properties": {
    "addr:full":"Calle de Puente Y Pellon, 11 Sevilla Sevilla 41004",
    "addr:housenumber":"11",
    "addr:postcode":"41004",
    "addr:street":"Calle De Puente Y Pellon",
    "iso:country":"ES",
    "sg:address":"Calle de Puente Y Pellon, 11",
    "sg:city":"Sevilla",
    "sg:orig_category":"Agencias Y Agentes Comerciales, Representantes",
    "sg:phone":"+34 954 56 01 44",
    "sg:postcode":"41004",
    "sg:province":"Sevilla",
    "wof:name":"Rodriguez Salinas Luis",
    "wof:placetype":"venue"
},
  "geometry": {"coordinates":[-5.9919919968,37.391582489],"type":"Point"}
}