{
  "type": "Feature",
  "properties": {
    "iso:country":"ES",
    "sg:address":"Calle de Ancha, 52",
    "sg:city":"Huetor-tajar",
    "sg:orig_category":"Cajas De Ahorro",
    "sg:phone":"+34 958 33 25 53",
    "sg:postcode":"18360",
    "sg:province":"Granada",
    "sg:website":"www.cajasur.es",
    "wof:name":"Caja De Ahorros Y Monte De Piedad De Cordoba",
    "wof:placetype":"venue"
},
  "geometry": {"coordinates":[-4.047328949,37.1970825195],"type":"Point"}
}