{
  "type": "Feature",
  "properties": {
    "iso:country":"ES",
    "sg:address":"Calle de San Blas, 9",
    "sg:city":"Fuentes Ebro",
    "sg:orig_category":"Congelados: Productos Alimentarios (al Por Menor)",
    "sg:phone":"+34 976 16 10 57",
    "sg:postcode":"50740",
    "sg:province":"Zaragoza",
    "wof:name":"Sanz Lou Gloria",
    "wof:placetype":"venue"
},
  "geometry": {"coordinates":[-0.6282280087,41.5109519958],"type":"Point"}
}