{
  "type": "Feature",
  "properties": {
    "addr:full":"Rond Segovia, 38 Madrid Madrid 28005",
    "addr:housenumber":"38",
    "addr:postcode":"madrid;28005",
    "addr:street":"Segovia",
    "iso:country":"ES",
    "sg:address":"Rond Segovia, 38",
    "sg:city":"Madrid",
    "sg:orig_category":"Alimentaci\u00d3n General (al Por Menor)",
    "sg:phone":"+34 913 65 56 24",
    "sg:postcode":"28005",
    "sg:province":"Madrid",
    "wof:name":"Zhu  Ensheng",
    "wof:placetype":"venue"
},
  "geometry": {"coordinates":[-3.7146356106,40.4077644348],"type":"Point"}
}