{
  "type": "Feature",
  "properties": {
    "iso:country":"ES",
    "sg:address":"Calle de Libertad, 14",
    "sg:city":"Pola De Laviana",
    "sg:orig_category":"Tintes (fabricaci\u00d3n, Al Por Mayor)",
    "sg:phone":"+34 985 60 06 85",
    "sg:postcode":"33980",
    "sg:province":"Asturias",
    "wof:name":"Gonzalez Suarez Caterina",
    "wof:placetype":"venue"
},
  "geometry": {"coordinates":[-5.563065052,43.2481002808],"type":"Point"}
}