{
  "type": "Feature",
  "properties": {
    "addr:full":"Pase Constitucion (la), 26 Zaragoza Zaragoza 50008",
    "addr:housenumber":"26",
    "addr:postcode":"50008",
    "addr:street":"Constitucion La",
    "iso:country":"ES",
    "sg:address":"Pase Constitucion (la), 26",
    "sg:city":"Zaragoza",
    "sg:orig_category":"Inmobiliaria (agencias)",
    "sg:phone":"+34 976 22 19 48",
    "sg:postcode":"50008",
    "sg:province":"Zaragoza",
    "wof:name":"Hermanos Baraza Cilveti Comunidad De Bienes",
    "wof:placetype":"venue"
},
  "geometry": {"coordinates":[-0.8806840181,41.6472549438],"type":"Point"}
}