{
  "type": "Feature",
  "properties": {
    "iso:country":"ES",
    "sg:address":"Carr Maria Pujolar, 21",
    "sg:city":"Figueres",
    "sg:orig_category":"Empresas De Pintura Y Revestimientos",
    "sg:phone":"+34 972 50 16 46",
    "sg:postcode":"17600",
    "sg:province":"Girona",
    "wof:name":"Cortada Berta Jaime",
    "wof:placetype":"venue"
},
  "geometry": {"coordinates":[2.9512300491,42.2694015503],"type":"Point"}
}