{
  "type": "Feature",
  "properties": {
    "addr:full":"Calle de Alcalde Guillermo Rein, 160 Malaga M\u00e1laga 29006",
    "addr:housenumber":"160",
    "addr:postcode":"29006",
    "addr:street":"Calle De Alcalde Guillermo Rein;Ma\u0301Laga",
    "iso:country":"ES",
    "sg:address":"Calle de Alcalde Guillermo Rein, 160",
    "sg:city":"Malaga",
    "sg:orig_category":"Mec\u00c1nica General",
    "sg:phone":"+34 952 34 21 38",
    "sg:postcode":"29006",
    "sg:province":"M\u00e1laga",
    "wof:name":"Climalaga S.l.",
    "wof:placetype":"venue"
},
  "geometry": {"coordinates":[-4.4839267731,36.7111968994],"type":"Point"}
}