{
  "type": "Feature",
  "properties": {
    "iso:country":"ES",
    "sg:address":"Calle de Cuesta Maria Jesus, 1",
    "sg:city":"Lebrija",
    "sg:orig_category":"Molduras, Junquillos, Listones Y Molduras Perforadas",
    "sg:phone":"+34 955 97 42 45",
    "sg:postcode":"41740",
    "sg:province":"Sevilla",
    "wof:name":"Vadillo Moreno Francisco",
    "wof:placetype":"venue"
},
  "geometry": {"coordinates":[-6.0761609077,36.9179458618],"type":"Point"}
}