{
  "type": "Feature",
  "properties": {
    "addr:full":"Cno. Viejo Guejar Sierra, 10 Cenes Vega Granada 18190",
    "addr:housenumber":"10",
    "addr:postcode":"18190",
    "addr:street":"Cno. Viejo Guejar Sierra",
    "iso:country":"ES",
    "sg:address":"Cno. Viejo Guejar Sierra, 10",
    "sg:city":"Cenes Vega",
    "sg:orig_category":"Audiovisuales (producci\u00d3n, Edici\u00d3n, Realizaci\u00d3n)",
    "sg:phone":"+34 958 48 65 64",
    "sg:postcode":"18190",
    "sg:province":"Granada",
    "wof:name":"Campos Duaso Javier",
    "wof:placetype":"venue"
},
  "geometry": {"coordinates":[-3.5423738956,37.1603355408],"type":"Point"}
}