{
  "type": "Feature",
  "properties": {
    "addr:full":"Avda Colon, 138 San Antonio Abad Murcia 30205",
    "addr:housenumber":"138",
    "addr:postcode":"30205",
    "addr:street":"Avda Colon",
    "iso:country":"ES",
    "sg:address":"Avda Colon, 138",
    "sg:city":"San Antonio Abad",
    "sg:orig_category":"Electrodom\u00c9sticos (fabricaci\u00d3n, Al Por Mayor)",
    "sg:phone":"+34 968 51 15 49",
    "sg:postcode":"30205",
    "sg:province":"Murcia",
    "wof:name":"Pe\u00f1a Jordan Jose",
    "wof:placetype":"venue"
},
  "geometry": {"coordinates":[-1.1302499771,37.9829597473],"type":"Point"}
}