{
  "type": "Feature",
  "properties": {
    "addr:full":"Fuente Nueva, 24 Iglesuela Cid Teruel 44142",
    "addr:housenumber":"24",
    "addr:postcode":"44142",
    "addr:street":"Nueva",
    "iso:country":"ES",
    "sg:address":"Fuente Nueva, 24",
    "sg:city":"Iglesuela Cid",
    "sg:orig_category":"Molduras, Junquillos, Listones Y Molduras Perforadas",
    "sg:phone":"+34 964 44 33 32",
    "sg:postcode":"44142",
    "sg:province":"Teruel",
    "wof:name":"Alcon Mompel Camilo",
    "wof:placetype":"venue"
},
  "geometry": {"coordinates":[-1.1069096327,40.3441085815],"type":"Point"}
}