{
  "type": "Feature",
  "properties": {
    "addr:full":"Calle de Horacio Fernandez Inguanzo 'el Paisano', 2 Aguilas Murcia 30880",
    "addr:housenumber":"2",
    "addr:postcode":"30880",
    "addr:street":"Calle De Horacio Fernandez Inguanzo ' El;'",
    "iso:country":"ES",
    "sg:address":"Calle de Horacio Fernandez Inguanzo 'el Paisano', 2",
    "sg:city":"Aguilas",
    "sg:orig_category":"Transporte De Barcos",
    "sg:phone":"+34 968 41 37 54",
    "sg:postcode":"30880",
    "sg:province":"Murcia",
    "wof:name":"Perez Reverte Jose",
    "wof:placetype":"venue"
},
  "geometry": {"coordinates":[-1.5804040432,37.4104576111],"type":"Point"}
}