{
  "type": "Feature",
  "properties": {
    "iso:country":"ES",
    "sg:address":"Calle de Segovia (de), 2",
    "sg:city":"Humanes De Madrid",
    "sg:orig_category":"Pintura, Barniz, Productos Asimilables (fabricaci\u00d3n, Al Por Mayor)",
    "sg:phone":"+34 916 90 02 55",
    "sg:postcode":"28970",
    "sg:province":"Madrid",
    "wof:name":"Estrella Y Lugar S. L.",
    "wof:placetype":"venue"
},
  "geometry": {"coordinates":[-3.8208010197,40.2718505859],"type":"Point"}
}