{
  "type": "Feature",
  "properties": {
    "iso:country":"ES",
    "sg:address":"Calle de Rabi Don Sem Tob, 2",
    "sg:city":"Carrion De Los Condes",
    "sg:classifiers":[
        {
            "category":"Personal",
            "subcategory":"Barber",
            "type":"Services"
        }
    ],
    "sg:phone":"+34 979 88 05 11",
    "sg:postcode":"34120",
    "sg:province":"Palencia",
    "sg:tags":[
        "caballeros",
        "de",
        "peluqueros"
    ],
    "wof:name":"Abad Gutierrez Donato",
    "wof:placetype":"venue"
},
  "geometry": {"coordinates":[-4.601404,42.34119],"type":"Point"}
}