{
  "type": "Feature",
  "properties": {
    "addr:full":"Carrer de Comte D'urgell, 117 Barcelona Barcelona 08011",
    "addr:housenumber":"117",
    "addr:postcode":"08011",
    "addr:street":"Carrer De Comte D'Urgell",
    "iso:country":"ES",
    "sg:address":"Carrer de Comte D'urgell, 117",
    "sg:city":"Barcelona",
    "sg:orig_category":"Aud\u00cdfonos",
    "sg:phone":"+34 934 53 78 40",
    "sg:postcode":"08011",
    "sg:province":"Barcelona",
    "wof:name":"Auditus S.l.",
    "wof:placetype":"venue"
},
  "geometry": {"coordinates":[2.1548631191,41.384929657],"type":"Point"}
}