{
  "type": "Feature",
  "properties": {
    "addr:full":"Calle de Urzabal, 3 Salvatierra O Agurain \u00c1lava 01200",
    "addr:housenumber":"3",
    "addr:postcode":"01200",
    "addr:street":"Calle De Urzabal;A\u0301Lava",
    "iso:country":"ES",
    "sg:address":"Calle de Urzabal, 3",
    "sg:city":"Salvatierra O Agurain",
    "sg:orig_category":"Molduras, Junquillos, Listones Y Molduras Perforadas",
    "sg:phone":"+34 945 30 09 01",
    "sg:postcode":"01200",
    "sg:province":"\u00c1lava",
    "wof:name":"Cristal Preto Marcolino Emilio",
    "wof:placetype":"venue"
},
  "geometry": {"coordinates":[-2.3920099735,42.8489379883],"type":"Point"}
}