{
  "type": "Feature",
  "properties": {
    "iso:country":"ES",
    "sg:address":"Calle de Perez Galdos, 2",
    "sg:city":"Valladolid",
    "sg:orig_category":"Colchones (fabricaci\u00d3n, Al Por Mayor, Al Por Menor)",
    "sg:phone":"+34 983 29 56 11",
    "sg:postcode":"47005",
    "sg:province":"Valladolid",
    "wof:name":"Franco Payo Francisco Javier",
    "wof:placetype":"venue"
},
  "geometry": {"coordinates":[-4.7167568207,41.6478042603],"type":"Point"}
}