{
  "type": "Feature",
  "properties": {
    "addr:full":"Calle de Alcalde Sainz De Baranda, 72 Madrid Madrid 28007",
    "addr:housenumber":"72",
    "addr:postcode":"madrid;28007",
    "addr:street":"Calle De Alcalde Sainz De Baranda",
    "iso:country":"ES",
    "sg:address":"Calle de Alcalde Sainz De Baranda, 72",
    "sg:city":"Madrid",
    "sg:orig_category":"Electromec\u00c1nica",
    "sg:phone":"+34 915 73 76 26",
    "sg:postcode":"28007",
    "sg:province":"Madrid",
    "wof:name":"Martinez Salmeron Jesus Maria",
    "wof:placetype":"venue"
},
  "geometry": {"coordinates":[-3.6678218842,40.4171485901],"type":"Point"}
}