{
  "type": "Feature",
  "properties": {
    "addr:full":"Calle de Obispo Jaime Perez, 36 Valencia Valencia 46006",
    "addr:housenumber":"36",
    "addr:postcode":"46006",
    "addr:street":"Calle De Obispo Jaime Perez",
    "iso:country":"ES",
    "sg:address":"Calle de Obispo Jaime Perez, 36",
    "sg:city":"Valencia",
    "sg:orig_category":"Agencias De Aduana",
    "sg:phone":"+34 963 34 07 01",
    "sg:postcode":"46006",
    "sg:province":"Valencia",
    "wof:name":"Transitos Gesdepsa S.l.",
    "wof:placetype":"venue"
},
  "geometry": {"coordinates":[-0.3643868864,39.4564285278],"type":"Point"}
}