{
  "type": "Feature",
  "properties": {
    "addr:full":"Carrer de Argentona (d'), 76 Mataro Barcelona 08302",
    "addr:housenumber":"76",
    "addr:postcode":"08302",
    "addr:street":"Carrer De Argentona D '",
    "iso:country":"ES",
    "sg:address":"Carrer de Argentona (d'), 76",
    "sg:city":"Mataro",
    "sg:classifiers":[
        {
            "category":"Arts & Performance",
            "subcategory":"Art Gallery",
            "type":"Entertainment"
        }
    ],
    "sg:phone":"+34 937 98 74 11",
    "sg:postcode":"08302",
    "sg:province":"Barcelona",
    "sg:tags":[
        "arte",
        "de",
        "galer\u00cdas"
    ],
    "wof:name":"Pons Brothers S.l.",
    "wof:placetype":"venue"
},
  "geometry": {"coordinates":[2.4412589073,41.5409164429],"type":"Point"}
}