{
  "type": "Feature",
  "properties": {
    "iso:country":"ES",
    "sg:address":"Calle de Rambla Obispo Orbera, 24",
    "sg:city":"Almeria",
    "sg:orig_category":"Zapatos (al Por Mayor)",
    "sg:phone":"+34 950 27 46 77",
    "sg:postcode":"04001",
    "sg:province":"Almer\u00eda",
    "wof:name":"Valliblan S.l.",
    "wof:placetype":"venue"
},
  "geometry": {"coordinates":[-2.4619688988,36.8403358459],"type":"Point"}
}