{
  "type": "Feature",
  "properties": {
    "addr:full":"Calle de Uribarri, 27 Bilbao Vizcaya 48007",
    "addr:housenumber":"27",
    "addr:postcode":"48007",
    "addr:street":"Calle De Uribarri",
    "iso:country":"ES",
    "sg:address":"Calle de Uribarri, 27",
    "sg:city":"Bilbao",
    "sg:orig_category":"Escayola Y Productos De Escayola (fabricaci\u00d3n, Al Por Mayor)",
    "sg:phone":"+34 944 45 01 44",
    "sg:postcode":"48007",
    "sg:province":"Vizcaya",
    "wof:name":"Fernandez Comonte Jose Maria",
    "wof:placetype":"venue"
},
  "geometry": {"coordinates":[-2.9220290184,43.2684326172],"type":"Point"}
}