{
  "type": "Feature",
  "properties": {
    "iso:country":"ES",
    "sg:address":"Calle de Reino De Murcia, S/n",
    "sg:city":"Molina Segura",
    "sg:orig_category":"Farmacias",
    "sg:phone":"+34 968 64 81 47",
    "sg:postcode":"30500",
    "sg:province":"Murcia",
    "wof:name":"Ca\u00f1amas Gadea Macarena",
    "wof:placetype":"venue"
},
  "geometry": {"coordinates":[-1.2119740248,38.0535736084],"type":"Point"}
}