{
  "type": "Feature",
  "properties": {
    "addr:full":"Calle de Juan De Austria, 4 Aspe Alicante 03680",
    "addr:housenumber":"4",
    "addr:postcode":"03680",
    "addr:street":"Calle De Juan De Austria",
    "iso:country":"ES",
    "sg:address":"Calle de Juan De Austria, 4",
    "sg:city":"Aspe",
    "sg:orig_category":"Promotores Constructores",
    "sg:phone":"+34 965 49 37 87",
    "sg:postcode":"03680",
    "sg:province":"Alicante",
    "wof:name":"Edificaciones Mnuel Aznar Y Asociados S.l.",
    "wof:placetype":"venue"
},
  "geometry": {"coordinates":[-0.7681409717,38.3480911255],"type":"Point"}
}