{
  "type": "Feature",
  "properties": {
    "addr:full":"Cm\u00d1o Vello, 8 Vilamean Pontevedra 36350",
    "addr:housenumber":"8",
    "addr:postcode":"36350",
    "addr:street":"Vello",
    "iso:country":"ES",
    "sg:address":"Cm\u00d1o Vello, 8",
    "sg:city":"Vilamean",
    "sg:orig_category":"Peluquer\u00cdas, Peluquer\u00cda Mixta",
    "sg:phone":"+34 986 36 67 88",
    "sg:postcode":"36350",
    "sg:province":"Pontevedra",
    "wof:name":"Salon Bellisima Nigran S.l. (dos Estilos",
    "wof:placetype":"venue"
},
  "geometry": {"coordinates":[-8.8062238693,42.141494751],"type":"Point"}
}