{
  "type": "Feature",
  "properties": {
    "addr:full":"Los Angeles, 27 Puerto Santiago Santa Cruz De Tenerife 38683",
    "addr:housenumber":"27",
    "addr:postcode":"38683",
    "addr:street":"Los Angeles",
    "iso:country":"ES",
    "sg:address":"Los Angeles, 27",
    "sg:city":"Puerto Santiago",
    "sg:orig_category":"Agencias De Viajes",
    "sg:phone":"+34 922 86 07 73",
    "sg:postcode":"38683",
    "sg:province":"Santa Cruz De Tenerife",
    "wof:name":"Tui Espa\u00f1a Turismo S. A.",
    "wof:placetype":"venue"
},
  "geometry": {"coordinates":[-16.8416538239,28.2378063202],"type":"Point"}
}