{
  "type": "Feature",
  "properties": {
    "iso:country":"ES",
    "sg:address":"Calle de Cuarte, 71",
    "sg:city":"Zaragoza",
    "sg:orig_category":"Internados & Ense\u00d1anza Privada",
    "sg:phone":"+34 976 37 92 96",
    "sg:postcode":"50007",
    "sg:province":"Zaragoza",
    "wof:name":"Congregacion De Madres Dominicas De Nuestra Se\u00d1ora De Las Victorias",
    "wof:placetype":"venue"
},
  "geometry": {"coordinates":[-0.8908689022,41.629322052],"type":"Point"}
}