{
  "type": "Feature",
  "properties": {
    "iso:country":"ES",
    "sg:address":"Avda Republica Argentina, 31",
    "sg:city":"Logro\u00f1o",
    "sg:orig_category":"Confecci\u00d3n (fabricaci\u00d3n, Al Por Mayor)",
    "sg:phone":"+34 941 25 58 69",
    "sg:postcode":"26002",
    "sg:province":"La Rioja",
    "wof:name":"Sanchez Hernandez Francisco",
    "wof:placetype":"venue"
},
  "geometry": {"coordinates":[-2.4495339394,42.4596366882],"type":"Point"}
}