{
  "type": "Feature",
  "properties": {
    "addr:full":"C/ Major, 3 Alaior Islas Baleares 07730",
    "addr:housenumber":"3",
    "addr:postcode":"07730",
    "addr:street":"C / Major",
    "iso:country":"ES",
    "sg:address":"C/ Major, 3",
    "sg:city":"Alaior",
    "sg:orig_category":"Estancos",
    "sg:phone":"+34 971 37 22 34",
    "sg:postcode":"07730",
    "sg:province":"Islas Baleares",
    "wof:name":"Garcia Pons Magdalena",
    "wof:placetype":"venue"
},
  "geometry": {"coordinates":[4.139901638,39.9338569641],"type":"Point"}
}