{
  "type": "Feature",
  "properties": {
    "addr:full":"Carrer de Consell De Cent, 314 Barcelona Barcelona 08007",
    "addr:housenumber":"314",
    "addr:postcode":"08007",
    "addr:street":"Carrer De Consell De Cent",
    "iso:country":"ES",
    "sg:address":"Carrer de Consell De Cent, 314",
    "sg:city":"Barcelona",
    "sg:orig_category":"Sociedades, Compa\u00d1\u00cdas Aseguradoras",
    "sg:phone":"+34 934 87 93 66",
    "sg:postcode":"08007",
    "sg:province":"Barcelona",
    "wof:name":"Usach Rofes Enrique",
    "wof:placetype":"venue"
},
  "geometry": {"coordinates":[2.1665849686,41.3915748596],"type":"Point"}
}