{
  "type": "Feature",
  "properties": {
    "addr:full":"Calle de San Ramon, 22 Barbastro Huesca 22300",
    "addr:housenumber":"22",
    "addr:postcode":"22300",
    "addr:street":"Calle De San Ramon",
    "iso:country":"ES",
    "sg:address":"Calle de San Ramon, 22",
    "sg:city":"Barbastro",
    "sg:orig_category":"Peluqueros: De Se\u00d1oras",
    "sg:phone":"+34 974 31 14 93",
    "sg:postcode":"22300",
    "sg:province":"Huesca",
    "wof:name":"Escala Nadal Pilar",
    "wof:placetype":"venue"
},
  "geometry": {"coordinates":[0.1242730021,42.0355186462],"type":"Point"}
}