{
  "type": "Feature",
  "properties": {
    "iso:country":"ES",
    "sg:address":"Avda Lugo (de), S/n",
    "sg:city":"Santiago De Compostela",
    "sg:orig_category":"Alquiler De Veh\u00cdculos: Turismos Y Utilitarios",
    "sg:phone":"+34 981 59 74 76",
    "sg:postcode":"15703",
    "sg:province":"La Coru\u00f1a",
    "sg:website":"www.europcar.es",
    "wof:name":"Europcar Ib. S.a",
    "wof:placetype":"venue"
},
  "geometry": {"coordinates":[-8.5335140228,42.8836097717],"type":"Point"}
}