{
  "type": "Feature",
  "properties": {
    "addr:full":"Trav. Iglesia, 8 Cambre La Coru\u00f1a 15660",
    "addr:housenumber":"8",
    "addr:postcode":"15660",
    "addr:street":"Iglesia;La Corun\u0303A",
    "iso:country":"ES",
    "sg:address":"Trav. Iglesia, 8",
    "sg:city":"Cambre",
    "sg:orig_category":"Fabricaci\u00d3n De Juguetes Autom\u00c1ticos",
    "sg:phone":"+34 981 66 29 81",
    "sg:postcode":"15660",
    "sg:province":"La Coru\u00f1a",
    "wof:name":"Recreativos Vayga S. L.",
    "wof:placetype":"venue"
},
  "geometry": {"coordinates":[-8.3557987213,43.3154907227],"type":"Point"}
}