{
  "type": "Feature",
  "properties": {
    "addr:full":"Calle de Ballesteros, 42 Ubeda Ja\u00e9n 23400",
    "addr:housenumber":"42",
    "addr:postcode":"23400",
    "addr:street":"Calle De Ballesteros;Jae\u0301N",
    "iso:country":"ES",
    "sg:address":"Calle de Ballesteros, 42",
    "sg:city":"Ubeda",
    "sg:orig_category":"Mec\u00c1nico Del Autom\u00d3vil",
    "sg:phone":"+34 953 75 39 01",
    "sg:postcode":"23400",
    "sg:province":"Ja\u00e9n",
    "wof:name":"Gil Ortega Joaquin",
    "wof:placetype":"venue"
},
  "geometry": {"coordinates":[-3.3677473068,38.0214653015],"type":"Point"}
}