{
  "type": "Feature",
  "properties": {
    "iso:country":"ES",
    "sg:address":"Pl Sant Pere, 3",
    "sg:city":"Barcelona",
    "sg:orig_category":"Artesan\u00cda",
    "sg:phone":"+34 933 19 27 11",
    "sg:postcode":"08003",
    "sg:province":"Barcelona",
    "wof:name":"A.p.i.f.p.a.d.p San Jordi",
    "wof:placetype":"venue"
},
  "geometry": {"coordinates":[2.1790742874,41.3895301819],"type":"Point"}
}