{
  "type": "Feature",
  "properties": {
    "addr:full":"Carrer de Llibertat, 67 Ametlla Mar Tarragona 43860",
    "addr:housenumber":"67",
    "addr:postcode":"43860",
    "addr:street":"Carrer De Llibertat",
    "iso:country":"ES",
    "sg:address":"Carrer de Llibertat, 67",
    "sg:city":"Ametlla Mar",
    "sg:orig_category":"Empresarios",
    "sg:phone":"+34 977 45 63 08",
    "sg:postcode":"43860",
    "sg:province":"Tarragona",
    "wof:name":"Consarnau Margalef Juan",
    "wof:placetype":"venue"
},
  "geometry": {"coordinates":[0.8033540249,40.8864326477],"type":"Point"}
}