{
  "type": "Feature",
  "properties": {
    "iso:country":"ES",
    "sg:address":"Rua San Pedro (de), 4",
    "sg:city":"Santiago De Compostela",
    "sg:orig_category":"Molduras, Junquillos, Listones Y Molduras Perforadas",
    "sg:phone":"+34 981 58 63 92",
    "sg:postcode":"15703",
    "sg:province":"La Coru\u00f1a",
    "wof:name":"Esparis Esparis Oscar",
    "wof:placetype":"venue"
},
  "geometry": {"coordinates":[-8.5399198532,42.881816864],"type":"Point"}
}