{
  "type": "Feature",
  "properties": {
    "iso:country":"ES",
    "sg:address":"Carrer de Llull, 180",
    "sg:city":"Barcelona",
    "sg:orig_category":"Estudios, Instalaci\u00d3n De Climatizaci\u00d3n",
    "sg:phone":"+34 934 85 56 02",
    "sg:postcode":"08005",
    "sg:province":"Barcelona",
    "sg:website":"www.frioclima.com",
    "wof:name":"Climatizaciones Frioclima S.a.",
    "wof:placetype":"venue"
},
  "geometry": {"coordinates":[2.2013270855,41.4001922607],"type":"Point"}
}