{
  "type": "Feature",
  "properties": {
    "iso:country":"ES",
    "sg:address":"Calle de Juan Ramon Jimenez, 79",
    "sg:city":"Valencia",
    "sg:orig_category":"Formaci\u00d3n Continuada (variada)",
    "sg:phone":"+34 963 33 72 08",
    "sg:postcode":"46026",
    "sg:province":"Valencia",
    "wof:name":"Cebrian Jarrega Jose Carlos",
    "wof:placetype":"venue"
},
  "geometry": {"coordinates":[-0.3727419972,39.4504585266],"type":"Point"}
}