{
  "type": "Feature",
  "properties": {
    "iso:country":"ES",
    "sg:address":"Pl Cervantes, 3",
    "sg:city":"Palma De Cervello",
    "sg:orig_category":"Bibliotecas, Mediatecas",
    "sg:phone":"+34 936 72 06 95",
    "sg:postcode":"08756",
    "sg:province":"Barcelona",
    "wof:name":"Ajuntament De La Palma De Cervello",
    "wof:placetype":"venue"
},
  "geometry": {"coordinates":[1.9658845663,41.413356781],"type":"Point"}
}