{
  "type": "Feature",
  "properties": {
    "iso:country":"ES",
    "sg:address":"Carr Proissos, 3",
    "sg:city":"Felanitx",
    "sg:orig_category":"Plomeros",
    "sg:phone":"+34 971 82 72 16",
    "sg:postcode":"07200",
    "sg:province":"Islas Baleares",
    "wof:name":"Benito Pi\u00f1a Forteza S.l.",
    "wof:placetype":"venue"
},
  "geometry": {"coordinates":[3.1496338844,39.4710121155],"type":"Point"}
}