{
  "type": "Feature",
  "properties": {
    "iso:country":"ES",
    "sg:address":"Rua Estrella (de La), 4",
    "sg:city":"Monforte De Lemos",
    "sg:orig_category":"Empresas De Vigilancia, Guardia Y Protecci\u00d3n",
    "sg:phone":"+34 982 40 51 76",
    "sg:postcode":"27400",
    "sg:province":"Lugo",
    "wof:name":"Serramar Vigilancia Y Seguridad S.l.",
    "wof:placetype":"venue"
},
  "geometry": {"coordinates":[-7.5080890656,42.5196075439],"type":"Point"}
}