{
  "type": "Feature",
  "properties": {
    "addr:full":"Carrer de Pi I Margall, 49 Barcelona Barcelona 08024",
    "addr:housenumber":"49",
    "addr:postcode":"08024",
    "addr:street":"Carrer De Pi I Margall",
    "iso:country":"ES",
    "sg:address":"Carrer de Pi I Margall, 49",
    "sg:city":"Barcelona",
    "sg:orig_category":"Bancos",
    "sg:phone":"+34 932 13 01 67",
    "sg:postcode":"08024",
    "sg:province":"Barcelona",
    "wof:name":"Deutsche Bank S.a.e.",
    "wof:placetype":"venue"
},
  "geometry": {"coordinates":[2.1639099121,41.4088516235],"type":"Point"}
}