{
  "type": "Feature",
  "properties": {
    "iso:country":"ES",
    "sg:address":"Calle de Santa Eulalia, 16",
    "sg:city":"Santurtzi",
    "sg:orig_category":"Empresarios",
    "sg:phone":"+34 946 02 67 44",
    "sg:postcode":"48980",
    "sg:province":"Vizcaya",
    "wof:name":"Luis Quiroga Gutierrez",
    "wof:placetype":"venue"
},
  "geometry": {"coordinates":[-3.0318706036,43.3262863159],"type":"Point"}
}