{
  "type": "Feature",
  "properties": {
    "addr:full":"Calle de Luis Sauquillo, 45 Fuenlabrada Madrid 28944",
    "addr:housenumber":"45",
    "addr:postcode":"28944",
    "addr:street":"Calle De Luis Sauquillo",
    "iso:country":"ES",
    "sg:address":"Calle de Luis Sauquillo, 45",
    "sg:city":"Fuenlabrada",
    "sg:orig_category":"Electrodom\u00c9sticos (al Por Menor)",
    "sg:phone":"+34 916 90 37 13",
    "sg:postcode":"28944",
    "sg:province":"Madrid",
    "wof:name":"Hermanos De La Hoz Segura S.l",
    "wof:placetype":"venue"
},
  "geometry": {"coordinates":[-3.7964301109,40.2825698853],"type":"Point"}
}