{
  "type": "Feature",
  "properties": {
    "addr:full":"Plaz Generalisimo, 5 Polan Toledo 45161",
    "addr:housenumber":"5",
    "addr:postcode":"45161",
    "addr:street":"Plaz Generalisimo",
    "iso:country":"ES",
    "sg:address":"Plaz Generalisimo, 5",
    "sg:city":"Polan",
    "sg:orig_category":"Ingeniero",
    "sg:phone":"+34 925 37 04 19",
    "sg:postcode":"45161",
    "sg:province":"Toledo",
    "wof:name":"Manrique Lopez-rey S.l.",
    "wof:placetype":"venue"
},
  "geometry": {"coordinates":[-4.1675691605,39.7889404297],"type":"Point"}
}