{
  "type": "Feature",
  "properties": {
    "iso:country":"ES",
    "sg:address":"Calle de Azud, 8",
    "sg:city":"Brea De Aragon",
    "sg:orig_category":"Carnicer\u00cdas, Carnicer\u00cdas",
    "sg:phone":"+34 976 82 40 94",
    "sg:postcode":"50246",
    "sg:province":"Zaragoza",
    "wof:name":"Enbid Forcen Jesus Fernando",
    "wof:placetype":"venue"
},
  "geometry": {"coordinates":[-1.5999290943,41.5241203308],"type":"Point"}
}