{
  "type": "Feature",
  "properties": {
    "iso:country":"ES",
    "sg:address":"Pase Isla, 8",
    "sg:city":"Burgos",
    "sg:orig_category":"M\u00c9dicos: Cirug\u00cda Ortop\u00c9dica Y Traumatolog\u00cda",
    "sg:phone":"+34 947 26 07 86",
    "sg:postcode":"09003",
    "sg:province":"Burgos",
    "wof:name":"Arteche De Llano Juan Antonio",
    "wof:placetype":"venue"
},
  "geometry": {"coordinates":[-3.7105116844,42.3462677002],"type":"Point"}
}