{
  "type": "Feature",
  "properties": {
    "addr:full":"Zigordia Kalea, 21 Zarautz Guip\u00f9zcoa 20800",
    "addr:housenumber":"21",
    "addr:postcode":"20800",
    "addr:street":"Zigordia Kalea;Guipu\u0300Zcoa",
    "iso:country":"ES",
    "sg:address":"Zigordia Kalea, 21",
    "sg:city":"Zarautz",
    "sg:orig_category":"Caf\u00c9s, Bares, Cervecer\u00cdas",
    "sg:phone":"+34 943 13 20 26",
    "sg:postcode":"20800",
    "sg:province":"Guip\u00f9zcoa",
    "wof:name":"Garcia Gonzalez, Luis Mari",
    "wof:placetype":"venue"
},
  "geometry": {"coordinates":[-2.1747639179,43.2853088379],"type":"Point"}
}