{
  "type": "Feature",
  "properties": {
    "addr:full":"Calle de Sierra De Grazalema, 25 Malaga M\u00e1laga 29016",
    "addr:housenumber":"25",
    "addr:postcode":"29016",
    "addr:street":"Calle De Sierra De Grazalema;Ma\u0301Laga",
    "iso:country":"ES",
    "sg:address":"Calle de Sierra De Grazalema, 25",
    "sg:city":"Malaga",
    "sg:orig_category":"Perfumer\u00cda Y Cosm\u00c9tica (fabricaci\u00d3n, Al Por Mayor)",
    "sg:phone":"+34 952 22 84 10",
    "sg:postcode":"29016",
    "sg:province":"M\u00e1laga",
    "wof:name":"Nu\u00f1ez Padilla Maria Mercedes",
    "wof:placetype":"venue"
},
  "geometry": {"coordinates":[-4.4028072357,36.7296409607],"type":"Point"}
}