{
  "type": "Feature",
  "properties": {
    "addr:full":"Calle de Palma Del Rio, 37 Malaga M\u00e1laga 29004",
    "addr:housenumber":"37",
    "addr:postcode":"29004",
    "addr:street":"Calle De Palma Del Rio;Ma\u0301Laga",
    "iso:country":"ES",
    "sg:address":"Calle de Palma Del Rio, 37",
    "sg:city":"Malaga",
    "sg:orig_category":"Asesor\u00cda Fiscal Y Jur\u00cddica",
    "sg:phone":"+34 952 24 56 74",
    "sg:postcode":"29004",
    "sg:province":"M\u00e1laga",
    "wof:name":"Perez Gallardo Francisco Antonio",
    "wof:placetype":"venue"
},
  "geometry": {"coordinates":[-4.4565110207,36.6871871948],"type":"Point"}
}