{
  "type": "Feature",
  "properties": {
    "iso:country":"ES",
    "sg:address":"Plaz Independencia, 7",
    "sg:city":"Castellon",
    "sg:orig_category":"Muebles, Minoristas",
    "sg:phone":"+34 964 24 38 41",
    "sg:postcode":"12001",
    "sg:province":"Castell\u00f3n",
    "sg:website":"www.artespa\u00f1a.com",
    "wof:name":"Artespanya Castellon S.l",
    "wof:placetype":"venue"
},
  "geometry": {"coordinates":[-0.0384869985,39.9876441956],"type":"Point"}
}