{
  "type": "Feature",
  "properties": {
    "addr:full":"Calle de Haya, 2 Madrid Madrid 28044",
    "addr:housenumber":"2",
    "addr:postcode":"28044",
    "addr:street":"Calle De Haya",
    "iso:country":"ES",
    "sg:address":"Calle de Haya, 2",
    "sg:city":"Madrid",
    "sg:orig_category":"Ropa Para Se\u00d1oras Y Caballeros (al Por Menor)",
    "sg:phone":"+34 914 72 50 50",
    "sg:postcode":"28044",
    "sg:province":"Madrid",
    "sg:website":"www.zolder.com",
    "wof:name":"Zolder S.a.",
    "wof:placetype":"venue"
},
  "geometry": {"coordinates":[-3.747266531,40.3684806824],"type":"Point"}
}