{
  "type": "Feature",
  "properties": {
    "addr:full":"Avda Blasco Iba\u00d1ez, 145 Valencia Valencia 46022",
    "addr:housenumber":"145",
    "addr:postcode":"46022",
    "addr:street":"Avda Blasco Iban\u0303Ez",
    "iso:country":"ES",
    "sg:address":"Avda Blasco Iba\u00d1ez, 145",
    "sg:city":"Valencia",
    "sg:orig_category":"Arquitectos",
    "sg:phone":"+34 963 72 97 81",
    "sg:postcode":"46022",
    "sg:province":"Valencia",
    "wof:name":"Bosch Reig Ignacio",
    "wof:placetype":"venue"
},
  "geometry": {"coordinates":[-0.3408179879,39.4723548889],"type":"Point"}
}