{
  "type": "Feature",
  "properties": {
    "addr:full":"Carrer de Murillo, 5 Santa Pon\u00c7a Islas Baleares 07180",
    "addr:housenumber":"5",
    "addr:postcode":"07180",
    "addr:street":"Carrer De Murillo",
    "iso:country":"ES",
    "sg:address":"Carrer de Murillo, 5",
    "sg:city":"Santa Pon\u00c7a",
    "sg:orig_category":"Agencias Y Agentes Comerciales, Representantes",
    "sg:phone":"+34 971 69 67 20",
    "sg:postcode":"07180",
    "sg:province":"Islas Baleares",
    "wof:name":"Becker  Rolf Friederich Wilhem",
    "wof:placetype":"venue"
},
  "geometry": {"coordinates":[2.469219923,39.4947471619],"type":"Point"}
}