{
  "type": "Feature",
  "properties": {
    "addr:full":"Avda Monfrag\u00fce, 56 Trujillo C\u00e1ceres 10200",
    "addr:housenumber":"56",
    "addr:postcode":"10200",
    "addr:street":"Avda Monfraguee;Ca\u0301Ceres",
    "iso:country":"ES",
    "sg:address":"Avda Monfrag\u00fce, 56",
    "sg:city":"Trujillo",
    "sg:orig_category":"Albergues",
    "sg:phone":"+34 927 32 10 10",
    "sg:postcode":"10200",
    "sg:province":"C\u00e1ceres",
    "wof:name":"Escuela Hogar Guillen Cano Bote",
    "wof:placetype":"venue"
},
  "geometry": {"coordinates":[-5.8761949539,39.4637565613],"type":"Point"}
}