{
  "type": "Feature",
  "properties": {
    "addr:full":"Urb Cala Golf, S/n Cala M\u00e1laga 29649",
    "addr:housenumber":"/ n",
    "addr:postcode":"29649",
    "addr:street":"Urb;Golf;Ma\u0301Laga",
    "iso:country":"ES",
    "sg:address":"Urb Cala Golf, S/n",
    "sg:city":"Cala",
    "sg:orig_category":"Organismos De Reclutamiento",
    "sg:phone":"+34 952 49 27 73",
    "sg:postcode":"29649",
    "sg:province":"M\u00e1laga",
    "wof:name":"Ruizeraar Management Consultin Bv",
    "wof:placetype":"venue"
},
  "geometry": {"coordinates":[-4.6790738106,36.5038642883],"type":"Point"}
}