{
  "type": "Feature",
  "properties": {
    "iso:country":"ES",
    "sg:address":"Calle de Huertas (las), 32",
    "sg:city":"Algeciras",
    "sg:orig_category":"Bazares, Art\u00cdculos De Limpieza Y De Cocina (al Por Menor)",
    "sg:phone":"+34 956 63 22 79",
    "sg:postcode":"11201",
    "sg:province":"C\u00e1diz",
    "wof:name":"Guijarro Mateo Maria",
    "wof:placetype":"venue"
},
  "geometry": {"coordinates":[-5.4479618073,36.1280784607],"type":"Point"}
}