{
  "type": "Feature",
  "properties": {
    "addr:full":"Rua Fermin Bouza Brey, 5 Arteixo A Coru\u00f1a 15142",
    "addr:housenumber":"5",
    "addr:postcode":"15142",
    "addr:street":"Rua Fermin Bouza Brey;Corun\u0303A",
    "iso:country":"ES",
    "sg:address":"Rua Fermin Bouza Brey, 5",
    "sg:city":"Arteixo",
    "sg:orig_category":"Peluqueros: De Se\u00d1oras",
    "sg:phone":"+34 981 60 10 97",
    "sg:postcode":"15142",
    "sg:province":"A Coru\u00f1a",
    "wof:name":"Suarez Paz Emilia",
    "wof:placetype":"venue"
},
  "geometry": {"coordinates":[-8.5103797913,43.3043861389],"type":"Point"}
}