{
  "type": "Feature",
  "properties": {
    "iso:country":"ES",
    "sg:address":"Trva Paz (la), 1",
    "sg:city":"Avila",
    "sg:orig_category":"Internet: Espacios De Consulta",
    "sg:phone":"+34 920 25 69 07",
    "sg:postcode":"05003",
    "sg:province":"\u00c1vila",
    "wof:name":"Infociber",
    "wof:placetype":"venue"
},
  "geometry": {"coordinates":[-4.6605348587,40.6271286011],"type":"Point"}
}