{
  "type": "Feature",
  "properties": {
    "iso:country":"ES",
    "sg:address":"Avda Asturias, 12",
    "sg:city":"Fonsagrada",
    "sg:orig_category":"Producci\u00d3n, Distribuci\u00d3n De Electricidad",
    "sg:phone":"+34 982 34 04 64",
    "sg:postcode":"27100",
    "sg:province":"Lugo",
    "wof:name":"Electricidad Rodas C. B.",
    "wof:placetype":"venue"
},
  "geometry": {"coordinates":[-7.0673189163,43.125995636],"type":"Point"}
}