{
  "type": "Feature",
  "properties": {
    "iso:country":"ES",
    "sg:address":"C/ Senia (la), 8",
    "sg:city":"Elche",
    "sg:orig_category":"M\u00c1quinas De Escribir, M\u00c1quinas De Oficina (al Por Menor, Reparaci\u00d3n)",
    "sg:phone":"+34 965 46 86 94",
    "sg:postcode":"03201",
    "sg:province":"Alicante",
    "sg:website":"www.fdiaz.com",
    "wof:name":"Felipe Diaz S. L.",
    "wof:placetype":"venue"
},
  "geometry": {"coordinates":[-0.7018780112,38.2639465332],"type":"Point"}
}