{
  "type": "Feature",
  "properties": {
    "iso:country":"ES",
    "sg:address":"Calle de Ramon Y Cajal, S/n",
    "sg:city":"Sonseca",
    "sg:orig_category":"Art\u00cdculos De Madera (fabricaci\u00d3n Y Al Por Mayor)",
    "sg:phone":"+34 925 38 12 01",
    "sg:postcode":"45100",
    "sg:province":"Toledo",
    "wof:name":"Isabelo Madrid S.a.",
    "wof:placetype":"venue"
},
  "geometry": {"coordinates":[-3.9717390537,39.6806793213],"type":"Point"}
}