{
  "type": "Feature",
  "properties": {
    "addr:full":"Avda Constitucion De La, 12 S.gregorio Las Palmas 35200",
    "addr:housenumber":"12",
    "addr:postcode":"35200",
    "addr:street":"Avda Constitucion De La;Las Palmas",
    "iso:country":"ES",
    "sg:address":"Avda Constitucion De La, 12",
    "sg:city":"S.gregorio",
    "sg:orig_category":"Dise\u00d1o Industrial",
    "sg:phone":"+34 928 68 06 23",
    "sg:postcode":"35200",
    "sg:province":"Las Palmas",
    "wof:name":"Aleman Betancor Fernando",
    "wof:placetype":"venue"
},
  "geometry": {"coordinates":[-15.4300060272,28.1248226166],"type":"Point"}
}