{
  "type": "Feature",
  "properties": {
    "addr:full":"Carr Guilleries, 2 Girona Girona 17006",
    "addr:housenumber":"2",
    "addr:postcode":"17006",
    "addr:street":"Carr Guilleries",
    "iso:country":"ES",
    "sg:address":"Carr Guilleries, 2",
    "sg:city":"Girona",
    "sg:orig_category":"Institutos De Belleza",
    "sg:phone":"+34 972 24 16 76",
    "sg:postcode":"17006",
    "sg:province":"Girona",
    "wof:name":"Macia Lopez Anna",
    "wof:placetype":"venue"
},
  "geometry": {"coordinates":[2.8061709404,41.9770927429],"type":"Point"}
}