{
  "type": "Feature",
  "properties": {
    "iso:country":"ES",
    "sg:address":"Calle de Lourdes (de), 10",
    "sg:city":"Fuenlabrada",
    "sg:orig_category":"Carnicer\u00cdas, Carnicer\u00cdas",
    "sg:phone":"+34 916 15 58 94",
    "sg:postcode":"28944",
    "sg:province":"Madrid",
    "wof:name":"Herrero Vicente Juan Antonio",
    "wof:placetype":"venue"
},
  "geometry": {"coordinates":[-3.797631979,40.2808990479],"type":"Point"}
}