{
  "type": "Feature",
  "properties": {
    "iso:country":"ES",
    "sg:address":"Carrer de Benavent, 8",
    "sg:city":"Barcelona",
    "sg:orig_category":"Fotograf\u00cda Art\u00cdstica Y Retratos",
    "sg:phone":"+34 934 11 01 62",
    "sg:postcode":"08028",
    "sg:province":"Barcelona",
    "wof:name":"Bala\u00f1a Fontdevila Jaime",
    "wof:placetype":"venue"
},
  "geometry": {"coordinates":[2.1255171299,41.3778038025],"type":"Point"}
}