{
  "type": "Feature",
  "properties": {
    "iso:country":"ES",
    "sg:address":"Rua Baluro (do), 12",
    "sg:city":"Lugo",
    "sg:orig_category":"Contenedores Para Transporte De Mercanc\u00cdas",
    "sg:phone":"+34 982 23 17 48",
    "sg:postcode":"27004",
    "sg:province":"Lugo",
    "wof:name":"Contenedores Lucenses S.l.",
    "wof:placetype":"venue"
},
  "geometry": {"coordinates":[-7.5650258064,43.0092315674],"type":"Point"}
}