{
  "type": "Feature",
  "properties": {
    "addr:full":"Calle de Coca De La Pi\u00d1era, 1 Baeza Ja\u00e9n 23440",
    "addr:housenumber":"1",
    "addr:postcode":"23440",
    "addr:street":"Calle De Coca De La Pin\u0303Era",
    "iso:country":"ES",
    "sg:address":"Calle de Coca De La Pi\u00d1era, 1",
    "sg:city":"Baeza",
    "sg:orig_category":"Autob\u00das (explotaci\u00d3n Y Servicios De)",
    "sg:phone":"+34 953 74 70 86",
    "sg:postcode":"23440",
    "sg:province":"Ja\u00e9n",
    "wof:name":"Autocares Paco Monge Sll",
    "wof:placetype":"venue"
},
  "geometry": {"coordinates":[-3.4639549255,37.995475769],"type":"Point"}
}