{
  "type": "Feature",
  "properties": {
    "addr:full":"Pase Constitucion (de La), 33 Aguilas Murcia 30880",
    "addr:postcode":"30880",
    "iso:country":"ES",
    "sg:address":"Pase Constitucion (de La), 33",
    "sg:city":"Aguilas",
    "sg:orig_category":"Zapatos (al Por Menor)",
    "sg:phone":"+34 968 44 79 01",
    "sg:postcode":"30880",
    "sg:province":"Murcia",
    "wof:name":"Artesanos Navecal S.l.",
    "wof:placetype":"venue"
},
  "geometry": {"coordinates":[-1.5846846104,37.4031448364],"type":"Point"}
}