{
  "type": "Feature",
  "properties": {
    "addr:full":"Paseo Maritimo, 0 Benalmadena-costa M\u00e1laga 29630",
    "addr:housenumber":"0",
    "addr:postcode":"29630",
    "addr:street":"Paseo Maritimo;Ma\u0301Laga",
    "iso:country":"ES",
    "sg:address":"Paseo Maritimo, 0",
    "sg:city":"Benalmadena-costa",
    "sg:orig_category":"Art\u00cdculos De Regalo (al Por Menor)",
    "sg:phone":"+34 952 44 16 82",
    "sg:postcode":"29630",
    "sg:province":"M\u00e1laga",
    "wof:name":"Coronado Aguilar Ana",
    "wof:placetype":"venue"
},
  "geometry": {"coordinates":[-4.5162000656,36.5969467163],"type":"Point"}
}