{
  "type": "Feature",
  "properties": {
    "iso:country":"ES",
    "sg:address":"Calle de Toledo, 71",
    "sg:city":"Menasalbas",
    "sg:orig_category":"Producci\u00d3n De Abonos Y De Fertilizantes",
    "sg:phone":"+34 925 40 72 42",
    "sg:postcode":"45128",
    "sg:province":"Toledo",
    "sg:website":"www.abono-natural.com",
    "wof:name":"S. F. Regu S.l.",
    "wof:placetype":"venue"
},
  "geometry": {"coordinates":[-4.2789769173,39.6444625854],"type":"Point"}
}