{
  "type": "Feature",
  "properties": {
    "addr:full":"Calle de Colina De San Cristobal, 29 Almu\u00f1ecar Granada 18690",
    "addr:housenumber":"29",
    "addr:postcode":"18690",
    "addr:street":"Calle De Colina De San Cristobal",
    "iso:country":"ES",
    "sg:address":"Calle de Colina De San Cristobal, 29",
    "sg:city":"Almu\u00f1ecar",
    "sg:orig_category":"Promotores Constructores",
    "sg:phone":"+34 958 63 15 84",
    "sg:postcode":"18690",
    "sg:province":"Granada",
    "wof:name":"Construcciones Santa Colina S.l.",
    "wof:placetype":"venue"
},
  "geometry": {"coordinates":[-3.7053360939,36.7380905151],"type":"Point"}
}