{
  "type": "Feature",
  "properties": {
    "iso:country":"ES",
    "sg:address":"Calle de Alfonso Camin, 25",
    "sg:city":"Mieres",
    "sg:orig_category":"Empresas De Desmonte",
    "sg:phone":"+34 985 45 22 99",
    "sg:postcode":"33600",
    "sg:province":"Asturias",
    "wof:name":"Asturiana De Servicios Auxiliares De Obras S.l.",
    "wof:placetype":"venue"
},
  "geometry": {"coordinates":[-5.7742381096,43.2479171753],"type":"Point"}
}