{
  "type": "Feature",
  "properties": {
    "addr:full":"Calle de Maestro Mora, 7 Yecla Murcia 30510",
    "addr:housenumber":"7",
    "addr:postcode":"30510",
    "addr:street":"Calle De Maestro Mora",
    "iso:country":"ES",
    "sg:address":"Calle de Maestro Mora, 7",
    "sg:city":"Yecla",
    "sg:orig_category":"Cajas De Ahorro",
    "sg:phone":"+34 968 75 14 64",
    "sg:postcode":"30510",
    "sg:province":"Murcia",
    "sg:website":"www.cajamurcia.es",
    "wof:name":"Caja De Ahorros De Murcia",
    "wof:placetype":"venue"
},
  "geometry": {"coordinates":[-1.1107419729,38.6124916077],"type":"Point"}
}