{
  "type": "Feature",
  "properties": {
    "addr:full":"Calle de Santiago, 9 Valladolid Valladolid 47001",
    "addr:housenumber":"9",
    "addr:postcode":"47001",
    "addr:street":"Calle De Santiago",
    "iso:country":"ES",
    "sg:address":"Calle de Santiago, 9",
    "sg:city":"Valladolid",
    "sg:orig_category":"Estudios, Instalaci\u00d3n De Climatizaci\u00d3n",
    "sg:phone":"+34 983 36 18 00",
    "sg:postcode":"47001",
    "sg:province":"Valladolid",
    "sg:website":"www.axima.es",
    "wof:name":"Axima Sistemas E Instalaciones S.a.",
    "wof:placetype":"venue"
},
  "geometry": {"coordinates":[-4.7286367416,41.6506996155],"type":"Point"}
}