{
  "type": "Feature",
  "properties": {
    "iso:country":"ES",
    "sg:address":"Carrer de Libel.lula, 6",
    "sg:city":"Hospitalet Llobregat",
    "sg:orig_category":"Empresas De Carpinter\u00cda De Madera",
    "sg:phone":"+34 934 38 37 02",
    "sg:postcode":"08905",
    "sg:province":"Barcelona",
    "wof:name":"Montajes Y Decoracion Aceval S.c.p",
    "wof:placetype":"venue"
},
  "geometry": {"coordinates":[2.1105930805,41.3668327332],"type":"Point"}
}