{
  "type": "Feature",
  "properties": {
    "addr:full":"Carr Fernando El Catolico, 3 Benetusser Valencia 46910",
    "addr:housenumber":"3",
    "addr:postcode":"46910",
    "addr:street":"Carr Fernando El Catolico",
    "iso:country":"ES",
    "sg:address":"Carr Fernando El Catolico, 3",
    "sg:city":"Benetusser",
    "sg:orig_category":"Maquinaria Para Industrias Diversas",
    "sg:phone":"+34 963 96 01 74",
    "sg:postcode":"46910",
    "sg:province":"Valencia",
    "wof:name":"Puntival S.l.",
    "wof:placetype":"venue"
},
  "geometry": {"coordinates":[-0.3957229853,39.421081543],"type":"Point"}
}