{
  "type": "Feature",
  "properties": {
    "addr:full":"Calle de Mar Cantabrico (del), 8 Poligono De San Fernando De Henares Madrid 28830",
    "addr:housenumber":"8",
    "addr:postcode":"28830",
    "addr:street":"Calle De Mar Cantabrico Del",
    "iso:country":"ES",
    "sg:address":"Calle de Mar Cantabrico (del), 8",
    "sg:city":"Poligono De San Fernando De Henares",
    "sg:orig_category":"Empresas De Carpinter\u00cda De Madera",
    "sg:phone":"+34 916 78 11 15",
    "sg:postcode":"28830",
    "sg:province":"Madrid",
    "wof:name":"Quercus Robur S.l.",
    "wof:placetype":"venue"
},
  "geometry": {"coordinates":[-3.496530056,40.4579696655],"type":"Point"}
}