{
  "type": "Feature",
  "properties": {
    "addr:full":"Berezao Auzoa, 10 Berezao Guip\u00f9zcoa 20560",
    "addr:housenumber":"10",
    "addr:postcode":"20560",
    "addr:street":"Berezao Auzoa;Guipu\u0300Zcoa",
    "iso:country":"ES",
    "sg:address":"Berezao Auzoa, 10",
    "sg:city":"Berezao",
    "sg:orig_category":"Muebles, Minoristas",
    "sg:phone":"+34 943 71 63 39",
    "sg:postcode":"20560",
    "sg:province":"Guip\u00f9zcoa",
    "wof:name":"Arrizabalaga Bilbatua Jose",
    "wof:placetype":"venue"
},
  "geometry": {"coordinates":[-2.4078168869,43.0266571045],"type":"Point"}
}