{
  "type": "Feature",
  "properties": {
    "iso:country":"ES",
    "sg:address":"Calle de Pablo Gargallo, 22",
    "sg:city":"Madrid",
    "sg:orig_category":"Arquitectos",
    "sg:phone":"+34 913 73 80 59",
    "sg:postcode":"28035",
    "sg:province":"Madrid",
    "wof:name":"Brieva Beltran Ignacio",
    "wof:placetype":"venue"
},
  "geometry": {"coordinates":[-3.7334909439,40.4760093689],"type":"Point"}
}