{
  "type": "Feature",
  "properties": {
    "addr:full":"Pol Ind Isla Mayor, 112 Isla Mayor Sevilla 41140",
    "addr:housenumber":"112",
    "addr:postcode":"41140",
    "addr:street":"Isla",
    "iso:country":"ES",
    "sg:address":"Pol Ind Isla Mayor, 112",
    "sg:city":"Isla Mayor",
    "sg:orig_category":"Congelados: Productos Alimentarios (fabricaci\u00d3n, Al Por Mayor)",
    "sg:phone":"+34 954 77 77 91",
    "sg:postcode":"41140",
    "sg:province":"Sevilla",
    "sg:website":"www.emfacar.com",
    "wof:name":"Emfacar S.l.",
    "wof:placetype":"venue"
},
  "geometry": {"coordinates":[-6.1629891396,37.1334838867],"type":"Point"}
}