{
  "type": "Feature",
  "properties": {
    "iso:country":"ES",
    "sg:address":"Calle de San Restituto, 18",
    "sg:city":"Madrid",
    "sg:orig_category":"Inmobiliaria (agencias)",
    "sg:phone":"+34 913 98 04 55",
    "sg:postcode":"28039",
    "sg:province":"Madrid",
    "sg:website":"www.alfainmo.com/valdezarza",
    "wof:name":"Consulting Valdezarza Sl",
    "wof:placetype":"venue"
},
  "geometry": {"coordinates":[-3.7108879089,40.4648017883],"type":"Point"}
}