{
  "type": "Feature",
  "properties": {
    "iso:country":"ES",
    "sg:address":"Cra. Ulldecona, S/n",
    "sg:city":"La Senia",
    "sg:orig_category":"Fabricaci\u00d3n De Mobiliario Met\u00c1lico",
    "sg:phone":"+34 977 71 33 19",
    "sg:postcode":"43560",
    "sg:province":"Tarragona",
    "sg:website":"www.dissenia.com",
    "wof:name":"Talleres Vega S.a.l.",
    "wof:placetype":"venue"
},
  "geometry": {"coordinates":[0.284525007,40.63306427],"type":"Point"}
}