{
  "type": "Feature",
  "properties": {
    "addr:full":"Calle de Manzanos (de Los), 29 San Sebastian De Los Reyes Madrid 28700",
    "addr:housenumber":"29",
    "addr:postcode":"28700",
    "addr:street":"Calle De Manzanos De Los",
    "iso:country":"ES",
    "sg:address":"Calle de Manzanos (de Los), 29",
    "sg:city":"San Sebastian De Los Reyes",
    "sg:orig_category":"Herramientas Y Suministros Para Plomeros",
    "sg:phone":"+34 912 41 15 36",
    "sg:postcode":"28700",
    "sg:province":"Madrid",
    "wof:name":"Soportec 2003 S.l.",
    "wof:placetype":"venue"
},
  "geometry": {"coordinates":[-3.6183402538,40.5460777283],"type":"Point"}
}