{
  "type": "Feature",
  "properties": {
    "addr:full":"Calle de Bidasoa, 8 Bosque Madrid 28670",
    "addr:housenumber":"8",
    "addr:postcode":"28670",
    "addr:street":"Calle De Bidasoa",
    "iso:country":"ES",
    "sg:address":"Calle de Bidasoa, 8",
    "sg:city":"Bosque",
    "sg:orig_category":"Inversiones",
    "sg:phone":"+34 916 16 72 02",
    "sg:postcode":"28670",
    "sg:province":"Madrid",
    "wof:name":"Diestro Rivera Dionisio",
    "wof:placetype":"venue"
},
  "geometry": {"coordinates":[-3.9302031994,40.3868560791],"type":"Point"}
}