{
  "type": "Feature",
  "properties": {
    "iso:country":"ES",
    "sg:address":"Calle de Carretera, 40",
    "sg:city":"Rabita",
    "sg:orig_category":"Librer\u00cdas",
    "sg:phone":"+34 958 82 92 84",
    "sg:postcode":"18760",
    "sg:province":"Granada",
    "wof:name":"Ayala Ortega Nicolas",
    "wof:placetype":"venue"
},
  "geometry": {"coordinates":[-3.1706843376,36.7484893799],"type":"Point"}
}