{
  "type": "Feature",
  "properties": {
    "iso:country":"ES",
    "sg:address":"C. Guetara (p I Villarrosa), 30",
    "sg:city":"Malaga",
    "sg:orig_category":"Empresas De Impermeabilizaci\u00d3n",
    "sg:phone":"+34 952 24 74 06",
    "sg:postcode":"29004",
    "sg:province":"M\u00e1laga",
    "wof:name":"Integral P.m.i. S.l.",
    "wof:placetype":"venue"
},
  "geometry": {"coordinates":[-4.4720492363,36.6739196777],"type":"Point"}
}