{
  "type": "Feature",
  "properties": {
    "addr:full":"Carr Germanes Martinez, 58 Pu\u00e7ol Valencia 46530",
    "addr:housenumber":"58",
    "addr:postcode":"46530",
    "addr:street":"Carr Germanes Martinez",
    "iso:country":"ES",
    "sg:address":"Carr Germanes Martinez, 58",
    "sg:city":"Pu\u00e7ol",
    "sg:orig_category":"Empresas De Limpieza",
    "sg:phone":"+34 961 42 20 70",
    "sg:postcode":"46530",
    "sg:province":"Valencia",
    "sg:website":"www.vidaria.com",
    "wof:name":"O\u00f1a Esteve Consuelo",
    "wof:placetype":"venue"
},
  "geometry": {"coordinates":[-0.3028970063,39.6182136536],"type":"Point"}
}