{
  "type": "Feature",
  "properties": {
    "iso:country":"ES",
    "sg:address":"Ctra Mina, S/n",
    "sg:city":"Albujon",
    "sg:orig_category":"Carnes De Carnicer\u00cda (al Por Mayor)",
    "sg:phone":"+34 968 55 12 00",
    "sg:postcode":"30330",
    "sg:province":"Murcia",
    "wof:name":"Carnicas La Malineta S.coop",
    "wof:placetype":"venue"
},
  "geometry": {"coordinates":[-1.0482540131,37.7187614441],"type":"Point"}
}