{
  "type": "Feature",
  "properties": {
    "addr:full":"Carrer de Canigo, 10 Granollers Barcelona 08402",
    "addr:housenumber":"10",
    "addr:postcode":"08402",
    "addr:street":"Carrer De Canigo",
    "iso:country":"ES",
    "sg:address":"Carrer de Canigo, 10",
    "sg:city":"Granollers",
    "sg:orig_category":"Confecci\u00d3n De Trajes Para Se\u00d1oras",
    "sg:phone":"+34 938 79 29 05",
    "sg:postcode":"08402",
    "sg:province":"Barcelona",
    "wof:name":"Ruda Resina Eloisa",
    "wof:placetype":"venue"
},
  "geometry": {"coordinates":[2.2947330475,41.6076850891],"type":"Point"}
}