{
  "type": "Feature",
  "properties": {
    "addr:full":"Plaz Mayor, 7 Sahagun Le\u00f3n 24320",
    "addr:housenumber":"7",
    "addr:postcode":"24320",
    "addr:street":"Plaz Mayor;Leo\u0301N",
    "iso:country":"ES",
    "sg:address":"Plaz Mayor, 7",
    "sg:city":"Sahagun",
    "sg:orig_category":"Pr\u00c9stamos Personales E Hipotecarios",
    "sg:phone":"+34 987 78 02 11",
    "sg:postcode":"24320",
    "sg:province":"Le\u00f3n",
    "wof:name":"Crespo Torres Amalia",
    "wof:placetype":"venue"
},
  "geometry": {"coordinates":[-5.0312829018,42.3719825745],"type":"Point"}
}