{
  "type": "Feature",
  "properties": {
    "addr:full":"Calle de Monte Alto, 26 Pe\u00d1ascales Madrid 28250",
    "addr:housenumber":"26",
    "addr:postcode":"28250",
    "addr:street":"Calle De Monte Alto",
    "iso:country":"ES",
    "sg:address":"Calle de Monte Alto, 26",
    "sg:city":"Pe\u00d1ascales",
    "sg:orig_category":"Centros Empresariales",
    "sg:phone":"+34 918 42 95 00",
    "sg:postcode":"28250",
    "sg:province":"Madrid",
    "wof:name":"Azania Consulting S.l.",
    "wof:placetype":"venue"
},
  "geometry": {"coordinates":[-3.8862473965,40.5770492554],"type":"Point"}
}