{
  "type": "Feature",
  "properties": {
    "iso:country":"ES",
    "sg:address":"Calle de Sierra De Gredos, 52",
    "sg:city":"Guijuelo",
    "sg:orig_category":"Charcuter\u00cdas (al Por Mayor)",
    "sg:phone":"+34 923 58 16 12",
    "sg:postcode":"37770",
    "sg:province":"Salamanca",
    "wof:name":"Martin Cosme S.l.",
    "wof:placetype":"venue"
},
  "geometry": {"coordinates":[-5.6772289276,40.5363883972],"type":"Point"}
}