{
  "type": "Feature",
  "properties": {
    "iso:country":"ES",
    "sg:address":"Calle de Moreria, 3",
    "sg:city":"Ciudad Real",
    "sg:orig_category":"Reposter\u00cdas",
    "sg:phone":"+34 926 21 43 97",
    "sg:postcode":"13002",
    "sg:province":"Ciudad Real",
    "wof:name":"Real Pan S.l.",
    "wof:placetype":"venue"
},
  "geometry": {"coordinates":[-3.9309060574,38.9848861694],"type":"Point"}
}