{
  "type": "Feature",
  "properties": {
    "addr:full":"Prol. Alicante, 10 Alcoi Alicante 03801",
    "addr:housenumber":"10",
    "addr:postcode":"03801",
    "addr:street":"Prol. Alicante",
    "iso:country":"ES",
    "sg:address":"Prol. Alicante, 10",
    "sg:city":"Alcoi",
    "sg:orig_category":"Fabricaci\u00d3n De Telas Y Sedas",
    "sg:phone":"+34 965 54 01 80",
    "sg:postcode":"03801",
    "sg:province":"Alicante",
    "sg:website":"www.textilnumancia.com",
    "wof:name":"Perez Monllor Alvaro",
    "wof:placetype":"venue"
},
  "geometry": {"coordinates":[-0.4732739925,38.6984100342],"type":"Point"}
}