{
  "type": "Feature",
  "properties": {
    "iso:country":"ES",
    "sg:address":"Pla\u00c7 Independencia, 14",
    "sg:city":"Girona",
    "sg:orig_category":"Promotores Constructores",
    "sg:phone":"+34 972 20 55 08",
    "sg:postcode":"17001",
    "sg:province":"Girona",
    "wof:name":"Agrotec Oficina Tecnica Agricola S. Cv.",
    "wof:placetype":"venue"
},
  "geometry": {"coordinates":[2.8215665817,41.9854621887],"type":"Point"}
}