{
  "type": "Feature",
  "properties": {
    "addr:full":"Carr Sant Joan Baptista, 32 Figueres Girona 17600",
    "addr:housenumber":"32",
    "addr:postcode":"17600",
    "addr:street":"Carr Sant Joan Baptista",
    "iso:country":"ES",
    "sg:address":"Carr Sant Joan Baptista, 32",
    "sg:city":"Figueres",
    "sg:orig_category":"Empresas De Pintura Y Revestimientos",
    "sg:phone":"+34 972 50 54 34",
    "sg:postcode":"17600",
    "sg:province":"Girona",
    "wof:name":"Manzano Vila Josep",
    "wof:placetype":"venue"
},
  "geometry": {"coordinates":[2.9670290947,42.2671432495],"type":"Point"}
}