{
  "type": "Feature",
  "properties": {
    "iso:country":"ES",
    "sg:address":"Muelle Nuevo, S/n",
    "sg:city":"Port Pollen\u00e7a",
    "sg:orig_category":"Construcciones Navales Y Fluviales",
    "sg:phone":"+34 971 86 54 44",
    "sg:postcode":"07470",
    "sg:province":"Islas Baleares",
    "wof:name":"Astilleros Cabanellas S.l.",
    "wof:placetype":"venue"
},
  "geometry": {"coordinates":[3.017193079,39.8777542114],"type":"Point"}
}