{
  "type": "Feature",
  "properties": {
    "iso:country":"ES",
    "sg:address":"Carrer de Sant Cugat, 111",
    "sg:city":"Sabadell",
    "sg:orig_category":"Discotecas Y Salas De Baile",
    "sg:phone":"+34 937 25 77 14",
    "sg:postcode":"08201",
    "sg:province":"Barcelona",
    "wof:name":"Avantage Disc S.l.",
    "wof:placetype":"venue"
},
  "geometry": {"coordinates":[2.1035449505,41.5437889099],"type":"Point"}
}