{
  "type": "Feature",
  "properties": {
    "iso:country":"ES",
    "sg:address":"Cno. Albolote, S/n",
    "sg:city":"Maracena",
    "sg:orig_category":"Cerrajer\u00cda, Ferrallista",
    "sg:phone":"+34 958 42 15 53",
    "sg:postcode":"18200",
    "sg:province":"Granada",
    "wof:name":"Apesur 2005 S.l",
    "wof:placetype":"venue"
},
  "geometry": {"coordinates":[-3.6371071339,37.2142448425],"type":"Point"}
}