{
  "type": "Feature",
  "properties": {
    "addr:full":"Calle de Barrio Gimeno, 5 Burgos Burgos 09001",
    "addr:housenumber":"5",
    "addr:postcode":"09001",
    "addr:street":"Calle De Barrio Gimeno",
    "iso:country":"ES",
    "sg:address":"Calle de Barrio Gimeno, 5",
    "sg:city":"Burgos",
    "sg:orig_category":"Agentes, Concesionarios Y Sucursales De Camiones Y Veh\u00cdculos Industriales",
    "sg:phone":"+34 947 20 61 99",
    "sg:postcode":"09001",
    "sg:province":"Burgos",
    "wof:name":"Bicicletas De Castilla Y Leon S.l.",
    "wof:placetype":"venue"
},
  "geometry": {"coordinates":[-3.7030599117,42.3357810974],"type":"Point"}
}