{
  "type": "Feature",
  "properties": {
    "addr:full":"Pase Habana, 190 Madrid Madrid 28036",
    "addr:housenumber":"190",
    "addr:postcode":"madrid;28036",
    "iso:country":"ES",
    "sg:address":"Pase Habana, 190",
    "sg:city":"Madrid",
    "sg:orig_category":"Agencias Y Agentes Comerciales, Representantes",
    "sg:phone":"+34 913 50 29 91",
    "sg:postcode":"28036",
    "sg:province":"Madrid",
    "wof:name":"Alvarez Sanchez Rosa",
    "wof:placetype":"venue"
},
  "geometry": {"coordinates":[-3.6804602146,40.4617424011],"type":"Point"}
}