{
  "type": "Feature",
  "properties": {
    "addr:full":"Ctra Encinas Cantalapiedra, 4 Babilafuente Salamanca 37330",
    "addr:housenumber":"4",
    "addr:postcode":"37330",
    "addr:street":"Ctra Encinas Cantalapiedra",
    "iso:country":"ES",
    "sg:address":"Ctra Encinas Cantalapiedra, 4",
    "sg:city":"Babilafuente",
    "sg:orig_category":"Quincaller\u00cda (al Por Menor)",
    "sg:phone":"+34 923 36 08 62",
    "sg:postcode":"37330",
    "sg:province":"Salamanca",
    "wof:name":"Pavon Sanz Manuela",
    "wof:placetype":"venue"
},
  "geometry": {"coordinates":[-5.4237041473,40.9755210876],"type":"Point"}
}