{
  "type": "Feature",
  "properties": {
    "iso:country":"ES",
    "sg:address":"Calle de Marques De Jura Real, 14",
    "sg:city":"Madrid",
    "sg:orig_category":"Inform\u00c1tica (estudios, Servicios, Asesor\u00cda, Formaci\u00d3n)",
    "sg:phone":"+34 914 60 28 02",
    "sg:postcode":"28019",
    "sg:province":"Madrid",
    "wof:name":"Urkunde S.a.",
    "wof:placetype":"venue"
},
  "geometry": {"coordinates":[-3.7096879482,40.3923377991],"type":"Point"}
}