{
  "type": "Feature",
  "properties": {
    "addr:full":"Carrer de Mur, 157 Martorell Barcelona 08760",
    "addr:housenumber":"157",
    "addr:postcode":"08760",
    "addr:street":"Carrer De Mur",
    "iso:country":"ES",
    "sg:address":"Carrer de Mur, 157",
    "sg:city":"Martorell",
    "sg:orig_category":"Mec\u00c1nico Del Autom\u00d3vil",
    "sg:phone":"+34 937 75 49 25",
    "sg:postcode":"08760",
    "sg:province":"Barcelona",
    "wof:name":"Talleres Vilauto S.c.",
    "wof:placetype":"venue"
},
  "geometry": {"coordinates":[1.9362219572,41.4735679626],"type":"Point"}
}