{
  "type": "Feature",
  "properties": {
    "iso:country":"ES",
    "sg:address":"Grup San Juan, 19",
    "sg:city":"Castellon",
    "sg:orig_category":"Fabricaci\u00d3n De Muebles",
    "sg:phone":"+34 964 20 38 72",
    "sg:postcode":"12004",
    "sg:province":"Castell\u00f3n",
    "wof:name":"Talleres Eliosmar Vasel S.l.",
    "wof:placetype":"venue"
},
  "geometry": {"coordinates":[-0.0434890017,40.0005989075],"type":"Point"}
}