{
  "type": "Feature",
  "properties": {
    "addr:full":"Calle de Crisantemo, 6 Getafe Madrid 28903",
    "addr:housenumber":"6",
    "addr:postcode":"28903",
    "addr:street":"Calle De Crisantemo",
    "iso:country":"ES",
    "sg:address":"Calle de Crisantemo, 6",
    "sg:city":"Getafe",
    "sg:orig_category":"Arreglo, Reparaci\u00d3n, Piezas Sueltas De Televisi\u00d3n, V\u00cddeo, Hi",
    "sg:phone":"+34 916 96 17 64",
    "sg:postcode":"28903",
    "sg:province":"Madrid",
    "wof:name":"Nu\u00f1ez Matias Jose Maria",
    "wof:placetype":"venue"
},
  "geometry": {"coordinates":[-3.7235074043,40.3174591064],"type":"Point"}
}