{
  "type": "Feature",
  "properties": {
    "iso:country":"ES",
    "sg:address":"Calle de Gomez Becerra, 5",
    "sg:city":"Caceres",
    "sg:orig_category":"Caf\u00c9s, Bares, Cervecer\u00cdas",
    "sg:phone":"+34 927 24 94 62",
    "sg:postcode":"10001",
    "sg:province":"C\u00e1ceres",
    "wof:name":"Gomez Gomez Jose Maria",
    "wof:placetype":"venue"
},
  "geometry": {"coordinates":[-6.3799438477,39.4695281982],"type":"Point"}
}