{
  "type": "Feature",
  "properties": {
    "iso:country":"ES",
    "sg:address":"Pl Abastos, S/n",
    "sg:city":"Guadix",
    "sg:orig_category":"Carnicer\u00cdas, Carnicer\u00cdas",
    "sg:phone":"+34 958 66 14 49",
    "sg:postcode":"18500",
    "sg:province":"Granada",
    "wof:name":"Garcia Perez Josefa",
    "wof:placetype":"venue"
},
  "geometry": {"coordinates":[-3.1343688965,37.303894043],"type":"Point"}
}