{
  "type": "Feature",
  "properties": {
    "addr:full":"Calle de Rio Sella, 7 Gijon Asturias 33210",
    "addr:housenumber":"7",
    "addr:postcode":"33210",
    "addr:street":"Calle De Rio Sella",
    "iso:country":"ES",
    "sg:address":"Calle de Rio Sella, 7",
    "sg:city":"Gijon",
    "sg:orig_category":"Molduras, Junquillos, Listones Y Molduras Perforadas",
    "sg:phone":"+34 985 38 40 06",
    "sg:postcode":"33210",
    "sg:province":"Asturias",
    "wof:name":"Requena Fernandez Jose Ramon",
    "wof:placetype":"venue"
},
  "geometry": {"coordinates":[-5.6648578644,43.5220565796],"type":"Point"}
}