{
  "type": "Feature",
  "properties": {
    "iso:country":"ES",
    "sg:address":"Constitucion, 2",
    "sg:city":"Otero Herreros",
    "sg:orig_category":"Comerciantes Al Por Mayor De Vinos, Licores Y Alcoholes",
    "sg:phone":"+34 921 48 31 41",
    "sg:postcode":"40422",
    "sg:province":"Segovia",
    "wof:name":"Zancada Ares Juan Carlos",
    "wof:placetype":"venue"
},
  "geometry": {"coordinates":[-4.1192092896,40.9494285583],"type":"Point"}
}