{
  "type": "Feature",
  "properties": {
    "addr:full":"Calle de Mayor, 25 Sangonera La Verde O Ermita Nueva Murcia 30833",
    "addr:housenumber":"25",
    "addr:postcode":"30833",
    "addr:street":"Calle De Mayor",
    "iso:country":"ES",
    "sg:address":"Calle de Mayor, 25",
    "sg:city":"Sangonera La Verde O Ermita Nueva",
    "sg:orig_category":"Caf\u00c9s, Bares, Cervecer\u00cdas",
    "sg:phone":"+34 968 86 63 50",
    "sg:postcode":"30833",
    "sg:province":"Murcia",
    "wof:name":"Bastida Sanchez Juan",
    "wof:placetype":"venue"
},
  "geometry": {"coordinates":[-1.2084690332,37.9326210022],"type":"Point"}
}