{
  "type": "Feature",
  "properties": {
    "iso:country":"ES",
    "sg:address":"Carrer de Jesus, 28",
    "sg:city":"Reus",
    "sg:orig_category":"Heladeros",
    "sg:phone":"+34 977 34 07 27",
    "sg:postcode":"43201",
    "sg:province":"Tarragona",
    "wof:name":"Bondia Pinos S.l.",
    "wof:placetype":"venue"
},
  "geometry": {"coordinates":[1.1081039906,41.1543045044],"type":"Point"}
}