{
  "type": "Feature",
  "properties": {
    "iso:country":"ES",
    "sg:address":"Plza. Constitucion",
    "sg:city":"Almu\u00f1ecar",
    "sg:orig_category":"Ropa Para Ni\u00d1os (al Por Menor)",
    "sg:phone":"+34 958 88 06 25",
    "sg:postcode":"18690",
    "sg:province":"Granada",
    "wof:name":"Martin Cervera Maria Jose",
    "wof:placetype":"venue"
},
  "geometry": {"coordinates":[-3.6912341118,36.7338142395],"type":"Point"}
}