{
  "type": "Feature",
  "properties": {
    "addr:full":"Carr Mercat, 59 Pobla Islas Baleares 07420",
    "addr:housenumber":"59",
    "addr:postcode":"07420",
    "addr:street":"Carr Mercat;Baleares",
    "iso:country":"ES",
    "sg:address":"Carr Mercat, 59",
    "sg:city":"Pobla",
    "sg:orig_category":"Agencias De Viajes",
    "sg:phone":"+34 971 54 26 05",
    "sg:postcode":"07420",
    "sg:province":"Islas Baleares",
    "wof:name":"Agencia De Viajes Ca'n Picafort S. A.",
    "wof:placetype":"venue"
},
  "geometry": {"coordinates":[3.0269958973,39.7712249756],"type":"Point"}
}