{
  "type": "Feature",
  "properties": {
    "addr:full":"Carrer de Atlantic, 115 Barcelona Barcelona 08040",
    "addr:housenumber":"115",
    "addr:postcode":"08040",
    "addr:street":"Carrer De Atlantic",
    "iso:country":"ES",
    "sg:address":"Carrer de Atlantic, 115",
    "sg:city":"Barcelona",
    "sg:orig_category":"Fabricaci\u00d3n De Art\u00cdculos Y Equipos Deportivos Y De Ocio",
    "sg:phone":"+34 932 62 51 00",
    "sg:postcode":"08040",
    "sg:province":"Barcelona",
    "wof:name":"Amer Sports Spain S.a.",
    "wof:placetype":"venue"
},
  "geometry": {"coordinates":[2.1422102451,41.3263702393],"type":"Point"}
}