{
  "type": "Feature",
  "properties": {
    "iso:country":"ES",
    "sg:address":"Calle de Moreria, 19",
    "sg:city":"Ciudad Real",
    "sg:orig_category":"Peluquer\u00cdas, Peluquer\u00cda Mixta",
    "sg:phone":"+34 926 21 35 99",
    "sg:postcode":"13002",
    "sg:province":"Ciudad Real",
    "wof:name":"Puentes Funez Isabel",
    "wof:placetype":"venue"
},
  "geometry": {"coordinates":[-3.932790041,38.9859886169],"type":"Point"}
}