{
  "type": "Feature",
  "properties": {
    "iso:country":"ES",
    "sg:address":"Trva Zenete, 8",
    "sg:city":"San Jose",
    "sg:orig_category":"Arreglo, Reparaci\u00d3n, Piezas Sueltas De Televisi\u00d3n, V\u00cddeo, Hi",
    "sg:phone":"+34 968 46 50 40",
    "sg:postcode":"30800",
    "sg:province":"Murcia",
    "wof:name":"Servillorca Electronica",
    "wof:placetype":"venue"
},
  "geometry": {"coordinates":[-1.6905640364,37.680557251],"type":"Point"}
}