{
  "type": "Feature",
  "properties": {
    "iso:country":"ES",
    "sg:address":"Av Comte Guifre, 4",
    "sg:city":"Sant Joan De Les Abadesses",
    "sg:classifiers":[
        {
            "category":"Personal",
            "subcategory":"Barber",
            "type":"Services"
        }
    ],
    "sg:phone":"+34 972 72 03 40",
    "sg:postcode":"17860",
    "sg:province":"Girona",
    "sg:tags":[
        "caballeros",
        "de",
        "peluqueros"
    ],
    "wof:name":"Palau Verdaguer Pedro",
    "wof:placetype":"venue"
},
  "geometry": {"coordinates":[2.2864499092,42.2328643799],"type":"Point"}
}