{
  "type": "Feature",
  "properties": {
    "iso:country":"ES",
    "sg:address":"Calle de Estrella, 4",
    "sg:city":"Fuenlabrada De Los Montes",
    "sg:orig_category":"Agentes, Concesionarios Y Sucursales De Camiones Y Veh\u00cdculos Industriales",
    "sg:phone":"+34 924 65 60 01",
    "sg:postcode":"06660",
    "sg:province":"Badajoz",
    "wof:name":"La Calabresa S.l.",
    "wof:placetype":"venue"
},
  "geometry": {"coordinates":[-4.934032917,39.1314353943],"type":"Point"}
}