{
  "type": "Feature",
  "properties": {
    "iso:country":"ES",
    "sg:address":"Avda Aragon De, 38",
    "sg:city":"Fraga",
    "sg:orig_category":"Quincaller\u00cda (al Por Menor)",
    "sg:phone":"+34 974 47 19 38",
    "sg:postcode":"22520",
    "sg:province":"Huesca",
    "wof:name":"Surroca Mola Maria Asuncion",
    "wof:placetype":"venue"
},
  "geometry": {"coordinates":[0.3411409855,41.5215911865],"type":"Point"}
}