{
  "type": "Feature",
  "properties": {
    "addr:full":"Carr Sant Vicen\u00c7 Ferrer, 35 Blanes Girona 17300",
    "addr:housenumber":"35",
    "addr:postcode":"17300",
    "addr:street":"Carr Sant Vicenc\u0327 Ferrer",
    "iso:country":"ES",
    "sg:address":"Carr Sant Vicen\u00c7 Ferrer, 35",
    "sg:city":"Blanes",
    "sg:orig_category":"Cerrajer\u00cda, Ferrallista",
    "sg:phone":"+34 972 35 06 21",
    "sg:postcode":"17300",
    "sg:province":"Girona",
    "wof:name":"Montes Azogue Ivan",
    "wof:placetype":"venue"
},
  "geometry": {"coordinates":[2.7796900272,41.6720695496],"type":"Point"}
}