{
  "type": "Feature",
  "properties": {
    "iso:country":"ES",
    "sg:address":"C/ Campos, S/n",
    "sg:city":"Llucmajor",
    "sg:orig_category":"Fabricaci\u00d3n, Instalaci\u00d3n De Armarios",
    "sg:phone":"+34 971 66 08 92",
    "sg:postcode":"07620",
    "sg:province":"Islas Baleares",
    "wof:name":"Manresa Puig Miguel",
    "wof:placetype":"venue"
},
  "geometry": {"coordinates":[2.8980560303,39.4892272949],"type":"Point"}
}