{
  "type": "Feature",
  "properties": {
    "addr:full":"Carrer de Industria, 20 Barcelona Barcelona 08037",
    "addr:housenumber":"20",
    "addr:postcode":"08037",
    "addr:street":"Carrer De Industria",
    "iso:country":"ES",
    "sg:address":"Carrer de Industria, 20",
    "sg:city":"Barcelona",
    "sg:orig_category":"Asesor\u00cda De Formaci\u00d3n Y Gesti\u00d3n De Personal",
    "sg:phone":"+34 934 58 09 55",
    "sg:postcode":"08037",
    "sg:province":"Barcelona",
    "wof:name":"Zambrano Castejon Silvia",
    "wof:placetype":"venue"
},
  "geometry": {"coordinates":[2.1659297943,41.4031219482],"type":"Point"}
}