{
  "type": "Feature",
  "properties": {
    "addr:full":"Rbla Rambla, 118 Sabadell Barcelona 08201",
    "addr:postcode":"08201",
    "addr:street":"Rambla 118",
    "iso:country":"ES",
    "sg:address":"Rbla Rambla, 118",
    "sg:city":"Sabadell",
    "sg:orig_category":"Bancos",
    "sg:phone":"+34 937 26 12 88",
    "sg:postcode":"08201",
    "sg:province":"Barcelona",
    "sg:website":"www.bancopopular.es",
    "wof:name":"Banco Popular Espa\u00f1ol",
    "wof:placetype":"venue"
},
  "geometry": {"coordinates":[2.1105799675,41.5432128906],"type":"Point"}
}