{
  "type": "Feature",
  "properties": {
    "addr:full":"A Pol Ind Comarca I (agustinos), S/n Iru\u00f1a Navarra 31013",
    "addr:housenumber":"s",
    "addr:postcode":"31013",
    "addr:street":"/ N Irun\u0303A Navarra",
    "iso:country":"ES",
    "sg:address":"A Pol Ind Comarca I (agustinos), S/n",
    "sg:city":"Iru\u00f1a",
    "sg:orig_category":"Agencias De Viajes",
    "sg:phone":"+34 948 30 20 74",
    "sg:postcode":"31013",
    "sg:province":"Navarra",
    "sg:website":"www.viajeseroski.es",
    "wof:name":"Viajes Eroski S.a.",
    "wof:placetype":"venue"
},
  "geometry": {"coordinates":[-97.78224945069999,45.7040786743],"type":"Point"}
}