{
  "type": "Feature",
  "properties": {
    "iso:country":"ES",
    "sg:address":"Pol Ind Eluseder, S/n",
    "sg:city":"Areso",
    "sg:orig_category":"Aluminio Y Aleaciones (producci\u00d3n, Transformaci\u00d3n, Negocio)",
    "sg:phone":"+34 948 61 09 78",
    "sg:postcode":"31876",
    "sg:province":"Navarra",
    "wof:name":"Alpa Aluminio S.l",
    "wof:placetype":"venue"
},
  "geometry": {"coordinates":[-1.9539105892,43.0756874084],"type":"Point"}
}