{
  "type": "Feature",
  "properties": {
    "addr:full":"G.v. Lopez De Haro D. Diego, 39 Bilbao Vizcaya 48009",
    "addr:housenumber":"39",
    "addr:postcode":"48009",
    "addr:street":"Lopez De Haro D. Diego",
    "iso:country":"ES",
    "sg:address":"G.v. Lopez De Haro D. Diego, 39",
    "sg:city":"Bilbao",
    "sg:orig_category":"Asesor\u00cdas Y Estudios Financieros",
    "sg:phone":"+34 944 16 44 77",
    "sg:postcode":"48009",
    "sg:province":"Vizcaya",
    "wof:name":"Santamaria Rubio Francisco Javier",
    "wof:placetype":"venue"
},
  "geometry": {"coordinates":[-2.9341409206,43.2626647949],"type":"Point"}
}