{
  "type": "Feature",
  "properties": {
    "iso:country":"ES",
    "sg:address":"Calle de Heraldo De Aragon, 49",
    "sg:city":"Zaragoza",
    "sg:orig_category":"Tapicer\u00cdas",
    "sg:phone":"+34 976 33 82 56",
    "sg:postcode":"50012",
    "sg:province":"Zaragoza",
    "wof:name":"Pardos Lallana Miguel",
    "wof:placetype":"venue"
},
  "geometry": {"coordinates":[-0.9276220202,41.640007019],"type":"Point"}
}