{
  "type": "Feature",
  "properties": {
    "addr:full":"Calle de General Suarez Valdes, 11 Gijon Asturias 33204",
    "addr:housenumber":"11",
    "addr:postcode":"33204",
    "addr:street":"Calle De General Suarez Valdes",
    "iso:country":"ES",
    "sg:address":"Calle de General Suarez Valdes, 11",
    "sg:city":"Gijon",
    "sg:orig_category":"Electrodom\u00c9sticos (al Por Menor)",
    "sg:phone":"+34 985 37 39 35",
    "sg:postcode":"33204",
    "sg:province":"Asturias",
    "wof:name":"Pasa De Todo S.l.",
    "wof:placetype":"venue"
},
  "geometry": {"coordinates":[-5.6482839584,43.5329818726],"type":"Point"}
}