{
  "type": "Feature",
  "properties": {
    "iso:country":"ES",
    "sg:address":"Avda Tagomago, S/n",
    "sg:city":"Cala D'or",
    "sg:orig_category":"Inmobiliaria (alquileres Por Temporada Y Temporales)",
    "sg:phone":"+34 971 64 81 31",
    "sg:postcode":"07660",
    "sg:province":"Islas Baleares",
    "wof:name":"Almacen Perfumeria Aurai S.l.",
    "wof:placetype":"venue"
},
  "geometry": {"coordinates":[3.2295162678,39.3745613098],"type":"Point"}
}