{
  "type": "Feature",
  "properties": {
    "addr:full":"Carr Joan Xxiii, 3 Atzeneta D'albaida Valencia 46869",
    "addr:housenumber":"3",
    "addr:postcode":"46869",
    "addr:street":"Carr Joan Xxiii",
    "iso:country":"ES",
    "sg:address":"Carr Joan Xxiii, 3",
    "sg:city":"Atzeneta D'albaida",
    "sg:orig_category":"Cester\u00cda (fabricaci\u00d3n)",
    "sg:phone":"+34 962 35 60 56",
    "sg:postcode":"46869",
    "sg:province":"Valencia",
    "wof:name":"Ferri Soler S.l.",
    "wof:placetype":"venue"
},
  "geometry": {"coordinates":[-0.4981049895,38.8311805725],"type":"Point"}
}