{
  "type": "Feature",
  "properties": {
    "addr:full":"Carrer de Camp Arriassa, 104 Barcelona Barcelona 08020",
    "addr:housenumber":"104",
    "addr:postcode":"08020",
    "addr:street":"Carrer De Camp Arriassa",
    "iso:country":"ES",
    "sg:address":"Carrer de Camp Arriassa, 104",
    "sg:city":"Barcelona",
    "sg:orig_category":"Peluqueros: De Se\u00d1oras",
    "sg:phone":"+34 933 14 13 95",
    "sg:postcode":"08020",
    "sg:province":"Barcelona",
    "wof:name":"Gonzalez Urbano Lidia",
    "wof:placetype":"venue"
},
  "geometry": {"coordinates":[2.2016999722,41.4256439209],"type":"Point"}
}