{
  "type": "Feature",
  "properties": {
    "addr:full":"Carrer de Poima, 18 Poligon Industrial De Can Valero Islas Baleares 07011",
    "addr:housenumber":"18",
    "addr:postcode":"07011",
    "addr:street":"Carrer De Poima;Islas",
    "iso:country":"ES",
    "sg:address":"Carrer de Poima, 18",
    "sg:city":"Poligon Industrial De Can Valero",
    "sg:orig_category":"Molduras, Junquillos, Listones Y Molduras Perforadas",
    "sg:phone":"+34 971 20 06 20",
    "sg:postcode":"07011",
    "sg:province":"Islas Baleares",
    "wof:name":"Palmer Alemany Jose",
    "wof:placetype":"venue"
},
  "geometry": {"coordinates":[2.6205170155,39.5930747986],"type":"Point"}
}