{
  "type": "Feature",
  "properties": {
    "addr:full":"Avda Vi\u00d1uelas (de), 29 Tres Cantos Madrid 28760",
    "addr:housenumber":"29",
    "addr:postcode":"28760",
    "addr:street":"Avda Vin\u0303Uelas De",
    "iso:country":"ES",
    "sg:address":"Avda Vi\u00d1uelas (de), 29",
    "sg:city":"Tres Cantos",
    "sg:orig_category":"Cl\u00cdnicas M\u00c9dicas",
    "sg:phone":"+34 918 03 45 64",
    "sg:postcode":"28760",
    "sg:province":"Madrid",
    "wof:name":"Baz Lorenzo Purificacion",
    "wof:placetype":"venue"
},
  "geometry": {"coordinates":[-3.7023649216,40.5964317322],"type":"Point"}
}