{
  "type": "Feature",
  "properties": {
    "addr:full":"Carrer de Joan Guell, 174 Barcelona Barcelona 08028",
    "addr:housenumber":"174",
    "addr:postcode":"08028",
    "addr:street":"Carrer De Joan Guell",
    "iso:country":"ES",
    "sg:address":"Carrer de Joan Guell, 174",
    "sg:city":"Barcelona",
    "sg:orig_category":"Farmacias",
    "sg:phone":"+34 934 90 45 75",
    "sg:postcode":"08028",
    "sg:province":"Barcelona",
    "wof:name":"Collado Andanuche Montserrat",
    "wof:placetype":"venue"
},
  "geometry": {"coordinates":[2.1310229301,41.3841018677],"type":"Point"}
}