{
  "type": "Feature",
  "properties": {
    "iso:country":"ES",
    "sg:address":"Calle de Corrida, 46",
    "sg:city":"Gijon",
    "sg:orig_category":"M\u00c9dicos: Otorrinolaringolog\u00cda",
    "sg:phone":"+34 985 35 23 60",
    "sg:postcode":"33206",
    "sg:province":"Asturias",
    "wof:name":"Lozano Sanchez Antonio",
    "wof:placetype":"venue"
},
  "geometry": {"coordinates":[-5.6635351181,43.5401496887],"type":"Point"}
}