{
  "type": "Feature",
  "properties": {
    "addr:full":"Avda San Juan Bosco, 8 Utrera Sevilla 41710",
    "addr:housenumber":"8",
    "addr:postcode":"41710",
    "addr:street":"Avda San Juan Bosco",
    "iso:country":"ES",
    "sg:address":"Avda San Juan Bosco, 8",
    "sg:city":"Utrera",
    "sg:orig_category":"Comunidades Religiosas",
    "sg:phone":"+34 954 86 09 45",
    "sg:postcode":"41710",
    "sg:province":"Sevilla",
    "wof:name":"Hermandad Nuestro Padre Jesus Nazareno",
    "wof:placetype":"venue"
},
  "geometry": {"coordinates":[-5.7777848244,37.1766052246],"type":"Point"}
}