{
  "type": "Feature",
  "properties": {
    "addr:full":"Calle de Arco, 5 Palmas De Gran Canaria Las Palmas 35004",
    "addr:housenumber":"5",
    "addr:postcode":"35004",
    "addr:street":"Calle De Arco",
    "iso:country":"ES",
    "sg:address":"Calle de Arco, 5",
    "sg:city":"Palmas De Gran Canaria",
    "sg:orig_category":"Papel Pintado (al Por Menor)",
    "sg:phone":"+34 928 23 18 00",
    "sg:postcode":"35004",
    "sg:province":"Las Palmas",
    "wof:name":"Gil Quintana Juan Francisco",
    "wof:placetype":"venue"
},
  "geometry": {"coordinates":[-15.4251918793,28.1134662628],"type":"Point"}
}