{
  "type": "Feature",
  "properties": {
    "iso:country":"ES",
    "sg:address":"Plaz San Felix, 16",
    "sg:city":"Taco",
    "sg:orig_category":"Inform\u00c1tica (estudios, Servicios, Asesor\u00cda, Formaci\u00d3n)",
    "sg:phone":"+34 922 62 49 30",
    "sg:postcode":"38108",
    "sg:province":"Santa Cruz De Tenerife",
    "wof:name":"S.r.i. Tein S.l.",
    "wof:placetype":"venue"
},
  "geometry": {"coordinates":[-16.2957706451,28.4491081238],"type":"Point"}
}