{
  "type": "Feature",
  "properties": {
    "addr:full":"Calle de Bordadores (los), 35 Le\u00f3n Le\u00f3n 24006",
    "addr:housenumber":"35",
    "addr:postcode":"24006",
    "addr:street":"Calle De Bordadores Los;Leo\u0301N",
    "iso:country":"ES",
    "sg:address":"Calle de Bordadores (los), 35",
    "sg:city":"Le\u00f3n",
    "sg:orig_category":"Ingeniero",
    "sg:phone":"+34 987 26 37 10",
    "sg:postcode":"24006",
    "sg:province":"Le\u00f3n",
    "sg:website":"www.paginasamarillas.es",
    "wof:name":"Agrotecnos Y Digitalizacion S.l.",
    "wof:placetype":"venue"
},
  "geometry": {"coordinates":[-5.5609211922,42.5922889709],"type":"Point"}
}