{
  "type": "Feature",
  "properties": {
    "addr:full":"Calle de Doctor Fleming, 3 Calpe Alicante 03710",
    "addr:housenumber":"3",
    "addr:postcode":"03710",
    "addr:street":"Calle De Doctor Fleming",
    "iso:country":"ES",
    "sg:address":"Calle de Doctor Fleming, 3",
    "sg:city":"Calpe",
    "sg:orig_category":"Fiesta: Art\u00cdculos De (al Por Menor)",
    "sg:phone":"+34 965 83 09 05",
    "sg:postcode":"03710",
    "sg:province":"Alicante",
    "wof:name":"Party Calp",
    "wof:placetype":"venue"
},
  "geometry": {"coordinates":[0.0498079993,38.642868042],"type":"Point"}
}