{
  "type": "Feature",
  "properties": {
    "addr:full":"Calle de San Isidro, 1 Zamora Zamora 49027",
    "addr:postcode":"49027",
    "addr:street":"Calle De San Isidro",
    "iso:country":"ES",
    "sg:address":"Calle de San Isidro, 1",
    "sg:city":"Zamora",
    "sg:orig_category":"Hoteles",
    "sg:phone":"+34 980 51 26 98",
    "sg:postcode":"49027",
    "sg:province":"Zamora",
    "wof:name":"Ballesteros Fidalgo Francisco",
    "wof:placetype":"venue"
},
  "geometry": {"coordinates":[-5.7580718994,41.5053367615],"type":"Point"}
}