{
  "type": "Feature",
  "properties": {
    "addr:full":"Poli Industrial La Barca, 30 Villanueva Serena Badajoz 06700",
    "addr:housenumber":"30",
    "addr:postcode":"06700",
    "addr:street":"Villanueva Serena",
    "iso:country":"ES",
    "sg:address":"Poli Industrial La Barca, 30",
    "sg:city":"Villanueva Serena",
    "sg:orig_category":"Chapister\u00cda",
    "sg:phone":"+34 924 84 03 48",
    "sg:postcode":"06700",
    "sg:province":"Badajoz",
    "wof:name":"Auto Reparaciones Fort S.l.",
    "wof:placetype":"venue"
},
  "geometry": {"coordinates":[-6.9702835083,38.8785972595],"type":"Point"}
}