{
  "type": "Feature",
  "properties": {
    "addr:full":"Carr Guadiana, 21 Vila-roja Girona 17004",
    "addr:housenumber":"21",
    "addr:postcode":"17004",
    "addr:street":"Carr Guadiana",
    "iso:country":"ES",
    "sg:address":"Carr Guadiana, 21",
    "sg:city":"Vila-roja",
    "sg:orig_category":"Desinfecci\u00d3n, Desinsectaci\u00d3n, Desratizaci\u00d3n",
    "sg:phone":"+34 972 20 85 00",
    "sg:postcode":"17004",
    "sg:province":"Girona",
    "wof:name":"Antiplagues Girona S.c.",
    "wof:placetype":"venue"
},
  "geometry": {"coordinates":[2.843973875,41.973487854],"type":"Point"}
}