{
  "type": "Feature",
  "properties": {
    "iso:country":"ES",
    "sg:address":"Calle de Teniente Coronel Chapuli, 3",
    "sg:city":"Alacant",
    "sg:orig_category":"Serigraf\u00cda (material Y Suministros)",
    "sg:phone":"+34 965 21 82 51",
    "sg:postcode":"03001",
    "sg:province":"Alicante",
    "wof:name":"Print Shop S.l.",
    "wof:placetype":"venue"
},
  "geometry": {"coordinates":[-0.4839609861,38.3448104858],"type":"Point"}
}