{
  "type": "Feature",
  "properties": {
    "iso:country":"ES",
    "sg:address":"Calle de Villafranca, 1",
    "sg:city":"Astorga",
    "sg:orig_category":"Fabricaci\u00d3n De Art\u00cdculos Y Equipos Deportivos Y De Ocio",
    "sg:phone":"+34 987 61 64 39",
    "sg:postcode":"24700",
    "sg:province":"Le\u00f3n",
    "wof:name":"Deportes Gallego S.l.",
    "wof:placetype":"venue"
},
  "geometry": {"coordinates":[-6.0574321747,42.4563484192],"type":"Point"}
}