{
  "type": "Feature",
  "properties": {
    "addr:full":"Avgd 9 D'octubre, S/n Alcudia Crespins Valencia 46690",
    "addr:housenumber":"9;s / n",
    "addr:postcode":"46690",
    "addr:street":"Avgd;D'Octubre",
    "iso:country":"ES",
    "sg:address":"Avgd 9 D'octubre, S/n",
    "sg:city":"Alcudia Crespins",
    "sg:orig_category":"Hilaturas, Hilos Y Actividades Relacionadas",
    "sg:phone":"+34 962 24 25 44",
    "sg:postcode":"46690",
    "sg:province":"Valencia",
    "wof:name":"Multicoto Mp S.l.",
    "wof:placetype":"venue"
},
  "geometry": {"coordinates":[-0.3736720085,39.4934616089],"type":"Point"}
}