{
  "type": "Feature",
  "properties": {
    "addr:full":"Pol Ind Pilar De La Dehesa, Km. 0025,0 Jaen Ja\u00e9n 23006",
    "addr:postcode":"23006",
    "addr:street":"Dehesa Km. 0025,0 Jaen Jae\u0301N",
    "iso:country":"ES",
    "sg:address":"Pol Ind Pilar De La Dehesa, Km. 0025,0",
    "sg:city":"Jaen",
    "sg:orig_category":"Muebles Y Accesorios Para Cocinas Y Cuartos De Ba\u00d1o (al Por Menor)",
    "sg:phone":"+34 953 25 55 40",
    "sg:postcode":"23006",
    "sg:province":"Ja\u00e9n",
    "wof:name":"Cruz Moreno Francisco",
    "wof:placetype":"venue"
},
  "geometry": {"coordinates":[-3.7906870842,37.7650947571],"type":"Point"}
}