{
  "type": "Feature",
  "properties": {
    "addr:full":"Trva San Fernando, 2 Santa Cruz De Bezana Cantabria 39100",
    "addr:housenumber":"2",
    "addr:postcode":"39100",
    "addr:street":"Trva San Fernando",
    "iso:country":"ES",
    "sg:address":"Trva San Fernando, 2",
    "sg:city":"Santa Cruz De Bezana",
    "sg:orig_category":"Centros Empresariales",
    "sg:phone":"+34 942 58 56 10",
    "sg:postcode":"39100",
    "sg:province":"Cantabria",
    "wof:name":"Schief & Krumm S.l.",
    "wof:placetype":"venue"
},
  "geometry": {"coordinates":[-3.8987278938,43.440322876],"type":"Point"}
}