{
  "type": "Feature",
  "properties": {
    "addr:full":"Calle de Artur Perucho I Badia, 2 Burriana Castell\u00f3n 12530",
    "addr:housenumber":"2",
    "addr:postcode":"12530",
    "addr:street":"Calle De Artur Perucho I Badia",
    "iso:country":"ES",
    "sg:address":"Calle de Artur Perucho I Badia, 2",
    "sg:city":"Burriana",
    "sg:orig_category":"Institutos De Belleza",
    "sg:phone":"+34 964 57 02 70",
    "sg:postcode":"12530",
    "sg:province":"Castell\u00f3n",
    "wof:name":"Main'si C.b.",
    "wof:placetype":"venue"
},
  "geometry": {"coordinates":[-0.0807923973,39.8873825073],"type":"Point"}
}