{
  "type": "Feature",
  "properties": {
    "iso:country":"ES",
    "sg:address":"Carrer de Mig (del), 62",
    "sg:city":"Mas Rampinyo",
    "sg:orig_category":"Charcuter\u00cdas (al Por Mayor)",
    "sg:phone":"+34 935 75 11 90",
    "sg:postcode":"08110",
    "sg:province":"Barcelona",
    "wof:name":"Agustin Torrella S.a.",
    "wof:placetype":"venue"
},
  "geometry": {"coordinates":[2.1903452873,41.5024681091],"type":"Point"}
}