{
  "type": "Feature",
  "properties": {
    "iso:country":"ES",
    "sg:address":"Calle de San Pedro, 33",
    "sg:city":"Grao",
    "sg:orig_category":"Reposter\u00cdas",
    "sg:phone":"+34 964 21 70 41",
    "sg:postcode":"12004",
    "sg:province":"Castell\u00f3n",
    "wof:name":"Castello Gil Federico",
    "wof:placetype":"venue"
},
  "geometry": {"coordinates":[0.0330299996,40.0113639832],"type":"Point"}
}