{
  "type": "Feature",
  "properties": {
    "iso:country":"ES",
    "sg:address":"Santo, 2",
    "sg:city":"Garrovillas De Alconetar",
    "sg:orig_category":"Cerrajer\u00cda, Ferrallista",
    "sg:phone":"+34 927 30 91 28",
    "sg:postcode":"10940",
    "sg:province":"C\u00e1ceres",
    "wof:name":"Cerrajeria Cordero C.b",
    "wof:placetype":"venue"
},
  "geometry": {"coordinates":[-6.5512828827,39.7100067139],"type":"Point"}
}