{
  "type": "Feature",
  "properties": {
    "addr:full":"Calle de Luis De Vargas, 6 Sevilla Sevilla 41001",
    "addr:housenumber":"6",
    "addr:postcode":"41001",
    "addr:street":"Calle De Luis De Vargas",
    "iso:country":"ES",
    "sg:address":"Calle de Luis De Vargas, 6",
    "sg:city":"Sevilla",
    "sg:orig_category":"Alimentaci\u00d3n General (al Por Menor)",
    "sg:phone":"+34 954 21 09 50",
    "sg:postcode":"41001",
    "sg:province":"Sevilla",
    "wof:name":"Polianski  Andrei",
    "wof:placetype":"venue"
},
  "geometry": {"coordinates":[-6.0018568039,37.3902931213],"type":"Point"}
}