{
  "type": "Feature",
  "properties": {
    "iso:country":"ES",
    "sg:address":"Calle de Domingo Labajo, 5",
    "sg:city":"Candeleda",
    "sg:orig_category":"Telas Y Sedas (al Por Menor)",
    "sg:phone":"+34 920 38 00 17",
    "sg:postcode":"05480",
    "sg:province":"\u00c1vila",
    "wof:name":"Reviriego Monforte Casimiro",
    "wof:placetype":"venue"
},
  "geometry": {"coordinates":[-5.2406191826,40.1542320251],"type":"Point"}
}