{
  "type": "Feature",
  "properties": {
    "iso:country":"ES",
    "sg:address":"Calle de Izaro Monte, 8",
    "sg:city":"Bilbao",
    "sg:orig_category":"Molduras, Junquillos, Listones Y Molduras Perforadas",
    "sg:phone":"+34 944 13 20 03",
    "sg:postcode":"48007",
    "sg:province":"Vizcaya",
    "wof:name":"Ruty Iba\u00f1ez Salazar",
    "wof:placetype":"venue"
},
  "geometry": {"coordinates":[-2.9196429253,43.2674446106],"type":"Point"}
}