{
  "type": "Feature",
  "properties": {
    "addr:full":"Calle de Padre Victoriano Rodriguez, 3 Avila \u00c1vila 05005",
    "addr:housenumber":"3",
    "addr:postcode":"05005",
    "addr:street":"Calle De Padre Victoriano Rodriguez;A\u0301Vila",
    "iso:country":"ES",
    "sg:address":"Calle de Padre Victoriano Rodriguez, 3",
    "sg:city":"Avila",
    "sg:orig_category":"Perfumer\u00cda, Art\u00cdculos De Ba\u00d1o (fabricaci\u00d3n, Al Por Mayor)",
    "sg:phone":"+34 920 25 54 90",
    "sg:postcode":"05005",
    "sg:province":"\u00c1vila",
    "wof:name":"Yedra Rodrigo S.l.",
    "wof:placetype":"venue"
},
  "geometry": {"coordinates":[-4.6866722107,40.6594009399],"type":"Point"}
}