{
  "type": "Feature",
  "properties": {
    "iso:country":"ES",
    "sg:address":"Avda Rep Argentina, S/n",
    "sg:city":"Bormujos",
    "sg:orig_category":"Ingenier\u00cda, Centros De Estudios (diversos)",
    "sg:phone":"+34 954 57 17 85",
    "sg:postcode":"41930",
    "sg:province":"Sevilla",
    "wof:name":"Ingenieros Dintra 5 S.l.",
    "wof:placetype":"venue"
},
  "geometry": {"coordinates":[-6.0756187439,37.3786239624],"type":"Point"}
}