{
  "type": "Feature",
  "properties": {
    "iso:country":"ES",
    "sg:address":"Calle de Aragon, 8",
    "sg:city":"Orihuela",
    "sg:orig_category":"Tintes (fabricaci\u00d3n, Al Por Mayor)",
    "sg:phone":"+34 965 30 16 05",
    "sg:postcode":"03300",
    "sg:province":"Alicante",
    "wof:name":"Tintoreria Manolo C.b.",
    "wof:placetype":"venue"
},
  "geometry": {"coordinates":[-0.9486842752,38.0818786621],"type":"Point"}
}