{
  "type": "Feature",
  "properties": {
    "addr:full":"Carrer de Casp, 108 Barcelona Barcelona 08010",
    "addr:housenumber":"108",
    "addr:postcode":"08010",
    "addr:street":"Carrer De Casp",
    "iso:country":"ES",
    "sg:address":"Carrer de Casp, 108",
    "sg:city":"Barcelona",
    "sg:orig_category":"Asociaciones Humanitarias, De Cooperaci\u00d3n, De Acci\u00d3n Social",
    "sg:phone":"+34 934 12 57 46",
    "sg:postcode":"08010",
    "sg:province":"Barcelona",
    "wof:name":"Associacio De Familiars Amb Alzheimer",
    "wof:placetype":"venue"
},
  "geometry": {"coordinates":[2.1777331829,41.3946456909],"type":"Point"}
}