{
  "type": "Feature",
  "properties": {
    "addr:full":"Calle de Via, 25 Valladolid Valladolid 47005",
    "addr:housenumber":"25",
    "addr:postcode":"47005",
    "addr:street":"Calle De Via",
    "iso:country":"ES",
    "sg:address":"Calle de Via, 25",
    "sg:city":"Valladolid",
    "sg:orig_category":"Puertas Y Portales",
    "sg:phone":"+34 983 29 78 59",
    "sg:postcode":"47005",
    "sg:province":"Valladolid",
    "wof:name":"Alvarez Benedit Luis",
    "wof:placetype":"venue"
},
  "geometry": {"coordinates":[-4.7115211487,41.6499443054],"type":"Point"}
}