{
  "type": "Feature",
  "properties": {
    "iso:country":"ES",
    "sg:address":"Calle de Carmen, 1",
    "sg:city":"Mazarron",
    "sg:orig_category":"M\u00c9dicos: Salud P\u00dablica",
    "sg:phone":"+34 968 33 31 37",
    "sg:postcode":"30870",
    "sg:province":"Murcia",
    "sg:website":"www.grupospm.com",
    "wof:name":"Serpremur S.l.",
    "wof:placetype":"venue"
},
  "geometry": {"coordinates":[-1.3136110306,37.598777771],"type":"Point"}
}