{
  "type": "Feature",
  "properties": {
    "addr:full":"Avda Buenos Aires, 3 Palencia Palencia 34003",
    "addr:housenumber":"3",
    "addr:postcode":"34003",
    "addr:street":"Avda Buenos Aires",
    "iso:country":"ES",
    "sg:address":"Avda Buenos Aires, 3",
    "sg:city":"Palencia",
    "sg:orig_category":"Molduras, Junquillos, Listones Y Molduras Perforadas",
    "sg:phone":"+34 979 72 95 52",
    "sg:postcode":"34003",
    "sg:province":"Palencia",
    "wof:name":"Sanchez Sanchez Adrian",
    "wof:placetype":"venue"
},
  "geometry": {"coordinates":[-4.5231051445,42.0116577148],"type":"Point"}
}