{
  "type": "Feature",
  "properties": {
    "iso:country":"ES",
    "sg:address":"Calle de Mercado Chico, 83",
    "sg:city":"Barraco",
    "sg:orig_category":"Supermercados Y Hipermercados",
    "sg:phone":"+34 920 28 13 03",
    "sg:postcode":"05110",
    "sg:province":"\u00c1vila",
    "wof:name":"Alimentaciones General Hermanas Diaz Varas S.l.",
    "wof:placetype":"venue"
},
  "geometry": {"coordinates":[-4.6427760124,40.4757804871],"type":"Point"}
}