{
  "type": "Feature",
  "properties": {
    "addr:full":"Carrer de Avellaners (dels), 1 Reus Tarragona 43206",
    "addr:housenumber":"1",
    "addr:postcode":"43206",
    "addr:street":"Carrer De Avellaners Dels",
    "iso:country":"ES",
    "sg:address":"Carrer de Avellaners (dels), 1",
    "sg:city":"Reus",
    "sg:orig_category":"Guarder\u00cdas",
    "sg:phone":"+34 977 77 09 24",
    "sg:postcode":"43206",
    "sg:province":"Tarragona",
    "wof:name":"Mafalda Ii S.c.p.",
    "wof:placetype":"venue"
},
  "geometry": {"coordinates":[1.1112309694,41.1441459656],"type":"Point"}
}