{
  "type": "Feature",
  "properties": {
    "iso:country":"ES",
    "sg:address":"Calle de Josefa Diaz, 4",
    "sg:city":"Madrid",
    "sg:orig_category":"Pescader\u00cdas (al Por Menor)",
    "sg:phone":"+34 914 78 82 64",
    "sg:postcode":"28038",
    "sg:province":"Madrid",
    "wof:name":"Cadierno Fuente Eleuterio",
    "wof:placetype":"venue"
},
  "geometry": {"coordinates":[-3.6583740711,40.3930664062],"type":"Point"}
}