{
  "type": "Feature",
  "properties": {
    "addr:full":"Calle de Trasmiera, S/n Santander Cantabria 39005",
    "addr:housenumber":"s / n",
    "addr:postcode":"39005",
    "addr:street":"Calle De Trasmiera",
    "iso:country":"ES",
    "sg:address":"Calle de Trasmiera, S/n",
    "sg:city":"Santander",
    "sg:orig_category":"Tapicer\u00cdas",
    "sg:phone":"+34 942 27 70 74",
    "sg:postcode":"39005",
    "sg:province":"Cantabria",
    "wof:name":"Zamanillo Robledo Francisco",
    "wof:placetype":"venue"
},
  "geometry": {"coordinates":[-3.7918629646,43.4700508118],"type":"Point"}
}