{
  "type": "Feature",
  "properties": {
    "addr:full":"Calle de Mendez Nu\u00d1ez, 17 Almeria Almer\u00eda 04001",
    "addr:housenumber":"17",
    "addr:postcode":"04001",
    "addr:street":"Calle De Mendez Nun\u0303Ez",
    "iso:country":"ES",
    "sg:address":"Calle de Mendez Nu\u00d1ez, 17",
    "sg:city":"Almeria",
    "sg:orig_category":"Abogados",
    "sg:phone":"+34 950 24 48 45",
    "sg:postcode":"04001",
    "sg:province":"Almer\u00eda",
    "wof:name":"Caparros Torrecillas Francisco",
    "wof:placetype":"venue"
},
  "geometry": {"coordinates":[-2.4618699551,36.8388023376],"type":"Point"}
}