{
  "type": "Feature",
  "properties": {
    "addr:full":"Carrer de Marti Molins, 60 Barcelona Barcelona 08027",
    "addr:housenumber":"60",
    "addr:postcode":"08027",
    "addr:street":"Carrer De Marti Molins",
    "iso:country":"ES",
    "sg:address":"Carrer de Marti Molins, 60",
    "sg:city":"Barcelona",
    "sg:orig_category":"Asilos De Ancianos. Centros Privados",
    "sg:phone":"+34 933 40 54 40",
    "sg:postcode":"08027",
    "sg:province":"Barcelona",
    "wof:name":"Associacio De Serveis Als Avis De Sant Andreu I La Sagrera",
    "wof:placetype":"venue"
},
  "geometry": {"coordinates":[2.188426733,41.4240036011],"type":"Point"}
}