{
  "type": "Feature",
  "properties": {
    "iso:country":"ES",
    "sg:address":"Ctra. Jerez-cartagena, Km. 0140,8",
    "sg:city":"Campillos",
    "sg:orig_category":"Restaurantes",
    "sg:phone":"+34 952 72 24 91",
    "sg:postcode":"29320",
    "sg:province":"M\u00e1laga",
    "wof:name":"Agrotoscal S.l.",
    "wof:placetype":"venue"
},
  "geometry": {"coordinates":[-4.8604846001,37.0521812439],"type":"Point"}
}