{
  "type": "Feature",
  "properties": {
    "iso:country":"ES",
    "sg:address":"Calle de Ruiz Pons, 2",
    "sg:city":"Bu\u00f1ol",
    "sg:orig_category":"Asesor\u00cda Fiscal Y Jur\u00cddica",
    "sg:phone":"+34 962 50 14 36",
    "sg:postcode":"46360",
    "sg:province":"Valencia",
    "wof:name":"Hernandez Alepuz Jose Miguel",
    "wof:placetype":"venue"
},
  "geometry": {"coordinates":[-0.7883089781,39.417930603],"type":"Point"}
}