{
  "type": "Feature",
  "properties": {
    "iso:country":"ES",
    "sg:address":"Carrer de Galio, 3",
    "sg:city":"Magaluf",
    "sg:orig_category":"Oficinas De Cambio",
    "sg:phone":"+34 971 13 01 45",
    "sg:postcode":"07181",
    "sg:province":"Islas Baleares",
    "wof:name":"Campos Linde Miguel Angel",
    "wof:placetype":"venue"
},
  "geometry": {"coordinates":[2.5340778828,39.5097084045],"type":"Point"}
}