{
  "type": "Feature",
  "properties": {
    "iso:country":"ES",
    "sg:address":"Fons, 76",
    "sg:city":"Juneda",
    "sg:orig_category":"M\u00c1quinas De Jardiner\u00cda",
    "sg:phone":"+34 973 15 01 80",
    "sg:postcode":"25430",
    "sg:province":"Lleida",
    "wof:name":"Maquinaria Fruticola Vallverdu S.l.",
    "wof:placetype":"venue"
},
  "geometry": {"coordinates":[0.8262090087,41.5451660156],"type":"Point"}
}