{
  "type": "Feature",
  "properties": {
    "iso:country":"ES",
    "sg:address":"Calle de Ermita, 8",
    "sg:city":"Valencia",
    "sg:orig_category":"Fabricaci\u00d3n De Enlosados, Soler\u00cdas",
    "sg:phone":"+34 963 80 36 33",
    "sg:postcode":"46007",
    "sg:province":"Valencia",
    "wof:name":"Construcciones Sanfelix Pastor S.l.",
    "wof:placetype":"venue"
},
  "geometry": {"coordinates":[-0.3798609972,39.4649162292],"type":"Point"}
}