{
  "type": "Feature",
  "properties": {
    "iso:country":"ES",
    "sg:address":"Carr Vallcalent, 51",
    "sg:city":"Lleida",
    "sg:orig_category":"Empresas De Carpinter\u00cda De Madera",
    "sg:phone":"+34 973 26 63 94",
    "sg:postcode":"25006",
    "sg:province":"Lleida",
    "wof:name":"Freixinet Sales Jose",
    "wof:placetype":"venue"
},
  "geometry": {"coordinates":[0.6170629859,41.6176452637],"type":"Point"}
}