{
  "type": "Feature",
  "properties": {
    "addr:full":"Carrer de Roses (sants), 58 Barcelona Barcelona 08028",
    "addr:housenumber":"58",
    "addr:postcode":"08028",
    "addr:street":"Carrer De Roses Sants",
    "iso:country":"ES",
    "sg:address":"Carrer de Roses (sants), 58",
    "sg:city":"Barcelona",
    "sg:orig_category":"Promotores Constructores",
    "sg:phone":"+34 934 90 65 49",
    "sg:postcode":"08028",
    "sg:province":"Barcelona",
    "wof:name":"Sants Habitatges S.l.",
    "wof:placetype":"venue"
},
  "geometry": {"coordinates":[2.1336410046,41.3784637451],"type":"Point"}
}