{
  "type": "Feature",
  "properties": {
    "addr:full":"Avda Ategorrieta De, 75 Donostia-san Sebastian Guip\u00f9zcoa 20013",
    "addr:housenumber":"75",
    "addr:postcode":"20013",
    "addr:street":"Avda Ategorrieta De",
    "iso:country":"ES",
    "sg:address":"Avda Ategorrieta De, 75",
    "sg:city":"Donostia-san Sebastian",
    "sg:orig_category":"Molduras, Junquillos, Listones Y Molduras Perforadas",
    "sg:phone":"+34 943 32 27 09",
    "sg:postcode":"20013",
    "sg:province":"Guip\u00f9zcoa",
    "wof:name":"Go\u00f1i Achabal Miguel Maria",
    "wof:placetype":"venue"
},
  "geometry": {"coordinates":[-1.9600820541,43.3218460083],"type":"Point"}
}