{
  "type": "Feature",
  "properties": {
    "iso:country":"ES",
    "sg:address":"Avda Levante (de), 41",
    "sg:city":"Jumilla",
    "sg:orig_category":"Servicios De Telecomunicaciones",
    "sg:phone":"+34 968 75 62 33",
    "sg:postcode":"30520",
    "sg:province":"Murcia",
    "sg:website":"www.mundosatelite.es",
    "wof:name":"Gonzalez Abellan Antonio",
    "wof:placetype":"venue"
},
  "geometry": {"coordinates":[-1.3243249655,38.474521637],"type":"Point"}
}