{
  "type": "Feature",
  "properties": {
    "iso:country":"ES",
    "sg:address":"Avda Feria, 9",
    "sg:city":"Zamora",
    "sg:orig_category":"Molduras, Junquillos, Listones Y Molduras Perforadas",
    "sg:phone":"+34 980 53 18 18",
    "sg:postcode":"49004",
    "sg:province":"Zamora",
    "wof:name":"Gonzalez Gonzalez Adriano",
    "wof:placetype":"venue"
},
  "geometry": {"coordinates":[-5.749396801,41.5046730042],"type":"Point"}
}