{
  "type": "Feature",
  "properties": {
    "addr:full":"Calle de Educacion (de La), 19 Mostoles Madrid 28937",
    "addr:housenumber":"19",
    "addr:postcode":"28937",
    "addr:street":"Calle De Educacion De La",
    "iso:country":"ES",
    "sg:address":"Calle de Educacion (de La), 19",
    "sg:city":"Mostoles",
    "sg:orig_category":"Electricidad: Instaladores",
    "sg:phone":"+34 916 13 88 44",
    "sg:postcode":"28937",
    "sg:province":"Madrid",
    "wof:name":"Luansa Instalaciones S.l",
    "wof:placetype":"venue"
},
  "geometry": {"coordinates":[-3.8816790581,40.3262214661],"type":"Point"}
}