{
  "type": "Feature",
  "properties": {
    "iso:country":"ES",
    "sg:address":"Carrer de Sant Agusti, 2",
    "sg:city":"Pego",
    "sg:orig_category":"Molduras, Junquillos, Listones Y Molduras Perforadas",
    "sg:phone":"+34 965 57 03 01",
    "sg:postcode":"03780",
    "sg:province":"Alicante",
    "wof:name":"Rosello Alguer Roberto",
    "wof:placetype":"venue"
},
  "geometry": {"coordinates":[-0.1183770001,38.8417358398],"type":"Point"}
}