{
  "type": "Feature",
  "properties": {
    "addr:full":"Calle de Esperanto, S/n Valladolid Valladolid 47007",
    "addr:housenumber":"s / n",
    "addr:postcode":"47007",
    "addr:street":"Calle De Esperanto",
    "iso:country":"ES",
    "sg:address":"Calle de Esperanto, S/n",
    "sg:city":"Valladolid",
    "sg:orig_category":"Muebles, Minoristas",
    "sg:phone":"+34 983 22 72 37",
    "sg:postcode":"47007",
    "sg:province":"Valladolid",
    "wof:name":"Carmen Monje Decoracion Sl",
    "wof:placetype":"venue"
},
  "geometry": {"coordinates":[-4.7382540703,41.6335601807],"type":"Point"}
}