{
  "type": "Feature",
  "properties": {
    "iso:country":"ES",
    "sg:address":"Avgd Doctor Fleming, 27",
    "sg:city":"Lleida",
    "sg:orig_category":"Asesor\u00cdas Y Estudios Financieros",
    "sg:phone":"+34 973 26 84 34",
    "sg:postcode":"25006",
    "sg:province":"Lleida",
    "wof:name":"Guiu Assessoraments S.l.",
    "wof:placetype":"venue"
},
  "geometry": {"coordinates":[0.6147530079,41.6197280884],"type":"Point"}
}