{
  "type": "Feature",
  "properties": {
    "iso:country":"ES",
    "sg:address":"Calle de Higuera (la), 7",
    "sg:city":"Cordoba",
    "sg:orig_category":"Inmobiliaria (agencias)",
    "sg:phone":"+34 957 27 90 96",
    "sg:postcode":"14006",
    "sg:province":"C\u00f3rdoba",
    "wof:name":"Olaru Multiservices S.l.",
    "wof:placetype":"venue"
},
  "geometry": {"coordinates":[-4.7797760963,37.8979606628],"type":"Point"}
}