{
  "type": "Feature",
  "properties": {
    "addr:full":"Calle de Iglesia, 1 Nava De Arevalo \u00c1vila 05216",
    "addr:housenumber":"1",
    "addr:postcode":"05216",
    "addr:street":"Calle De Iglesia",
    "iso:country":"ES",
    "sg:address":"Calle de Iglesia, 1",
    "sg:city":"Nava De Arevalo",
    "sg:orig_category":"Iglesia Cat\u00d3lica",
    "sg:phone":"+34 920 31 40 05",
    "sg:postcode":"05216",
    "sg:province":"\u00c1vila",
    "wof:name":"Parroquia De Nava De Arevalo",
    "wof:placetype":"venue"
},
  "geometry": {"coordinates":[-4.7762088776,40.9774703979],"type":"Point"}
}