{
  "type": "Feature",
  "properties": {
    "addr:full":"Calle de Castilla, S/n Zaragoza Zaragoza 50009",
    "addr:housenumber":"s / n",
    "addr:postcode":"50009",
    "addr:street":"Calle De Castilla",
    "iso:country":"ES",
    "sg:address":"Calle de Castilla, S/n",
    "sg:city":"Zaragoza",
    "sg:orig_category":"Cajas De Ahorro",
    "sg:phone":"+34 976 75 21 43",
    "sg:postcode":"50009",
    "sg:province":"Zaragoza",
    "wof:name":"Caja De Ahorros De La Inmaculada",
    "wof:placetype":"venue"
},
  "geometry": {"coordinates":[-0.9108567834,41.6428527832],"type":"Point"}
}