{
  "type": "Feature",
  "properties": {
    "iso:country":"ES",
    "sg:address":"Pase Convento, 2",
    "sg:city":"Sisante",
    "sg:orig_category":"Centros De Educaci\u00d3n Especial",
    "sg:phone":"+34 969 38 71 12",
    "sg:postcode":"16700",
    "sg:province":"Cuenca",
    "wof:name":"Colegio Publico Fernandez Turegano",
    "wof:placetype":"venue"
},
  "geometry": {"coordinates":[-2.2006139755,39.4064064026],"type":"Point"}
}