{
  "type": "Feature",
  "properties": {
    "addr:full":"Carrer de Riera D'horta, 37 Barcelona Barcelona 08027",
    "addr:housenumber":"37",
    "addr:postcode":"08027",
    "addr:street":"Carrer De Riera D'Horta",
    "iso:country":"ES",
    "sg:address":"Carrer de Riera D'horta, 37",
    "sg:city":"Barcelona",
    "sg:orig_category":"Agencias Y Agentes Comerciales, Representantes",
    "sg:phone":"+34 934 08 23 56",
    "sg:postcode":"08027",
    "sg:province":"Barcelona",
    "wof:name":"Alvez Da Silva Vilma",
    "wof:placetype":"venue"
},
  "geometry": {"coordinates":[2.1817967892,41.4277267456],"type":"Point"}
}