{
  "type": "Feature",
  "properties": {
    "addr:full":"Avia Puente Colgante, S/n Valladolid Valladolid 47014",
    "addr:housenumber":"s / n",
    "addr:postcode":"47014",
    "addr:street":"Puente Colgante",
    "iso:country":"ES",
    "sg:address":"Avia Puente Colgante, S/n",
    "sg:city":"Valladolid",
    "sg:orig_category":"Animales (al Por Menor)",
    "sg:phone":"+34 983 34 49 44",
    "sg:postcode":"47014",
    "sg:province":"Valladolid",
    "wof:name":"Zoopucela S.l.",
    "wof:placetype":"venue"
},
  "geometry": {"coordinates":[-4.7536277771,41.6377105713],"type":"Point"}
}