{
  "type": "Feature",
  "properties": {
    "iso:country":"ES",
    "sg:address":"Rua Calvo Sotelo, 118",
    "sg:city":"Sarria",
    "sg:orig_category":"Farmacias",
    "sg:phone":"+34 982 53 10 88",
    "sg:postcode":"27600",
    "sg:province":"Lugo",
    "wof:name":"Lopez Vazquez Mercedes",
    "wof:placetype":"venue"
},
  "geometry": {"coordinates":[-7.4111561775,42.7787742615],"type":"Point"}
}