{
  "type": "Feature",
  "properties": {
    "addr:full":"Calle de Colombia, 8 Salamanca Salamanca 37003",
    "addr:housenumber":"8",
    "addr:postcode":"37003",
    "addr:street":"Calle De Colombia",
    "iso:country":"ES",
    "sg:address":"Calle de Colombia, 8",
    "sg:city":"Salamanca",
    "sg:orig_category":"Estudios De Grabaci\u00d3n Sonora",
    "sg:phone":"+34 923 18 00 21",
    "sg:postcode":"37003",
    "sg:province":"Salamanca",
    "wof:name":"Estudio El Rollo S.l.",
    "wof:placetype":"venue"
},
  "geometry": {"coordinates":[-5.6467871666,40.9685058594],"type":"Point"}
}