{
  "type": "Feature",
  "properties": {
    "addr:full":"Carr Constitucio, 17 Vila Joiosa Alicante 03570",
    "addr:housenumber":"17",
    "addr:postcode":"03570",
    "addr:street":"Carr Constitucio",
    "iso:country":"ES",
    "sg:address":"Carr Constitucio, 17",
    "sg:city":"Vila Joiosa",
    "sg:classifiers":[
        {
            "category":"Personal",
            "subcategory":"Barber",
            "type":"Services"
        }
    ],
    "sg:phone":"+34 966 85 08 36",
    "sg:postcode":"03570",
    "sg:province":"Alicante",
    "sg:tags":[
        "caballeros",
        "de",
        "peluqueros"
    ],
    "wof:name":"Botia Martinez Cristobal",
    "wof:placetype":"venue"
},
  "geometry": {"coordinates":[-0.2327190042,38.505821228],"type":"Point"}
}