{
  "type": "Feature",
  "properties": {
    "addr:full":"Calle de Vado De Pedro Mu\u00d1oz, 1 Santa Maria De Los Llanos Cuenca 16639",
    "addr:housenumber":"1",
    "addr:postcode":"16639",
    "addr:street":"Calle De Vado De Pedro Mun\u0303Oz",
    "iso:country":"ES",
    "sg:address":"Calle de Vado De Pedro Mu\u00d1oz, 1",
    "sg:city":"Santa Maria De Los Llanos",
    "sg:orig_category":"Frutas, Legumbres Frescas Y Tempranas (al Por Menor)",
    "sg:phone":"+34 967 18 71 11",
    "sg:postcode":"16639",
    "sg:province":"Cuenca",
    "wof:name":"Ristrasol S.l.",
    "wof:placetype":"venue"
},
  "geometry": {"coordinates":[-2.8076510429,39.4879989624],"type":"Point"}
}