{
  "type": "Feature",
  "properties": {
    "iso:country":"ES",
    "sg:address":"Calle de Medico Manero Molla, 6",
    "sg:city":"Alacant",
    "sg:orig_category":"Fabricaci\u00d3n De Sobres, Bolsas Y Fundas",
    "sg:phone":"+34 965 21 87 47",
    "sg:postcode":"03001",
    "sg:province":"Alicante",
    "wof:name":"Fu Tai S.l.",
    "wof:placetype":"venue"
},
  "geometry": {"coordinates":[-0.4836699963,38.3439216614],"type":"Point"}
}