{
  "type": "Feature",
  "properties": {
    "addr:full":"Ctra Terrassa, 76 Rubi Barcelona 08191",
    "addr:housenumber":"76",
    "addr:postcode":"08191",
    "addr:street":"Ctra Terrassa",
    "iso:country":"ES",
    "sg:address":"Ctra Terrassa, 76",
    "sg:city":"Rubi",
    "sg:orig_category":"Molduras, Junquillos, Listones Y Molduras Perforadas",
    "sg:phone":"+34 935 88 05 74",
    "sg:postcode":"08191",
    "sg:province":"Barcelona",
    "wof:name":"Moreno Medina Sergio",
    "wof:placetype":"venue"
},
  "geometry": {"coordinates":[2.0326910019,41.5002632141],"type":"Point"}
}