{
  "type": "Feature",
  "properties": {
    "iso:country":"ES",
    "sg:address":"Calle de Hermanos Valdes, 12",
    "sg:city":"Cuenca",
    "sg:orig_category":"Abogados",
    "sg:phone":"+34 969 23 41 77",
    "sg:postcode":"16002",
    "sg:province":"Cuenca",
    "wof:name":"Alique Lopez Francisco Javier",
    "wof:placetype":"venue"
},
  "geometry": {"coordinates":[-2.1364371777,40.0740623474],"type":"Point"}
}