{
  "type": "Feature",
  "properties": {
    "addr:full":"Calle de Miguel Yuste, 9 Madrid Madrid 28037",
    "addr:housenumber":"9",
    "addr:postcode":"madrid;28037",
    "addr:street":"Calle De Miguel Yuste",
    "iso:country":"ES",
    "sg:address":"Calle de Miguel Yuste, 9",
    "sg:city":"Madrid",
    "sg:orig_category":"Fabricaci\u00d3n De Bolsos Y Bolsos De Tela",
    "sg:phone":"+34 913 27 28 32",
    "sg:postcode":"28037",
    "sg:province":"Madrid",
    "sg:website":"www.noberplast.com",
    "wof:name":"Noberplast S.l.",
    "wof:placetype":"venue"
},
  "geometry": {"coordinates":[-3.6250779629,40.4403915405],"type":"Point"}
}