{
  "type": "Feature",
  "properties": {
    "iso:country":"ES",
    "sg:address":"Calle de Luis Feito, 5",
    "sg:city":"Madrid",
    "sg:orig_category":"Chapister\u00cda",
    "sg:phone":"+34 914 62 19 35",
    "sg:postcode":"28047",
    "sg:province":"Madrid",
    "wof:name":"Talleres Auto-fibra S.l.",
    "wof:placetype":"venue"
},
  "geometry": {"coordinates":[-3.7438819408,40.3910102844],"type":"Point"}
}