{
  "type": "Feature",
  "properties": {
    "iso:country":"ES",
    "sg:address":"Carrer de Era D'esquerra, 15",
    "sg:city":"Manresa",
    "sg:orig_category":"Asociaciones, Organismos Culturales Y Socioeducativos",
    "sg:phone":"+34 938 72 02 55",
    "sg:postcode":"08242",
    "sg:province":"Barcelona",
    "wof:name":"Casal Cultura Dansaires Manresans",
    "wof:placetype":"venue"
},
  "geometry": {"coordinates":[2.2522349358,41.4533424377],"type":"Point"}
}