{
  "type": "Feature",
  "properties": {
    "addr:full":"Pol Ind La Escarbada, S/n Ayamonte Huelva 21400",
    "addr:housenumber":"s",
    "addr:postcode":"21400",
    "addr:street":"/ N",
    "iso:country":"ES",
    "sg:address":"Pol Ind La Escarbada, S/n",
    "sg:city":"Ayamonte",
    "sg:orig_category":"Congelados: Productos Alimentarios (fabricaci\u00d3n, Al Por Mayor)",
    "sg:phone":"+34 959 32 00 23",
    "sg:postcode":"21400",
    "sg:province":"Huelva",
    "wof:name":"Manuel Amoros E Hijos S.a.",
    "wof:placetype":"venue"
},
  "geometry": {"coordinates":[-7.4089279175,37.2172279358],"type":"Point"}
}