{
  "type": "Feature",
  "properties": {
    "addr:full":"Calle de Jose Cobo, 15 Cuenca Cuenca 16004",
    "addr:housenumber":"15",
    "addr:postcode":"16004",
    "addr:street":"Calle De Jose Cobo",
    "iso:country":"ES",
    "sg:address":"Calle de Jose Cobo, 15",
    "sg:city":"Cuenca",
    "sg:orig_category":"Confecci\u00d3n De Trajes Para Se\u00d1oras",
    "sg:phone":"+34 969 23 23 80",
    "sg:postcode":"16004",
    "sg:province":"Cuenca",
    "wof:name":"Hernaiz Molina Africa",
    "wof:placetype":"venue"
},
  "geometry": {"coordinates":[-2.1362390518,40.0720710754],"type":"Point"}
}