{
  "type": "Feature",
  "properties": {
    "addr:full":"Calle de Campo Madre De Dios, 22 Cordoba C\u00f3rdoba 14002",
    "addr:housenumber":"22",
    "addr:postcode":"14002",
    "addr:street":"Calle De Campo Madre;Dios;Co\u0301Rdoba",
    "iso:country":"ES",
    "sg:address":"Calle de Campo Madre De Dios, 22",
    "sg:city":"Cordoba",
    "sg:orig_category":"Pescader\u00cdas (al Por Menor)",
    "sg:phone":"+34 957 25 27 52",
    "sg:postcode":"14002",
    "sg:province":"C\u00f3rdoba",
    "wof:name":"Santiago Fernandez Rafael",
    "wof:placetype":"venue"
},
  "geometry": {"coordinates":[-4.7667999268,37.883354187],"type":"Point"}
}