{
  "type": "Feature",
  "properties": {
    "addr:full":"Calle de Cruz, 4 Madrid Madrid 28012",
    "addr:housenumber":"4",
    "addr:postcode":"28012",
    "addr:street":"Calle De Cruz",
    "iso:country":"ES",
    "sg:address":"Calle de Cruz, 4",
    "sg:city":"Madrid",
    "sg:orig_category":"Panader\u00cdas, Panader\u00cdas",
    "sg:phone":"+34 915 32 38 86",
    "sg:postcode":"28012",
    "sg:province":"Madrid",
    "wof:name":"La Suiza S. A.",
    "wof:placetype":"venue"
},
  "geometry": {"coordinates":[-3.7007758617,40.4162864685],"type":"Point"}
}