{
  "type": "Feature",
  "properties": {
    "addr:full":"Av Aiguera, 5 Benidorm Alicante 03500",
    "addr:housenumber":"5",
    "addr:postcode":"03500",
    "addr:street":"Av Aiguera",
    "iso:country":"ES",
    "sg:address":"Av Aiguera, 5",
    "sg:city":"Benidorm",
    "sg:orig_category":"Cl\u00cdnicas M\u00c9dicas",
    "sg:phone":"+34 966 88 90 55",
    "sg:postcode":"03500",
    "sg:province":"Alicante",
    "wof:name":"Ibermutuamur",
    "wof:placetype":"venue"
},
  "geometry": {"coordinates":[-0.1743289977,38.5408058167],"type":"Point"}
}