{
  "type": "Feature",
  "properties": {
    "addr:full":"Plaz Almagra (de La), 4 Cordoba C\u00f3rdoba 14002",
    "addr:housenumber":"4",
    "addr:postcode":"14002",
    "addr:street":"Plaz;Cordoba Co\u0301Rdoba",
    "iso:country":"ES",
    "sg:address":"Plaz Almagra (de La), 4",
    "sg:city":"Cordoba",
    "sg:orig_category":"Inversiones",
    "sg:phone":"+34 957 49 09 53",
    "sg:postcode":"14002",
    "sg:province":"C\u00f3rdoba",
    "wof:name":"Hijos De Trivi\u00f1o Y Gonzalez S.l.",
    "wof:placetype":"venue"
},
  "geometry": {"coordinates":[-4.7728629112,37.8832550049],"type":"Point"}
}