{
  "type": "Feature",
  "properties": {
    "iso:country":"ES",
    "sg:address":"Calle de Muro Santa Maria, 10",
    "sg:city":"Alca\u00f1iz",
    "sg:orig_category":"Molduras, Junquillos, Listones Y Molduras Perforadas",
    "sg:phone":"+34 978 83 38 73",
    "sg:postcode":"44600",
    "sg:province":"Teruel",
    "wof:name":"Daroca Gracia Santiago",
    "wof:placetype":"venue"
},
  "geometry": {"coordinates":[-0.1355929971,41.051815033],"type":"Point"}
}