{
  "type": "Feature",
  "properties": {
    "iso:country":"ES",
    "sg:address":"Rond Muralla (da), 85",
    "sg:city":"Lugo",
    "sg:orig_category":"Ropa Para Se\u00d1oras (al Por Menor)",
    "sg:phone":"+34 982 24 29 06",
    "sg:postcode":"27003",
    "sg:province":"Lugo",
    "wof:name":"Zalo S.l.",
    "wof:placetype":"venue"
},
  "geometry": {"coordinates":[-7.513894558,43.034614563],"type":"Point"}
}