{
  "type": "Feature",
  "properties": {
    "iso:country":"ES",
    "sg:address":"Calle de Olmeda, 50",
    "sg:city":"Alguazas",
    "sg:orig_category":"Comercio, Reparaci\u00d3n De Bicicletas, De Motocicletas, De Accesorios",
    "sg:phone":"+34 968 62 01 24",
    "sg:postcode":"30560",
    "sg:province":"Murcia",
    "wof:name":"Franco Marco Onofre",
    "wof:placetype":"venue"
},
  "geometry": {"coordinates":[-1.242429018,38.0503578186],"type":"Point"}
}