{
  "type": "Feature",
  "properties": {
    "iso:country":"ES",
    "sg:address":"Urb. Guadalvillas, 136",
    "sg:city":"San Pedro Alcantara",
    "sg:orig_category":"Asesor\u00cda Sobre Comunicaci\u00d3n De Empresas",
    "sg:phone":"+34 952 78 12 34",
    "sg:postcode":"29670",
    "sg:province":"M\u00e1laga",
    "wof:name":"Dimersa Asesores S.l.",
    "wof:placetype":"venue"
},
  "geometry": {"coordinates":[-5.003718853,36.4735946655],"type":"Point"}
}