{
  "type": "Feature",
  "properties": {
    "addr:full":"Calle de Urkizuaran, S/n Elorrio Vizcaya 48230",
    "addr:housenumber":"s",
    "addr:postcode":"48230",
    "addr:street":"Calle De Urkizuaran;/ N",
    "iso:country":"ES",
    "sg:address":"Calle de Urkizuaran, S/n",
    "sg:city":"Elorrio",
    "sg:orig_category":"Maquinaria Para Industrias Diversas",
    "sg:phone":"+34 946 58 26 00",
    "sg:postcode":"48230",
    "sg:province":"Vizcaya",
    "wof:name":"Angio S. A.",
    "wof:placetype":"venue"
},
  "geometry": {"coordinates":[-2.5339620113,43.1229095459],"type":"Point"}
}