{
  "type": "Feature",
  "properties": {
    "iso:country":"ES",
    "sg:address":"Calle de Victor De La Serna, 31",
    "sg:city":"Madrid",
    "sg:orig_category":"Chapa Y Pintura Veh\u00cdculos",
    "sg:phone":"+34 915 19 89 28",
    "sg:postcode":"28016",
    "sg:province":"Madrid",
    "wof:name":"Plazio Sobron Carlos",
    "wof:placetype":"venue"
},
  "geometry": {"coordinates":[-3.6716680527,40.455871582],"type":"Point"}
}