{
  "type": "Feature",
  "properties": {
    "addr:full":"Ronda Vi\u00f1edos, 25 Jerez C\u00e1diz 11406",
    "addr:housenumber":"25",
    "addr:postcode":"11406",
    "addr:street":"Ronda Vin\u0303Edos",
    "iso:country":"ES",
    "sg:address":"Ronda Vi\u00f1edos, 25",
    "sg:city":"Jerez",
    "sg:classifiers":[
        {
            "category":"Autos & Motor Vehicles",
            "subcategory":"Automobile Sales",
            "type":"Retail Goods"
        }
    ],
    "sg:phone":"+34 956 34 30 54",
    "sg:postcode":"11406",
    "sg:province":"C\u00e1diz",
    "wof:name":"Angel Bocarando S.l.",
    "wof:placetype":"venue"
},
  "geometry": {"coordinates":[-6.120554924,36.6835784912],"type":"Point"}
}