{
  "type": "Feature",
  "properties": {
    "iso:country":"ES",
    "sg:address":"Avda Severo Ochoa, 24",
    "sg:city":"Marbella",
    "sg:orig_category":"M\u00c9dicos: Cirug\u00cda Urol\u00d3gica",
    "sg:phone":"+34 952 77 69 67",
    "sg:postcode":"29600",
    "sg:province":"M\u00e1laga",
    "wof:name":"Romero Dominguez Rafael",
    "wof:placetype":"venue"
},
  "geometry": {"coordinates":[-4.8735837936,36.5092658997],"type":"Point"}
}