{
  "type": "Feature",
  "properties": {
    "addr:full":"Calle de Belgica, 3 Valencia Valencia 46021",
    "addr:housenumber":"3",
    "addr:postcode":"46021",
    "addr:street":"Calle De Belgica",
    "iso:country":"ES",
    "sg:address":"Calle de Belgica, 3",
    "sg:city":"Valencia",
    "sg:orig_category":"Molduras, Junquillos, Listones Y Molduras Perforadas",
    "sg:phone":"+34 963 60 64 53",
    "sg:postcode":"46021",
    "sg:province":"Valencia",
    "wof:name":"Vendrell Toledo Enrique",
    "wof:placetype":"venue"
},
  "geometry": {"coordinates":[-0.356193006,39.4730377197],"type":"Point"}
}