{
  "type": "Feature",
  "properties": {
    "addr:full":"Ctra Lora-puebla Infantes, Km. 0005,0 Lora Rio Sevilla 41440",
    "addr:postcode":"41440",
    "addr:street":"Ctra Lora-Puebla Infantes Km. 0005,0",
    "iso:country":"ES",
    "sg:address":"Ctra Lora-puebla Infantes, Km. 0005,0",
    "sg:city":"Lora Rio",
    "sg:orig_category":"Plomeros",
    "sg:phone":"+34 955 95 60 56",
    "sg:postcode":"41440",
    "sg:province":"Sevilla",
    "wof:name":"Aqualia Gestion Integral Del Agua S.a.",
    "wof:placetype":"venue"
},
  "geometry": {"coordinates":[-5.9962949753,37.3826408386],"type":"Point"}
}