{
  "type": "Feature",
  "properties": {
    "iso:country":"ES",
    "sg:address":"Calle de Cuchilleria, 13",
    "sg:city":"Vitoria-gasteiz",
    "sg:orig_category":"Peluqueros: De Se\u00d1oras",
    "sg:phone":"+34 945 25 64 23",
    "sg:postcode":"01001",
    "sg:province":"\u00c1lava",
    "wof:name":"Diaz Otalora Maria Jesus",
    "wof:placetype":"venue"
},
  "geometry": {"coordinates":[-2.6708440781,42.8479156494],"type":"Point"}
}