{
  "type": "Feature",
  "properties": {
    "iso:country":"ES",
    "sg:address":"Calle de Marbella, 28",
    "sg:city":"Estacion",
    "sg:orig_category":"Chapister\u00cda",
    "sg:phone":"+34 952 42 09 78",
    "sg:postcode":"29580",
    "sg:province":"M\u00e1laga",
    "wof:name":"Guadalhorce S L",
    "wof:placetype":"venue"
},
  "geometry": {"coordinates":[-4.6112260818,36.7336540222],"type":"Point"}
}