{
  "type": "Feature",
  "properties": {
    "addr:full":"Av Sant Joan De Deu, 81 Playa De Calafell Tarragona 43820",
    "addr:housenumber":"81",
    "addr:postcode":"43820",
    "addr:street":"Av Sant Joan De Deu",
    "iso:country":"ES",
    "sg:address":"Av Sant Joan De Deu, 81",
    "sg:city":"Playa De Calafell",
    "sg:orig_category":"Ropa Para Se\u00d1oras (al Por Menor)",
    "sg:phone":"+34 977 69 36 53",
    "sg:postcode":"43820",
    "sg:province":"Tarragona",
    "wof:name":"Miralles Arroyo Tomasa",
    "wof:placetype":"venue"
},
  "geometry": {"coordinates":[1.573472023,41.1873092651],"type":"Point"}
}