{
  "type": "Feature",
  "properties": {
    "addr:full":"Carr Font D'arguines, S/n Alfara De Algimia Valencia 46148",
    "addr:housenumber":"s / n",
    "addr:postcode":"46148",
    "addr:street":"Carr Font D'Arguines",
    "iso:country":"ES",
    "sg:address":"Carr Font D'arguines, S/n",
    "sg:city":"Alfara De Algimia",
    "sg:orig_category":"Producci\u00d3n De Cart\u00d3n",
    "sg:phone":"+34 962 62 60 11",
    "sg:postcode":"46148",
    "sg:province":"Valencia",
    "wof:name":"Industria Papelera Nesa S. L.",
    "wof:placetype":"venue"
},
  "geometry": {"coordinates":[-0.356189996,39.7654914856],"type":"Point"}
}