{
  "type": "Feature",
  "properties": {
    "iso:country":"ES",
    "sg:address":"Calle de Huerta Chica, 16",
    "sg:city":"Marbella",
    "sg:orig_category":"Ropa Para Ni\u00d1os (al Por Menor)",
    "sg:phone":"+34 952 77 23 44",
    "sg:postcode":"29600",
    "sg:province":"M\u00e1laga",
    "sg:website":"www.cayetanababy.com",
    "wof:name":"Lopez Lima Isabel Maria",
    "wof:placetype":"venue"
},
  "geometry": {"coordinates":[-4.8866400719,36.509677887],"type":"Point"}
}