{
  "type": "Feature",
  "properties": {
    "addr:full":"Ctra Palma Del Rio (villarrubia), 200 Villarrubia C\u00f3rdoba 14710",
    "addr:housenumber":"200",
    "addr:postcode":"14710",
    "addr:street":"Ctra Palma Del Rio Villarrubia;Co\u0301Rdoba",
    "iso:country":"ES",
    "sg:address":"Ctra Palma Del Rio (villarrubia), 200",
    "sg:city":"Villarrubia",
    "sg:orig_category":"Cristaler\u00cdas",
    "sg:phone":"+34 957 45 85 35",
    "sg:postcode":"14710",
    "sg:province":"C\u00f3rdoba",
    "wof:name":"Acristalamiento Hermanos Serrano S.l.",
    "wof:placetype":"venue"
},
  "geometry": {"coordinates":[-4.9000496864,37.8542518616],"type":"Point"}
}