{
  "type": "Feature",
  "properties": {
    "iso:country":"ES",
    "sg:address":"Rua Santo Domingo, 45",
    "sg:city":"Ourense",
    "sg:orig_category":"Ropa Para Se\u00d1oras (al Por Menor)",
    "sg:phone":"+34 988 25 31 26",
    "sg:postcode":"32003",
    "sg:province":"Ourense",
    "wof:name":"Tilve Molares Pilar",
    "wof:placetype":"venue"
},
  "geometry": {"coordinates":[-7.8631339073,42.340385437],"type":"Point"}
}