{
  "type": "Feature",
  "properties": {
    "addr:full":"Calle de Sacratif, 28 Sevilla Sevilla 41016",
    "addr:housenumber":"28",
    "addr:postcode":"41016",
    "addr:street":"Calle De Sacratif",
    "iso:country":"ES",
    "sg:address":"Calle de Sacratif, 28",
    "sg:city":"Sevilla",
    "sg:orig_category":"Chapister\u00cda",
    "sg:phone":"+34 954 67 45 40",
    "sg:postcode":"41016",
    "sg:province":"Sevilla",
    "wof:name":"Moreno Perez Juan",
    "wof:placetype":"venue"
},
  "geometry": {"coordinates":[-5.9168348312,37.384563446],"type":"Point"}
}