{
  "type": "Feature",
  "properties": {
    "addr:full":"Calle de Almona De San Juan De Dios, 12 Granada Granada 18001",
    "addr:housenumber":"12",
    "addr:postcode":"18001",
    "addr:street":"Calle De Almona De San Juan;Dios",
    "iso:country":"ES",
    "sg:address":"Calle de Almona De San Juan De Dios, 12",
    "sg:city":"Granada",
    "sg:orig_category":"Asociaciones Y Clubs Deportivos",
    "sg:phone":"+34 958 20 67 04",
    "sg:postcode":"18001",
    "sg:province":"Granada",
    "wof:name":"Club Deportivo Bodyfactory",
    "wof:placetype":"venue"
},
  "geometry": {"coordinates":[-3.6030957699,37.1824645996],"type":"Point"}
}