{
  "type": "Feature",
  "properties": {
    "iso:country":"ES",
    "sg:address":"Landeta Hiribidea, 46",
    "sg:city":"Azpeitia",
    "sg:orig_category":"M\u00c1rmoles, Granitos Y Piedras Naturales",
    "sg:phone":"+34 943 15 14 13",
    "sg:postcode":"20730",
    "sg:province":"Guip\u00f9zcoa",
    "wof:name":"Larraga\u00f1a Arbelak S.l.",
    "wof:placetype":"venue"
},
  "geometry": {"coordinates":[-2.2528951168,43.1755027771],"type":"Point"}
}