{
  "type": "Feature",
  "properties": {
    "addr:full":"Calle de Nueva, 12 Donostia-san Sebastian Guip\u00f9zcoa 20001",
    "addr:housenumber":"12",
    "addr:postcode":"20001",
    "addr:street":"Calle De Nueva",
    "iso:country":"ES",
    "sg:address":"Calle de Nueva, 12",
    "sg:city":"Donostia-san Sebastian",
    "sg:orig_category":"Peluquer\u00cdas, Peluquer\u00cda Mixta",
    "sg:phone":"+34 943 27 92 70",
    "sg:postcode":"20001",
    "sg:province":"Guip\u00f9zcoa",
    "wof:name":"Legarra Cortajarena Ana Isabel",
    "wof:placetype":"venue"
},
  "geometry": {"coordinates":[-1.9735759497,43.3232269287],"type":"Point"}
}