{
  "type": "Feature",
  "properties": {
    "addr:full":"Calle de Burgos, 9 Santander Cantabria 39008",
    "addr:housenumber":"9",
    "addr:postcode":"39008",
    "addr:street":"Calle De Burgos",
    "iso:country":"ES",
    "sg:address":"Calle de Burgos, 9",
    "sg:city":"Santander",
    "sg:orig_category":"Zapatos (al Por Menor)",
    "sg:phone":"+34 942 23 49 46",
    "sg:postcode":"39008",
    "sg:province":"Cantabria",
    "wof:name":"Carrera Mesones Maria Soledad",
    "wof:placetype":"venue"
},
  "geometry": {"coordinates":[-3.815046072,43.4614562988],"type":"Point"}
}