{
  "type": "Feature",
  "properties": {
    "iso:country":"ES",
    "sg:address":"Zubietas, 3",
    "sg:city":"Dudea",
    "sg:orig_category":"Ebanister\u00cda",
    "sg:phone":"+34 946 30 00 60",
    "sg:postcode":"48290",
    "sg:province":"Vizcaya",
    "wof:name":"Carpinteria Elexalde S.a.",
    "wof:placetype":"venue"
},
  "geometry": {"coordinates":[-2.6911990643,43.1808815002],"type":"Point"}
}