{
  "type": "Feature",
  "properties": {
    "addr:full":"Calle de Achucarro Doctor, 9 Bilbao Vizcaya 48011",
    "addr:housenumber":"9",
    "addr:postcode":"48011",
    "addr:street":"Calle De Achucarro Doctor",
    "iso:country":"ES",
    "sg:address":"Calle de Achucarro Doctor, 9",
    "sg:city":"Bilbao",
    "sg:orig_category":"Supermercados Y Hipermercados",
    "sg:phone":"+34 944 15 08 80",
    "sg:postcode":"48011",
    "sg:province":"Vizcaya",
    "sg:website":"www.ercoreca.com",
    "wof:name":"Supermercado Ercoreca S.a.",
    "wof:placetype":"venue"
},
  "geometry": {"coordinates":[-2.9377861023,43.2627983093],"type":"Point"}
}