{
  "type": "Feature",
  "properties": {
    "iso:country":"ES",
    "sg:address":"Cmno Lonja (la), 19",
    "sg:city":"Albacete",
    "sg:orig_category":"Frutas Y Legumbres Frescas (al Por Mayor)",
    "sg:phone":"+34 967 24 30 34",
    "sg:postcode":"02006",
    "sg:province":"Albacete",
    "wof:name":"Frutas Anvarro Valverde Sl",
    "wof:placetype":"venue"
},
  "geometry": {"coordinates":[-2.044303894,39.0605888367],"type":"Point"}
}