{
  "type": "Feature",
  "properties": {
    "iso:country":"ES",
    "sg:address":"Calle de Infantas (las), S/n",
    "sg:city":"Victoria",
    "sg:orig_category":"Bares, Piano",
    "sg:phone":"+34 957 30 83 40",
    "sg:postcode":"14140",
    "sg:province":"C\u00f3rdoba",
    "wof:name":"Distribuidora Victore\u00f1a De Bebidas Sl",
    "wof:placetype":"venue"
},
  "geometry": {"coordinates":[-4.8560042381,37.6829490662],"type":"Point"}
}