{
  "type": "Feature",
  "properties": {
    "iso:country":"ES",
    "sg:address":"Av Alcudia, S/n",
    "sg:city":"Inca",
    "sg:orig_category":"Reposter\u00cdas",
    "sg:phone":"+34 971 50 19 66",
    "sg:postcode":"07300",
    "sg:province":"Islas Baleares",
    "wof:name":"Panaderia Y Pasteleria La Gloria S. A.",
    "wof:placetype":"venue"
},
  "geometry": {"coordinates":[2.9211149216,39.7258262634],"type":"Point"}
}