{
  "type": "Feature",
  "properties": {
    "iso:country":"ES",
    "sg:address":"Barr Llano (el), S/n",
    "sg:city":"Llano",
    "sg:orig_category":"Centros De Educaci\u00d3n Especial",
    "sg:phone":"+34 942 70 45 54",
    "sg:postcode":"39507",
    "sg:province":"Cantabria",
    "wof:name":"Colegio Publico Monte Corona",
    "wof:placetype":"venue"
},
  "geometry": {"coordinates":[-4.2478971481,43.3380584717],"type":"Point"}
}