{
  "type": "Feature",
  "properties": {
    "addr:full":"Carr Gustavo Mas, 59 Ciutadella Menorca Islas Baleares 07760",
    "addr:housenumber":"59",
    "addr:postcode":"07760",
    "addr:street":"Carr Gustavo Mas",
    "iso:country":"ES",
    "sg:address":"Carr Gustavo Mas, 59",
    "sg:city":"Ciutadella Menorca",
    "sg:orig_category":"Bisuter\u00cda, Joyer\u00cda, Relojer\u00cda (al Por Menor)",
    "sg:phone":"+34 971 38 10 30",
    "sg:postcode":"07760",
    "sg:province":"Islas Baleares",
    "wof:name":"Huguet Y Arguimbau S.c.p.",
    "wof:placetype":"venue"
},
  "geometry": {"coordinates":[3.8327260017,39.9980316162],"type":"Point"}
}