{
  "type": "Feature",
  "properties": {
    "iso:country":"ES",
    "sg:address":"Calle de Progreso, 34",
    "sg:city":"Rua De Valdeorras",
    "sg:orig_category":"Alimentaci\u00d3n General (al Por Mayor)",
    "sg:phone":"+34 988 31 07 05",
    "sg:postcode":"32350",
    "sg:province":"Ourense",
    "wof:name":"Vazquez Ensa Luis",
    "wof:placetype":"venue"
},
  "geometry": {"coordinates":[-7.1205739975,42.392490387],"type":"Point"}
}