{
  "type": "Feature",
  "properties": {
    "addr:full":"Carrer de Sant Sadurni, 52 Mataro Barcelona 08302",
    "addr:housenumber":"52",
    "addr:postcode":"08302",
    "addr:street":"Carrer De Sant Sadurni",
    "iso:country":"ES",
    "sg:address":"Carrer de Sant Sadurni, 52",
    "sg:city":"Mataro",
    "sg:orig_category":"Alimentaci\u00d3n General (al Por Menor)",
    "sg:phone":"+34 937 98 57 03",
    "sg:postcode":"08302",
    "sg:province":"Barcelona",
    "wof:name":"More Serra Maria Del Pilar",
    "wof:placetype":"venue"
},
  "geometry": {"coordinates":[2.4407711029,41.5414237976],"type":"Point"}
}