{
  "type": "Feature",
  "properties": {
    "addr:full":"Calle de Santa Isabel, 8 Santa Pola Alicante 03130",
    "addr:housenumber":"8",
    "addr:postcode":"03130",
    "addr:street":"Calle De Santa Isabel",
    "iso:country":"ES",
    "sg:address":"Calle de Santa Isabel, 8",
    "sg:city":"Santa Pola",
    "sg:orig_category":"Electromec\u00c1nica",
    "sg:phone":"+34 965 41 18 77",
    "sg:postcode":"03130",
    "sg:province":"Alicante",
    "wof:name":"Manzanaro Jover Manuel Jose",
    "wof:placetype":"venue"
},
  "geometry": {"coordinates":[-0.5563111901,38.1925697327],"type":"Point"}
}