{
  "type": "Feature",
  "properties": {
    "iso:country":"ES",
    "sg:address":"Avda Constitucion (de La), 15",
    "sg:city":"Granada",
    "sg:orig_category":"Ropa Para Se\u00d1oras Y Caballeros (al Por Menor)",
    "sg:phone":"+34 958 29 62 92",
    "sg:postcode":"18001",
    "sg:province":"Granada",
    "wof:name":"Albarran Morales Salvador",
    "wof:placetype":"venue"
},
  "geometry": {"coordinates":[-3.603315115,37.1837730408],"type":"Point"}
}