{
  "type": "Feature",
  "properties": {
    "iso:country":"ES",
    "sg:address":"Calle de Alfredo Truan, 11",
    "sg:city":"Gijon",
    "sg:orig_category":"M\u00c9dicos: Estomatolog\u00cda",
    "sg:phone":"+34 985 35 67 68",
    "sg:postcode":"33205",
    "sg:province":"Asturias",
    "wof:name":"Pelaez Rodriguez Luis Antonio",
    "wof:placetype":"venue"
},
  "geometry": {"coordinates":[-5.661567688,43.5371360779],"type":"Point"}
}