{
  "type": "Feature",
  "properties": {
    "addr:full":"Calle de Santos De La Piedra, 2 Llanera Ranes Valencia 46814",
    "addr:housenumber":"2",
    "addr:postcode":"46814",
    "addr:street":"Calle De Santos De La Piedra",
    "iso:country":"ES",
    "sg:address":"Calle de Santos De La Piedra, 2",
    "sg:city":"Llanera Ranes",
    "sg:orig_category":"Confecci\u00d3n De Ropa Interior",
    "sg:phone":"+34 962 25 45 71",
    "sg:postcode":"46814",
    "sg:province":"Valencia",
    "wof:name":"Olmedo Morata Julian",
    "wof:placetype":"venue"
},
  "geometry": {"coordinates":[-0.5729939938,38.9945602417],"type":"Point"}
}