{
  "type": "Feature",
  "properties": {
    "addr:full":"Carr Padro, 20 Madremanya Girona 17462",
    "addr:housenumber":"20",
    "addr:postcode":"17462",
    "addr:street":"Carr Padro",
    "iso:country":"ES",
    "sg:address":"Carr Padro, 20",
    "sg:city":"Madremanya",
    "sg:orig_category":"Centros Empresariales",
    "sg:phone":"+34 972 49 11 40",
    "sg:postcode":"17462",
    "sg:province":"Girona",
    "wof:name":"Lorca Gracia Joaquim",
    "wof:placetype":"venue"
},
  "geometry": {"coordinates":[2.9117949009,42.0443763733],"type":"Point"}
}