{
  "type": "Feature",
  "properties": {
    "iso:country":"ES",
    "sg:address":"Calle de Collados, 2",
    "sg:city":"Madrid",
    "sg:orig_category":"Peluqueros: De Se\u00d1oras",
    "sg:phone":"+34 913 77 56 23",
    "sg:postcode":"28017",
    "sg:province":"Madrid",
    "wof:name":"Garcia Perez Luz Mary",
    "wof:placetype":"venue"
},
  "geometry": {"coordinates":[-3.6497962475,40.4309883118],"type":"Point"}
}