{
  "type": "Feature",
  "properties": {
    "addr:full":"Calle de Tejar (el), 6 Orotava Santa Cruz De Tenerife 38300",
    "addr:housenumber":"6",
    "addr:postcode":"38300",
    "addr:street":"Calle De Tejar El",
    "iso:country":"ES",
    "sg:address":"Calle de Tejar (el), 6",
    "sg:city":"Orotava",
    "sg:orig_category":"Trajes Y Adornos De Boda (confecci\u00d3n, Al Por Menor)",
    "sg:phone":"+34 922 33 44 31",
    "sg:postcode":"38300",
    "sg:province":"Santa Cruz De Tenerife",
    "wof:name":"Perez Hernandez Mario",
    "wof:placetype":"venue"
},
  "geometry": {"coordinates":[-16.5158882141,28.3946342468],"type":"Point"}
}