{
  "type": "Feature",
  "properties": {
    "iso:country":"ES",
    "sg:address":"Calle de Amezti, 4",
    "sg:city":"Getxo",
    "sg:orig_category":"Estancos",
    "sg:phone":"+34 944 03 46 14",
    "sg:postcode":"48990",
    "sg:province":"Vizcaya",
    "wof:name":"Araceli Laiseka O\u00f1abeitia",
    "wof:placetype":"venue"
},
  "geometry": {"coordinates":[-3.0106515884,43.3490447998],"type":"Point"}
}