{
  "type": "Feature",
  "properties": {
    "iso:country":"ES",
    "sg:address":"Carrer de Jaume Balmes (de), 12",
    "sg:city":"Montornes Centre",
    "sg:orig_category":"Zapatos (al Por Menor)",
    "sg:phone":"+34 935 72 27 11",
    "sg:postcode":"08170",
    "sg:province":"Barcelona",
    "wof:name":"Huerta Benito Elena",
    "wof:placetype":"venue"
},
  "geometry": {"coordinates":[2.2635400295,41.541973114],"type":"Point"}
}