{
  "type": "Feature",
  "properties": {
    "addr:full":"Calle de Araucaria, 28 Getafe Madrid 28903",
    "addr:housenumber":"28",
    "addr:postcode":"28903",
    "addr:street":"Calle De Araucaria",
    "iso:country":"ES",
    "sg:address":"Calle de Araucaria, 28",
    "sg:city":"Getafe",
    "sg:orig_category":"Arquitectos",
    "sg:phone":"+34 916 83 57 04",
    "sg:postcode":"28903",
    "sg:province":"Madrid",
    "wof:name":"Fernandez Vara Jose Luis",
    "wof:placetype":"venue"
},
  "geometry": {"coordinates":[-3.7188429832,40.3239707947],"type":"Point"}
}