{
  "type": "Feature",
  "properties": {
    "iso:country":"ES",
    "sg:address":"Avda Juan Carlos I, S/n",
    "sg:city":"Espinardo",
    "sg:orig_category":"Promotores Constructores",
    "sg:phone":"+34 968 43 08 38",
    "sg:postcode":"30008",
    "sg:province":"Murcia",
    "wof:name":"J J Ros Restauracion S.l.",
    "wof:placetype":"venue"
},
  "geometry": {"coordinates":[-1.1320890188,37.9943161011],"type":"Point"}
}