{
  "type": "Feature",
  "properties": {
    "iso:country":"ES",
    "sg:address":"Calle de Hidalgo De Cisneros, 3",
    "sg:city":"Melilla",
    "sg:orig_category":"Bazares, Art\u00cdculos De Limpieza Y De Cocina (al Por Menor)",
    "sg:phone":"+34 952 68 50 57",
    "sg:postcode":"52002",
    "sg:province":"Melilla",
    "wof:name":"Benaisa Mohamed Mustafa",
    "wof:placetype":"venue"
},
  "geometry": {"coordinates":[-2.9445810318,35.296333313],"type":"Point"}
}