{
  "type": "Feature",
  "properties": {
    "iso:country":"ES",
    "sg:address":"Calle de Velazquez, 46",
    "sg:city":"Madrid",
    "sg:orig_category":"Institutos De Belleza",
    "sg:phone":"+34 917 81 48 48",
    "sg:postcode":"28001",
    "sg:province":"Madrid",
    "sg:website":"www.centrosinpelo.com",
    "wof:name":"Sinpelo S.l.",
    "wof:placetype":"venue"
},
  "geometry": {"coordinates":[-3.6838200092,40.4266967773],"type":"Point"}
}