{
  "type": "Feature",
  "properties": {
    "iso:country":"ES",
    "sg:address":"Playa Barro, 6",
    "sg:city":"Valdecaba\u00f1as",
    "sg:orig_category":"Asesores De Gesti\u00d3n Del Patrimonio",
    "sg:phone":"+34 916 32 10 93",
    "sg:postcode":"28669",
    "sg:province":"Madrid",
    "wof:name":"Trifaus S.l.",
    "wof:placetype":"venue"
},
  "geometry": {"coordinates":[-3.8887789249,40.4399642944],"type":"Point"}
}