{
  "type": "Feature",
  "properties": {
    "iso:country":"ES",
    "sg:address":"Trva Almazaras, 2",
    "sg:city":"Ontur",
    "sg:orig_category":"Iglesia Cat\u00d3lica",
    "sg:phone":"+34 967 32 43 24",
    "sg:postcode":"02652",
    "sg:province":"Albacete",
    "wof:name":"Obispado De Albacete",
    "wof:placetype":"venue"
},
  "geometry": {"coordinates":[-1.4989390373,38.6137809753],"type":"Point"}
}