{
  "type": "Feature",
  "properties": {
    "iso:country":"ES",
    "sg:address":"Compa\u00f1ia, 9",
    "sg:city":"Iru\u00f1a",
    "sg:orig_category":"Molduras, Junquillos, Listones Y Molduras Perforadas",
    "sg:phone":"+34 948 21 31 44",
    "sg:postcode":"31001",
    "sg:province":"Navarra",
    "wof:name":"Arregui Moso Maria Sagrario",
    "wof:placetype":"venue"
},
  "geometry": {"coordinates":[-1.6417454481,42.8189964294],"type":"Point"}
}