{
  "type": "Feature",
  "properties": {
    "iso:country":"ES",
    "sg:address":"Rua Peregrina (da), 15",
    "sg:city":"Pontevedra",
    "sg:orig_category":"Bisuter\u00cda, Joyer\u00cda, Relojer\u00cda (al Por Menor)",
    "sg:phone":"+34 986 85 21 97",
    "sg:postcode":"36001",
    "sg:province":"Pontevedra",
    "wof:name":"Joyeria Martinez Vilanova Cb",
    "wof:placetype":"venue"
},
  "geometry": {"coordinates":[-8.6432352066,42.4300003052],"type":"Point"}
}