{
  "type": "Feature",
  "properties": {
    "addr:full":"Avda Monforte De Lemos, S/n Madrid Madrid 28029",
    "addr:housenumber":"s / n",
    "addr:postcode":"28029",
    "addr:street":"Avda Monforte De Lemos",
    "iso:country":"ES",
    "sg:address":"Avda Monforte De Lemos, S/n",
    "sg:city":"Madrid",
    "sg:orig_category":"Lencer\u00cda Femenina, Corseter\u00cda, Trajes De Ba\u00d1o (al Por Menor)",
    "sg:phone":"+34 917 30 48 51",
    "sg:postcode":"28029",
    "sg:province":"Madrid",
    "sg:website":"www.etam.com",
    "wof:name":"Industria Franco Espa\u00f1ola De Moda S. A.",
    "wof:placetype":"venue"
},
  "geometry": {"coordinates":[-3.7155539989,40.4773712158],"type":"Point"}
}