{
  "type": "Feature",
  "properties": {
    "addr:full":"Calle de Comparsa Moros Beduinos, 3 Petrer Alicante 03610",
    "addr:housenumber":"3",
    "addr:postcode":"03610",
    "addr:street":"Calle De Comparsa;Beduinos",
    "iso:country":"ES",
    "sg:address":"Calle de Comparsa Moros Beduinos, 3",
    "sg:city":"Petrer",
    "sg:orig_category":"Cajas De Ahorro",
    "sg:phone":"+34 966 95 61 43",
    "sg:postcode":"03610",
    "sg:province":"Alicante",
    "sg:website":"www.bancaja.es",
    "wof:name":"Caja De Ahorros De Valencia Castellon Y Alicante",
    "wof:placetype":"venue"
},
  "geometry": {"coordinates":[-0.7794340253,38.4807281494],"type":"Point"}
}