{
  "type": "Feature",
  "properties": {
    "addr:full":"Calle de Diego Galvan, 284 Cordoba C\u00f3rdoba 14014",
    "addr:housenumber":"284",
    "addr:postcode":"14014",
    "addr:street":"Calle De Diego Galvan;Co\u0301Rdoba",
    "iso:country":"ES",
    "sg:address":"Calle de Diego Galvan, 284",
    "sg:city":"Cordoba",
    "sg:orig_category":"Electricidad (montaje, Ensamblaje De Componentes)",
    "sg:phone":"+34 957 32 23 04",
    "sg:postcode":"14014",
    "sg:province":"C\u00f3rdoba",
    "wof:name":"J.l.fuentes S.l.",
    "wof:placetype":"venue"
},
  "geometry": {"coordinates":[-4.7142076492,37.9048538208],"type":"Point"}
}