{
  "type": "Feature",
  "properties": {
    "addr:full":"Ptge Santa Catalina Sen, 2 Palma Islas Baleares 07002",
    "addr:housenumber":"2",
    "addr:postcode":"07002",
    "addr:street":"Ptge Santa Catalina Sen",
    "iso:country":"ES",
    "sg:address":"Ptge Santa Catalina Sen, 2",
    "sg:city":"Palma",
    "sg:orig_category":"Asesor\u00cdas Y Estudios Financieros",
    "sg:phone":"+34 971 72 00 05",
    "sg:postcode":"07002",
    "sg:province":"Islas Baleares",
    "wof:name":"Pi\u00d1a Ripoll Antonio",
    "wof:placetype":"venue"
},
  "geometry": {"coordinates":[2.6528949738,39.5747909546],"type":"Point"}
}