{
  "type": "Feature",
  "properties": {
    "addr:full":"Avda Rodriguez De Ledesma, 16 Caceres C\u00e1ceres 10001",
    "addr:housenumber":"16",
    "addr:postcode":"10001",
    "addr:street":"Avda Rodriguez De Ledesma;Ca\u0301Ceres",
    "iso:country":"ES",
    "sg:address":"Avda Rodriguez De Ledesma, 16",
    "sg:city":"Caceres",
    "sg:orig_category":"Asesor\u00cda Sobre Comunicaci\u00d3n De Empresas",
    "sg:phone":"+34 927 23 30 34",
    "sg:postcode":"10001",
    "sg:province":"C\u00e1ceres",
    "wof:name":"Instituto De Desarrollo San Miguel S.a.",
    "wof:placetype":"venue"
},
  "geometry": {"coordinates":[-6.3836688995,39.4704971313],"type":"Point"}
}