{
  "type": "Feature",
  "properties": {
    "addr:full":"Calle de Jose Abascal, 20 Madrid Madrid 28003",
    "addr:housenumber":"20",
    "addr:postcode":"madrid;28003",
    "addr:street":"Calle De Jose Abascal",
    "iso:country":"ES",
    "sg:address":"Calle de Jose Abascal, 20",
    "sg:city":"Madrid",
    "sg:orig_category":"Importaci\u00d3n",
    "sg:phone":"+34 914 42 25 11",
    "sg:postcode":"28003",
    "sg:province":"Madrid",
    "wof:name":"Foodimpex S. A.",
    "wof:placetype":"venue"
},
  "geometry": {"coordinates":[-3.6970510483,40.4381752014],"type":"Point"}
}