{
  "type": "Feature",
  "properties": {
    "iso:country":"ES",
    "sg:address":"Avda Ordo\u00d1o Ii, 30",
    "sg:city":"Le\u00f3n",
    "sg:orig_category":"Abogados",
    "sg:phone":"+34 987 22 00 78",
    "sg:postcode":"24001",
    "sg:province":"Le\u00f3n",
    "wof:name":"Gutierrez Lopez Cipriano",
    "wof:placetype":"venue"
},
  "geometry": {"coordinates":[-5.577067852,42.5966720581],"type":"Point"}
}