{
  "type": "Feature",
  "properties": {
    "addr:full":"Calle de Cervantes, 8 Sotillo Adrada \u00c1vila 05420",
    "addr:housenumber":"8",
    "addr:postcode":"05420",
    "addr:street":"Calle De Cervantes",
    "iso:country":"ES",
    "sg:address":"Calle de Cervantes, 8",
    "sg:city":"Sotillo Adrada",
    "sg:orig_category":"Deportes Y Ocio: Art\u00cdculos Y Ropas (al Por Menor Y Accesorios)",
    "sg:phone":"+34 918 66 10 63",
    "sg:postcode":"05420",
    "sg:province":"\u00c1vila",
    "wof:name":"Garcia Y Plaza Comunidad De Bienes",
    "wof:placetype":"venue"
},
  "geometry": {"coordinates":[-4.6325707436,40.3031921387],"type":"Point"}
}