{
  "type": "Feature",
  "properties": {
    "addr:full":"Calle de Nardiz Tar Jon, 44 Bermeo Vizcaya 48370",
    "addr:housenumber":"44",
    "addr:postcode":"48370",
    "addr:street":"Calle De Nardiz Tar Jon",
    "iso:country":"ES",
    "sg:address":"Calle de Nardiz Tar Jon, 44",
    "sg:city":"Bermeo",
    "sg:orig_category":"Asociaciones, Organismos Culturales Y Socioeducativos",
    "sg:phone":"+34 946 88 05 44",
    "sg:postcode":"48370",
    "sg:province":"Vizcaya",
    "wof:name":"Sociedad Ugerri",
    "wof:placetype":"venue"
},
  "geometry": {"coordinates":[-2.7481176853,43.4026641846],"type":"Point"}
}