{
  "type": "Feature",
  "properties": {
    "addr:full":"Calle de Virgen De La Paloma (de La), 11 S. Martin Vega Madrid 28330",
    "addr:housenumber":"11",
    "addr:postcode":"28330",
    "addr:street":"Calle De Virgen De La Paloma De La;S. Martin Vega",
    "iso:country":"ES",
    "sg:address":"Calle de Virgen De La Paloma (de La), 11",
    "sg:city":"S. Martin Vega",
    "sg:orig_category":"Controles De Edificaci\u00d3n (construcci\u00d3n, Seguridad)",
    "sg:phone":"+34 918 94 77 21",
    "sg:postcode":"28330",
    "sg:province":"Madrid",
    "wof:name":"Construcciones Llanco 56 Sl",
    "wof:placetype":"venue"
},
  "geometry": {"coordinates":[-3.5719230175,40.2122306824],"type":"Point"}
}