{
  "type": "Feature",
  "properties": {
    "iso:country":"ES",
    "sg:address":"Calle de Fray Juan De Los Angeles, 4",
    "sg:city":"Lagartera",
    "sg:orig_category":"Molduras, Junquillos, Listones Y Molduras Perforadas",
    "sg:phone":"+34 925 43 04 86",
    "sg:postcode":"45567",
    "sg:province":"Toledo",
    "wof:name":"Amor Ramos Sonsoles",
    "wof:placetype":"venue"
},
  "geometry": {"coordinates":[-5.2010550499,39.9064254761],"type":"Point"}
}