{
  "type": "Feature",
  "properties": {
    "addr:full":"Carrer de Venus, 9 Barcelona Barcelona 08012",
    "addr:housenumber":"9",
    "addr:postcode":"08012",
    "addr:street":"Carrer De Venus",
    "iso:country":"ES",
    "sg:address":"Carrer de Venus, 9",
    "sg:city":"Barcelona",
    "sg:orig_category":"Asociaciones Humanitarias, De Cooperaci\u00d3n, De Acci\u00d3n Social",
    "sg:phone":"+34 932 07 17 44",
    "sg:postcode":"08012",
    "sg:province":"Barcelona",
    "wof:name":"Eneida Sccl",
    "wof:placetype":"venue"
},
  "geometry": {"coordinates":[2.1624109745,41.3997306824],"type":"Point"}
}