{
  "type": "Feature",
  "properties": {
    "addr:full":"Calle de Catedratico Miguel Traviesas, 1 Oviedo Asturias 33005",
    "addr:housenumber":"1",
    "addr:postcode":"33005",
    "addr:street":"Calle De Catedratico Miguel Traviesas",
    "iso:country":"ES",
    "sg:address":"Calle de Catedratico Miguel Traviesas, 1",
    "sg:city":"Oviedo",
    "sg:orig_category":"M\u00c9dicos: Ginecolog\u00cda Y Obstetricia",
    "sg:phone":"+34 985 25 59 02",
    "sg:postcode":"33005",
    "sg:province":"Asturias",
    "wof:name":"Villaverde Fernandez Secundino",
    "wof:placetype":"venue"
},
  "geometry": {"coordinates":[-5.8556880951,43.3608970642],"type":"Point"}
}