{
  "type": "Feature",
  "properties": {
    "addr:full":"Carrer de Doctor Luis Rivera, 2 Guardamar Segura Alicante 03140",
    "addr:housenumber":"2",
    "addr:postcode":"03140",
    "addr:street":"Carrer De Doctor Luis Rivera",
    "iso:country":"ES",
    "sg:address":"Carrer de Doctor Luis Rivera, 2",
    "sg:city":"Guardamar Segura",
    "sg:orig_category":"Lencer\u00cda Femenina, Corseter\u00cda, Trajes De Ba\u00d1o (al Por Menor)",
    "sg:phone":"+34 965 72 85 04",
    "sg:postcode":"03140",
    "sg:province":"Alicante",
    "wof:name":"Moreno Marin Teresa",
    "wof:placetype":"venue"
},
  "geometry": {"coordinates":[-0.6536880136,38.0897789001],"type":"Point"}
}