{
  "type": "Feature",
  "properties": {
    "iso:country":"ES",
    "sg:address":"Avda San Pedro Apostol, 1",
    "sg:city":"Mengibar",
    "sg:orig_category":"Negocio De Materiales De Construcci\u00d3n",
    "sg:phone":"+34 953 37 12 88",
    "sg:postcode":"23620",
    "sg:province":"Ja\u00e9n",
    "wof:name":"Garcia Lopez Raul",
    "wof:placetype":"venue"
},
  "geometry": {"coordinates":[-3.8033540249,37.970615387],"type":"Point"}
}