{
  "type": "Feature",
  "properties": {
    "iso:country":"ES",
    "sg:address":"Carrer de Calassan\u00c7 Duran, 6",
    "sg:city":"Sabadell",
    "sg:orig_category":"Molduras, Junquillos, Listones Y Molduras Perforadas",
    "sg:phone":"+34 937 12 23 94",
    "sg:postcode":"08203",
    "sg:province":"Barcelona",
    "wof:name":"Astals Pe\u00f1alver Joaquin",
    "wof:placetype":"venue"
},
  "geometry": {"coordinates":[2.112793684,41.5393867493],"type":"Point"}
}