{
  "type": "Feature",
  "properties": {
    "addr:full":"Pl. Tornall, 1 Rialp Lleida 25594",
    "addr:housenumber":"1",
    "addr:postcode":"25594",
    "addr:street":"Pl. Tornall",
    "iso:country":"ES",
    "sg:address":"Pl. Tornall, 1",
    "sg:city":"Rialp",
    "sg:orig_category":"Administraciones Regionales, Departamentales Y Locales",
    "sg:phone":"+34 973 62 03 65",
    "sg:postcode":"25594",
    "sg:province":"Lleida",
    "wof:name":"Ayuntamiento De Rialp",
    "wof:placetype":"venue"
},
  "geometry": {"coordinates":[1.1356710196,42.4440422058],"type":"Point"}
}