{
  "type": "Feature",
  "properties": {
    "iso:country":"ES",
    "sg:address":"Calle de Pe\u00d1uelas, 5",
    "sg:city":"Marbella",
    "sg:orig_category":"Zapatos (al Por Menor)",
    "sg:phone":"+34 952 77 89 97",
    "sg:postcode":"29600",
    "sg:province":"M\u00e1laga",
    "wof:name":"Gutierrez Naranjo Jose",
    "wof:placetype":"venue"
},
  "geometry": {"coordinates":[-4.8817420006,36.5108451843],"type":"Point"}
}