{
  "type": "Feature",
  "properties": {
    "addr:full":"Avda Cayetano Del Toro, 34 Cadiz C\u00e1diz 11010",
    "addr:housenumber":"34",
    "addr:postcode":"11010",
    "addr:street":"Avda Cayetano Del Toro",
    "iso:country":"ES",
    "sg:address":"Avda Cayetano Del Toro, 34",
    "sg:city":"Cadiz",
    "sg:orig_category":"Institutos De Belleza",
    "sg:phone":"+34 956 28 66 60",
    "sg:postcode":"11010",
    "sg:province":"C\u00e1diz",
    "wof:name":"Jimenez Martinez Maria Teresa",
    "wof:placetype":"venue"
},
  "geometry": {"coordinates":[-6.2756857872,36.5038871765],"type":"Point"}
}