{
  "type": "Feature",
  "properties": {
    "iso:country":"ES",
    "sg:address":"Carr Pintor Gimeno, 3",
    "sg:city":"Torroella Montgri",
    "sg:orig_category":"Ropa Para Ni\u00d1os (al Por Menor)",
    "sg:phone":"+34 972 75 74 98",
    "sg:postcode":"17257",
    "sg:province":"Girona",
    "wof:name":"Casanas Colomer Asuncion",
    "wof:placetype":"venue"
},
  "geometry": {"coordinates":[3.1034500599,42.0303268433],"type":"Point"}
}