{
  "type": "Feature",
  "properties": {
    "addr:full":"Calle de Alozaina, 5 Alora M\u00e1laga 29500",
    "addr:housenumber":"5",
    "addr:postcode":"29500",
    "addr:street":"Calle De Alozaina;Ma\u0301Laga",
    "iso:country":"ES",
    "sg:address":"Calle de Alozaina, 5",
    "sg:city":"Alora",
    "sg:orig_category":"Asesor\u00cda Fiscal Y Jur\u00cddica",
    "sg:phone":"+34 952 49 61 06",
    "sg:postcode":"29500",
    "sg:province":"M\u00e1laga",
    "wof:name":"Ofiscal S.l.",
    "wof:placetype":"venue"
},
  "geometry": {"coordinates":[-4.7042922974,36.8269996643],"type":"Point"}
}