{
  "type": "Feature",
  "properties": {
    "iso:country":"ES",
    "sg:address":"Calle de Amsterdam, 4",
    "sg:city":"Zaragoza",
    "sg:orig_category":"Automatizaci\u00d3n De Procesos Industriales Y De Edificaci\u00d3n (estudios, Instalaci\u00d3n)",
    "sg:phone":"+34 976 40 44 94",
    "sg:postcode":"50003",
    "sg:province":"Zaragoza",
    "wof:name":"Sistemas Y Aplicaciones Telematicas S.l.",
    "wof:placetype":"venue"
},
  "geometry": {"coordinates":[-0.9049410224,41.6628570557],"type":"Point"}
}