{
  "type": "Feature",
  "properties": {
    "addr:full":"Pol Ind S. Nicolas, S/n Alcala Guadaira Sevilla 41500",
    "addr:postcode":"41500",
    "addr:street":"Nicolas S / N",
    "iso:country":"ES",
    "sg:address":"Pol Ind S. Nicolas, S/n",
    "sg:city":"Alcala Guadaira",
    "sg:orig_category":"Distribuci\u00d3n De Petr\u00d3leo Y Derivados",
    "sg:phone":"+34 955 63 07 05",
    "sg:postcode":"41500",
    "sg:province":"Sevilla",
    "wof:name":"Servicios Beticos De Carburante S.l.",
    "wof:placetype":"venue"
},
  "geometry": {"coordinates":[-5.8398590088,37.3383140564],"type":"Point"}
}