{
  "type": "Feature",
  "properties": {
    "iso:country":"ES",
    "sg:address":"Euskadi Etorbidea, S/n",
    "sg:city":"Pasai S. Pedro",
    "sg:orig_category":"Carnicer\u00cdas, Carnicer\u00cdas",
    "sg:phone":"+34 943 39 99 32",
    "sg:postcode":"20110",
    "sg:province":"Guip\u00f9zcoa",
    "wof:name":"Alegre Izquierdo Javier",
    "wof:placetype":"venue"
},
  "geometry": {"coordinates":[-1.9335404634,43.3229484558],"type":"Point"}
}