{
  "type": "Feature",
  "properties": {
    "iso:country":"ES",
    "sg:address":"Carrer de Independencia, 261",
    "sg:city":"Barcelona",
    "sg:orig_category":"Ropa Para Ni\u00d1os (al Por Menor)",
    "sg:phone":"+34 932 65 24 62",
    "sg:postcode":"08026",
    "sg:province":"Barcelona",
    "wof:name":"Baby Now S.l.",
    "wof:placetype":"venue"
},
  "geometry": {"coordinates":[2.1847169399,41.4066085815],"type":"Point"}
}