{
  "type": "Feature",
  "properties": {
    "iso:country":"ES",
    "sg:address":"Calle de Atlanta, 4",
    "sg:city":"Granada",
    "sg:orig_category":"Semiller\u00cdas",
    "sg:phone":"+34 902 20 05 02",
    "sg:postcode":"18016",
    "sg:province":"Granada",
    "sg:website":"www.paisajesdelsur.com",
    "wof:name":"Paisajes Del Sur S.l.",
    "wof:placetype":"venue"
},
  "geometry": {"coordinates":[-3.6175713539,37.1979942322],"type":"Point"}
}