{
  "type": "Feature",
  "properties": {
    "iso:country":"ES",
    "sg:address":"Calle de Nardiz Tar Jon, 47",
    "sg:city":"Bermeo",
    "sg:orig_category":"Plomeros",
    "sg:phone":"+34 946 88 04 96",
    "sg:postcode":"48370",
    "sg:province":"Vizcaya",
    "wof:name":"Iturgintza Garay",
    "wof:placetype":"venue"
},
  "geometry": {"coordinates":[-2.7247259617,43.4201278687],"type":"Point"}
}