{
  "type": "Feature",
  "properties": {
    "addr:full":"Plaz Pe\u00d1a Gudina, 3 Madrid Madrid 28018",
    "addr:housenumber":"3",
    "addr:postcode":"28018",
    "addr:street":"Plaz;Gudina",
    "iso:country":"ES",
    "sg:address":"Plaz Pe\u00d1a Gudina, 3",
    "sg:city":"Madrid",
    "sg:orig_category":"Distribuci\u00d3n De Petr\u00d3leo Y Derivados",
    "sg:phone":"+34 915 07 80 97",
    "sg:postcode":"28018",
    "sg:province":"Madrid",
    "wof:name":"Husco S.l.",
    "wof:placetype":"venue"
},
  "geometry": {"coordinates":[-3.6547195911,40.3813247681],"type":"Point"}
}