{
  "type": "Feature",
  "properties": {
    "iso:country":"ES",
    "sg:address":"Abejeras, 4",
    "sg:city":"Iru\u00f1a",
    "sg:orig_category":"Carpinteros",
    "sg:phone":"+34 948 17 73 67",
    "sg:postcode":"31007",
    "sg:province":"Navarra",
    "wof:name":"Distribucion E Instalaciones Leire S.l.",
    "wof:placetype":"venue"
},
  "geometry": {"coordinates":[-1.6490199566,42.8035125732],"type":"Point"}
}