{
  "type": "Feature",
  "properties": {
    "addr:full":"Calle de Feria, 22 Alora M\u00e1laga 29500",
    "addr:housenumber":"22",
    "addr:postcode":"29500",
    "addr:street":"Calle De Feria",
    "iso:country":"ES",
    "sg:address":"Calle de Feria, 22",
    "sg:city":"Alora",
    "sg:orig_category":"Transportes Por V\u00cdas Navegables",
    "sg:phone":"+34 952 49 86 72",
    "sg:postcode":"29500",
    "sg:province":"M\u00e1laga",
    "wof:name":"Gil Melero Antonio Jesus",
    "wof:placetype":"venue"
},
  "geometry": {"coordinates":[-4.7033829689,36.8308792114],"type":"Point"}
}