{
  "type": "Feature",
  "properties": {
    "addr:full":"Calle de Matarra\u00d1a, 1 Malaga M\u00e1laga 29011",
    "addr:housenumber":"1",
    "addr:postcode":"29011",
    "addr:street":"Calle De Matarran\u0303A;Ma\u0301Laga",
    "iso:country":"ES",
    "sg:address":"Calle de Matarra\u00d1a, 1",
    "sg:city":"Malaga",
    "sg:orig_category":"Ense\u00d1anza: Comercio, Gesti\u00d3n, Inform\u00c1tica",
    "sg:phone":"+34 952 30 52 86",
    "sg:postcode":"29011",
    "sg:province":"M\u00e1laga",
    "wof:name":"Llinares Lloret Angeles",
    "wof:placetype":"venue"
},
  "geometry": {"coordinates":[-4.437526226,36.7293930054],"type":"Point"}
}