{
  "type": "Feature",
  "properties": {
    "addr:full":"Carrer de Doctor Pasteur, 6 Vilafranca Penedes Barcelona 08720",
    "addr:housenumber":"6",
    "addr:postcode":"08720",
    "addr:street":"Carrer De Doctor Pasteur;Penedes Barcelona",
    "iso:country":"ES",
    "sg:address":"Carrer de Doctor Pasteur, 6",
    "sg:city":"Vilafranca Penedes",
    "sg:classifiers":[
        {
            "category":"Home & Garden",
            "subcategory":"Household Appliances",
            "type":"Retail Goods"
        }
    ],
    "sg:phone":"+34 938 90 30 66",
    "sg:postcode":"08720",
    "sg:province":"Barcelona",
    "sg:tags":[
        "bodega",
        "de",
        "vino",
        "acondicionamiento"
    ],
    "wof:name":"Bodegas Pinord S.a.",
    "wof:placetype":"venue"
},
  "geometry": {"coordinates":[1.703068018,41.3430709839],"type":"Point"}
}