{
  "type": "Feature",
  "properties": {
    "addr:full":"Calle de Armando Cotarelo, 8 Vegadeo Asturias 33770",
    "addr:housenumber":"8",
    "addr:postcode":"33770",
    "addr:street":"Calle De Armando Cotarelo",
    "iso:country":"ES",
    "sg:address":"Calle de Armando Cotarelo, 8",
    "sg:city":"Vegadeo",
    "sg:orig_category":"Pescader\u00cdas (al Por Menor)",
    "sg:phone":"+34 985 63 46 97",
    "sg:postcode":"33770",
    "sg:province":"Asturias",
    "wof:name":"Rodolfo Fernandez Paraje Y Arturo Fernandez Garcia C.b.",
    "wof:placetype":"venue"
},
  "geometry": {"coordinates":[-7.0496821404,43.4639282227],"type":"Point"}
}