{
  "type": "Feature",
  "properties": {
    "addr:full":"Calle de Murillo, 2 Sevilla Sevilla 41001",
    "addr:housenumber":"2",
    "addr:postcode":"41001",
    "addr:street":"Calle De Murillo",
    "iso:country":"ES",
    "sg:address":"Calle de Murillo, 2",
    "sg:city":"Sevilla",
    "sg:orig_category":"Electricidad: Instaladores",
    "sg:phone":"+34 954 56 26 26",
    "sg:postcode":"41001",
    "sg:province":"Sevilla",
    "wof:name":"Guerrero Cid Salvador",
    "wof:placetype":"venue"
},
  "geometry": {"coordinates":[-5.9975190163,37.3908996582],"type":"Point"}
}