{
  "type": "Feature",
  "properties": {
    "addr:full":"Calle de Pedralba, 90 Benaguasil Valencia 46180",
    "addr:housenumber":"90",
    "addr:postcode":"46180",
    "addr:street":"Calle De Pedralba",
    "iso:country":"ES",
    "sg:address":"Calle de Pedralba, 90",
    "sg:city":"Benaguasil",
    "sg:orig_category":"Reposter\u00cdas",
    "sg:phone":"+34 962 73 08 59",
    "sg:postcode":"46180",
    "sg:province":"Valencia",
    "wof:name":"Sanchis Asensi Francisco",
    "wof:placetype":"venue"
},
  "geometry": {"coordinates":[-0.5875390172,39.5956382751],"type":"Point"}
}