{
  "type": "Feature",
  "properties": {
    "addr:full":"Calle de Padre Pedro Juan De Molina, 68 Onil Alicante 03430",
    "addr:housenumber":"68",
    "addr:postcode":"03430",
    "addr:street":"Calle De Padre Pedro Juan De Molina",
    "iso:country":"ES",
    "sg:address":"Calle de Padre Pedro Juan De Molina, 68",
    "sg:city":"Onil",
    "sg:orig_category":"Promotores Constructores",
    "sg:phone":"+34 966 55 77 05",
    "sg:postcode":"03430",
    "sg:province":"Alicante",
    "sg:website":"www.rabel-cgi.com",
    "wof:name":"Rabel Construcciones Y Gestion Inmobiliaria S.l.",
    "wof:placetype":"venue"
},
  "geometry": {"coordinates":[-0.6688737273,38.6286621094],"type":"Point"}
}