{
  "type": "Feature",
  "properties": {
    "addr:full":"Carretera Segovia-ar\u00e9valo, 64 Sta M. Real Nieva Segovia 40440",
    "addr:housenumber":"64",
    "addr:postcode":"40440",
    "addr:street":"Carretera Segovia-Are\u0301Valo;M.",
    "iso:country":"ES",
    "sg:address":"Carretera Segovia-ar\u00e9valo, 64",
    "sg:city":"Sta M. Real Nieva",
    "sg:orig_category":"Plomeros",
    "sg:phone":"+34 921 59 40 60",
    "sg:postcode":"40440",
    "sg:province":"Segovia",
    "wof:name":"Pi\u00f1ataro Martin Pablo",
    "wof:placetype":"venue"
},
  "geometry": {"coordinates":[-4.4072508812,41.0704154968],"type":"Point"}
}