{
  "type": "Feature",
  "properties": {
    "addr:full":"Calle de Mayor, 48 Najera La Rioja 26300",
    "addr:housenumber":"48",
    "addr:postcode":"26300",
    "addr:street":"Calle De Mayor;Rioja",
    "iso:country":"ES",
    "sg:address":"Calle de Mayor, 48",
    "sg:city":"Najera",
    "sg:orig_category":"Confecci\u00d3n (fabricaci\u00d3n, Al Por Mayor)",
    "sg:phone":"+34 941 36 09 79",
    "sg:postcode":"26300",
    "sg:province":"La Rioja",
    "wof:name":"Alonso Ochoa Maria De Las Mercedes",
    "wof:placetype":"venue"
},
  "geometry": {"coordinates":[-2.7337408066,42.4173278809],"type":"Point"}
}