{
  "type": "Feature",
  "properties": {
    "addr:full":"Calle de Victoria, 47 Ventas Con Pe\u00e7a Aguilera Toledo 45127",
    "addr:housenumber":"47",
    "addr:postcode":"45127",
    "addr:street":"Calle De Victoria",
    "iso:country":"ES",
    "sg:address":"Calle de Victoria, 47",
    "sg:city":"Ventas Con Pe\u00e7a Aguilera",
    "sg:orig_category":"Cueros Y Pieles (al Por Mayor)",
    "sg:phone":"+34 925 41 81 32",
    "sg:postcode":"45127",
    "sg:province":"Toledo",
    "wof:name":"Romero Medina Francisco",
    "wof:placetype":"venue"
},
  "geometry": {"coordinates":[-4.2310872078,39.6094474792],"type":"Point"}
}