{
  "type": "Feature",
  "properties": {
    "iso:country":"ES",
    "sg:address":"Poli Industrial Autopista Sur, Km. 0064,1",
    "sg:city":"Castellon De La Plana",
    "sg:orig_category":"Suministros Para Carrocer\u00cdas",
    "sg:phone":"+34 964 21 22 73",
    "sg:postcode":"12006",
    "sg:province":"Castell\u00f3n",
    "sg:website":"www.carrocerias.net",
    "wof:name":"Carrocerias Beser Y Altava S. L.",
    "wof:placetype":"venue"
},
  "geometry": {"coordinates":[-0.1404139996,40.0213813782],"type":"Point"}
}