{
  "type": "Feature",
  "properties": {
    "addr:full":"Calle de Jose Sarabia, 40 Sevilla Sevilla 41006",
    "addr:housenumber":"40",
    "addr:postcode":"41006",
    "addr:street":"Calle De Jose Sarabia",
    "iso:country":"ES",
    "sg:address":"Calle de Jose Sarabia, 40",
    "sg:city":"Sevilla",
    "sg:orig_category":"Alimentaci\u00d3n General (al Por Menor)",
    "sg:phone":"+34 954 64 06 49",
    "sg:postcode":"41006",
    "sg:province":"Sevilla",
    "wof:name":"Santos Zambrano Jeronimo",
    "wof:placetype":"venue"
},
  "geometry": {"coordinates":[-5.9527797699,37.3711204529],"type":"Point"}
}