{
  "type": "Feature",
  "properties": {
    "iso:country":"ES",
    "sg:address":"Calle de Moises De Leon, 14",
    "sg:city":"Le\u00f3n",
    "sg:orig_category":"Ingeniero",
    "sg:phone":"+34 987 21 64 61",
    "sg:postcode":"24006",
    "sg:province":"Le\u00f3n",
    "wof:name":"Gonzalez Bernardo Francisco",
    "wof:placetype":"venue"
},
  "geometry": {"coordinates":[-5.5562601089,42.592754364],"type":"Point"}
}