{
  "type": "Feature",
  "properties": {
    "addr:full":"Carr Creueta, 2 Igualada Barcelona 08700",
    "addr:housenumber":"2",
    "addr:postcode":"08700",
    "addr:street":"Carr Creueta",
    "iso:country":"ES",
    "sg:address":"Carr Creueta, 2",
    "sg:city":"Igualada",
    "sg:orig_category":"Empresas De Carpinter\u00cda De Madera",
    "sg:phone":"+34 938 03 72 04",
    "sg:postcode":"08700",
    "sg:province":"Barcelona",
    "wof:name":"Galan Reguero Tomas",
    "wof:placetype":"venue"
},
  "geometry": {"coordinates":[1.6134873629,41.5787239075],"type":"Point"}
}