{
  "type": "Feature",
  "properties": {
    "addr:full":"Calle de Carretera, 171 Pradejon La Rioja 26510",
    "addr:postcode":"26510",
    "addr:street":"Calle De Carretera 171 Pradejon;Rioja",
    "iso:country":"ES",
    "sg:address":"Calle de Carretera, 171",
    "sg:city":"Pradejon",
    "sg:orig_category":"Productores Recolectores, Venta Directa De Vinos",
    "sg:phone":"+34 941 15 00 46",
    "sg:postcode":"26510",
    "sg:province":"La Rioja",
    "wof:name":"Bodega Cooperativa San Isidro Labrador",
    "wof:placetype":"venue"
},
  "geometry": {"coordinates":[-2.0711989403,42.3343009949],"type":"Point"}
}