{
  "type": "Feature",
  "properties": {
    "iso:country":"ES",
    "sg:address":"Rua Rosa (da), S/n",
    "sg:city":"Santiago De Compostela",
    "sg:orig_category":"Aparcamientos (infraestructuras, Accesorios)",
    "sg:phone":"+34 981 95 40 17",
    "sg:postcode":"15701",
    "sg:province":"La Coru\u00f1a",
    "sg:website":"www.continentalparking.com",
    "wof:name":"Continental Parking S.l.",
    "wof:placetype":"venue"
},
  "geometry": {"coordinates":[-8.5463724136,42.8732566833],"type":"Point"}
}