{
  "type": "Feature",
  "properties": {
    "iso:country":"ES",
    "sg:address":"Escultor G. Galmes, S/n",
    "sg:city":"Petra",
    "sg:orig_category":"Centros De Educaci\u00d3n Especial",
    "sg:phone":"+34 971 56 12 69",
    "sg:postcode":"07520",
    "sg:province":"Islas Baleares",
    "wof:name":"Colegio Nacional Mixto",
    "wof:placetype":"venue"
},
  "geometry": {"coordinates":[3.1161499023,39.6146087646],"type":"Point"}
}