{
  "type": "Feature",
  "properties": {
    "iso:country":"ES",
    "sg:address":"Foruen Kalea, 9",
    "sg:city":"Zarautz",
    "sg:orig_category":"Plomeros",
    "sg:phone":"+34 943 13 13 36",
    "sg:postcode":"20800",
    "sg:province":"Guip\u00f9zcoa",
    "wof:name":"Pe\u00f1agaricano Gurrutxaga Jose Luis",
    "wof:placetype":"venue"
},
  "geometry": {"coordinates":[-2.1757090092,43.2841796875],"type":"Point"}
}