{
  "type": "Feature",
  "properties": {
    "iso:country":"ES",
    "sg:address":"Hernandez Velasco, 1",
    "sg:city":"Motril",
    "sg:orig_category":"Cajas De Ahorro",
    "sg:phone":"+34 958 83 35 99",
    "sg:postcode":"18600",
    "sg:province":"Granada",
    "wof:name":"Monte De Piedad Y Caja De Ahorros De Huelva Y Sevilla",
    "wof:placetype":"venue"
},
  "geometry": {"coordinates":[-3.5198400021,36.741519928],"type":"Point"}
}