{
  "type": "Feature",
  "properties": {
    "iso:country":"ES",
    "sg:address":"Calle de Real, 2",
    "sg:city":"Estacion",
    "sg:orig_category":"Confecci\u00d3n (fabricaci\u00d3n, Al Por Mayor)",
    "sg:phone":"+34 918 50 10 81",
    "sg:postcode":"28400",
    "sg:province":"Madrid",
    "wof:name":"Menchu Villalba S.l.",
    "wof:placetype":"venue"
},
  "geometry": {"coordinates":[-4.3321399689,40.6035919189],"type":"Point"}
}