{
  "type": "Feature",
  "properties": {
    "iso:country":"ES",
    "sg:address":"Calle de Ciudad De Carlet, S/n",
    "sg:city":"Sevilla",
    "sg:classifiers":[
        {
            "category":"Communications",
            "subcategory":"Film & Video Production",
            "type":"Services"
        }
    ],
    "sg:phone":"+34 954 07 59 86",
    "sg:postcode":"41019",
    "sg:province":"Sevilla",
    "sg:tags":[
        "de",
        "material",
        "fotocomposici\u00d3n"
    ],
    "wof:name":"Canovas Y Baena Hermanos S.l.",
    "wof:placetype":"venue"
},
  "geometry": {"coordinates":[-5.927072525,37.4114761353],"type":"Point"}
}