{
  "type": "Feature",
  "properties": {
    "iso:country":"ES",
    "sg:address":"Carrer de Carrer de Europa, S/n",
    "sg:city":"Puerto Rico",
    "sg:orig_category":"Bazares, Art\u00cdculos De Limpieza Y De Cocina (al Por Menor)",
    "sg:phone":"+34 928 56 15 34",
    "sg:postcode":"35130",
    "sg:province":"Las Palmas",
    "wof:name":"Perez Calero Monica",
    "wof:placetype":"venue"
},
  "geometry": {"coordinates":[-13.9036235809,28.6303958893],"type":"Point"}
}