{
  "type": "Feature",
  "properties": {
    "addr:full":"Carrer de Sant Josep, 39 Manresa Barcelona 08242",
    "addr:housenumber":"39",
    "addr:postcode":"08242",
    "addr:street":"Carrer De Sant Josep",
    "iso:country":"ES",
    "sg:address":"Carrer de Sant Josep, 39",
    "sg:city":"Manresa",
    "sg:orig_category":"Cajas De Ahorro",
    "sg:phone":"+34 938 74 13 77",
    "sg:postcode":"08242",
    "sg:province":"Barcelona",
    "wof:name":"Caixa D'estalvis I Pensions De Barcelona",
    "wof:placetype":"venue"
},
  "geometry": {"coordinates":[1.8251310587,41.7337341309],"type":"Point"}
}