{
  "type": "Feature",
  "properties": {
    "addr:full":"Calle de Albentosa, 2 Madrid Madrid 28019",
    "addr:housenumber":"2",
    "addr:postcode":"28019",
    "addr:street":"Calle De Albentosa",
    "iso:country":"ES",
    "sg:address":"Calle de Albentosa, 2",
    "sg:city":"Madrid",
    "sg:orig_category":"Tapicer\u00cdas",
    "sg:phone":"+34 914 66 78 21",
    "sg:postcode":"28019",
    "sg:province":"Madrid",
    "wof:name":"De La Calle Garcia Jose Antonio",
    "wof:placetype":"venue"
},
  "geometry": {"coordinates":[-3.7399866581,40.3935470581],"type":"Point"}
}