{
  "type": "Feature",
  "properties": {
    "addr:full":"Calle de Federico Garcia Lorca, 14 Albacete Albacete 02001",
    "addr:housenumber":"14",
    "addr:postcode":"02001",
    "addr:street":"Calle De Federico Garcia Lorca",
    "iso:country":"ES",
    "sg:address":"Calle de Federico Garcia Lorca, 14",
    "sg:city":"Albacete",
    "sg:orig_category":"Fabricaci\u00d3n De Bibliotecas Y Estanter\u00cdas",
    "sg:phone":"+34 967 52 20 57",
    "sg:postcode":"02001",
    "sg:province":"Albacete",
    "wof:name":"Mecalux Levante S.a.",
    "wof:placetype":"venue"
},
  "geometry": {"coordinates":[-1.8469359875,38.9970436096],"type":"Point"}
}