{
  "type": "Feature",
  "properties": {
    "addr:full":"Calle de San Jose, 2 Coru\u00d1a A Coru\u00f1a 15008",
    "addr:housenumber":"2",
    "addr:postcode":"15008",
    "addr:street":"Calle De San Jose;Corun\u0303A",
    "iso:country":"ES",
    "sg:address":"Calle de San Jose, 2",
    "sg:city":"Coru\u00d1a",
    "sg:orig_category":"Planchado",
    "sg:phone":"+34 981 26 54 29",
    "sg:postcode":"15008",
    "sg:province":"A Coru\u00f1a",
    "wof:name":"Textisa Coru\u00f1esa S.l",
    "wof:placetype":"venue"
},
  "geometry": {"coordinates":[-8.4512443542,43.3434753418],"type":"Point"}
}