{
  "type": "Feature",
  "properties": {
    "addr:full":"Calle de Calvo Sotelo, 25 Marin Pontevedra 36900",
    "addr:housenumber":"25",
    "addr:postcode":"36900",
    "addr:street":"Calle De Calvo Sotelo",
    "iso:country":"ES",
    "sg:address":"Calle de Calvo Sotelo, 25",
    "sg:city":"Marin",
    "sg:orig_category":"Abogados",
    "sg:phone":"+34 986 89 20 91",
    "sg:postcode":"36900",
    "sg:province":"Pontevedra",
    "wof:name":"Sanchez Miguez Carlos",
    "wof:placetype":"venue"
},
  "geometry": {"coordinates":[-8.6994533539,42.3915939331],"type":"Point"}
}