{
  "type": "Feature",
  "properties": {
    "addr:full":"Calle de Secundino Esnaola, 7 Donostia-san Sebastian Guip\u00f9zcoa 20001",
    "addr:housenumber":"7",
    "addr:postcode":"20001",
    "addr:street":"Calle De Secundino Esnaola",
    "iso:country":"ES",
    "sg:address":"Calle de Secundino Esnaola, 7",
    "sg:city":"Donostia-san Sebastian",
    "sg:orig_category":"Carnicer\u00cdas, Carnicer\u00cdas",
    "sg:phone":"+34 943 27 79 94",
    "sg:postcode":"20001",
    "sg:province":"Guip\u00f9zcoa",
    "wof:name":"Aldareguia Go\u00f1i Luis",
    "wof:placetype":"venue"
},
  "geometry": {"coordinates":[-1.9747885466,43.3225021362],"type":"Point"}
}