{
  "type": "Feature",
  "properties": {
    "iso:country":"ES",
    "sg:address":"Calle de Salsipuedes, 140",
    "sg:city":"Guare\u00f1a",
    "sg:orig_category":"Promotores Constructores",
    "sg:phone":"+34 924 35 13 95",
    "sg:postcode":"06470",
    "sg:province":"Badajoz",
    "wof:name":"Construcciones Guare\u00f1a Sociedad Cooperativa Limitada",
    "wof:placetype":"venue"
},
  "geometry": {"coordinates":[-6.0951871872,38.8590545654],"type":"Point"}
}