{
  "type": "Feature",
  "properties": {
    "addr:full":"Plaz Salamanca, S/n Villanueva Serena Badajoz 06700",
    "addr:postcode":"06700",
    "addr:street":"Salamanca S / N Villanueva Serena",
    "iso:country":"ES",
    "sg:address":"Plaz Salamanca, S/n",
    "sg:city":"Villanueva Serena",
    "sg:orig_category":"Ense\u00d1anza, Formaci\u00d3n Profesional: Aprendizaje",
    "sg:phone":"+34 924 84 40 11",
    "sg:postcode":"06700",
    "sg:province":"Badajoz",
    "wof:name":"Servicio Extreme\u00d1o De Salud",
    "wof:placetype":"venue"
},
  "geometry": {"coordinates":[-5.7927408218,38.9731750488],"type":"Point"}
}