{
  "type": "Feature",
  "properties": {
    "iso:country":"ES",
    "sg:address":"Calle de Muelle, 17",
    "sg:city":"Santa Pola",
    "sg:orig_category":"Zapatos (al Por Menor)",
    "sg:phone":"+34 965 41 68 84",
    "sg:postcode":"03130",
    "sg:province":"Alicante",
    "wof:name":"Calzados La Fuente",
    "wof:placetype":"venue"
},
  "geometry": {"coordinates":[-0.5559189916,38.1912117004],"type":"Point"}
}