{
  "type": "Feature",
  "properties": {
    "addr:full":"Trueno, 66 Leganes Madrid 28918",
    "addr:housenumber":"66",
    "addr:postcode":"28918",
    "addr:street":"Trueno",
    "iso:country":"ES",
    "sg:address":"Trueno, 66",
    "sg:city":"Leganes",
    "sg:orig_category":"Colchones (fabricaci\u00d3n, Al Por Mayor, Al Por Menor)",
    "sg:phone":"+34 914 88 09 90",
    "sg:postcode":"28918",
    "sg:province":"Madrid",
    "wof:name":"Power Drems S.l.",
    "wof:placetype":"venue"
},
  "geometry": {"coordinates":[-3.7949619293,40.3488311768],"type":"Point"}
}