{
  "type": "Feature",
  "properties": {
    "iso:country":"ES",
    "sg:address":"Carrer de Industria, 16",
    "sg:city":"Roca Valles",
    "sg:orig_category":"Tubos Met\u00c1licos",
    "sg:phone":"+34 938 42 47 07",
    "sg:postcode":"08430",
    "sg:province":"Barcelona",
    "wof:name":"Tubos De Precision Delmas S.l.",
    "wof:placetype":"venue"
},
  "geometry": {"coordinates":[2.3228011131,41.5866165161],"type":"Point"}
}