{
  "type": "Feature",
  "properties": {
    "iso:country":"ES",
    "sg:address":"Carr Hostal De La Bordeta, 8",
    "sg:city":"Lleida",
    "sg:orig_category":"Agencias De Viajes",
    "sg:phone":"+34 973 21 12 03",
    "sg:postcode":"25001",
    "sg:province":"Lleida",
    "wof:name":"Viatges L'eixida Tours S.l.",
    "wof:placetype":"venue"
},
  "geometry": {"coordinates":[0.642252028,41.6044006348],"type":"Point"}
}