{
  "type": "Feature",
  "properties": {
    "iso:country":"ES",
    "sg:address":"Calle de Fortunato Arias, 93",
    "sg:city":"Palmar  O Lugar De Don Juan",
    "sg:orig_category":"Delegados, Agentes De Tr\u00c1nsito, Auxiliares De Transporte Internacional",
    "sg:phone":"+34 968 88 41 73",
    "sg:postcode":"30120",
    "sg:province":"Murcia",
    "wof:name":"Garcia Lujan Antonio",
    "wof:placetype":"venue"
},
  "geometry": {"coordinates":[-1.1302490234,37.9829597473],"type":"Point"}
}