{
  "type": "Feature",
  "properties": {
    "iso:country":"ES",
    "sg:address":"Avda Alfonso Xiii, 156",
    "sg:city":"Madrid",
    "sg:orig_category":"Promotores Constructores",
    "sg:phone":"+34 913 45 47 23",
    "sg:postcode":"28016",
    "sg:province":"Madrid",
    "wof:name":"Crespo Marcos Manuel",
    "wof:placetype":"venue"
},
  "geometry": {"coordinates":[-3.6710979939,40.4603042603],"type":"Point"}
}