{
  "type": "Feature",
  "properties": {
    "iso:country":"ES",
    "sg:address":"Calle de Palma, 1",
    "sg:city":"Cangas",
    "sg:orig_category":"Art\u00cdculos De Decoraci\u00d3n",
    "sg:phone":"+34 986 30 08 38",
    "sg:postcode":"36940",
    "sg:province":"Pontevedra",
    "wof:name":"Cabral Lemos Joaquin Fructuoso",
    "wof:placetype":"venue"
},
  "geometry": {"coordinates":[-8.7856712341,42.2626647949],"type":"Point"}
}