{
  "type": "Feature",
  "properties": {
    "iso:country":"ES",
    "sg:address":"Calle de San Cristobal, 5",
    "sg:city":"Madridejos",
    "sg:orig_category":"Alimentaci\u00d3n General (al Por Menor)",
    "sg:phone":"+34 925 46 33 42",
    "sg:postcode":"45710",
    "sg:province":"Toledo",
    "wof:name":"Hermanos Gonzalez Ortega C.b.",
    "wof:placetype":"venue"
},
  "geometry": {"coordinates":[-3.5262629986,39.4680557251],"type":"Point"}
}