{
  "type": "Feature",
  "properties": {
    "addr:full":"Avda Alcala (de), 1 Azuqueca Henares Guadalajara 19200",
    "addr:housenumber":"1",
    "addr:postcode":"19200",
    "addr:street":"Avda Alcala De",
    "iso:country":"ES",
    "sg:address":"Avda Alcala (de), 1",
    "sg:city":"Azuqueca Henares",
    "sg:orig_category":"Contenedores (mercanc\u00cdas)",
    "sg:phone":"+34 949 88 31 21",
    "sg:postcode":"19200",
    "sg:province":"Guadalajara",
    "wof:name":"Transportes Sedano S. A.",
    "wof:placetype":"venue"
},
  "geometry": {"coordinates":[-3.2718789577,40.5606918335],"type":"Point"}
}