{
  "type": "Feature",
  "properties": {
    "addr:full":"Calle de Estepona, 27 Fuengirola M\u00e1laga 29640",
    "addr:housenumber":"27",
    "addr:postcode":"29640",
    "addr:street":"Calle De Estepona;Ma\u0301Laga",
    "iso:country":"ES",
    "sg:address":"Calle de Estepona, 27",
    "sg:city":"Fuengirola",
    "sg:orig_category":"Panader\u00cdas, Panader\u00cdas",
    "sg:phone":"+34 952 47 69 01",
    "sg:postcode":"29640",
    "sg:province":"M\u00e1laga",
    "wof:name":"Toledo Larrubia Jose",
    "wof:placetype":"venue"
},
  "geometry": {"coordinates":[-4.6284132004,36.5408973694],"type":"Point"}
}