{
  "type": "Feature",
  "properties": {
    "addr:full":"Av Santa Coloma, 12 Olot Girona 17800",
    "addr:housenumber":"12",
    "addr:postcode":"17800",
    "addr:street":"Av Santa Coloma",
    "iso:country":"ES",
    "sg:address":"Av Santa Coloma, 12",
    "sg:city":"Olot",
    "sg:orig_category":"Negocio De Materiales De Construcci\u00d3n",
    "sg:phone":"+34 972 26 20 70",
    "sg:postcode":"17800",
    "sg:province":"Girona",
    "wof:name":"Comercial Faja S. A.",
    "wof:placetype":"venue"
},
  "geometry": {"coordinates":[2.480479002,42.1747627258],"type":"Point"}
}