{
  "type": "Feature",
  "properties": {
    "addr:full":"Calle de Iglesia (de La), 9 Coslada Madrid 28820",
    "addr:housenumber":"9",
    "addr:postcode":"28820",
    "addr:street":"Calle De Iglesia;La",
    "iso:country":"ES",
    "sg:address":"Calle de Iglesia (de La), 9",
    "sg:city":"Coslada",
    "sg:orig_category":"Papeler\u00cdas, Librer\u00cdas",
    "sg:phone":"+34 916 71 93 00",
    "sg:postcode":"28820",
    "sg:province":"Madrid",
    "sg:website":"http://usuarios.tripod.es/papeleriapitufos",
    "wof:name":"Gonzalez Carvajal Manuela",
    "wof:placetype":"venue"
},
  "geometry": {"coordinates":[-3.5679540634,40.4264144897],"type":"Point"}
}