{
  "type": "Feature",
  "properties": {
    "iso:country":"ES",
    "sg:address":"Av Dr. Fleming, De, 71",
    "sg:city":"S. Antoni Portmany",
    "sg:orig_category":"Cr\u00cda De Animales",
    "sg:phone":"+34 971 34 02 73",
    "sg:postcode":"07820",
    "sg:province":"Islas Baleares",
    "wof:name":"Calderon Tejero Vicente",
    "wof:placetype":"venue"
},
  "geometry": {"coordinates":[1.3090130091,38.9736938477],"type":"Point"}
}