{
  "type": "Feature",
  "properties": {
    "addr:full":"Calle de Eduardo Dato, 1 Utiel Valencia 46300",
    "addr:housenumber":"1",
    "addr:postcode":"46300",
    "addr:street":"Calle De Eduardo Dato",
    "iso:country":"ES",
    "sg:address":"Calle de Eduardo Dato, 1",
    "sg:city":"Utiel",
    "sg:orig_category":"Abogados",
    "sg:phone":"+34 962 17 03 79",
    "sg:postcode":"46300",
    "sg:province":"Valencia",
    "wof:name":"Andres Medina Jose",
    "wof:placetype":"venue"
},
  "geometry": {"coordinates":[-1.2032290697,39.5675315857],"type":"Point"}
}