{
  "type": "Feature",
  "properties": {
    "iso:country":"ES",
    "sg:address":"Las Eras, S/n",
    "sg:city":"Borchicayada",
    "sg:orig_category":"Cr\u00cda De Animales",
    "sg:phone":"+34 975 18 11 11",
    "sg:postcode":"42224",
    "sg:province":"Soria",
    "wof:name":"Tarancon Garcia Teodoro",
    "wof:placetype":"venue"
},
  "geometry": {"coordinates":[-2.4103341103,41.4470405579],"type":"Point"}
}