{
  "type": "Feature",
  "properties": {
    "addr:full":"Calle de Correo Viejo, 9 Malaga M\u00e1laga 29015",
    "addr:housenumber":"9",
    "addr:postcode":"29015",
    "addr:street":"Calle De Correo Viejo;Ma\u0301Laga",
    "iso:country":"ES",
    "sg:address":"Calle de Correo Viejo, 9",
    "sg:city":"Malaga",
    "sg:orig_category":"Promotores Constructores",
    "sg:phone":"+34 952 60 90 68",
    "sg:postcode":"29015",
    "sg:province":"M\u00e1laga",
    "wof:name":"Sierra Gorda Coin S.l.",
    "wof:placetype":"venue"
},
  "geometry": {"coordinates":[-4.4203128815,36.7214012146],"type":"Point"}
}