{
  "type": "Feature",
  "properties": {
    "addr:full":"Carrer de Perez Moya, 58 Sabadell Barcelona 08204",
    "addr:housenumber":"58",
    "addr:postcode":"08204",
    "addr:street":"Carrer De Perez Moya",
    "iso:country":"ES",
    "sg:address":"Carrer de Perez Moya, 58",
    "sg:city":"Sabadell",
    "sg:orig_category":"Molduras, Junquillos, Listones Y Molduras Perforadas",
    "sg:phone":"+34 937 10 87 46",
    "sg:postcode":"08204",
    "sg:province":"Barcelona",
    "wof:name":"Acebez Garcia Francisco",
    "wof:placetype":"venue"
},
  "geometry": {"coordinates":[2.1209683418,41.5293693542],"type":"Point"}
}