{
  "type": "Feature",
  "properties": {
    "iso:country":"ES",
    "sg:address":"Ctra. Tarrag-pobla De Mafumet, S/n",
    "sg:city":"Pobla Mafumet",
    "sg:orig_category":"Mantenimiento Industrial",
    "sg:phone":"+34 977 84 09 22",
    "sg:postcode":"43140",
    "sg:province":"Tarragona",
    "wof:name":"Imisa De Mantenimiento Y Montaje S.a",
    "wof:placetype":"venue"
},
  "geometry": {"coordinates":[1.2092289925,41.1888885498],"type":"Point"}
}