{
  "type": "Feature",
  "properties": {
    "addr:full":"Carrer de Juan De Garay, 13 Barcelona Barcelona 08041",
    "addr:housenumber":"13",
    "addr:postcode":"08041",
    "addr:street":"Carrer De Juan De Garay",
    "iso:country":"ES",
    "sg:address":"Carrer de Juan De Garay, 13",
    "sg:city":"Barcelona",
    "sg:orig_category":"Abogados",
    "sg:phone":"+34 933 59 92 24",
    "sg:postcode":"08041",
    "sg:province":"Barcelona",
    "wof:name":"Kassandra S.a.",
    "wof:placetype":"venue"
},
  "geometry": {"coordinates":[2.1815760136,41.4185295105],"type":"Point"}
}