{
  "type": "Feature",
  "properties": {
    "addr:full":"Avda Sancho El Sabio, S/n Arcos Navarra 31210",
    "addr:housenumber":"s",
    "addr:postcode":"31210",
    "addr:street":"Avda Sancho El Sabio;/ N",
    "iso:country":"ES",
    "sg:address":"Avda Sancho El Sabio, S/n",
    "sg:city":"Arcos",
    "sg:orig_category":"Cooperativas Agr\u00cdcolas",
    "sg:phone":"+34 948 64 08 08",
    "sg:postcode":"31210",
    "sg:province":"Navarra",
    "wof:name":"Sociedad Cooperativa Limitada Cerealista Odron",
    "wof:placetype":"venue"
},
  "geometry": {"coordinates":[-2.1922340393,42.568271637],"type":"Point"}
}