{
  "type": "Feature",
  "properties": {
    "addr:full":"Calle de Carrero Blanco, S/n Caion La Coru\u00f1a 15105",
    "addr:housenumber":"s / n",
    "addr:postcode":"15105",
    "addr:street":"Calle De Carrero Blanco;La Corun\u0303A",
    "iso:country":"ES",
    "sg:address":"Calle de Carrero Blanco, S/n",
    "sg:city":"Caion",
    "sg:orig_category":"Caf\u00c9s, Bares, Cervecer\u00cdas",
    "sg:phone":"+34 981 60 40 98",
    "sg:postcode":"15105",
    "sg:province":"La Coru\u00f1a",
    "wof:name":"Iglesias Rodriguez Guillermo",
    "wof:placetype":"venue"
},
  "geometry": {"coordinates":[-8.6054534912,43.3195991516],"type":"Point"}
}