{
  "type": "Feature",
  "properties": {
    "iso:country":"ES",
    "sg:address":"Avda Europa, 22",
    "sg:city":"Vista Alegre",
    "sg:orig_category":"Transportes Por V\u00cdas Navegables",
    "sg:phone":"+34 968 23 94 14",
    "sg:postcode":"30007",
    "sg:province":"Murcia",
    "wof:name":"Yantamar S.l.",
    "wof:placetype":"venue"
},
  "geometry": {"coordinates":[-1.1298867464,37.9834747314],"type":"Point"}
}