{
  "type": "Feature",
  "properties": {
    "iso:country":"ES",
    "sg:address":"Calle de Mancha Real, 20",
    "sg:city":"Jaen",
    "sg:orig_category":"Supermercados Y Hipermercados",
    "sg:phone":"+34 953 28 07 83",
    "sg:postcode":"23009",
    "sg:province":"Ja\u00e9n",
    "wof:name":"Coaliment Andalucia S.l.",
    "wof:placetype":"venue"
},
  "geometry": {"coordinates":[-3.7824220657,37.8013877869],"type":"Point"}
}