{
  "type": "Feature",
  "properties": {
    "iso:country":"ES",
    "sg:address":"Grup Cortes Pedro Medico Mun., 2",
    "sg:city":"Bilbao",
    "sg:orig_category":"Prot\u00c9sicos Dentales",
    "sg:phone":"+34 944 73 37 36",
    "sg:postcode":"48006",
    "sg:province":"Vizcaya",
    "wof:name":"Perez De Albeniz Arrieta Ignacio",
    "wof:placetype":"venue"
},
  "geometry": {"coordinates":[-2.9171590805,43.2605361938],"type":"Point"}
}