{
  "type": "Feature",
  "properties": {
    "iso:country":"ES",
    "sg:address":"Rua Castelao, 76",
    "sg:city":"Lugo",
    "sg:orig_category":"Autob\u00das (explotaci\u00d3n Y Servicios De)",
    "sg:phone":"+34 982 22 10 03",
    "sg:postcode":"27001",
    "sg:province":"Lugo",
    "wof:name":"Autocares Trigo S. L.",
    "wof:placetype":"venue"
},
  "geometry": {"coordinates":[-7.5523548126,43.0136909485],"type":"Point"}
}