{
  "type": "Feature",
  "properties": {
    "iso:country":"ES",
    "sg:address":"Carrer de Sant Carles, S/n",
    "sg:city":"Senia",
    "sg:orig_category":"Mec\u00c1nico Del Autom\u00d3vil",
    "sg:phone":"+34 977 71 30 67",
    "sg:postcode":"43560",
    "sg:province":"Tarragona",
    "wof:name":"Lleixa Armengol Daniel",
    "wof:placetype":"venue"
},
  "geometry": {"coordinates":[0.2842850089,40.6347885132],"type":"Point"}
}