{
  "type": "Feature",
  "properties": {
    "iso:country":"ES",
    "sg:address":"Calle de San Juan, 39",
    "sg:city":"Castellon",
    "sg:orig_category":"Distribuci\u00d3n De Petr\u00d3leo Y Derivados",
    "sg:phone":"+34 964 21 77 63",
    "sg:postcode":"12006",
    "sg:province":"Castell\u00f3n",
    "wof:name":"Monta\u00f1es Torres Juana",
    "wof:placetype":"venue"
},
  "geometry": {"coordinates":[-0.1292939931,40.0168533325],"type":"Point"}
}