{
  "type": "Feature",
  "properties": {
    "iso:country":"ES",
    "sg:address":"Rua Doctor Casares, 58",
    "sg:city":"Monforte De Lemos",
    "sg:orig_category":"Librer\u00cdas",
    "sg:phone":"+34 982 40 44 42",
    "sg:postcode":"27400",
    "sg:province":"Lugo",
    "wof:name":"Meira Vazquez Virginia",
    "wof:placetype":"venue"
},
  "geometry": {"coordinates":[-7.5119519234,42.5247802734],"type":"Point"}
}