{
  "type": "Feature",
  "properties": {
    "iso:country":"ES",
    "sg:address":"Faitanar, 10",
    "sg:city":"Paiporta",
    "sg:orig_category":"Electricidad, Electr\u00d3nica: Material Y Suministros (al Por Mayor)",
    "sg:phone":"+34 963 97 38 96",
    "sg:postcode":"46200",
    "sg:province":"Valencia",
    "wof:name":"Egasa Xxi S.a.",
    "wof:placetype":"venue"
},
  "geometry": {"coordinates":[-0.4047580063,39.4314613342],"type":"Point"}
}