{
  "type": "Feature",
  "properties": {
    "addr:full":"Pista Mirones, S/n El Ballestero Albacete 02614",
    "addr:housenumber":"s / n",
    "addr:postcode":"02614",
    "iso:country":"ES",
    "sg:address":"Pista Mirones, S/n",
    "sg:city":"El Ballestero",
    "sg:orig_category":"Ropa Y Accesorios",
    "sg:phone":"+34 967 58 11 02",
    "sg:postcode":"02614",
    "sg:province":"Albacete",
    "wof:name":"Exclusivas San Rafael S.a.",
    "wof:placetype":"venue"
},
  "geometry": {"coordinates":[-2.4530119896,38.841835022],"type":"Point"}
}