{
  "type": "Feature",
  "properties": {
    "addr:full":"Calle de Seco, 12 Madrid Madrid 28007",
    "addr:housenumber":"12",
    "addr:postcode":"madrid;28007",
    "addr:street":"Calle De Seco",
    "iso:country":"ES",
    "sg:address":"Calle de Seco, 12",
    "sg:city":"Madrid",
    "sg:orig_category":"Molduras, Junquillos, Listones Y Molduras Perforadas",
    "sg:phone":"+34 915 52 53 92",
    "sg:postcode":"28007",
    "sg:province":"Madrid",
    "wof:name":"Cristobal Palomar Victoriano",
    "wof:placetype":"venue"
},
  "geometry": {"coordinates":[-3.6726350784,40.3985023499],"type":"Point"}
}