{
  "type": "Feature",
  "properties": {
    "iso:country":"ES",
    "sg:address":"Bixkonde Kalea, 13",
    "sg:city":"Zarautz",
    "sg:orig_category":"Lanas (al Por Menor)",
    "sg:phone":"+34 943 83 19 76",
    "sg:postcode":"20800",
    "sg:province":"Guip\u00f9zcoa",
    "wof:name":"Agirrezabalaga Elosegi, Guillermina",
    "wof:placetype":"venue"
},
  "geometry": {"coordinates":[-2.1753790379,43.2868690491],"type":"Point"}
}