{
  "type": "Feature",
  "properties": {
    "iso:country":"ES",
    "sg:address":"Calle de Mula, 6",
    "sg:city":"Torres Cotillas",
    "sg:orig_category":"Muebles Y Accesorios Para Cocinas Y Cuartos De Ba\u00d1o (al Por Menor)",
    "sg:phone":"+34 968 62 69 55",
    "sg:postcode":"30565",
    "sg:province":"Murcia",
    "wof:name":"Morell Sandoval Joaquin",
    "wof:placetype":"venue"
},
  "geometry": {"coordinates":[-1.2419011593,38.0321578979],"type":"Point"}
}