{
  "type": "Feature",
  "properties": {
    "iso:country":"ES",
    "sg:address":"Carrer de Sant Carles, 25",
    "sg:city":"Lloret Mar",
    "sg:orig_category":"Cooperativas Agr\u00cdcolas",
    "sg:phone":"+34 972 34 93 13",
    "sg:postcode":"17310",
    "sg:province":"Girona",
    "wof:name":"Agricultores De Lloret S.l.",
    "wof:placetype":"venue"
},
  "geometry": {"coordinates":[2.8466303349,41.7007331848],"type":"Point"}
}