{
  "type": "Feature",
  "properties": {
    "iso:country":"ES",
    "sg:address":"Ctra Ulzama, Km. 0002,5",
    "sg:city":"Berriosuso",
    "sg:orig_category":"Combustibles: Fuel",
    "sg:phone":"+34 948 30 25 05",
    "sg:postcode":"31195",
    "sg:province":"Navarra",
    "wof:name":"Petronavarra S.l.",
    "wof:placetype":"venue"
},
  "geometry": {"coordinates":[-1.6878319979,42.8602561951],"type":"Point"}
}