{
  "type": "Feature",
  "properties": {
    "iso:country":"ES",
    "sg:address":"Carrer de Sant Nicasi, 55",
    "sg:city":"Gava",
    "sg:orig_category":"Delegados, Agentes De Tr\u00c1nsito, Auxiliares De Transporte Internacional",
    "sg:phone":"+34 936 38 03 93",
    "sg:postcode":"08850",
    "sg:province":"Barcelona",
    "wof:name":"Transportes Campmany S.a.",
    "wof:placetype":"venue"
},
  "geometry": {"coordinates":[2.0023100376,41.3060302734],"type":"Point"}
}