{
  "type": "Feature",
  "properties": {
    "addr:full":"Pg Estaselles (les), 26 Berga-ciudad Barcelona 08600",
    "addr:housenumber":"26",
    "addr:postcode":"08600",
    "addr:street":"Pg Estaselles Les;Barcelona",
    "iso:country":"ES",
    "sg:address":"Pg Estaselles (les), 26",
    "sg:city":"Berga-ciudad",
    "sg:orig_category":"Asesor\u00cda, Estudio Y Control Medioambiental",
    "sg:phone":"+34 938 21 50 65",
    "sg:postcode":"08600",
    "sg:province":"Barcelona",
    "wof:name":"Sensada Tor Maria Lourdes",
    "wof:placetype":"venue"
},
  "geometry": {"coordinates":[1.8413579464,42.1005935669],"type":"Point"}
}