{
  "type": "Feature",
  "properties": {
    "addr:full":"Calle de Muro, 80 Hoya Pavon Las Palmas 35110",
    "addr:housenumber":"80",
    "addr:postcode":"35110",
    "addr:street":"Calle De Muro;Pavon;Palmas",
    "iso:country":"ES",
    "sg:address":"Calle de Muro, 80",
    "sg:city":"Hoya Pavon",
    "sg:orig_category":"Perfumer\u00cda, Art\u00cdculos De Ba\u00d1o (fabricaci\u00d3n, Al Por Mayor)",
    "sg:phone":"+34 928 79 31 61",
    "sg:postcode":"35110",
    "sg:province":"Las Palmas",
    "wof:name":"Fransuca S.l.",
    "wof:placetype":"venue"
},
  "geometry": {"coordinates":[-15.4485340118,27.8392906189],"type":"Point"}
}