{
  "type": "Feature",
  "properties": {
    "addr:full":"Avda Andalucia (de), 15 Alcala Real Ja\u00e9n 23680",
    "addr:housenumber":"15",
    "addr:postcode":"23680",
    "addr:street":"Avda Andalucia De;Jae\u0301N",
    "iso:country":"ES",
    "sg:address":"Avda Andalucia (de), 15",
    "sg:city":"Alcala Real",
    "sg:orig_category":"Comercio De Piezas De Recambio Y De Accesorios De Veh\u00cdculos, Veh\u00cdculos Industriales",
    "sg:phone":"+34 953 58 14 42",
    "sg:postcode":"23680",
    "sg:province":"Ja\u00e9n",
    "wof:name":"Repuestos Alcala S.l.",
    "wof:placetype":"venue"
},
  "geometry": {"coordinates":[-3.9224700928,37.4586448669],"type":"Point"}
}