{
  "type": "Feature",
  "properties": {
    "addr:full":"Calle de Ponferrada, 43 Madrid Madrid 28029",
    "addr:housenumber":"43",
    "addr:postcode":"madrid;28029",
    "addr:street":"Calle De Ponferrada",
    "iso:country":"ES",
    "sg:address":"Calle de Ponferrada, 43",
    "sg:city":"Madrid",
    "sg:orig_category":"Confecci\u00d3n (fabricaci\u00d3n, Al Por Mayor)",
    "sg:phone":"+34 913 86 14 10",
    "sg:postcode":"28029",
    "sg:province":"Madrid",
    "wof:name":"Rodriguez Saria Inocente",
    "wof:placetype":"venue"
},
  "geometry": {"coordinates":[-3.7131690979,40.4753799438],"type":"Point"}
}