{
  "type": "Feature",
  "properties": {
    "addr:full":"Calle de Cesar Augusto, 4 Peligros Granada 18210",
    "addr:housenumber":"4",
    "addr:postcode":"18210",
    "addr:street":"Calle De Cesar Augusto",
    "iso:country":"ES",
    "sg:address":"Calle de Cesar Augusto, 4",
    "sg:city":"Peligros",
    "sg:orig_category":"Platos Preparados Refrigerados (fabricaci\u00d3n, Al Por Mayor)",
    "sg:phone":"+34 958 40 01 21",
    "sg:postcode":"18210",
    "sg:province":"Granada",
    "wof:name":"Bailon Nevado Antonio",
    "wof:placetype":"venue"
},
  "geometry": {"coordinates":[-3.6299335957,37.2334098816],"type":"Point"}
}