{
  "type": "Feature",
  "properties": {
    "iso:country":"ES",
    "sg:address":"Calle de Real, 111",
    "sg:city":"Calzada Calatrava",
    "sg:orig_category":"Centros Empresariales",
    "sg:phone":"+34 926 26 20 15",
    "sg:postcode":"13370",
    "sg:province":"Ciudad Real",
    "wof:name":"Telefonica Data Espa\u00f1a S.a.",
    "wof:placetype":"venue"
},
  "geometry": {"coordinates":[-3.7739908695,38.7010154724],"type":"Point"}
}