{
  "type": "Feature",
  "properties": {
    "addr:full":"Carr Manuel De Cabanyes, 4 Vilanova I La Geltru Barcelona 08800",
    "addr:housenumber":"4",
    "addr:postcode":"08800",
    "addr:street":"Carr Manuel De Cabanyes",
    "iso:country":"ES",
    "sg:address":"Carr Manuel De Cabanyes, 4",
    "sg:city":"Vilanova I La Geltru",
    "sg:orig_category":"Venta, Localizaci\u00d3n, Reparaci\u00d3n De Material E Instrumental M\u00c9dico",
    "sg:phone":"+34 938 14 71 80",
    "sg:postcode":"08800",
    "sg:province":"Barcelona",
    "sg:website":"www.vlferrandiz.com",
    "wof:name":"Ferrandiz Dr Vl Herederos S.l",
    "wof:placetype":"venue"
},
  "geometry": {"coordinates":[1.7232300043,41.2265701294],"type":"Point"}
}