{
  "type": "Feature",
  "properties": {
    "iso:country":"ES",
    "sg:address":"Pg Gracia, 12",
    "sg:city":"Barcelona",
    "sg:orig_category":"Peritos En Autom\u00d3viles",
    "sg:phone":"+34 933 17 16 93",
    "sg:postcode":"08007",
    "sg:province":"Barcelona",
    "sg:website":"www.aimsun.com",
    "wof:name":"Tss -transport Simulation Systems S.l.",
    "wof:placetype":"venue"
},
  "geometry": {"coordinates":[2.1691160202,41.3891448975],"type":"Point"}
}