{
  "type": "Feature",
  "properties": {
    "iso:country":"ES",
    "sg:address":"Pl Constitucio, 7",
    "sg:city":"Prat Llobregat",
    "sg:orig_category":"Muebles, Minoristas",
    "sg:phone":"+34 934 78 43 61",
    "sg:postcode":"08820",
    "sg:province":"Barcelona",
    "wof:name":"Garcia Garcia Antonio",
    "wof:placetype":"venue"
},
  "geometry": {"coordinates":[2.1017119884,41.3243942261],"type":"Point"}
}