{
  "type": "Feature",
  "properties": {
    "addr:full":"De La Plaza, 3 Iniesta Cuenca 16235",
    "addr:housenumber":"3",
    "addr:postcode":"16235",
    "iso:country":"ES",
    "sg:address":"De La Plaza, 3",
    "sg:city":"Iniesta",
    "sg:orig_category":"Supermercados Y Hipermercados",
    "sg:phone":"+34 967 49 00 40",
    "sg:postcode":"16235",
    "sg:province":"Cuenca",
    "wof:name":"Pamajedo S.l.",
    "wof:placetype":"venue"
},
  "geometry": {"coordinates":[-1.7489440441,39.4435081482],"type":"Point"}
}