{
  "type": "Feature",
  "properties": {
    "iso:country":"ES",
    "sg:address":"Calle de Tomas Breton, 2",
    "sg:city":"Barriada San Cristobal",
    "sg:orig_category":"Mec\u00c1nico Del Autom\u00d3vil",
    "sg:phone":"+34 968 51 51 08",
    "sg:postcode":"30310",
    "sg:province":"Murcia",
    "wof:name":"Talleres San Isidoro S.l.",
    "wof:placetype":"venue"
},
  "geometry": {"coordinates":[-1.0041860342,37.646812439],"type":"Point"}
}