{
  "type": "Feature",
  "properties": {
    "addr:full":"Av Sant Narcis, 96 Girona Girona 17005",
    "addr:housenumber":"96",
    "addr:postcode":"17005",
    "addr:street":"Av Sant Narcis",
    "iso:country":"ES",
    "sg:address":"Av Sant Narcis, 96",
    "sg:city":"Girona",
    "sg:orig_category":"Bancos",
    "sg:phone":"+34 972 40 11 77",
    "sg:postcode":"17005",
    "sg:province":"Girona",
    "wof:name":"Banc Sabadell S.a.",
    "wof:placetype":"venue"
},
  "geometry": {"coordinates":[2.8114020824,41.9703712463],"type":"Point"}
}