{
  "type": "Feature",
  "properties": {
    "iso:country":"ES",
    "sg:address":"Ctra Motores (los), S/n",
    "sg:city":"Parador Hortichuelas",
    "sg:orig_category":"Empresas De Carpinter\u00cda De Madera",
    "sg:phone":"+34 950 34 17 98",
    "sg:postcode":"04720",
    "sg:province":"Almer\u00eda",
    "wof:name":"Lopez Lopez Cristobal",
    "wof:placetype":"venue"
},
  "geometry": {"coordinates":[-2.5945138931,36.8065452576],"type":"Point"}
}