{
  "type": "Feature",
  "properties": {
    "addr:full":"Carretera Antiga Girona-olot, S/n Porqueres Girona 17834",
    "addr:housenumber":"s / n",
    "addr:postcode":"17834",
    "addr:street":"Carretera Antiga Girona-Olot",
    "iso:country":"ES",
    "sg:address":"Carretera Antiga Girona-olot, S/n",
    "sg:city":"Porqueres",
    "sg:orig_category":"Financiaci\u00d3n Y Cr\u00c9ditos",
    "sg:phone":"+34 972 57 06 16",
    "sg:postcode":"17834",
    "sg:province":"Girona",
    "wof:name":"Financial Center Banyoles S.l.",
    "wof:placetype":"venue"
},
  "geometry": {"coordinates":[2.747494936,42.1514892578],"type":"Point"}
}