{
  "type": "Feature",
  "properties": {
    "iso:country":"ES",
    "sg:address":"Avda Carmen Amigo, 115",
    "sg:city":"Puebla Calzada",
    "sg:orig_category":"Cerrajer\u00cda, Ferrallista",
    "sg:phone":"+34 924 45 02 22",
    "sg:postcode":"06490",
    "sg:province":"Badajoz",
    "wof:name":"Estructuras Tartesos S.a.",
    "wof:placetype":"venue"
},
  "geometry": {"coordinates":[-6.6321988106,38.8909606934],"type":"Point"}
}