{
  "type": "Feature",
  "properties": {
    "iso:country":"ES",
    "sg:address":"Calle de Andrestegi, 6",
    "sg:city":"Donostia-san Sebastian",
    "sg:orig_category":"Ense\u00d1anza: Idiomas",
    "sg:phone":"+34 943 31 15 25",
    "sg:postcode":"20018",
    "sg:province":"Guip\u00f9zcoa",
    "wof:name":"Jaureguy Sajot Didier",
    "wof:placetype":"venue"
},
  "geometry": {"coordinates":[-2.0112977028,43.3094406128],"type":"Point"}
}