{
  "type": "Feature",
  "properties": {
    "iso:country":"ES",
    "sg:address":"Calle de Mostoles (de), 36",
    "sg:city":"Fuenlabrada",
    "sg:orig_category":"Administradores De Bienes Y Delegados De Comunidades De Propietarios",
    "sg:phone":"+34 916 06 49 13",
    "sg:postcode":"28943",
    "sg:province":"Madrid",
    "wof:name":"Lorman Administraciones S.l.",
    "wof:placetype":"venue"
},
  "geometry": {"coordinates":[-3.7995307446,40.286403656],"type":"Point"}
}