{
  "type": "Feature",
  "properties": {
    "iso:country":"ES",
    "sg:address":"Carr Eivissa, 30",
    "sg:city":"Girona",
    "sg:orig_category":"Empresarios",
    "sg:phone":"+34 972 20 73 44",
    "sg:postcode":"17007",
    "sg:province":"Girona",
    "wof:name":"Beltran Quirantes Juan",
    "wof:placetype":"venue"
},
  "geometry": {"coordinates":[2.8241679668,42.006980896],"type":"Point"}
}