{
  "type": "Feature",
  "properties": {
    "addr:full":"Ronda De La Coru\u00f1a, 32 Melide La Coru\u00f1a 15800",
    "addr:housenumber":"32",
    "addr:postcode":"15800",
    "addr:street":"Ronda De La Corun\u0303A;La Corun\u0303A",
    "iso:country":"ES",
    "sg:address":"Ronda De La Coru\u00f1a, 32",
    "sg:city":"Melide",
    "sg:orig_category":"Electricidad: Instaladores",
    "sg:phone":"+34 981 50 78 55",
    "sg:postcode":"15800",
    "sg:province":"La Coru\u00f1a",
    "wof:name":"Instalaciones Benda\u00f1a S.l.",
    "wof:placetype":"venue"
},
  "geometry": {"coordinates":[-8.0153255463,42.9151649475],"type":"Point"}
}