{
  "type": "Feature",
  "properties": {
    "iso:country":"ES",
    "sg:address":"Calle de Moros, 24",
    "sg:city":"Gijon",
    "sg:orig_category":"Promotores Constructores",
    "sg:phone":"+34 985 17 22 21",
    "sg:postcode":"33206",
    "sg:province":"Asturias",
    "wof:name":"Construcciones Davila S.l.",
    "wof:placetype":"venue"
},
  "geometry": {"coordinates":[-5.6629657745,43.540977478],"type":"Point"}
}