{
  "type": "Feature",
  "properties": {
    "addr:full":"Rua Gasset, 15 Pobra Do Carami\u00e7al A Coru\u00f1a 15940",
    "addr:housenumber":"15",
    "addr:postcode":"15940",
    "addr:street":"Rua Gasset;Corun\u0303A",
    "iso:country":"ES",
    "sg:address":"Rua Gasset, 15",
    "sg:city":"Pobra Do Carami\u00e7al",
    "sg:orig_category":"Mercer\u00cda, Lencer\u00cda (al Por Menor)",
    "sg:phone":"+34 981 83 33 31",
    "sg:postcode":"15940",
    "sg:province":"A Coru\u00f1a",
    "wof:name":"Super Textil Vigo S.l.",
    "wof:placetype":"venue"
},
  "geometry": {"coordinates":[-8.9389667511,42.6036911011],"type":"Point"}
}