{
  "type": "Feature",
  "properties": {
    "addr:full":"Avda Constitucion, 121 Cistierna Le\u00f3n 24800",
    "addr:housenumber":"121",
    "addr:postcode":"24800",
    "addr:street":"Avda Constitucion;Leo\u0301N",
    "iso:country":"ES",
    "sg:address":"Avda Constitucion, 121",
    "sg:city":"Cistierna",
    "sg:orig_category":"Arquitectos",
    "sg:phone":"+34 987 70 09 74",
    "sg:postcode":"24800",
    "sg:province":"Le\u00f3n",
    "wof:name":"Miguel Garcia Joaquin",
    "wof:placetype":"venue"
},
  "geometry": {"coordinates":[-5.1292481422,42.8051605225],"type":"Point"}
}