{
  "type": "Feature",
  "properties": {
    "iso:country":"ES",
    "sg:address":"Calle de Luciano Travadelo, 10",
    "sg:city":"Chantada",
    "sg:orig_category":"Imprenta",
    "sg:phone":"+34 982 44 02 10",
    "sg:postcode":"27500",
    "sg:province":"Lugo",
    "wof:name":"Vence Lopez Marta",
    "wof:placetype":"venue"
},
  "geometry": {"coordinates":[-7.7680439949,42.6086997986],"type":"Point"}
}