{
  "type": "Feature",
  "properties": {
    "iso:country":"ES",
    "sg:address":"Calle de Fernandez Ladreda, 16",
    "sg:city":"Valladolid",
    "sg:orig_category":"Artes Gr\u00c1ficas, Artes Pl\u00c1sticas (curso)",
    "sg:phone":"+34 983 47 16 20",
    "sg:postcode":"47008",
    "sg:province":"Valladolid",
    "wof:name":"Grafolex S.l.",
    "wof:placetype":"venue"
},
  "geometry": {"coordinates":[-4.7350487709,41.6297187805],"type":"Point"}
}