{
  "type": "Feature",
  "properties": {
    "addr:full":"Calle de Andres Sobejano, 5 Purisima -barriomar Murcia 30010",
    "addr:housenumber":"5",
    "addr:postcode":"30010",
    "addr:street":"Calle De Andres Sobejano",
    "iso:country":"ES",
    "sg:address":"Calle de Andres Sobejano, 5",
    "sg:city":"Purisima -barriomar",
    "sg:orig_category":"Fabricaci\u00d3n, Venta, Instalaci\u00d3n De R\u00d3tulos, De R\u00d3tulos Luminosos",
    "sg:phone":"+34 968 34 12 00",
    "sg:postcode":"30010",
    "sg:province":"Murcia",
    "wof:name":"Manzanera Romero Jose Maria",
    "wof:placetype":"venue"
},
  "geometry": {"coordinates":[-1.1438002586,37.9755783081],"type":"Point"}
}