{
  "type": "Feature",
  "properties": {
    "addr:full":"Ctra. Puerto, S/n Motril Granada 18600",
    "addr:postcode":"18600",
    "addr:street":"Ctra. Puerto S / N;Granada",
    "iso:country":"ES",
    "sg:address":"Ctra. Puerto, S/n",
    "sg:city":"Motril",
    "sg:orig_category":"Muebles Y Accesorios Para Cocinas Y Cuartos De Ba\u00d1o (al Por Menor)",
    "sg:phone":"+34 958 82 56 64",
    "sg:postcode":"18600",
    "sg:province":"Granada",
    "wof:name":"Cocinas Chavil S.l.",
    "wof:placetype":"venue"
},
  "geometry": {"coordinates":[-3.5237839222,36.7498855591],"type":"Point"}
}