{
  "type": "Feature",
  "properties": {
    "addr:full":"Carrer de Berlin (de), 10 Salou Tarragona 43840",
    "addr:housenumber":"10",
    "addr:postcode":"43840",
    "addr:street":"Carrer De Berlin De",
    "iso:country":"ES",
    "sg:address":"Carrer de Berlin (de), 10",
    "sg:city":"Salou",
    "sg:orig_category":"Arquitectos",
    "sg:phone":"+34 977 35 13 41",
    "sg:postcode":"43840",
    "sg:province":"Tarragona",
    "wof:name":"Jose Oliva Oliva Arquitecte S.l.",
    "wof:placetype":"venue"
},
  "geometry": {"coordinates":[1.1373410225,41.0762252808],"type":"Point"}
}