{
  "type": "Feature",
  "properties": {
    "iso:country":"ES",
    "sg:address":"Calle de Salamanca, 17",
    "sg:city":"Mora",
    "sg:orig_category":"Calefacci\u00d3n Central: Material (fabricaci\u00d3n, Al Por Mayor)",
    "sg:phone":"+34 925 32 20 40",
    "sg:postcode":"45400",
    "sg:province":"Toledo",
    "wof:name":"Saneamiento Y Calefaccion Ceygesa S.l.",
    "wof:placetype":"venue"
},
  "geometry": {"coordinates":[-3.7718389034,39.6827201843],"type":"Point"}
}