{
  "type": "Feature",
  "properties": {
    "addr:full":"Luga Vilar-lestedo, 2 Lestedo A Coru\u00f1a 15881",
    "addr:housenumber":"2",
    "addr:postcode":"15881",
    "addr:street":"Vilar-Lestedo;Corun\u0303A",
    "iso:country":"ES",
    "sg:address":"Luga Vilar-lestedo, 2",
    "sg:city":"Lestedo",
    "sg:orig_category":"Asesor\u00cda Sobre Comunicaci\u00d3n De Empresas",
    "sg:phone":"+34 981 50 31 83",
    "sg:postcode":"15881",
    "sg:province":"A Coru\u00f1a",
    "wof:name":"Serficon Asesores S.l.",
    "wof:placetype":"venue"
},
  "geometry": {"coordinates":[-8.4128170013,42.8135566711],"type":"Point"}
}