{
  "type": "Feature",
  "properties": {
    "iso:country":"ES",
    "sg:address":"Industrialdea, S/n",
    "sg:city":"Itziar",
    "sg:orig_category":"Electromec\u00c1nica",
    "sg:phone":"+34 943 60 62 65",
    "sg:postcode":"20829",
    "sg:province":"Guip\u00f9zcoa",
    "wof:name":"Motor Kide S.l.",
    "wof:placetype":"venue"
},
  "geometry": {"coordinates":[-2.3285243511,43.2732963562],"type":"Point"}
}