{
  "type": "Feature",
  "properties": {
    "iso:country":"ES",
    "sg:address":"Avda Federico Anaya, 56",
    "sg:city":"Salamanca",
    "sg:orig_category":"Confecci\u00d3n (fabricaci\u00d3n, Al Por Mayor)",
    "sg:phone":"+34 923 24 11 17",
    "sg:postcode":"37004",
    "sg:province":"Salamanca",
    "wof:name":"Gonzalez Gonzalez Castor",
    "wof:placetype":"venue"
},
  "geometry": {"coordinates":[-5.6554617882,40.9750862122],"type":"Point"}
}