{
  "type": "Feature",
  "properties": {
    "addr:full":"Calle de Siroco, 6 Majadahonda Madrid 28220",
    "addr:housenumber":"6",
    "addr:postcode":"28220",
    "addr:street":"Calle De Siroco",
    "iso:country":"ES",
    "sg:address":"Calle de Siroco, 6",
    "sg:city":"Majadahonda",
    "sg:orig_category":"Plomeros",
    "sg:phone":"+34 916 39 52 93",
    "sg:postcode":"28220",
    "sg:province":"Madrid",
    "wof:name":"Aqua Consult Ingenieros S.l.",
    "wof:placetype":"venue"
},
  "geometry": {"coordinates":[-3.8514175415,40.477558136],"type":"Point"}
}