{
  "type": "Feature",
  "properties": {
    "addr:full":"Calle de Pedro Salinas, 2 Balsicas Murcia 30591",
    "addr:housenumber":"2",
    "addr:postcode":"30591",
    "addr:street":"Calle De Pedro Salinas",
    "iso:country":"ES",
    "sg:address":"Calle de Pedro Salinas, 2",
    "sg:city":"Balsicas",
    "sg:orig_category":"Contenedores (mercanc\u00cdas)",
    "sg:phone":"+34 968 58 01 72",
    "sg:postcode":"30591",
    "sg:province":"Murcia",
    "wof:name":"Escudero Ba\u00f1os Sebastian",
    "wof:placetype":"venue"
},
  "geometry": {"coordinates":[-0.9627190232,37.8192405701],"type":"Point"}
}