{
  "type": "Feature",
  "properties": {
    "addr:full":"Calle de San Pio X, 31 Valencia Valencia 46017",
    "addr:housenumber":"31",
    "addr:postcode":"46017",
    "addr:street":"Calle De San Pio X",
    "iso:country":"ES",
    "sg:address":"Calle de San Pio X, 31",
    "sg:city":"Valencia",
    "sg:orig_category":"Alimentaci\u00d3n General (al Por Menor)",
    "sg:phone":"+34 963 78 33 58",
    "sg:postcode":"46017",
    "sg:province":"Valencia",
    "wof:name":"Llovera Martinez Ramon",
    "wof:placetype":"venue"
},
  "geometry": {"coordinates":[-0.3900412023,39.443649292],"type":"Point"}
}