{
  "type": "Feature",
  "properties": {
    "addr:full":"Esperanza, S/n Villaricos Almer\u00eda 04618",
    "addr:housenumber":"s",
    "addr:postcode":"04618",
    "addr:street":"Esperanza;/ N Villaricos Almeri\u0301A",
    "iso:country":"ES",
    "sg:address":"Esperanza, S/n",
    "sg:city":"Villaricos",
    "sg:orig_category":"Molduras, Junquillos, Listones Y Molduras Perforadas",
    "sg:phone":"+34 950 46 77 23",
    "sg:postcode":"04618",
    "sg:province":"Almer\u00eda",
    "wof:name":"Rodriguez Rodriguez Felix",
    "wof:placetype":"venue"
},
  "geometry": {"coordinates":[-1.7685040236,37.2515449524],"type":"Point"}
}