{
  "type": "Feature",
  "properties": {
    "addr:full":"Calle de Peso (el), 9 Lucena C\u00f3rdoba 14900",
    "addr:housenumber":"9",
    "addr:postcode":"14900",
    "addr:street":"Calle De Peso El",
    "iso:country":"ES",
    "sg:address":"Calle de Peso (el), 9",
    "sg:city":"Lucena",
    "sg:orig_category":"Procuradores",
    "sg:phone":"+34 957 50 10 28",
    "sg:postcode":"14900",
    "sg:province":"C\u00f3rdoba",
    "wof:name":"Otero Lopez Julio Luis",
    "wof:placetype":"venue"
},
  "geometry": {"coordinates":[-4.4866251945,37.4087104797],"type":"Point"}
}