{
  "type": "Feature",
  "properties": {
    "addr:full":"Calle de San Ignacio, 2 Sevilla Sevilla 41018",
    "addr:housenumber":"2",
    "addr:postcode":"41018",
    "addr:street":"Calle De San Ignacio",
    "iso:country":"ES",
    "sg:address":"Calle de San Ignacio, 2",
    "sg:city":"Sevilla",
    "sg:orig_category":"M\u00c9dicos: Estomatolog\u00cda",
    "sg:phone":"+34 954 57 78 22",
    "sg:postcode":"41018",
    "sg:province":"Sevilla",
    "sg:website":"www.arrakis.es/sta.cruz.",
    "wof:name":"Servicios Medicos Santa Cruz S.l.",
    "wof:placetype":"venue"
},
  "geometry": {"coordinates":[-5.9767332077,37.386516571],"type":"Point"}
}