{
  "type": "Feature",
  "properties": {
    "addr:full":"Ctra. Ortigosa, 26 Sta M. Real Nieva Segovia 40440",
    "addr:housenumber":"26",
    "addr:postcode":"40440",
    "addr:street":"Ctra. Ortigosa;M.",
    "iso:country":"ES",
    "sg:address":"Ctra. Ortigosa, 26",
    "sg:city":"Sta M. Real Nieva",
    "sg:orig_category":"Cr\u00cda De Animales",
    "sg:phone":"+34 921 59 41 64",
    "sg:postcode":"40440",
    "sg:province":"Segovia",
    "wof:name":"Ganados Barpe S.l.",
    "wof:placetype":"venue"
},
  "geometry": {"coordinates":[-4.4034199715,41.0745506287],"type":"Point"}
}