{
  "type": "Feature",
  "properties": {
    "iso:country":"ES",
    "sg:address":"Carrer de Pedro I Pons, 9",
    "sg:city":"Barcelona",
    "sg:orig_category":"Asociaciones Y Clubs Deportivos",
    "sg:phone":"+34 932 05 51 11",
    "sg:postcode":"08034",
    "sg:province":"Barcelona",
    "wof:name":"Business Meeting Point S.l.",
    "wof:placetype":"venue"
},
  "geometry": {"coordinates":[2.1224501133,41.3898086548],"type":"Point"}
}