{
  "type": "Feature",
  "properties": {
    "iso:country":"ES",
    "sg:address":"Carrer de Argentina, 15",
    "sg:city":"Coloma",
    "sg:orig_category":"Cervecer\u00cdas",
    "sg:phone":"+34 965 87 32 33",
    "sg:postcode":"03530",
    "sg:province":"Alicante",
    "wof:name":"Kaskade S. L.",
    "wof:placetype":"venue"
},
  "geometry": {"coordinates":[-0.1249789968,38.6157951355],"type":"Point"}
}