{
  "type": "Feature",
  "properties": {
    "iso:country":"ES",
    "sg:address":"Calle de Platon, 46",
    "sg:city":"Merida",
    "sg:orig_category":"Agencias Y Agentes Comerciales, Representantes",
    "sg:phone":"+34 924 30 35 39",
    "sg:postcode":"06800",
    "sg:province":"Badajoz",
    "wof:name":"Costa Lorente Maria Gemma",
    "wof:placetype":"venue"
},
  "geometry": {"coordinates":[-6.3451571465,38.9279975891],"type":"Point"}
}