{
  "type": "Feature",
  "properties": {
    "iso:country":"ES",
    "sg:address":"Calle de Alcantara, 30",
    "sg:city":"Madrid",
    "sg:orig_category":"Electricidad (montaje, Ensamblaje De Componentes)",
    "sg:phone":"+34 914 01 20 69",
    "sg:postcode":"28006",
    "sg:province":"Madrid",
    "wof:name":"Rodriguez Monreal Jose Luis",
    "wof:placetype":"venue"
},
  "geometry": {"coordinates":[-3.673759222,40.4287071228],"type":"Point"}
}