{
  "type": "Feature",
  "properties": {
    "iso:country":"ES",
    "sg:address":"Calle de Eguia General, 18",
    "sg:city":"Bilbao",
    "sg:orig_category":"Fabricaci\u00d3n De Bicicletas, Motocicletas Y Piezas Sueltas",
    "sg:phone":"+34 944 27 08 41",
    "sg:postcode":"48010",
    "sg:province":"Vizcaya",
    "wof:name":"Ramos Pardo Pedro Luis",
    "wof:placetype":"venue"
},
  "geometry": {"coordinates":[-2.9437448978,43.2587852478],"type":"Point"}
}