{
  "type": "Feature",
  "properties": {
    "addr:full":"Calle de Vicente Montuno Morente, 1 Jaen Ja\u00e9n 23001",
    "addr:housenumber":"1;jae\u0301n",
    "addr:postcode":"23001",
    "addr:street":"Calle De Vicente Montuno Morente",
    "iso:country":"ES",
    "sg:address":"Calle de Vicente Montuno Morente, 1",
    "sg:city":"Jaen",
    "sg:orig_category":"Iglesia Cat\u00d3lica",
    "sg:phone":"+34 953 19 03 66",
    "sg:postcode":"23001",
    "sg:province":"Ja\u00e9n",
    "wof:name":"Parroquia El Salvador",
    "wof:placetype":"venue"
},
  "geometry": {"coordinates":[-3.7865240574,37.7663002014],"type":"Point"}
}