{
  "type": "Feature",
  "properties": {
    "addr:full":"Calle de San Gregorio, 22 Pozoblanco C\u00f3rdoba 14400",
    "addr:housenumber":"22",
    "addr:postcode":"14400",
    "addr:street":"Calle De San Gregorio",
    "iso:country":"ES",
    "sg:address":"Calle de San Gregorio, 22",
    "sg:city":"Pozoblanco",
    "sg:orig_category":"Ense\u00d1anza: Comercio, Gesti\u00d3n, Inform\u00c1tica",
    "sg:phone":"+34 957 77 28 60",
    "sg:postcode":"14400",
    "sg:province":"C\u00f3rdoba",
    "wof:name":"Academia Martinez Garcia S.l.",
    "wof:placetype":"venue"
},
  "geometry": {"coordinates":[-4.8522324562,38.3812255859],"type":"Point"}
}