{
  "type": "Feature",
  "properties": {
    "iso:country":"ES",
    "sg:address":"Carrer de Colon, S/n",
    "sg:city":"S. Feliu Guixols",
    "sg:orig_category":"Arquitectos",
    "sg:phone":"+34 972 32 44 87",
    "sg:postcode":"17220",
    "sg:province":"Girona",
    "wof:name":"Gandullo Guerrero Jesus",
    "wof:placetype":"venue"
},
  "geometry": {"coordinates":[3.0366640091,41.78099823],"type":"Point"}
}