{
  "type": "Feature",
  "properties": {
    "iso:country":"ES",
    "sg:address":"Calle de Seixo, S/n",
    "sg:city":"Cangas",
    "sg:orig_category":"Contenedores (mercanc\u00cdas)",
    "sg:phone":"+34 986 30 15 00",
    "sg:postcode":"36940",
    "sg:province":"Pontevedra",
    "wof:name":"Excavaciones Morrazo S.l.",
    "wof:placetype":"venue"
},
  "geometry": {"coordinates":[-8.8184690475,42.2742500305],"type":"Point"}
}