{
  "type": "Feature",
  "properties": {
    "iso:country":"ES",
    "sg:address":"Avda Lopez De Mena, 19",
    "sg:city":"San Pedro Alcantara",
    "sg:orig_category":"Molduras, Junquillos, Listones Y Molduras Perforadas",
    "sg:phone":"+34 952 78 05 89",
    "sg:postcode":"29670",
    "sg:province":"M\u00e1laga",
    "wof:name":"Vega Garcia Maria Isabel",
    "wof:placetype":"venue"
},
  "geometry": {"coordinates":[-4.9870300293,36.4837303162],"type":"Point"}
}