{
  "type": "Feature",
  "properties": {
    "iso:country":"ES",
    "sg:address":"Calle de Real, 65",
    "sg:city":"Rozas De Madrid",
    "sg:orig_category":"Electricidad: Instaladores",
    "sg:phone":"+34 916 37 06 84",
    "sg:postcode":"28230",
    "sg:province":"Madrid",
    "wof:name":"Aparicio Alonso Vicente",
    "wof:placetype":"venue"
},
  "geometry": {"coordinates":[-4.4651985168,40.2623748779],"type":"Point"}
}