{
  "type": "Feature",
  "properties": {
    "iso:country":"ES",
    "sg:address":"Calle de Maestro Alonso, 15",
    "sg:city":"Madrid",
    "sg:orig_category":"Institutos De Belleza",
    "sg:phone":"+34 917 26 45 23",
    "sg:postcode":"28028",
    "sg:province":"Madrid",
    "wof:name":"Francisco Caro Victor",
    "wof:placetype":"venue"
},
  "geometry": {"coordinates":[-3.6640050411,40.4287376404],"type":"Point"}
}