{
  "type": "Feature",
  "properties": {
    "addr:full":"Calle de Gerardo Cordon, 38 Madrid Madrid 28017",
    "addr:housenumber":"38",
    "addr:postcode":"madrid;28017",
    "addr:street":"Calle De Gerardo Cordon",
    "iso:country":"ES",
    "sg:address":"Calle de Gerardo Cordon, 38",
    "sg:city":"Madrid",
    "sg:orig_category":"Peluquer\u00cdas, Peluquer\u00cda Mixta",
    "sg:phone":"+34 914 04 92 69",
    "sg:postcode":"28017",
    "sg:province":"Madrid",
    "wof:name":"Carnicero Martinez Maria Jesus",
    "wof:placetype":"venue"
},
  "geometry": {"coordinates":[-3.6535251141,40.426776886],"type":"Point"}
}