{
  "type": "Feature",
  "properties": {
    "addr:full":"Calle de Mayor, 63 Alcorcon Madrid 28922",
    "addr:housenumber":"63",
    "addr:postcode":"28922",
    "addr:street":"Calle De Mayor",
    "iso:country":"ES",
    "sg:address":"Calle de Mayor, 63",
    "sg:city":"Alcorcon",
    "sg:orig_category":"Cajas De Ahorro",
    "sg:phone":"+34 916 43 40 98",
    "sg:postcode":"28922",
    "sg:province":"Madrid",
    "wof:name":"Caja De Avila",
    "wof:placetype":"venue"
},
  "geometry": {"coordinates":[-3.8275690079,40.3455505371],"type":"Point"}
}