{
  "type": "Feature",
  "properties": {
    "addr:full":"Calle de Alcala Galiano, 77 Alacant Alicante 03012",
    "addr:housenumber":"77",
    "addr:postcode":"03012",
    "addr:street":"Calle De Alcala Galiano",
    "iso:country":"ES",
    "sg:address":"Calle de Alcala Galiano, 77",
    "sg:city":"Alacant",
    "sg:orig_category":"Molinos",
    "sg:phone":"+34 965 24 30 24",
    "sg:postcode":"03012",
    "sg:province":"Alicante",
    "wof:name":"Sala Accesorios Molineria E Industria S.l.",
    "wof:placetype":"venue"
},
  "geometry": {"coordinates":[-0.4842574894,38.3571586609],"type":"Point"}
}