{
  "type": "Feature",
  "properties": {
    "addr:full":"Ptge Olive, 2 Cerdanyola Valles Barcelona 08290",
    "addr:housenumber":"2",
    "addr:postcode":"08290",
    "addr:street":"Ptge Olive;Valles Barcelona",
    "iso:country":"ES",
    "sg:address":"Ptge Olive, 2",
    "sg:city":"Cerdanyola Valles",
    "sg:orig_category":"Peluqueros: De Se\u00d1oras",
    "sg:phone":"+34 936 91 80 47",
    "sg:postcode":"08290",
    "sg:province":"Barcelona",
    "wof:name":"Aguila Pi\u00f1ol Juana",
    "wof:placetype":"venue"
},
  "geometry": {"coordinates":[2.1323504448,41.4819526672],"type":"Point"}
}