{
  "type": "Feature",
  "properties": {
    "addr:full":"Pl Colombia, 1 Mataro Barcelona 08304",
    "addr:housenumber":"1",
    "addr:postcode":"08304",
    "addr:street":"Pl Colombia",
    "iso:country":"ES",
    "sg:address":"Pl Colombia, 1",
    "sg:city":"Mataro",
    "sg:orig_category":"Radiocomunicaciones, Telefon\u00cda M\u00d3vil, Radiomensajer\u00cda: Servicios, Comercializaci\u00d3n",
    "sg:phone":"+34 937 90 17 61",
    "sg:postcode":"08304",
    "sg:province":"Barcelona",
    "wof:name":"Elbair  Abdeslam",
    "wof:placetype":"venue"
},
  "geometry": {"coordinates":[2.4473819733,41.54845047],"type":"Point"}
}