{
  "type": "Feature",
  "properties": {
    "iso:country":"ES",
    "sg:address":"Calle de Parma, 16",
    "sg:city":"Madrid",
    "sg:orig_category":"Internados & Ense\u00d1anza Privada",
    "sg:phone":"+34 913 00 24 31",
    "sg:postcode":"28043",
    "sg:province":"Madrid",
    "wof:name":"Swanson  Margaret Ann",
    "wof:placetype":"venue"
},
  "geometry": {"coordinates":[-3.6493935585,40.4559936523],"type":"Point"}
}