{
  "type": "Feature",
  "properties": {
    "iso:country":"ES",
    "sg:address":"Calle de Bego\u00d1a, 8",
    "sg:city":"Coslada",
    "sg:orig_category":"Laboratorios Y Trabajos De Fotograf\u00cda, V\u00cddeo Y Cine",
    "sg:phone":"+34 916 69 35 48",
    "sg:postcode":"28820",
    "sg:province":"Madrid",
    "wof:name":"Fotonet S.l.",
    "wof:placetype":"venue"
},
  "geometry": {"coordinates":[-3.5672206879,40.4257698059],"type":"Point"}
}