{
  "type": "Feature",
  "properties": {
    "addr:full":"Calle de Ruise\u00d1or, 7 Granada Granada 18014",
    "addr:housenumber":"7",
    "addr:postcode":"18014",
    "addr:street":"Calle De Ruisen\u0303Or",
    "iso:country":"ES",
    "sg:address":"Calle de Ruise\u00d1or, 7",
    "sg:city":"Granada",
    "sg:orig_category":"Tapones Y Art\u00cdculos De Corcho",
    "sg:phone":"+34 958 28 25 52",
    "sg:postcode":"18014",
    "sg:province":"Granada",
    "wof:name":"Rodriguez Garcia Manuel",
    "wof:placetype":"venue"
},
  "geometry": {"coordinates":[-3.6094698906,37.1855239868],"type":"Point"}
}