{
  "type": "Feature",
  "properties": {
    "addr:full":"Calle de San Bartolome Kalea, 8 Errenteria Vizcaya 48300",
    "addr:housenumber":"8",
    "addr:postcode":"48300",
    "addr:street":"Calle De San Bartolome Kalea",
    "iso:country":"ES",
    "sg:address":"Calle de San Bartolome Kalea, 8",
    "sg:city":"Errenteria",
    "sg:orig_category":"Molduras, Junquillos, Listones Y Molduras Perforadas",
    "sg:phone":"+34 946 25 37 47",
    "sg:postcode":"48300",
    "sg:province":"Vizcaya",
    "wof:name":"Larra\u00f1aga Orbe Francisco Javier",
    "wof:placetype":"venue"
},
  "geometry": {"coordinates":[-2.6761341095,43.3170585632],"type":"Point"}
}