{
  "type": "Feature",
  "properties": {
    "iso:country":"ES",
    "sg:address":"Pelai, 1",
    "sg:city":"Lliria",
    "sg:orig_category":"Centros De Coordinaci\u00d3n",
    "sg:phone":"+34 962 78 11 47",
    "sg:postcode":"46160",
    "sg:province":"Valencia",
    "wof:name":"Barber Gestoria-asesoria S.l.",
    "wof:placetype":"venue"
},
  "geometry": {"coordinates":[-0.5952839851,39.6247406006],"type":"Point"}
}