{
  "type": "Feature",
  "properties": {
    "addr:full":"Calle de Flores (de Las), 9 Pozuelo De Alarcon Madrid 28223",
    "addr:housenumber":"9",
    "addr:postcode":"28223",
    "addr:street":"Calle De Flores De Las",
    "iso:country":"ES",
    "sg:address":"Calle de Flores (de Las), 9",
    "sg:city":"Pozuelo De Alarcon",
    "sg:orig_category":"Escaneado",
    "sg:phone":"+34 913 51 36 77",
    "sg:postcode":"28223",
    "sg:province":"Madrid",
    "sg:website":"www.cipinformatica.com",
    "wof:name":"Centro Informatico Pozuelo S.l.",
    "wof:placetype":"venue"
},
  "geometry": {"coordinates":[-3.8138930798,40.435836792],"type":"Point"}
}