{
  "type": "Feature",
  "properties": {
    "addr:full":"Calle de Obispo Perez Caceres, 17 Candelaria Santa Cruz De Tenerife 38530",
    "addr:housenumber":"17",
    "addr:postcode":"38530",
    "addr:street":"Calle De Obispo Perez Caceres",
    "iso:country":"ES",
    "sg:address":"Calle de Obispo Perez Caceres, 17",
    "sg:city":"Candelaria",
    "sg:orig_category":"Bazares, Art\u00cdculos De Limpieza Y De Cocina (al Por Menor)",
    "sg:phone":"+34 922 50 44 18",
    "sg:postcode":"38530",
    "sg:province":"Santa Cruz De Tenerife",
    "wof:name":"Garcia Hidalgo Francisco",
    "wof:placetype":"venue"
},
  "geometry": {"coordinates":[-16.3700942993,28.3529052734],"type":"Point"}
}