{
  "type": "Feature",
  "properties": {
    "iso:country":"ES",
    "sg:address":"Calle de Francisco Grandmontagne, 28",
    "sg:city":"Burgos",
    "sg:orig_category":"Bancos",
    "sg:phone":"+34 947 24 40 99",
    "sg:postcode":"09007",
    "sg:province":"Burgos",
    "wof:name":"Bankinter S.a.",
    "wof:placetype":"venue"
},
  "geometry": {"coordinates":[-3.6702620983,42.3497505188],"type":"Point"}
}