{
  "type": "Feature",
  "properties": {
    "addr:full":"Calle de Roma, 6 Sagunt Valencia 46500",
    "addr:housenumber":"6",
    "addr:postcode":"46500",
    "addr:street":"Calle De Roma",
    "iso:country":"ES",
    "sg:address":"Calle de Roma, 6",
    "sg:city":"Sagunt",
    "sg:orig_category":"Farmacias",
    "sg:phone":"+34 962 66 20 04",
    "sg:postcode":"46500",
    "sg:province":"Valencia",
    "wof:name":"Martinez Serrano Blanca",
    "wof:placetype":"venue"
},
  "geometry": {"coordinates":[-0.2817470133,39.6815719604],"type":"Point"}
}