{
  "type": "Feature",
  "properties": {
    "addr:full":"Carrer de Mila I Fontanals, 57 Santa Coloma De Gramenet Barcelona 08922",
    "addr:housenumber":"57",
    "addr:postcode":"08922",
    "addr:street":"Carrer De Mila I Fontanals",
    "iso:country":"ES",
    "sg:address":"Carrer de Mila I Fontanals, 57",
    "sg:city":"Santa Coloma De Gramenet",
    "sg:orig_category":"Farmacias (repartici\u00d3n Y Al Por Mayor)",
    "sg:phone":"+34 934 66 54 40",
    "sg:postcode":"08922",
    "sg:province":"Barcelona",
    "wof:name":"Distribuidora Farmaceutica Colomenca S.l.",
    "wof:placetype":"venue"
},
  "geometry": {"coordinates":[2.2159230709,41.4499473572],"type":"Point"}
}