{
  "type": "Feature",
  "properties": {
    "iso:country":"ES",
    "sg:address":"Ctra Pamplona, Km. 0080,5",
    "sg:city":"Viana",
    "sg:orig_category":"Producci\u00d3n De Champi\u00d1ones",
    "sg:phone":"+34 948 64 51 31",
    "sg:postcode":"31230",
    "sg:province":"Navarra",
    "wof:name":"Garcia De Jalon Sanz Ricardo",
    "wof:placetype":"venue"
},
  "geometry": {"coordinates":[-2.3658239841,42.5151443481],"type":"Point"}
}