{
  "type": "Feature",
  "properties": {
    "addr:full":"Carrer de Bellesguard (de), 10 Montornes Centre Barcelona 08170",
    "addr:housenumber":"10",
    "addr:postcode":"08170",
    "addr:street":"Carrer De Bellesguard De;Centre Barcelona",
    "iso:country":"ES",
    "sg:address":"Carrer de Bellesguard (de), 10",
    "sg:city":"Montornes Centre",
    "sg:orig_category":"Empresarios",
    "sg:phone":"+34 935 68 14 96",
    "sg:postcode":"08170",
    "sg:province":"Barcelona",
    "wof:name":"Taberner Vi\u00f1allonga Jaime",
    "wof:placetype":"venue"
},
  "geometry": {"coordinates":[2.2648620605,41.5388069153],"type":"Point"}
}