{
  "type": "Feature",
  "properties": {
    "addr:full":"Mu\u00f1oz Olive, 17 Herrera Sevilla 41567",
    "addr:housenumber":"mun\u0303oz;17",
    "addr:postcode":"41567",
    "addr:street":"Olive",
    "iso:country":"ES",
    "sg:address":"Mu\u00f1oz Olive, 17",
    "sg:city":"Herrera",
    "sg:orig_category":"Supermercados Y Hipermercados",
    "sg:phone":"+34 954 01 35 52",
    "sg:postcode":"41567",
    "sg:province":"Sevilla",
    "wof:name":"Jurado Nu\u00f1ez Maria Jesus",
    "wof:placetype":"venue"
},
  "geometry": {"coordinates":[-4.8512010574,37.3655891418],"type":"Point"}
}