{
  "type": "Feature",
  "properties": {
    "addr:full":"Monteagudo, 12 Novelda Alicante 03660",
    "addr:housenumber":"12",
    "addr:postcode":"03660",
    "addr:street":"Monteagudo",
    "iso:country":"ES",
    "sg:address":"Monteagudo, 12",
    "sg:city":"Novelda",
    "sg:orig_category":"Persianas Interiores, Exteriores",
    "sg:phone":"+34 965 60 25 45",
    "sg:postcode":"03660",
    "sg:province":"Alicante",
    "wof:name":"Ortega Perez Manuel",
    "wof:placetype":"venue"
},
  "geometry": {"coordinates":[-0.7718489766,38.389251709],"type":"Point"}
}