{
  "type": "Feature",
  "properties": {
    "addr:full":"San Lorentzo Auzoa, 12 Ikaztegieta Guip\u00f9zcoa 20267",
    "addr:housenumber":"12",
    "addr:postcode":"20267",
    "addr:street":"San Lorentzo Auzoa;Guipu\u0300Zcoa",
    "iso:country":"ES",
    "sg:address":"San Lorentzo Auzoa, 12",
    "sg:city":"Ikaztegieta",
    "sg:orig_category":"Obras Y Organismos Sociales",
    "sg:phone":"+34 943 65 30 03",
    "sg:postcode":"20267",
    "sg:province":"Guip\u00f9zcoa",
    "wof:name":"Asociacion Guipuzcoana Pro Subnormales",
    "wof:placetype":"venue"
},
  "geometry": {"coordinates":[-2.1247370243,43.0944023132],"type":"Point"}
}