{
  "type": "Feature",
  "properties": {
    "addr:full":"Carrer de Puigmal, 4 Poligono Barcelona 08213",
    "addr:housenumber":"4",
    "addr:postcode":"08213",
    "addr:street":"Carrer De Puigmal;Barcelona",
    "iso:country":"ES",
    "sg:address":"Carrer de Puigmal, 4",
    "sg:city":"Poligono",
    "sg:orig_category":"Contenedores (mercanc\u00cdas)",
    "sg:phone":"+34 937 13 03 63",
    "sg:postcode":"08213",
    "sg:province":"Barcelona",
    "wof:name":"Rodriguez Cabrera Jose",
    "wof:placetype":"venue"
},
  "geometry": {"coordinates":[2.1571440697,41.5534934998],"type":"Point"}
}