{
  "type": "Feature",
  "properties": {
    "addr:full":"Carrer de Gongora, 35 Barcelona Barcelona 08042",
    "addr:housenumber":"35",
    "addr:postcode":"08042",
    "addr:street":"Carrer De Gongora",
    "iso:country":"ES",
    "sg:address":"Carrer de Gongora, 35",
    "sg:city":"Barcelona",
    "sg:orig_category":"Molduras, Junquillos, Listones Y Molduras Perforadas",
    "sg:phone":"+34 933 50 66 35",
    "sg:postcode":"08042",
    "sg:province":"Barcelona",
    "wof:name":"Rodriguez Lopez Antonio",
    "wof:placetype":"venue"
},
  "geometry": {"coordinates":[2.1755568981,41.4439277649],"type":"Point"}
}