{
  "type": "Feature",
  "properties": {
    "iso:country":"ES",
    "sg:address":"Avda Francisco Javier Sauquillo, 8",
    "sg:city":"Fuenlabrada",
    "sg:orig_category":"Reparaciones Y Remolcado De Veh\u00cdculos",
    "sg:phone":"+34 916 06 31 38",
    "sg:postcode":"28944",
    "sg:province":"Madrid",
    "wof:name":"Gruas Maxi,s.l.",
    "wof:placetype":"venue"
},
  "geometry": {"coordinates":[-3.786493063,40.2821960449],"type":"Point"}
}