{
  "type": "Feature",
  "properties": {
    "addr:full":"Carr Carme, 127 Girona Girona 17004",
    "addr:housenumber":"127",
    "addr:postcode":"17004",
    "addr:street":"Carr Carme",
    "iso:country":"ES",
    "sg:address":"Carr Carme, 127",
    "sg:city":"Girona",
    "sg:orig_category":"Farmacias",
    "sg:phone":"+34 972 20 88 09",
    "sg:postcode":"17004",
    "sg:province":"Girona",
    "wof:name":"Borrell Bousigue Maria",
    "wof:placetype":"venue"
},
  "geometry": {"coordinates":[2.8243649006,41.9767150879],"type":"Point"}
}