{
  "type": "Feature",
  "properties": {
    "addr:full":"Av D Jose Alarcon(ord Bahia), 82 Puerto Mazarron Murcia 30860",
    "addr:postcode":"82;30860",
    "addr:street":"Av D Jose Alarcon",
    "iso:country":"ES",
    "sg:address":"Av D Jose Alarcon(ord Bahia), 82",
    "sg:city":"Puerto Mazarron",
    "sg:orig_category":"Energ\u00cda Solar Y Nuevas Energ\u00cdas (equipo, Estudios)",
    "sg:phone":"+34 968 15 36 66",
    "sg:postcode":"30860",
    "sg:province":"Murcia",
    "wof:name":"Yepes Martin-portugues Concepcion",
    "wof:placetype":"venue"
},
  "geometry": {"coordinates":[-1.3136693239,37.5990715027],"type":"Point"}
}