{
  "type": "Feature",
  "properties": {
    "iso:country":"ES",
    "sg:address":"Calle de Calvo Sotelo, 6",
    "sg:city":"Llanos De Aridane",
    "sg:orig_category":"Ropa Para Se\u00d1oras (al Por Menor)",
    "sg:phone":"+34 922 46 01 26",
    "sg:postcode":"38760",
    "sg:province":"Santa Cruz De Tenerife",
    "wof:name":"Martin Gonzalez Angeles Yolis",
    "wof:placetype":"venue"
},
  "geometry": {"coordinates":[-17.9119300842,28.6588897705],"type":"Point"}
}