{
  "type": "Feature",
  "properties": {
    "addr:full":"Avda Manuel Rivera, 7 Palencia Palencia 34002",
    "addr:housenumber":"7",
    "addr:postcode":"34002",
    "addr:street":"Avda Manuel Rivera",
    "iso:country":"ES",
    "sg:address":"Avda Manuel Rivera, 7",
    "sg:city":"Palencia",
    "sg:orig_category":"Arquitectos",
    "sg:phone":"+34 979 72 06 55",
    "sg:postcode":"34002",
    "sg:province":"Palencia",
    "wof:name":"Junco Almodovar Carlos",
    "wof:placetype":"venue"
},
  "geometry": {"coordinates":[-4.5274891853,42.0089302063],"type":"Point"}
}