{
  "type": "Feature",
  "properties": {
    "iso:country":"ES",
    "sg:address":"Calle de Trujillo (de), 4",
    "sg:city":"Boadilla Del Monte",
    "sg:orig_category":"Farmacias",
    "sg:phone":"+34 916 33 41 17",
    "sg:postcode":"28660",
    "sg:province":"Madrid",
    "wof:name":"Terce\u00f1o Gonzalez Rosario",
    "wof:placetype":"venue"
},
  "geometry": {"coordinates":[-3.8832099438,40.4059677124],"type":"Point"}
}