{
  "type": "Feature",
  "properties": {
    "addr:full":"Av Comte De Sallent, 1 Palma Islas Baleares 07003",
    "addr:housenumber":"1",
    "addr:postcode":"07003",
    "iso:country":"ES",
    "sg:address":"Av Comte De Sallent, 1",
    "sg:city":"Palma",
    "sg:orig_category":"Cajas De Ahorro",
    "sg:phone":"+34 971 42 51 30",
    "sg:postcode":"07003",
    "sg:province":"Islas Baleares",
    "sg:website":"www.ibercaja.es",
    "wof:name":"Caja De Ahorros Y Monte De Piedad De Zaragoza Aragon Y Rioja",
    "wof:placetype":"venue"
},
  "geometry": {"coordinates":[2.6521658897,39.5774345398],"type":"Point"}
}