{
  "type": "Feature",
  "properties": {
    "addr:full":"Carr Novel.lista Blasco Iba\u00d1ez (del), 9 Lliria Valencia 46160",
    "addr:housenumber":"9",
    "addr:postcode":"46160",
    "addr:street":"Carr Novel.Lista Blasco Iban\u0303Ez Del",
    "iso:country":"ES",
    "sg:address":"Carr Novel.lista Blasco Iba\u00d1ez (del), 9",
    "sg:city":"Lliria",
    "sg:orig_category":"Artes Gr\u00c1ficas, Artes Pl\u00c1sticas (curso)",
    "sg:phone":"+34 962 78 22 45",
    "sg:postcode":"46160",
    "sg:province":"Valencia",
    "wof:name":"Pawlak  Veronica",
    "wof:placetype":"venue"
},
  "geometry": {"coordinates":[-0.5952839851,39.6247406006],"type":"Point"}
}