{
  "type": "Feature",
  "properties": {
    "addr:full":"Calle de Carolina Paino, 8 Madrid Madrid 28025",
    "addr:housenumber":"8",
    "addr:postcode":"madrid;28025",
    "addr:street":"Calle De Carolina Paino",
    "iso:country":"ES",
    "sg:address":"Calle de Carolina Paino, 8",
    "sg:city":"Madrid",
    "sg:orig_category":"Venta, Alquiler De Toldos",
    "sg:phone":"+34 914 62 87 11",
    "sg:postcode":"28025",
    "sg:province":"Madrid",
    "sg:website":"www.comercialcubiertasmu\u00f1oz.es",
    "wof:name":"Cubiertas Mu\u00d1oz S.a.",
    "wof:placetype":"venue"
},
  "geometry": {"coordinates":[-3.7414441109,40.3845367432],"type":"Point"}
}