{
  "type": "Feature",
  "properties": {
    "iso:country":"ES",
    "sg:address":"Carretera De Almaluez, S/n",
    "sg:city":"Utrilla",
    "sg:orig_category":"Cr\u00cda De Animales",
    "sg:phone":"+34 975 32 30 52",
    "sg:postcode":"42258",
    "sg:province":"Soria",
    "wof:name":"Cooperativa Santa Ana",
    "wof:placetype":"venue"
},
  "geometry": {"coordinates":[-2.2698140144,41.289150238],"type":"Point"}
}