{
  "type": "Feature",
  "properties": {
    "addr:full":"Pol Ind Tartessos, 74 S. Juan Puerto Huelva 21610",
    "addr:housenumber":"74",
    "addr:postcode":"21610",
    "addr:street":"Tartessos;S. Juan Puerto",
    "iso:country":"ES",
    "sg:address":"Pol Ind Tartessos, 74",
    "sg:city":"S. Juan Puerto",
    "sg:orig_category":"Andamiajes Y Escaleras De Mano (fabricaci\u00d3n, Al Por Mayor)",
    "sg:phone":"+34 959 54 02 31",
    "sg:postcode":"21610",
    "sg:province":"Huelva",
    "sg:website":"www.resaq.com",
    "wof:name":"Andamios Resasur S.l.",
    "wof:placetype":"venue"
},
  "geometry": {"coordinates":[-6.9495549202,37.2570991516],"type":"Point"}
}