{
  "type": "Feature",
  "properties": {
    "addr:full":"Ctra Ecija-herrera, Km. 0027,0 Ecija Sevilla 41400",
    "addr:postcode":"41400",
    "addr:street":"Ctra Ecija-Herrera Km. 0027,0",
    "iso:country":"ES",
    "sg:address":"Ctra Ecija-herrera, Km. 0027,0",
    "sg:city":"Ecija",
    "sg:orig_category":"Ense\u00d1anza, Formaci\u00d3n Profesional: Aprendizaje",
    "sg:phone":"+34 954 83 39 10",
    "sg:postcode":"41400",
    "sg:province":"Sevilla",
    "wof:name":"Fondo De Explotacion De Los Servicios De Cria Caballar Y Remonta",
    "wof:placetype":"venue"
},
  "geometry": {"coordinates":[-5.0782690048,37.5395584106],"type":"Point"}
}