{
  "type": "Feature",
  "properties": {
    "iso:country":"ES",
    "sg:address":"Grup Ibaizabal Auzunea, 4",
    "sg:city":"Durango",
    "sg:orig_category":"Agencias Y Asesores De Publicidad",
    "sg:phone":"+34 946 81 83 40",
    "sg:postcode":"48200",
    "sg:province":"Vizcaya",
    "wof:name":"Tromperri Banaketak Sll",
    "wof:placetype":"venue"
},
  "geometry": {"coordinates":[-2.6294579506,43.1700897217],"type":"Point"}
}