{
  "type": "Feature",
  "properties": {
    "iso:country":"ES",
    "sg:address":"Calle de Hospital, 4",
    "sg:city":"Molina",
    "sg:orig_category":"Electricidad: Instaladores",
    "sg:phone":"+34 949 83 12 89",
    "sg:postcode":"19300",
    "sg:province":"Guadalajara",
    "wof:name":"Tecmo Instalaciones Electricas S.l.",
    "wof:placetype":"venue"
},
  "geometry": {"coordinates":[-1.8902560472,40.842956543],"type":"Point"}
}