{
  "type": "Feature",
  "properties": {
    "addr:full":"Calle de San Juan, 1 Coru\u00d1a La Coru\u00f1a 15001",
    "addr:housenumber":"1",
    "addr:postcode":"15001",
    "addr:street":"Calle De San Juan;La Corun\u0303A",
    "iso:country":"ES",
    "sg:address":"Calle de San Juan, 1",
    "sg:city":"Coru\u00d1a",
    "sg:orig_category":"Producci\u00d3n De Abonos Y De Fertilizantes",
    "sg:phone":"+34 981 20 41 72",
    "sg:postcode":"15001",
    "sg:province":"La Coru\u00f1a",
    "wof:name":"Dadama S.l.",
    "wof:placetype":"venue"
},
  "geometry": {"coordinates":[-8.3966159821,43.3738136292],"type":"Point"}
}