{
  "type": "Feature",
  "properties": {
    "iso:country":"ES",
    "sg:address":"Carrer de Emili Darder,batle, 19",
    "sg:city":"Palma",
    "sg:orig_category":"Florister\u00cdas",
    "sg:phone":"+34 971 73 45 77",
    "sg:postcode":"07013",
    "sg:province":"Islas Baleares",
    "wof:name":"Miquel Pons Antonia",
    "wof:placetype":"venue"
},
  "geometry": {"coordinates":[2.6394760609,39.5776901245],"type":"Point"}
}