{
  "type": "Feature",
  "properties": {
    "iso:country":"ES",
    "sg:address":"Calle de Eras Del Cristo, 8",
    "sg:city":"Pe\u00f1afiel",
    "sg:orig_category":"Inmobiliaria (agencias)",
    "sg:phone":"+34 983 88 02 58",
    "sg:postcode":"47300",
    "sg:province":"Valladolid",
    "wof:name":"Alvs S.a.",
    "wof:placetype":"venue"
},
  "geometry": {"coordinates":[-4.1291208267,41.5979576111],"type":"Point"}
}