{
  "type": "Feature",
  "properties": {
    "addr:full":"Rond Fonti\u00d1as (das), 215 Lugo Lugo 27002",
    "addr:housenumber":"215",
    "addr:postcode":"27002",
    "iso:country":"ES",
    "sg:address":"Rond Fonti\u00d1as (das), 215",
    "sg:city":"Lugo",
    "sg:orig_category":"Deportes Y Ocio: Art\u00cdculos Y Ropas (al Por Menor Y Accesorios)",
    "sg:phone":"+34 982 22 51 86",
    "sg:postcode":"27002",
    "sg:province":"Lugo",
    "wof:name":"Lopez Lopez Alberto",
    "wof:placetype":"venue"
},
  "geometry": {"coordinates":[-7.5301399231,42.9997177124],"type":"Point"}
}