{
  "type": "Feature",
  "properties": {
    "iso:country":"ES",
    "sg:address":"Calle de Hermosilla, 147",
    "sg:city":"Madrid",
    "sg:orig_category":"Fotograf\u00cda Y Cine: Aparatos, Pel\u00cdculas Y Accesorios (al Por Menor)",
    "sg:phone":"+34 913 56 72 14",
    "sg:postcode":"28028",
    "sg:province":"Madrid",
    "wof:name":"Tecnica Electronica S. A.",
    "wof:placetype":"venue"
},
  "geometry": {"coordinates":[-3.6673440933,40.4256210327],"type":"Point"}
}