{
  "type": "Feature",
  "properties": {
    "addr:full":"Calle de Monasterio De Poblet, 30 Zaragoza Zaragoza 50013",
    "addr:housenumber":"30",
    "addr:postcode":"50013",
    "addr:street":"Calle De Monasterio De Poblet",
    "iso:country":"ES",
    "sg:address":"Calle de Monasterio De Poblet, 30",
    "sg:city":"Zaragoza",
    "sg:orig_category":"M\u00c9dicos: Naturistas",
    "sg:phone":"+34 976 42 85 56",
    "sg:postcode":"50013",
    "sg:province":"Zaragoza",
    "wof:name":"Pierna Bueso Sara",
    "wof:placetype":"venue"
},
  "geometry": {"coordinates":[-0.8700227737,41.6427116394],"type":"Point"}
}