{
  "type": "Feature",
  "properties": {
    "iso:country":"ES",
    "sg:address":"Carrer de Carolines, 28",
    "sg:city":"Barcelona",
    "sg:orig_category":"Molduras, Junquillos, Listones Y Molduras Perforadas",
    "sg:phone":"+34 932 37 43 10",
    "sg:postcode":"08012",
    "sg:province":"Barcelona",
    "wof:name":"Lozano Gomez Isabel",
    "wof:placetype":"venue"
},
  "geometry": {"coordinates":[2.1507248878,41.4034614563],"type":"Point"}
}