{
  "type": "Feature",
  "properties": {
    "iso:country":"ES",
    "sg:address":"Avda Federico Soto, 1",
    "sg:city":"Alacant",
    "sg:orig_category":"Agencias De Viajes",
    "sg:phone":"+34 965 14 05 11",
    "sg:postcode":"03003",
    "sg:province":"Alicante",
    "sg:website":"www.viajeselcorteingles.es",
    "wof:name":"Viajes El Corte Ingles S.a.",
    "wof:placetype":"venue"
},
  "geometry": {"coordinates":[-0.4892559946,38.3438262939],"type":"Point"}
}