{
  "type": "Feature",
  "properties": {
    "addr:full":"Calle de Reina Maria Cristina, 17 Montijo Badajoz 06480",
    "addr:housenumber":"17",
    "addr:postcode":"06480",
    "addr:street":"Calle De Reina Maria Cristina",
    "iso:country":"ES",
    "sg:address":"Calle de Reina Maria Cristina, 17",
    "sg:city":"Montijo",
    "sg:orig_category":"Cerrajer\u00cda, Ferrallista",
    "sg:phone":"+34 924 45 21 64",
    "sg:postcode":"06480",
    "sg:province":"Badajoz",
    "wof:name":"Gragera Almirante Vicente",
    "wof:placetype":"venue"
},
  "geometry": {"coordinates":[-6.6107540131,38.9082183838],"type":"Point"}
}