{
  "type": "Feature",
  "properties": {
    "addr:full":"Avda Canarias, 195 Vecindario Las Palmas 35110",
    "addr:housenumber":"195",
    "addr:postcode":"35110",
    "addr:street":"Avda Canarias;Palmas",
    "iso:country":"ES",
    "sg:address":"Avda Canarias, 195",
    "sg:city":"Vecindario",
    "sg:orig_category":"Cajas De Ahorro",
    "sg:phone":"+34 928 79 38 60",
    "sg:postcode":"35110",
    "sg:province":"Las Palmas",
    "wof:name":"Caja General De Ahorros De Canarias",
    "wof:placetype":"venue"
},
  "geometry": {"coordinates":[-15.4408693314,27.8513793945],"type":"Point"}
}