{
  "type": "Feature",
  "properties": {
    "addr:full":"Mendigorria, 22 Iru\u00f1a Navarra 31015",
    "addr:housenumber":"22",
    "addr:postcode":"31015",
    "addr:street":"Mendigorria",
    "iso:country":"ES",
    "sg:address":"Mendigorria, 22",
    "sg:city":"Iru\u00f1a",
    "sg:orig_category":"Peluqueros: De Se\u00d1oras",
    "sg:phone":"+34 948 12 77 29",
    "sg:postcode":"31015",
    "sg:province":"Navarra",
    "wof:name":"Hijosa Tollar Milagros",
    "wof:placetype":"venue"
},
  "geometry": {"coordinates":[-1.6303224564,42.824924469],"type":"Point"}
}