{
  "type": "Feature",
  "properties": {
    "addr:full":"Plaz Comandante Ramon Franco, 1 Palmas De Gran Canaria Las Palmas 35007",
    "addr:housenumber":"1",
    "addr:postcode":"35007",
    "addr:street":"Plaz;Ramon Franco",
    "iso:country":"ES",
    "sg:address":"Plaz Comandante Ramon Franco, 1",
    "sg:city":"Palmas De Gran Canaria",
    "sg:orig_category":"Molduras, Junquillos, Listones Y Molduras Perforadas",
    "sg:phone":"+34 928 22 08 99",
    "sg:postcode":"35007",
    "sg:province":"Las Palmas",
    "wof:name":"De La Osada Bordon Alejandro",
    "wof:placetype":"venue"
},
  "geometry": {"coordinates":[-15.4311704636,28.1380500793],"type":"Point"}
}