{
  "type": "Feature",
  "properties": {
    "iso:country":"ES",
    "sg:address":"Av Generalitat, 16",
    "sg:city":"Santa Coloma De Gramenet",
    "sg:orig_category":"Comercios E Industrias (cesi\u00d3n Y Reactivaci\u00d3n)",
    "sg:phone":"+34 934 66 03 74",
    "sg:postcode":"08922",
    "sg:province":"Barcelona",
    "wof:name":"Pobes Layunta David",
    "wof:placetype":"venue"
},
  "geometry": {"coordinates":[2.2096281052,41.4503250122],"type":"Point"}
}