{
  "type": "Feature",
  "properties": {
    "addr:full":"Calle de Gerardo Valdes, 20 Torre Esteban Hambran Toledo 45920",
    "addr:housenumber":"20",
    "addr:postcode":"45920",
    "addr:street":"Calle De Gerardo Valdes",
    "iso:country":"ES",
    "sg:address":"Calle de Gerardo Valdes, 20",
    "sg:city":"Torre Esteban Hambran",
    "sg:orig_category":"Peluquer\u00cdas, Peluquer\u00cda Mixta",
    "sg:phone":"+34 925 79 53 56",
    "sg:postcode":"45920",
    "sg:province":"Toledo",
    "wof:name":"Izquierdo Gutierrez Maria Dolores",
    "wof:placetype":"venue"
},
  "geometry": {"coordinates":[-4.2158298492,40.1685333252],"type":"Point"}
}