{
  "type": "Feature",
  "properties": {
    "iso:country":"ES",
    "sg:address":"Calle de Francisco Santos, 2",
    "sg:city":"Madrid",
    "sg:orig_category":"Material Y Suministros Para Veterinarios",
    "sg:phone":"+34 913 56 67 31",
    "sg:postcode":"28028",
    "sg:province":"Madrid",
    "wof:name":"Prolavi S.l.",
    "wof:placetype":"venue"
},
  "geometry": {"coordinates":[-3.6658329964,40.4326934814],"type":"Point"}
}