{
  "type": "Feature",
  "properties": {
    "iso:country":"ES",
    "sg:address":"Pol Ind Morea, S/n",
    "sg:city":"Beriain",
    "sg:orig_category":"Restaurantes",
    "sg:phone":"+34 948 31 82 53",
    "sg:postcode":"31191",
    "sg:province":"Navarra",
    "wof:name":"Bar Restaurante Salazar S.l.",
    "wof:placetype":"venue"
},
  "geometry": {"coordinates":[-1.6518089771,42.7533912659],"type":"Point"}
}