{
  "type": "Feature",
  "properties": {
    "addr:full":"Rego Da Moa, S/n Barallobre A Coru\u00f1a 15528",
    "addr:housenumber":"s",
    "addr:postcode":"15528",
    "addr:street":"/ N;Corun\u0303A",
    "iso:country":"ES",
    "sg:address":"Rego Da Moa, S/n",
    "sg:city":"Barallobre",
    "sg:orig_category":"Revestimientos Diversos",
    "sg:phone":"+34 981 34 21 00",
    "sg:postcode":"15528",
    "sg:province":"A Coru\u00f1a",
    "wof:name":"Teimper S.a.",
    "wof:placetype":"venue"
},
  "geometry": {"coordinates":[-8.1702842712,43.460899353],"type":"Point"}
}