{
  "type": "Feature",
  "properties": {
    "iso:country":"ES",
    "sg:address":"Calle de Blanca Luna, 19",
    "sg:city":"Madrid",
    "sg:orig_category":"Financiaci\u00d3n Y Cr\u00c9ditos",
    "sg:phone":"+34 913 72 10 86",
    "sg:postcode":"28034",
    "sg:province":"Madrid",
    "sg:website":"www.asociacionmercadosfinancieros.com",
    "wof:name":"Villanueva Garcia Manuel",
    "wof:placetype":"venue"
},
  "geometry": {"coordinates":[-3.6674389839,40.3889198303],"type":"Point"}
}