{
  "type": "Feature",
  "properties": {
    "addr:full":"Calle de Andra Mari, 35 Larrabetzu Vizcaya 48195",
    "addr:housenumber":"35",
    "addr:postcode":"48195",
    "addr:street":"Calle De Andra Mari",
    "iso:country":"ES",
    "sg:address":"Calle de Andra Mari, 35",
    "sg:city":"Larrabetzu",
    "sg:orig_category":"Transporte En General",
    "sg:phone":"+34 944 82 02 67",
    "sg:postcode":"48195",
    "sg:province":"Vizcaya",
    "wof:name":"Eroski Sociedad Cooperativa",
    "wof:placetype":"venue"
},
  "geometry": {"coordinates":[-2.7963132858,43.2587242126],"type":"Point"}
}