{
  "type": "Feature",
  "properties": {
    "iso:country":"ES",
    "sg:address":"Calle de Cecilio Pla, 5",
    "sg:city":"Valencia",
    "sg:orig_category":"Alumbrados",
    "sg:phone":"+34 963 65 83 06",
    "sg:postcode":"46019",
    "sg:province":"Valencia",
    "wof:name":"Balanza Cano Vicente Francisco",
    "wof:placetype":"venue"
},
  "geometry": {"coordinates":[-0.3677740097,39.4987983704],"type":"Point"}
}