{
  "type": "Feature",
  "properties": {
    "iso:country":"ES",
    "sg:address":"Carrer de Arago, 359",
    "sg:city":"Barcelona",
    "sg:orig_category":"Bisuteros (fabricaci\u00d3n, Al Por Mayor)",
    "sg:phone":"+34 934 59 22 41",
    "sg:postcode":"08009",
    "sg:province":"Barcelona",
    "wof:name":"Altimir Lluell Arturo",
    "wof:placetype":"venue"
},
  "geometry": {"coordinates":[2.1716806889,41.3973083496],"type":"Point"}
}