{
  "type": "Feature",
  "properties": {
    "iso:country":"ES",
    "sg:address":"Rua Rio Narla, 38",
    "sg:city":"Lugo",
    "sg:orig_category":"Caf\u00c9s, Bares, Cervecer\u00cdas",
    "sg:phone":"+34 982 24 47 49",
    "sg:postcode":"27003",
    "sg:province":"Lugo",
    "wof:name":"Teldelugo Comunicacion S.l.",
    "wof:placetype":"venue"
},
  "geometry": {"coordinates":[-7.561270237,43.0226287842],"type":"Point"}
}