{
  "type": "Feature",
  "properties": {
    "iso:country":"ES",
    "sg:address":"Carr Ramirez Cameno, 9",
    "sg:city":"Xativa",
    "sg:orig_category":"Animales (al Por Menor)",
    "sg:phone":"+34 962 27 50 22",
    "sg:postcode":"46800",
    "sg:province":"Valencia",
    "wof:name":"Sala Caballero Nieves",
    "wof:placetype":"venue"
},
  "geometry": {"coordinates":[-0.5150600076,38.9929237366],"type":"Point"}
}