{
  "type": "Feature",
  "properties": {
    "addr:full":"Plaz Luca De Tena, 4 Madrid Madrid 28045",
    "addr:housenumber":"4",
    "addr:postcode":"28045",
    "addr:street":"Plaz Luca De Tena",
    "iso:country":"ES",
    "sg:address":"Plaz Luca De Tena, 4",
    "sg:city":"Madrid",
    "sg:orig_category":"Lencer\u00cda Femenina, Corseter\u00cda, Trajes De Ba\u00d1o (al Por Menor)",
    "sg:phone":"+34 915 28 07 17",
    "sg:postcode":"28045",
    "sg:province":"Madrid",
    "wof:name":"Victoria Sahagun Jose Isaac",
    "wof:placetype":"venue"
},
  "geometry": {"coordinates":[-3.6930770874,40.402015686],"type":"Point"}
}