{
  "type": "Feature",
  "properties": {
    "iso:country":"ES",
    "sg:address":"C/ Federico Garcia Lorca, 63",
    "sg:city":"Elche",
    "sg:orig_category":"Rejas Y Cortinas Met\u00c1licas",
    "sg:phone":"+34 966 63 35 77",
    "sg:postcode":"03204",
    "sg:province":"Alicante",
    "sg:website":"www.eurosistem-puertas.com",
    "wof:name":"Eurdoors Puertas Y Automatismos S.l.",
    "wof:placetype":"venue"
},
  "geometry": {"coordinates":[-0.7030410171,38.2579727173],"type":"Point"}
}