{
  "type": "Feature",
  "properties": {
    "iso:country":"ES",
    "sg:address":"Av Meridiana, 278",
    "sg:city":"Barcelona",
    "sg:orig_category":"Inmobiliaria (agencias)",
    "sg:phone":"+34 932 43 22 80",
    "sg:postcode":"08027",
    "sg:province":"Barcelona",
    "wof:name":"Fincas Corral Barcino S.l.u.",
    "wof:placetype":"venue"
},
  "geometry": {"coordinates":[2.1870670319,41.4205627441],"type":"Point"}
}