{
  "type": "Feature",
  "properties": {
    "addr:full":"Calle de Alta Del Mar, 53 Valencia Valencia 46024",
    "addr:housenumber":"53",
    "addr:postcode":"46024",
    "addr:street":"Calle De Alta Del Mar",
    "iso:country":"ES",
    "sg:address":"Calle de Alta Del Mar, 53",
    "sg:city":"Valencia",
    "sg:orig_category":"Papeler\u00cdas, Librer\u00cdas",
    "sg:phone":"+34 963 67 41 32",
    "sg:postcode":"46024",
    "sg:province":"Valencia",
    "wof:name":"Arlandis Gaso Andres",
    "wof:placetype":"venue"
},
  "geometry": {"coordinates":[-0.3335742056,39.4496116638],"type":"Point"}
}