{
  "type": "Feature",
  "properties": {
    "iso:country":"ES",
    "sg:address":"Zona Font De Terrers, S/n",
    "sg:city":"Manlleu",
    "sg:orig_category":"Quincaller\u00cda (fabricaci\u00d3n)",
    "sg:phone":"+34 938 51 29 80",
    "sg:postcode":"08560",
    "sg:province":"Barcelona",
    "sg:website":"www.sauvic.com",
    "wof:name":"Sauvic S.l.",
    "wof:placetype":"venue"
},
  "geometry": {"coordinates":[2.3013260365,42.0091400146],"type":"Point"}
}