{
  "type": "Feature",
  "properties": {
    "addr:full":"Calle de Nueva, 29 Villabona Guip\u00f9zcoa 20150",
    "addr:housenumber":"29",
    "addr:postcode":"20150",
    "addr:street":"Calle De Nueva;Guipu\u0300Zcoa",
    "iso:country":"ES",
    "sg:address":"Calle de Nueva, 29",
    "sg:city":"Villabona",
    "sg:orig_category":"Molduras, Junquillos, Listones Y Molduras Perforadas",
    "sg:phone":"+34 943 69 06 23",
    "sg:postcode":"20150",
    "sg:province":"Guip\u00f9zcoa",
    "wof:name":"Patxi Mendizabal Otaegui Y Otra Cdad",
    "wof:placetype":"venue"
},
  "geometry": {"coordinates":[-2.0525279045,43.1881217957],"type":"Point"}
}