{
  "type": "Feature",
  "properties": {
    "addr:full":"Avda Castilla Y Leon, 34 Adrada \u00c1vila 05430",
    "addr:housenumber":"34",
    "addr:postcode":"05430",
    "addr:street":"Avda Castilla Y Leon",
    "iso:country":"ES",
    "sg:address":"Avda Castilla Y Leon, 34",
    "sg:city":"Adrada",
    "sg:orig_category":"Cristaler\u00cdas",
    "sg:phone":"+34 918 67 10 97",
    "sg:postcode":"05430",
    "sg:province":"\u00c1vila",
    "wof:name":"Cristaleria Y Aluminios Ca\u00f1as-serrano C.b.",
    "wof:placetype":"venue"
},
  "geometry": {"coordinates":[-4.6385259628,40.302444458],"type":"Point"}
}