{
  "type": "Feature",
  "properties": {
    "iso:country":"ES",
    "sg:address":"Trva Jesus (travessia), 4",
    "sg:city":"Palma",
    "sg:orig_category":"Peluqueros: De Se\u00d1oras",
    "sg:phone":"+34 971 20 26 71",
    "sg:postcode":"07010",
    "sg:province":"Islas Baleares",
    "wof:name":"Calls Casanova Susana",
    "wof:placetype":"venue"
},
  "geometry": {"coordinates":[2.6459751129,39.5829620361],"type":"Point"}
}