{
  "type": "Feature",
  "properties": {
    "addr:full":"Pase Colon, 17 Irun Guip\u00f9zcoa 20302",
    "addr:housenumber":"17",
    "addr:postcode":"20302",
    "addr:street":"Colon;Guipu\u0300Zcoa",
    "iso:country":"ES",
    "sg:address":"Pase Colon, 17",
    "sg:city":"Irun",
    "sg:orig_category":"Fabricaci\u00d3n De Sobres, Bolsas Y Fundas",
    "sg:phone":"+34 943 62 28 29",
    "sg:postcode":"20302",
    "sg:province":"Guip\u00f9zcoa",
    "wof:name":"Margallo Cordero Antonio Luis",
    "wof:placetype":"venue"
},
  "geometry": {"coordinates":[-1.7911579609,43.3395614624],"type":"Point"}
}