{
  "type": "Feature",
  "properties": {
    "addr:full":"Pase Balneario, 1 Arteixo La Coru\u00f1a 15142",
    "addr:postcode":"15142",
    "addr:street":"Corun\u0303A",
    "iso:country":"ES",
    "sg:address":"Pase Balneario, 1",
    "sg:city":"Arteixo",
    "sg:orig_category":"Asociaciones, Organismos Culturales Y Socioeducativos",
    "sg:phone":"+34 981 64 18 03",
    "sg:postcode":"15142",
    "sg:province":"La Coru\u00f1a",
    "wof:name":"Concello De Arteixo",
    "wof:placetype":"venue"
},
  "geometry": {"coordinates":[-8.507437706,43.3035774231],"type":"Point"}
}