{
  "type": "Feature",
  "properties": {
    "iso:country":"ES",
    "sg:address":"Calle de Candalija, 8",
    "sg:city":"Zaragoza",
    "sg:orig_category":"Abogados",
    "sg:phone":"+34 976 29 50 83",
    "sg:postcode":"50003",
    "sg:province":"Zaragoza",
    "wof:name":"Bel Arbunies Jose Luis",
    "wof:placetype":"venue"
},
  "geometry": {"coordinates":[-0.8817629814,41.6545562744],"type":"Point"}
}