{
  "type": "Feature",
  "properties": {
    "addr:full":"Calle de Cardenal Cisneros, 15 Madrid Madrid 28010",
    "addr:housenumber":"15",
    "addr:postcode":"madrid;28010",
    "addr:street":"Calle De Cardenal Cisneros",
    "iso:country":"ES",
    "sg:address":"Calle de Cardenal Cisneros, 15",
    "sg:city":"Madrid",
    "sg:orig_category":"Bisuteros (fabricaci\u00d3n, Al Por Mayor)",
    "sg:phone":"+34 914 46 93 82",
    "sg:postcode":"28010",
    "sg:province":"Madrid",
    "wof:name":"Eco Hispania S.l.",
    "wof:placetype":"venue"
},
  "geometry": {"coordinates":[-3.7018868923,40.4302368164],"type":"Point"}
}