{
  "type": "Feature",
  "properties": {
    "addr:full":"Luga Poligono Industrial, S/n Cabanillas Campo Guadalajara 19171",
    "addr:postcode":"19171",
    "addr:street":"Poligono Industrial S / N",
    "iso:country":"ES",
    "sg:address":"Luga Poligono Industrial, S/n",
    "sg:city":"Cabanillas Campo",
    "sg:orig_category":"Maquinaria Para Industrias Diversas",
    "sg:phone":"+34 949 20 04 20",
    "sg:postcode":"19171",
    "sg:province":"Guadalajara",
    "wof:name":"Servilotec S.l.",
    "wof:placetype":"venue"
},
  "geometry": {"coordinates":[-3.2194590569,40.5990333557],"type":"Point"}
}