{
  "type": "Feature",
  "properties": {
    "addr:full":"Calle de Caceres, 10 Alcorcon Madrid 28921",
    "addr:housenumber":"10",
    "addr:postcode":"28921",
    "addr:street":"Calle De Caceres",
    "iso:country":"ES",
    "sg:address":"Calle de Caceres, 10",
    "sg:city":"Alcorcon",
    "sg:orig_category":"Servicio De Salud",
    "sg:phone":"+34 916 19 57 21",
    "sg:postcode":"28921",
    "sg:province":"Madrid",
    "wof:name":"Vivar Caro Jesus",
    "wof:placetype":"venue"
},
  "geometry": {"coordinates":[-3.8320829868,40.348274231],"type":"Point"}
}