{
  "type": "Feature",
  "properties": {
    "addr:full":"Txonta Kalea, 22 Eibar Guip\u00f9zcoa 20600",
    "addr:housenumber":"22",
    "addr:postcode":"20600",
    "addr:street":"Txonta Kalea;Guipu\u0300Zcoa",
    "iso:country":"ES",
    "sg:address":"Txonta Kalea, 22",
    "sg:city":"Eibar",
    "sg:orig_category":"Art\u00cdculos De Limpieza Y De Cocina (fabricaci\u00d3n, Al Por Mayor)",
    "sg:phone":"+34 943 12 00 04",
    "sg:postcode":"20600",
    "sg:province":"Guip\u00f9zcoa",
    "wof:name":"Izquierdo Rioja Jesus",
    "wof:placetype":"venue"
},
  "geometry": {"coordinates":[-2.4618229866,43.1834945679],"type":"Point"}
}