{
  "type": "Feature",
  "properties": {
    "addr:full":"Ctra Alcala Rio-algaba, Km. 0001,0 Alcala Rio Sevilla 41200",
    "addr:postcode":"41200",
    "addr:street":"Ctra Alcala Rio-Algaba Km. 0001,0",
    "iso:country":"ES",
    "sg:address":"Ctra Alcala Rio-algaba, Km. 0001,0",
    "sg:city":"Alcala Rio",
    "sg:orig_category":"Inversiones",
    "sg:phone":"+34 954 78 07 95",
    "sg:postcode":"41200",
    "sg:province":"Sevilla",
    "wof:name":"Aguilera Servicios E Inversiones Agrarias S.l.",
    "wof:placetype":"venue"
},
  "geometry": {"coordinates":[-5.9962949753,37.3826408386],"type":"Point"}
}