{
  "type": "Feature",
  "properties": {
    "addr:full":"Calle de Pe\u00d1a Herbosa, 5 Santander Cantabria 39003",
    "addr:housenumber":"5",
    "addr:postcode":"39003",
    "addr:street":"Calle De Pen\u0303A Herbosa",
    "iso:country":"ES",
    "sg:address":"Calle de Pe\u00d1a Herbosa, 5",
    "sg:city":"Santander",
    "sg:orig_category":"Molduras, Junquillos, Listones Y Molduras Perforadas",
    "sg:phone":"+34 942 21 30 58",
    "sg:postcode":"39003",
    "sg:province":"Cantabria",
    "wof:name":"Gutierrez Floranes Paulino Laureano",
    "wof:placetype":"venue"
},
  "geometry": {"coordinates":[-3.7991950512,43.4634933472],"type":"Point"}
}