{
  "type": "Feature",
  "properties": {
    "addr:full":"Carr Democracia, 21 Lleida Lleida 25007",
    "addr:housenumber":"21",
    "addr:postcode":"25007",
    "addr:street":"Carr Democracia",
    "iso:country":"ES",
    "sg:address":"Carr Democracia, 21",
    "sg:city":"Lleida",
    "sg:orig_category":"Zapatos (al Por Menor)",
    "sg:phone":"+34 973 72 72 99",
    "sg:postcode":"25007",
    "sg:province":"Lleida",
    "wof:name":"Pey Giro Luis",
    "wof:placetype":"venue"
},
  "geometry": {"coordinates":[0.6294869781,41.6193389893],"type":"Point"}
}