{
  "type": "Feature",
  "properties": {
    "addr:full":"Calle de Pedro De Valdivia, 12 Taliga Badajoz 06133",
    "addr:housenumber":"12",
    "addr:postcode":"06133",
    "addr:street":"Calle De Pedro De Valdivia",
    "iso:country":"ES",
    "sg:address":"Calle de Pedro De Valdivia, 12",
    "sg:city":"Taliga",
    "sg:orig_category":"Fabricaci\u00d3n, Instalaci\u00d3n De Armarios",
    "sg:phone":"+34 924 42 21 11",
    "sg:postcode":"06133",
    "sg:province":"Badajoz",
    "wof:name":"Nu\u00f1ez Lopez Francisco",
    "wof:placetype":"venue"
},
  "geometry": {"coordinates":[-7.0174589157,38.5283699036],"type":"Point"}
}