{
  "type": "Feature",
  "properties": {
    "addr:full":"Calle de Benigno Soto, 10 Madrid Madrid 28002",
    "addr:housenumber":"10",
    "addr:postcode":"madrid;28002",
    "addr:street":"Calle De Benigno Soto",
    "iso:country":"ES",
    "sg:address":"Calle de Benigno Soto, 10",
    "sg:city":"Madrid",
    "sg:orig_category":"Lavado, Limpieza De Veh\u00cdculos",
    "sg:phone":"+34 914 16 97 29",
    "sg:postcode":"28002",
    "sg:province":"Madrid",
    "wof:name":"Malto Aviles Romeo",
    "wof:placetype":"venue"
},
  "geometry": {"coordinates":[-3.6746106148,40.4479980469],"type":"Point"}
}