{
  "type": "Feature",
  "properties": {
    "iso:country":"ES",
    "sg:address":"I\u00f1igo Arista, 9",
    "sg:city":"Iru\u00f1a",
    "sg:orig_category":"Ropa Para Se\u00d1oras (al Por Menor)",
    "sg:phone":"+34 948 26 83 09",
    "sg:postcode":"31007",
    "sg:province":"Navarra",
    "wof:name":"Gonzalo Galan Maria Del Carmen",
    "wof:placetype":"venue"
},
  "geometry": {"coordinates":[-1.6538740396,42.8069725037],"type":"Point"}
}