{
  "type": "Feature",
  "properties": {
    "iso:country":"ES",
    "sg:address":"Calle de Historiador Dozy, S/n",
    "sg:city":"Cordoba",
    "sg:orig_category":"Peluquer\u00cdas, Peluquer\u00cda Mixta",
    "sg:phone":"+34 957 40 07 16",
    "sg:postcode":"14011",
    "sg:province":"C\u00f3rdoba",
    "wof:name":"Santos Rodriguez Jose",
    "wof:placetype":"venue"
},
  "geometry": {"coordinates":[-4.7930040359,37.8900566101],"type":"Point"}
}