{
  "type": "Feature",
  "properties": {
    "iso:country":"ES",
    "sg:address":"Ptge Delicies (les), 7",
    "sg:city":"Cornella Llobregat",
    "sg:orig_category":"Inmobiliaria (agencias)",
    "sg:phone":"+34 933 77 88 52",
    "sg:postcode":"08940",
    "sg:province":"Barcelona",
    "sg:website":"www.odonnellfinca.com",
    "wof:name":"O'donnell Fincas Y Asociados S.c.p.",
    "wof:placetype":"venue"
},
  "geometry": {"coordinates":[2.0754458904,41.3599243164],"type":"Point"}
}