{
  "type": "Feature",
  "properties": {
    "iso:country":"ES",
    "sg:address":"Pase Fernando El Catolico, 6",
    "sg:city":"Zaragoza",
    "sg:orig_category":"Abogados",
    "sg:phone":"+34 976 55 16 70",
    "sg:postcode":"50005",
    "sg:province":"Zaragoza",
    "wof:name":"Redondo Ainsa Juan Jose",
    "wof:placetype":"venue"
},
  "geometry": {"coordinates":[-0.892629981,41.6438140869],"type":"Point"}
}