{
  "type": "Feature",
  "properties": {
    "addr:full":"Carrer de Tambor Del Bruc, 10 S. Joan Despi Barcelona 08970",
    "addr:housenumber":"10",
    "addr:postcode":"08970",
    "addr:street":"Carrer De Tambor Del Bruc;Joan",
    "iso:country":"ES",
    "sg:address":"Carrer de Tambor Del Bruc, 10",
    "sg:city":"S. Joan Despi",
    "sg:orig_category":"Alumbrados",
    "sg:phone":"+34 934 77 00 69",
    "sg:postcode":"08970",
    "sg:province":"Barcelona",
    "wof:name":"Metalarte S. A.",
    "wof:placetype":"venue"
},
  "geometry": {"coordinates":[2.0648729801,41.3644218445],"type":"Point"}
}