{
  "type": "Feature",
  "properties": {
    "addr:full":"Carrer de Drassanes, 27 Cambrils Tarragona 43850",
    "addr:housenumber":"27",
    "addr:postcode":"43850",
    "addr:street":"Carrer De Drassanes",
    "iso:country":"ES",
    "sg:address":"Carrer de Drassanes, 27",
    "sg:city":"Cambrils",
    "sg:orig_category":"Inmobiliaria (agencias)",
    "sg:phone":"+34 977 36 98 80",
    "sg:postcode":"43850",
    "sg:province":"Tarragona",
    "wof:name":"Finques Gestiomar S.l.",
    "wof:placetype":"venue"
},
  "geometry": {"coordinates":[1.0630899668,41.0669288635],"type":"Point"}
}