{
  "type": "Feature",
  "properties": {
    "addr:full":"Pl Major De La Vila, 19 Benaguasil Valencia 46180",
    "addr:housenumber":"19",
    "addr:postcode":"46180",
    "addr:street":"Pl",
    "iso:country":"ES",
    "sg:address":"Pl Major De La Vila, 19",
    "sg:city":"Benaguasil",
    "sg:orig_category":"Arquitectos",
    "sg:phone":"+34 962 73 71 30",
    "sg:postcode":"46180",
    "sg:province":"Valencia",
    "wof:name":"Escribano Navarro Raquel",
    "wof:placetype":"venue"
},
  "geometry": {"coordinates":[-0.5850510001,39.5935707092],"type":"Point"}
}