{
  "type": "Feature",
  "properties": {
    "addr:full":"Calle de Ntra Sra De Gracia, 3 Marbella M\u00e1laga 29600",
    "addr:housenumber":"3",
    "addr:postcode":"29600",
    "addr:street":"Calle De Ntra Sra De Gracia;Ma\u0301Laga",
    "iso:country":"ES",
    "sg:address":"Calle de Ntra Sra De Gracia, 3",
    "sg:city":"Marbella",
    "sg:orig_category":"Arquitectos",
    "sg:phone":"+34 952 86 56 42",
    "sg:postcode":"29600",
    "sg:province":"M\u00e1laga",
    "wof:name":"Gustavo Loiseau Y Asociados S.l.",
    "wof:placetype":"venue"
},
  "geometry": {"coordinates":[-4.8906259537,36.5092163086],"type":"Point"}
}