{
  "type": "Feature",
  "properties": {
    "addr:full":"Calle de Zaragoza, 7 Almeria Almer\u00eda 04001",
    "addr:housenumber":"7",
    "addr:postcode":"04001",
    "addr:street":"Calle De Zaragoza",
    "iso:country":"ES",
    "sg:address":"Calle de Zaragoza, 7",
    "sg:city":"Almeria",
    "sg:orig_category":"Abogados",
    "sg:phone":"+34 950 25 33 59",
    "sg:postcode":"04001",
    "sg:province":"Almer\u00eda",
    "wof:name":"La Calle Asociados C.b.",
    "wof:placetype":"venue"
},
  "geometry": {"coordinates":[-2.461879015,36.8393592834],"type":"Point"}
}