{
  "type": "Feature",
  "properties": {
    "addr:full":"Carrer de Can San\u00c7, 8 Palma Islas Baleares 07001",
    "addr:housenumber":"8",
    "addr:postcode":"07001",
    "addr:street":"Carrer De Can Sanc\u0327",
    "iso:country":"ES",
    "sg:address":"Carrer de Can San\u00c7, 8",
    "sg:city":"Palma",
    "sg:orig_category":"Comisarios",
    "sg:phone":"+34 971 71 42 91",
    "sg:postcode":"07001",
    "sg:province":"Islas Baleares",
    "wof:name":"Ripoll Billon Manuel",
    "wof:placetype":"venue"
},
  "geometry": {"coordinates":[2.6525011063,39.5698242188],"type":"Point"}
}