{
  "type": "Feature",
  "properties": {
    "iso:country":"ES",
    "sg:address":"Puente De Cordoba, S/n",
    "sg:city":"Lucena",
    "sg:orig_category":"Comercio De Muebles De Estilo Y Contempor\u00c1neos",
    "sg:phone":"+34 957 50 91 77",
    "sg:postcode":"14900",
    "sg:province":"C\u00f3rdoba",
    "wof:name":"Industrias Elizana S.a.",
    "wof:placetype":"venue"
},
  "geometry": {"coordinates":[-4.4955515862,37.4091072083],"type":"Point"}
}