{
  "type": "Feature",
  "properties": {
    "addr:full":"Montegrande, 1 Tarago\u00f1a A Coru\u00f1a 15985",
    "addr:housenumber":"1",
    "addr:postcode":"15985",
    "addr:street":"Montegrande;Corun\u0303A",
    "iso:country":"ES",
    "sg:address":"Montegrande, 1",
    "sg:city":"Tarago\u00f1a",
    "sg:orig_category":"Delegados, Agentes De Tr\u00c1nsito, Auxiliares De Transporte Internacional",
    "sg:phone":"+34 981 86 26 26",
    "sg:postcode":"15985",
    "sg:province":"A Coru\u00f1a",
    "wof:name":"Transagonza",
    "wof:placetype":"venue"
},
  "geometry": {"coordinates":[-8.8350944519,42.6831436157],"type":"Point"}
}