{
  "type": "Feature",
  "properties": {
    "iso:country":"ES",
    "sg:address":"Calle de Pelayo, 16",
    "sg:city":"Cangas Narcea",
    "sg:orig_category":"Empresas De Carpinter\u00cda Met\u00c1lica",
    "sg:phone":"+34 985 81 02 27",
    "sg:postcode":"33800",
    "sg:province":"Asturias",
    "wof:name":"Monteserin Fernandez Jose Antonio",
    "wof:placetype":"venue"
},
  "geometry": {"coordinates":[-6.5487589836,43.175868988],"type":"Point"}
}