{
  "type": "Feature",
  "properties": {
    "addr:full":"Ctra Siete Higueras, S/n Mirador Murcia 30739",
    "addr:housenumber":"/ n",
    "addr:postcode":"30739",
    "addr:street":"Ctra Siete Higueras S",
    "iso:country":"ES",
    "sg:address":"Ctra Siete Higueras, S/n",
    "sg:city":"Mirador",
    "sg:orig_category":"Carnicer\u00cdas, Carnicer\u00cdas",
    "sg:phone":"+34 968 17 41 88",
    "sg:postcode":"30739",
    "sg:province":"Murcia",
    "wof:name":"Zapata Hernandez Francisco Javier",
    "wof:placetype":"venue"
},
  "geometry": {"coordinates":[-0.8524757028,37.8445510864],"type":"Point"}
}