{
  "type": "Feature",
  "properties": {
    "addr:full":"Carrer de Emperador August, 3 Tarragona Tarragona 43003",
    "addr:housenumber":"3",
    "addr:postcode":"43003",
    "addr:street":"Carrer De Emperador August",
    "iso:country":"ES",
    "sg:address":"Carrer de Emperador August, 3",
    "sg:city":"Tarragona",
    "sg:orig_category":"Zapatos (al Por Menor)",
    "sg:phone":"+34 977 24 48 86",
    "sg:postcode":"43003",
    "sg:province":"Tarragona",
    "wof:name":"Gracia Marias Martin",
    "wof:placetype":"venue"
},
  "geometry": {"coordinates":[1.2541049719,41.1169281006],"type":"Point"}
}