{
  "type": "Feature",
  "properties": {
    "addr:full":"Rua Mendez Nu\u00d1ez, 17 Vilagarcia Pontevedra 36600",
    "addr:housenumber":"17",
    "addr:postcode":"36600",
    "addr:street":"Rua Mendez Nun\u0303Ez",
    "iso:country":"ES",
    "sg:address":"Rua Mendez Nu\u00d1ez, 17",
    "sg:city":"Vilagarcia",
    "sg:orig_category":"Alimentaci\u00d3n General (al Por Menor)",
    "sg:phone":"+34 986 50 03 47",
    "sg:postcode":"36600",
    "sg:province":"Pontevedra",
    "wof:name":"Perlas De Arousa C.b.",
    "wof:placetype":"venue"
},
  "geometry": {"coordinates":[-8.7655611038,42.5978355408],"type":"Point"}
}