{
  "type": "Feature",
  "properties": {
    "addr:full":"Calle de Madrid, 32 Burgos Burgos 09001",
    "addr:housenumber":"32",
    "addr:postcode":"09001",
    "addr:street":"Calle De Madrid",
    "iso:country":"ES",
    "sg:address":"Calle de Madrid, 32",
    "sg:city":"Burgos",
    "sg:orig_category":"Molduras, Junquillos, Listones Y Molduras Perforadas",
    "sg:phone":"+34 947 26 53 02",
    "sg:postcode":"09001",
    "sg:province":"Burgos",
    "wof:name":"Martinez Delgado Elisa",
    "wof:placetype":"venue"
},
  "geometry": {"coordinates":[-3.6999309063,42.3328781128],"type":"Point"}
}