{
  "type": "Feature",
  "properties": {
    "iso:country":"ES",
    "sg:address":"Calle de Real, 22",
    "sg:city":"Osma",
    "sg:orig_category":"Reposter\u00cdas",
    "sg:phone":"+34 975 34 09 71",
    "sg:postcode":"42300",
    "sg:province":"Soria",
    "wof:name":"Jesus Rocha Carazo Julio Rocha Carazo Y Juan Rocha Carazo Cdad",
    "wof:placetype":"venue"
},
  "geometry": {"coordinates":[-3.0822300911,41.5805244446],"type":"Point"}
}