{
  "type": "Feature",
  "properties": {
    "addr:full":"Galerias Pl. Major, 25 Palma Islas Baleares 07002",
    "addr:housenumber":"25",
    "addr:postcode":"07002",
    "addr:street":"Pl. Major",
    "iso:country":"ES",
    "sg:address":"Galerias Pl. Major, 25",
    "sg:city":"Palma",
    "sg:orig_category":"Complementos De Vestir (al Por Menor)",
    "sg:phone":"+34 971 72 79 81",
    "sg:postcode":"07002",
    "sg:province":"Islas Baleares",
    "wof:name":"Murcia Minguez Juan",
    "wof:placetype":"venue"
},
  "geometry": {"coordinates":[2.6469399929,39.5714836121],"type":"Point"}
}