{
  "type": "Feature",
  "properties": {
    "addr:full":"Calle de Calahorra, 60 Madrid Madrid 28032",
    "addr:housenumber":"60",
    "addr:postcode":"madrid;28032",
    "addr:street":"Calle De Calahorra",
    "iso:country":"ES",
    "sg:address":"Calle de Calahorra, 60",
    "sg:city":"Madrid",
    "sg:orig_category":"Restaurantes",
    "sg:phone":"+34 917 75 24 65",
    "sg:postcode":"28032",
    "sg:province":"Madrid",
    "wof:name":"Contreras Dominguez Maria Del Carmen",
    "wof:placetype":"venue"
},
  "geometry": {"coordinates":[-3.6126534939,40.408782959],"type":"Point"}
}