{
  "type": "Feature",
  "properties": {
    "addr:full":"Avda Elduayen, 34 Gondomar Pontevedra 36380",
    "addr:housenumber":"34",
    "addr:postcode":"36380",
    "addr:street":"Avda Elduayen",
    "iso:country":"ES",
    "sg:address":"Avda Elduayen, 34",
    "sg:city":"Gondomar",
    "sg:classifiers":[
        {
            "category":"Autos & Motor Vehicles",
            "subcategory":"Automobile Sales",
            "type":"Retail Goods"
        }
    ],
    "sg:phone":"+34 986 36 94 36",
    "sg:postcode":"36380",
    "sg:province":"Pontevedra",
    "wof:name":"Autoescuela Turbo Gondomar S.l.",
    "wof:placetype":"venue"
},
  "geometry": {"coordinates":[-8.7666482925,42.1119499207],"type":"Point"}
}