{
  "type": "Feature",
  "properties": {
    "addr:full":"Calle de Juego De Bolos, 3 Fuente Alamo Murcia 30320",
    "addr:housenumber":"3",
    "addr:postcode":"30320",
    "addr:street":"Calle De Juego De Bolos",
    "iso:country":"ES",
    "sg:address":"Calle de Juego De Bolos, 3",
    "sg:city":"Fuente Alamo",
    "sg:orig_category":"Peluqueros: De Se\u00d1oras",
    "sg:phone":"+34 968 59 76 93",
    "sg:postcode":"30320",
    "sg:province":"Murcia",
    "wof:name":"Perez Garcia Agustina",
    "wof:placetype":"venue"
},
  "geometry": {"coordinates":[-1.1718679667,37.7231140137],"type":"Point"}
}