{
  "type": "Feature",
  "properties": {
    "addr:full":"Calle de Cuba, 27 Chiclana De La Frontera C\u00e1diz 11130",
    "addr:housenumber":"27",
    "addr:postcode":"11130",
    "addr:street":"Calle De Cuba",
    "iso:country":"ES",
    "sg:address":"Calle de Cuba, 27",
    "sg:city":"Chiclana De La Frontera",
    "sg:orig_category":"Semiller\u00cdas",
    "sg:phone":"+34 956 40 14 19",
    "sg:postcode":"11130",
    "sg:province":"C\u00e1diz",
    "wof:name":"Caballero Roman Felipe",
    "wof:placetype":"venue"
},
  "geometry": {"coordinates":[-6.1606788635,36.4206008911],"type":"Point"}
}