{
  "type": "Feature",
  "properties": {
    "iso:country":"ES",
    "sg:address":"Rond Sant Ramon, 179",
    "sg:city":"S. Boi Llobregat",
    "sg:orig_category":"Escayola Y Productos De Escayola (fabricaci\u00d3n, Al Por Mayor)",
    "sg:phone":"+34 936 61 36 02",
    "sg:postcode":"08830",
    "sg:province":"Barcelona",
    "wof:name":"Enyesados Y Decoracion Tres Ddd",
    "wof:placetype":"venue"
},
  "geometry": {"coordinates":[2.0449779034,41.3480606079],"type":"Point"}
}