{
  "type": "Feature",
  "properties": {
    "addr:full":"Ctra Navaluenga, Km. 0007,0 San Juan De La Nava \u00c1vila 05111",
    "addr:postcode":"05111",
    "addr:street":"Ctra Navaluenga Km. 0007,0 San Juan;La;A\u0301Vila",
    "iso:country":"ES",
    "sg:address":"Ctra Navaluenga, Km. 0007,0",
    "sg:city":"San Juan De La Nava",
    "sg:orig_category":"Hormigonados",
    "sg:phone":"+34 920 28 72 97",
    "sg:postcode":"05111",
    "sg:province":"\u00c1vila",
    "wof:name":"Transportes Peral Herrero S.l.",
    "wof:placetype":"venue"
},
  "geometry": {"coordinates":[-4.675494194,40.46900177],"type":"Point"}
}