{
  "type": "Feature",
  "properties": {
    "addr:full":"Avgd Llosar, 150 Villafranca Cid Castell\u00f3n 12150",
    "addr:housenumber":"150",
    "addr:postcode":"12150",
    "iso:country":"ES",
    "sg:address":"Avgd Llosar, 150",
    "sg:city":"Villafranca Cid",
    "sg:orig_category":"Ense\u00d1anza, Formaci\u00d3n Profesional: Aprendizaje",
    "sg:phone":"+34 964 44 15 20",
    "sg:postcode":"12150",
    "sg:province":"Castell\u00f3n",
    "wof:name":"Generalitat Valenciana",
    "wof:placetype":"venue"
},
  "geometry": {"coordinates":[-0.0360242017,39.9860687256],"type":"Point"}
}