{
  "type": "Feature",
  "properties": {
    "iso:country":"ES",
    "sg:address":"Calle de Cruces, 17",
    "sg:city":"Churriana Vega",
    "sg:orig_category":"Servidores Y Editores De Bases De Datos",
    "sg:phone":"+34 958 55 35 35",
    "sg:postcode":"18194",
    "sg:province":"Granada",
    "wof:name":"Ruiz Rodriguez Guillermo",
    "wof:placetype":"venue"
},
  "geometry": {"coordinates":[-3.6455171108,37.1448745728],"type":"Point"}
}