{
  "type": "Feature",
  "properties": {
    "iso:country":"ES",
    "sg:address":"Ctra. Guipuzcoa, Km. 0005,6",
    "sg:city":"Aizoain",
    "sg:orig_category":"Asesor\u00cda Fiscal Y Jur\u00cddica",
    "sg:phone":"+34 948 30 22 85",
    "sg:postcode":"31195",
    "sg:province":"Navarra",
    "wof:name":"Dupouy Apestegui Juan",
    "wof:placetype":"venue"
},
  "geometry": {"coordinates":[-1.6867979765,42.8470611572],"type":"Point"}
}