{
  "type": "Feature",
  "properties": {
    "iso:country":"ES",
    "sg:address":"Carretera De Villada, Km. 0004,0",
    "sg:city":"Castroponce",
    "sg:orig_category":"Producci\u00d3n, Comercio De Cereales",
    "sg:phone":"+34 983 75 61 02",
    "sg:postcode":"47664",
    "sg:province":"Valladolid",
    "wof:name":"Agroaguilar S.a.",
    "wof:placetype":"venue"
},
  "geometry": {"coordinates":[-5.1692752838,42.1151275635],"type":"Point"}
}