{
  "type": "Feature",
  "properties": {
    "iso:country":"ES",
    "sg:address":"Poli Poligon Industrial, S/n",
    "sg:city":"Picassent",
    "sg:orig_category":"Distribuci\u00d3n De Petr\u00d3leo Y Derivados",
    "sg:phone":"+34 961 24 24 64",
    "sg:postcode":"46220",
    "sg:province":"Valencia",
    "wof:name":"Picagas S.l.",
    "wof:placetype":"venue"
},
  "geometry": {"coordinates":[-0.4524689913,39.3585700989],"type":"Point"}
}