{
  "type": "Feature",
  "properties": {
    "addr:full":"Calle de Jaca, 21 Zaragoza Zaragoza 50017",
    "addr:housenumber":"21",
    "addr:postcode":"50017",
    "addr:street":"Calle De Jaca",
    "iso:country":"ES",
    "sg:address":"Calle de Jaca, 21",
    "sg:city":"Zaragoza",
    "sg:orig_category":"Promotores Constructores",
    "sg:phone":"+34 976 33 39 27",
    "sg:postcode":"50017",
    "sg:province":"Zaragoza",
    "wof:name":"Construcciones Y Reformas J. Grima S.l.",
    "wof:placetype":"venue"
},
  "geometry": {"coordinates":[-0.9063040018,41.6514167786],"type":"Point"}
}