{
  "type": "Feature",
  "properties": {
    "iso:country":"ES",
    "sg:address":"Cami Mar, De La, 18",
    "sg:city":"S'illot-cala Morlanda",
    "sg:orig_category":"Cajas Para Embalar",
    "sg:phone":"+34 971 81 08 75",
    "sg:postcode":"07687",
    "sg:province":"Islas Baleares",
    "wof:name":"Caja Rural Provincial De Baleares",
    "wof:placetype":"venue"
},
  "geometry": {"coordinates":[3.3712379932,39.5647315979],"type":"Point"}
}