{
  "type": "Feature",
  "properties": {
    "iso:country":"ES",
    "sg:address":"Calle de Villalba Larga, 19",
    "sg:city":"Cartagena",
    "sg:orig_category":"Artes Gr\u00c1ficas, Artes Pl\u00c1sticas (curso)",
    "sg:phone":"+34 968 50 28 85",
    "sg:postcode":"30202",
    "sg:province":"Murcia",
    "wof:name":"Artes Graficas La Moderna",
    "wof:placetype":"venue"
},
  "geometry": {"coordinates":[-0.9825382233,37.603553772],"type":"Point"}
}