{
  "type": "Feature",
  "properties": {
    "iso:country":"ES",
    "sg:address":"Pase De La Acacia, 29",
    "sg:city":"Poligono Ind. La Mora",
    "sg:orig_category":"Fabricaci\u00d3n De Enlosados, Soler\u00cdas",
    "sg:phone":"+34 983 40 32 13",
    "sg:postcode":"47193",
    "sg:province":"Valladolid",
    "wof:name":"Taulell S.a.",
    "wof:placetype":"venue"
},
  "geometry": {"coordinates":[-4.6859240532,41.6106681824],"type":"Point"}
}