{
  "type": "Feature",
  "properties": {
    "iso:country":"ES",
    "sg:address":"Ctra Murcia De Cullar (de), S/n",
    "sg:city":"Cullar",
    "sg:orig_category":"Chapister\u00cda",
    "sg:phone":"+34 958 73 00 87",
    "sg:postcode":"18850",
    "sg:province":"Granada",
    "wof:name":"Pelaez Pozo Baltasar",
    "wof:placetype":"venue"
},
  "geometry": {"coordinates":[-2.576433897,37.5831489563],"type":"Point"}
}