{
  "type": "Feature",
  "properties": {
    "iso:country":"ES",
    "sg:address":"Av Francesc Macia, 66",
    "sg:city":"Olesa Montserrat",
    "sg:orig_category":"Agencias De Viajes",
    "sg:phone":"+34 937 78 40 41",
    "sg:postcode":"08640",
    "sg:province":"Barcelona",
    "wof:name":"Stoppi Viatges S.l.",
    "wof:placetype":"venue"
},
  "geometry": {"coordinates":[1.8924599886,41.5426673889],"type":"Point"}
}