{
  "type": "Feature",
  "properties": {
    "iso:country":"ES",
    "sg:address":"Calle de Ponferrada, 3",
    "sg:city":"Madrid",
    "sg:orig_category":"Relojer\u00cda (al Por Menor, Reparaci\u00d3n)",
    "sg:phone":"+34 913 86 31 09",
    "sg:postcode":"28029",
    "sg:province":"Madrid",
    "wof:name":"Serrano Sanchez Ana Maria",
    "wof:placetype":"venue"
},
  "geometry": {"coordinates":[-3.7140889168,40.4748382568],"type":"Point"}
}