{
  "type": "Feature",
  "properties": {
    "iso:country":"ES",
    "sg:address":"Calle de Gadifer De La Salle, S/n",
    "sg:city":"Villa De Teguise",
    "sg:orig_category":"Asociaciones Y Clubs Deportivos",
    "sg:phone":"+34 928 59 30 53",
    "sg:postcode":"35530",
    "sg:province":"Las Palmas",
    "wof:name":"Club Deportivo Teguise",
    "wof:placetype":"venue"
},
  "geometry": {"coordinates":[-13.5563936234,29.0625648499],"type":"Point"}
}