{
  "type": "Feature",
  "properties": {
    "iso:country":"ES",
    "sg:address":"Calle de Higueras, 19",
    "sg:city":"Monteclaro-la Caba\u00e7a",
    "sg:orig_category":"Inmobiliaria (agencias)",
    "sg:phone":"+34 913 52 86 16",
    "sg:postcode":"28223",
    "sg:province":"Madrid",
    "wof:name":"Inversiones Laminador S.l.",
    "wof:placetype":"venue"
},
  "geometry": {"coordinates":[-3.854829073,40.444568634],"type":"Point"}
}