{
  "type": "Feature",
  "properties": {
    "iso:country":"ES",
    "sg:address":"Avda America (de), 3",
    "sg:city":"Teruel",
    "sg:orig_category":"Pod\u00d3logos: Pedicuros",
    "sg:phone":"+34 978 62 12 47",
    "sg:postcode":"44002",
    "sg:province":"Teruel",
    "wof:name":"Moya Argente Maria",
    "wof:placetype":"venue"
},
  "geometry": {"coordinates":[-1.1090049744,40.3334350586],"type":"Point"}
}