{
  "type": "Feature",
  "properties": {
    "addr:full":"Carrer de Antoni Asens, 5 Mora D'ebre Tarragona 43740",
    "addr:housenumber":"5",
    "addr:postcode":"43740",
    "addr:street":"Carrer De Antoni Asens;D'Ebre",
    "iso:country":"ES",
    "sg:address":"Carrer de Antoni Asens, 5",
    "sg:city":"Mora D'ebre",
    "sg:orig_category":"Laboratorios Y Cl\u00cdnicas Veterinarias",
    "sg:phone":"+34 977 40 16 57",
    "sg:postcode":"43740",
    "sg:province":"Tarragona",
    "wof:name":"Blade Creixenti Enric",
    "wof:placetype":"venue"
},
  "geometry": {"coordinates":[1.2533479929,41.1210632324],"type":"Point"}
}