{
  "type": "Feature",
  "properties": {
    "addr:full":"Ctra Manzanares, Km. 0038,0 Alcazar S. Juan Ciudad Real 13600",
    "addr:postcode":"13600",
    "addr:street":"Ctra Manzanares Km. 0038,0 Alcazar S. Juan Ciudad Real",
    "iso:country":"ES",
    "sg:address":"Ctra Manzanares, Km. 0038,0",
    "sg:city":"Alcazar S. Juan",
    "sg:orig_category":"Cr\u00cda De Animales",
    "sg:phone":"+34 926 69 10 14",
    "sg:postcode":"13600",
    "sg:province":"Ciudad Real",
    "wof:name":"Ercapo S.l.",
    "wof:placetype":"venue"
},
  "geometry": {"coordinates":[-3.210203886,39.3900718689],"type":"Point"}
}