{
  "type": "Feature",
  "properties": {
    "iso:country":"ES",
    "sg:address":"Ptda Torre Carrals, 47",
    "sg:city":"Denia",
    "sg:orig_category":"Muebles",
    "sg:phone":"+34 965 78 16 94",
    "sg:postcode":"03700",
    "sg:province":"Alicante",
    "wof:name":"Strokeford S.l.",
    "wof:placetype":"venue"
},
  "geometry": {"coordinates":[0.1212330014,38.8181419373],"type":"Point"}
}