{
  "type": "Feature",
  "properties": {
    "addr:full":"Pg Estacio, 41 Balaguer Lleida 25600",
    "addr:housenumber":"41",
    "addr:postcode":"25600",
    "addr:street":"Pg Estacio",
    "iso:country":"ES",
    "sg:address":"Pg Estacio, 41",
    "sg:city":"Balaguer",
    "sg:orig_category":"Charcuter\u00cdas (al Por Mayor)",
    "sg:phone":"+34 973 44 55 51",
    "sg:postcode":"25600",
    "sg:province":"Lleida",
    "wof:name":"Embutidos Bi-her S. A.",
    "wof:placetype":"venue"
},
  "geometry": {"coordinates":[0.8111799955,41.7892417908],"type":"Point"}
}