{
  "type": "Feature",
  "properties": {
    "iso:country":"ES",
    "sg:address":"Carrer de Padilla, 295",
    "sg:city":"Barcelona",
    "sg:orig_category":"Doctores En Medicina",
    "sg:phone":"+34 933 48 03 47",
    "sg:postcode":"08025",
    "sg:province":"Barcelona",
    "wof:name":"Serradell Cabra Armando",
    "wof:placetype":"venue"
},
  "geometry": {"coordinates":[2.1748869419,41.4073524475],"type":"Point"}
}