{
  "type": "Feature",
  "properties": {
    "addr:full":"Calle de Veredilla, 19 Torrejon Ardoz Madrid 28850",
    "addr:housenumber":"19",
    "addr:postcode":"28850",
    "addr:street":"Calle De Veredilla",
    "iso:country":"ES",
    "sg:address":"Calle de Veredilla, 19",
    "sg:city":"Torrejon Ardoz",
    "sg:orig_category":"Cl\u00cdnicas Dentales",
    "sg:phone":"+34 916 56 19 52",
    "sg:postcode":"28850",
    "sg:province":"Madrid",
    "wof:name":"Clinica Dental San Jose S.l.",
    "wof:placetype":"venue"
},
  "geometry": {"coordinates":[-3.4702539444,40.4623794556],"type":"Point"}
}