{
  "type": "Feature",
  "properties": {
    "addr:full":"Pg Lloren\u00c7 Serra, 39 Santa Coloma De Gramenet Barcelona 08922",
    "addr:housenumber":"39",
    "addr:postcode":"08922",
    "addr:street":"Pg Llorenc\u0327 Serra",
    "iso:country":"ES",
    "sg:address":"Pg Lloren\u00c7 Serra, 39",
    "sg:city":"Santa Coloma De Gramenet",
    "sg:orig_category":"Peluquer\u00cdas, Peluquer\u00cda Mixta",
    "sg:phone":"+34 934 66 17 55",
    "sg:postcode":"08922",
    "sg:province":"Barcelona",
    "wof:name":"Font Martinez Pedro",
    "wof:placetype":"venue"
},
  "geometry": {"coordinates":[2.2053411007,41.4502792358],"type":"Point"}
}