{
  "type": "Feature",
  "properties": {
    "iso:country":"ES",
    "sg:address":"Carrer de Motors, 216",
    "sg:city":"Barcelona",
    "sg:orig_category":"Comercio De Hierro",
    "sg:phone":"+34 932 23 48 30",
    "sg:postcode":"08038",
    "sg:province":"Barcelona",
    "wof:name":"Gutmetal S.a.",
    "wof:placetype":"venue"
},
  "geometry": {"coordinates":[2.1508500576,41.3527908325],"type":"Point"}
}