{
  "type": "Feature",
  "properties": {
    "addr:full":"Avda Republica Argentina, 24 Logro\u00f1o La Rioja 26002",
    "addr:housenumber":"24",
    "addr:postcode":"26002",
    "addr:street":"Avda Republica Argentina;Rioja",
    "iso:country":"ES",
    "sg:address":"Avda Republica Argentina, 24",
    "sg:city":"Logro\u00f1o",
    "sg:orig_category":"M\u00c1quinas De Jardiner\u00cda",
    "sg:phone":"+34 941 24 20 39",
    "sg:postcode":"26002",
    "sg:province":"La Rioja",
    "wof:name":"Lopez Suberviola S.a.",
    "wof:placetype":"venue"
},
  "geometry": {"coordinates":[-2.448861599,42.4618415833],"type":"Point"}
}