{
  "type": "Feature",
  "properties": {
    "addr:full":"Plaz San Juan, 25 Monzon Huesca 22400",
    "addr:housenumber":"25",
    "addr:postcode":"22400",
    "addr:street":"Plaz San Juan",
    "iso:country":"ES",
    "sg:address":"Plaz San Juan, 25",
    "sg:city":"Monzon",
    "sg:orig_category":"Peluquer\u00cdas, Peluquer\u00cda Mixta",
    "sg:phone":"+34 974 41 57 75",
    "sg:postcode":"22400",
    "sg:province":"Huesca",
    "wof:name":"Perella Betbese Maria Del Carmen",
    "wof:placetype":"venue"
},
  "geometry": {"coordinates":[0.1883219928,41.90883255],"type":"Point"}
}