{
  "type": "Feature",
  "properties": {
    "addr:full":"Calle de Velez De Guevara, 55 Logro\u00f1o La Rioja 26005",
    "addr:housenumber":"55",
    "addr:postcode":"26005",
    "addr:street":"Calle De Velez De Guevara;Rioja",
    "iso:country":"ES",
    "sg:address":"Calle de Velez De Guevara, 55",
    "sg:city":"Logro\u00f1o",
    "sg:orig_category":"Inform\u00c1tica: Material Y Suministros",
    "sg:phone":"+34 941 25 11 55",
    "sg:postcode":"26005",
    "sg:province":"La Rioja",
    "wof:name":"Instrumentacion Y Componentes S.a.",
    "wof:placetype":"venue"
},
  "geometry": {"coordinates":[-2.4577829838,42.4590797424],"type":"Point"}
}