{
  "type": "Feature",
  "properties": {
    "iso:country":"ES",
    "sg:address":"Calle de Moro (del), 4",
    "sg:city":"Corralejo Playa",
    "sg:orig_category":"Promotores Constructores",
    "sg:phone":"+34 928 53 57 10",
    "sg:postcode":"35660",
    "sg:province":"Las Palmas",
    "wof:name":"Aloe Club Resort S.c.p.",
    "wof:placetype":"venue"
},
  "geometry": {"coordinates":[-15.4300060272,28.1248226166],"type":"Point"}
}