{
  "type": "Feature",
  "properties": {
    "iso:country":"ES",
    "sg:address":"Ptge Carnisseria, 12",
    "sg:city":"Selva Del Camp",
    "sg:orig_category":"Empresas De Carpinter\u00cda De Madera",
    "sg:phone":"+34 977 84 41 36",
    "sg:postcode":"43470",
    "sg:province":"Tarragona",
    "wof:name":"Fusteria Cogul S.l.",
    "wof:placetype":"venue"
},
  "geometry": {"coordinates":[1.1374540329,41.2162475586],"type":"Point"}
}