{
  "type": "Feature",
  "properties": {
    "addr:full":"Carrer de Perez Galdos, 5 Palma Islas Baleares 07006",
    "addr:housenumber":"5",
    "addr:postcode":"07006",
    "addr:street":"Carrer De Perez Galdos",
    "iso:country":"ES",
    "sg:address":"Carrer de Perez Galdos, 5",
    "sg:city":"Palma",
    "sg:orig_category":"Ingeniero",
    "sg:phone":"+34 971 77 52 96",
    "sg:postcode":"07006",
    "sg:province":"Islas Baleares",
    "wof:name":"Cinesi S.l.",
    "wof:placetype":"venue"
},
  "geometry": {"coordinates":[2.6588070393,39.567111969],"type":"Point"}
}