{
  "type": "Feature",
  "properties": {
    "iso:country":"ES",
    "sg:address":"La Aguera, S/n",
    "sg:city":"Rivero",
    "sg:classifiers":[
        {
            "category":"Manufacturing",
            "subcategory":"Metals",
            "type":"Manufacturing & Wholesale Goods"
        }
    ],
    "sg:phone":"+34 942 81 51 24",
    "sg:postcode":"39409",
    "sg:province":"Cantabria",
    "sg:tags":[
        "en",
        "fundiciones"
    ],
    "wof:name":"Talleres Andies S.l.l.",
    "wof:placetype":"venue"
},
  "geometry": {"coordinates":[-4.049325943,43.2750358582],"type":"Point"}
}