{
  "type": "Feature",
  "properties": {
    "iso:country":"ES",
    "sg:address":"C/ Joaquim Sorolla, 14",
    "sg:city":"Alcoi",
    "sg:classifiers":[
        {
            "category":"Personal",
            "subcategory":"Barber",
            "type":"Services"
        }
    ],
    "sg:phone":"+34 965 33 34 89",
    "sg:postcode":"03802",
    "sg:province":"Alicante",
    "sg:tags":[
        "caballeros",
        "de",
        "peluqueros"
    ],
    "wof:name":"Mora Hernandez Pedro Luis",
    "wof:placetype":"venue"
},
  "geometry": {"coordinates":[-0.4852890074,38.697479248],"type":"Point"}
}