{
  "type": "Feature",
  "properties": {
    "iso:country":"ES",
    "sg:address":"Pase Federico Garcia Lorca, 17",
    "sg:city":"Madrid",
    "sg:orig_category":"Molduras, Junquillos, Listones Y Molduras Perforadas",
    "sg:phone":"+34 913 32 02 73",
    "sg:postcode":"28031",
    "sg:province":"Madrid",
    "wof:name":"Sistelcom-telemensaje S.a.",
    "wof:placetype":"venue"
},
  "geometry": {"coordinates":[-3.6209421158,40.3778686523],"type":"Point"}
}