{
  "type": "Feature",
  "properties": {
    "addr:full":"Euskal Pilota Kalea, 4 Ordizia Guip\u00f9zcoa 20240",
    "addr:housenumber":"4",
    "addr:postcode":"20240",
    "addr:street":"Euskal Pilota Kalea;Guipu\u0300Zcoa",
    "iso:country":"ES",
    "sg:address":"Euskal Pilota Kalea, 4",
    "sg:city":"Ordizia",
    "sg:orig_category":"Panader\u00cdas, Panader\u00cdas",
    "sg:phone":"+34 943 88 20 27",
    "sg:postcode":"20240",
    "sg:province":"Guip\u00f9zcoa",
    "wof:name":"Perez Hernandez Justa",
    "wof:placetype":"venue"
},
  "geometry": {"coordinates":[-2.1723330021,43.0540618896],"type":"Point"}
}