{
  "type": "Feature",
  "properties": {
    "addr:full":"Avda Comuneros De Castilla, 22 Miranda Ebro Burgos 09200",
    "addr:housenumber":"22",
    "addr:postcode":"09200",
    "addr:street":"Avda Comuneros De Castilla",
    "iso:country":"ES",
    "sg:address":"Avda Comuneros De Castilla, 22",
    "sg:city":"Miranda Ebro",
    "sg:orig_category":"Ropa Para Se\u00d1oras (al Por Menor)",
    "sg:phone":"+34 947 33 11 56",
    "sg:postcode":"09200",
    "sg:province":"Burgos",
    "wof:name":"Valverde Mu\u00f1oz Laura",
    "wof:placetype":"venue"
},
  "geometry": {"coordinates":[-2.9422440529,42.6861572266],"type":"Point"}
}