{
  "type": "Feature",
  "properties": {
    "iso:country":"ES",
    "sg:address":"Calle de Santa Teresa, 27",
    "sg:city":"Barraco",
    "sg:orig_category":"Molduras, Junquillos, Listones Y Molduras Perforadas",
    "sg:phone":"+34 920 28 10 34",
    "sg:postcode":"05110",
    "sg:province":"\u00c1vila",
    "wof:name":"Gil Manso Jose Maria",
    "wof:placetype":"venue"
},
  "geometry": {"coordinates":[-4.6424131393,40.4755630493],"type":"Point"}
}