{
  "type": "Feature",
  "properties": {
    "addr:full":"Pl Esglesia, 10 Vallmoll Tarragona 43144",
    "addr:housenumber":"10",
    "addr:postcode":"43144",
    "addr:street":"Pl Esglesia",
    "iso:country":"ES",
    "sg:address":"Pl Esglesia, 10",
    "sg:city":"Vallmoll",
    "sg:orig_category":"Administraciones Regionales, Departamentales Y Locales",
    "sg:phone":"+34 977 63 74 06",
    "sg:postcode":"43144",
    "sg:province":"Tarragona",
    "wof:name":"Ajuntament De Vallmoll",
    "wof:placetype":"venue"
},
  "geometry": {"coordinates":[1.2486673594,41.2421569824],"type":"Point"}
}