{
  "type": "Feature",
  "properties": {
    "iso:country":"ES",
    "sg:address":"Avda Constitucion (de La), 4",
    "sg:city":"Granada",
    "sg:orig_category":"Ingenier\u00cda, Centros De Estudios (diversos)",
    "sg:phone":"+34 958 20 95 61",
    "sg:postcode":"18012",
    "sg:province":"Granada",
    "sg:website":"www.necso.es",
    "wof:name":"Acciona Infraestructuras S.a.",
    "wof:placetype":"venue"
},
  "geometry": {"coordinates":[-3.6035571098,37.183921814],"type":"Point"}
}