{
  "type": "Feature",
  "properties": {
    "addr:full":"Les Campanilles, S/n Alcoceber Castell\u00f3n 12579",
    "addr:housenumber":"s",
    "addr:postcode":"12579",
    "addr:street":"/ N Alcoceber Castello\u0301N",
    "iso:country":"ES",
    "sg:address":"Les Campanilles, S/n",
    "sg:city":"Alcoceber",
    "sg:orig_category":"Asociaciones Y Clubs Deportivos",
    "sg:phone":"+34 964 41 42 25",
    "sg:postcode":"12579",
    "sg:province":"Castell\u00f3n",
    "wof:name":"Club De Tenis San Francisco S.l.",
    "wof:placetype":"venue"
},
  "geometry": {"coordinates":[0.2850950062,40.2547187805],"type":"Point"}
}