{
  "type": "Feature",
  "properties": {
    "addr:full":"Av Coronel Estrada, 319 Hostalric Girona 17450",
    "addr:housenumber":"319",
    "addr:postcode":"17450",
    "addr:street":"Av Coronel Estrada",
    "iso:country":"ES",
    "sg:address":"Av Coronel Estrada, 319",
    "sg:city":"Hostalric",
    "sg:orig_category":"Agencias De Trabajo Temporal",
    "sg:phone":"+34 972 87 43 06",
    "sg:postcode":"17450",
    "sg:province":"Girona",
    "wof:name":"Master Work Empresas De Trabajo Temporal S.a.",
    "wof:placetype":"venue"
},
  "geometry": {"coordinates":[2.6347699165,41.7464904785],"type":"Point"}
}