{
  "type": "Feature",
  "properties": {
    "iso:country":"ES",
    "sg:address":"Av Pallaresos, S/n",
    "sg:city":"Sant Salvador",
    "sg:orig_category":"Asociaciones Y Clubs Deportivos",
    "sg:phone":"+34 977 52 34 19",
    "sg:postcode":"43130",
    "sg:province":"Tarragona",
    "wof:name":"Club De Tiro Jordi Tarrago",
    "wof:placetype":"venue"
},
  "geometry": {"coordinates":[1.2427459955,41.1642150879],"type":"Point"}
}