{
  "type": "Feature",
  "properties": {
    "addr:full":"Calle de Don Sancho, 10 Palencia Palencia 34001",
    "addr:housenumber":"10",
    "addr:postcode":"34001",
    "addr:street":"Calle De Don Sancho",
    "iso:country":"ES",
    "sg:address":"Calle de Don Sancho, 10",
    "sg:city":"Palencia",
    "sg:orig_category":"Asociaciones Y Clubs Deportivos",
    "sg:phone":"+34 979 70 70 63",
    "sg:postcode":"34001",
    "sg:province":"Palencia",
    "sg:website":"www.forumsport.es",
    "wof:name":"Forum Sport S.a.",
    "wof:placetype":"venue"
},
  "geometry": {"coordinates":[-4.5321850777,42.0096511841],"type":"Point"}
}