{
  "type": "Feature",
  "properties": {
    "iso:country":"ES",
    "sg:address":"Luga Brexo, 27",
    "sg:city":"Brexo-lema",
    "sg:orig_category":"Doctores En Medicina",
    "sg:phone":"+34 981 67 42 94",
    "sg:postcode":"15669",
    "sg:province":"La Coru\u00f1a",
    "wof:name":"Corbal Ramos Gerardo",
    "wof:placetype":"venue"
},
  "geometry": {"coordinates":[-8.3039340973,43.2731208801],"type":"Point"}
}