{
  "type": "Feature",
  "properties": {
    "iso:country":"ES",
    "sg:address":"Av. Cde. Salvatierra D'alava, 48",
    "sg:city":"Fontanars Dels Alforins",
    "sg:orig_category":"Tractores Agr\u00cdcolas Y Remolques",
    "sg:phone":"+34 962 22 21 08",
    "sg:postcode":"46635",
    "sg:province":"Valencia",
    "wof:name":"Mico Frances Alfredo",
    "wof:placetype":"venue"
},
  "geometry": {"coordinates":[-0.7847869992,38.782169342],"type":"Point"}
}