{
  "type": "Feature",
  "properties": {
    "iso:country":"ES",
    "sg:address":"Pase Juan Xxiii, 22",
    "sg:city":"Madrid",
    "sg:orig_category":"Inmobiliaria (agencias)",
    "sg:phone":"+34 915 34 52 21",
    "sg:postcode":"28040",
    "sg:province":"Madrid",
    "sg:website":"www.florisa.com",
    "wof:name":"Salto Navarro Natalio",
    "wof:placetype":"venue"
},
  "geometry": {"coordinates":[-3.7171061039,40.4476127625],"type":"Point"}
}