{
  "type": "Feature",
  "properties": {
    "addr:full":"Calle de Alfonso De Castro, 10 Salamanca Salamanca 37005",
    "addr:housenumber":"10",
    "addr:postcode":"37005",
    "addr:street":"Calle De Alfonso De Castro",
    "iso:country":"ES",
    "sg:address":"Calle de Alfonso De Castro, 10",
    "sg:city":"Salamanca",
    "sg:orig_category":"Molduras, Junquillos, Listones Y Molduras Perforadas",
    "sg:phone":"+34 923 25 07 98",
    "sg:postcode":"37005",
    "sg:province":"Salamanca",
    "wof:name":"Crego Garcia Eladio",
    "wof:placetype":"venue"
},
  "geometry": {"coordinates":[-5.6601672173,40.9723014832],"type":"Point"}
}