{
  "type": "Feature",
  "properties": {
    "iso:country":"ES",
    "sg:address":"Rua Fray Juan Navarrete, 4",
    "sg:city":"Pontevedra",
    "sg:orig_category":"Confecci\u00d3n (fabricaci\u00d3n, Al Por Mayor)",
    "sg:phone":"+34 986 85 94 19",
    "sg:postcode":"36001",
    "sg:province":"Pontevedra",
    "wof:name":"Garcia Blanco Jose",
    "wof:placetype":"venue"
},
  "geometry": {"coordinates":[-8.6417865753,42.4292755127],"type":"Point"}
}