{
  "type": "Feature",
  "properties": {
    "addr:full":"Calle de Cava, 2 Priego Cordoba C\u00f3rdoba 14800",
    "addr:housenumber":"2",
    "addr:postcode":"14800",
    "addr:street":"Calle De Cava;Cordoba Co\u0301Rdoba",
    "iso:country":"ES",
    "sg:address":"Calle de Cava, 2",
    "sg:city":"Priego Cordoba",
    "sg:orig_category":"Agentes Generales De Seguros",
    "sg:phone":"+34 957 54 02 58",
    "sg:postcode":"14800",
    "sg:province":"C\u00f3rdoba",
    "wof:name":"Navas Cruz Antonio",
    "wof:placetype":"venue"
},
  "geometry": {"coordinates":[-4.1961188316,37.4396095276],"type":"Point"}
}