{
  "type": "Feature",
  "properties": {
    "addr:full":"Avda Reina Mercedes, 35 Sevilla Sevilla 41012",
    "addr:housenumber":"35",
    "addr:postcode":"41012",
    "addr:street":"Avda Reina Mercedes",
    "iso:country":"ES",
    "sg:address":"Avda Reina Mercedes, 35",
    "sg:city":"Sevilla",
    "sg:orig_category":"Psic\u00d3logos",
    "sg:phone":"+34 954 23 43 80",
    "sg:postcode":"41012",
    "sg:province":"Sevilla",
    "wof:name":"Garrido Troncoso Mario",
    "wof:placetype":"venue"
},
  "geometry": {"coordinates":[-5.9863553047,37.359085083],"type":"Point"}
}