{
  "type": "Feature",
  "properties": {
    "iso:country":"ES",
    "sg:address":"Urb Mirador (el), 80",
    "sg:city":"Marbella",
    "sg:orig_category":"Jardiner\u00cdas, Vegetales, Art\u00cdculos De Jardiner\u00cda (al Por Menor)",
    "sg:phone":"+34 952 77 43 95",
    "sg:postcode":"29600",
    "sg:province":"M\u00e1laga",
    "wof:name":"Mol Schlesser Ana Maria",
    "wof:placetype":"venue"
},
  "geometry": {"coordinates":[-4.8833007812,36.5079956055],"type":"Point"}
}