{
  "type": "Feature",
  "properties": {
    "addr:full":"Avda Buenos Aires, 164 Ourense Ourense 32004",
    "addr:housenumber":"164",
    "addr:postcode":"32004",
    "addr:street":"Avda Buenos Aires",
    "iso:country":"ES",
    "sg:address":"Avda Buenos Aires, 164",
    "sg:city":"Ourense",
    "sg:orig_category":"Venta, Colocaci\u00d3n, Reparaci\u00d3n De Radiadores Para Veh\u00cdculos",
    "sg:phone":"+34 988 22 57 77",
    "sg:postcode":"32004",
    "sg:province":"Ourense",
    "wof:name":"Dopazo Chaudarcas Alfonso",
    "wof:placetype":"venue"
},
  "geometry": {"coordinates":[-7.853864193,42.342124939],"type":"Point"}
}