{
  "type": "Feature",
  "properties": {
    "addr:full":"Calle de Alei Kalea, 2 Irun Guip\u00f9zcoa 20303",
    "addr:housenumber":"2",
    "addr:postcode":"20303",
    "addr:street":"Calle De Alei Kalea;Guipu\u0300Zcoa",
    "iso:country":"ES",
    "sg:address":"Calle de Alei Kalea, 2",
    "sg:city":"Irun",
    "sg:orig_category":"Importaci\u00d3n",
    "sg:phone":"+34 943 57 02 24",
    "sg:postcode":"20303",
    "sg:province":"Guip\u00f9zcoa",
    "wof:name":"D&fidanverdi S.l",
    "wof:placetype":"venue"
},
  "geometry": {"coordinates":[-1.7902339697,43.3395233154],"type":"Point"}
}