{
  "type": "Feature",
  "properties": {
    "iso:country":"ES",
    "sg:address":"Pol. Argales, S/n",
    "sg:city":"Valladolid",
    "sg:orig_category":"Muebles, Minoristas",
    "sg:phone":"+34 983 47 25 07",
    "sg:postcode":"47008",
    "sg:province":"Valladolid",
    "wof:name":"Elecnor S.a.",
    "wof:placetype":"venue"
},
  "geometry": {"coordinates":[-4.7927489281,41.6193618774],"type":"Point"}
}