{
  "type": "Feature",
  "properties": {
    "addr:full":"Calle de Covachuelas, 3 Madrid Madrid 28021",
    "addr:housenumber":"3",
    "addr:postcode":"28021",
    "addr:street":"Calle De Covachuelas",
    "iso:country":"ES",
    "sg:address":"Calle de Covachuelas, 3",
    "sg:city":"Madrid",
    "sg:orig_category":"Internados & Ense\u00d1anza Privada",
    "sg:phone":"+34 917 97 75 67",
    "sg:postcode":"28021",
    "sg:province":"Madrid",
    "wof:name":"Institucion Docente Gyrsa S. A.",
    "wof:placetype":"venue"
},
  "geometry": {"coordinates":[-3.7081136703,40.3482589722],"type":"Point"}
}