{
  "type": "Feature",
  "properties": {
    "iso:country":"ES",
    "sg:address":"Calle de Vega La, 12",
    "sg:city":"Mieres",
    "sg:orig_category":"Ropa Para Se\u00d1oras Y Caballeros (al Por Menor)",
    "sg:phone":"+34 985 46 71 90",
    "sg:postcode":"33600",
    "sg:province":"Asturias",
    "wof:name":"Vigil Gonzalez Maria Elena",
    "wof:placetype":"venue"
},
  "geometry": {"coordinates":[-5.7733469009,43.2491531372],"type":"Point"}
}