{
  "type": "Feature",
  "properties": {
    "addr:full":"Pintor Sorolla, 17 Naquera Valencia 46119",
    "addr:housenumber":"17",
    "addr:postcode":"46119",
    "addr:street":"Pintor Sorolla",
    "iso:country":"ES",
    "sg:address":"Pintor Sorolla, 17",
    "sg:city":"Naquera",
    "sg:orig_category":"Cine (distribuci\u00d3n)",
    "sg:phone":"+34 961 68 18 65",
    "sg:postcode":"46119",
    "sg:province":"Valencia",
    "wof:name":"Proserpa S.a.",
    "wof:placetype":"venue"
},
  "geometry": {"coordinates":[-0.3933640122,39.6203536987],"type":"Point"}
}