{
  "type": "Feature",
  "properties": {
    "addr:full":"Carrer de Mallorca, 631 Barcelona Barcelona 08026",
    "addr:housenumber":"631",
    "addr:postcode":"08026",
    "addr:street":"Carrer De Mallorca",
    "iso:country":"ES",
    "sg:address":"Carrer de Mallorca, 631",
    "sg:city":"Barcelona",
    "sg:orig_category":"Molduras, Junquillos, Listones Y Molduras Perforadas",
    "sg:phone":"+34 933 51 00 20",
    "sg:postcode":"08026",
    "sg:province":"Barcelona",
    "wof:name":"Gonzalez Gonzalez Nery",
    "wof:placetype":"venue"
},
  "geometry": {"coordinates":[2.1881868839,41.4132804871],"type":"Point"}
}