{
  "type": "Feature",
  "properties": {
    "addr:full":"Calle de Corazon De Maria, 48 Madrid Madrid 28002",
    "addr:housenumber":"48",
    "addr:postcode":"madrid;28002",
    "addr:street":"Calle De Corazon;Maria",
    "iso:country":"ES",
    "sg:address":"Calle de Corazon De Maria, 48",
    "sg:city":"Madrid",
    "sg:orig_category":"Tapicer\u00cdas",
    "sg:phone":"+34 914 15 01 87",
    "sg:postcode":"28002",
    "sg:province":"Madrid",
    "wof:name":"Chester Tapiceria S.l.",
    "wof:placetype":"venue"
},
  "geometry": {"coordinates":[-3.6669917107,40.4448280334],"type":"Point"}
}