{
  "type": "Feature",
  "properties": {
    "addr:full":"Piedra Caballera, S/n Piedra Caballera \u00c1vila 05100",
    "addr:housenumber":"s / n",
    "addr:postcode":"05100",
    "addr:street":"Piedra Caballera A\u0301Vila",
    "iso:country":"ES",
    "sg:address":"Piedra Caballera, S/n",
    "sg:city":"Piedra Caballera",
    "sg:orig_category":"Internados & Ense\u00d1anza Privada",
    "sg:phone":"+34 920 28 71 85",
    "sg:postcode":"05100",
    "sg:province":"\u00c1vila",
    "wof:name":"Colegio Diocesano De La Asuncion De Nuestra Se\u00f1ora",
    "wof:placetype":"venue"
},
  "geometry": {"coordinates":[-4.7079491615,40.412979126],"type":"Point"}
}