{
  "type": "Feature",
  "properties": {
    "iso:country":"ES",
    "sg:address":"Pl Catalunya, S/n",
    "sg:city":"Olesa Montserrat",
    "sg:orig_category":"Frutas, Legumbres Frescas Y Tempranas (al Por Menor)",
    "sg:phone":"+34 937 75 70 51",
    "sg:postcode":"08640",
    "sg:province":"Barcelona",
    "wof:name":"Cortes Campos Encarna",
    "wof:placetype":"venue"
},
  "geometry": {"coordinates":[1.8934999704,41.5430831909],"type":"Point"}
}