{
  "type": "Feature",
  "properties": {
    "iso:country":"ES",
    "sg:address":"Avda Reyes Catolicos, 48",
    "sg:city":"Alcala Henares",
    "sg:orig_category":"Carnicer\u00cdas, Carnicer\u00cdas",
    "sg:phone":"+34 918 88 93 79",
    "sg:postcode":"28802",
    "sg:province":"Madrid",
    "wof:name":"Puente Sebastian Jesus",
    "wof:placetype":"venue"
},
  "geometry": {"coordinates":[-3.3786070347,40.4736022949],"type":"Point"}
}