{
  "type": "Feature",
  "properties": {
    "iso:country":"ES",
    "sg:address":"Calle de Alhaken Ii, 6",
    "sg:city":"Cordoba",
    "sg:orig_category":"Molduras, Junquillos, Listones Y Molduras Perforadas",
    "sg:phone":"+34 957 48 62 11",
    "sg:postcode":"14008",
    "sg:province":"C\u00f3rdoba",
    "wof:name":"Valencia Sales Rafael",
    "wof:placetype":"venue"
},
  "geometry": {"coordinates":[-4.7833328247,37.8894119263],"type":"Point"}
}