{
  "type": "Feature",
  "properties": {
    "iso:country":"ES",
    "sg:address":"Carr Colon, 11",
    "sg:city":"Alboraya",
    "sg:orig_category":"Fabricaci\u00d3n De Bebidas No Alcoh\u00d3licas",
    "sg:phone":"+34 961 85 65 94",
    "sg:postcode":"46120",
    "sg:province":"Valencia",
    "wof:name":"Bar Horchateria Miro S.l.",
    "wof:placetype":"venue"
},
  "geometry": {"coordinates":[-0.348488003,39.4987831116],"type":"Point"}
}