{
  "type": "Feature",
  "properties": {
    "addr:full":"Calle de Luis Vives, 8 Zaragoza Zaragoza 50006",
    "addr:housenumber":"8",
    "addr:postcode":"50006",
    "addr:street":"Calle De Luis Vives",
    "iso:country":"ES",
    "sg:address":"Calle de Luis Vives, 8",
    "sg:city":"Zaragoza",
    "sg:orig_category":"Impuestos, Tesoro P\u00dablico",
    "sg:phone":"+34 976 35 38 92",
    "sg:postcode":"50006",
    "sg:province":"Zaragoza",
    "wof:name":"Navarro Salafranca Felix",
    "wof:placetype":"venue"
},
  "geometry": {"coordinates":[-0.8956850171,41.638168335],"type":"Point"}
}