{
  "type": "Feature",
  "properties": {
    "iso:country":"ES",
    "sg:address":"Calle de Virgen De La Fuensanta, 3",
    "sg:city":"Sevilla",
    "sg:orig_category":"Abogados",
    "sg:phone":"+34 954 27 75 63",
    "sg:postcode":"41011",
    "sg:province":"Sevilla",
    "wof:name":"Perez Pino Virginia",
    "wof:placetype":"venue"
},
  "geometry": {"coordinates":[-5.9965996742,37.3753929138],"type":"Point"}
}