{
  "type": "Feature",
  "properties": {
    "addr:full":"Pl Ajuntament, 4 S. Boi Llobregat Barcelona 08830",
    "addr:housenumber":"4",
    "addr:postcode":"08830",
    "addr:street":"Pl Ajuntament",
    "iso:country":"ES",
    "sg:address":"Pl Ajuntament, 4",
    "sg:city":"S. Boi Llobregat",
    "sg:orig_category":"Arquitectos",
    "sg:phone":"+34 936 54 00 01",
    "sg:postcode":"08830",
    "sg:province":"Barcelona",
    "wof:name":"Reula Corbella Jose",
    "wof:placetype":"venue"
},
  "geometry": {"coordinates":[2.0427939892,41.3475990295],"type":"Point"}
}