{
  "type": "Feature",
  "properties": {
    "iso:country":"ES",
    "sg:address":"Calle de Pastor Y Landero, 20",
    "sg:city":"Sevilla",
    "sg:orig_category":"Restaurantes",
    "sg:phone":"+34 954 21 61 39",
    "sg:postcode":"41001",
    "sg:province":"Sevilla",
    "wof:name":"Sardelliba S.l.",
    "wof:placetype":"venue"
},
  "geometry": {"coordinates":[-5.9994192123,37.3876495361],"type":"Point"}
}