{
  "type": "Feature",
  "properties": {
    "iso:country":"ES",
    "sg:address":"Avda Madrid (de), 101",
    "sg:city":"Xinzo De Limia",
    "sg:orig_category":"Alquiler De V\u00cddeo",
    "sg:phone":"+34 988 46 00 69",
    "sg:postcode":"32630",
    "sg:province":"Ourense",
    "wof:name":"Lopez Saburido Candida",
    "wof:placetype":"venue"
},
  "geometry": {"coordinates":[-7.7252988815,42.0627288818],"type":"Point"}
}