{
  "type": "Feature",
  "properties": {
    "iso:country":"ES",
    "sg:address":"Calle de Sanchez Llevot, 6",
    "sg:city":"Alba Tormes",
    "sg:orig_category":"Bisuter\u00cda, Joyer\u00cda, Relojer\u00cda (al Por Menor)",
    "sg:phone":"+34 923 37 04 99",
    "sg:postcode":"37800",
    "sg:province":"Salamanca",
    "wof:name":"Driad C.b.",
    "wof:placetype":"venue"
},
  "geometry": {"coordinates":[-5.513792038,40.8270072937],"type":"Point"}
}