{
  "type": "Feature",
  "properties": {
    "addr:full":"Calle de Juan De La Cosa, 23 Santander Cantabria 39004",
    "addr:housenumber":"23",
    "addr:postcode":"39004",
    "addr:street":"Calle De Juan De La Cosa",
    "iso:country":"ES",
    "sg:address":"Calle de Juan De La Cosa, 23",
    "sg:city":"Santander",
    "sg:orig_category":"Transporte En General",
    "sg:phone":"+34 942 21 55 57",
    "sg:postcode":"39004",
    "sg:province":"Cantabria",
    "wof:name":"Ves S. L.",
    "wof:placetype":"venue"
},
  "geometry": {"coordinates":[-3.7933781147,43.4634742737],"type":"Point"}
}