{
  "type": "Feature",
  "properties": {
    "iso:country":"ES",
    "sg:address":"Calle de Tutulu, 10",
    "sg:city":"Bilbao",
    "sg:orig_category":"Prot\u00c9sicos Dentales",
    "sg:phone":"+34 944 46 19 46",
    "sg:postcode":"48007",
    "sg:province":"Vizcaya",
    "wof:name":"Maria Isabel Gonzalez Hurtado",
    "wof:placetype":"venue"
},
  "geometry": {"coordinates":[-2.9181909561,43.2673072815],"type":"Point"}
}