{
  "type": "Feature",
  "properties": {
    "iso:country":"ES",
    "sg:address":"Carlos Vii, 10",
    "sg:city":"Estella",
    "sg:orig_category":"Material Y Herramientas Agr\u00cdcolas",
    "sg:phone":"+34 948 55 10 22",
    "sg:postcode":"31200",
    "sg:province":"Navarra",
    "wof:name":"Guillermo Martinez Arzoz Fitosanitarios",
    "wof:placetype":"venue"
},
  "geometry": {"coordinates":[-2.0321609974,42.6659736633],"type":"Point"}
}