{
  "type": "Feature",
  "properties": {
    "addr:full":"Calle de San Jose, 1 Bolulla Alicante 03518",
    "addr:housenumber":"1",
    "addr:postcode":"03518",
    "addr:street":"Calle De San Jose",
    "iso:country":"ES",
    "sg:address":"Calle de San Jose, 1",
    "sg:city":"Bolulla",
    "sg:orig_category":"Ingeniero",
    "sg:phone":"+34 965 88 10 59",
    "sg:postcode":"03518",
    "sg:province":"Alicante",
    "wof:name":"Blanquer Guardiola Antonio",
    "wof:placetype":"venue"
},
  "geometry": {"coordinates":[-0.1125530005,38.6768112183],"type":"Point"}
}