{
  "type": "Feature",
  "properties": {
    "iso:country":"ES",
    "sg:address":"Calle de Oceania, 12",
    "sg:city":"Poligono Industrial Los Villares",
    "sg:orig_category":"Ebanister\u00cda",
    "sg:phone":"+34 923 23 57 47",
    "sg:postcode":"37184",
    "sg:province":"Salamanca",
    "wof:name":"Madetal S.l.",
    "wof:placetype":"venue"
},
  "geometry": {"coordinates":[-5.6479592323,40.9935188293],"type":"Point"}
}