{
  "type": "Feature",
  "properties": {
    "iso:country":"ES",
    "sg:address":"Cta. Molina, 9",
    "sg:city":"Pitres",
    "sg:orig_category":"Formaci\u00d3n Continuada (variada)",
    "sg:phone":"+34 958 76 62 64",
    "sg:postcode":"18414",
    "sg:province":"Granada",
    "wof:name":"Fundacion Andaluza Fondo De Formacion Y Empleo",
    "wof:placetype":"venue"
},
  "geometry": {"coordinates":[-3.3271839619,36.9368972778],"type":"Point"}
}