{
  "type": "Feature",
  "properties": {
    "addr:full":"Carr Migdia, 37 Girona Girona 17002",
    "addr:housenumber":"37",
    "addr:postcode":"17002",
    "addr:street":"Carr Migdia",
    "iso:country":"ES",
    "sg:address":"Carr Migdia, 37",
    "sg:city":"Girona",
    "sg:orig_category":"Asesor\u00cda Sobre Comunicaci\u00d3n De Empresas",
    "sg:phone":"+34 972 21 29 85",
    "sg:postcode":"17002",
    "sg:province":"Girona",
    "wof:name":"Fuentes Fernandez Monica",
    "wof:placetype":"venue"
},
  "geometry": {"coordinates":[2.8206849098,41.9752044678],"type":"Point"}
}