{
  "type": "Feature",
  "properties": {
    "iso:country":"ES",
    "sg:address":"Calle de Restoy, 2",
    "sg:city":"Almeria",
    "sg:orig_category":"Librer\u00cdas",
    "sg:phone":"+34 950 25 79 81",
    "sg:postcode":"04003",
    "sg:province":"Almer\u00eda",
    "wof:name":"Arenas Sanchez Maria Dolores",
    "wof:placetype":"venue"
},
  "geometry": {"coordinates":[-2.4666640759,36.8462715149],"type":"Point"}
}