{
  "type": "Feature",
  "properties": {
    "addr:full":"Calle de Carlos Aurioles, 37 Madrid Madrid 28018",
    "addr:housenumber":"37",
    "addr:postcode":"madrid;28018",
    "addr:street":"Calle De Carlos Aurioles",
    "iso:country":"ES",
    "sg:address":"Calle de Carlos Aurioles, 37",
    "sg:city":"Madrid",
    "sg:orig_category":"Radiocomunicaciones, Telefon\u00cda M\u00d3vil, Radiomensajer\u00cda: Servicios, Comercializaci\u00d3n",
    "sg:phone":"+34 915 07 66 80",
    "sg:postcode":"28018",
    "sg:province":"Madrid",
    "wof:name":"Sowfama Telecommunication, S.l.",
    "wof:placetype":"venue"
},
  "geometry": {"coordinates":[-3.6674342155,40.3815727234],"type":"Point"}
}