{
  "type": "Feature",
  "properties": {
    "iso:country":"ES",
    "sg:address":"Ctra Nacional 110, Km. 0284,0",
    "sg:city":"Mu\u00f1ana",
    "sg:orig_category":"Distribuci\u00d3n De Petr\u00d3leo Y Derivados",
    "sg:phone":"+34 920 23 17 29",
    "sg:postcode":"05540",
    "sg:province":"\u00c1vila",
    "wof:name":"Serexmart S.l.",
    "wof:placetype":"venue"
},
  "geometry": {"coordinates":[-5.0151391029,40.5894432068],"type":"Point"}
}