{
  "type": "Feature",
  "properties": {
    "addr:full":"Pase Duque De Mandas, 19 Donostia-san Sebastian Guip\u00f9zcoa 20012",
    "addr:housenumber":"19",
    "addr:postcode":"20012",
    "addr:street":"Mandas",
    "iso:country":"ES",
    "sg:address":"Pase Duque De Mandas, 19",
    "sg:city":"Donostia-san Sebastian",
    "sg:orig_category":"Psic\u00d3logos",
    "sg:phone":"+34 943 32 02 86",
    "sg:postcode":"20012",
    "sg:province":"Guip\u00f9zcoa",
    "wof:name":"Ruiz Larzabal Rosa Maria",
    "wof:placetype":"venue"
},
  "geometry": {"coordinates":[-1.9742540121,43.3192863464],"type":"Point"}
}