{
  "type": "Feature",
  "properties": {
    "addr:full":"Carr Estacio, S/n Alcoletge Lleida 25660",
    "addr:housenumber":"s / n",
    "addr:postcode":"25660",
    "addr:street":"Carr Estacio",
    "iso:country":"ES",
    "sg:address":"Carr Estacio, S/n",
    "sg:city":"Alcoletge",
    "sg:orig_category":"Cooperativas Agr\u00cdcolas",
    "sg:phone":"+34 973 19 62 73",
    "sg:postcode":"25660",
    "sg:province":"Lleida",
    "wof:name":"Cooperativa Agricola Alcoletge",
    "wof:placetype":"venue"
},
  "geometry": {"coordinates":[0.6896010041,41.6543426514],"type":"Point"}
}