{
  "type": "Feature",
  "properties": {
    "iso:country":"ES",
    "sg:address":"Crta. Viver-pto Burriana, Km. 0003,0",
    "sg:city":"Betxi",
    "sg:orig_category":"Centros Empresariales",
    "sg:phone":"+34 964 52 81 76",
    "sg:postcode":"12549",
    "sg:province":"Castell\u00f3n",
    "wof:name":"Nuevas Tecnicas De Mecanizado S.l.",
    "wof:placetype":"venue"
},
  "geometry": {"coordinates":[-0.1963589936,39.9285507202],"type":"Point"}
}