{
  "type": "Feature",
  "properties": {
    "iso:country":"ES",
    "sg:address":"Calle de Virgen Del Pilar, 9",
    "sg:city":"Villacarrillo",
    "sg:orig_category":"Alimentaci\u00d3n General (al Por Menor)",
    "sg:phone":"+34 953 44 03 08",
    "sg:postcode":"23300",
    "sg:province":"Ja\u00e9n",
    "wof:name":"Santafosta Linares Jose",
    "wof:placetype":"venue"
},
  "geometry": {"coordinates":[-3.0778129101,38.1174049377],"type":"Point"}
}