{
  "type": "Feature",
  "properties": {
    "iso:country":"ES",
    "sg:address":"Calle de Platero Pedro De Bares, 47",
    "sg:city":"Cordoba",
    "sg:orig_category":"Molduras, Junquillos, Listones Y Molduras Perforadas",
    "sg:phone":"+34 957 26 62 14",
    "sg:postcode":"14007",
    "sg:province":"C\u00f3rdoba",
    "wof:name":"Moyano Romero Jose",
    "wof:placetype":"venue"
},
  "geometry": {"coordinates":[-4.7540302277,37.8946876526],"type":"Point"}
}