{
  "type": "Feature",
  "properties": {
    "addr:full":"Ctra Sant Climent, 65 Viladecans Barcelona 08840",
    "addr:housenumber":"65",
    "addr:postcode":"08840",
    "addr:street":"Ctra Sant Climent",
    "iso:country":"ES",
    "sg:address":"Ctra Sant Climent, 65",
    "sg:city":"Viladecans",
    "sg:orig_category":"Autob\u00das (explotaci\u00d3n Y Servicios De)",
    "sg:phone":"+34 936 58 45 13",
    "sg:postcode":"08840",
    "sg:province":"Barcelona",
    "wof:name":"Magas Chico Teresa",
    "wof:placetype":"venue"
},
  "geometry": {"coordinates":[2.014318943,41.323638916],"type":"Point"}
}