{
  "type": "Feature",
  "properties": {
    "iso:country":"ES",
    "sg:address":"Calle de Nu\u00d1ez De Balboa, 57",
    "sg:city":"Azuaga",
    "sg:orig_category":"Imprenta",
    "sg:phone":"+34 924 89 11 05",
    "sg:postcode":"06920",
    "sg:province":"Badajoz",
    "wof:name":"Carrizosa Rudilla Fernando",
    "wof:placetype":"venue"
},
  "geometry": {"coordinates":[-5.6831388474,38.2619667053],"type":"Point"}
}