{
  "type": "Feature",
  "properties": {
    "iso:country":"ES",
    "sg:address":"Avda Leitariegos, 16",
    "sg:city":"Cangas Narcea",
    "sg:orig_category":"Electricidad: Instaladores",
    "sg:phone":"+34 985 81 28 62",
    "sg:postcode":"33800",
    "sg:province":"Asturias",
    "wof:name":"Rodriguez Rodriguez Angel",
    "wof:placetype":"venue"
},
  "geometry": {"coordinates":[-6.5463848114,43.1718788147],"type":"Point"}
}