{
  "type": "Feature",
  "properties": {
    "addr:full":"Carrer de Consell De Cent, 295 Barcelona Barcelona 08007",
    "addr:housenumber":"295",
    "addr:postcode":"08007",
    "addr:street":"Carrer De Consell De Cent",
    "iso:country":"ES",
    "sg:address":"Carrer de Consell De Cent, 295",
    "sg:city":"Barcelona",
    "sg:orig_category":"Fabricaci\u00d3n De Muebles",
    "sg:phone":"+34 934 51 05 82",
    "sg:postcode":"08007",
    "sg:province":"Barcelona",
    "wof:name":"Golovin Skopintseva Eugueny",
    "wof:placetype":"venue"
},
  "geometry": {"coordinates":[2.1620759964,41.3885650635],"type":"Point"}
}