{
  "type": "Feature",
  "properties": {
    "iso:country":"ES",
    "sg:address":"Calle de Constitucion, 50",
    "sg:city":"Santa Amalia",
    "sg:orig_category":"Zapatos (al Por Menor)",
    "sg:phone":"+34 924 83 02 21",
    "sg:postcode":"06410",
    "sg:province":"Badajoz",
    "wof:name":"Sanchez Perez Manuel",
    "wof:placetype":"venue"
},
  "geometry": {"coordinates":[-6.0096821785,39.0109100342],"type":"Point"}
}