{
  "type": "Feature",
  "properties": {
    "iso:country":"ES",
    "sg:address":"Ctra San Javier, 76",
    "sg:city":"Secano",
    "sg:orig_category":"Reposter\u00cdas",
    "sg:phone":"+34 968 82 11 34",
    "sg:postcode":"30579",
    "sg:province":"Murcia",
    "wof:name":"Lopez Hernandez Fernando",
    "wof:placetype":"venue"
},
  "geometry": {"coordinates":[-1.0529290438,37.9830245972],"type":"Point"}
}