{
  "type": "Feature",
  "properties": {
    "addr:full":"Carrer de Industria, S/n Masnou Barcelona 08320",
    "addr:postcode":"08320",
    "addr:street":"Carrer De Industria S / N",
    "iso:country":"ES",
    "sg:address":"Carrer de Industria, S/n",
    "sg:city":"Masnou",
    "sg:orig_category":"Empresas De Carpinter\u00cda De Madera",
    "sg:phone":"+34 935 55 87 40",
    "sg:postcode":"08320",
    "sg:province":"Barcelona",
    "wof:name":"Carpinteria Ramirez S.c.p",
    "wof:placetype":"venue"
},
  "geometry": {"coordinates":[2.3188750744,41.4888076782],"type":"Point"}
}