{
  "type": "Feature",
  "properties": {
    "iso:country":"ES",
    "sg:address":"Ctra Barcelona, 61",
    "sg:city":"Viladecans",
    "sg:orig_category":"Albergues",
    "sg:phone":"+34 936 37 90 56",
    "sg:postcode":"08840",
    "sg:province":"Barcelona",
    "wof:name":"Nadal 78 S.l.",
    "wof:placetype":"venue"
},
  "geometry": {"coordinates":[2.0255200863,41.319770813],"type":"Point"}
}