{
  "type": "Feature",
  "properties": {
    "addr:full":"Mcdo. Delicias, 12 Valladolid Valladolid 47013",
    "addr:housenumber":"12",
    "addr:postcode":"47013",
    "iso:country":"ES",
    "sg:address":"Mcdo. Delicias, 12",
    "sg:city":"Valladolid",
    "sg:orig_category":"Carnicer\u00cdas, Carnicer\u00cdas",
    "sg:phone":"+34 983 39 78 92",
    "sg:postcode":"47013",
    "sg:province":"Valladolid",
    "wof:name":"Velazquez Gonzalez Maria Jesus",
    "wof:placetype":"venue"
},
  "geometry": {"coordinates":[-4.7196850777,41.6395606995],"type":"Point"}
}