{
  "type": "Feature",
  "properties": {
    "addr:full":"Plaz Arrabal, S/n Huerto Huesca 22210",
    "addr:housenumber":"s",
    "addr:postcode":"22210",
    "addr:street":"Plaz Arrabal;/ N Huerto",
    "iso:country":"ES",
    "sg:address":"Plaz Arrabal, S/n",
    "sg:city":"Huerto",
    "sg:orig_category":"Arenas, Guijarros Y Granulados",
    "sg:phone":"+34 974 39 54 72",
    "sg:postcode":"22210",
    "sg:province":"Huesca",
    "wof:name":"Hormigones Gra\u00f1en S.l.",
    "wof:placetype":"venue"
},
  "geometry": {"coordinates":[-0.1667740047,41.9325408936],"type":"Point"}
}