{
  "type": "Feature",
  "properties": {
    "addr:full":"Calle de San Sebastian, 83 Villarrobledo Albacete 02600",
    "addr:housenumber":"83",
    "addr:postcode":"02600",
    "addr:street":"Calle De San Sebastian",
    "iso:country":"ES",
    "sg:address":"Calle de San Sebastian, 83",
    "sg:city":"Villarrobledo",
    "sg:orig_category":"Alimentaci\u00d3n General (al Por Mayor)",
    "sg:phone":"+34 967 14 15 74",
    "sg:postcode":"02600",
    "sg:province":"Albacete",
    "wof:name":"Diaz Camacho Juan",
    "wof:placetype":"venue"
},
  "geometry": {"coordinates":[-2.6011788845,39.2679405212],"type":"Point"}
}