{
  "type": "Feature",
  "properties": {
    "iso:country":"ES",
    "sg:address":"Calle de Jaboneria, 20",
    "sg:city":"Torrejon Ardoz",
    "sg:orig_category":"Asesor\u00cda Sobre Comunicaci\u00d3n De Empresas",
    "sg:phone":"+34 916 76 14 61",
    "sg:postcode":"28850",
    "sg:province":"Madrid",
    "wof:name":"Ph Consultance Firm S.l.",
    "wof:placetype":"venue"
},
  "geometry": {"coordinates":[-3.4773650169,40.4580307007],"type":"Point"}
}