{
  "type": "Feature",
  "properties": {
    "iso:country":"ES",
    "sg:address":"Calle de Cadiz, 22",
    "sg:city":"Valencia",
    "sg:orig_category":"Confecci\u00d3n (fabricaci\u00d3n, Al Por Mayor)",
    "sg:phone":"+34 963 41 67 75",
    "sg:postcode":"46006",
    "sg:province":"Valencia",
    "wof:name":"Timoner Fernandez Josefa",
    "wof:placetype":"venue"
},
  "geometry": {"coordinates":[-0.374591291,39.463180542],"type":"Point"}
}