{
  "type": "Feature",
  "properties": {
    "iso:country":"ES",
    "sg:address":"Calle de Rua De Dato, 17",
    "sg:city":"Calatayud",
    "sg:orig_category":"Droguer\u00cdas (al Por Menor)",
    "sg:phone":"+34 976 88 22 75",
    "sg:postcode":"50300",
    "sg:province":"Zaragoza",
    "wof:name":"Morlanes Decoracion S.l.",
    "wof:placetype":"venue"
},
  "geometry": {"coordinates":[-1.6439640522,41.353717804],"type":"Point"}
}