{
  "type": "Feature",
  "properties": {
    "addr:full":"Ctra Entrena, 5 Navarrete La Rioja 26370",
    "addr:housenumber":"5",
    "addr:postcode":"26370",
    "addr:street":"Ctra Entrena",
    "iso:country":"ES",
    "sg:address":"Ctra Entrena, 5",
    "sg:city":"Navarrete",
    "sg:orig_category":"Empresas De Pintura Y Revestimientos",
    "sg:phone":"+34 941 44 07 96",
    "sg:postcode":"26370",
    "sg:province":"La Rioja",
    "wof:name":"Bastida Ramirez Jesus Miguel",
    "wof:placetype":"venue"
},
  "geometry": {"coordinates":[-2.5627059937,42.4329109192],"type":"Point"}
}