{
  "type": "Feature",
  "properties": {
    "iso:country":"ES",
    "sg:address":"Calle de Constitucion (de La), 45",
    "sg:city":"Alcobendas",
    "sg:orig_category":"Pescader\u00cdas (al Por Menor)",
    "sg:phone":"+34 916 53 08 95",
    "sg:postcode":"28100",
    "sg:province":"Madrid",
    "wof:name":"Arroyo Camarero Domingo",
    "wof:placetype":"venue"
},
  "geometry": {"coordinates":[-3.6371045113,40.5427207947],"type":"Point"}
}