{
  "type": "Feature",
  "properties": {
    "addr:full":"Calle de Damaso Alonso, 61 Madrid Madrid 28050",
    "addr:housenumber":"61",
    "addr:postcode":"madrid;28050",
    "addr:street":"Calle De Damaso Alonso",
    "iso:country":"ES",
    "sg:address":"Calle de Damaso Alonso, 61",
    "sg:city":"Madrid",
    "sg:orig_category":"Arquitectos",
    "sg:phone":"+34 916 25 55 51",
    "sg:postcode":"28050",
    "sg:province":"Madrid",
    "wof:name":"Nabal Arquitecto S.l.",
    "wof:placetype":"venue"
},
  "geometry": {"coordinates":[-3.6355264187,40.5065689087],"type":"Point"}
}