{
  "type": "Feature",
  "properties": {
    "addr:full":"Carr Carraixet, 4 Almassera Valencia 46132",
    "addr:housenumber":"4",
    "addr:postcode":"46132",
    "addr:street":"Carr Carraixet",
    "iso:country":"ES",
    "sg:address":"Carr Carraixet, 4",
    "sg:city":"Almassera",
    "sg:orig_category":"Alimentaci\u00d3n General (al Por Mayor)",
    "sg:phone":"+34 961 86 92 40",
    "sg:postcode":"46132",
    "sg:province":"Valencia",
    "wof:name":"Maicerias Espa\u00f1olas S.a.",
    "wof:placetype":"venue"
},
  "geometry": {"coordinates":[-0.3589139879,39.5112266541],"type":"Point"}
}