{
  "type": "Feature",
  "properties": {
    "addr:full":"Av Cornella, 32 Esplugues Llobregat Barcelona 08950",
    "addr:housenumber":"32",
    "addr:postcode":"08950",
    "addr:street":"Av Cornella",
    "iso:country":"ES",
    "sg:address":"Av Cornella, 32",
    "sg:city":"Esplugues Llobregat",
    "sg:orig_category":"Cajas Para Embalar",
    "sg:phone":"+34 933 71 45 58",
    "sg:postcode":"08950",
    "sg:province":"Barcelona",
    "sg:website":"www.cajamar.es",
    "wof:name":"Cajamar",
    "wof:placetype":"venue"
},
  "geometry": {"coordinates":[2.0842609406,41.3737335205],"type":"Point"}
}