{
  "type": "Feature",
  "properties": {
    "addr:full":"Calle de Felipe Ricardos, S/n Torremolinos M\u00e1laga 29620",
    "addr:housenumber":"s / n",
    "addr:postcode":"29620",
    "addr:street":"Calle De Felipe Ricardos;Ma\u0301Laga",
    "iso:country":"ES",
    "sg:address":"Calle de Felipe Ricardos, S/n",
    "sg:city":"Torremolinos",
    "sg:orig_category":"Agentes Generales De Seguros",
    "sg:phone":"+34 952 37 69 42",
    "sg:postcode":"29620",
    "sg:province":"M\u00e1laga",
    "wof:name":"Sanchez Jimenez-pajarero Jesus",
    "wof:placetype":"venue"
},
  "geometry": {"coordinates":[-4.4972968102,36.6261024475],"type":"Point"}
}