{
  "type": "Feature",
  "properties": {
    "iso:country":"ES",
    "sg:address":"Urb Suelves (las), S/n",
    "sg:city":"Barbastro",
    "sg:orig_category":"Electrodom\u00c9sticos (al Por Menor)",
    "sg:phone":"+34 974 31 54 53",
    "sg:postcode":"22300",
    "sg:province":"Huesca",
    "wof:name":"Laplana Arnal Manuel",
    "wof:placetype":"venue"
},
  "geometry": {"coordinates":[0.1279940009,42.0360984802],"type":"Point"}
}