{
  "type": "Feature",
  "properties": {
    "addr:full":"Rua Montero Rios (de), 22 Santiago De Compostela La Coru\u00f1a 15706",
    "addr:housenumber":"22",
    "addr:postcode":"15706",
    "addr:street":"Rua Montero Rios De;Corun\u0303A",
    "iso:country":"ES",
    "sg:address":"Rua Montero Rios (de), 22",
    "sg:city":"Santiago De Compostela",
    "sg:orig_category":"Cl\u00cdnicas M\u00c9dicas",
    "sg:phone":"+34 981 57 14 20",
    "sg:postcode":"15706",
    "sg:province":"La Coru\u00f1a",
    "wof:name":"Clinica Adelest S.cv.",
    "wof:placetype":"venue"
},
  "geometry": {"coordinates":[-8.5466709137,42.8758087158],"type":"Point"}
}