{
  "type": "Feature",
  "properties": {
    "addr:full":"Calle de Trafalgar, 3 Malaga M\u00e1laga 29003",
    "addr:housenumber":"3",
    "addr:postcode":"29003",
    "addr:street":"Calle De Trafalgar;Ma\u0301Laga",
    "iso:country":"ES",
    "sg:address":"Calle de Trafalgar, 3",
    "sg:city":"Malaga",
    "sg:orig_category":"Ropa De Trabajo Y Profesionales (fabricaci\u00d3n, Al Por Mayor)",
    "sg:phone":"+34 952 32 30 45",
    "sg:postcode":"29003",
    "sg:province":"M\u00e1laga",
    "wof:name":"Robles Martin Francisca",
    "wof:placetype":"venue"
},
  "geometry": {"coordinates":[-4.4431819916,36.6974105835],"type":"Point"}
}