{
  "type": "Feature",
  "properties": {
    "addr:full":"Calle de Constitucion, S/n Illescas Toledo 45200",
    "addr:housenumber":"/ n",
    "addr:postcode":"45200",
    "addr:street":"Calle De Constitucion S",
    "iso:country":"ES",
    "sg:address":"Calle de Constitucion, S/n",
    "sg:city":"Illescas",
    "sg:orig_category":"Electricidad: Instalaciones Industriales",
    "sg:phone":"+34 925 51 23 27",
    "sg:postcode":"45200",
    "sg:province":"Toledo",
    "wof:name":"Rey Correa Francisco",
    "wof:placetype":"venue"
},
  "geometry": {"coordinates":[-3.8499116898,40.1281013489],"type":"Point"}
}