{
  "type": "Feature",
  "properties": {
    "addr:full":"Rbla Principal, 101 Vilanova I La Geltru Barcelona 08800",
    "addr:housenumber":"101",
    "addr:postcode":"08800",
    "addr:street":"Rbla Principal",
    "iso:country":"ES",
    "sg:address":"Rbla Principal, 101",
    "sg:city":"Vilanova I La Geltru",
    "sg:orig_category":"Internados & Ense\u00d1anza Privada",
    "sg:phone":"+34 938 16 54 63",
    "sg:postcode":"08800",
    "sg:province":"Barcelona",
    "wof:name":"Fundacio El Cim De Vilanova I La Geltru",
    "wof:placetype":"venue"
},
  "geometry": {"coordinates":[1.72656703,41.2211837769],"type":"Point"}
}