{
  "type": "Feature",
  "properties": {
    "iso:country":"ES",
    "sg:address":"Carrer de Valles, 16",
    "sg:city":"Granollers",
    "sg:orig_category":"Suministros Y Materiales Industriales",
    "sg:phone":"+34 938 60 00 80",
    "sg:postcode":"08401",
    "sg:province":"Barcelona",
    "wof:name":"Suministros Y Servicios Industriales Servitec S.a.",
    "wof:placetype":"venue"
},
  "geometry": {"coordinates":[2.2868421078,41.6022872925],"type":"Point"}
}