{
  "type": "Feature",
  "properties": {
    "addr:full":"Calle de Correria, 1 Vitoria-gasteiz \u00c1lava 01001",
    "addr:housenumber":"1",
    "addr:postcode":"01001",
    "addr:street":"Calle De Correria",
    "iso:country":"ES",
    "sg:address":"Calle de Correria, 1",
    "sg:city":"Vitoria-gasteiz",
    "sg:orig_category":"Carnicer\u00cdas, Carnicer\u00cdas",
    "sg:phone":"+34 945 25 75 95",
    "sg:postcode":"01001",
    "sg:province":"\u00c1lava",
    "wof:name":"Llanos Acebo Alberto",
    "wof:placetype":"venue"
},
  "geometry": {"coordinates":[-2.6732401848,42.8469734192],"type":"Point"}
}