{
  "type": "Feature",
  "properties": {
    "addr:full":"Urb Rosales (los), 17 Saron Cantabria 39620",
    "addr:housenumber":"17",
    "addr:postcode":"39620",
    "addr:street":"Urb Rosales Los",
    "iso:country":"ES",
    "sg:address":"Urb Rosales (los), 17",
    "sg:city":"Saron",
    "sg:orig_category":"Agencias De Viajes",
    "sg:phone":"+34 942 56 43 12",
    "sg:postcode":"39620",
    "sg:province":"Cantabria",
    "wof:name":"Nu\u00f1ez Martinez Jose Antonio 450139q S. L. N. E.",
    "wof:placetype":"venue"
},
  "geometry": {"coordinates":[-3.8524339199,43.3249206543],"type":"Point"}
}