{
  "type": "Feature",
  "properties": {
    "addr:full":"Calle de Cuatro Vientos, S/n Fuente Alamo Murcia 30320",
    "addr:housenumber":"s",
    "addr:postcode":"30320",
    "addr:street":"Calle De Cuatro Vientos;/ N",
    "iso:country":"ES",
    "sg:address":"Calle de Cuatro Vientos, S/n",
    "sg:city":"Fuente Alamo",
    "sg:orig_category":"M\u00c1rmoles, Granitos Y Piedras Naturales",
    "sg:phone":"+34 968 59 70 75",
    "sg:postcode":"30320",
    "sg:province":"Murcia",
    "wof:name":"Sanchez Hernandez Antonio",
    "wof:placetype":"venue"
},
  "geometry": {"coordinates":[-1.159276247,37.7230796814],"type":"Point"}
}