{
  "type": "Feature",
  "properties": {
    "iso:country":"ES",
    "sg:address":"Cra. Vall D'aran, Km. 0014,4",
    "sg:city":"Alguaire",
    "sg:orig_category":"Venta, Instalaci\u00d3n De Cocinas",
    "sg:phone":"+34 973 75 60 53",
    "sg:postcode":"25125",
    "sg:province":"Lleida",
    "wof:name":"Fernandez Martin Juan Luis",
    "wof:placetype":"venue"
},
  "geometry": {"coordinates":[0.5591199994,41.7370185852],"type":"Point"}
}