{
  "type": "Feature",
  "properties": {
    "addr:full":"Calle de Alarcos, 4 Ciudad Real Ciudad Real 13001",
    "addr:housenumber":"4",
    "addr:postcode":"13001",
    "addr:street":"Calle De Alarcos",
    "iso:country":"ES",
    "sg:address":"Calle de Alarcos, 4",
    "sg:city":"Ciudad Real",
    "sg:orig_category":"Asesor\u00cda Fiscal Y Jur\u00cddica",
    "sg:phone":"+34 926 27 32 71",
    "sg:postcode":"13001",
    "sg:province":"Ciudad Real",
    "wof:name":"Asimverfis S.l.",
    "wof:placetype":"venue"
},
  "geometry": {"coordinates":[-3.9311056137,38.9832382202],"type":"Point"}
}