{
  "type": "Feature",
  "properties": {
    "addr:full":"Calle de Espiga, 5 Melilla Melilla 52006",
    "addr:housenumber":"5",
    "addr:postcode":"52006",
    "addr:street":"Calle De Espiga",
    "iso:country":"ES",
    "sg:address":"Calle de Espiga, 5",
    "sg:city":"Melilla",
    "sg:orig_category":"Art\u00cdculos Funerarios (al Por Menor)",
    "sg:phone":"+34 952 67 76 37",
    "sg:postcode":"52006",
    "sg:province":"Melilla",
    "wof:name":"Servicios Funerarios Casa Calderon S.l.",
    "wof:placetype":"venue"
},
  "geometry": {"coordinates":[-2.9428050518,35.2723045349],"type":"Point"}
}