{
  "type": "Feature",
  "properties": {
    "iso:country":"ES",
    "sg:address":"Calle de Ermita De La Ca\u00d1ada, S/n",
    "sg:city":"Ca\u00e7ada De San Urbano",
    "sg:orig_category":"Electrodom\u00c9sticos (al Por Menor)",
    "sg:phone":"+34 950 29 01 23",
    "sg:postcode":"04120",
    "sg:province":"Almer\u00eda",
    "wof:name":"Muebles Y Electrodomesticos Joami S. A.",
    "wof:placetype":"venue"
},
  "geometry": {"coordinates":[-2.4108090401,36.8411712646],"type":"Point"}
}