{
  "type": "Feature",
  "properties": {
    "addr:full":"Av Rabassaires, 28 Mollet Valles Barcelona 08100",
    "addr:housenumber":"28",
    "addr:postcode":"08100",
    "addr:street":"Av Rabassaires",
    "iso:country":"ES",
    "sg:address":"Av Rabassaires, 28",
    "sg:city":"Mollet Valles",
    "sg:orig_category":"Electrodom\u00c9sticos (al Por Menor)",
    "sg:phone":"+34 935 79 76 00",
    "sg:postcode":"08100",
    "sg:province":"Barcelona",
    "wof:name":"Germans Bertolin S.l.",
    "wof:placetype":"venue"
},
  "geometry": {"coordinates":[2.2213389874,41.5396194458],"type":"Point"}
}