{
  "type": "Feature",
  "properties": {
    "addr:full":"Calle de Miguel De Unamuno, 28 Cehegin Murcia 30430",
    "addr:housenumber":"28",
    "addr:postcode":"30430",
    "addr:street":"Calle De Miguel De Unamuno",
    "iso:country":"ES",
    "sg:address":"Calle de Miguel De Unamuno, 28",
    "sg:city":"Cehegin",
    "sg:orig_category":"Electricidad: Instaladores",
    "sg:phone":"+34 968 74 25 45",
    "sg:postcode":"30430",
    "sg:province":"Murcia",
    "wof:name":"Sanchez Y Montalban S.l.",
    "wof:placetype":"venue"
},
  "geometry": {"coordinates":[-1.8010870218,38.0904388428],"type":"Point"}
}