{
  "type": "Feature",
  "properties": {
    "iso:country":"ES",
    "sg:address":"Calle de Arzobispo Sanchis, 43",
    "sg:city":"Alginet",
    "sg:orig_category":"Inmobiliaria (agencias)",
    "sg:phone":"+34 961 75 17 38",
    "sg:postcode":"46230",
    "sg:province":"Valencia",
    "wof:name":"Gest Spanish Fruits Sl",
    "wof:placetype":"venue"
},
  "geometry": {"coordinates":[-0.4680300951,39.2620315552],"type":"Point"}
}