{
  "type": "Feature",
  "properties": {
    "addr:full":"Plaz Comuneros (de Los), 2 Coslada Madrid 28820",
    "addr:housenumber":"2",
    "addr:postcode":"28820",
    "addr:street":"Plaz Comuneros De Los",
    "iso:country":"ES",
    "sg:address":"Plaz Comuneros (de Los), 2",
    "sg:city":"Coslada",
    "sg:orig_category":"Fabricaci\u00d3n, Importaci\u00d3n, Venta De Material De Telefon\u00cda, Peritelefon\u00cda",
    "sg:phone":"+34 916 69 79 15",
    "sg:postcode":"28820",
    "sg:province":"Madrid",
    "wof:name":"Tecnologia Y Compartimentacion S.l.",
    "wof:placetype":"venue"
},
  "geometry": {"coordinates":[-3.5645070076,40.4260902405],"type":"Point"}
}