{
  "type": "Feature",
  "properties": {
    "addr:full":"Av Congost, 34 Martorell Barcelona 08760",
    "addr:housenumber":"34",
    "addr:postcode":"08760",
    "addr:street":"Av Congost",
    "iso:country":"ES",
    "sg:address":"Av Congost, 34",
    "sg:city":"Martorell",
    "sg:orig_category":"Fabricaci\u00d3n, Instalaci\u00d3n De Armarios",
    "sg:phone":"+34 937 74 04 43",
    "sg:postcode":"08760",
    "sg:province":"Barcelona",
    "wof:name":"Gres Congost S.l.",
    "wof:placetype":"venue"
},
  "geometry": {"coordinates":[1.9265979528,41.474105835],"type":"Point"}
}