{
  "type": "Feature",
  "properties": {
    "iso:country":"ES",
    "sg:address":"Carrer de Mare De Deu Del Pilar, 34",
    "sg:city":"Cardedeu",
    "sg:orig_category":"Molduras, Junquillos, Listones Y Molduras Perforadas",
    "sg:phone":"+34 938 71 11 91",
    "sg:postcode":"08440",
    "sg:province":"Barcelona",
    "wof:name":"Alonso Perez Maria Cristina",
    "wof:placetype":"venue"
},
  "geometry": {"coordinates":[2.3517525196,41.6470298767],"type":"Point"}
}