{
  "type": "Feature",
  "properties": {
    "addr:full":"Carr Tuejar, S/n Eliana Valencia 46183",
    "addr:housenumber":"s / n",
    "addr:postcode":"46183",
    "addr:street":"Carr Tuejar",
    "iso:country":"ES",
    "sg:address":"Carr Tuejar, S/n",
    "sg:city":"Eliana",
    "sg:orig_category":"Marroquiner\u00cda (confecci\u00d3n)",
    "sg:phone":"+34 961 65 66 30",
    "sg:postcode":"46183",
    "sg:province":"Valencia",
    "wof:name":"Saez Cuenca Jose",
    "wof:placetype":"venue"
},
  "geometry": {"coordinates":[-0.528208971,39.5667457581],"type":"Point"}
}