{
  "type": "Feature",
  "properties": {
    "iso:country":"ES",
    "sg:address":"Carrer de Sardana, 11",
    "sg:city":"Reus",
    "sg:orig_category":"Art\u00cdculos De Limpieza Y De Cocina (fabricaci\u00d3n, Al Por Mayor)",
    "sg:phone":"+34 977 33 38 73",
    "sg:postcode":"43205",
    "sg:province":"Tarragona",
    "wof:name":"Siglhogar",
    "wof:placetype":"venue"
},
  "geometry": {"coordinates":[1.1051889658,41.1504516602],"type":"Point"}
}