{
  "type": "Feature",
  "properties": {
    "addr:full":"Hernandez Velasco, 5 Motril Granada 18600",
    "addr:housenumber":"5",
    "addr:postcode":"18600",
    "addr:street":"Velasco",
    "iso:country":"ES",
    "sg:address":"Hernandez Velasco, 5",
    "sg:city":"Motril",
    "sg:orig_category":"Confecci\u00d3n (fabricaci\u00d3n, Al Por Mayor)",
    "sg:phone":"+34 958 82 31 10",
    "sg:postcode":"18600",
    "sg:province":"Granada",
    "wof:name":"Rodriguez Sanchez Manuel",
    "wof:placetype":"venue"
},
  "geometry": {"coordinates":[-3.5206589699,36.7417182922],"type":"Point"}
}