{
  "type": "Feature",
  "properties": {
    "iso:country":"ES",
    "sg:address":"Avda Pablo Iglesias (de), 8",
    "sg:city":"Almeria",
    "sg:orig_category":"Psic\u00d3logos",
    "sg:phone":"+34 950 27 13 21",
    "sg:postcode":"04003",
    "sg:province":"Almer\u00eda",
    "wof:name":"Gongora Escudero Manuela",
    "wof:placetype":"venue"
},
  "geometry": {"coordinates":[-2.4644427299,36.8447875977],"type":"Point"}
}