{
  "type": "Feature",
  "properties": {
    "iso:country":"ES",
    "sg:address":"Peteiro(rois), 29",
    "sg:city":"Peteiro",
    "sg:orig_category":"Agencias Y Agentes Comerciales, Representantes",
    "sg:phone":"+34 981 79 54 93",
    "sg:postcode":"15166",
    "sg:province":"La Coru\u00f1a",
    "wof:name":"Milan Guiu Jose Benito",
    "wof:placetype":"venue"
},
  "geometry": {"coordinates":[-8.2616682053,43.3274726868],"type":"Point"}
}