{
  "type": "Feature",
  "properties": {
    "iso:country":"ES",
    "sg:address":"Part. Blancafort, S/n",
    "sg:city":"Riudoms",
    "sg:orig_category":"Colchones (fabricaci\u00d3n, Al Por Mayor, Al Por Menor)",
    "sg:phone":"+34 977 85 14 09",
    "sg:postcode":"43330",
    "sg:province":"Tarragona",
    "wof:name":"Artesanos Del Descanso C.b.",
    "wof:placetype":"venue"
},
  "geometry": {"coordinates":[1.0490374565,41.1454391479],"type":"Point"}
}