{
  "type": "Feature",
  "properties": {
    "iso:country":"ES",
    "sg:address":"Calle de Mendez Alvaro, 84",
    "sg:city":"Madrid",
    "sg:orig_category":"Delegados, Agentes De Tr\u00c1nsito, Auxiliares De Transporte Internacional",
    "sg:phone":"+34 915 30 23 35",
    "sg:postcode":"28053",
    "sg:province":"Madrid",
    "wof:name":"Trans European Suardiez S.l.",
    "wof:placetype":"venue"
},
  "geometry": {"coordinates":[-3.6742815971,40.3913269043],"type":"Point"}
}