{
  "type": "Feature",
  "properties": {
    "iso:country":"ES",
    "sg:address":"Calle de Luis Mariano, 14",
    "sg:city":"Irun",
    "sg:orig_category":"Abogados",
    "sg:phone":"+34 943 63 31 51",
    "sg:postcode":"20302",
    "sg:province":"Guip\u00f9zcoa",
    "wof:name":"Sanz De Hoyos Carlos",
    "wof:placetype":"venue"
},
  "geometry": {"coordinates":[-1.7927800417,43.3395004272],"type":"Point"}
}