{
  "type": "Feature",
  "properties": {
    "addr:full":"Avda Cervantes (de), 4 Cordoba C\u00f3rdoba 14008",
    "addr:housenumber":"4",
    "addr:postcode":"14008",
    "addr:street":"Avda Cervantes De;Co\u0301Rdoba",
    "iso:country":"ES",
    "sg:address":"Avda Cervantes (de), 4",
    "sg:city":"Cordoba",
    "sg:orig_category":"Expertos Contables",
    "sg:phone":"+34 957 47 47 53",
    "sg:postcode":"14008",
    "sg:province":"C\u00f3rdoba",
    "wof:name":"Asesoramientos Emilio Costi S.l.",
    "wof:placetype":"venue"
},
  "geometry": {"coordinates":[-4.7845778465,37.8871917725],"type":"Point"}
}