{
  "type": "Feature",
  "properties": {
    "iso:country":"ES",
    "sg:address":"Avda Bruselas, 48",
    "sg:city":"Madrid",
    "sg:orig_category":"Bisuter\u00cda, Joyer\u00cda, Relojer\u00cda (al Por Menor)",
    "sg:phone":"+34 917 26 24 01",
    "sg:postcode":"28028",
    "sg:province":"Madrid",
    "wof:name":"Joyeria Hermanos Perez Molino",
    "wof:placetype":"venue"
},
  "geometry": {"coordinates":[-3.6633009911,40.4380569458],"type":"Point"}
}