{
  "type": "Feature",
  "properties": {
    "iso:country":"ES",
    "sg:address":"C/ Formentera, De, 3",
    "sg:city":"S. Antoni Portmany",
    "sg:orig_category":"Alquiler De Apartamentos",
    "sg:phone":"+34 971 34 42 74",
    "sg:postcode":"07820",
    "sg:province":"Islas Baleares",
    "wof:name":"Promociones Hermanadas S. A.",
    "wof:placetype":"venue"
},
  "geometry": {"coordinates":[1.5188339949,39.1094055176],"type":"Point"}
}