{
  "type": "Feature",
  "properties": {
    "addr:full":"Ci Ramader (c Pilans), 21 Escala Girona 17130",
    "addr:housenumber":"21",
    "addr:postcode":"17130",
    "addr:street":"C Pilans",
    "iso:country":"ES",
    "sg:address":"Ci Ramader (c Pilans), 21",
    "sg:city":"Escala",
    "sg:orig_category":"Carnicer\u00cdas, Carnicer\u00cdas",
    "sg:phone":"+34 972 77 01 27",
    "sg:postcode":"17130",
    "sg:province":"Girona",
    "wof:name":"Llandrich Freixa Ramon",
    "wof:placetype":"venue"
},
  "geometry": {"coordinates":[3.1321649551,42.1229934692],"type":"Point"}
}