{
  "type": "Feature",
  "properties": {
    "iso:country":"ES",
    "sg:address":"Pasaje A. Crespo Romero, 1",
    "sg:city":"La Carlota",
    "sg:orig_category":"Agentes Generales De Seguros",
    "sg:phone":"+34 957 30 13 92",
    "sg:postcode":"14100",
    "sg:province":"C\u00f3rdoba",
    "wof:name":"Agrogileto S.a.",
    "wof:placetype":"venue"
},
  "geometry": {"coordinates":[-4.9338459969,37.6716308594],"type":"Point"}
}