{
  "type": "Feature",
  "properties": {
    "addr:full":"Calle de Juan Xxiii, 32 Dolores Alicante 03150",
    "addr:housenumber":"32",
    "addr:postcode":"03150",
    "addr:street":"Calle De Juan Xxiii",
    "iso:country":"ES",
    "sg:address":"Calle de Juan Xxiii, 32",
    "sg:city":"Dolores",
    "sg:orig_category":"Promotores Constructores",
    "sg:phone":"+34 965 72 63 29",
    "sg:postcode":"03150",
    "sg:province":"Alicante",
    "wof:name":"Comunidad De Propietarios Juan Xxiii",
    "wof:placetype":"venue"
},
  "geometry": {"coordinates":[-0.7734889984,38.1388206482],"type":"Point"}
}