{
  "type": "Feature",
  "properties": {
    "iso:country":"ES",
    "sg:address":"Calle de Sgto Moragues Vida, 8",
    "sg:city":"Palma",
    "sg:orig_category":"Plomeros",
    "sg:phone":"+34 971 73 45 50",
    "sg:postcode":"07013",
    "sg:province":"Islas Baleares",
    "wof:name":"Casa Pujadas S. A.",
    "wof:placetype":"venue"
},
  "geometry": {"coordinates":[2.6370069981,39.5778427124],"type":"Point"}
}