{
  "type": "Feature",
  "properties": {
    "iso:country":"ES",
    "sg:address":"Avda Reyes Catolicos, 1",
    "sg:city":"Sax",
    "sg:orig_category":"Organizaciones Internacionales",
    "sg:phone":"+34 965 47 46 69",
    "sg:postcode":"03630",
    "sg:province":"Alicante",
    "wof:name":"Cruz Roja Espa\u00f1ola",
    "wof:placetype":"venue"
},
  "geometry": {"coordinates":[-0.8162800074,38.5358467102],"type":"Point"}
}