{
  "type": "Feature",
  "properties": {
    "iso:country":"ES",
    "sg:address":"Zuazola Auzoa, 19",
    "sg:city":"Gabiria",
    "sg:orig_category":"Fabricaci\u00d3n De Ventanas",
    "sg:phone":"+34 943 88 83 38",
    "sg:postcode":"20217",
    "sg:province":"Guip\u00f9zcoa",
    "wof:name":"Edersal S.a.",
    "wof:placetype":"venue"
},
  "geometry": {"coordinates":[-2.2796189785,43.0503883362],"type":"Point"}
}