{
  "type": "Feature",
  "properties": {
    "addr:full":"Calle de Castillo, 8 Santa Cruz De Tenerife Santa Cruz De Tenerife 38002",
    "addr:housenumber":"8",
    "addr:postcode":"38002",
    "addr:street":"Calle De Castillo",
    "iso:country":"ES",
    "sg:address":"Calle de Castillo, 8",
    "sg:city":"Santa Cruz De Tenerife",
    "sg:orig_category":"M\u00c9dicos: Medicina Legal, Peritajes M\u00c9dicos",
    "sg:phone":"+34 922 15 14 61",
    "sg:postcode":"38002",
    "sg:province":"Santa Cruz De Tenerife",
    "wof:name":"Gestion Medica Tenerife S.l.",
    "wof:placetype":"venue"
},
  "geometry": {"coordinates":[-16.249578476,28.4669132233],"type":"Point"}
}