{
  "type": "Feature",
  "properties": {
    "iso:country":"ES",
    "sg:address":"Carrer de Pere Dezcallar Net, 14",
    "sg:city":"Palma",
    "sg:orig_category":"Arquitectos",
    "sg:phone":"+34 971 71 59 18",
    "sg:postcode":"07003",
    "sg:province":"Islas Baleares",
    "wof:name":"Vicente Cuadrado Gregorio De",
    "wof:placetype":"venue"
},
  "geometry": {"coordinates":[2.6492040157,39.5784034729],"type":"Point"}
}