{
  "type": "Feature",
  "properties": {
    "iso:country":"ES",
    "sg:address":"Calle de Fermin Morin, 19",
    "sg:city":"Santa Cruz De Tenerife",
    "sg:orig_category":"Ingeniero",
    "sg:phone":"+34 922 21 79 87",
    "sg:postcode":"38007",
    "sg:province":"Santa Cruz De Tenerife",
    "sg:website":"www.syncronet.es",
    "wof:name":"Syncronet",
    "wof:placetype":"venue"
},
  "geometry": {"coordinates":[-16.2691268921,28.4661121368],"type":"Point"}
}