{
  "type": "Feature",
  "properties": {
    "addr:full":"Rond Damaso Toran, 9 Teruel Teruel 44001",
    "addr:housenumber":"9",
    "addr:postcode":"44001",
    "addr:street":"Toran",
    "iso:country":"ES",
    "sg:address":"Rond Damaso Toran, 9",
    "sg:city":"Teruel",
    "sg:orig_category":"Institutos De Belleza",
    "sg:phone":"+34 978 60 27 92",
    "sg:postcode":"44001",
    "sg:province":"Teruel",
    "wof:name":"Sol Vip Teruel S.l.",
    "wof:placetype":"venue"
},
  "geometry": {"coordinates":[-1.1048259735,40.3439445496],"type":"Point"}
}