{
  "type": "Feature",
  "properties": {
    "iso:country":"ES",
    "sg:address":"Avda Aragon De, 3",
    "sg:city":"Fraga",
    "sg:orig_category":"\u00d3ptica: Instrumentos (fabricaci\u00d3n)",
    "sg:phone":"+34 974 47 01 37",
    "sg:postcode":"22520",
    "sg:province":"Huesca",
    "wof:name":"Cruellas Ibarz Antonio Jose",
    "wof:placetype":"venue"
},
  "geometry": {"coordinates":[0.3427700102,41.5220603943],"type":"Point"}
}