{
  "type": "Feature",
  "properties": {
    "addr:full":"Carrer de Marques De Campo, 42 Denia Alicante 03700",
    "addr:housenumber":"42",
    "addr:postcode":"03700",
    "addr:street":"Carrer De Marques De Campo",
    "iso:country":"ES",
    "sg:address":"Carrer de Marques De Campo, 42",
    "sg:city":"Denia",
    "sg:orig_category":"Bancos",
    "sg:phone":"+34 965 78 04 00",
    "sg:postcode":"03700",
    "sg:province":"Alicante",
    "wof:name":"Banco De Valencia S.a.",
    "wof:placetype":"venue"
},
  "geometry": {"coordinates":[0.1094020009,38.8404884338],"type":"Point"}
}