{
  "type": "Feature",
  "properties": {
    "addr:full":"Calle de Caridad, 44 Ciudad Rodrigo Salamanca 37500",
    "addr:housenumber":"44",
    "addr:postcode":"37500",
    "addr:street":"Calle De Caridad",
    "iso:country":"ES",
    "sg:address":"Calle de Caridad, 44",
    "sg:city":"Ciudad Rodrigo",
    "sg:orig_category":"Cr\u00cda De Bovinos",
    "sg:phone":"+34 923 46 17 81",
    "sg:postcode":"37500",
    "sg:province":"Salamanca",
    "wof:name":"Mil Lomas S.a.",
    "wof:placetype":"venue"
},
  "geometry": {"coordinates":[-6.5268597603,40.5960273743],"type":"Point"}
}