{
  "type": "Feature",
  "properties": {
    "iso:country":"ES",
    "sg:address":"Carrer de Ricardo Calvo, 6",
    "sg:city":"Barcelona",
    "sg:orig_category":"Ropa Para Se\u00d1oras (al Por Menor)",
    "sg:phone":"+34 932 11 38 39",
    "sg:postcode":"08022",
    "sg:province":"Barcelona",
    "wof:name":"Sedunion S.a.",
    "wof:placetype":"venue"
},
  "geometry": {"coordinates":[2.133202076,41.403087616],"type":"Point"}
}