{
  "type": "Feature",
  "properties": {
    "iso:country":"ES",
    "sg:address":"Cjto Benabola, 6",
    "sg:city":"Nueva Andalucia",
    "sg:classifiers":[
        {
            "category":"Arts & Performance",
            "subcategory":"Art Gallery",
            "type":"Entertainment"
        }
    ],
    "sg:phone":"+34 952 81 14 49",
    "sg:postcode":"29660",
    "sg:province":"M\u00e1laga",
    "sg:tags":[
        "arte",
        "de",
        "galer\u00cdas"
    ],
    "sg:website":"www.fornaragallery.com",
    "wof:name":"Fornara Erbeta Roberto",
    "wof:placetype":"venue"
},
  "geometry": {"coordinates":[-4.963350296,36.498714447],"type":"Point"}
}