{
  "type": "Feature",
  "properties": {
    "addr:full":"Calle de Caballa, 19 Punta Umbria Huelva 21100",
    "addr:housenumber":"19",
    "addr:postcode":"21100",
    "addr:street":"Calle De Caballa",
    "iso:country":"ES",
    "sg:address":"Calle de Caballa, 19",
    "sg:city":"Punta Umbria",
    "sg:orig_category":"Supermercados Y Hipermercados",
    "sg:phone":"+34 959 31 09 91",
    "sg:postcode":"21100",
    "sg:province":"Huelva",
    "wof:name":"Autoservicio Candido S.l.",
    "wof:placetype":"venue"
},
  "geometry": {"coordinates":[-6.9688673019,37.184879303],"type":"Point"}
}