{
  "type": "Feature",
  "properties": {
    "addr:full":"Calle de Barrachina, 75 Castellon Castell\u00f3n 12006",
    "addr:housenumber":"75",
    "addr:postcode":"12006",
    "addr:street":"Calle De Barrachina",
    "iso:country":"ES",
    "sg:address":"Calle de Barrachina, 75",
    "sg:city":"Castellon",
    "sg:orig_category":"Asociaciones Y Clubs Deportivos",
    "sg:phone":"+34 964 24 16 24",
    "sg:postcode":"12006",
    "sg:province":"Castell\u00f3n",
    "wof:name":"Gran Fraternidad Universal L. S. E.",
    "wof:placetype":"venue"
},
  "geometry": {"coordinates":[-0.0495023988,39.9821662903],"type":"Point"}
}