{
  "type": "Feature",
  "properties": {
    "addr:full":"Cmno San Pedro, S/n Medina Campo Valladolid 47400",
    "addr:housenumber":"/ n",
    "addr:postcode":"47400",
    "addr:street":"Cmno San Pedro S",
    "iso:country":"ES",
    "sg:address":"Cmno San Pedro, S/n",
    "sg:city":"Medina Campo",
    "sg:orig_category":"Metalurgia",
    "sg:phone":"+34 983 80 02 54",
    "sg:postcode":"47400",
    "sg:province":"Valladolid",
    "wof:name":"Metalurgica De Medina S.a.",
    "wof:placetype":"venue"
},
  "geometry": {"coordinates":[-4.913184166,41.3120155334],"type":"Point"}
}