{
  "type": "Feature",
  "properties": {
    "iso:country":"ES",
    "sg:address":"Barr Rolisas, S/n",
    "sg:city":"Mar",
    "sg:orig_category":"Empresas De Impermeabilizaci\u00d3n",
    "sg:phone":"+34 942 82 44 96",
    "sg:postcode":"39312",
    "sg:province":"Cantabria",
    "wof:name":"Jomafe Vertical S.l.--",
    "wof:placetype":"venue"
},
  "geometry": {"coordinates":[-4.0284891129,43.3888206482],"type":"Point"}
}