{
  "type": "Feature",
  "properties": {
    "iso:country":"ES",
    "sg:address":"Calle de Alcon, 9",
    "sg:city":"Ponferrada",
    "sg:orig_category":"Ortopedia General",
    "sg:phone":"+34 987 41 16 40",
    "sg:postcode":"24400",
    "sg:province":"Le\u00f3n",
    "wof:name":"Ortopedia Alcon S.l.",
    "wof:placetype":"venue"
},
  "geometry": {"coordinates":[-6.5994753838,42.5496330261],"type":"Point"}
}