{
  "type": "Feature",
  "properties": {
    "iso:country":"ES",
    "sg:address":"Rua De Amado Garra, 11",
    "sg:city":"Ponteareas",
    "sg:orig_category":"Inmobiliaria (agencias)",
    "sg:phone":"+34 986 66 18 18",
    "sg:postcode":"36860",
    "sg:province":"Pontevedra",
    "wof:name":"Martinez Martinez Alfredo",
    "wof:placetype":"venue"
},
  "geometry": {"coordinates":[-8.5053949356,42.172580719],"type":"Point"}
}