{
  "type": "Feature",
  "properties": {
    "addr:full":"Calle de Cilla, S/n Aldeadavila Ribera Salamanca 37250",
    "addr:housenumber":"s",
    "addr:postcode":"37250",
    "addr:street":"Calle De Cilla;/ N Aldeadavila Ribera",
    "iso:country":"ES",
    "sg:address":"Calle de Cilla, S/n",
    "sg:city":"Aldeadavila Ribera",
    "sg:orig_category":"Bancos",
    "sg:phone":"+34 923 50 51 88",
    "sg:postcode":"37250",
    "sg:province":"Salamanca",
    "wof:name":"Banco De Castilla",
    "wof:placetype":"venue"
},
  "geometry": {"coordinates":[-6.6189289093,41.2183914185],"type":"Point"}
}