{
  "type": "Feature",
  "properties": {
    "addr:full":"Calle de Sp Velez Malaga, 6 San Pedro Alcantara M\u00e1laga 29670",
    "addr:housenumber":"6",
    "addr:postcode":"29670",
    "addr:street":"Calle De Sp Velez Malaga",
    "iso:country":"ES",
    "sg:address":"Calle de Sp Velez Malaga, 6",
    "sg:city":"San Pedro Alcantara",
    "sg:orig_category":"Instalaci\u00d3n De Sanitarios",
    "sg:phone":"+34 952 78 62 31",
    "sg:postcode":"29670",
    "sg:province":"M\u00e1laga",
    "sg:website":"www.sintabac.es",
    "wof:name":"Sintabac",
    "wof:placetype":"venue"
},
  "geometry": {"coordinates":[-4.9911618233,36.4857711792],"type":"Point"}
}