{
  "type": "Feature",
  "properties": {
    "addr:full":"Plaz Espejos (los), 5 Segovia Segovia 40001",
    "addr:postcode":"40001",
    "iso:country":"ES",
    "sg:address":"Plaz Espejos (los), 5",
    "sg:city":"Segovia",
    "sg:orig_category":"Abogados",
    "sg:phone":"+34 921 46 24 18",
    "sg:postcode":"40001",
    "sg:province":"Segovia",
    "wof:name":"Salmeron Unturbe Jesus",
    "wof:placetype":"venue"
},
  "geometry": {"coordinates":[-4.1163592339,40.9482116699],"type":"Point"}
}