{
  "type": "Feature",
  "properties": {
    "addr:full":"Pl Catalunya, 1 Corbera D'ebre Tarragona 43784",
    "addr:housenumber":"1",
    "addr:postcode":"43784",
    "addr:street":"Pl Catalunya",
    "iso:country":"ES",
    "sg:address":"Pl Catalunya, 1",
    "sg:city":"Corbera D'ebre",
    "sg:orig_category":"Productores Recolectores, Venta Directa De Vinos",
    "sg:phone":"+34 977 42 04 34",
    "sg:postcode":"43784",
    "sg:province":"Tarragona",
    "wof:name":"Bodegas Cortiella S.a.",
    "wof:placetype":"venue"
},
  "geometry": {"coordinates":[1.2365549803,41.1228942871],"type":"Point"}
}