{
  "type": "Feature",
  "properties": {
    "iso:country":"ES",
    "sg:address":"Carr Alfareries, 3",
    "sg:city":"Alfara De Algimia",
    "sg:orig_category":"Ingeniero",
    "sg:phone":"+34 962 62 63 51",
    "sg:postcode":"46148",
    "sg:province":"Valencia",
    "wof:name":"Escrig Virvela Francisco",
    "wof:placetype":"venue"
},
  "geometry": {"coordinates":[-0.3624440134,39.7540664673],"type":"Point"}
}