{
  "type": "Feature",
  "properties": {
    "addr:full":"Bertolt Brecht, 5 Gijon Asturias 33211",
    "addr:housenumber":"5",
    "addr:postcode":"33211",
    "addr:street":"Bertolt Brecht",
    "iso:country":"ES",
    "sg:address":"Bertolt Brecht, 5",
    "sg:city":"Gijon",
    "sg:orig_category":"Empresas De Carpinter\u00cda",
    "sg:phone":"+34 985 30 15 91",
    "sg:postcode":"33211",
    "sg:province":"Asturias",
    "wof:name":"Astur Ventanas S.l.",
    "wof:placetype":"venue"
},
  "geometry": {"coordinates":[-5.6922883987,43.5348968506],"type":"Point"}
}