{
  "type": "Feature",
  "properties": {
    "iso:country":"ES",
    "sg:address":"Calle de Mirasierra, 1",
    "sg:city":"Matas-pinar-monte Rozas",
    "sg:orig_category":"Sanatorios M\u00c9dico",
    "sg:phone":"+34 916 30 13 75",
    "sg:postcode":"28290",
    "sg:province":"Madrid",
    "wof:name":"Ayuntamiento De Las Rozas Hogar Jubilados",
    "wof:placetype":"venue"
},
  "geometry": {"coordinates":[-3.8935110569,40.5532646179],"type":"Point"}
}