{
  "type": "Feature",
  "properties": {
    "iso:country":"ES",
    "sg:address":"Calle de Nueva, 36",
    "sg:city":"Orellana Vieja",
    "sg:orig_category":"Maquinaria Para Industrias Diversas",
    "sg:phone":"+34 924 86 72 94",
    "sg:postcode":"06740",
    "sg:province":"Badajoz",
    "wof:name":"Gil Mo\u00f1ino Pedro",
    "wof:placetype":"venue"
},
  "geometry": {"coordinates":[-5.5393600464,39.0029067993],"type":"Point"}
}