{
  "type": "Feature",
  "properties": {
    "addr:full":"Calle de Plaza De Don Juan Redin, S/n Sesma Navarra 31293",
    "addr:housenumber":"s / n",
    "addr:postcode":"31293",
    "addr:street":"Calle De Plaza De Don Juan Redin",
    "iso:country":"ES",
    "sg:address":"Calle de Plaza De Don Juan Redin, S/n",
    "sg:city":"Sesma",
    "sg:orig_category":"Asilos De Ancianos. Centros Privados",
    "sg:phone":"+34 948 69 80 41",
    "sg:postcode":"31293",
    "sg:province":"Navarra",
    "wof:name":"Club Jubilados Y Pensionistas Virgen De Almuza",
    "wof:placetype":"venue"
},
  "geometry": {"coordinates":[-2.0856089592,42.4784317017],"type":"Point"}
}