{
  "type": "Feature",
  "properties": {
    "iso:country":"ES",
    "sg:address":"Carrer de Gran De Gracia, 215",
    "sg:city":"Barcelona",
    "sg:orig_category":"Doctores En Medicina",
    "sg:phone":"+34 932 37 73 53",
    "sg:postcode":"08012",
    "sg:province":"Barcelona",
    "wof:name":"Antolin Mu\u00f1iz Justo",
    "wof:placetype":"venue"
},
  "geometry": {"coordinates":[2.1513562202,41.4046325684],"type":"Point"}
}