{
  "type": "Feature",
  "properties": {
    "iso:country":"ES",
    "sg:address":"Calle de Pizarro, 18",
    "sg:city":"Alfafar",
    "sg:orig_category":"Muebles, Minoristas",
    "sg:phone":"+34 963 75 00 00",
    "sg:postcode":"46910",
    "sg:province":"Valencia",
    "sg:website":"www.galeriasdelmueble.com",
    "wof:name":"Galerias Del Mueble Vicente Albiach S. L.",
    "wof:placetype":"venue"
},
  "geometry": {"coordinates":[-0.392877996,39.4266433716],"type":"Point"}
}