{
  "type": "Feature",
  "properties": {
    "iso:country":"ES",
    "sg:address":"Avda Manolete De, 43",
    "sg:city":"Nueva Andalucia",
    "sg:orig_category":"Moquetas, Alfombras (al Por Menor)",
    "sg:phone":"+34 952 81 83 05",
    "sg:postcode":"29660",
    "sg:province":"M\u00e1laga",
    "wof:name":"Kambyses S.l.",
    "wof:placetype":"venue"
},
  "geometry": {"coordinates":[-4.9584841728,36.4910087585],"type":"Point"}
}