{
  "type": "Feature",
  "properties": {
    "addr:full":"Calle de Gobelaurre, 21 Bis Getxo Vizcaya 48930",
    "addr:housenumber":"21 bis",
    "addr:postcode":"48930",
    "addr:street":"Calle De Gobelaurre",
    "iso:country":"ES",
    "sg:address":"Calle de Gobelaurre, 21 Bis",
    "sg:city":"Getxo",
    "sg:orig_category":"Telas Para Tapizar, Cortinas, Pasamaner\u00cda (fabricaci\u00d3n, Al Por Mayor)",
    "sg:phone":"+34 944 80 02 10",
    "sg:postcode":"48930",
    "sg:province":"Vizcaya",
    "wof:name":"Maria Del Pilar Fernandez Andrades",
    "wof:placetype":"venue"
},
  "geometry": {"coordinates":[-3.0068490505,43.3258285522],"type":"Point"}
}