{
  "type": "Feature",
  "properties": {
    "addr:full":"Calle de Luis Chamizo, 2 Esparragalejo Badajoz 06860",
    "addr:housenumber":"2",
    "addr:postcode":"06860",
    "addr:street":"Calle De Luis Chamizo",
    "iso:country":"ES",
    "sg:address":"Calle de Luis Chamizo, 2",
    "sg:city":"Esparragalejo",
    "sg:orig_category":"Empresas De Carpinter\u00cda De Madera",
    "sg:phone":"+34 924 32 24 85",
    "sg:postcode":"06860",
    "sg:province":"Badajoz",
    "wof:name":"Jimenez Gamito Diego",
    "wof:placetype":"venue"
},
  "geometry": {"coordinates":[-6.4364638329,38.9442062378],"type":"Point"}
}