{
  "type": "Feature",
  "properties": {
    "addr:full":"Estafeta, 60 Iru\u00f1a Navarra 31001",
    "addr:housenumber":"60",
    "addr:postcode":"31001",
    "addr:street":"Estafeta",
    "iso:country":"ES",
    "sg:address":"Estafeta, 60",
    "sg:city":"Iru\u00f1a",
    "sg:orig_category":"Abogados",
    "sg:phone":"+34 948 21 03 58",
    "sg:postcode":"31001",
    "sg:province":"Navarra",
    "wof:name":"Gomez Salvador Sergio",
    "wof:placetype":"venue"
},
  "geometry": {"coordinates":[-1.6415239573,42.8164329529],"type":"Point"}
}