{
  "type": "Feature",
  "properties": {
    "addr:full":"Pla\u00c7 Sant Francesc, 2 Lleida Lleida 25007",
    "addr:housenumber":"2",
    "addr:postcode":"25007",
    "addr:street":"Sant Francesc",
    "iso:country":"ES",
    "sg:address":"Pla\u00c7 Sant Francesc, 2",
    "sg:city":"Lleida",
    "sg:orig_category":"M\u00c9dicos: Medicina Interna",
    "sg:phone":"+34 973 23 65 52",
    "sg:postcode":"25007",
    "sg:province":"Lleida",
    "wof:name":"Miro Vidal Jaime",
    "wof:placetype":"venue"
},
  "geometry": {"coordinates":[0.629471004,41.6166954041],"type":"Point"}
}