{
  "type": "Feature",
  "properties": {
    "iso:country":"ES",
    "sg:address":"Calle de Juan De Herrera, 24",
    "sg:city":"Alacant",
    "sg:orig_category":"Cervecer\u00cdas",
    "sg:phone":"+34 965 14 39 80",
    "sg:postcode":"03004",
    "sg:province":"Alicante",
    "wof:name":"Castello Alberola Roberto Cristobal",
    "wof:placetype":"venue"
},
  "geometry": {"coordinates":[-0.4867480099,38.3506317139],"type":"Point"}
}